{"type": "Feature", "id": 23623360, "geometry": {"type": "Point", "coordinates": [-78.619461, 35.653278]}, "properties": {"woe:id": 23623360, "woe:parent_id": 55988833, "woe:name": "Rand Road Elementary School", "woe:placetype": 20, "woe:placetype_name": "POI", "woe:lang": "ENG", "iso:country": "US", "meta:provider": ["geoplanet:7.3.2", "geoplanet:7.4.0", "geoplanet:7.4.1", "geoplanet:7.5.1", "geoplanet:7.5.2", "geoplanet:7.6.0", "geoplanet:7.8.1", "geoplanet:7.9.0", "geoplanet:7.10.0", "geoplanet:8.0.0", "woeplanet:8.0.0"], "meta:indexed": "2020-08-20T22:02:39.835877", "woe:alias_ENG_V": ["Rand Road Elementary"], "meta:updated": "2020-10-14T11:19:36.932235", "woe:hierarchy": {"continent": 24865672, "country": 23424977, "town": 0, "planet": 1, "county": 12589465, "suburb": 0, "state": 2347592, "region": 0, "localadmin": 0}, "woe:timezone_id": 56043648, "woe:hash": "dq24ffrp3u8z", "woe:centroid": [-78.619461, 35.653278], "geom:latitude": 35.653278, "geom:longitude": -78.619461, "geom:hash": "dq24ffrp3u8z", "woe:latitude": 35.653278, "geom:centroid": [-78.619461, 35.653278], "woe:longitude": -78.619461, "woe:repo": "woeplanet-poi-us", "geom:area": 0.0, "woe:scale": 19}}