{"type": "Feature", "id": 23589895, "properties": {"woe:id": 23589895, "woe:parent_id": 26342913, "woe:name": "Clarkston Christian School", "woe:placetype": 20, "woe:placetype_name": "POI", "woe:lang": "ENG", "iso:country": "US", "meta:provider": ["geoplanet:7.4.0", "geoplanet:7.4.1", "geoplanet:7.5.1", "geoplanet:7.5.2", "geoplanet:7.6.0", "geoplanet:7.8.1", "geoplanet:7.9.0", "geoplanet:7.10.0", "geoplanet:8.0.0", "woeplanet:8.0.0"], "meta:indexed": "2020-08-20T23:55:10.921719", "meta:updated": "2020-08-22T02:57:39.393832", "woe:hierarchy": {"continent": 24865672, "country": 23424977, "town": 0, "planet": 1, "county": 12588776, "suburb": 0, "state": 2347581, "region": 0, "localadmin": 0}, "woe:timezone_id": 56043658, "woe:hash": "dpsenhsum90w", "woe:centroid": [-83.401443, 42.740299], "geom:latitude": 42.740299, "geom:longitude": -83.401443, "geom:hash": "dpsenhsum90w", "woe:latitude": 42.740299, "geom:centroid": [-83.401443, 42.740299], "woe:longitude": -83.401443, "woe:repo": "woeplanet-poi-us"}, "geometry": {"coordinates": [-83.401443, 42.740299], "type": "Point"}}