{"type": "Feature", "id": 28349558, "properties": {"woe:id": 28349558, "woe:parent_id": 29229500, "woe:name": "Reisterstown Rd Plaza", "woe:placetype": 20, "woe:placetype_name": "POI", "woe:lang": "ENG", "iso:country": "US", "meta:provider": ["geoplanet:7.3.1", "geoplanet:7.3.2", "geoplanet:7.4.0", "geoplanet:7.4.1", "geoplanet:7.5.1", "geoplanet:7.5.2", "geoplanet:7.6.0", "geoplanet:7.8.1", "geoplanet:7.9.0", "geoplanet:7.10.0", "geoplanet:8.0.0", "woeplanet:8.0.0"], "meta:indexed": "2020-08-20T20:19:15.655605", "meta:updated": "2020-08-22T02:58:20.046081", "woe:hierarchy": {"continent": 24865672, "country": 23424977, "town": 0, "planet": 1, "county": 12588679, "suburb": 0, "state": 2347579, "region": 0, "localadmin": 0}, "woe:timezone_id": 56043648, "woe:hash": "dqcrz0x8w4qu", "woe:centroid": [-76.674004, 39.3339], "geom:latitude": 39.3339, "geom:longitude": -76.674004, "geom:hash": "dqcrz0x8w4qu", "woe:latitude": 39.3339, "geom:centroid": [-76.674004, 39.3339], "woe:longitude": -76.674004, "woe:repo": "woeplanet-poi-us"}, "geometry": {"coordinates": [-76.674004, 39.3339], "type": "Point"}}