{"type": "Feature", "id": 23589801, "properties": {"woe:id": 23589801, "woe:parent_id": 2513653, "woe:name": "Hickory Woods Elementary School", "woe:placetype": 20, "woe:placetype_name": "POI", "woe:lang": "ENG", "iso:country": "US", "meta:provider": ["geoplanet:7.3.1", "geoplanet:7.3.2", "geoplanet:7.4.0", "geoplanet:7.4.1", "geoplanet:7.5.1", "geoplanet:7.5.2", "geoplanet:7.6.0", "geoplanet:7.8.1", "geoplanet:7.9.0", "geoplanet:7.10.0", "geoplanet:8.0.0", "woeplanet:8.0.0"], "meta:indexed": "2020-08-20T20:18:41.150782", "woe:alias_ENG_V": ["Hickory Woods Elementary"], "meta:updated": "2020-08-22T02:57:39.370913", "woe:hierarchy": {"continent": 24865672, "country": 23424977, "town": 0, "planet": 1, "county": 12588776, "suburb": 0, "state": 2347581, "region": 0, "localadmin": 0}, "woe:timezone_id": 56043658, "woe:hash": "dps9ussg6dsz", "woe:centroid": [-83.467484, 42.520409], "geom:latitude": 42.520409, "geom:longitude": -83.467484, "geom:hash": "dps9ussg6dsz", "woe:latitude": 42.520409, "geom:centroid": [-83.467484, 42.520409], "woe:longitude": -83.467484, "woe:repo": "woeplanet-poi-us"}, "geometry": {"coordinates": [-83.467484, 42.520409], "type": "Point"}}