{"type": "Feature", "id": 23668445, "geometry": {"type": "Point", "coordinates": [-122.927353, 46.13726]}, "properties": {"woe:id": 23668445, "woe:parent_id": 2431324, "woe:name": "Broadway Learning Center", "woe:placetype": 20, "woe:placetype_name": "POI", "woe:lang": "ENG", "iso:country": "US", "meta:provider": ["geoplanet:7.3.2", "geoplanet:7.4.0", "geoplanet:7.4.1", "geoplanet:7.5.1", "geoplanet:7.5.2", "geoplanet:7.6.0", "geoplanet:7.8.1", "geoplanet:7.9.0", "geoplanet:7.10.0", "geoplanet:8.0.0", "woeplanet:8.0.0"], "meta:indexed": "2020-08-20T22:02:59.576605", "meta:updated": "2020-10-14T11:19:36.496855", "woe:alias_ENG_V": ["Broadway School"], "woe:hierarchy": {"continent": 24865672, "country": 23424977, "town": 0, "planet": 1, "county": 12590447, "suburb": 0, "state": 2347606, "region": 0, "localadmin": 0}, "woe:timezone_id": 56043663, "woe:hash": "c20w6xp110dh", "woe:centroid": [-122.927353, 46.13726], "geom:latitude": 46.13726, "geom:longitude": -122.927353, "geom:hash": "c20w6xp110dh", "woe:latitude": 46.13726, "geom:centroid": [-122.927353, 46.13726], "woe:longitude": -122.927353, "woe:repo": "woeplanet-poi-us", "geom:area": 0.0, "woe:scale": 19}}