{"type": "Feature", "id": 23643520, "geometry": {"type": "Point", "coordinates": [-76.578453, 40.783009]}, "properties": {"woe:id": 23643520, "woe:parent_id": 2491552, "woe:name": "Shamokin Area Junior High School", "woe:placetype": 20, "woe:placetype_name": "POI", "woe:lang": "ENG", "iso:country": "US", "meta:provider": ["geoplanet:7.3.1", "geoplanet:7.3.2", "geoplanet:7.4.0", "geoplanet:7.4.1", "geoplanet:7.5.1", "geoplanet:7.5.2", "geoplanet:7.6.0", "geoplanet:7.8.1", "geoplanet:7.9.0", "geoplanet:7.10.0", "geoplanet:8.0.0", "woeplanet:8.0.0"], "meta:indexed": "2020-08-20T20:18:59.611781", "woe:alias_ENG_V": ["Shamokin Area School Jr Sr High", "Shamokin Area Junior High"], "meta:updated": "2020-10-14T11:19:48.486751", "woe:hierarchy": {"continent": 24865672, "country": 23424977, "town": 0, "planet": 1, "county": 12589776, "suburb": 0, "state": 2347597, "region": 0, "localadmin": 0}, "woe:timezone_id": 56043648, "woe:hash": "dr3812m60xyu", "woe:centroid": [-76.578453, 40.783009], "geom:latitude": 40.783009, "geom:longitude": -76.578453, "geom:hash": "dr3812m60xyu", "woe:latitude": 40.783009, "geom:centroid": [-76.578453, 40.783009], "woe:longitude": -76.578453, "woe:repo": "woeplanet-poi-us", "geom:area": 0.0, "woe:scale": 19}}