{"type": "Feature", "id": 23570762, "geometry": {"type": "Point", "coordinates": [-93.490463, 41.498371]}, "properties": {"woe:id": 23570762, "woe:parent_id": 12588362, "woe:name": "Carlisle Elementary School", "woe:placetype": 20, "woe:placetype_name": "POI", "woe:lang": "ENG", "iso:country": "US", "meta:provider": ["geoplanet:7.3.1", "geoplanet:7.3.2", "geoplanet:7.4.0", "geoplanet:7.4.1", "geoplanet:7.5.1", "geoplanet:7.5.2", "geoplanet:7.6.0", "geoplanet:7.8.1", "geoplanet:7.9.0", "geoplanet:7.10.0", "geoplanet:8.0.0", "woeplanet:8.0.0"], "meta:indexed": "2020-08-20T20:18:35.676951", "woe:alias_ENG_V": ["Carlisle Elementary"], "meta:updated": "2020-10-14T11:20:21.484037", "woe:hierarchy": {"continent": 24865672, "country": 23424977, "town": 0, "planet": 1, "county": 12588362, "suburb": 0, "state": 2347574, "region": 0, "localadmin": 0}, "woe:timezone_id": 56043661, "woe:hash": "9zms0dd3d341", "woe:centroid": [-93.490463, 41.498371], "geom:latitude": 41.498371, "geom:longitude": -93.490463, "geom:hash": "9zms0dd3d341", "woe:latitude": 41.498371, "geom:centroid": [-93.490463, 41.498371], "woe:longitude": -93.490463, "woe:repo": "woeplanet-poi-us", "geom:area": 0.0, "woe:scale": 19}}