{"type": "Feature", "id": 23600780, "properties": {"woe:id": 23600780, "woe:parent_id": 2413588, "woe:name": "Whittier School", "woe:placetype": 20, "woe:placetype_name": "POI", "woe:lang": "ENG", "iso:country": "US", "meta:provider": ["geoplanet:7.3.1", "geoplanet:7.3.2", "geoplanet:7.4.0", "geoplanet:7.4.1", "geoplanet:7.5.1", "geoplanet:7.5.2", "geoplanet:7.6.0", "geoplanet:7.8.1", "geoplanet:7.9.0", "geoplanet:7.10.0", "geoplanet:8.0.0", "woeplanet:8.0.0"], "meta:indexed": "2020-08-20T20:18:45.150865", "meta:updated": "2020-08-22T02:57:41.190357", "woe:alias_ENG_V": ["Whittier Elementary School"], "woe:hierarchy": {"continent": 24865672, "country": 23424977, "town": 0, "planet": 1, "county": 12589087, "suburb": 0, "state": 2347585, "region": 0, "localadmin": 0}, "woe:timezone_id": 56043665, "woe:hash": "c82y72wmcs6u", "woe:centroid": [-111.293839, 47.50864], "geom:latitude": 47.50864, "geom:longitude": -111.293839, "geom:hash": "c82y72wmcs6u", "woe:latitude": 47.50864, "geom:centroid": [-111.293839, 47.50864], "woe:longitude": -111.293839, "woe:repo": "woeplanet-poi-us"}, "geometry": {"coordinates": [-111.293839, 47.50864], "type": "Point"}}