{"type": "Feature", "id": 23566466, "geometry": {"type": "Point", "coordinates": [-85.205368, 40.379269]}, "properties": {"woe:id": 23566466, "woe:parent_id": 2394454, "woe:name": "West Jay County Middle School", "woe:placetype": 20, "woe:placetype_name": "POI", "woe:lang": "ENG", "iso:country": "US", "meta:provider": ["geoplanet:7.3.2", "geoplanet:7.4.0", "geoplanet:7.4.1", "geoplanet:7.5.1", "geoplanet:7.5.2", "geoplanet:7.6.0", "geoplanet:7.8.1", "geoplanet:7.9.0", "geoplanet:7.10.0", "geoplanet:8.0.0", "woeplanet:8.0.0"], "meta:indexed": "2020-08-20T22:02:16.949688", "woe:alias_ENG_V": ["W Jay County Middle School"], "meta:updated": "2020-10-14T11:20:22.869604", "woe:hierarchy": {"continent": 24865672, "country": 23424977, "town": 0, "planet": 1, "county": 12588217, "suburb": 0, "state": 2347573, "region": 0, "localadmin": 0}, "woe:timezone_id": 56043656, "woe:hash": "dp5mtng67129", "woe:centroid": [-85.205368, 40.379269], "geom:latitude": 40.379269, "geom:longitude": -85.205368, "geom:hash": "dp5mtng67129", "woe:latitude": 40.379269, "geom:centroid": [-85.205368, 40.379269], "woe:longitude": -85.205368, "woe:repo": "woeplanet-poi-us", "geom:area": 0.0, "woe:scale": 19}}