{"type": "Feature", "id": 24866838, "properties": {"woe:id": 24866838, "woe:parent_id": 2495968, "woe:name": "Holy Cross College", "woe:placetype": 20, "woe:placetype_name": "POI", "woe:lang": "ENG", "iso:country": "US", "meta:provider": ["geoplanet:7.3.1", "geoplanet:7.3.2", "geoplanet:7.4.0", "geoplanet:7.4.1", "geoplanet:7.5.1", "geoplanet:7.5.2", "geoplanet:7.6.0", "geoplanet:7.8.1", "geoplanet:7.9.0", "geoplanet:7.10.0", "geoplanet:8.0.0", "woeplanet:8.0.0"], "meta:indexed": "2020-08-20T20:19:15.354604", "meta:updated": "2020-08-22T02:58:19.910159", "woe:hierarchy": {"continent": 24865672, "country": 23424977, "town": 0, "planet": 1, "county": 12588253, "suburb": 0, "state": 2347573, "region": 0, "localadmin": 0}, "woe:timezone_id": 56043656, "woe:hash": "dp6tjq4jf9t7", "woe:centroid": [-86.250801, 41.694111], "geom:latitude": 41.694111, "geom:longitude": -86.250801, "geom:hash": "dp6tjq4jf9t7", "woe:latitude": 41.694111, "geom:centroid": [-86.250801, 41.694111], "woe:longitude": -86.250801, "woe:repo": "woeplanet-poi-us"}, "geometry": {"coordinates": [-86.250801, 41.694111], "type": "Point"}}