{"type": "Feature", "id": 23567299, "properties": {"woe:id": 23567299, "woe:parent_id": 55986638, "woe:name": "Maplewood Elementary School", "woe:placetype": 20, "woe:placetype_name": "POI", "woe:lang": "ENG", "iso:country": "US", "meta:provider": ["geoplanet:7.3.1", "geoplanet:7.3.2", "geoplanet:7.4.0", "geoplanet:7.4.1", "geoplanet:7.5.1", "geoplanet:7.5.2", "geoplanet:7.6.0", "geoplanet:7.8.1", "geoplanet:7.9.0", "geoplanet:7.10.0", "geoplanet:8.0.0", "woeplanet:8.0.0"], "meta:indexed": "2020-08-20T20:18:34.382918", "woe:alias_ENG_V": ["Maplewood Elementary"], "meta:updated": "2020-08-22T02:57:35.823296", "woe:hierarchy": {"continent": 24865672, "country": 23424977, "town": 0, "planet": 1, "county": 12588228, "suburb": 0, "state": 2347573, "region": 0, "localadmin": 0}, "woe:timezone_id": 56043656, "woe:hash": "dp4dj7nmpm9r", "woe:centroid": [-86.244766, 39.743931], "geom:latitude": 39.743931, "geom:longitude": -86.244766, "geom:hash": "dp4dj7nmpm9r", "woe:latitude": 39.743931, "geom:centroid": [-86.244766, 39.743931], "woe:longitude": -86.244766, "woe:repo": "woeplanet-poi-us"}, "geometry": {"coordinates": [-86.244766, 39.743931], "type": "Point"}}