{"type": "Feature", "id": 23668275, "geometry": {"type": "Point", "coordinates": [-122.403259, 45.593311]}, "properties": {"woe:id": 23668275, "woe:parent_id": 55996130, "woe:name": "Helen Baller Elementary School", "woe:placetype": 20, "woe:placetype_name": "POI", "woe:lang": "ENG", "iso:country": "US", "meta:provider": ["geoplanet:7.3.1", "geoplanet:7.3.2", "geoplanet:7.4.0", "geoplanet:7.4.1", "geoplanet:7.5.1", "geoplanet:7.5.2", "geoplanet:7.6.0", "geoplanet:7.8.1", "geoplanet:7.9.0", "geoplanet:7.10.0", "geoplanet:8.0.0", "woeplanet:8.0.0"], "meta:indexed": "2020-08-20T20:19:09.059203", "woe:alias_ENG_V": ["Helen Baller Elementary"], "meta:updated": "2020-10-14T11:19:35.088710", "woe:hierarchy": {"continent": 24865672, "country": 23424977, "town": 0, "planet": 1, "county": 12590445, "suburb": 0, "state": 2347606, "region": 0, "localadmin": 0}, "woe:timezone_id": 56043663, "woe:hash": "c20gqsh8m34v", "woe:centroid": [-122.403259, 45.593311], "geom:latitude": 45.593311, "geom:longitude": -122.403259, "geom:hash": "c20gqsh8m34v", "woe:latitude": 45.593311, "geom:centroid": [-122.403259, 45.593311], "woe:longitude": -122.403259, "woe:repo": "woeplanet-poi-us", "geom:area": 0.0, "woe:scale": 19}}