{"type": "Feature", "id": 23518474, "geometry": {"type": "Point", "coordinates": [-92.009293, 34.218391]}, "properties": {"woe:id": 23518474, "woe:parent_id": 2471945, "woe:name": "Pine Bluff High School", "woe:placetype": 20, "woe:placetype_name": "POI", "woe:lang": "ENG", "iso:country": "US", "meta:provider": ["geoplanet:7.3.1", "geoplanet:7.3.2", "geoplanet:7.4.0", "geoplanet:7.4.1", "geoplanet:7.5.1", "geoplanet:7.5.2", "geoplanet:7.6.0", "geoplanet:7.8.1", "geoplanet:7.9.0", "geoplanet:7.10.0", "geoplanet:8.0.0", "woeplanet:8.0.0"], "meta:indexed": "2020-08-20T20:18:19.081584", "woe:alias_ENG_V": ["Pine Bluff Senior High School", "Pine Bluff High", "Pine Bluff Senior High", "Pine Bluff HS", "Pine Bluff Senior HS"], "meta:updated": "2020-10-14T11:20:19.628619", "woe:hierarchy": {"continent": 24865672, "country": 23424977, "town": 0, "planet": 1, "county": 12587629, "suburb": 0, "state": 2347562, "region": 0, "localadmin": 0}, "woe:timezone_id": 56043661, "woe:hash": "9ynddm2bs46t", "woe:centroid": [-92.009293, 34.218391], "geom:latitude": 34.218391, "geom:longitude": -92.009293, "geom:hash": "9ynddm2bs46t", "woe:latitude": 34.218391, "geom:centroid": [-92.009293, 34.218391], "woe:longitude": -92.009293, "woe:repo": "woeplanet-poi-us", "geom:area": 0.0, "woe:scale": 19}}