{"type": "Feature", "id": 23599149, "geometry": {"type": "Point", "coordinates": [-94.654541, 39.225121]}, "properties": {"woe:id": 23599149, "woe:parent_id": 2435256, "woe:name": "Plaza Middle School", "woe:placetype": 20, "woe:placetype_name": "POI", "woe:lang": "ENG", "iso:country": "US", "meta:provider": ["geoplanet:7.3.1", "geoplanet:7.3.2", "geoplanet:7.4.0", "geoplanet:7.4.1", "geoplanet:7.5.1", "geoplanet:7.5.2", "geoplanet:7.6.0", "geoplanet:7.8.1", "geoplanet:7.9.0", "geoplanet:7.10.0", "geoplanet:8.0.0", "woeplanet:8.0.0"], "meta:indexed": "2020-08-20T20:18:44.520880", "meta:updated": "2020-10-14T11:20:08.871552", "woe:hierarchy": {"continent": 24865672, "country": 23424977, "town": 0, "planet": 1, "county": 12589048, "suburb": 0, "state": 2347584, "region": 0, "localadmin": 0}, "woe:timezone_id": 56043661, "woe:hash": "9yuxnhdwvkd8", "woe:centroid": [-94.654541, 39.225121], "geom:latitude": 39.225121, "geom:longitude": -94.654541, "geom:hash": "9yuxnhdwvkd8", "woe:latitude": 39.225121, "geom:centroid": [-94.654541, 39.225121], "woe:longitude": -94.654541, "woe:repo": "woeplanet-poi-us", "geom:area": 0.0, "woe:scale": 19}}