{"type": "Feature", "id": 23582410, "properties": {"woe:id": 23582410, "woe:parent_id": 2437775, "woe:name": "Lee Elementary School", "woe:placetype": 20, "woe:placetype_name": "POI", "woe:lang": "ENG", "iso:country": "US", "meta:provider": ["geoplanet:7.3.2", "geoplanet:7.4.0", "geoplanet:7.4.1", "geoplanet:7.5.1", "geoplanet:7.5.2", "geoplanet:7.6.0", "geoplanet:7.8.1", "geoplanet:7.9.0", "geoplanet:7.10.0", "geoplanet:8.0.0", "woeplanet:8.0.0"], "meta:indexed": "2020-08-20T22:02:23.748692", "woe:alias_ENG_V": ["Lee Elementary"], "meta:updated": "2020-08-22T02:57:38.230311", "woe:hierarchy": {"continent": 24865672, "country": 23424977, "town": 0, "planet": 1, "county": 12588701, "suburb": 0, "state": 2347580, "region": 0, "localadmin": 0}, "woe:timezone_id": 56043648, "woe:hash": "drebtjy4scnb", "woe:centroid": [-73.248383, 42.307411], "geom:latitude": 42.307411, "geom:longitude": -73.248383, "geom:hash": "drebtjy4scnb", "woe:latitude": 42.307411, "geom:centroid": [-73.248383, 42.307411], "woe:longitude": -73.248383, "woe:repo": "woeplanet-poi-us"}, "geometry": {"coordinates": [-73.248383, 42.307411], "type": "Point"}}