{"type": "Feature", "id": 23653985, "properties": {"woe:id": 23653985, "woe:parent_id": 2382467, "woe:name": "Santa Clara Catholic Academy", "woe:placetype": 20, "woe:placetype_name": "POI", "woe:lang": "ENG", "iso:country": "US", "meta:provider": ["geoplanet:7.4.0", "geoplanet:7.4.1", "geoplanet:7.5.1", "geoplanet:7.5.2", "geoplanet:7.6.0", "geoplanet:7.8.1", "geoplanet:7.9.0", "geoplanet:7.10.0", "geoplanet:8.0.0", "woeplanet:8.0.0"], "meta:indexed": "2020-08-20T23:55:38.513455", "meta:updated": "2020-08-22T02:57:48.966757", "woe:hierarchy": {"continent": 24865672, "country": 23424977, "town": 0, "planet": 1, "county": 12590063, "suburb": 0, "state": 2347602, "region": 0, "localadmin": 0}, "woe:timezone_id": 56043661, "woe:hash": "9vg470ezrvxg", "woe:centroid": [-96.893921, 32.743279], "geom:latitude": 32.743279, "geom:longitude": -96.893921, "geom:hash": "9vg470ezrvxg", "woe:latitude": 32.743279, "geom:centroid": [-96.893921, 32.743279], "woe:longitude": -96.893921, "woe:repo": "woeplanet-poi-us"}, "geometry": {"coordinates": [-96.893921, 32.743279], "type": "Point"}}