{"type": "Feature", "id": 23603394, "geometry": {"type": "Point", "coordinates": [-98.378738, 40.944969]}, "properties": {"woe:id": 23603394, "woe:parent_id": 2412798, "woe:name": "Webb Plaza Station", "woe:placetype": 20, "woe:placetype_name": "POI", "woe:lang": "ENG", "iso:country": "US", "meta:provider": ["geoplanet:7.3.1", "geoplanet:7.3.2", "geoplanet:7.4.0", "geoplanet:7.4.1", "geoplanet:7.5.1", "geoplanet:7.5.2", "geoplanet:7.6.0", "geoplanet:7.8.1", "geoplanet:7.9.0", "geoplanet:7.10.0", "geoplanet:8.0.0", "woeplanet:8.0.0"], "meta:indexed": "2020-08-20T20:18:45.744204", "meta:updated": "2020-10-14T11:19:36.636286", "woe:hierarchy": {"continent": 24865672, "country": 23424977, "town": 0, "planet": 1, "county": 12589177, "suburb": 0, "state": 2347586, "region": 0, "localadmin": 0}, "woe:timezone_id": 56043661, "woe:hash": "9z60cmfc9r2j", "woe:centroid": [-98.378738, 40.944969], "geom:latitude": 40.944969, "geom:longitude": -98.378738, "geom:hash": "9z60cmfc9r2j", "woe:latitude": 40.944969, "geom:centroid": [-98.378738, 40.944969], "woe:longitude": -98.378738, "woe:repo": "woeplanet-poi-us", "geom:area": 0.0, "woe:scale": 19}}