{"type": "Feature", "id": 23624166, "geometry": {"type": "Point", "coordinates": [-80.270683, 35.683182]}, "properties": {"woe:id": 23624166, "woe:parent_id": 2402815, "woe:name": "Southwood Elementary School", "woe:placetype": 20, "woe:placetype_name": "POI", "woe:lang": "ENG", "iso:country": "US", "meta:provider": ["geoplanet:7.3.1", "geoplanet:7.3.2", "geoplanet:7.4.0", "geoplanet:7.4.1", "geoplanet:7.5.1", "geoplanet:7.5.2", "geoplanet:7.6.0", "geoplanet:7.8.1", "geoplanet:7.9.0", "geoplanet:7.10.0", "geoplanet:8.0.0", "woeplanet:8.0.0"], "meta:indexed": "2020-08-20T20:18:52.694498", "woe:alias_ENG_V": ["Southwood Elementary"], "meta:updated": "2020-10-14T11:19:27.145358", "woe:hierarchy": {"continent": 24865672, "country": 23424977, "town": 0, "planet": 1, "county": 12589402, "suburb": 0, "state": 2347592, "region": 0, "localadmin": 0}, "woe:timezone_id": 56043648, "woe:hash": "dnqfvrutte0x", "woe:centroid": [-80.270683, 35.683182], "geom:latitude": 35.683182, "geom:longitude": -80.270683, "geom:hash": "dnqfvrutte0x", "woe:latitude": 35.683182, "geom:centroid": [-80.270683, 35.683182], "woe:longitude": -80.270683, "woe:repo": "woeplanet-poi-us", "geom:area": 0.0, "woe:scale": 19}}