{"type": "Feature", "id": 23573064, "properties": {"woe:id": 23573064, "woe:parent_id": 55859859, "woe:name": "National Agricultural Center and Hall of Fame", "woe:placetype": 20, "woe:placetype_name": "POI", "woe:lang": "ENG", "iso:country": "US", "meta:provider": ["geoplanet:7.3.1", "geoplanet:7.3.2", "geoplanet:7.4.0", "geoplanet:7.4.1", "geoplanet:7.5.1", "geoplanet:7.5.2", "geoplanet:7.6.0", "geoplanet:7.8.1", "geoplanet:7.9.0", "geoplanet:7.10.0", "geoplanet:8.0.0", "woeplanet:8.0.0"], "meta:indexed": "2020-08-20T20:18:36.514562", "woe:alias_ENG_V": ["Nat'l Agricultural Ctr Hall of Fame", "National Agricultural Center & Hall of Fame"], "meta:updated": "2020-08-22T02:57:36.741485", "woe:hierarchy": {"continent": 24865672, "country": 23424977, "town": 0, "planet": 1, "county": 12588475, "suburb": 0, "state": 2347575, "region": 0, "localadmin": 0}, "woe:timezone_id": 56043661, "woe:hash": "9yuw3p7kq0x7", "woe:centroid": [-94.873199, 39.107941], "geom:latitude": 39.107941, "geom:longitude": -94.873199, "geom:hash": "9yuw3p7kq0x7", "woe:latitude": 39.107941, "geom:centroid": [-94.873199, 39.107941], "woe:longitude": -94.873199, "woe:repo": "woeplanet-poi-us"}, "geometry": {"coordinates": [-94.873199, 39.107941], "type": "Point"}}