{"type": "Feature", "id": 23652935, "properties": {"woe:id": 23652935, "woe:parent_id": 2473480, "woe:name": "Alton Boyd Elementary School", "woe:placetype": 20, "woe:placetype_name": "POI", "woe:lang": "ENG", "iso:country": "US", "meta:provider": ["geoplanet:7.3.1", "geoplanet:7.3.2", "geoplanet:7.4.0", "geoplanet:7.4.1", "geoplanet:7.5.1", "geoplanet:7.5.2", "geoplanet:7.6.0", "geoplanet:7.8.1", "geoplanet:7.9.0", "geoplanet:7.10.0", "geoplanet:8.0.0", "woeplanet:8.0.0"], "meta:indexed": "2020-08-20T20:19:02.618420", "woe:alias_ENG_V": ["Alton Boyd Elementary"], "meta:updated": "2020-08-22T02:57:48.686462", "woe:hierarchy": {"continent": 24865672, "country": 23424977, "town": 0, "planet": 1, "county": 12590049, "suburb": 0, "state": 2347602, "region": 0, "localadmin": 0}, "woe:timezone_id": 56043661, "woe:hash": "9vgk0q3eddmj", "woe:centroid": [-96.666527, 33.081821], "geom:latitude": 33.081821, "geom:longitude": -96.666527, "geom:hash": "9vgk0q3eddmj", "woe:latitude": 33.081821, "geom:centroid": [-96.666527, 33.081821], "woe:longitude": -96.666527, "woe:repo": "woeplanet-poi-us"}, "geometry": {"coordinates": [-96.666527, 33.081821], "type": "Point"}}