{"type": "Feature", "id": 56054834, "geometry": {"type": "Point", "coordinates": [-87.653023, 41.874409]}, "properties": {"woe:id": 56054834, "woe:parent_id": 28288749, "woe:name": "Uic Theatre", "woe:placetype": 20, "woe:placetype_name": "POI", "woe:lang": "ENG", "iso:country": "US", "meta:provider": ["geoplanet:7.3.1", "geoplanet:7.3.2", "geoplanet:7.4.0", "geoplanet:7.4.1", "geoplanet:7.5.1", "geoplanet:7.5.2", "geoplanet:7.6.0", "geoplanet:7.8.1", "geoplanet:7.9.0", "geoplanet:7.10.0", "geoplanet:8.0.0", "woeplanet:8.0.0"], "meta:indexed": "2020-08-20T20:19:18.158255", "meta:updated": "2020-10-14T11:19:55.990780", "woe:hierarchy": {"continent": 24865672, "country": 23424977, "town": 0, "planet": 1, "county": 12588093, "suburb": 0, "state": 2347572, "region": 0, "localadmin": 0}, "woe:timezone_id": 56043661, "woe:hash": "dp3wjrj00e8g", "woe:centroid": [-87.653023, 41.874409], "geom:latitude": 41.874409, "geom:longitude": -87.653023, "geom:hash": "dp3wjrj00e8g", "woe:latitude": 41.874409, "geom:centroid": [-87.653023, 41.874409], "woe:longitude": -87.653023, "woe:repo": "woeplanet-poi-us", "geom:area": 0.0, "woe:scale": 19}}