{"type": "Feature", "id": 56064212, "properties": {"woe:id": 56064212, "woe:parent_id": 28288772, "woe:name": "Baltimore Street North Station", "woe:placetype": 20, "woe:placetype_name": "POI", "woe:lang": "ENG", "iso:country": "US", "meta:provider": ["geoplanet:7.3.1", "geoplanet:7.3.2", "geoplanet:7.4.0", "geoplanet:7.4.1", "geoplanet:7.5.1", "geoplanet:7.5.2", "geoplanet:7.6.0", "geoplanet:7.8.1", "geoplanet:7.9.0", "geoplanet:7.10.0", "geoplanet:8.0.0", "woeplanet:8.0.0"], "meta:indexed": "2020-08-20T20:19:21.098307", "woe:alias_ENG_V": ["Baltimore Street North Light Rail Station", "Light Rail Baltimore Street North Station", "Light Rail-Baltimore Street North"], "meta:updated": "2020-08-22T02:58:23.143814", "woe:hierarchy": {"continent": 24865672, "country": 23424977, "town": 0, "planet": 1, "county": 12588679, "suburb": 0, "state": 2347579, "region": 0, "localadmin": 0}, "woe:timezone_id": 56043648, "woe:hash": "dqcx82r7wu86", "woe:centroid": [-76.619392, 39.289108], "geom:latitude": 39.289108, "geom:longitude": -76.619392, "geom:hash": "dqcx82r7wu86", "woe:latitude": 39.289108, "geom:centroid": [-76.619392, 39.289108], "woe:longitude": -76.619392, "woe:repo": "woeplanet-poi-us"}, "geometry": {"coordinates": [-76.619392, 39.289108], "type": "Point"}}