{"type": "Feature", "id": 23581191, "properties": {"woe:id": 23581191, "woe:parent_id": 2520367, "woe:name": "Parkdale High School", "woe:placetype": 20, "woe:placetype_name": "POI", "woe:lang": "ENG", "iso:country": "US", "meta:provider": ["geoplanet:7.3.2", "geoplanet:7.4.0", "geoplanet:7.4.1", "geoplanet:7.5.1", "geoplanet:7.5.2", "geoplanet:7.6.0", "geoplanet:7.8.1", "geoplanet:7.9.0", "geoplanet:7.10.0", "geoplanet:8.0.0", "woeplanet:8.0.0"], "meta:indexed": "2020-08-20T22:02:23.280132", "woe:alias_ENG_V": ["Parkdale Senior High School", "Parkdale High", "Parkdale Senior High", "Parkdale HS", "Parkdale Senior HS"], "meta:updated": "2020-08-22T02:58:47.757997", "woe:hierarchy": {"continent": 24865672, "country": 23424977, "town": 0, "planet": 1, "county": 12588692, "suburb": 0, "state": 2347579, "region": 0, "localadmin": 0}, "woe:timezone_id": 56043648, "woe:hash": "dqcmdndjs87b", "woe:centroid": [-76.901352, 38.972198], "geom:latitude": 38.972198, "geom:longitude": -76.901352, "geom:hash": "dqcmdndjs87b", "woe:latitude": 38.972198, "geom:centroid": [-76.901352, 38.972198], "woe:longitude": -76.901352, "woe:repo": "woeplanet-poi-us"}, "geometry": {"coordinates": [-76.901352, 38.972198], "type": "Point"}}