{"type": "Feature", "id": 23600034, "geometry": {"type": "Point", "coordinates": [-93.19471, 39.11198]}, "properties": {"woe:id": 23600034, "woe:parent_id": 2446109, "woe:name": "Southeast Elementary School", "woe:placetype": 20, "woe:placetype_name": "POI", "woe:lang": "ENG", "iso:country": "US", "meta:provider": ["geoplanet:7.3.1", "geoplanet:7.3.2", "geoplanet:7.4.0", "geoplanet:7.4.1", "geoplanet:7.5.1", "geoplanet:7.5.2", "geoplanet:7.6.0", "geoplanet:7.8.1", "geoplanet:7.9.0", "geoplanet:7.10.0", "geoplanet:8.0.0", "woeplanet:8.0.0"], "meta:indexed": "2020-08-20T20:18:44.886368", "woe:alias_ENG_V": ["SE Elementary School", "SE Elementary", "Southeast Elementary"], "meta:updated": "2020-10-14T11:19:35.619185", "woe:hierarchy": {"continent": 24865672, "country": 23424977, "town": 0, "planet": 1, "county": 12589057, "suburb": 0, "state": 2347584, "region": 0, "localadmin": 0}, "woe:timezone_id": 56043661, "woe:hash": "9yvwx21evce8", "woe:centroid": [-93.19471, 39.11198], "geom:latitude": 39.11198, "geom:longitude": -93.19471, "geom:hash": "9yvwx21evce8", "woe:latitude": 39.11198, "geom:centroid": [-93.19471, 39.11198], "woe:longitude": -93.19471, "woe:repo": "woeplanet-poi-us", "geom:area": 0.0, "woe:scale": 19}}