{"type": "Feature", "id": 23549728, "geometry": {"type": "Point", "coordinates": [-80.175301, 25.910311]}, "properties": {"woe:id": 23549728, "woe:parent_id": 55860642, "woe:name": "Holy Family School", "woe:placetype": 20, "woe:placetype_name": "POI", "woe:lang": "ENG", "iso:country": "US", "meta:provider": ["geoplanet:7.3.1", "geoplanet:7.3.2", "geoplanet:7.4.0", "geoplanet:7.4.1", "geoplanet:7.5.1", "geoplanet:7.5.2", "geoplanet:7.6.0", "geoplanet:7.8.1", "geoplanet:7.9.0", "geoplanet:7.10.0", "geoplanet:8.0.0", "woeplanet:8.0.0"], "meta:indexed": "2020-08-20T20:18:28.060868", "meta:updated": "2020-10-14T11:20:27.950134", "woe:alias_ENG_V": ["Holy Family Catholic School"], "woe:hierarchy": {"continent": 24865672, "country": 23424977, "town": 0, "planet": 1, "county": 12587815, "suburb": 0, "state": 2347568, "region": 0, "localadmin": 0}, "woe:timezone_id": 56043648, "woe:hash": "dhwgrsf4s049", "woe:centroid": [-80.175301, 25.910311], "geom:latitude": 25.910311, "geom:longitude": -80.175301, "geom:hash": "dhwgrsf4s049", "woe:latitude": 25.910311, "geom:centroid": [-80.175301, 25.910311], "woe:longitude": -80.175301, "woe:repo": "woeplanet-poi-us", "geom:area": 0.0, "woe:scale": 19}}