{"type": "Feature", "id": 23575519, "properties": {"woe:id": 23575519, "woe:parent_id": 2385602, "woe:name": "Cottonport Elementary School", "woe:placetype": 20, "woe:placetype_name": "POI", "woe:lang": "ENG", "iso:country": "US", "meta:provider": ["geoplanet:7.3.1", "geoplanet:7.3.2", "geoplanet:7.4.0", "geoplanet:7.4.1", "geoplanet:7.5.1", "geoplanet:7.5.2", "geoplanet:7.6.0", "geoplanet:7.8.1", "geoplanet:7.9.0", "geoplanet:7.10.0", "geoplanet:8.0.0", "woeplanet:8.0.0"], "meta:indexed": "2020-08-20T20:18:37.204584", "woe:alias_ENG_V": ["Cottonport Elementary"], "meta:updated": "2020-08-22T02:57:37.103506", "woe:hierarchy": {"continent": 24865672, "country": 23424977, "town": 0, "planet": 1, "county": 12588600, "suburb": 0, "state": 2347577, "region": 0, "localadmin": 0}, "woe:timezone_id": 56043661, "woe:hash": "9vw8320gh7mz", "woe:centroid": [-92.053223, 30.981979], "geom:latitude": 30.981979, "geom:longitude": -92.053223, "geom:hash": "9vw8320gh7mz", "woe:latitude": 30.981979, "geom:centroid": [-92.053223, 30.981979], "woe:longitude": -92.053223, "woe:repo": "woeplanet-poi-us"}, "geometry": {"coordinates": [-92.053223, 30.981979], "type": "Point"}}