{"type": "Feature", "id": 23555241, "properties": {"woe:id": 23555241, "woe:parent_id": 2434019, "woe:name": "Kuna High School", "woe:placetype": 20, "woe:placetype_name": "POI", "woe:lang": "ENG", "iso:country": "US", "meta:provider": ["geoplanet:7.3.1", "geoplanet:7.3.2", "geoplanet:7.4.0", "geoplanet:7.4.1", "geoplanet:7.5.1", "geoplanet:7.5.2", "geoplanet:7.6.0", "geoplanet:7.8.1", "geoplanet:7.9.0", "geoplanet:7.10.0", "geoplanet:8.0.0", "woeplanet:8.0.0"], "meta:indexed": "2020-08-20T20:18:30.126247", "woe:alias_ENG_V": ["Kuna Senior High School", "Kuna High", "Kuna Senior High", "Kuna HS", "Kuna Senior HS", "Kuna Middle School"], "meta:updated": "2020-08-22T02:58:46.923485", "woe:hierarchy": {"continent": 24865672, "country": 23424977, "town": 0, "planet": 1, "county": 12588034, "suburb": 0, "state": 2347571, "region": 0, "localadmin": 0}, "woe:timezone_id": 56043662, "woe:hash": "9rtpqw4hwuw4", "woe:centroid": [-116.430061, 43.49567], "geom:latitude": 43.49567, "geom:longitude": -116.430061, "geom:hash": "9rtpqw4hwuw4", "woe:latitude": 43.49567, "geom:centroid": [-116.430061, 43.49567], "woe:longitude": -116.430061, "woe:repo": "woeplanet-poi-us"}, "geometry": {"coordinates": [-116.430061, 43.49567], "type": "Point"}}