{"type": "Feature", "id": 23529279, "properties": {"woe:id": 23529279, "woe:parent_id": 2427376, "woe:name": "Inyokern Elementary School", "woe:placetype": 20, "woe:placetype_name": "POI", "woe:lang": "ENG", "iso:country": "US", "meta:provider": ["geoplanet:7.3.1", "geoplanet:7.3.2", "geoplanet:7.4.0", "geoplanet:7.4.1", "geoplanet:7.5.1", "geoplanet:7.5.2", "geoplanet:7.6.0", "geoplanet:7.8.1", "geoplanet:7.9.0", "geoplanet:7.10.0", "geoplanet:8.0.0", "woeplanet:8.0.0"], "meta:indexed": "2020-08-20T20:18:21.411495", "woe:alias_ENG_V": ["Inyokern Elementary"], "meta:updated": "2020-08-22T02:57:28.486346", "woe:hierarchy": {"continent": 24865672, "country": 23424977, "town": 0, "planet": 1, "county": 12587684, "suburb": 0, "state": 2347563, "region": 0, "localadmin": 0}, "woe:timezone_id": 56043663, "woe:hash": "9qk4z11sf61x", "woe:centroid": [-117.815224, 35.645969], "geom:latitude": 35.645969, "geom:longitude": -117.815224, "geom:hash": "9qk4z11sf61x", "woe:latitude": 35.645969, "geom:centroid": [-117.815224, 35.645969], "woe:longitude": -117.815224, "woe:repo": "woeplanet-poi-us"}, "geometry": {"coordinates": [-117.815224, 35.645969], "type": "Point"}}