{"type": "Feature", "id": 56053454, "geometry": {"type": "Point", "coordinates": [-77.053581, 38.92712]}, "properties": {"woe:id": 56053454, "woe:parent_id": 55974727, "woe:name": "Boston University-Washington Center", "woe:placetype": 20, "woe:placetype_name": "POI", "woe:lang": "ENG", "iso:country": "US", "meta:provider": ["geoplanet:7.3.1", "geoplanet:7.3.2", "geoplanet:7.4.0", "geoplanet:7.4.1", "geoplanet:7.5.1", "geoplanet:7.5.2", "geoplanet:7.6.0", "geoplanet:7.8.1", "geoplanet:7.9.0", "geoplanet:7.10.0", "geoplanet:8.0.0", "woeplanet:8.0.0"], "meta:indexed": "2020-08-20T20:19:17.063179", "meta:updated": "2020-10-14T11:19:56.338424", "woe:hierarchy": {"continent": 24865672, "country": 23424977, "town": 0, "planet": 1, "county": 12587802, "suburb": 0, "state": 2347567, "region": 0, "localadmin": 0}, "woe:timezone_id": 56043648, "woe:hash": "dqcjqw7qcmje", "woe:centroid": [-77.053581, 38.92712], "geom:latitude": 38.92712, "geom:longitude": -77.053581, "geom:hash": "dqcjqw7qcmje", "woe:latitude": 38.92712, "geom:centroid": [-77.053581, 38.92712], "woe:longitude": -77.053581, "woe:repo": "woeplanet-poi-us", "geom:area": 0.0, "woe:scale": 19}}