{"type": "Feature", "id": 23682390, "geometry": {"type": "Point", "coordinates": [-74.088112, 40.714661]}, "properties": {"woe:id": 23682390, "woe:parent_id": 55859816, "woe:name": "West Side Avenue Station", "woe:placetype": 20, "woe:placetype_name": "POI", "woe:lang": "ENG", "iso:country": "US", "meta:provider": ["geoplanet:7.3.1", "geoplanet:7.3.2", "geoplanet:7.4.0", "geoplanet:7.4.1", "geoplanet:7.5.1", "geoplanet:7.5.2", "geoplanet:7.6.0", "geoplanet:7.8.1", "geoplanet:7.9.0", "geoplanet:7.10.0", "geoplanet:8.0.0", "woeplanet:8.0.0"], "meta:indexed": "2020-08-20T20:19:19.687177", "woe:alias_ENG_V": ["W Side Avenue Station", "West Side Avenue NJ Transit Station", "NJ Transit West Side Avenue Station", "Nj Transit-Hblr-West Side Ave"], "meta:updated": "2020-10-14T11:19:41.226281", "woe:hierarchy": {"continent": 24865672, "country": 23424977, "town": 0, "planet": 1, "county": 12589266, "suburb": 0, "state": 2347589, "region": 0, "localadmin": 0}, "woe:timezone_id": 56043648, "woe:hash": "dr5rd5fsjfgt", "woe:centroid": [-74.088112, 40.714661], "geom:latitude": 40.714661, "geom:longitude": -74.088112, "geom:hash": "dr5rd5fsjfgt", "woe:latitude": 40.714661, "geom:centroid": [-74.088112, 40.714661], "woe:longitude": -74.088112, "woe:repo": "woeplanet-poi-us", "geom:area": 0.0, "woe:scale": 19}}