{"type": "Feature", "id": 23544380, "properties": {"woe:id": 23544380, "woe:parent_id": 23417277, "woe:name": "Parent Resource & Exceptional", "woe:placetype": 20, "woe:placetype_name": "POI", "woe:lang": "ENG", "iso:country": "US", "meta:provider": ["geoplanet:7.3.1", "geoplanet:7.3.2", "geoplanet:7.4.0", "geoplanet:7.4.1", "geoplanet:7.5.1", "geoplanet:7.5.2", "geoplanet:7.6.0", "geoplanet:7.8.1", "geoplanet:7.9.0", "geoplanet:7.10.0", "geoplanet:8.0.0", "woeplanet:8.0.0"], "meta:indexed": "2020-08-20T20:18:25.580270", "woe:alias_ENG_V": ["Parent Resource and Exceptional"], "meta:updated": "2020-08-22T02:57:31.312834", "woe:hierarchy": {"continent": 24865672, "country": 23424977, "town": 0, "planet": 1, "county": 12587796, "suburb": 0, "state": 2347565, "region": 0, "localadmin": 0}, "woe:timezone_id": 56043648, "woe:hash": "drkenwhj842n", "woe:centroid": [-72.130737, 41.34251], "geom:latitude": 41.34251, "geom:longitude": -72.130737, "geom:hash": "drkenwhj842n", "woe:latitude": 41.34251, "geom:centroid": [-72.130737, 41.34251], "woe:longitude": -72.130737, "woe:repo": "woeplanet-poi-us"}, "geometry": {"coordinates": [-72.130737, 41.34251], "type": "Point"}}