{"type": "Feature", "id": 23525601, "properties": {"woe:id": 23525601, "woe:parent_id": 2518285, "woe:name": "Marjorie H. Tobias Elementary School", "woe:placetype": 20, "woe:placetype_name": "POI", "woe:lang": "ENG", "iso:country": "US", "meta:provider": ["geoplanet:7.3.1", "geoplanet:7.3.2", "geoplanet:7.4.0", "geoplanet:7.4.1", "geoplanet:7.5.1", "geoplanet:7.5.2", "geoplanet:7.6.0", "geoplanet:7.8.1", "geoplanet:7.9.0", "geoplanet:7.10.0", "geoplanet:8.0.0", "woeplanet:8.0.0"], "meta:indexed": "2020-08-20T20:18:20.645904", "woe:alias_ENG_V": ["Marjorie H Tobias Elementary School", "Marjorie H. Tobias Elementary"], "meta:updated": "2020-08-22T02:57:27.939576", "woe:hierarchy": {"continent": 24865672, "country": 23424977, "town": 0, "planet": 1, "county": 12587710, "suburb": 0, "state": 2347563, "region": 0, "localadmin": 0}, "woe:timezone_id": 56043663, "woe:hash": "9q8yktsf025d", "woe:centroid": [-122.49102, 37.691689], "geom:latitude": 37.691689, "geom:longitude": -122.49102, "geom:hash": "9q8yktsf025d", "woe:latitude": 37.691689, "geom:centroid": [-122.49102, 37.691689], "woe:longitude": -122.49102, "woe:repo": "woeplanet-poi-us"}, "geometry": {"coordinates": [-122.49102, 37.691689], "type": "Point"}}