{"type": "Feature", "id": 23633062, "properties": {"woe:id": 23633062, "woe:parent_id": 2517853, "woe:name": "Hilltop Elementary School", "woe:placetype": 20, "woe:placetype_name": "POI", "woe:lang": "ENG", "iso:country": "US", "meta:provider": ["geoplanet:7.3.2", "geoplanet:7.4.0", "geoplanet:7.4.1", "geoplanet:7.5.1", "geoplanet:7.5.2", "geoplanet:7.6.0", "geoplanet:7.8.1", "geoplanet:7.9.0", "geoplanet:7.10.0", "geoplanet:8.0.0", "woeplanet:8.0.0"], "meta:indexed": "2020-08-20T22:02:44.290420", "woe:alias_ENG_V": ["Hilltop Elementary"], "meta:updated": "2020-08-22T02:57:45.635701", "woe:hierarchy": {"continent": 24865672, "country": 23424977, "town": 0, "planet": 1, "county": 12589612, "suburb": 0, "state": 2347594, "region": 0, "localadmin": 0}, "woe:timezone_id": 56043648, "woe:hash": "dp7uwd6dztum", "woe:centroid": [-84.437157, 41.585129], "geom:latitude": 41.585129, "geom:longitude": -84.437157, "geom:hash": "dp7uwd6dztum", "woe:latitude": 41.585129, "geom:centroid": [-84.437157, 41.585129], "woe:longitude": -84.437157, "woe:repo": "woeplanet-poi-us"}, "geometry": {"coordinates": [-84.437157, 41.585129], "type": "Point"}}