{"type": "Feature", "id": 23626356, "geometry": {"type": "Point", "coordinates": [-100.763733, 46.736729]}, "properties": {"woe:id": 23626356, "woe:parent_id": 55858058, "woe:name": "Prairie Rose Elementary School", "woe:placetype": 20, "woe:placetype_name": "POI", "woe:lang": "ENG", "iso:country": "US", "meta:provider": ["geoplanet:7.3.2", "geoplanet:7.4.0", "geoplanet:7.4.1", "geoplanet:7.5.1", "geoplanet:7.5.2", "geoplanet:7.6.0", "geoplanet:7.8.1", "geoplanet:7.9.0", "geoplanet:7.10.0", "geoplanet:8.0.0", "woeplanet:8.0.0"], "meta:indexed": "2020-08-20T22:02:40.824639", "woe:alias_ENG_V": ["Prairie Rose Elementary"], "meta:updated": "2020-10-14T11:19:45.883808", "woe:hierarchy": {"continent": 24865672, "country": 23424977, "town": 0, "planet": 1, "county": 12589481, "suburb": 0, "state": 2347593, "region": 0, "localadmin": 0}, "woe:timezone_id": 56043661, "woe:hash": "cb23gh4j4vfb", "woe:centroid": [-100.763733, 46.736729], "geom:latitude": 46.736729, "geom:longitude": -100.763733, "geom:hash": "cb23gh4j4vfb", "woe:latitude": 46.736729, "geom:centroid": [-100.763733, 46.736729], "woe:longitude": -100.763733, "woe:repo": "woeplanet-poi-us", "geom:area": 0.0, "woe:scale": 19}}