{"type": "Feature", "id": 23526464, "properties": {"woe:id": 23526464, "woe:parent_id": 55969939, "woe:name": "Beacon School", "woe:placetype": 20, "woe:placetype_name": "POI", "woe:lang": "ENG", "iso:country": "US", "meta:provider": ["geoplanet:7.3.1", "geoplanet:7.3.2", "geoplanet:7.4.0", "geoplanet:7.4.1", "geoplanet:7.5.1", "geoplanet:7.5.2", "geoplanet:7.6.0", "geoplanet:7.8.1", "geoplanet:7.9.0", "geoplanet:7.10.0", "geoplanet:8.0.0", "woeplanet:8.0.0"], "meta:indexed": "2020-08-20T20:18:20.872901", "meta:updated": "2020-08-22T02:57:28.110072", "woe:hierarchy": {"continent": 24865672, "country": 23424977, "town": 0, "planet": 1, "county": 12587712, "suburb": 0, "state": 2347563, "region": 0, "localadmin": 0}, "woe:timezone_id": 56043663, "woe:hash": "9q97f427xz6j", "woe:centroid": [-121.903618, 37.23468], "geom:latitude": 37.23468, "geom:longitude": -121.903618, "geom:hash": "9q97f427xz6j", "woe:latitude": 37.23468, "geom:centroid": [-121.903618, 37.23468], "woe:longitude": -121.903618, "woe:repo": "woeplanet-poi-us"}, "geometry": {"coordinates": [-121.903618, 37.23468], "type": "Point"}}