{"type": "Feature", "id": 23526832, "geometry": {"type": "Point", "coordinates": [-121.846283, 36.92585]}, "properties": {"woe:id": 23526832, "woe:parent_id": 2405316, "woe:name": "Renaissance High School", "woe:placetype": 20, "woe:placetype_name": "POI", "woe:lang": "ENG", "iso:country": "US", "meta:provider": ["geoplanet:7.3.2", "geoplanet:7.4.0", "geoplanet:7.4.1", "geoplanet:7.5.1", "geoplanet:7.5.2", "geoplanet:7.6.0", "geoplanet:7.8.1", "geoplanet:7.9.0", "geoplanet:7.10.0", "geoplanet:8.0.0", "woeplanet:8.0.0"], "meta:indexed": "2020-08-20T22:02:00.519395", "woe:alias_ENG_V": ["Renaissance Senior High School", "Renaissance High", "Renaissance Senior High", "Renaissance HS", "Renaissance Senior HS"], "meta:updated": "2020-10-14T11:20:07.186749", "woe:hierarchy": {"continent": 24865672, "country": 23424977, "town": 0, "planet": 1, "county": 12587713, "suburb": 0, "state": 2347563, "region": 0, "localadmin": 0}, "woe:timezone_id": 56043663, "woe:hash": "9q96564hxv67", "woe:centroid": [-121.846283, 36.92585], "geom:latitude": 36.92585, "geom:longitude": -121.846283, "geom:hash": "9q96564hxv67", "woe:latitude": 36.92585, "geom:centroid": [-121.846283, 36.92585], "woe:longitude": -121.846283, "woe:repo": "woeplanet-poi-us", "geom:area": 0.0, "woe:scale": 19}}