{"type": "Feature", "id": 23656425, "geometry": {"type": "Point", "coordinates": [-97.227768, 32.841068]}, "properties": {"woe:id": 23656425, "woe:parent_id": 2461528, "woe:name": "Richland High School", "woe:placetype": 20, "woe:placetype_name": "POI", "woe:lang": "ENG", "iso:country": "US", "meta:provider": ["geoplanet:7.3.1", "geoplanet:7.3.2", "geoplanet:7.4.0", "geoplanet:7.4.1", "geoplanet:7.5.1", "geoplanet:7.5.2", "geoplanet:7.6.0", "geoplanet:7.8.1", "geoplanet:7.9.0", "geoplanet:7.10.0", "geoplanet:8.0.0", "woeplanet:8.0.0"], "meta:indexed": "2020-08-20T20:19:04.338791", "woe:alias_ENG_V": ["Richland Senior High School", "Richland High", "Richland Senior High", "Richland HS", "Richland Senior HS"], "meta:updated": "2020-10-14T11:19:41.433609", "woe:hierarchy": {"continent": 24865672, "country": 23424977, "town": 0, "planet": 1, "county": 12590226, "suburb": 0, "state": 2347602, "region": 0, "localadmin": 0}, "woe:timezone_id": 56043661, "woe:hash": "9vffgd8chfc9", "woe:centroid": [-97.227768, 32.841068], "geom:latitude": 32.841068, "geom:longitude": -97.227768, "geom:hash": "9vffgd8chfc9", "woe:latitude": 32.841068, "geom:centroid": [-97.227768, 32.841068], "woe:longitude": -97.227768, "woe:repo": "woeplanet-poi-us", "geom:area": 0.0, "woe:scale": 19}}