{"type": "Feature", "id": 23654374, "properties": {"woe:id": 23654374, "woe:parent_id": 2481693, "woe:name": "Rising Star High School", "woe:placetype": 20, "woe:placetype_name": "POI", "woe:lang": "ENG", "iso:country": "US", "meta:provider": ["geoplanet:7.3.1", "geoplanet:7.3.2", "geoplanet:7.4.0", "geoplanet:7.4.1", "geoplanet:7.5.1", "geoplanet:7.5.2", "geoplanet:7.6.0", "geoplanet:7.8.1", "geoplanet:7.9.0", "geoplanet:7.10.0", "geoplanet:8.0.0", "woeplanet:8.0.0"], "meta:indexed": "2020-08-20T20:19:03.338356", "woe:alias_ENG_V": ["Rising Star Senior High School", "Rising Star High", "Rising Star Senior High", "Rising Star HS", "Rising Star Senior HS"], "meta:updated": "2020-08-22T02:58:49.823637", "woe:hierarchy": {"continent": 24865672, "country": 23424977, "town": 0, "planet": 1, "county": 12590073, "suburb": 0, "state": 2347602, "region": 0, "localadmin": 0}, "woe:timezone_id": 56043661, "woe:hash": "9v9wsh2mt266", "woe:centroid": [-98.964272, 32.10437], "geom:latitude": 32.10437, "geom:longitude": -98.964272, "geom:hash": "9v9wsh2mt266", "woe:latitude": 32.10437, "geom:centroid": [-98.964272, 32.10437], "woe:longitude": -98.964272, "woe:repo": "woeplanet-poi-us"}, "geometry": {"coordinates": [-98.964272, 32.10437], "type": "Point"}}