{"type": "Feature", "id": 23540955, "geometry": {"type": "Point", "coordinates": [-105.146011, 39.84156]}, "properties": {"woe:id": 23540955, "woe:parent_id": 2438893, "woe:name": "Ralston Valley Senior High School", "woe:placetype": 20, "woe:placetype_name": "POI", "woe:lang": "ENG", "iso:country": "US", "meta:provider": ["geoplanet:7.3.1", "geoplanet:7.3.2", "geoplanet:7.4.0", "geoplanet:7.4.1", "geoplanet:7.5.1", "geoplanet:7.5.2", "geoplanet:7.6.0", "geoplanet:7.8.1", "geoplanet:7.9.0", "geoplanet:7.10.0", "geoplanet:8.0.0", "woeplanet:8.0.0"], "meta:indexed": "2020-08-20T20:18:24.636184", "woe:alias_ENG_V": ["Ralston Valley Senior High", "Ralston Valley High School", "Ralston Valley High", "Ralston Valley Senior HS", "Ralston Valley HS"], "meta:updated": "2020-10-14T11:20:18.103519", "woe:hierarchy": {"continent": 24865672, "country": 23424977, "town": 0, "planet": 1, "county": 12587757, "suburb": 0, "state": 2347564, "region": 0, "localadmin": 0}, "woe:timezone_id": 56043665, "woe:hash": "9xj4xkgjbm5d", "woe:centroid": [-105.146011, 39.84156], "geom:latitude": 39.84156, "geom:longitude": -105.146011, "geom:hash": "9xj4xkgjbm5d", "woe:latitude": 39.84156, "geom:centroid": [-105.146011, 39.84156], "woe:longitude": -105.146011, "woe:repo": "woeplanet-poi-us", "geom:area": 0.0, "woe:scale": 19}}