{"type": "Feature", "id": 23541338, "geometry": {"type": "Point", "coordinates": [-105.073822, 40.563351]}, "properties": {"woe:id": 23541338, "woe:parent_id": 55859030, "woe:name": "Rivendell School of N. Colorado", "woe:placetype": 20, "woe:placetype_name": "POI", "woe:lang": "ENG", "iso:country": "US", "meta:provider": ["geoplanet:7.3.1", "geoplanet:7.3.2", "geoplanet:7.4.0", "geoplanet:7.4.1", "geoplanet:7.5.1", "geoplanet:7.5.2", "geoplanet:7.6.0", "geoplanet:7.8.1", "geoplanet:7.9.0", "geoplanet:7.10.0", "geoplanet:8.0.0", "woeplanet:8.0.0"], "meta:indexed": "2020-08-20T20:18:24.719517", "meta:updated": "2020-10-14T11:20:03.321128", "woe:hierarchy": {"continent": 24865672, "country": 23424977, "town": 0, "planet": 1, "county": 12587762, "suburb": 0, "state": 2347564, "region": 0, "localadmin": 0}, "woe:timezone_id": 56043665, "woe:hash": "9xjqbbrddkxt", "woe:centroid": [-105.073822, 40.563351], "geom:latitude": 40.563351, "geom:longitude": -105.073822, "geom:hash": "9xjqbbrddkxt", "woe:latitude": 40.563351, "geom:centroid": [-105.073822, 40.563351], "woe:longitude": -105.073822, "woe:repo": "woeplanet-poi-us", "geom:area": 0.0, "woe:scale": 19}}