{"type": "Feature", "id": 23580778, "geometry": {"type": "Point", "coordinates": [-77.249702, 39.0816]}, "properties": {"woe:id": 23580778, "woe:parent_id": 2364061, "woe:name": "Travilah Elementary School", "woe:placetype": 20, "woe:placetype_name": "POI", "woe:lang": "ENG", "iso:country": "US", "meta:provider": ["geoplanet:7.3.2", "geoplanet:7.4.0", "geoplanet:7.4.1", "geoplanet:7.5.1", "geoplanet:7.5.2", "geoplanet:7.6.0", "geoplanet:7.8.1", "geoplanet:7.9.0", "geoplanet:7.10.0", "geoplanet:8.0.0", "woeplanet:8.0.0"], "meta:indexed": "2020-08-20T22:02:23.079505", "woe:alias_ENG_V": ["Travilah Elementary"], "meta:updated": "2020-10-14T11:20:12.415625", "woe:hierarchy": {"continent": 24865672, "country": 23424977, "town": 0, "planet": 1, "county": 12588691, "suburb": 0, "state": 2347579, "region": 0, "localadmin": 0}, "woe:timezone_id": 56043648, "woe:hash": "dqcn64s6z6r2", "woe:centroid": [-77.249702, 39.0816], "geom:latitude": 39.0816, "geom:longitude": -77.249702, "geom:hash": "dqcn64s6z6r2", "woe:latitude": 39.0816, "geom:centroid": [-77.249702, 39.0816], "woe:longitude": -77.249702, "woe:repo": "woeplanet-poi-us", "geom:area": 0.0, "woe:scale": 19}}