{"type": "Feature", "id": 23632967, "geometry": {"type": "Point", "coordinates": [-81.601929, 39.281101]}, "properties": {"woe:id": 23632967, "woe:parent_id": 2362317, "woe:name": "William R Stone Elementary School", "woe:placetype": 20, "woe:placetype_name": "POI", "woe:lang": "ENG", "iso:country": "US", "meta:provider": ["geoplanet:7.3.1", "geoplanet:7.3.2", "geoplanet:7.4.0", "geoplanet:7.4.1", "geoplanet:7.5.1", "geoplanet:7.5.2", "geoplanet:7.6.0", "geoplanet:7.8.1", "geoplanet:7.9.0", "geoplanet:7.10.0", "geoplanet:8.0.0", "woeplanet:8.0.0"], "meta:indexed": "2020-08-20T20:18:55.836259", "woe:alias_ENG_V": ["William R Stone Elementary"], "meta:updated": "2020-10-14T11:19:35.800275", "woe:hierarchy": {"continent": 24865672, "country": 23424977, "town": 0, "planet": 1, "county": 12589610, "suburb": 0, "state": 2347594, "region": 0, "localadmin": 0}, "woe:timezone_id": 56043648, "woe:hash": "dnvzrngkcpzw", "woe:centroid": [-81.601929, 39.281101], "geom:latitude": 39.281101, "geom:longitude": -81.601929, "geom:hash": "dnvzrngkcpzw", "woe:latitude": 39.281101, "geom:centroid": [-81.601929, 39.281101], "woe:longitude": -81.601929, "woe:repo": "woeplanet-poi-us", "geom:area": 0.0, "woe:scale": 19}}