{"type": "Feature", "id": 23596354, "properties": {"woe:id": 23596354, "woe:parent_id": 2359957, "woe:name": "Batesville Intermediate School", "woe:placetype": 20, "woe:placetype_name": "POI", "woe:lang": "ENG", "iso:country": "US", "meta:provider": ["geoplanet:7.3.1", "geoplanet:7.3.2", "geoplanet:7.4.0", "geoplanet:7.4.1", "geoplanet:7.5.1", "geoplanet:7.5.2", "geoplanet:7.6.0", "geoplanet:7.8.1", "geoplanet:7.9.0", "geoplanet:7.10.0", "geoplanet:8.0.0", "woeplanet:8.0.0"], "meta:indexed": "2020-08-20T20:18:43.481259", "meta:updated": "2020-08-22T02:57:40.455401", "woe:hierarchy": {"continent": 24865672, "country": 23424977, "town": 0, "planet": 1, "county": 12588937, "suburb": 0, "state": 2347583, "region": 0, "localadmin": 0}, "woe:timezone_id": 56043661, "woe:hash": "dn051pfyb504", "woe:centroid": [-89.952278, 34.321091], "geom:latitude": 34.321091, "geom:longitude": -89.952278, "geom:hash": "dn051pfyb504", "woe:latitude": 34.321091, "geom:centroid": [-89.952278, 34.321091], "woe:longitude": -89.952278, "woe:repo": "woeplanet-poi-us"}, "geometry": {"coordinates": [-89.952278, 34.321091], "type": "Point"}}