{"type": "Feature", "id": 23579423, "properties": {"woe:id": 23579423, "woe:parent_id": 2354877, "woe:name": "Tyler Heights Elementary School", "woe:placetype": 20, "woe:placetype_name": "POI", "woe:lang": "ENG", "iso:country": "US", "meta:provider": ["geoplanet:7.3.2", "geoplanet:7.4.0", "geoplanet:7.4.1", "geoplanet:7.5.1", "geoplanet:7.5.2", "geoplanet:7.6.0", "geoplanet:7.8.1", "geoplanet:7.9.0", "geoplanet:7.10.0", "geoplanet:8.0.0", "woeplanet:8.0.0"], "meta:indexed": "2020-08-20T22:02:22.462065", "woe:alias_ENG_V": ["Tyler Heights Elementary"], "meta:updated": "2020-08-22T02:57:37.671442", "woe:hierarchy": {"continent": 24865672, "country": 23424977, "town": 0, "planet": 1, "county": 12588677, "suburb": 0, "state": 2347579, "region": 0, "localadmin": 0}, "woe:timezone_id": 56043648, "woe:hash": "dqcte5w3pwkt", "woe:centroid": [-76.499878, 38.954979], "geom:latitude": 38.954979, "geom:longitude": -76.499878, "geom:hash": "dqcte5w3pwkt", "woe:latitude": 38.954979, "geom:centroid": [-76.499878, 38.954979], "woe:longitude": -76.499878, "woe:repo": "woeplanet-poi-us"}, "geometry": {"coordinates": [-76.499878, 38.954979], "type": "Point"}}