{"type": "Feature", "id": 23636424, "properties": {"woe:id": 23636424, "woe:parent_id": 55858845, "woe:name": "Meadow View Elementary School", "woe:placetype": 20, "woe:placetype_name": "POI", "woe:lang": "ENG", "iso:country": "US", "meta:provider": ["geoplanet:7.3.1", "geoplanet:7.3.2", "geoplanet:7.4.0", "geoplanet:7.4.1", "geoplanet:7.5.1", "geoplanet:7.5.2", "geoplanet:7.6.0", "geoplanet:7.8.1", "geoplanet:7.9.0", "geoplanet:7.10.0", "geoplanet:8.0.0", "woeplanet:8.0.0"], "meta:indexed": "2020-08-20T20:18:56.995365", "woe:alias_ENG_V": ["Meadow View School", "Meadow View Elementary"], "meta:updated": "2020-08-22T02:57:46.102310", "woe:hierarchy": {"continent": 24865672, "country": 23424977, "town": 0, "planet": 1, "county": 12589711, "suburb": 0, "state": 2347596, "region": 0, "localadmin": 0}, "woe:timezone_id": 56043663, "woe:hash": "9rb6u3n1ct4y", "woe:centroid": [-123.203362, 44.08297], "geom:latitude": 44.08297, "geom:longitude": -123.203362, "geom:hash": "9rb6u3n1ct4y", "woe:latitude": 44.08297, "geom:centroid": [-123.203362, 44.08297], "woe:longitude": -123.203362, "woe:repo": "woeplanet-poi-us"}, "geometry": {"coordinates": [-123.203362, 44.08297], "type": "Point"}}