{"type": "Feature", "id": 23685388, "geometry": {"type": "Point", "coordinates": [-121.997482, 37.52615]}, "properties": {"woe:id": 23685388, "woe:parent_id": 2459268, "woe:name": "New Park Mall", "woe:placetype": 20, "woe:placetype_name": "POI", "woe:lang": "ENG", "iso:country": "US", "meta:provider": ["geoplanet:7.3.1", "geoplanet:7.3.2", "geoplanet:7.4.0", "geoplanet:7.4.1", "geoplanet:7.5.1", "geoplanet:7.5.2", "geoplanet:7.6.0", "geoplanet:7.8.1", "geoplanet:7.9.0", "geoplanet:7.10.0", "geoplanet:8.0.0", "woeplanet:8.0.0"], "meta:indexed": "2020-08-20T20:19:13.662451", "meta:updated": "2020-10-14T11:19:50.492297", "woe:alias_ENG_V": ["Newpark Mall"], "woe:hierarchy": {"continent": 24865672, "country": 23424977, "town": 0, "planet": 1, "county": 12587670, "suburb": 0, "state": 2347563, "region": 0, "localadmin": 0}, "woe:timezone_id": 56043663, "woe:hash": "9q9jrzkjstkh", "woe:centroid": [-121.997482, 37.52615], "geom:latitude": 37.52615, "geom:longitude": -121.997482, "geom:hash": "9q9jrzkjstkh", "woe:latitude": 37.52615, "geom:centroid": [-121.997482, 37.52615], "woe:longitude": -121.997482, "woe:repo": "woeplanet-poi-us", "geom:area": 0.0, "woe:scale": 19}}