{"type": "Feature", "id": 23637908, "properties": {"woe:id": 23637908, "woe:parent_id": 2487061, "woe:name": "Valley Catholic School", "woe:placetype": 20, "woe:placetype_name": "POI", "woe:lang": "ENG", "iso:country": "US", "meta:provider": ["geoplanet:7.3.1", "geoplanet:7.3.2", "geoplanet:7.4.0", "geoplanet:7.4.1", "geoplanet:7.5.1", "geoplanet:7.5.2", "geoplanet:7.6.0", "geoplanet:7.8.1", "geoplanet:7.9.0", "geoplanet:7.10.0", "geoplanet:8.0.0", "woeplanet:8.0.0"], "meta:indexed": "2020-08-20T20:18:57.547965", "meta:updated": "2020-08-22T02:57:46.304082", "woe:hierarchy": {"continent": 24865672, "country": 23424977, "town": 0, "planet": 1, "county": 12589725, "suburb": 0, "state": 2347596, "region": 0, "localadmin": 0}, "woe:timezone_id": 56043663, "woe:hash": "c20ducnbhkbm", "woe:centroid": [-122.828682, 45.488918], "geom:latitude": 45.488918, "geom:longitude": -122.828682, "geom:hash": "c20ducnbhkbm", "woe:latitude": 45.488918, "geom:centroid": [-122.828682, 45.488918], "woe:longitude": -122.828682, "woe:repo": "woeplanet-poi-us"}, "geometry": {"coordinates": [-122.828682, 45.488918], "type": "Point"}}