{"type": "Feature", "id": 23657318, "geometry": {"type": "Point", "coordinates": [-98.480301, 29.36319]}, "properties": {"woe:id": 23657318, "woe:parent_id": 29230231, "woe:name": "Mission San Jose Y San Miguel De Aguayo", "woe:placetype": 20, "woe:placetype_name": "POI", "woe:lang": "ENG", "iso:country": "US", "meta:provider": ["geoplanet:7.3.1", "geoplanet:7.3.2", "geoplanet:7.4.0", "geoplanet:7.4.1", "geoplanet:7.5.1", "geoplanet:7.5.2", "geoplanet:7.6.0", "geoplanet:7.8.1", "geoplanet:7.9.0", "geoplanet:7.10.0", "geoplanet:8.0.0", "woeplanet:8.0.0"], "meta:indexed": "2020-08-20T20:19:04.799537", "meta:updated": "2020-10-14T11:19:26.927856", "woe:hierarchy": {"continent": 24865672, "country": 23424977, "town": 0, "planet": 1, "county": 12590021, "suburb": 0, "state": 2347602, "region": 0, "localadmin": 0}, "woe:timezone_id": 56043661, "woe:hash": "9v1zp12ufxm7", "woe:centroid": [-98.480301, 29.36319], "geom:latitude": 29.36319, "geom:longitude": -98.480301, "geom:hash": "9v1zp12ufxm7", "woe:latitude": 29.36319, "geom:centroid": [-98.480301, 29.36319], "woe:longitude": -98.480301, "woe:repo": "woeplanet-poi-us", "geom:area": 0.0, "woe:scale": 19}}