{"type": "Feature", "id": 23649252, "properties": {"woe:id": 23649252, "woe:parent_id": 2441553, "woe:name": "La Follette East Elementary School", "woe:placetype": 20, "woe:placetype_name": "POI", "woe:lang": "ENG", "iso:country": "US", "meta:provider": ["geoplanet:7.4.0", "geoplanet:7.4.1", "geoplanet:7.5.1", "geoplanet:7.5.2", "geoplanet:7.6.0", "geoplanet:7.8.1", "geoplanet:7.9.0", "geoplanet:7.10.0", "geoplanet:8.0.0", "woeplanet:8.0.0"], "meta:indexed": "2020-08-20T23:56:01.286279", "meta:updated": "2020-08-22T02:58:23.594843", "woe:hierarchy": {"continent": 24865672, "country": 23424977, "town": 0, "planet": 1, "county": 12589918, "suburb": 0, "state": 2347601, "region": 0, "localadmin": 0}, "woe:timezone_id": 56043648, "woe:hash": "dnknypb0gn3p", "woe:centroid": [-84.111198, 36.385509], "geom:latitude": 36.385509, "geom:longitude": -84.111198, "geom:hash": "dnknypb0gn3p", "woe:latitude": 36.385509, "geom:centroid": [-84.111198, 36.385509], "woe:longitude": -84.111198, "woe:repo": "woeplanet-poi-us"}, "geometry": {"coordinates": [-84.111198, 36.385509], "type": "Point"}}