{"type": "Feature", "id": 23519848, "geometry": {"type": "Point", "coordinates": [-122.235924, 37.786758]}, "properties": {"woe:id": 23519848, "woe:parent_id": 55806278, "woe:name": "Garfield Year-round Elementary School", "woe:placetype": 20, "woe:placetype_name": "POI", "woe:lang": "ENG", "iso:country": "US", "meta:provider": ["geoplanet:7.3.1", "geoplanet:7.3.2", "geoplanet:7.4.0", "geoplanet:7.4.1", "geoplanet:7.5.1", "geoplanet:7.5.2", "geoplanet:7.6.0", "geoplanet:7.8.1", "geoplanet:7.9.0", "geoplanet:7.10.0", "geoplanet:8.0.0", "woeplanet:8.0.0"], "meta:indexed": "2020-08-20T20:18:19.560711", "woe:alias_ENG_V": ["Garfield Elementary School", "Garfield Year-round Elementary"], "meta:updated": "2020-10-14T11:20:26.370585", "woe:hierarchy": {"continent": 24865672, "country": 23424977, "town": 0, "planet": 1, "county": 12587670, "suburb": 0, "state": 2347563, "region": 0, "localadmin": 0}, "woe:timezone_id": 56043663, "woe:hash": "9q9nfqyebd0z", "woe:centroid": [-122.235924, 37.786758], "geom:latitude": 37.786758, "geom:longitude": -122.235924, "geom:hash": "9q9nfqyebd0z", "woe:latitude": 37.786758, "geom:centroid": [-122.235924, 37.786758], "woe:longitude": -122.235924, "woe:repo": "woeplanet-poi-us", "geom:area": 0.0, "woe:scale": 19}}