{"type": "Feature", "id": 23674771, "geometry": {"type": "Point", "coordinates": [-87.951378, 43.078979]}, "properties": {"woe:id": 23674771, "woe:parent_id": 29230102, "woe:name": "Career Youth Dvlp School of Ex", "woe:placetype": 20, "woe:placetype_name": "POI", "woe:lang": "ENG", "iso:country": "US", "meta:provider": ["geoplanet:7.3.1", "geoplanet:7.3.2", "geoplanet:7.4.0", "geoplanet:7.4.1", "geoplanet:7.5.1", "geoplanet:7.5.2", "geoplanet:7.6.0", "geoplanet:7.8.1", "geoplanet:7.9.0", "geoplanet:7.10.0", "geoplanet:8.0.0", "woeplanet:8.0.0"], "meta:indexed": "2020-08-20T20:19:11.160386", "meta:updated": "2020-10-14T11:19:46.878279", "woe:hierarchy": {"continent": 24865672, "country": 23424977, "town": 0, "planet": 1, "county": 12590574, "suburb": 0, "state": 2347608, "region": 0, "localadmin": 0}, "woe:timezone_id": 56043661, "woe:hash": "dp9mnd7c0rer", "woe:centroid": [-87.951378, 43.078979], "geom:latitude": 43.078979, "geom:longitude": -87.951378, "geom:hash": "dp9mnd7c0rer", "woe:latitude": 43.078979, "geom:centroid": [-87.951378, 43.078979], "woe:longitude": -87.951378, "woe:repo": "woeplanet-poi-us", "geom:area": 0.0, "woe:scale": 19}}