{"type": "Feature", "id": 23656366, "properties": {"woe:id": 23656366, "woe:parent_id": 56022725, "woe:name": "Shackelford Junior High School", "woe:placetype": 20, "woe:placetype_name": "POI", "woe:lang": "ENG", "iso:country": "US", "meta:provider": ["geoplanet:7.3.1", "geoplanet:7.3.2", "geoplanet:7.4.0", "geoplanet:7.4.1", "geoplanet:7.5.1", "geoplanet:7.5.2", "geoplanet:7.6.0", "geoplanet:7.8.1", "geoplanet:7.9.0", "geoplanet:7.10.0", "geoplanet:8.0.0", "woeplanet:8.0.0"], "meta:indexed": "2020-08-20T20:19:04.298627", "woe:alias_ENG_V": ["Shackelford Junior High"], "meta:updated": "2020-08-22T02:57:49.522081", "woe:hierarchy": {"continent": 24865672, "country": 23424977, "town": 0, "planet": 1, "county": 12590226, "suburb": 0, "state": 2347602, "region": 0, "localadmin": 0}, "woe:timezone_id": 56043661, "woe:hash": "9vffmtnb6wjr", "woe:centroid": [-97.131729, 32.7668], "geom:latitude": 32.7668, "geom:longitude": -97.131729, "geom:hash": "9vffmtnb6wjr", "woe:latitude": 32.7668, "geom:centroid": [-97.131729, 32.7668], "woe:longitude": -97.131729, "woe:repo": "woeplanet-poi-us"}, "geometry": {"coordinates": [-97.131729, 32.7668], "type": "Point"}}