{"type": "Feature", "id": 23583290, "geometry": {"type": "Point", "coordinates": [-72.53476, 42.533428]}, "properties": {"woe:id": 23583290, "woe:parent_id": 2453105, "woe:name": "Montague Center", "woe:placetype": 20, "woe:placetype_name": "POI", "woe:lang": "ENG", "iso:country": "US", "meta:provider": ["geoplanet:7.3.2", "geoplanet:7.4.0", "geoplanet:7.4.1", "geoplanet:7.5.1", "geoplanet:7.5.2", "geoplanet:7.6.0", "geoplanet:7.8.1", "geoplanet:7.9.0", "geoplanet:7.10.0", "geoplanet:8.0.0", "woeplanet:8.0.0"], "meta:indexed": "2020-08-20T22:02:23.985408", "meta:updated": "2020-10-14T11:20:04.085599", "woe:alias_ENG_V": ["Montague Center Elementary School"], "woe:hierarchy": {"continent": 24865672, "country": 23424977, "town": 0, "planet": 1, "county": 12588705, "suburb": 0, "state": 2347580, "region": 0, "localadmin": 0}, "woe:timezone_id": 56043648, "woe:hash": "drs3vqvz1tdu", "woe:centroid": [-72.53476, 42.533428], "geom:latitude": 42.533428, "geom:longitude": -72.53476, "geom:hash": "drs3vqvz1tdu", "woe:latitude": 42.533428, "geom:centroid": [-72.53476, 42.533428], "woe:longitude": -72.53476, "woe:repo": "woeplanet-poi-us", "geom:area": 0.0, "woe:scale": 19}}