{"type": "Feature", "id": 23537051, "geometry": {"type": "Point", "coordinates": [-117.293907, 33.25806]}, "properties": {"woe:id": 23537051, "woe:parent_id": 55860672, "woe:name": "Del Rio Elementary School", "woe:placetype": 20, "woe:placetype_name": "POI", "woe:lang": "ENG", "iso:country": "US", "meta:provider": ["geoplanet:7.3.2", "geoplanet:7.4.0", "geoplanet:7.4.1", "geoplanet:7.5.1", "geoplanet:7.5.2", "geoplanet:7.6.0", "geoplanet:7.8.1", "geoplanet:7.9.0", "geoplanet:7.10.0", "geoplanet:8.0.0", "woeplanet:8.0.0"], "meta:indexed": "2020-08-20T22:02:04.821758", "woe:alias_ENG_V": ["Del Rio Elementary"], "meta:updated": "2020-10-14T11:20:21.074758", "woe:hierarchy": {"continent": 24865672, "country": 23424977, "town": 0, "planet": 1, "county": 12587706, "suburb": 0, "state": 2347563, "region": 0, "localadmin": 0}, "woe:timezone_id": 56043663, "woe:hash": "9mut4ymnjzez", "woe:centroid": [-117.293907, 33.25806], "geom:latitude": 33.25806, "geom:longitude": -117.293907, "geom:hash": "9mut4ymnjzez", "woe:latitude": 33.25806, "geom:centroid": [-117.293907, 33.25806], "woe:longitude": -117.293907, "woe:repo": "woeplanet-poi-us", "geom:area": 0.0, "woe:scale": 19}}