{"type": "Feature", "id": 23632694, "geometry": {"type": "Point", "coordinates": [-80.581337, 41.152351]}, "properties": {"woe:id": 23632694, "woe:parent_id": 2425164, "woe:name": "Hubbard High School", "woe:placetype": 20, "woe:placetype_name": "POI", "woe:lang": "ENG", "iso:country": "US", "meta:provider": ["geoplanet:7.3.1", "geoplanet:7.3.2", "geoplanet:7.4.0", "geoplanet:7.4.1", "geoplanet:7.5.1", "geoplanet:7.5.2", "geoplanet:7.6.0", "geoplanet:7.8.1", "geoplanet:7.9.0", "geoplanet:7.10.0", "geoplanet:8.0.0", "woeplanet:8.0.0"], "meta:indexed": "2020-08-20T20:18:55.718459", "woe:alias_ENG_V": ["Hubbard Senior High School", "Hubbard High", "Hubbard Senior High", "Hubbard HS", "Hubbard Senior HS"], "meta:updated": "2020-10-14T11:19:34.826935", "woe:hierarchy": {"continent": 24865672, "country": 23424977, "town": 0, "planet": 1, "county": 12589604, "suburb": 0, "state": 2347594, "region": 0, "localadmin": 0}, "woe:timezone_id": 56043648, "woe:hash": "dpqdn7d3yf0p", "woe:centroid": [-80.581337, 41.152351], "geom:latitude": 41.152351, "geom:longitude": -80.581337, "geom:hash": "dpqdn7d3yf0p", "woe:latitude": 41.152351, "geom:centroid": [-80.581337, 41.152351], "woe:longitude": -80.581337, "woe:repo": "woeplanet-poi-us", "geom:area": 0.0, "woe:scale": 19}}