{"type": "Feature", "id": 23566061, "geometry": {"type": "Point", "coordinates": [-85.642128, 40.52998]}, "properties": {"woe:id": 23566061, "woe:parent_id": 2445763, "woe:name": "Southeast Elementary School", "woe:placetype": 20, "woe:placetype_name": "POI", "woe:lang": "ENG", "iso:country": "US", "meta:provider": ["geoplanet:7.3.1", "geoplanet:7.3.2", "geoplanet:7.4.0", "geoplanet:7.4.1", "geoplanet:7.5.1", "geoplanet:7.5.2", "geoplanet:7.6.0", "geoplanet:7.8.1", "geoplanet:7.9.0", "geoplanet:7.10.0", "geoplanet:8.0.0", "woeplanet:8.0.0"], "meta:indexed": "2020-08-20T20:18:33.858307", "woe:alias_ENG_V": ["SE Elementary School", "SE Elementary", "Southeast Elementary"], "meta:updated": "2020-10-14T11:20:17.939348", "woe:hierarchy": {"continent": 24865672, "country": 23424977, "town": 0, "planet": 1, "county": 12588206, "suburb": 0, "state": 2347573, "region": 0, "localadmin": 0}, "woe:timezone_id": 56043656, "woe:hash": "dp5ne4m21zbu", "woe:centroid": [-85.642128, 40.52998], "geom:latitude": 40.52998, "geom:longitude": -85.642128, "geom:hash": "dp5ne4m21zbu", "woe:latitude": 40.52998, "geom:centroid": [-85.642128, 40.52998], "woe:longitude": -85.642128, "woe:repo": "woeplanet-poi-us", "geom:area": 0.0, "woe:scale": 19}}