{"type": "Feature", "id": 23513819, "properties": {"woe:id": 23513819, "woe:parent_id": 2522047, "woe:name": "Winfield High School", "woe:placetype": 20, "woe:placetype_name": "POI", "woe:lang": "ENG", "iso:country": "US", "meta:provider": ["geoplanet:7.3.1", "geoplanet:7.3.2", "geoplanet:7.4.0", "geoplanet:7.4.1", "geoplanet:7.5.1", "geoplanet:7.5.2", "geoplanet:7.6.0", "geoplanet:7.8.1", "geoplanet:7.9.0", "geoplanet:7.10.0", "geoplanet:8.0.0", "woeplanet:8.0.0"], "meta:indexed": "2020-08-20T20:18:17.518116", "woe:alias_ENG_V": ["Winfield Senior High School", "Winfield High", "Winfield Senior High", "Winfield HS", "Winfield Senior HS"], "meta:updated": "2020-08-22T02:58:45.874687", "woe:hierarchy": {"continent": 24865672, "country": 23424977, "town": 0, "planet": 1, "county": 12587533, "suburb": 0, "state": 2347559, "region": 0, "localadmin": 0}, "woe:timezone_id": 56043661, "woe:hash": "dn191c1nhhfy", "woe:centroid": [-87.812172, 33.932331], "geom:latitude": 33.932331, "geom:longitude": -87.812172, "geom:hash": "dn191c1nhhfy", "woe:latitude": 33.932331, "geom:centroid": [-87.812172, 33.932331], "woe:longitude": -87.812172, "woe:repo": "woeplanet-poi-us"}, "geometry": {"coordinates": [-87.812172, 33.932331], "type": "Point"}}