{"type": "Feature", "id": 23568832, "geometry": {"type": "Point", "coordinates": [-92.344231, 42.465359]}, "properties": {"woe:id": 23568832, "woe:parent_id": 2515157, "woe:name": "Columbus High School", "woe:placetype": 20, "woe:placetype_name": "POI", "woe:lang": "ENG", "iso:country": "US", "meta:provider": ["geoplanet:7.3.1", "geoplanet:7.3.2", "geoplanet:7.4.0", "geoplanet:7.4.1", "geoplanet:7.5.1", "geoplanet:7.5.2", "geoplanet:7.6.0", "geoplanet:7.8.1", "geoplanet:7.9.0", "geoplanet:7.10.0", "geoplanet:8.0.0", "woeplanet:8.0.0"], "meta:indexed": "2020-08-20T20:18:34.948560", "woe:alias_ENG_V": ["Columbus Senior High School", "Columbus High", "Columbus Senior High", "Columbus HS", "Columbus Senior HS"], "meta:updated": "2020-10-14T11:20:06.115965", "woe:hierarchy": {"continent": 24865672, "country": 23424977, "town": 0, "planet": 1, "county": 12588278, "suburb": 0, "state": 2347574, "region": 0, "localadmin": 0}, "woe:timezone_id": 56043661, "woe:hash": "9zw3ddsfxkwt", "woe:centroid": [-92.344231, 42.465359], "geom:latitude": 42.465359, "geom:longitude": -92.344231, "geom:hash": "9zw3ddsfxkwt", "woe:latitude": 42.465359, "geom:centroid": [-92.344231, 42.465359], "woe:longitude": -92.344231, "woe:repo": "woeplanet-poi-us", "geom:area": 0.0, "woe:scale": 19}}