{"type": "Feature", "id": 23568304, "geometry": {"type": "Point", "coordinates": [-86.830849, 40.5126]}, "properties": {"woe:id": 23568304, "woe:parent_id": 2360058, "woe:name": "Battle Ground Middle School", "woe:placetype": 20, "woe:placetype_name": "POI", "woe:lang": "ENG", "iso:country": "US", "meta:provider": ["geoplanet:7.3.2", "geoplanet:7.4.0", "geoplanet:7.4.1", "geoplanet:7.5.1", "geoplanet:7.5.2", "geoplanet:7.6.0", "geoplanet:7.8.1", "geoplanet:7.9.0", "geoplanet:7.10.0", "geoplanet:8.0.0", "woeplanet:8.0.0"], "meta:indexed": "2020-08-20T22:02:17.751638", "meta:updated": "2020-10-14T11:20:09.430401", "woe:hierarchy": {"continent": 24865672, "country": 23424977, "town": 0, "planet": 1, "county": 12588258, "suburb": 0, "state": 2347573, "region": 0, "localadmin": 0}, "woe:timezone_id": 56043656, "woe:hash": "dp4q2p5en842", "woe:centroid": [-86.830849, 40.5126], "geom:latitude": 40.5126, "geom:longitude": -86.830849, "geom:hash": "dp4q2p5en842", "woe:latitude": 40.5126, "geom:centroid": [-86.830849, 40.5126], "woe:longitude": -86.830849, "woe:repo": "woeplanet-poi-us", "geom:area": 0.0, "woe:scale": 19}}