{"type": "Feature", "id": 23549338, "properties": {"woe:id": 23549338, "woe:parent_id": 23512172, "woe:name": "Miami Marine Stadium", "woe:placetype": 20, "woe:placetype_name": "POI", "woe:lang": "ENG", "iso:country": "US", "meta:provider": ["geoplanet:7.4.0", "geoplanet:7.4.1", "geoplanet:7.5.1", "geoplanet:7.5.2", "geoplanet:7.6.0", "geoplanet:7.8.1", "geoplanet:7.9.0", "geoplanet:7.10.0", "geoplanet:8.0.0", "woeplanet:8.0.0"], "meta:indexed": "2020-08-20T23:54:53.069365", "meta:updated": "2020-08-22T02:57:32.336005", "woe:hierarchy": {"continent": 24865672, "country": 23424977, "town": 0, "planet": 1, "county": 12587815, "suburb": 0, "state": 2347568, "region": 0, "localadmin": 0}, "woe:timezone_id": 56043648, "woe:hash": "dhwfrtyud4kt", "woe:centroid": [-80.168861, 25.740379], "geom:latitude": 25.740379, "geom:longitude": -80.168861, "geom:hash": "dhwfrtyud4kt", "woe:latitude": 25.740379, "geom:centroid": [-80.168861, 25.740379], "woe:longitude": -80.168861, "woe:repo": "woeplanet-poi-us"}, "geometry": {"coordinates": [-80.168861, 25.740379], "type": "Point"}}