{"type": "Feature", "id": 23603302, "geometry": {"type": "Point", "coordinates": [-97.614647, 40.536678]}, "properties": {"woe:id": 23603302, "woe:parent_id": 2409501, "woe:name": "Geneva North Elementary School", "woe:placetype": 20, "woe:placetype_name": "POI", "woe:lang": "ENG", "iso:country": "US", "meta:provider": ["geoplanet:7.3.1", "geoplanet:7.3.2", "geoplanet:7.4.0", "geoplanet:7.4.1", "geoplanet:7.5.1", "geoplanet:7.5.2", "geoplanet:7.6.0", "geoplanet:7.8.1", "geoplanet:7.9.0", "geoplanet:7.10.0", "geoplanet:8.0.0", "woeplanet:8.0.0"], "meta:indexed": "2020-08-20T20:18:45.699641", "woe:alias_ENG_V": ["Geneva North Elementary"], "meta:updated": "2020-10-14T11:19:36.630449", "woe:hierarchy": {"continent": 24865672, "country": 23424977, "town": 0, "planet": 1, "county": 12589167, "suburb": 0, "state": 2347586, "region": 0, "localadmin": 0}, "woe:timezone_id": 56043661, "woe:hash": "9z4wderpmb7x", "woe:centroid": [-97.614647, 40.536678], "geom:latitude": 40.536678, "geom:longitude": -97.614647, "geom:hash": "9z4wderpmb7x", "woe:latitude": 40.536678, "geom:centroid": [-97.614647, 40.536678], "woe:longitude": -97.614647, "woe:repo": "woeplanet-poi-us", "geom:area": 0.0, "woe:scale": 19}}