{"type": "Feature", "id": 23528791, "geometry": {"type": "Point", "coordinates": [-121.764717, 38.554001]}, "properties": {"woe:id": 23528791, "woe:parent_id": 55858645, "woe:name": "Robert E. Willett Elementary School", "woe:placetype": 20, "woe:placetype_name": "POI", "woe:lang": "ENG", "iso:country": "US", "meta:provider": ["geoplanet:7.3.1", "geoplanet:7.3.2", "geoplanet:7.4.0", "geoplanet:7.4.1", "geoplanet:7.5.1", "geoplanet:7.5.2", "geoplanet:7.6.0", "geoplanet:7.8.1", "geoplanet:7.9.0", "geoplanet:7.10.0", "geoplanet:8.0.0", "woeplanet:8.0.0"], "meta:indexed": "2020-08-20T20:18:21.303883", "woe:alias_ENG_V": ["Robert E Willett Elementary School", "Robert E. Willett Elementary"], "meta:updated": "2020-10-14T11:20:03.937267", "woe:hierarchy": {"continent": 24865672, "country": 23424977, "town": 0, "planet": 1, "county": 12587726, "suburb": 0, "state": 2347563, "region": 0, "localadmin": 0}, "woe:timezone_id": 56043663, "woe:hash": "9qc7m4t9k6wq", "woe:centroid": [-121.764717, 38.554001], "geom:latitude": 38.554001, "geom:longitude": -121.764717, "geom:hash": "9qc7m4t9k6wq", "woe:latitude": 38.554001, "geom:centroid": [-121.764717, 38.554001], "woe:longitude": -121.764717, "woe:repo": "woeplanet-poi-us", "geom:area": 0.0, "woe:scale": 19}}