{"type": "Feature", "id": 23546483, "geometry": {"type": "Point", "coordinates": [-84.581207, 30.578529]}, "properties": {"woe:id": 23546483, "woe:parent_id": 55981058, "woe:name": "Carter-parramore Middle School", "woe:placetype": 20, "woe:placetype_name": "POI", "woe:lang": "ENG", "iso:country": "US", "meta:provider": ["geoplanet:7.3.1", "geoplanet:7.3.2", "geoplanet:7.4.0", "geoplanet:7.4.1", "geoplanet:7.5.1", "geoplanet:7.5.2", "geoplanet:7.6.0", "geoplanet:7.8.1", "geoplanet:7.9.0", "geoplanet:7.10.0", "geoplanet:8.0.0", "woeplanet:8.0.0"], "meta:indexed": "2020-08-20T20:18:26.468343", "meta:updated": "2020-10-14T11:20:04.977360", "woe:alias_ENG_V": ["Carter-Parramore Academy"], "woe:hierarchy": {"continent": 24865672, "country": 23424977, "town": 0, "planet": 1, "county": 12587822, "suburb": 0, "state": 2347568, "region": 0, "localadmin": 0}, "woe:timezone_id": 56043648, "woe:hash": "dj7vgq9ug4by", "woe:centroid": [-84.581207, 30.578529], "geom:latitude": 30.578529, "geom:longitude": -84.581207, "geom:hash": "dj7vgq9ug4by", "woe:latitude": 30.578529, "geom:centroid": [-84.581207, 30.578529], "woe:longitude": -84.581207, "woe:repo": "woeplanet-poi-us", "geom:area": 0.0, "woe:scale": 19}}