{"type": "Feature", "id": 23680881, "geometry": {"type": "Point", "coordinates": [-82.049248, 28.74258]}, "properties": {"woe:id": 23680881, "woe:parent_id": 2501865, "woe:name": "Sumterville Station", "woe:placetype": 20, "woe:placetype_name": "POI", "woe:lang": "ENG", "iso:country": "US", "meta:provider": ["geoplanet:7.3.1", "geoplanet:7.3.2", "geoplanet:7.4.0", "geoplanet:7.4.1", "geoplanet:7.5.1", "geoplanet:7.5.2", "geoplanet:7.6.0", "geoplanet:7.8.1", "geoplanet:7.9.0", "geoplanet:7.10.0", "geoplanet:8.0.0", "woeplanet:8.0.0"], "meta:indexed": "2020-08-20T20:19:18.726993", "meta:updated": "2020-10-14T11:19:51.876338", "woe:hierarchy": {"continent": 24865672, "country": 23424977, "town": 0, "planet": 1, "county": 12587862, "suburb": 0, "state": 2347568, "region": 0, "localadmin": 0}, "woe:timezone_id": 56043648, "woe:hash": "djjesbmt9vq2", "woe:centroid": [-82.049248, 28.74258], "geom:latitude": 28.74258, "geom:longitude": -82.049248, "geom:hash": "djjesbmt9vq2", "woe:latitude": 28.74258, "geom:centroid": [-82.049248, 28.74258], "woe:longitude": -82.049248, "woe:repo": "woeplanet-poi-us", "geom:area": 0.0, "woe:scale": 19}}