{"type": "Feature", "id": 23629065, "geometry": {"type": "Point", "coordinates": [-82.878372, 39.96455]}, "properties": {"woe:id": 23629065, "woe:parent_id": 2519655, "woe:name": "Etna Road Elementary School", "woe:placetype": 20, "woe:placetype_name": "POI", "woe:lang": "ENG", "iso:country": "US", "meta:provider": ["geoplanet:7.3.1", "geoplanet:7.3.2", "geoplanet:7.4.0", "geoplanet:7.4.1", "geoplanet:7.5.1", "geoplanet:7.5.2", "geoplanet:7.6.0", "geoplanet:7.8.1", "geoplanet:7.9.0", "geoplanet:7.10.0", "geoplanet:8.0.0", "woeplanet:8.0.0"], "meta:indexed": "2020-08-20T20:18:54.064007", "woe:alias_ENG_V": ["Etna Road Elementary"], "meta:updated": "2020-10-14T11:19:38.955168", "woe:hierarchy": {"continent": 24865672, "country": 23424977, "town": 0, "planet": 1, "county": 12589551, "suburb": 0, "state": 2347594, "region": 0, "localadmin": 0}, "woe:timezone_id": 56043648, "woe:hash": "dpj5653f3und", "woe:centroid": [-82.878372, 39.96455], "geom:latitude": 39.96455, "geom:longitude": -82.878372, "geom:hash": "dpj5653f3und", "woe:latitude": 39.96455, "geom:centroid": [-82.878372, 39.96455], "woe:longitude": -82.878372, "woe:repo": "woeplanet-poi-us", "geom:area": 0.0, "woe:scale": 19}}