{"type": "Feature", "id": 23579500, "properties": {"woe:id": 23579500, "woe:parent_id": 2354877, "woe:name": "Calvary Center", "woe:placetype": 20, "woe:placetype_name": "POI", "woe:lang": "ENG", "iso:country": "US", "meta:provider": ["geoplanet:7.3.1", "geoplanet:7.3.2", "geoplanet:7.4.0", "geoplanet:7.4.1", "geoplanet:7.5.1", "geoplanet:7.5.2", "geoplanet:7.6.0", "geoplanet:7.8.1", "geoplanet:7.9.0", "geoplanet:7.10.0", "geoplanet:8.0.0", "woeplanet:8.0.0"], "meta:indexed": "2020-08-20T20:18:38.382880", "meta:updated": "2020-08-22T02:57:37.688128", "woe:hierarchy": {"continent": 24865672, "country": 23424977, "town": 0, "planet": 1, "county": 12588677, "suburb": 0, "state": 2347579, "region": 0, "localadmin": 0}, "woe:timezone_id": 56043648, "woe:hash": "dqctg1k7d3f0", "woe:centroid": [-76.502853, 38.986969], "geom:latitude": 38.986969, "geom:longitude": -76.502853, "geom:hash": "dqctg1k7d3f0", "woe:latitude": 38.986969, "geom:centroid": [-76.502853, 38.986969], "woe:longitude": -76.502853, "woe:repo": "woeplanet-poi-us"}, "geometry": {"coordinates": [-76.502853, 38.986969], "type": "Point"}}