{"type": "Feature", "id": 23548523, "geometry": {"type": "Point", "coordinates": [-81.80265, 26.262329]}, "properties": {"woe:id": 23548523, "woe:parent_id": 55979831, "woe:name": "Grace Community School", "woe:placetype": 20, "woe:placetype_name": "POI", "woe:lang": "ENG", "iso:country": "US", "meta:provider": ["geoplanet:7.3.1", "geoplanet:7.3.2", "geoplanet:7.4.0", "geoplanet:7.4.1", "geoplanet:7.5.1", "geoplanet:7.5.2", "geoplanet:7.6.0", "geoplanet:7.8.1", "geoplanet:7.9.0", "geoplanet:7.10.0", "geoplanet:8.0.0", "woeplanet:8.0.0"], "meta:indexed": "2020-08-20T20:18:27.406995", "meta:updated": "2020-10-14T11:20:05.863076", "woe:hierarchy": {"continent": 24865672, "country": 23424977, "town": 0, "planet": 1, "county": 12587813, "suburb": 0, "state": 2347568, "region": 0, "localadmin": 0}, "woe:timezone_id": 56043648, "woe:hash": "dhtv6scjhhgn", "woe:centroid": [-81.80265, 26.262329], "geom:latitude": 26.262329, "geom:longitude": -81.80265, "geom:hash": "dhtv6scjhhgn", "woe:latitude": 26.262329, "geom:centroid": [-81.80265, 26.262329], "woe:longitude": -81.80265, "woe:repo": "woeplanet-poi-us", "geom:area": 0.0, "woe:scale": 19}}