{"type": "Feature", "id": 23624464, "properties": {"woe:id": 23624464, "woe:parent_id": 2484164, "woe:name": "Archer Elementary School", "woe:placetype": 20, "woe:placetype_name": "POI", "woe:lang": "ENG", "iso:country": "US", "meta:provider": ["geoplanet:7.3.2", "geoplanet:7.4.0", "geoplanet:7.4.1", "geoplanet:7.5.1", "geoplanet:7.5.2", "geoplanet:7.6.0", "geoplanet:7.8.1", "geoplanet:7.9.0", "geoplanet:7.10.0", "geoplanet:8.0.0", "woeplanet:8.0.0"], "meta:indexed": "2020-08-20T22:02:40.254695", "woe:alias_ENG_V": ["Archer Elementary"], "meta:updated": "2020-08-22T02:57:44.343593", "woe:hierarchy": {"continent": 24865672, "country": 23424977, "town": 0, "planet": 1, "county": 12589414, "suburb": 0, "state": 2347592, "region": 0, "localadmin": 0}, "woe:timezone_id": 56043648, "woe:hash": "dnrhzrmvben6", "woe:centroid": [-79.82972, 36.03204], "geom:latitude": 36.03204, "geom:longitude": -79.82972, "geom:hash": "dnrhzrmvben6", "woe:latitude": 36.03204, "geom:centroid": [-79.82972, 36.03204], "woe:longitude": -79.82972, "woe:repo": "woeplanet-poi-us"}, "geometry": {"coordinates": [-79.82972, 36.03204], "type": "Point"}}