{"type": "Feature", "id": 23536902, "properties": {"woe:id": 23536902, "woe:parent_id": 28337859, "woe:name": "Joseph Casillas Elementary School", "woe:placetype": 20, "woe:placetype_name": "POI", "woe:lang": "ENG", "iso:country": "US", "meta:provider": ["geoplanet:7.3.1", "geoplanet:7.3.2", "geoplanet:7.4.0", "geoplanet:7.4.1", "geoplanet:7.5.1", "geoplanet:7.5.2", "geoplanet:7.6.0", "geoplanet:7.8.1", "geoplanet:7.9.0", "geoplanet:7.10.0", "geoplanet:8.0.0", "woeplanet:8.0.0"], "meta:indexed": "2020-08-20T20:18:23.395214", "woe:alias_ENG_V": ["Joseph Casillas Elementary"], "meta:updated": "2020-08-22T02:57:29.913147", "woe:hierarchy": {"continent": 24865672, "country": 23424977, "town": 0, "planet": 1, "county": 12587706, "suburb": 0, "state": 2347563, "region": 0, "localadmin": 0}, "woe:timezone_id": 56043663, "woe:hash": "9muc9k55xqc6", "woe:centroid": [-117.010948, 32.630032], "geom:latitude": 32.630032, "geom:longitude": -117.010948, "geom:hash": "9muc9k55xqc6", "woe:latitude": 32.630032, "geom:centroid": [-117.010948, 32.630032], "woe:longitude": -117.010948, "woe:repo": "woeplanet-poi-us"}, "geometry": {"coordinates": [-117.010948, 32.630032], "type": "Point"}}