{"type": "Feature", "id": 23551592, "geometry": {"type": "Point", "coordinates": [-83.387238, 33.951729]}, "properties": {"woe:id": 23551592, "woe:parent_id": 2356940, "woe:name": "Clarke Central High School", "woe:placetype": 20, "woe:placetype_name": "POI", "woe:lang": "ENG", "iso:country": "US", "meta:provider": ["geoplanet:7.3.1", "geoplanet:7.3.2", "geoplanet:7.4.0", "geoplanet:7.4.1", "geoplanet:7.5.1", "geoplanet:7.5.2", "geoplanet:7.6.0", "geoplanet:7.8.1", "geoplanet:7.9.0", "geoplanet:7.10.0", "geoplanet:8.0.0", "woeplanet:8.0.0"], "meta:indexed": "2020-08-20T20:18:28.939935", "woe:alias_ENG_V": ["Clarke Central Senior High School", "Clarke Central High", "Clarke Central Senior High", "Clarke Central HS", "Clarke Central Senior HS"], "meta:updated": "2020-10-14T11:20:16.782748", "woe:hierarchy": {"continent": 24865672, "country": 23424977, "town": 0, "planet": 1, "county": 12587898, "suburb": 0, "state": 2347569, "region": 0, "localadmin": 0}, "woe:timezone_id": 56043648, "woe:hash": "dnh9nkxr0t08", "woe:centroid": [-83.387238, 33.951729], "geom:latitude": 33.951729, "geom:longitude": -83.387238, "geom:hash": "dnh9nkxr0t08", "woe:latitude": 33.951729, "geom:centroid": [-83.387238, 33.951729], "woe:longitude": -83.387238, "woe:repo": "woeplanet-poi-us", "geom:area": 0.0, "woe:scale": 19}}