{"type": "Feature", "id": 23575813, "properties": {"woe:id": 23575813, "woe:parent_id": 2501471, "woe:name": "Jake Drost School for Exceptional Children", "woe:placetype": 20, "woe:placetype_name": "POI", "woe:lang": "ENG", "iso:country": "US", "meta:provider": ["geoplanet:7.3.1", "geoplanet:7.3.2", "geoplanet:7.4.0", "geoplanet:7.4.1", "geoplanet:7.5.1", "geoplanet:7.5.2", "geoplanet:7.6.0", "geoplanet:7.8.1", "geoplanet:7.9.0", "geoplanet:7.10.0", "geoplanet:8.0.0", "woeplanet:8.0.0"], "meta:indexed": "2020-08-20T20:18:37.313394", "meta:updated": "2020-08-22T02:57:37.149888", "woe:alias_ENG_V": ["Drost School for Exceptional Chldrn"], "woe:hierarchy": {"continent": 24865672, "country": 23424977, "town": 0, "planet": 1, "county": 12588605, "suburb": 0, "state": 2347577, "region": 0, "localadmin": 0}, "woe:timezone_id": 56043661, "woe:hash": "9vms546nur0b", "woe:centroid": [-93.380859, 30.247931], "geom:latitude": 30.247931, "geom:longitude": -93.380859, "geom:hash": "9vms546nur0b", "woe:latitude": 30.247931, "geom:centroid": [-93.380859, 30.247931], "woe:longitude": -93.380859, "woe:repo": "woeplanet-poi-us"}, "geometry": {"coordinates": [-93.380859, 30.247931], "type": "Point"}}