{"type": "Feature", "id": 23549931, "properties": {"woe:id": 23549931, "woe:parent_id": 23510747, "woe:name": "Wagner Montessori School", "woe:placetype": 20, "woe:placetype_name": "POI", "woe:lang": "ENG", "iso:country": "US", "meta:provider": ["geoplanet:7.3.1", "geoplanet:7.3.2", "geoplanet:7.4.0", "geoplanet:7.4.1", "geoplanet:7.5.1", "geoplanet:7.5.2", "geoplanet:7.6.0", "geoplanet:7.8.1", "geoplanet:7.9.0", "geoplanet:7.10.0", "geoplanet:8.0.0", "woeplanet:8.0.0"], "meta:indexed": "2020-08-20T20:18:28.157351", "meta:updated": "2020-08-22T02:57:32.488610", "woe:hierarchy": {"continent": 24865672, "country": 23424977, "town": 0, "planet": 1, "county": 12587815, "suburb": 0, "state": 2347568, "region": 0, "localadmin": 0}, "woe:timezone_id": 56043648, "woe:hash": "dhwfku9hxxs9", "woe:centroid": [-80.297371, 25.73354], "geom:latitude": 25.73354, "geom:longitude": -80.297371, "geom:hash": "dhwfku9hxxs9", "woe:latitude": 25.73354, "geom:centroid": [-80.297371, 25.73354], "woe:longitude": -80.297371, "woe:repo": "woeplanet-poi-us"}, "geometry": {"coordinates": [-80.297371, 25.73354], "type": "Point"}}