{"type": "Feature", "id": 23647121, "geometry": {"type": "Point", "coordinates": [-82.311829, 34.85899]}, "properties": {"woe:id": 23647121, "woe:parent_id": 2504375, "woe:name": "Pelham Road Elementary School", "woe:placetype": 20, "woe:placetype_name": "POI", "woe:lang": "ENG", "iso:country": "US", "meta:provider": ["geoplanet:7.4.0", "geoplanet:7.4.1", "geoplanet:7.5.1", "geoplanet:7.5.2", "geoplanet:7.6.0", "geoplanet:7.8.1", "geoplanet:7.9.0", "geoplanet:7.10.0", "geoplanet:8.0.0", "woeplanet:8.0.0"], "meta:indexed": "2020-08-20T23:56:01.190753", "meta:updated": "2020-10-14T11:19:33.753097", "woe:hierarchy": {"continent": 24865672, "country": 23424977, "town": 0, "planet": 1, "county": 12589822, "suburb": 0, "state": 2347599, "region": 0, "localadmin": 0}, "woe:timezone_id": 56043648, "woe:hash": "dnjqqcyk76ez", "woe:centroid": [-82.311829, 34.85899], "geom:latitude": 34.85899, "geom:longitude": -82.311829, "geom:hash": "dnjqqcyk76ez", "woe:latitude": 34.85899, "geom:centroid": [-82.311829, 34.85899], "woe:longitude": -82.311829, "woe:repo": "woeplanet-poi-us", "geom:area": 0.0, "woe:scale": 19}}