{"type": "Feature", "id": 23649649, "properties": {"woe:id": 23649649, "woe:parent_id": 29389123, "woe:name": "Hume Fogg Magnet High School", "woe:placetype": 20, "woe:placetype_name": "POI", "woe:lang": "ENG", "iso:country": "US", "meta:provider": ["geoplanet:7.3.1", "geoplanet:7.3.2", "geoplanet:7.4.0", "geoplanet:7.4.1", "geoplanet:7.5.1", "geoplanet:7.5.2", "geoplanet:7.6.0", "geoplanet:7.8.1", "geoplanet:7.9.0", "geoplanet:7.10.0", "geoplanet:8.0.0", "woeplanet:8.0.0"], "meta:indexed": "2020-08-20T20:19:01.585230", "woe:alias_ENG_V": ["Hume Fogg Magnet Senior High School", "Hume Fogg Magnet High", "Hume Fogg Magnet Senior High", "Hume Fogg Magnet HS", "Hume Fogg Magnet Senior HS"], "meta:updated": "2020-08-22T02:58:49.677665", "woe:hierarchy": {"continent": 24865672, "country": 23424977, "town": 0, "planet": 1, "county": 12589930, "suburb": 0, "state": 2347601, "region": 0, "localadmin": 0}, "woe:timezone_id": 56043661, "woe:hash": "dn6m9q858ysj", "woe:centroid": [-86.780968, 36.159389], "geom:latitude": 36.159389, "geom:longitude": -86.780968, "geom:hash": "dn6m9q858ysj", "woe:latitude": 36.159389, "geom:centroid": [-86.780968, 36.159389], "woe:longitude": -86.780968, "woe:repo": "woeplanet-poi-us"}, "geometry": {"coordinates": [-86.780968, 36.159389], "type": "Point"}}