{"type": "Feature", "id": 23542002, "properties": {"woe:id": 23542002, "woe:parent_id": 2478667, "woe:name": "Rangely Middle School", "woe:placetype": 20, "woe:placetype_name": "POI", "woe:lang": "ENG", "iso:country": "US", "meta:provider": ["geoplanet:7.3.1", "geoplanet:7.3.2", "geoplanet:7.4.0", "geoplanet:7.4.1", "geoplanet:7.5.1", "geoplanet:7.5.2", "geoplanet:7.6.0", "geoplanet:7.8.1", "geoplanet:7.9.0", "geoplanet:7.10.0", "geoplanet:8.0.0", "woeplanet:8.0.0"], "meta:indexed": "2020-08-20T20:18:24.835750", "meta:updated": "2020-08-22T02:57:30.905990", "woe:hierarchy": {"continent": 24865672, "country": 23424977, "town": 0, "planet": 1, "county": 12587779, "suburb": 0, "state": 2347564, "region": 0, "localadmin": 0}, "woe:timezone_id": 56043665, "woe:hash": "9x4s5bv2c2vd", "woe:centroid": [-108.812309, 40.082378], "geom:latitude": 40.082378, "geom:longitude": -108.812309, "geom:hash": "9x4s5bv2c2vd", "woe:latitude": 40.082378, "geom:centroid": [-108.812309, 40.082378], "woe:longitude": -108.812309, "woe:repo": "woeplanet-poi-us"}, "geometry": {"coordinates": [-108.812309, 40.082378], "type": "Point"}}