{"type": "Feature", "id": 23625683, "geometry": {"type": "Point", "coordinates": [-79.680313, 36.363049]}, "properties": {"woe:id": 23625683, "woe:parent_id": 2480004, "woe:name": "Moss Street Elementary School", "woe:placetype": 20, "woe:placetype_name": "POI", "woe:lang": "ENG", "iso:country": "US", "meta:provider": ["geoplanet:7.3.2", "geoplanet:7.4.0", "geoplanet:7.4.1", "geoplanet:7.5.1", "geoplanet:7.5.2", "geoplanet:7.6.0", "geoplanet:7.8.1", "geoplanet:7.9.0", "geoplanet:7.10.0", "geoplanet:8.0.0", "woeplanet:8.0.0"], "meta:indexed": "2020-08-20T22:02:40.635594", "woe:alias_ENG_V": ["Moss Street Elementary"], "meta:updated": "2020-10-14T11:19:39.604657", "woe:hierarchy": {"continent": 24865672, "country": 23424977, "town": 0, "planet": 1, "county": 12589452, "suburb": 0, "state": 2347592, "region": 0, "localadmin": 0}, "woe:timezone_id": 56043648, "woe:hash": "dnrqfgdw45sk", "woe:centroid": [-79.680313, 36.363049], "geom:latitude": 36.363049, "geom:longitude": -79.680313, "geom:hash": "dnrqfgdw45sk", "woe:latitude": 36.363049, "geom:centroid": [-79.680313, 36.363049], "woe:longitude": -79.680313, "woe:repo": "woeplanet-poi-us", "geom:area": 0.0, "woe:scale": 19}}