{"type": "Feature", "id": 23643437, "geometry": {"type": "Point", "coordinates": [-75.328461, 40.570358]}, "properties": {"woe:id": 23643437, "woe:parent_id": 2442656, "woe:name": "Saucon Valley Elementary School", "woe:placetype": 20, "woe:placetype_name": "POI", "woe:lang": "ENG", "iso:country": "US", "meta:provider": ["geoplanet:7.3.1", "geoplanet:7.3.2", "geoplanet:7.4.0", "geoplanet:7.4.1", "geoplanet:7.5.1", "geoplanet:7.5.2", "geoplanet:7.6.0", "geoplanet:7.8.1", "geoplanet:7.9.0", "geoplanet:7.10.0", "geoplanet:8.0.0", "woeplanet:8.0.0"], "meta:indexed": "2020-08-20T20:18:59.578877", "woe:alias_ENG_V": ["Saucon Valley Elementary"], "meta:updated": "2020-10-14T11:19:39.655269", "woe:hierarchy": {"continent": 24865672, "country": 23424977, "town": 0, "planet": 1, "county": 12589775, "suburb": 0, "state": 2347597, "region": 0, "localadmin": 0}, "woe:timezone_id": 56043648, "woe:hash": "dr4qvce7rwuk", "woe:centroid": [-75.328461, 40.570358], "geom:latitude": 40.570358, "geom:longitude": -75.328461, "geom:hash": "dr4qvce7rwuk", "woe:latitude": 40.570358, "geom:centroid": [-75.328461, 40.570358], "woe:longitude": -75.328461, "woe:repo": "woeplanet-poi-us", "geom:area": 0.0, "woe:scale": 19}}