{"type": "Feature", "id": 23668011, "geometry": {"type": "Point", "coordinates": [-119.771294, 46.211319]}, "properties": {"woe:id": 23668011, "woe:parent_id": 2476986, "woe:name": "Prosser Falls Education Center", "woe:placetype": 20, "woe:placetype_name": "POI", "woe:lang": "ENG", "iso:country": "US", "meta:provider": ["geoplanet:7.3.2", "geoplanet:7.4.0", "geoplanet:7.4.1", "geoplanet:7.5.1", "geoplanet:7.5.2", "geoplanet:7.6.0", "geoplanet:7.8.1", "geoplanet:7.9.0", "geoplanet:7.10.0", "geoplanet:8.0.0", "woeplanet:8.0.0"], "meta:indexed": "2020-08-20T22:02:59.418992", "meta:updated": "2020-10-14T11:19:53.945148", "woe:alias_ENG_V": ["Prosser Falls High School"], "woe:hierarchy": {"continent": 24865672, "country": 23424977, "town": 0, "planet": 1, "county": 12590442, "suburb": 0, "state": 2347606, "region": 0, "localadmin": 0}, "woe:timezone_id": 56043663, "woe:hash": "c24yfs90qw4p", "woe:centroid": [-119.771294, 46.211319], "geom:latitude": 46.211319, "geom:longitude": -119.771294, "geom:hash": "c24yfs90qw4p", "woe:latitude": 46.211319, "geom:centroid": [-119.771294, 46.211319], "woe:longitude": -119.771294, "woe:repo": "woeplanet-poi-us", "geom:area": 0.0, "woe:scale": 19}}