{"type": "Feature", "id": 23568638, "properties": {"woe:id": 23568638, "woe:parent_id": 2497896, "woe:name": "Community Christian School", "woe:placetype": 20, "woe:placetype_name": "POI", "woe:lang": "ENG", "iso:country": "US", "meta:provider": ["geoplanet:7.3.1", "geoplanet:7.3.2", "geoplanet:7.4.0", "geoplanet:7.4.1", "geoplanet:7.5.1", "geoplanet:7.5.2", "geoplanet:7.6.0", "geoplanet:7.8.1", "geoplanet:7.9.0", "geoplanet:7.10.0", "geoplanet:8.0.0", "woeplanet:8.0.0"], "meta:indexed": "2020-08-20T20:18:34.872962", "meta:updated": "2020-08-22T02:57:36.022481", "woe:hierarchy": {"continent": 24865672, "country": 23424977, "town": 0, "planet": 1, "county": 12588268, "suburb": 0, "state": 2347573, "region": 0, "localadmin": 0}, "woe:timezone_id": 56043656, "woe:hash": "dp5dt5v429zj", "woe:centroid": [-84.851501, 39.835449], "geom:latitude": 39.835449, "geom:longitude": -84.851501, "geom:hash": "dp5dt5v429zj", "woe:latitude": 39.835449, "geom:centroid": [-84.851501, 39.835449], "woe:longitude": -84.851501, "woe:repo": "woeplanet-poi-us"}, "geometry": {"coordinates": [-84.851501, 39.835449], "type": "Point"}}