{"type": "Feature", "id": 23671219, "properties": {"woe:id": 23671219, "woe:parent_id": 55861951, "woe:name": "Northwest Christian Schools", "woe:placetype": 20, "woe:placetype_name": "POI", "woe:lang": "ENG", "iso:country": "US", "meta:provider": ["geoplanet:7.3.1", "geoplanet:7.3.2", "geoplanet:7.4.0", "geoplanet:7.4.1", "geoplanet:7.5.1", "geoplanet:7.5.2", "geoplanet:7.6.0", "geoplanet:7.8.1", "geoplanet:7.9.0", "geoplanet:7.10.0", "geoplanet:8.0.0", "woeplanet:8.0.0"], "meta:indexed": "2020-08-20T20:19:09.843702", "woe:alias_ENG_V": ["NW Christian Schools"], "meta:updated": "2020-08-22T02:57:52.263890", "woe:hierarchy": {"continent": 24865672, "country": 23424977, "town": 0, "planet": 1, "county": 12590471, "suburb": 0, "state": 2347606, "region": 0, "localadmin": 0}, "woe:timezone_id": 56043663, "woe:hash": "c2krrv8hz3wb", "woe:centroid": [-117.432541, 47.7117], "geom:latitude": 47.7117, "geom:longitude": -117.432541, "geom:hash": "c2krrv8hz3wb", "woe:latitude": 47.7117, "geom:centroid": [-117.432541, 47.7117], "woe:longitude": -117.432541, "woe:repo": "woeplanet-poi-us"}, "geometry": {"coordinates": [-117.432541, 47.7117], "type": "Point"}}