{"type": "Feature", "id": 56053725, "properties": {"woe:id": 56053725, "woe:parent_id": 2437916, "woe:name": "Midlands Technical Col-Ft Jackson", "woe:placetype": 20, "woe:placetype_name": "POI", "woe:lang": "ENG", "iso:country": "US", "meta:provider": ["geoplanet:7.3.1", "geoplanet:7.3.2", "geoplanet:7.4.0", "geoplanet:7.4.1", "geoplanet:7.5.1", "geoplanet:7.5.2", "geoplanet:7.6.0", "geoplanet:7.8.1", "geoplanet:7.9.0", "geoplanet:7.10.0", "geoplanet:8.0.0", "woeplanet:8.0.0"], "meta:indexed": "2020-08-20T20:19:17.270094", "meta:updated": "2020-08-22T02:58:20.983755", "woe:alias_ENG_V": ["Midlands Technical College-Fort Jackson"], "woe:hierarchy": {"continent": 24865672, "country": 23424977, "town": 0, "planet": 1, "county": 12589839, "suburb": 0, "state": 2347599, "region": 0, "localadmin": 0}, "woe:timezone_id": 56043648, "woe:hash": "dnn3qrs29z2t", "woe:centroid": [-80.930367, 34.011051], "geom:latitude": 34.011051, "geom:longitude": -80.930367, "geom:hash": "dnn3qrs29z2t", "woe:latitude": 34.011051, "geom:centroid": [-80.930367, 34.011051], "woe:longitude": -80.930367, "woe:repo": "woeplanet-poi-us"}, "geometry": {"coordinates": [-80.930367, 34.011051], "type": "Point"}}