{"type": "Feature", "id": 23551200, "geometry": {"type": "Point", "coordinates": [-84.71891, 34.342621]}, "properties": {"woe:id": 23551200, "woe:parent_id": 2486202, "woe:name": "Pine Log Elementary School", "woe:placetype": 20, "woe:placetype_name": "POI", "woe:lang": "ENG", "iso:country": "US", "meta:provider": ["geoplanet:7.3.1", "geoplanet:7.3.2", "geoplanet:7.4.0", "geoplanet:7.4.1", "geoplanet:7.5.1", "geoplanet:7.5.2", "geoplanet:7.6.0", "geoplanet:7.8.1", "geoplanet:7.9.0", "geoplanet:7.10.0", "geoplanet:8.0.0", "woeplanet:8.0.0"], "meta:indexed": "2020-08-20T20:18:28.757669", "woe:alias_ENG_V": ["Pine Log Elementary"], "meta:updated": "2020-10-14T11:20:18.022537", "woe:hierarchy": {"continent": 24865672, "country": 23424977, "town": 0, "planet": 1, "county": 12587877, "suburb": 0, "state": 2347569, "region": 0, "localadmin": 0}, "woe:timezone_id": 56043648, "woe:hash": "dn5g25vs62d1", "woe:centroid": [-84.71891, 34.342621], "geom:latitude": 34.342621, "geom:longitude": -84.71891, "geom:hash": "dn5g25vs62d1", "woe:latitude": 34.342621, "geom:centroid": [-84.71891, 34.342621], "woe:longitude": -84.71891, "woe:repo": "woeplanet-poi-us", "geom:area": 0.0, "woe:scale": 19}}