{"type": "Feature", "id": 23562687, "properties": {"woe:id": 23562687, "woe:parent_id": 55986393, "woe:name": "Saint Anastasia School", "woe:placetype": 20, "woe:placetype_name": "POI", "woe:lang": "ENG", "iso:country": "US", "meta:provider": ["geoplanet:7.4.0", "geoplanet:7.4.1", "geoplanet:7.5.1", "geoplanet:7.5.2", "geoplanet:7.6.0", "geoplanet:7.8.1", "geoplanet:7.9.0", "geoplanet:7.10.0", "geoplanet:8.0.0", "woeplanet:8.0.0"], "meta:indexed": "2020-08-20T23:54:58.982699", "meta:updated": "2020-08-22T02:57:34.842410", "woe:hierarchy": {"continent": 24865672, "country": 23424977, "town": 0, "planet": 1, "county": 12588127, "suburb": 0, "state": 2347572, "region": 0, "localadmin": 0}, "woe:timezone_id": 56043661, "woe:hash": "dp9914w6q3uz", "woe:centroid": [-87.837822, 42.377411], "geom:latitude": 42.377411, "geom:longitude": -87.837822, "geom:hash": "dp9914w6q3uz", "woe:latitude": 42.377411, "geom:centroid": [-87.837822, 42.377411], "woe:longitude": -87.837822, "woe:repo": "woeplanet-poi-us"}, "geometry": {"coordinates": [-87.837822, 42.377411], "type": "Point"}}