{"type": "Feature", "id": 23536981, "geometry": {"type": "Point", "coordinates": [-116.979698, 32.816811]}, "properties": {"woe:id": 23536981, "woe:parent_id": 55969423, "woe:name": "Phoenix High School", "woe:placetype": 20, "woe:placetype_name": "POI", "woe:lang": "ENG", "iso:country": "US", "meta:provider": ["geoplanet:7.3.1", "geoplanet:7.3.2", "geoplanet:7.4.0", "geoplanet:7.4.1", "geoplanet:7.5.1", "geoplanet:7.5.2", "geoplanet:7.6.0", "geoplanet:7.8.1", "geoplanet:7.9.0", "geoplanet:7.10.0", "geoplanet:8.0.0", "woeplanet:8.0.0"], "meta:indexed": "2020-08-20T20:18:23.417915", "woe:alias_ENG_V": ["Phoenix Senior High School", "Phoenix High", "Phoenix Senior High", "Phoenix HS", "Phoenix Senior HS"], "meta:updated": "2020-10-14T11:20:15.774763", "woe:hierarchy": {"continent": 24865672, "country": 23424977, "town": 0, "planet": 1, "county": 12587706, "suburb": 0, "state": 2347563, "region": 0, "localadmin": 0}, "woe:timezone_id": 56043663, "woe:hash": "9mufdn1gz2zn", "woe:centroid": [-116.979698, 32.816811], "geom:latitude": 32.816811, "geom:longitude": -116.979698, "geom:hash": "9mufdn1gz2zn", "woe:latitude": 32.816811, "geom:centroid": [-116.979698, 32.816811], "woe:longitude": -116.979698, "woe:repo": "woeplanet-poi-us", "geom:area": 0.0, "woe:scale": 19}}