{"type": "Feature", "id": 23583045, "properties": {"woe:id": 23583045, "woe:parent_id": 2460580, "woe:name": "North Andover Middle School", "woe:placetype": 20, "woe:placetype_name": "POI", "woe:lang": "ENG", "iso:country": "US", "meta:provider": ["geoplanet:7.3.1", "geoplanet:7.3.2", "geoplanet:7.4.0", "geoplanet:7.4.1", "geoplanet:7.5.1", "geoplanet:7.5.2", "geoplanet:7.6.0", "geoplanet:7.8.1", "geoplanet:7.9.0", "geoplanet:7.10.0", "geoplanet:8.0.0", "woeplanet:8.0.0"], "meta:indexed": "2020-08-20T20:18:39.161190", "woe:alias_ENG_V": ["N Andover Middle School"], "meta:updated": "2020-08-22T02:57:38.286616", "woe:hierarchy": {"continent": 24865672, "country": 23424977, "town": 0, "planet": 1, "county": 12588704, "suburb": 0, "state": 2347580, "region": 0, "localadmin": 0}, "woe:timezone_id": 56043648, "woe:hash": "drt6vs4vs306", "woe:centroid": [-71.121529, 42.693821], "geom:latitude": 42.693821, "geom:longitude": -71.121529, "geom:hash": "drt6vs4vs306", "woe:latitude": 42.693821, "geom:centroid": [-71.121529, 42.693821], "woe:longitude": -71.121529, "woe:repo": "woeplanet-poi-us"}, "geometry": {"coordinates": [-71.121529, 42.693821], "type": "Point"}}