{"type": "Feature", "id": 23678055, "geometry": {"type": "Point", "coordinates": [-73.94944, 40.796669]}, "properties": {"woe:id": 23678055, "woe:parent_id": 12589342, "woe:name": "Frawley Circle", "woe:placetype": 20, "woe:placetype_name": "POI", "woe:lang": "ENG", "iso:country": "US", "meta:provider": ["geoplanet:7.3.1", "geoplanet:7.3.2", "geoplanet:7.4.0", "geoplanet:7.4.1", "geoplanet:7.5.1", "geoplanet:7.5.2", "geoplanet:7.6.0", "geoplanet:7.8.1", "geoplanet:7.9.0", "geoplanet:7.10.0", "geoplanet:8.0.0", "woeplanet:8.0.0"], "meta:indexed": "2020-08-20T20:19:12.298716", "meta:updated": "2020-10-14T11:19:45.009853", "woe:hierarchy": {"continent": 24865672, "country": 23424977, "town": 0, "planet": 1, "county": 12589342, "suburb": 0, "state": 2347591, "region": 0, "localadmin": 0}, "woe:timezone_id": 56043648, "woe:hash": "dr72j4z9v4kc", "woe:centroid": [-73.94944, 40.796669], "geom:latitude": 40.796669, "geom:longitude": -73.94944, "geom:hash": "dr72j4z9v4kc", "woe:latitude": 40.796669, "geom:centroid": [-73.94944, 40.796669], "woe:longitude": -73.94944, "woe:repo": "woeplanet-poi-us", "geom:area": 0.0, "woe:scale": 19}}