{"type": "Feature", "id": 23615144, "properties": {"woe:id": 23615144, "woe:parent_id": 55992160, "woe:name": "Ps 157 Franklin School", "woe:placetype": 20, "woe:placetype_name": "POI", "woe:lang": "ENG", "iso:country": "US", "meta:provider": ["geoplanet:7.3.1", "geoplanet:7.3.2", "geoplanet:7.4.0", "geoplanet:7.4.1", "geoplanet:7.5.1", "geoplanet:7.5.2", "geoplanet:7.6.0", "geoplanet:7.8.1", "geoplanet:7.9.0", "geoplanet:7.10.0", "geoplanet:8.0.0", "woeplanet:8.0.0"], "meta:indexed": "2020-08-20T20:18:49.413054", "meta:updated": "2020-08-22T02:57:42.978108", "woe:hierarchy": {"continent": 24865672, "country": 23424977, "town": 0, "planet": 1, "county": 12589335, "suburb": 0, "state": 2347591, "region": 0, "localadmin": 0}, "woe:timezone_id": 56043648, "woe:hash": "dr5rt00qf8jm", "woe:centroid": [-73.959503, 40.694519], "geom:latitude": 40.694519, "geom:longitude": -73.959503, "geom:hash": "dr5rt00qf8jm", "woe:latitude": 40.694519, "geom:centroid": [-73.959503, 40.694519], "woe:longitude": -73.959503, "woe:repo": "woeplanet-poi-us"}, "geometry": {"coordinates": [-73.959503, 40.694519], "type": "Point"}}