{"type": "Feature", "id": 23537533, "geometry": {"type": "Point", "coordinates": [-117.006172, 32.750462]}, "properties": {"woe:id": 23537533, "woe:parent_id": 2375840, "woe:name": "Trinity Christian School", "woe:placetype": 20, "woe:placetype_name": "POI", "woe:lang": "ENG", "iso:country": "US", "meta:provider": ["geoplanet:7.3.1", "geoplanet:7.3.2", "geoplanet:7.4.0", "geoplanet:7.4.1", "geoplanet:7.5.1", "geoplanet:7.5.2", "geoplanet:7.6.0", "geoplanet:7.8.1", "geoplanet:7.9.0", "geoplanet:7.10.0", "geoplanet:8.0.0", "woeplanet:8.0.0"], "meta:indexed": "2020-08-20T20:18:23.581543", "meta:updated": "2020-10-14T11:20:11.783370", "woe:hierarchy": {"continent": 24865672, "country": 23424977, "town": 0, "planet": 1, "county": 12587706, "suburb": 0, "state": 2347563, "region": 0, "localadmin": 0}, "woe:timezone_id": 56043663, "woe:hash": "9muf36n9q8de", "woe:centroid": [-117.006172, 32.750462], "geom:latitude": 32.750462, "geom:longitude": -117.006172, "geom:hash": "9muf36n9q8de", "woe:latitude": 32.750462, "geom:centroid": [-117.006172, 32.750462], "woe:longitude": -117.006172, "woe:repo": "woeplanet-poi-us", "geom:area": 0.0, "woe:scale": 19}}