{"type": "Feature", "id": 23660678, "geometry": {"type": "Point", "coordinates": [-97.415192, 27.742229]}, "properties": {"woe:id": 23660678, "woe:parent_id": 55806869, "woe:name": "Fannin Elementary School", "woe:placetype": 20, "woe:placetype_name": "POI", "woe:lang": "ENG", "iso:country": "US", "meta:provider": ["geoplanet:7.3.1", "geoplanet:7.3.2", "geoplanet:7.4.0", "geoplanet:7.4.1", "geoplanet:7.5.1", "geoplanet:7.5.2", "geoplanet:7.6.0", "geoplanet:7.8.1", "geoplanet:7.9.0", "geoplanet:7.10.0", "geoplanet:8.0.0", "woeplanet:8.0.0"], "meta:indexed": "2020-08-20T20:19:06.566148", "woe:alias_ENG_V": ["Fannin Elementary"], "meta:updated": "2020-10-14T11:19:48.677447", "woe:hierarchy": {"continent": 24865672, "country": 23424977, "town": 0, "planet": 1, "county": 12590184, "suburb": 0, "state": 2347602, "region": 0, "localadmin": 0}, "woe:timezone_id": 56043661, "woe:hash": "9uftz626jw24", "woe:centroid": [-97.415192, 27.742229], "geom:latitude": 27.742229, "geom:longitude": -97.415192, "geom:hash": "9uftz626jw24", "woe:latitude": 27.742229, "geom:centroid": [-97.415192, 27.742229], "woe:longitude": -97.415192, "woe:repo": "woeplanet-poi-us", "geom:area": 0.0, "woe:scale": 19}}