{"type": "Feature", "id": 23571343, "geometry": {"type": "Point", "coordinates": [-94.952003, 39.763672]}, "properties": {"woe:id": 23571343, "woe:parent_id": 2515261, "woe:name": "Wathena High School", "woe:placetype": 20, "woe:placetype_name": "POI", "woe:lang": "ENG", "iso:country": "US", "meta:provider": ["geoplanet:7.3.2", "geoplanet:7.4.0", "geoplanet:7.4.1", "geoplanet:7.5.1", "geoplanet:7.5.2", "geoplanet:7.6.0", "geoplanet:7.8.1", "geoplanet:7.9.0", "geoplanet:7.10.0", "geoplanet:8.0.0", "woeplanet:8.0.0"], "meta:indexed": "2020-08-20T22:02:19.144433", "woe:alias_ENG_V": ["Wathena Senior High School", "Wathena High", "Wathena Senior High", "Wathena HS", "Wathena Senior HS"], "meta:updated": "2020-10-14T11:20:18.769714", "woe:hierarchy": {"continent": 24865672, "country": 23424977, "town": 0, "planet": 1, "county": 12588392, "suburb": 0, "state": 2347575, "region": 0, "localadmin": 0}, "woe:timezone_id": 56043661, "woe:hash": "9zh6pqf01vwy", "woe:centroid": [-94.952003, 39.763672], "geom:latitude": 39.763672, "geom:longitude": -94.952003, "geom:hash": "9zh6pqf01vwy", "woe:latitude": 39.763672, "geom:centroid": [-94.952003, 39.763672], "woe:longitude": -94.952003, "woe:repo": "woeplanet-poi-us", "geom:area": 0.0, "woe:scale": 19}}