{"type": "Feature", "id": 23675512, "geometry": {"type": "Point", "coordinates": [-92.609001, 44.847221]}, "properties": {"woe:id": 23675512, "woe:parent_id": 2481818, "woe:name": "Good Shepherd Christian Academy", "woe:placetype": 20, "woe:placetype_name": "POI", "woe:lang": "ENG", "iso:country": "US", "meta:provider": ["geoplanet:7.3.1", "geoplanet:7.3.2", "geoplanet:7.4.0", "geoplanet:7.4.1", "geoplanet:7.5.1", "geoplanet:7.5.2", "geoplanet:7.6.0", "geoplanet:7.8.1", "geoplanet:7.9.0", "geoplanet:7.10.0", "geoplanet:8.0.0", "woeplanet:8.0.0"], "meta:indexed": "2020-08-20T20:19:11.536053", "meta:updated": "2020-10-14T11:19:37.148040", "woe:hierarchy": {"continent": 24865672, "country": 23424977, "town": 0, "planet": 1, "county": 12590581, "suburb": 0, "state": 2347608, "region": 0, "localadmin": 0}, "woe:timezone_id": 56043661, "woe:hash": "9zyphshjvzgv", "woe:centroid": [-92.609001, 44.847221], "geom:latitude": 44.847221, "geom:longitude": -92.609001, "geom:hash": "9zyphshjvzgv", "woe:latitude": 44.847221, "geom:centroid": [-92.609001, 44.847221], "woe:longitude": -92.609001, "woe:repo": "woeplanet-poi-us", "geom:area": 0.0, "woe:scale": 19}}