{"type": "Feature", "id": 23569015, "properties": {"woe:id": 23569015, "woe:parent_id": 2394684, "woe:name": "Durant Middle School", "woe:placetype": 20, "woe:placetype_name": "POI", "woe:lang": "ENG", "iso:country": "US", "meta:provider": ["geoplanet:7.3.2", "geoplanet:7.4.0", "geoplanet:7.4.1", "geoplanet:7.5.1", "geoplanet:7.5.2", "geoplanet:7.6.0", "geoplanet:7.8.1", "geoplanet:7.9.0", "geoplanet:7.10.0", "geoplanet:8.0.0", "woeplanet:8.0.0"], "meta:indexed": "2020-08-20T22:02:18.085976", "meta:updated": "2020-08-22T02:57:36.080704", "woe:hierarchy": {"continent": 24865672, "country": 23424977, "town": 0, "planet": 1, "county": 12588287, "suburb": 0, "state": 2347574, "region": 0, "localadmin": 0}, "woe:timezone_id": 56043661, "woe:hash": "9zrkejwm1b9j", "woe:centroid": [-90.914192, 41.60334], "geom:latitude": 41.60334, "geom:longitude": -90.914192, "geom:hash": "9zrkejwm1b9j", "woe:latitude": 41.60334, "geom:centroid": [-90.914192, 41.60334], "woe:longitude": -90.914192, "woe:repo": "woeplanet-poi-us"}, "geometry": {"coordinates": [-90.914192, 41.60334], "type": "Point"}}