{"type": "Feature", "id": 23667089, "geometry": {"type": "Point", "coordinates": [-76.350479, 37.023472]}, "properties": {"woe:id": 23667089, "woe:parent_id": 2416847, "woe:name": "Hampton Montessori School", "woe:placetype": 20, "woe:placetype_name": "POI", "woe:lang": "ENG", "iso:country": "US", "meta:provider": ["geoplanet:7.4.0", "geoplanet:7.4.1", "geoplanet:7.5.1", "geoplanet:7.5.2", "geoplanet:7.6.0", "geoplanet:7.8.1", "geoplanet:7.9.0", "geoplanet:7.10.0", "geoplanet:8.0.0", "woeplanet:8.0.0"], "meta:indexed": "2020-08-20T23:55:45.219612", "meta:updated": "2020-10-14T11:19:37.366578", "woe:hierarchy": {"continent": 24865672, "country": 23424977, "town": 0, "planet": 1, "county": 12590361, "suburb": 0, "state": 2347605, "region": 0, "localadmin": 0}, "woe:timezone_id": 56043648, "woe:hash": "dq9dwegm2gkt", "woe:centroid": [-76.350479, 37.023472], "geom:latitude": 37.023472, "geom:longitude": -76.350479, "geom:hash": "dq9dwegm2gkt", "woe:latitude": 37.023472, "geom:centroid": [-76.350479, 37.023472], "woe:longitude": -76.350479, "woe:repo": "woeplanet-poi-us", "geom:area": 0.0, "woe:scale": 19}}