{"type": "Feature", "id": 23588772, "geometry": {"type": "Point", "coordinates": [-82.997017, 42.577549]}, "properties": {"woe:id": 23588772, "woe:parent_id": 2499659, "woe:name": "Rose Kidd Elementary School", "woe:placetype": 20, "woe:placetype_name": "POI", "woe:lang": "ENG", "iso:country": "US", "meta:provider": ["geoplanet:7.3.1", "geoplanet:7.3.2", "geoplanet:7.4.0", "geoplanet:7.4.1", "geoplanet:7.5.1", "geoplanet:7.5.2", "geoplanet:7.6.0", "geoplanet:7.8.1", "geoplanet:7.9.0", "geoplanet:7.10.0", "geoplanet:8.0.0", "woeplanet:8.0.0"], "meta:indexed": "2020-08-20T20:18:40.737177", "woe:alias_ENG_V": ["Rose Kidd Elementary"], "meta:updated": "2020-10-14T11:20:26.457699", "woe:hierarchy": {"continent": 24865672, "country": 23424977, "town": 0, "planet": 1, "county": 12588763, "suburb": 0, "state": 2347581, "region": 0, "localadmin": 0}, "woe:timezone_id": 56043658, "woe:hash": "dpsfpr52jq6s", "woe:centroid": [-82.997017, 42.577549], "geom:latitude": 42.577549, "geom:longitude": -82.997017, "geom:hash": "dpsfpr52jq6s", "woe:latitude": 42.577549, "geom:centroid": [-82.997017, 42.577549], "woe:longitude": -82.997017, "woe:repo": "woeplanet-poi-us", "geom:area": 0.0, "woe:scale": 19}}