{"type": "Feature", "id": 23588540, "properties": {"woe:id": 23588540, "woe:parent_id": 2425038, "woe:name": "Howell High School", "woe:placetype": 20, "woe:placetype_name": "POI", "woe:lang": "ENG", "iso:country": "US", "meta:provider": ["geoplanet:7.3.1", "geoplanet:7.3.2", "geoplanet:7.4.0", "geoplanet:7.4.1", "geoplanet:7.5.1", "geoplanet:7.5.2", "geoplanet:7.6.0", "geoplanet:7.8.1", "geoplanet:7.9.0", "geoplanet:7.10.0", "geoplanet:8.0.0", "woeplanet:8.0.0"], "meta:indexed": "2020-08-20T20:18:40.630654", "woe:alias_ENG_V": ["Howell Senior High School", "Howell High", "Howell Senior High", "Howell HS", "Howell Senior HS"], "meta:updated": "2020-08-22T02:58:47.973261", "woe:hierarchy": {"continent": 24865672, "country": 23424977, "town": 0, "planet": 1, "county": 12588760, "suburb": 0, "state": 2347581, "region": 0, "localadmin": 0}, "woe:timezone_id": 56043658, "woe:hash": "dps63tprdp7y", "woe:centroid": [-83.947472, 42.611801], "geom:latitude": 42.611801, "geom:longitude": -83.947472, "geom:hash": "dps63tprdp7y", "woe:latitude": 42.611801, "geom:centroid": [-83.947472, 42.611801], "woe:longitude": -83.947472, "woe:repo": "woeplanet-poi-us"}, "geometry": {"coordinates": [-83.947472, 42.611801], "type": "Point"}}