{"type": "Feature", "id": 23625597, "geometry": {"type": "Point", "coordinates": [-79.577942, 35.256748]}, "properties": {"woe:id": 23625597, "woe:parent_id": 2516957, "woe:name": "West End Elementary School", "woe:placetype": 20, "woe:placetype_name": "POI", "woe:lang": "ENG", "iso:country": "US", "meta:provider": ["geoplanet:7.4.0", "geoplanet:7.4.1", "geoplanet:7.5.1", "geoplanet:7.5.2", "geoplanet:7.6.0", "geoplanet:7.8.1", "geoplanet:7.9.0", "geoplanet:7.10.0", "geoplanet:8.0.0", "woeplanet:8.0.0"], "meta:indexed": "2020-08-20T23:55:26.002051", "woe:alias_ENG_V": ["W End Elementary School", "W End Elementary", "West End Elementary"], "meta:updated": "2020-10-14T11:19:34.391496", "woe:hierarchy": {"continent": 24865672, "country": 23424977, "town": 0, "planet": 1, "county": 12589436, "suburb": 0, "state": 2347592, "region": 0, "localadmin": 0}, "woe:timezone_id": 56043648, "woe:hash": "dnr2t4m17w1t", "woe:centroid": [-79.577942, 35.256748], "geom:latitude": 35.256748, "geom:longitude": -79.577942, "geom:hash": "dnr2t4m17w1t", "woe:latitude": 35.256748, "geom:centroid": [-79.577942, 35.256748], "woe:longitude": -79.577942, "woe:repo": "woeplanet-poi-us", "geom:area": 0.0, "woe:scale": 19}}