{"type": "Feature", "id": 23661203, "geometry": {"type": "Point", "coordinates": [-99.787987, 29.199989]}, "properties": {"woe:id": 23661203, "woe:parent_id": 2510571, "woe:name": "Robb Elementary School", "woe:placetype": 20, "woe:placetype_name": "POI", "woe:lang": "ENG", "iso:country": "US", "meta:provider": ["geoplanet:7.3.1", "geoplanet:7.3.2", "geoplanet:7.4.0", "geoplanet:7.4.1", "geoplanet:7.5.1", "geoplanet:7.5.2", "geoplanet:7.6.0", "geoplanet:7.8.1", "geoplanet:7.9.0", "geoplanet:7.10.0", "geoplanet:8.0.0", "woeplanet:8.0.0"], "meta:indexed": "2020-08-20T20:19:06.843289", "woe:alias_ENG_V": ["Robb Elementary"], "meta:updated": "2020-10-14T11:19:42.635298", "woe:hierarchy": {"continent": 24865672, "country": 23424977, "town": 0, "planet": 1, "county": 12590238, "suburb": 0, "state": 2347602, "region": 0, "localadmin": 0}, "woe:timezone_id": 56043661, "woe:hash": "9v1n178w727z", "woe:centroid": [-99.787987, 29.199989], "geom:latitude": 29.199989, "geom:longitude": -99.787987, "geom:hash": "9v1n178w727z", "woe:latitude": 29.199989, "geom:centroid": [-99.787987, 29.199989], "woe:longitude": -99.787987, "woe:repo": "woeplanet-poi-us", "geom:area": 0.0, "woe:scale": 19}}