{"type": "Feature", "id": 23565042, "geometry": {"type": "Point", "coordinates": [-88.943352, 37.730751]}, "properties": {"woe:id": 23565042, "woe:parent_id": 2445764, "woe:name": "Marion Junior High School", "woe:placetype": 20, "woe:placetype_name": "POI", "woe:lang": "ENG", "iso:country": "US", "meta:provider": ["geoplanet:7.3.1", "geoplanet:7.3.2", "geoplanet:7.4.0", "geoplanet:7.4.1", "geoplanet:7.5.1", "geoplanet:7.5.2", "geoplanet:7.6.0", "geoplanet:7.8.1", "geoplanet:7.9.0", "geoplanet:7.10.0", "geoplanet:8.0.0", "woeplanet:8.0.0"], "meta:indexed": "2020-08-20T20:18:33.456097", "woe:alias_ENG_V": ["Marion Junior High"], "meta:updated": "2020-10-14T11:20:15.043133", "woe:hierarchy": {"continent": 24865672, "country": 23424977, "town": 0, "planet": 1, "county": 12588177, "suburb": 0, "state": 2347572, "region": 0, "localadmin": 0}, "woe:timezone_id": 56043661, "woe:hash": "dn8y8h9mt9vb", "woe:centroid": [-88.943352, 37.730751], "geom:latitude": 37.730751, "geom:longitude": -88.943352, "geom:hash": "dn8y8h9mt9vb", "woe:latitude": 37.730751, "geom:centroid": [-88.943352, 37.730751], "woe:longitude": -88.943352, "woe:repo": "woeplanet-poi-us", "geom:area": 0.0, "woe:scale": 19}}