{"type": "Feature", "id": 23590655, "geometry": {"type": "Point", "coordinates": [-83.464043, 43.654709]}, "properties": {"woe:id": 23590655, "woe:parent_id": 2509988, "woe:name": "Unionville-sebewaing Elementary School", "woe:placetype": 20, "woe:placetype_name": "POI", "woe:lang": "ENG", "iso:country": "US", "meta:provider": ["geoplanet:7.3.1", "geoplanet:7.3.2", "geoplanet:7.4.0", "geoplanet:7.4.1", "geoplanet:7.5.1", "geoplanet:7.5.2", "geoplanet:7.6.0", "geoplanet:7.8.1", "geoplanet:7.9.0", "geoplanet:7.10.0", "geoplanet:8.0.0", "woeplanet:8.0.0"], "meta:indexed": "2020-08-20T20:18:41.422239", "woe:alias_ENG_V": ["Unionville-sebewaing Elementary"], "meta:updated": "2020-10-14T11:20:04.819492", "woe:hierarchy": {"continent": 24865672, "country": 23424977, "town": 0, "planet": 1, "county": 12588792, "suburb": 0, "state": 2347581, "region": 0, "localadmin": 0}, "woe:timezone_id": 56043658, "woe:hash": "dpu8kep74gdf", "woe:centroid": [-83.464043, 43.654709], "geom:latitude": 43.654709, "geom:longitude": -83.464043, "geom:hash": "dpu8kep74gdf", "woe:latitude": 43.654709, "geom:centroid": [-83.464043, 43.654709], "woe:longitude": -83.464043, "woe:repo": "woeplanet-poi-us", "geom:area": 0.0, "woe:scale": 19}}