{"type": "Feature", "id": 23645197, "geometry": {"type": "Point", "coordinates": [-80.396294, 40.077629]}, "properties": {"woe:id": 23645197, "woe:parent_id": 2395566, "woe:name": "East-west Finley Elementary School", "woe:placetype": 20, "woe:placetype_name": "POI", "woe:lang": "ENG", "iso:country": "US", "meta:provider": ["geoplanet:7.3.1", "geoplanet:7.3.2", "geoplanet:7.4.0", "geoplanet:7.4.1", "geoplanet:7.5.1", "geoplanet:7.5.2", "geoplanet:7.6.0", "geoplanet:7.8.1", "geoplanet:7.9.0", "geoplanet:7.10.0", "geoplanet:8.0.0", "woeplanet:8.0.0"], "meta:indexed": "2020-08-20T20:19:00.083266", "woe:alias_ENG_V": ["E-west Finley Elementary School", "E-west Finley Elementary", "East-west Finley Elementary"], "meta:updated": "2020-10-14T11:19:41.343136", "woe:hierarchy": {"continent": 24865672, "country": 23424977, "town": 0, "planet": 1, "county": 12589790, "suburb": 0, "state": 2347597, "region": 0, "localadmin": 0}, "woe:timezone_id": 56043648, "woe:hash": "dpngfxcjned1", "woe:centroid": [-80.396294, 40.077629], "geom:latitude": 40.077629, "geom:longitude": -80.396294, "geom:hash": "dpngfxcjned1", "woe:latitude": 40.077629, "geom:centroid": [-80.396294, 40.077629], "woe:longitude": -80.396294, "woe:repo": "woeplanet-poi-us", "geom:area": 0.0, "woe:scale": 19}}