{"type": "Feature", "id": 23554899, "properties": {"woe:id": 23554899, "woe:parent_id": 55986163, "woe:name": "Kaala Elementary School", "woe:placetype": 20, "woe:placetype_name": "POI", "woe:lang": "ENG", "iso:country": "US", "meta:provider": ["geoplanet:7.3.1", "geoplanet:7.3.2", "geoplanet:7.4.0", "geoplanet:7.4.1", "geoplanet:7.5.1", "geoplanet:7.5.2", "geoplanet:7.6.0", "geoplanet:7.8.1", "geoplanet:7.9.0", "geoplanet:7.10.0", "geoplanet:8.0.0", "woeplanet:8.0.0"], "meta:indexed": "2020-08-20T20:18:29.988497", "woe:alias_ENG_V": ["Kaala Elementary"], "meta:updated": "2020-08-22T02:57:33.486853", "woe:hierarchy": {"continent": 24865672, "country": 23424977, "town": 0, "planet": 1, "county": 12588030, "suburb": 0, "state": 2347570, "region": 0, "localadmin": 0}, "woe:timezone_id": 28350949, "woe:hash": "87zd7b9n5dcv", "woe:centroid": [-158.036804, 21.49305], "geom:latitude": 21.49305, "geom:longitude": -158.036804, "geom:hash": "87zd7b9n5dcv", "woe:latitude": 21.49305, "geom:centroid": [-158.036804, 21.49305], "woe:longitude": -158.036804, "woe:repo": "woeplanet-poi-us"}, "geometry": {"coordinates": [-158.036804, 21.49305], "type": "Point"}}