{"type": "Feature", "id": 23564432, "geometry": {"type": "Point", "coordinates": [-89.608147, 40.640179]}, "properties": {"woe:id": 23564432, "woe:parent_id": 2387236, "woe:name": "Homewood Heights Elementary School", "woe:placetype": 20, "woe:placetype_name": "POI", "woe:lang": "ENG", "iso:country": "US", "meta:provider": ["geoplanet:7.3.1", "geoplanet:7.3.2", "geoplanet:7.4.0", "geoplanet:7.4.1", "geoplanet:7.5.1", "geoplanet:7.5.2", "geoplanet:7.6.0", "geoplanet:7.8.1", "geoplanet:7.9.0", "geoplanet:7.10.0", "geoplanet:8.0.0", "woeplanet:8.0.0"], "meta:indexed": "2020-08-20T20:18:33.203181", "woe:alias_ENG_V": ["Homewood Heights Elementary"], "meta:updated": "2020-10-14T11:20:17.360796", "woe:hierarchy": {"continent": 24865672, "country": 23424977, "town": 0, "planet": 1, "county": 12588167, "suburb": 0, "state": 2347572, "region": 0, "localadmin": 0}, "woe:timezone_id": 56043661, "woe:hash": "dp0r0ym64y6y", "woe:centroid": [-89.608147, 40.640179], "geom:latitude": 40.640179, "geom:longitude": -89.608147, "geom:hash": "dp0r0ym64y6y", "woe:latitude": 40.640179, "geom:centroid": [-89.608147, 40.640179], "woe:longitude": -89.608147, "woe:repo": "woeplanet-poi-us", "geom:area": 0.0, "woe:scale": 19}}