{"type": "Feature", "id": 23684222, "properties": {"woe:id": 23684222, "woe:parent_id": 2363921, "woe:name": "Chippewa Mall Merchants Assn", "woe:placetype": 20, "woe:placetype_name": "POI", "woe:lang": "ENG", "iso:country": "US", "meta:provider": ["geoplanet:7.3.1", "geoplanet:7.3.2", "geoplanet:7.4.0", "geoplanet:7.4.1", "geoplanet:7.5.1", "geoplanet:7.5.2", "geoplanet:7.6.0", "geoplanet:7.8.1", "geoplanet:7.9.0", "geoplanet:7.10.0", "geoplanet:8.0.0", "woeplanet:8.0.0"], "meta:indexed": "2020-08-20T20:19:12.814293", "meta:updated": "2020-08-22T02:58:18.724059", "woe:hierarchy": {"continent": 24865672, "country": 23424977, "town": 0, "planet": 1, "county": 12589731, "suburb": 0, "state": 2347597, "region": 0, "localadmin": 0}, "woe:timezone_id": 56043648, "woe:hash": "dpnzgn8eh2wq", "woe:centroid": [-80.375099, 40.773529], "geom:latitude": 40.773529, "geom:longitude": -80.375099, "geom:hash": "dpnzgn8eh2wq", "woe:latitude": 40.773529, "geom:centroid": [-80.375099, 40.773529], "woe:longitude": -80.375099, "woe:repo": "woeplanet-poi-us"}, "geometry": {"coordinates": [-80.375099, 40.773529], "type": "Point"}}