{"type": "Feature", "id": 23535969, "geometry": {"type": "Point", "coordinates": [-117.593758, 34.09396]}, "properties": {"woe:id": 23535969, "woe:parent_id": 2478522, "woe:name": "Cucamonga Elementary School", "woe:placetype": 20, "woe:placetype_name": "POI", "woe:lang": "ENG", "iso:country": "US", "meta:provider": ["geoplanet:7.3.2", "geoplanet:7.4.0", "geoplanet:7.4.1", "geoplanet:7.5.1", "geoplanet:7.5.2", "geoplanet:7.6.0", "geoplanet:7.8.1", "geoplanet:7.9.0", "geoplanet:7.10.0", "geoplanet:8.0.0", "woeplanet:8.0.0"], "meta:indexed": "2020-08-20T22:02:04.424285", "woe:alias_ENG_V": ["Cucamonga Elementary"], "meta:updated": "2020-10-14T11:20:07.379811", "woe:hierarchy": {"continent": 24865672, "country": 23424977, "town": 0, "planet": 1, "county": 12587705, "suburb": 0, "state": 2347563, "region": 0, "localadmin": 0}, "woe:timezone_id": 56043663, "woe:hash": "9qh3undgdyf9", "woe:centroid": [-117.593758, 34.09396], "geom:latitude": 34.09396, "geom:longitude": -117.593758, "geom:hash": "9qh3undgdyf9", "woe:latitude": 34.09396, "geom:centroid": [-117.593758, 34.09396], "woe:longitude": -117.593758, "woe:repo": "woeplanet-poi-us", "geom:area": 0.0, "woe:scale": 19}}