{"type": "Feature", "id": 23641885, "properties": {"woe:id": 23641885, "woe:parent_id": 2360122, "woe:name": "Elizabeth R Martin Elementary School", "woe:placetype": 20, "woe:placetype_name": "POI", "woe:lang": "ENG", "iso:country": "US", "meta:provider": ["geoplanet:7.3.1", "geoplanet:7.3.2", "geoplanet:7.4.0", "geoplanet:7.4.1", "geoplanet:7.5.1", "geoplanet:7.5.2", "geoplanet:7.6.0", "geoplanet:7.8.1", "geoplanet:7.9.0", "geoplanet:7.10.0", "geoplanet:8.0.0", "woeplanet:8.0.0"], "meta:indexed": "2020-08-20T20:18:59.053959", "woe:alias_ENG_V": ["Elizabeth R Martin Elementary Sch", "Elizabeth R Martin Elementary"], "meta:updated": "2020-08-22T02:57:46.956844", "woe:hierarchy": {"continent": 24865672, "country": 23424977, "town": 0, "planet": 1, "county": 12589763, "suburb": 0, "state": 2347597, "region": 0, "localadmin": 0}, "woe:timezone_id": 56043648, "woe:hash": "dr1ewgem6qcy", "woe:centroid": [-76.339432, 40.010399], "geom:latitude": 40.010399, "geom:longitude": -76.339432, "geom:hash": "dr1ewgem6qcy", "woe:latitude": 40.010399, "geom:centroid": [-76.339432, 40.010399], "woe:longitude": -76.339432, "woe:repo": "woeplanet-poi-us"}, "geometry": {"coordinates": [-76.339432, 40.010399], "type": "Point"}}