{"type": "Feature", "id": 23648021, "geometry": {"type": "Point", "coordinates": [-81.927872, 34.941101]}, "properties": {"woe:id": 23648021, "woe:parent_id": 2497370, "woe:name": "Carver Junior High School", "woe:placetype": 20, "woe:placetype_name": "POI", "woe:lang": "ENG", "iso:country": "US", "meta:provider": ["geoplanet:7.3.1", "geoplanet:7.3.2", "geoplanet:7.4.0", "geoplanet:7.4.1", "geoplanet:7.5.1", "geoplanet:7.5.2", "geoplanet:7.6.0", "geoplanet:7.8.1", "geoplanet:7.9.0", "geoplanet:7.10.0", "geoplanet:8.0.0", "woeplanet:8.0.0"], "meta:indexed": "2020-08-20T20:19:00.977976", "woe:alias_ENG_V": ["Carver Junior High"], "meta:updated": "2020-10-14T11:19:30.722474", "woe:hierarchy": {"continent": 24865672, "country": 23424977, "town": 0, "planet": 1, "county": 12589841, "suburb": 0, "state": 2347599, "region": 0, "localadmin": 0}, "woe:timezone_id": 56043648, "woe:hash": "dnjwz8vfwjqf", "woe:centroid": [-81.927872, 34.941101], "geom:latitude": 34.941101, "geom:longitude": -81.927872, "geom:hash": "dnjwz8vfwjqf", "woe:latitude": 34.941101, "geom:centroid": [-81.927872, 34.941101], "woe:longitude": -81.927872, "woe:repo": "woeplanet-poi-us", "geom:area": 0.0, "woe:scale": 19}}