{"type": "Feature", "id": 23683987, "geometry": {"type": "Point", "coordinates": [-112.263062, 33.53043]}, "properties": {"woe:id": 23683987, "woe:parent_id": 55859433, "woe:name": "Jobing.com Arena", "woe:placetype": 20, "woe:placetype_name": "POI", "woe:lang": "ENG", "iso:country": "US", "meta:provider": ["geoplanet:7.3.1", "geoplanet:7.3.2", "geoplanet:7.4.0", "geoplanet:7.4.1", "geoplanet:7.5.1", "geoplanet:7.5.2", "geoplanet:7.6.0", "geoplanet:7.8.1", "geoplanet:7.9.0", "geoplanet:7.10.0", "geoplanet:8.0.0", "woeplanet:8.0.0"], "meta:indexed": "2020-08-20T20:19:12.651896", "woe:alias_ENG_V": ["Glendale Arena"], "meta:updated": "2020-10-14T11:19:36.302341", "woe:hierarchy": {"continent": 24865672, "country": 23424977, "town": 0, "planet": 1, "county": 12587587, "suburb": 0, "state": 2347561, "region": 0, "localadmin": 0}, "woe:timezone_id": 56043666, "woe:hash": "9tbnv2h8cj1v", "woe:centroid": [-112.263062, 33.53043], "geom:latitude": 33.53043, "geom:longitude": -112.263062, "geom:hash": "9tbnv2h8cj1v", "woe:latitude": 33.53043, "geom:centroid": [-112.263062, 33.53043], "woe:longitude": -112.263062, "woe:repo": "woeplanet-poi-us", "geom:area": 0.0, "woe:scale": 19}}