{"type": "Feature", "id": 23599696, "properties": {"woe:id": 23599696, "woe:parent_id": 2379335, "woe:name": "Highcroft Ridge Elementary School", "woe:placetype": 20, "woe:placetype_name": "POI", "woe:lang": "ENG", "iso:country": "US", "meta:provider": ["geoplanet:7.3.1", "geoplanet:7.3.2", "geoplanet:7.4.0", "geoplanet:7.4.1", "geoplanet:7.5.1", "geoplanet:7.5.2", "geoplanet:7.6.0", "geoplanet:7.8.1", "geoplanet:7.9.0", "geoplanet:7.10.0", "geoplanet:8.0.0", "woeplanet:8.0.0"], "meta:indexed": "2020-08-20T20:18:44.755324", "woe:alias_ENG_V": ["Highcroft Ridge Elementary"], "meta:updated": "2020-08-22T02:57:41.011220", "woe:hierarchy": {"continent": 24865672, "country": 23424977, "town": 0, "planet": 1, "county": 12589066, "suburb": 0, "state": 2347584, "region": 0, "localadmin": 0}, "woe:timezone_id": 56043661, "woe:hash": "9yzeg7pjckmm", "woe:centroid": [-90.550629, 38.64542], "geom:latitude": 38.64542, "geom:longitude": -90.550629, "geom:hash": "9yzeg7pjckmm", "woe:latitude": 38.64542, "geom:centroid": [-90.550629, 38.64542], "woe:longitude": -90.550629, "woe:repo": "woeplanet-poi-us"}, "geometry": {"coordinates": [-90.550629, 38.64542], "type": "Point"}}