{"type": "Feature", "id": 23659162, "properties": {"woe:id": 23659162, "woe:parent_id": 28751419, "woe:name": "Martinez C Elementary School", "woe:placetype": 20, "woe:placetype_name": "POI", "woe:lang": "ENG", "iso:country": "US", "meta:provider": ["geoplanet:7.3.1", "geoplanet:7.3.2", "geoplanet:7.4.0", "geoplanet:7.4.1", "geoplanet:7.5.1", "geoplanet:7.5.2", "geoplanet:7.6.0", "geoplanet:7.8.1", "geoplanet:7.9.0", "geoplanet:7.10.0", "geoplanet:8.0.0", "woeplanet:8.0.0"], "meta:indexed": "2020-08-20T20:19:05.873412", "woe:alias_ENG_V": ["Martinez C Elementary"], "meta:updated": "2020-08-22T02:57:50.255490", "woe:hierarchy": {"continent": 24865672, "country": 23424977, "town": 0, "planet": 1, "county": 12590107, "suburb": 0, "state": 2347602, "region": 0, "localadmin": 0}, "woe:timezone_id": 56043661, "woe:hash": "9vk1qp19mt0j", "woe:centroid": [-95.359032, 29.789671], "geom:latitude": 29.789671, "geom:longitude": -95.359032, "geom:hash": "9vk1qp19mt0j", "woe:latitude": 29.789671, "geom:centroid": [-95.359032, 29.789671], "woe:longitude": -95.359032, "woe:repo": "woeplanet-poi-us"}, "geometry": {"coordinates": [-95.359032, 29.789671], "type": "Point"}}