{"type": "Feature", "id": 23559855, "geometry": {"type": "Point", "coordinates": [-87.803818, 41.788979]}, "properties": {"woe:id": 23559855, "woe:parent_id": 28751263, "woe:name": "St Joseph Elementary School", "woe:placetype": 20, "woe:placetype_name": "POI", "woe:lang": "ENG", "iso:country": "US", "meta:provider": ["geoplanet:7.3.1", "geoplanet:7.3.2", "geoplanet:7.4.0", "geoplanet:7.4.1", "geoplanet:7.5.1", "geoplanet:7.5.2", "geoplanet:7.6.0", "geoplanet:7.8.1", "geoplanet:7.9.0", "geoplanet:7.10.0", "geoplanet:8.0.0", "woeplanet:8.0.0"], "meta:indexed": "2020-08-20T20:18:31.696829", "woe:alias_ENG_V": ["St Joseph Elementary"], "meta:updated": "2020-10-14T11:20:27.334658", "woe:hierarchy": {"continent": 24865672, "country": 23424977, "town": 0, "planet": 1, "county": 12588093, "suburb": 0, "state": 2347572, "region": 0, "localadmin": 0}, "woe:timezone_id": 56043661, "woe:hash": "dp3t9zrnqwrc", "woe:centroid": [-87.803818, 41.788979], "geom:latitude": 41.788979, "geom:longitude": -87.803818, "geom:hash": "dp3t9zrnqwrc", "woe:latitude": 41.788979, "geom:centroid": [-87.803818, 41.788979], "woe:longitude": -87.803818, "woe:repo": "woeplanet-poi-us", "geom:area": 0.0, "woe:scale": 19}}