{"type": "Feature", "id": 23640610, "geometry": {"type": "Point", "coordinates": [-76.944077, 40.30035]}, "properties": {"woe:id": 23640610, "woe:parent_id": 2516982, "woe:name": "East Pennsboro Elementary School", "woe:placetype": 20, "woe:placetype_name": "POI", "woe:lang": "ENG", "iso:country": "US", "meta:provider": ["geoplanet:7.3.1", "geoplanet:7.3.2", "geoplanet:7.4.0", "geoplanet:7.4.1", "geoplanet:7.5.1", "geoplanet:7.5.2", "geoplanet:7.6.0", "geoplanet:7.8.1", "geoplanet:7.9.0", "geoplanet:7.10.0", "geoplanet:8.0.0", "woeplanet:8.0.0"], "meta:indexed": "2020-08-20T20:18:58.576984", "woe:alias_ENG_V": ["E Pennsboro Elementary School", "E Pennsboro Elementary", "East Pennsboro Elementary"], "meta:updated": "2020-10-14T11:19:31.139063", "woe:hierarchy": {"continent": 24865672, "country": 23424977, "town": 0, "planet": 1, "county": 12589748, "suburb": 0, "state": 2347597, "region": 0, "localadmin": 0}, "woe:timezone_id": 56043648, "woe:hash": "dr1m307n919z", "woe:centroid": [-76.944077, 40.30035], "geom:latitude": 40.30035, "geom:longitude": -76.944077, "geom:hash": "dr1m307n919z", "woe:latitude": 40.30035, "geom:centroid": [-76.944077, 40.30035], "woe:longitude": -76.944077, "woe:repo": "woeplanet-poi-us", "geom:area": 0.0, "woe:scale": 19}}