{"type": "Feature", "id": 23638279, "geometry": {"type": "Point", "coordinates": [-80.05442, 40.52446]}, "properties": {"woe:id": 23638279, "woe:parent_id": 22664127, "woe:name": "Highcliff Elementary School", "woe:placetype": 20, "woe:placetype_name": "POI", "woe:lang": "ENG", "iso:country": "US", "meta:provider": ["geoplanet:7.3.1", "geoplanet:7.3.2", "geoplanet:7.4.0", "geoplanet:7.4.1", "geoplanet:7.5.1", "geoplanet:7.5.2", "geoplanet:7.6.0", "geoplanet:7.8.1", "geoplanet:7.9.0", "geoplanet:7.10.0", "geoplanet:8.0.0", "woeplanet:8.0.0"], "meta:indexed": "2020-08-20T20:18:57.719204", "woe:alias_ENG_V": ["Highcliff Elementary"], "meta:updated": "2020-10-14T11:19:50.750874", "woe:hierarchy": {"continent": 24865672, "country": 23424977, "town": 0, "planet": 1, "county": 12589729, "suburb": 0, "state": 2347597, "region": 0, "localadmin": 0}, "woe:timezone_id": 56043648, "woe:hash": "dppnd360hfcg", "woe:centroid": [-80.05442, 40.52446], "geom:latitude": 40.52446, "geom:longitude": -80.05442, "geom:hash": "dppnd360hfcg", "woe:latitude": 40.52446, "geom:centroid": [-80.05442, 40.52446], "woe:longitude": -80.05442, "woe:repo": "woeplanet-poi-us", "geom:area": 0.0, "woe:scale": 19}}