{"type": "Feature", "id": 23632244, "properties": {"woe:id": 23632244, "woe:parent_id": 56022254, "woe:name": "Timken High School", "woe:placetype": 20, "woe:placetype_name": "POI", "woe:lang": "ENG", "iso:country": "US", "meta:provider": ["geoplanet:7.3.2", "geoplanet:7.4.0", "geoplanet:7.4.1", "geoplanet:7.5.1", "geoplanet:7.5.2", "geoplanet:7.6.0", "geoplanet:7.8.1", "geoplanet:7.9.0", "geoplanet:7.10.0", "geoplanet:8.0.0", "woeplanet:8.0.0"], "meta:indexed": "2020-08-20T22:02:43.824062", "woe:alias_ENG_V": ["Timken Senior High School", "Timken High", "Timken Senior High", "Timken HS", "Timken Senior HS"], "meta:updated": "2020-08-22T02:58:49.267142", "woe:hierarchy": {"continent": 24865672, "country": 23424977, "town": 0, "planet": 1, "county": 12589602, "suburb": 0, "state": 2347594, "region": 0, "localadmin": 0}, "woe:timezone_id": 56043648, "woe:hash": "dpq0h5mby196", "woe:centroid": [-81.378563, 40.79924], "geom:latitude": 40.79924, "geom:longitude": -81.378563, "geom:hash": "dpq0h5mby196", "woe:latitude": 40.79924, "geom:centroid": [-81.378563, 40.79924], "woe:longitude": -81.378563, "woe:repo": "woeplanet-poi-us"}, "geometry": {"coordinates": [-81.378563, 40.79924], "type": "Point"}}