{"type": "Feature", "id": 23616647, "geometry": {"type": "Point", "coordinates": [-73.623741, 40.642849]}, "properties": {"woe:id": 23616647, "woe:parent_id": 2358644, "woe:name": "School 3", "woe:placetype": 20, "woe:placetype_name": "POI", "woe:lang": "ENG", "iso:country": "US", "meta:provider": ["geoplanet:7.3.1", "geoplanet:7.3.2", "geoplanet:7.4.0", "geoplanet:7.4.1", "geoplanet:7.5.1", "geoplanet:7.5.2", "geoplanet:7.6.0", "geoplanet:7.8.1", "geoplanet:7.9.0", "geoplanet:7.10.0", "geoplanet:8.0.0", "woeplanet:8.0.0"], "meta:indexed": "2020-08-20T20:18:50.092463", "meta:updated": "2020-10-14T11:19:40.466306", "woe:hierarchy": {"continent": 24865672, "country": 23424977, "town": 0, "planet": 1, "county": 12589341, "suburb": 0, "state": 2347591, "region": 0, "localadmin": 0}, "woe:timezone_id": 56043648, "woe:hash": "dr5xhwucf2pv", "woe:centroid": [-73.623741, 40.642849], "geom:latitude": 40.642849, "geom:longitude": -73.623741, "geom:hash": "dr5xhwucf2pv", "woe:latitude": 40.642849, "geom:centroid": [-73.623741, 40.642849], "woe:longitude": -73.623741, "woe:repo": "woeplanet-poi-us", "geom:area": 0.0, "woe:scale": 19}}