{"type": "Feature", "id": 23586429, "properties": {"woe:id": 23586429, "woe:parent_id": 2489990, "woe:name": "Brookview School", "woe:placetype": 20, "woe:placetype_name": "POI", "woe:lang": "ENG", "iso:country": "US", "meta:provider": ["geoplanet:7.3.1", "geoplanet:7.3.2", "geoplanet:7.4.0", "geoplanet:7.4.1", "geoplanet:7.5.1", "geoplanet:7.5.2", "geoplanet:7.6.0", "geoplanet:7.8.1", "geoplanet:7.9.0", "geoplanet:7.10.0", "geoplanet:8.0.0", "woeplanet:8.0.0"], "meta:indexed": "2020-08-20T20:18:39.977015", "meta:updated": "2020-08-22T02:57:38.695668", "woe:hierarchy": {"continent": 24865672, "country": 23424977, "town": 0, "planet": 1, "county": 12588724, "suburb": 0, "state": 2347581, "region": 0, "localadmin": 0}, "woe:timezone_id": 56043658, "woe:hash": "dp6x2fpcd8mh", "woe:centroid": [-86.440659, 42.06691], "geom:latitude": 42.06691, "geom:longitude": -86.440659, "geom:hash": "dp6x2fpcd8mh", "woe:latitude": 42.06691, "geom:centroid": [-86.440659, 42.06691], "woe:longitude": -86.440659, "woe:repo": "woeplanet-poi-us"}, "geometry": {"coordinates": [-86.440659, 42.06691], "type": "Point"}}