{"type": "Feature", "id": 28718478, "geometry": {"type": "Point", "coordinates": [-83.047043, 35.595741]}, "properties": {"woe:id": 28718478, "woe:parent_id": 2502805, "woe:name": "Cataloochee Ski Area", "woe:placetype": 20, "woe:placetype_name": "POI", "woe:lang": "ENG", "iso:country": "US", "meta:provider": ["geoplanet:7.3.1", "geoplanet:7.3.2", "geoplanet:7.4.0", "geoplanet:7.4.1", "geoplanet:7.5.1", "geoplanet:7.5.2", "geoplanet:7.6.0", "geoplanet:7.8.1", "geoplanet:7.9.0", "geoplanet:7.10.0", "geoplanet:8.0.0", "woeplanet:8.0.0"], "meta:indexed": "2020-08-20T20:19:15.736887", "meta:updated": "2020-10-14T11:19:25.664384", "woe:hierarchy": {"continent": 24865672, "country": 23424977, "town": 0, "planet": 1, "county": 12589417, "suburb": 0, "state": 2347592, "region": 0, "localadmin": 0}, "woe:timezone_id": 56043648, "woe:hash": "dnkfw0nbpxh9", "woe:centroid": [-83.047043, 35.595741], "geom:latitude": 35.595741, "geom:longitude": -83.047043, "geom:hash": "dnkfw0nbpxh9", "woe:latitude": 35.595741, "geom:centroid": [-83.047043, 35.595741], "woe:longitude": -83.047043, "woe:repo": "woeplanet-poi-us", "geom:area": 0.0, "woe:scale": 19}}