{"type": "Feature", "id": 23668785, "geometry": {"type": "Point", "coordinates": [-122.321297, 47.61573]}, "properties": {"woe:id": 23668785, "woe:parent_id": 2369586, "woe:name": "Seattle Central Community College", "woe:placetype": 20, "woe:placetype_name": "POI", "woe:lang": "ENG", "iso:country": "US", "meta:provider": ["geoplanet:7.3.1", "geoplanet:7.3.2", "geoplanet:7.4.0", "geoplanet:7.4.1", "geoplanet:7.5.1", "geoplanet:7.5.2", "geoplanet:7.6.0", "geoplanet:7.8.1", "geoplanet:7.9.0", "geoplanet:7.10.0", "geoplanet:8.0.0", "woeplanet:8.0.0"], "meta:indexed": "2020-08-20T20:19:09.193901", "woe:alias_ENG_V": ["Seattlecentralcommunitycollege"], "meta:updated": "2020-10-14T11:19:35.356147", "woe:hierarchy": {"continent": 24865672, "country": 23424977, "town": 0, "planet": 1, "county": 12590456, "suburb": 0, "state": 2347606, "region": 0, "localadmin": 0}, "woe:timezone_id": 56043663, "woe:hash": "c23nbs0mepqj", "woe:centroid": [-122.321297, 47.61573], "geom:latitude": 47.61573, "geom:longitude": -122.321297, "geom:hash": "c23nbs0mepqj", "woe:latitude": 47.61573, "geom:centroid": [-122.321297, 47.61573], "woe:longitude": -122.321297, "woe:repo": "woeplanet-poi-us", "geom:area": 0.0, "woe:scale": 19}}