{"type": "Feature", "id": 23587637, "geometry": {"type": "Point", "coordinates": [-84.913132, 42.881802]}, "properties": {"woe:id": 23587637, "woe:parent_id": 2475673, "woe:name": "Westwood School", "woe:placetype": 20, "woe:placetype_name": "POI", "woe:lang": "ENG", "iso:country": "US", "meta:provider": ["geoplanet:7.3.2", "geoplanet:7.4.0", "geoplanet:7.4.1", "geoplanet:7.5.1", "geoplanet:7.5.2", "geoplanet:7.6.0", "geoplanet:7.8.1", "geoplanet:7.9.0", "geoplanet:7.10.0", "geoplanet:8.0.0", "woeplanet:8.0.0"], "meta:indexed": "2020-08-20T22:02:25.484347", "meta:updated": "2020-10-14T11:20:13.310206", "woe:hierarchy": {"continent": 24865672, "country": 23424977, "town": 0, "planet": 1, "county": 12588747, "suburb": 0, "state": 2347581, "region": 0, "localadmin": 0}, "woe:timezone_id": 56043658, "woe:hash": "dpeegy2hse78", "woe:centroid": [-84.913132, 42.881802], "geom:latitude": 42.881802, "geom:longitude": -84.913132, "geom:hash": "dpeegy2hse78", "woe:latitude": 42.881802, "geom:centroid": [-84.913132, 42.881802], "woe:longitude": -84.913132, "woe:repo": "woeplanet-poi-us", "geom:area": 0.0, "woe:scale": 19}}