{"type": "Feature", "id": 23651845, "geometry": {"type": "Point", "coordinates": [-90.092087, 35.02636]}, "properties": {"woe:id": 23651845, "woe:parent_id": 2519680, "woe:name": "Westwood High School", "woe:placetype": 20, "woe:placetype_name": "POI", "woe:lang": "ENG", "iso:country": "US", "meta:provider": ["geoplanet:7.3.1", "geoplanet:7.3.2", "geoplanet:7.4.0", "geoplanet:7.4.1", "geoplanet:7.5.1", "geoplanet:7.5.2", "geoplanet:7.6.0", "geoplanet:7.8.1", "geoplanet:7.9.0", "geoplanet:7.10.0", "geoplanet:8.0.0", "woeplanet:8.0.0"], "meta:indexed": "2020-08-20T20:19:02.215505", "woe:alias_ENG_V": ["Westwood Senior High School", "Westwood High", "Westwood Senior High", "Westwood HS", "Westwood Senior HS"], "meta:updated": "2020-10-14T11:19:45.639334", "woe:hierarchy": {"continent": 24865672, "country": 23424977, "town": 0, "planet": 1, "county": 12589990, "suburb": 0, "state": 2347601, "region": 0, "localadmin": 0}, "woe:timezone_id": 56043661, "woe:hash": "9ypzmbkgq4wz", "woe:centroid": [-90.092087, 35.02636], "geom:latitude": 35.02636, "geom:longitude": -90.092087, "geom:hash": "9ypzmbkgq4wz", "woe:latitude": 35.02636, "geom:centroid": [-90.092087, 35.02636], "woe:longitude": -90.092087, "woe:repo": "woeplanet-poi-us", "geom:area": 0.0, "woe:scale": 19}}