{"type": "Feature", "id": 23648757, "geometry": {"type": "Point", "coordinates": [-96.598686, 44.048981]}, "properties": {"woe:id": 23648757, "woe:parent_id": 2404082, "woe:name": "Spafford Elementary School", "woe:placetype": 20, "woe:placetype_name": "POI", "woe:lang": "ENG", "iso:country": "US", "meta:provider": ["geoplanet:7.3.1", "geoplanet:7.3.2", "geoplanet:7.4.0", "geoplanet:7.4.1", "geoplanet:7.5.1", "geoplanet:7.5.2", "geoplanet:7.6.0", "geoplanet:7.8.1", "geoplanet:7.9.0", "geoplanet:7.10.0", "geoplanet:8.0.0", "woeplanet:8.0.0"], "meta:indexed": "2020-08-20T20:19:01.323712", "woe:alias_ENG_V": ["Spafford Elementary"], "meta:updated": "2020-10-14T11:19:41.929888", "woe:hierarchy": {"continent": 24865672, "country": 23424977, "town": 0, "planet": 1, "county": 12589895, "suburb": 0, "state": 2347600, "region": 0, "localadmin": 0}, "woe:timezone_id": 56043661, "woe:hash": "9zg69ffgzmpn", "woe:centroid": [-96.598686, 44.048981], "geom:latitude": 44.048981, "geom:longitude": -96.598686, "geom:hash": "9zg69ffgzmpn", "woe:latitude": 44.048981, "geom:centroid": [-96.598686, 44.048981], "woe:longitude": -96.598686, "woe:repo": "woeplanet-poi-us", "geom:area": 0.0, "woe:scale": 19}}