{"type": "Feature", "id": 23593597, "geometry": {"type": "Point", "coordinates": [-93.378616, 44.949371]}, "properties": {"woe:id": 23593597, "woe:parent_id": 2487020, "woe:name": "Timothy Lutheran School", "woe:placetype": 20, "woe:placetype_name": "POI", "woe:lang": "ENG", "iso:country": "US", "meta:provider": ["geoplanet:7.3.2", "geoplanet:7.4.0", "geoplanet:7.4.1", "geoplanet:7.5.1", "geoplanet:7.5.2", "geoplanet:7.6.0", "geoplanet:7.8.1", "geoplanet:7.9.0", "geoplanet:7.10.0", "geoplanet:8.0.0", "woeplanet:8.0.0"], "meta:indexed": "2020-08-20T22:02:28.370616", "meta:updated": "2020-10-14T11:20:23.567328", "woe:alias_ENG_V": ["Timothy Ltheran Ch School-Wels"], "woe:hierarchy": {"continent": 24865672, "country": 23424977, "town": 0, "planet": 1, "county": 12588823, "suburb": 0, "state": 2347582, "region": 0, "localadmin": 0}, "woe:timezone_id": 56043661, "woe:hash": "9zvxengc0d16", "woe:centroid": [-93.378616, 44.949371], "geom:latitude": 44.949371, "geom:longitude": -93.378616, "geom:hash": "9zvxengc0d16", "woe:latitude": 44.949371, "geom:centroid": [-93.378616, 44.949371], "woe:longitude": -93.378616, "woe:repo": "woeplanet-poi-us", "geom:area": 0.0, "woe:scale": 19}}