{"type": "Feature", "id": 23648220, "properties": {"woe:id": 23648220, "woe:parent_id": 2489923, "woe:name": "Scotland High School", "woe:placetype": 20, "woe:placetype_name": "POI", "woe:lang": "ENG", "iso:country": "US", "meta:provider": ["geoplanet:7.3.1", "geoplanet:7.3.2", "geoplanet:7.4.0", "geoplanet:7.4.1", "geoplanet:7.5.1", "geoplanet:7.5.2", "geoplanet:7.6.0", "geoplanet:7.8.1", "geoplanet:7.9.0", "geoplanet:7.10.0", "geoplanet:8.0.0", "woeplanet:8.0.0"], "meta:indexed": "2020-08-20T20:19:01.048397", "woe:alias_ENG_V": ["Scotland Senior High School", "Scotland High", "Scotland Senior High", "Scotland HS", "Scotland Senior HS"], "meta:updated": "2020-08-22T02:58:49.618533", "woe:hierarchy": {"continent": 24865672, "country": 23424977, "town": 0, "planet": 1, "county": 12589849, "suburb": 0, "state": 2347600, "region": 0, "localadmin": 0}, "woe:timezone_id": 56043661, "woe:hash": "9zdt2qvjh2n9", "woe:centroid": [-97.716331, 43.148289], "geom:latitude": 43.148289, "geom:longitude": -97.716331, "geom:hash": "9zdt2qvjh2n9", "woe:latitude": 43.148289, "geom:centroid": [-97.716331, 43.148289], "woe:longitude": -97.716331, "woe:repo": "woeplanet-poi-us"}, "geometry": {"coordinates": [-97.716331, 43.148289], "type": "Point"}}