{"type": "Feature", "id": 23646895, "geometry": {"type": "Point", "coordinates": [-79.373238, 34.42012]}, "properties": {"woe:id": 23646895, "woe:parent_id": 2392110, "woe:name": "J. V. Martin Junior High School", "woe:placetype": 20, "woe:placetype_name": "POI", "woe:lang": "ENG", "iso:country": "US", "meta:provider": ["geoplanet:7.3.1", "geoplanet:7.3.2", "geoplanet:7.4.0", "geoplanet:7.4.1", "geoplanet:7.5.1", "geoplanet:7.5.2", "geoplanet:7.6.0", "geoplanet:7.8.1", "geoplanet:7.9.0", "geoplanet:7.10.0", "geoplanet:8.0.0", "woeplanet:8.0.0"], "meta:indexed": "2020-08-20T20:19:00.636388", "woe:alias_ENG_V": ["J. V. Martin Junior High"], "meta:updated": "2020-10-14T11:19:53.183575", "woe:hierarchy": {"continent": 24865672, "country": 23424977, "town": 0, "planet": 1, "county": 12589816, "suburb": 0, "state": 2347599, "region": 0, "localadmin": 0}, "woe:timezone_id": 56043648, "woe:hash": "dnpeccfptx2j", "woe:centroid": [-79.373238, 34.42012], "geom:latitude": 34.42012, "geom:longitude": -79.373238, "geom:hash": "dnpeccfptx2j", "woe:latitude": 34.42012, "geom:centroid": [-79.373238, 34.42012], "woe:longitude": -79.373238, "woe:repo": "woeplanet-poi-us", "geom:area": 0.0, "woe:scale": 19}}