{"type": "Feature", "id": 23567008, "properties": {"woe:id": 23567008, "woe:parent_id": 2361179, "woe:name": "Parkview Intermediate School", "woe:placetype": 20, "woe:placetype_name": "POI", "woe:lang": "ENG", "iso:country": "US", "meta:provider": ["geoplanet:7.3.1", "geoplanet:7.3.2", "geoplanet:7.4.0", "geoplanet:7.4.1", "geoplanet:7.5.1", "geoplanet:7.5.2", "geoplanet:7.6.0", "geoplanet:7.8.1", "geoplanet:7.9.0", "geoplanet:7.10.0", "geoplanet:8.0.0", "woeplanet:8.0.0"], "meta:indexed": "2020-08-20T20:18:34.260962", "meta:updated": "2020-08-22T02:57:35.746792", "woe:hierarchy": {"continent": 24865672, "country": 23424977, "town": 0, "planet": 1, "county": 12588226, "suburb": 0, "state": 2347573, "region": 0, "localadmin": 0}, "woe:timezone_id": 56043656, "woe:hash": "dnfmpdkjuc9y", "woe:centroid": [-86.500648, 38.861012], "geom:latitude": 38.861012, "geom:longitude": -86.500648, "geom:hash": "dnfmpdkjuc9y", "woe:latitude": 38.861012, "geom:centroid": [-86.500648, 38.861012], "woe:longitude": -86.500648, "woe:repo": "woeplanet-poi-us"}, "geometry": {"coordinates": [-86.500648, 38.861012], "type": "Point"}}