{"type": "Feature", "id": 23660674, "properties": {"woe:id": 23660674, "woe:parent_id": 28340436, "woe:name": "Crossley Elementary School", "woe:placetype": 20, "woe:placetype_name": "POI", "woe:lang": "ENG", "iso:country": "US", "meta:provider": ["geoplanet:7.3.1", "geoplanet:7.3.2", "geoplanet:7.4.0", "geoplanet:7.4.1", "geoplanet:7.5.1", "geoplanet:7.5.2", "geoplanet:7.6.0", "geoplanet:7.8.1", "geoplanet:7.9.0", "geoplanet:7.10.0", "geoplanet:8.0.0", "woeplanet:8.0.0"], "meta:indexed": "2020-08-20T20:19:06.562950", "woe:alias_ENG_V": ["Crossley Elementary"], "meta:updated": "2020-08-22T02:57:50.556940", "woe:hierarchy": {"continent": 24865672, "country": 23424977, "town": 0, "planet": 1, "county": 12590184, "suburb": 0, "state": 2347602, "region": 0, "localadmin": 0}, "woe:timezone_id": 56043661, "woe:hash": "9ufwphzgxb42", "woe:centroid": [-97.415779, 27.800131], "geom:latitude": 27.800131, "geom:longitude": -97.415779, "geom:hash": "9ufwphzgxb42", "woe:latitude": 27.800131, "geom:centroid": [-97.415779, 27.800131], "woe:longitude": -97.415779, "woe:repo": "woeplanet-poi-us"}, "geometry": {"coordinates": [-97.415779, 27.800131], "type": "Point"}}