{"type": "Feature", "id": 23516416, "geometry": {"type": "Point", "coordinates": [-111.876411, 33.324261]}, "properties": {"woe:id": 23516416, "woe:parent_id": 2378015, "woe:name": "Seton Catholic High School", "woe:placetype": 20, "woe:placetype_name": "POI", "woe:lang": "ENG", "iso:country": "US", "meta:provider": ["geoplanet:7.3.1", "geoplanet:7.3.2", "geoplanet:7.4.0", "geoplanet:7.4.1", "geoplanet:7.5.1", "geoplanet:7.5.2", "geoplanet:7.6.0", "geoplanet:7.8.1", "geoplanet:7.9.0", "geoplanet:7.10.0", "geoplanet:8.0.0", "woeplanet:8.0.0"], "meta:indexed": "2020-08-20T20:18:18.430185", "woe:alias_ENG_V": ["Seton Catholic Senior High School", "Seton Catholic High", "Seton Catholic Senior High", "Seton Catholic HS", "Seton Catholic Senior HS"], "meta:updated": "2020-10-14T11:20:29.374606", "woe:hierarchy": {"continent": 24865672, "country": 23424977, "town": 0, "planet": 1, "county": 12587587, "suburb": 0, "state": 2347561, "region": 0, "localadmin": 0}, "woe:timezone_id": 56043666, "woe:hash": "9tbmw4qpfsmx", "woe:centroid": [-111.876411, 33.324261], "geom:latitude": 33.324261, "geom:longitude": -111.876411, "geom:hash": "9tbmw4qpfsmx", "woe:latitude": 33.324261, "geom:centroid": [-111.876411, 33.324261], "woe:longitude": -111.876411, "woe:repo": "woeplanet-poi-us", "geom:area": 0.0, "woe:scale": 19}}