{"type": "Feature", "id": 56204409, "geometry": {"type": "Point", "coordinates": [-73.980682, 40.635448]}, "properties": {"woe:id": 56204409, "woe:parent_id": 2367028, "woe:name": "Living Torah Museum", "woe:placetype": 20, "woe:placetype_name": "POI", "woe:lang": "ENG", "iso:country": "US", "meta:provider": ["geoplanet:7.6.0", "geoplanet:7.8.1", "geoplanet:7.9.0", "geoplanet:7.10.0", "geoplanet:8.0.0", "woeplanet:8.0.0"], "meta:indexed": "2020-08-21T08:24:23.972208", "meta:updated": "2020-10-14T11:20:01.282617", "woe:hierarchy": {"continent": 24865672, "country": 23424977, "town": 0, "planet": 1, "county": 12589335, "suburb": 0, "state": 2347591, "region": 0, "localadmin": 0}, "woe:timezone_id": 56043648, "woe:hash": "dr5rht2ytht3", "woe:centroid": [-73.980682, 40.635448], "geom:latitude": 40.635448, "geom:longitude": -73.980682, "geom:hash": "dr5rht2ytht3", "woe:latitude": 40.635448, "geom:centroid": [-73.980682, 40.635448], "woe:longitude": -73.980682, "woe:repo": "woeplanet-poi-us", "geom:area": 0.0, "woe:scale": 19}}