{"type": "Feature", "id": 23597661, "geometry": {"type": "Point", "coordinates": [-94.521523, 40.055328]}, "properties": {"woe:id": 23597661, "woe:parent_id": 2432499, "woe:name": "King City Elementary School", "woe:placetype": 20, "woe:placetype_name": "POI", "woe:lang": "ENG", "iso:country": "US", "meta:provider": ["geoplanet:7.3.1", "geoplanet:7.3.2", "geoplanet:7.4.0", "geoplanet:7.4.1", "geoplanet:7.5.1", "geoplanet:7.5.2", "geoplanet:7.6.0", "geoplanet:7.8.1", "geoplanet:7.9.0", "geoplanet:7.10.0", "geoplanet:8.0.0", "woeplanet:8.0.0"], "meta:indexed": "2020-08-20T20:18:43.959530", "woe:alias_ENG_V": ["King City Elementary"], "meta:updated": "2020-10-14T11:20:22.263225", "woe:hierarchy": {"continent": 24865672, "country": 23424977, "town": 0, "planet": 1, "county": 12589003, "suburb": 0, "state": 2347584, "region": 0, "localadmin": 0}, "woe:timezone_id": 56043661, "woe:hash": "9zhgc5ge0yk4", "woe:centroid": [-94.521523, 40.055328], "geom:latitude": 40.055328, "geom:longitude": -94.521523, "geom:hash": "9zhgc5ge0yk4", "woe:latitude": 40.055328, "geom:centroid": [-94.521523, 40.055328], "woe:longitude": -94.521523, "woe:repo": "woeplanet-poi-us", "geom:area": 0.0, "woe:scale": 19}}