{"type": "Feature", "id": 23676198, "properties": {"woe:id": 23676198, "woe:parent_id": 2519867, "woe:name": "Whitewater High School", "woe:placetype": 20, "woe:placetype_name": "POI", "woe:lang": "ENG", "iso:country": "US", "meta:provider": ["geoplanet:7.3.1", "geoplanet:7.3.2", "geoplanet:7.4.0", "geoplanet:7.4.1", "geoplanet:7.5.1", "geoplanet:7.5.2", "geoplanet:7.6.0", "geoplanet:7.8.1", "geoplanet:7.9.0", "geoplanet:7.10.0", "geoplanet:8.0.0", "woeplanet:8.0.0"], "meta:indexed": "2020-08-20T20:19:11.890928", "woe:alias_ENG_V": ["Whitewater Senior High School", "Whitewater High", "Whitewater Senior High", "Whitewater HS", "Whitewater Senior HS"], "meta:updated": "2020-08-22T02:58:50.551298", "woe:hierarchy": {"continent": 24865672, "country": 23424977, "town": 0, "planet": 1, "county": 12590598, "suburb": 0, "state": 2347608, "region": 0, "localadmin": 0}, "woe:timezone_id": 56043661, "woe:hash": "dp8gskeuz5er", "woe:centroid": [-88.75309, 42.828289], "geom:latitude": 42.828289, "geom:longitude": -88.75309, "geom:hash": "dp8gskeuz5er", "woe:latitude": 42.828289, "geom:centroid": [-88.75309, 42.828289], "woe:longitude": -88.75309, "woe:repo": "woeplanet-poi-us"}, "geometry": {"coordinates": [-88.75309, 42.828289], "type": "Point"}}