{"type": "Feature", "id": 23528615, "geometry": {"type": "Point", "coordinates": [-119.243019, 36.298988]}, "properties": {"woe:id": 23528615, "woe:parent_id": 2479188, "woe:name": "Union Elementary School", "woe:placetype": 20, "woe:placetype_name": "POI", "woe:lang": "ENG", "iso:country": "US", "meta:provider": ["geoplanet:7.3.2", "geoplanet:7.4.0", "geoplanet:7.4.1", "geoplanet:7.5.1", "geoplanet:7.5.2", "geoplanet:7.6.0", "geoplanet:7.8.1", "geoplanet:7.9.0", "geoplanet:7.10.0", "geoplanet:8.0.0", "woeplanet:8.0.0"], "meta:indexed": "2020-08-20T22:02:01.162257", "woe:alias_ENG_V": ["Union Elementary"], "meta:updated": "2020-10-14T11:20:03.532013", "woe:hierarchy": {"continent": 24865672, "country": 23424977, "town": 0, "planet": 1, "county": 12587723, "suburb": 0, "state": 2347563, "region": 0, "localadmin": 0}, "woe:timezone_id": 56043663, "woe:hash": "9q7nw81bumb9", "woe:centroid": [-119.243019, 36.298988], "geom:latitude": 36.298988, "geom:longitude": -119.243019, "geom:hash": "9q7nw81bumb9", "woe:latitude": 36.298988, "geom:centroid": [-119.243019, 36.298988], "woe:longitude": -119.243019, "woe:repo": "woeplanet-poi-us", "geom:area": 0.0, "woe:scale": 19}}