{"type": "Feature", "id": 24866082, "properties": {"woe:id": 24866082, "woe:parent_id": 2366438, "woe:name": "Southwest Baptist University", "woe:placetype": 20, "woe:placetype_name": "POI", "woe:lang": "ENG", "iso:country": "US", "meta:provider": ["geoplanet:7.3.2", "geoplanet:7.4.0", "geoplanet:7.4.1", "geoplanet:7.5.1", "geoplanet:7.5.2", "geoplanet:7.6.0", "geoplanet:7.8.1", "geoplanet:7.9.0", "geoplanet:7.10.0", "geoplanet:8.0.0", "woeplanet:8.0.0"], "meta:indexed": "2020-08-20T22:03:06.025617", "woe:alias_ENG_V": ["SW Baptist University"], "meta:updated": "2020-08-22T02:58:19.657903", "woe:hierarchy": {"continent": 24865672, "country": 23424977, "town": 0, "planet": 1, "county": 12589049, "suburb": 0, "state": 2347584, "region": 0, "localadmin": 0}, "woe:timezone_id": 56043661, "woe:hash": "9yttfkwnv5tn", "woe:centroid": [-93.408287, 37.59914], "geom:latitude": 37.59914, "geom:longitude": -93.408287, "geom:hash": "9yttfkwnv5tn", "woe:latitude": 37.59914, "geom:centroid": [-93.408287, 37.59914], "woe:longitude": -93.408287, "woe:repo": "woeplanet-poi-us"}, "geometry": {"coordinates": [-93.408287, 37.59914], "type": "Point"}}