{"type": "Feature", "id": 23641252, "geometry": {"type": "Point", "coordinates": [-80.139923, 42.083752]}, "properties": {"woe:id": 23641252, "woe:parent_id": 28744582, "woe:name": "Word of God Academy", "woe:placetype": 20, "woe:placetype_name": "POI", "woe:lang": "ENG", "iso:country": "US", "meta:provider": ["geoplanet:7.3.2", "geoplanet:7.4.0", "geoplanet:7.4.1", "geoplanet:7.5.1", "geoplanet:7.5.2", "geoplanet:7.6.0", "geoplanet:7.8.1", "geoplanet:7.9.0", "geoplanet:7.10.0", "geoplanet:8.0.0", "woeplanet:8.0.0"], "meta:indexed": "2020-08-20T22:02:47.616989", "meta:updated": "2020-10-14T11:19:48.792584", "woe:hierarchy": {"continent": 24865672, "country": 23424977, "town": 0, "planet": 1, "county": 12589752, "suburb": 0, "state": 2347597, "region": 0, "localadmin": 0}, "woe:timezone_id": 56043648, "woe:hash": "dprp2m5gs7yr", "woe:centroid": [-80.139923, 42.083752], "geom:latitude": 42.083752, "geom:longitude": -80.139923, "geom:hash": "dprp2m5gs7yr", "woe:latitude": 42.083752, "geom:centroid": [-80.139923, 42.083752], "woe:longitude": -80.139923, "woe:repo": "woeplanet-poi-us", "geom:area": 0.0, "woe:scale": 19}}