{"type": "Feature", "id": 23563076, "geometry": {"type": "Point", "coordinates": [-88.248962, 42.350479]}, "properties": {"woe:id": 23563076, "woe:parent_id": 2396653, "woe:name": "Hilltop Elementary School", "woe:placetype": 20, "woe:placetype_name": "POI", "woe:lang": "ENG", "iso:country": "US", "meta:provider": ["geoplanet:7.3.1", "geoplanet:7.3.2", "geoplanet:7.4.0", "geoplanet:7.4.1", "geoplanet:7.5.1", "geoplanet:7.5.2", "geoplanet:7.6.0", "geoplanet:7.8.1", "geoplanet:7.9.0", "geoplanet:7.10.0", "geoplanet:8.0.0", "woeplanet:8.0.0"], "meta:indexed": "2020-08-20T20:18:32.703597", "woe:alias_ENG_V": ["Hilltop Elementary"], "meta:updated": "2020-10-14T11:20:27.853670", "woe:hierarchy": {"continent": 24865672, "country": 23424977, "town": 0, "planet": 1, "county": 12588140, "suburb": 0, "state": 2347572, "region": 0, "localadmin": 0}, "woe:timezone_id": 56043661, "woe:hash": "dp90zvej6jkx", "woe:centroid": [-88.248962, 42.350479], "geom:latitude": 42.350479, "geom:longitude": -88.248962, "geom:hash": "dp90zvej6jkx", "woe:latitude": 42.350479, "geom:centroid": [-88.248962, 42.350479], "woe:longitude": -88.248962, "woe:repo": "woeplanet-poi-us", "geom:area": 0.0, "woe:scale": 19}}