{"type": "Feature", "id": 23522625, "geometry": {"type": "Point", "coordinates": [-122.564697, 38.097221]}, "properties": {"woe:id": 23522625, "woe:parent_id": 55970183, "woe:name": "North Bay Christian Academy", "woe:placetype": 20, "woe:placetype_name": "POI", "woe:lang": "ENG", "iso:country": "US", "meta:provider": ["geoplanet:7.3.1", "geoplanet:7.3.2", "geoplanet:7.4.0", "geoplanet:7.4.1", "geoplanet:7.5.1", "geoplanet:7.5.2", "geoplanet:7.6.0", "geoplanet:7.8.1", "geoplanet:7.9.0", "geoplanet:7.10.0", "geoplanet:8.0.0", "woeplanet:8.0.0"], "meta:indexed": "2020-08-20T20:18:20.002309", "woe:alias_ENG_V": ["N Bay Christian Academy"], "meta:updated": "2020-10-14T11:20:18.152521", "woe:hierarchy": {"continent": 24865672, "country": 23424977, "town": 0, "planet": 1, "county": 12587690, "suburb": 0, "state": 2347563, "region": 0, "localadmin": 0}, "woe:timezone_id": 56043663, "woe:hash": "9qbbdzrh7s9z", "woe:centroid": [-122.564697, 38.097221], "geom:latitude": 38.097221, "geom:longitude": -122.564697, "geom:hash": "9qbbdzrh7s9z", "woe:latitude": 38.097221, "geom:centroid": [-122.564697, 38.097221], "woe:longitude": -122.564697, "woe:repo": "woeplanet-poi-us", "geom:area": 0.0, "woe:scale": 19}}