{"type": "Feature", "id": 23655099, "geometry": {"type": "Point", "coordinates": [-96.14473, 32.355202]}, "properties": {"woe:id": 23655099, "woe:parent_id": 2415667, "woe:name": "Lakeview Elementary School", "woe:placetype": 20, "woe:placetype_name": "POI", "woe:lang": "ENG", "iso:country": "US", "meta:provider": ["geoplanet:7.3.1", "geoplanet:7.3.2", "geoplanet:7.4.0", "geoplanet:7.4.1", "geoplanet:7.5.1", "geoplanet:7.5.2", "geoplanet:7.6.0", "geoplanet:7.8.1", "geoplanet:7.9.0", "geoplanet:7.10.0", "geoplanet:8.0.0", "woeplanet:8.0.0"], "meta:indexed": "2020-08-20T20:19:03.705915", "woe:alias_ENG_V": ["Lakeview Elementary"], "meta:updated": "2020-10-14T11:19:50.674070", "woe:hierarchy": {"continent": 24865672, "country": 23424977, "town": 0, "planet": 1, "county": 12590113, "suburb": 0, "state": 2347602, "region": 0, "localadmin": 0}, "woe:timezone_id": 56043661, "woe:hash": "9vg8h4jd9qv1", "woe:centroid": [-96.14473, 32.355202], "geom:latitude": 32.355202, "geom:longitude": -96.14473, "geom:hash": "9vg8h4jd9qv1", "woe:latitude": 32.355202, "geom:centroid": [-96.14473, 32.355202], "woe:longitude": -96.14473, "woe:repo": "woeplanet-poi-us", "geom:area": 0.0, "woe:scale": 19}}