{"type": "Feature", "id": 23599181, "properties": {"woe:id": 23599181, "woe:parent_id": 2401244, "woe:name": "Fair Play Elementary School", "woe:placetype": 20, "woe:placetype_name": "POI", "woe:lang": "ENG", "iso:country": "US", "meta:provider": ["geoplanet:7.3.1", "geoplanet:7.3.2", "geoplanet:7.4.0", "geoplanet:7.4.1", "geoplanet:7.5.1", "geoplanet:7.5.2", "geoplanet:7.6.0", "geoplanet:7.8.1", "geoplanet:7.9.0", "geoplanet:7.10.0", "geoplanet:8.0.0", "woeplanet:8.0.0"], "meta:indexed": "2020-08-20T20:18:44.534327", "woe:alias_ENG_V": ["Fair Play Elementary"], "meta:updated": "2020-08-22T02:57:40.909569", "woe:hierarchy": {"continent": 24865672, "country": 23424977, "town": 0, "planet": 1, "county": 12589049, "suburb": 0, "state": 2347584, "region": 0, "localadmin": 0}, "woe:timezone_id": 56043661, "woe:hash": "9ytqne5f37md", "woe:centroid": [-93.576332, 37.634071], "geom:latitude": 37.634071, "geom:longitude": -93.576332, "geom:hash": "9ytqne5f37md", "woe:latitude": 37.634071, "geom:centroid": [-93.576332, 37.634071], "woe:longitude": -93.576332, "woe:repo": "woeplanet-poi-us"}, "geometry": {"coordinates": [-93.576332, 37.634071], "type": "Point"}}