{"type": "Feature", "id": 23682933, "properties": {"woe:id": 23682933, "woe:parent_id": 28751351, "woe:name": "Aqueduct-North Conduit Avenue Station", "woe:placetype": 20, "woe:placetype_name": "POI", "woe:lang": "ENG", "iso:country": "US", "meta:provider": ["geoplanet:7.3.1", "geoplanet:7.3.2", "geoplanet:7.4.0", "geoplanet:7.4.1", "geoplanet:7.5.1", "geoplanet:7.5.2", "geoplanet:7.6.0", "geoplanet:7.8.1", "geoplanet:7.9.0", "geoplanet:7.10.0", "geoplanet:8.0.0", "woeplanet:8.0.0"], "meta:indexed": "2020-08-20T20:19:19.995694", "woe:alias_ENG_V": ["Mta-Aqueduct-N Conduit Ave", "Aqueduct-North Conduit Avenue Subway Station", "Subway-Aqueduct/n Conduit Ave-A"], "meta:updated": "2020-08-22T02:58:22.559343", "woe:hierarchy": {"continent": 24865672, "country": 23424977, "town": 0, "planet": 1, "county": 12589352, "suburb": 0, "state": 2347591, "region": 0, "localadmin": 0}, "woe:timezone_id": 56043648, "woe:hash": "dr5rrg5r4q3z", "woe:centroid": [-73.834549, 40.66713], "geom:latitude": 40.66713, "geom:longitude": -73.834549, "geom:hash": "dr5rrg5r4q3z", "woe:latitude": 40.66713, "geom:centroid": [-73.834549, 40.66713], "woe:longitude": -73.834549, "woe:repo": "woeplanet-poi-us"}, "geometry": {"coordinates": [-73.834549, 40.66713], "type": "Point"}}