{"type": "Feature", "id": 23673805, "geometry": {"type": "Point", "coordinates": [-87.361153, 44.835449]}, "properties": {"woe:id": 23673805, "woe:parent_id": 2501123, "woe:name": "Walker Middle School", "woe:placetype": 20, "woe:placetype_name": "POI", "woe:lang": "ENG", "iso:country": "US", "meta:provider": ["geoplanet:7.3.1", "geoplanet:7.3.2", "geoplanet:7.4.0", "geoplanet:7.4.1", "geoplanet:7.5.1", "geoplanet:7.5.2", "geoplanet:7.6.0", "geoplanet:7.8.1", "geoplanet:7.9.0", "geoplanet:7.10.0", "geoplanet:8.0.0", "woeplanet:8.0.0"], "meta:indexed": "2020-08-20T20:19:10.693158", "meta:updated": "2020-10-14T11:19:39.346383", "woe:hierarchy": {"continent": 24865672, "country": 23424977, "town": 0, "planet": 1, "county": 12590548, "suburb": 0, "state": 2347608, "region": 0, "localadmin": 0}, "woe:timezone_id": 56043661, "woe:hash": "dpczh4193t6z", "woe:centroid": [-87.361153, 44.835449], "geom:latitude": 44.835449, "geom:longitude": -87.361153, "geom:hash": "dpczh4193t6z", "woe:latitude": 44.835449, "geom:centroid": [-87.361153, 44.835449], "woe:longitude": -87.361153, "woe:repo": "woeplanet-poi-us", "geom:area": 0.0, "woe:scale": 19}}