{"type": "Feature", "id": 23675655, "properties": {"woe:id": 23675655, "woe:parent_id": 2478038, "woe:name": "Winslow Elementary School", "woe:placetype": 20, "woe:placetype_name": "POI", "woe:lang": "ENG", "iso:country": "US", "meta:provider": ["geoplanet:7.3.1", "geoplanet:7.3.2", "geoplanet:7.4.0", "geoplanet:7.4.1", "geoplanet:7.5.1", "geoplanet:7.5.2", "geoplanet:7.6.0", "geoplanet:7.8.1", "geoplanet:7.9.0", "geoplanet:7.10.0", "geoplanet:8.0.0", "woeplanet:8.0.0"], "meta:indexed": "2020-08-20T20:19:11.615914", "woe:alias_ENG_V": ["Winslow Elementary"], "meta:updated": "2020-08-22T02:58:18.182034", "woe:hierarchy": {"continent": 24865672, "country": 23424977, "town": 0, "planet": 1, "county": 12590585, "suburb": 0, "state": 2347608, "region": 0, "localadmin": 0}, "woe:timezone_id": 56043661, "woe:hash": "dp9e42k6ndpv", "woe:centroid": [-87.785622, 42.716572], "geom:latitude": 42.716572, "geom:longitude": -87.785622, "geom:hash": "dp9e42k6ndpv", "woe:latitude": 42.716572, "geom:centroid": [-87.785622, 42.716572], "woe:longitude": -87.785622, "woe:repo": "woeplanet-poi-us"}, "geometry": {"coordinates": [-87.785622, 42.716572], "type": "Point"}}