{"type": "Feature", "id": 23679501, "geometry": {"type": "Point", "coordinates": [-122.458061, 37.797501]}, "properties": {"woe:id": 23679501, "woe:parent_id": 23512069, "woe:name": "Presidio Officers Club", "woe:placetype": 20, "woe:placetype_name": "POI", "woe:lang": "ENG", "iso:country": "US", "meta:provider": ["geoplanet:7.3.1", "geoplanet:7.3.2", "geoplanet:7.4.0", "geoplanet:7.4.1", "geoplanet:7.5.1", "geoplanet:7.5.2", "geoplanet:7.6.0", "geoplanet:7.8.1", "geoplanet:7.9.0", "geoplanet:7.10.0", "geoplanet:8.0.0", "woeplanet:8.0.0"], "meta:indexed": "2020-08-20T20:19:12.467721", "meta:updated": "2020-10-14T11:19:49.050868", "woe:hierarchy": {"continent": 24865672, "country": 23424977, "town": 0, "planet": 1, "county": 12587707, "suburb": 0, "state": 2347563, "region": 0, "localadmin": 0}, "woe:timezone_id": 56043663, "woe:hash": "9q8zj2uf2kge", "woe:centroid": [-122.458061, 37.797501], "geom:latitude": 37.797501, "geom:longitude": -122.458061, "geom:hash": "9q8zj2uf2kge", "woe:latitude": 37.797501, "geom:centroid": [-122.458061, 37.797501], "woe:longitude": -122.458061, "woe:repo": "woeplanet-poi-us", "geom:area": 0.0, "woe:scale": 19}}