{"type": "Feature", "id": 23626171, "geometry": {"type": "Point", "coordinates": [-81.125092, 36.24247]}, "properties": {"woe:id": 23626171, "woe:parent_id": 2419118, "woe:name": "Mountain View Elementary School", "woe:placetype": 20, "woe:placetype_name": "POI", "woe:lang": "ENG", "iso:country": "US", "meta:provider": ["geoplanet:7.3.2", "geoplanet:7.4.0", "geoplanet:7.4.1", "geoplanet:7.5.1", "geoplanet:7.5.2", "geoplanet:7.6.0", "geoplanet:7.8.1", "geoplanet:7.9.0", "geoplanet:7.10.0", "geoplanet:8.0.0", "woeplanet:8.0.0"], "meta:indexed": "2020-08-20T22:02:40.769553", "woe:alias_ENG_V": ["Mtn View Elementary School", "Mtn View Elementary", "Mountain View Elementary"], "meta:updated": "2020-10-14T11:19:35.758037", "woe:hierarchy": {"continent": 24865672, "country": 23424977, "town": 0, "planet": 1, "county": 12589470, "suburb": 0, "state": 2347592, "region": 0, "localadmin": 0}, "woe:timezone_id": 56043648, "woe:hash": "dnqq1vwx8q54", "woe:centroid": [-81.125092, 36.24247], "geom:latitude": 36.24247, "geom:longitude": -81.125092, "geom:hash": "dnqq1vwx8q54", "woe:latitude": 36.24247, "geom:centroid": [-81.125092, 36.24247], "woe:longitude": -81.125092, "woe:repo": "woeplanet-poi-us", "geom:area": 0.0, "woe:scale": 19}}