{"type": "Feature", "id": 23663778, "geometry": {"type": "Point", "coordinates": [-72.40229, 43.534321]}, "properties": {"woe:id": 23663778, "woe:parent_id": 2418300, "woe:name": "Hartland Elementary School", "woe:placetype": 20, "woe:placetype_name": "POI", "woe:lang": "ENG", "iso:country": "US", "meta:provider": ["geoplanet:7.3.2", "geoplanet:7.4.0", "geoplanet:7.4.1", "geoplanet:7.5.1", "geoplanet:7.5.2", "geoplanet:7.6.0", "geoplanet:7.8.1", "geoplanet:7.9.0", "geoplanet:7.10.0", "geoplanet:8.0.0", "woeplanet:8.0.0"], "meta:indexed": "2020-08-20T22:02:57.669388", "woe:alias_ENG_V": ["Hartland Elementary"], "meta:updated": "2020-10-14T11:19:46.165533", "woe:hierarchy": {"continent": 24865672, "country": 23424977, "town": 0, "planet": 1, "county": 12590303, "suburb": 0, "state": 2347604, "region": 0, "localadmin": 0}, "woe:timezone_id": 56043648, "woe:hash": "drsx8mnmb3es", "woe:centroid": [-72.40229, 43.534321], "geom:latitude": 43.534321, "geom:longitude": -72.40229, "geom:hash": "drsx8mnmb3es", "woe:latitude": 43.534321, "geom:centroid": [-72.40229, 43.534321], "woe:longitude": -72.40229, "woe:repo": "woeplanet-poi-us", "geom:area": 0.0, "woe:scale": 19}}