{"type": "Feature", "id": 23684309, "properties": {"woe:id": 23684309, "woe:parent_id": 28338914, "woe:name": "Free State Mall", "woe:placetype": 20, "woe:placetype_name": "POI", "woe:lang": "ENG", "iso:country": "US", "meta:provider": ["geoplanet:7.3.1", "geoplanet:7.3.2", "geoplanet:7.4.0", "geoplanet:7.4.1", "geoplanet:7.5.1", "geoplanet:7.5.2", "geoplanet:7.6.0", "geoplanet:7.8.1", "geoplanet:7.9.0", "geoplanet:7.10.0", "geoplanet:8.0.0", "woeplanet:8.0.0"], "meta:indexed": "2020-08-20T20:19:12.876770", "meta:updated": "2020-08-22T02:58:18.754537", "woe:hierarchy": {"continent": 24865672, "country": 23424977, "town": 0, "planet": 1, "county": 12588692, "suburb": 0, "state": 2347579, "region": 0, "localadmin": 0}, "woe:timezone_id": 56043648, "woe:hash": "dqcmtzfwph74", "woe:centroid": [-76.735764, 38.979172], "geom:latitude": 38.979172, "geom:longitude": -76.735764, "geom:hash": "dqcmtzfwph74", "woe:latitude": 38.979172, "geom:centroid": [-76.735764, 38.979172], "woe:longitude": -76.735764, "woe:repo": "woeplanet-poi-us"}, "geometry": {"coordinates": [-76.735764, 38.979172], "type": "Point"}}