{"type": "Feature", "id": 23605420, "properties": {"woe:id": 23605420, "woe:parent_id": 28339582, "woe:name": "Lakeland School", "woe:placetype": 20, "woe:placetype_name": "POI", "woe:lang": "ENG", "iso:country": "US", "meta:provider": ["geoplanet:7.4.0", "geoplanet:7.4.1", "geoplanet:7.5.1", "geoplanet:7.5.2", "geoplanet:7.6.0", "geoplanet:7.8.1", "geoplanet:7.9.0", "geoplanet:7.10.0", "geoplanet:8.0.0", "woeplanet:8.0.0"], "meta:indexed": "2020-08-20T23:55:17.406472", "meta:updated": "2020-08-22T02:57:41.692580", "woe:hierarchy": {"continent": 24865672, "country": 23424977, "town": 0, "planet": 1, "county": 12589248, "suburb": 0, "state": 2347588, "region": 0, "localadmin": 0}, "woe:timezone_id": 56043648, "woe:hash": "drv05vn9d3p9", "woe:centroid": [-71.544922, 43.621479], "geom:latitude": 43.621479, "geom:longitude": -71.544922, "geom:hash": "drv05vn9d3p9", "woe:latitude": 43.621479, "geom:centroid": [-71.544922, 43.621479], "woe:longitude": -71.544922, "woe:repo": "woeplanet-poi-us"}, "geometry": {"coordinates": [-71.544922, 43.621479], "type": "Point"}}