{"type": "Feature", "id": 23676393, "properties": {"woe:id": 23676393, "woe:parent_id": 2464176, "woe:name": "Park Lawn Elementary School", "woe:placetype": 20, "woe:placetype_name": "POI", "woe:lang": "ENG", "iso:country": "US", "meta:provider": ["geoplanet:7.3.1", "geoplanet:7.3.2", "geoplanet:7.4.0", "geoplanet:7.4.1", "geoplanet:7.5.1", "geoplanet:7.5.2", "geoplanet:7.6.0", "geoplanet:7.8.1", "geoplanet:7.9.0", "geoplanet:7.10.0", "geoplanet:8.0.0", "woeplanet:8.0.0"], "meta:indexed": "2020-08-20T20:19:11.988153", "woe:alias_ENG_V": ["Park Lawn Elementary"], "meta:updated": "2020-08-22T02:58:18.346693", "woe:hierarchy": {"continent": 24865672, "country": 23424977, "town": 0, "planet": 1, "county": 12590601, "suburb": 0, "state": 2347608, "region": 0, "localadmin": 0}, "woe:timezone_id": 56043661, "woe:hash": "dp9j1zxst6db", "woe:centroid": [-88.506317, 43.108391], "geom:latitude": 43.108391, "geom:longitude": -88.506317, "geom:hash": "dp9j1zxst6db", "woe:latitude": 43.108391, "geom:centroid": [-88.506317, 43.108391], "woe:longitude": -88.506317, "woe:repo": "woeplanet-poi-us"}, "geometry": {"coordinates": [-88.506317, 43.108391], "type": "Point"}}