{"type": "Feature", "id": 23527099, "properties": {"woe:id": 23527099, "woe:parent_id": 2479567, "woe:name": "Downtown Redding Station", "woe:placetype": 20, "woe:placetype_name": "POI", "woe:lang": "ENG", "iso:country": "US", "meta:provider": ["geoplanet:7.3.1", "geoplanet:7.3.2", "geoplanet:7.4.0", "geoplanet:7.4.1", "geoplanet:7.5.1", "geoplanet:7.5.2", "geoplanet:7.6.0", "geoplanet:7.8.1", "geoplanet:7.9.0", "geoplanet:7.10.0", "geoplanet:8.0.0", "woeplanet:8.0.0"], "meta:indexed": "2020-08-20T20:18:21.008084", "meta:updated": "2020-08-22T02:57:28.188419", "woe:hierarchy": {"continent": 24865672, "country": 23424977, "town": 0, "planet": 1, "county": 12587714, "suburb": 0, "state": 2347563, "region": 0, "localadmin": 0}, "woe:timezone_id": 56043663, "woe:hash": "9r0yyggfge1b", "woe:centroid": [-122.393379, 40.582611], "geom:latitude": 40.582611, "geom:longitude": -122.393379, "geom:hash": "9r0yyggfge1b", "woe:latitude": 40.582611, "geom:centroid": [-122.393379, 40.582611], "woe:longitude": -122.393379, "woe:repo": "woeplanet-poi-us"}, "geometry": {"coordinates": [-122.393379, 40.582611], "type": "Point"}}