{"type": "Feature", "id": 23595937, "geometry": {"type": "Point", "coordinates": [-88.807823, 30.413589]}, "properties": {"woe:id": 23595937, "woe:parent_id": 2464094, "woe:name": "Ocean Springs High School", "woe:placetype": 20, "woe:placetype_name": "POI", "woe:lang": "ENG", "iso:country": "US", "meta:provider": ["geoplanet:7.3.1", "geoplanet:7.3.2", "geoplanet:7.4.0", "geoplanet:7.4.1", "geoplanet:7.5.1", "geoplanet:7.5.2", "geoplanet:7.6.0", "geoplanet:7.8.1", "geoplanet:7.9.0", "geoplanet:7.10.0", "geoplanet:8.0.0", "woeplanet:8.0.0"], "meta:indexed": "2020-08-20T20:18:43.358393", "woe:alias_ENG_V": ["Ocean Springs Senior High School", "Ocean Springs High", "Ocean Springs Senior High", "Ocean Springs HS", "Ocean Springs Senior HS"], "meta:updated": "2020-10-14T11:20:18.324980", "woe:hierarchy": {"continent": 24865672, "country": 23424977, "town": 0, "planet": 1, "county": 12588913, "suburb": 0, "state": 2347583, "region": 0, "localadmin": 0}, "woe:timezone_id": 56043661, "woe:hash": "dj2v50s5gxzt", "woe:centroid": [-88.807823, 30.413589], "geom:latitude": 30.413589, "geom:longitude": -88.807823, "geom:hash": "dj2v50s5gxzt", "woe:latitude": 30.413589, "geom:centroid": [-88.807823, 30.413589], "woe:longitude": -88.807823, "woe:repo": "woeplanet-poi-us", "geom:area": 0.0, "woe:scale": 19}}