{"type": "Feature", "id": 23580200, "geometry": {"type": "Point", "coordinates": [-76.093628, 38.53825]}, "properties": {"woe:id": 23580200, "woe:parent_id": 2380159, "woe:name": "Maple Elementary School", "woe:placetype": 20, "woe:placetype_name": "POI", "woe:lang": "ENG", "iso:country": "US", "meta:provider": ["geoplanet:7.3.2", "geoplanet:7.4.0", "geoplanet:7.4.1", "geoplanet:7.5.1", "geoplanet:7.5.2", "geoplanet:7.6.0", "geoplanet:7.8.1", "geoplanet:7.9.0", "geoplanet:7.10.0", "geoplanet:8.0.0", "woeplanet:8.0.0"], "meta:indexed": "2020-08-20T22:02:22.813873", "woe:alias_ENG_V": ["Maple Elementary"], "meta:updated": "2020-10-14T11:20:28.773803", "woe:hierarchy": {"continent": 24865672, "country": 23424977, "town": 0, "planet": 1, "county": 12588685, "suburb": 0, "state": 2347579, "region": 0, "localadmin": 0}, "woe:timezone_id": 56043648, "woe:hash": "dqcghrwm9fqx", "woe:centroid": [-76.093628, 38.53825], "geom:latitude": 38.53825, "geom:longitude": -76.093628, "geom:hash": "dqcghrwm9fqx", "woe:latitude": 38.53825, "geom:centroid": [-76.093628, 38.53825], "woe:longitude": -76.093628, "woe:repo": "woeplanet-poi-us", "geom:area": 0.0, "woe:scale": 19}}