{"type": "Feature", "id": 23566351, "properties": {"woe:id": 23566351, "woe:parent_id": 2414519, "woe:name": "Eastern Junior & Senior High School", "woe:placetype": 20, "woe:placetype_name": "POI", "woe:lang": "ENG", "iso:country": "US", "meta:provider": ["geoplanet:7.3.1", "geoplanet:7.3.2", "geoplanet:7.4.0", "geoplanet:7.4.1", "geoplanet:7.5.1", "geoplanet:7.5.2", "geoplanet:7.6.0", "geoplanet:7.8.1", "geoplanet:7.9.0", "geoplanet:7.10.0", "geoplanet:8.0.0", "woeplanet:8.0.0"], "meta:indexed": "2020-08-20T20:18:33.970208", "woe:alias_ENG_V": ["Eastern Junior & Senior High", "Eastern Junior High School", "Eastern Junior & High", "Eastern Junior & Senior HS", "Eastern Junior HS", "Eastern Junior and Senior High", "Eastern Junior and Senior Senior High", "Eastern Junior and Senior Senior HS", "Eastern Junior and Senior HS", "Eastern Junior and Senior Senior High School", "Eastern Junior and Senior High School"], "meta:updated": "2020-08-22T02:58:47.213850", "woe:hierarchy": {"continent": 24865672, "country": 23424977, "town": 0, "planet": 1, "county": 12588213, "suburb": 0, "state": 2347573, "region": 0, "localadmin": 0}, "woe:timezone_id": 56043656, "woe:hash": "dp4y78n0wzt8", "woe:centroid": [-85.970467, 40.473759], "geom:latitude": 40.473759, "geom:longitude": -85.970467, "geom:hash": "dp4y78n0wzt8", "woe:latitude": 40.473759, "geom:centroid": [-85.970467, 40.473759], "woe:longitude": -85.970467, "woe:repo": "woeplanet-poi-us"}, "geometry": {"coordinates": [-85.970467, 40.473759], "type": "Point"}}