{"type": "Feature", "id": 23583939, "properties": {"woe:id": 23583939, "woe:parent_id": 55986832, "woe:name": "Fuller Middle School", "woe:placetype": 20, "woe:placetype_name": "POI", "woe:lang": "ENG", "iso:country": "US", "meta:provider": ["geoplanet:7.3.1", "geoplanet:7.3.2", "geoplanet:7.4.0", "geoplanet:7.4.1", "geoplanet:7.5.1", "geoplanet:7.5.2", "geoplanet:7.6.0", "geoplanet:7.8.1", "geoplanet:7.9.0", "geoplanet:7.10.0", "geoplanet:8.0.0", "woeplanet:8.0.0"], "meta:indexed": "2020-08-20T20:18:39.355710", "meta:updated": "2020-08-22T02:57:38.381948", "woe:hierarchy": {"continent": 24865672, "country": 23424977, "town": 0, "planet": 1, "county": 12588708, "suburb": 0, "state": 2347580, "region": 0, "localadmin": 0}, "woe:timezone_id": 56043648, "woe:hash": "drt0wgj45scy", "woe:centroid": [-71.4151, 42.29224], "geom:latitude": 42.29224, "geom:longitude": -71.4151, "geom:hash": "drt0wgj45scy", "woe:latitude": 42.29224, "geom:centroid": [-71.4151, 42.29224], "woe:longitude": -71.4151, "woe:repo": "woeplanet-poi-us"}, "geometry": {"coordinates": [-71.4151, 42.29224], "type": "Point"}}