{"type": "Feature", "id": 23633738, "geometry": {"type": "Point", "coordinates": [-96.778381, 34.086071]}, "properties": {"woe:id": 23633738, "woe:parent_id": 2443925, "woe:name": "Madill High School", "woe:placetype": 20, "woe:placetype_name": "POI", "woe:lang": "ENG", "iso:country": "US", "meta:provider": ["geoplanet:7.3.1", "geoplanet:7.3.2", "geoplanet:7.4.0", "geoplanet:7.4.1", "geoplanet:7.5.1", "geoplanet:7.5.2", "geoplanet:7.6.0", "geoplanet:7.8.1", "geoplanet:7.9.0", "geoplanet:7.10.0", "geoplanet:8.0.0", "woeplanet:8.0.0"], "meta:indexed": "2020-08-20T20:18:56.187677", "woe:alias_ENG_V": ["Madill Senior High School", "Madill High", "Madill Senior High", "Madill HS", "Madill Senior HS"], "meta:updated": "2020-10-14T11:19:39.107696", "woe:hierarchy": {"continent": 24865672, "country": 23424977, "town": 0, "planet": 1, "county": 12589659, "suburb": 0, "state": 2347595, "region": 0, "localadmin": 0}, "woe:timezone_id": 56043661, "woe:hash": "9y51vv0ju20v", "woe:centroid": [-96.778381, 34.086071], "geom:latitude": 34.086071, "geom:longitude": -96.778381, "geom:hash": "9y51vv0ju20v", "woe:latitude": 34.086071, "geom:centroid": [-96.778381, 34.086071], "woe:longitude": -96.778381, "woe:repo": "woeplanet-poi-us", "geom:area": 0.0, "woe:scale": 19}}