{"type": "Feature", "id": 23579858, "properties": {"woe:id": 23579858, "woe:parent_id": 2415829, "woe:name": "Jewish Community Center", "woe:placetype": 20, "woe:placetype_name": "POI", "woe:lang": "ENG", "iso:country": "US", "meta:provider": ["geoplanet:7.3.1", "geoplanet:7.3.2", "geoplanet:7.4.0", "geoplanet:7.4.1", "geoplanet:7.5.1", "geoplanet:7.5.2", "geoplanet:7.6.0", "geoplanet:7.8.1", "geoplanet:7.9.0", "geoplanet:7.10.0", "geoplanet:8.0.0", "woeplanet:8.0.0"], "meta:indexed": "2020-08-20T20:18:38.467819", "meta:updated": "2020-08-22T02:57:37.764446", "woe:hierarchy": {"continent": 24865672, "country": 23424977, "town": 0, "planet": 1, "county": 12588678, "suburb": 0, "state": 2347579, "region": 0, "localadmin": 0}, "woe:timezone_id": 56043648, "woe:hash": "dr12mhbdzmc9", "woe:centroid": [-76.771461, 39.445541], "geom:latitude": 39.445541, "geom:longitude": -76.771461, "geom:hash": "dr12mhbdzmc9", "woe:latitude": 39.445541, "geom:centroid": [-76.771461, 39.445541], "woe:longitude": -76.771461, "woe:repo": "woeplanet-poi-us"}, "geometry": {"coordinates": [-76.771461, 39.445541], "type": "Point"}}