{"type": "Feature", "id": 23675488, "geometry": {"type": "Point", "coordinates": [-91.772079, 44.653969]}, "properties": {"woe:id": 23675488, "woe:parent_id": 12590580, "woe:name": "Duscham Amish School", "woe:placetype": 20, "woe:placetype_name": "POI", "woe:lang": "ENG", "iso:country": "US", "meta:provider": ["geoplanet:7.3.1", "geoplanet:7.3.2", "geoplanet:7.4.0", "geoplanet:7.4.1", "geoplanet:7.5.1", "geoplanet:7.5.2", "geoplanet:7.6.0", "geoplanet:7.8.1", "geoplanet:7.9.0", "geoplanet:7.10.0", "geoplanet:8.0.0", "woeplanet:8.0.0"], "meta:indexed": "2020-08-20T20:19:11.518363", "meta:updated": "2020-10-14T11:19:31.026023", "woe:hierarchy": {"continent": 24865672, "country": 23424977, "town": 0, "planet": 1, "county": 12590580, "suburb": 0, "state": 2347608, "region": 0, "localadmin": 0}, "woe:timezone_id": 56043661, "woe:hash": "9zywp9j85x4h", "woe:centroid": [-91.772079, 44.653969], "geom:latitude": 44.653969, "geom:longitude": -91.772079, "geom:hash": "9zywp9j85x4h", "woe:latitude": 44.653969, "geom:centroid": [-91.772079, 44.653969], "woe:longitude": -91.772079, "woe:repo": "woeplanet-poi-us", "geom:area": 0.0, "woe:scale": 19}}