{"type": "Feature", "id": 23630608, "geometry": {"type": "Point", "coordinates": [-82.04023, 41.447609]}, "properties": {"woe:id": 23630608, "woe:parent_id": 2357827, "woe:name": "Avon High School", "woe:placetype": 20, "woe:placetype_name": "POI", "woe:lang": "ENG", "iso:country": "US", "meta:provider": ["geoplanet:7.3.1", "geoplanet:7.3.2", "geoplanet:7.4.0", "geoplanet:7.4.1", "geoplanet:7.5.1", "geoplanet:7.5.2", "geoplanet:7.6.0", "geoplanet:7.8.1", "geoplanet:7.9.0", "geoplanet:7.10.0", "geoplanet:8.0.0", "woeplanet:8.0.0"], "meta:indexed": "2020-08-20T20:18:54.752360", "woe:alias_ENG_V": ["Avon Senior High School", "Avon High", "Avon Senior High", "Avon HS", "Avon Senior HS"], "meta:updated": "2020-10-14T11:19:32.474209", "woe:hierarchy": {"continent": 24865672, "country": 23424977, "town": 0, "planet": 1, "county": 12589573, "suburb": 0, "state": 2347594, "region": 0, "localadmin": 0}, "woe:timezone_id": 56043648, "woe:hash": "dpmev1k1u46d", "woe:centroid": [-82.04023, 41.447609], "geom:latitude": 41.447609, "geom:longitude": -82.04023, "geom:hash": "dpmev1k1u46d", "woe:latitude": 41.447609, "geom:centroid": [-82.04023, 41.447609], "woe:longitude": -82.04023, "woe:repo": "woeplanet-poi-us", "geom:area": 0.0, "woe:scale": 19}}