{"type": "Feature", "id": 23585569, "properties": {"woe:id": 23585569, "woe:parent_id": 55986790, "woe:name": "East Boston Station", "woe:placetype": 20, "woe:placetype_name": "POI", "woe:lang": "ENG", "iso:country": "US", "meta:provider": ["geoplanet:7.3.1", "geoplanet:7.3.2", "geoplanet:7.4.0", "geoplanet:7.4.1", "geoplanet:7.5.1", "geoplanet:7.5.2", "geoplanet:7.6.0", "geoplanet:7.8.1", "geoplanet:7.9.0", "geoplanet:7.10.0", "geoplanet:8.0.0", "woeplanet:8.0.0"], "meta:indexed": "2020-08-20T20:18:39.742703", "woe:alias_ENG_V": ["E Boston Station"], "meta:updated": "2020-08-22T02:57:38.571443", "woe:hierarchy": {"continent": 24865672, "country": 23424977, "town": 0, "planet": 1, "county": 12588712, "suburb": 0, "state": 2347580, "region": 0, "localadmin": 0}, "woe:timezone_id": 56043648, "woe:hash": "drt3p3rn0t9h", "woe:centroid": [-71.038948, 42.371208], "geom:latitude": 42.371208, "geom:longitude": -71.038948, "geom:hash": "drt3p3rn0t9h", "woe:latitude": 42.371208, "geom:centroid": [-71.038948, 42.371208], "woe:longitude": -71.038948, "woe:repo": "woeplanet-poi-us"}, "geometry": {"coordinates": [-71.038948, 42.371208], "type": "Point"}}