{"type": "Feature", "id": 23624558, "geometry": {"type": "Point", "coordinates": [-79.991447, 35.959141]}, "properties": {"woe:id": 23624558, "woe:parent_id": 55989042, "woe:name": "Baldwins Chapel Sda Elementary School", "woe:placetype": 20, "woe:placetype_name": "POI", "woe:lang": "ENG", "iso:country": "US", "meta:provider": ["geoplanet:7.3.1", "geoplanet:7.3.2", "geoplanet:7.4.0", "geoplanet:7.4.1", "geoplanet:7.5.1", "geoplanet:7.5.2", "geoplanet:7.6.0", "geoplanet:7.8.1", "geoplanet:7.9.0", "geoplanet:7.10.0", "geoplanet:8.0.0", "woeplanet:8.0.0"], "meta:indexed": "2020-08-20T20:18:52.776038", "woe:alias_ENG_V": ["Rc Baldwin Educational Center", "Baldwins Chapel Sda Elementary"], "meta:updated": "2020-10-14T11:19:52.662015", "woe:hierarchy": {"continent": 24865672, "country": 23424977, "town": 0, "planet": 1, "county": 12589414, "suburb": 0, "state": 2347592, "region": 0, "localadmin": 0}, "woe:timezone_id": 56043648, "woe:hash": "dnrhef0j0jwp", "woe:centroid": [-79.991447, 35.959141], "geom:latitude": 35.959141, "geom:longitude": -79.991447, "geom:hash": "dnrhef0j0jwp", "woe:latitude": 35.959141, "geom:centroid": [-79.991447, 35.959141], "woe:longitude": -79.991447, "woe:repo": "woeplanet-poi-us", "geom:area": 0.0, "woe:scale": 19}}