{"type": "Feature", "id": 23624484, "geometry": {"type": "Point", "coordinates": [-79.798233, 36.10984]}, "properties": {"woe:id": 23624484, "woe:parent_id": 55859552, "woe:name": "Mendenhall Middle School", "woe:placetype": 20, "woe:placetype_name": "POI", "woe:lang": "ENG", "iso:country": "US", "meta:provider": ["geoplanet:7.3.1", "geoplanet:7.3.2", "geoplanet:7.4.0", "geoplanet:7.4.1", "geoplanet:7.5.1", "geoplanet:7.5.2", "geoplanet:7.6.0", "geoplanet:7.8.1", "geoplanet:7.9.0", "geoplanet:7.10.0", "geoplanet:8.0.0", "woeplanet:8.0.0"], "meta:indexed": "2020-08-20T20:18:52.758339", "meta:updated": "2020-10-14T11:19:36.668926", "woe:hierarchy": {"continent": 24865672, "country": 23424977, "town": 0, "planet": 1, "county": 12589414, "suburb": 0, "state": 2347592, "region": 0, "localadmin": 0}, "woe:timezone_id": 56043648, "woe:hash": "dnrm2jsen6hc", "woe:centroid": [-79.798233, 36.10984], "geom:latitude": 36.10984, "geom:longitude": -79.798233, "geom:hash": "dnrm2jsen6hc", "woe:latitude": 36.10984, "geom:centroid": [-79.798233, 36.10984], "woe:longitude": -79.798233, "woe:repo": "woeplanet-poi-us", "geom:area": 0.0, "woe:scale": 19}}