{"type": "Feature", "id": 23515961, "geometry": {"type": "Point", "coordinates": [-112.165489, 33.54211]}, "properties": {"woe:id": 23515961, "woe:parent_id": 55859280, "woe:name": "Melvin E Sine School", "woe:placetype": 20, "woe:placetype_name": "POI", "woe:lang": "ENG", "iso:country": "US", "meta:provider": ["geoplanet:7.3.1", "geoplanet:7.3.2", "geoplanet:7.4.0", "geoplanet:7.4.1", "geoplanet:7.5.1", "geoplanet:7.5.2", "geoplanet:7.6.0", "geoplanet:7.8.1", "geoplanet:7.9.0", "geoplanet:7.10.0", "geoplanet:8.0.0", "woeplanet:8.0.0"], "meta:indexed": "2020-08-20T20:18:18.147761", "meta:updated": "2020-10-14T11:20:03.683846", "woe:alias_ENG_V": ["Melvin E Sine Elementary School"], "woe:hierarchy": {"continent": 24865672, "country": 23424977, "town": 0, "planet": 1, "county": 12587587, "suburb": 0, "state": 2347561, "region": 0, "localadmin": 0}, "woe:timezone_id": 56043666, "woe:hash": "9tbnzd5sfwmr", "woe:centroid": [-112.165489, 33.54211], "geom:latitude": 33.54211, "geom:longitude": -112.165489, "geom:hash": "9tbnzd5sfwmr", "woe:latitude": 33.54211, "geom:centroid": [-112.165489, 33.54211], "woe:longitude": -112.165489, "woe:repo": "woeplanet-poi-us", "geom:area": 0.0, "woe:scale": 19}}