{"type": "Feature", "id": 23542748, "geometry": {"type": "Point", "coordinates": [-73.349747, 41.178558]}, "properties": {"woe:id": 23542748, "woe:parent_id": 55974723, "woe:name": "Coleytown Middle School", "woe:placetype": 20, "woe:placetype_name": "POI", "woe:lang": "ENG", "iso:country": "US", "meta:provider": ["geoplanet:7.3.1", "geoplanet:7.3.2", "geoplanet:7.4.0", "geoplanet:7.4.1", "geoplanet:7.5.1", "geoplanet:7.5.2", "geoplanet:7.6.0", "geoplanet:7.8.1", "geoplanet:7.9.0", "geoplanet:7.10.0", "geoplanet:8.0.0", "woeplanet:8.0.0"], "meta:indexed": "2020-08-20T20:18:25.024624", "meta:updated": "2020-10-14T11:20:24.266735", "woe:hierarchy": {"continent": 24865672, "country": 23424977, "town": 0, "planet": 1, "county": 12587791, "suburb": 0, "state": 2347565, "region": 0, "localadmin": 0}, "woe:timezone_id": 56043648, "woe:hash": "dr7f6bk67p86", "woe:centroid": [-73.349747, 41.178558], "geom:latitude": 41.178558, "geom:longitude": -73.349747, "geom:hash": "dr7f6bk67p86", "woe:latitude": 41.178558, "geom:centroid": [-73.349747, 41.178558], "woe:longitude": -73.349747, "woe:repo": "woeplanet-poi-us", "geom:area": 0.0, "woe:scale": 19}}