{"type": "Feature", "id": 23646273, "geometry": {"type": "Point", "coordinates": [-71.623543, 41.588539]}, "properties": {"woe:id": 23646273, "woe:parent_id": 2401076, "woe:name": "Wawaloam School", "woe:placetype": 20, "woe:placetype_name": "POI", "woe:lang": "ENG", "iso:country": "US", "meta:provider": ["geoplanet:7.3.1", "geoplanet:7.3.2", "geoplanet:7.4.0", "geoplanet:7.4.1", "geoplanet:7.5.1", "geoplanet:7.5.2", "geoplanet:7.6.0", "geoplanet:7.8.1", "geoplanet:7.9.0", "geoplanet:7.10.0", "geoplanet:8.0.0", "woeplanet:8.0.0"], "meta:indexed": "2020-08-20T20:19:00.439600", "meta:updated": "2020-10-14T11:19:28.679069", "woe:hierarchy": {"continent": 24865672, "country": 23424977, "town": 0, "planet": 1, "county": 12589799, "suburb": 0, "state": 2347598, "region": 0, "localadmin": 0}, "woe:timezone_id": 56043648, "woe:hash": "drmhd4vqf3x6", "woe:centroid": [-71.623543, 41.588539], "geom:latitude": 41.588539, "geom:longitude": -71.623543, "geom:hash": "drmhd4vqf3x6", "woe:latitude": 41.588539, "geom:centroid": [-71.623543, 41.588539], "woe:longitude": -71.623543, "woe:repo": "woeplanet-poi-us", "geom:area": 0.0, "woe:scale": 19}}