{"type": "Feature", "id": 23551602, "properties": {"woe:id": 23551602, "woe:parent_id": 2522368, "woe:name": "Coile Middle School", "woe:placetype": 20, "woe:placetype_name": "POI", "woe:lang": "ENG", "iso:country": "US", "meta:provider": ["geoplanet:7.3.2", "geoplanet:7.4.0", "geoplanet:7.4.1", "geoplanet:7.5.1", "geoplanet:7.5.2", "geoplanet:7.6.0", "geoplanet:7.8.1", "geoplanet:7.9.0", "geoplanet:7.10.0", "geoplanet:8.0.0", "woeplanet:8.0.0"], "meta:indexed": "2020-08-20T22:02:10.920854", "meta:updated": "2020-08-22T02:57:32.833504", "woe:alias_ENG_V": ["Wr Coile Middle School"], "woe:hierarchy": {"continent": 24865672, "country": 23424977, "town": 0, "planet": 1, "county": 12587898, "suburb": 0, "state": 2347569, "region": 0, "localadmin": 0}, "woe:timezone_id": 56043648, "woe:hash": "dnhc27jp8wyc", "woe:centroid": [-83.302429, 33.98753], "geom:latitude": 33.98753, "geom:longitude": -83.302429, "geom:hash": "dnhc27jp8wyc", "woe:latitude": 33.98753, "geom:centroid": [-83.302429, 33.98753], "woe:longitude": -83.302429, "woe:repo": "woeplanet-poi-us"}, "geometry": {"coordinates": [-83.302429, 33.98753], "type": "Point"}}