{"type": "Feature", "id": 23521583, "geometry": {"type": "Point", "coordinates": [-119.584633, 36.590618]}, "properties": {"woe:id": 23521583, "woe:parent_id": 2490713, "woe:name": "Indianola Elementary School", "woe:placetype": 20, "woe:placetype_name": "POI", "woe:lang": "ENG", "iso:country": "US", "meta:provider": ["geoplanet:7.3.2", "geoplanet:7.4.0", "geoplanet:7.4.1", "geoplanet:7.5.1", "geoplanet:7.5.2", "geoplanet:7.6.0", "geoplanet:7.8.1", "geoplanet:7.9.0", "geoplanet:7.10.0", "geoplanet:8.0.0", "woeplanet:8.0.0"], "meta:indexed": "2020-08-20T22:01:58.708083", "woe:alias_ENG_V": ["Indianola Elementary"], "meta:updated": "2020-10-14T11:20:29.214963", "woe:hierarchy": {"continent": 24865672, "country": 23424977, "town": 0, "planet": 1, "county": 12587679, "suburb": 0, "state": 2347563, "region": 0, "localadmin": 0}, "woe:timezone_id": 56043663, "woe:hash": "9qdbnv15u1df", "woe:centroid": [-119.584633, 36.590618], "geom:latitude": 36.590618, "geom:longitude": -119.584633, "geom:hash": "9qdbnv15u1df", "woe:latitude": 36.590618, "geom:centroid": [-119.584633, 36.590618], "woe:longitude": -119.584633, "woe:repo": "woeplanet-poi-us", "geom:area": 0.0, "woe:scale": 19}}