{"type": "Feature", "id": 23543571, "properties": {"woe:id": 23543571, "woe:parent_id": 2458752, "woe:name": "Grace Christian Academy", "woe:placetype": 20, "woe:placetype_name": "POI", "woe:lang": "ENG", "iso:country": "US", "meta:provider": ["geoplanet:7.3.2", "geoplanet:7.4.0", "geoplanet:7.4.1", "geoplanet:7.5.1", "geoplanet:7.5.2", "geoplanet:7.6.0", "geoplanet:7.8.1", "geoplanet:7.9.0", "geoplanet:7.10.0", "geoplanet:8.0.0", "woeplanet:8.0.0"], "meta:indexed": "2020-08-20T22:02:07.156163", "meta:updated": "2020-08-22T02:57:31.156648", "woe:hierarchy": {"continent": 24865672, "country": 23424977, "town": 0, "planet": 1, "county": 12587793, "suburb": 0, "state": 2347565, "region": 0, "localadmin": 0}, "woe:timezone_id": 56043648, "woe:hash": "dr7u3yyjqgmz", "woe:centroid": [-73.391121, 41.566319], "geom:latitude": 41.566319, "geom:longitude": -73.391121, "geom:hash": "dr7u3yyjqgmz", "woe:latitude": 41.566319, "geom:centroid": [-73.391121, 41.566319], "woe:longitude": -73.391121, "woe:repo": "woeplanet-poi-us"}, "geometry": {"coordinates": [-73.391121, 41.566319], "type": "Point"}}