{"type": "Feature", "id": 23666899, "properties": {"woe:id": 23666899, "woe:parent_id": 55858489, "woe:name": "Cedar Road Elementary School", "woe:placetype": 20, "woe:placetype_name": "POI", "woe:lang": "ENG", "iso:country": "US", "meta:provider": ["geoplanet:7.3.1", "geoplanet:7.3.2", "geoplanet:7.4.0", "geoplanet:7.4.1", "geoplanet:7.5.1", "geoplanet:7.5.2", "geoplanet:7.6.0", "geoplanet:7.8.1", "geoplanet:7.9.0", "geoplanet:7.10.0", "geoplanet:8.0.0", "woeplanet:8.0.0"], "meta:indexed": "2020-08-20T20:19:08.504500", "woe:alias_ENG_V": ["Cedar Road Elementary"], "meta:updated": "2020-08-22T02:57:51.512818", "woe:hierarchy": {"continent": 24865672, "country": 23424977, "town": 0, "planet": 1, "county": 12590329, "suburb": 0, "state": 2347605, "region": 0, "localadmin": 0}, "woe:timezone_id": 56043648, "woe:hash": "dq98zvdk9p6p", "woe:centroid": [-76.296913, 36.725361], "geom:latitude": 36.725361, "geom:longitude": -76.296913, "geom:hash": "dq98zvdk9p6p", "woe:latitude": 36.725361, "geom:centroid": [-76.296913, 36.725361], "woe:longitude": -76.296913, "woe:repo": "woeplanet-poi-us"}, "geometry": {"coordinates": [-76.296913, 36.725361], "type": "Point"}}