{"type": "Feature", "id": 23684076, "properties": {"woe:id": 23684076, "woe:parent_id": 2502932, "woe:name": "Swansea Mall", "woe:placetype": 20, "woe:placetype_name": "POI", "woe:lang": "ENG", "iso:country": "US", "meta:provider": ["geoplanet:7.3.1", "geoplanet:7.3.2", "geoplanet:7.4.0", "geoplanet:7.4.1", "geoplanet:7.5.1", "geoplanet:7.5.2", "geoplanet:7.6.0", "geoplanet:7.8.1", "geoplanet:7.9.0", "geoplanet:7.10.0", "geoplanet:8.0.0", "woeplanet:8.0.0"], "meta:indexed": "2020-08-20T20:19:12.712161", "meta:updated": "2020-08-22T02:58:18.670063", "woe:hierarchy": {"continent": 24865672, "country": 23424977, "town": 0, "planet": 1, "county": 12588702, "suburb": 0, "state": 2347580, "region": 0, "localadmin": 0}, "woe:timezone_id": 56043648, "woe:hash": "drmme6d3ygtw", "woe:centroid": [-71.220978, 41.7621], "geom:latitude": 41.7621, "geom:longitude": -71.220978, "geom:hash": "drmme6d3ygtw", "woe:latitude": 41.7621, "geom:centroid": [-71.220978, 41.7621], "woe:longitude": -71.220978, "woe:repo": "woeplanet-poi-us"}, "geometry": {"coordinates": [-71.220978, 41.7621], "type": "Point"}}