{"type": "Feature", "id": 23568857, "properties": {"woe:id": 23568857, "woe:parent_id": 2444050, "woe:name": "Madrid Elementary School", "woe:placetype": 20, "woe:placetype_name": "POI", "woe:lang": "ENG", "iso:country": "US", "meta:provider": ["geoplanet:7.3.1", "geoplanet:7.3.2", "geoplanet:7.4.0", "geoplanet:7.4.1", "geoplanet:7.5.1", "geoplanet:7.5.2", "geoplanet:7.6.0", "geoplanet:7.8.1", "geoplanet:7.9.0", "geoplanet:7.10.0", "geoplanet:8.0.0", "woeplanet:8.0.0"], "meta:indexed": "2020-08-20T20:18:34.957330", "woe:alias_ENG_V": ["Madrid Elementary"], "meta:updated": "2020-08-22T02:57:36.056281", "woe:hierarchy": {"continent": 24865672, "country": 23424977, "town": 0, "planet": 1, "county": 12588279, "suburb": 0, "state": 2347574, "region": 0, "localadmin": 0}, "woe:timezone_id": 56043661, "woe:hash": "9zmq1p2ygx3d", "woe:centroid": [-93.82206, 41.876961], "geom:latitude": 41.876961, "geom:longitude": -93.82206, "geom:hash": "9zmq1p2ygx3d", "woe:latitude": 41.876961, "geom:centroid": [-93.82206, 41.876961], "woe:longitude": -93.82206, "woe:repo": "woeplanet-poi-us"}, "geometry": {"coordinates": [-93.82206, 41.876961], "type": "Point"}}