{"type": "Feature", "id": 23622993, "geometry": {"type": "Point", "coordinates": [-79.051643, 35.999168]}, "properties": {"woe:id": 23622993, "woe:parent_id": 2458524, "woe:name": "Forest View Elementary School", "woe:placetype": 20, "woe:placetype_name": "POI", "woe:lang": "ENG", "iso:country": "US", "meta:provider": ["geoplanet:7.3.1", "geoplanet:7.3.2", "geoplanet:7.4.0", "geoplanet:7.4.1", "geoplanet:7.5.1", "geoplanet:7.5.2", "geoplanet:7.6.0", "geoplanet:7.8.1", "geoplanet:7.9.0", "geoplanet:7.10.0", "geoplanet:8.0.0", "woeplanet:8.0.0"], "meta:indexed": "2020-08-20T20:18:52.472104", "woe:alias_ENG_V": ["Forest View Elementary"], "meta:updated": "2020-10-14T11:19:38.291223", "woe:hierarchy": {"continent": 24865672, "country": 23424977, "town": 0, "planet": 1, "county": 12589441, "suburb": 0, "state": 2347592, "region": 0, "localadmin": 0}, "woe:timezone_id": 56043648, "woe:hash": "dnruc1kq75q9", "woe:centroid": [-79.051643, 35.999168], "geom:latitude": 35.999168, "geom:longitude": -79.051643, "geom:hash": "dnruc1kq75q9", "woe:latitude": 35.999168, "geom:centroid": [-79.051643, 35.999168], "woe:longitude": -79.051643, "woe:repo": "woeplanet-poi-us", "geom:area": 0.0, "woe:scale": 19}}