{"type": "Feature", "id": 56053256, "properties": {"woe:id": 56053256, "woe:parent_id": 2394475, "woe:name": "Ivy Tech State College", "woe:placetype": 20, "woe:placetype_name": "POI", "woe:lang": "ENG", "iso:country": "US", "meta:provider": ["geoplanet:7.3.1", "geoplanet:7.3.2", "geoplanet:7.4.0", "geoplanet:7.4.1", "geoplanet:7.5.1", "geoplanet:7.5.2", "geoplanet:7.6.0", "geoplanet:7.8.1", "geoplanet:7.9.0", "geoplanet:7.10.0", "geoplanet:8.0.0", "woeplanet:8.0.0"], "meta:indexed": "2020-08-20T20:19:16.894828", "meta:updated": "2020-08-22T02:58:20.769947", "woe:hierarchy": {"continent": 24865672, "country": 23424977, "town": 0, "planet": 1, "county": 12588199, "suburb": 0, "state": 2347573, "region": 0, "localadmin": 0}, "woe:timezone_id": 56043656, "woe:hash": "dp6vhubf2q5k", "woe:centroid": [-85.923027, 41.686668], "geom:latitude": 41.686668, "geom:longitude": -85.923027, "geom:hash": "dp6vhubf2q5k", "woe:latitude": 41.686668, "geom:centroid": [-85.923027, 41.686668], "woe:longitude": -85.923027, "woe:repo": "woeplanet-poi-us"}, "geometry": {"coordinates": [-85.923027, 41.686668], "type": "Point"}}