{"type": "Feature", "id": 23594859, "properties": {"woe:id": 23594859, "woe:parent_id": 2372908, "woe:name": "Talahi Community Elementary School", "woe:placetype": 20, "woe:placetype_name": "POI", "woe:lang": "ENG", "iso:country": "US", "meta:provider": ["geoplanet:7.3.1", "geoplanet:7.3.2", "geoplanet:7.4.0", "geoplanet:7.4.1", "geoplanet:7.5.1", "geoplanet:7.5.2", "geoplanet:7.6.0", "geoplanet:7.8.1", "geoplanet:7.9.0", "geoplanet:7.10.0", "geoplanet:8.0.0", "woeplanet:8.0.0"], "meta:indexed": "2020-08-20T20:18:43.036126", "woe:alias_ENG_V": ["Talahi Elementary School", "Talahi Community Elementary"], "meta:updated": "2020-08-22T02:57:40.231025", "woe:hierarchy": {"continent": 24865672, "country": 23424977, "town": 0, "planet": 1, "county": 12588866, "suburb": 0, "state": 2347582, "region": 0, "localadmin": 0}, "woe:timezone_id": 56043661, "woe:hash": "cbj51gvsuzzm", "woe:centroid": [-94.134079, 45.548801], "geom:latitude": 45.548801, "geom:longitude": -94.134079, "geom:hash": "cbj51gvsuzzm", "woe:latitude": 45.548801, "geom:centroid": [-94.134079, 45.548801], "woe:longitude": -94.134079, "woe:repo": "woeplanet-poi-us"}, "geometry": {"coordinates": [-94.134079, 45.548801], "type": "Point"}}