{"type": "Feature", "id": 23571034, "geometry": {"type": "Point", "coordinates": [-98.577393, 38.359829]}, "properties": {"woe:id": 23571034, "woe:parent_id": 2398684, "woe:name": "Ellinwood Elementary School", "woe:placetype": 20, "woe:placetype_name": "POI", "woe:lang": "ENG", "iso:country": "US", "meta:provider": ["geoplanet:7.3.1", "geoplanet:7.3.2", "geoplanet:7.4.0", "geoplanet:7.4.1", "geoplanet:7.5.1", "geoplanet:7.5.2", "geoplanet:7.6.0", "geoplanet:7.8.1", "geoplanet:7.9.0", "geoplanet:7.10.0", "geoplanet:8.0.0", "woeplanet:8.0.0"], "meta:indexed": "2020-08-20T20:18:35.774231", "woe:alias_ENG_V": ["Ellinwood Elementary"], "meta:updated": "2020-10-14T11:20:04.776192", "woe:hierarchy": {"continent": 24865672, "country": 23424977, "town": 0, "planet": 1, "county": 12588375, "suburb": 0, "state": 2347575, "region": 0, "localadmin": 0}, "woe:timezone_id": 56043661, "woe:hash": "9ycfhz4nhq2j", "woe:centroid": [-98.577393, 38.359829], "geom:latitude": 38.359829, "geom:longitude": -98.577393, "geom:hash": "9ycfhz4nhq2j", "woe:latitude": 38.359829, "geom:centroid": [-98.577393, 38.359829], "woe:longitude": -98.577393, "woe:repo": "woeplanet-poi-us", "geom:area": 0.0, "woe:scale": 19}}