{"type": "Feature", "id": 23686035, "geometry": {"type": "Point", "coordinates": [-72.929077, 41.306751]}, "properties": {"woe:id": 23686035, "woe:parent_id": 55860485, "woe:name": "Yale Law School", "woe:placetype": 20, "woe:placetype_name": "POI", "woe:lang": "ENG", "iso:country": "US", "meta:provider": ["geoplanet:7.3.1", "geoplanet:7.3.2", "geoplanet:7.4.0", "geoplanet:7.4.1", "geoplanet:7.5.1", "geoplanet:7.5.2", "geoplanet:7.6.0", "geoplanet:7.8.1", "geoplanet:7.9.0", "geoplanet:7.10.0", "geoplanet:8.0.0", "woeplanet:8.0.0"], "meta:indexed": "2020-08-20T20:19:14.098467", "meta:updated": "2020-10-14T11:19:27.673989", "woe:hierarchy": {"continent": 24865672, "country": 23424977, "town": 0, "planet": 1, "county": 12587795, "suburb": 0, "state": 2347565, "region": 0, "localadmin": 0}, "woe:timezone_id": 56043648, "woe:hash": "drk4urwtm26z", "woe:centroid": [-72.929077, 41.306751], "geom:latitude": 41.306751, "geom:longitude": -72.929077, "geom:hash": "drk4urwtm26z", "woe:latitude": 41.306751, "geom:centroid": [-72.929077, 41.306751], "woe:longitude": -72.929077, "woe:repo": "woeplanet-poi-us", "geom:area": 0.0, "woe:scale": 19}}