{"type": "Feature", "id": 23629685, "geometry": {"type": "Point", "coordinates": [-84.556999, 39.276421]}, "properties": {"woe:id": 23629685, "woe:parent_id": 2458114, "woe:name": "Frost Elementary School", "woe:placetype": 20, "woe:placetype_name": "POI", "woe:lang": "ENG", "iso:country": "US", "meta:provider": ["geoplanet:7.3.1", "geoplanet:7.3.2", "geoplanet:7.4.0", "geoplanet:7.4.1", "geoplanet:7.5.1", "geoplanet:7.5.2", "geoplanet:7.6.0", "geoplanet:7.8.1", "geoplanet:7.9.0", "geoplanet:7.10.0", "geoplanet:8.0.0", "woeplanet:8.0.0"], "meta:indexed": "2020-08-20T20:18:54.340031", "woe:alias_ENG_V": ["Frost Elementary"], "meta:updated": "2020-10-14T11:19:45.556477", "woe:hierarchy": {"continent": 24865672, "country": 23424977, "town": 0, "planet": 1, "county": 12589557, "suburb": 0, "state": 2347594, "region": 0, "localadmin": 0}, "woe:timezone_id": 56043648, "woe:hash": "dngz7y53xpe9", "woe:centroid": [-84.556999, 39.276421], "geom:latitude": 39.276421, "geom:longitude": -84.556999, "geom:hash": "dngz7y53xpe9", "woe:latitude": 39.276421, "geom:centroid": [-84.556999, 39.276421], "woe:longitude": -84.556999, "woe:repo": "woeplanet-poi-us", "geom:area": 0.0, "woe:scale": 19}}