{"type": "Feature", "id": 23590587, "properties": {"woe:id": 23590587, "woe:parent_id": 28743943, "woe:name": "Byron Area Elementary School", "woe:placetype": 20, "woe:placetype_name": "POI", "woe:lang": "ENG", "iso:country": "US", "meta:provider": ["geoplanet:7.3.1", "geoplanet:7.3.2", "geoplanet:7.4.0", "geoplanet:7.4.1", "geoplanet:7.5.1", "geoplanet:7.5.2", "geoplanet:7.6.0", "geoplanet:7.8.1", "geoplanet:7.9.0", "geoplanet:7.10.0", "geoplanet:8.0.0", "woeplanet:8.0.0"], "meta:indexed": "2020-08-20T20:18:41.399180", "woe:alias_ENG_V": ["Byron Area Elementary"], "meta:updated": "2020-08-22T02:57:39.494622", "woe:hierarchy": {"continent": 24865672, "country": 23424977, "town": 0, "planet": 1, "county": 12588789, "suburb": 0, "state": 2347581, "region": 0, "localadmin": 0}, "woe:timezone_id": 56043658, "woe:hash": "dps79gbee35b", "woe:centroid": [-83.945702, 42.82394], "geom:latitude": 42.82394, "geom:longitude": -83.945702, "geom:hash": "dps79gbee35b", "woe:latitude": 42.82394, "geom:centroid": [-83.945702, 42.82394], "woe:longitude": -83.945702, "woe:repo": "woeplanet-poi-us"}, "geometry": {"coordinates": [-83.945702, 42.82394], "type": "Point"}}