{"type": "Feature", "id": 23669664, "geometry": {"type": "Point", "coordinates": [-122.521393, 47.635529]}, "properties": {"woe:id": 23669664, "woe:parent_id": 2358364, "woe:name": "Odyssey Multiage Program", "woe:placetype": 20, "woe:placetype_name": "POI", "woe:lang": "ENG", "iso:country": "US", "meta:provider": ["geoplanet:7.3.1", "geoplanet:7.3.2", "geoplanet:7.4.0", "geoplanet:7.4.1", "geoplanet:7.5.1", "geoplanet:7.5.2", "geoplanet:7.6.0", "geoplanet:7.8.1", "geoplanet:7.9.0", "geoplanet:7.10.0", "geoplanet:8.0.0", "woeplanet:8.0.0"], "meta:indexed": "2020-08-20T20:19:09.502627", "meta:updated": "2020-10-14T11:19:38.754036", "woe:alias_ENG_V": ["Commodore Options School"], "woe:hierarchy": {"continent": 24865672, "country": 23424977, "town": 0, "planet": 1, "county": 12590457, "suburb": 0, "state": 2347606, "region": 0, "localadmin": 0}, "woe:timezone_id": 56043663, "woe:hash": "c22ygzy9hd5y", "woe:centroid": [-122.521393, 47.635529], "geom:latitude": 47.635529, "geom:longitude": -122.521393, "geom:hash": "c22ygzy9hd5y", "woe:latitude": 47.635529, "geom:centroid": [-122.521393, 47.635529], "woe:longitude": -122.521393, "woe:repo": "woeplanet-poi-us", "geom:area": 0.0, "woe:scale": 19}}