{"type": "Feature", "id": 56053428, "properties": {"woe:id": 56053428, "woe:parent_id": 2449854, "woe:name": "College of Southern Nv-Mesquite Center", "woe:placetype": 20, "woe:placetype_name": "POI", "woe:lang": "ENG", "iso:country": "US", "meta:provider": ["geoplanet:7.3.1", "geoplanet:7.3.2", "geoplanet:7.4.0", "geoplanet:7.4.1", "geoplanet:7.5.1", "geoplanet:7.5.2", "geoplanet:7.6.0", "geoplanet:7.8.1", "geoplanet:7.9.0", "geoplanet:7.10.0", "geoplanet:8.0.0", "woeplanet:8.0.0"], "meta:indexed": "2020-08-20T20:19:17.040372", "meta:updated": "2020-08-22T02:58:20.848299", "woe:alias_ENG_V": ["College of Southern Nv-Mesquite Ctr"], "woe:hierarchy": {"continent": 24865672, "country": 23424977, "town": 0, "planet": 1, "county": 12589233, "suburb": 0, "state": 2347587, "region": 0, "localadmin": 0}, "woe:timezone_id": 56043663, "woe:hash": "9qwckk61ms04", "woe:centroid": [-114.068062, 36.805809], "geom:latitude": 36.805809, "geom:longitude": -114.068062, "geom:hash": "9qwckk61ms04", "woe:latitude": 36.805809, "geom:centroid": [-114.068062, 36.805809], "woe:longitude": -114.068062, "woe:repo": "woeplanet-poi-us"}, "geometry": {"coordinates": [-114.068062, 36.805809], "type": "Point"}}