{"type": "Feature", "id": 23523302, "geometry": {"type": "Point", "coordinates": [-121.770981, 36.834991]}, "properties": {"woe:id": 23523302, "woe:parent_id": 2398486, "woe:name": "Moss Landing Middle School", "woe:placetype": 20, "woe:placetype_name": "POI", "woe:lang": "ENG", "iso:country": "US", "meta:provider": ["geoplanet:7.3.1", "geoplanet:7.3.2", "geoplanet:7.4.0", "geoplanet:7.4.1", "geoplanet:7.5.1", "geoplanet:7.5.2", "geoplanet:7.6.0", "geoplanet:7.8.1", "geoplanet:7.9.0", "geoplanet:7.10.0", "geoplanet:8.0.0", "woeplanet:8.0.0"], "meta:indexed": "2020-08-20T20:18:20.113834", "meta:updated": "2020-10-14T11:20:12.735077", "woe:hierarchy": {"continent": 24865672, "country": 23424977, "town": 0, "planet": 1, "county": 12587696, "suburb": 0, "state": 2347563, "region": 0, "localadmin": 0}, "woe:timezone_id": 56043663, "woe:hash": "9q93t1956kp8", "woe:centroid": [-121.770981, 36.834991], "geom:latitude": 36.834991, "geom:longitude": -121.770981, "geom:hash": "9q93t1956kp8", "woe:latitude": 36.834991, "geom:centroid": [-121.770981, 36.834991], "woe:longitude": -121.770981, "woe:repo": "woeplanet-poi-us", "geom:area": 0.0, "woe:scale": 19}}