{"type": "Feature", "id": 23643121, "geometry": {"type": "Point", "coordinates": [-75.467003, 40.21904]}, "properties": {"woe:id": 23643121, "woe:parent_id": 2470644, "woe:name": "Upper Perkiomen Middle School", "woe:placetype": 20, "woe:placetype_name": "POI", "woe:lang": "ENG", "iso:country": "US", "meta:provider": ["geoplanet:7.3.1", "geoplanet:7.3.2", "geoplanet:7.4.0", "geoplanet:7.4.1", "geoplanet:7.5.1", "geoplanet:7.5.2", "geoplanet:7.6.0", "geoplanet:7.8.1", "geoplanet:7.9.0", "geoplanet:7.10.0", "geoplanet:8.0.0", "woeplanet:8.0.0"], "meta:indexed": "2020-08-20T20:18:59.496904", "meta:updated": "2020-10-14T11:19:28.271080", "woe:alias_ENG_V": ["Perkiomen Valley Middle School"], "woe:hierarchy": {"continent": 24865672, "country": 23424977, "town": 0, "planet": 1, "county": 12589773, "suburb": 0, "state": 2347597, "region": 0, "localadmin": 0}, "woe:timezone_id": 56043648, "woe:hash": "dr4kf9wsgk7y", "woe:centroid": [-75.467003, 40.21904], "geom:latitude": 40.21904, "geom:longitude": -75.467003, "geom:hash": "dr4kf9wsgk7y", "woe:latitude": 40.21904, "geom:centroid": [-75.467003, 40.21904], "woe:longitude": -75.467003, "woe:repo": "woeplanet-poi-us", "geom:area": 0.0, "woe:scale": 19}}