{"type": "Feature", "id": 23595017, "properties": {"woe:id": 23595017, "woe:parent_id": 2514561, "woe:name": "Sacred Heart Elementary School", "woe:placetype": 20, "woe:placetype_name": "POI", "woe:lang": "ENG", "iso:country": "US", "meta:provider": ["geoplanet:7.3.1", "geoplanet:7.3.2", "geoplanet:7.4.0", "geoplanet:7.4.1", "geoplanet:7.5.1", "geoplanet:7.5.2", "geoplanet:7.6.0", "geoplanet:7.8.1", "geoplanet:7.9.0", "geoplanet:7.10.0", "geoplanet:8.0.0", "woeplanet:8.0.0"], "meta:indexed": "2020-08-20T20:18:43.098916", "woe:alias_ENG_V": ["Sacred Heart Elementary"], "meta:updated": "2020-08-22T02:57:40.261503", "woe:hierarchy": {"continent": 24865672, "country": 23424977, "town": 0, "planet": 1, "county": 12588877, "suburb": 0, "state": 2347582, "region": 0, "localadmin": 0}, "woe:timezone_id": 56043661, "woe:hash": "9zvdb05fjkfu", "woe:centroid": [-93.510246, 44.077518], "geom:latitude": 44.077518, "geom:longitude": -93.510246, "geom:hash": "9zvdb05fjkfu", "woe:latitude": 44.077518, "geom:centroid": [-93.510246, 44.077518], "woe:longitude": -93.510246, "woe:repo": "woeplanet-poi-us"}, "geometry": {"coordinates": [-93.510246, 44.077518], "type": "Point"}}