{"type": "Feature", "id": 23682516, "geometry": {"type": "Point", "coordinates": [-73.90052, 40.855942]}, "properties": {"woe:id": 23682516, "woe:parent_id": 2404946, "woe:name": "182th-183rd Street Station", "woe:placetype": 20, "woe:placetype_name": "POI", "woe:lang": "ENG", "iso:country": "US", "meta:provider": ["geoplanet:7.3.1", "geoplanet:7.3.2", "geoplanet:7.4.0", "geoplanet:7.4.1", "geoplanet:7.5.1", "geoplanet:7.5.2", "geoplanet:7.6.0", "geoplanet:7.8.1", "geoplanet:7.9.0", "geoplanet:7.10.0", "geoplanet:8.0.0", "woeplanet:8.0.0"], "meta:indexed": "2020-08-20T20:19:19.784129", "woe:alias_ENG_V": ["182th-183rd Street Subway Station", "Subway-182nd St/183rd St-B,d"], "meta:updated": "2020-10-14T11:19:42.197059", "woe:hierarchy": {"continent": 24865672, "country": 23424977, "town": 0, "planet": 1, "county": 12589314, "suburb": 0, "state": 2347591, "region": 0, "localadmin": 0}, "woe:timezone_id": 56043648, "woe:hash": "dr72qme715d7", "woe:centroid": [-73.90052, 40.855942], "geom:latitude": 40.855942, "geom:longitude": -73.90052, "geom:hash": "dr72qme715d7", "woe:latitude": 40.855942, "geom:centroid": [-73.90052, 40.855942], "woe:longitude": -73.90052, "woe:repo": "woeplanet-poi-us", "geom:area": 0.0, "woe:scale": 19}}