{"type": "Feature", "id": 23670431, "geometry": {"type": "Point", "coordinates": [-122.505188, 47.26086]}, "properties": {"woe:id": 23670431, "woe:parent_id": 55862570, "woe:name": "Wilson Senior High School", "woe:placetype": 20, "woe:placetype_name": "POI", "woe:lang": "ENG", "iso:country": "US", "meta:provider": ["geoplanet:7.3.1", "geoplanet:7.3.2", "geoplanet:7.4.0", "geoplanet:7.4.1", "geoplanet:7.5.1", "geoplanet:7.5.2", "geoplanet:7.6.0", "geoplanet:7.8.1", "geoplanet:7.9.0", "geoplanet:7.10.0", "geoplanet:8.0.0", "woeplanet:8.0.0"], "meta:indexed": "2020-08-20T20:19:09.679325", "woe:alias_ENG_V": ["Wilson Senior High", "Wilson High School", "Wilson High", "Wilson Senior HS", "Wilson HS"], "meta:updated": "2020-10-14T11:19:30.199724", "woe:hierarchy": {"continent": 24865672, "country": 23424977, "town": 0, "planet": 1, "county": 12590466, "suburb": 0, "state": 2347606, "region": 0, "localadmin": 0}, "woe:timezone_id": 56043663, "woe:hash": "c22uu7d6qnz5", "woe:centroid": [-122.505188, 47.26086], "geom:latitude": 47.26086, "geom:longitude": -122.505188, "geom:hash": "c22uu7d6qnz5", "woe:latitude": 47.26086, "geom:centroid": [-122.505188, 47.26086], "woe:longitude": -122.505188, "woe:repo": "woeplanet-poi-us", "geom:area": 0.0, "woe:scale": 19}}