{"type": "Feature", "id": 23541502, "geometry": {"type": "Point", "coordinates": [-108.51757, 39.041119]}, "properties": {"woe:id": 23541502, "woe:parent_id": 55973846, "woe:name": "Lincoln Orchard Mesa Elementary School", "woe:placetype": 20, "woe:placetype_name": "POI", "woe:lang": "ENG", "iso:country": "US", "meta:provider": ["geoplanet:7.3.1", "geoplanet:7.3.2", "geoplanet:7.4.0", "geoplanet:7.4.1", "geoplanet:7.5.1", "geoplanet:7.5.2", "geoplanet:7.6.0", "geoplanet:7.8.1", "geoplanet:7.9.0", "geoplanet:7.10.0", "geoplanet:8.0.0", "woeplanet:8.0.0"], "meta:indexed": "2020-08-20T20:18:24.740090", "woe:alias_ENG_V": ["Lincoln Orchard Mesa Elementary"], "meta:updated": "2020-10-14T11:20:19.858470", "woe:hierarchy": {"continent": 24865672, "country": 23424977, "town": 0, "planet": 1, "county": 12587766, "suburb": 0, "state": 2347564, "region": 0, "localadmin": 0}, "woe:timezone_id": 56043665, "woe:hash": "9wfy4e5zj254", "woe:centroid": [-108.51757, 39.041119], "geom:latitude": 39.041119, "geom:longitude": -108.51757, "geom:hash": "9wfy4e5zj254", "woe:latitude": 39.041119, "geom:centroid": [-108.51757, 39.041119], "woe:longitude": -108.51757, "woe:repo": "woeplanet-poi-us", "geom:area": 0.0, "woe:scale": 19}}