{"type": "Feature", "id": 23646196, "properties": {"woe:id": 23646196, "woe:parent_id": 55861277, "woe:name": "Friar Station", "woe:placetype": 20, "woe:placetype_name": "POI", "woe:lang": "ENG", "iso:country": "US", "meta:provider": ["geoplanet:7.3.1", "geoplanet:7.3.2", "geoplanet:7.4.0", "geoplanet:7.4.1", "geoplanet:7.5.1", "geoplanet:7.5.2", "geoplanet:7.6.0", "geoplanet:7.8.1", "geoplanet:7.9.0", "geoplanet:7.10.0", "geoplanet:8.0.0", "woeplanet:8.0.0"], "meta:indexed": "2020-08-20T20:19:00.433222", "meta:updated": "2020-08-22T02:57:47.573850", "woe:hierarchy": {"continent": 24865672, "country": 23424977, "town": 0, "planet": 1, "county": 12589798, "suburb": 0, "state": 2347598, "region": 0, "localadmin": 0}, "woe:timezone_id": 56043648, "woe:hash": "drmnn3632k50", "woe:centroid": [-71.440987, 41.84304], "geom:latitude": 41.84304, "geom:longitude": -71.440987, "geom:hash": "drmnn3632k50", "woe:latitude": 41.84304, "geom:centroid": [-71.440987, 41.84304], "woe:longitude": -71.440987, "woe:repo": "woeplanet-poi-us"}, "geometry": {"coordinates": [-71.440987, 41.84304], "type": "Point"}}