{"type": "Feature", "id": 23567023, "geometry": {"type": "Point", "coordinates": [-85.651871, 40.12051]}, "properties": {"woe:id": 23567023, "woe:parent_id": 2354570, "woe:name": "East Side Middle School", "woe:placetype": 20, "woe:placetype_name": "POI", "woe:lang": "ENG", "iso:country": "US", "meta:provider": ["geoplanet:7.3.2", "geoplanet:7.4.0", "geoplanet:7.4.1", "geoplanet:7.5.1", "geoplanet:7.5.2", "geoplanet:7.6.0", "geoplanet:7.8.1", "geoplanet:7.9.0", "geoplanet:7.10.0", "geoplanet:8.0.0", "woeplanet:8.0.0"], "meta:indexed": "2020-08-20T22:02:17.228941", "woe:alias_ENG_V": ["E Side Middle School"], "meta:updated": "2020-10-14T11:20:13.128494", "woe:hierarchy": {"continent": 24865672, "country": 23424977, "town": 0, "planet": 1, "county": 12588227, "suburb": 0, "state": 2347573, "region": 0, "localadmin": 0}, "woe:timezone_id": 56043656, "woe:hash": "dp5h4zwnytpu", "woe:centroid": [-85.651871, 40.12051], "geom:latitude": 40.12051, "geom:longitude": -85.651871, "geom:hash": "dp5h4zwnytpu", "woe:latitude": 40.12051, "geom:centroid": [-85.651871, 40.12051], "woe:longitude": -85.651871, "woe:repo": "woeplanet-poi-us", "geom:area": 0.0, "woe:scale": 19}}