{"type": "Feature", "id": 23550866, "geometry": {"type": "Point", "coordinates": [-81.96064, 27.89842]}, "properties": {"woe:id": 23550866, "woe:parent_id": 2456185, "woe:name": "Mulberry Senior High School", "woe:placetype": 20, "woe:placetype_name": "POI", "woe:lang": "ENG", "iso:country": "US", "meta:provider": ["geoplanet:7.3.1", "geoplanet:7.3.2", "geoplanet:7.4.0", "geoplanet:7.4.1", "geoplanet:7.5.1", "geoplanet:7.5.2", "geoplanet:7.6.0", "geoplanet:7.8.1", "geoplanet:7.9.0", "geoplanet:7.10.0", "geoplanet:8.0.0", "woeplanet:8.0.0"], "meta:indexed": "2020-08-20T20:18:28.602219", "woe:alias_ENG_V": ["Mulberry Senior High", "Mulberry High School", "Mulberry High", "Mulberry Senior HS", "Mulberry HS"], "meta:updated": "2020-10-14T11:20:12.295598", "woe:hierarchy": {"continent": 24865672, "country": 23424977, "town": 0, "planet": 1, "county": 12587855, "suburb": 0, "state": 2347568, "region": 0, "localadmin": 0}, "woe:timezone_id": 56043648, "woe:hash": "dhvwwyy04dmm", "woe:centroid": [-81.96064, 27.89842], "geom:latitude": 27.89842, "geom:longitude": -81.96064, "geom:hash": "dhvwwyy04dmm", "woe:latitude": 27.89842, "geom:centroid": [-81.96064, 27.89842], "woe:longitude": -81.96064, "woe:repo": "woeplanet-poi-us", "geom:area": 0.0, "woe:scale": 19}}