{"type": "Feature", "id": 23572009, "geometry": {"type": "Point", "coordinates": [-101.012177, 39.10461]}, "properties": {"woe:id": 23572009, "woe:parent_id": 2453610, "woe:name": "Monument Elementary School", "woe:placetype": 20, "woe:placetype_name": "POI", "woe:lang": "ENG", "iso:country": "US", "meta:provider": ["geoplanet:7.3.1", "geoplanet:7.3.2", "geoplanet:7.4.0", "geoplanet:7.4.1", "geoplanet:7.5.1", "geoplanet:7.5.2", "geoplanet:7.6.0", "geoplanet:7.8.1", "geoplanet:7.9.0", "geoplanet:7.10.0", "geoplanet:8.0.0", "woeplanet:8.0.0"], "meta:indexed": "2020-08-20T20:18:36.161821", "woe:alias_ENG_V": ["Monument Elementary"], "meta:updated": "2020-10-14T11:20:17.379429", "woe:hierarchy": {"continent": 24865672, "country": 23424977, "town": 0, "planet": 1, "county": 12588425, "suburb": 0, "state": 2347575, "region": 0, "localadmin": 0}, "woe:timezone_id": 56043661, "woe:hash": "9ybnmqv0vets", "woe:centroid": [-101.012177, 39.10461], "geom:latitude": 39.10461, "geom:longitude": -101.012177, "geom:hash": "9ybnmqv0vets", "woe:latitude": 39.10461, "geom:centroid": [-101.012177, 39.10461], "woe:longitude": -101.012177, "woe:repo": "woeplanet-poi-us", "geom:area": 0.0, "woe:scale": 19}}