{"type": "Feature", "id": 23569713, "properties": {"woe:id": 23569713, "woe:parent_id": 2453450, "woe:name": "Shannon Elementary School", "woe:placetype": 20, "woe:placetype_name": "POI", "woe:lang": "ENG", "iso:country": "US", "meta:provider": ["geoplanet:7.3.1", "geoplanet:7.3.2", "geoplanet:7.4.0", "geoplanet:7.4.1", "geoplanet:7.5.1", "geoplanet:7.5.2", "geoplanet:7.6.0", "geoplanet:7.8.1", "geoplanet:7.9.0", "geoplanet:7.10.0", "geoplanet:8.0.0", "woeplanet:8.0.0"], "meta:indexed": "2020-08-20T20:18:35.227573", "woe:alias_ENG_V": ["Shannon Elementary"], "meta:updated": "2020-08-22T02:57:36.179855", "woe:hierarchy": {"continent": 24865672, "country": 23424977, "town": 0, "planet": 1, "county": 12588324, "suburb": 0, "state": 2347574, "region": 0, "localadmin": 0}, "woe:timezone_id": 56043661, "woe:hash": "9zx0kb5th4fe", "woe:centroid": [-91.192528, 42.232319], "geom:latitude": 42.232319, "geom:longitude": -91.192528, "geom:hash": "9zx0kb5th4fe", "woe:latitude": 42.232319, "geom:centroid": [-91.192528, 42.232319], "woe:longitude": -91.192528, "woe:repo": "woeplanet-poi-us"}, "geometry": {"coordinates": [-91.192528, 42.232319], "type": "Point"}}