{"type": "Feature", "id": 23547145, "properties": {"woe:id": 23547145, "woe:parent_id": 2522300, "woe:name": "Maxey Elementary School", "woe:placetype": 20, "woe:placetype_name": "POI", "woe:lang": "ENG", "iso:country": "US", "meta:provider": ["geoplanet:7.3.1", "geoplanet:7.3.2", "geoplanet:7.4.0", "geoplanet:7.4.1", "geoplanet:7.5.1", "geoplanet:7.5.2", "geoplanet:7.6.0", "geoplanet:7.8.1", "geoplanet:7.9.0", "geoplanet:7.10.0", "geoplanet:8.0.0", "woeplanet:8.0.0"], "meta:indexed": "2020-08-20T20:18:26.736688", "woe:alias_ENG_V": ["William S Maxey Elementary School", "Maxey Elementary"], "meta:updated": "2020-08-22T02:57:31.907329", "woe:hierarchy": {"continent": 24865672, "country": 23424977, "town": 0, "planet": 1, "county": 12587850, "suburb": 0, "state": 2347568, "region": 0, "localadmin": 0}, "woe:timezone_id": 56043648, "woe:hash": "djjfrzs49yqu", "woe:centroid": [-81.567909, 28.56217], "geom:latitude": 28.56217, "geom:longitude": -81.567909, "geom:hash": "djjfrzs49yqu", "woe:latitude": 28.56217, "geom:centroid": [-81.567909, 28.56217], "woe:longitude": -81.567909, "woe:repo": "woeplanet-poi-us"}, "geometry": {"coordinates": [-81.567909, 28.56217], "type": "Point"}}