{"type": "Feature", "id": 23607534, "geometry": {"type": "Point", "coordinates": [-74.796959, 40.120029]}, "properties": {"woe:id": 23607534, "woe:parent_id": 2404498, "woe:name": "Florence Twp. Middle School", "woe:placetype": 20, "woe:placetype_name": "POI", "woe:lang": "ENG", "iso:country": "US", "meta:provider": ["geoplanet:7.3.1", "geoplanet:7.3.2", "geoplanet:7.4.0", "geoplanet:7.4.1", "geoplanet:7.5.1", "geoplanet:7.5.2", "geoplanet:7.6.0", "geoplanet:7.8.1", "geoplanet:7.9.0", "geoplanet:7.10.0", "geoplanet:8.0.0", "woeplanet:8.0.0"], "meta:indexed": "2020-08-20T20:18:46.785736", "meta:updated": "2020-10-14T11:19:54.079774", "woe:hierarchy": {"continent": 24865672, "country": 23424977, "town": 0, "planet": 1, "county": 12589260, "suburb": 0, "state": 2347589, "region": 0, "localadmin": 0}, "woe:timezone_id": 56043648, "woe:hash": "dr4u1zws0e3p", "woe:centroid": [-74.796959, 40.120029], "geom:latitude": 40.120029, "geom:longitude": -74.796959, "geom:hash": "dr4u1zws0e3p", "woe:latitude": 40.120029, "geom:centroid": [-74.796959, 40.120029], "woe:longitude": -74.796959, "woe:repo": "woeplanet-poi-us", "geom:area": 0.0, "woe:scale": 19}}