{"type": "Feature", "id": 23685306, "geometry": {"type": "Point", "coordinates": [-104.258118, 32.441139]}, "properties": {"woe:id": 23685306, "woe:parent_id": 2375061, "woe:name": "Carlsbad Mall", "woe:placetype": 20, "woe:placetype_name": "POI", "woe:lang": "ENG", "iso:country": "US", "meta:provider": ["geoplanet:7.3.1", "geoplanet:7.3.2", "geoplanet:7.4.0", "geoplanet:7.4.1", "geoplanet:7.5.1", "geoplanet:7.5.2", "geoplanet:7.6.0", "geoplanet:7.8.1", "geoplanet:7.9.0", "geoplanet:7.10.0", "geoplanet:8.0.0", "woeplanet:8.0.0"], "meta:indexed": "2020-08-20T20:19:13.599538", "meta:updated": "2020-10-14T11:19:50.528675", "woe:hierarchy": {"continent": 24865672, "country": 23424977, "town": 0, "planet": 1, "county": 12589287, "suburb": 0, "state": 2347590, "region": 0, "localadmin": 0}, "woe:timezone_id": 56043665, "woe:hash": "9tvbe99x3f8s", "woe:centroid": [-104.258118, 32.441139], "geom:latitude": 32.441139, "geom:longitude": -104.258118, "geom:hash": "9tvbe99x3f8s", "woe:latitude": 32.441139, "geom:centroid": [-104.258118, 32.441139], "woe:longitude": -104.258118, "woe:repo": "woeplanet-poi-us", "geom:area": 0.0, "woe:scale": 19}}