{"type": "Feature", "id": 23656615, "properties": {"woe:id": 23656615, "woe:parent_id": 2497078, "woe:name": "The Bridges Academy Alter", "woe:placetype": 20, "woe:placetype_name": "POI", "woe:lang": "ENG", "iso:country": "US", "meta:provider": ["geoplanet:7.3.1", "geoplanet:7.3.2", "geoplanet:7.4.0", "geoplanet:7.4.1", "geoplanet:7.5.1", "geoplanet:7.5.2", "geoplanet:7.6.0", "geoplanet:7.8.1", "geoplanet:7.9.0", "geoplanet:7.10.0", "geoplanet:8.0.0", "woeplanet:8.0.0"], "meta:indexed": "2020-08-20T20:19:04.473015", "meta:updated": "2020-08-22T02:57:49.613214", "woe:hierarchy": {"continent": 24865672, "country": 23424977, "town": 0, "planet": 1, "county": 12590226, "suburb": 0, "state": 2347602, "region": 0, "localadmin": 0}, "woe:timezone_id": 56043661, "woe:hash": "9vfgq0bgvg59", "woe:centroid": [-97.117859, 32.919819], "geom:latitude": 32.919819, "geom:longitude": -97.117859, "geom:hash": "9vfgq0bgvg59", "woe:latitude": 32.919819, "geom:centroid": [-97.117859, 32.919819], "woe:longitude": -97.117859, "woe:repo": "woeplanet-poi-us"}, "geometry": {"coordinates": [-97.117859, 32.919819], "type": "Point"}}