{"type": "Feature", "id": 23587896, "properties": {"woe:id": 23587896, "woe:parent_id": 2475549, "woe:name": "Portage Central High School", "woe:placetype": 20, "woe:placetype_name": "POI", "woe:lang": "ENG", "iso:country": "US", "meta:provider": ["geoplanet:7.3.2", "geoplanet:7.4.0", "geoplanet:7.4.1", "geoplanet:7.5.1", "geoplanet:7.5.2", "geoplanet:7.6.0", "geoplanet:7.8.1", "geoplanet:7.9.0", "geoplanet:7.10.0", "geoplanet:8.0.0", "woeplanet:8.0.0"], "meta:indexed": "2020-08-20T22:02:25.618727", "woe:alias_ENG_V": ["Portage Central Senior High School", "Portage Central High", "Portage Central Senior High", "Portage Central HS", "Portage Central Senior HS"], "meta:updated": "2020-08-22T02:58:47.947391", "woe:hierarchy": {"continent": 24865672, "country": 23424977, "town": 0, "planet": 1, "county": 12588752, "suburb": 0, "state": 2347581, "region": 0, "localadmin": 0}, "woe:timezone_id": 56043658, "woe:hash": "dpe0h65f9ncc", "woe:centroid": [-85.589287, 42.198952], "geom:latitude": 42.198952, "geom:longitude": -85.589287, "geom:hash": "dpe0h65f9ncc", "woe:latitude": 42.198952, "geom:centroid": [-85.589287, 42.198952], "woe:longitude": -85.589287, "woe:repo": "woeplanet-poi-us"}, "geometry": {"coordinates": [-85.589287, 42.198952], "type": "Point"}}