{"type": "Feature", "id": 23684806, "geometry": {"type": "Point", "coordinates": [-86.516068, 38.860981]}, "properties": {"woe:id": 23684806, "woe:parent_id": 2361179, "woe:name": "Stone City Mall", "woe:placetype": 20, "woe:placetype_name": "POI", "woe:lang": "ENG", "iso:country": "US", "meta:provider": ["geoplanet:7.3.1", "geoplanet:7.3.2", "geoplanet:7.4.0", "geoplanet:7.4.1", "geoplanet:7.5.1", "geoplanet:7.5.2", "geoplanet:7.6.0", "geoplanet:7.8.1", "geoplanet:7.9.0", "geoplanet:7.10.0", "geoplanet:8.0.0", "woeplanet:8.0.0"], "meta:indexed": "2020-08-20T20:19:13.218895", "meta:updated": "2020-10-14T11:19:33.666440", "woe:hierarchy": {"continent": 24865672, "country": 23424977, "town": 0, "planet": 1, "county": 12588226, "suburb": 0, "state": 2347573, "region": 0, "localadmin": 0}, "woe:timezone_id": 56043656, "woe:hash": "dnfmp62vt7zv", "woe:centroid": [-86.516068, 38.860981], "geom:latitude": 38.860981, "geom:longitude": -86.516068, "geom:hash": "dnfmp62vt7zv", "woe:latitude": 38.860981, "geom:centroid": [-86.516068, 38.860981], "woe:longitude": -86.516068, "woe:repo": "woeplanet-poi-us", "geom:area": 0.0, "woe:scale": 19}}