{"type": "Feature", "id": 23515661, "properties": {"woe:id": 23515661, "woe:parent_id": 29230214, "woe:name": "Hall of Flame Museum of Firefightng", "woe:placetype": 20, "woe:placetype_name": "POI", "woe:lang": "ENG", "iso:country": "US", "meta:provider": ["geoplanet:7.4.0", "geoplanet:7.4.1", "geoplanet:7.5.1", "geoplanet:7.5.2", "geoplanet:7.6.0", "geoplanet:7.8.1", "geoplanet:7.9.0", "geoplanet:7.10.0", "geoplanet:8.0.0", "woeplanet:8.0.0"], "meta:indexed": "2020-08-20T23:54:24.436387", "meta:updated": "2020-08-22T02:57:26.510636", "woe:alias_ENG_V": ["Hall of Flame Fire Museum"], "woe:hierarchy": {"continent": 24865672, "country": 23424977, "town": 0, "planet": 1, "county": 12587587, "suburb": 0, "state": 2347561, "region": 0, "localadmin": 0}, "woe:timezone_id": 56043666, "woe:hash": "9tbqk2yj802h", "woe:centroid": [-111.95343, 33.447449], "geom:latitude": 33.447449, "geom:longitude": -111.95343, "geom:hash": "9tbqk2yj802h", "woe:latitude": 33.447449, "geom:centroid": [-111.95343, 33.447449], "woe:longitude": -111.95343, "woe:repo": "woeplanet-poi-us"}, "geometry": {"coordinates": [-111.95343, 33.447449], "type": "Point"}}