{"type": "Feature", "id": 23604388, "properties": {"woe:id": 23604388, "woe:parent_id": 56022183, "woe:name": "Sunrise Acres Elementary School", "woe:placetype": 20, "woe:placetype_name": "POI", "woe:lang": "ENG", "iso:country": "US", "meta:provider": ["geoplanet:7.4.0", "geoplanet:7.4.1", "geoplanet:7.5.1", "geoplanet:7.5.2", "geoplanet:7.6.0", "geoplanet:7.8.1", "geoplanet:7.9.0", "geoplanet:7.10.0", "geoplanet:8.0.0", "woeplanet:8.0.0"], "meta:indexed": "2020-08-20T23:56:00.912001", "meta:updated": "2020-08-22T02:58:23.418780", "woe:hierarchy": {"continent": 24865672, "country": 23424977, "town": 0, "planet": 1, "county": 12589233, "suburb": 0, "state": 2347587, "region": 0, "localadmin": 0}, "woe:timezone_id": 56043663, "woe:hash": "9qqjsrpvbd0x", "woe:centroid": [-115.115067, 36.162498], "geom:latitude": 36.162498, "geom:longitude": -115.115067, "geom:hash": "9qqjsrpvbd0x", "woe:latitude": 36.162498, "geom:centroid": [-115.115067, 36.162498], "woe:longitude": -115.115067, "woe:repo": "woeplanet-poi-us"}, "geometry": {"coordinates": [-115.115067, 36.162498], "type": "Point"}}