{"type": "Feature", "id": 23516468, "properties": {"woe:id": 23516468, "woe:parent_id": 2446585, "woe:name": "Southwest Christian School", "woe:placetype": 20, "woe:placetype_name": "POI", "woe:lang": "ENG", "iso:country": "US", "meta:provider": ["geoplanet:7.3.1", "geoplanet:7.3.2", "geoplanet:7.4.0", "geoplanet:7.4.1", "geoplanet:7.5.1", "geoplanet:7.5.2", "geoplanet:7.6.0", "geoplanet:7.8.1", "geoplanet:7.9.0", "geoplanet:7.10.0", "geoplanet:8.0.0", "woeplanet:8.0.0"], "meta:indexed": "2020-08-20T20:18:18.452075", "woe:alias_ENG_V": ["Southwest Christian Elementary Sch", "SW Christian School"], "meta:updated": "2020-08-22T02:57:26.683343", "woe:hierarchy": {"continent": 24865672, "country": 23424977, "town": 0, "planet": 1, "county": 12587587, "suburb": 0, "state": 2347561, "region": 0, "localadmin": 0}, "woe:timezone_id": 56043666, "woe:hash": "9tbntc2jum0g", "woe:centroid": [-112.247131, 33.494209], "geom:latitude": 33.494209, "geom:longitude": -112.247131, "geom:hash": "9tbntc2jum0g", "woe:latitude": 33.494209, "geom:centroid": [-112.247131, 33.494209], "woe:longitude": -112.247131, "woe:repo": "woeplanet-poi-us"}, "geometry": {"coordinates": [-112.247131, 33.494209], "type": "Point"}}