{"type": "Feature", "id": 23667198, "geometry": {"type": "Point", "coordinates": [-79.884804, 36.691238]}, "properties": {"woe:id": 23667198, "woe:parent_id": 2446415, "woe:name": "Albert Harris Intermediate School", "woe:placetype": 20, "woe:placetype_name": "POI", "woe:lang": "ENG", "iso:country": "US", "meta:provider": ["geoplanet:7.3.1", "geoplanet:7.3.2", "geoplanet:7.4.0", "geoplanet:7.4.1", "geoplanet:7.5.1", "geoplanet:7.5.2", "geoplanet:7.6.0", "geoplanet:7.8.1", "geoplanet:7.9.0", "geoplanet:7.10.0", "geoplanet:8.0.0", "woeplanet:8.0.0"], "meta:indexed": "2020-08-20T20:19:08.642387", "meta:updated": "2020-10-14T11:19:38.440361", "woe:alias_ENG_V": ["Albert Harris Elementary School"], "woe:hierarchy": {"continent": 24865672, "country": 23424977, "town": 0, "planet": 1, "county": 12590383, "suburb": 0, "state": 2347605, "region": 0, "localadmin": 0}, "woe:timezone_id": 56043648, "woe:hash": "dnx0wpmtvnsb", "woe:centroid": [-79.884804, 36.691238], "geom:latitude": 36.691238, "geom:longitude": -79.884804, "geom:hash": "dnx0wpmtvnsb", "woe:latitude": 36.691238, "geom:centroid": [-79.884804, 36.691238], "woe:longitude": -79.884804, "woe:repo": "woeplanet-poi-us", "geom:area": 0.0, "woe:scale": 19}}