{"type": "Feature", "id": 23517927, "properties": {"woe:id": 23517927, "woe:parent_id": 2514376, "woe:name": "Warren Junior High School", "woe:placetype": 20, "woe:placetype_name": "POI", "woe:lang": "ENG", "iso:country": "US", "meta:provider": ["geoplanet:7.3.1", "geoplanet:7.3.2", "geoplanet:7.4.0", "geoplanet:7.4.1", "geoplanet:7.5.1", "geoplanet:7.5.2", "geoplanet:7.6.0", "geoplanet:7.8.1", "geoplanet:7.9.0", "geoplanet:7.10.0", "geoplanet:8.0.0", "woeplanet:8.0.0"], "meta:indexed": "2020-08-20T20:18:18.899362", "woe:alias_ENG_V": ["Warren Junior High"], "meta:updated": "2020-08-22T02:57:26.892019", "woe:hierarchy": {"continent": 24865672, "country": 23424977, "town": 0, "planet": 1, "county": 12587600, "suburb": 0, "state": 2347562, "region": 0, "localadmin": 0}, "woe:timezone_id": 56043661, "woe:hash": "9vyx0zve22e5", "woe:centroid": [-92.068848, 33.617352], "geom:latitude": 33.617352, "geom:longitude": -92.068848, "geom:hash": "9vyx0zve22e5", "woe:latitude": 33.617352, "geom:centroid": [-92.068848, 33.617352], "woe:longitude": -92.068848, "woe:repo": "woeplanet-poi-us"}, "geometry": {"coordinates": [-92.068848, 33.617352], "type": "Point"}}