{"type": "Feature", "id": 23563508, "geometry": {"type": "Point", "coordinates": [-89.129883, 38.532051]}, "properties": {"woe:id": 23563508, "woe:parent_id": 2377646, "woe:name": "Lincoln Elementary School", "woe:placetype": 20, "woe:placetype_name": "POI", "woe:lang": "ENG", "iso:country": "US", "meta:provider": ["geoplanet:7.3.1", "geoplanet:7.3.2", "geoplanet:7.4.0", "geoplanet:7.4.1", "geoplanet:7.5.1", "geoplanet:7.5.2", "geoplanet:7.6.0", "geoplanet:7.8.1", "geoplanet:7.9.0", "geoplanet:7.10.0", "geoplanet:8.0.0", "woeplanet:8.0.0"], "meta:indexed": "2020-08-20T20:18:32.864268", "woe:alias_ENG_V": ["Lincoln Elementary"], "meta:updated": "2020-10-14T11:20:03.085636", "woe:hierarchy": {"continent": 24865672, "country": 23424977, "town": 0, "planet": 1, "county": 12588135, "suburb": 0, "state": 2347572, "region": 0, "localadmin": 0}, "woe:timezone_id": 56043661, "woe:hash": "dnbe5y997nym", "woe:centroid": [-89.129883, 38.532051], "geom:latitude": 38.532051, "geom:longitude": -89.129883, "geom:hash": "dnbe5y997nym", "woe:latitude": 38.532051, "geom:centroid": [-89.129883, 38.532051], "woe:longitude": -89.129883, "woe:repo": "woeplanet-poi-us", "geom:area": 0.0, "woe:scale": 19}}