{"type": "Feature", "id": 23517271, "properties": {"woe:id": 23517271, "woe:parent_id": 55805862, "woe:name": "Tucson Christian School", "woe:placetype": 20, "woe:placetype_name": "POI", "woe:lang": "ENG", "iso:country": "US", "meta:provider": ["geoplanet:7.3.2", "geoplanet:7.4.0", "geoplanet:7.4.1", "geoplanet:7.5.1", "geoplanet:7.5.2", "geoplanet:7.6.0", "geoplanet:7.8.1", "geoplanet:7.9.0", "geoplanet:7.10.0", "geoplanet:8.0.0", "woeplanet:8.0.0"], "meta:indexed": "2020-08-20T22:01:57.020236", "meta:updated": "2020-08-22T02:57:26.812761", "woe:hierarchy": {"continent": 24865672, "country": 23424977, "town": 0, "planet": 1, "county": 12587590, "suburb": 0, "state": 2347561, "region": 0, "localadmin": 0}, "woe:timezone_id": 56043666, "woe:hash": "9t9psbx11zch", "woe:centroid": [-110.87532, 32.25882], "geom:latitude": 32.25882, "geom:longitude": -110.87532, "geom:hash": "9t9psbx11zch", "woe:latitude": 32.25882, "geom:centroid": [-110.87532, 32.25882], "woe:longitude": -110.87532, "woe:repo": "woeplanet-poi-us"}, "geometry": {"coordinates": [-110.87532, 32.25882], "type": "Point"}}