{"type": "Feature", "id": 23641887, "properties": {"woe:id": 23641887, "woe:parent_id": 2436076, "woe:name": "King Elementary School", "woe:placetype": 20, "woe:placetype_name": "POI", "woe:lang": "ENG", "iso:country": "US", "meta:provider": ["geoplanet:7.3.1", "geoplanet:7.3.2", "geoplanet:7.4.0", "geoplanet:7.4.1", "geoplanet:7.5.1", "geoplanet:7.5.2", "geoplanet:7.6.0", "geoplanet:7.8.1", "geoplanet:7.9.0", "geoplanet:7.10.0", "geoplanet:8.0.0", "woeplanet:8.0.0"], "meta:indexed": "2020-08-20T20:18:59.055473", "woe:alias_ENG_V": ["King Elementary"], "meta:updated": "2020-08-22T02:57:46.957488", "woe:hierarchy": {"continent": 24865672, "country": 23424977, "town": 0, "planet": 1, "county": 12589763, "suburb": 0, "state": 2347597, "region": 0, "localadmin": 0}, "woe:timezone_id": 56043648, "woe:hash": "dr1exxzkd7zw", "woe:centroid": [-76.300972, 40.0336], "geom:latitude": 40.0336, "geom:longitude": -76.300972, "geom:hash": "dr1exxzkd7zw", "woe:latitude": 40.0336, "geom:centroid": [-76.300972, 40.0336], "woe:longitude": -76.300972, "woe:repo": "woeplanet-poi-us"}, "geometry": {"coordinates": [-76.300972, 40.0336], "type": "Point"}}