{"type": "Feature", "id": 23643063, "geometry": {"type": "Point", "coordinates": [-75.34893, 40.236649]}, "properties": {"woe:id": 23643063, "woe:parent_id": 2434009, "woe:name": "General Nash Elementary School", "woe:placetype": 20, "woe:placetype_name": "POI", "woe:lang": "ENG", "iso:country": "US", "meta:provider": ["geoplanet:7.3.1", "geoplanet:7.3.2", "geoplanet:7.4.0", "geoplanet:7.4.1", "geoplanet:7.5.1", "geoplanet:7.5.2", "geoplanet:7.6.0", "geoplanet:7.8.1", "geoplanet:7.9.0", "geoplanet:7.10.0", "geoplanet:8.0.0", "woeplanet:8.0.0"], "meta:indexed": "2020-08-20T20:18:59.452349", "woe:alias_ENG_V": ["General Nash Elementary"], "meta:updated": "2020-10-14T11:19:37.886115", "woe:hierarchy": {"continent": 24865672, "country": 23424977, "town": 0, "planet": 1, "county": 12589773, "suburb": 0, "state": 2347597, "region": 0, "localadmin": 0}, "woe:timezone_id": 56043648, "woe:hash": "dr4kvkue6xj8", "woe:centroid": [-75.34893, 40.236649], "geom:latitude": 40.236649, "geom:longitude": -75.34893, "geom:hash": "dr4kvkue6xj8", "woe:latitude": 40.236649, "geom:centroid": [-75.34893, 40.236649], "woe:longitude": -75.34893, "woe:repo": "woeplanet-poi-us", "geom:area": 0.0, "woe:scale": 19}}