{"type": "Feature", "id": 23536882, "properties": {"woe:id": 23536882, "woe:parent_id": 55969249, "woe:name": "Karl H. Kellogg Elementary School", "woe:placetype": 20, "woe:placetype_name": "POI", "woe:lang": "ENG", "iso:country": "US", "meta:provider": ["geoplanet:7.3.1", "geoplanet:7.3.2", "geoplanet:7.4.0", "geoplanet:7.4.1", "geoplanet:7.5.1", "geoplanet:7.5.2", "geoplanet:7.6.0", "geoplanet:7.8.1", "geoplanet:7.9.0", "geoplanet:7.10.0", "geoplanet:8.0.0", "woeplanet:8.0.0"], "meta:indexed": "2020-08-20T20:18:23.387371", "woe:alias_ENG_V": ["Kellogg Elementary School", "Karl H. Kellogg Elementary"], "meta:updated": "2020-08-22T02:57:29.907537", "woe:hierarchy": {"continent": 24865672, "country": 23424977, "town": 0, "planet": 1, "county": 12587706, "suburb": 0, "state": 2347563, "region": 0, "localadmin": 0}, "woe:timezone_id": 56043663, "woe:hash": "9muc8d0nzkrp", "woe:centroid": [-117.048019, 32.619591], "geom:latitude": 32.619591, "geom:longitude": -117.048019, "geom:hash": "9muc8d0nzkrp", "woe:latitude": 32.619591, "geom:centroid": [-117.048019, 32.619591], "woe:longitude": -117.048019, "woe:repo": "woeplanet-poi-us"}, "geometry": {"coordinates": [-117.048019, 32.619591], "type": "Point"}}