{"type": "Feature", "id": 23637399, "properties": {"woe:id": 23637399, "woe:parent_id": 2395028, "woe:name": "Western Mennonite School", "woe:placetype": 20, "woe:placetype_name": "POI", "woe:lang": "ENG", "iso:country": "US", "meta:provider": ["geoplanet:7.3.1", "geoplanet:7.3.2", "geoplanet:7.4.0", "geoplanet:7.4.1", "geoplanet:7.5.1", "geoplanet:7.5.2", "geoplanet:7.6.0", "geoplanet:7.8.1", "geoplanet:7.9.0", "geoplanet:7.10.0", "geoplanet:8.0.0", "woeplanet:8.0.0"], "meta:indexed": "2020-08-20T20:18:57.412877", "meta:updated": "2020-08-22T02:57:46.256673", "woe:hierarchy": {"continent": 24865672, "country": 23424977, "town": 0, "planet": 1, "county": 12589718, "suburb": 0, "state": 2347596, "region": 0, "localadmin": 0}, "woe:timezone_id": 56043663, "woe:hash": "c202rmjd7d9z", "woe:centroid": [-123.072128, 45.071812], "geom:latitude": 45.071812, "geom:longitude": -123.072128, "geom:hash": "c202rmjd7d9z", "woe:latitude": 45.071812, "geom:centroid": [-123.072128, 45.071812], "woe:longitude": -123.072128, "woe:repo": "woeplanet-poi-us"}, "geometry": {"coordinates": [-123.072128, 45.071812], "type": "Point"}}