{"type": "Feature", "id": 23600822, "geometry": {"type": "Point", "coordinates": [-105.840912, 46.404549]}, "properties": {"woe:id": 23600822, "woe:parent_id": 2450922, "woe:name": "S H School", "woe:placetype": 20, "woe:placetype_name": "POI", "woe:lang": "ENG", "iso:country": "US", "meta:provider": ["geoplanet:7.3.1", "geoplanet:7.3.2", "geoplanet:7.4.0", "geoplanet:7.4.1", "geoplanet:7.5.1", "geoplanet:7.5.2", "geoplanet:7.6.0", "geoplanet:7.8.1", "geoplanet:7.9.0", "geoplanet:7.10.0", "geoplanet:8.0.0", "woeplanet:8.0.0"], "meta:indexed": "2020-08-20T20:18:45.162232", "meta:updated": "2020-10-14T11:19:39.981060", "woe:hierarchy": {"continent": 24865672, "country": 23424977, "town": 0, "planet": 1, "county": 12589089, "suburb": 0, "state": 2347585, "region": 0, "localadmin": 0}, "woe:timezone_id": 56043665, "woe:hash": "c8hxzx8ypfzv", "woe:centroid": [-105.840912, 46.404549], "geom:latitude": 46.404549, "geom:longitude": -105.840912, "geom:hash": "c8hxzx8ypfzv", "woe:latitude": 46.404549, "geom:centroid": [-105.840912, 46.404549], "woe:longitude": -105.840912, "woe:repo": "woeplanet-poi-us", "geom:area": 0.0, "woe:scale": 19}}