{"type": "Feature", "id": 23642906, "geometry": {"type": "Point", "coordinates": [-77.572929, 40.600288]}, "properties": {"woe:id": 23642906, "woe:parent_id": 2433379, "woe:name": "Sacred Heart of Jesus School", "woe:placetype": 20, "woe:placetype_name": "POI", "woe:lang": "ENG", "iso:country": "US", "meta:provider": ["geoplanet:7.3.2", "geoplanet:7.4.0", "geoplanet:7.4.1", "geoplanet:7.5.1", "geoplanet:7.5.2", "geoplanet:7.6.0", "geoplanet:7.8.1", "geoplanet:7.9.0", "geoplanet:7.10.0", "geoplanet:8.0.0", "woeplanet:8.0.0"], "meta:indexed": "2020-08-20T22:02:48.197035", "meta:updated": "2020-10-14T11:19:32.080240", "woe:hierarchy": {"continent": 24865672, "country": 23424977, "town": 0, "planet": 1, "county": 12589771, "suburb": 0, "state": 2347597, "region": 0, "localadmin": 0}, "woe:timezone_id": 56043648, "woe:hash": "dr0yfz11gdpz", "woe:centroid": [-77.572929, 40.600288], "geom:latitude": 40.600288, "geom:longitude": -77.572929, "geom:hash": "dr0yfz11gdpz", "woe:latitude": 40.600288, "geom:centroid": [-77.572929, 40.600288], "woe:longitude": -77.572929, "woe:repo": "woeplanet-poi-us", "geom:area": 0.0, "woe:scale": 19}}