{"type": "Feature", "id": 23633017, "properties": {"woe:id": 23633017, "woe:parent_id": 56022556, "woe:name": "Layton Elementary School", "woe:placetype": 20, "woe:placetype_name": "POI", "woe:lang": "ENG", "iso:country": "US", "meta:provider": ["geoplanet:7.3.1", "geoplanet:7.3.2", "geoplanet:7.4.0", "geoplanet:7.4.1", "geoplanet:7.5.1", "geoplanet:7.5.2", "geoplanet:7.6.0", "geoplanet:7.8.1", "geoplanet:7.9.0", "geoplanet:7.10.0", "geoplanet:8.0.0", "woeplanet:8.0.0"], "meta:indexed": "2020-08-20T20:18:55.867988", "woe:alias_ENG_V": ["Layton Elementary"], "meta:updated": "2020-08-22T02:57:45.629993", "woe:hierarchy": {"continent": 24865672, "country": 23424977, "town": 0, "planet": 1, "county": 12589611, "suburb": 0, "state": 2347594, "region": 0, "localadmin": 0}, "woe:timezone_id": 56043648, "woe:hash": "dpm8prw0hbp3", "woe:centroid": [-81.938568, 40.822449], "geom:latitude": 40.822449, "geom:longitude": -81.938568, "geom:hash": "dpm8prw0hbp3", "woe:latitude": 40.822449, "geom:centroid": [-81.938568, 40.822449], "woe:longitude": -81.938568, "woe:repo": "woeplanet-poi-us"}, "geometry": {"coordinates": [-81.938568, 40.822449], "type": "Point"}}