{"type": "Feature", "id": 23528988, "properties": {"woe:id": 23528988, "woe:parent_id": 2397747, "woe:name": "Martin Luther Junior King Elementary School", "woe:placetype": 20, "woe:placetype_name": "POI", "woe:lang": "ENG", "iso:country": "US", "meta:provider": ["geoplanet:7.3.1", "geoplanet:7.3.2", "geoplanet:7.4.0", "geoplanet:7.4.1", "geoplanet:7.5.1", "geoplanet:7.5.2", "geoplanet:7.6.0", "geoplanet:7.8.1", "geoplanet:7.9.0", "geoplanet:7.10.0", "geoplanet:8.0.0", "woeplanet:8.0.0"], "meta:indexed": "2020-08-20T20:18:21.339260", "woe:alias_ENG_V": ["Martin Luther Junior King Elementary"], "meta:updated": "2020-08-22T02:57:28.430073", "woe:hierarchy": {"continent": 24865672, "country": 23424977, "town": 0, "planet": 1, "county": 12587682, "suburb": 0, "state": 2347563, "region": 0, "localadmin": 0}, "woe:timezone_id": 56043663, "woe:hash": "9mvf9gwr53k4", "woe:centroid": [-115.57843, 32.803638], "geom:latitude": 32.803638, "geom:longitude": -115.57843, "geom:hash": "9mvf9gwr53k4", "woe:latitude": 32.803638, "geom:centroid": [-115.57843, 32.803638], "woe:longitude": -115.57843, "woe:repo": "woeplanet-poi-us"}, "geometry": {"coordinates": [-115.57843, 32.803638], "type": "Point"}}