{"type": "Feature", "id": 23532956, "geometry": {"type": "Point", "coordinates": [-118.47538, 34.228321]}, "properties": {"woe:id": 23532956, "woe:parent_id": 2461140, "woe:name": "Ann Williams Preschool Kindergarten", "woe:placetype": 20, "woe:placetype_name": "POI", "woe:lang": "ENG", "iso:country": "US", "meta:provider": ["geoplanet:7.3.1", "geoplanet:7.3.2", "geoplanet:7.4.0", "geoplanet:7.4.1", "geoplanet:7.5.1", "geoplanet:7.5.2", "geoplanet:7.6.0", "geoplanet:7.8.1", "geoplanet:7.9.0", "geoplanet:7.10.0", "geoplanet:8.0.0", "woeplanet:8.0.0"], "meta:indexed": "2020-08-20T20:18:22.408122", "meta:updated": "2020-10-14T11:20:11.432044", "woe:hierarchy": {"continent": 24865672, "country": 23424977, "town": 0, "planet": 1, "county": 12587688, "suburb": 0, "state": 2347563, "region": 0, "localadmin": 0}, "woe:timezone_id": 56043663, "woe:hash": "9q5f8p0f7t3x", "woe:centroid": [-118.47538, 34.228321], "geom:latitude": 34.228321, "geom:longitude": -118.47538, "geom:hash": "9q5f8p0f7t3x", "woe:latitude": 34.228321, "geom:centroid": [-118.47538, 34.228321], "woe:longitude": -118.47538, "woe:repo": "woeplanet-poi-us", "geom:area": 0.0, "woe:scale": 19}}