{"type": "Feature", "id": 23620456, "properties": {"woe:id": 23620456, "woe:parent_id": 2359974, "woe:name": "Haverling Junior High School", "woe:placetype": 20, "woe:placetype_name": "POI", "woe:lang": "ENG", "iso:country": "US", "meta:provider": ["geoplanet:7.3.1", "geoplanet:7.3.2", "geoplanet:7.4.0", "geoplanet:7.4.1", "geoplanet:7.5.1", "geoplanet:7.5.2", "geoplanet:7.6.0", "geoplanet:7.8.1", "geoplanet:7.9.0", "geoplanet:7.10.0", "geoplanet:8.0.0", "woeplanet:8.0.0"], "meta:indexed": "2020-08-20T20:18:51.623816", "woe:alias_ENG_V": ["Haverling Junior High"], "meta:updated": "2020-08-22T02:57:43.746015", "woe:hierarchy": {"continent": 24865672, "country": 23424977, "town": 0, "planet": 1, "county": 12589362, "suburb": 0, "state": 2347591, "region": 0, "localadmin": 0}, "woe:timezone_id": 56043648, "woe:hash": "dr90b7xn9egn", "woe:centroid": [-77.323082, 42.339699], "geom:latitude": 42.339699, "geom:longitude": -77.323082, "geom:hash": "dr90b7xn9egn", "woe:latitude": 42.339699, "geom:centroid": [-77.323082, 42.339699], "woe:longitude": -77.323082, "woe:repo": "woeplanet-poi-us"}, "geometry": {"coordinates": [-77.323082, 42.339699], "type": "Point"}}