{"type": "Feature", "id": 23523597, "properties": {"woe:id": 23523597, "woe:parent_id": 2353823, "woe:name": "Silver Springs High School", "woe:placetype": 20, "woe:placetype_name": "POI", "woe:lang": "ENG", "iso:country": "US", "meta:provider": ["geoplanet:7.3.2", "geoplanet:7.4.0", "geoplanet:7.4.1", "geoplanet:7.5.1", "geoplanet:7.5.2", "geoplanet:7.6.0", "geoplanet:7.8.1", "geoplanet:7.9.0", "geoplanet:7.10.0", "geoplanet:8.0.0", "woeplanet:8.0.0"], "meta:indexed": "2020-08-20T22:01:59.246574", "woe:alias_ENG_V": ["Silver Springs Senior High School", "Silver Springs High", "Silver Springs Senior High", "Silver Springs HS", "Silver Springs Senior HS", "Bitney Springs Charter High", "Bitney Springs Charter High School", "Bitney Springs Charter HS", "Bitney Springs Charter Senior High", "Bitney Springs Charter Senior High School", "Bitney Springs Charter Senior HS"], "meta:updated": "2020-08-22T02:58:46.139547", "woe:hierarchy": {"continent": 24865672, "country": 23424977, "town": 0, "planet": 1, "county": 12587698, "suburb": 0, "state": 2347563, "region": 0, "localadmin": 0}, "woe:timezone_id": 56043663, "woe:hash": "9qczh2p5rupt", "woe:centroid": [-121.092339, 39.199799], "geom:latitude": 39.199799, "geom:longitude": -121.092339, "geom:hash": "9qczh2p5rupt", "woe:latitude": 39.199799, "geom:centroid": [-121.092339, 39.199799], "woe:longitude": -121.092339, "woe:repo": "woeplanet-poi-us"}, "geometry": {"coordinates": [-121.092339, 39.199799], "type": "Point"}}