{"type": "Feature", "id": 23573471, "geometry": {"type": "Point", "coordinates": [-84.489441, 39.084942]}, "properties": {"woe:id": 23573471, "woe:parent_id": 2459593, "woe:name": "A D Owens Elementary School", "woe:placetype": 20, "woe:placetype_name": "POI", "woe:lang": "ENG", "iso:country": "US", "meta:provider": ["geoplanet:7.3.2", "geoplanet:7.4.0", "geoplanet:7.4.1", "geoplanet:7.5.1", "geoplanet:7.5.2", "geoplanet:7.6.0", "geoplanet:7.8.1", "geoplanet:7.9.0", "geoplanet:7.10.0", "geoplanet:8.0.0", "woeplanet:8.0.0"], "meta:indexed": "2020-08-20T22:02:20.102760", "woe:alias_ENG_V": ["A D Owens Elementary"], "meta:updated": "2020-10-14T11:20:24.851771", "woe:hierarchy": {"continent": 24865672, "country": 23424977, "town": 0, "planet": 1, "county": 12588494, "suburb": 0, "state": 2347576, "region": 0, "localadmin": 0}, "woe:timezone_id": 56043647, "woe:hash": "dngym7hwm368", "woe:centroid": [-84.489441, 39.084942], "geom:latitude": 39.084942, "geom:longitude": -84.489441, "geom:hash": "dngym7hwm368", "woe:latitude": 39.084942, "geom:centroid": [-84.489441, 39.084942], "woe:longitude": -84.489441, "woe:repo": "woeplanet-poi-us", "geom:area": 0.0, "woe:scale": 19}}