{"type": "Feature", "id": 23610639, "geometry": {"type": "Point", "coordinates": [-74.2472, 40.669651]}, "properties": {"woe:id": 23610639, "woe:parent_id": 2399023, "woe:name": "Number 21 Victor Mravlag Elementary School", "woe:placetype": 20, "woe:placetype_name": "POI", "woe:lang": "ENG", "iso:country": "US", "meta:provider": ["geoplanet:7.3.1", "geoplanet:7.3.2", "geoplanet:7.4.0", "geoplanet:7.4.1", "geoplanet:7.5.1", "geoplanet:7.5.2", "geoplanet:7.6.0", "geoplanet:7.8.1", "geoplanet:7.9.0", "geoplanet:7.10.0", "geoplanet:8.0.0", "woeplanet:8.0.0"], "meta:indexed": "2020-08-20T20:19:16.081627", "woe:alias_ENG_V": ["Number 21, Victor Mravlag Elementary School", "Number 21, Victor Mravlag Elementary"], "meta:updated": "2020-10-14T11:19:41.409282", "woe:hierarchy": {"continent": 24865672, "country": 23424977, "town": 0, "planet": 1, "county": 12589277, "suburb": 0, "state": 2347589, "region": 0, "localadmin": 0}, "woe:timezone_id": 56043648, "woe:hash": "dr5pq7wvfu7n", "woe:centroid": [-74.2472, 40.669651], "geom:latitude": 40.669651, "geom:longitude": -74.2472, "geom:hash": "dr5pq7wvfu7n", "woe:latitude": 40.669651, "geom:centroid": [-74.2472, 40.669651], "woe:longitude": -74.2472, "woe:repo": "woeplanet-poi-us", "geom:area": 0.0, "woe:scale": 19}}