{"type": "Feature", "id": 56054025, "properties": {"woe:id": 56054025, "woe:parent_id": 23417362, "woe:name": "Edison College-Hendry Glade Center", "woe:placetype": 20, "woe:placetype_name": "POI", "woe:lang": "ENG", "iso:country": "US", "meta:provider": ["geoplanet:7.3.1", "geoplanet:7.3.2", "geoplanet:7.4.0", "geoplanet:7.4.1", "geoplanet:7.5.1", "geoplanet:7.5.2", "geoplanet:7.6.0", "geoplanet:7.8.1", "geoplanet:7.9.0", "geoplanet:7.10.0", "geoplanet:8.0.0", "woeplanet:8.0.0"], "meta:indexed": "2020-08-20T20:19:17.499647", "meta:updated": "2020-08-22T02:58:21.123185", "woe:hierarchy": {"continent": 24865672, "country": 23424977, "town": 0, "planet": 1, "county": 12587828, "suburb": 0, "state": 2347568, "region": 0, "localadmin": 0}, "woe:timezone_id": 56043648, "woe:hash": "dhy05tnrdkzr", "woe:centroid": [-81.400002, 26.74753], "geom:latitude": 26.74753, "geom:longitude": -81.400002, "geom:hash": "dhy05tnrdkzr", "woe:latitude": 26.74753, "geom:centroid": [-81.400002, 26.74753], "woe:longitude": -81.400002, "woe:repo": "woeplanet-poi-us"}, "geometry": {"coordinates": [-81.400002, 26.74753], "type": "Point"}}