{"type": "Feature", "id": 23530585, "geometry": {"type": "Point", "coordinates": [-118.32534, 33.952068]}, "properties": {"woe:id": 23530585, "woe:parent_id": 2454214, "woe:name": "Warren Lane Elementary School", "woe:placetype": 20, "woe:placetype_name": "POI", "woe:lang": "ENG", "iso:country": "US", "meta:provider": ["geoplanet:7.3.1", "geoplanet:7.3.2", "geoplanet:7.4.0", "geoplanet:7.4.1", "geoplanet:7.5.1", "geoplanet:7.5.2", "geoplanet:7.6.0", "geoplanet:7.8.1", "geoplanet:7.9.0", "geoplanet:7.10.0", "geoplanet:8.0.0", "woeplanet:8.0.0"], "meta:indexed": "2020-08-20T20:18:21.663763", "woe:alias_ENG_V": ["Lane Elementary School", "Warren Lane Elementary"], "meta:updated": "2020-10-14T11:20:09.635943", "woe:hierarchy": {"continent": 24865672, "country": 23424977, "town": 0, "planet": 1, "county": 12587688, "suburb": 0, "state": 2347563, "region": 0, "localadmin": 0}, "woe:timezone_id": 56043663, "woe:hash": "9q5c5ky15spw", "woe:centroid": [-118.32534, 33.952068], "geom:latitude": 33.952068, "geom:longitude": -118.32534, "geom:hash": "9q5c5ky15spw", "woe:latitude": 33.952068, "geom:centroid": [-118.32534, 33.952068], "woe:longitude": -118.32534, "woe:repo": "woeplanet-poi-us", "geom:area": 0.0, "woe:scale": 19}}