{"type": "Feature", "id": 23577630, "properties": {"woe:id": 23577630, "woe:parent_id": 2424721, "woe:name": "Mulberry Elementary School", "woe:placetype": 20, "woe:placetype_name": "POI", "woe:lang": "ENG", "iso:country": "US", "meta:provider": ["geoplanet:7.3.1", "geoplanet:7.3.2", "geoplanet:7.4.0", "geoplanet:7.4.1", "geoplanet:7.5.1", "geoplanet:7.5.2", "geoplanet:7.6.0", "geoplanet:7.8.1", "geoplanet:7.9.0", "geoplanet:7.10.0", "geoplanet:8.0.0", "woeplanet:8.0.0"], "meta:indexed": "2020-08-20T20:18:37.955583", "woe:alias_ENG_V": ["Mulberry Elementary"], "meta:updated": "2020-08-22T02:57:37.458515", "woe:hierarchy": {"continent": 24865672, "country": 23424977, "town": 0, "planet": 1, "county": 12588650, "suburb": 0, "state": 2347577, "region": 0, "localadmin": 0}, "woe:timezone_id": 56043661, "woe:hash": "9vr2pnwr6r4p", "woe:centroid": [-90.738388, 29.568239], "geom:latitude": 29.568239, "geom:longitude": -90.738388, "geom:hash": "9vr2pnwr6r4p", "woe:latitude": 29.568239, "geom:centroid": [-90.738388, 29.568239], "woe:longitude": -90.738388, "woe:repo": "woeplanet-poi-us"}, "geometry": {"coordinates": [-90.738388, 29.568239], "type": "Point"}}