{"type": "Feature", "id": 23662250, "geometry": {"type": "Point", "coordinates": [-111.950043, 40.594028]}, "properties": {"woe:id": 23662250, "woe:parent_id": 2517245, "woe:name": "Westvale Elementary School", "woe:placetype": 20, "woe:placetype_name": "POI", "woe:lang": "ENG", "iso:country": "US", "meta:provider": ["geoplanet:7.3.1", "geoplanet:7.3.2", "geoplanet:7.4.0", "geoplanet:7.4.1", "geoplanet:7.5.1", "geoplanet:7.5.2", "geoplanet:7.6.0", "geoplanet:7.8.1", "geoplanet:7.9.0", "geoplanet:7.10.0", "geoplanet:8.0.0", "woeplanet:8.0.0"], "meta:indexed": "2020-08-20T20:19:07.198945", "woe:alias_ENG_V": ["Westvale Elementary"], "meta:updated": "2020-10-14T11:19:53.342968", "woe:hierarchy": {"continent": 24865672, "country": 23424977, "town": 0, "planet": 1, "county": 12590278, "suburb": 0, "state": 2347603, "region": 0, "localadmin": 0}, "woe:timezone_id": 56043665, "woe:hash": "9x0qutbmqgm9", "woe:centroid": [-111.950043, 40.594028], "geom:latitude": 40.594028, "geom:longitude": -111.950043, "geom:hash": "9x0qutbmqgm9", "woe:latitude": 40.594028, "geom:centroid": [-111.950043, 40.594028], "woe:longitude": -111.950043, "woe:repo": "woeplanet-poi-us", "geom:area": 0.0, "woe:scale": 19}}