{"type": "Feature", "id": 23669986, "geometry": {"type": "Point", "coordinates": [-123.109741, 47.21426]}, "properties": {"woe:id": 23669986, "woe:parent_id": 2492259, "woe:name": "Choice High School", "woe:placetype": 20, "woe:placetype_name": "POI", "woe:lang": "ENG", "iso:country": "US", "meta:provider": ["geoplanet:7.3.1", "geoplanet:7.3.2", "geoplanet:7.4.0", "geoplanet:7.4.1", "geoplanet:7.5.1", "geoplanet:7.5.2", "geoplanet:7.6.0", "geoplanet:7.8.1", "geoplanet:7.9.0", "geoplanet:7.10.0", "geoplanet:8.0.0", "woeplanet:8.0.0"], "meta:indexed": "2020-08-20T20:19:09.560921", "woe:alias_ENG_V": ["Choice Senior High School", "Choice High", "Choice Senior High", "Choice HS", "Choice Senior HS", "Choice Alternative School"], "meta:updated": "2020-10-14T11:19:36.778620", "woe:hierarchy": {"continent": 24865672, "country": 23424977, "town": 0, "planet": 1, "county": 12590462, "suburb": 0, "state": 2347606, "region": 0, "localadmin": 0}, "woe:timezone_id": 56043663, "woe:hash": "c22kwe44zpgx", "woe:centroid": [-123.109741, 47.21426], "geom:latitude": 47.21426, "geom:longitude": -123.109741, "geom:hash": "c22kwe44zpgx", "woe:latitude": 47.21426, "geom:centroid": [-123.109741, 47.21426], "woe:longitude": -123.109741, "woe:repo": "woeplanet-poi-us", "geom:area": 0.0, "woe:scale": 19}}