{"type": "Feature", "id": 23547223, "properties": {"woe:id": 23547223, "woe:parent_id": 55860754, "woe:name": "Good Shepherd Catholic School", "woe:placetype": 20, "woe:placetype_name": "POI", "woe:lang": "ENG", "iso:country": "US", "meta:provider": ["geoplanet:7.3.2", "geoplanet:7.4.0", "geoplanet:7.4.1", "geoplanet:7.5.1", "geoplanet:7.5.2", "geoplanet:7.6.0", "geoplanet:7.8.1", "geoplanet:7.9.0", "geoplanet:7.10.0", "geoplanet:8.0.0", "woeplanet:8.0.0"], "meta:indexed": "2020-08-20T22:02:08.662014", "meta:updated": "2020-08-22T02:57:31.930772", "woe:hierarchy": {"continent": 24865672, "country": 23424977, "town": 0, "planet": 1, "county": 12587850, "suburb": 0, "state": 2347568, "region": 0, "localadmin": 0}, "woe:timezone_id": 56043648, "woe:hash": "djn4my02xkcm", "woe:centroid": [-81.309158, 28.553579], "geom:latitude": 28.553579, "geom:longitude": -81.309158, "geom:hash": "djn4my02xkcm", "woe:latitude": 28.553579, "geom:centroid": [-81.309158, 28.553579], "woe:longitude": -81.309158, "woe:repo": "woeplanet-poi-us"}, "geometry": {"coordinates": [-81.309158, 28.553579], "type": "Point"}}