{"type": "Feature", "id": 23557079, "geometry": {"type": "Point", "coordinates": [-89.183601, 39.640541]}, "properties": {"woe:id": 23557079, "woe:parent_id": 2500454, "woe:name": "Stonington Elementary School", "woe:placetype": 20, "woe:placetype_name": "POI", "woe:lang": "ENG", "iso:country": "US", "meta:provider": ["geoplanet:7.3.1", "geoplanet:7.3.2", "geoplanet:7.4.0", "geoplanet:7.4.1", "geoplanet:7.5.1", "geoplanet:7.5.2", "geoplanet:7.6.0", "geoplanet:7.8.1", "geoplanet:7.9.0", "geoplanet:7.10.0", "geoplanet:8.0.0", "woeplanet:8.0.0"], "meta:indexed": "2020-08-20T20:18:30.560400", "woe:alias_ENG_V": ["Stonington Elementary"], "meta:updated": "2020-10-14T11:20:25.716219", "woe:hierarchy": {"continent": 24865672, "country": 23424977, "town": 0, "planet": 1, "county": 12588088, "suburb": 0, "state": 2347572, "region": 0, "localadmin": 0}, "woe:timezone_id": 56043661, "woe:hash": "dp09d866zkrj", "woe:centroid": [-89.183601, 39.640541], "geom:latitude": 39.640541, "geom:longitude": -89.183601, "geom:hash": "dp09d866zkrj", "woe:latitude": 39.640541, "geom:centroid": [-89.183601, 39.640541], "woe:longitude": -89.183601, "woe:repo": "woeplanet-poi-us", "geom:area": 0.0, "woe:scale": 19}}