{"type": "Feature", "id": 23620913, "geometry": {"type": "Point", "coordinates": [-73.150162, 40.85276]}, "properties": {"woe:id": 23620913, "woe:parent_id": 2457832, "woe:name": "Nesconset Elementary School", "woe:placetype": 20, "woe:placetype_name": "POI", "woe:lang": "ENG", "iso:country": "US", "meta:provider": ["geoplanet:7.3.1", "geoplanet:7.3.2", "geoplanet:7.4.0", "geoplanet:7.4.1", "geoplanet:7.5.1", "geoplanet:7.5.2", "geoplanet:7.6.0", "geoplanet:7.8.1", "geoplanet:7.9.0", "geoplanet:7.10.0", "geoplanet:8.0.0", "woeplanet:8.0.0"], "meta:indexed": "2020-08-20T20:18:51.836218", "woe:alias_ENG_V": ["Nesconset Elementary"], "meta:updated": "2020-10-14T11:19:33.875696", "woe:hierarchy": {"continent": 24865672, "country": 23424977, "town": 0, "planet": 1, "county": 12589363, "suburb": 0, "state": 2347591, "region": 0, "localadmin": 0}, "woe:timezone_id": 56043648, "woe:hash": "dr7brmj8tdmv", "woe:centroid": [-73.150162, 40.85276], "geom:latitude": 40.85276, "geom:longitude": -73.150162, "geom:hash": "dr7brmj8tdmv", "woe:latitude": 40.85276, "geom:centroid": [-73.150162, 40.85276], "woe:longitude": -73.150162, "woe:repo": "woeplanet-poi-us", "geom:area": 0.0, "woe:scale": 19}}