{"type": "Feature", "id": 23671565, "geometry": {"type": "Point", "coordinates": [-122.20813, 48.7183]}, "properties": {"woe:id": 23671565, "woe:parent_id": 2351763, "woe:name": "Acme Elementary School", "woe:placetype": 20, "woe:placetype_name": "POI", "woe:lang": "ENG", "iso:country": "US", "meta:provider": ["geoplanet:7.3.2", "geoplanet:7.4.0", "geoplanet:7.4.1", "geoplanet:7.5.1", "geoplanet:7.5.2", "geoplanet:7.6.0", "geoplanet:7.8.1", "geoplanet:7.9.0", "geoplanet:7.10.0", "geoplanet:8.0.0", "woeplanet:8.0.0"], "meta:indexed": "2020-08-20T22:03:00.756413", "woe:alias_ENG_V": ["Acme Elementary"], "meta:updated": "2020-10-14T11:19:29.969647", "woe:hierarchy": {"continent": 24865672, "country": 23424977, "town": 0, "planet": 1, "county": 12590476, "suburb": 0, "state": 2347606, "region": 0, "localadmin": 0}, "woe:timezone_id": 56043663, "woe:hash": "c29j5hfu8jme", "woe:centroid": [-122.20813, 48.7183], "geom:latitude": 48.7183, "geom:longitude": -122.20813, "geom:hash": "c29j5hfu8jme", "woe:latitude": 48.7183, "geom:centroid": [-122.20813, 48.7183], "woe:longitude": -122.20813, "woe:repo": "woeplanet-poi-us", "geom:area": 0.0, "woe:scale": 19}}