{"type": "Feature", "id": 23544665, "properties": {"woe:id": 23544665, "woe:parent_id": 2479878, "woe:name": "Lake Forest High School", "woe:placetype": 20, "woe:placetype_name": "POI", "woe:lang": "ENG", "iso:country": "US", "meta:provider": ["geoplanet:7.3.1", "geoplanet:7.3.2", "geoplanet:7.4.0", "geoplanet:7.4.1", "geoplanet:7.5.1", "geoplanet:7.5.2", "geoplanet:7.6.0", "geoplanet:7.8.1", "geoplanet:7.9.0", "geoplanet:7.10.0", "geoplanet:8.0.0", "woeplanet:8.0.0"], "meta:indexed": "2020-08-20T20:18:25.663115", "woe:alias_ENG_V": ["Lake Forest Senior High School", "Lake Forest High", "Lake Forest Senior High", "Lake Forest HS", "Lake Forest Senior HS", "Lk Forest High", "Lk Forest High School", "Lk Forest HS", "Lk Forest Senior High", "Lk Forest Senior High School", "Lk Forest Senior HS"], "meta:updated": "2020-08-22T02:58:46.664924", "woe:hierarchy": {"continent": 24865672, "country": 23424977, "town": 0, "planet": 1, "county": 12587799, "suburb": 0, "state": 2347566, "region": 0, "localadmin": 0}, "woe:timezone_id": 56043648, "woe:hash": "dqfmbcb9nn3g", "woe:centroid": [-75.552032, 38.989311], "geom:latitude": 38.989311, "geom:longitude": -75.552032, "geom:hash": "dqfmbcb9nn3g", "woe:latitude": 38.989311, "geom:centroid": [-75.552032, 38.989311], "woe:longitude": -75.552032, "woe:repo": "woeplanet-poi-us"}, "geometry": {"coordinates": [-75.552032, 38.989311], "type": "Point"}}