{"type": "Feature", "id": 23518083, "geometry": {"type": "Point", "coordinates": [-90.741142, 35.777771]}, "properties": {"woe:id": 23518083, "woe:parent_id": 2429863, "woe:name": "Valley View High School", "woe:placetype": 20, "woe:placetype_name": "POI", "woe:lang": "ENG", "iso:country": "US", "meta:provider": ["geoplanet:7.3.1", "geoplanet:7.3.2", "geoplanet:7.4.0", "geoplanet:7.4.1", "geoplanet:7.5.1", "geoplanet:7.5.2", "geoplanet:7.6.0", "geoplanet:7.8.1", "geoplanet:7.9.0", "geoplanet:7.10.0", "geoplanet:8.0.0", "woeplanet:8.0.0"], "meta:indexed": "2020-08-20T20:18:18.946931", "woe:alias_ENG_V": ["Valley View Senior High School", "Valley View High", "Valley View Senior High", "Valley View HS", "Valley View Senior HS", "Valley View Jr High", "Valley View Jr High School", "Valley View Jr HS", "Valley View Jr Senior High", "Valley View Jr Senior High School", "Valley View Jr Senior HS"], "meta:updated": "2020-10-14T11:20:08.278802", "woe:hierarchy": {"continent": 24865672, "country": 23424977, "town": 0, "planet": 1, "county": 12587610, "suburb": 0, "state": 2347562, "region": 0, "localadmin": 0}, "woe:timezone_id": 56043661, "woe:hash": "9yr7x1hkd5um", "woe:centroid": [-90.741142, 35.777771], "geom:latitude": 35.777771, "geom:longitude": -90.741142, "geom:hash": "9yr7x1hkd5um", "woe:latitude": 35.777771, "geom:centroid": [-90.741142, 35.777771], "woe:longitude": -90.741142, "woe:repo": "woeplanet-poi-us", "geom:area": 0.0, "woe:scale": 19}}