{"type": "Feature", "id": 23608165, "geometry": {"type": "Point", "coordinates": [-74.21064, 40.793072]}, "properties": {"woe:id": 23608165, "woe:parent_id": 2365577, "woe:name": "Linden Avenue Elementary School", "woe:placetype": 20, "woe:placetype_name": "POI", "woe:lang": "ENG", "iso:country": "US", "meta:provider": ["geoplanet:7.3.1", "geoplanet:7.3.2", "geoplanet:7.4.0", "geoplanet:7.4.1", "geoplanet:7.5.1", "geoplanet:7.5.2", "geoplanet:7.6.0", "geoplanet:7.8.1", "geoplanet:7.9.0", "geoplanet:7.10.0", "geoplanet:8.0.0", "woeplanet:8.0.0"], "meta:indexed": "2020-08-20T20:18:47.024448", "woe:alias_ENG_V": ["Linden Avenue Elementary"], "meta:updated": "2020-10-14T11:19:32.182217", "woe:hierarchy": {"continent": 24865672, "country": 23424977, "town": 0, "planet": 1, "county": 12589264, "suburb": 0, "state": 2347589, "region": 0, "localadmin": 0}, "woe:timezone_id": 56043648, "woe:hash": "dr70p61kygb0", "woe:centroid": [-74.21064, 40.793072], "geom:latitude": 40.793072, "geom:longitude": -74.21064, "geom:hash": "dr70p61kygb0", "woe:latitude": 40.793072, "geom:centroid": [-74.21064, 40.793072], "woe:longitude": -74.21064, "woe:repo": "woeplanet-poi-us", "geom:area": 0.0, "woe:scale": 19}}