{"type": "Feature", "id": 23628217, "geometry": {"type": "Point", "coordinates": [-81.570847, 41.472752]}, "properties": {"woe:id": 23628217, "woe:parent_id": 56022507, "woe:name": "Shaker Hts High School", "woe:placetype": 20, "woe:placetype_name": "POI", "woe:lang": "ENG", "iso:country": "US", "meta:provider": ["geoplanet:7.3.2", "geoplanet:7.4.0", "geoplanet:7.4.1", "geoplanet:7.5.1", "geoplanet:7.5.2", "geoplanet:7.6.0", "geoplanet:7.8.1", "geoplanet:7.9.0", "geoplanet:7.10.0", "geoplanet:8.0.0", "woeplanet:8.0.0"], "meta:indexed": "2020-08-20T22:02:41.752721", "woe:alias_ENG_V": ["Shaker Hts Senior High School", "Shaker Hts High", "Shaker Hts Senior High", "Shaker Hts HS", "Shaker Hts Senior HS"], "meta:updated": "2020-10-14T11:19:38.781327", "woe:hierarchy": {"continent": 24865672, "country": 23424977, "town": 0, "planet": 1, "county": 12589544, "suburb": 0, "state": 2347594, "region": 0, "localadmin": 0}, "woe:timezone_id": 56043648, "woe:hash": "dpmgzvcum924", "woe:centroid": [-81.570847, 41.472752], "geom:latitude": 41.472752, "geom:longitude": -81.570847, "geom:hash": "dpmgzvcum924", "woe:latitude": 41.472752, "geom:centroid": [-81.570847, 41.472752], "woe:longitude": -81.570847, "woe:repo": "woeplanet-poi-us", "geom:area": 0.0, "woe:scale": 19}}