{"type": "Feature", "id": 23616691, "geometry": {"type": "Point", "coordinates": [-73.49482, 40.684311]}, "properties": {"woe:id": 23616691, "woe:parent_id": 55992278, "woe:name": "Seaford Senior High School", "woe:placetype": 20, "woe:placetype_name": "POI", "woe:lang": "ENG", "iso:country": "US", "meta:provider": ["geoplanet:7.3.1", "geoplanet:7.3.2", "geoplanet:7.4.0", "geoplanet:7.4.1", "geoplanet:7.5.1", "geoplanet:7.5.2", "geoplanet:7.6.0", "geoplanet:7.8.1", "geoplanet:7.9.0", "geoplanet:7.10.0", "geoplanet:8.0.0", "woeplanet:8.0.0"], "meta:indexed": "2020-08-20T20:18:50.129516", "woe:alias_ENG_V": ["Seaford Senior High", "Seaford High School", "Seaford High", "Seaford Senior HS", "Seaford HS"], "meta:updated": "2020-10-14T11:19:40.437765", "woe:hierarchy": {"continent": 24865672, "country": 23424977, "town": 0, "planet": 1, "county": 12589341, "suburb": 0, "state": 2347591, "region": 0, "localadmin": 0}, "woe:timezone_id": 56043648, "woe:hash": "dr5xrw6eq960", "woe:centroid": [-73.49482, 40.684311], "geom:latitude": 40.684311, "geom:longitude": -73.49482, "geom:hash": "dr5xrw6eq960", "woe:latitude": 40.684311, "geom:centroid": [-73.49482, 40.684311], "woe:longitude": -73.49482, "woe:repo": "woeplanet-poi-us", "geom:area": 0.0, "woe:scale": 19}}