{"type": "Feature", "id": 23663431, "properties": {"woe:id": 23663431, "woe:parent_id": 2522592, "woe:name": "Green Mountain Waldorf School", "woe:placetype": 20, "woe:placetype_name": "POI", "woe:lang": "ENG", "iso:country": "US", "meta:provider": ["geoplanet:7.4.0", "geoplanet:7.4.1", "geoplanet:7.5.1", "geoplanet:7.5.2", "geoplanet:7.6.0", "geoplanet:7.8.1", "geoplanet:7.9.0", "geoplanet:7.10.0", "geoplanet:8.0.0", "woeplanet:8.0.0"], "meta:indexed": "2020-08-20T23:55:43.898948", "meta:updated": "2020-08-22T02:57:51.000740", "woe:hierarchy": {"continent": 24865672, "country": 23424977, "town": 0, "planet": 1, "county": 12590297, "suburb": 0, "state": 2347604, "region": 0, "localadmin": 0}, "woe:timezone_id": 56043648, "woe:hash": "drumrjj2q9zz", "woe:centroid": [-72.458321, 44.544121], "geom:latitude": 44.544121, "geom:longitude": -72.458321, "geom:hash": "drumrjj2q9zz", "woe:latitude": 44.544121, "geom:centroid": [-72.458321, 44.544121], "woe:longitude": -72.458321, "woe:repo": "woeplanet-poi-us"}, "geometry": {"coordinates": [-72.458321, 44.544121], "type": "Point"}}