{"type": "Feature", "id": 23541504, "properties": {"woe:id": 23541504, "woe:parent_id": 2441207, "woe:name": "Loma Elementary School", "woe:placetype": 20, "woe:placetype_name": "POI", "woe:lang": "ENG", "iso:country": "US", "meta:provider": ["geoplanet:7.3.1", "geoplanet:7.3.2", "geoplanet:7.4.0", "geoplanet:7.4.1", "geoplanet:7.5.1", "geoplanet:7.5.2", "geoplanet:7.6.0", "geoplanet:7.8.1", "geoplanet:7.9.0", "geoplanet:7.10.0", "geoplanet:8.0.0", "woeplanet:8.0.0"], "meta:indexed": "2020-08-20T20:18:24.741859", "woe:alias_ENG_V": ["Loma Elementary"], "meta:updated": "2020-08-22T02:57:30.862784", "woe:hierarchy": {"continent": 24865672, "country": 23424977, "town": 0, "planet": 1, "county": 12587766, "suburb": 0, "state": 2347564, "region": 0, "localadmin": 0}, "woe:timezone_id": 56043665, "woe:hash": "9wfx5bkgkpeh", "woe:centroid": [-108.812881, 39.201191], "geom:latitude": 39.201191, "geom:longitude": -108.812881, "geom:hash": "9wfx5bkgkpeh", "woe:latitude": 39.201191, "geom:centroid": [-108.812881, 39.201191], "woe:longitude": -108.812881, "woe:repo": "woeplanet-poi-us"}, "geometry": {"coordinates": [-108.812881, 39.201191], "type": "Point"}}