{"type": "Feature", "id": 23629003, "geometry": {"type": "Point", "coordinates": [-83.063141, 40.067822]}, "properties": {"woe:id": 23629003, "woe:parent_id": 55992334, "woe:name": "Gables Elementary School", "woe:placetype": 20, "woe:placetype_name": "POI", "woe:lang": "ENG", "iso:country": "US", "meta:provider": ["geoplanet:7.3.1", "geoplanet:7.3.2", "geoplanet:7.4.0", "geoplanet:7.4.1", "geoplanet:7.5.1", "geoplanet:7.5.2", "geoplanet:7.6.0", "geoplanet:7.8.1", "geoplanet:7.9.0", "geoplanet:7.10.0", "geoplanet:8.0.0", "woeplanet:8.0.0"], "meta:indexed": "2020-08-20T20:18:54.018025", "woe:alias_ENG_V": ["Gables Elementary"], "meta:updated": "2020-10-14T11:19:38.973770", "woe:hierarchy": {"continent": 24865672, "country": 23424977, "town": 0, "planet": 1, "county": 12589551, "suburb": 0, "state": 2347594, "region": 0, "localadmin": 0}, "woe:timezone_id": 56043648, "woe:hash": "dphgvy57bx2u", "woe:centroid": [-83.063141, 40.067822], "geom:latitude": 40.067822, "geom:longitude": -83.063141, "geom:hash": "dphgvy57bx2u", "woe:latitude": 40.067822, "geom:centroid": [-83.063141, 40.067822], "woe:longitude": -83.063141, "woe:repo": "woeplanet-poi-us", "geom:area": 0.0, "woe:scale": 19}}