{"type": "Feature", "id": 23671624, "properties": {"woe:id": 23671624, "woe:parent_id": 2477224, "woe:name": "Sunnyside Elementary School", "woe:placetype": 20, "woe:placetype_name": "POI", "woe:lang": "ENG", "iso:country": "US", "meta:provider": ["geoplanet:7.3.2", "geoplanet:7.4.0", "geoplanet:7.4.1", "geoplanet:7.5.1", "geoplanet:7.5.2", "geoplanet:7.6.0", "geoplanet:7.8.1", "geoplanet:7.9.0", "geoplanet:7.10.0", "geoplanet:8.0.0", "woeplanet:8.0.0"], "meta:indexed": "2020-08-20T22:03:00.785339", "woe:alias_ENG_V": ["Sunnyside Elementary"], "meta:updated": "2020-08-22T02:57:52.312138", "woe:hierarchy": {"continent": 24865672, "country": 23424977, "town": 0, "planet": 1, "county": 12590477, "suburb": 0, "state": 2347606, "region": 0, "localadmin": 0}, "woe:timezone_id": 56043663, "woe:hash": "c2k9v6d8f5u8", "woe:centroid": [-117.187637, 46.727749], "geom:latitude": 46.727749, "geom:longitude": -117.187637, "geom:hash": "c2k9v6d8f5u8", "woe:latitude": 46.727749, "geom:centroid": [-117.187637, 46.727749], "woe:longitude": -117.187637, "woe:repo": "woeplanet-poi-us"}, "geometry": {"coordinates": [-117.187637, 46.727749], "type": "Point"}}