{"type": "Feature", "id": 23553403, "geometry": {"type": "Point", "coordinates": [-83.645477, 32.636391]}, "properties": {"woe:id": 23553403, "woe:parent_id": 2398051, "woe:name": "Northside Middle School", "woe:placetype": 20, "woe:placetype_name": "POI", "woe:lang": "ENG", "iso:country": "US", "meta:provider": ["geoplanet:7.3.1", "geoplanet:7.3.2", "geoplanet:7.4.0", "geoplanet:7.4.1", "geoplanet:7.5.1", "geoplanet:7.5.2", "geoplanet:7.6.0", "geoplanet:7.8.1", "geoplanet:7.9.0", "geoplanet:7.10.0", "geoplanet:8.0.0", "woeplanet:8.0.0"], "meta:indexed": "2020-08-20T20:18:29.622375", "meta:updated": "2020-10-14T11:20:18.471323", "woe:hierarchy": {"continent": 24865672, "country": 23424977, "town": 0, "planet": 1, "county": 12587945, "suburb": 0, "state": 2347569, "region": 0, "localadmin": 0}, "woe:timezone_id": 56043648, "woe:hash": "dju98t70z05z", "woe:centroid": [-83.645477, 32.636391], "geom:latitude": 32.636391, "geom:longitude": -83.645477, "geom:hash": "dju98t70z05z", "woe:latitude": 32.636391, "geom:centroid": [-83.645477, 32.636391], "woe:longitude": -83.645477, "woe:repo": "woeplanet-poi-us", "geom:area": 0.0, "woe:scale": 19}}