{"type": "Feature", "id": 56052416, "geometry": {"type": "Point", "coordinates": [-112.110542, 33.654739]}, "properties": {"woe:id": 56052416, "woe:parent_id": 2390460, "woe:name": "University of Phoenix-Northwest", "woe:placetype": 20, "woe:placetype_name": "POI", "woe:lang": "ENG", "iso:country": "US", "meta:provider": ["geoplanet:7.3.1", "geoplanet:7.3.2", "geoplanet:7.4.0", "geoplanet:7.4.1", "geoplanet:7.5.1", "geoplanet:7.5.2", "geoplanet:7.6.0", "geoplanet:7.8.1", "geoplanet:7.9.0", "geoplanet:7.10.0", "geoplanet:8.0.0", "woeplanet:8.0.0"], "meta:indexed": "2020-08-20T20:19:16.304559", "meta:updated": "2020-10-14T11:19:57.038647", "woe:hierarchy": {"continent": 24865672, "country": 23424977, "town": 0, "planet": 1, "county": 12587587, "suburb": 0, "state": 2347561, "region": 0, "localadmin": 0}, "woe:timezone_id": 56043666, "woe:hash": "9tbr2yet540f", "woe:centroid": [-112.110542, 33.654739], "geom:latitude": 33.654739, "geom:longitude": -112.110542, "geom:hash": "9tbr2yet540f", "woe:latitude": 33.654739, "geom:centroid": [-112.110542, 33.654739], "woe:longitude": -112.110542, "woe:repo": "woeplanet-poi-us", "geom:area": 0.0, "woe:scale": 19}}