{"type": "Feature", "id": 23651307, "geometry": {"type": "Point", "coordinates": [-85.500061, 36.175468]}, "properties": {"woe:id": 23651307, "woe:parent_id": 2384455, "woe:name": "Prescott Central Middle School", "woe:placetype": 20, "woe:placetype_name": "POI", "woe:lang": "ENG", "iso:country": "US", "meta:provider": ["geoplanet:7.3.2", "geoplanet:7.4.0", "geoplanet:7.4.1", "geoplanet:7.5.1", "geoplanet:7.5.2", "geoplanet:7.6.0", "geoplanet:7.8.1", "geoplanet:7.9.0", "geoplanet:7.10.0", "geoplanet:8.0.0", "woeplanet:8.0.0"], "meta:indexed": "2020-08-20T22:02:51.302088", "meta:updated": "2020-10-14T11:19:46.954133", "woe:hierarchy": {"continent": 24865672, "country": 23424977, "town": 0, "planet": 1, "county": 12589982, "suburb": 0, "state": 2347601, "region": 0, "localadmin": 0}, "woe:timezone_id": 56043661, "woe:hash": "dn7jy3sc2hj8", "woe:centroid": [-85.500061, 36.175468], "geom:latitude": 36.175468, "geom:longitude": -85.500061, "geom:hash": "dn7jy3sc2hj8", "woe:latitude": 36.175468, "geom:centroid": [-85.500061, 36.175468], "woe:longitude": -85.500061, "woe:repo": "woeplanet-poi-us", "geom:area": 0.0, "woe:scale": 19}}