{"type": "Feature", "id": 23582082, "geometry": {"type": "Point", "coordinates": [-76.584442, 39.288849]}, "properties": {"woe:id": 23582082, "woe:parent_id": 29229454, "woe:name": "The Salvation Army Day Care Center", "woe:placetype": 20, "woe:placetype_name": "POI", "woe:lang": "ENG", "iso:country": "US", "meta:provider": ["geoplanet:7.3.1", "geoplanet:7.3.2", "geoplanet:7.4.0", "geoplanet:7.4.1", "geoplanet:7.5.1", "geoplanet:7.5.2", "geoplanet:7.6.0", "geoplanet:7.8.1", "geoplanet:7.9.0", "geoplanet:7.10.0", "geoplanet:8.0.0", "woeplanet:8.0.0"], "meta:indexed": "2020-08-20T20:18:38.980998", "meta:updated": "2020-10-14T11:20:04.680259", "woe:hierarchy": {"continent": 24865672, "country": 23424977, "town": 0, "planet": 1, "county": 12588679, "suburb": 0, "state": 2347579, "region": 0, "localadmin": 0}, "woe:timezone_id": 56043648, "woe:hash": "dqcx922fjhm1", "woe:centroid": [-76.584442, 39.288849], "geom:latitude": 39.288849, "geom:longitude": -76.584442, "geom:hash": "dqcx922fjhm1", "woe:latitude": 39.288849, "geom:centroid": [-76.584442, 39.288849], "woe:longitude": -76.584442, "woe:repo": "woeplanet-poi-us", "geom:area": 0.0, "woe:scale": 19}}