{"type": "Feature", "id": 23559309, "properties": {"woe:id": 23559309, "woe:parent_id": 2426824, "woe:name": "Beacon Hill Elementary School", "woe:placetype": 20, "woe:placetype_name": "POI", "woe:lang": "ENG", "iso:country": "US", "meta:provider": ["geoplanet:7.3.1", "geoplanet:7.3.2", "geoplanet:7.4.0", "geoplanet:7.4.1", "geoplanet:7.5.1", "geoplanet:7.5.2", "geoplanet:7.6.0", "geoplanet:7.8.1", "geoplanet:7.9.0", "geoplanet:7.10.0", "geoplanet:8.0.0", "woeplanet:8.0.0"], "meta:indexed": "2020-08-20T20:18:31.405345", "woe:alias_ENG_V": ["Beacon Hill Elementary"], "meta:updated": "2020-08-22T02:57:34.200332", "woe:hierarchy": {"continent": 24865672, "country": 23424977, "town": 0, "planet": 1, "county": 12588093, "suburb": 0, "state": 2347572, "region": 0, "localadmin": 0}, "woe:timezone_id": 56043661, "woe:hash": "dp3sj4qgu7wj", "woe:centroid": [-87.661438, 41.497398], "geom:latitude": 41.497398, "geom:longitude": -87.661438, "geom:hash": "dp3sj4qgu7wj", "woe:latitude": 41.497398, "geom:centroid": [-87.661438, 41.497398], "woe:longitude": -87.661438, "woe:repo": "woeplanet-poi-us"}, "geometry": {"coordinates": [-87.661438, 41.497398], "type": "Point"}}