{"type": "Feature", "id": 23605625, "properties": {"woe:id": 23605625, "woe:parent_id": 2502969, "woe:name": "Monadnock Regional Junior High School", "woe:placetype": 20, "woe:placetype_name": "POI", "woe:lang": "ENG", "iso:country": "US", "meta:provider": ["geoplanet:7.3.1", "geoplanet:7.3.2", "geoplanet:7.4.0", "geoplanet:7.4.1", "geoplanet:7.5.1", "geoplanet:7.5.2", "geoplanet:7.6.0", "geoplanet:7.8.1", "geoplanet:7.9.0", "geoplanet:7.10.0", "geoplanet:8.0.0", "woeplanet:8.0.0"], "meta:indexed": "2020-08-20T20:18:46.261139", "woe:alias_ENG_V": ["Monadnock Regional Junior High"], "meta:updated": "2020-08-22T02:57:41.704360", "woe:hierarchy": {"continent": 24865672, "country": 23424977, "town": 0, "planet": 1, "county": 12589250, "suburb": 0, "state": 2347588, "region": 0, "localadmin": 0}, "woe:timezone_id": 56043648, "woe:hash": "drsegm35r8sg", "woe:centroid": [-72.277351, 42.87608], "geom:latitude": 42.87608, "geom:longitude": -72.277351, "geom:hash": "drsegm35r8sg", "woe:latitude": 42.87608, "geom:centroid": [-72.277351, 42.87608], "woe:longitude": -72.277351, "woe:repo": "woeplanet-poi-us"}, "geometry": {"coordinates": [-72.277351, 42.87608], "type": "Point"}}