{"type": "Feature", "id": 23658279, "geometry": {"type": "Point", "coordinates": [-95.53067, 29.57164]}, "properties": {"woe:id": 23658279, "woe:parent_id": 55994632, "woe:name": "Lantern Lane Elementary School", "woe:placetype": 20, "woe:placetype_name": "POI", "woe:lang": "ENG", "iso:country": "US", "meta:provider": ["geoplanet:7.3.1", "geoplanet:7.3.2", "geoplanet:7.4.0", "geoplanet:7.4.1", "geoplanet:7.5.1", "geoplanet:7.5.2", "geoplanet:7.6.0", "geoplanet:7.8.1", "geoplanet:7.9.0", "geoplanet:7.10.0", "geoplanet:8.0.0", "woeplanet:8.0.0"], "meta:indexed": "2020-08-20T20:19:05.350092", "woe:alias_ENG_V": ["Lantern Lane Elementary"], "meta:updated": "2020-10-14T11:19:43.632929", "woe:hierarchy": {"continent": 24865672, "country": 23424977, "town": 0, "planet": 1, "county": 12590085, "suburb": 0, "state": 2347602, "region": 0, "localadmin": 0}, "woe:timezone_id": 56043661, "woe:hash": "9vk04pkeq11x", "woe:centroid": [-95.53067, 29.57164], "geom:latitude": 29.57164, "geom:longitude": -95.53067, "geom:hash": "9vk04pkeq11x", "woe:latitude": 29.57164, "geom:centroid": [-95.53067, 29.57164], "woe:longitude": -95.53067, "woe:repo": "woeplanet-poi-us", "geom:area": 0.0, "woe:scale": 19}}