{"type": "Feature", "id": 23580585, "properties": {"woe:id": 23580585, "woe:parent_id": 2387774, "woe:name": "Love of Learning Montessori School", "woe:placetype": 20, "woe:placetype_name": "POI", "woe:lang": "ENG", "iso:country": "US", "meta:provider": ["geoplanet:7.3.1", "geoplanet:7.3.2", "geoplanet:7.4.0", "geoplanet:7.4.1", "geoplanet:7.5.1", "geoplanet:7.5.2", "geoplanet:7.6.0", "geoplanet:7.8.1", "geoplanet:7.9.0", "geoplanet:7.10.0", "geoplanet:8.0.0", "woeplanet:8.0.0"], "meta:indexed": "2020-08-20T20:18:38.609899", "meta:updated": "2020-08-22T02:57:37.888663", "woe:hierarchy": {"continent": 24865672, "country": 23424977, "town": 0, "planet": 1, "county": 12588689, "suburb": 0, "state": 2347579, "region": 0, "localadmin": 0}, "woe:timezone_id": 56043648, "woe:hash": "dqcr5yj66yfu", "woe:centroid": [-76.820061, 39.232601], "geom:latitude": 39.232601, "geom:longitude": -76.820061, "geom:hash": "dqcr5yj66yfu", "woe:latitude": 39.232601, "geom:centroid": [-76.820061, 39.232601], "woe:longitude": -76.820061, "woe:repo": "woeplanet-poi-us"}, "geometry": {"coordinates": [-76.820061, 39.232601], "type": "Point"}}