{"type": "Feature", "id": 23658148, "geometry": {"type": "Point", "coordinates": [-97.499619, 25.90233]}, "properties": {"woe:id": 23658148, "woe:parent_id": 55858368, "woe:name": "Downtown Brownsville Station", "woe:placetype": 20, "woe:placetype_name": "POI", "woe:lang": "ENG", "iso:country": "US", "meta:provider": ["geoplanet:7.3.1", "geoplanet:7.3.2", "geoplanet:7.4.0", "geoplanet:7.4.1", "geoplanet:7.5.1", "geoplanet:7.5.2", "geoplanet:7.6.0", "geoplanet:7.8.1", "geoplanet:7.9.0", "geoplanet:7.10.0", "geoplanet:8.0.0", "woeplanet:8.0.0"], "meta:indexed": "2020-08-20T20:19:05.290600", "meta:updated": "2020-10-14T11:19:30.938015", "woe:hierarchy": {"continent": 24865672, "country": 23424977, "town": 0, "planet": 1, "county": 12590037, "suburb": 0, "state": 2347602, "region": 0, "localadmin": 0}, "woe:timezone_id": 56043661, "woe:hash": "9udem76un0qc", "woe:centroid": [-97.499619, 25.90233], "geom:latitude": 25.90233, "geom:longitude": -97.499619, "geom:hash": "9udem76un0qc", "woe:latitude": 25.90233, "geom:centroid": [-97.499619, 25.90233], "woe:longitude": -97.499619, "woe:repo": "woeplanet-poi-us", "geom:area": 0.0, "woe:scale": 19}}