{"type": "Feature", "id": 56204440, "geometry": {"type": "Point", "coordinates": [-73.962807, 40.673]}, "properties": {"woe:id": 56204440, "woe:parent_id": 28751452, "woe:name": "Montessori Day School of Brooklyn", "woe:placetype": 20, "woe:placetype_name": "POI", "woe:lang": "ENG", "iso:country": "US", "meta:provider": ["geoplanet:7.6.0", "geoplanet:7.8.1", "geoplanet:7.9.0", "geoplanet:7.10.0", "geoplanet:8.0.0", "woeplanet:8.0.0"], "meta:indexed": "2020-08-21T08:24:23.995149", "meta:updated": "2020-10-14T11:20:01.296546", "woe:hierarchy": {"continent": 24865672, "country": 23424977, "town": 0, "planet": 1, "county": 12589335, "suburb": 0, "state": 2347591, "region": 0, "localadmin": 0}, "woe:timezone_id": 56043648, "woe:hash": "dr5rkumcmstz", "woe:centroid": [-73.962807, 40.673], "geom:latitude": 40.673, "geom:longitude": -73.962807, "geom:hash": "dr5rkumcmstz", "woe:latitude": 40.673, "geom:centroid": [-73.962807, 40.673], "woe:longitude": -73.962807, "woe:repo": "woeplanet-poi-us", "geom:area": 0.0, "woe:scale": 19}}