{"type": "Feature", "id": 23618348, "properties": {"woe:id": 23618348, "woe:parent_id": 55862055, "woe:name": "Bellevue Elementary School", "woe:placetype": 20, "woe:placetype_name": "POI", "woe:lang": "ENG", "iso:country": "US", "meta:provider": ["geoplanet:7.3.1", "geoplanet:7.3.2", "geoplanet:7.4.0", "geoplanet:7.4.1", "geoplanet:7.5.1", "geoplanet:7.5.2", "geoplanet:7.6.0", "geoplanet:7.8.1", "geoplanet:7.9.0", "geoplanet:7.10.0", "geoplanet:8.0.0", "woeplanet:8.0.0"], "meta:indexed": "2020-08-20T20:18:50.803948", "woe:alias_ENG_V": ["Bellevue Elementary"], "meta:updated": "2020-08-22T02:57:43.446687", "woe:hierarchy": {"continent": 24865672, "country": 23424977, "town": 0, "planet": 1, "county": 12589345, "suburb": 0, "state": 2347591, "region": 0, "localadmin": 0}, "woe:timezone_id": 56043648, "woe:hash": "dr9uf9kug1w1", "woe:centroid": [-76.172539, 43.030151], "geom:latitude": 43.030151, "geom:longitude": -76.172539, "geom:hash": "dr9uf9kug1w1", "woe:latitude": 43.030151, "geom:centroid": [-76.172539, 43.030151], "woe:longitude": -76.172539, "woe:repo": "woeplanet-poi-us"}, "geometry": {"coordinates": [-76.172539, 43.030151], "type": "Point"}}