{"type": "Feature", "id": 23606708, "geometry": {"type": "Point", "coordinates": [-70.898178, 43.02224]}, "properties": {"woe:id": 23606708, "woe:parent_id": 2500764, "woe:name": "Highland Farm School The", "woe:placetype": 20, "woe:placetype_name": "POI", "woe:lang": "ENG", "iso:country": "US", "meta:provider": ["geoplanet:7.3.1", "geoplanet:7.3.2", "geoplanet:7.4.0", "geoplanet:7.4.1", "geoplanet:7.5.1", "geoplanet:7.5.2", "geoplanet:7.6.0", "geoplanet:7.8.1", "geoplanet:7.9.0", "geoplanet:7.10.0", "geoplanet:8.0.0", "woeplanet:8.0.0"], "meta:indexed": "2020-08-20T20:18:46.540082", "meta:updated": "2020-10-14T11:19:46.131643", "woe:hierarchy": {"continent": 24865672, "country": 23424977, "town": 0, "planet": 1, "county": 12589255, "suburb": 0, "state": 2347588, "region": 0, "localadmin": 0}, "woe:timezone_id": 56043648, "woe:hash": "drtsdxvw8wyf", "woe:centroid": [-70.898178, 43.02224], "geom:latitude": 43.02224, "geom:longitude": -70.898178, "geom:hash": "drtsdxvw8wyf", "woe:latitude": 43.02224, "geom:centroid": [-70.898178, 43.02224], "woe:longitude": -70.898178, "woe:repo": "woeplanet-poi-us", "geom:area": 0.0, "woe:scale": 19}}