{"type": "Feature", "id": 23671961, "geometry": {"type": "Point", "coordinates": [-81.106987, 38.053291]}, "properties": {"woe:id": 23671961, "woe:parent_id": 2402729, "woe:name": "Fayetteville Middle School", "woe:placetype": 20, "woe:placetype_name": "POI", "woe:lang": "ENG", "iso:country": "US", "meta:provider": ["geoplanet:7.3.1", "geoplanet:7.3.2", "geoplanet:7.4.0", "geoplanet:7.4.1", "geoplanet:7.5.1", "geoplanet:7.5.2", "geoplanet:7.6.0", "geoplanet:7.8.1", "geoplanet:7.9.0", "geoplanet:7.10.0", "geoplanet:8.0.0", "woeplanet:8.0.0"], "meta:indexed": "2020-08-20T20:19:10.034822", "meta:updated": "2020-10-14T11:19:27.247208", "woe:hierarchy": {"continent": 24865672, "country": 23424977, "town": 0, "planet": 1, "county": 12590488, "suburb": 0, "state": 2347607, "region": 0, "localadmin": 0}, "woe:timezone_id": 56043648, "woe:hash": "dny26r7sqpx4", "woe:centroid": [-81.106987, 38.053291], "geom:latitude": 38.053291, "geom:longitude": -81.106987, "geom:hash": "dny26r7sqpx4", "woe:latitude": 38.053291, "geom:centroid": [-81.106987, 38.053291], "woe:longitude": -81.106987, "woe:repo": "woeplanet-poi-us", "geom:area": 0.0, "woe:scale": 19}}