{"type": "Feature", "id": 23551008, "geometry": {"type": "Point", "coordinates": [-80.35273, 27.3256]}, "properties": {"woe:id": 23551008, "woe:parent_id": 2481889, "woe:name": "Northport Middle School", "woe:placetype": 20, "woe:placetype_name": "POI", "woe:lang": "ENG", "iso:country": "US", "meta:provider": ["geoplanet:7.3.1", "geoplanet:7.3.2", "geoplanet:7.4.0", "geoplanet:7.4.1", "geoplanet:7.5.1", "geoplanet:7.5.2", "geoplanet:7.6.0", "geoplanet:7.8.1", "geoplanet:7.9.0", "geoplanet:7.10.0", "geoplanet:8.0.0", "woeplanet:8.0.0"], "meta:indexed": "2020-08-20T20:18:28.680377", "meta:updated": "2020-10-14T11:20:09.493609", "woe:alias_ENG_V": ["Northport K-8 School"], "woe:hierarchy": {"continent": 24865672, "country": 23424977, "town": 0, "planet": 1, "county": 12587861, "suburb": 0, "state": 2347568, "region": 0, "localadmin": 0}, "woe:timezone_id": 56043648, "woe:hash": "dhyg7w2zjtjc", "woe:centroid": [-80.35273, 27.3256], "geom:latitude": 27.3256, "geom:longitude": -80.35273, "geom:hash": "dhyg7w2zjtjc", "woe:latitude": 27.3256, "geom:centroid": [-80.35273, 27.3256], "woe:longitude": -80.35273, "woe:repo": "woeplanet-poi-us", "geom:area": 0.0, "woe:scale": 19}}