{"type": "Feature", "id": 23640876, "geometry": {"type": "Point", "coordinates": [-75.506111, 39.864368]}, "properties": {"woe:id": 23640876, "woe:parent_id": 28745185, "woe:name": "Concord Elementary School", "woe:placetype": 20, "woe:placetype_name": "POI", "woe:lang": "ENG", "iso:country": "US", "meta:provider": ["geoplanet:7.3.1", "geoplanet:7.3.2", "geoplanet:7.4.0", "geoplanet:7.4.1", "geoplanet:7.5.1", "geoplanet:7.5.2", "geoplanet:7.6.0", "geoplanet:7.8.1", "geoplanet:7.9.0", "geoplanet:7.10.0", "geoplanet:8.0.0", "woeplanet:8.0.0"], "meta:indexed": "2020-08-20T20:18:58.695103", "woe:alias_ENG_V": ["Concord Elementary"], "meta:updated": "2020-10-14T11:19:51.288982", "woe:hierarchy": {"continent": 24865672, "country": 23424977, "town": 0, "planet": 1, "county": 12589750, "suburb": 0, "state": 2347597, "region": 0, "localadmin": 0}, "woe:timezone_id": 56043648, "woe:hash": "dr46cc44u0fc", "woe:centroid": [-75.506111, 39.864368], "geom:latitude": 39.864368, "geom:longitude": -75.506111, "geom:hash": "dr46cc44u0fc", "woe:latitude": 39.864368, "geom:centroid": [-75.506111, 39.864368], "woe:longitude": -75.506111, "woe:repo": "woeplanet-poi-us", "geom:area": 0.0, "woe:scale": 19}}