{"type": "Feature", "id": 23520408, "geometry": {"type": "Point", "coordinates": [-121.592392, 39.815369]}, "properties": {"woe:id": 23520408, "woe:parent_id": 2468180, "woe:name": "Pines Academy", "woe:placetype": 20, "woe:placetype_name": "POI", "woe:lang": "ENG", "iso:country": "US", "meta:provider": ["geoplanet:7.3.2", "geoplanet:7.4.0", "geoplanet:7.4.1", "geoplanet:7.5.1", "geoplanet:7.5.2", "geoplanet:7.6.0", "geoplanet:7.8.1", "geoplanet:7.9.0", "geoplanet:7.10.0", "geoplanet:8.0.0", "woeplanet:8.0.0"], "meta:indexed": "2020-08-20T22:01:58.224963", "meta:updated": "2020-10-14T11:20:03.383035", "woe:alias_ENG_V": ["Pines Christian Academy"], "woe:hierarchy": {"continent": 24865672, "country": 23424977, "town": 0, "planet": 1, "county": 12587673, "suburb": 0, "state": 2347563, "region": 0, "localadmin": 0}, "woe:timezone_id": 56043663, "woe:hash": "9r1d905j7ftp", "woe:centroid": [-121.592392, 39.815369], "geom:latitude": 39.815369, "geom:longitude": -121.592392, "geom:hash": "9r1d905j7ftp", "woe:latitude": 39.815369, "geom:centroid": [-121.592392, 39.815369], "woe:longitude": -121.592392, "woe:repo": "woeplanet-poi-us", "geom:area": 0.0, "woe:scale": 19}}