{"type": "Feature", "id": 23655527, "geometry": {"type": "Point", "coordinates": [-101.815491, 33.57058]}, "properties": {"woe:id": 23655527, "woe:parent_id": 55860067, "woe:name": "Dunbar Junior High School", "woe:placetype": 20, "woe:placetype_name": "POI", "woe:lang": "ENG", "iso:country": "US", "meta:provider": ["geoplanet:7.3.1", "geoplanet:7.3.2", "geoplanet:7.4.0", "geoplanet:7.4.1", "geoplanet:7.5.1", "geoplanet:7.5.2", "geoplanet:7.6.0", "geoplanet:7.8.1", "geoplanet:7.9.0", "geoplanet:7.10.0", "geoplanet:8.0.0", "woeplanet:8.0.0"], "meta:indexed": "2020-08-20T20:19:03.908898", "woe:alias_ENG_V": ["Dunbar Junior High"], "meta:updated": "2020-10-14T11:19:38.573271", "woe:hierarchy": {"continent": 24865672, "country": 23424977, "town": 0, "planet": 1, "county": 12590158, "suburb": 0, "state": 2347602, "region": 0, "localadmin": 0}, "woe:timezone_id": 56043661, "woe:hash": "9tzwgpk4z1eq", "woe:centroid": [-101.815491, 33.57058], "geom:latitude": 33.57058, "geom:longitude": -101.815491, "geom:hash": "9tzwgpk4z1eq", "woe:latitude": 33.57058, "geom:centroid": [-101.815491, 33.57058], "woe:longitude": -101.815491, "woe:repo": "woeplanet-poi-us", "geom:area": 0.0, "woe:scale": 19}}