{"type": "Feature", "id": 56054170, "geometry": {"type": "Point", "coordinates": [-77.093147, 43.027409]}, "properties": {"woe:id": 56054170, "woe:parent_id": 2459267, "woe:name": "Finger Lakes Community College-Newark", "woe:placetype": 20, "woe:placetype_name": "POI", "woe:lang": "ENG", "iso:country": "US", "meta:provider": ["geoplanet:7.3.1", "geoplanet:7.3.2", "geoplanet:7.4.0", "geoplanet:7.4.1", "geoplanet:7.5.1", "geoplanet:7.5.2", "geoplanet:7.6.0", "geoplanet:7.8.1", "geoplanet:7.9.0", "geoplanet:7.10.0", "geoplanet:8.0.0", "woeplanet:8.0.0"], "meta:indexed": "2020-08-20T20:19:17.620583", "meta:updated": "2020-10-14T11:19:56.650108", "woe:hierarchy": {"continent": 24865672, "country": 23424977, "town": 0, "planet": 1, "county": 12589370, "suburb": 0, "state": 2347591, "region": 0, "localadmin": 0}, "woe:timezone_id": 56043648, "woe:hash": "dr9hv8ykz6rh", "woe:centroid": [-77.093147, 43.027409], "geom:latitude": 43.027409, "geom:longitude": -77.093147, "geom:hash": "dr9hv8ykz6rh", "woe:latitude": 43.027409, "geom:centroid": [-77.093147, 43.027409], "woe:longitude": -77.093147, "woe:repo": "woeplanet-poi-us", "geom:area": 0.0, "woe:scale": 19}}