{"type": "Feature", "id": 23583671, "properties": {"woe:id": 23583671, "woe:parent_id": 2415963, "woe:name": "Hopkins Academy", "woe:placetype": 20, "woe:placetype_name": "POI", "woe:lang": "ENG", "iso:country": "US", "meta:provider": ["geoplanet:7.3.1", "geoplanet:7.3.2", "geoplanet:7.4.0", "geoplanet:7.4.1", "geoplanet:7.5.1", "geoplanet:7.5.2", "geoplanet:7.6.0", "geoplanet:7.8.1", "geoplanet:7.9.0", "geoplanet:7.10.0", "geoplanet:8.0.0", "woeplanet:8.0.0"], "meta:indexed": "2020-08-20T20:18:39.310298", "meta:updated": "2020-08-22T02:57:38.357688", "woe:hierarchy": {"continent": 24865672, "country": 23424977, "town": 0, "planet": 1, "county": 12588707, "suburb": 0, "state": 2347580, "region": 0, "localadmin": 0}, "woe:timezone_id": 56043648, "woe:hash": "drs2uhhsu6bz", "woe:centroid": [-72.591293, 42.34214], "geom:latitude": 42.34214, "geom:longitude": -72.591293, "geom:hash": "drs2uhhsu6bz", "woe:latitude": 42.34214, "geom:centroid": [-72.591293, 42.34214], "woe:longitude": -72.591293, "woe:repo": "woeplanet-poi-us"}, "geometry": {"coordinates": [-72.591293, 42.34214], "type": "Point"}}