{"type": "Feature", "id": 23523462, "geometry": {"type": "Point", "coordinates": [-122.320396, 38.242981]}, "properties": {"woe:id": 23523462, "woe:parent_id": 12587697, "woe:name": "Carneros Elementary School", "woe:placetype": 20, "woe:placetype_name": "POI", "woe:lang": "ENG", "iso:country": "US", "meta:provider": ["geoplanet:7.3.2", "geoplanet:7.4.0", "geoplanet:7.4.1", "geoplanet:7.5.1", "geoplanet:7.5.2", "geoplanet:7.6.0", "geoplanet:7.8.1", "geoplanet:7.9.0", "geoplanet:7.10.0", "geoplanet:8.0.0", "woeplanet:8.0.0"], "meta:indexed": "2020-08-20T22:01:59.205881", "woe:alias_ENG_V": ["Carneros Elementary"], "meta:updated": "2020-10-14T11:20:05.301022", "woe:hierarchy": {"continent": 24865672, "country": 23424977, "town": 0, "planet": 1, "county": 12587697, "suburb": 0, "state": 2347563, "region": 0, "localadmin": 0}, "woe:timezone_id": 56043663, "woe:hash": "9qc189cj80q5", "woe:centroid": [-122.320396, 38.242981], "geom:latitude": 38.242981, "geom:longitude": -122.320396, "geom:hash": "9qc189cj80q5", "woe:latitude": 38.242981, "geom:centroid": [-122.320396, 38.242981], "woe:longitude": -122.320396, "woe:repo": "woeplanet-poi-us", "geom:area": 0.0, "woe:scale": 19}}