{"type": "Feature", "id": 23597229, "properties": {"woe:id": 23597229, "woe:parent_id": 2500093, "woe:name": "Stockton Elementary School", "woe:placetype": 20, "woe:placetype_name": "POI", "woe:lang": "ENG", "iso:country": "US", "meta:provider": ["geoplanet:7.3.1", "geoplanet:7.3.2", "geoplanet:7.4.0", "geoplanet:7.4.1", "geoplanet:7.5.1", "geoplanet:7.5.2", "geoplanet:7.6.0", "geoplanet:7.8.1", "geoplanet:7.9.0", "geoplanet:7.10.0", "geoplanet:8.0.0", "woeplanet:8.0.0"], "meta:indexed": "2020-08-20T20:18:43.790566", "woe:alias_ENG_V": ["Stockton Elementary"], "meta:updated": "2020-08-22T02:57:40.585830", "woe:hierarchy": {"continent": 24865672, "country": 23424977, "town": 0, "planet": 1, "county": 12588985, "suburb": 0, "state": 2347584, "region": 0, "localadmin": 0}, "woe:timezone_id": 56043661, "woe:hash": "9ytq3tedw7m1", "woe:centroid": [-93.796188, 37.691792], "geom:latitude": 37.691792, "geom:longitude": -93.796188, "geom:hash": "9ytq3tedw7m1", "woe:latitude": 37.691792, "geom:centroid": [-93.796188, 37.691792], "woe:longitude": -93.796188, "woe:repo": "woeplanet-poi-us"}, "geometry": {"coordinates": [-93.796188, 37.691792], "type": "Point"}}