{"type": "Feature", "id": 23570812, "geometry": {"type": "Point", "coordinates": [-93.320221, 40.75811]}, "properties": {"woe:id": 23570812, "woe:parent_id": 2385405, "woe:name": "Wayne Community High School", "woe:placetype": 20, "woe:placetype_name": "POI", "woe:lang": "ENG", "iso:country": "US", "meta:provider": ["geoplanet:7.3.1", "geoplanet:7.3.2", "geoplanet:7.4.0", "geoplanet:7.4.1", "geoplanet:7.5.1", "geoplanet:7.5.2", "geoplanet:7.6.0", "geoplanet:7.8.1", "geoplanet:7.9.0", "geoplanet:7.10.0", "geoplanet:8.0.0", "woeplanet:8.0.0"], "meta:indexed": "2020-08-20T20:18:35.694161", "woe:alias_ENG_V": ["Wayne Community Senior High School", "Wayne Community High", "Wayne Community Senior High", "Wayne Community HS", "Wayne Community Senior HS"], "meta:updated": "2020-10-14T11:20:07.031732", "woe:hierarchy": {"continent": 24865672, "country": 23424977, "town": 0, "planet": 1, "county": 12588364, "suburb": 0, "state": 2347574, "region": 0, "localadmin": 0}, "woe:timezone_id": 56043661, "woe:hash": "9zjxu7y31nru", "woe:centroid": [-93.320221, 40.75811], "geom:latitude": 40.75811, "geom:longitude": -93.320221, "geom:hash": "9zjxu7y31nru", "woe:latitude": 40.75811, "geom:centroid": [-93.320221, 40.75811], "woe:longitude": -93.320221, "woe:repo": "woeplanet-poi-us", "geom:area": 0.0, "woe:scale": 19}}