{"type": "Feature", "id": 23576780, "properties": {"woe:id": 23576780, "woe:parent_id": 23512140, "woe:name": "Bauduit Agnes L Elementary School", "woe:placetype": 20, "woe:placetype_name": "POI", "woe:lang": "ENG", "iso:country": "US", "meta:provider": ["geoplanet:7.3.1", "geoplanet:7.3.2", "geoplanet:7.4.0", "geoplanet:7.4.1", "geoplanet:7.5.1", "geoplanet:7.5.2", "geoplanet:7.6.0", "geoplanet:7.8.1", "geoplanet:7.9.0", "geoplanet:7.10.0", "geoplanet:8.0.0", "woeplanet:8.0.0"], "meta:indexed": "2020-08-20T20:19:15.982296", "woe:alias_ENG_V": ["Agnes Bauduit Elementary School", "Bauduit, Agnes L, Elementary School", "Bauduit, Agnes L, Elementary"], "meta:updated": "2020-08-22T02:58:20.228107", "woe:hierarchy": {"continent": 24865672, "country": 23424977, "town": 0, "planet": 1, "county": 12588631, "suburb": 0, "state": 2347577, "region": 0, "localadmin": 0}, "woe:timezone_id": 56043661, "woe:hash": "9vrfjyubj5kx", "woe:centroid": [-90.092133, 29.91991], "geom:latitude": 29.91991, "geom:longitude": -90.092133, "geom:hash": "9vrfjyubj5kx", "woe:latitude": 29.91991, "geom:centroid": [-90.092133, 29.91991], "woe:longitude": -90.092133, "woe:repo": "woeplanet-poi-us"}, "geometry": {"coordinates": [-90.092133, 29.91991], "type": "Point"}}