{"type": "Feature", "id": 23540744, "properties": {"woe:id": 23540744, "woe:parent_id": 2513927, "woe:name": "John Mall High School", "woe:placetype": 20, "woe:placetype_name": "POI", "woe:lang": "ENG", "iso:country": "US", "meta:provider": ["geoplanet:7.3.1", "geoplanet:7.3.2", "geoplanet:7.4.0", "geoplanet:7.4.1", "geoplanet:7.5.1", "geoplanet:7.5.2", "geoplanet:7.6.0", "geoplanet:7.8.1", "geoplanet:7.9.0", "geoplanet:7.10.0", "geoplanet:8.0.0", "woeplanet:8.0.0"], "meta:indexed": "2020-08-20T20:18:24.521929", "woe:alias_ENG_V": ["John Mall Senior High School", "John Mall High", "John Mall Senior High", "John Mall HS", "John Mall Senior HS"], "meta:updated": "2020-08-22T02:58:46.580199", "woe:hierarchy": {"continent": 24865672, "country": 23424977, "town": 0, "planet": 1, "county": 12587755, "suburb": 0, "state": 2347564, "region": 0, "localadmin": 0}, "woe:timezone_id": 56043665, "woe:hash": "9wtqp6v4t5jn", "woe:centroid": [-104.791496, 37.63274], "geom:latitude": 37.63274, "geom:longitude": -104.791496, "geom:hash": "9wtqp6v4t5jn", "woe:latitude": 37.63274, "geom:centroid": [-104.791496, 37.63274], "woe:longitude": -104.791496, "woe:repo": "woeplanet-poi-us"}, "geometry": {"coordinates": [-104.791496, 37.63274], "type": "Point"}}