{"type": "Feature", "id": 23648791, "geometry": {"type": "Point", "coordinates": [-103.228577, 44.076859]}, "properties": {"woe:id": 23648791, "woe:parent_id": 2478734, "woe:name": "Dakota Middle School", "woe:placetype": 20, "woe:placetype_name": "POI", "woe:lang": "ENG", "iso:country": "US", "meta:provider": ["geoplanet:7.3.1", "geoplanet:7.3.2", "geoplanet:7.4.0", "geoplanet:7.4.1", "geoplanet:7.5.1", "geoplanet:7.5.2", "geoplanet:7.6.0", "geoplanet:7.8.1", "geoplanet:7.9.0", "geoplanet:7.10.0", "geoplanet:8.0.0", "woeplanet:8.0.0"], "meta:indexed": "2020-08-20T20:19:01.337415", "meta:updated": "2020-10-14T11:19:41.919391", "woe:hierarchy": {"continent": 24865672, "country": 23424977, "town": 0, "planet": 1, "county": 12589896, "suburb": 0, "state": 2347600, "region": 0, "localadmin": 0}, "woe:timezone_id": 56043665, "woe:hash": "9xyddzznrf41", "woe:centroid": [-103.228577, 44.076859], "geom:latitude": 44.076859, "geom:longitude": -103.228577, "geom:hash": "9xyddzznrf41", "woe:latitude": 44.076859, "geom:centroid": [-103.228577, 44.076859], "woe:longitude": -103.228577, "woe:repo": "woeplanet-poi-us", "geom:area": 0.0, "woe:scale": 19}}