{"type": "Feature", "id": 23676354, "geometry": {"type": "Point", "coordinates": [-88.343086, 43.114262]}, "properties": {"woe:id": 23676354, "woe:parent_id": 2418302, "woe:name": "Arrowhead High School", "woe:placetype": 20, "woe:placetype_name": "POI", "woe:lang": "ENG", "iso:country": "US", "meta:provider": ["geoplanet:7.3.1", "geoplanet:7.3.2", "geoplanet:7.4.0", "geoplanet:7.4.1", "geoplanet:7.5.1", "geoplanet:7.5.2", "geoplanet:7.6.0", "geoplanet:7.8.1", "geoplanet:7.9.0", "geoplanet:7.10.0", "geoplanet:8.0.0", "woeplanet:8.0.0"], "meta:indexed": "2020-08-20T20:19:11.956949", "woe:alias_ENG_V": ["Arrowhead Senior High School", "Arrowhead High", "Arrowhead Senior High", "Arrowhead HS", "Arrowhead Senior HS"], "meta:updated": "2020-10-14T11:19:28.413938", "woe:hierarchy": {"continent": 24865672, "country": 23424977, "town": 0, "planet": 1, "county": 12590601, "suburb": 0, "state": 2347608, "region": 0, "localadmin": 0}, "woe:timezone_id": 56043661, "woe:hash": "dp9jm8wwbbuw", "woe:centroid": [-88.343086, 43.114262], "geom:latitude": 43.114262, "geom:longitude": -88.343086, "geom:hash": "dp9jm8wwbbuw", "woe:latitude": 43.114262, "geom:centroid": [-88.343086, 43.114262], "woe:longitude": -88.343086, "woe:repo": "woeplanet-poi-us", "geom:area": 0.0, "woe:scale": 19}}