{"type": "Feature", "id": 56053689, "geometry": {"type": "Point", "coordinates": [-81.069641, 36.958649]}, "properties": {"woe:id": 56053689, "woe:parent_id": 2524410, "woe:name": "Wytheville Community College", "woe:placetype": 20, "woe:placetype_name": "POI", "woe:lang": "ENG", "iso:country": "US", "meta:provider": ["geoplanet:7.3.1", "geoplanet:7.3.2", "geoplanet:7.4.0", "geoplanet:7.4.1", "geoplanet:7.5.1", "geoplanet:7.5.2", "geoplanet:7.6.0", "geoplanet:7.8.1", "geoplanet:7.9.0", "geoplanet:7.10.0", "geoplanet:8.0.0", "woeplanet:8.0.0"], "meta:indexed": "2020-08-20T20:19:17.241967", "meta:updated": "2020-10-14T11:19:55.809445", "woe:hierarchy": {"continent": 24865672, "country": 23424977, "town": 0, "planet": 1, "county": 12590438, "suburb": 0, "state": 2347605, "region": 0, "localadmin": 0}, "woe:timezone_id": 56043648, "woe:hash": "dnw670ngsrw2", "woe:centroid": [-81.069641, 36.958649], "geom:latitude": 36.958649, "geom:longitude": -81.069641, "geom:hash": "dnw670ngsrw2", "woe:latitude": 36.958649, "geom:centroid": [-81.069641, 36.958649], "woe:longitude": -81.069641, "woe:repo": "woeplanet-poi-us", "geom:area": 0.0, "woe:scale": 19}}