{"type": "Feature", "id": 23518699, "geometry": {"type": "Point", "coordinates": [-89.900818, 35.93634]}, "properties": {"woe:id": 23518699, "woe:parent_id": 2366136, "woe:name": "East Junior High School", "woe:placetype": 20, "woe:placetype_name": "POI", "woe:lang": "ENG", "iso:country": "US", "meta:provider": ["geoplanet:7.3.1", "geoplanet:7.3.2", "geoplanet:7.4.0", "geoplanet:7.4.1", "geoplanet:7.5.1", "geoplanet:7.5.2", "geoplanet:7.6.0", "geoplanet:7.8.1", "geoplanet:7.9.0", "geoplanet:7.10.0", "geoplanet:8.0.0", "woeplanet:8.0.0"], "meta:indexed": "2020-08-20T20:18:19.161357", "woe:alias_ENG_V": ["E Junior High School", "E Junior High", "East Junior High"], "meta:updated": "2020-10-14T11:20:12.092632", "woe:hierarchy": {"continent": 24865672, "country": 23424977, "town": 0, "planet": 1, "county": 12587641, "suburb": 0, "state": 2347562, "region": 0, "localadmin": 0}, "woe:timezone_id": 56043661, "woe:hash": "dn2h6q00r576", "woe:centroid": [-89.900818, 35.93634], "geom:latitude": 35.93634, "geom:longitude": -89.900818, "geom:hash": "dn2h6q00r576", "woe:latitude": 35.93634, "geom:centroid": [-89.900818, 35.93634], "woe:longitude": -89.900818, "woe:repo": "woeplanet-poi-us", "geom:area": 0.0, "woe:scale": 19}}