{"type": "Feature", "id": 23589517, "geometry": {"type": "Point", "coordinates": [-83.226334, 42.630409]}, "properties": {"woe:id": 23589517, "woe:parent_id": 2357305, "woe:name": "Auburn Elementary School", "woe:placetype": 20, "woe:placetype_name": "POI", "woe:lang": "ENG", "iso:country": "US", "meta:provider": ["geoplanet:7.3.1", "geoplanet:7.3.2", "geoplanet:7.4.0", "geoplanet:7.4.1", "geoplanet:7.5.1", "geoplanet:7.5.2", "geoplanet:7.6.0", "geoplanet:7.8.1", "geoplanet:7.9.0", "geoplanet:7.10.0", "geoplanet:8.0.0", "woeplanet:8.0.0"], "meta:indexed": "2020-08-20T20:18:40.979914", "woe:alias_ENG_V": ["Auburn Elementary"], "meta:updated": "2020-10-14T11:20:26.825790", "woe:hierarchy": {"continent": 24865672, "country": 23424977, "town": 0, "planet": 1, "county": 12588776, "suburb": 0, "state": 2347581, "region": 0, "localadmin": 0}, "woe:timezone_id": 56043658, "woe:hash": "dpsfd0skju5r", "woe:centroid": [-83.226334, 42.630409], "geom:latitude": 42.630409, "geom:longitude": -83.226334, "geom:hash": "dpsfd0skju5r", "woe:latitude": 42.630409, "geom:centroid": [-83.226334, 42.630409], "woe:longitude": -83.226334, "woe:repo": "woeplanet-poi-us", "geom:area": 0.0, "woe:scale": 19}}