{"type": "Feature", "id": 23674162, "properties": {"woe:id": 23674162, "woe:parent_id": 2515210, "woe:name": "St Marks Lutheran School", "woe:placetype": 20, "woe:placetype_name": "POI", "woe:lang": "ENG", "iso:country": "US", "meta:provider": ["geoplanet:7.3.2", "geoplanet:7.4.0", "geoplanet:7.4.1", "geoplanet:7.5.1", "geoplanet:7.5.2", "geoplanet:7.6.0", "geoplanet:7.8.1", "geoplanet:7.9.0", "geoplanet:7.10.0", "geoplanet:8.0.0", "woeplanet:8.0.0"], "meta:indexed": "2020-08-20T22:03:01.834687", "meta:updated": "2020-08-22T02:58:17.848934", "woe:hierarchy": {"continent": 24865672, "country": 23424977, "town": 0, "planet": 1, "county": 12590561, "suburb": 0, "state": 2347608, "region": 0, "localadmin": 0}, "woe:timezone_id": 56043661, "woe:hash": "dp8vtptdjb5b", "woe:centroid": [-88.717781, 43.195839], "geom:latitude": 43.195839, "geom:longitude": -88.717781, "geom:hash": "dp8vtptdjb5b", "woe:latitude": 43.195839, "geom:centroid": [-88.717781, 43.195839], "woe:longitude": -88.717781, "woe:repo": "woeplanet-poi-us"}, "geometry": {"coordinates": [-88.717781, 43.195839], "type": "Point"}}