{"type": "Feature", "id": 24930918, "geometry": {"type": "Point", "coordinates": [-81.037003, 33.994678]}, "properties": {"woe:id": 24930918, "woe:parent_id": 55858526, "woe:name": "Colonial Center", "woe:placetype": 20, "woe:placetype_name": "POI", "woe:lang": "ENG", "iso:country": "US", "meta:provider": ["geoplanet:7.3.1", "geoplanet:7.3.2", "geoplanet:7.4.0", "geoplanet:7.4.1", "geoplanet:7.5.1", "geoplanet:7.5.2", "geoplanet:7.6.0", "geoplanet:7.8.1", "geoplanet:7.9.0", "geoplanet:7.10.0", "geoplanet:8.0.0", "woeplanet:8.0.0"], "meta:indexed": "2020-08-20T20:19:15.524228", "meta:updated": "2020-10-14T11:20:59.759116", "woe:alias_ENG_V": ["Colonial Life Arena"], "woe:hierarchy": {"continent": 24865672, "country": 23424977, "town": 0, "planet": 1, "county": 12589839, "suburb": 0, "state": 2347599, "region": 0, "localadmin": 0}, "woe:timezone_id": 56043648, "woe:hash": "dnn37uw9kgqc", "woe:centroid": [-81.037003, 33.994678], "geom:latitude": 33.994678, "geom:longitude": -81.037003, "geom:hash": "dnn37uw9kgqc", "woe:latitude": 33.994678, "geom:centroid": [-81.037003, 33.994678], "woe:longitude": -81.037003, "woe:repo": "woeplanet-poi-us", "geom:area": 0.0, "woe:scale": 19}}