{"type": "Feature", "id": 23530186, "properties": {"woe:id": 23530186, "woe:parent_id": 2436084, "woe:name": "Antelope Valley High School", "woe:placetype": 20, "woe:placetype_name": "POI", "woe:lang": "ENG", "iso:country": "US", "meta:provider": ["geoplanet:7.3.2", "geoplanet:7.4.0", "geoplanet:7.4.1", "geoplanet:7.5.1", "geoplanet:7.5.2", "geoplanet:7.6.0", "geoplanet:7.8.1", "geoplanet:7.9.0", "geoplanet:7.10.0", "geoplanet:8.0.0", "woeplanet:8.0.0"], "meta:indexed": "2020-08-20T22:02:01.601033", "woe:alias_ENG_V": ["Antelope Valley Senior High School", "Antelope Valley High", "Antelope Valley Senior High", "Antelope Valley HS", "Antelope Valley Senior HS"], "meta:updated": "2020-08-22T02:58:46.304066", "woe:hierarchy": {"continent": 24865672, "country": 23424977, "town": 0, "planet": 1, "county": 12587688, "suburb": 0, "state": 2347563, "region": 0, "localadmin": 0}, "woe:timezone_id": 56043663, "woe:hash": "9q5vrugbqspg", "woe:centroid": [-118.130547, 34.699009], "geom:latitude": 34.699009, "geom:longitude": -118.130547, "geom:hash": "9q5vrugbqspg", "woe:latitude": 34.699009, "geom:centroid": [-118.130547, 34.699009], "woe:longitude": -118.130547, "woe:repo": "woeplanet-poi-us"}, "geometry": {"coordinates": [-118.130547, 34.699009], "type": "Point"}}