{"type": "Feature", "id": 56063810, "properties": {"woe:id": 56063810, "woe:parent_id": 2396127, "woe:name": "Fairview Heights Station", "woe:placetype": 20, "woe:placetype_name": "POI", "woe:lang": "ENG", "iso:country": "US", "meta:provider": ["geoplanet:7.3.1", "geoplanet:7.3.2", "geoplanet:7.4.0", "geoplanet:7.4.1", "geoplanet:7.5.1", "geoplanet:7.5.2", "geoplanet:7.6.0", "geoplanet:7.8.1", "geoplanet:7.9.0", "geoplanet:7.10.0", "geoplanet:8.0.0", "woeplanet:8.0.0"], "meta:indexed": "2020-08-20T20:19:20.789778", "woe:alias_ENG_V": ["Fairview Heights Metrolink Station", "Metrolink Fairview Heights Station", "Metrolink-Fairview Heights Station"], "meta:updated": "2020-08-22T02:58:22.976654", "woe:hierarchy": {"continent": 24865672, "country": 23424977, "town": 0, "planet": 1, "county": 12588164, "suburb": 0, "state": 2347572, "region": 0, "localadmin": 0}, "woe:timezone_id": 56043661, "woe:hash": "9yzgwfk19rtc", "woe:centroid": [-90.049377, 38.596642], "geom:latitude": 38.596642, "geom:longitude": -90.049377, "geom:hash": "9yzgwfk19rtc", "woe:latitude": 38.596642, "geom:centroid": [-90.049377, 38.596642], "woe:longitude": -90.049377, "woe:repo": "woeplanet-poi-us"}, "geometry": {"coordinates": [-90.049377, 38.596642], "type": "Point"}}