{"type": "Feature", "id": 23661194, "geometry": {"type": "Point", "coordinates": [-94.416069, 30.77809]}, "properties": {"woe:id": 23661194, "woe:parent_id": 2523829, "woe:name": "Woodville Intermediate School", "woe:placetype": 20, "woe:placetype_name": "POI", "woe:lang": "ENG", "iso:country": "US", "meta:provider": ["geoplanet:7.3.1", "geoplanet:7.3.2", "geoplanet:7.4.0", "geoplanet:7.4.1", "geoplanet:7.5.1", "geoplanet:7.5.2", "geoplanet:7.6.0", "geoplanet:7.8.1", "geoplanet:7.9.0", "geoplanet:7.10.0", "geoplanet:8.0.0", "woeplanet:8.0.0"], "meta:indexed": "2020-08-20T20:19:06.839286", "meta:updated": "2020-10-14T11:19:46.097426", "woe:hierarchy": {"continent": 24865672, "country": 23424977, "town": 0, "planet": 1, "county": 12590235, "suburb": 0, "state": 2347602, "region": 0, "localadmin": 0}, "woe:timezone_id": 56043661, "woe:hash": "9vkz5dbr65u6", "woe:centroid": [-94.416069, 30.77809], "geom:latitude": 30.77809, "geom:longitude": -94.416069, "geom:hash": "9vkz5dbr65u6", "woe:latitude": 30.77809, "geom:centroid": [-94.416069, 30.77809], "woe:longitude": -94.416069, "woe:repo": "woeplanet-poi-us", "geom:area": 0.0, "woe:scale": 19}}