{"type": "Feature", "id": 23651953, "geometry": {"type": "Point", "coordinates": [-89.871498, 35.17749]}, "properties": {"woe:id": 23651953, "woe:parent_id": 2478302, "woe:name": "Harding Academy of Sycamore View", "woe:placetype": 20, "woe:placetype_name": "POI", "woe:lang": "ENG", "iso:country": "US", "meta:provider": ["geoplanet:7.4.0", "geoplanet:7.4.1", "geoplanet:7.5.1", "geoplanet:7.5.2", "geoplanet:7.6.0", "geoplanet:7.8.1", "geoplanet:7.9.0", "geoplanet:7.10.0", "geoplanet:8.0.0", "woeplanet:8.0.0"], "meta:indexed": "2020-08-20T23:55:37.440334", "meta:updated": "2020-10-14T11:19:46.662413", "woe:hierarchy": {"continent": 24865672, "country": 23424977, "town": 0, "planet": 1, "county": 12589990, "suburb": 0, "state": 2347601, "region": 0, "localadmin": 0}, "woe:timezone_id": 56043661, "woe:hash": "dn204gvedr6j", "woe:centroid": [-89.871498, 35.17749], "geom:latitude": 35.17749, "geom:longitude": -89.871498, "geom:hash": "dn204gvedr6j", "woe:latitude": 35.17749, "geom:centroid": [-89.871498, 35.17749], "woe:longitude": -89.871498, "woe:repo": "woeplanet-poi-us", "geom:area": 0.0, "woe:scale": 19}}