{"type": "Feature", "id": 23684754, "properties": {"woe:id": 23684754, "woe:parent_id": 2498036, "woe:name": "Richland Mall Shopping Center", "woe:placetype": 20, "woe:placetype_name": "POI", "woe:lang": "ENG", "iso:country": "US", "meta:provider": ["geoplanet:7.3.1", "geoplanet:7.3.2", "geoplanet:7.4.0", "geoplanet:7.4.1", "geoplanet:7.5.1", "geoplanet:7.5.2", "geoplanet:7.6.0", "geoplanet:7.8.1", "geoplanet:7.9.0", "geoplanet:7.10.0", "geoplanet:8.0.0", "woeplanet:8.0.0"], "meta:indexed": "2020-08-20T20:19:13.182640", "meta:updated": "2020-08-22T02:58:18.905918", "woe:hierarchy": {"continent": 24865672, "country": 23424977, "town": 0, "planet": 1, "county": 12589596, "suburb": 0, "state": 2347594, "region": 0, "localadmin": 0}, "woe:timezone_id": 56043648, "woe:hash": "dpm20s5zb1tv", "woe:centroid": [-82.590057, 40.804562], "geom:latitude": 40.804562, "geom:longitude": -82.590057, "geom:hash": "dpm20s5zb1tv", "woe:latitude": 40.804562, "geom:centroid": [-82.590057, 40.804562], "woe:longitude": -82.590057, "woe:repo": "woeplanet-poi-us"}, "geometry": {"coordinates": [-82.590057, 40.804562], "type": "Point"}}