{"type": "Feature", "id": 23680830, "geometry": {"type": "Point", "coordinates": [-83.629448, 30.49003]}, "properties": {"woe:id": 23680830, "woe:parent_id": 2414590, "woe:name": "Reams Station", "woe:placetype": 20, "woe:placetype_name": "POI", "woe:lang": "ENG", "iso:country": "US", "meta:provider": ["geoplanet:7.3.1", "geoplanet:7.3.2", "geoplanet:7.4.0", "geoplanet:7.4.1", "geoplanet:7.5.1", "geoplanet:7.5.2", "geoplanet:7.6.0", "geoplanet:7.8.1", "geoplanet:7.9.0", "geoplanet:7.10.0", "geoplanet:8.0.0", "woeplanet:8.0.0"], "meta:indexed": "2020-08-20T20:19:18.690221", "meta:updated": "2020-10-14T11:19:51.890531", "woe:hierarchy": {"continent": 24865672, "country": 23424977, "town": 0, "planet": 1, "county": 12587842, "suburb": 0, "state": 2347568, "region": 0, "localadmin": 0}, "woe:timezone_id": 56043648, "woe:hash": "djkt2ywck9ec", "woe:centroid": [-83.629448, 30.49003], "geom:latitude": 30.49003, "geom:longitude": -83.629448, "geom:hash": "djkt2ywck9ec", "woe:latitude": 30.49003, "geom:centroid": [-83.629448, 30.49003], "woe:longitude": -83.629448, "woe:repo": "woeplanet-poi-us", "geom:area": 0.0, "woe:scale": 19}}