{"type": "Feature", "id": 56063576, "properties": {"woe:id": 56063576, "woe:parent_id": 55986736, "woe:name": "New Orleans Station", "woe:placetype": 20, "woe:placetype_name": "POI", "woe:lang": "ENG", "iso:country": "US", "meta:provider": ["geoplanet:7.3.1", "geoplanet:7.3.2", "geoplanet:7.4.0", "geoplanet:7.4.1", "geoplanet:7.5.1", "geoplanet:7.5.2", "geoplanet:7.6.0", "geoplanet:7.8.1", "geoplanet:7.9.0", "geoplanet:7.10.0", "geoplanet:8.0.0", "woeplanet:8.0.0"], "meta:indexed": "2020-08-20T20:19:20.628729", "woe:alias_ENG_V": ["New Orleans Amtrak Station", "Amtrak New Orleans Station", "Amtrak-New Orleans"], "meta:updated": "2020-08-22T02:58:22.886654", "woe:hierarchy": {"continent": 24865672, "country": 23424977, "town": 0, "planet": 1, "county": 12588631, "suburb": 0, "state": 2347577, "region": 0, "localadmin": 0}, "woe:timezone_id": 56043661, "woe:hash": "9vrfq5x4uds5", "woe:centroid": [-90.078079, 29.94647], "geom:latitude": 29.94647, "geom:longitude": -90.078079, "geom:hash": "9vrfq5x4uds5", "woe:latitude": 29.94647, "geom:centroid": [-90.078079, 29.94647], "woe:longitude": -90.078079, "woe:repo": "woeplanet-poi-us"}, "geometry": {"coordinates": [-90.078079, 29.94647], "type": "Point"}}