{"type": "Feature", "id": 23634752, "geometry": {"type": "Point", "coordinates": [-95.993538, 36.23344]}, "properties": {"woe:id": 23634752, "woe:parent_id": 2508750, "woe:name": "Gilcrease Intermediate School", "woe:placetype": 20, "woe:placetype_name": "POI", "woe:lang": "ENG", "iso:country": "US", "meta:provider": ["geoplanet:7.3.2", "geoplanet:7.4.0", "geoplanet:7.4.1", "geoplanet:7.5.1", "geoplanet:7.5.2", "geoplanet:7.6.0", "geoplanet:7.8.1", "geoplanet:7.9.0", "geoplanet:7.10.0", "geoplanet:8.0.0", "woeplanet:8.0.0"], "meta:indexed": "2020-08-20T22:02:45.070996", "meta:updated": "2020-10-14T11:19:48.509947", "woe:alias_ENG_V": ["Gilcrease Middle School"], "woe:hierarchy": {"continent": 24865672, "country": 23424977, "town": 0, "planet": 1, "county": 12589686, "suburb": 0, "state": 2347595, "region": 0, "localadmin": 0}, "woe:timezone_id": 56043661, "woe:hash": "9y7wps5eh6y0", "woe:centroid": [-95.993538, 36.23344], "geom:latitude": 36.23344, "geom:longitude": -95.993538, "geom:hash": "9y7wps5eh6y0", "woe:latitude": 36.23344, "geom:centroid": [-95.993538, 36.23344], "woe:longitude": -95.993538, "woe:repo": "woeplanet-poi-us", "geom:area": 0.0, "woe:scale": 19}}