{"type": "Feature", "id": 23680910, "geometry": {"type": "Point", "coordinates": [-86.115623, 30.72035]}, "properties": {"woe:id": 23680910, "woe:parent_id": 2389955, "woe:name": "De Funiak Springs Station", "woe:placetype": 20, "woe:placetype_name": "POI", "woe:lang": "ENG", "iso:country": "US", "meta:provider": ["geoplanet:7.3.1", "geoplanet:7.3.2", "geoplanet:7.4.0", "geoplanet:7.4.1", "geoplanet:7.5.1", "geoplanet:7.5.2", "geoplanet:7.6.0", "geoplanet:7.8.1", "geoplanet:7.9.0", "geoplanet:7.10.0", "geoplanet:8.0.0", "woeplanet:8.0.0"], "meta:indexed": "2020-08-20T20:19:18.750130", "meta:updated": "2020-10-14T11:19:42.965824", "woe:hierarchy": {"continent": 24865672, "country": 23424977, "town": 0, "planet": 1, "county": 12587868, "suburb": 0, "state": 2347568, "region": 0, "localadmin": 0}, "woe:timezone_id": 56043661, "woe:hash": "dj6yb2kx0833", "woe:centroid": [-86.115623, 30.72035], "geom:latitude": 30.72035, "geom:longitude": -86.115623, "geom:hash": "dj6yb2kx0833", "woe:latitude": 30.72035, "geom:centroid": [-86.115623, 30.72035], "woe:longitude": -86.115623, "woe:repo": "woeplanet-poi-us", "geom:area": 0.0, "woe:scale": 19}}