{"type": "Feature", "id": 23516420, "properties": {"woe:id": 23516420, "woe:parent_id": 29230211, "woe:name": "Phoenix Christian Junior Senior High School", "woe:placetype": 20, "woe:placetype_name": "POI", "woe:lang": "ENG", "iso:country": "US", "meta:provider": ["geoplanet:7.3.1", "geoplanet:7.3.2", "geoplanet:7.4.0", "geoplanet:7.4.1", "geoplanet:7.5.1", "geoplanet:7.5.2", "geoplanet:7.6.0", "geoplanet:7.8.1", "geoplanet:7.9.0", "geoplanet:7.10.0", "geoplanet:8.0.0", "woeplanet:8.0.0"], "meta:indexed": "2020-08-20T20:18:18.432536", "woe:alias_ENG_V": ["Phoenix Christian Junior Senior High", "Phoenix Christian Junior High School", "Phoenix Christian Junior High", "Phoenix Christian Junior Senior HS", "Phoenix Christian Junior HS"], "meta:updated": "2020-08-22T02:58:45.937379", "woe:hierarchy": {"continent": 24865672, "country": 23424977, "town": 0, "planet": 1, "county": 12587587, "suburb": 0, "state": 2347561, "region": 0, "localadmin": 0}, "woe:timezone_id": 56043666, "woe:hash": "9tbq91tdhmwr", "woe:centroid": [-112.096748, 33.494942], "geom:latitude": 33.494942, "geom:longitude": -112.096748, "geom:hash": "9tbq91tdhmwr", "woe:latitude": 33.494942, "geom:centroid": [-112.096748, 33.494942], "woe:longitude": -112.096748, "woe:repo": "woeplanet-poi-us"}, "geometry": {"coordinates": [-112.096748, 33.494942], "type": "Point"}}