{"type": "Feature", "id": 23613368, "geometry": {"type": "Point", "coordinates": [-78.472969, 42.517578]}, "properties": {"woe:id": 23613368, "woe:parent_id": 2524896, "woe:name": "Central Baptist Christian School", "woe:placetype": 20, "woe:placetype_name": "POI", "woe:lang": "ENG", "iso:country": "US", "meta:provider": ["geoplanet:7.3.1", "geoplanet:7.3.2", "geoplanet:7.4.0", "geoplanet:7.4.1", "geoplanet:7.5.1", "geoplanet:7.5.2", "geoplanet:7.6.0", "geoplanet:7.8.1", "geoplanet:7.9.0", "geoplanet:7.10.0", "geoplanet:8.0.0", "woeplanet:8.0.0"], "meta:indexed": "2020-08-20T20:18:48.810814", "meta:updated": "2020-10-14T11:19:29.829628", "woe:hierarchy": {"continent": 24865672, "country": 23424977, "town": 0, "planet": 1, "county": 12589316, "suburb": 0, "state": 2347591, "region": 0, "localadmin": 0}, "woe:timezone_id": 56043648, "woe:hash": "dr81yk1dz6cr", "woe:centroid": [-78.472969, 42.517578], "geom:latitude": 42.517578, "geom:longitude": -78.472969, "geom:hash": "dr81yk1dz6cr", "woe:latitude": 42.517578, "geom:centroid": [-78.472969, 42.517578], "woe:longitude": -78.472969, "woe:repo": "woeplanet-poi-us", "geom:area": 0.0, "woe:scale": 19}}