{"type": "Feature", "id": 23657163, "properties": {"woe:id": 23657163, "woe:parent_id": 28340483, "woe:name": "Quitman High School", "woe:placetype": 20, "woe:placetype_name": "POI", "woe:lang": "ENG", "iso:country": "US", "meta:provider": ["geoplanet:7.3.1", "geoplanet:7.3.2", "geoplanet:7.4.0", "geoplanet:7.4.1", "geoplanet:7.5.1", "geoplanet:7.5.2", "geoplanet:7.6.0", "geoplanet:7.8.1", "geoplanet:7.9.0", "geoplanet:7.10.0", "geoplanet:8.0.0", "woeplanet:8.0.0"], "meta:indexed": "2020-08-20T20:19:04.731090", "woe:alias_ENG_V": ["Quitman Senior High School", "Quitman High", "Quitman Senior High", "Quitman HS", "Quitman Senior HS"], "meta:updated": "2020-08-22T02:58:49.941169", "woe:hierarchy": {"continent": 24865672, "country": 23424977, "town": 0, "planet": 1, "county": 12590256, "suburb": 0, "state": 2347602, "region": 0, "localadmin": 0}, "woe:timezone_id": 56043661, "woe:hash": "9vu4s6636ps4", "woe:centroid": [-95.435051, 32.795818], "geom:latitude": 32.795818, "geom:longitude": -95.435051, "geom:hash": "9vu4s6636ps4", "woe:latitude": 32.795818, "geom:centroid": [-95.435051, 32.795818], "woe:longitude": -95.435051, "woe:repo": "woeplanet-poi-us"}, "geometry": {"coordinates": [-95.435051, 32.795818], "type": "Point"}}