{"type": "Feature", "id": 23645342, "geometry": {"type": "Point", "coordinates": [-79.703644, 40.3372]}, "properties": {"woe:id": 23645342, "woe:parent_id": 26342964, "woe:name": "Shaw Elementary School", "woe:placetype": 20, "woe:placetype_name": "POI", "woe:lang": "ENG", "iso:country": "US", "meta:provider": ["geoplanet:7.3.1", "geoplanet:7.3.2", "geoplanet:7.4.0", "geoplanet:7.4.1", "geoplanet:7.5.1", "geoplanet:7.5.2", "geoplanet:7.6.0", "geoplanet:7.8.1", "geoplanet:7.9.0", "geoplanet:7.10.0", "geoplanet:8.0.0", "woeplanet:8.0.0"], "meta:indexed": "2020-08-20T20:19:00.146815", "woe:alias_ENG_V": ["Shaw Elementary"], "meta:updated": "2020-10-14T11:19:44.431684", "woe:hierarchy": {"continent": 24865672, "country": 23424977, "town": 0, "planet": 1, "county": 12589792, "suburb": 0, "state": 2347597, "region": 0, "localadmin": 0}, "woe:timezone_id": 56043648, "woe:hash": "dppm6r1t4rp6", "woe:centroid": [-79.703644, 40.3372], "geom:latitude": 40.3372, "geom:longitude": -79.703644, "geom:hash": "dppm6r1t4rp6", "woe:latitude": 40.3372, "geom:centroid": [-79.703644, 40.3372], "woe:longitude": -79.703644, "woe:repo": "woeplanet-poi-us", "geom:area": 0.0, "woe:scale": 19}}