{"type": "Feature", "id": 56203813, "geometry": {"type": "Point", "coordinates": [-122.483673, 37.757648]}, "properties": {"woe:id": 56203813, "woe:parent_id": 2502443, "woe:name": "Cornerstone Academy-k Annex", "woe:placetype": 20, "woe:placetype_name": "POI", "woe:lang": "ENG", "iso:country": "US", "meta:provider": ["geoplanet:7.6.0", "geoplanet:7.8.1", "geoplanet:7.9.0", "geoplanet:7.10.0", "geoplanet:8.0.0", "woeplanet:8.0.0"], "meta:indexed": "2020-08-21T08:24:23.535622", "meta:updated": "2020-10-14T11:19:58.724427", "woe:hierarchy": {"continent": 24865672, "country": 23424977, "town": 0, "planet": 1, "county": 12587707, "suburb": 0, "state": 2347563, "region": 0, "localadmin": 0}, "woe:timezone_id": 56043663, "woe:hash": "9q8yucd45x9z", "woe:centroid": [-122.483673, 37.757648], "geom:latitude": 37.757648, "geom:longitude": -122.483673, "geom:hash": "9q8yucd45x9z", "woe:latitude": 37.757648, "geom:centroid": [-122.483673, 37.757648], "woe:longitude": -122.483673, "woe:repo": "woeplanet-poi-us", "geom:area": 0.0, "woe:scale": 19}}