{"type": "Feature", "id": 23651444, "geometry": {"type": "Point", "coordinates": [-86.489632, 36.008492]}, "properties": {"woe:id": 23651444, "woe:parent_id": 2495232, "woe:name": "Colemon Elementary School", "woe:placetype": 20, "woe:placetype_name": "POI", "woe:lang": "ENG", "iso:country": "US", "meta:provider": ["geoplanet:7.3.1", "geoplanet:7.3.2", "geoplanet:7.4.0", "geoplanet:7.4.1", "geoplanet:7.5.1", "geoplanet:7.5.2", "geoplanet:7.6.0", "geoplanet:7.8.1", "geoplanet:7.9.0", "geoplanet:7.10.0", "geoplanet:8.0.0", "woeplanet:8.0.0"], "meta:indexed": "2020-08-20T20:19:02.073056", "woe:alias_ENG_V": ["Colemon Elementary"], "meta:updated": "2020-10-14T11:19:42.397225", "woe:hierarchy": {"continent": 24865672, "country": 23424977, "town": 0, "planet": 1, "county": 12589986, "suburb": 0, "state": 2347601, "region": 0, "localadmin": 0}, "woe:timezone_id": 56043661, "woe:hash": "dn6kzghhtt2j", "woe:centroid": [-86.489632, 36.008492], "geom:latitude": 36.008492, "geom:longitude": -86.489632, "geom:hash": "dn6kzghhtt2j", "woe:latitude": 36.008492, "geom:centroid": [-86.489632, 36.008492], "woe:longitude": -86.489632, "woe:repo": "woeplanet-poi-us", "geom:area": 0.0, "woe:scale": 19}}