{"type": "Feature", "id": 23575912, "properties": {"woe:id": 23575912, "woe:parent_id": 2493346, "woe:name": "Sicily Island Elementary School", "woe:placetype": 20, "woe:placetype_name": "POI", "woe:lang": "ENG", "iso:country": "US", "meta:provider": ["geoplanet:7.3.1", "geoplanet:7.3.2", "geoplanet:7.4.0", "geoplanet:7.4.1", "geoplanet:7.5.1", "geoplanet:7.5.2", "geoplanet:7.6.0", "geoplanet:7.8.1", "geoplanet:7.9.0", "geoplanet:7.10.0", "geoplanet:8.0.0", "woeplanet:8.0.0"], "meta:indexed": "2020-08-20T20:18:37.343441", "woe:alias_ENG_V": ["Sicily Island Elementary"], "meta:updated": "2020-08-22T02:57:37.164116", "woe:hierarchy": {"continent": 24865672, "country": 23424977, "town": 0, "planet": 1, "county": 12588608, "suburb": 0, "state": 2347577, "region": 0, "localadmin": 0}, "woe:timezone_id": 56043661, "woe:hash": "9vwv4m1br69e", "woe:centroid": [-91.656219, 31.843929], "geom:latitude": 31.843929, "geom:longitude": -91.656219, "geom:hash": "9vwv4m1br69e", "woe:latitude": 31.843929, "geom:centroid": [-91.656219, 31.843929], "woe:longitude": -91.656219, "woe:repo": "woeplanet-poi-us"}, "geometry": {"coordinates": [-91.656219, 31.843929], "type": "Point"}}