{"type": "Feature", "id": 23514182, "geometry": {"type": "Point", "coordinates": [-86.3032, 32.36422]}, "properties": {"woe:id": 23514182, "woe:parent_id": 2382016, "woe:name": "Montessori Academy", "woe:placetype": 20, "woe:placetype_name": "POI", "woe:lang": "ENG", "iso:country": "US", "meta:provider": ["geoplanet:7.3.2", "geoplanet:7.4.0", "geoplanet:7.4.1", "geoplanet:7.5.1", "geoplanet:7.5.2", "geoplanet:7.6.0", "geoplanet:7.8.1", "geoplanet:7.9.0", "geoplanet:7.10.0", "geoplanet:8.0.0", "woeplanet:8.0.0"], "meta:indexed": "2020-08-20T22:01:55.674383", "meta:updated": "2020-10-14T11:20:26.177132", "woe:hierarchy": {"continent": 24865672, "country": 23424977, "town": 0, "planet": 1, "county": 12587537, "suburb": 0, "state": 2347559, "region": 0, "localadmin": 0}, "woe:timezone_id": 56043661, "woe:hash": "djf8h5ezjxvu", "woe:centroid": [-86.3032, 32.36422], "geom:latitude": 32.36422, "geom:longitude": -86.3032, "geom:hash": "djf8h5ezjxvu", "woe:latitude": 32.36422, "geom:centroid": [-86.3032, 32.36422], "woe:longitude": -86.3032, "woe:repo": "woeplanet-poi-us", "geom:area": 0.0, "woe:scale": 19}}