{"type": "Feature", "id": 23559541, "geometry": {"type": "Point", "coordinates": [-87.688988, 41.708092]}, "properties": {"woe:id": 23559541, "woe:parent_id": 28297342, "woe:name": "St John Fisher Elementary School", "woe:placetype": 20, "woe:placetype_name": "POI", "woe:lang": "ENG", "iso:country": "US", "meta:provider": ["geoplanet:7.3.1", "geoplanet:7.3.2", "geoplanet:7.4.0", "geoplanet:7.4.1", "geoplanet:7.5.1", "geoplanet:7.5.2", "geoplanet:7.6.0", "geoplanet:7.8.1", "geoplanet:7.9.0", "geoplanet:7.10.0", "geoplanet:8.0.0", "woeplanet:8.0.0"], "meta:indexed": "2020-08-20T20:18:31.559011", "woe:alias_ENG_V": ["St John Fisher Elementary"], "meta:updated": "2020-10-14T11:20:26.067963", "woe:hierarchy": {"continent": 24865672, "country": 23424977, "town": 0, "planet": 1, "county": 12588093, "suburb": 0, "state": 2347572, "region": 0, "localadmin": 0}, "woe:timezone_id": 56043661, "woe:hash": "dp3tk8dz4rz7", "woe:centroid": [-87.688988, 41.708092], "geom:latitude": 41.708092, "geom:longitude": -87.688988, "geom:hash": "dp3tk8dz4rz7", "woe:latitude": 41.708092, "geom:centroid": [-87.688988, 41.708092], "woe:longitude": -87.688988, "woe:repo": "woeplanet-poi-us", "geom:area": 0.0, "woe:scale": 19}}