{"type": "Feature", "id": 23574559, "properties": {"woe:id": 23574559, "woe:parent_id": 2441858, "woe:name": "Covington Catholic High School", "woe:placetype": 20, "woe:placetype_name": "POI", "woe:lang": "ENG", "iso:country": "US", "meta:provider": ["geoplanet:7.3.1", "geoplanet:7.3.2", "geoplanet:7.4.0", "geoplanet:7.4.1", "geoplanet:7.5.1", "geoplanet:7.5.2", "geoplanet:7.6.0", "geoplanet:7.8.1", "geoplanet:7.9.0", "geoplanet:7.10.0", "geoplanet:8.0.0", "woeplanet:8.0.0"], "meta:indexed": "2020-08-20T20:18:36.993072", "woe:alias_ENG_V": ["Covington Catholic Senior High School", "Covington Catholic High", "Covington Catholic Senior High", "Covington Catholic HS", "Covington Catholic Senior HS"], "meta:updated": "2020-08-22T02:58:47.557149", "woe:hierarchy": {"continent": 24865672, "country": 23424977, "town": 0, "planet": 1, "county": 12588534, "suburb": 0, "state": 2347576, "region": 0, "localadmin": 0}, "woe:timezone_id": 56043647, "woe:hash": "dngyhr77r3zh", "woe:centroid": [-84.535011, 39.063831], "geom:latitude": 39.063831, "geom:longitude": -84.535011, "geom:hash": "dngyhr77r3zh", "woe:latitude": 39.063831, "geom:centroid": [-84.535011, 39.063831], "woe:longitude": -84.535011, "woe:repo": "woeplanet-poi-us"}, "geometry": {"coordinates": [-84.535011, 39.063831], "type": "Point"}}