{"type": "Feature", "id": 23648018, "properties": {"woe:id": 23648018, "woe:parent_id": 2497370, "woe:name": "Pine Street Elementary School", "woe:placetype": 20, "woe:placetype_name": "POI", "woe:lang": "ENG", "iso:country": "US", "meta:provider": ["geoplanet:7.3.1", "geoplanet:7.3.2", "geoplanet:7.4.0", "geoplanet:7.4.1", "geoplanet:7.5.1", "geoplanet:7.5.2", "geoplanet:7.6.0", "geoplanet:7.8.1", "geoplanet:7.9.0", "geoplanet:7.10.0", "geoplanet:8.0.0", "woeplanet:8.0.0"], "meta:indexed": "2020-08-20T20:19:00.977133", "woe:alias_ENG_V": ["Pine Street Elementary"], "meta:updated": "2020-08-22T02:57:47.837964", "woe:hierarchy": {"continent": 24865672, "country": 23424977, "town": 0, "planet": 1, "county": 12589841, "suburb": 0, "state": 2347599, "region": 0, "localadmin": 0}, "woe:timezone_id": 56043648, "woe:hash": "dnjyb13723gh", "woe:centroid": [-81.912331, 34.943958], "geom:latitude": 34.943958, "geom:longitude": -81.912331, "geom:hash": "dnjyb13723gh", "woe:latitude": 34.943958, "geom:centroid": [-81.912331, 34.943958], "woe:longitude": -81.912331, "woe:repo": "woeplanet-poi-us"}, "geometry": {"coordinates": [-81.912331, 34.943958], "type": "Point"}}