{"type": "Feature", "id": 23608695, "properties": {"woe:id": 23608695, "woe:parent_id": 2460673, "woe:name": "Hcst-north Hudson Center", "woe:placetype": 20, "woe:placetype_name": "POI", "woe:lang": "ENG", "iso:country": "US", "meta:provider": ["geoplanet:7.4.0", "geoplanet:7.4.1", "geoplanet:7.5.1", "geoplanet:7.5.2", "geoplanet:7.6.0", "geoplanet:7.8.1", "geoplanet:7.9.0", "geoplanet:7.10.0", "geoplanet:8.0.0", "woeplanet:8.0.0"], "meta:indexed": "2020-08-20T23:55:18.779020", "meta:updated": "2020-08-22T02:57:42.129810", "woe:hierarchy": {"continent": 24865672, "country": 23424977, "town": 0, "planet": 1, "county": 12589266, "suburb": 0, "state": 2347589, "region": 0, "localadmin": 0}, "woe:timezone_id": 56043648, "woe:hash": "dr725v0ktx2h", "woe:centroid": [-74.014313, 40.809528], "geom:latitude": 40.809528, "geom:longitude": -74.014313, "geom:hash": "dr725v0ktx2h", "woe:latitude": 40.809528, "geom:centroid": [-74.014313, 40.809528], "woe:longitude": -74.014313, "woe:repo": "woeplanet-poi-us"}, "geometry": {"coordinates": [-74.014313, 40.809528], "type": "Point"}}