{"type": "Feature", "id": 23518200, "properties": {"woe:id": 23518200, "woe:parent_id": 2453456, "woe:name": "Monticello High School", "woe:placetype": 20, "woe:placetype_name": "POI", "woe:lang": "ENG", "iso:country": "US", "meta:provider": ["geoplanet:7.3.1", "geoplanet:7.3.2", "geoplanet:7.4.0", "geoplanet:7.4.1", "geoplanet:7.5.1", "geoplanet:7.5.2", "geoplanet:7.6.0", "geoplanet:7.8.1", "geoplanet:7.9.0", "geoplanet:7.10.0", "geoplanet:8.0.0", "woeplanet:8.0.0"], "meta:indexed": "2020-08-20T20:18:18.990025", "woe:alias_ENG_V": ["Monticello Senior High School", "Monticello High", "Monticello Senior High", "Monticello HS", "Monticello Senior HS"], "meta:updated": "2020-08-22T02:58:45.971507", "woe:hierarchy": {"continent": 24865672, "country": 23424977, "town": 0, "planet": 1, "county": 12587616, "suburb": 0, "state": 2347562, "region": 0, "localadmin": 0}, "woe:timezone_id": 56043661, "woe:hash": "9vyxnz0t05t8", "woe:centroid": [-91.81205, 33.613548], "geom:latitude": 33.613548, "geom:longitude": -91.81205, "geom:hash": "9vyxnz0t05t8", "woe:latitude": 33.613548, "geom:centroid": [-91.81205, 33.613548], "woe:longitude": -91.81205, "woe:repo": "woeplanet-poi-us"}, "geometry": {"coordinates": [-91.81205, 33.613548], "type": "Point"}}