{"type": "Feature", "id": 24866757, "properties": {"woe:id": 24866757, "woe:parent_id": 2473601, "woe:name": "University of Wisconsin Platteville", "woe:placetype": 20, "woe:placetype_name": "POI", "woe:lang": "ENG", "iso:country": "US", "meta:provider": ["geoplanet:7.3.1", "geoplanet:7.3.2", "geoplanet:7.4.0", "geoplanet:7.4.1", "geoplanet:7.5.1", "geoplanet:7.5.2", "geoplanet:7.6.0", "geoplanet:7.8.1", "geoplanet:7.9.0", "geoplanet:7.10.0", "geoplanet:8.0.0", "woeplanet:8.0.0"], "meta:indexed": "2020-08-20T20:19:16.155354", "woe:alias_ENG_V": ["University of Wisconsin-Platteville", "University of Wisconsin, Platteville"], "meta:updated": "2020-08-22T02:58:20.319207", "woe:hierarchy": {"continent": 24865672, "country": 23424977, "town": 0, "planet": 1, "county": 12590555, "suburb": 0, "state": 2347608, "region": 0, "localadmin": 0}, "woe:timezone_id": 56043661, "woe:hash": "9zxej5kqzfft", "woe:centroid": [-90.477226, 42.733871], "geom:latitude": 42.733871, "geom:longitude": -90.477226, "geom:hash": "9zxej5kqzfft", "woe:latitude": 42.733871, "geom:centroid": [-90.477226, 42.733871], "woe:longitude": -90.477226, "woe:repo": "woeplanet-poi-us"}, "geometry": {"coordinates": [-90.477226, 42.733871], "type": "Point"}}