{"type": "Feature", "id": 23548848, "geometry": {"type": "Point", "coordinates": [-82.440887, 27.97435]}, "properties": {"woe:id": 23548848, "woe:parent_id": 2396228, "woe:name": "Orange Grove Middle School", "woe:placetype": 20, "woe:placetype_name": "POI", "woe:lang": "ENG", "iso:country": "US", "meta:provider": ["geoplanet:7.3.1", "geoplanet:7.3.2", "geoplanet:7.4.0", "geoplanet:7.4.1", "geoplanet:7.5.1", "geoplanet:7.5.2", "geoplanet:7.6.0", "geoplanet:7.8.1", "geoplanet:7.9.0", "geoplanet:7.10.0", "geoplanet:8.0.0", "woeplanet:8.0.0"], "meta:indexed": "2020-08-20T20:18:27.593940", "meta:updated": "2020-10-14T11:20:20.159333", "woe:alias_ENG_V": ["Orange Grove Middle Magnet School"], "woe:hierarchy": {"continent": 24865672, "country": 23424977, "town": 0, "planet": 1, "county": 12587831, "suburb": 0, "state": 2347568, "region": 0, "localadmin": 0}, "woe:timezone_id": 56043648, "woe:hash": "dhvrhh86khg1", "woe:centroid": [-82.440887, 27.97435], "geom:latitude": 27.97435, "geom:longitude": -82.440887, "geom:hash": "dhvrhh86khg1", "woe:latitude": 27.97435, "geom:centroid": [-82.440887, 27.97435], "woe:longitude": -82.440887, "woe:repo": "woeplanet-poi-us", "geom:area": 0.0, "woe:scale": 19}}