{"type": "Feature", "id": 23588439, "geometry": {"type": "Point", "coordinates": [-85.971184, 44.914181]}, "properties": {"woe:id": 23588439, "woe:parent_id": 2437861, "woe:name": "The Leelanau School", "woe:placetype": 20, "woe:placetype_name": "POI", "woe:lang": "ENG", "iso:country": "US", "meta:provider": ["geoplanet:7.3.2", "geoplanet:7.4.0", "geoplanet:7.4.1", "geoplanet:7.5.1", "geoplanet:7.5.2", "geoplanet:7.6.0", "geoplanet:7.8.1", "geoplanet:7.9.0", "geoplanet:7.10.0", "geoplanet:8.0.0", "woeplanet:8.0.0"], "meta:indexed": "2020-08-20T22:02:25.888690", "meta:updated": "2020-10-14T11:20:12.496675", "woe:hierarchy": {"continent": 24865672, "country": 23424977, "town": 0, "planet": 1, "county": 12588758, "suburb": 0, "state": 2347581, "region": 0, "localadmin": 0}, "woe:timezone_id": 56043658, "woe:hash": "dpfze8msn4nv", "woe:centroid": [-85.971184, 44.914181], "geom:latitude": 44.914181, "geom:longitude": -85.971184, "geom:hash": "dpfze8msn4nv", "woe:latitude": 44.914181, "geom:centroid": [-85.971184, 44.914181], "woe:longitude": -85.971184, "woe:repo": "woeplanet-poi-us", "geom:area": 0.0, "woe:scale": 19}}