{"type": "Feature", "id": 23668520, "geometry": {"type": "Point", "coordinates": [-119.20639, 46.254169]}, "properties": {"woe:id": 23668520, "woe:parent_id": 23418241, "woe:name": "Mcloughlin Middle School", "woe:placetype": 20, "woe:placetype_name": "POI", "woe:lang": "ENG", "iso:country": "US", "meta:provider": ["geoplanet:7.3.1", "geoplanet:7.3.2", "geoplanet:7.4.0", "geoplanet:7.4.1", "geoplanet:7.5.1", "geoplanet:7.5.2", "geoplanet:7.6.0", "geoplanet:7.8.1", "geoplanet:7.9.0", "geoplanet:7.10.0", "geoplanet:8.0.0", "woeplanet:8.0.0"], "meta:indexed": "2020-08-20T20:19:09.136584", "meta:updated": "2020-10-14T11:19:37.495069", "woe:alias_ENG_V": ["Mclaughlin Middle School"], "woe:hierarchy": {"continent": 24865672, "country": 23424977, "town": 0, "planet": 1, "county": 12590450, "suburb": 0, "state": 2347606, "region": 0, "localadmin": 0}, "woe:timezone_id": 56043663, "woe:hash": "c25ppkkd1f11", "woe:centroid": [-119.20639, 46.254169], "geom:latitude": 46.254169, "geom:longitude": -119.20639, "geom:hash": "c25ppkkd1f11", "woe:latitude": 46.254169, "geom:centroid": [-119.20639, 46.254169], "woe:longitude": -119.20639, "woe:repo": "woeplanet-poi-us", "geom:area": 0.0, "woe:scale": 19}}