{"type": "Feature", "id": 23526339, "geometry": {"type": "Point", "coordinates": [-122.15757, 37.437981]}, "properties": {"woe:id": 23526339, "woe:parent_id": 55860945, "woe:name": "Palo Alto High School", "woe:placetype": 20, "woe:placetype_name": "POI", "woe:lang": "ENG", "iso:country": "US", "meta:provider": ["geoplanet:7.3.2", "geoplanet:7.4.0", "geoplanet:7.4.1", "geoplanet:7.5.1", "geoplanet:7.5.2", "geoplanet:7.6.0", "geoplanet:7.8.1", "geoplanet:7.9.0", "geoplanet:7.10.0", "geoplanet:8.0.0", "woeplanet:8.0.0"], "meta:indexed": "2020-08-20T22:02:00.320105", "woe:alias_ENG_V": ["Palo Alto Senior High School", "Palo Alto High", "Palo Alto Senior High", "Palo Alto HS", "Palo Alto Senior HS", "Paly"], "meta:updated": "2020-10-14T11:20:20.818862", "woe:hierarchy": {"continent": 24865672, "country": 23424977, "town": 0, "planet": 1, "county": 12587712, "suburb": 0, "state": 2347563, "region": 0, "localadmin": 0}, "woe:timezone_id": 56043663, "woe:hash": "9q9huprs433z", "woe:centroid": [-122.15757, 37.437981], "geom:latitude": 37.437981, "geom:longitude": -122.15757, "geom:hash": "9q9huprs433z", "woe:latitude": 37.437981, "geom:centroid": [-122.15757, 37.437981], "woe:longitude": -122.15757, "woe:repo": "woeplanet-poi-us", "geom:area": 0.0, "woe:scale": 19}}