{"type": "Feature", "id": 23620767, "geometry": {"type": "Point", "coordinates": [-72.369461, 41.100128]}, "properties": {"woe:id": 23620767, "woe:parent_id": 2414425, "woe:name": "Greenport Elementary School", "woe:placetype": 20, "woe:placetype_name": "POI", "woe:lang": "ENG", "iso:country": "US", "meta:provider": ["geoplanet:7.3.1", "geoplanet:7.3.2", "geoplanet:7.4.0", "geoplanet:7.4.1", "geoplanet:7.5.1", "geoplanet:7.5.2", "geoplanet:7.6.0", "geoplanet:7.8.1", "geoplanet:7.9.0", "geoplanet:7.10.0", "geoplanet:8.0.0", "woeplanet:8.0.0"], "meta:indexed": "2020-08-20T20:18:51.718766", "woe:alias_ENG_V": ["Greenport Elementary"], "meta:updated": "2020-10-14T11:19:28.599926", "woe:hierarchy": {"continent": 24865672, "country": 23424977, "town": 0, "planet": 1, "county": 12589363, "suburb": 0, "state": 2347591, "region": 0, "localadmin": 0}, "woe:timezone_id": 56043648, "woe:hash": "drk9c4n1t74t", "woe:centroid": [-72.369461, 41.100128], "geom:latitude": 41.100128, "geom:longitude": -72.369461, "geom:hash": "drk9c4n1t74t", "woe:latitude": 41.100128, "geom:centroid": [-72.369461, 41.100128], "woe:longitude": -72.369461, "woe:repo": "woeplanet-poi-us", "geom:area": 0.0, "woe:scale": 19}}