{"type": "Feature", "id": 56063888, "properties": {"woe:id": 56063888, "woe:parent_id": 28751490, "woe:name": "Fannin South Station", "woe:placetype": 20, "woe:placetype_name": "POI", "woe:lang": "ENG", "iso:country": "US", "meta:provider": ["geoplanet:7.3.1", "geoplanet:7.3.2", "geoplanet:7.4.0", "geoplanet:7.4.1", "geoplanet:7.5.1", "geoplanet:7.5.2", "geoplanet:7.6.0", "geoplanet:7.8.1", "geoplanet:7.9.0", "geoplanet:7.10.0", "geoplanet:8.0.0", "woeplanet:8.0.0"], "meta:indexed": "2020-08-20T20:19:20.845336", "woe:alias_ENG_V": ["Fannin South Metrorail Station", "Metrorail Fannin South Station", "Metrorail-Fannin South"], "meta:updated": "2020-08-22T02:58:23.008771", "woe:hierarchy": {"continent": 24865672, "country": 23424977, "town": 0, "planet": 1, "county": 12590107, "suburb": 0, "state": 2347602, "region": 0, "localadmin": 0}, "woe:timezone_id": 56043661, "woe:hash": "9vk0v4181v35", "woe:centroid": [-95.403137, 29.674101], "geom:latitude": 29.674101, "geom:longitude": -95.403137, "geom:hash": "9vk0v4181v35", "woe:latitude": 29.674101, "geom:centroid": [-95.403137, 29.674101], "woe:longitude": -95.403137, "woe:repo": "woeplanet-poi-us"}, "geometry": {"coordinates": [-95.403137, 29.674101], "type": "Point"}}