{"type": "Feature", "id": 23544251, "properties": {"woe:id": 23544251, "woe:parent_id": 2415223, "woe:name": "University of Connecticut Southeastern Branch", "woe:placetype": 20, "woe:placetype_name": "POI", "woe:lang": "ENG", "iso:country": "US", "meta:provider": ["geoplanet:7.4.0", "geoplanet:7.4.1", "geoplanet:7.5.1", "geoplanet:7.5.2", "geoplanet:7.6.0", "geoplanet:7.8.1", "geoplanet:7.9.0", "geoplanet:7.10.0", "geoplanet:8.0.0", "woeplanet:8.0.0"], "meta:indexed": "2020-08-20T23:54:50.556612", "meta:updated": "2020-08-22T02:57:31.279540", "woe:hierarchy": {"continent": 24865672, "country": 23424977, "town": 0, "planet": 1, "county": 12587796, "suburb": 0, "state": 2347565, "region": 0, "localadmin": 0}, "woe:timezone_id": 56043648, "woe:hash": "drkg01sstf7t", "woe:centroid": [-72.063881, 41.317619], "geom:latitude": 41.317619, "geom:longitude": -72.063881, "geom:hash": "drkg01sstf7t", "woe:latitude": 41.317619, "geom:centroid": [-72.063881, 41.317619], "woe:longitude": -72.063881, "woe:repo": "woeplanet-poi-us"}, "geometry": {"coordinates": [-72.063881, 41.317619], "type": "Point"}}