{"type": "Feature", "id": 23597814, "properties": {"woe:id": 23597814, "woe:parent_id": 55861991, "woe:name": "Spfd James River Postal Stor Station", "woe:placetype": 20, "woe:placetype_name": "POI", "woe:lang": "ENG", "iso:country": "US", "meta:provider": ["geoplanet:7.3.1", "geoplanet:7.3.2", "geoplanet:7.4.0", "geoplanet:7.4.1", "geoplanet:7.5.1", "geoplanet:7.5.2", "geoplanet:7.6.0", "geoplanet:7.8.1", "geoplanet:7.9.0", "geoplanet:7.10.0", "geoplanet:8.0.0", "woeplanet:8.0.0"], "meta:indexed": "2020-08-20T20:18:44.024616", "meta:updated": "2020-08-22T02:57:40.686549", "woe:hierarchy": {"continent": 24865672, "country": 23424977, "town": 0, "planet": 1, "county": 12589004, "suburb": 0, "state": 2347584, "region": 0, "localadmin": 0}, "woe:timezone_id": 56043661, "woe:hash": "9ytemc2zu2yn", "woe:centroid": [-93.261719, 37.141991], "geom:latitude": 37.141991, "geom:longitude": -93.261719, "geom:hash": "9ytemc2zu2yn", "woe:latitude": 37.141991, "geom:centroid": [-93.261719, 37.141991], "woe:longitude": -93.261719, "woe:repo": "woeplanet-poi-us"}, "geometry": {"coordinates": [-93.261719, 37.141991], "type": "Point"}}