{"type": "Feature", "id": 23666631, "geometry": {"type": "Point", "coordinates": [-81.815361, 36.775478]}, "properties": {"woe:id": 23666631, "woe:parent_id": 2399496, "woe:name": "Patrick Henry High School", "woe:placetype": 20, "woe:placetype_name": "POI", "woe:lang": "ENG", "iso:country": "US", "meta:provider": ["geoplanet:7.3.2", "geoplanet:7.4.0", "geoplanet:7.4.1", "geoplanet:7.5.1", "geoplanet:7.5.2", "geoplanet:7.6.0", "geoplanet:7.8.1", "geoplanet:7.9.0", "geoplanet:7.10.0", "geoplanet:8.0.0", "woeplanet:8.0.0"], "meta:indexed": "2020-08-20T22:02:58.686080", "woe:alias_ENG_V": ["Patrick Henry Senior High School", "Patrick Henry High", "Patrick Henry Senior High", "Patrick Henry HS", "Patrick Henry Senior HS"], "meta:updated": "2020-10-14T11:19:45.476913", "woe:hierarchy": {"continent": 24865672, "country": 23424977, "town": 0, "planet": 1, "county": 12590432, "suburb": 0, "state": 2347605, "region": 0, "localadmin": 0}, "woe:timezone_id": 56043648, "woe:hash": "dntc4nzbevvp", "woe:centroid": [-81.815361, 36.775478], "geom:latitude": 36.775478, "geom:longitude": -81.815361, "geom:hash": "dntc4nzbevvp", "woe:latitude": 36.775478, "geom:centroid": [-81.815361, 36.775478], "woe:longitude": -81.815361, "woe:repo": "woeplanet-poi-us", "geom:area": 0.0, "woe:scale": 19}}