{"type": "Feature", "id": 23597775, "geometry": {"type": "Point", "coordinates": [-93.319633, 37.21912]}, "properties": {"woe:id": 23597775, "woe:parent_id": 55861976, "woe:name": "York Elementary School", "woe:placetype": 20, "woe:placetype_name": "POI", "woe:lang": "ENG", "iso:country": "US", "meta:provider": ["geoplanet:7.3.1", "geoplanet:7.3.2", "geoplanet:7.4.0", "geoplanet:7.4.1", "geoplanet:7.5.1", "geoplanet:7.5.2", "geoplanet:7.6.0", "geoplanet:7.8.1", "geoplanet:7.9.0", "geoplanet:7.10.0", "geoplanet:8.0.0", "woeplanet:8.0.0"], "meta:indexed": "2020-08-20T20:18:44.009275", "woe:alias_ENG_V": ["York Elementary"], "meta:updated": "2020-10-14T11:20:11.864655", "woe:hierarchy": {"continent": 24865672, "country": 23424977, "town": 0, "planet": 1, "county": 12589004, "suburb": 0, "state": 2347584, "region": 0, "localadmin": 0}, "woe:timezone_id": 56043661, "woe:hash": "9ytesrw9nfy4", "woe:centroid": [-93.319633, 37.21912], "geom:latitude": 37.21912, "geom:longitude": -93.319633, "geom:hash": "9ytesrw9nfy4", "woe:latitude": 37.21912, "geom:centroid": [-93.319633, 37.21912], "woe:longitude": -93.319633, "woe:repo": "woeplanet-poi-us", "geom:area": 0.0, "woe:scale": 19}}