{"type": "Feature", "id": 23671542, "properties": {"woe:id": 23671542, "woe:parent_id": 2365151, "woe:name": "Blaine Middle School", "woe:placetype": 20, "woe:placetype_name": "POI", "woe:lang": "ENG", "iso:country": "US", "meta:provider": ["geoplanet:7.3.1", "geoplanet:7.3.2", "geoplanet:7.4.0", "geoplanet:7.4.1", "geoplanet:7.5.1", "geoplanet:7.5.2", "geoplanet:7.6.0", "geoplanet:7.8.1", "geoplanet:7.9.0", "geoplanet:7.10.0", "geoplanet:8.0.0", "woeplanet:8.0.0"], "meta:indexed": "2020-08-20T20:19:09.908853", "meta:updated": "2020-08-22T02:57:52.298172", "woe:hierarchy": {"continent": 24865672, "country": 23424977, "town": 0, "planet": 1, "county": 12590476, "suburb": 0, "state": 2347606, "region": 0, "localadmin": 0}, "woe:timezone_id": 56043663, "woe:hash": "c28wwyymvv5y", "woe:centroid": [-122.741409, 48.993172], "geom:latitude": 48.993172, "geom:longitude": -122.741409, "geom:hash": "c28wwyymvv5y", "woe:latitude": 48.993172, "geom:centroid": [-122.741409, 48.993172], "woe:longitude": -122.741409, "woe:repo": "woeplanet-poi-us"}, "geometry": {"coordinates": [-122.741409, 48.993172], "type": "Point"}}