{"type": "Feature", "id": 23685065, "properties": {"woe:id": 23685065, "woe:parent_id": 2407402, "woe:name": "Fremont Mall", "woe:placetype": 20, "woe:placetype_name": "POI", "woe:lang": "ENG", "iso:country": "US", "meta:provider": ["geoplanet:7.3.1", "geoplanet:7.3.2", "geoplanet:7.4.0", "geoplanet:7.4.1", "geoplanet:7.5.1", "geoplanet:7.5.2", "geoplanet:7.6.0", "geoplanet:7.8.1", "geoplanet:7.9.0", "geoplanet:7.10.0", "geoplanet:8.0.0", "woeplanet:8.0.0"], "meta:indexed": "2020-08-20T20:19:13.410876", "meta:updated": "2020-08-22T02:58:19.018688", "woe:hierarchy": {"continent": 24865672, "country": 23424977, "town": 0, "planet": 1, "county": 12589164, "suburb": 0, "state": 2347586, "region": 0, "localadmin": 0}, "woe:timezone_id": 56043661, "woe:hash": "9z77u3up99g6", "woe:centroid": [-96.487358, 41.45134], "geom:latitude": 41.45134, "geom:longitude": -96.487358, "geom:hash": "9z77u3up99g6", "woe:latitude": 41.45134, "geom:centroid": [-96.487358, 41.45134], "woe:longitude": -96.487358, "woe:repo": "woeplanet-poi-us"}, "geometry": {"coordinates": [-96.487358, 41.45134], "type": "Point"}}