{"type": "Feature", "id": 23623861, "properties": {"woe:id": 23623861, "woe:parent_id": 55989557, "woe:name": "Mount Pleasant Elementary School", "woe:placetype": 20, "woe:placetype_name": "POI", "woe:lang": "ENG", "iso:country": "US", "meta:provider": ["geoplanet:7.4.0", "geoplanet:7.4.1", "geoplanet:7.5.1", "geoplanet:7.5.2", "geoplanet:7.6.0", "geoplanet:7.8.1", "geoplanet:7.9.0", "geoplanet:7.10.0", "geoplanet:8.0.0", "woeplanet:8.0.0"], "meta:indexed": "2020-08-20T23:55:25.424004", "woe:alias_ENG_V": ["Mt Pleasant Elementary School", "Mt Pleasant Elementary", "Mount Pleasant Elementary"], "meta:updated": "2020-08-22T02:57:44.261828", "woe:hierarchy": {"continent": 24865672, "country": 23424977, "town": 0, "planet": 1, "county": 12589386, "suburb": 0, "state": 2347592, "region": 0, "localadmin": 0}, "woe:timezone_id": 56043648, "woe:hash": "dnqc3wvn7hn1", "woe:centroid": [-80.434891, 35.41415], "geom:latitude": 35.41415, "geom:longitude": -80.434891, "geom:hash": "dnqc3wvn7hn1", "woe:latitude": 35.41415, "geom:centroid": [-80.434891, 35.41415], "woe:longitude": -80.434891, "woe:repo": "woeplanet-poi-us"}, "geometry": {"coordinates": [-80.434891, 35.41415], "type": "Point"}}