{"type": "Feature", "id": 24609981, "properties": {"woe:id": 24609981, "woe:parent_id": 2377942, "woe:name": "Jillian's", "woe:placetype": 20, "woe:placetype_name": "POI", "woe:lang": "ENG", "iso:country": "US", "meta:provider": ["geoplanet:7.3.1", "geoplanet:7.3.2", "geoplanet:7.4.0", "geoplanet:7.4.1", "geoplanet:7.5.1", "geoplanet:7.5.2", "geoplanet:7.6.0", "geoplanet:7.8.1", "geoplanet:7.9.0", "geoplanet:7.10.0", "geoplanet:8.0.0", "woeplanet:8.0.0"], "meta:indexed": "2020-08-20T20:19:14.306222", "meta:updated": "2020-08-22T02:58:19.408027", "woe:hierarchy": {"continent": 24865672, "country": 23424977, "town": 0, "planet": 1, "county": 12588087, "suburb": 0, "state": 2347572, "region": 0, "localadmin": 0}, "woe:timezone_id": 56043661, "woe:hash": "dp1hpw317cm4", "woe:centroid": [-88.262619, 40.112679], "geom:latitude": 40.112679, "geom:longitude": -88.262619, "geom:hash": "dp1hpw317cm4", "woe:latitude": 40.112679, "geom:centroid": [-88.262619, 40.112679], "woe:longitude": -88.262619, "woe:repo": "woeplanet-poi-us"}, "geometry": {"coordinates": [-88.262619, 40.112679], "type": "Point"}}