{"type": "Feature", "id": 23647889, "geometry": {"type": "Point", "coordinates": [-80.920403, 33.954731]}, "properties": {"woe:id": 23647889, "woe:parent_id": 56022630, "woe:name": "Temple Baptist Church Kindergarten", "woe:placetype": 20, "woe:placetype_name": "POI", "woe:lang": "ENG", "iso:country": "US", "meta:provider": ["geoplanet:7.3.1", "geoplanet:7.3.2", "geoplanet:7.4.0", "geoplanet:7.4.1", "geoplanet:7.5.1", "geoplanet:7.5.2", "geoplanet:7.6.0", "geoplanet:7.8.1", "geoplanet:7.9.0", "geoplanet:7.10.0", "geoplanet:8.0.0", "woeplanet:8.0.0"], "meta:indexed": "2020-08-20T20:19:00.938185", "meta:updated": "2020-10-14T11:19:47.441284", "woe:hierarchy": {"continent": 24865672, "country": 23424977, "town": 0, "planet": 1, "county": 12589839, "suburb": 0, "state": 2347599, "region": 0, "localadmin": 0}, "woe:timezone_id": 56043648, "woe:hash": "dnn3nt789uw5", "woe:centroid": [-80.920403, 33.954731], "geom:latitude": 33.954731, "geom:longitude": -80.920403, "geom:hash": "dnn3nt789uw5", "woe:latitude": 33.954731, "geom:centroid": [-80.920403, 33.954731], "woe:longitude": -80.920403, "woe:repo": "woeplanet-poi-us", "geom:area": 0.0, "woe:scale": 19}}