{"type": "Feature", "id": 23595237, "properties": {"woe:id": 23595237, "woe:parent_id": 2486832, "woe:name": "St Pauls Lutheran School", "woe:placetype": 20, "woe:placetype_name": "POI", "woe:lang": "ENG", "iso:country": "US", "meta:provider": ["geoplanet:7.3.1", "geoplanet:7.3.2", "geoplanet:7.4.0", "geoplanet:7.4.1", "geoplanet:7.5.1", "geoplanet:7.5.2", "geoplanet:7.6.0", "geoplanet:7.8.1", "geoplanet:7.9.0", "geoplanet:7.10.0", "geoplanet:8.0.0", "woeplanet:8.0.0"], "meta:indexed": "2020-08-20T20:18:43.146864", "meta:updated": "2020-08-22T02:57:40.283131", "woe:hierarchy": {"continent": 24865672, "country": 23424977, "town": 0, "planet": 1, "county": 12588879, "suburb": 0, "state": 2347582, "region": 0, "localadmin": 0}, "woe:timezone_id": 56043661, "woe:hash": "9zudny93vtyk", "woe:centroid": [-94.623283, 43.98135], "geom:latitude": 43.98135, "geom:longitude": -94.623283, "geom:hash": "9zudny93vtyk", "woe:latitude": 43.98135, "geom:centroid": [-94.623283, 43.98135], "woe:longitude": -94.623283, "woe:repo": "woeplanet-poi-us"}, "geometry": {"coordinates": [-94.623283, 43.98135], "type": "Point"}}