{"type": "Feature", "id": 23594388, "geometry": {"type": "Point", "coordinates": [-93.122818, 45.013451]}, "properties": {"woe:id": 23594388, "woe:parent_id": 2484863, "woe:name": "Central Park Elementary School", "woe:placetype": 20, "woe:placetype_name": "POI", "woe:lang": "ENG", "iso:country": "US", "meta:provider": ["geoplanet:7.3.1", "geoplanet:7.3.2", "geoplanet:7.4.0", "geoplanet:7.4.1", "geoplanet:7.5.1", "geoplanet:7.5.2", "geoplanet:7.6.0", "geoplanet:7.8.1", "geoplanet:7.9.0", "geoplanet:7.10.0", "geoplanet:8.0.0", "woeplanet:8.0.0"], "meta:indexed": "2020-08-20T20:18:42.823509", "woe:alias_ENG_V": ["Central Park Elementary"], "meta:updated": "2020-10-14T11:20:23.935430", "woe:hierarchy": {"continent": 24865672, "country": 23424977, "town": 0, "planet": 1, "county": 12588858, "suburb": 0, "state": 2347582, "region": 0, "localadmin": 0}, "woe:timezone_id": 56043661, "woe:hash": "cbjb0fqn356n", "woe:centroid": [-93.122818, 45.013451], "geom:latitude": 45.013451, "geom:longitude": -93.122818, "geom:hash": "cbjb0fqn356n", "woe:latitude": 45.013451, "geom:centroid": [-93.122818, 45.013451], "woe:longitude": -93.122818, "woe:repo": "woeplanet-poi-us", "geom:area": 0.0, "woe:scale": 19}}