{"type": "Feature", "id": 23647976, "geometry": {"type": "Point", "coordinates": [-82.098579, 35.05043]}, "properties": {"woe:id": 23647976, "woe:parent_id": 2427276, "woe:name": "Chapman High School", "woe:placetype": 20, "woe:placetype_name": "POI", "woe:lang": "ENG", "iso:country": "US", "meta:provider": ["geoplanet:7.3.1", "geoplanet:7.3.2", "geoplanet:7.4.0", "geoplanet:7.4.1", "geoplanet:7.5.1", "geoplanet:7.5.2", "geoplanet:7.6.0", "geoplanet:7.8.1", "geoplanet:7.9.0", "geoplanet:7.10.0", "geoplanet:8.0.0", "woeplanet:8.0.0"], "meta:indexed": "2020-08-20T20:19:00.957767", "woe:alias_ENG_V": ["Chapman Senior High School", "Chapman High", "Chapman Senior High", "Chapman HS", "Chapman Senior HS"], "meta:updated": "2020-10-14T11:19:53.985370", "woe:hierarchy": {"continent": 24865672, "country": 23424977, "town": 0, "planet": 1, "county": 12589841, "suburb": 0, "state": 2347599, "region": 0, "localadmin": 0}, "woe:timezone_id": 56043648, "woe:hash": "dnjx7u9xs3wx", "woe:centroid": [-82.098579, 35.05043], "geom:latitude": 35.05043, "geom:longitude": -82.098579, "geom:hash": "dnjx7u9xs3wx", "woe:latitude": 35.05043, "geom:centroid": [-82.098579, 35.05043], "woe:longitude": -82.098579, "woe:repo": "woeplanet-poi-us", "geom:area": 0.0, "woe:scale": 19}}