{"type": "Feature", "id": 23644117, "geometry": {"type": "Point", "coordinates": [-75.167419, 39.922779]}, "properties": {"woe:id": 23644117, "woe:parent_id": 28288863, "woe:name": "Epiphany of Our Lord School", "woe:placetype": 20, "woe:placetype_name": "POI", "woe:lang": "ENG", "iso:country": "US", "meta:provider": ["geoplanet:7.3.1", "geoplanet:7.3.2", "geoplanet:7.4.0", "geoplanet:7.4.1", "geoplanet:7.5.1", "geoplanet:7.5.2", "geoplanet:7.6.0", "geoplanet:7.8.1", "geoplanet:7.9.0", "geoplanet:7.10.0", "geoplanet:8.0.0", "woeplanet:8.0.0"], "meta:indexed": "2020-08-20T20:18:59.853578", "meta:updated": "2020-10-14T11:19:43.764977", "woe:hierarchy": {"continent": 24865672, "country": 23424977, "town": 0, "planet": 1, "county": 12589778, "suburb": 0, "state": 2347597, "region": 0, "localadmin": 0}, "woe:timezone_id": 56043648, "woe:hash": "dr4e1e8z01qj", "woe:centroid": [-75.167419, 39.922779], "geom:latitude": 39.922779, "geom:longitude": -75.167419, "geom:hash": "dr4e1e8z01qj", "woe:latitude": 39.922779, "geom:centroid": [-75.167419, 39.922779], "woe:longitude": -75.167419, "woe:repo": "woeplanet-poi-us", "geom:area": 0.0, "woe:scale": 19}}