{"type": "Feature", "id": 23642976, "geometry": {"type": "Point", "coordinates": [-75.276878, 40.174351]}, "properties": {"woe:id": 23642976, "woe:parent_id": 28745154, "woe:name": "Montgomery County Community College", "woe:placetype": 20, "woe:placetype_name": "POI", "woe:lang": "ENG", "iso:country": "US", "meta:provider": ["geoplanet:7.3.1", "geoplanet:7.3.2", "geoplanet:7.4.0", "geoplanet:7.4.1", "geoplanet:7.5.1", "geoplanet:7.5.2", "geoplanet:7.6.0", "geoplanet:7.8.1", "geoplanet:7.9.0", "geoplanet:7.10.0", "geoplanet:8.0.0", "woeplanet:8.0.0"], "meta:indexed": "2020-08-20T20:18:59.389984", "meta:updated": "2020-10-14T11:19:32.056452", "woe:alias_ENG_V": ["Montgomery Cnty Cmty Col-Central"], "woe:hierarchy": {"continent": 24865672, "country": 23424977, "town": 0, "planet": 1, "county": 12589773, "suburb": 0, "state": 2347597, "region": 0, "localadmin": 0}, "woe:timezone_id": 56043648, "woe:hash": "dr4kx19099g6", "woe:centroid": [-75.276878, 40.174351], "geom:latitude": 40.174351, "geom:longitude": -75.276878, "geom:hash": "dr4kx19099g6", "woe:latitude": 40.174351, "geom:centroid": [-75.276878, 40.174351], "woe:longitude": -75.276878, "woe:repo": "woeplanet-poi-us", "geom:area": 0.0, "woe:scale": 19}}