{"type": "Feature", "id": 23526198, "properties": {"woe:id": 23526198, "woe:parent_id": 55971173, "woe:name": "Millbrook Elementary School", "woe:placetype": 20, "woe:placetype_name": "POI", "woe:lang": "ENG", "iso:country": "US", "meta:provider": ["geoplanet:7.3.2", "geoplanet:7.4.0", "geoplanet:7.4.1", "geoplanet:7.5.1", "geoplanet:7.5.2", "geoplanet:7.6.0", "geoplanet:7.8.1", "geoplanet:7.9.0", "geoplanet:7.10.0", "geoplanet:8.0.0", "woeplanet:8.0.0"], "meta:indexed": "2020-08-20T22:02:00.210617", "woe:alias_ENG_V": ["Millbrook Elementary"], "meta:updated": "2020-08-22T02:57:28.037406", "woe:hierarchy": {"continent": 24865672, "country": 23424977, "town": 0, "planet": 1, "county": 12587712, "suburb": 0, "state": 2347563, "region": 0, "localadmin": 0}, "woe:timezone_id": 56043663, "woe:hash": "9q9kk9u99rmr", "woe:centroid": [-121.788193, 37.319481], "geom:latitude": 37.319481, "geom:longitude": -121.788193, "geom:hash": "9q9kk9u99rmr", "woe:latitude": 37.319481, "geom:centroid": [-121.788193, 37.319481], "woe:longitude": -121.788193, "woe:repo": "woeplanet-poi-us"}, "geometry": {"coordinates": [-121.788193, 37.319481], "type": "Point"}}