{"type": "Feature", "id": 23642016, "properties": {"woe:id": 23642016, "woe:parent_id": 28745225, "woe:name": "West Eby School", "woe:placetype": 20, "woe:placetype_name": "POI", "woe:lang": "ENG", "iso:country": "US", "meta:provider": ["geoplanet:7.3.2", "geoplanet:7.4.0", "geoplanet:7.4.1", "geoplanet:7.5.1", "geoplanet:7.5.2", "geoplanet:7.6.0", "geoplanet:7.8.1", "geoplanet:7.9.0", "geoplanet:7.10.0", "geoplanet:8.0.0", "woeplanet:8.0.0"], "meta:indexed": "2020-08-20T22:02:47.903728", "woe:alias_ENG_V": ["W Eby School"], "meta:updated": "2020-08-22T02:57:46.989518", "woe:hierarchy": {"continent": 24865672, "country": 23424977, "town": 0, "planet": 1, "county": 12589763, "suburb": 0, "state": 2347597, "region": 0, "localadmin": 0}, "woe:timezone_id": 56043648, "woe:hash": "dr1gfw7q712f", "woe:centroid": [-76.174606, 40.069592], "geom:latitude": 40.069592, "geom:longitude": -76.174606, "geom:hash": "dr1gfw7q712f", "woe:latitude": 40.069592, "geom:centroid": [-76.174606, 40.069592], "woe:longitude": -76.174606, "woe:repo": "woeplanet-poi-us"}, "geometry": {"coordinates": [-76.174606, 40.069592], "type": "Point"}}