{"type": "Feature", "id": 23531667, "geometry": {"type": "Point", "coordinates": [-118.461617, 34.426659]}, "properties": {"woe:id": 23531667, "woe:parent_id": 55861644, "woe:name": "Leona H. Cox Community Elementary School", "woe:placetype": 20, "woe:placetype_name": "POI", "woe:lang": "ENG", "iso:country": "US", "meta:provider": ["geoplanet:7.3.1", "geoplanet:7.3.2", "geoplanet:7.4.0", "geoplanet:7.4.1", "geoplanet:7.5.1", "geoplanet:7.5.2", "geoplanet:7.6.0", "geoplanet:7.8.1", "geoplanet:7.9.0", "geoplanet:7.10.0", "geoplanet:8.0.0", "woeplanet:8.0.0"], "meta:indexed": "2020-08-20T20:18:21.908332", "woe:alias_ENG_V": ["Leona Cox Community Elementary Sch", "Leona H. Cox Community Elementary"], "meta:updated": "2020-10-14T11:20:17.016919", "woe:hierarchy": {"continent": 24865672, "country": 23424977, "town": 0, "planet": 1, "county": 12587688, "suburb": 0, "state": 2347563, "region": 0, "localadmin": 0}, "woe:timezone_id": 56043663, "woe:hash": "9q5gb74vu62h", "woe:centroid": [-118.461617, 34.426659], "geom:latitude": 34.426659, "geom:longitude": -118.461617, "geom:hash": "9q5gb74vu62h", "woe:latitude": 34.426659, "geom:centroid": [-118.461617, 34.426659], "woe:longitude": -118.461617, "woe:repo": "woeplanet-poi-us", "geom:area": 0.0, "woe:scale": 19}}