{"type": "Feature", "id": 23531367, "properties": {"woe:id": 23531367, "woe:parent_id": 2442137, "woe:name": "Rancho Santa Gertrudes Elementary School", "woe:placetype": 20, "woe:placetype_name": "POI", "woe:lang": "ENG", "iso:country": "US", "meta:provider": ["geoplanet:7.3.2", "geoplanet:7.4.0", "geoplanet:7.4.1", "geoplanet:7.5.1", "geoplanet:7.5.2", "geoplanet:7.6.0", "geoplanet:7.8.1", "geoplanet:7.9.0", "geoplanet:7.10.0", "geoplanet:8.0.0", "woeplanet:8.0.0"], "meta:indexed": "2020-08-20T22:02:02.406411", "woe:alias_ENG_V": ["Rancho Santa Gertrudes Elem School", "Rancho Santa Gertrudes Elementary"], "meta:updated": "2020-08-22T02:57:28.891711", "woe:hierarchy": {"continent": 24865672, "country": 23424977, "town": 0, "planet": 1, "county": 12587688, "suburb": 0, "state": 2347563, "region": 0, "localadmin": 0}, "woe:timezone_id": 56043663, "woe:hash": "9qh10vpy8tpp", "woe:centroid": [-118.081367, 33.954391], "geom:latitude": 33.954391, "geom:longitude": -118.081367, "geom:hash": "9qh10vpy8tpp", "woe:latitude": 33.954391, "geom:centroid": [-118.081367, 33.954391], "woe:longitude": -118.081367, "woe:repo": "woeplanet-poi-us"}, "geometry": {"coordinates": [-118.081367, 33.954391], "type": "Point"}}