{"type": "Feature", "id": 23646114, "geometry": {"type": "Point", "coordinates": [-71.354309, 41.875011]}, "properties": {"woe:id": 23646114, "woe:parent_id": 2389444, "woe:name": "Darlington Early Childhood Center", "woe:placetype": 20, "woe:placetype_name": "POI", "woe:lang": "ENG", "iso:country": "US", "meta:provider": ["geoplanet:7.3.1", "geoplanet:7.3.2", "geoplanet:7.4.0", "geoplanet:7.4.1", "geoplanet:7.5.1", "geoplanet:7.5.2", "geoplanet:7.6.0", "geoplanet:7.8.1", "geoplanet:7.9.0", "geoplanet:7.10.0", "geoplanet:8.0.0", "woeplanet:8.0.0"], "meta:indexed": "2020-08-20T20:19:00.417521", "meta:updated": "2020-10-14T11:19:28.793591", "woe:hierarchy": {"continent": 24865672, "country": 23424977, "town": 0, "planet": 1, "county": 12589798, "suburb": 0, "state": 2347598, "region": 0, "localadmin": 0}, "woe:timezone_id": 56043648, "woe:hash": "drmq0r17s5ff", "woe:centroid": [-71.354309, 41.875011], "geom:latitude": 41.875011, "geom:longitude": -71.354309, "geom:hash": "drmq0r17s5ff", "woe:latitude": 41.875011, "geom:centroid": [-71.354309, 41.875011], "woe:longitude": -71.354309, "woe:repo": "woeplanet-poi-us", "geom:area": 0.0, "woe:scale": 19}}