{"type": "Feature", "id": 24866122, "properties": {"woe:id": 24866122, "woe:parent_id": 2377757, "woe:name": "Chadron State College", "woe:placetype": 20, "woe:placetype_name": "POI", "woe:lang": "ENG", "iso:country": "US", "meta:provider": ["geoplanet:7.3.1", "geoplanet:7.3.2", "geoplanet:7.4.0", "geoplanet:7.4.1", "geoplanet:7.5.1", "geoplanet:7.5.2", "geoplanet:7.6.0", "geoplanet:7.8.1", "geoplanet:7.9.0", "geoplanet:7.10.0", "geoplanet:8.0.0", "woeplanet:8.0.0"], "meta:indexed": "2020-08-20T20:19:14.899302", "meta:updated": "2020-08-22T02:58:19.670894", "woe:hierarchy": {"continent": 24865672, "country": 23424977, "town": 0, "planet": 1, "county": 12589160, "suburb": 0, "state": 2347586, "region": 0, "localadmin": 0}, "woe:timezone_id": 56043665, "woe:hash": "9xwg85kjp2wv", "woe:centroid": [-103.001999, 42.821449], "geom:latitude": 42.821449, "geom:longitude": -103.001999, "geom:hash": "9xwg85kjp2wv", "woe:latitude": 42.821449, "geom:centroid": [-103.001999, 42.821449], "woe:longitude": -103.001999, "woe:repo": "woeplanet-poi-us"}, "geometry": {"coordinates": [-103.001999, 42.821449], "type": "Point"}}