{"type": "Feature", "id": 23540215, "properties": {"woe:id": 23540215, "woe:parent_id": 55806479, "woe:name": "Taylor Elementary School", "woe:placetype": 20, "woe:placetype_name": "POI", "woe:lang": "ENG", "iso:country": "US", "meta:provider": ["geoplanet:7.3.2", "geoplanet:7.4.0", "geoplanet:7.4.1", "geoplanet:7.5.1", "geoplanet:7.5.2", "geoplanet:7.6.0", "geoplanet:7.8.1", "geoplanet:7.9.0", "geoplanet:7.10.0", "geoplanet:8.0.0", "woeplanet:8.0.0"], "meta:indexed": "2020-08-20T22:02:06.091638", "woe:alias_ENG_V": ["Paylor Elementary School", "Taylor Elementary"], "meta:updated": "2020-08-22T02:57:30.717719", "woe:hierarchy": {"continent": 24865672, "country": 23424977, "town": 0, "planet": 1, "county": 12587747, "suburb": 0, "state": 2347564, "region": 0, "localadmin": 0}, "woe:timezone_id": 56043665, "woe:hash": "9wvmp10ruzr9", "woe:centroid": [-104.809013, 38.854519], "geom:latitude": 38.854519, "geom:longitude": -104.809013, "geom:hash": "9wvmp10ruzr9", "woe:latitude": 38.854519, "geom:centroid": [-104.809013, 38.854519], "woe:longitude": -104.809013, "woe:repo": "woeplanet-poi-us"}, "geometry": {"coordinates": [-104.809013, 38.854519], "type": "Point"}}