{"type": "Feature", "id": 23618035, "geometry": {"type": "Point", "coordinates": [-75.233261, 43.336899]}, "properties": {"woe:id": 23618035, "woe:parent_id": 2499702, "woe:name": "Steuben Memorial State Historic Site", "woe:placetype": 20, "woe:placetype_name": "POI", "woe:lang": "ENG", "iso:country": "US", "meta:provider": ["geoplanet:7.3.1", "geoplanet:7.3.2", "geoplanet:7.4.0", "geoplanet:7.4.1", "geoplanet:7.5.1", "geoplanet:7.5.2", "geoplanet:7.6.0", "geoplanet:7.8.1", "geoplanet:7.9.0", "geoplanet:7.10.0", "geoplanet:8.0.0", "woeplanet:8.0.0"], "meta:indexed": "2020-08-20T20:18:50.653105", "meta:updated": "2020-10-14T11:19:31.852922", "woe:hierarchy": {"continent": 24865672, "country": 23424977, "town": 0, "planet": 1, "county": 12589344, "suburb": 0, "state": 2347591, "region": 0, "localadmin": 0}, "woe:timezone_id": 56043648, "woe:hash": "drdw810z9zw8", "woe:centroid": [-75.233261, 43.336899], "geom:latitude": 43.336899, "geom:longitude": -75.233261, "geom:hash": "drdw810z9zw8", "woe:latitude": 43.336899, "geom:centroid": [-75.233261, 43.336899], "woe:longitude": -75.233261, "woe:repo": "woeplanet-poi-us", "geom:area": 0.0, "woe:scale": 19}}