{"type": "Feature", "id": 23552595, "geometry": {"type": "Point", "coordinates": [-85.159653, 34.233421]}, "properties": {"woe:id": 23552595, "woe:parent_id": 2357094, "woe:name": "East Central Elementary School", "woe:placetype": 20, "woe:placetype_name": "POI", "woe:lang": "ENG", "iso:country": "US", "meta:provider": ["geoplanet:7.3.1", "geoplanet:7.3.2", "geoplanet:7.4.0", "geoplanet:7.4.1", "geoplanet:7.5.1", "geoplanet:7.5.2", "geoplanet:7.6.0", "geoplanet:7.8.1", "geoplanet:7.9.0", "geoplanet:7.10.0", "geoplanet:8.0.0", "woeplanet:8.0.0"], "meta:indexed": "2020-08-20T20:18:29.315309", "woe:alias_ENG_V": ["E Central Elementary School", "E Central Elementary", "East Central Elementary"], "meta:updated": "2020-10-14T11:20:17.882635", "woe:hierarchy": {"continent": 24865672, "country": 23424977, "town": 0, "planet": 1, "county": 12587926, "suburb": 0, "state": 2347569, "region": 0, "localadmin": 0}, "woe:timezone_id": 56043648, "woe:hash": "dn56y0h8hk0q", "woe:centroid": [-85.159653, 34.233421], "geom:latitude": 34.233421, "geom:longitude": -85.159653, "geom:hash": "dn56y0h8hk0q", "woe:latitude": 34.233421, "geom:centroid": [-85.159653, 34.233421], "woe:longitude": -85.159653, "woe:repo": "woeplanet-poi-us", "geom:area": 0.0, "woe:scale": 19}}