{"type": "Feature", "id": 23630064, "properties": {"woe:id": 23630064, "woe:parent_id": 2431714, "woe:name": "Eastcrest Elementary School", "woe:placetype": 20, "woe:placetype_name": "POI", "woe:lang": "ENG", "iso:country": "US", "meta:provider": ["geoplanet:7.3.1", "geoplanet:7.3.2", "geoplanet:7.4.0", "geoplanet:7.4.1", "geoplanet:7.5.1", "geoplanet:7.5.2", "geoplanet:7.6.0", "geoplanet:7.8.1", "geoplanet:7.9.0", "geoplanet:7.10.0", "geoplanet:8.0.0", "woeplanet:8.0.0"], "meta:indexed": "2020-08-20T20:18:54.494258", "woe:alias_ENG_V": ["Eastcrest Elementary"], "meta:updated": "2020-08-22T02:57:45.135553", "woe:hierarchy": {"continent": 24865672, "country": 23424977, "town": 0, "planet": 1, "county": 12589559, "suburb": 0, "state": 2347594, "region": 0, "localadmin": 0}, "woe:timezone_id": 56043648, "woe:hash": "dphx1wywnxzv", "woe:centroid": [-83.596741, 40.64362], "geom:latitude": 40.64362, "geom:longitude": -83.596741, "geom:hash": "dphx1wywnxzv", "woe:latitude": 40.64362, "geom:centroid": [-83.596741, 40.64362], "woe:longitude": -83.596741, "woe:repo": "woeplanet-poi-us"}, "geometry": {"coordinates": [-83.596741, 40.64362], "type": "Point"}}