{"type": "Feature", "id": 23543934, "properties": {"woe:id": 23543934, "woe:parent_id": 2450978, "woe:name": "Orchard Hills School", "woe:placetype": 20, "woe:placetype_name": "POI", "woe:lang": "ENG", "iso:country": "US", "meta:provider": ["geoplanet:7.3.1", "geoplanet:7.3.2", "geoplanet:7.4.0", "geoplanet:7.4.1", "geoplanet:7.5.1", "geoplanet:7.5.2", "geoplanet:7.6.0", "geoplanet:7.8.1", "geoplanet:7.9.0", "geoplanet:7.10.0", "geoplanet:8.0.0", "woeplanet:8.0.0"], "meta:indexed": "2020-08-20T20:18:25.392250", "meta:updated": "2020-08-22T02:57:31.202108", "woe:alias_ENG_V": ["Orchard Hills Elementary School"], "woe:hierarchy": {"continent": 24865672, "country": 23424977, "town": 0, "planet": 1, "county": 12587795, "suburb": 0, "state": 2347565, "region": 0, "localadmin": 0}, "woe:timezone_id": 56043648, "woe:hash": "drk4d24bhxh1", "woe:centroid": [-73.022148, 41.220741], "geom:latitude": 41.220741, "geom:longitude": -73.022148, "geom:hash": "drk4d24bhxh1", "woe:latitude": 41.220741, "geom:centroid": [-73.022148, 41.220741], "woe:longitude": -73.022148, "woe:repo": "woeplanet-poi-us"}, "geometry": {"coordinates": [-73.022148, 41.220741], "type": "Point"}}