{"type": "Feature", "id": 56204157, "geometry": {"type": "Point", "coordinates": [-122.086166, 37.428921]}, "properties": {"woe:id": 56204157, "woe:parent_id": 55860930, "woe:name": "Shoreline Golf Links", "woe:placetype": 20, "woe:placetype_name": "POI", "woe:lang": "ENG", "iso:country": "US", "meta:provider": ["geoplanet:7.6.0", "geoplanet:7.8.1", "geoplanet:7.9.0", "geoplanet:7.10.0", "geoplanet:8.0.0", "woeplanet:8.0.0"], "meta:indexed": "2020-08-21T08:24:23.769306", "meta:updated": "2020-10-14T11:19:58.451659", "woe:hierarchy": {"continent": 24865672, "country": 23424977, "town": 0, "planet": 1, "county": 12587712, "suburb": 0, "state": 2347563, "region": 0, "localadmin": 0}, "woe:timezone_id": 56043663, "woe:hash": "9q9hvvex60sd", "woe:centroid": [-122.086166, 37.428921], "geom:latitude": 37.428921, "geom:longitude": -122.086166, "geom:hash": "9q9hvvex60sd", "woe:latitude": 37.428921, "geom:centroid": [-122.086166, 37.428921], "woe:longitude": -122.086166, "woe:repo": "woeplanet-poi-us", "geom:area": 0.0, "woe:scale": 19}}