{"type": "Feature", "id": 23543902, "properties": {"woe:id": 23543902, "woe:parent_id": 2519996, "woe:name": "Ridge Hill School", "woe:placetype": 20, "woe:placetype_name": "POI", "woe:lang": "ENG", "iso:country": "US", "meta:provider": ["geoplanet:7.3.1", "geoplanet:7.3.2", "geoplanet:7.4.0", "geoplanet:7.4.1", "geoplanet:7.5.1", "geoplanet:7.5.2", "geoplanet:7.6.0", "geoplanet:7.8.1", "geoplanet:7.9.0", "geoplanet:7.10.0", "geoplanet:8.0.0", "woeplanet:8.0.0"], "meta:indexed": "2020-08-20T20:18:25.370014", "meta:updated": "2020-08-22T02:57:31.192651", "woe:hierarchy": {"continent": 24865672, "country": 23424977, "town": 0, "planet": 1, "county": 12587795, "suburb": 0, "state": 2347565, "region": 0, "localadmin": 0}, "woe:timezone_id": 56043648, "woe:hash": "drk5jnvj55w1", "woe:centroid": [-72.89827, 41.34655], "geom:latitude": 41.34655, "geom:longitude": -72.89827, "geom:hash": "drk5jnvj55w1", "woe:latitude": 41.34655, "geom:centroid": [-72.89827, 41.34655], "woe:longitude": -72.89827, "woe:repo": "woeplanet-poi-us"}, "geometry": {"coordinates": [-72.89827, 41.34655], "type": "Point"}}