{"type": "Feature", "id": 23575910, "geometry": {"type": "Point", "coordinates": [-91.843872, 31.760759]}, "properties": {"woe:id": 23575910, "woe:parent_id": 2418118, "woe:name": "Harrisonburg High School", "woe:placetype": 20, "woe:placetype_name": "POI", "woe:lang": "ENG", "iso:country": "US", "meta:provider": ["geoplanet:7.3.1", "geoplanet:7.3.2", "geoplanet:7.4.0", "geoplanet:7.4.1", "geoplanet:7.5.1", "geoplanet:7.5.2", "geoplanet:7.6.0", "geoplanet:7.8.1", "geoplanet:7.9.0", "geoplanet:7.10.0", "geoplanet:8.0.0", "woeplanet:8.0.0"], "meta:indexed": "2020-08-20T20:18:37.341803", "woe:alias_ENG_V": ["Harrisonburg Senior High School", "Harrisonburg High", "Harrisonburg Senior High", "Harrisonburg HS", "Harrisonburg Senior HS"], "meta:updated": "2020-10-14T11:20:21.282275", "woe:hierarchy": {"continent": 24865672, "country": 23424977, "town": 0, "planet": 1, "county": 12588608, "suburb": 0, "state": 2347577, "region": 0, "localadmin": 0}, "woe:timezone_id": 56043661, "woe:hash": "9vwswjc7fdt7", "woe:centroid": [-91.843872, 31.760759], "geom:latitude": 31.760759, "geom:longitude": -91.843872, "geom:hash": "9vwswjc7fdt7", "woe:latitude": 31.760759, "geom:centroid": [-91.843872, 31.760759], "woe:longitude": -91.843872, "woe:repo": "woeplanet-poi-us", "geom:area": 0.0, "woe:scale": 19}}