{"type": "Feature", "id": 23661693, "properties": {"woe:id": 23661693, "woe:parent_id": 2437416, "woe:name": "Layton High School", "woe:placetype": 20, "woe:placetype_name": "POI", "woe:lang": "ENG", "iso:country": "US", "meta:provider": ["geoplanet:7.4.0", "geoplanet:7.4.1", "geoplanet:7.5.1", "geoplanet:7.5.2", "geoplanet:7.6.0", "geoplanet:7.8.1", "geoplanet:7.9.0", "geoplanet:7.10.0", "geoplanet:8.0.0", "woeplanet:8.0.0"], "meta:indexed": "2020-08-20T23:55:43.275774", "woe:alias_ENG_V": ["Layton Senior High School", "Layton High", "Layton Senior High", "Layton HS", "Layton Senior HS"], "meta:updated": "2020-08-22T02:58:50.106199", "woe:hierarchy": {"continent": 24865672, "country": 23424977, "town": 0, "planet": 1, "county": 12590266, "suburb": 0, "state": 2347603, "region": 0, "localadmin": 0}, "woe:timezone_id": 56043665, "woe:hash": "9x23s7ghp6nd", "woe:centroid": [-111.95723, 41.066219], "geom:latitude": 41.066219, "geom:longitude": -111.95723, "geom:hash": "9x23s7ghp6nd", "woe:latitude": 41.066219, "geom:centroid": [-111.95723, 41.066219], "woe:longitude": -111.95723, "woe:repo": "woeplanet-poi-us"}, "geometry": {"coordinates": [-111.95723, 41.066219], "type": "Point"}}