{"type": "Feature", "id": 23594612, "properties": {"woe:id": 23594612, "woe:parent_id": 2364479, "woe:name": "Bold-bird Island Elementary School", "woe:placetype": 20, "woe:placetype_name": "POI", "woe:lang": "ENG", "iso:country": "US", "meta:provider": ["geoplanet:7.3.1", "geoplanet:7.3.2", "geoplanet:7.4.0", "geoplanet:7.4.1", "geoplanet:7.5.1", "geoplanet:7.5.2", "geoplanet:7.6.0", "geoplanet:7.8.1", "geoplanet:7.9.0", "geoplanet:7.10.0", "geoplanet:8.0.0", "woeplanet:8.0.0"], "meta:indexed": "2020-08-20T20:18:42.927745", "woe:alias_ENG_V": ["Bold Elementary School", "Bold-bird Island Elementary"], "meta:updated": "2020-08-22T02:57:40.180291", "woe:hierarchy": {"continent": 24865672, "country": 23424977, "town": 0, "planet": 1, "county": 12588861, "suburb": 0, "state": 2347582, "region": 0, "localadmin": 0}, "woe:timezone_id": 56043661, "woe:hash": "9zuw8t3rrj7n", "woe:centroid": [-94.897881, 44.766441], "geom:latitude": 44.766441, "geom:longitude": -94.897881, "geom:hash": "9zuw8t3rrj7n", "woe:latitude": 44.766441, "geom:centroid": [-94.897881, 44.766441], "woe:longitude": -94.897881, "woe:repo": "woeplanet-poi-us"}, "geometry": {"coordinates": [-94.897881, 44.766441], "type": "Point"}}