{"type": "Feature", "id": 23543997, "geometry": {"type": "Point", "coordinates": [-72.802818, 41.333912]}, "properties": {"woe:id": 23543997, "woe:parent_id": 2460717, "woe:name": "North Branford High School", "woe:placetype": 20, "woe:placetype_name": "POI", "woe:lang": "ENG", "iso:country": "US", "meta:provider": ["geoplanet:7.3.1", "geoplanet:7.3.2", "geoplanet:7.4.0", "geoplanet:7.4.1", "geoplanet:7.5.1", "geoplanet:7.5.2", "geoplanet:7.6.0", "geoplanet:7.8.1", "geoplanet:7.9.0", "geoplanet:7.10.0", "geoplanet:8.0.0", "woeplanet:8.0.0"], "meta:indexed": "2020-08-20T20:18:25.434377", "woe:alias_ENG_V": ["North Branford Senior High School", "North Branford High", "North Branford Senior High", "North Branford HS", "North Branford Senior HS", "N Branford High", "N Branford High School", "N Branford HS", "N Branford Senior High", "N Branford Senior High School", "N Branford Senior HS"], "meta:updated": "2020-10-14T11:20:07.969351", "woe:hierarchy": {"continent": 24865672, "country": 23424977, "town": 0, "planet": 1, "county": 12587795, "suburb": 0, "state": 2347565, "region": 0, "localadmin": 0}, "woe:timezone_id": 56043648, "woe:hash": "drk5pkde7rsm", "woe:centroid": [-72.802818, 41.333912], "geom:latitude": 41.333912, "geom:longitude": -72.802818, "geom:hash": "drk5pkde7rsm", "woe:latitude": 41.333912, "geom:centroid": [-72.802818, 41.333912], "woe:longitude": -72.802818, "woe:repo": "woeplanet-poi-us", "geom:area": 0.0, "woe:scale": 19}}