{"type": "Feature", "id": 23651727, "geometry": {"type": "Point", "coordinates": [-90.040291, 35.165981]}, "properties": {"woe:id": 23651727, "woe:parent_id": 28288879, "woe:name": "Caldwell Elementary School", "woe:placetype": 20, "woe:placetype_name": "POI", "woe:lang": "ENG", "iso:country": "US", "meta:provider": ["geoplanet:7.3.1", "geoplanet:7.3.2", "geoplanet:7.4.0", "geoplanet:7.4.1", "geoplanet:7.5.1", "geoplanet:7.5.2", "geoplanet:7.6.0", "geoplanet:7.8.1", "geoplanet:7.9.0", "geoplanet:7.10.0", "geoplanet:8.0.0", "woeplanet:8.0.0"], "meta:indexed": "2020-08-20T20:19:02.127781", "woe:alias_ENG_V": ["Caldwell Elementary"], "meta:updated": "2020-10-14T11:19:50.758054", "woe:hierarchy": {"continent": 24865672, "country": 23424977, "town": 0, "planet": 1, "county": 12589990, "suburb": 0, "state": 2347601, "region": 0, "localadmin": 0}, "woe:timezone_id": 56043661, "woe:hash": "9yrbp1f8tjuz", "woe:centroid": [-90.040291, 35.165981], "geom:latitude": 35.165981, "geom:longitude": -90.040291, "geom:hash": "9yrbp1f8tjuz", "woe:latitude": 35.165981, "geom:centroid": [-90.040291, 35.165981], "woe:longitude": -90.040291, "woe:repo": "woeplanet-poi-us", "geom:area": 0.0, "woe:scale": 19}}