{"type": "Feature", "id": 23518923, "geometry": {"type": "Point", "coordinates": [-91.581268, 34.782711]}, "properties": {"woe:id": 23518923, "woe:parent_id": 2419300, "woe:name": "Hazen Elementary School", "woe:placetype": 20, "woe:placetype_name": "POI", "woe:lang": "ENG", "iso:country": "US", "meta:provider": ["geoplanet:7.3.1", "geoplanet:7.3.2", "geoplanet:7.4.0", "geoplanet:7.4.1", "geoplanet:7.5.1", "geoplanet:7.5.2", "geoplanet:7.6.0", "geoplanet:7.8.1", "geoplanet:7.9.0", "geoplanet:7.10.0", "geoplanet:8.0.0", "woeplanet:8.0.0"], "meta:indexed": "2020-08-20T20:18:19.221625", "woe:alias_ENG_V": ["Hazen Elementary"], "meta:updated": "2020-10-14T11:20:14.490534", "woe:hierarchy": {"continent": 24865672, "country": 23424977, "town": 0, "planet": 1, "county": 12587653, "suburb": 0, "state": 2347562, "region": 0, "localadmin": 0}, "woe:timezone_id": 56043661, "woe:hash": "9ynvu5bxcz31", "woe:centroid": [-91.581268, 34.782711], "geom:latitude": 34.782711, "geom:longitude": -91.581268, "geom:hash": "9ynvu5bxcz31", "woe:latitude": 34.782711, "geom:centroid": [-91.581268, 34.782711], "woe:longitude": -91.581268, "woe:repo": "woeplanet-poi-us", "geom:area": 0.0, "woe:scale": 19}}