{"type": "Feature", "id": 23620346, "properties": {"woe:id": 23620346, "woe:parent_id": 2489634, "woe:name": "Our Lady of Mt Carmel School", "woe:placetype": 20, "woe:placetype_name": "POI", "woe:lang": "ENG", "iso:country": "US", "meta:provider": ["geoplanet:7.3.1", "geoplanet:7.3.2", "geoplanet:7.4.0", "geoplanet:7.4.1", "geoplanet:7.5.1", "geoplanet:7.5.2", "geoplanet:7.6.0", "geoplanet:7.8.1", "geoplanet:7.9.0", "geoplanet:7.10.0", "geoplanet:8.0.0", "woeplanet:8.0.0"], "meta:indexed": "2020-08-20T20:18:51.593177", "meta:updated": "2020-08-22T02:57:43.734408", "woe:hierarchy": {"continent": 24865672, "country": 23424977, "town": 0, "planet": 1, "county": 12589357, "suburb": 0, "state": 2347591, "region": 0, "localadmin": 0}, "woe:timezone_id": 56043648, "woe:hash": "dre7mq3t8yu1", "woe:centroid": [-73.946877, 42.794102], "geom:latitude": 42.794102, "geom:longitude": -73.946877, "geom:hash": "dre7mq3t8yu1", "woe:latitude": 42.794102, "geom:centroid": [-73.946877, 42.794102], "woe:longitude": -73.946877, "woe:repo": "woeplanet-poi-us"}, "geometry": {"coordinates": [-73.946877, 42.794102], "type": "Point"}}