{"type": "Feature", "id": 23547453, "properties": {"woe:id": 23547453, "woe:parent_id": 12587860, "woe:name": "Osceola Elementary School", "woe:placetype": 20, "woe:placetype_name": "POI", "woe:lang": "ENG", "iso:country": "US", "meta:provider": ["geoplanet:7.3.1", "geoplanet:7.3.2", "geoplanet:7.4.0", "geoplanet:7.4.1", "geoplanet:7.5.1", "geoplanet:7.5.2", "geoplanet:7.6.0", "geoplanet:7.8.1", "geoplanet:7.9.0", "geoplanet:7.10.0", "geoplanet:8.0.0", "woeplanet:8.0.0"], "meta:indexed": "2020-08-20T20:18:26.899556", "woe:alias_ENG_V": ["Osceola Elementary"], "meta:updated": "2020-08-22T02:57:31.970348", "woe:hierarchy": {"continent": 24865672, "country": 23424977, "town": 0, "planet": 1, "county": 12587860, "suburb": 0, "state": 2347568, "region": 0, "localadmin": 0}, "woe:timezone_id": 56043648, "woe:hash": "djq1vjfun3ub", "woe:centroid": [-81.338722, 29.871149], "geom:latitude": 29.871149, "geom:longitude": -81.338722, "geom:hash": "djq1vjfun3ub", "woe:latitude": 29.871149, "geom:centroid": [-81.338722, 29.871149], "woe:longitude": -81.338722, "woe:repo": "woeplanet-poi-us"}, "geometry": {"coordinates": [-81.338722, 29.871149], "type": "Point"}}