{"type": "Feature", "id": 23607547, "geometry": {"type": "Point", "coordinates": [-74.838097, 39.88018]}, "properties": {"woe:id": 23607547, "woe:parent_id": 2448924, "woe:name": "Taunton Forge Elementary School", "woe:placetype": 20, "woe:placetype_name": "POI", "woe:lang": "ENG", "iso:country": "US", "meta:provider": ["geoplanet:7.3.1", "geoplanet:7.3.2", "geoplanet:7.4.0", "geoplanet:7.4.1", "geoplanet:7.5.1", "geoplanet:7.5.2", "geoplanet:7.6.0", "geoplanet:7.8.1", "geoplanet:7.9.0", "geoplanet:7.10.0", "geoplanet:8.0.0", "woeplanet:8.0.0"], "meta:indexed": "2020-08-20T20:18:46.793753", "woe:alias_ENG_V": ["Taunton Forge Elementary"], "meta:updated": "2020-10-14T11:19:54.105421", "woe:hierarchy": {"continent": 24865672, "country": 23424977, "town": 0, "planet": 1, "county": 12589260, "suburb": 0, "state": 2347589, "region": 0, "localadmin": 0}, "woe:timezone_id": 56043648, "woe:hash": "dr4fc5bwcuqk", "woe:centroid": [-74.838097, 39.88018], "geom:latitude": 39.88018, "geom:longitude": -74.838097, "geom:hash": "dr4fc5bwcuqk", "woe:latitude": 39.88018, "geom:centroid": [-74.838097, 39.88018], "woe:longitude": -74.838097, "woe:repo": "woeplanet-poi-us", "geom:area": 0.0, "woe:scale": 19}}