{"type": "Feature", "id": 23621770, "properties": {"woe:id": 23621770, "woe:parent_id": 2418942, "woe:name": "Hawthorne Elementary School", "woe:placetype": 20, "woe:placetype_name": "POI", "woe:lang": "ENG", "iso:country": "US", "meta:provider": ["geoplanet:7.3.1", "geoplanet:7.3.2", "geoplanet:7.4.0", "geoplanet:7.4.1", "geoplanet:7.5.1", "geoplanet:7.5.2", "geoplanet:7.6.0", "geoplanet:7.8.1", "geoplanet:7.9.0", "geoplanet:7.10.0", "geoplanet:8.0.0", "woeplanet:8.0.0"], "meta:indexed": "2020-08-20T20:18:52.111685", "woe:alias_ENG_V": ["Hawthorne Elementary"], "meta:updated": "2020-08-22T02:57:43.917878", "woe:hierarchy": {"continent": 24865672, "country": 23424977, "town": 0, "planet": 1, "county": 12589371, "suburb": 0, "state": 2347591, "region": 0, "localadmin": 0}, "woe:timezone_id": 56043648, "woe:hash": "dr79bdsn6kcg", "woe:centroid": [-73.80056, 41.103699], "geom:latitude": 41.103699, "geom:longitude": -73.80056, "geom:hash": "dr79bdsn6kcg", "woe:latitude": 41.103699, "geom:centroid": [-73.80056, 41.103699], "woe:longitude": -73.80056, "woe:repo": "woeplanet-poi-us"}, "geometry": {"coordinates": [-73.80056, 41.103699], "type": "Point"}}