{"type": "Feature", "id": 56052352, "geometry": {"type": "Point", "coordinates": [-83.432709, 42.41806]}, "properties": {"woe:id": 56052352, "woe:parent_id": 56021978, "woe:name": "Schoolcraft College-Livonia", "woe:placetype": 20, "woe:placetype_name": "POI", "woe:lang": "ENG", "iso:country": "US", "meta:provider": ["geoplanet:7.3.1", "geoplanet:7.3.2", "geoplanet:7.4.0", "geoplanet:7.4.1", "geoplanet:7.5.1", "geoplanet:7.5.2", "geoplanet:7.6.0", "geoplanet:7.8.1", "geoplanet:7.9.0", "geoplanet:7.10.0", "geoplanet:8.0.0", "woeplanet:8.0.0"], "meta:indexed": "2020-08-20T20:19:16.259795", "meta:updated": "2020-10-14T11:19:55.465539", "woe:hierarchy": {"continent": 24865672, "country": 23424977, "town": 0, "planet": 1, "county": 12588795, "suburb": 0, "state": 2347581, "region": 0, "localadmin": 0}, "woe:timezone_id": 56043658, "woe:hash": "dps9m3yphgrp", "woe:centroid": [-83.432709, 42.41806], "geom:latitude": 42.41806, "geom:longitude": -83.432709, "geom:hash": "dps9m3yphgrp", "woe:latitude": 42.41806, "geom:centroid": [-83.432709, 42.41806], "woe:longitude": -83.432709, "woe:repo": "woeplanet-poi-us", "geom:area": 0.0, "woe:scale": 19}}