{"type": "Feature", "id": 23659887, "geometry": {"type": "Point", "coordinates": [-95.2108, 29.71261]}, "properties": {"woe:id": 23659887, "woe:parent_id": 2468963, "woe:name": "Bob Harris Station", "woe:placetype": 20, "woe:placetype_name": "POI", "woe:lang": "ENG", "iso:country": "US", "meta:provider": ["geoplanet:7.3.1", "geoplanet:7.3.2", "geoplanet:7.4.0", "geoplanet:7.4.1", "geoplanet:7.5.1", "geoplanet:7.5.2", "geoplanet:7.6.0", "geoplanet:7.8.1", "geoplanet:7.9.0", "geoplanet:7.10.0", "geoplanet:8.0.0", "woeplanet:8.0.0"], "meta:indexed": "2020-08-20T20:19:06.196556", "meta:updated": "2020-10-14T11:19:52.377221", "woe:hierarchy": {"continent": 24865672, "country": 23424977, "town": 0, "planet": 1, "county": 12590107, "suburb": 0, "state": 2347602, "region": 0, "localadmin": 0}, "woe:timezone_id": 56043661, "woe:hash": "9vk313j87xcy", "woe:centroid": [-95.2108, 29.71261], "geom:latitude": 29.71261, "geom:longitude": -95.2108, "geom:hash": "9vk313j87xcy", "woe:latitude": 29.71261, "geom:centroid": [-95.2108, 29.71261], "woe:longitude": -95.2108, "woe:repo": "woeplanet-poi-us", "geom:area": 0.0, "woe:scale": 19}}