{"type": "Feature", "id": 23651096, "geometry": {"type": "Point", "coordinates": [-87.401314, 36.578499]}, "properties": {"woe:id": 23651096, "woe:parent_id": 2380893, "woe:name": "Kenwood Middle School", "woe:placetype": 20, "woe:placetype_name": "POI", "woe:lang": "ENG", "iso:country": "US", "meta:provider": ["geoplanet:7.3.1", "geoplanet:7.3.2", "geoplanet:7.4.0", "geoplanet:7.4.1", "geoplanet:7.5.1", "geoplanet:7.5.2", "geoplanet:7.6.0", "geoplanet:7.8.1", "geoplanet:7.9.0", "geoplanet:7.10.0", "geoplanet:8.0.0", "woeplanet:8.0.0"], "meta:indexed": "2020-08-20T20:19:01.990982", "meta:updated": "2020-10-14T11:19:33.305374", "woe:hierarchy": {"continent": 24865672, "country": 23424977, "town": 0, "planet": 1, "county": 12589974, "suburb": 0, "state": 2347601, "region": 0, "localadmin": 0}, "woe:timezone_id": 56043661, "woe:hash": "dn9b54um1y2t", "woe:centroid": [-87.401314, 36.578499], "geom:latitude": 36.578499, "geom:longitude": -87.401314, "geom:hash": "dn9b54um1y2t", "woe:latitude": 36.578499, "geom:centroid": [-87.401314, 36.578499], "woe:longitude": -87.401314, "woe:repo": "woeplanet-poi-us", "geom:area": 0.0, "woe:scale": 19}}