{"type": "Feature", "id": 23626957, "properties": {"woe:id": 23626957, "woe:parent_id": 2370983, "woe:name": "Pingree-buchanan Elementary School", "woe:placetype": 20, "woe:placetype_name": "POI", "woe:lang": "ENG", "iso:country": "US", "meta:provider": ["geoplanet:7.3.1", "geoplanet:7.3.2", "geoplanet:7.4.0", "geoplanet:7.4.1", "geoplanet:7.5.1", "geoplanet:7.5.2", "geoplanet:7.6.0", "geoplanet:7.8.1", "geoplanet:7.9.0", "geoplanet:7.10.0", "geoplanet:8.0.0", "woeplanet:8.0.0"], "meta:indexed": "2020-08-20T20:18:53.084337", "woe:alias_ENG_V": ["Pingree-buchanan Elementary"], "meta:updated": "2020-08-22T02:57:44.605515", "woe:hierarchy": {"continent": 24865672, "country": 23424977, "town": 0, "planet": 1, "county": 12589520, "suburb": 0, "state": 2347593, "region": 0, "localadmin": 0}, "woe:timezone_id": 56043661, "woe:hash": "cb3exp7nsd7x", "woe:centroid": [-98.82869, 47.062439], "geom:latitude": 47.062439, "geom:longitude": -98.82869, "geom:hash": "cb3exp7nsd7x", "woe:latitude": 47.062439, "geom:centroid": [-98.82869, 47.062439], "woe:longitude": -98.82869, "woe:repo": "woeplanet-poi-us"}, "geometry": {"coordinates": [-98.82869, 47.062439], "type": "Point"}}