{"type": "Feature", "id": 23551745, "properties": {"woe:id": 23551745, "woe:parent_id": 2378691, "woe:name": "Eastvalley Elementary School", "woe:placetype": 20, "woe:placetype_name": "POI", "woe:lang": "ENG", "iso:country": "US", "meta:provider": ["geoplanet:7.3.2", "geoplanet:7.4.0", "geoplanet:7.4.1", "geoplanet:7.5.1", "geoplanet:7.5.2", "geoplanet:7.6.0", "geoplanet:7.8.1", "geoplanet:7.9.0", "geoplanet:7.10.0", "geoplanet:8.0.0", "woeplanet:8.0.0"], "meta:indexed": "2020-08-20T22:02:10.999018", "woe:alias_ENG_V": ["Eastvalley Elementary"], "meta:updated": "2020-08-22T02:57:32.868690", "woe:hierarchy": {"continent": 24865672, "country": 23424977, "town": 0, "planet": 1, "county": 12587902, "suburb": 0, "state": 2347569, "region": 0, "localadmin": 0}, "woe:timezone_id": 56043648, "woe:hash": "dn5cjejjjrfd", "woe:centroid": [-84.477768, 33.943161], "geom:latitude": 33.943161, "geom:longitude": -84.477768, "geom:hash": "dn5cjejjjrfd", "woe:latitude": 33.943161, "geom:centroid": [-84.477768, 33.943161], "woe:longitude": -84.477768, "woe:repo": "woeplanet-poi-us"}, "geometry": {"coordinates": [-84.477768, 33.943161], "type": "Point"}}