{"type": "Feature", "id": 23586527, "geometry": {"type": "Point", "coordinates": [-84.736473, 42.24514]}, "properties": {"woe:id": 23586527, "woe:parent_id": 2358076, "woe:name": "Harrington School", "woe:placetype": 20, "woe:placetype_name": "POI", "woe:lang": "ENG", "iso:country": "US", "meta:provider": ["geoplanet:7.3.1", "geoplanet:7.3.2", "geoplanet:7.4.0", "geoplanet:7.4.1", "geoplanet:7.5.1", "geoplanet:7.5.2", "geoplanet:7.6.0", "geoplanet:7.8.1", "geoplanet:7.9.0", "geoplanet:7.10.0", "geoplanet:8.0.0", "woeplanet:8.0.0"], "meta:indexed": "2020-08-20T20:18:40.009871", "meta:updated": "2020-10-14T11:20:19.560361", "woe:hierarchy": {"continent": 24865672, "country": 23424977, "town": 0, "planet": 1, "county": 12588726, "suburb": 0, "state": 2347581, "region": 0, "localadmin": 0}, "woe:timezone_id": 56043658, "woe:hash": "dpe8rf2zc0f5", "woe:centroid": [-84.736473, 42.24514], "geom:latitude": 42.24514, "geom:longitude": -84.736473, "geom:hash": "dpe8rf2zc0f5", "woe:latitude": 42.24514, "geom:centroid": [-84.736473, 42.24514], "woe:longitude": -84.736473, "woe:repo": "woeplanet-poi-us", "geom:area": 0.0, "woe:scale": 19}}