{"type": "Feature", "id": 23539382, "geometry": {"type": "Point", "coordinates": [-105.232368, 40.006451]}, "properties": {"woe:id": 23539382, "woe:parent_id": 55858125, "woe:name": "Sage Elementary School", "woe:placetype": 20, "woe:placetype_name": "POI", "woe:lang": "ENG", "iso:country": "US", "meta:provider": ["geoplanet:7.3.1", "geoplanet:7.3.2", "geoplanet:7.4.0", "geoplanet:7.4.1", "geoplanet:7.5.1", "geoplanet:7.5.2", "geoplanet:7.6.0", "geoplanet:7.8.1", "geoplanet:7.9.0", "geoplanet:7.10.0", "geoplanet:8.0.0", "woeplanet:8.0.0"], "meta:indexed": "2020-08-20T20:18:24.124745", "woe:alias_ENG_V": ["Sage Elementary"], "meta:updated": "2020-10-14T11:20:16.161275", "woe:hierarchy": {"continent": 24865672, "country": 23424977, "town": 0, "planet": 1, "county": 12587734, "suburb": 0, "state": 2347564, "region": 0, "localadmin": 0}, "woe:timezone_id": 56043665, "woe:hash": "9xj5t6unkngp", "woe:centroid": [-105.232368, 40.006451], "geom:latitude": 40.006451, "geom:longitude": -105.232368, "geom:hash": "9xj5t6unkngp", "woe:latitude": 40.006451, "geom:centroid": [-105.232368, 40.006451], "woe:longitude": -105.232368, "woe:repo": "woeplanet-poi-us", "geom:area": 0.0, "woe:scale": 19}}