{"type": "Feature", "id": 23571825, "properties": {"woe:id": 23571825, "woe:parent_id": 2466942, "woe:name": "Prairie Star Middle School", "woe:placetype": 20, "woe:placetype_name": "POI", "woe:lang": "ENG", "iso:country": "US", "meta:provider": ["geoplanet:7.3.1", "geoplanet:7.3.2", "geoplanet:7.4.0", "geoplanet:7.4.1", "geoplanet:7.5.1", "geoplanet:7.5.2", "geoplanet:7.6.0", "geoplanet:7.8.1", "geoplanet:7.9.0", "geoplanet:7.10.0", "geoplanet:8.0.0", "woeplanet:8.0.0"], "meta:indexed": "2020-08-20T20:18:36.094687", "meta:updated": "2020-08-22T02:57:36.547589", "woe:hierarchy": {"continent": 24865672, "country": 23424977, "town": 0, "planet": 1, "county": 12588416, "suburb": 0, "state": 2347575, "region": 0, "localadmin": 0}, "woe:timezone_id": 56043661, "woe:hash": "9yutnskjf80h", "woe:centroid": [-94.63063, 38.87199], "geom:latitude": 38.87199, "geom:longitude": -94.63063, "geom:hash": "9yutnskjf80h", "woe:latitude": 38.87199, "geom:centroid": [-94.63063, 38.87199], "woe:longitude": -94.63063, "woe:repo": "woeplanet-poi-us"}, "geometry": {"coordinates": [-94.63063, 38.87199], "type": "Point"}}