{"type": "Feature", "id": 23639580, "geometry": {"type": "Point", "coordinates": [-79.792381, 41.08997]}, "properties": {"woe:id": 23639580, "woe:parent_id": 28744540, "woe:name": "Washington Elementary School", "woe:placetype": 20, "woe:placetype_name": "POI", "woe:lang": "ENG", "iso:country": "US", "meta:provider": ["geoplanet:7.3.1", "geoplanet:7.3.2", "geoplanet:7.4.0", "geoplanet:7.4.1", "geoplanet:7.5.1", "geoplanet:7.5.2", "geoplanet:7.6.0", "geoplanet:7.8.1", "geoplanet:7.9.0", "geoplanet:7.10.0", "geoplanet:8.0.0", "woeplanet:8.0.0"], "meta:indexed": "2020-08-20T20:18:58.266041", "woe:alias_ENG_V": ["Washington Elementary"], "meta:updated": "2020-10-14T11:19:32.597449", "woe:hierarchy": {"continent": 24865672, "country": 23424977, "town": 0, "planet": 1, "county": 12589737, "suburb": 0, "state": 2347597, "region": 0, "localadmin": 0}, "woe:timezone_id": 56043648, "woe:hash": "dpr3b20yqv86", "woe:centroid": [-79.792381, 41.08997], "geom:latitude": 41.08997, "geom:longitude": -79.792381, "geom:hash": "dpr3b20yqv86", "woe:latitude": 41.08997, "geom:centroid": [-79.792381, 41.08997], "woe:longitude": -79.792381, "woe:repo": "woeplanet-poi-us", "geom:area": 0.0, "woe:scale": 19}}