{"type": "Feature", "id": 23534308, "properties": {"woe:id": 23534308, "woe:parent_id": 2507523, "woe:name": "Trabuco Elementary School", "woe:placetype": 20, "woe:placetype_name": "POI", "woe:lang": "ENG", "iso:country": "US", "meta:provider": ["geoplanet:7.3.1", "geoplanet:7.3.2", "geoplanet:7.4.0", "geoplanet:7.4.1", "geoplanet:7.5.1", "geoplanet:7.5.2", "geoplanet:7.6.0", "geoplanet:7.8.1", "geoplanet:7.9.0", "geoplanet:7.10.0", "geoplanet:8.0.0", "woeplanet:8.0.0"], "meta:indexed": "2020-08-20T20:18:22.727555", "woe:alias_ENG_V": ["Trabuco Elementary"], "meta:updated": "2020-08-22T02:57:29.434304", "woe:hierarchy": {"continent": 24865672, "country": 23424977, "town": 0, "planet": 1, "county": 12587699, "suburb": 0, "state": 2347563, "region": 0, "localadmin": 0}, "woe:timezone_id": 56043663, "woe:hash": "9murkpw2mhsy", "woe:centroid": [-117.588852, 33.659431], "geom:latitude": 33.659431, "geom:longitude": -117.588852, "geom:hash": "9murkpw2mhsy", "woe:latitude": 33.659431, "geom:centroid": [-117.588852, 33.659431], "woe:longitude": -117.588852, "woe:repo": "woeplanet-poi-us"}, "geometry": {"coordinates": [-117.588852, 33.659431], "type": "Point"}}