{"type": "Feature", "id": 23607722, "geometry": {"type": "Point", "coordinates": [-75.095573, 39.924339]}, "properties": {"woe:id": 23607722, "woe:parent_id": 2468672, "woe:name": "Brimm Medical Arts High School", "woe:placetype": 20, "woe:placetype_name": "POI", "woe:lang": "ENG", "iso:country": "US", "meta:provider": ["geoplanet:7.3.2", "geoplanet:7.4.0", "geoplanet:7.4.1", "geoplanet:7.5.1", "geoplanet:7.5.2", "geoplanet:7.6.0", "geoplanet:7.8.1", "geoplanet:7.9.0", "geoplanet:7.10.0", "geoplanet:8.0.0", "woeplanet:8.0.0"], "meta:indexed": "2020-08-20T22:02:33.379616", "woe:alias_ENG_V": ["Brimm Medical Arts Senior High School", "Brimm Medical Arts High", "Brimm Medical Arts Senior High", "Brimm Medical Arts HS", "Brimm Medical Arts Senior HS"], "meta:updated": "2020-10-14T11:19:35.661359", "woe:hierarchy": {"continent": 24865672, "country": 23424977, "town": 0, "planet": 1, "county": 12589261, "suburb": 0, "state": 2347589, "region": 0, "localadmin": 0}, "woe:timezone_id": 56043648, "woe:hash": "dr4e5hj04k4q", "woe:centroid": [-75.095573, 39.924339], "geom:latitude": 39.924339, "geom:longitude": -75.095573, "geom:hash": "dr4e5hj04k4q", "woe:latitude": 39.924339, "geom:centroid": [-75.095573, 39.924339], "woe:longitude": -75.095573, "woe:repo": "woeplanet-poi-us", "geom:area": 0.0, "woe:scale": 19}}