{"type": "Feature", "id": 23597549, "geometry": {"type": "Point", "coordinates": [-90.071709, 36.238899]}, "properties": {"woe:id": 23597549, "woe:parent_id": 2431569, "woe:name": "Kennett Area Vocational School", "woe:placetype": 20, "woe:placetype_name": "POI", "woe:lang": "ENG", "iso:country": "US", "meta:provider": ["geoplanet:7.3.1", "geoplanet:7.3.2", "geoplanet:7.4.0", "geoplanet:7.4.1", "geoplanet:7.5.1", "geoplanet:7.5.2", "geoplanet:7.6.0", "geoplanet:7.8.1", "geoplanet:7.9.0", "geoplanet:7.10.0", "geoplanet:8.0.0", "woeplanet:8.0.0"], "meta:indexed": "2020-08-20T20:18:43.918594", "meta:updated": "2020-10-14T11:20:25.514237", "woe:hierarchy": {"continent": 24865672, "country": 23424977, "town": 0, "planet": 1, "county": 12589000, "suburb": 0, "state": 2347584, "region": 0, "localadmin": 0}, "woe:timezone_id": 56043661, "woe:hash": "9yrynm5fch3u", "woe:centroid": [-90.071709, 36.238899], "geom:latitude": 36.238899, "geom:longitude": -90.071709, "geom:hash": "9yrynm5fch3u", "woe:latitude": 36.238899, "geom:centroid": [-90.071709, 36.238899], "woe:longitude": -90.071709, "woe:repo": "woeplanet-poi-us", "geom:area": 0.0, "woe:scale": 19}}