{"type": "Feature", "id": 23670873, "geometry": {"type": "Point", "coordinates": [-121.557831, 47.81987]}, "properties": {"woe:id": 23670873, "woe:parent_id": 2426750, "woe:name": "Index Elementary School", "woe:placetype": 20, "woe:placetype_name": "POI", "woe:lang": "ENG", "iso:country": "US", "meta:provider": ["geoplanet:7.3.1", "geoplanet:7.3.2", "geoplanet:7.4.0", "geoplanet:7.4.1", "geoplanet:7.5.1", "geoplanet:7.5.2", "geoplanet:7.6.0", "geoplanet:7.8.1", "geoplanet:7.9.0", "geoplanet:7.10.0", "geoplanet:8.0.0", "woeplanet:8.0.0"], "meta:indexed": "2020-08-20T20:19:09.751285", "woe:alias_ENG_V": ["Index Elementary"], "meta:updated": "2020-10-14T11:19:30.560746", "woe:hierarchy": {"continent": 24865672, "country": 23424977, "town": 0, "planet": 1, "county": 12590470, "suburb": 0, "state": 2347606, "region": 0, "localadmin": 0}, "woe:timezone_id": 56043663, "woe:hash": "c2981ck6cjze", "woe:centroid": [-121.557831, 47.81987], "geom:latitude": 47.81987, "geom:longitude": -121.557831, "geom:hash": "c2981ck6cjze", "woe:latitude": 47.81987, "geom:centroid": [-121.557831, 47.81987], "woe:longitude": -121.557831, "woe:repo": "woeplanet-poi-us", "geom:area": 0.0, "woe:scale": 19}}