{"type": "Feature", "id": 23674958, "properties": {"woe:id": 23674958, "woe:parent_id": 2462704, "woe:name": "Oak Creek High School", "woe:placetype": 20, "woe:placetype_name": "POI", "woe:lang": "ENG", "iso:country": "US", "meta:provider": ["geoplanet:7.3.1", "geoplanet:7.3.2", "geoplanet:7.4.0", "geoplanet:7.4.1", "geoplanet:7.5.1", "geoplanet:7.5.2", "geoplanet:7.6.0", "geoplanet:7.8.1", "geoplanet:7.9.0", "geoplanet:7.10.0", "geoplanet:8.0.0", "woeplanet:8.0.0"], "meta:indexed": "2020-08-20T20:19:11.288853", "woe:alias_ENG_V": ["Oak Creek Senior High School", "Oak Creek High", "Oak Creek Senior High", "Oak Creek HS", "Oak Creek Senior HS"], "meta:updated": "2020-08-22T02:58:50.491954", "woe:hierarchy": {"continent": 24865672, "country": 23424977, "town": 0, "planet": 1, "county": 12590574, "suburb": 0, "state": 2347608, "region": 0, "localadmin": 0}, "woe:timezone_id": 56043661, "woe:hash": "dp97zx78x71m", "woe:centroid": [-87.907478, 42.886608], "geom:latitude": 42.886608, "geom:longitude": -87.907478, "geom:hash": "dp97zx78x71m", "woe:latitude": 42.886608, "geom:centroid": [-87.907478, 42.886608], "woe:longitude": -87.907478, "woe:repo": "woeplanet-poi-us"}, "geometry": {"coordinates": [-87.907478, 42.886608], "type": "Point"}}