{"type": "Feature", "id": 23544789, "geometry": {"type": "Point", "coordinates": [-75.542648, 39.745708]}, "properties": {"woe:id": 23544789, "woe:parent_id": 28338026, "woe:name": "Howard High School of Technology", "woe:placetype": 20, "woe:placetype_name": "POI", "woe:lang": "ENG", "iso:country": "US", "meta:provider": ["geoplanet:7.3.1", "geoplanet:7.3.2", "geoplanet:7.4.0", "geoplanet:7.4.1", "geoplanet:7.5.1", "geoplanet:7.5.2", "geoplanet:7.6.0", "geoplanet:7.8.1", "geoplanet:7.9.0", "geoplanet:7.10.0", "geoplanet:8.0.0", "woeplanet:8.0.0"], "meta:indexed": "2020-08-20T20:18:25.707196", "meta:updated": "2020-10-14T11:20:26.265043", "woe:alias_ENG_V": ["Howard Senior High of Technology", "Howard High School of Technology", "Howard High of Technology", "Howard Senior HS of Technology", "Howard HS of Technology"], "woe:hierarchy": {"continent": 24865672, "country": 23424977, "town": 0, "planet": 1, "county": 12587800, "suburb": 0, "state": 2347566, "region": 0, "localadmin": 0}, "woe:timezone_id": 56043648, "woe:hash": "dr460grx88yz", "woe:centroid": [-75.542648, 39.745708], "geom:latitude": 39.745708, "geom:longitude": -75.542648, "geom:hash": "dr460grx88yz", "woe:latitude": 39.745708, "geom:centroid": [-75.542648, 39.745708], "woe:longitude": -75.542648, "woe:repo": "woeplanet-poi-us", "geom:area": 0.0, "woe:scale": 19}}