{"type": "Feature", "id": 23683361, "geometry": {"type": "Point", "coordinates": [-75.256561, 40.184399]}, "properties": {"woe:id": 23683361, "woe:parent_id": 2415825, "woe:name": "Gwynedd Valley Station", "woe:placetype": 20, "woe:placetype_name": "POI", "woe:lang": "ENG", "iso:country": "US", "meta:provider": ["geoplanet:7.3.1", "geoplanet:7.3.2", "geoplanet:7.4.0", "geoplanet:7.4.1", "geoplanet:7.5.1", "geoplanet:7.5.2", "geoplanet:7.6.0", "geoplanet:7.8.1", "geoplanet:7.9.0", "geoplanet:7.10.0", "geoplanet:8.0.0", "woeplanet:8.0.0"], "meta:indexed": "2020-08-20T20:19:20.239977", "woe:alias_ENG_V": ["Gwynedd Valley SEPTA Station", "SEPTA Gwynedd Valley Station", "Septa R5-Gwynedd Valley"], "meta:updated": "2020-10-14T11:19:50.858858", "woe:hierarchy": {"continent": 24865672, "country": 23424977, "town": 0, "planet": 1, "county": 12589773, "suburb": 0, "state": 2347597, "region": 0, "localadmin": 0}, "woe:timezone_id": 56043648, "woe:hash": "dr4kx7rg54bv", "woe:centroid": [-75.256561, 40.184399], "geom:latitude": 40.184399, "geom:longitude": -75.256561, "geom:hash": "dr4kx7rg54bv", "woe:latitude": 40.184399, "geom:centroid": [-75.256561, 40.184399], "woe:longitude": -75.256561, "woe:repo": "woeplanet-poi-us", "geom:area": 0.0, "woe:scale": 19}}