{"type": "Feature", "id": 24866205, "properties": {"woe:id": 24866205, "woe:parent_id": 2390624, "woe:name": "Defiance College", "woe:placetype": 20, "woe:placetype_name": "POI", "woe:lang": "ENG", "iso:country": "US", "meta:provider": ["geoplanet:7.3.1", "geoplanet:7.3.2", "geoplanet:7.4.0", "geoplanet:7.4.1", "geoplanet:7.5.1", "geoplanet:7.5.2", "geoplanet:7.6.0", "geoplanet:7.8.1", "geoplanet:7.9.0", "geoplanet:7.10.0", "geoplanet:8.0.0", "woeplanet:8.0.0"], "meta:indexed": "2020-08-20T20:19:14.951493", "meta:updated": "2020-08-22T02:58:19.699188", "woe:hierarchy": {"continent": 24865672, "country": 23424977, "town": 0, "planet": 1, "county": 12589546, "suburb": 0, "state": 2347594, "region": 0, "localadmin": 0}, "woe:timezone_id": 56043648, "woe:hash": "dpk4bmdkd3p9", "woe:centroid": [-84.360817, 41.295639], "geom:latitude": 41.295639, "geom:longitude": -84.360817, "geom:hash": "dpk4bmdkd3p9", "woe:latitude": 41.295639, "geom:centroid": [-84.360817, 41.295639], "woe:longitude": -84.360817, "woe:repo": "woeplanet-poi-us"}, "geometry": {"coordinates": [-84.360817, 41.295639], "type": "Point"}}