{"type": "Feature", "id": 23682974, "properties": {"woe:id": 23682974, "woe:parent_id": 23511871, "woe:name": "121st Street Station", "woe:placetype": 20, "woe:placetype_name": "POI", "woe:lang": "ENG", "iso:country": "US", "meta:provider": ["geoplanet:7.3.1", "geoplanet:7.3.2", "geoplanet:7.4.0", "geoplanet:7.4.1", "geoplanet:7.5.1", "geoplanet:7.5.2", "geoplanet:7.6.0", "geoplanet:7.8.1", "geoplanet:7.9.0", "geoplanet:7.10.0", "geoplanet:8.0.0", "woeplanet:8.0.0"], "meta:indexed": "2020-08-20T20:19:20.026173", "woe:alias_ENG_V": ["Mta-121st St", "121st Street Subway Station", "Subway-121st St-J,z"], "meta:updated": "2020-08-22T02:58:22.576481", "woe:hierarchy": {"continent": 24865672, "country": 23424977, "town": 0, "planet": 1, "county": 12589352, "suburb": 0, "state": 2347591, "region": 0, "localadmin": 0}, "woe:timezone_id": 56043648, "woe:hash": "dr5rxcr8cby6", "woe:centroid": [-73.828728, 40.700359], "geom:latitude": 40.700359, "geom:longitude": -73.828728, "geom:hash": "dr5rxcr8cby6", "woe:latitude": 40.700359, "geom:centroid": [-73.828728, 40.700359], "woe:longitude": -73.828728, "woe:repo": "woeplanet-poi-us"}, "geometry": {"coordinates": [-73.828728, 40.700359], "type": "Point"}}