{"type": "Feature", "id": 23610636, "properties": {"woe:id": 23610636, "woe:parent_id": 2398316, "woe:name": "Number 18 Robert Morris Elementary School", "woe:placetype": 20, "woe:placetype_name": "POI", "woe:lang": "ENG", "iso:country": "US", "meta:provider": ["geoplanet:7.3.1", "geoplanet:7.3.2", "geoplanet:7.4.0", "geoplanet:7.4.1", "geoplanet:7.5.1", "geoplanet:7.5.2", "geoplanet:7.6.0", "geoplanet:7.8.1", "geoplanet:7.9.0", "geoplanet:7.10.0", "geoplanet:8.0.0", "woeplanet:8.0.0"], "meta:indexed": "2020-08-20T20:19:16.079792", "woe:alias_ENG_V": ["Number 18, Robert Morris Elementary School", "Number 18, Robert Morris Elementary"], "meta:updated": "2020-08-22T02:58:20.277865", "woe:hierarchy": {"continent": 24865672, "country": 23424977, "town": 0, "planet": 1, "county": 12589277, "suburb": 0, "state": 2347589, "region": 0, "localadmin": 0}, "woe:timezone_id": 56043648, "woe:hash": "dr5prq1w9vcp", "woe:centroid": [-74.21051, 40.683521], "geom:latitude": 40.683521, "geom:longitude": -74.21051, "geom:hash": "dr5prq1w9vcp", "woe:latitude": 40.683521, "geom:centroid": [-74.21051, 40.683521], "woe:longitude": -74.21051, "woe:repo": "woeplanet-poi-us"}, "geometry": {"coordinates": [-74.21051, 40.683521], "type": "Point"}}