{"type": "Feature", "id": 23660790, "geometry": {"type": "Point", "coordinates": [-93.820862, 30.038919]}, "properties": {"woe:id": 23660790, "woe:parent_id": 2368872, "woe:name": "Bridge City High School", "woe:placetype": 20, "woe:placetype_name": "POI", "woe:lang": "ENG", "iso:country": "US", "meta:provider": ["geoplanet:7.3.1", "geoplanet:7.3.2", "geoplanet:7.4.0", "geoplanet:7.4.1", "geoplanet:7.5.1", "geoplanet:7.5.2", "geoplanet:7.6.0", "geoplanet:7.8.1", "geoplanet:7.9.0", "geoplanet:7.10.0", "geoplanet:8.0.0", "woeplanet:8.0.0"], "meta:indexed": "2020-08-20T20:19:06.621340", "woe:alias_ENG_V": ["Bridge City Senior High School", "Bridge City High", "Bridge City Senior High", "Bridge City HS", "Bridge City Senior HS"], "meta:updated": "2020-10-14T11:19:40.307472", "woe:hierarchy": {"continent": 24865672, "country": 23424977, "town": 0, "planet": 1, "county": 12590187, "suburb": 0, "state": 2347602, "region": 0, "localadmin": 0}, "woe:timezone_id": 56043661, "woe:hash": "9vm6ch3trkqg", "woe:centroid": [-93.820862, 30.038919], "geom:latitude": 30.038919, "geom:longitude": -93.820862, "geom:hash": "9vm6ch3trkqg", "woe:latitude": 30.038919, "geom:centroid": [-93.820862, 30.038919], "woe:longitude": -93.820862, "woe:repo": "woeplanet-poi-us", "geom:area": 0.0, "woe:scale": 19}}