{"type": "Feature", "id": 23660108, "geometry": {"type": "Point", "coordinates": [-98.230057, 26.20974]}, "properties": {"woe:id": 23660108, "woe:parent_id": 2447466, "woe:name": "Our Lady of Sorrows School", "woe:placetype": 20, "woe:placetype_name": "POI", "woe:lang": "ENG", "iso:country": "US", "meta:provider": ["geoplanet:7.3.1", "geoplanet:7.3.2", "geoplanet:7.4.0", "geoplanet:7.4.1", "geoplanet:7.5.1", "geoplanet:7.5.2", "geoplanet:7.6.0", "geoplanet:7.8.1", "geoplanet:7.9.0", "geoplanet:7.10.0", "geoplanet:8.0.0", "woeplanet:8.0.0"], "meta:indexed": "2020-08-20T20:19:06.303878", "meta:updated": "2020-10-14T11:19:50.383091", "woe:hierarchy": {"continent": 24865672, "country": 23424977, "town": 0, "planet": 1, "county": 12590114, "suburb": 0, "state": 2347602, "region": 0, "localadmin": 0}, "woe:timezone_id": 56043661, "woe:hash": "9udjher4cc8t", "woe:centroid": [-98.230057, 26.20974], "geom:latitude": 26.20974, "geom:longitude": -98.230057, "geom:hash": "9udjher4cc8t", "woe:latitude": 26.20974, "geom:centroid": [-98.230057, 26.20974], "woe:longitude": -98.230057, "woe:repo": "woeplanet-poi-us", "geom:area": 0.0, "woe:scale": 19}}