{"type": "Feature", "id": 23598719, "geometry": {"type": "Point", "coordinates": [-93.09832, 39.78788]}, "properties": {"woe:id": 23598719, "woe:parent_id": 2369839, "woe:name": "Brookfield High School", "woe:placetype": 20, "woe:placetype_name": "POI", "woe:lang": "ENG", "iso:country": "US", "meta:provider": ["geoplanet:7.3.2", "geoplanet:7.4.0", "geoplanet:7.4.1", "geoplanet:7.5.1", "geoplanet:7.5.2", "geoplanet:7.6.0", "geoplanet:7.8.1", "geoplanet:7.9.0", "geoplanet:7.10.0", "geoplanet:8.0.0", "woeplanet:8.0.0"], "meta:indexed": "2020-08-20T22:02:30.489270", "woe:alias_ENG_V": ["Brookfield Senior High School", "Brookfield High", "Brookfield Senior High", "Brookfield HS", "Brookfield Senior HS"], "meta:updated": "2020-10-14T11:20:05.388514", "woe:hierarchy": {"continent": 24865672, "country": 23424977, "town": 0, "planet": 1, "county": 12589023, "suburb": 0, "state": 2347584, "region": 0, "localadmin": 0}, "woe:timezone_id": 56043661, "woe:hash": "9zjf37pv5ymj", "woe:centroid": [-93.09832, 39.78788], "geom:latitude": 39.78788, "geom:longitude": -93.09832, "geom:hash": "9zjf37pv5ymj", "woe:latitude": 39.78788, "geom:centroid": [-93.09832, 39.78788], "woe:longitude": -93.09832, "woe:repo": "woeplanet-poi-us", "geom:area": 0.0, "woe:scale": 19}}