{"type": "Feature", "id": 23589774, "properties": {"woe:id": 23589774, "woe:parent_id": 56021802, "woe:name": "Schroeder Elementary School", "woe:placetype": 20, "woe:placetype_name": "POI", "woe:lang": "ENG", "iso:country": "US", "meta:provider": ["geoplanet:7.3.2", "geoplanet:7.4.0", "geoplanet:7.4.1", "geoplanet:7.5.1", "geoplanet:7.5.2", "geoplanet:7.6.0", "geoplanet:7.8.1", "geoplanet:7.9.0", "geoplanet:7.10.0", "geoplanet:8.0.0", "woeplanet:8.0.0"], "meta:indexed": "2020-08-20T22:02:26.635913", "woe:alias_ENG_V": ["Schroeder Elementary"], "meta:updated": "2020-08-22T02:57:39.363940", "woe:hierarchy": {"continent": 24865672, "country": 23424977, "town": 0, "planet": 1, "county": 12588776, "suburb": 0, "state": 2347581, "region": 0, "localadmin": 0}, "woe:timezone_id": 56043658, "woe:hash": "dpsf4vmhhf1y", "woe:centroid": [-83.19239, 42.5686], "geom:latitude": 42.5686, "geom:longitude": -83.19239, "geom:hash": "dpsf4vmhhf1y", "woe:latitude": 42.5686, "geom:centroid": [-83.19239, 42.5686], "woe:longitude": -83.19239, "woe:repo": "woeplanet-poi-us"}, "geometry": {"coordinates": [-83.19239, 42.5686], "type": "Point"}}