{"type": "Feature", "id": 23552401, "properties": {"woe:id": 23552401, "woe:parent_id": 2364243, "woe:name": "Alexander High School", "woe:placetype": 20, "woe:placetype_name": "POI", "woe:lang": "ENG", "iso:country": "US", "meta:provider": ["geoplanet:7.3.2", "geoplanet:7.4.0", "geoplanet:7.4.1", "geoplanet:7.5.1", "geoplanet:7.5.2", "geoplanet:7.6.0", "geoplanet:7.8.1", "geoplanet:7.9.0", "geoplanet:7.10.0", "geoplanet:8.0.0", "woeplanet:8.0.0"], "meta:indexed": "2020-08-20T22:02:11.332144", "woe:alias_ENG_V": ["Alexander Senior High School", "Alexander High", "Alexander Senior High", "Alexander HS", "Alexander Senior HS"], "meta:updated": "2020-08-22T02:58:46.852636", "woe:hierarchy": {"continent": 24865672, "country": 23424977, "town": 0, "planet": 1, "county": 12587917, "suburb": 0, "state": 2347569, "region": 0, "localadmin": 0}, "woe:timezone_id": 56043648, "woe:hash": "djgxw78zkgr7", "woe:centroid": [-84.802223, 33.682598], "geom:latitude": 33.682598, "geom:longitude": -84.802223, "geom:hash": "djgxw78zkgr7", "woe:latitude": 33.682598, "geom:centroid": [-84.802223, 33.682598], "woe:longitude": -84.802223, "woe:repo": "woeplanet-poi-us"}, "geometry": {"coordinates": [-84.802223, 33.682598], "type": "Point"}}