{"type": "Feature", "id": 23666624, "properties": {"woe:id": 23666624, "woe:parent_id": 2351607, "woe:name": "Abingdon High School", "woe:placetype": 20, "woe:placetype_name": "POI", "woe:lang": "ENG", "iso:country": "US", "meta:provider": ["geoplanet:7.3.2", "geoplanet:7.4.0", "geoplanet:7.4.1", "geoplanet:7.5.1", "geoplanet:7.5.2", "geoplanet:7.6.0", "geoplanet:7.8.1", "geoplanet:7.9.0", "geoplanet:7.10.0", "geoplanet:8.0.0", "woeplanet:8.0.0"], "meta:indexed": "2020-08-20T22:02:58.679502", "woe:alias_ENG_V": ["Abingdon Senior High School", "Abingdon High", "Abingdon Senior High", "Abingdon HS", "Abingdon Senior HS"], "meta:updated": "2020-08-22T02:58:50.208895", "woe:hierarchy": {"continent": 24865672, "country": 23424977, "town": 0, "planet": 1, "county": 12590432, "suburb": 0, "state": 2347605, "region": 0, "localadmin": 0}, "woe:timezone_id": 56043648, "woe:hash": "dnt8zhdqynx1", "woe:centroid": [-81.954651, 36.720249], "geom:latitude": 36.720249, "geom:longitude": -81.954651, "geom:hash": "dnt8zhdqynx1", "woe:latitude": 36.720249, "geom:centroid": [-81.954651, 36.720249], "woe:longitude": -81.954651, "woe:repo": "woeplanet-poi-us"}, "geometry": {"coordinates": [-81.954651, 36.720249], "type": "Point"}}