{"type": "Feature", "id": 23585107, "geometry": {"type": "Point", "coordinates": [-71.027618, 42.106602]}, "properties": {"woe:id": 23585107, "woe:parent_id": 2453246, "woe:name": "South Shore Christian School", "woe:placetype": 20, "woe:placetype_name": "POI", "woe:lang": "ENG", "iso:country": "US", "meta:provider": ["geoplanet:7.3.1", "geoplanet:7.3.2", "geoplanet:7.4.0", "geoplanet:7.4.1", "geoplanet:7.5.1", "geoplanet:7.5.2", "geoplanet:7.6.0", "geoplanet:7.8.1", "geoplanet:7.9.0", "geoplanet:7.10.0", "geoplanet:8.0.0", "woeplanet:8.0.0"], "meta:indexed": "2020-08-20T20:18:39.642011", "woe:alias_ENG_V": ["S Shore Christian School"], "meta:updated": "2020-10-14T11:20:24.122688", "woe:hierarchy": {"continent": 24865672, "country": 23424977, "town": 0, "planet": 1, "county": 12588711, "suburb": 0, "state": 2347580, "region": 0, "localadmin": 0}, "woe:timezone_id": 56043648, "woe:hash": "drmrx9r28x92", "woe:centroid": [-71.027618, 42.106602], "geom:latitude": 42.106602, "geom:longitude": -71.027618, "geom:hash": "drmrx9r28x92", "woe:latitude": 42.106602, "geom:centroid": [-71.027618, 42.106602], "woe:longitude": -71.027618, "woe:repo": "woeplanet-poi-us", "geom:area": 0.0, "woe:scale": 19}}