{"type": "Feature", "id": 23534071, "geometry": {"type": "Point", "coordinates": [-117.930443, 33.738159]}, "properties": {"woe:id": 23534071, "woe:parent_id": 55806589, "woe:name": "Stephen R. Fitz Intermediate School", "woe:placetype": 20, "woe:placetype_name": "POI", "woe:lang": "ENG", "iso:country": "US", "meta:provider": ["geoplanet:7.3.1", "geoplanet:7.3.2", "geoplanet:7.4.0", "geoplanet:7.4.1", "geoplanet:7.5.1", "geoplanet:7.5.2", "geoplanet:7.6.0", "geoplanet:7.8.1", "geoplanet:7.9.0", "geoplanet:7.10.0", "geoplanet:8.0.0", "woeplanet:8.0.0"], "meta:indexed": "2020-08-20T20:18:22.614481", "meta:updated": "2020-10-14T11:20:09.405432", "woe:alias_ENG_V": ["Fitz Intermediate School"], "woe:hierarchy": {"continent": 24865672, "country": 23424977, "town": 0, "planet": 1, "county": 12587699, "suburb": 0, "state": 2347563, "region": 0, "localadmin": 0}, "woe:timezone_id": 56043663, "woe:hash": "9mupumvej88j", "woe:centroid": [-117.930443, 33.738159], "geom:latitude": 33.738159, "geom:longitude": -117.930443, "geom:hash": "9mupumvej88j", "woe:latitude": 33.738159, "geom:centroid": [-117.930443, 33.738159], "woe:longitude": -117.930443, "woe:repo": "woeplanet-poi-us", "geom:area": 0.0, "woe:scale": 19}}