{"type": "Feature", "id": 23543683, "geometry": {"type": "Point", "coordinates": [-72.655968, 41.566292]}, "properties": {"woe:id": 23543683, "woe:parent_id": 2450408, "woe:name": "Macdonough School", "woe:placetype": 20, "woe:placetype_name": "POI", "woe:lang": "ENG", "iso:country": "US", "meta:provider": ["geoplanet:7.3.1", "geoplanet:7.3.2", "geoplanet:7.4.0", "geoplanet:7.4.1", "geoplanet:7.5.1", "geoplanet:7.5.2", "geoplanet:7.6.0", "geoplanet:7.8.1", "geoplanet:7.9.0", "geoplanet:7.10.0", "geoplanet:8.0.0", "woeplanet:8.0.0"], "meta:indexed": "2020-08-20T20:18:25.307913", "meta:updated": "2020-10-14T11:20:17.141196", "woe:alias_ENG_V": ["Commodore Macdonough Elementary Sch"], "woe:hierarchy": {"continent": 24865672, "country": 23424977, "town": 0, "planet": 1, "county": 12587794, "suburb": 0, "state": 2347565, "region": 0, "localadmin": 0}, "woe:timezone_id": 56043648, "woe:hash": "drkk6wvt1nrt", "woe:centroid": [-72.655968, 41.566292], "geom:latitude": 41.566292, "geom:longitude": -72.655968, "geom:hash": "drkk6wvt1nrt", "woe:latitude": 41.566292, "geom:centroid": [-72.655968, 41.566292], "woe:longitude": -72.655968, "woe:repo": "woeplanet-poi-us", "geom:area": 0.0, "woe:scale": 19}}