{"type": "Feature", "id": 23615824, "properties": {"woe:id": 23615824, "woe:parent_id": 2389061, "woe:name": "Keshequa Elementary School", "woe:placetype": 20, "woe:placetype_name": "POI", "woe:lang": "ENG", "iso:country": "US", "meta:provider": ["geoplanet:7.3.1", "geoplanet:7.3.2", "geoplanet:7.4.0", "geoplanet:7.4.1", "geoplanet:7.5.1", "geoplanet:7.5.2", "geoplanet:7.6.0", "geoplanet:7.8.1", "geoplanet:7.9.0", "geoplanet:7.10.0", "geoplanet:8.0.0", "woeplanet:8.0.0"], "meta:indexed": "2020-08-20T20:18:49.733684", "woe:alias_ENG_V": ["Keshequa Elementary"], "meta:updated": "2020-08-22T02:57:43.090169", "woe:hierarchy": {"continent": 24865672, "country": 23424977, "town": 0, "planet": 1, "county": 12589337, "suburb": 0, "state": 2347591, "region": 0, "localadmin": 0}, "woe:timezone_id": 56043648, "woe:hash": "dr8d4052xxks", "woe:centroid": [-77.954193, 42.539188], "geom:latitude": 42.539188, "geom:longitude": -77.954193, "geom:hash": "dr8d4052xxks", "woe:latitude": 42.539188, "geom:centroid": [-77.954193, 42.539188], "woe:longitude": -77.954193, "woe:repo": "woeplanet-poi-us"}, "geometry": {"coordinates": [-77.954193, 42.539188], "type": "Point"}}