{"type": "Feature", "id": 23623028, "geometry": {"type": "Point", "coordinates": [-76.224258, 36.302261]}, "properties": {"woe:id": 23623028, "woe:parent_id": 2398322, "woe:name": "Sheep-harney Elementary School", "woe:placetype": 20, "woe:placetype_name": "POI", "woe:lang": "ENG", "iso:country": "US", "meta:provider": ["geoplanet:7.3.2", "geoplanet:7.4.0", "geoplanet:7.4.1", "geoplanet:7.5.1", "geoplanet:7.5.2", "geoplanet:7.6.0", "geoplanet:7.8.1", "geoplanet:7.9.0", "geoplanet:7.10.0", "geoplanet:8.0.0", "woeplanet:8.0.0"], "meta:indexed": "2020-08-20T22:02:39.622968", "woe:alias_ENG_V": ["Sheep-harney Elementary"], "meta:updated": "2020-10-14T11:19:27.191352", "woe:hierarchy": {"continent": 24865672, "country": 23424977, "town": 0, "planet": 1, "county": 12589443, "suburb": 0, "state": 2347592, "region": 0, "localadmin": 0}, "woe:timezone_id": 56043648, "woe:hash": "dq3y92x5ypct", "woe:centroid": [-76.224258, 36.302261], "geom:latitude": 36.302261, "geom:longitude": -76.224258, "geom:hash": "dq3y92x5ypct", "woe:latitude": 36.302261, "geom:centroid": [-76.224258, 36.302261], "woe:longitude": -76.224258, "woe:repo": "woeplanet-poi-us", "geom:area": 0.0, "woe:scale": 19}}