{"type": "Feature", "id": 23555057, "properties": {"woe:id": 23555057, "woe:parent_id": 2434002, "woe:name": "Aina Haina Station", "woe:placetype": 20, "woe:placetype_name": "POI", "woe:lang": "ENG", "iso:country": "US", "meta:provider": ["geoplanet:7.3.1", "geoplanet:7.3.2", "geoplanet:7.4.0", "geoplanet:7.4.1", "geoplanet:7.5.1", "geoplanet:7.5.2", "geoplanet:7.6.0", "geoplanet:7.8.1", "geoplanet:7.9.0", "geoplanet:7.10.0", "geoplanet:8.0.0", "woeplanet:8.0.0"], "meta:indexed": "2020-08-20T20:18:30.063044", "meta:updated": "2020-08-22T02:57:33.531625", "woe:hierarchy": {"continent": 24865672, "country": 23424977, "town": 0, "planet": 1, "county": 12588030, "suburb": 0, "state": 2347570, "region": 0, "localadmin": 0}, "woe:timezone_id": 28350949, "woe:hash": "87zc41wp9n46", "woe:centroid": [-157.755386, 21.279091], "geom:latitude": 21.279091, "geom:longitude": -157.755386, "geom:hash": "87zc41wp9n46", "woe:latitude": 21.279091, "geom:centroid": [-157.755386, 21.279091], "woe:longitude": -157.755386, "woe:repo": "woeplanet-poi-us"}, "geometry": {"coordinates": [-157.755386, 21.279091], "type": "Point"}}