{"type": "Feature", "id": 23643658, "geometry": {"type": "Point", "coordinates": [-75.154533, 39.980541]}, "properties": {"woe:id": 23643658, "woe:parent_id": 2418346, "woe:name": "Temple University", "woe:placetype": 20, "woe:placetype_name": "POI", "woe:lang": "ENG", "iso:country": "US", "meta:provider": ["geoplanet:7.3.1", "geoplanet:7.3.2", "geoplanet:7.4.0", "geoplanet:7.4.1", "geoplanet:7.5.1", "geoplanet:7.5.2", "geoplanet:7.6.0", "geoplanet:7.8.1", "geoplanet:7.9.0", "geoplanet:7.10.0", "geoplanet:8.0.0", "woeplanet:8.0.0"], "meta:indexed": "2020-08-20T20:18:59.635578", "meta:updated": "2020-10-14T11:19:41.853824", "woe:hierarchy": {"continent": 24865672, "country": 23424977, "town": 0, "planet": 1, "county": 12589778, "suburb": 0, "state": 2347597, "region": 0, "localadmin": 0}, "woe:timezone_id": 56043648, "woe:hash": "dr4e3y4ps3n8", "woe:centroid": [-75.154533, 39.980541], "geom:latitude": 39.980541, "geom:longitude": -75.154533, "geom:hash": "dr4e3y4ps3n8", "woe:latitude": 39.980541, "geom:centroid": [-75.154533, 39.980541], "woe:longitude": -75.154533, "woe:repo": "woeplanet-poi-us", "geom:area": 0.0, "woe:scale": 19}}