{"type": "Feature", "id": 56063642, "geometry": {"type": "Point", "coordinates": [-88.414268, 41.88216]}, "properties": {"woe:id": 56063642, "woe:parent_id": 2434193, "woe:name": "La Fox Metra Station", "woe:placetype": 20, "woe:placetype_name": "POI", "woe:lang": "ENG", "iso:country": "US", "meta:provider": ["geoplanet:7.3.1", "geoplanet:7.3.2", "geoplanet:7.4.0", "geoplanet:7.4.1", "geoplanet:7.5.1", "geoplanet:7.5.2", "geoplanet:7.6.0", "geoplanet:7.8.1", "geoplanet:7.9.0", "geoplanet:7.10.0", "geoplanet:8.0.0", "woeplanet:8.0.0"], "meta:indexed": "2020-08-20T20:19:20.673838", "meta:updated": "2020-10-14T11:19:56.225222", "woe:alias_ENG_V": ["Metra-la Fox Station"], "woe:hierarchy": {"continent": 24865672, "country": 23424977, "town": 0, "planet": 1, "county": 12588122, "suburb": 0, "state": 2347572, "region": 0, "localadmin": 0}, "woe:timezone_id": 56043661, "woe:hash": "dp3nk06tq0rr", "woe:centroid": [-88.414268, 41.88216], "geom:latitude": 41.88216, "geom:longitude": -88.414268, "geom:hash": "dp3nk06tq0rr", "woe:latitude": 41.88216, "geom:centroid": [-88.414268, 41.88216], "woe:longitude": -88.414268, "woe:repo": "woeplanet-poi-us", "geom:area": 0.0, "woe:scale": 19}}