{"type": "Feature", "id": 23635145, "geometry": {"type": "Point", "coordinates": [-122.663918, 45.40387]}, "properties": {"woe:id": 23635145, "woe:parent_id": 55859921, "woe:name": "Hallinan Elementary School", "woe:placetype": 20, "woe:placetype_name": "POI", "woe:lang": "ENG", "iso:country": "US", "meta:provider": ["geoplanet:7.3.1", "geoplanet:7.3.2", "geoplanet:7.4.0", "geoplanet:7.4.1", "geoplanet:7.5.1", "geoplanet:7.5.2", "geoplanet:7.6.0", "geoplanet:7.8.1", "geoplanet:7.9.0", "geoplanet:7.10.0", "geoplanet:8.0.0", "woeplanet:8.0.0"], "meta:indexed": "2020-08-20T20:18:56.705785", "woe:alias_ENG_V": ["Hallinan Elementary"], "meta:updated": "2020-10-14T11:19:40.644365", "woe:hierarchy": {"continent": 24865672, "country": 23424977, "town": 0, "planet": 1, "county": 12589694, "suburb": 0, "state": 2347596, "region": 0, "localadmin": 0}, "woe:timezone_id": 56043663, "woe:hash": "c20f29wbewc6", "woe:centroid": [-122.663918, 45.40387], "geom:latitude": 45.40387, "geom:longitude": -122.663918, "geom:hash": "c20f29wbewc6", "woe:latitude": 45.40387, "geom:centroid": [-122.663918, 45.40387], "woe:longitude": -122.663918, "woe:repo": "woeplanet-poi-us", "geom:area": 0.0, "woe:scale": 19}}