{"type": "Feature", "id": 23525635, "properties": {"woe:id": 23525635, "woe:parent_id": 2395993, "woe:name": "Green Oaks Kindergarten", "woe:placetype": 20, "woe:placetype_name": "POI", "woe:lang": "ENG", "iso:country": "US", "meta:provider": ["geoplanet:7.3.1", "geoplanet:7.3.2", "geoplanet:7.4.0", "geoplanet:7.4.1", "geoplanet:7.5.1", "geoplanet:7.5.2", "geoplanet:7.6.0", "geoplanet:7.8.1", "geoplanet:7.9.0", "geoplanet:7.10.0", "geoplanet:8.0.0", "woeplanet:8.0.0"], "meta:indexed": "2020-08-20T20:18:20.655494", "meta:updated": "2020-08-22T02:57:27.949851", "woe:alias_ENG_V": ["Green Oaks Academy"], "woe:hierarchy": {"continent": 24865672, "country": 23424977, "town": 0, "planet": 1, "county": 12587710, "suburb": 0, "state": 2347563, "region": 0, "localadmin": 0}, "woe:timezone_id": 56043663, "woe:hash": "9q9jhmzs0d0u", "woe:centroid": [-122.14666, 37.47369], "geom:latitude": 37.47369, "geom:longitude": -122.14666, "geom:hash": "9q9jhmzs0d0u", "woe:latitude": 37.47369, "geom:centroid": [-122.14666, 37.47369], "woe:longitude": -122.14666, "woe:repo": "woeplanet-poi-us"}, "geometry": {"coordinates": [-122.14666, 37.47369], "type": "Point"}}