{"type": "Feature", "id": 23662514, "properties": {"woe:id": 23662514, "woe:parent_id": 2454226, "woe:name": "Wasatch Academy", "woe:placetype": 20, "woe:placetype_name": "POI", "woe:lang": "ENG", "iso:country": "US", "meta:provider": ["geoplanet:7.3.1", "geoplanet:7.3.2", "geoplanet:7.4.0", "geoplanet:7.4.1", "geoplanet:7.5.1", "geoplanet:7.5.2", "geoplanet:7.6.0", "geoplanet:7.8.1", "geoplanet:7.9.0", "geoplanet:7.10.0", "geoplanet:8.0.0", "woeplanet:8.0.0"], "meta:indexed": "2020-08-20T20:19:07.294721", "meta:updated": "2020-08-22T02:57:50.886786", "woe:hierarchy": {"continent": 24865672, "country": 23424977, "town": 0, "planet": 1, "county": 12590280, "suburb": 0, "state": 2347603, "region": 0, "localadmin": 0}, "woe:timezone_id": 56043665, "woe:hash": "9x08ufcszf66", "woe:centroid": [-111.585739, 39.52277], "geom:latitude": 39.52277, "geom:longitude": -111.585739, "geom:hash": "9x08ufcszf66", "woe:latitude": 39.52277, "geom:centroid": [-111.585739, 39.52277], "woe:longitude": -111.585739, "woe:repo": "woeplanet-poi-us"}, "geometry": {"coordinates": [-111.585739, 39.52277], "type": "Point"}}