{"type": "Feature", "id": 23622617, "properties": {"woe:id": 23622617, "woe:parent_id": 2372633, "woe:name": "Butner-stem Elementary School", "woe:placetype": 20, "woe:placetype_name": "POI", "woe:lang": "ENG", "iso:country": "US", "meta:provider": ["geoplanet:7.3.2", "geoplanet:7.4.0", "geoplanet:7.4.1", "geoplanet:7.5.1", "geoplanet:7.5.2", "geoplanet:7.6.0", "geoplanet:7.8.1", "geoplanet:7.9.0", "geoplanet:7.10.0", "geoplanet:8.0.0", "woeplanet:8.0.0"], "meta:indexed": "2020-08-20T22:02:39.439090", "woe:alias_ENG_V": ["Butner-stem Elementary"], "meta:updated": "2020-08-22T02:57:44.055357", "woe:hierarchy": {"continent": 24865672, "country": 23424977, "town": 0, "planet": 1, "county": 12589412, "suburb": 0, "state": 2347592, "region": 0, "localadmin": 0}, "woe:timezone_id": 56043648, "woe:hash": "dnrvxf6j00vc", "woe:centroid": [-78.758232, 36.136269], "geom:latitude": 36.136269, "geom:longitude": -78.758232, "geom:hash": "dnrvxf6j00vc", "woe:latitude": 36.136269, "geom:centroid": [-78.758232, 36.136269], "woe:longitude": -78.758232, "woe:repo": "woeplanet-poi-us"}, "geometry": {"coordinates": [-78.758232, 36.136269], "type": "Point"}}