{"type": "Feature", "id": 23524863, "geometry": {"type": "Point", "coordinates": [-122.448868, 37.730221]}, "properties": {"woe:id": 23524863, "woe:parent_id": 55970978, "woe:name": "Sunnyside Elementary School", "woe:placetype": 20, "woe:placetype_name": "POI", "woe:lang": "ENG", "iso:country": "US", "meta:provider": ["geoplanet:7.3.2", "geoplanet:7.4.0", "geoplanet:7.4.1", "geoplanet:7.5.1", "geoplanet:7.5.2", "geoplanet:7.6.0", "geoplanet:7.8.1", "geoplanet:7.9.0", "geoplanet:7.10.0", "geoplanet:8.0.0", "woeplanet:8.0.0"], "meta:indexed": "2020-08-20T22:01:59.698387", "woe:alias_ENG_V": ["Sunnyside Elementary"], "meta:updated": "2020-10-14T11:20:08.563684", "woe:hierarchy": {"continent": 24865672, "country": 23424977, "town": 0, "planet": 1, "county": 12587707, "suburb": 0, "state": 2347563, "region": 0, "localadmin": 0}, "woe:timezone_id": 56043663, "woe:hash": "9q8ytse6qwfr", "woe:centroid": [-122.448868, 37.730221], "geom:latitude": 37.730221, "geom:longitude": -122.448868, "geom:hash": "9q8ytse6qwfr", "woe:latitude": 37.730221, "geom:centroid": [-122.448868, 37.730221], "woe:longitude": -122.448868, "woe:repo": "woeplanet-poi-us", "geom:area": 0.0, "woe:scale": 19}}