{"type": "Feature", "id": 23654106, "properties": {"woe:id": 23654106, "woe:parent_id": 55859775, "woe:name": "Downtown Irving Station", "woe:placetype": 20, "woe:placetype_name": "POI", "woe:lang": "ENG", "iso:country": "US", "meta:provider": ["geoplanet:7.3.1", "geoplanet:7.3.2", "geoplanet:7.4.0", "geoplanet:7.4.1", "geoplanet:7.5.1", "geoplanet:7.5.2", "geoplanet:7.6.0", "geoplanet:7.8.1", "geoplanet:7.9.0", "geoplanet:7.10.0", "geoplanet:8.0.0", "woeplanet:8.0.0"], "meta:indexed": "2020-08-20T20:19:03.204066", "meta:updated": "2020-08-22T02:57:48.980489", "woe:hierarchy": {"continent": 24865672, "country": 23424977, "town": 0, "planet": 1, "county": 12590063, "suburb": 0, "state": 2347602, "region": 0, "localadmin": 0}, "woe:timezone_id": 56043661, "woe:hash": "9vg49vjtwmku", "woe:centroid": [-96.946518, 32.811642], "geom:latitude": 32.811642, "geom:longitude": -96.946518, "geom:hash": "9vg49vjtwmku", "woe:latitude": 32.811642, "geom:centroid": [-96.946518, 32.811642], "woe:longitude": -96.946518, "woe:repo": "woeplanet-poi-us"}, "geometry": {"coordinates": [-96.946518, 32.811642], "type": "Point"}}