{"type": "Feature", "id": 23564956, "geometry": {"type": "Point", "coordinates": [-88.135971, 41.51503]}, "properties": {"woe:id": 23564956, "woe:parent_id": 2429708, "woe:name": "Saint Jude School", "woe:placetype": 20, "woe:placetype_name": "POI", "woe:lang": "ENG", "iso:country": "US", "meta:provider": ["geoplanet:7.3.1", "geoplanet:7.3.2", "geoplanet:7.4.0", "geoplanet:7.4.1", "geoplanet:7.5.1", "geoplanet:7.5.2", "geoplanet:7.6.0", "geoplanet:7.8.1", "geoplanet:7.9.0", "geoplanet:7.10.0", "geoplanet:8.0.0", "woeplanet:8.0.0"], "meta:indexed": "2020-08-20T20:18:33.431505", "meta:updated": "2020-10-14T11:20:13.365042", "woe:hierarchy": {"continent": 24865672, "country": 23424977, "town": 0, "planet": 1, "county": 12588176, "suburb": 0, "state": 2347572, "region": 0, "localadmin": 0}, "woe:timezone_id": 56043661, "woe:hash": "dp3k4mt6e48b", "woe:centroid": [-88.135971, 41.51503], "geom:latitude": 41.51503, "geom:longitude": -88.135971, "geom:hash": "dp3k4mt6e48b", "woe:latitude": 41.51503, "geom:centroid": [-88.135971, 41.51503], "woe:longitude": -88.135971, "woe:repo": "woeplanet-poi-us", "geom:area": 0.0, "woe:scale": 19}}