{"type": "Feature", "id": 23620464, "geometry": {"type": "Point", "coordinates": [-77.064209, 42.155312]}, "properties": {"woe:id": 23620464, "woe:parent_id": 2385177, "woe:name": "Hugh W. Gregg Elementary School", "woe:placetype": 20, "woe:placetype_name": "POI", "woe:lang": "ENG", "iso:country": "US", "meta:provider": ["geoplanet:7.3.1", "geoplanet:7.3.2", "geoplanet:7.4.0", "geoplanet:7.4.1", "geoplanet:7.5.1", "geoplanet:7.5.2", "geoplanet:7.6.0", "geoplanet:7.8.1", "geoplanet:7.9.0", "geoplanet:7.10.0", "geoplanet:8.0.0", "woeplanet:8.0.0"], "meta:indexed": "2020-08-20T20:18:51.630100", "woe:alias_ENG_V": ["Hugh W. Gregg Elementary"], "meta:updated": "2020-10-14T11:19:27.040067", "woe:hierarchy": {"continent": 24865672, "country": 23424977, "town": 0, "planet": 1, "county": 12589362, "suburb": 0, "state": 2347591, "region": 0, "localadmin": 0}, "woe:timezone_id": 56043648, "woe:hash": "dr3py65s3z8z", "woe:centroid": [-77.064209, 42.155312], "geom:latitude": 42.155312, "geom:longitude": -77.064209, "geom:hash": "dr3py65s3z8z", "woe:latitude": 42.155312, "geom:centroid": [-77.064209, 42.155312], "woe:longitude": -77.064209, "woe:repo": "woeplanet-poi-us", "geom:area": 0.0, "woe:scale": 19}}