{"type": "Feature", "id": 23632993, "geometry": {"type": "Point", "coordinates": [-81.853813, 40.866852]}, "properties": {"woe:id": 23632993, "woe:parent_id": 2495111, "woe:name": "Greene Middle School", "woe:placetype": 20, "woe:placetype_name": "POI", "woe:lang": "ENG", "iso:country": "US", "meta:provider": ["geoplanet:7.3.1", "geoplanet:7.3.2", "geoplanet:7.4.0", "geoplanet:7.4.1", "geoplanet:7.5.1", "geoplanet:7.5.2", "geoplanet:7.6.0", "geoplanet:7.8.1", "geoplanet:7.9.0", "geoplanet:7.10.0", "geoplanet:8.0.0", "woeplanet:8.0.0"], "meta:indexed": "2020-08-20T20:18:55.849984", "meta:updated": "2020-10-14T11:19:35.810343", "woe:hierarchy": {"continent": 24865672, "country": 23424977, "town": 0, "planet": 1, "county": 12589611, "suburb": 0, "state": 2347594, "region": 0, "localadmin": 0}, "woe:timezone_id": 56043648, "woe:hash": "dpmb3refevm7", "woe:centroid": [-81.853813, 40.866852], "geom:latitude": 40.866852, "geom:longitude": -81.853813, "geom:hash": "dpmb3refevm7", "woe:latitude": 40.866852, "geom:centroid": [-81.853813, 40.866852], "woe:longitude": -81.853813, "woe:repo": "woeplanet-poi-us", "geom:area": 0.0, "woe:scale": 19}}