{"type": "Feature", "id": 23544311, "properties": {"woe:id": 23544311, "woe:parent_id": 2429324, "woe:name": "Griswold Intermediate School", "woe:placetype": 20, "woe:placetype_name": "POI", "woe:lang": "ENG", "iso:country": "US", "meta:provider": ["geoplanet:7.3.1", "geoplanet:7.3.2", "geoplanet:7.4.0", "geoplanet:7.4.1", "geoplanet:7.5.1", "geoplanet:7.5.2", "geoplanet:7.6.0", "geoplanet:7.8.1", "geoplanet:7.9.0", "geoplanet:7.10.0", "geoplanet:8.0.0", "woeplanet:8.0.0"], "meta:indexed": "2020-08-20T20:18:25.542649", "meta:updated": "2020-08-22T02:57:31.286709", "woe:hierarchy": {"continent": 24865672, "country": 23424977, "town": 0, "planet": 1, "county": 12587796, "suburb": 0, "state": 2347565, "region": 0, "localadmin": 0}, "woe:timezone_id": 56043648, "woe:hash": "drkudhdmnz01", "woe:centroid": [-71.979042, 41.597881], "geom:latitude": 41.597881, "geom:longitude": -71.979042, "geom:hash": "drkudhdmnz01", "woe:latitude": 41.597881, "geom:centroid": [-71.979042, 41.597881], "woe:longitude": -71.979042, "woe:repo": "woeplanet-poi-us"}, "geometry": {"coordinates": [-71.979042, 41.597881], "type": "Point"}}