{"type": "Feature", "id": 23522577, "properties": {"woe:id": 23522577, "woe:parent_id": 55970183, "woe:name": "Hill Middle School", "woe:placetype": 20, "woe:placetype_name": "POI", "woe:lang": "ENG", "iso:country": "US", "meta:provider": ["geoplanet:7.3.1", "geoplanet:7.3.2", "geoplanet:7.4.0", "geoplanet:7.4.1", "geoplanet:7.5.1", "geoplanet:7.5.2", "geoplanet:7.6.0", "geoplanet:7.8.1", "geoplanet:7.9.0", "geoplanet:7.10.0", "geoplanet:8.0.0", "woeplanet:8.0.0"], "meta:indexed": "2020-08-20T20:18:19.987276", "meta:updated": "2020-08-22T02:57:27.531743", "woe:hierarchy": {"continent": 24865672, "country": 23424977, "town": 0, "planet": 1, "county": 12587690, "suburb": 0, "state": 2347563, "region": 0, "localadmin": 0}, "woe:timezone_id": 56043663, "woe:hash": "9qbbdxw0eusu", "woe:centroid": [-122.577042, 38.09795], "geom:latitude": 38.09795, "geom:longitude": -122.577042, "geom:hash": "9qbbdxw0eusu", "woe:latitude": 38.09795, "geom:centroid": [-122.577042, 38.09795], "woe:longitude": -122.577042, "woe:repo": "woeplanet-poi-us"}, "geometry": {"coordinates": [-122.577042, 38.09795], "type": "Point"}}