{"type": "Feature", "id": 23634486, "geometry": {"type": "Point", "coordinates": [-95.426041, 36.53521]}, "properties": {"woe:id": 23634486, "woe:parent_id": 2378821, "woe:name": "Mcintosh Elementary School", "woe:placetype": 20, "woe:placetype_name": "POI", "woe:lang": "ENG", "iso:country": "US", "meta:provider": ["geoplanet:7.3.1", "geoplanet:7.3.2", "geoplanet:7.4.0", "geoplanet:7.4.1", "geoplanet:7.5.1", "geoplanet:7.5.2", "geoplanet:7.6.0", "geoplanet:7.8.1", "geoplanet:7.9.0", "geoplanet:7.10.0", "geoplanet:8.0.0", "woeplanet:8.0.0"], "meta:indexed": "2020-08-20T20:18:56.473034", "woe:alias_ENG_V": ["Mcintosh Elementary"], "meta:updated": "2020-10-14T11:19:27.848490", "woe:hierarchy": {"continent": 24865672, "country": 23424977, "town": 0, "planet": 1, "county": 12589680, "suburb": 0, "state": 2347595, "region": 0, "localadmin": 0}, "woe:timezone_id": 56043661, "woe:hash": "9ykpue0ch0f8", "woe:centroid": [-95.426041, 36.53521], "geom:latitude": 36.53521, "geom:longitude": -95.426041, "geom:hash": "9ykpue0ch0f8", "woe:latitude": 36.53521, "geom:centroid": [-95.426041, 36.53521], "woe:longitude": -95.426041, "woe:repo": "woeplanet-poi-us", "geom:area": 0.0, "woe:scale": 19}}