{"type": "Feature", "id": 23549070, "properties": {"woe:id": 23549070, "woe:parent_id": 55984618, "woe:name": "Beach Station", "woe:placetype": 20, "woe:placetype_name": "POI", "woe:lang": "ENG", "iso:country": "US", "meta:provider": ["geoplanet:7.3.1", "geoplanet:7.3.2", "geoplanet:7.4.0", "geoplanet:7.4.1", "geoplanet:7.5.1", "geoplanet:7.5.2", "geoplanet:7.6.0", "geoplanet:7.8.1", "geoplanet:7.9.0", "geoplanet:7.10.0", "geoplanet:8.0.0", "woeplanet:8.0.0"], "meta:indexed": "2020-08-20T20:18:27.668344", "meta:updated": "2020-08-22T02:57:32.288725", "woe:hierarchy": {"continent": 24865672, "country": 23424977, "town": 0, "planet": 1, "county": 12587833, "suburb": 0, "state": 2347568, "region": 0, "localadmin": 0}, "woe:timezone_id": 56043648, "woe:hash": "dhyv73vry497", "woe:centroid": [-80.357521, 27.652559], "geom:latitude": 27.652559, "geom:longitude": -80.357521, "geom:hash": "dhyv73vry497", "woe:latitude": 27.652559, "geom:centroid": [-80.357521, 27.652559], "woe:longitude": -80.357521, "woe:repo": "woeplanet-poi-us"}, "geometry": {"coordinates": [-80.357521, 27.652559], "type": "Point"}}