{"type": "Feature", "id": 23613093, "properties": {"woe:id": 23613093, "woe:parent_id": 2404946, "woe:name": "Our Lady of Mercy School", "woe:placetype": 20, "woe:placetype_name": "POI", "woe:lang": "ENG", "iso:country": "US", "meta:provider": ["geoplanet:7.3.1", "geoplanet:7.3.2", "geoplanet:7.4.0", "geoplanet:7.4.1", "geoplanet:7.5.1", "geoplanet:7.5.2", "geoplanet:7.6.0", "geoplanet:7.8.1", "geoplanet:7.9.0", "geoplanet:7.10.0", "geoplanet:8.0.0", "woeplanet:8.0.0"], "meta:indexed": "2020-08-20T20:18:48.687008", "meta:updated": "2020-08-22T02:57:42.713935", "woe:hierarchy": {"continent": 24865672, "country": 23424977, "town": 0, "planet": 1, "county": 12589314, "suburb": 0, "state": 2347591, "region": 0, "localadmin": 0}, "woe:timezone_id": 56043648, "woe:hash": "dr72qw8eezt8", "woe:centroid": [-73.893188, 40.861542], "geom:latitude": 40.861542, "geom:longitude": -73.893188, "geom:hash": "dr72qw8eezt8", "woe:latitude": 40.861542, "geom:centroid": [-73.893188, 40.861542], "woe:longitude": -73.893188, "woe:repo": "woeplanet-poi-us"}, "geometry": {"coordinates": [-73.893188, 40.861542], "type": "Point"}}