{"type": "Feature", "id": 23522170, "geometry": {"type": "Point", "coordinates": [-122.9142, 39.059261]}, "properties": {"woe:id": 23522170, "woe:parent_id": 23417131, "woe:name": "Lakeport Elementary School", "woe:placetype": 20, "woe:placetype_name": "POI", "woe:lang": "ENG", "iso:country": "US", "meta:provider": ["geoplanet:7.3.2", "geoplanet:7.4.0", "geoplanet:7.4.1", "geoplanet:7.5.1", "geoplanet:7.5.2", "geoplanet:7.6.0", "geoplanet:7.8.1", "geoplanet:7.9.0", "geoplanet:7.10.0", "geoplanet:8.0.0", "woeplanet:8.0.0"], "meta:indexed": "2020-08-20T22:01:58.864374", "woe:alias_ENG_V": ["Lakeport Elementary"], "meta:updated": "2020-10-14T11:20:10.807011", "woe:hierarchy": {"continent": 24865672, "country": 23424977, "town": 0, "planet": 1, "county": 12587686, "suburb": 0, "state": 2347563, "region": 0, "localadmin": 0}, "woe:timezone_id": 56043663, "woe:hash": "9qbw5n88etcx", "woe:centroid": [-122.9142, 39.059261], "geom:latitude": 39.059261, "geom:longitude": -122.9142, "geom:hash": "9qbw5n88etcx", "woe:latitude": 39.059261, "geom:centroid": [-122.9142, 39.059261], "woe:longitude": -122.9142, "woe:repo": "woeplanet-poi-us", "geom:area": 0.0, "woe:scale": 19}}