{"type": "Feature", "id": 24866068, "geometry": {"type": "Point", "coordinates": [-94.577217, 39.01157]}, "properties": {"woe:id": 24866068, "woe:parent_id": 2513375, "woe:name": "Cleveland Chiropractic College", "woe:placetype": 20, "woe:placetype_name": "POI", "woe:lang": "ENG", "iso:country": "US", "meta:provider": ["geoplanet:7.3.2", "geoplanet:7.4.0", "geoplanet:7.4.1", "geoplanet:7.5.1", "geoplanet:7.5.2", "geoplanet:7.6.0", "geoplanet:7.8.1", "geoplanet:7.9.0", "geoplanet:7.10.0", "geoplanet:8.0.0", "woeplanet:8.0.0"], "meta:indexed": "2020-08-20T22:03:06.016354", "meta:updated": "2020-10-14T11:19:26.062130", "woe:hierarchy": {"continent": 24865672, "country": 23424977, "town": 0, "planet": 1, "county": 12589013, "suburb": 0, "state": 2347584, "region": 0, "localadmin": 0}, "woe:timezone_id": 56043661, "woe:hash": "9yutzvffz5ex", "woe:centroid": [-94.577217, 39.01157], "geom:latitude": 39.01157, "geom:longitude": -94.577217, "geom:hash": "9yutzvffz5ex", "woe:latitude": 39.01157, "geom:centroid": [-94.577217, 39.01157], "woe:longitude": -94.577217, "woe:repo": "woeplanet-poi-us", "geom:area": 0.0, "woe:scale": 19}}