{"type": "Feature", "id": 23568744, "geometry": {"type": "Point", "coordinates": [-91.224419, 43.36198]}, "properties": {"woe:id": 23568744, "woe:parent_id": 2436452, "woe:name": "Lansing Middle School", "woe:placetype": 20, "woe:placetype_name": "POI", "woe:lang": "ENG", "iso:country": "US", "meta:provider": ["geoplanet:7.3.1", "geoplanet:7.3.2", "geoplanet:7.4.0", "geoplanet:7.4.1", "geoplanet:7.5.1", "geoplanet:7.5.2", "geoplanet:7.6.0", "geoplanet:7.8.1", "geoplanet:7.9.0", "geoplanet:7.10.0", "geoplanet:8.0.0", "woeplanet:8.0.0"], "meta:indexed": "2020-08-20T20:18:34.902585", "meta:updated": "2020-10-14T11:20:11.087212", "woe:alias_ENG_V": ["Eastern Allamakee Middle School"], "woe:hierarchy": {"continent": 24865672, "country": 23424977, "town": 0, "planet": 1, "county": 12588274, "suburb": 0, "state": 2347574, "region": 0, "localadmin": 0}, "woe:timezone_id": 56043661, "woe:hash": "9zxnsju3ufzn", "woe:centroid": [-91.224419, 43.36198], "geom:latitude": 43.36198, "geom:longitude": -91.224419, "geom:hash": "9zxnsju3ufzn", "woe:latitude": 43.36198, "geom:centroid": [-91.224419, 43.36198], "woe:longitude": -91.224419, "woe:repo": "woeplanet-poi-us", "geom:area": 0.0, "woe:scale": 19}}