{"type": "Feature", "id": 23657364, "properties": {"woe:id": 23657364, "woe:parent_id": 29230246, "woe:name": "L B Johnson Elementary School", "woe:placetype": 20, "woe:placetype_name": "POI", "woe:lang": "ENG", "iso:country": "US", "meta:provider": ["geoplanet:7.3.2", "geoplanet:7.4.0", "geoplanet:7.4.1", "geoplanet:7.5.1", "geoplanet:7.5.2", "geoplanet:7.6.0", "geoplanet:7.8.1", "geoplanet:7.9.0", "geoplanet:7.10.0", "geoplanet:8.0.0", "woeplanet:8.0.0"], "meta:indexed": "2020-08-20T22:02:54.452159", "woe:alias_ENG_V": ["L B Johnson Elementary"], "meta:updated": "2020-08-22T02:57:49.789003", "woe:hierarchy": {"continent": 24865672, "country": 23424977, "town": 0, "planet": 1, "county": 12590021, "suburb": 0, "state": 2347602, "region": 0, "localadmin": 0}, "woe:timezone_id": 56043661, "woe:hash": "9v1zkw31fd21", "woe:centroid": [-98.589828, 29.434059], "geom:latitude": 29.434059, "geom:longitude": -98.589828, "geom:hash": "9v1zkw31fd21", "woe:latitude": 29.434059, "geom:centroid": [-98.589828, 29.434059], "woe:longitude": -98.589828, "woe:repo": "woeplanet-poi-us"}, "geometry": {"coordinates": [-98.589828, 29.434059], "type": "Point"}}