{"type": "Feature", "id": 23646938, "geometry": {"type": "Point", "coordinates": [-81.871262, 33.803989]}, "properties": {"woe:id": 23646938, "woe:parent_id": 12589818, "woe:name": "Strom Thurmond High School", "woe:placetype": 20, "woe:placetype_name": "POI", "woe:lang": "ENG", "iso:country": "US", "meta:provider": ["geoplanet:7.3.1", "geoplanet:7.3.2", "geoplanet:7.4.0", "geoplanet:7.4.1", "geoplanet:7.5.1", "geoplanet:7.5.2", "geoplanet:7.6.0", "geoplanet:7.8.1", "geoplanet:7.9.0", "geoplanet:7.10.0", "geoplanet:8.0.0", "woeplanet:8.0.0"], "meta:indexed": "2020-08-20T20:19:00.652034", "woe:alias_ENG_V": ["Strom Thurmond Senior High School", "Strom Thurmond High", "Strom Thurmond Senior High", "Strom Thurmond HS", "Strom Thurmond Senior HS"], "meta:updated": "2020-10-14T11:19:54.582364", "woe:hierarchy": {"continent": 24865672, "country": 23424977, "town": 0, "planet": 1, "county": 12589818, "suburb": 0, "state": 2347599, "region": 0, "localadmin": 0}, "woe:timezone_id": 56043648, "woe:hash": "dnjb2cz4t262", "woe:centroid": [-81.871262, 33.803989], "geom:latitude": 33.803989, "geom:longitude": -81.871262, "geom:hash": "dnjb2cz4t262", "woe:latitude": 33.803989, "geom:centroid": [-81.871262, 33.803989], "woe:longitude": -81.871262, "woe:repo": "woeplanet-poi-us", "geom:area": 0.0, "woe:scale": 19}}