{"type": "Feature", "id": 23680815, "geometry": {"type": "Point", "coordinates": [-81.922432, 28.454901]}, "properties": {"woe:id": 23680815, "woe:parent_id": 2360210, "woe:name": "Bay Lake Station", "woe:placetype": 20, "woe:placetype_name": "POI", "woe:lang": "ENG", "iso:country": "US", "meta:provider": ["geoplanet:7.3.1", "geoplanet:7.3.2", "geoplanet:7.4.0", "geoplanet:7.4.1", "geoplanet:7.5.1", "geoplanet:7.5.2", "geoplanet:7.6.0", "geoplanet:7.8.1", "geoplanet:7.9.0", "geoplanet:7.10.0", "geoplanet:8.0.0", "woeplanet:8.0.0"], "meta:indexed": "2020-08-20T20:19:18.678531", "meta:updated": "2020-10-14T11:19:51.860843", "woe:hierarchy": {"continent": 24865672, "country": 23424977, "town": 0, "planet": 1, "county": 12587837, "suburb": 0, "state": 2347568, "region": 0, "localadmin": 0}, "woe:timezone_id": 56043648, "woe:hash": "djj9zu1cufp0", "woe:centroid": [-81.922432, 28.454901], "geom:latitude": 28.454901, "geom:longitude": -81.922432, "geom:hash": "djj9zu1cufp0", "woe:latitude": 28.454901, "geom:centroid": [-81.922432, 28.454901], "woe:longitude": -81.922432, "woe:repo": "woeplanet-poi-us", "geom:area": 0.0, "woe:scale": 19}}