{"type": "Feature", "id": 23657429, "geometry": {"type": "Point", "coordinates": [-98.500549, 29.537951]}, "properties": {"woe:id": 23657429, "woe:parent_id": 29230240, "woe:name": "Harmony Hills Elementary School", "woe:placetype": 20, "woe:placetype_name": "POI", "woe:lang": "ENG", "iso:country": "US", "meta:provider": ["geoplanet:7.3.1", "geoplanet:7.3.2", "geoplanet:7.4.0", "geoplanet:7.4.1", "geoplanet:7.5.1", "geoplanet:7.5.2", "geoplanet:7.6.0", "geoplanet:7.8.1", "geoplanet:7.9.0", "geoplanet:7.10.0", "geoplanet:8.0.0", "woeplanet:8.0.0"], "meta:indexed": "2020-08-20T20:19:04.887274", "woe:alias_ENG_V": ["Harmony Hills Elementary"], "meta:updated": "2020-10-14T11:19:47.047065", "woe:hierarchy": {"continent": 24865672, "country": 23424977, "town": 0, "planet": 1, "county": 12590021, "suburb": 0, "state": 2347602, "region": 0, "localadmin": 0}, "woe:timezone_id": 56043661, "woe:hash": "9v3bn94p4c5m", "woe:centroid": [-98.500549, 29.537951], "geom:latitude": 29.537951, "geom:longitude": -98.500549, "geom:hash": "9v3bn94p4c5m", "woe:latitude": 29.537951, "geom:centroid": [-98.500549, 29.537951], "woe:longitude": -98.500549, "woe:repo": "woeplanet-poi-us", "geom:area": 0.0, "woe:scale": 19}}