{"type": "Feature", "id": 24866458, "properties": {"woe:id": 24866458, "woe:parent_id": 2442304, "woe:name": "Louisburg College", "woe:placetype": 20, "woe:placetype_name": "POI", "woe:lang": "ENG", "iso:country": "US", "meta:provider": ["geoplanet:7.3.1", "geoplanet:7.3.2", "geoplanet:7.4.0", "geoplanet:7.4.1", "geoplanet:7.5.1", "geoplanet:7.5.2", "geoplanet:7.6.0", "geoplanet:7.8.1", "geoplanet:7.9.0", "geoplanet:7.10.0", "geoplanet:8.0.0", "woeplanet:8.0.0"], "meta:indexed": "2020-08-20T20:19:15.115368", "meta:updated": "2020-08-22T02:58:19.785591", "woe:hierarchy": {"continent": 24865672, "country": 23424977, "town": 0, "planet": 1, "county": 12589408, "suburb": 0, "state": 2347592, "region": 0, "localadmin": 0}, "woe:timezone_id": 56043648, "woe:hash": "dq2m6k3m9vq9", "woe:centroid": [-78.29776, 36.10342], "geom:latitude": 36.10342, "geom:longitude": -78.29776, "geom:hash": "dq2m6k3m9vq9", "woe:latitude": 36.10342, "geom:centroid": [-78.29776, 36.10342], "woe:longitude": -78.29776, "woe:repo": "woeplanet-poi-us"}, "geometry": {"coordinates": [-78.29776, 36.10342], "type": "Point"}}