{"type": "Feature", "id": 23561543, "properties": {"woe:id": 23561543, "woe:parent_id": 2511273, "woe:name": "Washington Elementary School", "woe:placetype": 20, "woe:placetype_name": "POI", "woe:lang": "ENG", "iso:country": "US", "meta:provider": ["geoplanet:7.3.1", "geoplanet:7.3.2", "geoplanet:7.4.0", "geoplanet:7.4.1", "geoplanet:7.5.1", "geoplanet:7.5.2", "geoplanet:7.6.0", "geoplanet:7.8.1", "geoplanet:7.9.0", "geoplanet:7.10.0", "geoplanet:8.0.0", "woeplanet:8.0.0"], "meta:indexed": "2020-08-20T20:18:32.168750", "woe:alias_ENG_V": ["Washington Elementary"], "meta:updated": "2020-08-22T02:57:34.620347", "woe:hierarchy": {"continent": 24865672, "country": 23424977, "town": 0, "planet": 1, "county": 12588103, "suburb": 0, "state": 2347572, "region": 0, "localadmin": 0}, "woe:timezone_id": 56043661, "woe:hash": "dnbtskrhuf3u", "woe:centroid": [-89.100288, 38.959721], "geom:latitude": 38.959721, "geom:longitude": -89.100288, "geom:hash": "dnbtskrhuf3u", "woe:latitude": 38.959721, "geom:centroid": [-89.100288, 38.959721], "woe:longitude": -89.100288, "woe:repo": "woeplanet-poi-us"}, "geometry": {"coordinates": [-89.100288, 38.959721], "type": "Point"}}