{"type": "Feature", "id": 56054312, "properties": {"woe:id": 56054312, "woe:parent_id": 2440051, "woe:name": "Estrella Mountain Community College", "woe:placetype": 20, "woe:placetype_name": "POI", "woe:lang": "ENG", "iso:country": "US", "meta:provider": ["geoplanet:7.3.1", "geoplanet:7.3.2", "geoplanet:7.4.0", "geoplanet:7.4.1", "geoplanet:7.5.1", "geoplanet:7.5.2", "geoplanet:7.6.0", "geoplanet:7.8.1", "geoplanet:7.9.0", "geoplanet:7.10.0", "geoplanet:8.0.0", "woeplanet:8.0.0"], "meta:indexed": "2020-08-20T20:19:17.734704", "meta:updated": "2020-08-22T02:58:21.254695", "woe:hierarchy": {"continent": 24865672, "country": 23424977, "town": 0, "planet": 1, "county": 12587587, "suburb": 0, "state": 2347561, "region": 0, "localadmin": 0}, "woe:timezone_id": 56043666, "woe:hash": "9tbn7wgfbw8f", "woe:centroid": [-112.341019, 33.479969], "geom:latitude": 33.479969, "geom:longitude": -112.341019, "geom:hash": "9tbn7wgfbw8f", "woe:latitude": 33.479969, "geom:centroid": [-112.341019, 33.479969], "woe:longitude": -112.341019, "woe:repo": "woeplanet-poi-us"}, "geometry": {"coordinates": [-112.341019, 33.479969], "type": "Point"}}