{"type": "Feature", "id": 23559324, "properties": {"woe:id": 23559324, "woe:parent_id": 28751422, "woe:name": "Pennoyer Elementary School", "woe:placetype": 20, "woe:placetype_name": "POI", "woe:lang": "ENG", "iso:country": "US", "meta:provider": ["geoplanet:7.3.1", "geoplanet:7.3.2", "geoplanet:7.4.0", "geoplanet:7.4.1", "geoplanet:7.5.1", "geoplanet:7.5.2", "geoplanet:7.6.0", "geoplanet:7.8.1", "geoplanet:7.9.0", "geoplanet:7.10.0", "geoplanet:8.0.0", "woeplanet:8.0.0"], "meta:indexed": "2020-08-20T20:18:31.415989", "woe:alias_ENG_V": ["Pennoyer Elementary"], "meta:updated": "2020-08-22T02:57:34.206860", "woe:hierarchy": {"continent": 24865672, "country": 23424977, "town": 0, "planet": 1, "county": 12588093, "suburb": 0, "state": 2347572, "region": 0, "localadmin": 0}, "woe:timezone_id": 56043661, "woe:hash": "dp3wc1pk3bwb", "woe:centroid": [-87.836639, 41.973999], "geom:latitude": 41.973999, "geom:longitude": -87.836639, "geom:hash": "dp3wc1pk3bwb", "woe:latitude": 41.973999, "geom:centroid": [-87.836639, 41.973999], "woe:longitude": -87.836639, "woe:repo": "woeplanet-poi-us"}, "geometry": {"coordinates": [-87.836639, 41.973999], "type": "Point"}}