{"type": "Feature", "id": 23519055, "properties": {"woe:id": 23519055, "woe:parent_id": 2503066, "woe:name": "Wilbur D. Mills High School", "woe:placetype": 20, "woe:placetype_name": "POI", "woe:lang": "ENG", "iso:country": "US", "meta:provider": ["geoplanet:7.3.2", "geoplanet:7.4.0", "geoplanet:7.4.1", "geoplanet:7.5.1", "geoplanet:7.5.2", "geoplanet:7.6.0", "geoplanet:7.8.1", "geoplanet:7.9.0", "geoplanet:7.10.0", "geoplanet:8.0.0", "woeplanet:8.0.0"], "meta:indexed": "2020-08-20T22:01:57.668494", "woe:alias_ENG_V": ["Wilbur D. Mills Senior High School", "Wilbur D. Mills High", "Wilbur D. Mills Senior High", "Wilbur D. Mills HS", "Wilbur D. Mills Senior HS", "Wilbur D Mills High", "Wilbur D Mills High School", "Wilbur D Mills HS", "Wilbur D Mills Senior High", "Wilbur D Mills Senior High School", "Wilbur D Mills Senior HS"], "meta:updated": "2020-08-22T02:58:46.001283", "woe:hierarchy": {"continent": 24865672, "country": 23424977, "town": 0, "planet": 1, "county": 12587654, "suburb": 0, "state": 2347562, "region": 0, "localadmin": 0}, "woe:timezone_id": 56043661, "woe:hash": "9ynmhzbeufzr", "woe:centroid": [-92.251297, 34.672138], "geom:latitude": 34.672138, "geom:longitude": -92.251297, "geom:hash": "9ynmhzbeufzr", "woe:latitude": 34.672138, "geom:centroid": [-92.251297, 34.672138], "woe:longitude": -92.251297, "woe:repo": "woeplanet-poi-us"}, "geometry": {"coordinates": [-92.251297, 34.672138], "type": "Point"}}