{"type": "Feature", "id": 24865899, "geometry": {"type": "Point", "coordinates": [-90.197952, 41.84988]}, "properties": {"woe:id": 24865899, "woe:parent_id": 2381771, "woe:name": "Mount St. Clare College", "woe:placetype": 20, "woe:placetype_name": "POI", "woe:lang": "ENG", "iso:country": "US", "meta:provider": ["geoplanet:7.3.1", "geoplanet:7.3.2", "geoplanet:7.4.0", "geoplanet:7.4.1", "geoplanet:7.5.1", "geoplanet:7.5.2", "geoplanet:7.6.0", "geoplanet:7.8.1", "geoplanet:7.9.0", "geoplanet:7.10.0", "geoplanet:8.0.0", "woeplanet:8.0.0"], "meta:indexed": "2020-08-20T20:19:14.683258", "woe:alias_ENG_V": ["Mt St. Clare College"], "meta:updated": "2020-10-14T11:19:26.371222", "woe:hierarchy": {"continent": 24865672, "country": 23424977, "town": 0, "planet": 1, "county": 12588294, "suburb": 0, "state": 2347574, "region": 0, "localadmin": 0}, "woe:timezone_id": 56043661, "woe:hash": "9zry56xc5rh6", "woe:centroid": [-90.197952, 41.84988], "geom:latitude": 41.84988, "geom:longitude": -90.197952, "geom:hash": "9zry56xc5rh6", "woe:latitude": 41.84988, "geom:centroid": [-90.197952, 41.84988], "woe:longitude": -90.197952, "woe:repo": "woeplanet-poi-us", "geom:area": 0.0, "woe:scale": 19}}