{"type": "Feature", "id": 23682285, "properties": {"woe:id": 23682285, "woe:parent_id": 2428987, "woe:name": "Battle Mountain Station", "woe:placetype": 20, "woe:placetype_name": "POI", "woe:lang": "ENG", "iso:country": "US", "meta:provider": ["geoplanet:7.3.1", "geoplanet:7.3.2", "geoplanet:7.4.0", "geoplanet:7.4.1", "geoplanet:7.5.1", "geoplanet:7.5.2", "geoplanet:7.6.0", "geoplanet:7.8.1", "geoplanet:7.9.0", "geoplanet:7.10.0", "geoplanet:8.0.0", "woeplanet:8.0.0"], "meta:indexed": "2020-08-20T20:19:19.601926", "meta:updated": "2020-08-22T02:58:22.328231", "woe:hierarchy": {"continent": 24865672, "country": 23424977, "town": 0, "planet": 1, "county": 12589239, "suburb": 0, "state": 2347587, "region": 0, "localadmin": 0}, "woe:timezone_id": 56043663, "woe:hash": "9rhz5p1g3mmw", "woe:centroid": [-116.936012, 40.644508], "geom:latitude": 40.644508, "geom:longitude": -116.936012, "geom:hash": "9rhz5p1g3mmw", "woe:latitude": 40.644508, "geom:centroid": [-116.936012, 40.644508], "woe:longitude": -116.936012, "woe:repo": "woeplanet-poi-us"}, "geometry": {"coordinates": [-116.936012, 40.644508], "type": "Point"}}