{"type": "Feature", "id": 23610400, "geometry": {"type": "Point", "coordinates": [-75.467972, 39.57016]}, "properties": {"woe:id": 23610400, "woe:parent_id": 2487378, "woe:name": "Salem Middle School", "woe:placetype": 20, "woe:placetype_name": "POI", "woe:lang": "ENG", "iso:country": "US", "meta:provider": ["geoplanet:7.3.1", "geoplanet:7.3.2", "geoplanet:7.4.0", "geoplanet:7.4.1", "geoplanet:7.5.1", "geoplanet:7.5.2", "geoplanet:7.6.0", "geoplanet:7.8.1", "geoplanet:7.9.0", "geoplanet:7.10.0", "geoplanet:8.0.0", "woeplanet:8.0.0"], "meta:indexed": "2020-08-20T20:18:47.943301", "meta:updated": "2020-10-14T11:19:35.109715", "woe:hierarchy": {"continent": 24865672, "country": 23424977, "town": 0, "planet": 1, "county": 12589274, "suburb": 0, "state": 2347589, "region": 0, "localadmin": 0}, "woe:timezone_id": 56043648, "woe:hash": "dr434etbuu3q", "woe:centroid": [-75.467972, 39.57016], "geom:latitude": 39.57016, "geom:longitude": -75.467972, "geom:hash": "dr434etbuu3q", "woe:latitude": 39.57016, "geom:centroid": [-75.467972, 39.57016], "woe:longitude": -75.467972, "woe:repo": "woeplanet-poi-us", "geom:area": 0.0, "woe:scale": 19}}