{"type": "Feature", "id": 23629731, "properties": {"woe:id": 23629731, "woe:parent_id": 2418388, "woe:name": "Wyoming Middle School", "woe:placetype": 20, "woe:placetype_name": "POI", "woe:lang": "ENG", "iso:country": "US", "meta:provider": ["geoplanet:7.3.1", "geoplanet:7.3.2", "geoplanet:7.4.0", "geoplanet:7.4.1", "geoplanet:7.5.1", "geoplanet:7.5.2", "geoplanet:7.6.0", "geoplanet:7.8.1", "geoplanet:7.9.0", "geoplanet:7.10.0", "geoplanet:8.0.0", "woeplanet:8.0.0"], "meta:indexed": "2020-08-20T20:18:54.369166", "meta:updated": "2020-08-22T02:57:45.083070", "woe:hierarchy": {"continent": 24865672, "country": 23424977, "town": 0, "planet": 1, "county": 12589557, "suburb": 0, "state": 2347594, "region": 0, "localadmin": 0}, "woe:timezone_id": 56043648, "woe:hash": "dngzjv151zcj", "woe:centroid": [-84.472427, 39.227242], "geom:latitude": 39.227242, "geom:longitude": -84.472427, "geom:hash": "dngzjv151zcj", "woe:latitude": 39.227242, "geom:centroid": [-84.472427, 39.227242], "woe:longitude": -84.472427, "woe:repo": "woeplanet-poi-us"}, "geometry": {"coordinates": [-84.472427, 39.227242], "type": "Point"}}