{"type": "Feature", "id": 56064066, "properties": {"woe:id": 56064066, "woe:parent_id": 23511866, "woe:name": "Terminals 2/3 Station", "woe:placetype": 20, "woe:placetype_name": "POI", "woe:lang": "ENG", "iso:country": "US", "meta:provider": ["geoplanet:7.3.1", "geoplanet:7.3.2", "geoplanet:7.4.0", "geoplanet:7.4.1", "geoplanet:7.5.1", "geoplanet:7.5.2", "geoplanet:7.6.0", "geoplanet:7.8.1", "geoplanet:7.9.0", "geoplanet:7.10.0", "geoplanet:8.0.0", "woeplanet:8.0.0"], "meta:indexed": "2020-08-20T20:19:20.978434", "woe:alias_ENG_V": ["Terminals 2/3 Airtrain JFK Station", "Airtrain JFK Terminals 2/3 Station", "Airtrain Jfk-Terminals 2/3"], "meta:updated": "2020-08-22T02:58:23.080698", "woe:hierarchy": {"continent": 24865672, "country": 23424977, "town": 0, "planet": 1, "county": 12589352, "suburb": 0, "state": 2347591, "region": 0, "localadmin": 0}, "woe:timezone_id": 56043648, "woe:hash": "dr5x0yy95xzb", "woe:centroid": [-73.786079, 40.642761], "geom:latitude": 40.642761, "geom:longitude": -73.786079, "geom:hash": "dr5x0yy95xzb", "woe:latitude": 40.642761, "geom:centroid": [-73.786079, 40.642761], "woe:longitude": -73.786079, "woe:repo": "woeplanet-poi-us"}, "geometry": {"coordinates": [-73.786079, 40.642761], "type": "Point"}}