{"type": "Feature", "id": 23574948, "properties": {"woe:id": 23574948, "woe:parent_id": 2455458, "woe:name": "Montgomery Co High School", "woe:placetype": 20, "woe:placetype_name": "POI", "woe:lang": "ENG", "iso:country": "US", "meta:provider": ["geoplanet:7.3.1", "geoplanet:7.3.2", "geoplanet:7.4.0", "geoplanet:7.4.1", "geoplanet:7.5.1", "geoplanet:7.5.2", "geoplanet:7.6.0", "geoplanet:7.8.1", "geoplanet:7.9.0", "geoplanet:7.10.0", "geoplanet:8.0.0", "woeplanet:8.0.0"], "meta:indexed": "2020-08-20T20:18:37.062605", "woe:alias_ENG_V": ["Montgomery Co Senior High School", "Montgomery Co High", "Montgomery Co Senior High", "Montgomery Co HS", "Montgomery Co Senior HS"], "meta:updated": "2020-08-22T02:58:47.564475", "woe:hierarchy": {"continent": 24865672, "country": 23424977, "town": 0, "planet": 1, "county": 12588562, "suburb": 0, "state": 2347576, "region": 0, "localadmin": 0}, "woe:timezone_id": 56043647, "woe:hash": "dnu23y52v98t", "woe:centroid": [-83.941833, 38.045792], "geom:latitude": 38.045792, "geom:longitude": -83.941833, "geom:hash": "dnu23y52v98t", "woe:latitude": 38.045792, "geom:centroid": [-83.941833, 38.045792], "woe:longitude": -83.941833, "woe:repo": "woeplanet-poi-us"}, "geometry": {"coordinates": [-83.941833, 38.045792], "type": "Point"}}