{"type": "Feature", "id": 23631057, "geometry": {"type": "Point", "coordinates": [-80.612648, 40.987862]}, "properties": {"woe:id": 23631057, "woe:parent_id": 2454107, "woe:name": "New Life Christian Preschool & Kindergarten", "woe:placetype": 20, "woe:placetype_name": "POI", "woe:lang": "ENG", "iso:country": "US", "meta:provider": ["geoplanet:7.3.1", "geoplanet:7.3.2", "geoplanet:7.4.0", "geoplanet:7.4.1", "geoplanet:7.5.1", "geoplanet:7.5.2", "geoplanet:7.6.0", "geoplanet:7.8.1", "geoplanet:7.9.0", "geoplanet:7.10.0", "geoplanet:8.0.0", "woeplanet:8.0.0"], "meta:indexed": "2020-08-20T20:18:54.967721", "woe:alias_ENG_V": ["New Life Christian Preschool and Kindergarten"], "meta:updated": "2020-10-14T11:19:52.019377", "woe:hierarchy": {"continent": 24865672, "country": 23424977, "town": 0, "planet": 1, "county": 12589576, "suburb": 0, "state": 2347594, "region": 0, "localadmin": 0}, "woe:timezone_id": 56043648, "woe:hash": "dpq9jteet5kb", "woe:centroid": [-80.612648, 40.987862], "geom:latitude": 40.987862, "geom:longitude": -80.612648, "geom:hash": "dpq9jteet5kb", "woe:latitude": 40.987862, "geom:centroid": [-80.612648, 40.987862], "woe:longitude": -80.612648, "woe:repo": "woeplanet-poi-us", "geom:area": 0.0, "woe:scale": 19}}