{"type": "Feature", "id": 23638561, "properties": {"woe:id": 23638561, "woe:parent_id": 2369927, "woe:name": "Jubilee Christian School", "woe:placetype": 20, "woe:placetype_name": "POI", "woe:lang": "ENG", "iso:country": "US", "meta:provider": ["geoplanet:7.3.2", "geoplanet:7.4.0", "geoplanet:7.4.1", "geoplanet:7.5.1", "geoplanet:7.5.2", "geoplanet:7.6.0", "geoplanet:7.8.1", "geoplanet:7.9.0", "geoplanet:7.10.0", "geoplanet:8.0.0", "woeplanet:8.0.0"], "meta:indexed": "2020-08-20T22:02:46.591577", "meta:updated": "2020-08-22T02:57:46.431404", "woe:hierarchy": {"continent": 24865672, "country": 23424977, "town": 0, "planet": 1, "county": 12589729, "suburb": 0, "state": 2347597, "region": 0, "localadmin": 0}, "woe:timezone_id": 56043648, "woe:hash": "dppjfcncnymf", "woe:centroid": [-80.025833, 40.391441], "geom:latitude": 40.391441, "geom:longitude": -80.025833, "geom:hash": "dppjfcncnymf", "woe:latitude": 40.391441, "geom:centroid": [-80.025833, 40.391441], "woe:longitude": -80.025833, "woe:repo": "woeplanet-poi-us"}, "geometry": {"coordinates": [-80.025833, 40.391441], "type": "Point"}}