{"type": "Feature", "id": 23542753, "geometry": {"type": "Point", "coordinates": [-73.438988, 41.173828]}, "properties": {"woe:id": 23542753, "woe:parent_id": 2521596, "woe:name": "Ina E. Driscoll School", "woe:placetype": 20, "woe:placetype_name": "POI", "woe:lang": "ENG", "iso:country": "US", "meta:provider": ["geoplanet:7.3.2", "geoplanet:7.4.0", "geoplanet:7.4.1", "geoplanet:7.5.1", "geoplanet:7.5.2", "geoplanet:7.6.0", "geoplanet:7.8.1", "geoplanet:7.9.0", "geoplanet:7.10.0", "geoplanet:8.0.0", "woeplanet:8.0.0"], "meta:indexed": "2020-08-20T22:02:06.816421", "meta:updated": "2020-10-14T11:20:24.265806", "woe:alias_ENG_V": ["Ina E Driscoll School"], "woe:hierarchy": {"continent": 24865672, "country": 23424977, "town": 0, "planet": 1, "county": 12587791, "suburb": 0, "state": 2347565, "region": 0, "localadmin": 0}, "woe:timezone_id": 56043648, "woe:hash": "dr7f0z7qgtcd", "woe:centroid": [-73.438988, 41.173828], "geom:latitude": 41.173828, "geom:longitude": -73.438988, "geom:hash": "dr7f0z7qgtcd", "woe:latitude": 41.173828, "geom:centroid": [-73.438988, 41.173828], "woe:longitude": -73.438988, "woe:repo": "woeplanet-poi-us", "geom:area": 0.0, "woe:scale": 19}}