{"type": "Feature", "id": 23576346, "properties": {"woe:id": 23576346, "woe:parent_id": 2357870, "woe:name": "Ford Henry Junior High School", "woe:placetype": 20, "woe:placetype_name": "POI", "woe:lang": "ENG", "iso:country": "US", "meta:provider": ["geoplanet:7.3.1", "geoplanet:7.3.2", "geoplanet:7.4.0", "geoplanet:7.4.1", "geoplanet:7.5.1", "geoplanet:7.5.2", "geoplanet:7.6.0", "geoplanet:7.8.1", "geoplanet:7.9.0", "geoplanet:7.10.0", "geoplanet:8.0.0", "woeplanet:8.0.0"], "meta:indexed": "2020-08-20T20:19:15.958779", "woe:alias_ENG_V": ["Henry Ford Middle School", "Ford, Henry, Junior High School", "Ford, Henry, Junior High"], "meta:updated": "2020-08-22T02:58:20.216884", "woe:hierarchy": {"continent": 24865672, "country": 23424977, "town": 0, "planet": 1, "county": 12588621, "suburb": 0, "state": 2347577, "region": 0, "localadmin": 0}, "woe:timezone_id": 56043661, "woe:hash": "9vrf57393bny", "woe:centroid": [-90.206596, 29.900881], "geom:latitude": 29.900881, "geom:longitude": -90.206596, "geom:hash": "9vrf57393bny", "woe:latitude": 29.900881, "geom:centroid": [-90.206596, 29.900881], "woe:longitude": -90.206596, "woe:repo": "woeplanet-poi-us"}, "geometry": {"coordinates": [-90.206596, 29.900881], "type": "Point"}}