{"type": "Feature", "id": 23605226, "properties": {"woe:id": 23605226, "woe:parent_id": 55861346, "woe:name": "Bd Billinghurst Middle School", "woe:placetype": 20, "woe:placetype_name": "POI", "woe:lang": "ENG", "iso:country": "US", "meta:provider": ["geoplanet:7.4.0", "geoplanet:7.4.1", "geoplanet:7.5.1", "geoplanet:7.5.2", "geoplanet:7.6.0", "geoplanet:7.8.1", "geoplanet:7.9.0", "geoplanet:7.10.0", "geoplanet:8.0.0", "woeplanet:8.0.0"], "meta:indexed": "2020-08-20T23:55:17.337756", "meta:updated": "2020-08-22T02:57:41.665215", "woe:hierarchy": {"continent": 24865672, "country": 23424977, "town": 0, "planet": 1, "county": 12589246, "suburb": 0, "state": 2347587, "region": 0, "localadmin": 0}, "woe:timezone_id": 56043663, "woe:hash": "9r48zdwteepj", "woe:centroid": [-119.895699, 39.52153], "geom:latitude": 39.52153, "geom:longitude": -119.895699, "geom:hash": "9r48zdwteepj", "woe:latitude": 39.52153, "geom:centroid": [-119.895699, 39.52153], "woe:longitude": -119.895699, "woe:repo": "woeplanet-poi-us"}, "geometry": {"coordinates": [-119.895699, 39.52153], "type": "Point"}}