{"type": "Feature", "id": 23675686, "properties": {"woe:id": 23675686, "woe:parent_id": 2478038, "woe:name": "St Johns Lutheran School", "woe:placetype": 20, "woe:placetype_name": "POI", "woe:lang": "ENG", "iso:country": "US", "meta:provider": ["geoplanet:7.3.1", "geoplanet:7.3.2", "geoplanet:7.4.0", "geoplanet:7.4.1", "geoplanet:7.5.1", "geoplanet:7.5.2", "geoplanet:7.6.0", "geoplanet:7.8.1", "geoplanet:7.9.0", "geoplanet:7.10.0", "geoplanet:8.0.0", "woeplanet:8.0.0"], "meta:indexed": "2020-08-20T20:19:11.631294", "meta:updated": "2020-08-22T02:58:18.188299", "woe:hierarchy": {"continent": 24865672, "country": 23424977, "town": 0, "planet": 1, "county": 12590585, "suburb": 0, "state": 2347608, "region": 0, "localadmin": 0}, "woe:timezone_id": 56043661, "woe:hash": "dp9e4kknxk96", "woe:centroid": [-87.785942, 42.73933], "geom:latitude": 42.73933, "geom:longitude": -87.785942, "geom:hash": "dp9e4kknxk96", "woe:latitude": 42.73933, "geom:centroid": [-87.785942, 42.73933], "woe:longitude": -87.785942, "woe:repo": "woeplanet-poi-us"}, "geometry": {"coordinates": [-87.785942, 42.73933], "type": "Point"}}