{"type": "Feature", "id": 23575691, "properties": {"woe:id": 23575691, "woe:parent_id": 55861892, "woe:name": "Creswell Elementary School", "woe:placetype": 20, "woe:placetype_name": "POI", "woe:lang": "ENG", "iso:country": "US", "meta:provider": ["geoplanet:7.3.1", "geoplanet:7.3.2", "geoplanet:7.4.0", "geoplanet:7.4.1", "geoplanet:7.5.1", "geoplanet:7.5.2", "geoplanet:7.6.0", "geoplanet:7.8.1", "geoplanet:7.9.0", "geoplanet:7.10.0", "geoplanet:8.0.0", "woeplanet:8.0.0"], "meta:indexed": "2020-08-20T20:18:37.249676", "woe:alias_ENG_V": ["Creswell Elementary"], "meta:updated": "2020-08-22T02:57:37.125175", "woe:hierarchy": {"continent": 24865672, "country": 23424977, "town": 0, "planet": 1, "county": 12588604, "suburb": 0, "state": 2347577, "region": 0, "localadmin": 0}, "woe:timezone_id": 56043661, "woe:hash": "9vv2fc7q9gyk", "woe:centroid": [-93.741791, 32.483589], "geom:latitude": 32.483589, "geom:longitude": -93.741791, "geom:hash": "9vv2fc7q9gyk", "woe:latitude": 32.483589, "geom:centroid": [-93.741791, 32.483589], "woe:longitude": -93.741791, "woe:repo": "woeplanet-poi-us"}, "geometry": {"coordinates": [-93.741791, 32.483589], "type": "Point"}}