{"type": "Feature", "id": 23648378, "geometry": {"type": "Point", "coordinates": [-98.017029, 43.716518]}, "properties": {"woe:id": 23648378, "woe:parent_id": 2452429, "woe:name": "Mitchell High School", "woe:placetype": 20, "woe:placetype_name": "POI", "woe:lang": "ENG", "iso:country": "US", "meta:provider": ["geoplanet:7.3.1", "geoplanet:7.3.2", "geoplanet:7.4.0", "geoplanet:7.4.1", "geoplanet:7.5.1", "geoplanet:7.5.2", "geoplanet:7.6.0", "geoplanet:7.8.1", "geoplanet:7.9.0", "geoplanet:7.10.0", "geoplanet:8.0.0", "woeplanet:8.0.0"], "meta:indexed": "2020-08-20T20:19:01.131978", "woe:alias_ENG_V": ["Mitchell Senior High School", "Mitchell High", "Mitchell Senior High", "Mitchell HS", "Mitchell Senior HS"], "meta:updated": "2020-10-14T11:19:29.913753", "woe:hierarchy": {"continent": 24865672, "country": 23424977, "town": 0, "planet": 1, "county": 12589862, "suburb": 0, "state": 2347600, "region": 0, "localadmin": 0}, "woe:timezone_id": 56043661, "woe:hash": "9zf29w65jttg", "woe:centroid": [-98.017029, 43.716518], "geom:latitude": 43.716518, "geom:longitude": -98.017029, "geom:hash": "9zf29w65jttg", "woe:latitude": 43.716518, "geom:centroid": [-98.017029, 43.716518], "woe:longitude": -98.017029, "woe:repo": "woeplanet-poi-us", "geom:area": 0.0, "woe:scale": 19}}