{"type": "Feature", "id": 23571309, "geometry": {"type": "Point", "coordinates": [-97.216507, 38.928501]}, "properties": {"woe:id": 23571309, "woe:parent_id": 2351597, "woe:name": "Abilene High School", "woe:placetype": 20, "woe:placetype_name": "POI", "woe:lang": "ENG", "iso:country": "US", "meta:provider": ["geoplanet:7.3.1", "geoplanet:7.3.2", "geoplanet:7.4.0", "geoplanet:7.4.1", "geoplanet:7.5.1", "geoplanet:7.5.2", "geoplanet:7.6.0", "geoplanet:7.8.1", "geoplanet:7.9.0", "geoplanet:7.10.0", "geoplanet:8.0.0", "woeplanet:8.0.0"], "meta:indexed": "2020-08-20T20:18:35.869157", "woe:alias_ENG_V": ["Abilene Senior High School", "Abilene High", "Abilene Senior High", "Abilene HS", "Abilene Senior HS"], "meta:updated": "2020-10-14T11:20:18.743079", "woe:hierarchy": {"continent": 24865672, "country": 23424977, "town": 0, "planet": 1, "county": 12588391, "suburb": 0, "state": 2347575, "region": 0, "localadmin": 0}, "woe:timezone_id": 56043661, "woe:hash": "9yfv7y9ngnw3", "woe:centroid": [-97.216507, 38.928501], "geom:latitude": 38.928501, "geom:longitude": -97.216507, "geom:hash": "9yfv7y9ngnw3", "woe:latitude": 38.928501, "geom:centroid": [-97.216507, 38.928501], "woe:longitude": -97.216507, "woe:repo": "woeplanet-poi-us", "geom:area": 0.0, "woe:scale": 19}}