{"type": "Feature", "id": 23656565, "geometry": {"type": "Point", "coordinates": [-97.35379, 32.803188]}, "properties": {"woe:id": 23656565, "woe:parent_id": 56022745, "woe:name": "Washington Heights Elementary School", "woe:placetype": 20, "woe:placetype_name": "POI", "woe:lang": "ENG", "iso:country": "US", "meta:provider": ["geoplanet:7.3.1", "geoplanet:7.3.2", "geoplanet:7.4.0", "geoplanet:7.4.1", "geoplanet:7.5.1", "geoplanet:7.5.2", "geoplanet:7.6.0", "geoplanet:7.8.1", "geoplanet:7.9.0", "geoplanet:7.10.0", "geoplanet:8.0.0", "woeplanet:8.0.0"], "meta:indexed": "2020-08-20T20:19:04.441390", "woe:alias_ENG_V": ["Washington Heights Elementary"], "meta:updated": "2020-10-14T11:19:51.950458", "woe:hierarchy": {"continent": 24865672, "country": 23424977, "town": 0, "planet": 1, "county": 12590226, "suburb": 0, "state": 2347602, "region": 0, "localadmin": 0}, "woe:timezone_id": 56043661, "woe:hash": "9vff8ethkm2w", "woe:centroid": [-97.35379, 32.803188], "geom:latitude": 32.803188, "geom:longitude": -97.35379, "geom:hash": "9vff8ethkm2w", "woe:latitude": 32.803188, "geom:centroid": [-97.35379, 32.803188], "woe:longitude": -97.35379, "woe:repo": "woeplanet-poi-us", "geom:area": 0.0, "woe:scale": 19}}