{"type": "Feature", "id": 23514140, "properties": {"woe:id": 23514140, "woe:parent_id": 55860386, "woe:name": "Jefferson Davis High School", "woe:placetype": 20, "woe:placetype_name": "POI", "woe:lang": "ENG", "iso:country": "US", "meta:provider": ["geoplanet:7.3.1", "geoplanet:7.3.2", "geoplanet:7.4.0", "geoplanet:7.4.1", "geoplanet:7.5.1", "geoplanet:7.5.2", "geoplanet:7.6.0", "geoplanet:7.8.1", "geoplanet:7.9.0", "geoplanet:7.10.0", "geoplanet:8.0.0", "woeplanet:8.0.0"], "meta:indexed": "2020-08-20T20:18:17.645253", "woe:alias_ENG_V": ["Jefferson Davis Senior High School", "Jefferson Davis High", "Jefferson Davis Senior High", "Jefferson Davis HS", "Jefferson Davis Senior HS", "Jefferson Davis Sr High", "Jefferson Davis Sr High School", "Jefferson Davis Sr HS", "Jefferson Davis Sr Senior High", "Jefferson Davis Sr Senior High School", "Jefferson Davis Sr Senior HS"], "meta:updated": "2020-08-22T02:58:45.881293", "woe:hierarchy": {"continent": 24865672, "country": 23424977, "town": 0, "planet": 1, "county": 12587537, "suburb": 0, "state": 2347559, "region": 0, "localadmin": 0}, "woe:timezone_id": 56043661, "woe:hash": "djdxvpf9xwst", "woe:centroid": [-86.260887, 32.34267], "geom:latitude": 32.34267, "geom:longitude": -86.260887, "geom:hash": "djdxvpf9xwst", "woe:latitude": 32.34267, "geom:centroid": [-86.260887, 32.34267], "woe:longitude": -86.260887, "woe:repo": "woeplanet-poi-us"}, "geometry": {"coordinates": [-86.260887, 32.34267], "type": "Point"}}