{"type": "Feature", "id": 23598974, "properties": {"woe:id": 23598974, "woe:parent_id": 2468854, "woe:name": "Parnell Elementary School", "woe:placetype": 20, "woe:placetype_name": "POI", "woe:lang": "ENG", "iso:country": "US", "meta:provider": ["geoplanet:7.3.1", "geoplanet:7.3.2", "geoplanet:7.4.0", "geoplanet:7.4.1", "geoplanet:7.5.1", "geoplanet:7.5.2", "geoplanet:7.6.0", "geoplanet:7.8.1", "geoplanet:7.9.0", "geoplanet:7.10.0", "geoplanet:8.0.0", "woeplanet:8.0.0"], "meta:indexed": "2020-08-20T20:18:44.475941", "woe:alias_ENG_V": ["Parnell Elementary"], "meta:updated": "2020-08-22T02:57:40.880500", "woe:hierarchy": {"continent": 24865672, "country": 23424977, "town": 0, "planet": 1, "county": 12589039, "suburb": 0, "state": 2347584, "region": 0, "localadmin": 0}, "woe:timezone_id": 56043661, "woe:hash": "9zhwnctpcbq2", "woe:centroid": [-94.618294, 40.439259], "geom:latitude": 40.439259, "geom:longitude": -94.618294, "geom:hash": "9zhwnctpcbq2", "woe:latitude": 40.439259, "geom:centroid": [-94.618294, 40.439259], "woe:longitude": -94.618294, "woe:repo": "woeplanet-poi-us"}, "geometry": {"coordinates": [-94.618294, 40.439259], "type": "Point"}}