{"type": "Feature", "id": 23617959, "properties": {"woe:id": 23617959, "woe:parent_id": 2461718, "woe:name": "North Tonawanda Senior High School", "woe:placetype": 20, "woe:placetype_name": "POI", "woe:lang": "ENG", "iso:country": "US", "meta:provider": ["geoplanet:7.3.1", "geoplanet:7.3.2", "geoplanet:7.4.0", "geoplanet:7.4.1", "geoplanet:7.5.1", "geoplanet:7.5.2", "geoplanet:7.6.0", "geoplanet:7.8.1", "geoplanet:7.9.0", "geoplanet:7.10.0", "geoplanet:8.0.0", "woeplanet:8.0.0"], "meta:indexed": "2020-08-20T20:18:50.623648", "woe:alias_ENG_V": ["North Tonawanda Senior High", "North Tonawanda High School", "North Tonawanda High", "North Tonawanda Senior HS", "North Tonawanda HS", "N Tonawanda Senior High", "N Tonawanda Senior Senior High", "N Tonawanda Senior Senior HS", "N Tonawanda Senior HS", "N Tonawanda Senior Senior High School", "N Tonawanda Senior High School", "N Tonawanda High School", "N Tonawanda High", "N Tonawanda HS"], "meta:updated": "2020-08-22T02:58:48.781482", "woe:hierarchy": {"continent": 24865672, "country": 23424977, "town": 0, "planet": 1, "county": 12589343, "suburb": 0, "state": 2347591, "region": 0, "localadmin": 0}, "woe:timezone_id": 56043648, "woe:hash": "dpxuvm2stt29", "woe:centroid": [-78.869926, 43.052101], "geom:latitude": 43.052101, "geom:longitude": -78.869926, "geom:hash": "dpxuvm2stt29", "woe:latitude": 43.052101, "geom:centroid": [-78.869926, 43.052101], "woe:longitude": -78.869926, "woe:repo": "woeplanet-poi-us"}, "geometry": {"coordinates": [-78.869926, 43.052101], "type": "Point"}}