{"type": "Feature", "id": 23664517, "geometry": {"type": "Point", "coordinates": [-77.995132, 38.475201]}, "properties": {"woe:id": 23664517, "woe:parent_id": 2388161, "woe:name": "Epiphany Catholic School", "woe:placetype": 20, "woe:placetype_name": "POI", "woe:lang": "ENG", "iso:country": "US", "meta:provider": ["geoplanet:7.3.1", "geoplanet:7.3.2", "geoplanet:7.4.0", "geoplanet:7.4.1", "geoplanet:7.5.1", "geoplanet:7.5.2", "geoplanet:7.6.0", "geoplanet:7.8.1", "geoplanet:7.9.0", "geoplanet:7.10.0", "geoplanet:8.0.0", "woeplanet:8.0.0"], "meta:indexed": "2020-08-20T20:19:07.773930", "meta:updated": "2020-10-14T11:19:39.911372", "woe:hierarchy": {"continent": 24865672, "country": 23424977, "town": 0, "planet": 1, "county": 12590336, "suburb": 0, "state": 2347605, "region": 0, "localadmin": 0}, "woe:timezone_id": 56043648, "woe:hash": "dqbdchjwm9q3", "woe:centroid": [-77.995132, 38.475201], "geom:latitude": 38.475201, "geom:longitude": -77.995132, "geom:hash": "dqbdchjwm9q3", "woe:latitude": 38.475201, "geom:centroid": [-77.995132, 38.475201], "woe:longitude": -77.995132, "woe:repo": "woeplanet-poi-us", "geom:area": 0.0, "woe:scale": 19}}