{"type": "Feature", "id": 23583314, "properties": {"woe:id": 23583314, "woe:parent_id": 2414303, "woe:name": "Cornerstone Christian School", "woe:placetype": 20, "woe:placetype_name": "POI", "woe:lang": "ENG", "iso:country": "US", "meta:provider": ["geoplanet:7.3.1", "geoplanet:7.3.2", "geoplanet:7.4.0", "geoplanet:7.4.1", "geoplanet:7.5.1", "geoplanet:7.5.2", "geoplanet:7.6.0", "geoplanet:7.8.1", "geoplanet:7.9.0", "geoplanet:7.10.0", "geoplanet:8.0.0", "woeplanet:8.0.0"], "meta:indexed": "2020-08-20T20:18:39.228232", "meta:updated": "2020-08-22T02:57:38.323941", "woe:hierarchy": {"continent": 24865672, "country": 23424977, "town": 0, "planet": 1, "county": 12588705, "suburb": 0, "state": 2347580, "region": 0, "localadmin": 0}, "woe:timezone_id": 56043648, "woe:hash": "drs67ggz6c4v", "woe:centroid": [-72.603371, 42.604858], "geom:latitude": 42.604858, "geom:longitude": -72.603371, "geom:hash": "drs67ggz6c4v", "woe:latitude": 42.604858, "geom:centroid": [-72.603371, 42.604858], "woe:longitude": -72.603371, "woe:repo": "woeplanet-poi-us"}, "geometry": {"coordinates": [-72.603371, 42.604858], "type": "Point"}}