{"type": "Feature", "id": 23600620, "geometry": {"type": "Point", "coordinates": [-112.63723, 45.213989]}, "properties": {"woe:id": 23600620, "woe:parent_id": 2392109, "woe:name": "Mary Innes School", "woe:placetype": 20, "woe:placetype_name": "POI", "woe:lang": "ENG", "iso:country": "US", "meta:provider": ["geoplanet:7.3.1", "geoplanet:7.3.2", "geoplanet:7.4.0", "geoplanet:7.4.1", "geoplanet:7.5.1", "geoplanet:7.5.2", "geoplanet:7.6.0", "geoplanet:7.8.1", "geoplanet:7.9.0", "geoplanet:7.10.0", "geoplanet:8.0.0", "woeplanet:8.0.0"], "meta:indexed": "2020-08-20T20:18:45.119719", "meta:updated": "2020-10-14T11:19:46.586198", "woe:hierarchy": {"continent": 24865672, "country": 23424977, "town": 0, "planet": 1, "county": 12589081, "suburb": 0, "state": 2347585, "region": 0, "localadmin": 0}, "woe:timezone_id": 56043665, "woe:hash": "c2pchyund63y", "woe:centroid": [-112.63723, 45.213989], "geom:latitude": 45.213989, "geom:longitude": -112.63723, "geom:hash": "c2pchyund63y", "woe:latitude": 45.213989, "geom:centroid": [-112.63723, 45.213989], "woe:longitude": -112.63723, "woe:repo": "woeplanet-poi-us", "geom:area": 0.0, "woe:scale": 19}}