{"type": "Feature", "id": 23607543, "properties": {"woe:id": 23607543, "woe:parent_id": 2448924, "woe:name": "Cranberry Pine Elementary School", "woe:placetype": 20, "woe:placetype_name": "POI", "woe:lang": "ENG", "iso:country": "US", "meta:provider": ["geoplanet:7.3.1", "geoplanet:7.3.2", "geoplanet:7.4.0", "geoplanet:7.4.1", "geoplanet:7.5.1", "geoplanet:7.5.2", "geoplanet:7.6.0", "geoplanet:7.8.1", "geoplanet:7.9.0", "geoplanet:7.10.0", "geoplanet:8.0.0", "woeplanet:8.0.0"], "meta:indexed": "2020-08-20T20:18:46.790590", "woe:alias_ENG_V": ["Cranberry Pines School", "Cranberry Pine Elementary"], "meta:updated": "2020-08-22T02:57:41.935636", "woe:hierarchy": {"continent": 24865672, "country": 23424977, "town": 0, "planet": 1, "county": 12589260, "suburb": 0, "state": 2347589, "region": 0, "localadmin": 0}, "woe:timezone_id": 56043648, "woe:hash": "dr4f8z30hknt", "woe:centroid": [-74.848289, 39.854301], "geom:latitude": 39.854301, "geom:longitude": -74.848289, "geom:hash": "dr4f8z30hknt", "woe:latitude": 39.854301, "geom:centroid": [-74.848289, 39.854301], "woe:longitude": -74.848289, "woe:repo": "woeplanet-poi-us"}, "geometry": {"coordinates": [-74.848289, 39.854301], "type": "Point"}}