{"type": "Feature", "id": 23588525, "geometry": {"type": "Point", "coordinates": [-83.772018, 42.507561]}, "properties": {"woe:id": 23588525, "woe:parent_id": 2468309, "woe:name": "Hawkins Elementary School", "woe:placetype": 20, "woe:placetype_name": "POI", "woe:lang": "ENG", "iso:country": "US", "meta:provider": ["geoplanet:7.3.1", "geoplanet:7.3.2", "geoplanet:7.4.0", "geoplanet:7.4.1", "geoplanet:7.5.1", "geoplanet:7.5.2", "geoplanet:7.6.0", "geoplanet:7.8.1", "geoplanet:7.9.0", "geoplanet:7.10.0", "geoplanet:8.0.0", "woeplanet:8.0.0"], "meta:indexed": "2020-08-20T20:18:40.623124", "woe:alias_ENG_V": ["Hawkins Elementary"], "meta:updated": "2020-10-14T11:20:08.886784", "woe:hierarchy": {"continent": 24865672, "country": 23424977, "town": 0, "planet": 1, "county": 12588760, "suburb": 0, "state": 2347581, "region": 0, "localadmin": 0}, "woe:timezone_id": 56043658, "woe:hash": "dps3vdr06rxy", "woe:centroid": [-83.772018, 42.507561], "geom:latitude": 42.507561, "geom:longitude": -83.772018, "geom:hash": "dps3vdr06rxy", "woe:latitude": 42.507561, "geom:centroid": [-83.772018, 42.507561], "woe:longitude": -83.772018, "woe:repo": "woeplanet-poi-us", "geom:area": 0.0, "woe:scale": 19}}