{"type": "Feature", "id": 23658236, "properties": {"woe:id": 23658236, "woe:parent_id": 2407353, "woe:name": "Freer High School", "woe:placetype": 20, "woe:placetype_name": "POI", "woe:lang": "ENG", "iso:country": "US", "meta:provider": ["geoplanet:7.3.1", "geoplanet:7.3.2", "geoplanet:7.4.0", "geoplanet:7.4.1", "geoplanet:7.5.1", "geoplanet:7.5.2", "geoplanet:7.6.0", "geoplanet:7.8.1", "geoplanet:7.9.0", "geoplanet:7.10.0", "geoplanet:8.0.0", "woeplanet:8.0.0"], "meta:indexed": "2020-08-20T20:19:05.328277", "woe:alias_ENG_V": ["Freer Senior High School", "Freer High", "Freer Senior High", "Freer HS", "Freer Senior HS"], "meta:updated": "2020-08-22T02:58:49.980497", "woe:hierarchy": {"continent": 24865672, "country": 23424977, "town": 0, "planet": 1, "county": 12590072, "suburb": 0, "state": 2347602, "region": 0, "localadmin": 0}, "woe:timezone_id": 56043661, "woe:hash": "9ucyefkw5bmj", "woe:centroid": [-98.61792, 27.87472], "geom:latitude": 27.87472, "geom:longitude": -98.61792, "geom:hash": "9ucyefkw5bmj", "woe:latitude": 27.87472, "geom:centroid": [-98.61792, 27.87472], "woe:longitude": -98.61792, "woe:repo": "woeplanet-poi-us"}, "geometry": {"coordinates": [-98.61792, 27.87472], "type": "Point"}}