{"type": "Feature", "id": 23515864, "geometry": {"type": "Point", "coordinates": [-112.134087, 33.518921]}, "properties": {"woe:id": 23515864, "woe:parent_id": 2353133, "woe:name": "Cordova Primary School", "woe:placetype": 20, "woe:placetype_name": "POI", "woe:lang": "ENG", "iso:country": "US", "meta:provider": ["geoplanet:7.3.1", "geoplanet:7.3.2", "geoplanet:7.4.0", "geoplanet:7.4.1", "geoplanet:7.5.1", "geoplanet:7.5.2", "geoplanet:7.6.0", "geoplanet:7.8.1", "geoplanet:7.9.0", "geoplanet:7.10.0", "geoplanet:8.0.0", "woeplanet:8.0.0"], "meta:indexed": "2020-08-20T20:18:18.087894", "meta:updated": "2020-10-14T11:20:15.336603", "woe:alias_ENG_V": ["Cordova Middle School"], "woe:hierarchy": {"continent": 24865672, "country": 23424977, "town": 0, "planet": 1, "county": 12587587, "suburb": 0, "state": 2347561, "region": 0, "localadmin": 0}, "woe:timezone_id": 56043666, "woe:hash": "9tbq8mfmy7u8", "woe:centroid": [-112.134087, 33.518921], "geom:latitude": 33.518921, "geom:longitude": -112.134087, "geom:hash": "9tbq8mfmy7u8", "woe:latitude": 33.518921, "geom:centroid": [-112.134087, 33.518921], "woe:longitude": -112.134087, "woe:repo": "woeplanet-poi-us", "geom:area": 0.0, "woe:scale": 19}}