{"type": "Feature", "id": 23650034, "geometry": {"type": "Point", "coordinates": [-82.690178, 36.214329]}, "properties": {"woe:id": 23650034, "woe:parent_id": 2380193, "woe:name": "Chuckey Elementary School", "woe:placetype": 20, "woe:placetype_name": "POI", "woe:lang": "ENG", "iso:country": "US", "meta:provider": ["geoplanet:7.3.2", "geoplanet:7.4.0", "geoplanet:7.4.1", "geoplanet:7.5.1", "geoplanet:7.5.2", "geoplanet:7.6.0", "geoplanet:7.8.1", "geoplanet:7.9.0", "geoplanet:7.10.0", "geoplanet:8.0.0", "woeplanet:8.0.0"], "meta:indexed": "2020-08-20T22:02:50.927359", "woe:alias_ENG_V": ["Chuckey Elementary"], "meta:updated": "2020-10-14T11:19:34.607687", "woe:hierarchy": {"continent": 24865672, "country": 23424977, "town": 0, "planet": 1, "county": 12589941, "suburb": 0, "state": 2347601, "region": 0, "localadmin": 0}, "woe:timezone_id": 56043648, "woe:hash": "dnmnn2dgg0nr", "woe:centroid": [-82.690178, 36.214329], "geom:latitude": 36.214329, "geom:longitude": -82.690178, "geom:hash": "dnmnn2dgg0nr", "woe:latitude": 36.214329, "geom:centroid": [-82.690178, 36.214329], "woe:longitude": -82.690178, "woe:repo": "woeplanet-poi-us", "geom:area": 0.0, "woe:scale": 19}}