{"type": "Feature", "id": 23652945, "geometry": {"type": "Point", "coordinates": [-96.699249, 33.119671]}, "properties": {"woe:id": 23652945, "woe:parent_id": 2353276, "woe:name": "Kerr Elementary School", "woe:placetype": 20, "woe:placetype_name": "POI", "woe:lang": "ENG", "iso:country": "US", "meta:provider": ["geoplanet:7.3.2", "geoplanet:7.4.0", "geoplanet:7.4.1", "geoplanet:7.5.1", "geoplanet:7.5.2", "geoplanet:7.6.0", "geoplanet:7.8.1", "geoplanet:7.9.0", "geoplanet:7.10.0", "geoplanet:8.0.0", "woeplanet:8.0.0"], "meta:indexed": "2020-08-20T22:02:52.051358", "woe:alias_ENG_V": ["Kerr Elementary"], "meta:updated": "2020-10-14T11:19:51.023256", "woe:hierarchy": {"continent": 24865672, "country": 23424977, "town": 0, "planet": 1, "county": 12590049, "suburb": 0, "state": 2347602, "region": 0, "localadmin": 0}, "woe:timezone_id": 56043661, "woe:hash": "9vghrt3b04jv", "woe:centroid": [-96.699249, 33.119671], "geom:latitude": 33.119671, "geom:longitude": -96.699249, "geom:hash": "9vghrt3b04jv", "woe:latitude": 33.119671, "geom:centroid": [-96.699249, 33.119671], "woe:longitude": -96.699249, "woe:repo": "woeplanet-poi-us", "geom:area": 0.0, "woe:scale": 19}}