{"type": "Feature", "id": 23540019, "geometry": {"type": "Point", "coordinates": [-104.856354, 39.37257]}, "properties": {"woe:id": 23540019, "woe:parent_id": 2376128, "woe:name": "Cantril School", "woe:placetype": 20, "woe:placetype_name": "POI", "woe:lang": "ENG", "iso:country": "US", "meta:provider": ["geoplanet:7.3.1", "geoplanet:7.3.2", "geoplanet:7.4.0", "geoplanet:7.4.1", "geoplanet:7.5.1", "geoplanet:7.5.2", "geoplanet:7.6.0", "geoplanet:7.8.1", "geoplanet:7.9.0", "geoplanet:7.10.0", "geoplanet:8.0.0", "woeplanet:8.0.0"], "meta:indexed": "2020-08-20T20:18:24.318570", "meta:updated": "2020-10-14T11:20:29.015144", "woe:hierarchy": {"continent": 24865672, "country": 23424977, "town": 0, "planet": 1, "county": 12587745, "suburb": 0, "state": 2347564, "region": 0, "localadmin": 0}, "woe:timezone_id": 56043665, "woe:hash": "9wvrvztcvg58", "woe:centroid": [-104.856354, 39.37257], "geom:latitude": 39.37257, "geom:longitude": -104.856354, "geom:hash": "9wvrvztcvg58", "woe:latitude": 39.37257, "geom:centroid": [-104.856354, 39.37257], "woe:longitude": -104.856354, "woe:repo": "woeplanet-poi-us", "geom:area": 0.0, "woe:scale": 19}}