{"type": "Feature", "id": 23599701, "geometry": {"type": "Point", "coordinates": [-90.501343, 38.603569]}, "properties": {"woe:id": 23599701, "woe:parent_id": 2444653, "woe:name": "Pierremont Elementary School", "woe:placetype": 20, "woe:placetype_name": "POI", "woe:lang": "ENG", "iso:country": "US", "meta:provider": ["geoplanet:7.3.1", "geoplanet:7.3.2", "geoplanet:7.4.0", "geoplanet:7.4.1", "geoplanet:7.5.1", "geoplanet:7.5.2", "geoplanet:7.6.0", "geoplanet:7.8.1", "geoplanet:7.9.0", "geoplanet:7.10.0", "geoplanet:8.0.0", "woeplanet:8.0.0"], "meta:indexed": "2020-08-20T20:18:44.757984", "woe:alias_ENG_V": ["Pierremont Elementary"], "meta:updated": "2020-10-14T11:20:28.144392", "woe:hierarchy": {"continent": 24865672, "country": 23424977, "town": 0, "planet": 1, "county": 12589066, "suburb": 0, "state": 2347584, "region": 0, "localadmin": 0}, "woe:timezone_id": 56043661, "woe:hash": "9yzesedfjfgd", "woe:centroid": [-90.501343, 38.603569], "geom:latitude": 38.603569, "geom:longitude": -90.501343, "geom:hash": "9yzesedfjfgd", "woe:latitude": 38.603569, "geom:centroid": [-90.501343, 38.603569], "woe:longitude": -90.501343, "woe:repo": "woeplanet-poi-us", "geom:area": 0.0, "woe:scale": 19}}