{"type": "Feature", "id": 23554996, "geometry": {"type": "Point", "coordinates": [-158.018463, 21.50152]}, "properties": {"woe:id": 23554996, "woe:parent_id": 55986163, "woe:name": "Leeward Adventist Mission School", "woe:placetype": 20, "woe:placetype_name": "POI", "woe:lang": "ENG", "iso:country": "US", "meta:provider": ["geoplanet:7.3.1", "geoplanet:7.3.2", "geoplanet:7.4.0", "geoplanet:7.4.1", "geoplanet:7.5.1", "geoplanet:7.5.2", "geoplanet:7.6.0", "geoplanet:7.8.1", "geoplanet:7.9.0", "geoplanet:7.10.0", "geoplanet:8.0.0", "woeplanet:8.0.0"], "meta:indexed": "2020-08-20T20:18:30.044111", "meta:updated": "2020-10-14T11:20:04.637313", "woe:hierarchy": {"continent": 24865672, "country": 23424977, "town": 0, "planet": 1, "county": 12588030, "suburb": 0, "state": 2347570, "region": 0, "localadmin": 0}, "woe:timezone_id": 28350949, "woe:hash": "87zdk4nrqvvf", "woe:centroid": [-158.018463, 21.50152], "geom:latitude": 21.50152, "geom:longitude": -158.018463, "geom:hash": "87zdk4nrqvvf", "woe:latitude": 21.50152, "geom:centroid": [-158.018463, 21.50152], "woe:longitude": -158.018463, "woe:repo": "woeplanet-poi-us", "geom:area": 0.0, "woe:scale": 19}}