{"type": "Feature", "id": 23633453, "properties": {"woe:id": 23633453, "woe:parent_id": 2393823, "woe:name": "Edison Elementary School", "woe:placetype": 20, "woe:placetype_name": "POI", "woe:lang": "ENG", "iso:country": "US", "meta:provider": ["geoplanet:7.3.1", "geoplanet:7.3.2", "geoplanet:7.4.0", "geoplanet:7.4.1", "geoplanet:7.5.1", "geoplanet:7.5.2", "geoplanet:7.6.0", "geoplanet:7.8.1", "geoplanet:7.9.0", "geoplanet:7.10.0", "geoplanet:8.0.0", "woeplanet:8.0.0"], "meta:indexed": "2020-08-20T20:18:56.074377", "woe:alias_ENG_V": ["Edison Middle School", "Edison Elementary"], "meta:updated": "2020-08-22T02:57:45.701798", "woe:hierarchy": {"continent": 24865672, "country": 23424977, "town": 0, "planet": 1, "county": 12589633, "suburb": 0, "state": 2347595, "region": 0, "localadmin": 0}, "woe:timezone_id": 56043661, "woe:hash": "9y7kcbeq5n2v", "woe:centroid": [-96.59819, 35.995022], "geom:latitude": 35.995022, "geom:longitude": -96.59819, "geom:hash": "9y7kcbeq5n2v", "woe:latitude": 35.995022, "geom:centroid": [-96.59819, 35.995022], "woe:longitude": -96.59819, "woe:repo": "woeplanet-poi-us"}, "geometry": {"coordinates": [-96.59819, 35.995022], "type": "Point"}}