{"type": "Feature", "id": 23593711, "properties": {"woe:id": 23593711, "woe:parent_id": 55806410, "woe:name": "Butler Quarter Station", "woe:placetype": 20, "woe:placetype_name": "POI", "woe:lang": "ENG", "iso:country": "US", "meta:provider": ["geoplanet:7.3.1", "geoplanet:7.3.2", "geoplanet:7.4.0", "geoplanet:7.4.1", "geoplanet:7.5.1", "geoplanet:7.5.2", "geoplanet:7.6.0", "geoplanet:7.8.1", "geoplanet:7.9.0", "geoplanet:7.10.0", "geoplanet:8.0.0", "woeplanet:8.0.0"], "meta:indexed": "2020-08-20T20:18:42.567066", "meta:updated": "2020-08-22T02:57:40.020644", "woe:hierarchy": {"continent": 24865672, "country": 23424977, "town": 0, "planet": 1, "county": 12588823, "suburb": 0, "state": 2347582, "region": 0, "localadmin": 0}, "woe:timezone_id": 56043661, "woe:hash": "9zvxvkr3swhh", "woe:centroid": [-93.274757, 44.979691], "geom:latitude": 44.979691, "geom:longitude": -93.274757, "geom:hash": "9zvxvkr3swhh", "woe:latitude": 44.979691, "geom:centroid": [-93.274757, 44.979691], "woe:longitude": -93.274757, "woe:repo": "woeplanet-poi-us"}, "geometry": {"coordinates": [-93.274757, 44.979691], "type": "Point"}}