{"type": "Feature", "id": 23536126, "properties": {"woe:id": 23536126, "woe:parent_id": 55861637, "woe:name": "San Andreas High School", "woe:placetype": 20, "woe:placetype_name": "POI", "woe:lang": "ENG", "iso:country": "US", "meta:provider": ["geoplanet:7.3.2", "geoplanet:7.4.0", "geoplanet:7.4.1", "geoplanet:7.5.1", "geoplanet:7.5.2", "geoplanet:7.6.0", "geoplanet:7.8.1", "geoplanet:7.9.0", "geoplanet:7.10.0", "geoplanet:8.0.0", "woeplanet:8.0.0"], "meta:indexed": "2020-08-20T22:02:04.538949", "woe:alias_ENG_V": ["San Andreas Senior High School", "San Andreas High", "San Andreas Senior High", "San Andreas HS", "San Andreas Senior HS"], "meta:updated": "2020-08-22T02:58:46.479760", "woe:hierarchy": {"continent": 24865672, "country": 23424977, "town": 0, "planet": 1, "county": 12587705, "suburb": 0, "state": 2347563, "region": 0, "localadmin": 0}, "woe:timezone_id": 56043663, "woe:hash": "9qhdhsvkbvus", "woe:centroid": [-117.216873, 34.128502], "geom:latitude": 34.128502, "geom:longitude": -117.216873, "geom:hash": "9qhdhsvkbvus", "woe:latitude": 34.128502, "geom:centroid": [-117.216873, 34.128502], "woe:longitude": -117.216873, "woe:repo": "woeplanet-poi-us"}, "geometry": {"coordinates": [-117.216873, 34.128502], "type": "Point"}}