{"type": "Feature", "id": 23608474, "geometry": {"type": "Point", "coordinates": [-74.230949, 40.73922]}, "properties": {"woe:id": 23608474, "woe:parent_id": 55806614, "woe:name": "Vailsburg Station", "woe:placetype": 20, "woe:placetype_name": "POI", "woe:lang": "ENG", "iso:country": "US", "meta:provider": ["geoplanet:7.3.1", "geoplanet:7.3.2", "geoplanet:7.4.0", "geoplanet:7.4.1", "geoplanet:7.5.1", "geoplanet:7.5.2", "geoplanet:7.6.0", "geoplanet:7.8.1", "geoplanet:7.9.0", "geoplanet:7.10.0", "geoplanet:8.0.0", "woeplanet:8.0.0"], "meta:indexed": "2020-08-20T20:18:47.167561", "meta:updated": "2020-10-14T11:19:38.686667", "woe:hierarchy": {"continent": 24865672, "country": 23424977, "town": 0, "planet": 1, "county": 12589264, "suburb": 0, "state": 2347589, "region": 0, "localadmin": 0}, "woe:timezone_id": 56043648, "woe:hash": "dr5pyb6ejt09", "woe:centroid": [-74.230949, 40.73922], "geom:latitude": 40.73922, "geom:longitude": -74.230949, "geom:hash": "dr5pyb6ejt09", "woe:latitude": 40.73922, "geom:centroid": [-74.230949, 40.73922], "woe:longitude": -74.230949, "woe:repo": "woeplanet-poi-us", "geom:area": 0.0, "woe:scale": 19}}