{"type": "Feature", "id": 23658602, "geometry": {"type": "Point", "coordinates": [-94.174469, 30.35836]}, "properties": {"woe:id": 23658602, "woe:parent_id": 2493568, "woe:name": "John H Kirby Elementary School", "woe:placetype": 20, "woe:placetype_name": "POI", "woe:lang": "ENG", "iso:country": "US", "meta:provider": ["geoplanet:7.3.1", "geoplanet:7.3.2", "geoplanet:7.4.0", "geoplanet:7.4.1", "geoplanet:7.5.1", "geoplanet:7.5.2", "geoplanet:7.6.0", "geoplanet:7.8.1", "geoplanet:7.9.0", "geoplanet:7.10.0", "geoplanet:8.0.0", "woeplanet:8.0.0"], "meta:indexed": "2020-08-20T20:19:05.508718", "woe:alias_ENG_V": ["John H Kirby Elementary"], "meta:updated": "2020-10-14T11:19:53.997184", "woe:hierarchy": {"continent": 24865672, "country": 23424977, "town": 0, "planet": 1, "county": 12590106, "suburb": 0, "state": 2347602, "region": 0, "localadmin": 0}, "woe:timezone_id": 56043661, "woe:hash": "9vmh9n84rb6r", "woe:centroid": [-94.174469, 30.35836], "geom:latitude": 30.35836, "geom:longitude": -94.174469, "geom:hash": "9vmh9n84rb6r", "woe:latitude": 30.35836, "geom:centroid": [-94.174469, 30.35836], "woe:longitude": -94.174469, "woe:repo": "woeplanet-poi-us", "geom:area": 0.0, "woe:scale": 19}}