{"type": "Feature", "id": 23656074, "properties": {"woe:id": 23656074, "woe:parent_id": 2374555, "woe:name": "Crestview Elementary School", "woe:placetype": 20, "woe:placetype_name": "POI", "woe:lang": "ENG", "iso:country": "US", "meta:provider": ["geoplanet:7.3.1", "geoplanet:7.3.2", "geoplanet:7.4.0", "geoplanet:7.4.1", "geoplanet:7.5.1", "geoplanet:7.5.2", "geoplanet:7.6.0", "geoplanet:7.8.1", "geoplanet:7.9.0", "geoplanet:7.10.0", "geoplanet:8.0.0", "woeplanet:8.0.0"], "meta:indexed": "2020-08-20T20:19:04.166870", "woe:alias_ENG_V": ["Crestview Elementary"], "meta:updated": "2020-08-22T02:57:49.458822", "woe:hierarchy": {"continent": 24865672, "country": 23424977, "town": 0, "planet": 1, "county": 12590197, "suburb": 0, "state": 2347602, "region": 0, "localadmin": 0}, "woe:timezone_id": 56043661, "woe:hash": "9wpx07mnt7fg", "woe:centroid": [-101.935043, 34.999458], "geom:latitude": 34.999458, "geom:longitude": -101.935043, "geom:hash": "9wpx07mnt7fg", "woe:latitude": 34.999458, "geom:centroid": [-101.935043, 34.999458], "woe:longitude": -101.935043, "woe:repo": "woeplanet-poi-us"}, "geometry": {"coordinates": [-101.935043, 34.999458], "type": "Point"}}