{"type": "Feature", "id": 23576775, "properties": {"woe:id": 23576775, "woe:parent_id": 23512110, "woe:name": "New Orleans Science & Mathematics High School", "woe:placetype": 20, "woe:placetype_name": "POI", "woe:lang": "ENG", "iso:country": "US", "meta:provider": ["geoplanet:7.3.1", "geoplanet:7.3.2", "geoplanet:7.4.0", "geoplanet:7.4.1", "geoplanet:7.5.1", "geoplanet:7.5.2", "geoplanet:7.6.0", "geoplanet:7.8.1", "geoplanet:7.9.0", "geoplanet:7.10.0", "geoplanet:8.0.0", "woeplanet:8.0.0"], "meta:indexed": "2020-08-20T20:18:37.666216", "woe:alias_ENG_V": ["New Orleans Science & Mathematics Senior High School", "New Orleans Science & Mathematics High", "New Orleans Science & Mathematics Senior High", "New Orleans Science & Mathematics HS", "New Orleans Science & Mathematics Senior HS", "New Orleans Science and Mathematics High", "New Orleans Science and Mathematics High School", "New Orleans Science and Mathematics HS", "New Orleans Science and Mathematics Senior High", "New Orleans Science and Mathematics Senior High School", "New Orleans Science and Mathematics Senior HS"], "meta:updated": "2020-08-22T02:58:47.627662", "woe:hierarchy": {"continent": 24865672, "country": 23424977, "town": 0, "planet": 1, "county": 12588631, "suburb": 0, "state": 2347577, "region": 0, "localadmin": 0}, "woe:timezone_id": 56043661, "woe:hash": "9vrftem5x47r", "woe:centroid": [-90.102692, 29.98917], "geom:latitude": 29.98917, "geom:longitude": -90.102692, "geom:hash": "9vrftem5x47r", "woe:latitude": 29.98917, "geom:centroid": [-90.102692, 29.98917], "woe:longitude": -90.102692, "woe:repo": "woeplanet-poi-us"}, "geometry": {"coordinates": [-90.102692, 29.98917], "type": "Point"}}