{"type": "Feature", "id": 23572683, "properties": {"woe:id": 23572683, "woe:parent_id": 55806512, "woe:name": "Northwest High School", "woe:placetype": 20, "woe:placetype_name": "POI", "woe:lang": "ENG", "iso:country": "US", "meta:provider": ["geoplanet:7.3.2", "geoplanet:7.4.0", "geoplanet:7.4.1", "geoplanet:7.5.1", "geoplanet:7.5.2", "geoplanet:7.6.0", "geoplanet:7.8.1", "geoplanet:7.9.0", "geoplanet:7.10.0", "geoplanet:8.0.0", "woeplanet:8.0.0"], "meta:indexed": "2020-08-20T22:02:19.778687", "woe:alias_ENG_V": ["Northwest Senior High School", "Northwest High", "Northwest Senior High", "Northwest HS", "Northwest Senior HS", "NW High", "NW High School", "NW HS", "NW Senior High", "NW Senior High School", "NW Senior HS"], "meta:updated": "2020-08-22T02:58:47.496853", "woe:hierarchy": {"continent": 24865672, "country": 23424977, "town": 0, "planet": 1, "county": 12588457, "suburb": 0, "state": 2347575, "region": 0, "localadmin": 0}, "woe:timezone_id": 56043661, "woe:hash": "9ydwqxg1wvmg", "woe:centroid": [-97.444313, 37.703991], "geom:latitude": 37.703991, "geom:longitude": -97.444313, "geom:hash": "9ydwqxg1wvmg", "woe:latitude": 37.703991, "geom:centroid": [-97.444313, 37.703991], "woe:longitude": -97.444313, "woe:repo": "woeplanet-poi-us"}, "geometry": {"coordinates": [-97.444313, 37.703991], "type": "Point"}}