{"type": "Feature", "id": 23656356, "geometry": {"type": "Point", "coordinates": [-97.085388, 32.709579]}, "properties": {"woe:id": 23656356, "woe:parent_id": 56022648, "woe:name": "Hutcheson Junior High School", "woe:placetype": 20, "woe:placetype_name": "POI", "woe:lang": "ENG", "iso:country": "US", "meta:provider": ["geoplanet:7.3.1", "geoplanet:7.3.2", "geoplanet:7.4.0", "geoplanet:7.4.1", "geoplanet:7.5.1", "geoplanet:7.5.2", "geoplanet:7.6.0", "geoplanet:7.8.1", "geoplanet:7.9.0", "geoplanet:7.10.0", "geoplanet:8.0.0", "woeplanet:8.0.0"], "meta:indexed": "2020-08-20T20:19:04.292147", "woe:alias_ENG_V": ["Hutcheson Junior High"], "meta:updated": "2020-10-14T11:19:49.616923", "woe:hierarchy": {"continent": 24865672, "country": 23424977, "town": 0, "planet": 1, "county": 12590226, "suburb": 0, "state": 2347602, "region": 0, "localadmin": 0}, "woe:timezone_id": 56043661, "woe:hash": "9vffnf8e47ry", "woe:centroid": [-97.085388, 32.709579], "geom:latitude": 32.709579, "geom:longitude": -97.085388, "geom:hash": "9vffnf8e47ry", "woe:latitude": 32.709579, "geom:centroid": [-97.085388, 32.709579], "woe:longitude": -97.085388, "woe:repo": "woeplanet-poi-us", "geom:area": 0.0, "woe:scale": 19}}