{"type": "Feature", "id": 23598794, "geometry": {"type": "Point", "coordinates": [-90.16346, 37.431599]}, "properties": {"woe:id": 23598794, "woe:parent_id": 2446007, "woe:name": "Marquand-zion High School", "woe:placetype": 20, "woe:placetype_name": "POI", "woe:lang": "ENG", "iso:country": "US", "meta:provider": ["geoplanet:7.3.2", "geoplanet:7.4.0", "geoplanet:7.4.1", "geoplanet:7.5.1", "geoplanet:7.5.2", "geoplanet:7.6.0", "geoplanet:7.8.1", "geoplanet:7.9.0", "geoplanet:7.10.0", "geoplanet:8.0.0", "woeplanet:8.0.0"], "meta:indexed": "2020-08-20T22:02:30.518044", "woe:alias_ENG_V": ["Marquand-zion Senior High School", "Marquand-zion High", "Marquand-zion Senior High", "Marquand-zion HS", "Marquand-zion Senior HS"], "meta:updated": "2020-10-14T11:20:05.395267", "woe:hierarchy": {"continent": 24865672, "country": 23424977, "town": 0, "planet": 1, "county": 12589026, "suburb": 0, "state": 2347584, "region": 0, "localadmin": 0}, "woe:timezone_id": 56043661, "woe:hash": "9yxuuq0yz5g3", "woe:centroid": [-90.16346, 37.431599], "geom:latitude": 37.431599, "geom:longitude": -90.16346, "geom:hash": "9yxuuq0yz5g3", "woe:latitude": 37.431599, "geom:centroid": [-90.16346, 37.431599], "woe:longitude": -90.16346, "woe:repo": "woeplanet-poi-us", "geom:area": 0.0, "woe:scale": 19}}