{"type": "Feature", "id": 23594950, "geometry": {"type": "Point", "coordinates": [-93.221542, 44.09864]}, "properties": {"woe:id": 23594950, "woe:parent_id": 2467020, "woe:name": "Mckinley Elementary School", "woe:placetype": 20, "woe:placetype_name": "POI", "woe:lang": "ENG", "iso:country": "US", "meta:provider": ["geoplanet:7.3.1", "geoplanet:7.3.2", "geoplanet:7.4.0", "geoplanet:7.4.1", "geoplanet:7.5.1", "geoplanet:7.5.2", "geoplanet:7.6.0", "geoplanet:7.8.1", "geoplanet:7.9.0", "geoplanet:7.10.0", "geoplanet:8.0.0", "woeplanet:8.0.0"], "meta:indexed": "2020-08-20T20:18:43.077325", "woe:alias_ENG_V": ["Mckinley Elementary"], "meta:updated": "2020-10-14T11:20:10.544568", "woe:hierarchy": {"continent": 24865672, "country": 23424977, "town": 0, "planet": 1, "county": 12588870, "suburb": 0, "state": 2347582, "region": 0, "localadmin": 0}, "woe:timezone_id": 56043661, "woe:hash": "9zvdyeyjhwk4", "woe:centroid": [-93.221542, 44.09864], "geom:latitude": 44.09864, "geom:longitude": -93.221542, "geom:hash": "9zvdyeyjhwk4", "woe:latitude": 44.09864, "geom:centroid": [-93.221542, 44.09864], "woe:longitude": -93.221542, "woe:repo": "woeplanet-poi-us", "geom:area": 0.0, "woe:scale": 19}}