{"type": "Feature", "id": 23546371, "geometry": {"type": "Point", "coordinates": [-87.257668, 30.97364]}, "properties": {"woe:id": 23546371, "woe:parent_id": 2377686, "woe:name": "Century Elementary School", "woe:placetype": 20, "woe:placetype_name": "POI", "woe:lang": "ENG", "iso:country": "US", "meta:provider": ["geoplanet:7.3.1", "geoplanet:7.3.2", "geoplanet:7.4.0", "geoplanet:7.4.1", "geoplanet:7.5.1", "geoplanet:7.5.2", "geoplanet:7.6.0", "geoplanet:7.8.1", "geoplanet:7.9.0", "geoplanet:7.10.0", "geoplanet:8.0.0", "woeplanet:8.0.0"], "meta:indexed": "2020-08-20T20:18:26.414009", "woe:alias_ENG_V": ["Century Elementary"], "meta:updated": "2020-10-14T11:20:22.670302", "woe:hierarchy": {"continent": 24865672, "country": 23424977, "town": 0, "planet": 1, "county": 12587819, "suburb": 0, "state": 2347568, "region": 0, "localadmin": 0}, "woe:timezone_id": 56043661, "woe:hash": "dj9bnqsfsbyz", "woe:centroid": [-87.257668, 30.97364], "geom:latitude": 30.97364, "geom:longitude": -87.257668, "geom:hash": "dj9bnqsfsbyz", "woe:latitude": 30.97364, "geom:centroid": [-87.257668, 30.97364], "woe:longitude": -87.257668, "woe:repo": "woeplanet-poi-us", "geom:area": 0.0, "woe:scale": 19}}