{"type": "Feature", "id": 23558990, "properties": {"woe:id": 23558990, "woe:parent_id": 2391500, "woe:name": "North Elementary School", "woe:placetype": 20, "woe:placetype_name": "POI", "woe:lang": "ENG", "iso:country": "US", "meta:provider": ["geoplanet:7.3.1", "geoplanet:7.3.2", "geoplanet:7.4.0", "geoplanet:7.4.1", "geoplanet:7.5.1", "geoplanet:7.5.2", "geoplanet:7.6.0", "geoplanet:7.8.1", "geoplanet:7.9.0", "geoplanet:7.10.0", "geoplanet:8.0.0", "woeplanet:8.0.0"], "meta:indexed": "2020-08-20T20:18:31.172337", "woe:alias_ENG_V": ["N Elementary School", "N Elementary", "North Elementary"], "meta:updated": "2020-08-22T02:57:34.077034", "woe:hierarchy": {"continent": 24865672, "country": 23424977, "town": 0, "planet": 1, "county": 12588093, "suburb": 0, "state": 2347572, "region": 0, "localadmin": 0}, "woe:timezone_id": 56043661, "woe:hash": "dp3x0npf1x56", "woe:centroid": [-87.879913, 42.045059], "geom:latitude": 42.045059, "geom:longitude": -87.879913, "geom:hash": "dp3x0npf1x56", "woe:latitude": 42.045059, "geom:centroid": [-87.879913, 42.045059], "woe:longitude": -87.879913, "woe:repo": "woeplanet-poi-us"}, "geometry": {"coordinates": [-87.879913, 42.045059], "type": "Point"}}