{"type": "Feature", "id": 23626764, "geometry": {"type": "Point", "coordinates": [-102.488953, 47.98048]}, "properties": {"woe:id": 23626764, "woe:parent_id": 2459039, "woe:name": "New Town High School", "woe:placetype": 20, "woe:placetype_name": "POI", "woe:lang": "ENG", "iso:country": "US", "meta:provider": ["geoplanet:7.3.2", "geoplanet:7.4.0", "geoplanet:7.4.1", "geoplanet:7.5.1", "geoplanet:7.5.2", "geoplanet:7.6.0", "geoplanet:7.8.1", "geoplanet:7.9.0", "geoplanet:7.10.0", "geoplanet:8.0.0", "woeplanet:8.0.0"], "meta:indexed": "2020-08-20T22:02:40.990825", "woe:alias_ENG_V": ["New Town Senior High School", "New Town High", "New Town Senior High", "New Town HS", "New Town Senior HS"], "meta:updated": "2020-10-14T11:19:36.809457", "woe:hierarchy": {"continent": 24865672, "country": 23424977, "town": 0, "planet": 1, "county": 12589504, "suburb": 0, "state": 2347593, "region": 0, "localadmin": 0}, "woe:timezone_id": 56043661, "woe:hash": "c8x0gy9fd39x", "woe:centroid": [-102.488953, 47.98048], "geom:latitude": 47.98048, "geom:longitude": -102.488953, "geom:hash": "c8x0gy9fd39x", "woe:latitude": 47.98048, "geom:centroid": [-102.488953, 47.98048], "woe:longitude": -102.488953, "woe:repo": "woeplanet-poi-us", "geom:area": 0.0, "woe:scale": 19}}