{"type": "Feature", "id": 23655992, "properties": {"woe:id": 23655992, "woe:parent_id": 55857738, "woe:name": "Forest Hill Elementary School", "woe:placetype": 20, "woe:placetype_name": "POI", "woe:lang": "ENG", "iso:country": "US", "meta:provider": ["geoplanet:7.3.1", "geoplanet:7.3.2", "geoplanet:7.4.0", "geoplanet:7.4.1", "geoplanet:7.5.1", "geoplanet:7.5.2", "geoplanet:7.6.0", "geoplanet:7.8.1", "geoplanet:7.9.0", "geoplanet:7.10.0", "geoplanet:8.0.0", "woeplanet:8.0.0"], "meta:indexed": "2020-08-20T20:19:04.121573", "woe:alias_ENG_V": ["Forest Hill Elementary"], "meta:updated": "2020-08-22T02:57:49.435815", "woe:hierarchy": {"continent": 24865672, "country": 23424977, "town": 0, "planet": 1, "county": 12590194, "suburb": 0, "state": 2347602, "region": 0, "localadmin": 0}, "woe:timezone_id": 56043661, "woe:hash": "9wr87ecysz99", "woe:centroid": [-101.796707, 35.221951], "geom:latitude": 35.221951, "geom:longitude": -101.796707, "geom:hash": "9wr87ecysz99", "woe:latitude": 35.221951, "geom:centroid": [-101.796707, 35.221951], "woe:longitude": -101.796707, "woe:repo": "woeplanet-poi-us"}, "geometry": {"coordinates": [-101.796707, 35.221951], "type": "Point"}}