{"type": "Feature", "id": 23514728, "properties": {"woe:id": 23514728, "woe:parent_id": 55807152, "woe:name": "Steller Secondary School", "woe:placetype": 20, "woe:placetype_name": "POI", "woe:lang": "ENG", "iso:country": "US", "meta:provider": ["geoplanet:7.3.1", "geoplanet:7.3.2", "geoplanet:7.4.0", "geoplanet:7.4.1", "geoplanet:7.5.1", "geoplanet:7.5.2", "geoplanet:7.6.0", "geoplanet:7.8.1", "geoplanet:7.9.0", "geoplanet:7.10.0", "geoplanet:8.0.0", "woeplanet:8.0.0"], "meta:indexed": "2020-08-20T20:18:17.850607", "meta:updated": "2020-08-22T02:57:26.432946", "woe:hierarchy": {"continent": 24865672, "country": 23424977, "town": 0, "planet": 1, "county": 12587556, "suburb": 0, "state": 2347560, "region": 0, "localadmin": 0}, "woe:timezone_id": 56043669, "woe:hash": "bdvkjher5h29", "woe:centroid": [-149.892868, 61.197819], "geom:latitude": 61.197819, "geom:longitude": -149.892868, "geom:hash": "bdvkjher5h29", "woe:latitude": 61.197819, "geom:centroid": [-149.892868, 61.197819], "woe:longitude": -149.892868, "woe:repo": "woeplanet-poi-us"}, "geometry": {"coordinates": [-149.892868, 61.197819], "type": "Point"}}