{"type": "Feature", "id": 23567089, "geometry": {"type": "Point", "coordinates": [-86.13298, 39.710209]}, "properties": {"woe:id": 23567089, "woe:parent_id": 55986610, "woe:name": "University of Indianapolis", "woe:placetype": 20, "woe:placetype_name": "POI", "woe:lang": "ENG", "iso:country": "US", "meta:provider": ["geoplanet:7.3.1", "geoplanet:7.3.2", "geoplanet:7.4.0", "geoplanet:7.4.1", "geoplanet:7.5.1", "geoplanet:7.5.2", "geoplanet:7.6.0", "geoplanet:7.8.1", "geoplanet:7.9.0", "geoplanet:7.10.0", "geoplanet:8.0.0", "woeplanet:8.0.0"], "meta:indexed": "2020-08-20T20:18:34.285381", "meta:updated": "2020-10-14T11:20:13.116699", "woe:hierarchy": {"continent": 24865672, "country": 23424977, "town": 0, "planet": 1, "county": 12588228, "suburb": 0, "state": 2347573, "region": 0, "localadmin": 0}, "woe:timezone_id": 56043656, "woe:hash": "dp49zvpbsp7p", "woe:centroid": [-86.13298, 39.710209], "geom:latitude": 39.710209, "geom:longitude": -86.13298, "geom:hash": "dp49zvpbsp7p", "woe:latitude": 39.710209, "geom:centroid": [-86.13298, 39.710209], "woe:longitude": -86.13298, "woe:repo": "woeplanet-poi-us", "geom:area": 0.0, "woe:scale": 19}}