{"type": "Feature", "id": 23526255, "geometry": {"type": "Point", "coordinates": [-121.90097, 37.45208]}, "properties": {"woe:id": 23526255, "woe:parent_id": 2451745, "woe:name": "Marshall Pomeroy Elementary School", "woe:placetype": 20, "woe:placetype_name": "POI", "woe:lang": "ENG", "iso:country": "US", "meta:provider": ["geoplanet:7.3.1", "geoplanet:7.3.2", "geoplanet:7.4.0", "geoplanet:7.4.1", "geoplanet:7.5.1", "geoplanet:7.5.2", "geoplanet:7.6.0", "geoplanet:7.8.1", "geoplanet:7.9.0", "geoplanet:7.10.0", "geoplanet:8.0.0", "woeplanet:8.0.0"], "meta:indexed": "2020-08-20T20:18:20.797924", "woe:alias_ENG_V": ["Marshall Pomeroy Elementary"], "meta:updated": "2020-10-14T11:20:07.710704", "woe:hierarchy": {"continent": 24865672, "country": 23424977, "town": 0, "planet": 1, "county": 12587712, "suburb": 0, "state": 2347563, "region": 0, "localadmin": 0}, "woe:timezone_id": 56043663, "woe:hash": "9q9m41fqjt8x", "woe:centroid": [-121.90097, 37.45208], "geom:latitude": 37.45208, "geom:longitude": -121.90097, "geom:hash": "9q9m41fqjt8x", "woe:latitude": 37.45208, "geom:centroid": [-121.90097, 37.45208], "woe:longitude": -121.90097, "woe:repo": "woeplanet-poi-us", "geom:area": 0.0, "woe:scale": 19}}