{"type": "Feature", "id": 23550743, "properties": {"woe:id": 23550743, "woe:parent_id": 55861575, "woe:name": "Garden of Peace Lutheran School", "woe:placetype": 20, "woe:placetype_name": "POI", "woe:lang": "ENG", "iso:country": "US", "meta:provider": ["geoplanet:7.3.1", "geoplanet:7.3.2", "geoplanet:7.4.0", "geoplanet:7.4.1", "geoplanet:7.5.1", "geoplanet:7.5.2", "geoplanet:7.6.0", "geoplanet:7.8.1", "geoplanet:7.9.0", "geoplanet:7.10.0", "geoplanet:8.0.0", "woeplanet:8.0.0"], "meta:indexed": "2020-08-20T20:18:28.542772", "meta:updated": "2020-08-22T02:57:32.652268", "woe:alias_ENG_V": ["Central Christian School"], "woe:hierarchy": {"continent": 24865672, "country": 23424977, "town": 0, "planet": 1, "county": 12587854, "suburb": 0, "state": 2347568, "region": 0, "localadmin": 0}, "woe:timezone_id": 56043648, "woe:hash": "dhvnjem6zvpu", "woe:centroid": [-82.719498, 27.79179], "geom:latitude": 27.79179, "geom:longitude": -82.719498, "geom:hash": "dhvnjem6zvpu", "woe:latitude": 27.79179, "geom:centroid": [-82.719498, 27.79179], "woe:longitude": -82.719498, "woe:repo": "woeplanet-poi-us"}, "geometry": {"coordinates": [-82.719498, 27.79179], "type": "Point"}}