{"type": "Feature", "id": 23618318, "properties": {"woe:id": 23618318, "woe:parent_id": 2402720, "woe:name": "Fayetteville Elementary School", "woe:placetype": 20, "woe:placetype_name": "POI", "woe:lang": "ENG", "iso:country": "US", "meta:provider": ["geoplanet:7.3.1", "geoplanet:7.3.2", "geoplanet:7.4.0", "geoplanet:7.4.1", "geoplanet:7.5.1", "geoplanet:7.5.2", "geoplanet:7.6.0", "geoplanet:7.8.1", "geoplanet:7.9.0", "geoplanet:7.10.0", "geoplanet:8.0.0", "woeplanet:8.0.0"], "meta:indexed": "2020-08-20T20:18:50.775509", "woe:alias_ENG_V": ["Fayetteville Elementary"], "meta:updated": "2020-08-22T02:57:43.438954", "woe:hierarchy": {"continent": 24865672, "country": 23424977, "town": 0, "planet": 1, "county": 12589345, "suburb": 0, "state": 2347591, "region": 0, "localadmin": 0}, "woe:timezone_id": 56043648, "woe:hash": "dr9uy84f32tb", "woe:centroid": [-75.99958, 43.02285], "geom:latitude": 43.02285, "geom:longitude": -75.99958, "geom:hash": "dr9uy84f32tb", "woe:latitude": 43.02285, "geom:centroid": [-75.99958, 43.02285], "woe:longitude": -75.99958, "woe:repo": "woeplanet-poi-us"}, "geometry": {"coordinates": [-75.99958, 43.02285], "type": "Point"}}