{"type": "Feature", "id": 23655156, "geometry": {"type": "Point", "coordinates": [-95.61071, 33.122101]}, "properties": {"woe:id": 23655156, "woe:parent_id": 2501528, "woe:name": "Sulphur Springs Middle School", "woe:placetype": 20, "woe:placetype_name": "POI", "woe:lang": "ENG", "iso:country": "US", "meta:provider": ["geoplanet:7.3.1", "geoplanet:7.3.2", "geoplanet:7.4.0", "geoplanet:7.4.1", "geoplanet:7.5.1", "geoplanet:7.5.2", "geoplanet:7.6.0", "geoplanet:7.8.1", "geoplanet:7.9.0", "geoplanet:7.10.0", "geoplanet:8.0.0", "woeplanet:8.0.0"], "meta:indexed": "2020-08-20T20:19:03.733373", "meta:updated": "2020-10-14T11:19:51.255150", "woe:hierarchy": {"continent": 24865672, "country": 23424977, "town": 0, "planet": 1, "county": 12590118, "suburb": 0, "state": 2347602, "region": 0, "localadmin": 0}, "woe:timezone_id": 56043661, "woe:hash": "9vuh2mdqhzpk", "woe:centroid": [-95.61071, 33.122101], "geom:latitude": 33.122101, "geom:longitude": -95.61071, "geom:hash": "9vuh2mdqhzpk", "woe:latitude": 33.122101, "geom:centroid": [-95.61071, 33.122101], "woe:longitude": -95.61071, "woe:repo": "woeplanet-poi-us", "geom:area": 0.0, "woe:scale": 19}}