{"type": "Feature", "id": 23566378, "properties": {"woe:id": 23566378, "woe:parent_id": 2433742, "woe:name": "Kokomo Academy", "woe:placetype": 20, "woe:placetype_name": "POI", "woe:lang": "ENG", "iso:country": "US", "meta:provider": ["geoplanet:7.3.2", "geoplanet:7.4.0", "geoplanet:7.4.1", "geoplanet:7.5.1", "geoplanet:7.5.2", "geoplanet:7.6.0", "geoplanet:7.8.1", "geoplanet:7.9.0", "geoplanet:7.10.0", "geoplanet:8.0.0", "woeplanet:8.0.0"], "meta:indexed": "2020-08-20T22:02:16.917589", "meta:updated": "2020-08-22T02:57:35.609118", "woe:hierarchy": {"continent": 24865672, "country": 23424977, "town": 0, "planet": 1, "county": 12588213, "suburb": 0, "state": 2347573, "region": 0, "localadmin": 0}, "woe:timezone_id": 56043656, "woe:hash": "dp4wr3r2yumx", "woe:centroid": [-86.155518, 40.480652], "geom:latitude": 40.480652, "geom:longitude": -86.155518, "geom:hash": "dp4wr3r2yumx", "woe:latitude": 40.480652, "geom:centroid": [-86.155518, 40.480652], "woe:longitude": -86.155518, "woe:repo": "woeplanet-poi-us"}, "geometry": {"coordinates": [-86.155518, 40.480652], "type": "Point"}}