{"type": "Feature", "id": 23669227, "geometry": {"type": "Point", "coordinates": [-122.301666, 47.60796]}, "properties": {"woe:id": 23669227, "woe:parent_id": 23512099, "woe:name": "Nova High School", "woe:placetype": 20, "woe:placetype_name": "POI", "woe:lang": "ENG", "iso:country": "US", "meta:provider": ["geoplanet:7.3.1", "geoplanet:7.3.2", "geoplanet:7.4.0", "geoplanet:7.4.1", "geoplanet:7.5.1", "geoplanet:7.5.2", "geoplanet:7.6.0", "geoplanet:7.8.1", "geoplanet:7.9.0", "geoplanet:7.10.0", "geoplanet:8.0.0", "woeplanet:8.0.0"], "meta:indexed": "2020-08-20T20:19:09.358369", "woe:alias_ENG_V": ["Nova Senior High School", "Nova High", "Nova Senior High", "Nova HS", "Nova Senior HS", "Nova Alternative High", "Nova Alternative High School", "Nova Alternative HS", "Nova Alternative Senior High", "Nova Alternative Senior High School", "Nova Alternative Senior HS"], "meta:updated": "2020-10-14T11:19:45.081232", "woe:hierarchy": {"continent": 24865672, "country": 23424977, "town": 0, "planet": 1, "county": 12590456, "suburb": 0, "state": 2347606, "region": 0, "localadmin": 0}, "woe:timezone_id": 56043663, "woe:hash": "c23nbfy8kwup", "woe:centroid": [-122.301666, 47.60796], "geom:latitude": 47.60796, "geom:longitude": -122.301666, "geom:hash": "c23nbfy8kwup", "woe:latitude": 47.60796, "geom:centroid": [-122.301666, 47.60796], "woe:longitude": -122.301666, "woe:repo": "woeplanet-poi-us", "geom:area": 0.0, "woe:scale": 19}}