{"type": "Feature", "id": 23528121, "properties": {"woe:id": 23528121, "woe:parent_id": 55971998, "woe:name": "April Lane Elementary School", "woe:placetype": 20, "woe:placetype_name": "POI", "woe:lang": "ENG", "iso:country": "US", "meta:provider": ["geoplanet:7.3.2", "geoplanet:7.4.0", "geoplanet:7.4.1", "geoplanet:7.5.1", "geoplanet:7.5.2", "geoplanet:7.6.0", "geoplanet:7.8.1", "geoplanet:7.9.0", "geoplanet:7.10.0", "geoplanet:8.0.0", "woeplanet:8.0.0"], "meta:indexed": "2020-08-20T22:02:01.035499", "woe:alias_ENG_V": ["April Lane Elementary"], "meta:updated": "2020-08-22T02:57:28.334919", "woe:hierarchy": {"continent": 24865672, "country": 23424977, "town": 0, "planet": 1, "county": 12587720, "suburb": 0, "state": 2347563, "region": 0, "localadmin": 0}, "woe:timezone_id": 56043663, "woe:hash": "9qcw8rb24et2", "woe:centroid": [-121.629181, 39.153919], "geom:latitude": 39.153919, "geom:longitude": -121.629181, "geom:hash": "9qcw8rb24et2", "woe:latitude": 39.153919, "geom:centroid": [-121.629181, 39.153919], "woe:longitude": -121.629181, "woe:repo": "woeplanet-poi-us"}, "geometry": {"coordinates": [-121.629181, 39.153919], "type": "Point"}}