{"type": "Feature", "id": 23519738, "geometry": {"type": "Point", "coordinates": [-121.984451, 37.57695]}, "properties": {"woe:id": 23519738, "woe:parent_id": 2459989, "woe:name": "Niles Elementary School", "woe:placetype": 20, "woe:placetype_name": "POI", "woe:lang": "ENG", "iso:country": "US", "meta:provider": ["geoplanet:7.3.2", "geoplanet:7.4.0", "geoplanet:7.4.1", "geoplanet:7.5.1", "geoplanet:7.5.2", "geoplanet:7.6.0", "geoplanet:7.8.1", "geoplanet:7.9.0", "geoplanet:7.10.0", "geoplanet:8.0.0", "woeplanet:8.0.0"], "meta:indexed": "2020-08-20T22:01:57.948821", "woe:alias_ENG_V": ["Niles Elementary"], "meta:updated": "2020-10-14T11:20:21.901593", "woe:hierarchy": {"continent": 24865672, "country": 23424977, "town": 0, "planet": 1, "county": 12587670, "suburb": 0, "state": 2347563, "region": 0, "localadmin": 0}, "woe:timezone_id": 56043663, "woe:hash": "9q9mb0tts70v", "woe:centroid": [-121.984451, 37.57695], "geom:latitude": 37.57695, "geom:longitude": -121.984451, "geom:hash": "9q9mb0tts70v", "woe:latitude": 37.57695, "geom:centroid": [-121.984451, 37.57695], "woe:longitude": -121.984451, "woe:repo": "woeplanet-poi-us", "geom:area": 0.0, "woe:scale": 19}}