{"type": "Feature", "id": 23666943, "properties": {"woe:id": 23666943, "woe:parent_id": 2383323, "woe:name": "Lakeview Elementary School", "woe:placetype": 20, "woe:placetype_name": "POI", "woe:lang": "ENG", "iso:country": "US", "meta:provider": ["geoplanet:7.3.1", "geoplanet:7.3.2", "geoplanet:7.4.0", "geoplanet:7.4.1", "geoplanet:7.5.1", "geoplanet:7.5.2", "geoplanet:7.6.0", "geoplanet:7.8.1", "geoplanet:7.9.0", "geoplanet:7.10.0", "geoplanet:8.0.0", "woeplanet:8.0.0"], "meta:indexed": "2020-08-20T20:19:08.524876", "woe:alias_ENG_V": ["Lakeview Elementary"], "meta:updated": "2020-08-22T02:57:51.525329", "woe:hierarchy": {"continent": 24865672, "country": 23424977, "town": 0, "planet": 1, "county": 12590333, "suburb": 0, "state": 2347605, "region": 0, "localadmin": 0}, "woe:timezone_id": 56043648, "woe:hash": "dq8un25xzeh7", "woe:centroid": [-77.41552, 37.266972], "geom:latitude": 37.266972, "geom:longitude": -77.41552, "geom:hash": "dq8un25xzeh7", "woe:latitude": 37.266972, "geom:centroid": [-77.41552, 37.266972], "woe:longitude": -77.41552, "woe:repo": "woeplanet-poi-us"}, "geometry": {"coordinates": [-77.41552, 37.266972], "type": "Point"}}