{"type": "Feature", "id": 23650172, "properties": {"woe:id": 23650172, "woe:parent_id": 2396089, "woe:name": "East Ridge Elementary School", "woe:placetype": 20, "woe:placetype_name": "POI", "woe:lang": "ENG", "iso:country": "US", "meta:provider": ["geoplanet:7.3.1", "geoplanet:7.3.2", "geoplanet:7.4.0", "geoplanet:7.4.1", "geoplanet:7.5.1", "geoplanet:7.5.2", "geoplanet:7.6.0", "geoplanet:7.8.1", "geoplanet:7.9.0", "geoplanet:7.10.0", "geoplanet:8.0.0", "woeplanet:8.0.0"], "meta:indexed": "2020-08-20T20:19:01.743633", "woe:alias_ENG_V": ["E Ridge Elementary School", "E Ridge Elementary", "East Ridge Elementary"], "meta:updated": "2020-08-22T02:57:48.215652", "woe:hierarchy": {"continent": 24865672, "country": 23424977, "town": 0, "planet": 1, "county": 12589944, "suburb": 0, "state": 2347601, "region": 0, "localadmin": 0}, "woe:timezone_id": 56043648, "woe:hash": "dn5rh4fqvtn5", "woe:centroid": [-85.250572, 34.996761], "geom:latitude": 34.996761, "geom:longitude": -85.250572, "geom:hash": "dn5rh4fqvtn5", "woe:latitude": 34.996761, "geom:centroid": [-85.250572, 34.996761], "woe:longitude": -85.250572, "woe:repo": "woeplanet-poi-us"}, "geometry": {"coordinates": [-85.250572, 34.996761], "type": "Point"}}