{"type": "Feature", "id": 23617405, "geometry": {"type": "Point", "coordinates": [-73.951462, 40.770191]}, "properties": {"woe:id": 23617405, "woe:parent_id": 23511826, "woe:name": "Ps 158 Baylord Taylor School", "woe:placetype": 20, "woe:placetype_name": "POI", "woe:lang": "ENG", "iso:country": "US", "meta:provider": ["geoplanet:7.3.1", "geoplanet:7.3.2", "geoplanet:7.4.0", "geoplanet:7.4.1", "geoplanet:7.5.1", "geoplanet:7.5.2", "geoplanet:7.6.0", "geoplanet:7.8.1", "geoplanet:7.9.0", "geoplanet:7.10.0", "geoplanet:8.0.0", "woeplanet:8.0.0"], "meta:indexed": "2020-08-20T20:18:50.382373", "meta:updated": "2020-10-14T11:19:47.859947", "woe:hierarchy": {"continent": 24865672, "country": 23424977, "town": 0, "planet": 1, "county": 12589342, "suburb": 0, "state": 2347591, "region": 0, "localadmin": 0}, "woe:timezone_id": 56043648, "woe:hash": "dr5rvjypw43q", "woe:centroid": [-73.951462, 40.770191], "geom:latitude": 40.770191, "geom:longitude": -73.951462, "geom:hash": "dr5rvjypw43q", "woe:latitude": 40.770191, "geom:centroid": [-73.951462, 40.770191], "woe:longitude": -73.951462, "woe:repo": "woeplanet-poi-us", "geom:area": 0.0, "woe:scale": 19}}