{"type": "Feature", "id": 23580302, "geometry": {"type": "Point", "coordinates": [-77.278313, 39.328091]}, "properties": {"woe:id": 23580302, "woe:parent_id": 2407663, "woe:name": "Friends Meeting School", "woe:placetype": 20, "woe:placetype_name": "POI", "woe:lang": "ENG", "iso:country": "US", "meta:provider": ["geoplanet:7.3.1", "geoplanet:7.3.2", "geoplanet:7.4.0", "geoplanet:7.4.1", "geoplanet:7.5.1", "geoplanet:7.5.2", "geoplanet:7.6.0", "geoplanet:7.8.1", "geoplanet:7.9.0", "geoplanet:7.10.0", "geoplanet:8.0.0", "woeplanet:8.0.0"], "meta:indexed": "2020-08-20T20:18:38.562598", "meta:updated": "2020-10-14T11:20:08.466311", "woe:hierarchy": {"continent": 24865672, "country": 23424977, "town": 0, "planet": 1, "county": 12588686, "suburb": 0, "state": 2347579, "region": 0, "localadmin": 0}, "woe:timezone_id": 56043648, "woe:hash": "dqcp9rrwsz92", "woe:centroid": [-77.278313, 39.328091], "geom:latitude": 39.328091, "geom:longitude": -77.278313, "geom:hash": "dqcp9rrwsz92", "woe:latitude": 39.328091, "geom:centroid": [-77.278313, 39.328091], "woe:longitude": -77.278313, "woe:repo": "woeplanet-poi-us", "geom:area": 0.0, "woe:scale": 19}}