{"type": "Feature", "id": 23561693, "geometry": {"type": "Point", "coordinates": [-91.343437, 40.3964]}, "properties": {"woe:id": 23561693, "woe:parent_id": 2416595, "woe:name": "Hamilton High School", "woe:placetype": 20, "woe:placetype_name": "POI", "woe:lang": "ENG", "iso:country": "US", "meta:provider": ["geoplanet:7.3.1", "geoplanet:7.3.2", "geoplanet:7.4.0", "geoplanet:7.4.1", "geoplanet:7.5.1", "geoplanet:7.5.2", "geoplanet:7.6.0", "geoplanet:7.8.1", "geoplanet:7.9.0", "geoplanet:7.10.0", "geoplanet:8.0.0", "woeplanet:8.0.0"], "meta:indexed": "2020-08-20T20:18:32.219183", "woe:alias_ENG_V": ["Hamilton Senior High School", "Hamilton High", "Hamilton Senior High", "Hamilton HS", "Hamilton Senior HS"], "meta:updated": "2020-10-14T11:20:05.599582", "woe:hierarchy": {"continent": 24865672, "country": 23424977, "town": 0, "planet": 1, "county": 12588111, "suburb": 0, "state": 2347572, "region": 0, "localadmin": 0}, "woe:timezone_id": 56043661, "woe:hash": "9zpjc3vwpdub", "woe:centroid": [-91.343437, 40.3964], "geom:latitude": 40.3964, "geom:longitude": -91.343437, "geom:hash": "9zpjc3vwpdub", "woe:latitude": 40.3964, "geom:centroid": [-91.343437, 40.3964], "woe:longitude": -91.343437, "woe:repo": "woeplanet-poi-us", "geom:area": 0.0, "woe:scale": 19}}