{"type": "Feature", "id": 23517163, "properties": {"woe:id": 23517163, "woe:parent_id": 23417097, "woe:name": "Anna Lawrence Intermediate School", "woe:placetype": 20, "woe:placetype_name": "POI", "woe:lang": "ENG", "iso:country": "US", "meta:provider": ["geoplanet:7.3.2", "geoplanet:7.4.0", "geoplanet:7.4.1", "geoplanet:7.5.1", "geoplanet:7.5.2", "geoplanet:7.6.0", "geoplanet:7.8.1", "geoplanet:7.9.0", "geoplanet:7.10.0", "geoplanet:8.0.0", "woeplanet:8.0.0"], "meta:indexed": "2020-08-20T22:01:56.937451", "meta:updated": "2020-08-22T02:57:26.781022", "woe:alias_ENG_V": ["Lawrence Intermediate School"], "woe:hierarchy": {"continent": 24865672, "country": 23424977, "town": 0, "planet": 1, "county": 12587590, "suburb": 0, "state": 2347561, "region": 0, "localadmin": 0}, "woe:timezone_id": 56043666, "woe:hash": "9t9nb867t262", "woe:centroid": [-111.068459, 32.125999], "geom:latitude": 32.125999, "geom:longitude": -111.068459, "geom:hash": "9t9nb867t262", "woe:latitude": 32.125999, "geom:centroid": [-111.068459, 32.125999], "woe:longitude": -111.068459, "woe:repo": "woeplanet-poi-us"}, "geometry": {"coordinates": [-111.068459, 32.125999], "type": "Point"}}