{"type": "Feature", "id": 23654826, "geometry": {"type": "Point", "coordinates": [-101.445091, 34.120579]}, "properties": {"woe:id": 23654826, "woe:parent_id": 2440834, "woe:name": "Lockney Junior High School", "woe:placetype": 20, "woe:placetype_name": "POI", "woe:lang": "ENG", "iso:country": "US", "meta:provider": ["geoplanet:7.3.1", "geoplanet:7.3.2", "geoplanet:7.4.0", "geoplanet:7.4.1", "geoplanet:7.5.1", "geoplanet:7.5.2", "geoplanet:7.6.0", "geoplanet:7.8.1", "geoplanet:7.9.0", "geoplanet:7.10.0", "geoplanet:8.0.0", "woeplanet:8.0.0"], "meta:indexed": "2020-08-20T20:19:03.577348", "woe:alias_ENG_V": ["Lockney Junior High"], "meta:updated": "2020-10-14T11:19:38.909818", "woe:hierarchy": {"continent": 24865672, "country": 23424977, "town": 0, "planet": 1, "county": 12590083, "suburb": 0, "state": 2347602, "region": 0, "localadmin": 0}, "woe:timezone_id": 56043661, "woe:hash": "9wpf5e3yy0ct", "woe:centroid": [-101.445091, 34.120579], "geom:latitude": 34.120579, "geom:longitude": -101.445091, "geom:hash": "9wpf5e3yy0ct", "woe:latitude": 34.120579, "geom:centroid": [-101.445091, 34.120579], "woe:longitude": -101.445091, "woe:repo": "woeplanet-poi-us", "geom:area": 0.0, "woe:scale": 19}}