{"type": "Feature", "id": 23654526, "properties": {"woe:id": 23654526, "woe:parent_id": 2381738, "woe:name": "Wm David Surratt Elementary School", "woe:placetype": 20, "woe:placetype_name": "POI", "woe:lang": "ENG", "iso:country": "US", "meta:provider": ["geoplanet:7.3.1", "geoplanet:7.3.2", "geoplanet:7.4.0", "geoplanet:7.4.1", "geoplanet:7.5.1", "geoplanet:7.5.2", "geoplanet:7.6.0", "geoplanet:7.8.1", "geoplanet:7.9.0", "geoplanet:7.10.0", "geoplanet:8.0.0", "woeplanet:8.0.0"], "meta:indexed": "2020-08-20T20:19:03.404013", "woe:alias_ENG_V": ["William David Surratt Elementary", "Wm David Surratt Elementary"], "meta:updated": "2020-08-22T02:57:49.078630", "woe:hierarchy": {"continent": 24865672, "country": 23424977, "town": 0, "planet": 1, "county": 12590076, "suburb": 0, "state": 2347602, "region": 0, "localadmin": 0}, "woe:timezone_id": 56043665, "woe:hash": "9ts7wrru35xt", "woe:centroid": [-106.238083, 31.593309], "geom:latitude": 31.593309, "geom:longitude": -106.238083, "geom:hash": "9ts7wrru35xt", "woe:latitude": 31.593309, "geom:centroid": [-106.238083, 31.593309], "woe:longitude": -106.238083, "woe:repo": "woeplanet-poi-us"}, "geometry": {"coordinates": [-106.238083, 31.593309], "type": "Point"}}