{"type": "Feature", "id": 23580952, "geometry": {"type": "Point", "coordinates": [-77.192802, 39.044029]}, "properties": {"woe:id": 23580952, "woe:parent_id": 2472254, "woe:name": "Har Shalom Nursery School", "woe:placetype": 20, "woe:placetype_name": "POI", "woe:lang": "ENG", "iso:country": "US", "meta:provider": ["geoplanet:7.3.1", "geoplanet:7.3.2", "geoplanet:7.4.0", "geoplanet:7.4.1", "geoplanet:7.5.1", "geoplanet:7.5.2", "geoplanet:7.6.0", "geoplanet:7.8.1", "geoplanet:7.9.0", "geoplanet:7.10.0", "geoplanet:8.0.0", "woeplanet:8.0.0"], "meta:indexed": "2020-08-20T20:18:38.709946", "meta:updated": "2020-10-14T11:20:18.223966", "woe:hierarchy": {"continent": 24865672, "country": 23424977, "town": 0, "planet": 1, "county": 12588691, "suburb": 0, "state": 2347579, "region": 0, "localadmin": 0}, "woe:timezone_id": 56043648, "woe:hash": "dqcn57tzvqdc", "woe:centroid": [-77.192802, 39.044029], "geom:latitude": 39.044029, "geom:longitude": -77.192802, "geom:hash": "dqcn57tzvqdc", "woe:latitude": 39.044029, "geom:centroid": [-77.192802, 39.044029], "woe:longitude": -77.192802, "woe:repo": "woeplanet-poi-us", "geom:area": 0.0, "woe:scale": 19}}