{"type": "Feature", "id": 23676080, "properties": {"woe:id": 23676080, "woe:parent_id": 2466638, "woe:name": "Osseo Elementary School", "woe:placetype": 20, "woe:placetype_name": "POI", "woe:lang": "ENG", "iso:country": "US", "meta:provider": ["geoplanet:7.3.1", "geoplanet:7.3.2", "geoplanet:7.4.0", "geoplanet:7.4.1", "geoplanet:7.5.1", "geoplanet:7.5.2", "geoplanet:7.6.0", "geoplanet:7.8.1", "geoplanet:7.9.0", "geoplanet:7.10.0", "geoplanet:8.0.0", "woeplanet:8.0.0"], "meta:indexed": "2020-08-20T20:19:11.836595", "woe:alias_ENG_V": ["Osseo Elementary"], "meta:updated": "2020-08-22T02:58:18.280255", "woe:hierarchy": {"continent": 24865672, "country": 23424977, "town": 0, "planet": 1, "county": 12590595, "suburb": 0, "state": 2347608, "region": 0, "localadmin": 0}, "woe:timezone_id": 56043661, "woe:hash": "9zzjsk5d54y4", "woe:centroid": [-91.214539, 44.582878], "geom:latitude": 44.582878, "geom:longitude": -91.214539, "geom:hash": "9zzjsk5d54y4", "woe:latitude": 44.582878, "geom:centroid": [-91.214539, 44.582878], "woe:longitude": -91.214539, "woe:repo": "woeplanet-poi-us"}, "geometry": {"coordinates": [-91.214539, 44.582878], "type": "Point"}}