{"type": "Feature", "id": 23586391, "geometry": {"type": "Point", "coordinates": [-86.520576, 42.041431]}, "properties": {"woe:id": 23586391, "woe:parent_id": 28743841, "woe:name": "Stewart Elementary School", "woe:placetype": 20, "woe:placetype_name": "POI", "woe:lang": "ENG", "iso:country": "US", "meta:provider": ["geoplanet:7.3.1", "geoplanet:7.3.2", "geoplanet:7.4.0", "geoplanet:7.4.1", "geoplanet:7.5.1", "geoplanet:7.5.2", "geoplanet:7.6.0", "geoplanet:7.8.1", "geoplanet:7.9.0", "geoplanet:7.10.0", "geoplanet:8.0.0", "woeplanet:8.0.0"], "meta:indexed": "2020-08-20T20:18:39.959017", "woe:alias_ENG_V": ["Stewart Elementary"], "meta:updated": "2020-10-14T11:20:21.367641", "woe:hierarchy": {"continent": 24865672, "country": 23424977, "town": 0, "planet": 1, "county": 12588724, "suburb": 0, "state": 2347581, "region": 0, "localadmin": 0}, "woe:timezone_id": 56043658, "woe:hash": "dp6rpjmth6y8", "woe:centroid": [-86.520576, 42.041431], "geom:latitude": 42.041431, "geom:longitude": -86.520576, "geom:hash": "dp6rpjmth6y8", "woe:latitude": 42.041431, "geom:centroid": [-86.520576, 42.041431], "woe:longitude": -86.520576, "woe:repo": "woeplanet-poi-us", "geom:area": 0.0, "woe:scale": 19}}