{"type": "Feature", "id": 23563999, "properties": {"woe:id": 23563999, "woe:parent_id": 2496697, "woe:name": "Earl H Hanson Elementary School", "woe:placetype": 20, "woe:placetype_name": "POI", "woe:lang": "ENG", "iso:country": "US", "meta:provider": ["geoplanet:7.3.1", "geoplanet:7.3.2", "geoplanet:7.4.0", "geoplanet:7.4.1", "geoplanet:7.5.1", "geoplanet:7.5.2", "geoplanet:7.6.0", "geoplanet:7.8.1", "geoplanet:7.9.0", "geoplanet:7.10.0", "geoplanet:8.0.0", "woeplanet:8.0.0"], "meta:indexed": "2020-08-20T20:18:33.035961", "woe:alias_ENG_V": ["Earl a Hanson Elementary School", "Earl H Hanson Elementary"], "meta:updated": "2020-08-22T02:57:35.105560", "woe:hierarchy": {"continent": 24865672, "country": 23424977, "town": 0, "planet": 1, "county": 12588158, "suburb": 0, "state": 2347572, "region": 0, "localadmin": 0}, "woe:timezone_id": 56043661, "woe:hash": "9zreftsspmxk", "woe:centroid": [-90.586761, 41.471359], "geom:latitude": 41.471359, "geom:longitude": -90.586761, "geom:hash": "9zreftsspmxk", "woe:latitude": 41.471359, "geom:centroid": [-90.586761, 41.471359], "woe:longitude": -90.586761, "woe:repo": "woeplanet-poi-us"}, "geometry": {"coordinates": [-90.586761, 41.471359], "type": "Point"}}