{"type": "Feature", "id": 23577502, "properties": {"woe:id": 23577502, "woe:parent_id": 28338858, "woe:name": "Northlake Christian School", "woe:placetype": 20, "woe:placetype_name": "POI", "woe:lang": "ENG", "iso:country": "US", "meta:provider": ["geoplanet:7.3.1", "geoplanet:7.3.2", "geoplanet:7.4.0", "geoplanet:7.4.1", "geoplanet:7.5.1", "geoplanet:7.5.2", "geoplanet:7.6.0", "geoplanet:7.8.1", "geoplanet:7.9.0", "geoplanet:7.10.0", "geoplanet:8.0.0", "woeplanet:8.0.0"], "meta:indexed": "2020-08-20T20:18:37.913981", "meta:updated": "2020-08-22T02:57:37.438767", "woe:hierarchy": {"continent": 24865672, "country": 23424977, "town": 0, "planet": 1, "county": 12588647, "suburb": 0, "state": 2347577, "region": 0, "localadmin": 0}, "woe:timezone_id": 56043661, "woe:hash": "9vrvjzvfepy8", "woe:centroid": [-90.090843, 30.453199], "geom:latitude": 30.453199, "geom:longitude": -90.090843, "geom:hash": "9vrvjzvfepy8", "woe:latitude": 30.453199, "geom:centroid": [-90.090843, 30.453199], "woe:longitude": -90.090843, "woe:repo": "woeplanet-poi-us"}, "geometry": {"coordinates": [-90.090843, 30.453199], "type": "Point"}}