{"type": "Feature", "id": 23681445, "properties": {"woe:id": 23681445, "woe:parent_id": 2507478, "woe:name": "Towns Station", "woe:placetype": 20, "woe:placetype_name": "POI", "woe:lang": "ENG", "iso:country": "US", "meta:provider": ["geoplanet:7.3.1", "geoplanet:7.3.2", "geoplanet:7.4.0", "geoplanet:7.4.1", "geoplanet:7.5.1", "geoplanet:7.5.2", "geoplanet:7.6.0", "geoplanet:7.8.1", "geoplanet:7.9.0", "geoplanet:7.10.0", "geoplanet:8.0.0", "woeplanet:8.0.0"], "meta:indexed": "2020-08-20T20:19:19.150418", "meta:updated": "2020-08-22T02:58:22.049088", "woe:hierarchy": {"continent": 24865672, "country": 23424977, "town": 0, "planet": 1, "county": 12588003, "suburb": 0, "state": 2347569, "region": 0, "localadmin": 0}, "woe:timezone_id": 56043648, "woe:hash": "djtnhfeyen0g", "woe:centroid": [-82.75473, 32.007069], "geom:latitude": 32.007069, "geom:longitude": -82.75473, "geom:hash": "djtnhfeyen0g", "woe:latitude": 32.007069, "geom:centroid": [-82.75473, 32.007069], "woe:longitude": -82.75473, "woe:repo": "woeplanet-poi-us"}, "geometry": {"coordinates": [-82.75473, 32.007069], "type": "Point"}}