{"type": "Feature", "id": 23639942, "properties": {"woe:id": 23639942, "woe:parent_id": 28745473, "woe:name": "Park Forest Middle School", "woe:placetype": 20, "woe:placetype_name": "POI", "woe:lang": "ENG", "iso:country": "US", "meta:provider": ["geoplanet:7.3.1", "geoplanet:7.3.2", "geoplanet:7.4.0", "geoplanet:7.4.1", "geoplanet:7.5.1", "geoplanet:7.5.2", "geoplanet:7.6.0", "geoplanet:7.8.1", "geoplanet:7.9.0", "geoplanet:7.10.0", "geoplanet:8.0.0", "woeplanet:8.0.0"], "meta:indexed": "2020-08-20T20:18:58.386046", "meta:updated": "2020-08-22T02:57:46.702524", "woe:hierarchy": {"continent": 24865672, "country": 23424977, "town": 0, "planet": 1, "county": 12589741, "suburb": 0, "state": 2347597, "region": 0, "localadmin": 0}, "woe:timezone_id": 56043648, "woe:hash": "dr284uk1y2u7", "woe:centroid": [-77.920258, 40.804901], "geom:latitude": 40.804901, "geom:longitude": -77.920258, "geom:hash": "dr284uk1y2u7", "woe:latitude": 40.804901, "geom:centroid": [-77.920258, 40.804901], "woe:longitude": -77.920258, "woe:repo": "woeplanet-poi-us"}, "geometry": {"coordinates": [-77.920258, 40.804901], "type": "Point"}}