{"type": "Feature", "id": 24701324, "properties": {"woe:id": 24701324, "woe:parent_id": 2416016, "woe:name": "Hagerman Fossil Beds National Monument", "woe:placetype": 20, "woe:placetype_name": "POI", "woe:lang": "ENG", "iso:country": "US", "meta:provider": ["geoplanet:7.3.2", "geoplanet:7.4.0", "geoplanet:7.4.1", "geoplanet:7.5.1", "geoplanet:7.5.2", "geoplanet:7.6.0", "geoplanet:7.8.1", "geoplanet:7.9.0", "geoplanet:7.10.0", "geoplanet:8.0.0", "woeplanet:8.0.0"], "meta:indexed": "2020-08-20T22:03:05.754859", "woe:alias_ENG_V": ["Hagerman Fossil Beds NM", "Hagerman Fossil Beds Natl Monument"], "meta:updated": "2020-08-22T02:58:19.536107", "woe:hierarchy": {"continent": 24865672, "country": 23424977, "town": 0, "planet": 1, "county": 12588057, "suburb": 0, "state": 2347571, "region": 0, "localadmin": 0}, "woe:timezone_id": 56043662, "woe:hash": "9rw789u31zbf", "woe:centroid": [-114.933052, 42.812561], "geom:latitude": 42.812561, "geom:longitude": -114.933052, "geom:hash": "9rw789u31zbf", "woe:latitude": 42.812561, "geom:centroid": [-114.933052, 42.812561], "woe:longitude": -114.933052, "woe:repo": "woeplanet-poi-us"}, "geometry": {"coordinates": [-114.933052, 42.812561], "type": "Point"}}