{"type": "Feature", "id": 23683797, "properties": {"woe:id": 23683797, "woe:parent_id": 2369932, "woe:name": "Brookline Village Station", "woe:placetype": 20, "woe:placetype_name": "POI", "woe:lang": "ENG", "iso:country": "US", "meta:provider": ["geoplanet:7.4.0", "geoplanet:7.4.1", "geoplanet:7.5.1", "geoplanet:7.5.2", "geoplanet:7.6.0", "geoplanet:7.8.1", "geoplanet:7.9.0", "geoplanet:7.10.0", "geoplanet:8.0.0", "woeplanet:8.0.0"], "meta:indexed": "2020-08-20T23:56:01.664310", "woe:alias_ENG_V": ["Brookline Village MBTA Station", "MBTA Brookline Village Station", "Mbta-Brookline Village"], "meta:updated": "2020-08-22T02:58:23.793351", "woe:hierarchy": {"continent": 24865672, "country": 23424977, "town": 0, "planet": 1, "county": 12588710, "suburb": 0, "state": 2347580, "region": 0, "localadmin": 0}, "woe:timezone_id": 56043648, "woe:hash": "drt2vdqnn09s", "woe:centroid": [-71.116989, 42.332729], "geom:latitude": 42.332729, "geom:longitude": -71.116989, "geom:hash": "drt2vdqnn09s", "woe:latitude": 42.332729, "geom:centroid": [-71.116989, 42.332729], "woe:longitude": -71.116989, "woe:repo": "woeplanet-poi-us"}, "geometry": {"coordinates": [-71.116989, 42.332729], "type": "Point"}}