{"type": "Feature", "id": 23513298, "geometry": {"type": "Point", "coordinates": [-86.595383, 33.656319]}, "properties": {"woe:id": 23513298, "woe:parent_id": 2508312, "woe:name": "Hewitt-trussville High School", "woe:placetype": 20, "woe:placetype_name": "POI", "woe:lang": "ENG", "iso:country": "US", "meta:provider": ["geoplanet:7.3.1", "geoplanet:7.3.2", "geoplanet:7.4.0", "geoplanet:7.4.1", "geoplanet:7.5.1", "geoplanet:7.5.2", "geoplanet:7.6.0", "geoplanet:7.8.1", "geoplanet:7.9.0", "geoplanet:7.10.0", "geoplanet:8.0.0", "woeplanet:8.0.0"], "meta:indexed": "2020-08-20T20:18:17.350947", "woe:alias_ENG_V": ["Hewitt-trussville Senior High School", "Hewitt-trussville High", "Hewitt-trussville Senior High", "Hewitt-trussville HS", "Hewitt-trussville Senior HS"], "meta:updated": "2020-10-14T11:20:09.931508", "woe:hierarchy": {"continent": 24865672, "country": 23424977, "town": 0, "planet": 1, "county": 12587523, "suburb": 0, "state": 2347559, "region": 0, "localadmin": 0}, "woe:timezone_id": 56043661, "woe:hash": "djfrmqznm2d7", "woe:centroid": [-86.595383, 33.656319], "geom:latitude": 33.656319, "geom:longitude": -86.595383, "geom:hash": "djfrmqznm2d7", "woe:latitude": 33.656319, "geom:centroid": [-86.595383, 33.656319], "woe:longitude": -86.595383, "woe:repo": "woeplanet-poi-us", "geom:area": 0.0, "woe:scale": 19}}