{"type": "Feature", "id": 23633151, "geometry": {"type": "Point", "coordinates": [-83.391068, 40.700649]}, "properties": {"woe:id": 23633151, "woe:parent_id": 2446063, "woe:name": "Marseilles Elementary School", "woe:placetype": 20, "woe:placetype_name": "POI", "woe:lang": "ENG", "iso:country": "US", "meta:provider": ["geoplanet:7.3.1", "geoplanet:7.3.2", "geoplanet:7.4.0", "geoplanet:7.4.1", "geoplanet:7.5.1", "geoplanet:7.5.2", "geoplanet:7.6.0", "geoplanet:7.8.1", "geoplanet:7.9.0", "geoplanet:7.10.0", "geoplanet:8.0.0", "woeplanet:8.0.0"], "meta:indexed": "2020-08-20T20:18:55.923976", "woe:alias_ENG_V": ["Marseilles Elementary"], "meta:updated": "2020-10-14T11:19:42.526767", "woe:hierarchy": {"continent": 24865672, "country": 23424977, "town": 0, "planet": 1, "county": 12589614, "suburb": 0, "state": 2347594, "region": 0, "localadmin": 0}, "woe:timezone_id": 56043648, "woe:hash": "dphxw3k6rqbu", "woe:centroid": [-83.391068, 40.700649], "geom:latitude": 40.700649, "geom:longitude": -83.391068, "geom:hash": "dphxw3k6rqbu", "woe:latitude": 40.700649, "geom:centroid": [-83.391068, 40.700649], "woe:longitude": -83.391068, "woe:repo": "woeplanet-poi-us", "geom:area": 0.0, "woe:scale": 19}}