{"type": "Feature", "id": 23592844, "properties": {"woe:id": 23592844, "woe:parent_id": 56022166, "woe:name": "Vista View Elementary School", "woe:placetype": 20, "woe:placetype_name": "POI", "woe:lang": "ENG", "iso:country": "US", "meta:provider": ["geoplanet:7.3.1", "geoplanet:7.3.2", "geoplanet:7.4.0", "geoplanet:7.4.1", "geoplanet:7.5.1", "geoplanet:7.5.2", "geoplanet:7.6.0", "geoplanet:7.8.1", "geoplanet:7.9.0", "geoplanet:7.10.0", "geoplanet:8.0.0", "woeplanet:8.0.0"], "meta:indexed": "2020-08-20T20:18:42.194345", "woe:alias_ENG_V": ["Vista View Elementary"], "meta:updated": "2020-08-22T02:57:39.861206", "woe:hierarchy": {"continent": 24865672, "country": 23424977, "town": 0, "planet": 1, "county": 12588815, "suburb": 0, "state": 2347582, "region": 0, "localadmin": 0}, "woe:timezone_id": 56043661, "woe:hash": "9zvwsv6jtr6u", "woe:centroid": [-93.303909, 44.766151], "geom:latitude": 44.766151, "geom:longitude": -93.303909, "geom:hash": "9zvwsv6jtr6u", "woe:latitude": 44.766151, "geom:centroid": [-93.303909, 44.766151], "woe:longitude": -93.303909, "woe:repo": "woeplanet-poi-us"}, "geometry": {"coordinates": [-93.303909, 44.766151], "type": "Point"}}