{"type": "Feature", "id": 23516075, "properties": {"woe:id": 23516075, "woe:parent_id": 55806326, "woe:name": "Sunridge Learning Center", "woe:placetype": 20, "woe:placetype_name": "POI", "woe:lang": "ENG", "iso:country": "US", "meta:provider": ["geoplanet:7.3.1", "geoplanet:7.3.2", "geoplanet:7.4.0", "geoplanet:7.4.1", "geoplanet:7.5.1", "geoplanet:7.5.2", "geoplanet:7.6.0", "geoplanet:7.8.1", "geoplanet:7.9.0", "geoplanet:7.10.0", "geoplanet:8.0.0", "woeplanet:8.0.0"], "meta:indexed": "2020-08-20T20:18:18.213398", "meta:updated": "2020-08-22T02:57:26.590537", "woe:hierarchy": {"continent": 24865672, "country": 23424977, "town": 0, "planet": 1, "county": 12587587, "suburb": 0, "state": 2347561, "region": 0, "localadmin": 0}, "woe:timezone_id": 56043666, "woe:hash": "9tbmyc9pye4e", "woe:centroid": [-111.850151, 33.364079], "geom:latitude": 33.364079, "geom:longitude": -111.850151, "geom:hash": "9tbmyc9pye4e", "woe:latitude": 33.364079, "geom:centroid": [-111.850151, 33.364079], "woe:longitude": -111.850151, "woe:repo": "woeplanet-poi-us"}, "geometry": {"coordinates": [-111.850151, 33.364079], "type": "Point"}}