{"type": "Feature", "id": 56054782, "geometry": {"type": "Point", "coordinates": [-75.650337, 39.688171]}, "properties": {"woe:id": 56054782, "woe:parent_id": 2397095, "woe:name": "Delaware Tech & Community College", "woe:placetype": 20, "woe:placetype_name": "POI", "woe:lang": "ENG", "iso:country": "US", "meta:provider": ["geoplanet:7.3.1", "geoplanet:7.3.2", "geoplanet:7.4.0", "geoplanet:7.4.1", "geoplanet:7.5.1", "geoplanet:7.5.2", "geoplanet:7.6.0", "geoplanet:7.8.1", "geoplanet:7.9.0", "geoplanet:7.10.0", "geoplanet:8.0.0", "woeplanet:8.0.0"], "meta:indexed": "2020-08-20T20:19:18.115181", "meta:updated": "2020-10-14T11:19:55.378870", "woe:hierarchy": {"continent": 24865672, "country": 23424977, "town": 0, "planet": 1, "county": 12587800, "suburb": 0, "state": 2347566, "region": 0, "localadmin": 0}, "woe:timezone_id": 56043648, "woe:hash": "dr41y91077k3", "woe:centroid": [-75.650337, 39.688171], "geom:latitude": 39.688171, "geom:longitude": -75.650337, "geom:hash": "dr41y91077k3", "woe:latitude": 39.688171, "geom:centroid": [-75.650337, 39.688171], "woe:longitude": -75.650337, "woe:repo": "woeplanet-poi-us", "geom:area": 0.0, "woe:scale": 19}}