{"type": "Feature", "id": 23620371, "geometry": {"type": "Point", "coordinates": [-74.331238, 42.596119]}, "properties": {"woe:id": 23620371, "woe:parent_id": 2450301, "woe:name": "Middleburgh Middle School", "woe:placetype": 20, "woe:placetype_name": "POI", "woe:lang": "ENG", "iso:country": "US", "meta:provider": ["geoplanet:7.3.1", "geoplanet:7.3.2", "geoplanet:7.4.0", "geoplanet:7.4.1", "geoplanet:7.5.1", "geoplanet:7.5.2", "geoplanet:7.6.0", "geoplanet:7.8.1", "geoplanet:7.9.0", "geoplanet:7.10.0", "geoplanet:8.0.0", "woeplanet:8.0.0"], "meta:indexed": "2020-08-20T20:18:51.597838", "meta:updated": "2020-10-14T11:19:45.846089", "woe:hierarchy": {"continent": 24865672, "country": 23424977, "town": 0, "planet": 1, "county": 12589358, "suburb": 0, "state": 2347591, "region": 0, "localadmin": 0}, "woe:timezone_id": 56043648, "woe:hash": "dre4kd3sks5g", "woe:centroid": [-74.331238, 42.596119], "geom:latitude": 42.596119, "geom:longitude": -74.331238, "geom:hash": "dre4kd3sks5g", "woe:latitude": 42.596119, "geom:centroid": [-74.331238, 42.596119], "woe:longitude": -74.331238, "woe:repo": "woeplanet-poi-us", "geom:area": 0.0, "woe:scale": 19}}