{"type": "Feature", "id": 23632016, "geometry": {"type": "Point", "coordinates": [-82.51886, 40.756149]}, "properties": {"woe:id": 23632016, "woe:parent_id": 56022425, "woe:name": "St Peters High School", "woe:placetype": 20, "woe:placetype_name": "POI", "woe:lang": "ENG", "iso:country": "US", "meta:provider": ["geoplanet:7.3.1", "geoplanet:7.3.2", "geoplanet:7.4.0", "geoplanet:7.4.1", "geoplanet:7.5.1", "geoplanet:7.5.2", "geoplanet:7.6.0", "geoplanet:7.8.1", "geoplanet:7.9.0", "geoplanet:7.10.0", "geoplanet:8.0.0", "woeplanet:8.0.0"], "meta:indexed": "2020-08-20T20:18:55.401624", "woe:alias_ENG_V": ["St Peters Senior High School", "St Peters High", "St Peters Senior High", "St Peters HS", "St Peters Senior HS"], "meta:updated": "2020-10-14T11:19:43.564451", "woe:hierarchy": {"continent": 24865672, "country": 23424977, "town": 0, "planet": 1, "county": 12589596, "suburb": 0, "state": 2347594, "region": 0, "localadmin": 0}, "woe:timezone_id": 56043648, "woe:hash": "dpjrf5rtg0y6", "woe:centroid": [-82.51886, 40.756149], "geom:latitude": 40.756149, "geom:longitude": -82.51886, "geom:hash": "dpjrf5rtg0y6", "woe:latitude": 40.756149, "geom:centroid": [-82.51886, 40.756149], "woe:longitude": -82.51886, "woe:repo": "woeplanet-poi-us", "geom:area": 0.0, "woe:scale": 19}}