{"type": "Feature", "id": 23683734, "properties": {"woe:id": 23683734, "woe:parent_id": 28751422, "woe:name": "Cumberland Station", "woe:placetype": 20, "woe:placetype_name": "POI", "woe:lang": "ENG", "iso:country": "US", "meta:provider": ["geoplanet:7.3.1", "geoplanet:7.3.2", "geoplanet:7.4.0", "geoplanet:7.4.1", "geoplanet:7.5.1", "geoplanet:7.5.2", "geoplanet:7.6.0", "geoplanet:7.8.1", "geoplanet:7.9.0", "geoplanet:7.10.0", "geoplanet:8.0.0", "woeplanet:8.0.0"], "meta:indexed": "2020-08-20T20:19:20.486670", "woe:alias_ENG_V": ["Cta-Cumberland", "Cumberland CTA Station", "CTA Cumberland Station", "Cta-Blue Line-Cumberland"], "meta:updated": "2020-08-22T02:58:22.812574", "woe:hierarchy": {"continent": 24865672, "country": 23424977, "town": 0, "planet": 1, "county": 12588093, "suburb": 0, "state": 2347572, "region": 0, "localadmin": 0}, "woe:timezone_id": 56043661, "woe:hash": "dp3wc4xqh4ft", "woe:centroid": [-87.836548, 41.982552], "geom:latitude": 41.982552, "geom:longitude": -87.836548, "geom:hash": "dp3wc4xqh4ft", "woe:latitude": 41.982552, "geom:centroid": [-87.836548, 41.982552], "woe:longitude": -87.836548, "woe:repo": "woeplanet-poi-us"}, "geometry": {"coordinates": [-87.836548, 41.982552], "type": "Point"}}