{"type": "Feature", "id": 23563080, "properties": {"woe:id": 23563080, "woe:parent_id": 2448048, "woe:name": "Riverwood Elementary School", "woe:placetype": 20, "woe:placetype_name": "POI", "woe:lang": "ENG", "iso:country": "US", "meta:provider": ["geoplanet:7.3.1", "geoplanet:7.3.2", "geoplanet:7.4.0", "geoplanet:7.4.1", "geoplanet:7.5.1", "geoplanet:7.5.2", "geoplanet:7.6.0", "geoplanet:7.8.1", "geoplanet:7.9.0", "geoplanet:7.10.0", "geoplanet:8.0.0", "woeplanet:8.0.0"], "meta:indexed": "2020-08-20T20:18:32.706246", "woe:alias_ENG_V": ["Riverwood Elementary"], "meta:updated": "2020-08-22T02:57:34.920097", "woe:hierarchy": {"continent": 24865672, "country": 23424977, "town": 0, "planet": 1, "county": 12588140, "suburb": 0, "state": 2347572, "region": 0, "localadmin": 0}, "woe:timezone_id": 56043661, "woe:hash": "dp90yc0cygb6", "woe:centroid": [-88.295799, 42.32515], "geom:latitude": 42.32515, "geom:longitude": -88.295799, "geom:hash": "dp90yc0cygb6", "woe:latitude": 42.32515, "geom:centroid": [-88.295799, 42.32515], "woe:longitude": -88.295799, "woe:repo": "woeplanet-poi-us"}, "geometry": {"coordinates": [-88.295799, 42.32515], "type": "Point"}}