{"type": "Feature", "id": 23552082, "geometry": {"type": "Point", "coordinates": [-84.290169, 33.765461]}, "properties": {"woe:id": 23552082, "woe:parent_id": 55985341, "woe:name": "Winnona Park Elementary School", "woe:placetype": 20, "woe:placetype_name": "POI", "woe:lang": "ENG", "iso:country": "US", "meta:provider": ["geoplanet:7.3.1", "geoplanet:7.3.2", "geoplanet:7.4.0", "geoplanet:7.4.1", "geoplanet:7.5.1", "geoplanet:7.5.2", "geoplanet:7.6.0", "geoplanet:7.8.1", "geoplanet:7.9.0", "geoplanet:7.10.0", "geoplanet:8.0.0", "woeplanet:8.0.0"], "meta:indexed": "2020-08-20T20:18:29.125867", "woe:alias_ENG_V": ["Winnona Park Elementary"], "meta:updated": "2020-10-14T11:20:21.040946", "woe:hierarchy": {"continent": 24865672, "country": 23424977, "town": 0, "planet": 1, "county": 12587913, "suburb": 0, "state": 2347569, "region": 0, "localadmin": 0}, "woe:timezone_id": 56043648, "woe:hash": "dnh01fvf0dns", "woe:centroid": [-84.290169, 33.765461], "geom:latitude": 33.765461, "geom:longitude": -84.290169, "geom:hash": "dnh01fvf0dns", "woe:latitude": 33.765461, "geom:centroid": [-84.290169, 33.765461], "woe:longitude": -84.290169, "woe:repo": "woeplanet-poi-us", "geom:area": 0.0, "woe:scale": 19}}