{"type": "Feature", "id": 23630333, "geometry": {"type": "Point", "coordinates": [-81.315643, 41.663559]}, "properties": {"woe:id": 23630333, "woe:parent_id": 56022459, "woe:name": "Hopkins Elementary School", "woe:placetype": 20, "woe:placetype_name": "POI", "woe:lang": "ENG", "iso:country": "US", "meta:provider": ["geoplanet:7.3.1", "geoplanet:7.3.2", "geoplanet:7.4.0", "geoplanet:7.4.1", "geoplanet:7.5.1", "geoplanet:7.5.2", "geoplanet:7.6.0", "geoplanet:7.8.1", "geoplanet:7.9.0", "geoplanet:7.10.0", "geoplanet:8.0.0", "woeplanet:8.0.0"], "meta:indexed": "2020-08-20T20:18:54.610590", "woe:alias_ENG_V": ["Hopkins Elementary"], "meta:updated": "2020-10-14T11:19:26.616819", "woe:hierarchy": {"continent": 24865672, "country": 23424977, "town": 0, "planet": 1, "county": 12589569, "suburb": 0, "state": 2347594, "region": 0, "localadmin": 0}, "woe:timezone_id": 56043648, "woe:hash": "dpqjj8egb4mf", "woe:centroid": [-81.315643, 41.663559], "geom:latitude": 41.663559, "geom:longitude": -81.315643, "geom:hash": "dpqjj8egb4mf", "woe:latitude": 41.663559, "geom:centroid": [-81.315643, 41.663559], "woe:longitude": -81.315643, "woe:repo": "woeplanet-poi-us", "geom:area": 0.0, "woe:scale": 19}}