{"type": "Feature", "id": 23651461, "properties": {"woe:id": 23651461, "woe:parent_id": 2365011, "woe:name": "Franklin Road Christian School", "woe:placetype": 20, "woe:placetype_name": "POI", "woe:lang": "ENG", "iso:country": "US", "meta:provider": ["geoplanet:7.3.1", "geoplanet:7.3.2", "geoplanet:7.4.0", "geoplanet:7.4.1", "geoplanet:7.5.1", "geoplanet:7.5.2", "geoplanet:7.6.0", "geoplanet:7.8.1", "geoplanet:7.9.0", "geoplanet:7.10.0", "geoplanet:8.0.0", "woeplanet:8.0.0"], "meta:indexed": "2020-08-20T20:19:02.082928", "meta:updated": "2020-08-22T02:57:48.409794", "woe:hierarchy": {"continent": 24865672, "country": 23424977, "town": 0, "planet": 1, "county": 12589986, "suburb": 0, "state": 2347601, "region": 0, "localadmin": 0}, "woe:timezone_id": 56043661, "woe:hash": "dn6ebv3k81vd", "woe:centroid": [-86.449692, 35.845051], "geom:latitude": 35.845051, "geom:longitude": -86.449692, "geom:hash": "dn6ebv3k81vd", "woe:latitude": 35.845051, "geom:centroid": [-86.449692, 35.845051], "woe:longitude": -86.449692, "woe:repo": "woeplanet-poi-us"}, "geometry": {"coordinates": [-86.449692, 35.845051], "type": "Point"}}