{"type": "Feature", "id": 23598395, "geometry": {"type": "Point", "coordinates": [-94.303497, 37.339691]}, "properties": {"woe:id": 23598395, "woe:parent_id": 2428726, "woe:name": "Jasper County Elementary School", "woe:placetype": 20, "woe:placetype_name": "POI", "woe:lang": "ENG", "iso:country": "US", "meta:provider": ["geoplanet:7.3.1", "geoplanet:7.3.2", "geoplanet:7.4.0", "geoplanet:7.4.1", "geoplanet:7.5.1", "geoplanet:7.5.2", "geoplanet:7.6.0", "geoplanet:7.8.1", "geoplanet:7.9.0", "geoplanet:7.10.0", "geoplanet:8.0.0", "woeplanet:8.0.0"], "meta:indexed": "2020-08-20T20:18:44.256977", "woe:alias_ENG_V": ["Jasper Elementary School", "Jasper County Elementary"], "meta:updated": "2020-10-14T11:20:26.821325", "woe:hierarchy": {"continent": 24865672, "country": 23424977, "town": 0, "planet": 1, "county": 12589014, "suburb": 0, "state": 2347584, "region": 0, "localadmin": 0}, "woe:timezone_id": 56043661, "woe:hash": "9ysuqj6r3qbh", "woe:centroid": [-94.303497, 37.339691], "geom:latitude": 37.339691, "geom:longitude": -94.303497, "geom:hash": "9ysuqj6r3qbh", "woe:latitude": 37.339691, "geom:centroid": [-94.303497, 37.339691], "woe:longitude": -94.303497, "woe:repo": "woeplanet-poi-us", "geom:area": 0.0, "woe:scale": 19}}