{"type": "Feature", "id": 23553125, "geometry": {"type": "Point", "coordinates": [-84.199081, 33.874802]}, "properties": {"woe:id": 23553125, "woe:parent_id": 2439241, "woe:name": "Nesbit Elementary School", "woe:placetype": 20, "woe:placetype_name": "POI", "woe:lang": "ENG", "iso:country": "US", "meta:provider": ["geoplanet:7.3.1", "geoplanet:7.3.2", "geoplanet:7.4.0", "geoplanet:7.4.1", "geoplanet:7.5.1", "geoplanet:7.5.2", "geoplanet:7.6.0", "geoplanet:7.8.1", "geoplanet:7.9.0", "geoplanet:7.10.0", "geoplanet:8.0.0", "woeplanet:8.0.0"], "meta:indexed": "2020-08-20T20:18:29.498727", "woe:alias_ENG_V": ["Nesbit Elementary"], "meta:updated": "2020-10-14T11:20:15.804742", "woe:hierarchy": {"continent": 24865672, "country": 23424977, "town": 0, "planet": 1, "county": 12587936, "suburb": 0, "state": 2347569, "region": 0, "localadmin": 0}, "woe:timezone_id": 56043648, "woe:hash": "dnh0sn8p50y8", "woe:centroid": [-84.199081, 33.874802], "geom:latitude": 33.874802, "geom:longitude": -84.199081, "geom:hash": "dnh0sn8p50y8", "woe:latitude": 33.874802, "geom:centroid": [-84.199081, 33.874802], "woe:longitude": -84.199081, "woe:repo": "woeplanet-poi-us", "geom:area": 0.0, "woe:scale": 19}}