{"type": "Feature", "id": 23545800, "properties": {"woe:id": 23545800, "woe:parent_id": 26342874, "woe:name": "Brevard Zoo", "woe:placetype": 20, "woe:placetype_name": "POI", "woe:lang": "ENG", "iso:country": "US", "meta:provider": ["geoplanet:7.3.1", "geoplanet:7.3.2", "geoplanet:7.4.0", "geoplanet:7.4.1", "geoplanet:7.5.1", "geoplanet:7.5.2", "geoplanet:7.6.0", "geoplanet:7.8.1", "geoplanet:7.9.0", "geoplanet:7.10.0", "geoplanet:8.0.0", "woeplanet:8.0.0"], "meta:indexed": "2020-08-20T20:18:26.062267", "meta:updated": "2020-08-22T02:57:31.591736", "woe:hierarchy": {"continent": 24865672, "country": 23424977, "town": 0, "planet": 1, "county": 12587807, "suburb": 0, "state": 2347568, "region": 0, "localadmin": 0}, "woe:timezone_id": 56043648, "woe:hash": "djn8e63euyx2", "woe:centroid": [-80.714279, 28.225929], "geom:latitude": 28.225929, "geom:longitude": -80.714279, "geom:hash": "djn8e63euyx2", "woe:latitude": 28.225929, "geom:centroid": [-80.714279, 28.225929], "woe:longitude": -80.714279, "woe:repo": "woeplanet-poi-us"}, "geometry": {"coordinates": [-80.714279, 28.225929], "type": "Point"}}