{"type": "Feature", "id": 23625835, "properties": {"woe:id": 23625835, "woe:parent_id": 2454747, "woe:name": "Bruce H Tharrington Elementary School", "woe:placetype": 20, "woe:placetype_name": "POI", "woe:lang": "ENG", "iso:country": "US", "meta:provider": ["geoplanet:7.3.1", "geoplanet:7.3.2", "geoplanet:7.4.0", "geoplanet:7.4.1", "geoplanet:7.5.1", "geoplanet:7.5.2", "geoplanet:7.6.0", "geoplanet:7.8.1", "geoplanet:7.9.0", "geoplanet:7.10.0", "geoplanet:8.0.0", "woeplanet:8.0.0"], "meta:indexed": "2020-08-20T20:18:52.946545", "woe:alias_ENG_V": ["Tharrington Elementary School", "Bruce H Tharrington Elementary"], "meta:updated": "2020-08-22T02:57:44.504180", "woe:hierarchy": {"continent": 24865672, "country": 23424977, "town": 0, "planet": 1, "county": 12589459, "suburb": 0, "state": 2347592, "region": 0, "localadmin": 0}, "woe:timezone_id": 56043648, "woe:hash": "dnqxtg5dxf6m", "woe:centroid": [-80.601547, 36.491531], "geom:latitude": 36.491531, "geom:longitude": -80.601547, "geom:hash": "dnqxtg5dxf6m", "woe:latitude": 36.491531, "geom:centroid": [-80.601547, 36.491531], "woe:longitude": -80.601547, "woe:repo": "woeplanet-poi-us"}, "geometry": {"coordinates": [-80.601547, 36.491531], "type": "Point"}}