{"type": "Feature", "id": 23644045, "geometry": {"type": "Point", "coordinates": [-75.229599, 39.947811]}, "properties": {"woe:id": 23644045, "woe:parent_id": 2432720, "woe:name": "Harrington Avery Day School", "woe:placetype": 20, "woe:placetype_name": "POI", "woe:lang": "ENG", "iso:country": "US", "meta:provider": ["geoplanet:7.3.1", "geoplanet:7.3.2", "geoplanet:7.4.0", "geoplanet:7.4.1", "geoplanet:7.5.1", "geoplanet:7.5.2", "geoplanet:7.6.0", "geoplanet:7.8.1", "geoplanet:7.9.0", "geoplanet:7.10.0", "geoplanet:8.0.0", "woeplanet:8.0.0"], "meta:indexed": "2020-08-20T20:18:59.818917", "meta:updated": "2020-10-14T11:19:38.132926", "woe:alias_ENG_V": ["Harrington Elementary School"], "woe:hierarchy": {"continent": 24865672, "country": 23424977, "town": 0, "planet": 1, "county": 12589778, "suburb": 0, "state": 2347597, "region": 0, "localadmin": 0}, "woe:timezone_id": 56043648, "woe:hash": "dr4e2072z79n", "woe:centroid": [-75.229599, 39.947811], "geom:latitude": 39.947811, "geom:longitude": -75.229599, "geom:hash": "dr4e2072z79n", "woe:latitude": 39.947811, "geom:centroid": [-75.229599, 39.947811], "woe:longitude": -75.229599, "woe:repo": "woeplanet-poi-us", "geom:area": 0.0, "woe:scale": 19}}