{"type": "Feature", "id": 23660797, "properties": {"woe:id": 23660797, "woe:parent_id": 2512155, "woe:name": "Oak Forest Elementary School", "woe:placetype": 20, "woe:placetype_name": "POI", "woe:lang": "ENG", "iso:country": "US", "meta:provider": ["geoplanet:7.3.1", "geoplanet:7.3.2", "geoplanet:7.4.0", "geoplanet:7.4.1", "geoplanet:7.5.1", "geoplanet:7.5.2", "geoplanet:7.6.0", "geoplanet:7.8.1", "geoplanet:7.9.0", "geoplanet:7.10.0", "geoplanet:8.0.0", "woeplanet:8.0.0"], "meta:indexed": "2020-08-20T20:19:06.626140", "woe:alias_ENG_V": ["Oak Forest Elementary"], "meta:updated": "2020-08-22T02:57:50.589252", "woe:hierarchy": {"continent": 24865672, "country": 23424977, "town": 0, "planet": 1, "county": 12590187, "suburb": 0, "state": 2347602, "region": 0, "localadmin": 0}, "woe:timezone_id": 56043661, "woe:hash": "9vm5mpqs84mv", "woe:centroid": [-93.990089, 30.14315], "geom:latitude": 30.14315, "geom:longitude": -93.990089, "geom:hash": "9vm5mpqs84mv", "woe:latitude": 30.14315, "geom:centroid": [-93.990089, 30.14315], "woe:longitude": -93.990089, "woe:repo": "woeplanet-poi-us"}, "geometry": {"coordinates": [-93.990089, 30.14315], "type": "Point"}}