{"type": "Feature", "id": 23539019, "properties": {"woe:id": 23539019, "woe:parent_id": 55806601, "woe:name": "Dakota Valley Elementary School", "woe:placetype": 20, "woe:placetype_name": "POI", "woe:lang": "ENG", "iso:country": "US", "meta:provider": ["geoplanet:7.3.1", "geoplanet:7.3.2", "geoplanet:7.4.0", "geoplanet:7.4.1", "geoplanet:7.5.1", "geoplanet:7.5.2", "geoplanet:7.6.0", "geoplanet:7.8.1", "geoplanet:7.9.0", "geoplanet:7.10.0", "geoplanet:8.0.0", "woeplanet:8.0.0"], "meta:indexed": "2020-08-20T20:18:23.992337", "woe:alias_ENG_V": ["Dakota Valley Elementary"], "meta:updated": "2020-08-22T02:57:30.383410", "woe:hierarchy": {"continent": 24865672, "country": 23424977, "town": 0, "planet": 1, "county": 12587730, "suburb": 0, "state": 2347564, "region": 0, "localadmin": 0}, "woe:timezone_id": 56043665, "woe:hash": "9xj983jfgjbq", "woe:centroid": [-104.746613, 39.644669], "geom:latitude": 39.644669, "geom:longitude": -104.746613, "geom:hash": "9xj983jfgjbq", "woe:latitude": 39.644669, "geom:centroid": [-104.746613, 39.644669], "woe:longitude": -104.746613, "woe:repo": "woeplanet-poi-us"}, "geometry": {"coordinates": [-104.746613, 39.644669], "type": "Point"}}