{"type": "Feature", "id": 23589083, "geometry": {"type": "Point", "coordinates": [-84.274261, 43.64119]}, "properties": {"woe:id": 23589083, "woe:parent_id": 28744384, "woe:name": "H.h. Dow High School", "woe:placetype": 20, "woe:placetype_name": "POI", "woe:lang": "ENG", "iso:country": "US", "meta:provider": ["geoplanet:7.3.2", "geoplanet:7.4.0", "geoplanet:7.4.1", "geoplanet:7.5.1", "geoplanet:7.5.2", "geoplanet:7.6.0", "geoplanet:7.8.1", "geoplanet:7.9.0", "geoplanet:7.10.0", "geoplanet:8.0.0", "woeplanet:8.0.0"], "meta:indexed": "2020-08-20T22:02:26.245853", "woe:alias_ENG_V": ["H.h. Dow Senior High School", "H.h. Dow High", "H.h. Dow Senior High", "H.h. Dow HS", "H.h. Dow Senior HS"], "meta:updated": "2020-10-14T11:20:09.474855", "woe:hierarchy": {"continent": 24865672, "country": 23424977, "town": 0, "planet": 1, "county": 12588769, "suburb": 0, "state": 2347581, "region": 0, "localadmin": 0}, "woe:timezone_id": 56043658, "woe:hash": "dpu0629k77kq", "woe:centroid": [-84.274261, 43.64119], "geom:latitude": 43.64119, "geom:longitude": -84.274261, "geom:hash": "dpu0629k77kq", "woe:latitude": 43.64119, "geom:centroid": [-84.274261, 43.64119], "woe:longitude": -84.274261, "woe:repo": "woeplanet-poi-us", "geom:area": 0.0, "woe:scale": 19}}