{"type": "Feature", "id": 23670458, "geometry": {"type": "Point", "coordinates": [-122.510918, 47.159431]}, "properties": {"woe:id": 23670458, "woe:parent_id": 2381970, "woe:name": "Saint Frances Cabrini School", "woe:placetype": 20, "woe:placetype_name": "POI", "woe:lang": "ENG", "iso:country": "US", "meta:provider": ["geoplanet:7.4.0", "geoplanet:7.4.1", "geoplanet:7.5.1", "geoplanet:7.5.2", "geoplanet:7.6.0", "geoplanet:7.8.1", "geoplanet:7.9.0", "geoplanet:7.10.0", "geoplanet:8.0.0", "woeplanet:8.0.0"], "meta:indexed": "2020-08-20T23:55:46.842481", "meta:updated": "2020-10-14T11:19:30.208340", "woe:alias_ENG_V": ["St Francis Cabrini School"], "woe:hierarchy": {"continent": 24865672, "country": 23424977, "town": 0, "planet": 1, "county": 12590466, "suburb": 0, "state": 2347606, "region": 0, "localadmin": 0}, "woe:timezone_id": 56043663, "woe:hash": "c22uk1n78ene", "woe:centroid": [-122.510918, 47.159431], "geom:latitude": 47.159431, "geom:longitude": -122.510918, "geom:hash": "c22uk1n78ene", "woe:latitude": 47.159431, "geom:centroid": [-122.510918, 47.159431], "woe:longitude": -122.510918, "woe:repo": "woeplanet-poi-us", "geom:area": 0.0, "woe:scale": 19}}