{"type": "Feature", "id": 23668943, "properties": {"woe:id": 23668943, "woe:parent_id": 28747351, "woe:name": "Adelaide Elementary School", "woe:placetype": 20, "woe:placetype_name": "POI", "woe:lang": "ENG", "iso:country": "US", "meta:provider": ["geoplanet:7.3.1", "geoplanet:7.3.2", "geoplanet:7.4.0", "geoplanet:7.4.1", "geoplanet:7.5.1", "geoplanet:7.5.2", "geoplanet:7.6.0", "geoplanet:7.8.1", "geoplanet:7.9.0", "geoplanet:7.10.0", "geoplanet:8.0.0", "woeplanet:8.0.0"], "meta:indexed": "2020-08-20T20:19:09.232826", "woe:alias_ENG_V": ["Adelaide Elementary"], "meta:updated": "2020-08-22T02:57:51.921119", "woe:hierarchy": {"continent": 24865672, "country": 23424977, "town": 0, "planet": 1, "county": 12590456, "suburb": 0, "state": 2347606, "region": 0, "localadmin": 0}, "woe:timezone_id": 56043663, "woe:hash": "c22vr8p4ywxf", "woe:centroid": [-122.35582, 47.329609], "geom:latitude": 47.329609, "geom:longitude": -122.35582, "geom:hash": "c22vr8p4ywxf", "woe:latitude": 47.329609, "geom:centroid": [-122.35582, 47.329609], "woe:longitude": -122.35582, "woe:repo": "woeplanet-poi-us"}, "geometry": {"coordinates": [-122.35582, 47.329609], "type": "Point"}}