{"type": "Feature", "id": 23555208, "properties": {"woe:id": 23555208, "woe:parent_id": 23504809, "woe:name": "Koelsch Elementary School", "woe:placetype": 20, "woe:placetype_name": "POI", "woe:lang": "ENG", "iso:country": "US", "meta:provider": ["geoplanet:7.3.1", "geoplanet:7.3.2", "geoplanet:7.4.0", "geoplanet:7.4.1", "geoplanet:7.5.1", "geoplanet:7.5.2", "geoplanet:7.6.0", "geoplanet:7.8.1", "geoplanet:7.9.0", "geoplanet:7.10.0", "geoplanet:8.0.0", "woeplanet:8.0.0"], "meta:indexed": "2020-08-20T20:18:30.105966", "woe:alias_ENG_V": ["Koelsch Elementary"], "meta:updated": "2020-08-22T02:57:33.554543", "woe:hierarchy": {"continent": 24865672, "country": 23424977, "town": 0, "planet": 1, "county": 12588034, "suburb": 0, "state": 2347571, "region": 0, "localadmin": 0}, "woe:timezone_id": 56043662, "woe:hash": "9rv24t6ejv5b", "woe:centroid": [-116.253639, 43.623131], "geom:latitude": 43.623131, "geom:longitude": -116.253639, "geom:hash": "9rv24t6ejv5b", "woe:latitude": 43.623131, "geom:centroid": [-116.253639, 43.623131], "woe:longitude": -116.253639, "woe:repo": "woeplanet-poi-us"}, "geometry": {"coordinates": [-116.253639, 43.623131], "type": "Point"}}