{"type": "Feature", "id": 23653254, "properties": {"woe:id": 23653254, "woe:parent_id": 56022686, "woe:name": "Kennedy Assassination Site", "woe:placetype": 20, "woe:placetype_name": "POI", "woe:lang": "ENG", "iso:country": "US", "meta:provider": ["geoplanet:7.3.1", "geoplanet:7.3.2", "geoplanet:7.4.0", "geoplanet:7.4.1", "geoplanet:7.5.1", "geoplanet:7.5.2", "geoplanet:7.6.0", "geoplanet:7.8.1", "geoplanet:7.9.0", "geoplanet:7.10.0", "geoplanet:8.0.0", "woeplanet:8.0.0"], "meta:indexed": "2020-08-20T20:19:02.765677", "meta:updated": "2020-08-22T02:57:48.756077", "woe:hierarchy": {"continent": 24865672, "country": 23424977, "town": 0, "planet": 1, "county": 12590063, "suburb": 0, "state": 2347602, "region": 0, "localadmin": 0}, "woe:timezone_id": 56043661, "woe:hash": "9vg4mp69xgzy", "woe:centroid": [-96.807747, 32.779362], "geom:latitude": 32.779362, "geom:longitude": -96.807747, "geom:hash": "9vg4mp69xgzy", "woe:latitude": 32.779362, "geom:centroid": [-96.807747, 32.779362], "woe:longitude": -96.807747, "woe:repo": "woeplanet-poi-us"}, "geometry": {"coordinates": [-96.807747, 32.779362], "type": "Point"}}