{"type": "Feature", "id": 23614600, "properties": {"woe:id": 23614600, "woe:parent_id": 2435095, "woe:name": "Saint Agnes School", "woe:placetype": 20, "woe:placetype_name": "POI", "woe:lang": "ENG", "iso:country": "US", "meta:provider": ["geoplanet:7.4.0", "geoplanet:7.4.1", "geoplanet:7.5.1", "geoplanet:7.5.2", "geoplanet:7.6.0", "geoplanet:7.8.1", "geoplanet:7.9.0", "geoplanet:7.10.0", "geoplanet:8.0.0", "woeplanet:8.0.0"], "meta:indexed": "2020-08-20T23:55:21.165659", "meta:updated": "2020-08-22T02:57:42.906940", "woe:hierarchy": {"continent": 24865672, "country": 23424977, "town": 0, "planet": 1, "county": 12589327, "suburb": 0, "state": 2347591, "region": 0, "localadmin": 0}, "woe:timezone_id": 56043648, "woe:hash": "drg7ur5f8cu7", "woe:centroid": [-73.987732, 44.291821], "geom:latitude": 44.291821, "geom:longitude": -73.987732, "geom:hash": "drg7ur5f8cu7", "woe:latitude": 44.291821, "geom:centroid": [-73.987732, 44.291821], "woe:longitude": -73.987732, "woe:repo": "woeplanet-poi-us"}, "geometry": {"coordinates": [-73.987732, 44.291821], "type": "Point"}}