{"type": "Feature", "id": 23625590, "geometry": {"type": "Point", "coordinates": [-79.26532, 35.32589]}, "properties": {"woe:id": 23625590, "woe:parent_id": 2373702, "woe:name": "Cameron Elementary School", "woe:placetype": 20, "woe:placetype_name": "POI", "woe:lang": "ENG", "iso:country": "US", "meta:provider": ["geoplanet:7.4.0", "geoplanet:7.4.1", "geoplanet:7.5.1", "geoplanet:7.5.2", "geoplanet:7.6.0", "geoplanet:7.8.1", "geoplanet:7.9.0", "geoplanet:7.10.0", "geoplanet:8.0.0", "woeplanet:8.0.0"], "meta:indexed": "2020-08-20T23:56:01.024157", "meta:updated": "2020-10-14T11:19:34.402533", "woe:hierarchy": {"continent": 24865672, "country": 23424977, "town": 0, "planet": 1, "county": 12589436, "suburb": 0, "state": 2347592, "region": 0, "localadmin": 0}, "woe:timezone_id": 56043648, "woe:hash": "dnr8uqbu0pjw", "woe:centroid": [-79.26532, 35.32589], "geom:latitude": 35.32589, "geom:longitude": -79.26532, "geom:hash": "dnr8uqbu0pjw", "woe:latitude": 35.32589, "geom:centroid": [-79.26532, 35.32589], "woe:longitude": -79.26532, "woe:repo": "woeplanet-poi-us", "geom:area": 0.0, "woe:scale": 19}}