{"type": "Feature", "id": 23596027, "properties": {"woe:id": 23596027, "woe:parent_id": 2467174, "woe:name": "Bramlett Elementary School", "woe:placetype": 20, "woe:placetype_name": "POI", "woe:lang": "ENG", "iso:country": "US", "meta:provider": ["geoplanet:7.3.1", "geoplanet:7.3.2", "geoplanet:7.4.0", "geoplanet:7.4.1", "geoplanet:7.5.1", "geoplanet:7.5.2", "geoplanet:7.6.0", "geoplanet:7.8.1", "geoplanet:7.9.0", "geoplanet:7.10.0", "geoplanet:8.0.0", "woeplanet:8.0.0"], "meta:indexed": "2020-08-20T20:18:43.387250", "woe:alias_ENG_V": ["Bramlett Elementary"], "meta:updated": "2020-08-22T02:57:40.405052", "woe:hierarchy": {"continent": 24865672, "country": 23424977, "town": 0, "planet": 1, "county": 12588919, "suburb": 0, "state": 2347583, "region": 0, "localadmin": 0}, "woe:timezone_id": 56043661, "woe:hash": "dn07e1nn8911", "woe:centroid": [-89.508339, 34.371849], "geom:latitude": 34.371849, "geom:longitude": -89.508339, "geom:hash": "dn07e1nn8911", "woe:latitude": 34.371849, "geom:centroid": [-89.508339, 34.371849], "woe:longitude": -89.508339, "woe:repo": "woeplanet-poi-us"}, "geometry": {"coordinates": [-89.508339, 34.371849], "type": "Point"}}