{"type": "Feature", "id": 23645316, "properties": {"woe:id": 23645316, "woe:parent_id": 28744937, "woe:name": "Mountain View Elementary School", "woe:placetype": 20, "woe:placetype_name": "POI", "woe:lang": "ENG", "iso:country": "US", "meta:provider": ["geoplanet:7.3.1", "geoplanet:7.3.2", "geoplanet:7.4.0", "geoplanet:7.4.1", "geoplanet:7.5.1", "geoplanet:7.5.2", "geoplanet:7.6.0", "geoplanet:7.8.1", "geoplanet:7.9.0", "geoplanet:7.10.0", "geoplanet:8.0.0", "woeplanet:8.0.0"], "meta:indexed": "2020-08-20T20:19:00.127584", "woe:alias_ENG_V": ["Mtn View Elementary School", "Mtn View Elementary", "Mountain View Elementary"], "meta:updated": "2020-08-22T02:57:47.428421", "woe:hierarchy": {"continent": 24865672, "country": 23424977, "town": 0, "planet": 1, "county": 12589792, "suburb": 0, "state": 2347597, "region": 0, "localadmin": 0}, "woe:timezone_id": 56043648, "woe:hash": "dppmrc0bz2bg", "woe:centroid": [-79.462769, 40.303478], "geom:latitude": 40.303478, "geom:longitude": -79.462769, "geom:hash": "dppmrc0bz2bg", "woe:latitude": 40.303478, "geom:centroid": [-79.462769, 40.303478], "woe:longitude": -79.462769, "woe:repo": "woeplanet-poi-us"}, "geometry": {"coordinates": [-79.462769, 40.303478], "type": "Point"}}