{"type": "Feature", "id": 23577127, "geometry": {"type": "Point", "coordinates": [-92.191971, 31.367479]}, "properties": {"woe:id": 23577127, "woe:parent_id": 2371064, "woe:name": "Buckeye Elementary School", "woe:placetype": 20, "woe:placetype_name": "POI", "woe:lang": "ENG", "iso:country": "US", "meta:provider": ["geoplanet:7.3.1", "geoplanet:7.3.2", "geoplanet:7.4.0", "geoplanet:7.4.1", "geoplanet:7.5.1", "geoplanet:7.5.2", "geoplanet:7.6.0", "geoplanet:7.8.1", "geoplanet:7.9.0", "geoplanet:7.10.0", "geoplanet:8.0.0", "woeplanet:8.0.0"], "meta:indexed": "2020-08-20T20:18:37.773397", "woe:alias_ENG_V": ["Buckeye Elementary"], "meta:updated": "2020-10-14T11:20:12.316297", "woe:hierarchy": {"continent": 24865672, "country": 23424977, "town": 0, "planet": 1, "county": 12588635, "suburb": 0, "state": 2347577, "region": 0, "localadmin": 0}, "woe:timezone_id": 56043661, "woe:hash": "9vw6qn7bg3gu", "woe:centroid": [-92.191971, 31.367479], "geom:latitude": 31.367479, "geom:longitude": -92.191971, "geom:hash": "9vw6qn7bg3gu", "woe:latitude": 31.367479, "geom:centroid": [-92.191971, 31.367479], "woe:longitude": -92.191971, "woe:repo": "woeplanet-poi-us", "geom:area": 0.0, "woe:scale": 19}}