{"type": "Feature", "id": 23626549, "geometry": {"type": "Point", "coordinates": [-100.228683, 46.266609]}, "properties": {"woe:id": 23626549, "woe:parent_id": 2439893, "woe:name": "Linton Elementary School", "woe:placetype": 20, "woe:placetype_name": "POI", "woe:lang": "ENG", "iso:country": "US", "meta:provider": ["geoplanet:7.3.1", "geoplanet:7.3.2", "geoplanet:7.4.0", "geoplanet:7.4.1", "geoplanet:7.5.1", "geoplanet:7.5.2", "geoplanet:7.6.0", "geoplanet:7.8.1", "geoplanet:7.9.0", "geoplanet:7.10.0", "geoplanet:8.0.0", "woeplanet:8.0.0"], "meta:indexed": "2020-08-20T20:18:53.028702", "woe:alias_ENG_V": ["Linton Elementary"], "meta:updated": "2020-10-14T11:19:51.981179", "woe:hierarchy": {"continent": 24865672, "country": 23424977, "town": 0, "planet": 1, "county": 12589488, "suburb": 0, "state": 2347593, "region": 0, "localadmin": 0}, "woe:timezone_id": 56043661, "woe:hash": "cb0xpnxdw3j0", "woe:centroid": [-100.228683, 46.266609], "geom:latitude": 46.266609, "geom:longitude": -100.228683, "geom:hash": "cb0xpnxdw3j0", "woe:latitude": 46.266609, "geom:centroid": [-100.228683, 46.266609], "woe:longitude": -100.228683, "woe:repo": "woeplanet-poi-us", "geom:area": 0.0, "woe:scale": 19}}