{"type": "Feature", "id": 23626783, "geometry": {"type": "Point", "coordinates": [-97.61953, 48.79388]}, "properties": {"woe:id": 23626783, "woe:parent_id": 2376401, "woe:name": "Cavalier High School", "woe:placetype": 20, "woe:placetype_name": "POI", "woe:lang": "ENG", "iso:country": "US", "meta:provider": ["geoplanet:7.3.2", "geoplanet:7.4.0", "geoplanet:7.4.1", "geoplanet:7.5.1", "geoplanet:7.5.2", "geoplanet:7.6.0", "geoplanet:7.8.1", "geoplanet:7.9.0", "geoplanet:7.10.0", "geoplanet:8.0.0", "woeplanet:8.0.0"], "meta:indexed": "2020-08-20T22:02:40.996630", "woe:alias_ENG_V": ["Cavalier Senior High School", "Cavalier High", "Cavalier Senior High", "Cavalier HS", "Cavalier Senior HS"], "meta:updated": "2020-10-14T11:19:36.826718", "woe:hierarchy": {"continent": 24865672, "country": 23424977, "town": 0, "planet": 1, "county": 12589507, "suburb": 0, "state": 2347593, "region": 0, "localadmin": 0}, "woe:timezone_id": 56043661, "woe:hash": "cbdtddesun6x", "woe:centroid": [-97.61953, 48.79388], "geom:latitude": 48.79388, "geom:longitude": -97.61953, "geom:hash": "cbdtddesun6x", "woe:latitude": 48.79388, "geom:centroid": [-97.61953, 48.79388], "woe:longitude": -97.61953, "woe:repo": "woeplanet-poi-us", "geom:area": 0.0, "woe:scale": 19}}