{"type": "Feature", "id": 23537181, "geometry": {"type": "Point", "coordinates": [-117.173218, 32.793591]}, "properties": {"woe:id": 23537181, "woe:parent_id": 2439636, "woe:name": "Linda Vista Elementary School", "woe:placetype": 20, "woe:placetype_name": "POI", "woe:lang": "ENG", "iso:country": "US", "meta:provider": ["geoplanet:7.3.2", "geoplanet:7.4.0", "geoplanet:7.4.1", "geoplanet:7.5.1", "geoplanet:7.5.2", "geoplanet:7.6.0", "geoplanet:7.8.1", "geoplanet:7.9.0", "geoplanet:7.10.0", "geoplanet:8.0.0", "woeplanet:8.0.0"], "meta:indexed": "2020-08-20T22:02:04.900674", "woe:alias_ENG_V": ["Linda Vista Elementary"], "meta:updated": "2020-10-14T11:20:11.957866", "woe:hierarchy": {"continent": 24865672, "country": 23424977, "town": 0, "planet": 1, "county": 12587706, "suburb": 0, "state": 2347563, "region": 0, "localadmin": 0}, "woe:timezone_id": 56043663, "woe:hash": "9mudt9vhd0kn", "woe:centroid": [-117.173218, 32.793591], "geom:latitude": 32.793591, "geom:longitude": -117.173218, "geom:hash": "9mudt9vhd0kn", "woe:latitude": 32.793591, "geom:centroid": [-117.173218, 32.793591], "woe:longitude": -117.173218, "woe:repo": "woeplanet-poi-us", "geom:area": 0.0, "woe:scale": 19}}