{"type": "Feature", "id": 23518832, "geometry": {"type": "Point", "coordinates": [-90.517502, 35.674198]}, "properties": {"woe:id": 23518832, "woe:parent_id": 2508291, "woe:name": "Trumann High School", "woe:placetype": 20, "woe:placetype_name": "POI", "woe:lang": "ENG", "iso:country": "US", "meta:provider": ["geoplanet:7.3.1", "geoplanet:7.3.2", "geoplanet:7.4.0", "geoplanet:7.4.1", "geoplanet:7.5.1", "geoplanet:7.5.2", "geoplanet:7.6.0", "geoplanet:7.8.1", "geoplanet:7.9.0", "geoplanet:7.10.0", "geoplanet:8.0.0", "woeplanet:8.0.0"], "meta:indexed": "2020-08-20T20:18:19.188669", "woe:alias_ENG_V": ["Trumann Senior High School", "Trumann High", "Trumann Senior High", "Trumann HS", "Trumann Senior HS", "Trumann Intermediate School"], "meta:updated": "2020-10-14T11:20:10.507900", "woe:hierarchy": {"continent": 24865672, "country": 23424977, "town": 0, "planet": 1, "county": 12587650, "suburb": 0, "state": 2347562, "region": 0, "localadmin": 0}, "woe:timezone_id": 56043661, "woe:hash": "9yrdunr1m2d8", "woe:centroid": [-90.517502, 35.674198], "geom:latitude": 35.674198, "geom:longitude": -90.517502, "geom:hash": "9yrdunr1m2d8", "woe:latitude": 35.674198, "geom:centroid": [-90.517502, 35.674198], "woe:longitude": -90.517502, "woe:repo": "woeplanet-poi-us", "geom:area": 0.0, "woe:scale": 19}}