{"type": "Feature", "id": 56054873, "geometry": {"type": "Point", "coordinates": [-112.050919, 43.516319]}, "properties": {"woe:id": 56054873, "woe:parent_id": 2426440, "woe:name": "Idaho State/univ of Idaho-Idaho Fls", "woe:placetype": 20, "woe:placetype_name": "POI", "woe:lang": "ENG", "iso:country": "US", "meta:provider": ["geoplanet:7.3.1", "geoplanet:7.3.2", "geoplanet:7.4.0", "geoplanet:7.4.1", "geoplanet:7.5.1", "geoplanet:7.5.2", "geoplanet:7.6.0", "geoplanet:7.8.1", "geoplanet:7.9.0", "geoplanet:7.10.0", "geoplanet:8.0.0", "woeplanet:8.0.0"], "meta:indexed": "2020-08-20T20:19:18.191789", "meta:updated": "2020-10-14T11:19:56.007257", "woe:hierarchy": {"continent": 24865672, "country": 23424977, "town": 0, "planet": 1, "county": 12588043, "suburb": 0, "state": 2347571, "region": 0, "localadmin": 0}, "woe:timezone_id": 56043662, "woe:hash": "9x8rd1zhbmg4", "woe:centroid": [-112.050919, 43.516319], "geom:latitude": 43.516319, "geom:longitude": -112.050919, "geom:hash": "9x8rd1zhbmg4", "woe:latitude": 43.516319, "geom:centroid": [-112.050919, 43.516319], "woe:longitude": -112.050919, "woe:repo": "woeplanet-poi-us", "geom:area": 0.0, "woe:scale": 19}}