{"type": "Feature", "id": 23646705, "geometry": {"type": "Point", "coordinates": [-79.973457, 32.734989]}, "properties": {"woe:id": 23646705, "woe:parent_id": 2378319, "woe:name": "Ft Johnson Middle School", "woe:placetype": 20, "woe:placetype_name": "POI", "woe:lang": "ENG", "iso:country": "US", "meta:provider": ["geoplanet:7.3.1", "geoplanet:7.3.2", "geoplanet:7.4.0", "geoplanet:7.4.1", "geoplanet:7.5.1", "geoplanet:7.5.2", "geoplanet:7.6.0", "geoplanet:7.8.1", "geoplanet:7.9.0", "geoplanet:7.10.0", "geoplanet:8.0.0", "woeplanet:8.0.0"], "meta:indexed": "2020-08-20T20:19:00.580095", "meta:updated": "2020-10-14T11:19:49.758363", "woe:alias_ENG_V": ["Fort Johnson Middle School"], "woe:hierarchy": {"continent": 24865672, "country": 23424977, "town": 0, "planet": 1, "county": 12589809, "suburb": 0, "state": 2347599, "region": 0, "localadmin": 0}, "woe:timezone_id": 56043648, "woe:hash": "djz4hpjp5khr", "woe:centroid": [-79.973457, 32.734989], "geom:latitude": 32.734989, "geom:longitude": -79.973457, "geom:hash": "djz4hpjp5khr", "woe:latitude": 32.734989, "geom:centroid": [-79.973457, 32.734989], "woe:longitude": -79.973457, "woe:repo": "woeplanet-poi-us", "geom:area": 0.0, "woe:scale": 19}}