{"type": "Feature", "id": 23650242, "properties": {"woe:id": 23650242, "woe:parent_id": 2425001, "woe:name": "Apison S D A Elementary School", "woe:placetype": 20, "woe:placetype_name": "POI", "woe:lang": "ENG", "iso:country": "US", "meta:provider": ["geoplanet:7.3.1", "geoplanet:7.3.2", "geoplanet:7.4.0", "geoplanet:7.4.1", "geoplanet:7.5.1", "geoplanet:7.5.2", "geoplanet:7.6.0", "geoplanet:7.8.1", "geoplanet:7.9.0", "geoplanet:7.10.0", "geoplanet:8.0.0", "woeplanet:8.0.0"], "meta:indexed": "2020-08-20T20:19:01.776403", "woe:alias_ENG_V": ["Apison S D A Elementary"], "meta:updated": "2020-08-22T02:57:48.238858", "woe:hierarchy": {"continent": 24865672, "country": 23424977, "town": 0, "planet": 1, "county": 12589944, "suburb": 0, "state": 2347601, "region": 0, "localadmin": 0}, "woe:timezone_id": 56043648, "woe:hash": "dn5x1xwsw03s", "woe:centroid": [-85.003021, 35.022442], "geom:latitude": 35.022442, "geom:longitude": -85.003021, "geom:hash": "dn5x1xwsw03s", "woe:latitude": 35.022442, "geom:centroid": [-85.003021, 35.022442], "woe:longitude": -85.003021, "woe:repo": "woeplanet-poi-us"}, "geometry": {"coordinates": [-85.003021, 35.022442], "type": "Point"}}