{"type": "Feature", "id": 56052776, "properties": {"woe:id": 56052776, "woe:parent_id": 2430083, "woe:name": "Devry University-Seattle", "woe:placetype": 20, "woe:placetype_name": "POI", "woe:lang": "ENG", "iso:country": "US", "meta:provider": ["geoplanet:7.3.1", "geoplanet:7.3.2", "geoplanet:7.4.0", "geoplanet:7.4.1", "geoplanet:7.5.1", "geoplanet:7.5.2", "geoplanet:7.6.0", "geoplanet:7.8.1", "geoplanet:7.9.0", "geoplanet:7.10.0", "geoplanet:8.0.0", "woeplanet:8.0.0"], "meta:indexed": "2020-08-20T20:19:16.553122", "meta:updated": "2020-08-22T02:58:20.556394", "woe:hierarchy": {"continent": 24865672, "country": 23424977, "town": 0, "planet": 1, "county": 12590456, "suburb": 0, "state": 2347606, "region": 0, "localadmin": 0}, "woe:timezone_id": 56043663, "woe:hash": "c23j132ryjpn", "woe:centroid": [-122.288208, 47.293381], "geom:latitude": 47.293381, "geom:longitude": -122.288208, "geom:hash": "c23j132ryjpn", "woe:latitude": 47.293381, "geom:centroid": [-122.288208, 47.293381], "woe:longitude": -122.288208, "woe:repo": "woeplanet-poi-us"}, "geometry": {"coordinates": [-122.288208, 47.293381], "type": "Point"}}