{"type": "Feature", "id": 23543986, "geometry": {"type": "Point", "coordinates": [-72.914139, 41.324032]}, "properties": {"woe:id": 23543986, "woe:parent_id": 55860487, "woe:name": "Worthington Hooker School", "woe:placetype": 20, "woe:placetype_name": "POI", "woe:lang": "ENG", "iso:country": "US", "meta:provider": ["geoplanet:7.3.1", "geoplanet:7.3.2", "geoplanet:7.4.0", "geoplanet:7.4.1", "geoplanet:7.5.1", "geoplanet:7.5.2", "geoplanet:7.6.0", "geoplanet:7.8.1", "geoplanet:7.9.0", "geoplanet:7.10.0", "geoplanet:8.0.0", "woeplanet:8.0.0"], "meta:indexed": "2020-08-20T20:18:25.428676", "meta:updated": "2020-10-14T11:20:07.946630", "woe:alias_ENG_V": ["Worthington Hooker Elem School"], "woe:hierarchy": {"continent": 24865672, "country": 23424977, "town": 0, "planet": 1, "county": 12587795, "suburb": 0, "state": 2347565, "region": 0, "localadmin": 0}, "woe:timezone_id": 56043648, "woe:hash": "drk5hfc9cmvk", "woe:centroid": [-72.914139, 41.324032], "geom:latitude": 41.324032, "geom:longitude": -72.914139, "geom:hash": "drk5hfc9cmvk", "woe:latitude": 41.324032, "geom:centroid": [-72.914139, 41.324032], "woe:longitude": -72.914139, "woe:repo": "woeplanet-poi-us", "geom:area": 0.0, "woe:scale": 19}}