{"type": "Feature", "id": 23685395, "properties": {"woe:id": 23685395, "woe:parent_id": 2504841, "woe:name": "Northgate Mall", "woe:placetype": 20, "woe:placetype_name": "POI", "woe:lang": "ENG", "iso:country": "US", "meta:provider": ["geoplanet:7.3.1", "geoplanet:7.3.2", "geoplanet:7.4.0", "geoplanet:7.4.1", "geoplanet:7.5.1", "geoplanet:7.5.2", "geoplanet:7.6.0", "geoplanet:7.8.1", "geoplanet:7.9.0", "geoplanet:7.10.0", "geoplanet:8.0.0", "woeplanet:8.0.0"], "meta:indexed": "2020-08-20T20:19:13.664542", "meta:updated": "2020-08-22T02:58:19.124577", "woe:hierarchy": {"continent": 24865672, "country": 23424977, "town": 0, "planet": 1, "county": 12587690, "suburb": 0, "state": 2347563, "region": 0, "localadmin": 0}, "woe:timezone_id": 56043663, "woe:hash": "9qbb5qwhx8kg", "woe:centroid": [-122.543922, 38.00523], "geom:latitude": 38.00523, "geom:longitude": -122.543922, "geom:hash": "9qbb5qwhx8kg", "woe:latitude": 38.00523, "geom:centroid": [-122.543922, 38.00523], "woe:longitude": -122.543922, "woe:repo": "woeplanet-poi-us"}, "geometry": {"coordinates": [-122.543922, 38.00523], "type": "Point"}}