{"type": "Feature", "id": 23563980, "geometry": {"type": "Point", "coordinates": [-90.494972, 41.485802]}, "properties": {"woe:id": 23563980, "woe:parent_id": 2452776, "woe:name": "Jefferson Early Childhood Center", "woe:placetype": 20, "woe:placetype_name": "POI", "woe:lang": "ENG", "iso:country": "US", "meta:provider": ["geoplanet:7.3.1", "geoplanet:7.3.2", "geoplanet:7.4.0", "geoplanet:7.4.1", "geoplanet:7.5.1", "geoplanet:7.5.2", "geoplanet:7.6.0", "geoplanet:7.8.1", "geoplanet:7.9.0", "geoplanet:7.10.0", "geoplanet:8.0.0", "woeplanet:8.0.0"], "meta:indexed": "2020-08-20T20:18:33.021152", "meta:updated": "2020-10-14T11:20:15.698727", "woe:hierarchy": {"continent": 24865672, "country": 23424977, "town": 0, "planet": 1, "county": 12588158, "suburb": 0, "state": 2347572, "region": 0, "localadmin": 0}, "woe:timezone_id": 56043661, "woe:hash": "9zrsh8r86640", "woe:centroid": [-90.494972, 41.485802], "geom:latitude": 41.485802, "geom:longitude": -90.494972, "geom:hash": "9zrsh8r86640", "woe:latitude": 41.485802, "geom:centroid": [-90.494972, 41.485802], "woe:longitude": -90.494972, "woe:repo": "woeplanet-poi-us", "geom:area": 0.0, "woe:scale": 19}}