{"type": "Feature", "id": 24866903, "properties": {"woe:id": 24866903, "woe:parent_id": 2355371, "woe:name": "Appalachian State University", "woe:placetype": 20, "woe:placetype_name": "POI", "woe:lang": "ENG", "iso:country": "US", "meta:provider": ["geoplanet:7.3.1", "geoplanet:7.3.2", "geoplanet:7.4.0", "geoplanet:7.4.1", "geoplanet:7.5.1", "geoplanet:7.5.2", "geoplanet:7.6.0", "geoplanet:7.8.1", "geoplanet:7.9.0", "geoplanet:7.10.0", "geoplanet:8.0.0", "woeplanet:8.0.0"], "meta:indexed": "2020-08-20T20:19:15.389324", "meta:updated": "2020-08-22T02:58:19.930278", "woe:hierarchy": {"continent": 24865672, "country": 23424977, "town": 0, "planet": 1, "county": 12588692, "suburb": 0, "state": 2347579, "region": 0, "localadmin": 0}, "woe:timezone_id": 56043648, "woe:hash": "dqc7qpznr695", "woe:centroid": [-76.71859, 38.583698], "geom:latitude": 38.583698, "geom:longitude": -76.71859, "geom:hash": "dqc7qpznr695", "woe:latitude": 38.583698, "geom:centroid": [-76.71859, 38.583698], "woe:longitude": -76.71859, "woe:repo": "woeplanet-poi-us"}, "geometry": {"coordinates": [-76.71859, 38.583698], "type": "Point"}}