{"type": "Feature", "id": 23620218, "properties": {"woe:id": 23620218, "woe:parent_id": 2358763, "woe:name": "Wood Road Intermediate School", "woe:placetype": 20, "woe:placetype_name": "POI", "woe:lang": "ENG", "iso:country": "US", "meta:provider": ["geoplanet:7.3.1", "geoplanet:7.3.2", "geoplanet:7.4.0", "geoplanet:7.4.1", "geoplanet:7.5.1", "geoplanet:7.5.2", "geoplanet:7.6.0", "geoplanet:7.8.1", "geoplanet:7.9.0", "geoplanet:7.10.0", "geoplanet:8.0.0", "woeplanet:8.0.0"], "meta:indexed": "2020-08-20T20:18:51.522046", "meta:updated": "2020-08-22T02:57:43.710332", "woe:hierarchy": {"continent": 24865672, "country": 23424977, "town": 0, "planet": 1, "county": 12589356, "suburb": 0, "state": 2347591, "region": 0, "localadmin": 0}, "woe:timezone_id": 56043648, "woe:hash": "drekx5feygb2", "woe:centroid": [-73.868347, 42.999779], "geom:latitude": 42.999779, "geom:longitude": -73.868347, "geom:hash": "drekx5feygb2", "woe:latitude": 42.999779, "geom:centroid": [-73.868347, 42.999779], "woe:longitude": -73.868347, "woe:repo": "woeplanet-poi-us"}, "geometry": {"coordinates": [-73.868347, 42.999779], "type": "Point"}}