{"type": "Feature", "id": 23667794, "geometry": {"type": "Point", "coordinates": [-76.033867, 36.752602]}, "properties": {"woe:id": 23667794, "woe:parent_id": 2512636, "woe:name": "Princess Anne Elementary School", "woe:placetype": 20, "woe:placetype_name": "POI", "woe:lang": "ENG", "iso:country": "US", "meta:provider": ["geoplanet:7.3.1", "geoplanet:7.3.2", "geoplanet:7.4.0", "geoplanet:7.4.1", "geoplanet:7.5.1", "geoplanet:7.5.2", "geoplanet:7.6.0", "geoplanet:7.8.1", "geoplanet:7.9.0", "geoplanet:7.10.0", "geoplanet:8.0.0", "woeplanet:8.0.0"], "meta:indexed": "2020-08-20T20:19:08.927556", "woe:alias_ENG_V": ["Princess Anne Elementary"], "meta:updated": "2020-10-14T11:19:29.785650", "woe:hierarchy": {"continent": 24865672, "country": 23424977, "town": 0, "planet": 1, "county": 12590430, "suburb": 0, "state": 2347605, "region": 0, "localadmin": 0}, "woe:timezone_id": 56043648, "woe:hash": "dq9cjf9g6mxd", "woe:centroid": [-76.033867, 36.752602], "geom:latitude": 36.752602, "geom:longitude": -76.033867, "geom:hash": "dq9cjf9g6mxd", "woe:latitude": 36.752602, "geom:centroid": [-76.033867, 36.752602], "woe:longitude": -76.033867, "woe:repo": "woeplanet-poi-us", "geom:area": 0.0, "woe:scale": 19}}