{"type": "Feature", "id": 23619617, "geometry": {"type": "Point", "coordinates": [-73.898148, 40.707611]}, "properties": {"woe:id": 23619617, "woe:parent_id": 2411081, "woe:name": "Fresh Pond Station", "woe:placetype": 20, "woe:placetype_name": "POI", "woe:lang": "ENG", "iso:country": "US", "meta:provider": ["geoplanet:7.3.1", "geoplanet:7.3.2", "geoplanet:7.4.0", "geoplanet:7.4.1", "geoplanet:7.5.1", "geoplanet:7.5.2", "geoplanet:7.6.0", "geoplanet:7.8.1", "geoplanet:7.9.0", "geoplanet:7.10.0", "geoplanet:8.0.0", "woeplanet:8.0.0"], "meta:indexed": "2020-08-20T20:18:51.297023", "meta:updated": "2020-10-14T11:19:39.466228", "woe:hierarchy": {"continent": 24865672, "country": 23424977, "town": 0, "planet": 1, "county": 12589352, "suburb": 0, "state": 2347591, "region": 0, "localadmin": 0}, "woe:timezone_id": 56043648, "woe:hash": "dr5rw6t502en", "woe:centroid": [-73.898148, 40.707611], "geom:latitude": 40.707611, "geom:longitude": -73.898148, "geom:hash": "dr5rw6t502en", "woe:latitude": 40.707611, "geom:centroid": [-73.898148, 40.707611], "woe:longitude": -73.898148, "woe:repo": "woeplanet-poi-us", "geom:area": 0.0, "woe:scale": 19}}