{"type": "Feature", "id": 23538791, "properties": {"woe:id": 23538791, "woe:parent_id": 55972397, "woe:name": "Brighton Heritage Academy", "woe:placetype": 20, "woe:placetype_name": "POI", "woe:lang": "ENG", "iso:country": "US", "meta:provider": ["geoplanet:7.3.2", "geoplanet:7.4.0", "geoplanet:7.4.1", "geoplanet:7.5.1", "geoplanet:7.5.2", "geoplanet:7.6.0", "geoplanet:7.8.1", "geoplanet:7.9.0", "geoplanet:7.10.0", "geoplanet:8.0.0", "woeplanet:8.0.0"], "meta:indexed": "2020-08-20T22:02:05.542701", "meta:updated": "2020-08-22T02:57:30.328199", "woe:alias_ENG_V": ["Brighton Heritage Acadeny"], "woe:hierarchy": {"continent": 24865672, "country": 23424977, "town": 0, "planet": 1, "county": 12587728, "suburb": 0, "state": 2347564, "region": 0, "localadmin": 0}, "woe:timezone_id": 56043665, "woe:hash": "9xj7qzq59nf4", "woe:centroid": [-104.812271, 39.986752], "geom:latitude": 39.986752, "geom:longitude": -104.812271, "geom:hash": "9xj7qzq59nf4", "woe:latitude": 39.986752, "geom:centroid": [-104.812271, 39.986752], "woe:longitude": -104.812271, "woe:repo": "woeplanet-poi-us"}, "geometry": {"coordinates": [-104.812271, 39.986752], "type": "Point"}}