{"type": "Feature", "id": 23650999, "geometry": {"type": "Point", "coordinates": [-87.10331, 35.593819]}, "properties": {"woe:id": 23650999, "woe:parent_id": 2383551, "woe:name": "J E Woodard Elementary School", "woe:placetype": 20, "woe:placetype_name": "POI", "woe:lang": "ENG", "iso:country": "US", "meta:provider": ["geoplanet:7.3.2", "geoplanet:7.4.0", "geoplanet:7.4.1", "geoplanet:7.5.1", "geoplanet:7.5.2", "geoplanet:7.6.0", "geoplanet:7.8.1", "geoplanet:7.9.0", "geoplanet:7.10.0", "geoplanet:8.0.0", "woeplanet:8.0.0"], "meta:indexed": "2020-08-20T22:02:51.244030", "woe:alias_ENG_V": ["J E Woodard Elementary"], "meta:updated": "2020-10-14T11:19:44.378700", "woe:hierarchy": {"continent": 24865672, "country": 23424977, "town": 0, "planet": 1, "county": 12589969, "suburb": 0, "state": 2347601, "region": 0, "localadmin": 0}, "woe:timezone_id": 56043661, "woe:hash": "dn643ztm1bb8", "woe:centroid": [-87.10331, 35.593819], "geom:latitude": 35.593819, "geom:longitude": -87.10331, "geom:hash": "dn643ztm1bb8", "woe:latitude": 35.593819, "geom:centroid": [-87.10331, 35.593819], "woe:longitude": -87.10331, "woe:repo": "woeplanet-poi-us", "geom:area": 0.0, "woe:scale": 19}}