{"type": "Feature", "id": 23673477, "geometry": {"type": "Point", "coordinates": [-89.540863, 42.858749]}, "properties": {"woe:id": 23673477, "woe:parent_id": 2361989, "woe:name": "Belleville Intermediate School", "woe:placetype": 20, "woe:placetype_name": "POI", "woe:lang": "ENG", "iso:country": "US", "meta:provider": ["geoplanet:7.3.1", "geoplanet:7.3.2", "geoplanet:7.4.0", "geoplanet:7.4.1", "geoplanet:7.5.1", "geoplanet:7.5.2", "geoplanet:7.6.0", "geoplanet:7.8.1", "geoplanet:7.9.0", "geoplanet:7.10.0", "geoplanet:8.0.0", "woeplanet:8.0.0"], "meta:indexed": "2020-08-20T20:19:10.533589", "meta:updated": "2020-10-14T11:19:50.215068", "woe:hierarchy": {"continent": 24865672, "country": 23424977, "town": 0, "planet": 1, "county": 12590546, "suburb": 0, "state": 2347608, "region": 0, "localadmin": 0}, "woe:timezone_id": 56043661, "woe:hash": "dp87f6nq69vk", "woe:centroid": [-89.540863, 42.858749], "geom:latitude": 42.858749, "geom:longitude": -89.540863, "geom:hash": "dp87f6nq69vk", "woe:latitude": 42.858749, "geom:centroid": [-89.540863, 42.858749], "woe:longitude": -89.540863, "woe:repo": "woeplanet-poi-us", "geom:area": 0.0, "woe:scale": 19}}