{"type": "Feature", "id": 23605621, "geometry": {"type": "Point", "coordinates": [-72.304512, 42.93803]}, "properties": {"woe:id": 23605621, "woe:parent_id": 55991484, "woe:name": "Symonds Elementary School", "woe:placetype": 20, "woe:placetype_name": "POI", "woe:lang": "ENG", "iso:country": "US", "meta:provider": ["geoplanet:7.3.1", "geoplanet:7.3.2", "geoplanet:7.4.0", "geoplanet:7.4.1", "geoplanet:7.5.1", "geoplanet:7.5.2", "geoplanet:7.6.0", "geoplanet:7.8.1", "geoplanet:7.9.0", "geoplanet:7.10.0", "geoplanet:8.0.0", "woeplanet:8.0.0"], "meta:indexed": "2020-08-20T20:18:46.257857", "woe:alias_ENG_V": ["Symonds Elementary"], "meta:updated": "2020-10-14T11:19:43.672543", "woe:hierarchy": {"continent": 24865672, "country": 23424977, "town": 0, "planet": 1, "county": 12589250, "suburb": 0, "state": 2347588, "region": 0, "localadmin": 0}, "woe:timezone_id": 56043648, "woe:hash": "drss68tknubj", "woe:centroid": [-72.304512, 42.93803], "geom:latitude": 42.93803, "geom:longitude": -72.304512, "geom:hash": "drss68tknubj", "woe:latitude": 42.93803, "geom:centroid": [-72.304512, 42.93803], "woe:longitude": -72.304512, "woe:repo": "woeplanet-poi-us", "geom:area": 0.0, "woe:scale": 19}}