{"type": "Feature", "id": 23604306, "geometry": {"type": "Point", "coordinates": [-114.834129, 35.973389]}, "properties": {"woe:id": 23604306, "woe:parent_id": 2367248, "woe:name": "Boulder City High School", "woe:placetype": 20, "woe:placetype_name": "POI", "woe:lang": "ENG", "iso:country": "US", "meta:provider": ["geoplanet:7.3.1", "geoplanet:7.3.2", "geoplanet:7.4.0", "geoplanet:7.4.1", "geoplanet:7.5.1", "geoplanet:7.5.2", "geoplanet:7.6.0", "geoplanet:7.8.1", "geoplanet:7.9.0", "geoplanet:7.10.0", "geoplanet:8.0.0", "woeplanet:8.0.0"], "meta:indexed": "2020-08-20T20:18:46.049098", "woe:alias_ENG_V": ["Boulder City Senior High School", "Boulder City High", "Boulder City Senior High", "Boulder City HS", "Boulder City Senior HS"], "meta:updated": "2020-10-14T11:19:33.049478", "woe:hierarchy": {"continent": 24865672, "country": 23424977, "town": 0, "planet": 1, "county": 12589233, "suburb": 0, "state": 2347587, "region": 0, "localadmin": 0}, "woe:timezone_id": 56043663, "woe:hash": "9qqkduu24vg2", "woe:centroid": [-114.834129, 35.973389], "geom:latitude": 35.973389, "geom:longitude": -114.834129, "geom:hash": "9qqkduu24vg2", "woe:latitude": 35.973389, "geom:centroid": [-114.834129, 35.973389], "woe:longitude": -114.834129, "woe:repo": "woeplanet-poi-us", "geom:area": 0.0, "woe:scale": 19}}