{"type": "Feature", "id": 23590312, "geometry": {"type": "Point", "coordinates": [-84.015152, 43.458988]}, "properties": {"woe:id": 23590312, "woe:parent_id": 22664128, "woe:name": "Heritage High School", "woe:placetype": 20, "woe:placetype_name": "POI", "woe:lang": "ENG", "iso:country": "US", "meta:provider": ["geoplanet:7.3.1", "geoplanet:7.3.2", "geoplanet:7.4.0", "geoplanet:7.4.1", "geoplanet:7.5.1", "geoplanet:7.5.2", "geoplanet:7.6.0", "geoplanet:7.8.1", "geoplanet:7.9.0", "geoplanet:7.10.0", "geoplanet:8.0.0", "woeplanet:8.0.0"], "meta:indexed": "2020-08-20T20:18:41.322570", "woe:alias_ENG_V": ["Heritage Senior High School", "Heritage High", "Heritage Senior High", "Heritage HS", "Heritage Senior HS"], "meta:updated": "2020-10-14T11:20:18.626591", "woe:hierarchy": {"continent": 24865672, "country": 23424977, "town": 0, "planet": 1, "county": 12588786, "suburb": 0, "state": 2347581, "region": 0, "localadmin": 0}, "woe:timezone_id": 56043658, "woe:hash": "dpsr0pqncnd1", "woe:centroid": [-84.015152, 43.458988], "geom:latitude": 43.458988, "geom:longitude": -84.015152, "geom:hash": "dpsr0pqncnd1", "woe:latitude": 43.458988, "geom:centroid": [-84.015152, 43.458988], "woe:longitude": -84.015152, "woe:repo": "woeplanet-poi-us", "geom:area": 0.0, "woe:scale": 19}}