{"type": "Feature", "id": 23537583, "geometry": {"type": "Point", "coordinates": [-117.182678, 32.80669]}, "properties": {"woe:id": 23537583, "woe:parent_id": 29388989, "woe:name": "Wee Care Preschool", "woe:placetype": 20, "woe:placetype_name": "POI", "woe:lang": "ENG", "iso:country": "US", "meta:provider": ["geoplanet:7.3.2", "geoplanet:7.4.0", "geoplanet:7.4.1", "geoplanet:7.5.1", "geoplanet:7.5.2", "geoplanet:7.6.0", "geoplanet:7.8.1", "geoplanet:7.9.0", "geoplanet:7.10.0", "geoplanet:8.0.0", "woeplanet:8.0.0"], "meta:indexed": "2020-08-20T22:02:05.115510", "meta:updated": "2020-10-14T11:20:11.776696", "woe:hierarchy": {"continent": 24865672, "country": 23424977, "town": 0, "planet": 1, "county": 12587706, "suburb": 0, "state": 2347563, "region": 0, "localadmin": 0}, "woe:timezone_id": 56043663, "woe:hash": "9mudtkq0vdq0", "woe:centroid": [-117.182678, 32.80669], "geom:latitude": 32.80669, "geom:longitude": -117.182678, "geom:hash": "9mudtkq0vdq0", "woe:latitude": 32.80669, "geom:centroid": [-117.182678, 32.80669], "woe:longitude": -117.182678, "woe:repo": "woeplanet-poi-us", "geom:area": 0.0, "woe:scale": 19}}