{"type": "Feature", "id": 23574857, "properties": {"woe:id": 23574857, "woe:parent_id": 2407840, "woe:name": "Saint Charles Middle School", "woe:placetype": 20, "woe:placetype_name": "POI", "woe:lang": "ENG", "iso:country": "US", "meta:provider": ["geoplanet:7.3.2", "geoplanet:7.4.0", "geoplanet:7.4.1", "geoplanet:7.5.1", "geoplanet:7.5.2", "geoplanet:7.6.0", "geoplanet:7.8.1", "geoplanet:7.9.0", "geoplanet:7.10.0", "geoplanet:8.0.0", "woeplanet:8.0.0"], "meta:indexed": "2020-08-20T22:02:20.689501", "meta:updated": "2020-08-22T02:57:37.016640", "woe:hierarchy": {"continent": 24865672, "country": 23424977, "town": 0, "planet": 1, "county": 12588550, "suburb": 0, "state": 2347576, "region": 0, "localadmin": 0}, "woe:timezone_id": 56043647, "woe:hash": "dnemccvqnkux", "woe:centroid": [-85.345299, 37.583912], "geom:latitude": 37.583912, "geom:longitude": -85.345299, "geom:hash": "dnemccvqnkux", "woe:latitude": 37.583912, "geom:centroid": [-85.345299, 37.583912], "woe:longitude": -85.345299, "woe:repo": "woeplanet-poi-us"}, "geometry": {"coordinates": [-85.345299, 37.583912], "type": "Point"}}