{"type": "Feature", "id": 55862640, "geometry": {"type": "Point", "coordinates": [-117.918892, 33.813061]}, "properties": {"woe:id": 55862640, "woe:parent_id": 55806745, "woe:name": "Disneyland Resort", "woe:placetype": 20, "woe:placetype_name": "POI", "woe:lang": "ENG", "iso:country": "US", "meta:provider": ["geoplanet:7.3.1", "geoplanet:7.3.2", "geoplanet:7.4.0", "geoplanet:7.4.1", "geoplanet:7.5.1", "geoplanet:7.5.2", "geoplanet:7.6.0", "geoplanet:7.8.1", "geoplanet:7.9.0", "geoplanet:7.10.0", "geoplanet:8.0.0", "woeplanet:8.0.0"], "meta:indexed": "2020-08-20T20:18:22.535326", "woe:alias_ENG_V": ["Disney Land", "Disneylandresort", "Disney Land Resort", "Disneyland"], "meta:updated": "2020-10-14T11:19:25.702074", "woe:hierarchy": {"continent": 24865672, "country": 23424977, "town": 0, "planet": 1, "county": 12587699, "suburb": 0, "state": 2347563, "region": 0, "localadmin": 0}, "woe:timezone_id": 56043663, "woe:hash": "9qh0keqp6emm", "woe:centroid": [-117.918892, 33.813061], "geom:latitude": 33.813061, "geom:longitude": -117.918892, "geom:hash": "9qh0keqp6emm", "woe:latitude": 33.813061, "geom:centroid": [-117.918892, 33.813061], "woe:longitude": -117.918892, "woe:repo": "woeplanet-poi-us", "geom:area": 0.0, "woe:scale": 19}}