{"type": "Feature", "id": 23680488, "properties": {"woe:id": 23680488, "woe:parent_id": 2509082, "woe:name": "Twin Buttes Station", "woe:placetype": 20, "woe:placetype_name": "POI", "woe:lang": "ENG", "iso:country": "US", "meta:provider": ["geoplanet:7.3.1", "geoplanet:7.3.2", "geoplanet:7.4.0", "geoplanet:7.4.1", "geoplanet:7.5.1", "geoplanet:7.5.2", "geoplanet:7.6.0", "geoplanet:7.8.1", "geoplanet:7.9.0", "geoplanet:7.10.0", "geoplanet:8.0.0", "woeplanet:8.0.0"], "meta:indexed": "2020-08-20T20:19:18.487741", "meta:updated": "2020-08-22T02:58:21.668831", "woe:hierarchy": {"continent": 24865672, "country": 23424977, "town": 0, "planet": 1, "county": 12587723, "suburb": 0, "state": 2347563, "region": 0, "localadmin": 0}, "woe:timezone_id": 56043663, "woe:hash": "9q7prqk6q94q", "woe:centroid": [-119.206528, 36.465389], "geom:latitude": 36.465389, "geom:longitude": -119.206528, "geom:hash": "9q7prqk6q94q", "woe:latitude": 36.465389, "geom:centroid": [-119.206528, 36.465389], "woe:longitude": -119.206528, "woe:repo": "woeplanet-poi-us"}, "geometry": {"coordinates": [-119.206528, 36.465389], "type": "Point"}}