{"type": "Feature", "id": 23556956, "geometry": {"type": "Point", "coordinates": [-90.21701, 39.94643]}, "properties": {"woe:id": 23556956, "woe:parent_id": 2512618, "woe:name": "Virginia Senior High School", "woe:placetype": 20, "woe:placetype_name": "POI", "woe:lang": "ENG", "iso:country": "US", "meta:provider": ["geoplanet:7.3.1", "geoplanet:7.3.2", "geoplanet:7.4.0", "geoplanet:7.4.1", "geoplanet:7.5.1", "geoplanet:7.5.2", "geoplanet:7.6.0", "geoplanet:7.8.1", "geoplanet:7.9.0", "geoplanet:7.10.0", "geoplanet:8.0.0", "woeplanet:8.0.0"], "meta:indexed": "2020-08-20T20:18:30.510117", "woe:alias_ENG_V": ["Virginia Senior High", "Virginia High School", "Virginia High", "Virginia Senior HS", "Virginia HS"], "meta:updated": "2020-10-14T11:20:10.949281", "woe:hierarchy": {"continent": 24865672, "country": 23424977, "town": 0, "planet": 1, "county": 12588086, "suburb": 0, "state": 2347572, "region": 0, "localadmin": 0}, "woe:timezone_id": 56043661, "woe:hash": "9zpg701bz638", "woe:centroid": [-90.21701, 39.94643], "geom:latitude": 39.94643, "geom:longitude": -90.21701, "geom:hash": "9zpg701bz638", "woe:latitude": 39.94643, "geom:centroid": [-90.21701, 39.94643], "woe:longitude": -90.21701, "woe:repo": "woeplanet-poi-us", "geom:area": 0.0, "woe:scale": 19}}