{"type": "Feature", "id": 23535273, "geometry": {"type": "Point", "coordinates": [-117.223381, 33.801182]}, "properties": {"woe:id": 23535273, "woe:parent_id": 2470680, "woe:name": "Perris High School", "woe:placetype": 20, "woe:placetype_name": "POI", "woe:lang": "ENG", "iso:country": "US", "meta:provider": ["geoplanet:7.3.2", "geoplanet:7.4.0", "geoplanet:7.4.1", "geoplanet:7.5.1", "geoplanet:7.5.2", "geoplanet:7.6.0", "geoplanet:7.8.1", "geoplanet:7.9.0", "geoplanet:7.10.0", "geoplanet:8.0.0", "woeplanet:8.0.0"], "meta:indexed": "2020-08-20T22:02:04.165724", "woe:alias_ENG_V": ["Perris Senior High School", "Perris High", "Perris Senior High", "Perris HS", "Perris Senior HS"], "meta:updated": "2020-10-14T11:20:17.508928", "woe:hierarchy": {"continent": 24865672, "country": 23424977, "town": 0, "planet": 1, "county": 12587702, "suburb": 0, "state": 2347563, "region": 0, "localadmin": 0}, "woe:timezone_id": 56043663, "woe:hash": "9qh8k92d1jpb", "woe:centroid": [-117.223381, 33.801182], "geom:latitude": 33.801182, "geom:longitude": -117.223381, "geom:hash": "9qh8k92d1jpb", "woe:latitude": 33.801182, "geom:centroid": [-117.223381, 33.801182], "woe:longitude": -117.223381, "woe:repo": "woeplanet-poi-us", "geom:area": 0.0, "woe:scale": 19}}