{"type": "Feature", "id": 23555367, "geometry": {"type": "Point", "coordinates": [-112.177551, 42.575241]}, "properties": {"woe:id": 23555367, "woe:parent_id": 2355806, "woe:name": "Marsh Valley High School", "woe:placetype": 20, "woe:placetype_name": "POI", "woe:lang": "ENG", "iso:country": "US", "meta:provider": ["geoplanet:7.3.1", "geoplanet:7.3.2", "geoplanet:7.4.0", "geoplanet:7.4.1", "geoplanet:7.5.1", "geoplanet:7.5.2", "geoplanet:7.6.0", "geoplanet:7.8.1", "geoplanet:7.9.0", "geoplanet:7.10.0", "geoplanet:8.0.0", "woeplanet:8.0.0"], "meta:indexed": "2020-08-20T20:18:30.159873", "woe:alias_ENG_V": ["Marsh Valley Senior High School", "Marsh Valley High", "Marsh Valley Senior High", "Marsh Valley HS", "Marsh Valley Senior HS"], "meta:updated": "2020-10-14T11:20:11.161567", "woe:hierarchy": {"continent": 24865672, "country": 23424977, "town": 0, "planet": 1, "county": 12588036, "suburb": 0, "state": 2347571, "region": 0, "localadmin": 0}, "woe:timezone_id": 56043662, "woe:hash": "9x84pqdfc85m", "woe:centroid": [-112.177551, 42.575241], "geom:latitude": 42.575241, "geom:longitude": -112.177551, "geom:hash": "9x84pqdfc85m", "woe:latitude": 42.575241, "geom:centroid": [-112.177551, 42.575241], "woe:longitude": -112.177551, "woe:repo": "woeplanet-poi-us", "geom:area": 0.0, "woe:scale": 19}}