{"type": "Feature", "id": 23530418, "properties": {"woe:id": 23530418, "woe:parent_id": 2407631, "woe:name": "Murphy Ranch Elementary School", "woe:placetype": 20, "woe:placetype_name": "POI", "woe:lang": "ENG", "iso:country": "US", "meta:provider": ["geoplanet:7.3.2", "geoplanet:7.4.0", "geoplanet:7.4.1", "geoplanet:7.5.1", "geoplanet:7.5.2", "geoplanet:7.6.0", "geoplanet:7.8.1", "geoplanet:7.9.0", "geoplanet:7.10.0", "geoplanet:8.0.0", "woeplanet:8.0.0"], "meta:indexed": "2020-08-20T22:02:01.747372", "woe:alias_ENG_V": ["Murphy Ranch Elementary"], "meta:updated": "2020-08-22T02:57:28.618032", "woe:hierarchy": {"continent": 24865672, "country": 23424977, "town": 0, "planet": 1, "county": 12587688, "suburb": 0, "state": 2347563, "region": 0, "localadmin": 0}, "woe:timezone_id": 56043663, "woe:hash": "9qh155gbsq0d", "woe:centroid": [-117.987831, 33.946499], "geom:latitude": 33.946499, "geom:longitude": -117.987831, "geom:hash": "9qh155gbsq0d", "woe:latitude": 33.946499, "geom:centroid": [-117.987831, 33.946499], "woe:longitude": -117.987831, "woe:repo": "woeplanet-poi-us"}, "geometry": {"coordinates": [-117.987831, 33.946499], "type": "Point"}}