{"type": "Feature", "id": 23541312, "geometry": {"type": "Point", "coordinates": [-105.068062, 40.419151]}, "properties": {"woe:id": 23541312, "woe:parent_id": 2442436, "woe:name": "Conrad Ball Middle School", "woe:placetype": 20, "woe:placetype_name": "POI", "woe:lang": "ENG", "iso:country": "US", "meta:provider": ["geoplanet:7.3.1", "geoplanet:7.3.2", "geoplanet:7.4.0", "geoplanet:7.4.1", "geoplanet:7.5.1", "geoplanet:7.5.2", "geoplanet:7.6.0", "geoplanet:7.8.1", "geoplanet:7.9.0", "geoplanet:7.10.0", "geoplanet:8.0.0", "woeplanet:8.0.0"], "meta:indexed": "2020-08-20T20:18:24.699638", "meta:updated": "2020-10-14T11:20:03.343732", "woe:hierarchy": {"continent": 24865672, "country": 23424977, "town": 0, "planet": 1, "county": 12587762, "suburb": 0, "state": 2347564, "region": 0, "localadmin": 0}, "woe:timezone_id": 56043665, "woe:hash": "9xjmcn5f8eye", "woe:centroid": [-105.068062, 40.419151], "geom:latitude": 40.419151, "geom:longitude": -105.068062, "geom:hash": "9xjmcn5f8eye", "woe:latitude": 40.419151, "geom:centroid": [-105.068062, 40.419151], "woe:longitude": -105.068062, "woe:repo": "woeplanet-poi-us", "geom:area": 0.0, "woe:scale": 19}}