{"type": "Feature", "id": 24610047, "properties": {"woe:id": 24610047, "woe:parent_id": 2410778, "woe:name": "Club Raleigh", "woe:placetype": 20, "woe:placetype_name": "POI", "woe:lang": "ENG", "iso:country": "US", "meta:provider": ["geoplanet:7.3.1", "geoplanet:7.3.2", "geoplanet:7.4.0", "geoplanet:7.4.1", "geoplanet:7.5.1", "geoplanet:7.5.2", "geoplanet:7.6.0", "geoplanet:7.8.1", "geoplanet:7.9.0", "geoplanet:7.10.0", "geoplanet:8.0.0", "woeplanet:8.0.0"], "meta:indexed": "2020-08-20T20:19:14.357787", "meta:updated": "2020-08-22T02:58:19.439670", "woe:hierarchy": {"continent": 24865672, "country": 23424977, "town": 0, "planet": 1, "county": 12589465, "suburb": 0, "state": 2347592, "region": 0, "localadmin": 0}, "woe:timezone_id": 56043648, "woe:hash": "dq25c9t43dej", "woe:centroid": [-78.677147, 35.82407], "geom:latitude": 35.82407, "geom:longitude": -78.677147, "geom:hash": "dq25c9t43dej", "woe:latitude": 35.82407, "geom:centroid": [-78.677147, 35.82407], "woe:longitude": -78.677147, "woe:repo": "woeplanet-poi-us"}, "geometry": {"coordinates": [-78.677147, 35.82407], "type": "Point"}}