{"type": "Feature", "id": 23668589, "properties": {"woe:id": 23668589, "woe:parent_id": 28340643, "woe:name": "Moses Lake Christian School", "woe:placetype": 20, "woe:placetype_name": "POI", "woe:lang": "ENG", "iso:country": "US", "meta:provider": ["geoplanet:7.3.1", "geoplanet:7.3.2", "geoplanet:7.4.0", "geoplanet:7.4.1", "geoplanet:7.5.1", "geoplanet:7.5.2", "geoplanet:7.6.0", "geoplanet:7.8.1", "geoplanet:7.9.0", "geoplanet:7.10.0", "geoplanet:8.0.0", "woeplanet:8.0.0"], "meta:indexed": "2020-08-20T20:19:09.154929", "meta:updated": "2020-08-22T02:57:51.880719", "woe:hierarchy": {"continent": 24865672, "country": 23424977, "town": 0, "planet": 1, "county": 12590452, "suburb": 0, "state": 2347606, "region": 0, "localadmin": 0}, "woe:timezone_id": 56043663, "woe:hash": "c27hjqhdbhmq", "woe:centroid": [-119.29435, 47.14283], "geom:latitude": 47.14283, "geom:longitude": -119.29435, "geom:hash": "c27hjqhdbhmq", "woe:latitude": 47.14283, "geom:centroid": [-119.29435, 47.14283], "woe:longitude": -119.29435, "woe:repo": "woeplanet-poi-us"}, "geometry": {"coordinates": [-119.29435, 47.14283], "type": "Point"}}