{"type": "Feature", "id": 23554709, "geometry": {"type": "Point", "coordinates": [-84.975533, 34.779819]}, "properties": {"woe:id": 23554709, "woe:parent_id": 2389073, "woe:name": "Westwood Elementary School", "woe:placetype": 20, "woe:placetype_name": "POI", "woe:lang": "ENG", "iso:country": "US", "meta:provider": ["geoplanet:7.3.2", "geoplanet:7.4.0", "geoplanet:7.4.1", "geoplanet:7.5.1", "geoplanet:7.5.2", "geoplanet:7.6.0", "geoplanet:7.8.1", "geoplanet:7.9.0", "geoplanet:7.10.0", "geoplanet:8.0.0", "woeplanet:8.0.0"], "meta:indexed": "2020-08-20T22:02:12.225642", "woe:alias_ENG_V": ["Westwood Elementary"], "meta:updated": "2020-10-14T11:20:05.625834", "woe:hierarchy": {"continent": 24865672, "country": 23424977, "town": 0, "planet": 1, "county": 12588024, "suburb": 0, "state": 2347569, "region": 0, "localadmin": 0}, "woe:timezone_id": 56043648, "woe:hash": "dn5tf76xns4j", "woe:centroid": [-84.975533, 34.779819], "geom:latitude": 34.779819, "geom:longitude": -84.975533, "geom:hash": "dn5tf76xns4j", "woe:latitude": 34.779819, "geom:centroid": [-84.975533, 34.779819], "woe:longitude": -84.975533, "woe:repo": "woeplanet-poi-us", "geom:area": 0.0, "woe:scale": 19}}