{"type": "Feature", "id": 23655475, "geometry": {"type": "Point", "coordinates": [-102.012756, 33.50721]}, "properties": {"woe:id": 23655475, "woe:parent_id": 2522685, "woe:name": "Frenship Junior High School", "woe:placetype": 20, "woe:placetype_name": "POI", "woe:lang": "ENG", "iso:country": "US", "meta:provider": ["geoplanet:7.3.1", "geoplanet:7.3.2", "geoplanet:7.4.0", "geoplanet:7.4.1", "geoplanet:7.5.1", "geoplanet:7.5.2", "geoplanet:7.6.0", "geoplanet:7.8.1", "geoplanet:7.9.0", "geoplanet:7.10.0", "geoplanet:8.0.0", "woeplanet:8.0.0"], "meta:indexed": "2020-08-20T20:19:03.867806", "woe:alias_ENG_V": ["Frenship Junior High"], "meta:updated": "2020-10-14T11:19:35.180397", "woe:hierarchy": {"continent": 24865672, "country": 23424977, "town": 0, "planet": 1, "county": 12590158, "suburb": 0, "state": 2347602, "region": 0, "localadmin": 0}, "woe:timezone_id": 56043661, "woe:hash": "9tzqweu9dkxv", "woe:centroid": [-102.012756, 33.50721], "geom:latitude": 33.50721, "geom:longitude": -102.012756, "geom:hash": "9tzqweu9dkxv", "woe:latitude": 33.50721, "geom:centroid": [-102.012756, 33.50721], "woe:longitude": -102.012756, "woe:repo": "woeplanet-poi-us", "geom:area": 0.0, "woe:scale": 19}}