{"type": "Feature", "id": 23670298, "properties": {"woe:id": 23670298, "woe:parent_id": 2403315, "woe:name": "Fife High School", "woe:placetype": 20, "woe:placetype_name": "POI", "woe:lang": "ENG", "iso:country": "US", "meta:provider": ["geoplanet:7.3.1", "geoplanet:7.3.2", "geoplanet:7.4.0", "geoplanet:7.4.1", "geoplanet:7.5.1", "geoplanet:7.5.2", "geoplanet:7.6.0", "geoplanet:7.8.1", "geoplanet:7.9.0", "geoplanet:7.10.0", "geoplanet:8.0.0", "woeplanet:8.0.0"], "meta:indexed": "2020-08-20T20:19:09.608788", "woe:alias_ENG_V": ["Fife Senior High School", "Fife High", "Fife Senior High", "Fife HS", "Fife Senior HS"], "meta:updated": "2020-08-22T02:58:50.319371", "woe:hierarchy": {"continent": 24865672, "country": 23424977, "town": 0, "planet": 1, "county": 12590466, "suburb": 0, "state": 2347606, "region": 0, "localadmin": 0}, "woe:timezone_id": 56043663, "woe:hash": "c22uxz868sx4", "woe:centroid": [-122.354362, 47.238918], "geom:latitude": 47.238918, "geom:longitude": -122.354362, "geom:hash": "c22uxz868sx4", "woe:latitude": 47.238918, "geom:centroid": [-122.354362, 47.238918], "woe:longitude": -122.354362, "woe:repo": "woeplanet-poi-us"}, "geometry": {"coordinates": [-122.354362, 47.238918], "type": "Point"}}