{"type": "Feature", "id": 23570543, "geometry": {"type": "Point", "coordinates": [-90.605827, 41.524361]}, "properties": {"woe:id": 23570543, "woe:parent_id": 2389559, "woe:name": "Frank L Smart Intermediate School", "woe:placetype": 20, "woe:placetype_name": "POI", "woe:lang": "ENG", "iso:country": "US", "meta:provider": ["geoplanet:7.3.1", "geoplanet:7.3.2", "geoplanet:7.4.0", "geoplanet:7.4.1", "geoplanet:7.5.1", "geoplanet:7.5.2", "geoplanet:7.6.0", "geoplanet:7.8.1", "geoplanet:7.9.0", "geoplanet:7.10.0", "geoplanet:8.0.0", "woeplanet:8.0.0"], "meta:indexed": "2020-08-20T20:18:35.551814", "meta:updated": "2020-10-14T11:20:03.925072", "woe:alias_ENG_V": ["Smart Intermediate School"], "woe:hierarchy": {"continent": 24865672, "country": 23424977, "town": 0, "planet": 1, "county": 12588353, "suburb": 0, "state": 2347574, "region": 0, "localadmin": 0}, "woe:timezone_id": 56043661, "woe:hash": "9zrs4pqbgjyt", "woe:centroid": [-90.605827, 41.524361], "geom:latitude": 41.524361, "geom:longitude": -90.605827, "geom:hash": "9zrs4pqbgjyt", "woe:latitude": 41.524361, "geom:centroid": [-90.605827, 41.524361], "woe:longitude": -90.605827, "woe:repo": "woeplanet-poi-us", "geom:area": 0.0, "woe:scale": 19}}