{"type": "Feature", "id": 23684387, "geometry": {"type": "Point", "coordinates": [-80.275963, 39.312099]}, "properties": {"woe:id": 23684387, "woe:parent_id": 2368943, "woe:name": "Meadowbrook Mall", "woe:placetype": 20, "woe:placetype_name": "POI", "woe:lang": "ENG", "iso:country": "US", "meta:provider": ["geoplanet:7.3.1", "geoplanet:7.3.2", "geoplanet:7.4.0", "geoplanet:7.4.1", "geoplanet:7.5.1", "geoplanet:7.5.2", "geoplanet:7.6.0", "geoplanet:7.8.1", "geoplanet:7.9.0", "geoplanet:7.10.0", "geoplanet:8.0.0", "woeplanet:8.0.0"], "meta:indexed": "2020-08-20T20:19:12.932554", "meta:updated": "2020-10-14T11:19:46.712651", "woe:hierarchy": {"continent": 24865672, "country": 23424977, "town": 0, "planet": 1, "county": 12590495, "suburb": 0, "state": 2347607, "region": 0, "localadmin": 0}, "woe:timezone_id": 56043648, "woe:hash": "dnyztk8cd6rs", "woe:centroid": [-80.275963, 39.312099], "geom:latitude": 39.312099, "geom:longitude": -80.275963, "geom:hash": "dnyztk8cd6rs", "woe:latitude": 39.312099, "geom:centroid": [-80.275963, 39.312099], "woe:longitude": -80.275963, "woe:repo": "woeplanet-poi-us", "geom:area": 0.0, "woe:scale": 19}}