{"type": "Feature", "id": 23545191, "properties": {"woe:id": 23545191, "woe:parent_id": 2514905, "woe:name": "Mcgogney Elementary School", "woe:placetype": 20, "woe:placetype_name": "POI", "woe:lang": "ENG", "iso:country": "US", "meta:provider": ["geoplanet:7.3.1", "geoplanet:7.3.2", "geoplanet:7.4.0", "geoplanet:7.4.1", "geoplanet:7.5.1", "geoplanet:7.5.2", "geoplanet:7.6.0", "geoplanet:7.8.1", "geoplanet:7.9.0", "geoplanet:7.10.0", "geoplanet:8.0.0", "woeplanet:8.0.0"], "meta:indexed": "2020-08-20T20:18:25.810163", "woe:alias_ENG_V": ["Mcgogney Elementary"], "meta:updated": "2020-08-22T02:57:31.461902", "woe:hierarchy": {"continent": 24865672, "country": 23424977, "town": 0, "planet": 1, "county": 12587802, "suburb": 0, "state": 2347567, "region": 0, "localadmin": 0}, "woe:timezone_id": 56043648, "woe:hash": "dqchzywyj0sv", "woe:centroid": [-76.993683, 38.84045], "geom:latitude": 38.84045, "geom:longitude": -76.993683, "geom:hash": "dqchzywyj0sv", "woe:latitude": 38.84045, "geom:centroid": [-76.993683, 38.84045], "woe:longitude": -76.993683, "woe:repo": "woeplanet-poi-us"}, "geometry": {"coordinates": [-76.993683, 38.84045], "type": "Point"}}