{"type": "Feature", "id": 23671454, "properties": {"woe:id": 23671454, "woe:parent_id": 2513583, "woe:name": "Discovery Center", "woe:placetype": 20, "woe:placetype_name": "POI", "woe:lang": "ENG", "iso:country": "US", "meta:provider": ["geoplanet:7.3.2", "geoplanet:7.4.0", "geoplanet:7.4.1", "geoplanet:7.5.1", "geoplanet:7.5.2", "geoplanet:7.6.0", "geoplanet:7.8.1", "geoplanet:7.9.0", "geoplanet:7.10.0", "geoplanet:8.0.0", "woeplanet:8.0.0"], "meta:indexed": "2020-08-20T22:03:00.725793", "meta:updated": "2020-08-22T02:57:52.295601", "woe:hierarchy": {"continent": 24865672, "country": 23424977, "town": 0, "planet": 1, "county": 12590475, "suburb": 0, "state": 2347606, "region": 0, "localadmin": 0}, "woe:timezone_id": 56043663, "woe:hash": "c25y51kvyrk8", "woe:centroid": [-118.337929, 46.06258], "geom:latitude": 46.06258, "geom:longitude": -118.337929, "geom:hash": "c25y51kvyrk8", "woe:latitude": 46.06258, "geom:centroid": [-118.337929, 46.06258], "woe:longitude": -118.337929, "woe:repo": "woeplanet-poi-us"}, "geometry": {"coordinates": [-118.337929, 46.06258], "type": "Point"}}