{"type": "Feature", "id": 23539369, "geometry": {"type": "Point", "coordinates": [-105.102669, 40.05896]}, "properties": {"woe:id": 23539369, "woe:parent_id": 56019678, "woe:name": "Alexander Dawson School", "woe:placetype": 20, "woe:placetype_name": "POI", "woe:lang": "ENG", "iso:country": "US", "meta:provider": ["geoplanet:7.3.2", "geoplanet:7.4.0", "geoplanet:7.4.1", "geoplanet:7.5.1", "geoplanet:7.5.2", "geoplanet:7.6.0", "geoplanet:7.8.1", "geoplanet:7.9.0", "geoplanet:7.10.0", "geoplanet:8.0.0", "woeplanet:8.0.0"], "meta:indexed": "2020-08-20T22:02:05.799908", "meta:updated": "2020-10-14T11:20:16.131370", "woe:hierarchy": {"continent": 24865672, "country": 23424977, "town": 0, "planet": 1, "county": 12587734, "suburb": 0, "state": 2347564, "region": 0, "localadmin": 0}, "woe:timezone_id": 56043665, "woe:hash": "9xj7bkd8673u", "woe:centroid": [-105.102669, 40.05896], "geom:latitude": 40.05896, "geom:longitude": -105.102669, "geom:hash": "9xj7bkd8673u", "woe:latitude": 40.05896, "geom:centroid": [-105.102669, 40.05896], "woe:longitude": -105.102669, "woe:repo": "woeplanet-poi-us", "geom:area": 0.0, "woe:scale": 19}}