{"type": "Feature", "id": 24865912, "properties": {"woe:id": 24865912, "woe:parent_id": 55986243, "woe:name": "Benedictine University", "woe:placetype": 20, "woe:placetype_name": "POI", "woe:lang": "ENG", "iso:country": "US", "meta:provider": ["geoplanet:7.3.1", "geoplanet:7.3.2", "geoplanet:7.4.0", "geoplanet:7.4.1", "geoplanet:7.5.1", "geoplanet:7.5.2", "geoplanet:7.6.0", "geoplanet:7.8.1", "geoplanet:7.9.0", "geoplanet:7.10.0", "geoplanet:8.0.0", "woeplanet:8.0.0"], "meta:indexed": "2020-08-20T20:19:14.693880", "meta:updated": "2020-08-22T02:58:19.601852", "woe:hierarchy": {"continent": 24865672, "country": 23424977, "town": 0, "planet": 1, "county": 12588099, "suburb": 0, "state": 2347572, "region": 0, "localadmin": 0}, "woe:timezone_id": 56043661, "woe:hash": "dp3mekgqvgey", "woe:centroid": [-88.09465, 41.775318], "geom:latitude": 41.775318, "geom:longitude": -88.09465, "geom:hash": "dp3mekgqvgey", "woe:latitude": 41.775318, "geom:centroid": [-88.09465, 41.775318], "woe:longitude": -88.09465, "woe:repo": "woeplanet-poi-us"}, "geometry": {"coordinates": [-88.09465, 41.775318], "type": "Point"}}