{"type": "Feature", "id": 23603447, "geometry": {"type": "Point", "coordinates": [-101.710999, 41.130219]}, "properties": {"woe:id": 23603447, "woe:parent_id": 2464313, "woe:name": "Ogallala High School", "woe:placetype": 20, "woe:placetype_name": "POI", "woe:lang": "ENG", "iso:country": "US", "meta:provider": ["geoplanet:7.3.1", "geoplanet:7.3.2", "geoplanet:7.4.0", "geoplanet:7.4.1", "geoplanet:7.5.1", "geoplanet:7.5.2", "geoplanet:7.6.0", "geoplanet:7.8.1", "geoplanet:7.9.0", "geoplanet:7.10.0", "geoplanet:8.0.0", "woeplanet:8.0.0"], "meta:indexed": "2020-08-20T20:18:45.766346", "woe:alias_ENG_V": ["Ogallala Senior High School", "Ogallala High", "Ogallala Senior High", "Ogallala HS", "Ogallala Senior HS"], "meta:updated": "2020-10-14T11:19:35.946276", "woe:hierarchy": {"continent": 24865672, "country": 23424977, "town": 0, "planet": 1, "county": 12589188, "suburb": 0, "state": 2347586, "region": 0, "localadmin": 0}, "woe:timezone_id": 56043665, "woe:hash": "9xr9vx82cuw1", "woe:centroid": [-101.710999, 41.130219], "geom:latitude": 41.130219, "geom:longitude": -101.710999, "geom:hash": "9xr9vx82cuw1", "woe:latitude": 41.130219, "geom:centroid": [-101.710999, 41.130219], "woe:longitude": -101.710999, "woe:repo": "woeplanet-poi-us", "geom:area": 0.0, "woe:scale": 19}}