{"type": "Feature", "id": 23589049, "geometry": {"type": "Point", "coordinates": [-87.616966, 45.10907]}, "properties": {"woe:id": 23589049, "woe:parent_id": 2432014, "woe:name": "Menominee Middle School", "woe:placetype": 20, "woe:placetype_name": "POI", "woe:lang": "ENG", "iso:country": "US", "meta:provider": ["geoplanet:7.3.1", "geoplanet:7.3.2", "geoplanet:7.4.0", "geoplanet:7.4.1", "geoplanet:7.5.1", "geoplanet:7.5.2", "geoplanet:7.6.0", "geoplanet:7.8.1", "geoplanet:7.9.0", "geoplanet:7.10.0", "geoplanet:8.0.0", "woeplanet:8.0.0"], "meta:indexed": "2020-08-20T20:18:40.843557", "meta:updated": "2020-10-14T11:20:09.477233", "woe:alias_ENG_V": ["Blesch Intermediate School"], "woe:hierarchy": {"continent": 24865672, "country": 23424977, "town": 0, "planet": 1, "county": 12588768, "suburb": 0, "state": 2347581, "region": 0, "localadmin": 0}, "woe:timezone_id": 56043657, "woe:hash": "f018w5z72sng", "woe:centroid": [-87.616966, 45.10907], "geom:latitude": 45.10907, "geom:longitude": -87.616966, "geom:hash": "f018w5z72sng", "woe:latitude": 45.10907, "geom:centroid": [-87.616966, 45.10907], "woe:longitude": -87.616966, "woe:repo": "woeplanet-poi-us", "geom:area": 0.0, "woe:scale": 19}}