{"type": "Feature", "id": 23629045, "properties": {"woe:id": 23629045, "woe:parent_id": 2510225, "woe:name": "Windermere Elementary School", "woe:placetype": 20, "woe:placetype_name": "POI", "woe:lang": "ENG", "iso:country": "US", "meta:provider": ["geoplanet:7.3.1", "geoplanet:7.3.2", "geoplanet:7.4.0", "geoplanet:7.4.1", "geoplanet:7.5.1", "geoplanet:7.5.2", "geoplanet:7.6.0", "geoplanet:7.8.1", "geoplanet:7.9.0", "geoplanet:7.10.0", "geoplanet:8.0.0", "woeplanet:8.0.0"], "meta:indexed": "2020-08-20T20:18:54.048750", "woe:alias_ENG_V": ["Windermere Elementary"], "meta:updated": "2020-08-22T02:57:44.959634", "woe:hierarchy": {"continent": 24865672, "country": 23424977, "town": 0, "planet": 1, "county": 12589551, "suburb": 0, "state": 2347594, "region": 0, "localadmin": 0}, "woe:timezone_id": 56043648, "woe:hash": "dphgv2wxcuqg", "woe:centroid": [-83.080589, 40.03828], "geom:latitude": 40.03828, "geom:longitude": -83.080589, "geom:hash": "dphgv2wxcuqg", "woe:latitude": 40.03828, "geom:centroid": [-83.080589, 40.03828], "woe:longitude": -83.080589, "woe:repo": "woeplanet-poi-us"}, "geometry": {"coordinates": [-83.080589, 40.03828], "type": "Point"}}