{"type": "Feature", "id": 23638948, "geometry": {"type": "Point", "coordinates": [-78.49881, 40.016109]}, "properties": {"woe:id": 23638948, "woe:parent_id": 2361181, "woe:name": "Bedford Senior High School", "woe:placetype": 20, "woe:placetype_name": "POI", "woe:lang": "ENG", "iso:country": "US", "meta:provider": ["geoplanet:7.3.1", "geoplanet:7.3.2", "geoplanet:7.4.0", "geoplanet:7.4.1", "geoplanet:7.5.1", "geoplanet:7.5.2", "geoplanet:7.6.0", "geoplanet:7.8.1", "geoplanet:7.9.0", "geoplanet:7.10.0", "geoplanet:8.0.0", "woeplanet:8.0.0"], "meta:indexed": "2020-08-20T20:18:58.001659", "woe:alias_ENG_V": ["Bedford Senior High", "Bedford High School", "Bedford High", "Bedford Senior HS", "Bedford HS"], "meta:updated": "2020-10-14T11:19:53.688480", "woe:hierarchy": {"continent": 24865672, "country": 23424977, "town": 0, "planet": 1, "county": 12589732, "suburb": 0, "state": 2347597, "region": 0, "localadmin": 0}, "woe:timezone_id": 56043648, "woe:hash": "dr05tswytpku", "woe:centroid": [-78.49881, 40.016109], "geom:latitude": 40.016109, "geom:longitude": -78.49881, "geom:hash": "dr05tswytpku", "woe:latitude": 40.016109, "geom:centroid": [-78.49881, 40.016109], "woe:longitude": -78.49881, "woe:repo": "woeplanet-poi-us", "geom:area": 0.0, "woe:scale": 19}}