{"type": "Feature", "id": 23674197, "properties": {"woe:id": 23674197, "woe:parent_id": 2522759, "woe:name": "Wonewoc High School", "woe:placetype": 20, "woe:placetype_name": "POI", "woe:lang": "ENG", "iso:country": "US", "meta:provider": ["geoplanet:7.3.1", "geoplanet:7.3.2", "geoplanet:7.4.0", "geoplanet:7.4.1", "geoplanet:7.5.1", "geoplanet:7.5.2", "geoplanet:7.6.0", "geoplanet:7.8.1", "geoplanet:7.9.0", "geoplanet:7.10.0", "geoplanet:8.0.0", "woeplanet:8.0.0"], "meta:indexed": "2020-08-20T20:19:10.896269", "woe:alias_ENG_V": ["Wonewoc Senior High School", "Wonewoc High", "Wonewoc Senior High", "Wonewoc HS", "Wonewoc Senior HS"], "meta:updated": "2020-08-22T02:58:50.462450", "woe:hierarchy": {"continent": 24865672, "country": 23424977, "town": 0, "planet": 1, "county": 12590562, "suburb": 0, "state": 2347608, "region": 0, "localadmin": 0}, "woe:timezone_id": 56043661, "woe:hash": "9zzb6utvj366", "woe:centroid": [-90.222588, 43.66328], "geom:latitude": 43.66328, "geom:longitude": -90.222588, "geom:hash": "9zzb6utvj366", "woe:latitude": 43.66328, "geom:centroid": [-90.222588, 43.66328], "woe:longitude": -90.222588, "woe:repo": "woeplanet-poi-us"}, "geometry": {"coordinates": [-90.222588, 43.66328], "type": "Point"}}