{"type": "Feature", "id": 23608142, "properties": {"woe:id": 23608142, "woe:parent_id": 2354389, "woe:name": "Clifford J. Scott High School", "woe:placetype": 20, "woe:placetype_name": "POI", "woe:lang": "ENG", "iso:country": "US", "meta:provider": ["geoplanet:7.3.1", "geoplanet:7.3.2", "geoplanet:7.4.0", "geoplanet:7.4.1", "geoplanet:7.5.1", "geoplanet:7.5.2", "geoplanet:7.6.0", "geoplanet:7.8.1", "geoplanet:7.9.0", "geoplanet:7.10.0", "geoplanet:8.0.0", "woeplanet:8.0.0"], "meta:indexed": "2020-08-20T20:18:47.016124", "woe:alias_ENG_V": ["Clifford J. Scott Senior High School", "Clifford J. Scott High", "Clifford J. Scott Senior High", "Clifford J. Scott HS", "Clifford J. Scott Senior HS"], "meta:updated": "2020-08-22T02:58:48.522014", "woe:hierarchy": {"continent": 24865672, "country": 23424977, "town": 0, "planet": 1, "county": 12589264, "suburb": 0, "state": 2347589, "region": 0, "localadmin": 0}, "woe:timezone_id": 56043648, "woe:hash": "dr5pzx06737c", "woe:centroid": [-74.201172, 40.77615], "geom:latitude": 40.77615, "geom:longitude": -74.201172, "geom:hash": "dr5pzx06737c", "woe:latitude": 40.77615, "geom:centroid": [-74.201172, 40.77615], "woe:longitude": -74.201172, "woe:repo": "woeplanet-poi-us"}, "geometry": {"coordinates": [-74.201172, 40.77615], "type": "Point"}}