{"type": "Feature", "id": 23609067, "geometry": {"type": "Point", "coordinates": [-74.686783, 40.345661]}, "properties": {"woe:id": 23609067, "woe:parent_id": 2476729, "woe:name": "Johnson Park School", "woe:placetype": 20, "woe:placetype_name": "POI", "woe:lang": "ENG", "iso:country": "US", "meta:provider": ["geoplanet:7.3.1", "geoplanet:7.3.2", "geoplanet:7.4.0", "geoplanet:7.4.1", "geoplanet:7.5.1", "geoplanet:7.5.2", "geoplanet:7.6.0", "geoplanet:7.8.1", "geoplanet:7.9.0", "geoplanet:7.10.0", "geoplanet:8.0.0", "woeplanet:8.0.0"], "meta:indexed": "2020-08-20T20:18:47.403470", "meta:updated": "2020-10-14T11:19:35.018616", "woe:hierarchy": {"continent": 24865672, "country": 23424977, "town": 0, "planet": 1, "county": 12589268, "suburb": 0, "state": 2347589, "region": 0, "localadmin": 0}, "woe:timezone_id": 56043648, "woe:hash": "dr4vs2wwxb64", "woe:centroid": [-74.686783, 40.345661], "geom:latitude": 40.345661, "geom:longitude": -74.686783, "geom:hash": "dr4vs2wwxb64", "woe:latitude": 40.345661, "geom:centroid": [-74.686783, 40.345661], "woe:longitude": -74.686783, "woe:repo": "woeplanet-poi-us", "geom:area": 0.0, "woe:scale": 19}}