{"type": "Feature", "id": 23540817, "geometry": {"type": "Point", "coordinates": [-105.125877, 39.808788]}, "properties": {"woe:id": 23540817, "woe:parent_id": 2455226, "woe:name": "Arvada West High School", "woe:placetype": 20, "woe:placetype_name": "POI", "woe:lang": "ENG", "iso:country": "US", "meta:provider": ["geoplanet:7.3.1", "geoplanet:7.3.2", "geoplanet:7.4.0", "geoplanet:7.4.1", "geoplanet:7.5.1", "geoplanet:7.5.2", "geoplanet:7.6.0", "geoplanet:7.8.1", "geoplanet:7.9.0", "geoplanet:7.10.0", "geoplanet:8.0.0", "woeplanet:8.0.0"], "meta:indexed": "2020-08-20T20:18:24.530158", "woe:alias_ENG_V": ["Arvada West Senior High School", "Arvada West High", "Arvada West Senior High", "Arvada West HS", "Arvada West Senior HS"], "meta:updated": "2020-10-14T11:20:25.942836", "woe:hierarchy": {"continent": 24865672, "country": 23424977, "town": 0, "planet": 1, "county": 12587757, "suburb": 0, "state": 2347564, "region": 0, "localadmin": 0}, "woe:timezone_id": 56043665, "woe:hash": "9xj4rycwvxbw", "woe:centroid": [-105.125877, 39.808788], "geom:latitude": 39.808788, "geom:longitude": -105.125877, "geom:hash": "9xj4rycwvxbw", "woe:latitude": 39.808788, "geom:centroid": [-105.125877, 39.808788], "woe:longitude": -105.125877, "woe:repo": "woeplanet-poi-us", "geom:area": 0.0, "woe:scale": 19}}