{"type": "Feature", "id": 23571712, "geometry": {"type": "Point", "coordinates": [-94.983101, 38.968201]}, "properties": {"woe:id": 23571712, "woe:parent_id": 2390005, "woe:name": "Lexington Trails Middle School", "woe:placetype": 20, "woe:placetype_name": "POI", "woe:lang": "ENG", "iso:country": "US", "meta:provider": ["geoplanet:7.3.1", "geoplanet:7.3.2", "geoplanet:7.4.0", "geoplanet:7.4.1", "geoplanet:7.5.1", "geoplanet:7.5.2", "geoplanet:7.6.0", "geoplanet:7.8.1", "geoplanet:7.9.0", "geoplanet:7.10.0", "geoplanet:8.0.0", "woeplanet:8.0.0"], "meta:indexed": "2020-08-20T20:18:36.015880", "meta:updated": "2020-10-14T11:20:09.764534", "woe:hierarchy": {"continent": 24865672, "country": 23424977, "town": 0, "planet": 1, "county": 12588416, "suburb": 0, "state": 2347575, "region": 0, "localadmin": 0}, "woe:timezone_id": 56043661, "woe:hash": "9yumwtgqjr4t", "woe:centroid": [-94.983101, 38.968201], "geom:latitude": 38.968201, "geom:longitude": -94.983101, "geom:hash": "9yumwtgqjr4t", "woe:latitude": 38.968201, "geom:centroid": [-94.983101, 38.968201], "woe:longitude": -94.983101, "woe:repo": "woeplanet-poi-us", "geom:area": 0.0, "woe:scale": 19}}