{"type": "Feature", "id": 23654710, "geometry": {"type": "Point", "coordinates": [-106.406754, 31.894541]}, "properties": {"woe:id": 23654710, "woe:parent_id": 55993605, "woe:name": "Northeast Christian Academy", "woe:placetype": 20, "woe:placetype_name": "POI", "woe:lang": "ENG", "iso:country": "US", "meta:provider": ["geoplanet:7.3.1", "geoplanet:7.3.2", "geoplanet:7.4.0", "geoplanet:7.4.1", "geoplanet:7.5.1", "geoplanet:7.5.2", "geoplanet:7.6.0", "geoplanet:7.8.1", "geoplanet:7.9.0", "geoplanet:7.10.0", "geoplanet:8.0.0", "woeplanet:8.0.0"], "meta:indexed": "2020-08-20T20:19:03.538043", "woe:alias_ENG_V": ["NE Christian Academy"], "meta:updated": "2020-10-14T11:19:29.231581", "woe:hierarchy": {"continent": 24865672, "country": 23424977, "town": 0, "planet": 1, "county": 12590076, "suburb": 0, "state": 2347602, "region": 0, "localadmin": 0}, "woe:timezone_id": 56043665, "woe:hash": "9tsm6whznvme", "woe:centroid": [-106.406754, 31.894541], "geom:latitude": 31.894541, "geom:longitude": -106.406754, "geom:hash": "9tsm6whznvme", "woe:latitude": 31.894541, "geom:centroid": [-106.406754, 31.894541], "woe:longitude": -106.406754, "woe:repo": "woeplanet-poi-us", "geom:area": 0.0, "woe:scale": 19}}