{"type": "Feature", "id": 56204534, "geometry": {"type": "Point", "coordinates": [-73.948593, 40.600182]}, "properties": {"woe:id": 56204534, "woe:parent_id": 12589335, "woe:name": "Theodore Lauer", "woe:placetype": 20, "woe:placetype_name": "POI", "woe:lang": "ENG", "iso:country": "US", "meta:provider": ["geoplanet:7.6.0", "geoplanet:7.8.1", "geoplanet:7.9.0", "geoplanet:7.10.0", "geoplanet:8.0.0", "woeplanet:8.0.0"], "meta:indexed": "2020-08-21T08:24:24.074741", "meta:updated": "2020-10-14T11:19:59.638343", "woe:hierarchy": {"continent": 24865672, "country": 23424977, "town": 0, "planet": 1, "county": 12589335, "suburb": 0, "state": 2347591, "region": 0, "localadmin": 0}, "woe:timezone_id": 56043648, "woe:hash": "dr5qvr030ykx", "woe:centroid": [-73.948593, 40.600182], "geom:latitude": 40.600182, "geom:longitude": -73.948593, "geom:hash": "dr5qvr030ykx", "woe:latitude": 40.600182, "geom:centroid": [-73.948593, 40.600182], "woe:longitude": -73.948593, "woe:repo": "woeplanet-poi-us", "geom:area": 0.0, "woe:scale": 19}}