{"type": "Feature", "id": 23637880, "geometry": {"type": "Point", "coordinates": [-123.141548, 45.434921]}, "properties": {"woe:id": 23637880, "woe:parent_id": 2409217, "woe:name": "Gaston Elementary School", "woe:placetype": 20, "woe:placetype_name": "POI", "woe:lang": "ENG", "iso:country": "US", "meta:provider": ["geoplanet:7.3.1", "geoplanet:7.3.2", "geoplanet:7.4.0", "geoplanet:7.4.1", "geoplanet:7.5.1", "geoplanet:7.5.2", "geoplanet:7.6.0", "geoplanet:7.8.1", "geoplanet:7.9.0", "geoplanet:7.10.0", "geoplanet:8.0.0", "woeplanet:8.0.0"], "meta:indexed": "2020-08-20T20:18:57.530089", "woe:alias_ENG_V": ["Gaston Elementary"], "meta:updated": "2020-10-14T11:19:44.135486", "woe:hierarchy": {"continent": 24865672, "country": 23424977, "town": 0, "planet": 1, "county": 12589725, "suburb": 0, "state": 2347596, "region": 0, "localadmin": 0}, "woe:timezone_id": 56043663, "woe:hash": "c206mz5j9gns", "woe:centroid": [-123.141548, 45.434921], "geom:latitude": 45.434921, "geom:longitude": -123.141548, "geom:hash": "c206mz5j9gns", "woe:latitude": 45.434921, "geom:centroid": [-123.141548, 45.434921], "woe:longitude": -123.141548, "woe:repo": "woeplanet-poi-us", "geom:area": 0.0, "woe:scale": 19}}