{"type": "Feature", "id": 23592459, "geometry": {"type": "Point", "coordinates": [-93.580933, 44.860489]}, "properties": {"woe:id": 23592459, "woe:parent_id": 2378051, "woe:name": "Bluff Creek Elementary School", "woe:placetype": 20, "woe:placetype_name": "POI", "woe:lang": "ENG", "iso:country": "US", "meta:provider": ["geoplanet:7.3.1", "geoplanet:7.3.2", "geoplanet:7.4.0", "geoplanet:7.4.1", "geoplanet:7.5.1", "geoplanet:7.5.2", "geoplanet:7.6.0", "geoplanet:7.8.1", "geoplanet:7.9.0", "geoplanet:7.10.0", "geoplanet:8.0.0", "woeplanet:8.0.0"], "meta:indexed": "2020-08-20T20:18:42.132368", "woe:alias_ENG_V": ["Bluff Creek Elementary"], "meta:updated": "2020-10-14T11:20:12.861090", "woe:hierarchy": {"continent": 24865672, "country": 23424977, "town": 0, "planet": 1, "county": 12588806, "suburb": 0, "state": 2347582, "region": 0, "localadmin": 0}, "woe:timezone_id": 56043661, "woe:hash": "9zvrnw87q1qb", "woe:centroid": [-93.580933, 44.860489], "geom:latitude": 44.860489, "geom:longitude": -93.580933, "geom:hash": "9zvrnw87q1qb", "woe:latitude": 44.860489, "geom:centroid": [-93.580933, 44.860489], "woe:longitude": -93.580933, "woe:repo": "woeplanet-poi-us", "geom:area": 0.0, "woe:scale": 19}}