{"type": "Feature", "id": 23654426, "properties": {"woe:id": 23654426, "woe:parent_id": 2464257, "woe:name": "Christ Lutheran School", "woe:placetype": 20, "woe:placetype_name": "POI", "woe:lang": "ENG", "iso:country": "US", "meta:provider": ["geoplanet:7.3.2", "geoplanet:7.4.0", "geoplanet:7.4.1", "geoplanet:7.5.1", "geoplanet:7.5.2", "geoplanet:7.6.0", "geoplanet:7.8.1", "geoplanet:7.9.0", "geoplanet:7.10.0", "geoplanet:8.0.0", "woeplanet:8.0.0"], "meta:indexed": "2020-08-20T22:02:52.881838", "meta:updated": "2020-08-22T02:57:49.061920", "woe:hierarchy": {"continent": 24865672, "country": 23424977, "town": 0, "planet": 1, "county": 12590074, "suburb": 0, "state": 2347602, "region": 0, "localadmin": 0}, "woe:timezone_id": 56043661, "woe:hash": "9txjq204tb5c", "woe:centroid": [-102.38134, 31.860781], "geom:latitude": 31.860781, "geom:longitude": -102.38134, "geom:hash": "9txjq204tb5c", "woe:latitude": 31.860781, "geom:centroid": [-102.38134, 31.860781], "woe:longitude": -102.38134, "woe:repo": "woeplanet-poi-us"}, "geometry": {"coordinates": [-102.38134, 31.860781], "type": "Point"}}