{"type": "Feature", "id": 23667138, "geometry": {"type": "Point", "coordinates": [-79.451141, 37.78067]}, "properties": {"woe:id": 23667138, "woe:parent_id": 2438834, "woe:name": "Harrington Waddell Elementary School", "woe:placetype": 20, "woe:placetype_name": "POI", "woe:lang": "ENG", "iso:country": "US", "meta:provider": ["geoplanet:7.3.1", "geoplanet:7.3.2", "geoplanet:7.4.0", "geoplanet:7.4.1", "geoplanet:7.5.1", "geoplanet:7.5.2", "geoplanet:7.6.0", "geoplanet:7.8.1", "geoplanet:7.9.0", "geoplanet:7.10.0", "geoplanet:8.0.0", "woeplanet:8.0.0"], "meta:indexed": "2020-08-20T20:19:08.612650", "woe:alias_ENG_V": ["Harrington Waddell Elementary"], "meta:updated": "2020-10-14T11:19:38.425017", "woe:hierarchy": {"continent": 24865672, "country": 23424977, "town": 0, "planet": 1, "county": 12590375, "suburb": 0, "state": 2347605, "region": 0, "localadmin": 0}, "woe:timezone_id": 56043648, "woe:hash": "dnxwbjc2q5r7", "woe:centroid": [-79.451141, 37.78067], "geom:latitude": 37.78067, "geom:longitude": -79.451141, "geom:hash": "dnxwbjc2q5r7", "woe:latitude": 37.78067, "geom:centroid": [-79.451141, 37.78067], "woe:longitude": -79.451141, "woe:repo": "woeplanet-poi-us", "geom:area": 0.0, "woe:scale": 19}}