{"type": "Feature", "id": 23684799, "properties": {"woe:id": 23684799, "woe:parent_id": 2380873, "woe:name": "River Falls Mall", "woe:placetype": 20, "woe:placetype_name": "POI", "woe:lang": "ENG", "iso:country": "US", "meta:provider": ["geoplanet:7.3.1", "geoplanet:7.3.2", "geoplanet:7.4.0", "geoplanet:7.4.1", "geoplanet:7.5.1", "geoplanet:7.5.2", "geoplanet:7.6.0", "geoplanet:7.8.1", "geoplanet:7.9.0", "geoplanet:7.10.0", "geoplanet:8.0.0", "woeplanet:8.0.0"], "meta:indexed": "2020-08-20T20:19:13.213336", "meta:updated": "2020-08-22T02:58:18.921811", "woe:hierarchy": {"continent": 24865672, "country": 23424977, "town": 0, "planet": 1, "county": 12588189, "suburb": 0, "state": 2347573, "region": 0, "localadmin": 0}, "woe:timezone_id": 56043656, "woe:hash": "dng1bx0xs6qn", "woe:centroid": [-85.7584, 38.31612], "geom:latitude": 38.31612, "geom:longitude": -85.7584, "geom:hash": "dng1bx0xs6qn", "woe:latitude": 38.31612, "geom:centroid": [-85.7584, 38.31612], "woe:longitude": -85.7584, "woe:repo": "woeplanet-poi-us"}, "geometry": {"coordinates": [-85.7584, 38.31612], "type": "Point"}}