{"type": "Feature", "id": 56052543, "properties": {"woe:id": 56052543, "woe:parent_id": 2488828, "woe:name": "Antioch University-Santa Barbara", "woe:placetype": 20, "woe:placetype_name": "POI", "woe:lang": "ENG", "iso:country": "US", "meta:provider": ["geoplanet:7.3.1", "geoplanet:7.3.2", "geoplanet:7.4.0", "geoplanet:7.4.1", "geoplanet:7.5.1", "geoplanet:7.5.2", "geoplanet:7.6.0", "geoplanet:7.8.1", "geoplanet:7.9.0", "geoplanet:7.10.0", "geoplanet:8.0.0", "woeplanet:8.0.0"], "meta:indexed": "2020-08-20T20:19:16.387942", "meta:updated": "2020-08-22T02:58:20.461539", "woe:hierarchy": {"continent": 24865672, "country": 23424977, "town": 0, "planet": 1, "county": 12587711, "suburb": 0, "state": 2347563, "region": 0, "localadmin": 0}, "woe:timezone_id": 56043663, "woe:hash": "9q4gu4xbkqjz", "woe:centroid": [-119.696198, 34.422989], "geom:latitude": 34.422989, "geom:longitude": -119.696198, "geom:hash": "9q4gu4xbkqjz", "woe:latitude": 34.422989, "geom:centroid": [-119.696198, 34.422989], "woe:longitude": -119.696198, "woe:repo": "woeplanet-poi-us"}, "geometry": {"coordinates": [-119.696198, 34.422989], "type": "Point"}}