{"type": "Feature", "id": 23586507, "properties": {"woe:id": 23586507, "woe:parent_id": 2360052, "woe:name": "Fremont School", "woe:placetype": 20, "woe:placetype_name": "POI", "woe:lang": "ENG", "iso:country": "US", "meta:provider": ["geoplanet:7.3.1", "geoplanet:7.3.2", "geoplanet:7.4.0", "geoplanet:7.4.1", "geoplanet:7.5.1", "geoplanet:7.5.2", "geoplanet:7.6.0", "geoplanet:7.8.1", "geoplanet:7.9.0", "geoplanet:7.10.0", "geoplanet:8.0.0", "woeplanet:8.0.0"], "meta:indexed": "2020-08-20T20:18:39.998396", "meta:updated": "2020-08-22T02:57:38.706951", "woe:hierarchy": {"continent": 24865672, "country": 23424977, "town": 0, "planet": 1, "county": 12588726, "suburb": 0, "state": 2347581, "region": 0, "localadmin": 0}, "woe:timezone_id": 56043658, "woe:hash": "dpe2vccm9ywy", "woe:centroid": [-85.175201, 42.329929], "geom:latitude": 42.329929, "geom:longitude": -85.175201, "geom:hash": "dpe2vccm9ywy", "woe:latitude": 42.329929, "geom:centroid": [-85.175201, 42.329929], "woe:longitude": -85.175201, "woe:repo": "woeplanet-poi-us"}, "geometry": {"coordinates": [-85.175201, 42.329929], "type": "Point"}}