{"type": "Feature", "id": 23652514, "properties": {"woe:id": 23652514, "woe:parent_id": 12590006, "woe:name": "Tuckers Cross Roads Elementary School", "woe:placetype": 20, "woe:placetype_name": "POI", "woe:lang": "ENG", "iso:country": "US", "meta:provider": ["geoplanet:7.4.0", "geoplanet:7.4.1", "geoplanet:7.5.1", "geoplanet:7.5.2", "geoplanet:7.6.0", "geoplanet:7.8.1", "geoplanet:7.9.0", "geoplanet:7.10.0", "geoplanet:8.0.0", "woeplanet:8.0.0"], "meta:indexed": "2020-08-20T23:56:01.305769", "meta:updated": "2020-08-22T02:58:23.604544", "woe:hierarchy": {"continent": 24865672, "country": 23424977, "town": 0, "planet": 1, "county": 12590006, "suburb": 0, "state": 2347601, "region": 0, "localadmin": 0}, "woe:timezone_id": 56043661, "woe:hash": "dn6tzjbdwjcn", "woe:centroid": [-86.175812, 36.199039], "geom:latitude": 36.199039, "geom:longitude": -86.175812, "geom:hash": "dn6tzjbdwjcn", "woe:latitude": 36.199039, "geom:centroid": [-86.175812, 36.199039], "woe:longitude": -86.175812, "woe:repo": "woeplanet-poi-us"}, "geometry": {"coordinates": [-86.175812, 36.199039], "type": "Point"}}