{"type": "Feature", "id": 23520750, "geometry": {"type": "Point", "coordinates": [-122.298698, 37.929131]}, "properties": {"woe:id": 23520750, "woe:parent_id": 55969428, "woe:name": "Madera Elementary School", "woe:placetype": 20, "woe:placetype_name": "POI", "woe:lang": "ENG", "iso:country": "US", "meta:provider": ["geoplanet:7.3.2", "geoplanet:7.4.0", "geoplanet:7.4.1", "geoplanet:7.5.1", "geoplanet:7.5.2", "geoplanet:7.6.0", "geoplanet:7.8.1", "geoplanet:7.9.0", "geoplanet:7.10.0", "geoplanet:8.0.0", "woeplanet:8.0.0"], "meta:indexed": "2020-08-20T22:01:58.378782", "woe:alias_ENG_V": ["Madera Elementary"], "meta:updated": "2020-10-14T11:20:04.903949", "woe:hierarchy": {"continent": 24865672, "country": 23424977, "town": 0, "planet": 1, "county": 12587676, "suburb": 0, "state": 2347563, "region": 0, "localadmin": 0}, "woe:timezone_id": 56043663, "woe:hash": "9q9pc0bc1y3p", "woe:centroid": [-122.298698, 37.929131], "geom:latitude": 37.929131, "geom:longitude": -122.298698, "geom:hash": "9q9pc0bc1y3p", "woe:latitude": 37.929131, "geom:centroid": [-122.298698, 37.929131], "woe:longitude": -122.298698, "woe:repo": "woeplanet-poi-us", "geom:area": 0.0, "woe:scale": 19}}