{"type": "Feature", "id": 23586815, "geometry": {"type": "Point", "coordinates": [-84.829803, 42.551331]}, "properties": {"woe:id": 23586815, "woe:parent_id": 2378425, "woe:name": "St Mary Elementary School", "woe:placetype": 20, "woe:placetype_name": "POI", "woe:lang": "ENG", "iso:country": "US", "meta:provider": ["geoplanet:7.3.2", "geoplanet:7.4.0", "geoplanet:7.4.1", "geoplanet:7.5.1", "geoplanet:7.5.2", "geoplanet:7.6.0", "geoplanet:7.8.1", "geoplanet:7.9.0", "geoplanet:7.10.0", "geoplanet:8.0.0", "woeplanet:8.0.0"], "meta:indexed": "2020-08-20T22:02:25.159487", "woe:alias_ENG_V": ["St Mary Elementary"], "meta:updated": "2020-10-14T11:20:26.525798", "woe:hierarchy": {"continent": 24865672, "country": 23424977, "town": 0, "planet": 1, "county": 12588736, "suburb": 0, "state": 2347581, "region": 0, "localadmin": 0}, "woe:timezone_id": 56043658, "woe:hash": "dpedjdhz6r42", "woe:centroid": [-84.829803, 42.551331], "geom:latitude": 42.551331, "geom:longitude": -84.829803, "geom:hash": "dpedjdhz6r42", "woe:latitude": 42.551331, "geom:centroid": [-84.829803, 42.551331], "woe:longitude": -84.829803, "woe:repo": "woeplanet-poi-us", "geom:area": 0.0, "woe:scale": 19}}