{"type": "Feature", "id": 23543299, "properties": {"woe:id": 23543299, "woe:parent_id": 28338003, "woe:name": "Miss Porter's School", "woe:placetype": 20, "woe:placetype_name": "POI", "woe:lang": "ENG", "iso:country": "US", "meta:provider": ["geoplanet:7.3.1", "geoplanet:7.3.2", "geoplanet:7.4.0", "geoplanet:7.4.1", "geoplanet:7.5.1", "geoplanet:7.5.2", "geoplanet:7.6.0", "geoplanet:7.8.1", "geoplanet:7.9.0", "geoplanet:7.10.0", "geoplanet:8.0.0", "woeplanet:8.0.0"], "meta:indexed": "2020-08-20T20:18:25.231636", "meta:updated": "2020-08-22T02:57:31.114435", "woe:hierarchy": {"continent": 24865672, "country": 23424977, "town": 0, "planet": 1, "county": 12587792, "suburb": 0, "state": 2347565, "region": 0, "localadmin": 0}, "woe:timezone_id": 56043648, "woe:hash": "drkjqer2g1wj", "woe:centroid": [-72.829262, 41.722092], "geom:latitude": 41.722092, "geom:longitude": -72.829262, "geom:hash": "drkjqer2g1wj", "woe:latitude": 41.722092, "geom:centroid": [-72.829262, 41.722092], "woe:longitude": -72.829262, "woe:repo": "woeplanet-poi-us"}, "geometry": {"coordinates": [-72.829262, 41.722092], "type": "Point"}}