{"type": "Feature", "id": 23623410, "properties": {"woe:id": 23623410, "woe:parent_id": 55989727, "woe:name": "Montessori School of Raleigh", "woe:placetype": 20, "woe:placetype_name": "POI", "woe:lang": "ENG", "iso:country": "US", "meta:provider": ["geoplanet:7.3.1", "geoplanet:7.3.2", "geoplanet:7.4.0", "geoplanet:7.4.1", "geoplanet:7.5.1", "geoplanet:7.5.2", "geoplanet:7.6.0", "geoplanet:7.8.1", "geoplanet:7.9.0", "geoplanet:7.10.0", "geoplanet:8.0.0", "woeplanet:8.0.0"], "meta:indexed": "2020-08-20T20:18:52.582033", "meta:updated": "2020-08-22T02:57:44.205073", "woe:hierarchy": {"continent": 24865672, "country": 23424977, "town": 0, "planet": 1, "county": 12589465, "suburb": 0, "state": 2347592, "region": 0, "localadmin": 0}, "woe:timezone_id": 56043648, "woe:hash": "dq2h1frxy4zp", "woe:centroid": [-78.662529, 35.873081], "geom:latitude": 35.873081, "geom:longitude": -78.662529, "geom:hash": "dq2h1frxy4zp", "woe:latitude": 35.873081, "geom:centroid": [-78.662529, 35.873081], "woe:longitude": -78.662529, "woe:repo": "woeplanet-poi-us"}, "geometry": {"coordinates": [-78.662529, 35.873081], "type": "Point"}}