{"type": "Feature", "id": 23663753, "properties": {"woe:id": 23663753, "woe:parent_id": 2496458, "woe:name": "Stratton Mtn Station", "woe:placetype": 20, "woe:placetype_name": "POI", "woe:lang": "ENG", "iso:country": "US", "meta:provider": ["geoplanet:7.3.1", "geoplanet:7.3.2", "geoplanet:7.4.0", "geoplanet:7.4.1", "geoplanet:7.5.1", "geoplanet:7.5.2", "geoplanet:7.6.0", "geoplanet:7.8.1", "geoplanet:7.9.0", "geoplanet:7.10.0", "geoplanet:8.0.0", "woeplanet:8.0.0"], "meta:indexed": "2020-08-20T20:19:07.589865", "meta:updated": "2020-08-22T02:57:51.028309", "woe:hierarchy": {"continent": 24865672, "country": 23424977, "town": 0, "planet": 1, "county": 12590302, "suburb": 0, "state": 2347604, "region": 0, "localadmin": 0}, "woe:timezone_id": 56043648, "woe:hash": "drsjxnfkkuz9", "woe:centroid": [-72.814079, 43.192131], "geom:latitude": 43.192131, "geom:longitude": -72.814079, "geom:hash": "drsjxnfkkuz9", "woe:latitude": 43.192131, "geom:centroid": [-72.814079, 43.192131], "woe:longitude": -72.814079, "woe:repo": "woeplanet-poi-us"}, "geometry": {"coordinates": [-72.814079, 43.192131], "type": "Point"}}