{"type": "Feature", "id": 23602267, "properties": {"woe:id": 23602267, "woe:parent_id": 2416594, "woe:name": "Daly School", "woe:placetype": 20, "woe:placetype_name": "POI", "woe:lang": "ENG", "iso:country": "US", "meta:provider": ["geoplanet:7.3.2", "geoplanet:7.4.0", "geoplanet:7.4.1", "geoplanet:7.5.1", "geoplanet:7.5.2", "geoplanet:7.6.0", "geoplanet:7.8.1", "geoplanet:7.9.0", "geoplanet:7.10.0", "geoplanet:8.0.0", "woeplanet:8.0.0"], "meta:indexed": "2020-08-20T22:02:31.538054", "meta:updated": "2020-08-22T02:57:41.270246", "woe:alias_ENG_V": ["Daly Elementary School"], "woe:hierarchy": {"continent": 24865672, "country": 23424977, "town": 0, "planet": 1, "county": 12589121, "suburb": 0, "state": 2347585, "region": 0, "localadmin": 0}, "woe:timezone_id": 56043665, "woe:hash": "c2nz43y2hucu", "woe:centroid": [-114.150146, 46.240108], "geom:latitude": 46.240108, "geom:longitude": -114.150146, "geom:hash": "c2nz43y2hucu", "woe:latitude": 46.240108, "geom:centroid": [-114.150146, 46.240108], "woe:longitude": -114.150146, "woe:repo": "woeplanet-poi-us"}, "geometry": {"coordinates": [-114.150146, 46.240108], "type": "Point"}}