{"type": "Feature", "id": 23652457, "geometry": {"type": "Point", "coordinates": [-87.125221, 35.99147]}, "properties": {"woe:id": 23652457, "woe:parent_id": 2401879, "woe:name": "Westwood Elementary School", "woe:placetype": 20, "woe:placetype_name": "POI", "woe:lang": "ENG", "iso:country": "US", "meta:provider": ["geoplanet:7.3.1", "geoplanet:7.3.2", "geoplanet:7.4.0", "geoplanet:7.4.1", "geoplanet:7.5.1", "geoplanet:7.5.2", "geoplanet:7.6.0", "geoplanet:7.8.1", "geoplanet:7.9.0", "geoplanet:7.10.0", "geoplanet:8.0.0", "woeplanet:8.0.0"], "meta:indexed": "2020-08-20T20:19:02.423493", "woe:alias_ENG_V": ["Westwood Elementary"], "meta:updated": "2020-10-14T11:19:53.735066", "woe:hierarchy": {"continent": 24865672, "country": 23424977, "town": 0, "planet": 1, "county": 12590005, "suburb": 0, "state": 2347601, "region": 0, "localadmin": 0}, "woe:timezone_id": 56043661, "woe:hash": "dn6hc2j3e0q9", "woe:centroid": [-87.125221, 35.99147], "geom:latitude": 35.99147, "geom:longitude": -87.125221, "geom:hash": "dn6hc2j3e0q9", "woe:latitude": 35.99147, "geom:centroid": [-87.125221, 35.99147], "woe:longitude": -87.125221, "woe:repo": "woeplanet-poi-us", "geom:area": 0.0, "woe:scale": 19}}