{"type": "Feature", "id": 23566122, "geometry": {"type": "Point", "coordinates": [-86.096199, 39.971191]}, "properties": {"woe:id": 23566122, "woe:parent_id": 2462148, "woe:name": "Mohawk Trails Elementary School", "woe:placetype": 20, "woe:placetype_name": "POI", "woe:lang": "ENG", "iso:country": "US", "meta:provider": ["geoplanet:7.3.1", "geoplanet:7.3.2", "geoplanet:7.4.0", "geoplanet:7.4.1", "geoplanet:7.5.1", "geoplanet:7.5.2", "geoplanet:7.6.0", "geoplanet:7.8.1", "geoplanet:7.9.0", "geoplanet:7.10.0", "geoplanet:8.0.0", "woeplanet:8.0.0"], "meta:indexed": "2020-08-20T20:18:33.875006", "woe:alias_ENG_V": ["Mohawk Trails Elementary"], "meta:updated": "2020-10-14T11:20:12.034508", "woe:hierarchy": {"continent": 24865672, "country": 23424977, "town": 0, "planet": 1, "county": 12588208, "suburb": 0, "state": 2347573, "region": 0, "localadmin": 0}, "woe:timezone_id": 56043656, "woe:hash": "dp4g2ud9j4j1", "woe:centroid": [-86.096199, 39.971191], "geom:latitude": 39.971191, "geom:longitude": -86.096199, "geom:hash": "dp4g2ud9j4j1", "woe:latitude": 39.971191, "geom:centroid": [-86.096199, 39.971191], "woe:longitude": -86.096199, "woe:repo": "woeplanet-poi-us", "geom:area": 0.0, "woe:scale": 19}}