{"type": "Feature", "id": 23680375, "properties": {"woe:id": 23680375, "woe:parent_id": 2402973, "woe:name": "Fergus Station", "woe:placetype": 20, "woe:placetype_name": "POI", "woe:lang": "ENG", "iso:country": "US", "meta:provider": ["geoplanet:7.3.1", "geoplanet:7.3.2", "geoplanet:7.4.0", "geoplanet:7.4.1", "geoplanet:7.5.1", "geoplanet:7.5.2", "geoplanet:7.6.0", "geoplanet:7.8.1", "geoplanet:7.9.0", "geoplanet:7.10.0", "geoplanet:8.0.0", "woeplanet:8.0.0"], "meta:indexed": "2020-08-20T20:19:18.410194", "meta:updated": "2020-08-22T02:58:21.629515", "woe:hierarchy": {"continent": 24865672, "country": 23424977, "town": 0, "planet": 1, "county": 12587693, "suburb": 0, "state": 2347563, "region": 0, "localadmin": 0}, "woe:timezone_id": 56043663, "woe:hash": "9qdk31ekwwf3", "woe:centroid": [-120.537247, 37.318619], "geom:latitude": 37.318619, "geom:longitude": -120.537247, "geom:hash": "9qdk31ekwwf3", "woe:latitude": 37.318619, "geom:centroid": [-120.537247, 37.318619], "woe:longitude": -120.537247, "woe:repo": "woeplanet-poi-us"}, "geometry": {"coordinates": [-120.537247, 37.318619], "type": "Point"}}