{"type": "Feature", "id": 56063578, "properties": {"woe:id": 56063578, "woe:parent_id": 2414581, "woe:name": "Baton Rouge Station", "woe:placetype": 20, "woe:placetype_name": "POI", "woe:lang": "ENG", "iso:country": "US", "meta:provider": ["geoplanet:7.3.1", "geoplanet:7.3.2", "geoplanet:7.4.0", "geoplanet:7.4.1", "geoplanet:7.5.1", "geoplanet:7.5.2", "geoplanet:7.6.0", "geoplanet:7.8.1", "geoplanet:7.9.0", "geoplanet:7.10.0", "geoplanet:8.0.0", "woeplanet:8.0.0"], "meta:indexed": "2020-08-20T20:19:20.629973", "woe:alias_ENG_V": ["Baton Rouge Amtrak Station", "Amtrak Baton Rouge Station", "Amtrak-Baton Rouge"], "meta:updated": "2020-08-22T02:58:22.887574", "woe:hierarchy": {"continent": 24865672, "country": 23424977, "town": 0, "planet": 1, "county": 12588612, "suburb": 0, "state": 2347577, "region": 0, "localadmin": 0}, "woe:timezone_id": 56043661, "woe:hash": "9vrjjppnjxy0", "woe:centroid": [-91.176666, 30.44968], "geom:latitude": 30.44968, "geom:longitude": -91.176666, "geom:hash": "9vrjjppnjxy0", "woe:latitude": 30.44968, "geom:centroid": [-91.176666, 30.44968], "woe:longitude": -91.176666, "woe:repo": "woeplanet-poi-us"}, "geometry": {"coordinates": [-91.176666, 30.44968], "type": "Point"}}