{"type": "Feature", "id": 23681724, "geometry": {"type": "Point", "coordinates": [-87.68132, 40.538921]}, "properties": {"woe:id": 23681724, "woe:parent_id": 2516232, "woe:name": "Wellington Station", "woe:placetype": 20, "woe:placetype_name": "POI", "woe:lang": "ENG", "iso:country": "US", "meta:provider": ["geoplanet:7.3.1", "geoplanet:7.3.2", "geoplanet:7.4.0", "geoplanet:7.4.1", "geoplanet:7.5.1", "geoplanet:7.5.2", "geoplanet:7.6.0", "geoplanet:7.8.1", "geoplanet:7.9.0", "geoplanet:7.10.0", "geoplanet:8.0.0", "woeplanet:8.0.0"], "meta:indexed": "2020-08-20T20:19:19.288006", "meta:updated": "2020-10-14T11:19:48.380589", "woe:hierarchy": {"continent": 24865672, "country": 23424977, "town": 0, "planet": 1, "county": 12588115, "suburb": 0, "state": 2347572, "region": 0, "localadmin": 0}, "woe:timezone_id": 56043661, "woe:hash": "dp1wsgbkm4t5", "woe:centroid": [-87.68132, 40.538921], "geom:latitude": 40.538921, "geom:longitude": -87.68132, "geom:hash": "dp1wsgbkm4t5", "woe:latitude": 40.538921, "geom:centroid": [-87.68132, 40.538921], "woe:longitude": -87.68132, "woe:repo": "woeplanet-poi-us", "geom:area": 0.0, "woe:scale": 19}}