{"type": "Feature", "id": 56052618, "geometry": {"type": "Point", "coordinates": [-83.233673, 42.32325]}, "properties": {"woe:id": 56052618, "woe:parent_id": 56021821, "woe:name": "Henry Ford Community College", "woe:placetype": 20, "woe:placetype_name": "POI", "woe:lang": "ENG", "iso:country": "US", "meta:provider": ["geoplanet:7.3.1", "geoplanet:7.3.2", "geoplanet:7.4.0", "geoplanet:7.4.1", "geoplanet:7.5.1", "geoplanet:7.5.2", "geoplanet:7.6.0", "geoplanet:7.8.1", "geoplanet:7.9.0", "geoplanet:7.10.0", "geoplanet:8.0.0", "woeplanet:8.0.0"], "meta:indexed": "2020-08-20T20:19:16.438686", "meta:updated": "2020-10-14T11:19:56.933539", "woe:hierarchy": {"continent": 24865672, "country": 23424977, "town": 0, "planet": 1, "county": 12588795, "suburb": 0, "state": 2347581, "region": 0, "localadmin": 0}, "woe:timezone_id": 56043658, "woe:hash": "dpsbcbxnfceh", "woe:centroid": [-83.233673, 42.32325], "geom:latitude": 42.32325, "geom:longitude": -83.233673, "geom:hash": "dpsbcbxnfceh", "woe:latitude": 42.32325, "geom:centroid": [-83.233673, 42.32325], "woe:longitude": -83.233673, "woe:repo": "woeplanet-poi-us", "geom:area": 0.0, "woe:scale": 19}}