{"type": "Feature", "id": 23553416, "properties": {"woe:id": 23553416, "woe:parent_id": 2514331, "woe:name": "Miller Elementary School", "woe:placetype": 20, "woe:placetype_name": "POI", "woe:lang": "ENG", "iso:country": "US", "meta:provider": ["geoplanet:7.3.1", "geoplanet:7.3.2", "geoplanet:7.4.0", "geoplanet:7.4.1", "geoplanet:7.5.1", "geoplanet:7.5.2", "geoplanet:7.6.0", "geoplanet:7.8.1", "geoplanet:7.9.0", "geoplanet:7.10.0", "geoplanet:8.0.0", "woeplanet:8.0.0"], "meta:indexed": "2020-08-20T20:18:29.630271", "woe:alias_ENG_V": ["Miller Elementary"], "meta:updated": "2020-08-22T02:57:33.248322", "woe:hierarchy": {"continent": 24865672, "country": 23424977, "town": 0, "planet": 1, "county": 12587945, "suburb": 0, "state": 2347569, "region": 0, "localadmin": 0}, "woe:timezone_id": 56043648, "woe:hash": "dju98c2bjk4z", "woe:centroid": [-83.637657, 32.614311], "geom:latitude": 32.614311, "geom:longitude": -83.637657, "geom:hash": "dju98c2bjk4z", "woe:latitude": 32.614311, "geom:centroid": [-83.637657, 32.614311], "woe:longitude": -83.637657, "woe:repo": "woeplanet-poi-us"}, "geometry": {"coordinates": [-83.637657, 32.614311], "type": "Point"}}