{"type": "Feature", "id": 23660723, "properties": {"woe:id": 23660723, "woe:parent_id": 2404601, "woe:name": "Flour Bluff Primary School", "woe:placetype": 20, "woe:placetype_name": "POI", "woe:lang": "ENG", "iso:country": "US", "meta:provider": ["geoplanet:7.3.1", "geoplanet:7.3.2", "geoplanet:7.4.0", "geoplanet:7.4.1", "geoplanet:7.5.1", "geoplanet:7.5.2", "geoplanet:7.6.0", "geoplanet:7.8.1", "geoplanet:7.9.0", "geoplanet:7.10.0", "geoplanet:8.0.0", "woeplanet:8.0.0"], "meta:indexed": "2020-08-20T20:19:06.599224", "meta:updated": "2020-08-22T02:57:50.575290", "woe:hierarchy": {"continent": 24865672, "country": 23424977, "town": 0, "planet": 1, "county": 12590184, "suburb": 0, "state": 2347602, "region": 0, "localadmin": 0}, "woe:timezone_id": 56043661, "woe:hash": "9ufv611f0mgw", "woe:centroid": [-97.292503, 27.64747], "geom:latitude": 27.64747, "geom:longitude": -97.292503, "geom:hash": "9ufv611f0mgw", "woe:latitude": 27.64747, "geom:centroid": [-97.292503, 27.64747], "woe:longitude": -97.292503, "woe:repo": "woeplanet-poi-us"}, "geometry": {"coordinates": [-97.292503, 27.64747], "type": "Point"}}