{"type": "Feature", "id": 56053035, "properties": {"woe:id": 56053035, "woe:parent_id": 2433662, "woe:name": "Roane State Community Col-Knoxville", "woe:placetype": 20, "woe:placetype_name": "POI", "woe:lang": "ENG", "iso:country": "US", "meta:provider": ["geoplanet:7.3.1", "geoplanet:7.3.2", "geoplanet:7.4.0", "geoplanet:7.4.1", "geoplanet:7.5.1", "geoplanet:7.5.2", "geoplanet:7.6.0", "geoplanet:7.8.1", "geoplanet:7.9.0", "geoplanet:7.10.0", "geoplanet:8.0.0", "woeplanet:8.0.0"], "meta:indexed": "2020-08-20T20:19:16.733712", "meta:updated": "2020-08-22T02:58:20.672566", "woe:hierarchy": {"continent": 24865672, "country": 23424977, "town": 0, "planet": 1, "county": 12589958, "suburb": 0, "state": 2347601, "region": 0, "localadmin": 0}, "woe:timezone_id": 56043648, "woe:hash": "dnkhq1n4bsqe", "woe:centroid": [-84.103058, 35.909309], "geom:latitude": 35.909309, "geom:longitude": -84.103058, "geom:hash": "dnkhq1n4bsqe", "woe:latitude": 35.909309, "geom:centroid": [-84.103058, 35.909309], "woe:longitude": -84.103058, "woe:repo": "woeplanet-poi-us"}, "geometry": {"coordinates": [-84.103058, 35.909309], "type": "Point"}}