{"type": "Feature", "id": 23650457, "properties": {"woe:id": 23650457, "woe:parent_id": 2392556, "woe:name": "Dodson Branch Elementary School", "woe:placetype": 20, "woe:placetype_name": "POI", "woe:lang": "ENG", "iso:country": "US", "meta:provider": ["geoplanet:7.3.2", "geoplanet:7.4.0", "geoplanet:7.4.1", "geoplanet:7.5.1", "geoplanet:7.5.2", "geoplanet:7.6.0", "geoplanet:7.8.1", "geoplanet:7.9.0", "geoplanet:7.10.0", "geoplanet:8.0.0", "woeplanet:8.0.0"], "meta:indexed": "2020-08-20T22:02:51.065840", "woe:alias_ENG_V": ["Dodson Branch Elementary"], "meta:updated": "2020-08-22T02:57:48.267670", "woe:hierarchy": {"continent": 24865672, "country": 23424977, "town": 0, "planet": 1, "county": 12589955, "suburb": 0, "state": 2347601, "region": 0, "localadmin": 0}, "woe:timezone_id": 56043661, "woe:hash": "dn7nt9xmkup4", "woe:centroid": [-85.529381, 36.307991], "geom:latitude": 36.307991, "geom:longitude": -85.529381, "geom:hash": "dn7nt9xmkup4", "woe:latitude": 36.307991, "geom:centroid": [-85.529381, 36.307991], "woe:longitude": -85.529381, "woe:repo": "woeplanet-poi-us"}, "geometry": {"coordinates": [-85.529381, 36.307991], "type": "Point"}}