{"type": "Feature", "id": 23537072, "properties": {"woe:id": 23537072, "woe:parent_id": 29389019, "woe:name": "Mesa Verde Middle School", "woe:placetype": 20, "woe:placetype_name": "POI", "woe:lang": "ENG", "iso:country": "US", "meta:provider": ["geoplanet:7.3.1", "geoplanet:7.3.2", "geoplanet:7.4.0", "geoplanet:7.4.1", "geoplanet:7.5.1", "geoplanet:7.5.2", "geoplanet:7.6.0", "geoplanet:7.8.1", "geoplanet:7.9.0", "geoplanet:7.10.0", "geoplanet:8.0.0", "woeplanet:8.0.0"], "meta:indexed": "2020-08-20T20:18:23.439508", "meta:updated": "2020-08-22T02:57:29.957086", "woe:hierarchy": {"continent": 24865672, "country": 23424977, "town": 0, "planet": 1, "county": 12587706, "suburb": 0, "state": 2347563, "region": 0, "localadmin": 0}, "woe:timezone_id": 56043663, "woe:hash": "9muew29mrvxc", "woe:centroid": [-117.145157, 32.962662], "geom:latitude": 32.962662, "geom:longitude": -117.145157, "geom:hash": "9muew29mrvxc", "woe:latitude": 32.962662, "geom:centroid": [-117.145157, 32.962662], "woe:longitude": -117.145157, "woe:repo": "woeplanet-poi-us"}, "geometry": {"coordinates": [-117.145157, 32.962662], "type": "Point"}}