{"type": "Feature", "id": 23546710, "properties": {"woe:id": 23546710, "woe:parent_id": 55862106, "woe:name": "Sabal Palm Elementary School", "woe:placetype": 20, "woe:placetype_name": "POI", "woe:lang": "ENG", "iso:country": "US", "meta:provider": ["geoplanet:7.3.1", "geoplanet:7.3.2", "geoplanet:7.4.0", "geoplanet:7.4.1", "geoplanet:7.5.1", "geoplanet:7.5.2", "geoplanet:7.6.0", "geoplanet:7.8.1", "geoplanet:7.9.0", "geoplanet:7.10.0", "geoplanet:8.0.0", "woeplanet:8.0.0"], "meta:indexed": "2020-08-20T20:18:26.523182", "woe:alias_ENG_V": ["Sabal Palm Elementary"], "meta:updated": "2020-08-22T02:57:31.809811", "woe:hierarchy": {"continent": 24865672, "country": 23424977, "town": 0, "planet": 1, "county": 12587839, "suburb": 0, "state": 2347568, "region": 0, "localadmin": 0}, "woe:timezone_id": 56043648, "woe:hash": "djkj0gne8w2v", "woe:centroid": [-84.333092, 30.427271], "geom:latitude": 30.427271, "geom:longitude": -84.333092, "geom:hash": "djkj0gne8w2v", "woe:latitude": 30.427271, "geom:centroid": [-84.333092, 30.427271], "woe:longitude": -84.333092, "woe:repo": "woeplanet-poi-us"}, "geometry": {"coordinates": [-84.333092, 30.427271], "type": "Point"}}