{"type": "Feature", "id": 23588106, "properties": {"woe:id": 23588106, "woe:parent_id": 55859467, "woe:name": "Dickinson School", "woe:placetype": 20, "woe:placetype_name": "POI", "woe:lang": "ENG", "iso:country": "US", "meta:provider": ["geoplanet:7.3.1", "geoplanet:7.3.2", "geoplanet:7.4.0", "geoplanet:7.4.1", "geoplanet:7.5.1", "geoplanet:7.5.2", "geoplanet:7.6.0", "geoplanet:7.8.1", "geoplanet:7.9.0", "geoplanet:7.10.0", "geoplanet:8.0.0", "woeplanet:8.0.0"], "meta:indexed": "2020-08-20T20:18:40.484669", "meta:updated": "2020-08-22T02:57:39.047531", "woe:hierarchy": {"continent": 24865672, "country": 23424977, "town": 0, "planet": 1, "county": 12588754, "suburb": 0, "state": 2347581, "region": 0, "localadmin": 0}, "woe:timezone_id": 56043658, "woe:hash": "dpeh4zdsm36b", "woe:centroid": [-85.656738, 42.93256], "geom:latitude": 42.93256, "geom:longitude": -85.656738, "geom:hash": "dpeh4zdsm36b", "woe:latitude": 42.93256, "geom:centroid": [-85.656738, 42.93256], "woe:longitude": -85.656738, "woe:repo": "woeplanet-poi-us"}, "geometry": {"coordinates": [-85.656738, 42.93256], "type": "Point"}}