{"type": "Feature", "id": 23552837, "geometry": {"type": "Point", "coordinates": [-84.23175, 34.055069]}, "properties": {"woe:id": 23552837, "woe:parent_id": 55864893, "woe:name": "Ocee Elementary School", "woe:placetype": 20, "woe:placetype_name": "POI", "woe:lang": "ENG", "iso:country": "US", "meta:provider": ["geoplanet:7.3.1", "geoplanet:7.3.2", "geoplanet:7.4.0", "geoplanet:7.4.1", "geoplanet:7.5.1", "geoplanet:7.5.2", "geoplanet:7.6.0", "geoplanet:7.8.1", "geoplanet:7.9.0", "geoplanet:7.10.0", "geoplanet:8.0.0", "woeplanet:8.0.0"], "meta:indexed": "2020-08-20T20:18:29.425638", "woe:alias_ENG_V": ["Ocee Elementary"], "meta:updated": "2020-10-14T11:20:28.565687", "woe:hierarchy": {"continent": 24865672, "country": 23424977, "town": 0, "planet": 1, "county": 12587929, "suburb": 0, "state": 2347569, "region": 0, "localadmin": 0}, "woe:timezone_id": 56043648, "woe:hash": "dnh1er831uyz", "woe:centroid": [-84.23175, 34.055069], "geom:latitude": 34.055069, "geom:longitude": -84.23175, "geom:hash": "dnh1er831uyz", "woe:latitude": 34.055069, "geom:centroid": [-84.23175, 34.055069], "woe:longitude": -84.23175, "woe:repo": "woeplanet-poi-us", "geom:area": 0.0, "woe:scale": 19}}