{"type": "Feature", "id": 23652539, "geometry": {"type": "Point", "coordinates": [-95.682381, 31.73139]}, "properties": {"woe:id": 23652539, "woe:parent_id": 2467622, "woe:name": "Westwood Junior High School", "woe:placetype": 20, "woe:placetype_name": "POI", "woe:lang": "ENG", "iso:country": "US", "meta:provider": ["geoplanet:7.3.1", "geoplanet:7.3.2", "geoplanet:7.4.0", "geoplanet:7.4.1", "geoplanet:7.5.1", "geoplanet:7.5.2", "geoplanet:7.6.0", "geoplanet:7.8.1", "geoplanet:7.9.0", "geoplanet:7.10.0", "geoplanet:8.0.0", "woeplanet:8.0.0"], "meta:indexed": "2020-08-20T20:19:02.455705", "woe:alias_ENG_V": ["Westwood Junior High"], "meta:updated": "2020-10-14T11:19:42.654325", "woe:hierarchy": {"continent": 24865672, "country": 23424977, "town": 0, "planet": 1, "county": 12590007, "suburb": 0, "state": 2347602, "region": 0, "localadmin": 0}, "woe:timezone_id": 56043661, "woe:hash": "9veuw8w0wzvd", "woe:centroid": [-95.682381, 31.73139], "geom:latitude": 31.73139, "geom:longitude": -95.682381, "geom:hash": "9veuw8w0wzvd", "woe:latitude": 31.73139, "geom:centroid": [-95.682381, 31.73139], "woe:longitude": -95.682381, "woe:repo": "woeplanet-poi-us", "geom:area": 0.0, "woe:scale": 19}}