{"type": "Feature", "id": 23606223, "geometry": {"type": "Point", "coordinates": [-71.730057, 43.094711]}, "properties": {"woe:id": 23606223, "woe:parent_id": 2515714, "woe:name": "Weare Middle School", "woe:placetype": 20, "woe:placetype_name": "POI", "woe:lang": "ENG", "iso:country": "US", "meta:provider": ["geoplanet:7.3.1", "geoplanet:7.3.2", "geoplanet:7.4.0", "geoplanet:7.4.1", "geoplanet:7.5.1", "geoplanet:7.5.2", "geoplanet:7.6.0", "geoplanet:7.8.1", "geoplanet:7.9.0", "geoplanet:7.10.0", "geoplanet:8.0.0", "woeplanet:8.0.0"], "meta:indexed": "2020-08-20T20:18:46.385775", "meta:updated": "2020-10-14T11:19:45.382827", "woe:hierarchy": {"continent": 24865672, "country": 23424977, "town": 0, "planet": 1, "county": 12589253, "suburb": 0, "state": 2347588, "region": 0, "localadmin": 0}, "woe:timezone_id": 56043648, "woe:hash": "drsvptpubs2u", "woe:centroid": [-71.730057, 43.094711], "geom:latitude": 43.094711, "geom:longitude": -71.730057, "geom:hash": "drsvptpubs2u", "woe:latitude": 43.094711, "geom:centroid": [-71.730057, 43.094711], "woe:longitude": -71.730057, "woe:repo": "woeplanet-poi-us", "geom:area": 0.0, "woe:scale": 19}}