{"type": "Feature", "id": 23519001, "properties": {"woe:id": 23519001, "woe:parent_id": 55860038, "woe:name": "David O'dodd Elementary School", "woe:placetype": 20, "woe:placetype_name": "POI", "woe:lang": "ENG", "iso:country": "US", "meta:provider": ["geoplanet:7.3.1", "geoplanet:7.3.2", "geoplanet:7.4.0", "geoplanet:7.4.1", "geoplanet:7.5.1", "geoplanet:7.5.2", "geoplanet:7.6.0", "geoplanet:7.8.1", "geoplanet:7.9.0", "geoplanet:7.10.0", "geoplanet:8.0.0", "woeplanet:8.0.0"], "meta:indexed": "2020-08-20T20:18:19.261152", "woe:alias_ENG_V": ["David o Dodd Elementary School", "David O'dodd Elementary"], "meta:updated": "2020-08-22T02:57:27.019335", "woe:hierarchy": {"continent": 24865672, "country": 23424977, "town": 0, "planet": 1, "county": 12587654, "suburb": 0, "state": 2347562, "region": 0, "localadmin": 0}, "woe:timezone_id": 56043661, "woe:hash": "9ynm3dbqb8c6", "woe:centroid": [-92.394653, 34.689121], "geom:latitude": 34.689121, "geom:longitude": -92.394653, "geom:hash": "9ynm3dbqb8c6", "woe:latitude": 34.689121, "geom:centroid": [-92.394653, 34.689121], "woe:longitude": -92.394653, "woe:repo": "woeplanet-poi-us"}, "geometry": {"coordinates": [-92.394653, 34.689121], "type": "Point"}}