{"type": "Feature", "id": 23655728, "geometry": {"type": "Point", "coordinates": [-102.078377, 32.027382]}, "properties": {"woe:id": 23655728, "woe:parent_id": 55994302, "woe:name": "Milam Elementary School", "woe:placetype": 20, "woe:placetype_name": "POI", "woe:lang": "ENG", "iso:country": "US", "meta:provider": ["geoplanet:7.3.1", "geoplanet:7.3.2", "geoplanet:7.4.0", "geoplanet:7.4.1", "geoplanet:7.5.1", "geoplanet:7.5.2", "geoplanet:7.6.0", "geoplanet:7.8.1", "geoplanet:7.9.0", "geoplanet:7.10.0", "geoplanet:8.0.0", "woeplanet:8.0.0"], "meta:indexed": "2020-08-20T20:19:04.011130", "woe:alias_ENG_V": ["Milam Elementary"], "meta:updated": "2020-10-14T11:19:29.406589", "woe:hierarchy": {"continent": 24865672, "country": 23424977, "town": 0, "planet": 1, "county": 12590171, "suburb": 0, "state": 2347602, "region": 0, "localadmin": 0}, "woe:timezone_id": 56043661, "woe:hash": "9txqjnkv12tr", "woe:centroid": [-102.078377, 32.027382], "geom:latitude": 32.027382, "geom:longitude": -102.078377, "geom:hash": "9txqjnkv12tr", "woe:latitude": 32.027382, "geom:centroid": [-102.078377, 32.027382], "woe:longitude": -102.078377, "woe:repo": "woeplanet-poi-us", "geom:area": 0.0, "woe:scale": 19}}