{"type": "Feature", "id": 23645499, "geometry": {"type": "Point", "coordinates": [-76.959663, 39.786831]}, "properties": {"woe:id": 23645499, "woe:parent_id": 2468742, "woe:name": "South Western Senior High School", "woe:placetype": 20, "woe:placetype_name": "POI", "woe:lang": "ENG", "iso:country": "US", "meta:provider": ["geoplanet:7.3.1", "geoplanet:7.3.2", "geoplanet:7.4.0", "geoplanet:7.4.1", "geoplanet:7.5.1", "geoplanet:7.5.2", "geoplanet:7.6.0", "geoplanet:7.8.1", "geoplanet:7.9.0", "geoplanet:7.10.0", "geoplanet:8.0.0", "woeplanet:8.0.0"], "meta:indexed": "2020-08-20T20:19:00.213915", "woe:alias_ENG_V": ["South Western Senior High", "South Western High School", "South Western High", "South Western Senior HS", "South Western HS", "S Western Senior High", "S Western Senior Senior High", "S Western Senior Senior HS", "S Western Senior HS", "S Western Senior Senior High School", "S Western Senior High School", "S Western High School", "S Western High", "S Western HS"], "meta:updated": "2020-10-14T11:19:37.098112", "woe:hierarchy": {"continent": 24865672, "country": 23424977, "town": 0, "planet": 1, "county": 12589794, "suburb": 0, "state": 2347597, "region": 0, "localadmin": 0}, "woe:timezone_id": 56043648, "woe:hash": "dr162dzxjfu5", "woe:centroid": [-76.959663, 39.786831], "geom:latitude": 39.786831, "geom:longitude": -76.959663, "geom:hash": "dr162dzxjfu5", "woe:latitude": 39.786831, "geom:centroid": [-76.959663, 39.786831], "woe:longitude": -76.959663, "woe:repo": "woeplanet-poi-us", "geom:area": 0.0, "woe:scale": 19}}