{"type": "Feature", "id": 23611680, "geometry": {"type": "Point", "coordinates": [-103.350143, 32.93869]}, "properties": {"woe:id": 23611680, "woe:parent_id": 2442504, "woe:name": "Llano Elementary School", "woe:placetype": 20, "woe:placetype_name": "POI", "woe:lang": "ENG", "iso:country": "US", "meta:provider": ["geoplanet:7.3.2", "geoplanet:7.4.0", "geoplanet:7.4.1", "geoplanet:7.5.1", "geoplanet:7.5.2", "geoplanet:7.6.0", "geoplanet:7.8.1", "geoplanet:7.9.0", "geoplanet:7.10.0", "geoplanet:8.0.0", "woeplanet:8.0.0"], "meta:indexed": "2020-08-20T22:02:35.173366", "woe:alias_ENG_V": ["Llano Elementary"], "meta:updated": "2020-10-14T11:19:42.362919", "woe:hierarchy": {"continent": 24865672, "country": 23424977, "town": 0, "planet": 1, "county": 12589292, "suburb": 0, "state": 2347590, "region": 0, "localadmin": 0}, "woe:timezone_id": 56043665, "woe:hash": "9tye2hq9z0gg", "woe:centroid": [-103.350143, 32.93869], "geom:latitude": 32.93869, "geom:longitude": -103.350143, "geom:hash": "9tye2hq9z0gg", "woe:latitude": 32.93869, "geom:centroid": [-103.350143, 32.93869], "woe:longitude": -103.350143, "woe:repo": "woeplanet-poi-us", "geom:area": 0.0, "woe:scale": 19}}