{"type": "Feature", "id": 23681713, "properties": {"woe:id": 23681713, "woe:parent_id": 2389217, "woe:name": "Danforth Station", "woe:placetype": 20, "woe:placetype_name": "POI", "woe:lang": "ENG", "iso:country": "US", "meta:provider": ["geoplanet:7.3.1", "geoplanet:7.3.2", "geoplanet:7.4.0", "geoplanet:7.4.1", "geoplanet:7.5.1", "geoplanet:7.5.2", "geoplanet:7.6.0", "geoplanet:7.8.1", "geoplanet:7.9.0", "geoplanet:7.10.0", "geoplanet:8.0.0", "woeplanet:8.0.0"], "meta:indexed": "2020-08-20T20:19:19.279512", "meta:updated": "2020-08-22T02:58:22.128079", "woe:hierarchy": {"continent": 24865672, "country": 23424977, "town": 0, "planet": 1, "county": 12588115, "suburb": 0, "state": 2347572, "region": 0, "localadmin": 0}, "woe:timezone_id": 56043661, "woe:hash": "dp32np055q7f", "woe:centroid": [-87.978371, 40.820251], "geom:latitude": 40.820251, "geom:longitude": -87.978371, "geom:hash": "dp32np055q7f", "woe:latitude": 40.820251, "geom:centroid": [-87.978371, 40.820251], "woe:longitude": -87.978371, "woe:repo": "woeplanet-poi-us"}, "geometry": {"coordinates": [-87.978371, 40.820251], "type": "Point"}}