{"type": "Feature", "id": 23649141, "properties": {"woe:id": 23649141, "woe:parent_id": 2446594, "woe:name": "Fort Craig Elementary School", "woe:placetype": 20, "woe:placetype_name": "POI", "woe:lang": "ENG", "iso:country": "US", "meta:provider": ["geoplanet:7.3.1", "geoplanet:7.3.2", "geoplanet:7.4.0", "geoplanet:7.4.1", "geoplanet:7.5.1", "geoplanet:7.5.2", "geoplanet:7.6.0", "geoplanet:7.8.1", "geoplanet:7.9.0", "geoplanet:7.10.0", "geoplanet:8.0.0", "woeplanet:8.0.0"], "meta:indexed": "2020-08-20T20:19:01.455065", "woe:alias_ENG_V": ["Ft Craig Elementary School", "Ft Craig Elementary", "Fort Craig Elementary"], "meta:updated": "2020-08-22T02:57:48.061271", "woe:hierarchy": {"continent": 24865672, "country": 23424977, "town": 0, "planet": 1, "county": 12589916, "suburb": 0, "state": 2347601, "region": 0, "localadmin": 0}, "woe:timezone_id": 56043648, "woe:hash": "dnk73m7h9egr", "woe:centroid": [-83.964317, 35.757172], "geom:latitude": 35.757172, "geom:longitude": -83.964317, "geom:hash": "dnk73m7h9egr", "woe:latitude": 35.757172, "geom:centroid": [-83.964317, 35.757172], "woe:longitude": -83.964317, "woe:repo": "woeplanet-poi-us"}, "geometry": {"coordinates": [-83.964317, 35.757172], "type": "Point"}}