{"type": "Feature", "id": 23660270, "geometry": {"type": "Point", "coordinates": [-94.101547, 30.078091]}, "properties": {"woe:id": 23660270, "woe:parent_id": 2360899, "woe:name": "St. Anthony Cathedral", "woe:placetype": 20, "woe:placetype_name": "POI", "woe:lang": "ENG", "iso:country": "US", "meta:provider": ["geoplanet:7.4.0", "geoplanet:7.4.1", "geoplanet:7.5.1", "geoplanet:7.5.2", "geoplanet:7.6.0", "geoplanet:7.8.1", "geoplanet:7.9.0", "geoplanet:7.10.0", "geoplanet:8.0.0", "woeplanet:8.0.0"], "meta:indexed": "2020-08-20T23:55:42.299482", "meta:updated": "2020-10-14T11:19:33.559110", "woe:hierarchy": {"continent": 24865672, "country": 23424977, "town": 0, "planet": 1, "county": 12590129, "suburb": 0, "state": 2347602, "region": 0, "localadmin": 0}, "woe:timezone_id": 56043661, "woe:hash": "9vm54et3e48c", "woe:centroid": [-94.101547, 30.078091], "geom:latitude": 30.078091, "geom:longitude": -94.101547, "geom:hash": "9vm54et3e48c", "woe:latitude": 30.078091, "geom:centroid": [-94.101547, 30.078091], "woe:longitude": -94.101547, "woe:repo": "woeplanet-poi-us", "geom:area": 0.0, "woe:scale": 19}}