{"type": "Feature", "id": 23587796, "properties": {"woe:id": 23587796, "woe:parent_id": 2428185, "woe:name": "St John Elementary School", "woe:placetype": 20, "woe:placetype_name": "POI", "woe:lang": "ENG", "iso:country": "US", "meta:provider": ["geoplanet:7.3.2", "geoplanet:7.4.0", "geoplanet:7.4.1", "geoplanet:7.5.1", "geoplanet:7.5.2", "geoplanet:7.6.0", "geoplanet:7.8.1", "geoplanet:7.9.0", "geoplanet:7.10.0", "geoplanet:8.0.0", "woeplanet:8.0.0"], "meta:indexed": "2020-08-20T22:02:25.564826", "woe:alias_ENG_V": ["St John Elementary"], "meta:updated": "2020-08-22T02:57:38.991844", "woe:hierarchy": {"continent": 24865672, "country": 23424977, "town": 0, "planet": 1, "county": 12588751, "suburb": 0, "state": 2347581, "region": 0, "localadmin": 0}, "woe:timezone_id": 56043658, "woe:hash": "dpebrmj2qf87", "woe:centroid": [-84.400459, 42.258968], "geom:latitude": 42.258968, "geom:longitude": -84.400459, "geom:hash": "dpebrmj2qf87", "woe:latitude": 42.258968, "geom:centroid": [-84.400459, 42.258968], "woe:longitude": -84.400459, "woe:repo": "woeplanet-poi-us"}, "geometry": {"coordinates": [-84.400459, 42.258968], "type": "Point"}}