{"type": "Feature", "id": 23630085, "geometry": {"type": "Point", "coordinates": [-81.246643, 40.228062]}, "properties": {"woe:id": 23630085, "woe:parent_id": 2407339, "woe:name": "Harrison Lakeland Elementary School", "woe:placetype": 20, "woe:placetype_name": "POI", "woe:lang": "ENG", "iso:country": "US", "meta:provider": ["geoplanet:7.4.0", "geoplanet:7.4.1", "geoplanet:7.5.1", "geoplanet:7.5.2", "geoplanet:7.6.0", "geoplanet:7.8.1", "geoplanet:7.9.0", "geoplanet:7.10.0", "geoplanet:8.0.0", "woeplanet:8.0.0"], "meta:indexed": "2020-08-20T23:56:01.052585", "meta:updated": "2020-10-14T11:19:27.946699", "woe:hierarchy": {"continent": 24865672, "country": 23424977, "town": 0, "planet": 1, "county": 12589560, "suburb": 0, "state": 2347594, "region": 0, "localadmin": 0}, "woe:timezone_id": 56043648, "woe:hash": "dpnhz5q12n21", "woe:centroid": [-81.246643, 40.228062], "geom:latitude": 40.228062, "geom:longitude": -81.246643, "geom:hash": "dpnhz5q12n21", "woe:latitude": 40.228062, "geom:centroid": [-81.246643, 40.228062], "woe:longitude": -81.246643, "woe:repo": "woeplanet-poi-us", "geom:area": 0.0, "woe:scale": 19}}