{"type": "Feature", "id": 23656723, "properties": {"woe:id": 23656723, "woe:parent_id": 56022648, "woe:name": "Country Day School of Arlington", "woe:placetype": 20, "woe:placetype_name": "POI", "woe:lang": "ENG", "iso:country": "US", "meta:provider": ["geoplanet:7.4.0", "geoplanet:7.4.1", "geoplanet:7.5.1", "geoplanet:7.5.2", "geoplanet:7.6.0", "geoplanet:7.8.1", "geoplanet:7.9.0", "geoplanet:7.10.0", "geoplanet:8.0.0", "woeplanet:8.0.0"], "meta:indexed": "2020-08-20T23:55:40.109705", "meta:updated": "2020-08-22T02:57:49.650794", "woe:hierarchy": {"continent": 24865672, "country": 23424977, "town": 0, "planet": 1, "county": 12590226, "suburb": 0, "state": 2347602, "region": 0, "localadmin": 0}, "woe:timezone_id": 56043661, "woe:hash": "9vffq6nphyrh", "woe:centroid": [-97.099701, 32.75148], "geom:latitude": 32.75148, "geom:longitude": -97.099701, "geom:hash": "9vffq6nphyrh", "woe:latitude": 32.75148, "geom:centroid": [-97.099701, 32.75148], "woe:longitude": -97.099701, "woe:repo": "woeplanet-poi-us"}, "geometry": {"coordinates": [-97.099701, 32.75148], "type": "Point"}}