{"type": "Feature", "id": 56072850, "geometry": {"type": "Point", "coordinates": [-123.002922, 38.468071]}, "properties": {"woe:id": 56072850, "woe:parent_id": 2453208, "woe:name": "Bohemian Grove", "woe:placetype": 20, "woe:placetype_name": "POI", "woe:lang": "ENG", "iso:country": "US", "meta:provider": ["geoplanet:7.5.1", "geoplanet:7.5.2", "geoplanet:7.6.0", "geoplanet:7.8.1", "geoplanet:7.9.0", "geoplanet:7.10.0", "geoplanet:8.0.0", "woeplanet:8.0.0"], "meta:indexed": "2020-08-21T04:29:57.680241", "meta:updated": "2020-10-14T11:19:57.117321", "woe:hierarchy": {"continent": 24865672, "country": 23424977, "town": 0, "planet": 1, "county": 12587718, "suburb": 0, "state": 2347563, "region": 0, "localadmin": 0}, "woe:timezone_id": 56043663, "woe:hash": "9qbdc4bhb0jt", "woe:centroid": [-123.002922, 38.468071], "geom:latitude": 38.468071, "geom:longitude": -123.002922, "geom:hash": "9qbdc4bhb0jt", "woe:latitude": 38.468071, "geom:centroid": [-123.002922, 38.468071], "woe:longitude": -123.002922, "woe:repo": "woeplanet-poi-us", "geom:area": 0.0, "woe:scale": 19}}