{"type": "Feature", "id": 23685267, "geometry": {"type": "Point", "coordinates": [-106.835007, 40.486382]}, "properties": {"woe:id": 23685267, "woe:parent_id": 55974442, "woe:name": "Franklins Mall", "woe:placetype": 20, "woe:placetype_name": "POI", "woe:lang": "ENG", "iso:country": "US", "meta:provider": ["geoplanet:7.3.1", "geoplanet:7.3.2", "geoplanet:7.4.0", "geoplanet:7.4.1", "geoplanet:7.5.1", "geoplanet:7.5.2", "geoplanet:7.6.0", "geoplanet:7.8.1", "geoplanet:7.9.0", "geoplanet:7.10.0", "geoplanet:8.0.0", "woeplanet:8.0.0"], "meta:indexed": "2020-08-20T20:19:13.569558", "meta:updated": "2020-10-14T11:19:35.559383", "woe:hierarchy": {"continent": 24865672, "country": 23424977, "town": 0, "planet": 1, "county": 12587781, "suburb": 0, "state": 2347564, "region": 0, "localadmin": 0}, "woe:timezone_id": 56043665, "woe:hash": "9xhn2fm47bsg", "woe:centroid": [-106.835007, 40.486382], "geom:latitude": 40.486382, "geom:longitude": -106.835007, "geom:hash": "9xhn2fm47bsg", "woe:latitude": 40.486382, "geom:centroid": [-106.835007, 40.486382], "woe:longitude": -106.835007, "woe:repo": "woeplanet-poi-us", "geom:area": 0.0, "woe:scale": 19}}