{"type": "Feature", "id": 23572025, "geometry": {"type": "Point", "coordinates": [-96.175072, 38.40871]}, "properties": {"woe:id": 23572025, "woe:parent_id": 2399543, "woe:name": "W A White Elementary School", "woe:placetype": 20, "woe:placetype_name": "POI", "woe:lang": "ENG", "iso:country": "US", "meta:provider": ["geoplanet:7.3.1", "geoplanet:7.3.2", "geoplanet:7.4.0", "geoplanet:7.4.1", "geoplanet:7.5.1", "geoplanet:7.5.2", "geoplanet:7.6.0", "geoplanet:7.8.1", "geoplanet:7.9.0", "geoplanet:7.10.0", "geoplanet:8.0.0", "woeplanet:8.0.0"], "meta:indexed": "2020-08-20T20:18:36.167993", "woe:alias_ENG_V": ["William Ellen White Elementary Sch", "W A White Elementary"], "meta:updated": "2020-10-14T11:20:17.380859", "woe:hierarchy": {"continent": 24865672, "country": 23424977, "town": 0, "planet": 1, "county": 12588426, "suburb": 0, "state": 2347575, "region": 0, "localadmin": 0}, "woe:timezone_id": 56043661, "woe:hash": "9ygde2p6yqkx", "woe:centroid": [-96.175072, 38.40871], "geom:latitude": 38.40871, "geom:longitude": -96.175072, "geom:hash": "9ygde2p6yqkx", "woe:latitude": 38.40871, "geom:centroid": [-96.175072, 38.40871], "woe:longitude": -96.175072, "woe:repo": "woeplanet-poi-us", "geom:area": 0.0, "woe:scale": 19}}