{"type": "Feature", "id": 23631896, "geometry": {"type": "Point", "coordinates": [-81.357117, 41.155891]}, "properties": {"woe:id": 23631896, "woe:parent_id": 56022367, "woe:name": "St Patrick Elementary School", "woe:placetype": 20, "woe:placetype_name": "POI", "woe:lang": "ENG", "iso:country": "US", "meta:provider": ["geoplanet:7.3.2", "geoplanet:7.4.0", "geoplanet:7.4.1", "geoplanet:7.5.1", "geoplanet:7.5.2", "geoplanet:7.6.0", "geoplanet:7.8.1", "geoplanet:7.9.0", "geoplanet:7.10.0", "geoplanet:8.0.0", "woeplanet:8.0.0"], "meta:indexed": "2020-08-20T22:02:43.644250", "woe:alias_ENG_V": ["St Patrick Elementary"], "meta:updated": "2020-10-14T11:19:45.468200", "woe:hierarchy": {"continent": 24865672, "country": 23424977, "town": 0, "planet": 1, "county": 12589593, "suburb": 0, "state": 2347594, "region": 0, "localadmin": 0}, "woe:timezone_id": 56043648, "woe:hash": "dpq4hsjw3y0s", "woe:centroid": [-81.357117, 41.155891], "geom:latitude": 41.155891, "geom:longitude": -81.357117, "geom:hash": "dpq4hsjw3y0s", "woe:latitude": 41.155891, "geom:centroid": [-81.357117, 41.155891], "woe:longitude": -81.357117, "woe:repo": "woeplanet-poi-us", "geom:area": 0.0, "woe:scale": 19}}