{"type": "Feature", "id": 23594521, "geometry": {"type": "Point", "coordinates": [-93.015373, 45.08263]}, "properties": {"woe:id": 23594521, "woe:parent_id": 2519189, "woe:name": "St Mary of the Lake School", "woe:placetype": 20, "woe:placetype_name": "POI", "woe:lang": "ENG", "iso:country": "US", "meta:provider": ["geoplanet:7.3.1", "geoplanet:7.3.2", "geoplanet:7.4.0", "geoplanet:7.4.1", "geoplanet:7.5.1", "geoplanet:7.5.2", "geoplanet:7.6.0", "geoplanet:7.8.1", "geoplanet:7.9.0", "geoplanet:7.10.0", "geoplanet:8.0.0", "woeplanet:8.0.0"], "meta:indexed": "2020-08-20T20:18:42.904605", "meta:updated": "2020-10-14T11:20:16.453169", "woe:hierarchy": {"continent": 24865672, "country": 23424977, "town": 0, "planet": 1, "county": 12588858, "suburb": 0, "state": 2347582, "region": 0, "localadmin": 0}, "woe:timezone_id": 56043661, "woe:hash": "cbjb7rh32eqg", "woe:centroid": [-93.015373, 45.08263], "geom:latitude": 45.08263, "geom:longitude": -93.015373, "geom:hash": "cbjb7rh32eqg", "woe:latitude": 45.08263, "geom:centroid": [-93.015373, 45.08263], "woe:longitude": -93.015373, "woe:repo": "woeplanet-poi-us", "geom:area": 0.0, "woe:scale": 19}}