{"type": "Feature", "id": 23656564, "properties": {"woe:id": 23656564, "woe:parent_id": 56022739, "woe:name": "Maudrie Walton Elementary School", "woe:placetype": 20, "woe:placetype_name": "POI", "woe:lang": "ENG", "iso:country": "US", "meta:provider": ["geoplanet:7.3.1", "geoplanet:7.3.2", "geoplanet:7.4.0", "geoplanet:7.4.1", "geoplanet:7.5.1", "geoplanet:7.5.2", "geoplanet:7.6.0", "geoplanet:7.8.1", "geoplanet:7.9.0", "geoplanet:7.10.0", "geoplanet:8.0.0", "woeplanet:8.0.0"], "meta:indexed": "2020-08-20T20:19:04.440647", "woe:alias_ENG_V": ["Maudrie Walton Elementary"], "meta:updated": "2020-08-22T02:57:49.596178", "woe:hierarchy": {"continent": 24865672, "country": 23424977, "town": 0, "planet": 1, "county": 12590226, "suburb": 0, "state": 2347602, "region": 0, "localadmin": 0}, "woe:timezone_id": 56043661, "woe:hash": "9vff5kyerngm", "woe:centroid": [-97.230759, 32.722], "geom:latitude": 32.722, "geom:longitude": -97.230759, "geom:hash": "9vff5kyerngm", "woe:latitude": 32.722, "geom:centroid": [-97.230759, 32.722], "woe:longitude": -97.230759, "woe:repo": "woeplanet-poi-us"}, "geometry": {"coordinates": [-97.230759, 32.722], "type": "Point"}}