{"type": "Feature", "id": 23627449, "properties": {"woe:id": 23627449, "woe:parent_id": 2450391, "woe:name": "Middletown High School", "woe:placetype": 20, "woe:placetype_name": "POI", "woe:lang": "ENG", "iso:country": "US", "meta:provider": ["geoplanet:7.3.1", "geoplanet:7.3.2", "geoplanet:7.4.0", "geoplanet:7.4.1", "geoplanet:7.5.1", "geoplanet:7.5.2", "geoplanet:7.6.0", "geoplanet:7.8.1", "geoplanet:7.9.0", "geoplanet:7.10.0", "geoplanet:8.0.0", "woeplanet:8.0.0"], "meta:indexed": "2020-08-20T20:18:53.249219", "woe:alias_ENG_V": ["Middletown Senior High School", "Middletown High", "Middletown Senior High", "Middletown HS", "Middletown Senior HS"], "meta:updated": "2020-08-22T02:58:49.070163", "woe:hierarchy": {"continent": 24865672, "country": 23424977, "town": 0, "planet": 1, "county": 12589535, "suburb": 0, "state": 2347594, "region": 0, "localadmin": 0}, "woe:timezone_id": 56043648, "woe:hash": "dph0bdb2ucx8", "woe:centroid": [-84.35247, 39.522079], "geom:latitude": 39.522079, "geom:longitude": -84.35247, "geom:hash": "dph0bdb2ucx8", "woe:latitude": 39.522079, "geom:centroid": [-84.35247, 39.522079], "woe:longitude": -84.35247, "woe:repo": "woeplanet-poi-us"}, "geometry": {"coordinates": [-84.35247, 39.522079], "type": "Point"}}