{"type": "Feature", "id": 23619240, "geometry": {"type": "Point", "coordinates": [-73.852272, 40.722759]}, "properties": {"woe:id": 23619240, "woe:parent_id": 23511863, "woe:name": "Jhs 190 R. Sage Junior High School", "woe:placetype": 20, "woe:placetype_name": "POI", "woe:lang": "ENG", "iso:country": "US", "meta:provider": ["geoplanet:7.3.1", "geoplanet:7.3.2", "geoplanet:7.4.0", "geoplanet:7.4.1", "geoplanet:7.5.1", "geoplanet:7.5.2", "geoplanet:7.6.0", "geoplanet:7.8.1", "geoplanet:7.9.0", "geoplanet:7.10.0", "geoplanet:8.0.0", "woeplanet:8.0.0"], "meta:indexed": "2020-08-20T20:18:51.156781", "woe:alias_ENG_V": ["Jhs 190 R. Sage Junior High"], "meta:updated": "2020-10-14T11:19:53.076800", "woe:hierarchy": {"continent": 24865672, "country": 23424977, "town": 0, "planet": 1, "county": 12589352, "suburb": 0, "state": 2347591, "region": 0, "localadmin": 0}, "woe:timezone_id": 56043648, "woe:hash": "dr5rxmq7m26x", "woe:centroid": [-73.852272, 40.722759], "geom:latitude": 40.722759, "geom:longitude": -73.852272, "geom:hash": "dr5rxmq7m26x", "woe:latitude": 40.722759, "geom:centroid": [-73.852272, 40.722759], "woe:longitude": -73.852272, "woe:repo": "woeplanet-poi-us", "geom:area": 0.0, "woe:scale": 19}}