{"type": "Feature", "id": 56204310, "geometry": {"type": "Point", "coordinates": [-73.947021, 40.684521]}, "properties": {"woe:id": 56204310, "woe:parent_id": 55992160, "woe:name": "Concord Baptist School", "woe:placetype": 20, "woe:placetype_name": "POI", "woe:lang": "ENG", "iso:country": "US", "meta:provider": ["geoplanet:7.6.0", "geoplanet:7.8.1", "geoplanet:7.9.0", "geoplanet:7.10.0", "geoplanet:8.0.0", "woeplanet:8.0.0"], "meta:indexed": "2020-08-21T08:24:23.887882", "meta:updated": "2020-10-14T11:19:58.114903", "woe:hierarchy": {"continent": 24865672, "country": 23424977, "town": 0, "planet": 1, "county": 12589335, "suburb": 0, "state": 2347591, "region": 0, "localadmin": 0}, "woe:timezone_id": 56043648, "woe:hash": "dr5rmq3kt82t", "woe:centroid": [-73.947021, 40.684521], "geom:latitude": 40.684521, "geom:longitude": -73.947021, "geom:hash": "dr5rmq3kt82t", "woe:latitude": 40.684521, "geom:centroid": [-73.947021, 40.684521], "woe:longitude": -73.947021, "woe:repo": "woeplanet-poi-us", "geom:area": 0.0, "woe:scale": 19}}