{"type": "Feature", "id": 23628741, "properties": {"woe:id": 23628741, "woe:parent_id": 2378598, "woe:name": "Firelands Montessori Academy", "woe:placetype": 20, "woe:placetype_name": "POI", "woe:lang": "ENG", "iso:country": "US", "meta:provider": ["geoplanet:7.3.2", "geoplanet:7.4.0", "geoplanet:7.4.1", "geoplanet:7.5.1", "geoplanet:7.5.2", "geoplanet:7.6.0", "geoplanet:7.8.1", "geoplanet:7.9.0", "geoplanet:7.10.0", "geoplanet:8.0.0", "woeplanet:8.0.0"], "meta:indexed": "2020-08-20T22:02:41.979835", "meta:updated": "2020-08-22T02:57:44.893917", "woe:hierarchy": {"continent": 24865672, "country": 23424977, "town": 0, "planet": 1, "county": 12589548, "suburb": 0, "state": 2347594, "region": 0, "localadmin": 0}, "woe:timezone_id": 56043648, "woe:hash": "dpm73y9348tq", "woe:centroid": [-82.538452, 41.38842], "geom:latitude": 41.38842, "geom:longitude": -82.538452, "geom:hash": "dpm73y9348tq", "woe:latitude": 41.38842, "geom:centroid": [-82.538452, 41.38842], "woe:longitude": -82.538452, "woe:repo": "woeplanet-poi-us"}, "geometry": {"coordinates": [-82.538452, 41.38842], "type": "Point"}}