{"type": "Feature", "id": 23535305, "properties": {"woe:id": 23535305, "woe:parent_id": 55806881, "woe:name": "Mountain View Elementary School", "woe:placetype": 20, "woe:placetype_name": "POI", "woe:lang": "ENG", "iso:country": "US", "meta:provider": ["geoplanet:7.3.2", "geoplanet:7.4.0", "geoplanet:7.4.1", "geoplanet:7.5.1", "geoplanet:7.5.2", "geoplanet:7.6.0", "geoplanet:7.8.1", "geoplanet:7.9.0", "geoplanet:7.10.0", "geoplanet:8.0.0", "woeplanet:8.0.0"], "meta:indexed": "2020-08-20T22:02:04.190672", "woe:alias_ENG_V": ["Mtn View Elementary School", "Mtn View Elementary", "Mountain View Elementary"], "meta:updated": "2020-08-22T02:57:29.686280", "woe:hierarchy": {"continent": 24865672, "country": 23424977, "town": 0, "planet": 1, "county": 12587702, "suburb": 0, "state": 2347563, "region": 0, "localadmin": 0}, "woe:timezone_id": 56043663, "woe:hash": "9qh90n47zj5r", "woe:centroid": [-117.41848, 33.959412], "geom:latitude": 33.959412, "geom:longitude": -117.41848, "geom:hash": "9qh90n47zj5r", "woe:latitude": 33.959412, "geom:centroid": [-117.41848, 33.959412], "woe:longitude": -117.41848, "woe:repo": "woeplanet-poi-us"}, "geometry": {"coordinates": [-117.41848, 33.959412], "type": "Point"}}