{"type": "Feature", "id": 23646614, "properties": {"woe:id": 23646614, "woe:parent_id": 2378319, "woe:name": "Joseph P. Riley Jr. Park", "woe:placetype": 20, "woe:placetype_name": "POI", "woe:lang": "ENG", "iso:country": "US", "meta:provider": ["geoplanet:7.3.1", "geoplanet:7.3.2", "geoplanet:7.4.0", "geoplanet:7.4.1", "geoplanet:7.5.1", "geoplanet:7.5.2", "geoplanet:7.6.0", "geoplanet:7.8.1", "geoplanet:7.9.0", "geoplanet:7.10.0", "geoplanet:8.0.0", "woeplanet:8.0.0"], "meta:indexed": "2020-08-20T20:19:00.552483", "woe:alias_ENG_V": ["The Joseph P. Riley Jr. Park"], "meta:updated": "2020-08-22T02:57:47.628344", "woe:hierarchy": {"continent": 24865672, "country": 23424977, "town": 0, "planet": 1, "county": 12589809, "suburb": 0, "state": 2347599, "region": 0, "localadmin": 0}, "woe:timezone_id": 56043648, "woe:hash": "djz4s3rnjmdm", "woe:centroid": [-79.959641, 32.79113], "geom:latitude": 32.79113, "geom:longitude": -79.959641, "geom:hash": "djz4s3rnjmdm", "woe:latitude": 32.79113, "geom:centroid": [-79.959641, 32.79113], "woe:longitude": -79.959641, "woe:repo": "woeplanet-poi-us"}, "geometry": {"coordinates": [-79.959641, 32.79113], "type": "Point"}}