{"type": "Feature", "id": 23600281, "geometry": {"type": "Point", "coordinates": [-90.786888, 37.93874]}, "properties": {"woe:id": 23600281, "woe:parent_id": 2475928, "woe:name": "Potosi Preschool", "woe:placetype": 20, "woe:placetype_name": "POI", "woe:lang": "ENG", "iso:country": "US", "meta:provider": ["geoplanet:7.3.1", "geoplanet:7.3.2", "geoplanet:7.4.0", "geoplanet:7.4.1", "geoplanet:7.5.1", "geoplanet:7.5.2", "geoplanet:7.6.0", "geoplanet:7.8.1", "geoplanet:7.9.0", "geoplanet:7.10.0", "geoplanet:8.0.0", "woeplanet:8.0.0"], "meta:indexed": "2020-08-20T20:18:44.969458", "meta:updated": "2020-10-14T11:19:36.323604", "woe:hierarchy": {"continent": 24865672, "country": 23424977, "town": 0, "planet": 1, "county": 12589076, "suburb": 0, "state": 2347584, "region": 0, "localadmin": 0}, "woe:timezone_id": 56043661, "woe:hash": "9yxry4e10jtz", "woe:centroid": [-90.786888, 37.93874], "geom:latitude": 37.93874, "geom:longitude": -90.786888, "geom:hash": "9yxry4e10jtz", "woe:latitude": 37.93874, "geom:centroid": [-90.786888, 37.93874], "woe:longitude": -90.786888, "woe:repo": "woeplanet-poi-us", "geom:area": 0.0, "woe:scale": 19}}