{"type": "Feature", "id": 23577930, "geometry": {"type": "Point", "coordinates": [-68.009262, 46.672668]}, "properties": {"woe:id": 23577930, "woe:parent_id": 2476467, "woe:name": "Pine Street Elementary School", "woe:placetype": 20, "woe:placetype_name": "POI", "woe:lang": "ENG", "iso:country": "US", "meta:provider": ["geoplanet:7.3.1", "geoplanet:7.3.2", "geoplanet:7.4.0", "geoplanet:7.4.1", "geoplanet:7.5.1", "geoplanet:7.5.2", "geoplanet:7.6.0", "geoplanet:7.8.1", "geoplanet:7.9.0", "geoplanet:7.10.0", "geoplanet:8.0.0", "woeplanet:8.0.0"], "meta:indexed": "2020-08-20T20:18:38.063578", "woe:alias_ENG_V": ["Pine Street Elementary"], "meta:updated": "2020-10-14T11:20:06.147236", "woe:hierarchy": {"continent": 24865672, "country": 23424977, "town": 0, "planet": 1, "county": 12588661, "suburb": 0, "state": 2347578, "region": 0, "localadmin": 0}, "woe:timezone_id": 56043648, "woe:hash": "f2r9s2mpvrft", "woe:centroid": [-68.009262, 46.672668], "geom:latitude": 46.672668, "geom:longitude": -68.009262, "geom:hash": "f2r9s2mpvrft", "woe:latitude": 46.672668, "geom:centroid": [-68.009262, 46.672668], "woe:longitude": -68.009262, "woe:repo": "woeplanet-poi-us", "geom:area": 0.0, "woe:scale": 19}}