{"type": "Feature", "id": 23591861, "geometry": {"type": "Point", "coordinates": [-83.077652, 42.432919]}, "properties": {"woe:id": 23591861, "woe:parent_id": 29229806, "woe:name": "W L Bonner Christian Academy", "woe:placetype": 20, "woe:placetype_name": "POI", "woe:lang": "ENG", "iso:country": "US", "meta:provider": ["geoplanet:7.3.1", "geoplanet:7.3.2", "geoplanet:7.4.0", "geoplanet:7.4.1", "geoplanet:7.5.1", "geoplanet:7.5.2", "geoplanet:7.6.0", "geoplanet:7.8.1", "geoplanet:7.9.0", "geoplanet:7.10.0", "geoplanet:8.0.0", "woeplanet:8.0.0"], "meta:indexed": "2020-08-20T20:18:41.958286", "meta:updated": "2020-10-14T11:20:18.476330", "woe:hierarchy": {"continent": 24865672, "country": 23424977, "town": 0, "planet": 1, "county": 12588795, "suburb": 0, "state": 2347581, "region": 0, "localadmin": 0}, "woe:timezone_id": 56043658, "woe:hash": "dpscms8twmkv", "woe:centroid": [-83.077652, 42.432919], "geom:latitude": 42.432919, "geom:longitude": -83.077652, "geom:hash": "dpscms8twmkv", "woe:latitude": 42.432919, "geom:centroid": [-83.077652, 42.432919], "woe:longitude": -83.077652, "woe:repo": "woeplanet-poi-us", "geom:area": 0.0, "woe:scale": 19}}