{"type": "Feature", "id": 23591567, "geometry": {"type": "Point", "coordinates": [-82.908928, 42.409142]}, "properties": {"woe:id": 23591567, "woe:parent_id": 56021923, "woe:name": "Brownell Middle School", "woe:placetype": 20, "woe:placetype_name": "POI", "woe:lang": "ENG", "iso:country": "US", "meta:provider": ["geoplanet:7.3.1", "geoplanet:7.3.2", "geoplanet:7.4.0", "geoplanet:7.4.1", "geoplanet:7.5.1", "geoplanet:7.5.2", "geoplanet:7.6.0", "geoplanet:7.8.1", "geoplanet:7.9.0", "geoplanet:7.10.0", "geoplanet:8.0.0", "woeplanet:8.0.0"], "meta:indexed": "2020-08-20T20:18:41.810682", "meta:updated": "2020-10-14T11:20:24.065536", "woe:hierarchy": {"continent": 24865672, "country": 23424977, "town": 0, "planet": 1, "county": 12588795, "suburb": 0, "state": 2347581, "region": 0, "localadmin": 0}, "woe:timezone_id": 56043658, "woe:hash": "dpt1327e1vnd", "woe:centroid": [-82.908928, 42.409142], "geom:latitude": 42.409142, "geom:longitude": -82.908928, "geom:hash": "dpt1327e1vnd", "woe:latitude": 42.409142, "geom:centroid": [-82.908928, 42.409142], "woe:longitude": -82.908928, "woe:repo": "woeplanet-poi-us", "geom:area": 0.0, "woe:scale": 19}}