{"type": "Feature", "id": 23627482, "properties": {"woe:id": 23627482, "woe:parent_id": 12589535, "woe:name": "Hopewell Elementary School", "woe:placetype": 20, "woe:placetype_name": "POI", "woe:lang": "ENG", "iso:country": "US", "meta:provider": ["geoplanet:7.3.1", "geoplanet:7.3.2", "geoplanet:7.4.0", "geoplanet:7.4.1", "geoplanet:7.5.1", "geoplanet:7.5.2", "geoplanet:7.6.0", "geoplanet:7.8.1", "geoplanet:7.9.0", "geoplanet:7.10.0", "geoplanet:8.0.0", "woeplanet:8.0.0"], "meta:indexed": "2020-08-20T20:18:53.274689", "woe:alias_ENG_V": ["Hopewell Elementary"], "meta:updated": "2020-08-22T02:57:44.680996", "woe:hierarchy": {"continent": 24865672, "country": 23424977, "town": 0, "planet": 1, "county": 12589535, "suburb": 0, "state": 2347594, "region": 0, "localadmin": 0}, "woe:timezone_id": 56043648, "woe:hash": "dnupb1wqqrt4", "woe:centroid": [-84.366142, 39.340408], "geom:latitude": 39.340408, "geom:longitude": -84.366142, "geom:hash": "dnupb1wqqrt4", "woe:latitude": 39.340408, "geom:centroid": [-84.366142, 39.340408], "woe:longitude": -84.366142, "woe:repo": "woeplanet-poi-us"}, "geometry": {"coordinates": [-84.366142, 39.340408], "type": "Point"}}