{"type": "Feature", "id": 23564541, "properties": {"woe:id": 23564541, "woe:parent_id": 2389336, "woe:name": "East Park Elementary School", "woe:placetype": 20, "woe:placetype_name": "POI", "woe:lang": "ENG", "iso:country": "US", "meta:provider": ["geoplanet:7.3.1", "geoplanet:7.3.2", "geoplanet:7.4.0", "geoplanet:7.4.1", "geoplanet:7.5.1", "geoplanet:7.5.2", "geoplanet:7.6.0", "geoplanet:7.8.1", "geoplanet:7.9.0", "geoplanet:7.10.0", "geoplanet:8.0.0", "woeplanet:8.0.0"], "meta:indexed": "2020-08-20T20:18:33.264744", "woe:alias_ENG_V": ["E Park Elementary School", "E Park Elementary", "East Park Elementary"], "meta:updated": "2020-08-22T02:57:35.236080", "woe:hierarchy": {"continent": 24865672, "country": 23424977, "town": 0, "planet": 1, "county": 12588169, "suburb": 0, "state": 2347572, "region": 0, "localadmin": 0}, "woe:timezone_id": 56043661, "woe:hash": "dp1sqe20cjpf", "woe:centroid": [-87.604927, 40.140079], "geom:latitude": 40.140079, "geom:longitude": -87.604927, "geom:hash": "dp1sqe20cjpf", "woe:latitude": 40.140079, "geom:centroid": [-87.604927, 40.140079], "woe:longitude": -87.604927, "woe:repo": "woeplanet-poi-us"}, "geometry": {"coordinates": [-87.604927, 40.140079], "type": "Point"}}