{"type": "Feature", "id": 23626838, "properties": {"woe:id": 23626838, "woe:parent_id": 2439993, "woe:name": "Lisbon High School", "woe:placetype": 20, "woe:placetype_name": "POI", "woe:lang": "ENG", "iso:country": "US", "meta:provider": ["geoplanet:7.3.2", "geoplanet:7.4.0", "geoplanet:7.4.1", "geoplanet:7.5.1", "geoplanet:7.5.2", "geoplanet:7.6.0", "geoplanet:7.8.1", "geoplanet:7.9.0", "geoplanet:7.10.0", "geoplanet:8.0.0", "woeplanet:8.0.0"], "meta:indexed": "2020-08-20T22:02:41.017868", "woe:alias_ENG_V": ["Lisbon Senior High School", "Lisbon High", "Lisbon Senior High", "Lisbon HS", "Lisbon Senior HS"], "meta:updated": "2020-08-22T02:58:49.041496", "woe:hierarchy": {"continent": 24865672, "country": 23424977, "town": 0, "planet": 1, "county": 12589510, "suburb": 0, "state": 2347593, "region": 0, "localadmin": 0}, "woe:timezone_id": 56043661, "woe:hash": "cb681n6wct5p", "woe:centroid": [-97.686928, 46.441769], "geom:latitude": 46.441769, "geom:longitude": -97.686928, "geom:hash": "cb681n6wct5p", "woe:latitude": 46.441769, "geom:centroid": [-97.686928, 46.441769], "woe:longitude": -97.686928, "woe:repo": "woeplanet-poi-us"}, "geometry": {"coordinates": [-97.686928, 46.441769], "type": "Point"}}