{"type": "Feature", "id": 23622815, "geometry": {"type": "Point", "coordinates": [-77.058418, 35.859241]}, "properties": {"woe:id": 23622815, "woe:parent_id": 2520902, "woe:name": "Williamston Middle School", "woe:placetype": 20, "woe:placetype_name": "POI", "woe:lang": "ENG", "iso:country": "US", "meta:provider": ["geoplanet:7.3.1", "geoplanet:7.3.2", "geoplanet:7.4.0", "geoplanet:7.4.1", "geoplanet:7.5.1", "geoplanet:7.5.2", "geoplanet:7.6.0", "geoplanet:7.8.1", "geoplanet:7.9.0", "geoplanet:7.10.0", "geoplanet:8.0.0", "woeplanet:8.0.0"], "meta:indexed": "2020-08-20T20:18:52.427414", "meta:updated": "2020-10-14T11:19:44.497252", "woe:hierarchy": {"continent": 24865672, "country": 23424977, "town": 0, "planet": 1, "county": 12589431, "suburb": 0, "state": 2347592, "region": 0, "localadmin": 0}, "woe:timezone_id": 56043648, "woe:hash": "dq35yrzz0xnb", "woe:centroid": [-77.058418, 35.859241], "geom:latitude": 35.859241, "geom:longitude": -77.058418, "geom:hash": "dq35yrzz0xnb", "woe:latitude": 35.859241, "geom:centroid": [-77.058418, 35.859241], "woe:longitude": -77.058418, "woe:repo": "woeplanet-poi-us", "geom:area": 0.0, "woe:scale": 19}}