{"type": "Feature", "id": 23653176, "properties": {"woe:id": 23653176, "woe:parent_id": 2384831, "woe:name": "Care-a-lot School", "woe:placetype": 20, "woe:placetype_name": "POI", "woe:lang": "ENG", "iso:country": "US", "meta:provider": ["geoplanet:7.3.2", "geoplanet:7.4.0", "geoplanet:7.4.1", "geoplanet:7.5.1", "geoplanet:7.5.2", "geoplanet:7.6.0", "geoplanet:7.8.1", "geoplanet:7.9.0", "geoplanet:7.10.0", "geoplanet:8.0.0", "woeplanet:8.0.0"], "meta:indexed": "2020-08-20T22:02:52.195234", "meta:updated": "2020-08-22T02:57:48.748841", "woe:hierarchy": {"continent": 24865672, "country": 23424977, "town": 0, "planet": 1, "county": 12590056, "suburb": 0, "state": 2347602, "region": 0, "localadmin": 0}, "woe:timezone_id": 56043661, "woe:hash": "9vd3h1nwyj1y", "woe:centroid": [-97.90097, 31.119961], "geom:latitude": 31.119961, "geom:longitude": -97.90097, "geom:hash": "9vd3h1nwyj1y", "woe:latitude": 31.119961, "geom:centroid": [-97.90097, 31.119961], "woe:longitude": -97.90097, "woe:repo": "woeplanet-poi-us"}, "geometry": {"coordinates": [-97.90097, 31.119961], "type": "Point"}}