{"type": "Feature", "id": 23582263, "properties": {"woe:id": 23582263, "woe:parent_id": 2402193, "woe:name": "Falmouth High School", "woe:placetype": 20, "woe:placetype_name": "POI", "woe:lang": "ENG", "iso:country": "US", "meta:provider": ["geoplanet:7.3.2", "geoplanet:7.4.0", "geoplanet:7.4.1", "geoplanet:7.5.1", "geoplanet:7.5.2", "geoplanet:7.6.0", "geoplanet:7.8.1", "geoplanet:7.9.0", "geoplanet:7.10.0", "geoplanet:8.0.0", "woeplanet:8.0.0"], "meta:indexed": "2020-08-20T22:02:23.718158", "woe:alias_ENG_V": ["Falmouth Senior High School", "Falmouth High", "Falmouth Senior High", "Falmouth HS", "Falmouth Senior HS"], "meta:updated": "2020-08-22T02:58:47.779107", "woe:hierarchy": {"continent": 24865672, "country": 23424977, "town": 0, "planet": 1, "county": 12588700, "suburb": 0, "state": 2347580, "region": 0, "localadmin": 0}, "woe:timezone_id": 56043648, "woe:hash": "drmu97ddjjj2", "woe:centroid": [-70.605476, 41.591862], "geom:latitude": 41.591862, "geom:longitude": -70.605476, "geom:hash": "drmu97ddjjj2", "woe:latitude": 41.591862, "geom:centroid": [-70.605476, 41.591862], "woe:longitude": -70.605476, "woe:repo": "woeplanet-poi-us"}, "geometry": {"coordinates": [-70.605476, 41.591862], "type": "Point"}}