{"type": "Feature", "id": 23537035, "properties": {"woe:id": 23537035, "woe:parent_id": 2475933, "woe:name": "Potrero Elementary School", "woe:placetype": 20, "woe:placetype_name": "POI", "woe:lang": "ENG", "iso:country": "US", "meta:provider": ["geoplanet:7.3.2", "geoplanet:7.4.0", "geoplanet:7.4.1", "geoplanet:7.5.1", "geoplanet:7.5.2", "geoplanet:7.6.0", "geoplanet:7.8.1", "geoplanet:7.9.0", "geoplanet:7.10.0", "geoplanet:8.0.0", "woeplanet:8.0.0"], "meta:indexed": "2020-08-20T22:02:04.809129", "woe:alias_ENG_V": ["Potrero Elementary"], "meta:updated": "2020-08-22T02:57:29.946402", "woe:hierarchy": {"continent": 24865672, "country": 23424977, "town": 0, "planet": 1, "county": 12587706, "suburb": 0, "state": 2347563, "region": 0, "localadmin": 0}, "woe:timezone_id": 56043663, "woe:hash": "9mv1d2hg42z8", "woe:centroid": [-116.613243, 32.607941], "geom:latitude": 32.607941, "geom:longitude": -116.613243, "geom:hash": "9mv1d2hg42z8", "woe:latitude": 32.607941, "geom:centroid": [-116.613243, 32.607941], "woe:longitude": -116.613243, "woe:repo": "woeplanet-poi-us"}, "geometry": {"coordinates": [-116.613243, 32.607941], "type": "Point"}}