{"type": "Feature", "id": 56203884, "properties": {"woe:id": 56203884, "woe:parent_id": 23512025, "woe:name": "American Conservatory Theatre", "woe:placetype": 20, "woe:placetype_name": "POI", "woe:lang": "ENG", "iso:country": "US", "meta:provider": ["geoplanet:7.6.0", "geoplanet:7.8.1", "geoplanet:7.9.0", "geoplanet:7.10.0", "geoplanet:8.0.0", "woeplanet:8.0.0"], "meta:indexed": "2020-08-21T08:24:23.584165", "meta:updated": "2020-08-22T02:58:23.906146", "woe:alias_ENG_V": ["A.C.T."], "woe:hierarchy": {"continent": 24865672, "country": 23424977, "town": 0, "planet": 1, "county": 12587707, "suburb": 0, "state": 2347563, "region": 0, "localadmin": 0}, "woe:timezone_id": 56043663, "woe:hash": "9q8yyqzvbpjq", "woe:centroid": [-122.410004, 37.787128], "geom:latitude": 37.787128, "geom:longitude": -122.410004, "geom:hash": "9q8yyqzvbpjq", "woe:latitude": 37.787128, "geom:centroid": [-122.410004, 37.787128], "woe:longitude": -122.410004, "woe:repo": "woeplanet-poi-us"}, "geometry": {"coordinates": [-122.410004, 37.787128], "type": "Point"}}