{"type": "Feature", "id": 23591263, "properties": {"woe:id": 23591263, "woe:parent_id": 55987167, "woe:name": "Atkinson Elementary School", "woe:placetype": 20, "woe:placetype_name": "POI", "woe:lang": "ENG", "iso:country": "US", "meta:provider": ["geoplanet:7.3.2", "geoplanet:7.4.0", "geoplanet:7.4.1", "geoplanet:7.5.1", "geoplanet:7.5.2", "geoplanet:7.6.0", "geoplanet:7.8.1", "geoplanet:7.9.0", "geoplanet:7.10.0", "geoplanet:8.0.0", "woeplanet:8.0.0"], "meta:indexed": "2020-08-20T22:02:27.331248", "woe:alias_ENG_V": ["Atkinson Elementary"], "meta:updated": "2020-08-22T02:57:39.604897", "woe:hierarchy": {"continent": 24865672, "country": 23424977, "town": 0, "planet": 1, "county": 12588795, "suburb": 0, "state": 2347581, "region": 0, "localadmin": 0}, "woe:timezone_id": 56043658, "woe:hash": "dpscqh1fcj1v", "woe:centroid": [-83.054192, 42.429699], "geom:latitude": 42.429699, "geom:longitude": -83.054192, "geom:hash": "dpscqh1fcj1v", "woe:latitude": 42.429699, "geom:centroid": [-83.054192, 42.429699], "woe:longitude": -83.054192, "woe:repo": "woeplanet-poi-us"}, "geometry": {"coordinates": [-83.054192, 42.429699], "type": "Point"}}