{"type": "Feature", "id": 23549713, "geometry": {"type": "Point", "coordinates": [-80.203423, 25.805611]}, "properties": {"woe:id": 23549713, "woe:parent_id": 2461329, "woe:name": "Jose De Diego Middle School", "woe:placetype": 20, "woe:placetype_name": "POI", "woe:lang": "ENG", "iso:country": "US", "meta:provider": ["geoplanet:7.3.1", "geoplanet:7.3.2", "geoplanet:7.4.0", "geoplanet:7.4.1", "geoplanet:7.5.1", "geoplanet:7.5.2", "geoplanet:7.6.0", "geoplanet:7.8.1", "geoplanet:7.9.0", "geoplanet:7.10.0", "geoplanet:8.0.0", "woeplanet:8.0.0"], "meta:indexed": "2020-08-20T20:18:28.055544", "meta:updated": "2020-10-14T11:20:27.955789", "woe:hierarchy": {"continent": 24865672, "country": 23424977, "town": 0, "planet": 1, "county": 12587815, "suburb": 0, "state": 2347568, "region": 0, "localadmin": 0}, "woe:timezone_id": 56043648, "woe:hash": "dhwfycv8sf93", "woe:centroid": [-80.203423, 25.805611], "geom:latitude": 25.805611, "geom:longitude": -80.203423, "geom:hash": "dhwfycv8sf93", "woe:latitude": 25.805611, "geom:centroid": [-80.203423, 25.805611], "woe:longitude": -80.203423, "woe:repo": "woeplanet-poi-us", "geom:area": 0.0, "woe:scale": 19}}