{"type": "Feature", "id": 23674545, "geometry": {"type": "Point", "coordinates": [-89.833702, 44.92934]}, "properties": {"woe:id": 23674545, "woe:parent_id": 2445443, "woe:name": "Marathon Elementary School", "woe:placetype": 20, "woe:placetype_name": "POI", "woe:lang": "ENG", "iso:country": "US", "meta:provider": ["geoplanet:7.3.1", "geoplanet:7.3.2", "geoplanet:7.4.0", "geoplanet:7.4.1", "geoplanet:7.5.1", "geoplanet:7.5.2", "geoplanet:7.6.0", "geoplanet:7.8.1", "geoplanet:7.9.0", "geoplanet:7.10.0", "geoplanet:8.0.0", "woeplanet:8.0.0"], "meta:indexed": "2020-08-20T20:19:11.050507", "woe:alias_ENG_V": ["Marathon Elementary"], "meta:updated": "2020-10-14T11:19:48.040250", "woe:hierarchy": {"continent": 24865672, "country": 23424977, "town": 0, "planet": 1, "county": 12590570, "suburb": 0, "state": 2347608, "region": 0, "localadmin": 0}, "woe:timezone_id": 56043661, "woe:hash": "dpbpeg1h7h0b", "woe:centroid": [-89.833702, 44.92934], "geom:latitude": 44.92934, "geom:longitude": -89.833702, "geom:hash": "dpbpeg1h7h0b", "woe:latitude": 44.92934, "geom:centroid": [-89.833702, 44.92934], "woe:longitude": -89.833702, "woe:repo": "woeplanet-poi-us", "geom:area": 0.0, "woe:scale": 19}}