{"type": "Feature", "id": 23592947, "properties": {"woe:id": 23592947, "woe:parent_id": 2516518, "woe:name": "Berea Lutheran School", "woe:placetype": 20, "woe:placetype_name": "POI", "woe:lang": "ENG", "iso:country": "US", "meta:provider": ["geoplanet:7.3.2", "geoplanet:7.4.0", "geoplanet:7.4.1", "geoplanet:7.5.1", "geoplanet:7.5.2", "geoplanet:7.6.0", "geoplanet:7.8.1", "geoplanet:7.9.0", "geoplanet:7.10.0", "geoplanet:8.0.0", "woeplanet:8.0.0"], "meta:indexed": "2020-08-20T22:02:28.088738", "meta:updated": "2020-08-22T02:57:39.889896", "woe:hierarchy": {"continent": 24865672, "country": 23424977, "town": 0, "planet": 1, "county": 12588815, "suburb": 0, "state": 2347582, "region": 0, "localadmin": 0}, "woe:timezone_id": 56043661, "woe:hash": "9zvycwjgmjsc", "woe:centroid": [-93.090027, 44.81382], "geom:latitude": 44.81382, "geom:longitude": -93.090027, "geom:hash": "9zvycwjgmjsc", "woe:latitude": 44.81382, "geom:centroid": [-93.090027, 44.81382], "woe:longitude": -93.090027, "woe:repo": "woeplanet-poi-us"}, "geometry": {"coordinates": [-93.090027, 44.81382], "type": "Point"}}