{"type": "Feature", "id": 23675523, "geometry": {"type": "Point", "coordinates": [-92.46817, 45.484138]}, "properties": {"woe:id": 23675523, "woe:parent_id": 2358799, "woe:name": "Unity High School", "woe:placetype": 20, "woe:placetype_name": "POI", "woe:lang": "ENG", "iso:country": "US", "meta:provider": ["geoplanet:7.3.1", "geoplanet:7.3.2", "geoplanet:7.4.0", "geoplanet:7.4.1", "geoplanet:7.5.1", "geoplanet:7.5.2", "geoplanet:7.6.0", "geoplanet:7.8.1", "geoplanet:7.9.0", "geoplanet:7.10.0", "geoplanet:8.0.0", "woeplanet:8.0.0"], "meta:indexed": "2020-08-20T20:19:11.541260", "woe:alias_ENG_V": ["Unity Senior High School", "Unity High", "Unity Senior High", "Unity HS", "Unity Senior HS"], "meta:updated": "2020-10-14T11:19:37.139294", "woe:hierarchy": {"continent": 24865672, "country": 23424977, "town": 0, "planet": 1, "county": 12590582, "suburb": 0, "state": 2347608, "region": 0, "localadmin": 0}, "woe:timezone_id": 56043661, "woe:hash": "cbn4zb4sr3z5", "woe:centroid": [-92.46817, 45.484138], "geom:latitude": 45.484138, "geom:longitude": -92.46817, "geom:hash": "cbn4zb4sr3z5", "woe:latitude": 45.484138, "geom:centroid": [-92.46817, 45.484138], "woe:longitude": -92.46817, "woe:repo": "woeplanet-poi-us", "geom:area": 0.0, "woe:scale": 19}}