{"type": "Feature", "id": 23571477, "geometry": {"type": "Point", "coordinates": [-100.017593, 37.76318]}, "properties": {"woe:id": 23571477, "woe:parent_id": 2392522, "woe:name": "Dodge City High School", "woe:placetype": 20, "woe:placetype_name": "POI", "woe:lang": "ENG", "iso:country": "US", "meta:provider": ["geoplanet:7.3.1", "geoplanet:7.3.2", "geoplanet:7.4.0", "geoplanet:7.4.1", "geoplanet:7.5.1", "geoplanet:7.5.2", "geoplanet:7.6.0", "geoplanet:7.8.1", "geoplanet:7.9.0", "geoplanet:7.10.0", "geoplanet:8.0.0", "woeplanet:8.0.0"], "meta:indexed": "2020-08-20T20:18:35.936515", "woe:alias_ENG_V": ["Dodge City Senior High School", "Dodge City High", "Dodge City Senior High", "Dodge City HS", "Dodge City Senior HS"], "meta:updated": "2020-10-14T11:20:20.860474", "woe:hierarchy": {"continent": 24865672, "country": 23424977, "town": 0, "planet": 1, "county": 12588399, "suburb": 0, "state": 2347575, "region": 0, "localadmin": 0}, "woe:timezone_id": 56043661, "woe:hash": "9y8yu496mnvr", "woe:centroid": [-100.017593, 37.76318], "geom:latitude": 37.76318, "geom:longitude": -100.017593, "geom:hash": "9y8yu496mnvr", "woe:latitude": 37.76318, "geom:centroid": [-100.017593, 37.76318], "woe:longitude": -100.017593, "woe:repo": "woeplanet-poi-us", "geom:area": 0.0, "woe:scale": 19}}