{"type": "Feature", "id": 23612990, "properties": {"woe:id": 23612990, "woe:parent_id": 2482052, "woe:name": "M.s./h.s. 141 Riverdale School", "woe:placetype": 20, "woe:placetype_name": "POI", "woe:lang": "ENG", "iso:country": "US", "meta:provider": ["geoplanet:7.3.1", "geoplanet:7.3.2", "geoplanet:7.4.0", "geoplanet:7.4.1", "geoplanet:7.5.1", "geoplanet:7.5.2", "geoplanet:7.6.0", "geoplanet:7.8.1", "geoplanet:7.9.0", "geoplanet:7.10.0", "geoplanet:8.0.0", "woeplanet:8.0.0"], "meta:indexed": "2020-08-20T20:18:48.649065", "meta:updated": "2020-08-22T02:57:42.700386", "woe:hierarchy": {"continent": 24865672, "country": 23424977, "town": 0, "planet": 1, "county": 12589314, "suburb": 0, "state": 2347591, "region": 0, "localadmin": 0}, "woe:timezone_id": 56043648, "woe:hash": "dr72w53x3k05", "woe:centroid": [-73.913902, 40.88826], "geom:latitude": 40.88826, "geom:longitude": -73.913902, "geom:hash": "dr72w53x3k05", "woe:latitude": 40.88826, "geom:centroid": [-73.913902, 40.88826], "woe:longitude": -73.913902, "woe:repo": "woeplanet-poi-us"}, "geometry": {"coordinates": [-73.913902, 40.88826], "type": "Point"}}