{"type": "Feature", "id": 23602405, "geometry": {"type": "Point", "coordinates": [-112.498459, 46.000069]}, "properties": {"woe:id": 23602405, "woe:parent_id": 2372641, "woe:name": "East Middle School", "woe:placetype": 20, "woe:placetype_name": "POI", "woe:lang": "ENG", "iso:country": "US", "meta:provider": ["geoplanet:7.3.1", "geoplanet:7.3.2", "geoplanet:7.4.0", "geoplanet:7.4.1", "geoplanet:7.5.1", "geoplanet:7.5.2", "geoplanet:7.6.0", "geoplanet:7.8.1", "geoplanet:7.9.0", "geoplanet:7.10.0", "geoplanet:8.0.0", "woeplanet:8.0.0"], "meta:indexed": "2020-08-20T20:18:45.326121", "woe:alias_ENG_V": ["E Middle School"], "meta:updated": "2020-10-14T11:19:31.422151", "woe:hierarchy": {"continent": 24865672, "country": 23424977, "town": 0, "planet": 1, "county": 12589127, "suburb": 0, "state": 2347585, "region": 0, "localadmin": 0}, "woe:timezone_id": 56043665, "woe:hash": "c80j8n11gfm5", "woe:centroid": [-112.498459, 46.000069], "geom:latitude": 46.000069, "geom:longitude": -112.498459, "geom:hash": "c80j8n11gfm5", "woe:latitude": 46.000069, "geom:centroid": [-112.498459, 46.000069], "woe:longitude": -112.498459, "woe:repo": "woeplanet-poi-us", "geom:area": 0.0, "woe:scale": 19}}