{"type": "Feature", "id": 23574183, "geometry": {"type": "Point", "coordinates": [-85.680893, 38.127689]}, "properties": {"woe:id": 23574183, "woe:parent_id": 2464609, "woe:name": "Southern High School", "woe:placetype": 20, "woe:placetype_name": "POI", "woe:lang": "ENG", "iso:country": "US", "meta:provider": ["geoplanet:7.3.1", "geoplanet:7.3.2", "geoplanet:7.4.0", "geoplanet:7.4.1", "geoplanet:7.5.1", "geoplanet:7.5.2", "geoplanet:7.6.0", "geoplanet:7.8.1", "geoplanet:7.9.0", "geoplanet:7.10.0", "geoplanet:8.0.0", "woeplanet:8.0.0"], "meta:indexed": "2020-08-20T20:18:36.824604", "woe:alias_ENG_V": ["Southern Senior High School", "Southern High", "Southern Senior High", "Southern HS", "Southern Senior HS"], "meta:updated": "2020-10-14T11:20:04.255579", "woe:hierarchy": {"continent": 24865672, "country": 23424977, "town": 0, "planet": 1, "county": 12588531, "suburb": 0, "state": 2347576, "region": 0, "localadmin": 0}, "woe:timezone_id": 56043647, "woe:hash": "dng0fkcjfkrs", "woe:centroid": [-85.680893, 38.127689], "geom:latitude": 38.127689, "geom:longitude": -85.680893, "geom:hash": "dng0fkcjfkrs", "woe:latitude": 38.127689, "geom:centroid": [-85.680893, 38.127689], "woe:longitude": -85.680893, "woe:repo": "woeplanet-poi-us", "geom:area": 0.0, "woe:scale": 19}}