{"type": "Feature", "id": 24610155, "geometry": {"type": "Point", "coordinates": [-75.163643, 39.953461]}, "properties": {"woe:id": 24610155, "woe:parent_id": 29389144, "woe:name": "Elephant and Castle", "woe:placetype": 20, "woe:placetype_name": "POI", "woe:lang": "ENG", "iso:country": "US", "meta:provider": ["geoplanet:7.3.1", "geoplanet:7.3.2", "geoplanet:7.4.0", "geoplanet:7.4.1", "geoplanet:7.5.1", "geoplanet:7.5.2", "geoplanet:7.6.0", "geoplanet:7.8.1", "geoplanet:7.9.0", "geoplanet:7.10.0", "geoplanet:8.0.0", "woeplanet:8.0.0"], "meta:indexed": "2020-08-20T20:19:14.439569", "woe:alias_ENG_V": ["Elephant & Castle"], "meta:updated": "2020-10-14T11:19:54.944601", "woe:hierarchy": {"continent": 24865672, "country": 23424977, "town": 0, "planet": 1, "county": 12589778, "suburb": 0, "state": 2347597, "region": 0, "localadmin": 0}, "woe:timezone_id": 56043648, "woe:hash": "dr4e3979b0vw", "woe:centroid": [-75.163643, 39.953461], "geom:latitude": 39.953461, "geom:longitude": -75.163643, "geom:hash": "dr4e3979b0vw", "woe:latitude": 39.953461, "geom:centroid": [-75.163643, 39.953461], "woe:longitude": -75.163643, "woe:repo": "woeplanet-poi-us", "geom:area": 0.0, "woe:scale": 19}}