{"type": "Feature", "id": 23581408, "properties": {"woe:id": 23581408, "woe:parent_id": 2413251, "woe:name": "Grasonville Elementary School", "woe:placetype": 20, "woe:placetype_name": "POI", "woe:lang": "ENG", "iso:country": "US", "meta:provider": ["geoplanet:7.3.1", "geoplanet:7.3.2", "geoplanet:7.4.0", "geoplanet:7.4.1", "geoplanet:7.5.1", "geoplanet:7.5.2", "geoplanet:7.6.0", "geoplanet:7.8.1", "geoplanet:7.9.0", "geoplanet:7.10.0", "geoplanet:8.0.0", "woeplanet:8.0.0"], "meta:indexed": "2020-08-20T20:18:38.812349", "woe:alias_ENG_V": ["Grasonville Elementary"], "meta:updated": "2020-08-22T02:57:38.078213", "woe:hierarchy": {"continent": 24865672, "country": 23424977, "town": 0, "planet": 1, "county": 12588693, "suburb": 0, "state": 2347579, "region": 0, "localadmin": 0}, "woe:timezone_id": 56043648, "woe:hash": "dqcvdkg6jr5h", "woe:centroid": [-76.185493, 38.962021], "geom:latitude": 38.962021, "geom:longitude": -76.185493, "geom:hash": "dqcvdkg6jr5h", "woe:latitude": 38.962021, "geom:centroid": [-76.185493, 38.962021], "woe:longitude": -76.185493, "woe:repo": "woeplanet-poi-us"}, "geometry": {"coordinates": [-76.185493, 38.962021], "type": "Point"}}