{"type": "Feature", "id": 23547547, "geometry": {"type": "Point", "coordinates": [-81.270943, 28.778549]}, "properties": {"woe:id": 23547547, "woe:parent_id": 2488744, "woe:name": "Pine Crest Elementary School", "woe:placetype": 20, "woe:placetype_name": "POI", "woe:lang": "ENG", "iso:country": "US", "meta:provider": ["geoplanet:7.3.1", "geoplanet:7.3.2", "geoplanet:7.4.0", "geoplanet:7.4.1", "geoplanet:7.5.1", "geoplanet:7.5.2", "geoplanet:7.6.0", "geoplanet:7.8.1", "geoplanet:7.9.0", "geoplanet:7.10.0", "geoplanet:8.0.0", "woeplanet:8.0.0"], "meta:indexed": "2020-08-20T20:18:26.940685", "woe:alias_ENG_V": ["Pine Crest Elementary"], "meta:updated": "2020-10-14T11:20:21.827711", "woe:hierarchy": {"continent": 24865672, "country": 23424977, "town": 0, "planet": 1, "county": 12587859, "suburb": 0, "state": 2347568, "region": 0, "localadmin": 0}, "woe:timezone_id": 56043648, "woe:hash": "djn5wwur1y2e", "woe:centroid": [-81.270943, 28.778549], "geom:latitude": 28.778549, "geom:longitude": -81.270943, "geom:hash": "djn5wwur1y2e", "woe:latitude": 28.778549, "geom:centroid": [-81.270943, 28.778549], "woe:longitude": -81.270943, "woe:repo": "woeplanet-poi-us", "geom:area": 0.0, "woe:scale": 19}}