{"type": "Feature", "id": 56203986, "properties": {"woe:id": 56203986, "woe:parent_id": 23512060, "woe:name": "Wah Mei School", "woe:placetype": 20, "woe:placetype_name": "POI", "woe:lang": "ENG", "iso:country": "US", "meta:provider": ["geoplanet:7.6.0", "geoplanet:7.8.1", "geoplanet:7.9.0", "geoplanet:7.10.0", "geoplanet:8.0.0", "woeplanet:8.0.0"], "meta:indexed": "2020-08-21T08:24:23.642180", "meta:updated": "2020-08-22T02:58:23.941816", "woe:hierarchy": {"continent": 24865672, "country": 23424977, "town": 0, "planet": 1, "county": 12587707, "suburb": 0, "state": 2347563, "region": 0, "localadmin": 0}, "woe:timezone_id": 56043663, "woe:hash": "9q8yufqcumnh", "woe:centroid": [-122.477112, 37.761711], "geom:latitude": 37.761711, "geom:longitude": -122.477112, "geom:hash": "9q8yufqcumnh", "woe:latitude": 37.761711, "geom:centroid": [-122.477112, 37.761711], "woe:longitude": -122.477112, "woe:repo": "woeplanet-poi-us"}, "geometry": {"coordinates": [-122.477112, 37.761711], "type": "Point"}}