{"type": "Feature", "id": 23534463, "properties": {"woe:id": 23534463, "woe:parent_id": 55969303, "woe:name": "St Hedwig Elementary School", "woe:placetype": 20, "woe:placetype_name": "POI", "woe:lang": "ENG", "iso:country": "US", "meta:provider": ["geoplanet:7.3.1", "geoplanet:7.3.2", "geoplanet:7.4.0", "geoplanet:7.4.1", "geoplanet:7.5.1", "geoplanet:7.5.2", "geoplanet:7.6.0", "geoplanet:7.8.1", "geoplanet:7.9.0", "geoplanet:7.10.0", "geoplanet:8.0.0", "woeplanet:8.0.0"], "meta:indexed": "2020-08-20T20:18:22.797523", "woe:alias_ENG_V": ["St Hedwig Elementary"], "meta:updated": "2020-08-22T02:57:29.478734", "woe:hierarchy": {"continent": 24865672, "country": 23424977, "town": 0, "planet": 1, "county": 12587699, "suburb": 0, "state": 2347563, "region": 0, "localadmin": 0}, "woe:timezone_id": 56043663, "woe:hash": "9qh03224g3s3", "woe:centroid": [-118.069923, 33.795799], "geom:latitude": 33.795799, "geom:longitude": -118.069923, "geom:hash": "9qh03224g3s3", "woe:latitude": 33.795799, "geom:centroid": [-118.069923, 33.795799], "woe:longitude": -118.069923, "woe:repo": "woeplanet-poi-us"}, "geometry": {"coordinates": [-118.069923, 33.795799], "type": "Point"}}