{"type": "Feature", "id": 23536136, "properties": {"woe:id": 23536136, "woe:parent_id": 2390711, "woe:name": "Del Vallejo Middle School", "woe:placetype": 20, "woe:placetype_name": "POI", "woe:lang": "ENG", "iso:country": "US", "meta:provider": ["geoplanet:7.3.1", "geoplanet:7.3.2", "geoplanet:7.4.0", "geoplanet:7.4.1", "geoplanet:7.5.1", "geoplanet:7.5.2", "geoplanet:7.6.0", "geoplanet:7.8.1", "geoplanet:7.9.0", "geoplanet:7.10.0", "geoplanet:8.0.0", "woeplanet:8.0.0"], "meta:indexed": "2020-08-20T20:18:23.248077", "meta:updated": "2020-08-22T02:57:29.834929", "woe:hierarchy": {"continent": 24865672, "country": 23424977, "town": 0, "planet": 1, "county": 12587705, "suburb": 0, "state": 2347563, "region": 0, "localadmin": 0}, "woe:timezone_id": 56043663, "woe:hash": "9qhd7bnx0d0u", "woe:centroid": [-117.248131, 34.146721], "geom:latitude": 34.146721, "geom:longitude": -117.248131, "geom:hash": "9qhd7bnx0d0u", "woe:latitude": 34.146721, "geom:centroid": [-117.248131, 34.146721], "woe:longitude": -117.248131, "woe:repo": "woeplanet-poi-us"}, "geometry": {"coordinates": [-117.248131, 34.146721], "type": "Point"}}