{"type": "Feature", "id": 23546389, "properties": {"woe:id": 23546389, "woe:parent_id": 2517552, "woe:name": "Sherwood Elementary School", "woe:placetype": 20, "woe:placetype_name": "POI", "woe:lang": "ENG", "iso:country": "US", "meta:provider": ["geoplanet:7.3.1", "geoplanet:7.3.2", "geoplanet:7.4.0", "geoplanet:7.4.1", "geoplanet:7.5.1", "geoplanet:7.5.2", "geoplanet:7.6.0", "geoplanet:7.8.1", "geoplanet:7.9.0", "geoplanet:7.10.0", "geoplanet:8.0.0", "woeplanet:8.0.0"], "meta:indexed": "2020-08-20T20:18:26.427262", "woe:alias_ENG_V": ["Sherwood Elementary"], "meta:updated": "2020-08-22T02:57:31.761604", "woe:hierarchy": {"continent": 24865672, "country": 23424977, "town": 0, "planet": 1, "county": 12587819, "suburb": 0, "state": 2347568, "region": 0, "localadmin": 0}, "woe:timezone_id": 56043661, "woe:hash": "dj3vjsutx70v", "woe:centroid": [-87.290871, 30.43721], "geom:latitude": 30.43721, "geom:longitude": -87.290871, "geom:hash": "dj3vjsutx70v", "woe:latitude": 30.43721, "geom:centroid": [-87.290871, 30.43721], "woe:longitude": -87.290871, "woe:repo": "woeplanet-poi-us"}, "geometry": {"coordinates": [-87.290871, 30.43721], "type": "Point"}}