{"type": "Feature", "id": 23514506, "properties": {"woe:id": 23514506, "woe:parent_id": 2503709, "woe:name": "Stemley Road Elementary School", "woe:placetype": 20, "woe:placetype_name": "POI", "woe:lang": "ENG", "iso:country": "US", "meta:provider": ["geoplanet:7.3.1", "geoplanet:7.3.2", "geoplanet:7.4.0", "geoplanet:7.4.1", "geoplanet:7.5.1", "geoplanet:7.5.2", "geoplanet:7.6.0", "geoplanet:7.8.1", "geoplanet:7.9.0", "geoplanet:7.10.0", "geoplanet:8.0.0", "woeplanet:8.0.0"], "meta:indexed": "2020-08-20T20:18:17.767792", "woe:alias_ENG_V": ["Stemly Road Elementary School", "Stemley Road Elementary"], "meta:updated": "2020-08-22T02:57:26.393382", "woe:hierarchy": {"continent": 24865672, "country": 23424977, "town": 0, "planet": 1, "county": 12587547, "suburb": 0, "state": 2347559, "region": 0, "localadmin": 0}, "woe:timezone_id": 56043661, "woe:hash": "djfwxg4h72s2", "woe:centroid": [-86.140907, 33.50354], "geom:latitude": 33.50354, "geom:longitude": -86.140907, "geom:hash": "djfwxg4h72s2", "woe:latitude": 33.50354, "geom:centroid": [-86.140907, 33.50354], "woe:longitude": -86.140907, "woe:repo": "woeplanet-poi-us"}, "geometry": {"coordinates": [-86.140907, 33.50354], "type": "Point"}}