{"type": "Feature", "id": 23591121, "geometry": {"type": "Point", "coordinates": [-83.379128, 42.313042]}, "properties": {"woe:id": 23591121, "woe:parent_id": 56022156, "woe:name": "Wildwood Elementary School", "woe:placetype": 20, "woe:placetype_name": "POI", "woe:lang": "ENG", "iso:country": "US", "meta:provider": ["geoplanet:7.3.2", "geoplanet:7.4.0", "geoplanet:7.4.1", "geoplanet:7.5.1", "geoplanet:7.5.2", "geoplanet:7.6.0", "geoplanet:7.8.1", "geoplanet:7.9.0", "geoplanet:7.10.0", "geoplanet:8.0.0", "woeplanet:8.0.0"], "meta:indexed": "2020-08-20T22:02:27.219093", "woe:alias_ENG_V": ["Wildwood Elementary"], "meta:updated": "2020-10-14T11:20:12.789499", "woe:hierarchy": {"continent": 24865672, "country": 23424977, "town": 0, "planet": 1, "county": 12588795, "suburb": 0, "state": 2347581, "region": 0, "localadmin": 0}, "woe:timezone_id": 56043658, "woe:hash": "dps8wwv5m6xz", "woe:centroid": [-83.379128, 42.313042], "geom:latitude": 42.313042, "geom:longitude": -83.379128, "geom:hash": "dps8wwv5m6xz", "woe:latitude": 42.313042, "geom:centroid": [-83.379128, 42.313042], "woe:longitude": -83.379128, "woe:repo": "woeplanet-poi-us", "geom:area": 0.0, "woe:scale": 19}}