{"type": "Feature", "id": 23537235, "properties": {"woe:id": 23537235, "woe:parent_id": 55970883, "woe:name": "Webster Elementary School", "woe:placetype": 20, "woe:placetype_name": "POI", "woe:lang": "ENG", "iso:country": "US", "meta:provider": ["geoplanet:7.3.2", "geoplanet:7.4.0", "geoplanet:7.4.1", "geoplanet:7.5.1", "geoplanet:7.5.2", "geoplanet:7.6.0", "geoplanet:7.8.1", "geoplanet:7.9.0", "geoplanet:7.10.0", "geoplanet:8.0.0", "woeplanet:8.0.0"], "meta:indexed": "2020-08-20T22:02:04.941977", "woe:alias_ENG_V": ["Webster Academy for Sci & Research", "Webster Elementary"], "meta:updated": "2020-08-22T02:57:30.001452", "woe:hierarchy": {"continent": 24865672, "country": 23424977, "town": 0, "planet": 1, "county": 12587706, "suburb": 0, "state": 2347563, "region": 0, "localadmin": 0}, "woe:timezone_id": 56043663, "woe:hash": "9mudpt0pu20x", "woe:centroid": [-117.092102, 32.72411], "geom:latitude": 32.72411, "geom:longitude": -117.092102, "geom:hash": "9mudpt0pu20x", "woe:latitude": 32.72411, "geom:centroid": [-117.092102, 32.72411], "woe:longitude": -117.092102, "woe:repo": "woeplanet-poi-us"}, "geometry": {"coordinates": [-117.092102, 32.72411], "type": "Point"}}