{"type": "Feature", "id": 23665040, "geometry": {"type": "Point", "coordinates": [-78.178078, 39.2136]}, "properties": {"woe:id": 23665040, "woe:parent_id": 2502239, "woe:name": "Apple Pie Ridge Elementary School", "woe:placetype": 20, "woe:placetype_name": "POI", "woe:lang": "ENG", "iso:country": "US", "meta:provider": ["geoplanet:7.3.1", "geoplanet:7.3.2", "geoplanet:7.4.0", "geoplanet:7.4.1", "geoplanet:7.5.1", "geoplanet:7.5.2", "geoplanet:7.6.0", "geoplanet:7.8.1", "geoplanet:7.9.0", "geoplanet:7.10.0", "geoplanet:8.0.0", "woeplanet:8.0.0"], "meta:indexed": "2020-08-20T20:19:07.988932", "woe:alias_ENG_V": ["Apple Pie Ridge Elementary"], "meta:updated": "2020-10-14T11:19:39.717681", "woe:hierarchy": {"continent": 24865672, "country": 23424977, "town": 0, "planet": 1, "county": 12590351, "suburb": 0, "state": 2347605, "region": 0, "localadmin": 0}, "woe:timezone_id": 56043648, "woe:hash": "dqbrj487y8zg", "woe:centroid": [-78.178078, 39.2136], "geom:latitude": 39.2136, "geom:longitude": -78.178078, "geom:hash": "dqbrj487y8zg", "woe:latitude": 39.2136, "geom:centroid": [-78.178078, 39.2136], "woe:longitude": -78.178078, "woe:repo": "woeplanet-poi-us", "geom:area": 0.0, "woe:scale": 19}}