{"type": "Feature", "id": 23642072, "geometry": {"type": "Point", "coordinates": [-76.307167, 40.046371]}, "properties": {"woe:id": 23642072, "woe:parent_id": 2444784, "woe:name": "Owl Hill Learning Center", "woe:placetype": 20, "woe:placetype_name": "POI", "woe:lang": "ENG", "iso:country": "US", "meta:provider": ["geoplanet:7.3.2", "geoplanet:7.4.0", "geoplanet:7.4.1", "geoplanet:7.5.1", "geoplanet:7.5.2", "geoplanet:7.6.0", "geoplanet:7.8.1", "geoplanet:7.9.0", "geoplanet:7.10.0", "geoplanet:8.0.0", "woeplanet:8.0.0"], "meta:indexed": "2020-08-20T22:02:47.931183", "meta:updated": "2020-10-14T11:19:47.621654", "woe:hierarchy": {"continent": 24865672, "country": 23424977, "town": 0, "planet": 1, "county": 12589763, "suburb": 0, "state": 2347597, "region": 0, "localadmin": 0}, "woe:timezone_id": 56043648, "woe:hash": "dr1ezd4z40sk", "woe:centroid": [-76.307167, 40.046371], "geom:latitude": 40.046371, "geom:longitude": -76.307167, "geom:hash": "dr1ezd4z40sk", "woe:latitude": 40.046371, "geom:centroid": [-76.307167, 40.046371], "woe:longitude": -76.307167, "woe:repo": "woeplanet-poi-us", "geom:area": 0.0, "woe:scale": 19}}