{"type": "Feature", "id": 23631708, "geometry": {"type": "Point", "coordinates": [-82.09597, 39.959621]}, "properties": {"woe:id": 23631708, "woe:parent_id": 2455454, "woe:name": "West Muskingum High School", "woe:placetype": 20, "woe:placetype_name": "POI", "woe:lang": "ENG", "iso:country": "US", "meta:provider": ["geoplanet:7.3.2", "geoplanet:7.4.0", "geoplanet:7.4.1", "geoplanet:7.5.1", "geoplanet:7.5.2", "geoplanet:7.6.0", "geoplanet:7.8.1", "geoplanet:7.9.0", "geoplanet:7.10.0", "geoplanet:8.0.0", "woeplanet:8.0.0"], "meta:indexed": "2020-08-20T22:02:43.533491", "woe:alias_ENG_V": ["West Muskingum Senior High School", "West Muskingum High", "West Muskingum Senior High", "West Muskingum HS", "West Muskingum Senior HS", "W Muskingum High", "W Muskingum High School", "W Muskingum HS", "W Muskingum Senior High", "W Muskingum Senior High School", "W Muskingum Senior HS"], "meta:updated": "2020-10-14T11:19:45.399966", "woe:hierarchy": {"continent": 24865672, "country": 23424977, "town": 0, "planet": 1, "county": 12589586, "suburb": 0, "state": 2347594, "region": 0, "localadmin": 0}, "woe:timezone_id": 56043648, "woe:hash": "dpje7f7t9jrb", "woe:centroid": [-82.09597, 39.959621], "geom:latitude": 39.959621, "geom:longitude": -82.09597, "geom:hash": "dpje7f7t9jrb", "woe:latitude": 39.959621, "geom:centroid": [-82.09597, 39.959621], "woe:longitude": -82.09597, "woe:repo": "woeplanet-poi-us", "geom:area": 0.0, "woe:scale": 19}}