{"type": "Feature", "id": 23627959, "geometry": {"type": "Point", "coordinates": [-81.941704, 41.485062]}, "properties": {"woe:id": 23627959, "woe:parent_id": 56022552, "woe:name": "Bay High School", "woe:placetype": 20, "woe:placetype_name": "POI", "woe:lang": "ENG", "iso:country": "US", "meta:provider": ["geoplanet:7.3.1", "geoplanet:7.3.2", "geoplanet:7.4.0", "geoplanet:7.4.1", "geoplanet:7.5.1", "geoplanet:7.5.2", "geoplanet:7.6.0", "geoplanet:7.8.1", "geoplanet:7.9.0", "geoplanet:7.10.0", "geoplanet:8.0.0", "woeplanet:8.0.0"], "meta:indexed": "2020-08-20T20:18:53.478104", "woe:alias_ENG_V": ["Bay Senior High School", "Bay High", "Bay Senior High", "Bay HS", "Bay Senior HS"], "meta:updated": "2020-10-14T11:19:40.044236", "woe:hierarchy": {"continent": 24865672, "country": 23424977, "town": 0, "planet": 1, "county": 12589544, "suburb": 0, "state": 2347594, "region": 0, "localadmin": 0}, "woe:timezone_id": 56043648, "woe:hash": "dpmsp25u5bj4", "woe:centroid": [-81.941704, 41.485062], "geom:latitude": 41.485062, "geom:longitude": -81.941704, "geom:hash": "dpmsp25u5bj4", "woe:latitude": 41.485062, "geom:centroid": [-81.941704, 41.485062], "woe:longitude": -81.941704, "woe:repo": "woeplanet-poi-us", "geom:area": 0.0, "woe:scale": 19}}