{"type": "Feature", "id": 23674645, "geometry": {"type": "Point", "coordinates": [-89.320953, 43.79673]}, "properties": {"woe:id": 23674645, "woe:parent_id": 2453247, "woe:name": "Montello Junior & Senior High School", "woe:placetype": 20, "woe:placetype_name": "POI", "woe:lang": "ENG", "iso:country": "US", "meta:provider": ["geoplanet:7.3.1", "geoplanet:7.3.2", "geoplanet:7.4.0", "geoplanet:7.4.1", "geoplanet:7.5.1", "geoplanet:7.5.2", "geoplanet:7.6.0", "geoplanet:7.8.1", "geoplanet:7.9.0", "geoplanet:7.10.0", "geoplanet:8.0.0", "woeplanet:8.0.0"], "meta:indexed": "2020-08-20T20:19:11.106904", "woe:alias_ENG_V": ["Montello Junior & Senior High", "Montello Junior High School", "Montello Junior & High", "Montello Junior & Senior HS", "Montello Junior HS", "Montello Junior and Senior High", "Montello Junior and Senior Senior High", "Montello Junior and Senior Senior HS", "Montello Junior and Senior HS", "Montello Junior and Senior Senior High School", "Montello Junior and Senior High School"], "meta:updated": "2020-10-14T11:19:41.874762", "woe:hierarchy": {"continent": 24865672, "country": 23424977, "town": 0, "planet": 1, "county": 12590572, "suburb": 0, "state": 2347608, "region": 0, "localadmin": 0}, "woe:timezone_id": 56043661, "woe:hash": "dpb3pkyqqynn", "woe:centroid": [-89.320953, 43.79673], "geom:latitude": 43.79673, "geom:longitude": -89.320953, "geom:hash": "dpb3pkyqqynn", "woe:latitude": 43.79673, "geom:centroid": [-89.320953, 43.79673], "woe:longitude": -89.320953, "woe:repo": "woeplanet-poi-us", "geom:area": 0.0, "woe:scale": 19}}