{"type": "Feature", "id": 23565541, "properties": {"woe:id": 23565541, "woe:parent_id": 2441141, "woe:name": "Columbia Elementary School", "woe:placetype": 20, "woe:placetype_name": "POI", "woe:lang": "ENG", "iso:country": "US", "meta:provider": ["geoplanet:7.3.1", "geoplanet:7.3.2", "geoplanet:7.4.0", "geoplanet:7.4.1", "geoplanet:7.5.1", "geoplanet:7.5.2", "geoplanet:7.6.0", "geoplanet:7.8.1", "geoplanet:7.9.0", "geoplanet:7.10.0", "geoplanet:8.0.0", "woeplanet:8.0.0"], "meta:indexed": "2020-08-20T20:18:33.672087", "woe:alias_ENG_V": ["Columbia Elementary"], "meta:updated": "2020-08-22T02:57:35.458498", "woe:hierarchy": {"continent": 24865672, "country": 23424977, "town": 0, "planet": 1, "county": 12588188, "suburb": 0, "state": 2347573, "region": 0, "localadmin": 0}, "woe:timezone_id": 56043656, "woe:hash": "dp4xfsd01fy9", "woe:centroid": [-86.371681, 40.762039], "geom:latitude": 40.762039, "geom:longitude": -86.371681, "geom:hash": "dp4xfsd01fy9", "woe:latitude": 40.762039, "geom:centroid": [-86.371681, 40.762039], "woe:longitude": -86.371681, "woe:repo": "woeplanet-poi-us"}, "geometry": {"coordinates": [-86.371681, 40.762039], "type": "Point"}}