{"type": "Feature", "id": 23584554, "properties": {"woe:id": 23584554, "woe:parent_id": 2456968, "woe:name": "Nantucket Elementary School", "woe:placetype": 20, "woe:placetype_name": "POI", "woe:lang": "ENG", "iso:country": "US", "meta:provider": ["geoplanet:7.3.2", "geoplanet:7.4.0", "geoplanet:7.4.1", "geoplanet:7.5.1", "geoplanet:7.5.2", "geoplanet:7.6.0", "geoplanet:7.8.1", "geoplanet:7.9.0", "geoplanet:7.10.0", "geoplanet:8.0.0", "woeplanet:8.0.0"], "meta:indexed": "2020-08-20T22:02:24.363687", "woe:alias_ENG_V": ["Nantucket Elementary"], "meta:updated": "2020-08-22T02:57:38.455622", "woe:hierarchy": {"continent": 24865672, "country": 23424977, "town": 0, "planet": 1, "county": 12588709, "suburb": 0, "state": 2347580, "region": 0, "localadmin": 0}, "woe:timezone_id": 56043648, "woe:hash": "drq4ubftpxuu", "woe:centroid": [-70.099998, 41.269669], "geom:latitude": 41.269669, "geom:longitude": -70.099998, "geom:hash": "drq4ubftpxuu", "woe:latitude": 41.269669, "geom:centroid": [-70.099998, 41.269669], "woe:longitude": -70.099998, "woe:repo": "woeplanet-poi-us"}, "geometry": {"coordinates": [-70.099998, 41.269669], "type": "Point"}}