{"type": "Feature", "id": 23579581, "geometry": {"type": "Point", "coordinates": [-76.712448, 39.25547]}, "properties": {"woe:id": 23579581, "woe:parent_id": 2386336, "woe:name": "University of Maryland College Park", "woe:placetype": 20, "woe:placetype_name": "POI", "woe:lang": "ENG", "iso:country": "US", "meta:provider": ["geoplanet:7.3.1", "geoplanet:7.3.2", "geoplanet:7.4.0", "geoplanet:7.4.1", "geoplanet:7.5.1", "geoplanet:7.5.2", "geoplanet:7.6.0", "geoplanet:7.8.1", "geoplanet:7.9.0", "geoplanet:7.10.0", "geoplanet:8.0.0", "woeplanet:8.0.0"], "meta:indexed": "2020-08-20T20:18:38.393225", "meta:updated": "2020-10-14T11:20:23.883997", "woe:hierarchy": {"continent": 24865672, "country": 23424977, "town": 0, "planet": 1, "county": 12588678, "suburb": 0, "state": 2347579, "region": 0, "localadmin": 0}, "woe:timezone_id": 56043648, "woe:hash": "dqcrq65xwmuz", "woe:centroid": [-76.712448, 39.25547], "geom:latitude": 39.25547, "geom:longitude": -76.712448, "geom:hash": "dqcrq65xwmuz", "woe:latitude": 39.25547, "geom:centroid": [-76.712448, 39.25547], "woe:longitude": -76.712448, "woe:repo": "woeplanet-poi-us", "geom:area": 0.0, "woe:scale": 19}}