{"type": "Feature", "id": 23521387, "geometry": {"type": "Point", "coordinates": [-119.70327, 36.815731]}, "properties": {"woe:id": 23521387, "woe:parent_id": 2382067, "woe:name": "Sierra Vista Elementary School", "woe:placetype": 20, "woe:placetype_name": "POI", "woe:lang": "ENG", "iso:country": "US", "meta:provider": ["geoplanet:7.3.2", "geoplanet:7.4.0", "geoplanet:7.4.1", "geoplanet:7.5.1", "geoplanet:7.5.2", "geoplanet:7.6.0", "geoplanet:7.8.1", "geoplanet:7.9.0", "geoplanet:7.10.0", "geoplanet:8.0.0", "woeplanet:8.0.0"], "meta:indexed": "2020-08-20T22:01:58.574330", "woe:alias_ENG_V": ["Sierra Vista Elementary"], "meta:updated": "2020-10-14T11:20:12.986263", "woe:hierarchy": {"continent": 24865672, "country": 23424977, "town": 0, "planet": 1, "county": 12587679, "suburb": 0, "state": 2347563, "region": 0, "localadmin": 0}, "woe:timezone_id": 56043663, "woe:hash": "9qdckn4eptst", "woe:centroid": [-119.70327, 36.815731], "geom:latitude": 36.815731, "geom:longitude": -119.70327, "geom:hash": "9qdckn4eptst", "woe:latitude": 36.815731, "geom:centroid": [-119.70327, 36.815731], "woe:longitude": -119.70327, "woe:repo": "woeplanet-poi-us", "geom:area": 0.0, "woe:scale": 19}}