{"type": "Feature", "id": 56053142, "geometry": {"type": "Point", "coordinates": [-71.250458, 42.779419]}, "properties": {"woe:id": 56053142, "woe:parent_id": 2487373, "woe:name": "Hesser College-Salem", "woe:placetype": 20, "woe:placetype_name": "POI", "woe:lang": "ENG", "iso:country": "US", "meta:provider": ["geoplanet:7.3.1", "geoplanet:7.3.2", "geoplanet:7.4.0", "geoplanet:7.4.1", "geoplanet:7.5.1", "geoplanet:7.5.2", "geoplanet:7.6.0", "geoplanet:7.8.1", "geoplanet:7.9.0", "geoplanet:7.10.0", "geoplanet:8.0.0", "woeplanet:8.0.0"], "meta:indexed": "2020-08-20T20:19:16.810042", "meta:updated": "2020-10-14T11:19:56.127763", "woe:hierarchy": {"continent": 24865672, "country": 23424977, "town": 0, "planet": 1, "county": 12589255, "suburb": 0, "state": 2347588, "region": 0, "localadmin": 0}, "woe:timezone_id": 56043648, "woe:hash": "drt76eubpvxy", "woe:centroid": [-71.250458, 42.779419], "geom:latitude": 42.779419, "geom:longitude": -71.250458, "geom:hash": "drt76eubpvxy", "woe:latitude": 42.779419, "geom:centroid": [-71.250458, 42.779419], "woe:longitude": -71.250458, "woe:repo": "woeplanet-poi-us", "geom:area": 0.0, "woe:scale": 19}}