{"type": "Feature", "id": 23685030, "properties": {"woe:id": 23685030, "woe:parent_id": 2405575, "woe:name": "Hickory Point Mall General Ofc", "woe:placetype": 20, "woe:placetype_name": "POI", "woe:lang": "ENG", "iso:country": "US", "meta:provider": ["geoplanet:7.3.1", "geoplanet:7.3.2", "geoplanet:7.4.0", "geoplanet:7.4.1", "geoplanet:7.5.1", "geoplanet:7.5.2", "geoplanet:7.6.0", "geoplanet:7.8.1", "geoplanet:7.9.0", "geoplanet:7.10.0", "geoplanet:8.0.0", "woeplanet:8.0.0"], "meta:indexed": "2020-08-20T20:19:13.387806", "meta:updated": "2020-08-22T02:58:19.007847", "woe:hierarchy": {"continent": 24865672, "country": 23424977, "town": 0, "planet": 1, "county": 12588132, "suburb": 0, "state": 2347572, "region": 0, "localadmin": 0}, "woe:timezone_id": 56043661, "woe:hash": "dp0epeftjxjy", "woe:centroid": [-88.963608, 39.92384], "geom:latitude": 39.92384, "geom:longitude": -88.963608, "geom:hash": "dp0epeftjxjy", "woe:latitude": 39.92384, "geom:centroid": [-88.963608, 39.92384], "woe:longitude": -88.963608, "woe:repo": "woeplanet-poi-us"}, "geometry": {"coordinates": [-88.963608, 39.92384], "type": "Point"}}