{"type": "Feature", "id": 23568358, "geometry": {"type": "Point", "coordinates": [-84.9216, 39.635471]}, "properties": {"woe:id": 23568358, "woe:parent_id": 2438940, "woe:name": "Union County High School", "woe:placetype": 20, "woe:placetype_name": "POI", "woe:lang": "ENG", "iso:country": "US", "meta:provider": ["geoplanet:7.3.1", "geoplanet:7.3.2", "geoplanet:7.4.0", "geoplanet:7.4.1", "geoplanet:7.5.1", "geoplanet:7.5.2", "geoplanet:7.6.0", "geoplanet:7.8.1", "geoplanet:7.9.0", "geoplanet:7.10.0", "geoplanet:8.0.0", "woeplanet:8.0.0"], "meta:indexed": "2020-08-20T20:18:34.765123", "woe:alias_ENG_V": ["Union County Senior High School", "Union County High", "Union County Senior High", "Union County HS", "Union County Senior HS"], "meta:updated": "2020-10-14T11:20:09.435173", "woe:hierarchy": {"continent": 24865672, "country": 23424977, "town": 0, "planet": 1, "county": 12588260, "suburb": 0, "state": 2347573, "region": 0, "localadmin": 0}, "woe:timezone_id": 56043656, "woe:hash": "dp597x3vr736", "woe:centroid": [-84.9216, 39.635471], "geom:latitude": 39.635471, "geom:longitude": -84.9216, "geom:hash": "dp597x3vr736", "woe:latitude": 39.635471, "geom:centroid": [-84.9216, 39.635471], "woe:longitude": -84.9216, "woe:repo": "woeplanet-poi-us", "geom:area": 0.0, "woe:scale": 19}}