{"type": "Feature", "id": 23530305, "properties": {"woe:id": 23530305, "woe:parent_id": 55969569, "woe:name": "Cedargrove Elementary School", "woe:placetype": 20, "woe:placetype_name": "POI", "woe:lang": "ENG", "iso:country": "US", "meta:provider": ["geoplanet:7.4.0", "geoplanet:7.4.1", "geoplanet:7.5.1", "geoplanet:7.5.2", "geoplanet:7.6.0", "geoplanet:7.8.1", "geoplanet:7.9.0", "geoplanet:7.10.0", "geoplanet:8.0.0", "woeplanet:8.0.0"], "meta:indexed": "2020-08-20T23:54:30.394216", "woe:alias_ENG_V": ["Cedargrove Elementary"], "meta:updated": "2020-08-22T02:57:28.586075", "woe:hierarchy": {"continent": 24865672, "country": 23424977, "town": 0, "planet": 1, "county": 12587688, "suburb": 0, "state": 2347563, "region": 0, "localadmin": 0}, "woe:timezone_id": 56043663, "woe:hash": "9qh4jbq1n8dv", "woe:centroid": [-117.863792, 34.103111], "geom:latitude": 34.103111, "geom:longitude": -117.863792, "geom:hash": "9qh4jbq1n8dv", "woe:latitude": 34.103111, "geom:centroid": [-117.863792, 34.103111], "woe:longitude": -117.863792, "woe:repo": "woeplanet-poi-us"}, "geometry": {"coordinates": [-117.863792, 34.103111], "type": "Point"}}