{"type": "Feature", "id": 23671803, "geometry": {"type": "Point", "coordinates": [-120.009911, 46.330978]}, "properties": {"woe:id": 23671803, "woe:parent_id": 2502246, "woe:name": "Sunnyside Christian Elementary School", "woe:placetype": 20, "woe:placetype_name": "POI", "woe:lang": "ENG", "iso:country": "US", "meta:provider": ["geoplanet:7.3.1", "geoplanet:7.3.2", "geoplanet:7.4.0", "geoplanet:7.4.1", "geoplanet:7.5.1", "geoplanet:7.5.2", "geoplanet:7.6.0", "geoplanet:7.8.1", "geoplanet:7.9.0", "geoplanet:7.10.0", "geoplanet:8.0.0", "woeplanet:8.0.0"], "meta:indexed": "2020-08-20T20:19:09.983704", "woe:alias_ENG_V": ["Sunnyside Christian Elem School", "Sunnyside Christian Elementary"], "meta:updated": "2020-10-14T11:19:53.371167", "woe:hierarchy": {"continent": 24865672, "country": 23424977, "town": 0, "planet": 1, "county": 12590478, "suburb": 0, "state": 2347606, "region": 0, "localadmin": 0}, "woe:timezone_id": 56043663, "woe:hash": "c24xt473w2k3", "woe:centroid": [-120.009911, 46.330978], "geom:latitude": 46.330978, "geom:longitude": -120.009911, "geom:hash": "c24xt473w2k3", "woe:latitude": 46.330978, "geom:centroid": [-120.009911, 46.330978], "woe:longitude": -120.009911, "woe:repo": "woeplanet-poi-us", "geom:area": 0.0, "woe:scale": 19}}