{"type": "Feature", "id": 56053742, "properties": {"woe:id": 56053742, "woe:parent_id": 2354569, "woe:name": "Anderson University", "woe:placetype": 20, "woe:placetype_name": "POI", "woe:lang": "ENG", "iso:country": "US", "meta:provider": ["geoplanet:7.3.1", "geoplanet:7.3.2", "geoplanet:7.4.0", "geoplanet:7.4.1", "geoplanet:7.5.1", "geoplanet:7.5.2", "geoplanet:7.6.0", "geoplanet:7.8.1", "geoplanet:7.9.0", "geoplanet:7.10.0", "geoplanet:8.0.0", "woeplanet:8.0.0"], "meta:indexed": "2020-08-20T20:19:17.284340", "meta:updated": "2020-08-22T02:58:20.991616", "woe:hierarchy": {"continent": 24865672, "country": 23424977, "town": 0, "planet": 1, "county": 12589803, "suburb": 0, "state": 2347599, "region": 0, "localadmin": 0}, "woe:timezone_id": 56043648, "woe:hash": "dnjhrdbbkk08", "woe:centroid": [-82.637947, 34.512241], "geom:latitude": 34.512241, "geom:longitude": -82.637947, "geom:hash": "dnjhrdbbkk08", "woe:latitude": 34.512241, "geom:centroid": [-82.637947, 34.512241], "woe:longitude": -82.637947, "woe:repo": "woeplanet-poi-us"}, "geometry": {"coordinates": [-82.637947, 34.512241], "type": "Point"}}