{"type": "Feature", "id": 23605408, "geometry": {"type": "Point", "coordinates": [-71.479568, 43.45322]}, "properties": {"woe:id": 23605408, "woe:parent_id": 2362233, "woe:name": "Belmont High School", "woe:placetype": 20, "woe:placetype_name": "POI", "woe:lang": "ENG", "iso:country": "US", "meta:provider": ["geoplanet:7.3.1", "geoplanet:7.3.2", "geoplanet:7.4.0", "geoplanet:7.4.1", "geoplanet:7.5.1", "geoplanet:7.5.2", "geoplanet:7.6.0", "geoplanet:7.8.1", "geoplanet:7.9.0", "geoplanet:7.10.0", "geoplanet:8.0.0", "woeplanet:8.0.0"], "meta:indexed": "2020-08-20T20:18:46.228615", "woe:alias_ENG_V": ["Belmont Senior High School", "Belmont High", "Belmont Senior High", "Belmont HS", "Belmont Senior HS"], "meta:updated": "2020-10-14T11:19:26.767391", "woe:hierarchy": {"continent": 24865672, "country": 23424977, "town": 0, "planet": 1, "county": 12589248, "suburb": 0, "state": 2347588, "region": 0, "localadmin": 0}, "woe:timezone_id": 56043648, "woe:hash": "drtpjqqjm771", "woe:centroid": [-71.479568, 43.45322], "geom:latitude": 43.45322, "geom:longitude": -71.479568, "geom:hash": "drtpjqqjm771", "woe:latitude": 43.45322, "geom:centroid": [-71.479568, 43.45322], "woe:longitude": -71.479568, "woe:repo": "woeplanet-poi-us", "geom:area": 0.0, "woe:scale": 19}}