{"type": "Feature", "id": 23594698, "properties": {"woe:id": 23594698, "woe:parent_id": 2379943, "woe:name": "Vaughan Elementary School", "woe:placetype": 20, "woe:placetype_name": "POI", "woe:lang": "ENG", "iso:country": "US", "meta:provider": ["geoplanet:7.3.1", "geoplanet:7.3.2", "geoplanet:7.4.0", "geoplanet:7.4.1", "geoplanet:7.5.1", "geoplanet:7.5.2", "geoplanet:7.6.0", "geoplanet:7.8.1", "geoplanet:7.9.0", "geoplanet:7.10.0", "geoplanet:8.0.0", "woeplanet:8.0.0"], "meta:indexed": "2020-08-20T20:18:42.956614", "woe:alias_ENG_V": ["Vaughan-Steffensrud Elem. School", "Vaughan Elementary"], "meta:updated": "2020-08-22T02:57:40.195236", "woe:hierarchy": {"continent": 24865672, "country": 23424977, "town": 0, "planet": 1, "county": 12588868, "suburb": 0, "state": 2347582, "region": 0, "localadmin": 0}, "woe:timezone_id": 56043661, "woe:hash": "cbmynwdx6rxw", "woe:centroid": [-92.874878, 47.497929], "geom:latitude": 47.497929, "geom:longitude": -92.874878, "geom:hash": "cbmynwdx6rxw", "woe:latitude": 47.497929, "geom:centroid": [-92.874878, 47.497929], "woe:longitude": -92.874878, "woe:repo": "woeplanet-poi-us"}, "geometry": {"coordinates": [-92.874878, 47.497929], "type": "Point"}}