{"type": "Feature", "id": 23631660, "geometry": {"type": "Point", "coordinates": [-81.665993, 39.629391]}, "properties": {"woe:id": 23631660, "woe:parent_id": 2415919, "woe:name": "Center Elementary School", "woe:placetype": 20, "woe:placetype_name": "POI", "woe:lang": "ENG", "iso:country": "US", "meta:provider": ["geoplanet:7.3.1", "geoplanet:7.3.2", "geoplanet:7.4.0", "geoplanet:7.4.1", "geoplanet:7.5.1", "geoplanet:7.5.2", "geoplanet:7.6.0", "geoplanet:7.8.1", "geoplanet:7.9.0", "geoplanet:7.10.0", "geoplanet:8.0.0", "woeplanet:8.0.0"], "meta:indexed": "2020-08-20T20:18:55.255614", "woe:alias_ENG_V": ["Center Elementary"], "meta:updated": "2020-10-14T11:19:41.747454", "woe:hierarchy": {"continent": 24865672, "country": 23424977, "town": 0, "planet": 1, "county": 12589584, "suburb": 0, "state": 2347594, "region": 0, "localadmin": 0}, "woe:timezone_id": 56043648, "woe:hash": "dpjcmwk9umyj", "woe:centroid": [-81.665993, 39.629391], "geom:latitude": 39.629391, "geom:longitude": -81.665993, "geom:hash": "dpjcmwk9umyj", "woe:latitude": 39.629391, "geom:centroid": [-81.665993, 39.629391], "woe:longitude": -81.665993, "woe:repo": "woeplanet-poi-us", "geom:area": 0.0, "woe:scale": 19}}