{"type": "Feature", "id": 23591431, "geometry": {"type": "Point", "coordinates": [-82.955902, 42.416088]}, "properties": {"woe:id": 23591431, "woe:parent_id": 29229839, "woe:name": "Wayne Elementary School", "woe:placetype": 20, "woe:placetype_name": "POI", "woe:lang": "ENG", "iso:country": "US", "meta:provider": ["geoplanet:7.3.1", "geoplanet:7.3.2", "geoplanet:7.4.0", "geoplanet:7.4.1", "geoplanet:7.5.1", "geoplanet:7.5.2", "geoplanet:7.6.0", "geoplanet:7.8.1", "geoplanet:7.9.0", "geoplanet:7.10.0", "geoplanet:8.0.0", "woeplanet:8.0.0"], "meta:indexed": "2020-08-20T20:18:41.729344", "woe:alias_ENG_V": ["Wayne Elementary"], "meta:updated": "2020-10-14T11:20:21.607269", "woe:hierarchy": {"continent": 24865672, "country": 23424977, "town": 0, "planet": 1, "county": 12588795, "suburb": 0, "state": 2347581, "region": 0, "localadmin": 0}, "woe:timezone_id": 56043658, "woe:hash": "dpt12397e7uh", "woe:centroid": [-82.955902, 42.416088], "geom:latitude": 42.416088, "geom:longitude": -82.955902, "geom:hash": "dpt12397e7uh", "woe:latitude": 42.416088, "geom:centroid": [-82.955902, 42.416088], "woe:longitude": -82.955902, "woe:repo": "woeplanet-poi-us", "geom:area": 0.0, "woe:scale": 19}}