{"type": "Feature", "id": 23595191, "properties": {"woe:id": 23595191, "woe:parent_id": 2522948, "woe:name": "Middleton Elementary School", "woe:placetype": 20, "woe:placetype_name": "POI", "woe:lang": "ENG", "iso:country": "US", "meta:provider": ["geoplanet:7.3.1", "geoplanet:7.3.2", "geoplanet:7.4.0", "geoplanet:7.4.1", "geoplanet:7.5.1", "geoplanet:7.5.2", "geoplanet:7.6.0", "geoplanet:7.8.1", "geoplanet:7.9.0", "geoplanet:7.10.0", "geoplanet:8.0.0", "woeplanet:8.0.0"], "meta:indexed": "2020-08-20T20:18:43.128527", "woe:alias_ENG_V": ["Middleton Elementary"], "meta:updated": "2020-08-22T02:57:40.275566", "woe:hierarchy": {"continent": 24865672, "country": 23424977, "town": 0, "planet": 1, "county": 12588878, "suburb": 0, "state": 2347582, "region": 0, "localadmin": 0}, "woe:timezone_id": 56043661, "woe:hash": "9zvzmqzb7hbs", "woe:centroid": [-92.922577, 44.905312], "geom:latitude": 44.905312, "geom:longitude": -92.922577, "geom:hash": "9zvzmqzb7hbs", "woe:latitude": 44.905312, "geom:centroid": [-92.922577, 44.905312], "woe:longitude": -92.922577, "woe:repo": "woeplanet-poi-us"}, "geometry": {"coordinates": [-92.922577, 44.905312], "type": "Point"}}