{"type": "Feature", "id": 23568708, "properties": {"woe:id": 23568708, "woe:parent_id": 2380311, "woe:name": "Churubusco High School", "woe:placetype": 20, "woe:placetype_name": "POI", "woe:lang": "ENG", "iso:country": "US", "meta:provider": ["geoplanet:7.3.1", "geoplanet:7.3.2", "geoplanet:7.4.0", "geoplanet:7.4.1", "geoplanet:7.5.1", "geoplanet:7.5.2", "geoplanet:7.6.0", "geoplanet:7.8.1", "geoplanet:7.9.0", "geoplanet:7.10.0", "geoplanet:8.0.0", "woeplanet:8.0.0"], "meta:indexed": "2020-08-20T20:18:34.893804", "woe:alias_ENG_V": ["Churubusco Senior High School", "Churubusco High", "Churubusco Senior High", "Churubusco HS", "Churubusco Senior HS"], "meta:updated": "2020-08-22T02:58:47.286756", "woe:hierarchy": {"continent": 24865672, "country": 23424977, "town": 0, "planet": 1, "county": 12588271, "suburb": 0, "state": 2347573, "region": 0, "localadmin": 0}, "woe:timezone_id": 56043656, "woe:hash": "dp76d3we7cvm", "woe:centroid": [-85.321716, 41.229511], "geom:latitude": 41.229511, "geom:longitude": -85.321716, "geom:hash": "dp76d3we7cvm", "woe:latitude": 41.229511, "geom:centroid": [-85.321716, 41.229511], "woe:longitude": -85.321716, "woe:repo": "woeplanet-poi-us"}, "geometry": {"coordinates": [-85.321716, 41.229511], "type": "Point"}}