{"type": "Feature", "id": 23524270, "geometry": {"type": "Point", "coordinates": [-121.392097, 38.60569]}, "properties": {"woe:id": 23524270, "woe:parent_id": 55969083, "woe:name": "Cottage Elementary School", "woe:placetype": 20, "woe:placetype_name": "POI", "woe:lang": "ENG", "iso:country": "US", "meta:provider": ["geoplanet:7.3.2", "geoplanet:7.4.0", "geoplanet:7.4.1", "geoplanet:7.5.1", "geoplanet:7.5.2", "geoplanet:7.6.0", "geoplanet:7.8.1", "geoplanet:7.9.0", "geoplanet:7.10.0", "geoplanet:8.0.0", "woeplanet:8.0.0"], "meta:indexed": "2020-08-20T22:01:59.493459", "woe:alias_ENG_V": ["Cottage Elementary"], "meta:updated": "2020-10-14T11:20:06.785826", "woe:hierarchy": {"continent": 24865672, "country": 23424977, "town": 0, "planet": 1, "county": 12587703, "suburb": 0, "state": 2347563, "region": 0, "localadmin": 0}, "woe:timezone_id": 56043663, "woe:hash": "9qceteuyrn5z", "woe:centroid": [-121.392097, 38.60569], "geom:latitude": 38.60569, "geom:longitude": -121.392097, "geom:hash": "9qceteuyrn5z", "woe:latitude": 38.60569, "geom:centroid": [-121.392097, 38.60569], "woe:longitude": -121.392097, "woe:repo": "woeplanet-poi-us", "geom:area": 0.0, "woe:scale": 19}}