{"type": "Feature", "id": 23552938, "geometry": {"type": "Point", "coordinates": [-84.342133, 34.040878]}, "properties": {"woe:id": 23552938, "woe:parent_id": 2485064, "woe:name": "Roswell Postal Store Station", "woe:placetype": 20, "woe:placetype_name": "POI", "woe:lang": "ENG", "iso:country": "US", "meta:provider": ["geoplanet:7.3.1", "geoplanet:7.3.2", "geoplanet:7.4.0", "geoplanet:7.4.1", "geoplanet:7.5.1", "geoplanet:7.5.2", "geoplanet:7.6.0", "geoplanet:7.8.1", "geoplanet:7.9.0", "geoplanet:7.10.0", "geoplanet:8.0.0", "woeplanet:8.0.0"], "meta:indexed": "2020-08-20T20:18:29.457153", "meta:updated": "2020-10-14T11:20:25.718174", "woe:hierarchy": {"continent": 24865672, "country": 23424977, "town": 0, "planet": 1, "county": 12587929, "suburb": 0, "state": 2347569, "region": 0, "localadmin": 0}, "woe:timezone_id": 56043648, "woe:hash": "dnh18szymze6", "woe:centroid": [-84.342133, 34.040878], "geom:latitude": 34.040878, "geom:longitude": -84.342133, "geom:hash": "dnh18szymze6", "woe:latitude": 34.040878, "geom:centroid": [-84.342133, 34.040878], "woe:longitude": -84.342133, "woe:repo": "woeplanet-poi-us", "geom:area": 0.0, "woe:scale": 19}}