{"type": "Feature", "id": 23543124, "geometry": {"type": "Point", "coordinates": [-72.69738, 41.784611]}, "properties": {"woe:id": 23543124, "woe:parent_id": 55859601, "woe:name": "Fox Middle School", "woe:placetype": 20, "woe:placetype_name": "POI", "woe:lang": "ENG", "iso:country": "US", "meta:provider": ["geoplanet:7.3.1", "geoplanet:7.3.2", "geoplanet:7.4.0", "geoplanet:7.4.1", "geoplanet:7.5.1", "geoplanet:7.5.2", "geoplanet:7.6.0", "geoplanet:7.8.1", "geoplanet:7.9.0", "geoplanet:7.10.0", "geoplanet:8.0.0", "woeplanet:8.0.0"], "meta:indexed": "2020-08-20T20:18:25.137877", "meta:updated": "2020-10-14T11:20:04.527249", "woe:alias_ENG_V": ["Lewis Fox Middle School"], "woe:hierarchy": {"continent": 24865672, "country": 23424977, "town": 0, "planet": 1, "county": 12587792, "suburb": 0, "state": 2347565, "region": 0, "localadmin": 0}, "woe:timezone_id": 56043648, "woe:hash": "drkm9wxmh209", "woe:centroid": [-72.69738, 41.784611], "geom:latitude": 41.784611, "geom:longitude": -72.69738, "geom:hash": "drkm9wxmh209", "woe:latitude": 41.784611, "geom:centroid": [-72.69738, 41.784611], "woe:longitude": -72.69738, "woe:repo": "woeplanet-poi-us", "geom:area": 0.0, "woe:scale": 19}}