{"type": "Feature", "id": 23685364, "geometry": {"type": "Point", "coordinates": [-117.941544, 33.83836]}, "properties": {"woe:id": 23685364, "woe:parent_id": 2516615, "woe:name": "Anaheim Plaza Mall", "woe:placetype": 20, "woe:placetype_name": "POI", "woe:lang": "ENG", "iso:country": "US", "meta:provider": ["geoplanet:7.3.1", "geoplanet:7.3.2", "geoplanet:7.4.0", "geoplanet:7.4.1", "geoplanet:7.5.1", "geoplanet:7.5.2", "geoplanet:7.6.0", "geoplanet:7.8.1", "geoplanet:7.9.0", "geoplanet:7.10.0", "geoplanet:8.0.0", "woeplanet:8.0.0"], "meta:indexed": "2020-08-20T20:19:13.641414", "meta:updated": "2020-10-14T11:19:50.486510", "woe:alias_ENG_V": ["Anaheim Plaza"], "woe:hierarchy": {"continent": 24865672, "country": 23424977, "town": 0, "planet": 1, "county": 12587699, "suburb": 0, "state": 2347563, "region": 0, "localadmin": 0}, "woe:timezone_id": 56043663, "woe:hash": "9qh0s0jddz6x", "woe:centroid": [-117.941544, 33.83836], "geom:latitude": 33.83836, "geom:longitude": -117.941544, "geom:hash": "9qh0s0jddz6x", "woe:latitude": 33.83836, "geom:centroid": [-117.941544, 33.83836], "woe:longitude": -117.941544, "woe:repo": "woeplanet-poi-us", "geom:area": 0.0, "woe:scale": 19}}