{"type": "Feature", "id": 23672528, "properties": {"woe:id": 23672528, "woe:parent_id": 2518975, "woe:name": "Triadelphia Middle School", "woe:placetype": 20, "woe:placetype_name": "POI", "woe:lang": "ENG", "iso:country": "US", "meta:provider": ["geoplanet:7.3.1", "geoplanet:7.3.2", "geoplanet:7.4.0", "geoplanet:7.4.1", "geoplanet:7.5.1", "geoplanet:7.5.2", "geoplanet:7.6.0", "geoplanet:7.8.1", "geoplanet:7.9.0", "geoplanet:7.10.0", "geoplanet:8.0.0", "woeplanet:8.0.0"], "meta:indexed": "2020-08-20T20:19:10.218640", "meta:updated": "2020-08-22T02:58:17.515441", "woe:hierarchy": {"continent": 24865672, "country": 23424977, "town": 0, "planet": 1, "county": 12590513, "suburb": 0, "state": 2347607, "region": 0, "localadmin": 0}, "woe:timezone_id": 56043648, "woe:hash": "dpneuhx5uzr6", "woe:centroid": [-80.673767, 40.059582], "geom:latitude": 40.059582, "geom:longitude": -80.673767, "geom:hash": "dpneuhx5uzr6", "woe:latitude": 40.059582, "geom:centroid": [-80.673767, 40.059582], "woe:longitude": -80.673767, "woe:repo": "woeplanet-poi-us"}, "geometry": {"coordinates": [-80.673767, 40.059582], "type": "Point"}}