{"type": "Feature", "id": 23535187, "properties": {"woe:id": 23535187, "woe:parent_id": 2399771, "woe:name": "Rubidoux High School", "woe:placetype": 20, "woe:placetype_name": "POI", "woe:lang": "ENG", "iso:country": "US", "meta:provider": ["geoplanet:7.3.2", "geoplanet:7.4.0", "geoplanet:7.4.1", "geoplanet:7.5.1", "geoplanet:7.5.2", "geoplanet:7.6.0", "geoplanet:7.8.1", "geoplanet:7.9.0", "geoplanet:7.10.0", "geoplanet:8.0.0", "woeplanet:8.0.0"], "meta:indexed": "2020-08-20T22:02:04.109226", "woe:alias_ENG_V": ["Rubidoux Senior High School", "Rubidoux High", "Rubidoux Senior High", "Rubidoux HS", "Rubidoux Senior HS"], "meta:updated": "2020-08-22T02:58:46.451047", "woe:hierarchy": {"continent": 24865672, "country": 23424977, "town": 0, "planet": 1, "county": 12587702, "suburb": 0, "state": 2347563, "region": 0, "localadmin": 0}, "woe:timezone_id": 56043663, "woe:hash": "9qh3rv5zurq4", "woe:centroid": [-117.427521, 33.998562], "geom:latitude": 33.998562, "geom:longitude": -117.427521, "geom:hash": "9qh3rv5zurq4", "woe:latitude": 33.998562, "geom:centroid": [-117.427521, 33.998562], "woe:longitude": -117.427521, "woe:repo": "woeplanet-poi-us"}, "geometry": {"coordinates": [-117.427521, 33.998562], "type": "Point"}}