{"type": "Feature", "id": 23615967, "geometry": {"type": "Point", "coordinates": [-77.94529, 43.207481]}, "properties": {"woe:id": 23615967, "woe:parent_id": 55864829, "woe:name": "A.d. Oliver Middle School", "woe:placetype": 20, "woe:placetype_name": "POI", "woe:lang": "ENG", "iso:country": "US", "meta:provider": ["geoplanet:7.3.1", "geoplanet:7.3.2", "geoplanet:7.4.0", "geoplanet:7.4.1", "geoplanet:7.5.1", "geoplanet:7.5.2", "geoplanet:7.6.0", "geoplanet:7.8.1", "geoplanet:7.9.0", "geoplanet:7.10.0", "geoplanet:8.0.0", "woeplanet:8.0.0"], "meta:indexed": "2020-08-20T20:18:49.765911", "meta:updated": "2020-10-14T11:19:27.367993", "woe:hierarchy": {"continent": 24865672, "country": 23424977, "town": 0, "planet": 1, "county": 12589339, "suburb": 0, "state": 2347591, "region": 0, "localadmin": 0}, "woe:timezone_id": 56043648, "woe:hash": "dr8tf39vz45r", "woe:centroid": [-77.94529, 43.207481], "geom:latitude": 43.207481, "geom:longitude": -77.94529, "geom:hash": "dr8tf39vz45r", "woe:latitude": 43.207481, "geom:centroid": [-77.94529, 43.207481], "woe:longitude": -77.94529, "woe:repo": "woeplanet-poi-us", "geom:area": 0.0, "woe:scale": 19}}