{"type": "Feature", "id": 23680984, "properties": {"woe:id": 23680984, "woe:parent_id": 2483292, "woe:name": "Rockdale Station", "woe:placetype": 20, "woe:placetype_name": "POI", "woe:lang": "ENG", "iso:country": "US", "meta:provider": ["geoplanet:7.3.1", "geoplanet:7.3.2", "geoplanet:7.4.0", "geoplanet:7.4.1", "geoplanet:7.5.1", "geoplanet:7.5.2", "geoplanet:7.6.0", "geoplanet:7.8.1", "geoplanet:7.9.0", "geoplanet:7.10.0", "geoplanet:8.0.0", "woeplanet:8.0.0"], "meta:indexed": "2020-08-20T20:19:18.806253", "meta:updated": "2020-08-22T02:58:21.843665", "woe:hierarchy": {"continent": 24865672, "country": 23424977, "town": 0, "planet": 1, "county": 12587815, "suburb": 0, "state": 2347568, "region": 0, "localadmin": 0}, "woe:timezone_id": 56043648, "woe:hash": "dhwcgf12ks7s", "woe:centroid": [-80.341103, 25.63117], "geom:latitude": 25.63117, "geom:longitude": -80.341103, "geom:hash": "dhwcgf12ks7s", "woe:latitude": 25.63117, "geom:centroid": [-80.341103, 25.63117], "woe:longitude": -80.341103, "woe:repo": "woeplanet-poi-us"}, "geometry": {"coordinates": [-80.341103, 25.63117], "type": "Point"}}