{"type": "Feature", "id": 23561518, "geometry": {"type": "Point", "coordinates": [-88.4851, 39.130058]}, "properties": {"woe:id": 23561518, "woe:parent_id": 2504992, "woe:name": "Teutopolis High School", "woe:placetype": 20, "woe:placetype_name": "POI", "woe:lang": "ENG", "iso:country": "US", "meta:provider": ["geoplanet:7.3.1", "geoplanet:7.3.2", "geoplanet:7.4.0", "geoplanet:7.4.1", "geoplanet:7.5.1", "geoplanet:7.5.2", "geoplanet:7.6.0", "geoplanet:7.8.1", "geoplanet:7.9.0", "geoplanet:7.10.0", "geoplanet:8.0.0", "woeplanet:8.0.0"], "meta:indexed": "2020-08-20T20:18:32.158591", "woe:alias_ENG_V": ["Teutopolis Senior High School", "Teutopolis High", "Teutopolis Senior High", "Teutopolis HS", "Teutopolis Senior HS"], "meta:updated": "2020-10-14T11:20:16.168848", "woe:hierarchy": {"continent": 24865672, "country": 23424977, "town": 0, "planet": 1, "county": 12588102, "suburb": 0, "state": 2347572, "region": 0, "localadmin": 0}, "woe:timezone_id": 56043661, "woe:hash": "dncnd7rj5ex2", "woe:centroid": [-88.4851, 39.130058], "geom:latitude": 39.130058, "geom:longitude": -88.4851, "geom:hash": "dncnd7rj5ex2", "woe:latitude": 39.130058, "geom:centroid": [-88.4851, 39.130058], "woe:longitude": -88.4851, "woe:repo": "woeplanet-poi-us", "geom:area": 0.0, "woe:scale": 19}}