{"type": "Feature", "id": 23608717, "geometry": {"type": "Point", "coordinates": [-74.050087, 40.754089]}, "properties": {"woe:id": 23608717, "woe:parent_id": 55859837, "woe:name": "Alfred E. Zampella No. 27 Elementary School", "woe:placetype": 20, "woe:placetype_name": "POI", "woe:lang": "ENG", "iso:country": "US", "meta:provider": ["geoplanet:7.3.1", "geoplanet:7.3.2", "geoplanet:7.4.0", "geoplanet:7.4.1", "geoplanet:7.5.1", "geoplanet:7.5.2", "geoplanet:7.6.0", "geoplanet:7.8.1", "geoplanet:7.9.0", "geoplanet:7.10.0", "geoplanet:8.0.0", "woeplanet:8.0.0"], "meta:indexed": "2020-08-20T20:18:47.253628", "woe:alias_ENG_V": ["Alfred E. Zampella No. 27 Elementary"], "meta:updated": "2020-10-14T11:19:50.096700", "woe:hierarchy": {"continent": 24865672, "country": 23424977, "town": 0, "planet": 1, "county": 12589266, "suburb": 0, "state": 2347589, "region": 0, "localadmin": 0}, "woe:timezone_id": 56043648, "woe:hash": "dr5rfgn3gbv4", "woe:centroid": [-74.050087, 40.754089], "geom:latitude": 40.754089, "geom:longitude": -74.050087, "geom:hash": "dr5rfgn3gbv4", "woe:latitude": 40.754089, "geom:centroid": [-74.050087, 40.754089], "woe:longitude": -74.050087, "woe:repo": "woeplanet-poi-us", "geom:area": 0.0, "woe:scale": 19}}