{"type": "Feature", "id": 23647524, "geometry": {"type": "Point", "coordinates": [-81.094902, 33.73756]}, "properties": {"woe:id": 23647524, "woe:parent_id": 2502934, "woe:name": "Swansea High School", "woe:placetype": 20, "woe:placetype_name": "POI", "woe:lang": "ENG", "iso:country": "US", "meta:provider": ["geoplanet:7.3.1", "geoplanet:7.3.2", "geoplanet:7.4.0", "geoplanet:7.4.1", "geoplanet:7.5.1", "geoplanet:7.5.2", "geoplanet:7.6.0", "geoplanet:7.8.1", "geoplanet:7.9.0", "geoplanet:7.10.0", "geoplanet:8.0.0", "woeplanet:8.0.0"], "meta:indexed": "2020-08-20T20:19:00.835775", "woe:alias_ENG_V": ["Swansea Senior High School", "Swansea High", "Swansea Senior High", "Swansea HS", "Swansea Senior HS"], "meta:updated": "2020-10-14T11:19:46.781448", "woe:hierarchy": {"continent": 24865672, "country": 23424977, "town": 0, "planet": 1, "county": 12589831, "suburb": 0, "state": 2347599, "region": 0, "localadmin": 0}, "woe:timezone_id": 56043648, "woe:hash": "djyrftsrxc42", "woe:centroid": [-81.094902, 33.73756], "geom:latitude": 33.73756, "geom:longitude": -81.094902, "geom:hash": "djyrftsrxc42", "woe:latitude": 33.73756, "geom:centroid": [-81.094902, 33.73756], "woe:longitude": -81.094902, "woe:repo": "woeplanet-poi-us", "geom:area": 0.0, "woe:scale": 19}}