{"type": "Feature", "id": 23607300, "properties": {"woe:id": 23607300, "woe:parent_id": 55991749, "woe:name": "Grace Lutheran School", "woe:placetype": 20, "woe:placetype_name": "POI", "woe:lang": "ENG", "iso:country": "US", "meta:provider": ["geoplanet:7.3.1", "geoplanet:7.3.2", "geoplanet:7.4.0", "geoplanet:7.4.1", "geoplanet:7.5.1", "geoplanet:7.5.2", "geoplanet:7.6.0", "geoplanet:7.8.1", "geoplanet:7.9.0", "geoplanet:7.10.0", "geoplanet:8.0.0", "woeplanet:8.0.0"], "meta:indexed": "2020-08-20T20:18:46.738514", "meta:updated": "2020-08-22T02:57:41.913512", "woe:hierarchy": {"continent": 24865672, "country": 23424977, "town": 0, "planet": 1, "county": 12589259, "suburb": 0, "state": 2347589, "region": 0, "localadmin": 0}, "woe:timezone_id": 56043648, "woe:hash": "dr72etbef9tj", "woe:centroid": [-74.025078, 40.901379], "geom:latitude": 40.901379, "geom:longitude": -74.025078, "geom:hash": "dr72etbef9tj", "woe:latitude": 40.901379, "geom:centroid": [-74.025078, 40.901379], "woe:longitude": -74.025078, "woe:repo": "woeplanet-poi-us"}, "geometry": {"coordinates": [-74.025078, 40.901379], "type": "Point"}}