{"type": "Feature", "id": 23657497, "properties": {"woe:id": 23657497, "woe:parent_id": 2358566, "woe:name": "Neff Middle School", "woe:placetype": 20, "woe:placetype_name": "POI", "woe:lang": "ENG", "iso:country": "US", "meta:provider": ["geoplanet:7.3.1", "geoplanet:7.3.2", "geoplanet:7.4.0", "geoplanet:7.4.1", "geoplanet:7.5.1", "geoplanet:7.5.2", "geoplanet:7.6.0", "geoplanet:7.8.1", "geoplanet:7.9.0", "geoplanet:7.10.0", "geoplanet:8.0.0", "woeplanet:8.0.0"], "meta:indexed": "2020-08-20T20:19:04.945235", "meta:updated": "2020-08-22T02:57:49.838406", "woe:hierarchy": {"continent": 24865672, "country": 23424977, "town": 0, "planet": 1, "county": 12590021, "suburb": 0, "state": 2347602, "region": 0, "localadmin": 0}, "woe:timezone_id": 56043661, "woe:hash": "9v1zsx16kmy6", "woe:centroid": [-98.589401, 29.482229], "geom:latitude": 29.482229, "geom:longitude": -98.589401, "geom:hash": "9v1zsx16kmy6", "woe:latitude": 29.482229, "geom:centroid": [-98.589401, 29.482229], "woe:longitude": -98.589401, "woe:repo": "woeplanet-poi-us"}, "geometry": {"coordinates": [-98.589401, 29.482229], "type": "Point"}}