{"type": "Feature", "id": 56054743, "properties": {"woe:id": 56054743, "woe:parent_id": 2444784, "woe:name": "Lancaster General College of Nursing", "woe:placetype": 20, "woe:placetype_name": "POI", "woe:lang": "ENG", "iso:country": "US", "meta:provider": ["geoplanet:7.3.1", "geoplanet:7.3.2", "geoplanet:7.4.0", "geoplanet:7.4.1", "geoplanet:7.5.1", "geoplanet:7.5.2", "geoplanet:7.6.0", "geoplanet:7.8.1", "geoplanet:7.9.0", "geoplanet:7.10.0", "geoplanet:8.0.0", "woeplanet:8.0.0"], "meta:indexed": "2020-08-20T20:19:18.084258", "meta:updated": "2020-08-22T02:58:21.452341", "woe:alias_ENG_V": ["Lancaster General Col of Nursing"], "woe:hierarchy": {"continent": 24865672, "country": 23424977, "town": 0, "planet": 1, "county": 12589763, "suburb": 0, "state": 2347597, "region": 0, "localadmin": 0}, "woe:timezone_id": 56043648, "woe:hash": "dr1ez9yns87b", "woe:centroid": [-76.302597, 40.04491], "geom:latitude": 40.04491, "geom:longitude": -76.302597, "geom:hash": "dr1ez9yns87b", "woe:latitude": 40.04491, "geom:centroid": [-76.302597, 40.04491], "woe:longitude": -76.302597, "woe:repo": "woeplanet-poi-us"}, "geometry": {"coordinates": [-76.302597, 40.04491], "type": "Point"}}