{"type": "Feature", "id": 23513959, "properties": {"woe:id": 23513959, "woe:parent_id": 2412758, "woe:name": "Grand Bay Middle School", "woe:placetype": 20, "woe:placetype_name": "POI", "woe:lang": "ENG", "iso:country": "US", "meta:provider": ["geoplanet:7.3.1", "geoplanet:7.3.2", "geoplanet:7.4.0", "geoplanet:7.4.1", "geoplanet:7.5.1", "geoplanet:7.5.2", "geoplanet:7.6.0", "geoplanet:7.8.1", "geoplanet:7.9.0", "geoplanet:7.10.0", "geoplanet:8.0.0", "woeplanet:8.0.0"], "meta:indexed": "2020-08-20T20:18:17.569254", "meta:updated": "2020-08-22T02:57:26.301755", "woe:hierarchy": {"continent": 24865672, "country": 23424977, "town": 0, "planet": 1, "county": 12587535, "suburb": 0, "state": 2347559, "region": 0, "localadmin": 0}, "woe:timezone_id": 56043661, "woe:hash": "dj3jmswhpxsx", "woe:centroid": [-88.343483, 30.479549], "geom:latitude": 30.479549, "geom:longitude": -88.343483, "geom:hash": "dj3jmswhpxsx", "woe:latitude": 30.479549, "geom:centroid": [-88.343483, 30.479549], "woe:longitude": -88.343483, "woe:repo": "woeplanet-poi-us"}, "geometry": {"coordinates": [-88.343483, 30.479549], "type": "Point"}}