{"type": "Feature", "id": 23544950, "properties": {"woe:id": 23544950, "woe:parent_id": 2523232, "woe:name": "North Laurel Elementary School", "woe:placetype": 20, "woe:placetype_name": "POI", "woe:lang": "ENG", "iso:country": "US", "meta:provider": ["geoplanet:7.3.1", "geoplanet:7.3.2", "geoplanet:7.4.0", "geoplanet:7.4.1", "geoplanet:7.5.1", "geoplanet:7.5.2", "geoplanet:7.6.0", "geoplanet:7.8.1", "geoplanet:7.9.0", "geoplanet:7.10.0", "geoplanet:8.0.0", "woeplanet:8.0.0"], "meta:indexed": "2020-08-20T20:18:25.749165", "woe:alias_ENG_V": ["N Laurel Elementary School", "N Laurel Elementary", "North Laurel Elementary"], "meta:updated": "2020-08-22T02:57:31.428188", "woe:hierarchy": {"continent": 24865672, "country": 23424977, "town": 0, "planet": 1, "county": 12587801, "suburb": 0, "state": 2347566, "region": 0, "localadmin": 0}, "woe:timezone_id": 56043648, "woe:hash": "dqf72kewm4j2", "woe:centroid": [-75.569923, 38.565842], "geom:latitude": 38.565842, "geom:longitude": -75.569923, "geom:hash": "dqf72kewm4j2", "woe:latitude": 38.565842, "geom:centroid": [-75.569923, 38.565842], "woe:longitude": -75.569923, "woe:repo": "woeplanet-poi-us"}, "geometry": {"coordinates": [-75.569923, 38.565842], "type": "Point"}}