{"type": "Feature", "id": 23560633, "properties": {"woe:id": 23560633, "woe:parent_id": 28338236, "woe:name": "Palestine Grade School", "woe:placetype": 20, "woe:placetype_name": "POI", "woe:lang": "ENG", "iso:country": "US", "meta:provider": ["geoplanet:7.3.1", "geoplanet:7.3.2", "geoplanet:7.4.0", "geoplanet:7.4.1", "geoplanet:7.5.1", "geoplanet:7.5.2", "geoplanet:7.6.0", "geoplanet:7.8.1", "geoplanet:7.9.0", "geoplanet:7.10.0", "geoplanet:8.0.0", "woeplanet:8.0.0"], "meta:indexed": "2020-08-20T20:18:31.844797", "meta:updated": "2020-08-22T02:57:34.466529", "woe:hierarchy": {"continent": 24865672, "country": 23424977, "town": 0, "planet": 1, "county": 12588094, "suburb": 0, "state": 2347572, "region": 0, "localadmin": 0}, "woe:timezone_id": 56043661, "woe:hash": "dnctyk4rdqzd", "woe:centroid": [-87.61277, 39.002789], "geom:latitude": 39.002789, "geom:longitude": -87.61277, "geom:hash": "dnctyk4rdqzd", "woe:latitude": 39.002789, "geom:centroid": [-87.61277, 39.002789], "woe:longitude": -87.61277, "woe:repo": "woeplanet-poi-us"}, "geometry": {"coordinates": [-87.61277, 39.002789], "type": "Point"}}