{"type": "Feature", "id": 23644768, "properties": {"woe:id": 23644768, "woe:parent_id": 28340167, "woe:name": "Middleburg Elementary School", "woe:placetype": 20, "woe:placetype_name": "POI", "woe:lang": "ENG", "iso:country": "US", "meta:provider": ["geoplanet:7.3.1", "geoplanet:7.3.2", "geoplanet:7.4.0", "geoplanet:7.4.1", "geoplanet:7.5.1", "geoplanet:7.5.2", "geoplanet:7.6.0", "geoplanet:7.8.1", "geoplanet:7.9.0", "geoplanet:7.10.0", "geoplanet:8.0.0", "woeplanet:8.0.0"], "meta:indexed": "2020-08-20T20:18:59.995120", "woe:alias_ENG_V": ["Middleburg Elementary"], "meta:updated": "2020-08-22T02:57:47.374189", "woe:hierarchy": {"continent": 24865672, "country": 23424977, "town": 0, "planet": 1, "county": 12589782, "suburb": 0, "state": 2347597, "region": 0, "localadmin": 0}, "woe:timezone_id": 56043648, "woe:hash": "dr30p0bzcr0p", "woe:centroid": [-77.035049, 40.786739], "geom:latitude": 40.786739, "geom:longitude": -77.035049, "geom:hash": "dr30p0bzcr0p", "woe:latitude": 40.786739, "geom:centroid": [-77.035049, 40.786739], "woe:longitude": -77.035049, "woe:repo": "woeplanet-poi-us"}, "geometry": {"coordinates": [-77.035049, 40.786739], "type": "Point"}}