{"type": "Feature", "id": 23528999, "geometry": {"type": "Point", "coordinates": [-115.732292, 32.758308]}, "properties": {"woe:id": 23528999, "woe:parent_id": 2397078, "woe:name": "Westside Elementary School", "woe:placetype": 20, "woe:placetype_name": "POI", "woe:lang": "ENG", "iso:country": "US", "meta:provider": ["geoplanet:7.3.2", "geoplanet:7.4.0", "geoplanet:7.4.1", "geoplanet:7.5.1", "geoplanet:7.5.2", "geoplanet:7.6.0", "geoplanet:7.8.1", "geoplanet:7.9.0", "geoplanet:7.10.0", "geoplanet:8.0.0", "woeplanet:8.0.0"], "meta:indexed": "2020-08-20T22:02:01.295889", "woe:alias_ENG_V": ["Westside Elementary"], "meta:updated": "2020-10-14T11:20:10.470199", "woe:hierarchy": {"continent": 24865672, "country": 23424977, "town": 0, "planet": 1, "county": 12587682, "suburb": 0, "state": 2347563, "region": 0, "localadmin": 0}, "woe:timezone_id": 56043663, "woe:hash": "9mvdq7qqfphq", "woe:centroid": [-115.732292, 32.758308], "geom:latitude": 32.758308, "geom:longitude": -115.732292, "geom:hash": "9mvdq7qqfphq", "woe:latitude": 32.758308, "geom:centroid": [-115.732292, 32.758308], "woe:longitude": -115.732292, "woe:repo": "woeplanet-poi-us", "geom:area": 0.0, "woe:scale": 19}}