{"type": "Feature", "id": 23519906, "geometry": {"type": "Point", "coordinates": [-122.168022, 37.787552]}, "properties": {"woe:id": 23519906, "woe:parent_id": 55806210, "woe:name": "Merritt Middle College High School", "woe:placetype": 20, "woe:placetype_name": "POI", "woe:lang": "ENG", "iso:country": "US", "meta:provider": ["geoplanet:7.3.2", "geoplanet:7.4.0", "geoplanet:7.4.1", "geoplanet:7.5.1", "geoplanet:7.5.2", "geoplanet:7.6.0", "geoplanet:7.8.1", "geoplanet:7.9.0", "geoplanet:7.10.0", "geoplanet:8.0.0", "woeplanet:8.0.0"], "meta:indexed": "2020-08-20T22:01:58.052599", "woe:alias_ENG_V": ["Merritt Middle College Senior High School", "Merritt Middle College High", "Merritt Middle College Senior High", "Merritt Middle College HS", "Merritt Middle College Senior HS"], "meta:updated": "2020-10-14T11:20:09.373386", "woe:hierarchy": {"continent": 24865672, "country": 23424977, "town": 0, "planet": 1, "county": 12587670, "suburb": 0, "state": 2347563, "region": 0, "localadmin": 0}, "woe:timezone_id": 56043663, "woe:hash": "9q9ngzpbqy0r", "woe:centroid": [-122.168022, 37.787552], "geom:latitude": 37.787552, "geom:longitude": -122.168022, "geom:hash": "9q9ngzpbqy0r", "woe:latitude": 37.787552, "geom:centroid": [-122.168022, 37.787552], "woe:longitude": -122.168022, "woe:repo": "woeplanet-poi-us", "geom:area": 0.0, "woe:scale": 19}}