{"type": "Feature", "id": 23645707, "geometry": {"type": "Point", "coordinates": [-71.574898, 41.680191]}, "properties": {"woe:id": 23645707, "woe:parent_id": 2386191, "woe:name": "Father John V Doyle School", "woe:placetype": 20, "woe:placetype_name": "POI", "woe:lang": "ENG", "iso:country": "US", "meta:provider": ["geoplanet:7.3.1", "geoplanet:7.3.2", "geoplanet:7.4.0", "geoplanet:7.4.1", "geoplanet:7.5.1", "geoplanet:7.5.2", "geoplanet:7.6.0", "geoplanet:7.8.1", "geoplanet:7.9.0", "geoplanet:7.10.0", "geoplanet:8.0.0", "woeplanet:8.0.0"], "meta:indexed": "2020-08-20T20:19:00.285075", "meta:updated": "2020-10-14T11:19:50.470910", "woe:hierarchy": {"continent": 24865672, "country": 23424977, "town": 0, "planet": 1, "county": 12589796, "suburb": 0, "state": 2347598, "region": 0, "localadmin": 0}, "woe:timezone_id": 56043648, "woe:hash": "drmj578sxyxz", "woe:centroid": [-71.574898, 41.680191], "geom:latitude": 41.680191, "geom:longitude": -71.574898, "geom:hash": "drmj578sxyxz", "woe:latitude": 41.680191, "geom:centroid": [-71.574898, 41.680191], "woe:longitude": -71.574898, "woe:repo": "woeplanet-poi-us", "geom:area": 0.0, "woe:scale": 19}}