{"type": "Feature", "id": 23549743, "geometry": {"type": "Point", "coordinates": [-80.282997, 25.69338]}, "properties": {"woe:id": 23549743, "woe:parent_id": 56019927, "woe:name": "Epiphany Elementary School", "woe:placetype": 20, "woe:placetype_name": "POI", "woe:lang": "ENG", "iso:country": "US", "meta:provider": ["geoplanet:7.3.1", "geoplanet:7.3.2", "geoplanet:7.4.0", "geoplanet:7.4.1", "geoplanet:7.5.1", "geoplanet:7.5.2", "geoplanet:7.6.0", "geoplanet:7.8.1", "geoplanet:7.9.0", "geoplanet:7.10.0", "geoplanet:8.0.0", "woeplanet:8.0.0"], "meta:indexed": "2020-08-20T20:18:28.066194", "woe:alias_ENG_V": ["Epiphany Catholic School", "Epiphany Elementary"], "meta:updated": "2020-10-14T11:20:27.959908", "woe:hierarchy": {"continent": 24865672, "country": 23424977, "town": 0, "planet": 1, "county": 12587815, "suburb": 0, "state": 2347568, "region": 0, "localadmin": 0}, "woe:timezone_id": 56043648, "woe:hash": "dhwfjj7dy94t", "woe:centroid": [-80.282997, 25.69338], "geom:latitude": 25.69338, "geom:longitude": -80.282997, "geom:hash": "dhwfjj7dy94t", "woe:latitude": 25.69338, "geom:centroid": [-80.282997, 25.69338], "woe:longitude": -80.282997, "woe:repo": "woeplanet-poi-us", "geom:area": 0.0, "woe:scale": 19}}