{"type": "Feature", "id": 23625599, "properties": {"woe:id": 23625599, "woe:parent_id": 2421797, "woe:name": "New Century Middle School", "woe:placetype": 20, "woe:placetype_name": "POI", "woe:lang": "ENG", "iso:country": "US", "meta:provider": ["geoplanet:7.3.1", "geoplanet:7.3.2", "geoplanet:7.4.0", "geoplanet:7.4.1", "geoplanet:7.5.1", "geoplanet:7.5.2", "geoplanet:7.6.0", "geoplanet:7.8.1", "geoplanet:7.9.0", "geoplanet:7.10.0", "geoplanet:8.0.0", "woeplanet:8.0.0"], "meta:indexed": "2020-08-20T20:18:52.899466", "meta:updated": "2020-08-22T02:57:44.462579", "woe:hierarchy": {"continent": 24865672, "country": 23424977, "town": 0, "planet": 1, "county": 12589436, "suburb": 0, "state": 2347592, "region": 0, "localadmin": 0}, "woe:timezone_id": 56043648, "woe:hash": "dnr8fnvczzfx", "woe:centroid": [-79.357002, 35.325508], "geom:latitude": 35.325508, "geom:longitude": -79.357002, "geom:hash": "dnr8fnvczzfx", "woe:latitude": 35.325508, "geom:centroid": [-79.357002, 35.325508], "woe:longitude": -79.357002, "woe:repo": "woeplanet-poi-us"}, "geometry": {"coordinates": [-79.357002, 35.325508], "type": "Point"}}