{"type": "Feature", "id": 23627634, "geometry": {"type": "Point", "coordinates": [-83.82589, 39.956821]}, "properties": {"woe:id": 23627634, "woe:parent_id": 2395015, "woe:name": "Ridgewood School", "woe:placetype": 20, "woe:placetype_name": "POI", "woe:lang": "ENG", "iso:country": "US", "meta:provider": ["geoplanet:7.3.1", "geoplanet:7.3.2", "geoplanet:7.4.0", "geoplanet:7.4.1", "geoplanet:7.5.1", "geoplanet:7.5.2", "geoplanet:7.6.0", "geoplanet:7.8.1", "geoplanet:7.9.0", "geoplanet:7.10.0", "geoplanet:8.0.0", "woeplanet:8.0.0"], "meta:indexed": "2020-08-20T20:18:53.352417", "meta:updated": "2020-10-14T11:19:36.212862", "woe:hierarchy": {"continent": 24865672, "country": 23424977, "town": 0, "planet": 1, "county": 12589538, "suburb": 0, "state": 2347594, "region": 0, "localadmin": 0}, "woe:timezone_id": 56043648, "woe:hash": "dph7k3zv75q1", "woe:centroid": [-83.82589, 39.956821], "geom:latitude": 39.956821, "geom:longitude": -83.82589, "geom:hash": "dph7k3zv75q1", "woe:latitude": 39.956821, "geom:centroid": [-83.82589, 39.956821], "woe:longitude": -83.82589, "woe:repo": "woeplanet-poi-us", "geom:area": 0.0, "woe:scale": 19}}