{"type": "Feature", "id": 23516170, "geometry": {"type": "Point", "coordinates": [-111.787727, 33.450668]}, "properties": {"woe:id": 23516170, "woe:parent_id": 2449808, "woe:name": "Tutor Time Charter School-ne Mesa", "woe:placetype": 20, "woe:placetype_name": "POI", "woe:lang": "ENG", "iso:country": "US", "meta:provider": ["geoplanet:7.3.1", "geoplanet:7.3.2", "geoplanet:7.4.0", "geoplanet:7.4.1", "geoplanet:7.5.1", "geoplanet:7.5.2", "geoplanet:7.6.0", "geoplanet:7.8.1", "geoplanet:7.9.0", "geoplanet:7.10.0", "geoplanet:8.0.0", "woeplanet:8.0.0"], "meta:indexed": "2020-08-20T20:18:18.277469", "meta:updated": "2020-10-14T11:20:13.225317", "woe:alias_ENG_V": ["Tutor Time Charter School"], "woe:hierarchy": {"continent": 24865672, "country": 23424977, "town": 0, "planet": 1, "county": 12587587, "suburb": 0, "state": 2347561, "region": 0, "localadmin": 0}, "woe:timezone_id": 56043666, "woe:hash": "9tbw21w8m0mp", "woe:centroid": [-111.787727, 33.450668], "geom:latitude": 33.450668, "geom:longitude": -111.787727, "geom:hash": "9tbw21w8m0mp", "woe:latitude": 33.450668, "geom:centroid": [-111.787727, 33.450668], "woe:longitude": -111.787727, "woe:repo": "woeplanet-poi-us", "geom:area": 0.0, "woe:scale": 19}}