{"type": "Feature", "id": 23568594, "properties": {"woe:id": 23568594, "woe:parent_id": 2487377, "woe:name": "Salem Middle School", "woe:placetype": 20, "woe:placetype_name": "POI", "woe:lang": "ENG", "iso:country": "US", "meta:provider": ["geoplanet:7.3.1", "geoplanet:7.3.2", "geoplanet:7.4.0", "geoplanet:7.4.1", "geoplanet:7.5.1", "geoplanet:7.5.2", "geoplanet:7.6.0", "geoplanet:7.8.1", "geoplanet:7.9.0", "geoplanet:7.10.0", "geoplanet:8.0.0", "woeplanet:8.0.0"], "meta:indexed": "2020-08-20T20:18:34.855543", "meta:updated": "2020-08-22T02:57:36.012876", "woe:hierarchy": {"continent": 24865672, "country": 23424977, "town": 0, "planet": 1, "county": 12588267, "suburb": 0, "state": 2347573, "region": 0, "localadmin": 0}, "woe:timezone_id": 56043656, "woe:hash": "dnfg8t792081", "woe:centroid": [-86.106033, 38.613041], "geom:latitude": 38.613041, "geom:longitude": -86.106033, "geom:hash": "dnfg8t792081", "woe:latitude": 38.613041, "geom:centroid": [-86.106033, 38.613041], "woe:longitude": -86.106033, "woe:repo": "woeplanet-poi-us"}, "geometry": {"coordinates": [-86.106033, 38.613041], "type": "Point"}}