{"type": "Feature", "id": 23568223, "geometry": {"type": "Point", "coordinates": [-84.994591, 41.643509]}, "properties": {"woe:id": 23568223, "woe:parent_id": 2354778, "woe:name": "Carlin Park Elementary School", "woe:placetype": 20, "woe:placetype_name": "POI", "woe:lang": "ENG", "iso:country": "US", "meta:provider": ["geoplanet:7.3.1", "geoplanet:7.3.2", "geoplanet:7.4.0", "geoplanet:7.4.1", "geoplanet:7.5.1", "geoplanet:7.5.2", "geoplanet:7.6.0", "geoplanet:7.8.1", "geoplanet:7.9.0", "geoplanet:7.10.0", "geoplanet:8.0.0", "woeplanet:8.0.0"], "meta:indexed": "2020-08-20T20:18:34.720277", "woe:alias_ENG_V": ["Carlin Park Elementary"], "meta:updated": "2020-10-14T11:20:10.873113", "woe:hierarchy": {"continent": 24865672, "country": 23424977, "town": 0, "planet": 1, "county": 12588255, "suburb": 0, "state": 2347573, "region": 0, "localadmin": 0}, "woe:timezone_id": 56043656, "woe:hash": "dp7scuuz42xr", "woe:centroid": [-84.994591, 41.643509], "geom:latitude": 41.643509, "geom:longitude": -84.994591, "geom:hash": "dp7scuuz42xr", "woe:latitude": 41.643509, "geom:centroid": [-84.994591, 41.643509], "woe:longitude": -84.994591, "woe:repo": "woeplanet-poi-us", "geom:area": 0.0, "woe:scale": 19}}