{"type": "Feature", "id": 23623293, "geometry": {"type": "Point", "coordinates": [-78.629593, 35.841011]}, "properties": {"woe:id": 23623293, "woe:parent_id": 2402575, "woe:name": "Douglas Elementary School", "woe:placetype": 20, "woe:placetype_name": "POI", "woe:lang": "ENG", "iso:country": "US", "meta:provider": ["geoplanet:7.3.2", "geoplanet:7.4.0", "geoplanet:7.4.1", "geoplanet:7.5.1", "geoplanet:7.5.2", "geoplanet:7.6.0", "geoplanet:7.8.1", "geoplanet:7.9.0", "geoplanet:7.10.0", "geoplanet:8.0.0", "woeplanet:8.0.0"], "meta:indexed": "2020-08-20T22:02:39.778888", "woe:alias_ENG_V": ["Douglas Elementary"], "meta:updated": "2020-10-14T11:19:33.094517", "woe:hierarchy": {"continent": 24865672, "country": 23424977, "town": 0, "planet": 1, "county": 12589465, "suburb": 0, "state": 2347592, "region": 0, "localadmin": 0}, "woe:timezone_id": 56043648, "woe:hash": "dq25fsxtj8ty", "woe:centroid": [-78.629593, 35.841011], "geom:latitude": 35.841011, "geom:longitude": -78.629593, "geom:hash": "dq25fsxtj8ty", "woe:latitude": 35.841011, "geom:centroid": [-78.629593, 35.841011], "woe:longitude": -78.629593, "woe:repo": "woeplanet-poi-us", "geom:area": 0.0, "woe:scale": 19}}