{"type": "Feature", "id": 23676620, "properties": {"woe:id": 23676620, "woe:parent_id": 2466597, "woe:name": "Sunset Elementary School", "woe:placetype": 20, "woe:placetype_name": "POI", "woe:lang": "ENG", "iso:country": "US", "meta:provider": ["geoplanet:7.3.1", "geoplanet:7.3.2", "geoplanet:7.4.0", "geoplanet:7.4.1", "geoplanet:7.5.1", "geoplanet:7.5.2", "geoplanet:7.6.0", "geoplanet:7.8.1", "geoplanet:7.9.0", "geoplanet:7.10.0", "geoplanet:8.0.0", "woeplanet:8.0.0"], "meta:indexed": "2020-08-20T20:19:12.104126", "woe:alias_ENG_V": ["Sunset Elementary"], "meta:updated": "2020-08-22T02:58:18.404272", "woe:hierarchy": {"continent": 24865672, "country": 23424977, "town": 0, "planet": 1, "county": 12590604, "suburb": 0, "state": 2347608, "region": 0, "localadmin": 0}, "woe:timezone_id": 56043661, "woe:hash": "dpc48mud6svd", "woe:centroid": [-88.576469, 44.065201], "geom:latitude": 44.065201, "geom:longitude": -88.576469, "geom:hash": "dpc48mud6svd", "woe:latitude": 44.065201, "geom:centroid": [-88.576469, 44.065201], "woe:longitude": -88.576469, "woe:repo": "woeplanet-poi-us"}, "geometry": {"coordinates": [-88.576469, 44.065201], "type": "Point"}}