{"type": "Feature", "id": 23561742, "geometry": {"type": "Point", "coordinates": [-90.157417, 41.44487]}, "properties": {"woe:id": 23561742, "woe:parent_id": 2409475, "woe:name": "Southwest Elementary School", "woe:placetype": 20, "woe:placetype_name": "POI", "woe:lang": "ENG", "iso:country": "US", "meta:provider": ["geoplanet:7.3.1", "geoplanet:7.3.2", "geoplanet:7.4.0", "geoplanet:7.4.1", "geoplanet:7.5.1", "geoplanet:7.5.2", "geoplanet:7.6.0", "geoplanet:7.8.1", "geoplanet:7.9.0", "geoplanet:7.10.0", "geoplanet:8.0.0", "woeplanet:8.0.0"], "meta:indexed": "2020-08-20T20:18:32.232686", "woe:alias_ENG_V": ["SW Elementary School", "SW Elementary", "Southwest Elementary"], "meta:updated": "2020-10-14T11:20:28.397779", "woe:hierarchy": {"continent": 24865672, "country": 23424977, "town": 0, "planet": 1, "county": 12588114, "suburb": 0, "state": 2347572, "region": 0, "localadmin": 0}, "woe:timezone_id": 56043661, "woe:hash": "9zrgu2v3ggtr", "woe:centroid": [-90.157417, 41.44487], "geom:latitude": 41.44487, "geom:longitude": -90.157417, "geom:hash": "9zrgu2v3ggtr", "woe:latitude": 41.44487, "geom:centroid": [-90.157417, 41.44487], "woe:longitude": -90.157417, "woe:repo": "woeplanet-poi-us", "geom:area": 0.0, "woe:scale": 19}}