{"type": "Feature", "id": 23628834, "properties": {"woe:id": 23628834, "woe:parent_id": 55992341, "woe:name": "Capital University", "woe:placetype": 20, "woe:placetype_name": "POI", "woe:lang": "ENG", "iso:country": "US", "meta:provider": ["geoplanet:7.3.1", "geoplanet:7.3.2", "geoplanet:7.4.0", "geoplanet:7.4.1", "geoplanet:7.5.1", "geoplanet:7.5.2", "geoplanet:7.6.0", "geoplanet:7.8.1", "geoplanet:7.9.0", "geoplanet:7.10.0", "geoplanet:8.0.0", "woeplanet:8.0.0"], "meta:indexed": "2020-08-20T20:18:53.906093", "meta:updated": "2020-08-22T02:57:44.909520", "woe:hierarchy": {"continent": 24865672, "country": 23424977, "town": 0, "planet": 1, "county": 12589551, "suburb": 0, "state": 2347594, "region": 0, "localadmin": 0}, "woe:timezone_id": 56043648, "woe:hash": "dpj529y72777", "woe:centroid": [-82.938179, 39.956478], "geom:latitude": 39.956478, "geom:longitude": -82.938179, "geom:hash": "dpj529y72777", "woe:latitude": 39.956478, "geom:centroid": [-82.938179, 39.956478], "woe:longitude": -82.938179, "woe:repo": "woeplanet-poi-us"}, "geometry": {"coordinates": [-82.938179, 39.956478], "type": "Point"}}