{"type": "Feature", "id": 23657024, "geometry": {"type": "Point", "coordinates": [-95.643143, 32.51577]}, "properties": {"woe:id": 23657024, "woe:parent_id": 2511096, "woe:name": "Van Junior High School", "woe:placetype": 20, "woe:placetype_name": "POI", "woe:lang": "ENG", "iso:country": "US", "meta:provider": ["geoplanet:7.3.1", "geoplanet:7.3.2", "geoplanet:7.4.0", "geoplanet:7.4.1", "geoplanet:7.5.1", "geoplanet:7.5.2", "geoplanet:7.6.0", "geoplanet:7.8.1", "geoplanet:7.9.0", "geoplanet:7.10.0", "geoplanet:8.0.0", "woeplanet:8.0.0"], "meta:indexed": "2020-08-20T20:19:04.664952", "woe:alias_ENG_V": ["Van Junior High"], "meta:updated": "2020-10-14T11:19:50.956868", "woe:hierarchy": {"continent": 24865672, "country": 23424977, "town": 0, "planet": 1, "county": 12590240, "suburb": 0, "state": 2347602, "region": 0, "localadmin": 0}, "woe:timezone_id": 56043661, "woe:hash": "9vgbzx6f14ze", "woe:centroid": [-95.643143, 32.51577], "geom:latitude": 32.51577, "geom:longitude": -95.643143, "geom:hash": "9vgbzx6f14ze", "woe:latitude": 32.51577, "geom:centroid": [-95.643143, 32.51577], "woe:longitude": -95.643143, "woe:repo": "woeplanet-poi-us", "geom:area": 0.0, "woe:scale": 19}}