{"type": "Feature", "id": 23602503, "properties": {"woe:id": 23602503, "woe:parent_id": 2430165, "woe:name": "Judith Gap School", "woe:placetype": 20, "woe:placetype_name": "POI", "woe:lang": "ENG", "iso:country": "US", "meta:provider": ["geoplanet:7.3.2", "geoplanet:7.4.0", "geoplanet:7.4.1", "geoplanet:7.5.1", "geoplanet:7.5.2", "geoplanet:7.6.0", "geoplanet:7.8.1", "geoplanet:7.9.0", "geoplanet:7.10.0", "geoplanet:8.0.0", "woeplanet:8.0.0"], "meta:indexed": "2020-08-20T22:02:31.597923", "meta:updated": "2020-08-22T02:57:41.290056", "woe:hierarchy": {"continent": 24865672, "country": 23424977, "town": 0, "planet": 1, "county": 12589134, "suburb": 0, "state": 2347585, "region": 0, "localadmin": 0}, "woe:timezone_id": 56043665, "woe:hash": "c83cw995z555", "woe:centroid": [-109.75174, 46.678822], "geom:latitude": 46.678822, "geom:longitude": -109.75174, "geom:hash": "c83cw995z555", "woe:latitude": 46.678822, "geom:centroid": [-109.75174, 46.678822], "woe:longitude": -109.75174, "woe:repo": "woeplanet-poi-us"}, "geometry": {"coordinates": [-109.75174, 46.678822], "type": "Point"}}