{"type": "Feature", "id": 23681306, "geometry": {"type": "Point", "coordinates": [-84.196541, 33.115238]}, "properties": {"woe:id": 23681306, "woe:parent_id": 2451710, "woe:name": "Milner Station", "woe:placetype": 20, "woe:placetype_name": "POI", "woe:lang": "ENG", "iso:country": "US", "meta:provider": ["geoplanet:7.3.1", "geoplanet:7.3.2", "geoplanet:7.4.0", "geoplanet:7.4.1", "geoplanet:7.5.1", "geoplanet:7.5.2", "geoplanet:7.6.0", "geoplanet:7.8.1", "geoplanet:7.9.0", "geoplanet:7.10.0", "geoplanet:8.0.0", "woeplanet:8.0.0"], "meta:indexed": "2020-08-20T20:19:19.047281", "meta:updated": "2020-10-14T11:19:47.266403", "woe:hierarchy": {"continent": 24865672, "country": 23424977, "town": 0, "planet": 1, "county": 12587954, "suburb": 0, "state": 2347569, "region": 0, "localadmin": 0}, "woe:timezone_id": 56043648, "woe:hash": "djuhkh3ynru9", "woe:centroid": [-84.196541, 33.115238], "geom:latitude": 33.115238, "geom:longitude": -84.196541, "geom:hash": "djuhkh3ynru9", "woe:latitude": 33.115238, "geom:centroid": [-84.196541, 33.115238], "woe:longitude": -84.196541, "woe:repo": "woeplanet-poi-us", "geom:area": 0.0, "woe:scale": 19}}