{"type": "Feature", "id": 23668231, "properties": {"woe:id": 23668231, "woe:parent_id": 2405493, "woe:name": "Forks Alternative School", "woe:placetype": 20, "woe:placetype_name": "POI", "woe:lang": "ENG", "iso:country": "US", "meta:provider": ["geoplanet:7.3.1", "geoplanet:7.3.2", "geoplanet:7.4.0", "geoplanet:7.4.1", "geoplanet:7.5.1", "geoplanet:7.5.2", "geoplanet:7.6.0", "geoplanet:7.8.1", "geoplanet:7.9.0", "geoplanet:7.10.0", "geoplanet:8.0.0", "woeplanet:8.0.0"], "meta:indexed": "2020-08-20T20:19:09.045387", "meta:updated": "2020-08-22T02:57:51.819792", "woe:hierarchy": {"continent": 24865672, "country": 23424977, "town": 0, "planet": 1, "county": 12590444, "suburb": 0, "state": 2347606, "region": 0, "localadmin": 0}, "woe:timezone_id": 56043663, "woe:hash": "c0x8c821421b", "woe:centroid": [-124.387108, 47.945881], "geom:latitude": 47.945881, "geom:longitude": -124.387108, "geom:hash": "c0x8c821421b", "woe:latitude": 47.945881, "geom:centroid": [-124.387108, 47.945881], "woe:longitude": -124.387108, "woe:repo": "woeplanet-poi-us"}, "geometry": {"coordinates": [-124.387108, 47.945881], "type": "Point"}}