{"type": "Feature", "id": 56053365, "geometry": {"type": "Point", "coordinates": [-87.7752, 41.891861]}, "properties": {"woe:id": 56053365, "woe:parent_id": 2357534, "woe:name": "West Suburban College of Nursing", "woe:placetype": 20, "woe:placetype_name": "POI", "woe:lang": "ENG", "iso:country": "US", "meta:provider": ["geoplanet:7.3.1", "geoplanet:7.3.2", "geoplanet:7.4.0", "geoplanet:7.4.1", "geoplanet:7.5.1", "geoplanet:7.5.2", "geoplanet:7.6.0", "geoplanet:7.8.1", "geoplanet:7.9.0", "geoplanet:7.10.0", "geoplanet:8.0.0", "woeplanet:8.0.0"], "meta:indexed": "2020-08-20T20:19:16.987444", "meta:updated": "2020-10-14T11:19:55.678339", "woe:hierarchy": {"continent": 24865672, "country": 23424977, "town": 0, "planet": 1, "county": 12588093, "suburb": 0, "state": 2347572, "region": 0, "localadmin": 0}, "woe:timezone_id": 56043661, "woe:hash": "dp3w6dhjc8gh", "woe:centroid": [-87.7752, 41.891861], "geom:latitude": 41.891861, "geom:longitude": -87.7752, "geom:hash": "dp3w6dhjc8gh", "woe:latitude": 41.891861, "geom:centroid": [-87.7752, 41.891861], "woe:longitude": -87.7752, "woe:repo": "woeplanet-poi-us", "geom:area": 0.0, "woe:scale": 19}}