{"type": "Feature", "id": 23536984, "geometry": {"type": "Point", "coordinates": [-116.853508, 32.73008]}, "properties": {"woe:id": 23536984, "woe:parent_id": 2426959, "woe:name": "Jamul Intermediate School", "woe:placetype": 20, "woe:placetype_name": "POI", "woe:lang": "ENG", "iso:country": "US", "meta:provider": ["geoplanet:7.3.1", "geoplanet:7.3.2", "geoplanet:7.4.0", "geoplanet:7.4.1", "geoplanet:7.5.1", "geoplanet:7.5.2", "geoplanet:7.6.0", "geoplanet:7.8.1", "geoplanet:7.9.0", "geoplanet:7.10.0", "geoplanet:8.0.0", "woeplanet:8.0.0"], "meta:indexed": "2020-08-20T20:18:23.420791", "meta:updated": "2020-10-14T11:20:15.759086", "woe:hierarchy": {"continent": 24865672, "country": 23424977, "town": 0, "planet": 1, "county": 12587706, "suburb": 0, "state": 2347563, "region": 0, "localadmin": 0}, "woe:timezone_id": 56043663, "woe:hash": "9mufhymfecjh", "woe:centroid": [-116.853508, 32.73008], "geom:latitude": 32.73008, "geom:longitude": -116.853508, "geom:hash": "9mufhymfecjh", "woe:latitude": 32.73008, "geom:centroid": [-116.853508, 32.73008], "woe:longitude": -116.853508, "woe:repo": "woeplanet-poi-us", "geom:area": 0.0, "woe:scale": 19}}