{"type": "Feature", "id": 23565870, "properties": {"woe:id": 23565870, "woe:parent_id": 2398466, "woe:name": "Beck Elementary School", "woe:placetype": 20, "woe:placetype_name": "POI", "woe:lang": "ENG", "iso:country": "US", "meta:provider": ["geoplanet:7.3.2", "geoplanet:7.4.0", "geoplanet:7.4.1", "geoplanet:7.5.1", "geoplanet:7.5.2", "geoplanet:7.6.0", "geoplanet:7.8.1", "geoplanet:7.9.0", "geoplanet:7.10.0", "geoplanet:8.0.0", "woeplanet:8.0.0"], "meta:indexed": "2020-08-20T22:02:16.689302", "woe:alias_ENG_V": ["Beck Elementary"], "meta:updated": "2020-08-22T02:57:35.509064", "woe:hierarchy": {"continent": 24865672, "country": 23424977, "town": 0, "planet": 1, "county": 12588199, "suburb": 0, "state": 2347573, "region": 0, "localadmin": 0}, "woe:timezone_id": 56043656, "woe:hash": "dp6v5fz7kmw8", "woe:centroid": [-85.95787, 41.67585], "geom:latitude": 41.67585, "geom:longitude": -85.95787, "geom:hash": "dp6v5fz7kmw8", "woe:latitude": 41.67585, "geom:centroid": [-85.95787, 41.67585], "woe:longitude": -85.95787, "woe:repo": "woeplanet-poi-us"}, "geometry": {"coordinates": [-85.95787, 41.67585], "type": "Point"}}