{"type": "Feature", "id": 23577476, "geometry": {"type": "Point", "coordinates": [-90.097198, 30.384701]}, "properties": {"woe:id": 23577476, "woe:parent_id": 2438725, "woe:name": "Mandeville High School", "woe:placetype": 20, "woe:placetype_name": "POI", "woe:lang": "ENG", "iso:country": "US", "meta:provider": ["geoplanet:7.3.1", "geoplanet:7.3.2", "geoplanet:7.4.0", "geoplanet:7.4.1", "geoplanet:7.5.1", "geoplanet:7.5.2", "geoplanet:7.6.0", "geoplanet:7.8.1", "geoplanet:7.9.0", "geoplanet:7.10.0", "geoplanet:8.0.0", "woeplanet:8.0.0"], "meta:indexed": "2020-08-20T20:18:37.896828", "woe:alias_ENG_V": ["Mandeville Senior High School", "Mandeville High", "Mandeville Senior High", "Mandeville HS", "Mandeville Senior HS"], "meta:updated": "2020-10-14T11:20:16.842987", "woe:hierarchy": {"continent": 24865672, "country": 23424977, "town": 0, "planet": 1, "county": 12588647, "suburb": 0, "state": 2347577, "region": 0, "localadmin": 0}, "woe:timezone_id": 56043661, "woe:hash": "9vruvg35xngc", "woe:centroid": [-90.097198, 30.384701], "geom:latitude": 30.384701, "geom:longitude": -90.097198, "geom:hash": "9vruvg35xngc", "woe:latitude": 30.384701, "geom:centroid": [-90.097198, 30.384701], "woe:longitude": -90.097198, "woe:repo": "woeplanet-poi-us", "geom:area": 0.0, "woe:scale": 19}}