{"type": "Feature", "id": 23535045, "properties": {"woe:id": 23535045, "woe:parent_id": 2504627, "woe:name": "Temecula Valley High School", "woe:placetype": 20, "woe:placetype_name": "POI", "woe:lang": "ENG", "iso:country": "US", "meta:provider": ["geoplanet:7.3.2", "geoplanet:7.4.0", "geoplanet:7.4.1", "geoplanet:7.5.1", "geoplanet:7.5.2", "geoplanet:7.6.0", "geoplanet:7.8.1", "geoplanet:7.9.0", "geoplanet:7.10.0", "geoplanet:8.0.0", "woeplanet:8.0.0"], "meta:indexed": "2020-08-20T22:02:04.012924", "woe:alias_ENG_V": ["Temecula Valley Senior High School", "Temecula Valley High", "Temecula Valley Senior High", "Temecula Valley HS", "Temecula Valley Senior HS"], "meta:updated": "2020-08-22T02:58:46.438300", "woe:hierarchy": {"continent": 24865672, "country": 23424977, "town": 0, "planet": 1, "county": 12587702, "suburb": 0, "state": 2347563, "region": 0, "localadmin": 0}, "woe:timezone_id": 56043663, "woe:hash": "9muwx56vj64y", "woe:centroid": [-117.110252, 33.505051], "geom:latitude": 33.505051, "geom:longitude": -117.110252, "geom:hash": "9muwx56vj64y", "woe:latitude": 33.505051, "geom:centroid": [-117.110252, 33.505051], "woe:longitude": -117.110252, "woe:repo": "woeplanet-poi-us"}, "geometry": {"coordinates": [-117.110252, 33.505051], "type": "Point"}}