{"type": "Feature", "id": 23655946, "geometry": {"type": "Point", "coordinates": [-97.805687, 32.762989]}, "properties": {"woe:id": 23655946, "woe:parent_id": 2515725, "woe:name": "Travis Elementary School", "woe:placetype": 20, "woe:placetype_name": "POI", "woe:lang": "ENG", "iso:country": "US", "meta:provider": ["geoplanet:7.3.1", "geoplanet:7.3.2", "geoplanet:7.4.0", "geoplanet:7.4.1", "geoplanet:7.5.1", "geoplanet:7.5.2", "geoplanet:7.6.0", "geoplanet:7.8.1", "geoplanet:7.9.0", "geoplanet:7.10.0", "geoplanet:8.0.0", "woeplanet:8.0.0"], "meta:indexed": "2020-08-20T20:19:04.102513", "woe:alias_ENG_V": ["Travis Elementary"], "meta:updated": "2020-10-14T11:19:39.276062", "woe:hierarchy": {"continent": 24865672, "country": 23424977, "town": 0, "planet": 1, "county": 12590190, "suburb": 0, "state": 2347602, "region": 0, "localadmin": 0}, "woe:timezone_id": 56043661, "woe:hash": "9vf6qkk44rcf", "woe:centroid": [-97.805687, 32.762989], "geom:latitude": 32.762989, "geom:longitude": -97.805687, "geom:hash": "9vf6qkk44rcf", "woe:latitude": 32.762989, "geom:centroid": [-97.805687, 32.762989], "woe:longitude": -97.805687, "woe:repo": "woeplanet-poi-us", "geom:area": 0.0, "woe:scale": 19}}