{"type": "Feature", "id": 23540919, "properties": {"woe:id": 23540919, "woe:parent_id": 22664079, "woe:name": "Stony Creek Elementary School", "woe:placetype": 20, "woe:placetype_name": "POI", "woe:lang": "ENG", "iso:country": "US", "meta:provider": ["geoplanet:7.4.0", "geoplanet:7.4.1", "geoplanet:7.5.1", "geoplanet:7.5.2", "geoplanet:7.6.0", "geoplanet:7.8.1", "geoplanet:7.9.0", "geoplanet:7.10.0", "geoplanet:8.0.0", "woeplanet:8.0.0"], "meta:indexed": "2020-08-20T23:56:00.728367", "meta:updated": "2020-08-22T02:58:23.343616", "woe:hierarchy": {"continent": 24865672, "country": 23424977, "town": 0, "planet": 1, "county": 12587757, "suburb": 0, "state": 2347564, "region": 0, "localadmin": 0}, "woe:timezone_id": 56043665, "woe:hash": "9xj30qrhe43j", "woe:centroid": [-105.096458, 39.585899], "geom:latitude": 39.585899, "geom:longitude": -105.096458, "geom:hash": "9xj30qrhe43j", "woe:latitude": 39.585899, "geom:centroid": [-105.096458, 39.585899], "woe:longitude": -105.096458, "woe:repo": "woeplanet-poi-us"}, "geometry": {"coordinates": [-105.096458, 39.585899], "type": "Point"}}