{"type": "Feature", "id": 23538524, "properties": {"woe:id": 23538524, "woe:parent_id": 55860925, "woe:name": "Norman R. Brekke Elementary School", "woe:placetype": 20, "woe:placetype_name": "POI", "woe:lang": "ENG", "iso:country": "US", "meta:provider": ["geoplanet:7.3.1", "geoplanet:7.3.2", "geoplanet:7.4.0", "geoplanet:7.4.1", "geoplanet:7.5.1", "geoplanet:7.5.2", "geoplanet:7.6.0", "geoplanet:7.8.1", "geoplanet:7.9.0", "geoplanet:7.10.0", "geoplanet:8.0.0", "woeplanet:8.0.0"], "meta:indexed": "2020-08-20T20:18:23.776409", "woe:alias_ENG_V": ["Brekke Elementary School", "Norman R. Brekke Elementary"], "meta:updated": "2020-08-22T02:57:30.271045", "woe:hierarchy": {"continent": 24865672, "country": 23424977, "town": 0, "planet": 1, "county": 12587725, "suburb": 0, "state": 2347563, "region": 0, "localadmin": 0}, "woe:timezone_id": 56043663, "woe:hash": "9q568keq9f8d", "woe:centroid": [-119.164162, 34.215302], "geom:latitude": 34.215302, "geom:longitude": -119.164162, "geom:hash": "9q568keq9f8d", "woe:latitude": 34.215302, "geom:centroid": [-119.164162, 34.215302], "woe:longitude": -119.164162, "woe:repo": "woeplanet-poi-us"}, "geometry": {"coordinates": [-119.164162, 34.215302], "type": "Point"}}