{"type": "Feature", "id": 23552731, "geometry": {"type": "Point", "coordinates": [-84.470284, 33.803371]}, "properties": {"woe:id": 23552731, "woe:parent_id": 55806103, "woe:name": "Scott Elementary School", "woe:placetype": 20, "woe:placetype_name": "POI", "woe:lang": "ENG", "iso:country": "US", "meta:provider": ["geoplanet:7.3.1", "geoplanet:7.3.2", "geoplanet:7.4.0", "geoplanet:7.4.1", "geoplanet:7.5.1", "geoplanet:7.5.2", "geoplanet:7.6.0", "geoplanet:7.8.1", "geoplanet:7.9.0", "geoplanet:7.10.0", "geoplanet:8.0.0", "woeplanet:8.0.0"], "meta:indexed": "2020-08-20T20:18:29.370896", "woe:alias_ENG_V": ["Scott Elementary"], "meta:updated": "2020-10-14T11:20:18.634010", "woe:hierarchy": {"continent": 24865672, "country": 23424977, "town": 0, "planet": 1, "county": 12587929, "suburb": 0, "state": 2347569, "region": 0, "localadmin": 0}, "woe:timezone_id": 56043648, "woe:hash": "dn5bmcdwgtp4", "woe:centroid": [-84.470284, 33.803371], "geom:latitude": 33.803371, "geom:longitude": -84.470284, "geom:hash": "dn5bmcdwgtp4", "woe:latitude": 33.803371, "geom:centroid": [-84.470284, 33.803371], "woe:longitude": -84.470284, "woe:repo": "woeplanet-poi-us", "geom:area": 0.0, "woe:scale": 19}}