{"type": "Feature", "id": 24610071, "geometry": {"type": "Point", "coordinates": [-74.062912, 40.989361]}, "properties": {"woe:id": 24610071, "woe:parent_id": 23417705, "woe:name": "Seasons", "woe:placetype": 20, "woe:placetype_name": "POI", "woe:lang": "ENG", "iso:country": "US", "meta:provider": ["geoplanet:7.3.1", "geoplanet:7.3.2", "geoplanet:7.4.0", "geoplanet:7.4.1", "geoplanet:7.5.1", "geoplanet:7.5.2", "geoplanet:7.6.0", "geoplanet:7.8.1", "geoplanet:7.9.0", "geoplanet:7.10.0", "geoplanet:8.0.0", "woeplanet:8.0.0"], "meta:indexed": "2020-08-20T20:19:14.376190", "meta:updated": "2020-10-14T11:19:54.744955", "woe:hierarchy": {"continent": 24865672, "country": 23424977, "town": 0, "planet": 1, "county": 12589259, "suburb": 0, "state": 2347589, "region": 0, "localadmin": 0}, "woe:timezone_id": 56043648, "woe:hash": "dr734tvh34dn", "woe:centroid": [-74.062912, 40.989361], "geom:latitude": 40.989361, "geom:longitude": -74.062912, "geom:hash": "dr734tvh34dn", "woe:latitude": 40.989361, "geom:centroid": [-74.062912, 40.989361], "woe:longitude": -74.062912, "woe:repo": "woeplanet-poi-us", "geom:area": 0.0, "woe:scale": 19}}