{"type": "Feature", "id": 23643983, "geometry": {"type": "Point", "coordinates": [-75.215477, 39.964119]}, "properties": {"woe:id": 23643983, "woe:parent_id": 2451065, "woe:name": "Sulzberger Mayer Middle School", "woe:placetype": 20, "woe:placetype_name": "POI", "woe:lang": "ENG", "iso:country": "US", "meta:provider": ["geoplanet:7.3.1", "geoplanet:7.3.2", "geoplanet:7.4.0", "geoplanet:7.4.1", "geoplanet:7.5.1", "geoplanet:7.5.2", "geoplanet:7.6.0", "geoplanet:7.8.1", "geoplanet:7.9.0", "geoplanet:7.10.0", "geoplanet:8.0.0", "woeplanet:8.0.0"], "meta:indexed": "2020-08-20T20:18:59.776333", "meta:updated": "2020-10-14T11:19:31.521683", "woe:alias_ENG_V": ["Parkway West High School"], "woe:hierarchy": {"continent": 24865672, "country": 23424977, "town": 0, "planet": 1, "county": 12589778, "suburb": 0, "state": 2347597, "region": 0, "localadmin": 0}, "woe:timezone_id": 56043648, "woe:hash": "dr4e27jzb7er", "woe:centroid": [-75.215477, 39.964119], "geom:latitude": 39.964119, "geom:longitude": -75.215477, "geom:hash": "dr4e27jzb7er", "woe:latitude": 39.964119, "geom:centroid": [-75.215477, 39.964119], "woe:longitude": -75.215477, "woe:repo": "woeplanet-poi-us", "geom:area": 0.0, "woe:scale": 19}}