{"type": "Feature", "id": 23512975, "geometry": {"type": "Point", "coordinates": [-85.448196, 31.243361]}, "properties": {"woe:id": 23512975, "woe:parent_id": 2393127, "woe:name": "Houston Academy", "woe:placetype": 20, "woe:placetype_name": "POI", "woe:lang": "ENG", "iso:country": "US", "meta:provider": ["geoplanet:7.3.1", "geoplanet:7.3.2", "geoplanet:7.4.0", "geoplanet:7.4.1", "geoplanet:7.5.1", "geoplanet:7.5.2", "geoplanet:7.6.0", "geoplanet:7.8.1", "geoplanet:7.9.0", "geoplanet:7.10.0", "geoplanet:8.0.0", "woeplanet:8.0.0"], "meta:indexed": "2020-08-20T20:18:17.234567", "meta:updated": "2020-10-14T11:20:14.409139", "woe:hierarchy": {"continent": 24865672, "country": 23424977, "town": 0, "planet": 1, "county": 12587521, "suburb": 0, "state": 2347559, "region": 0, "localadmin": 0}, "woe:timezone_id": 56043661, "woe:hash": "dje1xxdtb8x5", "woe:centroid": [-85.448196, 31.243361], "geom:latitude": 31.243361, "geom:longitude": -85.448196, "geom:hash": "dje1xxdtb8x5", "woe:latitude": 31.243361, "geom:centroid": [-85.448196, 31.243361], "woe:longitude": -85.448196, "woe:repo": "woeplanet-poi-us", "geom:area": 0.0, "woe:scale": 19}}