{"type": "Feature", "id": 23571307, "geometry": {"type": "Point", "coordinates": [-97.230247, 38.91544]}, "properties": {"woe:id": 23571307, "woe:parent_id": 2351597, "woe:name": "Mckinley Elementary School", "woe:placetype": 20, "woe:placetype_name": "POI", "woe:lang": "ENG", "iso:country": "US", "meta:provider": ["geoplanet:7.3.1", "geoplanet:7.3.2", "geoplanet:7.4.0", "geoplanet:7.4.1", "geoplanet:7.5.1", "geoplanet:7.5.2", "geoplanet:7.6.0", "geoplanet:7.8.1", "geoplanet:7.9.0", "geoplanet:7.10.0", "geoplanet:8.0.0", "woeplanet:8.0.0"], "meta:indexed": "2020-08-20T20:18:35.867937", "woe:alias_ENG_V": ["Mckinley Elementary"], "meta:updated": "2020-10-14T11:20:18.752452", "woe:hierarchy": {"continent": 24865672, "country": 23424977, "town": 0, "planet": 1, "county": 12588391, "suburb": 0, "state": 2347575, "region": 0, "localadmin": 0}, "woe:timezone_id": 56043661, "woe:hash": "9yfv7kr4g5c1", "woe:centroid": [-97.230247, 38.91544], "geom:latitude": 38.91544, "geom:longitude": -97.230247, "geom:hash": "9yfv7kr4g5c1", "woe:latitude": 38.91544, "geom:centroid": [-97.230247, 38.91544], "woe:longitude": -97.230247, "woe:repo": "woeplanet-poi-us", "geom:area": 0.0, "woe:scale": 19}}