{"type": "Feature", "id": 23664064, "geometry": {"type": "Point", "coordinates": [-77.083832, 38.891769]}, "properties": {"woe:id": 23664064, "woe:parent_id": 55857855, "woe:name": "Court House Arlington Station", "woe:placetype": 20, "woe:placetype_name": "POI", "woe:lang": "ENG", "iso:country": "US", "meta:provider": ["geoplanet:7.3.1", "geoplanet:7.3.2", "geoplanet:7.4.0", "geoplanet:7.4.1", "geoplanet:7.5.1", "geoplanet:7.5.2", "geoplanet:7.6.0", "geoplanet:7.8.1", "geoplanet:7.9.0", "geoplanet:7.10.0", "geoplanet:8.0.0", "woeplanet:8.0.0"], "meta:indexed": "2020-08-20T20:19:07.661262", "meta:updated": "2020-10-14T11:19:34.791823", "woe:hierarchy": {"continent": 24865672, "country": 23424977, "town": 0, "planet": 1, "county": 12590311, "suburb": 0, "state": 2347605, "region": 0, "localadmin": 0}, "woe:timezone_id": 56043648, "woe:hash": "dqcjmbj2bx0y", "woe:centroid": [-77.083832, 38.891769], "geom:latitude": 38.891769, "geom:longitude": -77.083832, "geom:hash": "dqcjmbj2bx0y", "woe:latitude": 38.891769, "geom:centroid": [-77.083832, 38.891769], "woe:longitude": -77.083832, "woe:repo": "woeplanet-poi-us", "geom:area": 0.0, "woe:scale": 19}}