{"type": "Feature", "id": 23627002, "geometry": {"type": "Point", "coordinates": [-97.866722, 48.497459]}, "properties": {"woe:id": 23627002, "woe:parent_id": 2397368, "woe:name": "Edinburg High School", "woe:placetype": 20, "woe:placetype_name": "POI", "woe:lang": "ENG", "iso:country": "US", "meta:provider": ["geoplanet:7.3.2", "geoplanet:7.4.0", "geoplanet:7.4.1", "geoplanet:7.5.1", "geoplanet:7.5.2", "geoplanet:7.6.0", "geoplanet:7.8.1", "geoplanet:7.9.0", "geoplanet:7.10.0", "geoplanet:8.0.0", "woeplanet:8.0.0"], "meta:indexed": "2020-08-20T22:02:41.077007", "woe:alias_ENG_V": ["Edinburg Senior High School", "Edinburg High", "Edinburg Senior High", "Edinburg HS", "Edinburg Senior HS"], "meta:updated": "2020-10-14T11:19:46.193376", "woe:hierarchy": {"continent": 24865672, "country": 23424977, "town": 0, "planet": 1, "county": 12589523, "suburb": 0, "state": 2347593, "region": 0, "localadmin": 0}, "woe:timezone_id": 56043661, "woe:hash": "cbd7uuxwhjdg", "woe:centroid": [-97.866722, 48.497459], "geom:latitude": 48.497459, "geom:longitude": -97.866722, "geom:hash": "cbd7uuxwhjdg", "woe:latitude": 48.497459, "geom:centroid": [-97.866722, 48.497459], "woe:longitude": -97.866722, "woe:repo": "woeplanet-poi-us", "geom:area": 0.0, "woe:scale": 19}}