{"type": "Feature", "id": 23634868, "properties": {"woe:id": 23634868, "woe:parent_id": 2517836, "woe:name": "West Tulsa Station", "woe:placetype": 20, "woe:placetype_name": "POI", "woe:lang": "ENG", "iso:country": "US", "meta:provider": ["geoplanet:7.3.1", "geoplanet:7.3.2", "geoplanet:7.4.0", "geoplanet:7.4.1", "geoplanet:7.5.1", "geoplanet:7.5.2", "geoplanet:7.6.0", "geoplanet:7.8.1", "geoplanet:7.9.0", "geoplanet:7.10.0", "geoplanet:8.0.0", "woeplanet:8.0.0"], "meta:indexed": "2020-08-20T20:18:56.627332", "woe:alias_ENG_V": ["W Tulsa Station"], "meta:updated": "2020-08-22T02:57:45.950985", "woe:hierarchy": {"continent": 24865672, "country": 23424977, "town": 0, "planet": 1, "county": 12589686, "suburb": 0, "state": 2347595, "region": 0, "localadmin": 0}, "woe:timezone_id": 56043661, "woe:hash": "9y7tqu06jy7v", "woe:centroid": [-96.030899, 36.101452], "geom:latitude": 36.101452, "geom:longitude": -96.030899, "geom:hash": "9y7tqu06jy7v", "woe:latitude": 36.101452, "geom:centroid": [-96.030899, 36.101452], "woe:longitude": -96.030899, "woe:repo": "woeplanet-poi-us"}, "geometry": {"coordinates": [-96.030899, 36.101452], "type": "Point"}}