{"type": "Feature", "id": 23634923, "geometry": {"type": "Point", "coordinates": [-98.649223, 36.803398]}, "properties": {"woe:id": 23634923, "woe:parent_id": 2354032, "woe:name": "Washington Elementary School", "woe:placetype": 20, "woe:placetype_name": "POI", "woe:lang": "ENG", "iso:country": "US", "meta:provider": ["geoplanet:7.3.1", "geoplanet:7.3.2", "geoplanet:7.4.0", "geoplanet:7.4.1", "geoplanet:7.5.1", "geoplanet:7.5.2", "geoplanet:7.6.0", "geoplanet:7.8.1", "geoplanet:7.9.0", "geoplanet:7.10.0", "geoplanet:8.0.0", "woeplanet:8.0.0"], "meta:indexed": "2020-08-20T20:18:56.652416", "woe:alias_ENG_V": ["Washington Elementary"], "meta:updated": "2020-10-14T11:19:33.977863", "woe:hierarchy": {"continent": 24865672, "country": 23424977, "town": 0, "planet": 1, "county": 12589690, "suburb": 0, "state": 2347595, "region": 0, "localadmin": 0}, "woe:timezone_id": 56043661, "woe:hash": "9y9c75vg66xu", "woe:centroid": [-98.649223, 36.803398], "geom:latitude": 36.803398, "geom:longitude": -98.649223, "geom:hash": "9y9c75vg66xu", "woe:latitude": 36.803398, "geom:centroid": [-98.649223, 36.803398], "woe:longitude": -98.649223, "woe:repo": "woeplanet-poi-us", "geom:area": 0.0, "woe:scale": 19}}