{"type": "Feature", "id": 23613607, "properties": {"woe:id": 23613607, "woe:parent_id": 2399001, "woe:name": "Cohen Elementary School", "woe:placetype": 20, "woe:placetype_name": "POI", "woe:lang": "ENG", "iso:country": "US", "meta:provider": ["geoplanet:7.3.1", "geoplanet:7.3.2", "geoplanet:7.4.0", "geoplanet:7.4.1", "geoplanet:7.5.1", "geoplanet:7.5.2", "geoplanet:7.6.0", "geoplanet:7.8.1", "geoplanet:7.9.0", "geoplanet:7.10.0", "geoplanet:8.0.0", "woeplanet:8.0.0"], "meta:indexed": "2020-08-20T20:18:48.880923", "woe:alias_ENG_V": ["Cohen Elementary"], "meta:updated": "2020-08-22T02:57:42.787538", "woe:hierarchy": {"continent": 24865672, "country": 23424977, "town": 0, "planet": 1, "county": 12589319, "suburb": 0, "state": 2347591, "region": 0, "localadmin": 0}, "woe:timezone_id": 56043648, "woe:hash": "dr3resjw987k", "woe:centroid": [-76.830757, 42.1227], "geom:latitude": 42.1227, "geom:longitude": -76.830757, "geom:hash": "dr3resjw987k", "woe:latitude": 42.1227, "geom:centroid": [-76.830757, 42.1227], "woe:longitude": -76.830757, "woe:repo": "woeplanet-poi-us"}, "geometry": {"coordinates": [-76.830757, 42.1227], "type": "Point"}}