{"type": "Feature", "id": 23534152, "geometry": {"type": "Point", "coordinates": [-118.068863, 33.810379]}, "properties": {"woe:id": 23534152, "woe:parent_id": 55969304, "woe:name": "Los Alamitos High School", "woe:placetype": 20, "woe:placetype_name": "POI", "woe:lang": "ENG", "iso:country": "US", "meta:provider": ["geoplanet:7.3.2", "geoplanet:7.4.0", "geoplanet:7.4.1", "geoplanet:7.5.1", "geoplanet:7.5.2", "geoplanet:7.6.0", "geoplanet:7.8.1", "geoplanet:7.9.0", "geoplanet:7.10.0", "geoplanet:8.0.0", "woeplanet:8.0.0"], "meta:indexed": "2020-08-20T22:02:03.659737", "woe:alias_ENG_V": ["Los Alamitos Senior High School", "Los Alamitos High", "Los Alamitos Senior High", "Los Alamitos HS", "Los Alamitos Senior HS"], "meta:updated": "2020-10-14T11:20:05.333180", "woe:hierarchy": {"continent": 24865672, "country": 23424977, "town": 0, "planet": 1, "county": 12587699, "suburb": 0, "state": 2347563, "region": 0, "localadmin": 0}, "woe:timezone_id": 56043663, "woe:hash": "9qh036bzsp6y", "woe:centroid": [-118.068863, 33.810379], "geom:latitude": 33.810379, "geom:longitude": -118.068863, "geom:hash": "9qh036bzsp6y", "woe:latitude": 33.810379, "geom:centroid": [-118.068863, 33.810379], "woe:longitude": -118.068863, "woe:repo": "woeplanet-poi-us", "geom:area": 0.0, "woe:scale": 19}}