{"type": "Feature", "id": 23543569, "geometry": {"type": "Point", "coordinates": [-73.304337, 41.63694]}, "properties": {"woe:id": 23543569, "woe:parent_id": 28338007, "woe:name": "Devereux Glenholme School", "woe:placetype": 20, "woe:placetype_name": "POI", "woe:lang": "ENG", "iso:country": "US", "meta:provider": ["geoplanet:7.3.1", "geoplanet:7.3.2", "geoplanet:7.4.0", "geoplanet:7.4.1", "geoplanet:7.5.1", "geoplanet:7.5.2", "geoplanet:7.6.0", "geoplanet:7.8.1", "geoplanet:7.9.0", "geoplanet:7.10.0", "geoplanet:8.0.0", "woeplanet:8.0.0"], "meta:indexed": "2020-08-20T20:18:25.294091", "meta:updated": "2020-10-14T11:20:23.362507", "woe:hierarchy": {"continent": 24865672, "country": 23424977, "town": 0, "planet": 1, "county": 12587793, "suburb": 0, "state": 2347565, "region": 0, "localadmin": 0}, "woe:timezone_id": 56043648, "woe:hash": "dr7uggv2v0ht", "woe:centroid": [-73.304337, 41.63694], "geom:latitude": 41.63694, "geom:longitude": -73.304337, "geom:hash": "dr7uggv2v0ht", "woe:latitude": 41.63694, "geom:centroid": [-73.304337, 41.63694], "woe:longitude": -73.304337, "woe:repo": "woeplanet-poi-us", "geom:area": 0.0, "woe:scale": 19}}