{"type": "Feature", "id": 23608560, "properties": {"woe:id": 23608560, "woe:parent_id": 2511741, "woe:name": "Saint Matthew Regional School", "woe:placetype": 20, "woe:placetype_name": "POI", "woe:lang": "ENG", "iso:country": "US", "meta:provider": ["geoplanet:7.4.0", "geoplanet:7.4.1", "geoplanet:7.5.1", "geoplanet:7.5.2", "geoplanet:7.6.0", "geoplanet:7.8.1", "geoplanet:7.9.0", "geoplanet:7.10.0", "geoplanet:8.0.0", "woeplanet:8.0.0"], "meta:indexed": "2020-08-20T23:55:18.747288", "meta:updated": "2020-08-22T02:57:42.118910", "woe:alias_ENG_V": ["St Matthew School"], "woe:hierarchy": {"continent": 24865672, "country": 23424977, "town": 0, "planet": 1, "county": 12589265, "suburb": 0, "state": 2347589, "region": 0, "localadmin": 0}, "woe:timezone_id": 56043648, "woe:hash": "dr4dc87pt7fu", "woe:centroid": [-75.164108, 39.86108], "geom:latitude": 39.86108, "geom:longitude": -75.164108, "geom:hash": "dr4dc87pt7fu", "woe:latitude": 39.86108, "geom:centroid": [-75.164108, 39.86108], "woe:longitude": -75.164108, "woe:repo": "woeplanet-poi-us"}, "geometry": {"coordinates": [-75.164108, 39.86108], "type": "Point"}}