{"type": "Feature", "id": 23666712, "geometry": {"type": "Point", "coordinates": [-80.912308, 36.84898]}, "properties": {"woe:id": 23666712, "woe:parent_id": 2357611, "woe:name": "Austinville Elementary School", "woe:placetype": 20, "woe:placetype_name": "POI", "woe:lang": "ENG", "iso:country": "US", "meta:provider": ["geoplanet:7.3.1", "geoplanet:7.3.2", "geoplanet:7.4.0", "geoplanet:7.4.1", "geoplanet:7.5.1", "geoplanet:7.5.2", "geoplanet:7.6.0", "geoplanet:7.8.1", "geoplanet:7.9.0", "geoplanet:7.10.0", "geoplanet:8.0.0", "woeplanet:8.0.0"], "meta:indexed": "2020-08-20T20:19:08.424661", "woe:alias_ENG_V": ["Austinville/jackson Elementary Sch", "Austinville Elementary"], "meta:updated": "2020-10-14T11:19:47.798559", "woe:hierarchy": {"continent": 24865672, "country": 23424977, "town": 0, "planet": 1, "county": 12590438, "suburb": 0, "state": 2347605, "region": 0, "localadmin": 0}, "woe:timezone_id": 56043648, "woe:hash": "dnw3wu1kyedr", "woe:centroid": [-80.912308, 36.84898], "geom:latitude": 36.84898, "geom:longitude": -80.912308, "geom:hash": "dnw3wu1kyedr", "woe:latitude": 36.84898, "geom:centroid": [-80.912308, 36.84898], "woe:longitude": -80.912308, "woe:repo": "woeplanet-poi-us", "geom:area": 0.0, "woe:scale": 19}}