{"type": "Feature", "id": 23546394, "properties": {"woe:id": 23546394, "woe:parent_id": 2470377, "woe:name": "Warrington Middle School", "woe:placetype": 20, "woe:placetype_name": "POI", "woe:lang": "ENG", "iso:country": "US", "meta:provider": ["geoplanet:7.3.1", "geoplanet:7.3.2", "geoplanet:7.4.0", "geoplanet:7.4.1", "geoplanet:7.5.1", "geoplanet:7.5.2", "geoplanet:7.6.0", "geoplanet:7.8.1", "geoplanet:7.9.0", "geoplanet:7.10.0", "geoplanet:8.0.0", "woeplanet:8.0.0"], "meta:indexed": "2020-08-20T20:18:26.430411", "meta:updated": "2020-08-22T02:57:31.763494", "woe:hierarchy": {"continent": 24865672, "country": 23424977, "town": 0, "planet": 1, "county": 12587819, "suburb": 0, "state": 2347568, "region": 0, "localadmin": 0}, "woe:timezone_id": 56043661, "woe:hash": "dj3uyn9142r6", "woe:centroid": [-87.273911, 30.40209], "geom:latitude": 30.40209, "geom:longitude": -87.273911, "geom:hash": "dj3uyn9142r6", "woe:latitude": 30.40209, "geom:centroid": [-87.273911, 30.40209], "woe:longitude": -87.273911, "woe:repo": "woeplanet-poi-us"}, "geometry": {"coordinates": [-87.273911, 30.40209], "type": "Point"}}