{"type": "Feature", "id": 23528013, "properties": {"woe:id": 23528013, "woe:parent_id": 55860296, "woe:name": "Somerset Middle School", "woe:placetype": 20, "woe:placetype_name": "POI", "woe:lang": "ENG", "iso:country": "US", "meta:provider": ["geoplanet:7.3.1", "geoplanet:7.3.2", "geoplanet:7.4.0", "geoplanet:7.4.1", "geoplanet:7.5.1", "geoplanet:7.5.2", "geoplanet:7.6.0", "geoplanet:7.8.1", "geoplanet:7.9.0", "geoplanet:7.10.0", "geoplanet:8.0.0", "woeplanet:8.0.0"], "meta:indexed": "2020-08-20T20:18:21.200698", "meta:updated": "2020-08-22T02:57:28.318486", "woe:hierarchy": {"continent": 24865672, "country": 23424977, "town": 0, "planet": 1, "county": 12587719, "suburb": 0, "state": 2347563, "region": 0, "localadmin": 0}, "woe:timezone_id": 56043663, "woe:hash": "9q9yr50frxsz", "woe:centroid": [-120.980087, 37.67804], "geom:latitude": 37.67804, "geom:longitude": -120.980087, "geom:hash": "9q9yr50frxsz", "woe:latitude": 37.67804, "geom:centroid": [-120.980087, 37.67804], "woe:longitude": -120.980087, "woe:repo": "woeplanet-poi-us"}, "geometry": {"coordinates": [-120.980087, 37.67804], "type": "Point"}}