{"type": "Feature", "id": 23575153, "geometry": {"type": "Point", "coordinates": [-84.592651, 37.097698]}, "properties": {"woe:id": 23575153, "woe:parent_id": 2495699, "woe:name": "Meece Middle School", "woe:placetype": 20, "woe:placetype_name": "POI", "woe:lang": "ENG", "iso:country": "US", "meta:provider": ["geoplanet:7.3.1", "geoplanet:7.3.2", "geoplanet:7.4.0", "geoplanet:7.4.1", "geoplanet:7.5.1", "geoplanet:7.5.2", "geoplanet:7.6.0", "geoplanet:7.8.1", "geoplanet:7.9.0", "geoplanet:7.10.0", "geoplanet:8.0.0", "woeplanet:8.0.0"], "meta:indexed": "2020-08-20T20:18:37.092627", "meta:updated": "2020-10-14T11:20:27.629326", "woe:hierarchy": {"continent": 24865672, "country": 23424977, "town": 0, "planet": 1, "county": 12588575, "suburb": 0, "state": 2347576, "region": 0, "localadmin": 0}, "woe:timezone_id": 56043647, "woe:hash": "dneg513tb25s", "woe:centroid": [-84.592651, 37.097698], "geom:latitude": 37.097698, "geom:longitude": -84.592651, "geom:hash": "dneg513tb25s", "woe:latitude": 37.097698, "geom:centroid": [-84.592651, 37.097698], "woe:longitude": -84.592651, "woe:repo": "woeplanet-poi-us", "geom:area": 0.0, "woe:scale": 19}}