{"type": "Feature", "id": 56052610, "properties": {"woe:id": 56052610, "woe:parent_id": 55986628, "woe:name": "Ivy Tech Community Col-Indianapolis", "woe:placetype": 20, "woe:placetype_name": "POI", "woe:lang": "ENG", "iso:country": "US", "meta:provider": ["geoplanet:7.3.1", "geoplanet:7.3.2", "geoplanet:7.4.0", "geoplanet:7.4.1", "geoplanet:7.5.1", "geoplanet:7.5.2", "geoplanet:7.6.0", "geoplanet:7.8.1", "geoplanet:7.9.0", "geoplanet:7.10.0", "geoplanet:8.0.0", "woeplanet:8.0.0"], "meta:indexed": "2020-08-20T20:19:16.433861", "meta:updated": "2020-08-22T02:58:20.485994", "woe:hierarchy": {"continent": 24865672, "country": 23424977, "town": 0, "planet": 1, "county": 12588228, "suburb": 0, "state": 2347573, "region": 0, "localadmin": 0}, "woe:timezone_id": 56043656, "woe:hash": "dp4drmvzcgn8", "woe:centroid": [-86.157791, 39.80344], "geom:latitude": 39.80344, "geom:longitude": -86.157791, "geom:hash": "dp4drmvzcgn8", "woe:latitude": 39.80344, "geom:centroid": [-86.157791, 39.80344], "woe:longitude": -86.157791, "woe:repo": "woeplanet-poi-us"}, "geometry": {"coordinates": [-86.157791, 39.80344], "type": "Point"}}