{"type": "Feature", "id": 23527261, "properties": {"woe:id": 23527261, "woe:parent_id": 2455436, "woe:name": "Mt. Shasta High School", "woe:placetype": 20, "woe:placetype_name": "POI", "woe:lang": "ENG", "iso:country": "US", "meta:provider": ["geoplanet:7.3.2", "geoplanet:7.4.0", "geoplanet:7.4.1", "geoplanet:7.5.1", "geoplanet:7.5.2", "geoplanet:7.6.0", "geoplanet:7.8.1", "geoplanet:7.9.0", "geoplanet:7.10.0", "geoplanet:8.0.0", "woeplanet:8.0.0"], "meta:indexed": "2020-08-20T22:02:00.644444", "woe:alias_ENG_V": ["Mt. Shasta Senior High School", "Mt. Shasta High", "Mt. Shasta Senior High", "Mt. Shasta HS", "Mt. Shasta Senior HS"], "meta:updated": "2020-08-22T02:58:46.228575", "woe:hierarchy": {"continent": 24865672, "country": 23424977, "town": 0, "planet": 1, "county": 12587716, "suburb": 0, "state": 2347563, "region": 0, "localadmin": 0}, "woe:timezone_id": 56043663, "woe:hash": "9r350fe3e50u", "woe:centroid": [-122.306198, 41.322601], "geom:latitude": 41.322601, "geom:longitude": -122.306198, "geom:hash": "9r350fe3e50u", "woe:latitude": 41.322601, "geom:centroid": [-122.306198, 41.322601], "woe:longitude": -122.306198, "woe:repo": "woeplanet-poi-us"}, "geometry": {"coordinates": [-122.306198, 41.322601], "type": "Point"}}