{"type": "Feature", "id": 23653115, "properties": {"woe:id": 23653115, "woe:parent_id": 2383736, "woe:name": "Jefferies Junior High School", "woe:placetype": 20, "woe:placetype_name": "POI", "woe:lang": "ENG", "iso:country": "US", "meta:provider": ["geoplanet:7.3.1", "geoplanet:7.3.2", "geoplanet:7.4.0", "geoplanet:7.4.1", "geoplanet:7.5.1", "geoplanet:7.5.2", "geoplanet:7.6.0", "geoplanet:7.8.1", "geoplanet:7.9.0", "geoplanet:7.10.0", "geoplanet:8.0.0", "woeplanet:8.0.0"], "meta:indexed": "2020-08-20T20:19:02.721908", "woe:alias_ENG_V": ["Jefferies Junior High"], "meta:updated": "2020-08-22T02:57:48.738023", "woe:hierarchy": {"continent": 24865672, "country": 23424977, "town": 0, "planet": 1, "county": 12590053, "suburb": 0, "state": 2347602, "region": 0, "localadmin": 0}, "woe:timezone_id": 56043661, "woe:hash": "9v9vs8b3tfg2", "woe:centroid": [-98.590714, 31.908689], "geom:latitude": 31.908689, "geom:longitude": -98.590714, "geom:hash": "9v9vs8b3tfg2", "woe:latitude": 31.908689, "geom:centroid": [-98.590714, 31.908689], "woe:longitude": -98.590714, "woe:repo": "woeplanet-poi-us"}, "geometry": {"coordinates": [-98.590714, 31.908689], "type": "Point"}}