{"type": "Feature", "id": 23544956, "geometry": {"type": "Point", "coordinates": [-75.614616, 38.650982]}, "properties": {"woe:id": 23544956, "woe:parent_id": 2490252, "woe:name": "Seaford Central Elementary School", "woe:placetype": 20, "woe:placetype_name": "POI", "woe:lang": "ENG", "iso:country": "US", "meta:provider": ["geoplanet:7.3.1", "geoplanet:7.3.2", "geoplanet:7.4.0", "geoplanet:7.4.1", "geoplanet:7.5.1", "geoplanet:7.5.2", "geoplanet:7.6.0", "geoplanet:7.8.1", "geoplanet:7.9.0", "geoplanet:7.10.0", "geoplanet:8.0.0", "woeplanet:8.0.0"], "meta:indexed": "2020-08-20T20:18:25.750442", "woe:alias_ENG_V": ["Seaford Central Elementary"], "meta:updated": "2020-10-14T11:20:16.583462", "woe:hierarchy": {"continent": 24865672, "country": 23424977, "town": 0, "planet": 1, "county": 12587801, "suburb": 0, "state": 2347566, "region": 0, "localadmin": 0}, "woe:timezone_id": 56043648, "woe:hash": "dqf5zk5n79rb", "woe:centroid": [-75.614616, 38.650982], "geom:latitude": 38.650982, "geom:longitude": -75.614616, "geom:hash": "dqf5zk5n79rb", "woe:latitude": 38.650982, "geom:centroid": [-75.614616, 38.650982], "woe:longitude": -75.614616, "woe:repo": "woeplanet-poi-us", "geom:area": 0.0, "woe:scale": 19}}