{"type": "Feature", "id": 23515843, "geometry": {"type": "Point", "coordinates": [-111.99453, 33.413288]}, "properties": {"woe:id": 23515843, "woe:parent_id": 2496616, "woe:name": "Phoenix Academy of Performing Arts South", "woe:placetype": 20, "woe:placetype_name": "POI", "woe:lang": "ENG", "iso:country": "US", "meta:provider": ["geoplanet:7.3.1", "geoplanet:7.3.2", "geoplanet:7.4.0", "geoplanet:7.4.1", "geoplanet:7.5.1", "geoplanet:7.5.2", "geoplanet:7.6.0", "geoplanet:7.8.1", "geoplanet:7.9.0", "geoplanet:7.10.0", "geoplanet:8.0.0", "woeplanet:8.0.0"], "meta:indexed": "2020-08-20T20:18:18.075763", "meta:updated": "2020-10-14T11:20:15.381127", "woe:hierarchy": {"continent": 24865672, "country": 23424977, "town": 0, "planet": 1, "county": 12587587, "suburb": 0, "state": 2347561, "region": 0, "localadmin": 0}, "woe:timezone_id": 56043666, "woe:hash": "9tbq5d8nd23d", "woe:centroid": [-111.99453, 33.413288], "geom:latitude": 33.413288, "geom:longitude": -111.99453, "geom:hash": "9tbq5d8nd23d", "woe:latitude": 33.413288, "geom:centroid": [-111.99453, 33.413288], "woe:longitude": -111.99453, "woe:repo": "woeplanet-poi-us", "geom:area": 0.0, "woe:scale": 19}}