{"type": "Feature", "id": 23596218, "geometry": {"type": "Point", "coordinates": [-90.140839, 32.432091]}, "properties": {"woe:id": 23596218, "woe:parent_id": 2481193, "woe:name": "Olde Towne Elementary School", "woe:placetype": 20, "woe:placetype_name": "POI", "woe:lang": "ENG", "iso:country": "US", "meta:provider": ["geoplanet:7.3.1", "geoplanet:7.3.2", "geoplanet:7.4.0", "geoplanet:7.4.1", "geoplanet:7.5.1", "geoplanet:7.5.2", "geoplanet:7.6.0", "geoplanet:7.8.1", "geoplanet:7.9.0", "geoplanet:7.10.0", "geoplanet:8.0.0", "woeplanet:8.0.0"], "meta:indexed": "2020-08-20T20:18:43.440691", "woe:alias_ENG_V": ["Olde Towne Elementary"], "meta:updated": "2020-10-14T11:20:14.062040", "woe:hierarchy": {"continent": 24865672, "country": 23424977, "town": 0, "planet": 1, "county": 12588928, "suburb": 0, "state": 2347583, "region": 0, "localadmin": 0}, "woe:timezone_id": 56043661, "woe:hash": "9vzbsb16w5yy", "woe:centroid": [-90.140839, 32.432091], "geom:latitude": 32.432091, "geom:longitude": -90.140839, "geom:hash": "9vzbsb16w5yy", "woe:latitude": 32.432091, "geom:centroid": [-90.140839, 32.432091], "woe:longitude": -90.140839, "woe:repo": "woeplanet-poi-us", "geom:area": 0.0, "woe:scale": 19}}