{"type": "Feature", "id": 23637958, "geometry": {"type": "Point", "coordinates": [-122.783653, 45.3843]}, "properties": {"woe:id": 23637958, "woe:parent_id": 2508349, "woe:name": "Tualatin Dcu Station", "woe:placetype": 20, "woe:placetype_name": "POI", "woe:lang": "ENG", "iso:country": "US", "meta:provider": ["geoplanet:7.3.1", "geoplanet:7.3.2", "geoplanet:7.4.0", "geoplanet:7.4.1", "geoplanet:7.5.1", "geoplanet:7.5.2", "geoplanet:7.6.0", "geoplanet:7.8.1", "geoplanet:7.9.0", "geoplanet:7.10.0", "geoplanet:8.0.0", "woeplanet:8.0.0"], "meta:indexed": "2020-08-20T20:18:57.560181", "meta:updated": "2020-10-14T11:19:48.949061", "woe:hierarchy": {"continent": 24865672, "country": 23424977, "town": 0, "planet": 1, "county": 12589725, "suburb": 0, "state": 2347596, "region": 0, "localadmin": 0}, "woe:timezone_id": 56043663, "woe:hash": "c20djvzwtw8w", "woe:centroid": [-122.783653, 45.3843], "geom:latitude": 45.3843, "geom:longitude": -122.783653, "geom:hash": "c20djvzwtw8w", "woe:latitude": 45.3843, "geom:centroid": [-122.783653, 45.3843], "woe:longitude": -122.783653, "woe:repo": "woeplanet-poi-us", "geom:area": 0.0, "woe:scale": 19}}