{"type": "Feature", "id": 23663272, "properties": {"woe:id": 23663272, "woe:parent_id": 2451795, "woe:name": "Milton Elementary School", "woe:placetype": 20, "woe:placetype_name": "POI", "woe:lang": "ENG", "iso:country": "US", "meta:provider": ["geoplanet:7.3.1", "geoplanet:7.3.2", "geoplanet:7.4.0", "geoplanet:7.4.1", "geoplanet:7.5.1", "geoplanet:7.5.2", "geoplanet:7.6.0", "geoplanet:7.8.1", "geoplanet:7.9.0", "geoplanet:7.10.0", "geoplanet:8.0.0", "woeplanet:8.0.0"], "meta:indexed": "2020-08-20T20:19:07.497574", "woe:alias_ENG_V": ["Milton Elementary"], "meta:updated": "2020-08-22T02:57:50.981372", "woe:hierarchy": {"continent": 24865672, "country": 23424977, "town": 0, "planet": 1, "county": 12590293, "suburb": 0, "state": 2347604, "region": 0, "localadmin": 0}, "woe:timezone_id": 56043648, "woe:hash": "drujbm47z7z0", "woe:centroid": [-73.110603, 44.632622], "geom:latitude": 44.632622, "geom:longitude": -73.110603, "geom:hash": "drujbm47z7z0", "woe:latitude": 44.632622, "geom:centroid": [-73.110603, 44.632622], "woe:longitude": -73.110603, "woe:repo": "woeplanet-poi-us"}, "geometry": {"coordinates": [-73.110603, 44.632622], "type": "Point"}}