{"type": "Feature", "id": 23683252, "geometry": {"type": "Point", "coordinates": [-84.699257, 40.785709]}, "properties": {"woe:id": 23683252, "woe:parent_id": 2411222, "woe:name": "Glenmore Station", "woe:placetype": 20, "woe:placetype_name": "POI", "woe:lang": "ENG", "iso:country": "US", "meta:provider": ["geoplanet:7.3.1", "geoplanet:7.3.2", "geoplanet:7.4.0", "geoplanet:7.4.1", "geoplanet:7.5.1", "geoplanet:7.5.2", "geoplanet:7.6.0", "geoplanet:7.8.1", "geoplanet:7.9.0", "geoplanet:7.10.0", "geoplanet:8.0.0", "woeplanet:8.0.0"], "meta:indexed": "2020-08-20T20:19:20.191288", "meta:updated": "2020-10-14T11:19:27.733581", "woe:hierarchy": {"continent": 24865672, "country": 23424977, "town": 0, "planet": 1, "county": 12589607, "suburb": 0, "state": 2347594, "region": 0, "localadmin": 0}, "woe:timezone_id": 56043648, "woe:hash": "dp7b08gcur0q", "woe:centroid": [-84.699257, 40.785709], "geom:latitude": 40.785709, "geom:longitude": -84.699257, "geom:hash": "dp7b08gcur0q", "woe:latitude": 40.785709, "geom:centroid": [-84.699257, 40.785709], "woe:longitude": -84.699257, "woe:repo": "woeplanet-poi-us", "geom:area": 0.0, "woe:scale": 19}}