{"type": "Feature", "id": 23623374, "properties": {"woe:id": 23623374, "woe:parent_id": 55990346, "woe:name": "Wakefield Middle School", "woe:placetype": 20, "woe:placetype_name": "POI", "woe:lang": "ENG", "iso:country": "US", "meta:provider": ["geoplanet:7.3.1", "geoplanet:7.3.2", "geoplanet:7.4.0", "geoplanet:7.4.1", "geoplanet:7.5.1", "geoplanet:7.5.2", "geoplanet:7.6.0", "geoplanet:7.8.1", "geoplanet:7.9.0", "geoplanet:7.10.0", "geoplanet:8.0.0", "woeplanet:8.0.0"], "meta:indexed": "2020-08-20T20:18:52.569049", "meta:updated": "2020-08-22T02:57:44.198262", "woe:hierarchy": {"continent": 24865672, "country": 23424977, "town": 0, "planet": 1, "county": 12589465, "suburb": 0, "state": 2347592, "region": 0, "localadmin": 0}, "woe:timezone_id": 56043648, "woe:hash": "dq2hkpvqsz3t", "woe:centroid": [-78.566803, 35.947048], "geom:latitude": 35.947048, "geom:longitude": -78.566803, "geom:hash": "dq2hkpvqsz3t", "woe:latitude": 35.947048, "geom:centroid": [-78.566803, 35.947048], "woe:longitude": -78.566803, "woe:repo": "woeplanet-poi-us"}, "geometry": {"coordinates": [-78.566803, 35.947048], "type": "Point"}}