{"type": "Feature", "id": 23596307, "properties": {"woe:id": 23596307, "woe:parent_id": 2390185, "woe:name": "Newton County High School", "woe:placetype": 20, "woe:placetype_name": "POI", "woe:lang": "ENG", "iso:country": "US", "meta:provider": ["geoplanet:7.3.2", "geoplanet:7.4.0", "geoplanet:7.4.1", "geoplanet:7.5.1", "geoplanet:7.5.2", "geoplanet:7.6.0", "geoplanet:7.8.1", "geoplanet:7.9.0", "geoplanet:7.10.0", "geoplanet:8.0.0", "woeplanet:8.0.0"], "meta:indexed": "2020-08-20T22:02:29.469498", "woe:alias_ENG_V": ["Newton County Senior High School", "Newton County High", "Newton County Senior High", "Newton County HS", "Newton County Senior HS"], "meta:updated": "2020-08-22T02:58:48.146849", "woe:hierarchy": {"continent": 24865672, "country": 23424977, "town": 0, "planet": 1, "county": 12588934, "suburb": 0, "state": 2347583, "region": 0, "localadmin": 0}, "woe:timezone_id": 56043661, "woe:hash": "djb8s34ddnez", "woe:centroid": [-89.106583, 32.437599], "geom:latitude": 32.437599, "geom:longitude": -89.106583, "geom:hash": "djb8s34ddnez", "woe:latitude": 32.437599, "geom:centroid": [-89.106583, 32.437599], "woe:longitude": -89.106583, "woe:repo": "woeplanet-poi-us"}, "geometry": {"coordinates": [-89.106583, 32.437599], "type": "Point"}}