{"type": "Feature", "id": 24866062, "geometry": {"type": "Point", "coordinates": [-93.261017, 44.96981]}, "properties": {"woe:id": 24866062, "woe:parent_id": 55806431, "woe:name": "North Central University", "woe:placetype": 20, "woe:placetype_name": "POI", "woe:lang": "ENG", "iso:country": "US", "meta:provider": ["geoplanet:7.3.2", "geoplanet:7.4.0", "geoplanet:7.4.1", "geoplanet:7.5.1", "geoplanet:7.5.2", "geoplanet:7.6.0", "geoplanet:7.8.1", "geoplanet:7.9.0", "geoplanet:7.10.0", "geoplanet:8.0.0", "woeplanet:8.0.0"], "meta:indexed": "2020-08-20T22:03:06.012212", "woe:alias_ENG_V": ["N Central University"], "meta:updated": "2020-10-14T11:19:26.052969", "woe:hierarchy": {"continent": 24865672, "country": 23424977, "town": 0, "planet": 1, "county": 12588823, "suburb": 0, "state": 2347582, "region": 0, "localadmin": 0}, "woe:timezone_id": 56043661, "woe:hash": "9zvxvf92hu1m", "woe:centroid": [-93.261017, 44.96981], "geom:latitude": 44.96981, "geom:longitude": -93.261017, "geom:hash": "9zvxvf92hu1m", "woe:latitude": 44.96981, "geom:centroid": [-93.261017, 44.96981], "woe:longitude": -93.261017, "woe:repo": "woeplanet-poi-us", "geom:area": 0.0, "woe:scale": 19}}