{"type": "Feature", "id": 23616479, "geometry": {"type": "Point", "coordinates": [-73.604591, 40.67001]}, "properties": {"woe:id": 23616479, "woe:parent_id": 26342955, "woe:name": "Brookside Elementary School", "woe:placetype": 20, "woe:placetype_name": "POI", "woe:lang": "ENG", "iso:country": "US", "meta:provider": ["geoplanet:7.3.1", "geoplanet:7.3.2", "geoplanet:7.4.0", "geoplanet:7.4.1", "geoplanet:7.5.1", "geoplanet:7.5.2", "geoplanet:7.6.0", "geoplanet:7.8.1", "geoplanet:7.9.0", "geoplanet:7.10.0", "geoplanet:8.0.0", "woeplanet:8.0.0"], "meta:indexed": "2020-08-20T20:18:49.956565", "woe:alias_ENG_V": ["Brookside Elementary"], "meta:updated": "2020-10-14T11:19:54.522726", "woe:hierarchy": {"continent": 24865672, "country": 23424977, "town": 0, "planet": 1, "county": 12589341, "suburb": 0, "state": 2347591, "region": 0, "localadmin": 0}, "woe:timezone_id": 56043648, "woe:hash": "dr5xm5dzbxr5", "woe:centroid": [-73.604591, 40.67001], "geom:latitude": 40.67001, "geom:longitude": -73.604591, "geom:hash": "dr5xm5dzbxr5", "woe:latitude": 40.67001, "geom:centroid": [-73.604591, 40.67001], "woe:longitude": -73.604591, "woe:repo": "woeplanet-poi-us", "geom:area": 0.0, "woe:scale": 19}}