{"type": "Feature", "id": 23569886, "geometry": {"type": "Point", "coordinates": [-96.168358, 43.419868]}, "properties": {"woe:id": 23569886, "woe:parent_id": 2483192, "woe:name": "Central Lyon Elementary School", "woe:placetype": 20, "woe:placetype_name": "POI", "woe:lang": "ENG", "iso:country": "US", "meta:provider": ["geoplanet:7.3.2", "geoplanet:7.4.0", "geoplanet:7.4.1", "geoplanet:7.5.1", "geoplanet:7.5.2", "geoplanet:7.6.0", "geoplanet:7.8.1", "geoplanet:7.9.0", "geoplanet:7.10.0", "geoplanet:8.0.0", "woeplanet:8.0.0"], "meta:indexed": "2020-08-20T22:02:18.448637", "woe:alias_ENG_V": ["Central Lyon Elementary"], "meta:updated": "2020-10-14T11:20:25.613123", "woe:hierarchy": {"continent": 24865672, "country": 23424977, "town": 0, "planet": 1, "county": 12588331, "suburb": 0, "state": 2347574, "region": 0, "localadmin": 0}, "woe:timezone_id": 56043661, "woe:hash": "9zex58k74f4c", "woe:centroid": [-96.168358, 43.419868], "geom:latitude": 43.419868, "geom:longitude": -96.168358, "geom:hash": "9zex58k74f4c", "woe:latitude": 43.419868, "geom:centroid": [-96.168358, 43.419868], "woe:longitude": -96.168358, "woe:repo": "woeplanet-poi-us", "geom:area": 0.0, "woe:scale": 19}}