{"type": "Feature", "id": 23511618, "geometry": {"type": "Point", "coordinates": [-76.50885, 42.444111]}, "properties": {"woe:id": 23511618, "woe:parent_id": 55859795, "woe:name": "Cornell University", "woe:placetype": 20, "woe:placetype_name": "POI", "woe:lang": "ENG", "iso:country": "US", "meta:provider": ["geoplanet:7.3.1", "geoplanet:7.3.2", "geoplanet:7.4.0", "geoplanet:7.4.1", "geoplanet:7.5.1", "geoplanet:7.5.2", "geoplanet:7.6.0", "geoplanet:7.8.1", "geoplanet:7.9.0", "geoplanet:7.10.0", "geoplanet:8.0.0", "woeplanet:8.0.0"], "meta:indexed": "2020-08-20T20:18:16.963610", "woe:alias_ENG_V": ["Cornell"], "meta:updated": "2020-10-14T11:20:17.584230", "woe:hierarchy": {"continent": 24865672, "country": 23424977, "town": 0, "planet": 1, "county": 12589366, "suburb": 0, "state": 2347591, "region": 0, "localadmin": 0}, "woe:timezone_id": 56043648, "woe:hash": "dr996yxyyef8", "woe:centroid": [-76.50885, 42.444111], "geom:latitude": 42.444111, "geom:longitude": -76.50885, "geom:hash": "dr996yxyyef8", "woe:latitude": 42.444111, "geom:centroid": [-76.50885, 42.444111], "woe:longitude": -76.50885, "woe:repo": "woeplanet-poi-us", "geom:area": 0.0, "woe:scale": 19}}