{"type": "Feature", "id": 23643131, "geometry": {"type": "Point", "coordinates": [-75.212761, 40.100491]}, "properties": {"woe:id": 23643131, "woe:parent_id": 2400017, "woe:name": "St Genevieve School", "woe:placetype": 20, "woe:placetype_name": "POI", "woe:lang": "ENG", "iso:country": "US", "meta:provider": ["geoplanet:7.4.0", "geoplanet:7.4.1", "geoplanet:7.5.1", "geoplanet:7.5.2", "geoplanet:7.6.0", "geoplanet:7.8.1", "geoplanet:7.9.0", "geoplanet:7.10.0", "geoplanet:8.0.0", "woeplanet:8.0.0"], "meta:indexed": "2020-08-20T23:55:33.944874", "meta:updated": "2020-10-14T11:19:28.252946", "woe:hierarchy": {"continent": 24865672, "country": 23424977, "town": 0, "planet": 1, "county": 12589773, "suburb": 0, "state": 2347597, "region": 0, "localadmin": 0}, "woe:timezone_id": 56043648, "woe:hash": "dr4s0kpdr9kd", "woe:centroid": [-75.212761, 40.100491], "geom:latitude": 40.100491, "geom:longitude": -75.212761, "geom:hash": "dr4s0kpdr9kd", "woe:latitude": 40.100491, "geom:centroid": [-75.212761, 40.100491], "woe:longitude": -75.212761, "woe:repo": "woeplanet-poi-us", "geom:area": 0.0, "woe:scale": 19}}