{"type": "Feature", "id": 23682655, "properties": {"woe:id": 23682655, "woe:parent_id": 28751222, "woe:name": "Dekalb Avenue Station", "woe:placetype": 20, "woe:placetype_name": "POI", "woe:lang": "ENG", "iso:country": "US", "meta:provider": ["geoplanet:7.3.1", "geoplanet:7.3.2", "geoplanet:7.4.0", "geoplanet:7.4.1", "geoplanet:7.5.1", "geoplanet:7.5.2", "geoplanet:7.6.0", "geoplanet:7.8.1", "geoplanet:7.9.0", "geoplanet:7.10.0", "geoplanet:8.0.0", "woeplanet:8.0.0"], "meta:indexed": "2020-08-20T20:19:19.857952", "woe:alias_ENG_V": ["Mta-Dekalb Ave-L Line", "Dekalb Avenue Subway Station", "Subway-Dekalb Ave-L"], "meta:updated": "2020-08-22T02:58:22.473052", "woe:hierarchy": {"continent": 24865672, "country": 23424977, "town": 0, "planet": 1, "county": 12589335, "suburb": 0, "state": 2347591, "region": 0, "localadmin": 0}, "woe:timezone_id": 56043648, "woe:hash": "dr5rtcvxyzq1", "woe:centroid": [-73.919151, 40.704342], "geom:latitude": 40.704342, "geom:longitude": -73.919151, "geom:hash": "dr5rtcvxyzq1", "woe:latitude": 40.704342, "geom:centroid": [-73.919151, 40.704342], "woe:longitude": -73.919151, "woe:repo": "woeplanet-poi-us"}, "geometry": {"coordinates": [-73.919151, 40.704342], "type": "Point"}}