{"type": "Feature", "id": 23632706, "geometry": {"type": "Point", "coordinates": [-80.536812, 41.211941]}, "properties": {"woe:id": 23632706, "woe:parent_id": 2446779, "woe:name": "Stevenson Elementary School", "woe:placetype": 20, "woe:placetype_name": "POI", "woe:lang": "ENG", "iso:country": "US", "meta:provider": ["geoplanet:7.3.1", "geoplanet:7.3.2", "geoplanet:7.4.0", "geoplanet:7.4.1", "geoplanet:7.5.1", "geoplanet:7.5.2", "geoplanet:7.6.0", "geoplanet:7.8.1", "geoplanet:7.9.0", "geoplanet:7.10.0", "geoplanet:8.0.0", "woeplanet:8.0.0"], "meta:indexed": "2020-08-20T20:18:55.726353", "woe:alias_ENG_V": ["Stevenson Elementary"], "meta:updated": "2020-10-14T11:19:53.618214", "woe:hierarchy": {"continent": 24865672, "country": 23424977, "town": 0, "planet": 1, "county": 12589604, "suburb": 0, "state": 2347594, "region": 0, "localadmin": 0}, "woe:timezone_id": 56043648, "woe:hash": "dpqdrq6uuq87", "woe:centroid": [-80.536812, 41.211941], "geom:latitude": 41.211941, "geom:longitude": -80.536812, "geom:hash": "dpqdrq6uuq87", "woe:latitude": 41.211941, "geom:centroid": [-80.536812, 41.211941], "woe:longitude": -80.536812, "woe:repo": "woeplanet-poi-us", "geom:area": 0.0, "woe:scale": 19}}