{"type": "Feature", "id": 23530233, "geometry": {"type": "Point", "coordinates": [-117.975754, 34.099361]}, "properties": {"woe:id": 23530233, "woe:parent_id": 55969113, "woe:name": "Olive Middle School", "woe:placetype": 20, "woe:placetype_name": "POI", "woe:lang": "ENG", "iso:country": "US", "meta:provider": ["geoplanet:7.3.1", "geoplanet:7.3.2", "geoplanet:7.4.0", "geoplanet:7.4.1", "geoplanet:7.5.1", "geoplanet:7.5.2", "geoplanet:7.6.0", "geoplanet:7.8.1", "geoplanet:7.9.0", "geoplanet:7.10.0", "geoplanet:8.0.0", "woeplanet:8.0.0"], "meta:indexed": "2020-08-20T20:18:21.555962", "meta:updated": "2020-10-14T11:20:17.124387", "woe:hierarchy": {"continent": 24865672, "country": 23424977, "town": 0, "planet": 1, "county": 12587688, "suburb": 0, "state": 2347563, "region": 0, "localadmin": 0}, "woe:timezone_id": 56043663, "woe:hash": "9qh1grsejttg", "woe:centroid": [-117.975754, 34.099361], "geom:latitude": 34.099361, "geom:longitude": -117.975754, "geom:hash": "9qh1grsejttg", "woe:latitude": 34.099361, "geom:centroid": [-117.975754, 34.099361], "woe:longitude": -117.975754, "woe:repo": "woeplanet-poi-us", "geom:area": 0.0, "woe:scale": 19}}