{"type": "Feature", "id": 23600837, "geometry": {"type": "Point", "coordinates": [-104.929916, 47.412849]}, "properties": {"woe:id": 23600837, "woe:parent_id": 2365576, "woe:name": "Bloomfield School", "woe:placetype": 20, "woe:placetype_name": "POI", "woe:lang": "ENG", "iso:country": "US", "meta:provider": ["geoplanet:7.3.1", "geoplanet:7.3.2", "geoplanet:7.4.0", "geoplanet:7.4.1", "geoplanet:7.5.1", "geoplanet:7.5.2", "geoplanet:7.6.0", "geoplanet:7.8.1", "geoplanet:7.9.0", "geoplanet:7.10.0", "geoplanet:8.0.0", "woeplanet:8.0.0"], "meta:indexed": "2020-08-20T20:18:45.167850", "meta:updated": "2020-10-14T11:19:39.986689", "woe:hierarchy": {"continent": 24865672, "country": 23424977, "town": 0, "planet": 1, "county": 12589091, "suburb": 0, "state": 2347585, "region": 0, "localadmin": 0}, "woe:timezone_id": 56043665, "woe:hash": "c8mmsr0rgexu", "woe:centroid": [-104.929916, 47.412849], "geom:latitude": 47.412849, "geom:longitude": -104.929916, "geom:hash": "c8mmsr0rgexu", "woe:latitude": 47.412849, "geom:centroid": [-104.929916, 47.412849], "woe:longitude": -104.929916, "woe:repo": "woeplanet-poi-us", "geom:area": 0.0, "woe:scale": 19}}