{"type": "Feature", "id": 23553724, "geometry": {"type": "Point", "coordinates": [-84.726273, 31.172159]}, "properties": {"woe:id": 23553724, "woe:parent_id": 2383494, "woe:name": "Colquitt Christian Academy", "woe:placetype": 20, "woe:placetype_name": "POI", "woe:lang": "ENG", "iso:country": "US", "meta:provider": ["geoplanet:7.3.1", "geoplanet:7.3.2", "geoplanet:7.4.0", "geoplanet:7.4.1", "geoplanet:7.5.1", "geoplanet:7.5.2", "geoplanet:7.6.0", "geoplanet:7.8.1", "geoplanet:7.9.0", "geoplanet:7.10.0", "geoplanet:8.0.0", "woeplanet:8.0.0"], "meta:indexed": "2020-08-20T20:18:29.709331", "meta:updated": "2020-10-14T11:20:16.247317", "woe:hierarchy": {"continent": 24865672, "country": 23424977, "town": 0, "planet": 1, "county": 12587969, "suburb": 0, "state": 2347569, "region": 0, "localadmin": 0}, "woe:timezone_id": 56043648, "woe:hash": "djec248nyxxg", "woe:centroid": [-84.726273, 31.172159], "geom:latitude": 31.172159, "geom:longitude": -84.726273, "geom:hash": "djec248nyxxg", "woe:latitude": 31.172159, "geom:centroid": [-84.726273, 31.172159], "woe:longitude": -84.726273, "woe:repo": "woeplanet-poi-us", "geom:area": 0.0, "woe:scale": 19}}