{"type": "Feature", "id": 23516652, "geometry": {"type": "Point", "coordinates": [-111.771141, 33.40995]}, "properties": {"woe:id": 23516652, "woe:parent_id": 2449808, "woe:name": "Sherwood Station", "woe:placetype": 20, "woe:placetype_name": "POI", "woe:lang": "ENG", "iso:country": "US", "meta:provider": ["geoplanet:7.3.1", "geoplanet:7.3.2", "geoplanet:7.4.0", "geoplanet:7.4.1", "geoplanet:7.5.1", "geoplanet:7.5.2", "geoplanet:7.6.0", "geoplanet:7.8.1", "geoplanet:7.9.0", "geoplanet:7.10.0", "geoplanet:8.0.0", "woeplanet:8.0.0"], "meta:indexed": "2020-08-20T20:18:18.496076", "meta:updated": "2020-10-14T11:20:15.845457", "woe:hierarchy": {"continent": 24865672, "country": 23424977, "town": 0, "planet": 1, "county": 12587587, "suburb": 0, "state": 2347561, "region": 0, "localadmin": 0}, "woe:timezone_id": 56043666, "woe:hash": "9tbw0d4epdhd", "woe:centroid": [-111.771141, 33.40995], "geom:latitude": 33.40995, "geom:longitude": -111.771141, "geom:hash": "9tbw0d4epdhd", "woe:latitude": 33.40995, "geom:centroid": [-111.771141, 33.40995], "woe:longitude": -111.771141, "woe:repo": "woeplanet-poi-us", "geom:area": 0.0, "woe:scale": 19}}