{"type": "Feature", "id": 23522989, "properties": {"woe:id": 23522989, "woe:parent_id": 2449492, "woe:name": "Yosemite High School", "woe:placetype": 20, "woe:placetype_name": "POI", "woe:lang": "ENG", "iso:country": "US", "meta:provider": ["geoplanet:7.3.1", "geoplanet:7.3.2", "geoplanet:7.4.0", "geoplanet:7.4.1", "geoplanet:7.5.1", "geoplanet:7.5.2", "geoplanet:7.6.0", "geoplanet:7.8.1", "geoplanet:7.9.0", "geoplanet:7.10.0", "geoplanet:8.0.0", "woeplanet:8.0.0"], "meta:indexed": "2020-08-20T20:18:20.066514", "woe:alias_ENG_V": ["Yosemite Senior High School", "Yosemite High", "Yosemite Senior High", "Yosemite HS", "Yosemite Senior HS"], "meta:updated": "2020-08-22T02:58:46.120943", "woe:hierarchy": {"continent": 24865672, "country": 23424977, "town": 0, "planet": 1, "county": 12587693, "suburb": 0, "state": 2347563, "region": 0, "localadmin": 0}, "woe:timezone_id": 56043663, "woe:hash": "9qdk4w3h0wr5", "woe:centroid": [-120.47467, 37.300678], "geom:latitude": 37.300678, "geom:longitude": -120.47467, "geom:hash": "9qdk4w3h0wr5", "woe:latitude": 37.300678, "geom:centroid": [-120.47467, 37.300678], "woe:longitude": -120.47467, "woe:repo": "woeplanet-poi-us"}, "geometry": {"coordinates": [-120.47467, 37.300678], "type": "Point"}}