{"type": "Feature", "id": 23611414, "properties": {"woe:id": 23611414, "woe:parent_id": 2382069, "woe:name": "Highland Elementary School", "woe:placetype": 20, "woe:placetype_name": "POI", "woe:lang": "ENG", "iso:country": "US", "meta:provider": ["geoplanet:7.3.1", "geoplanet:7.3.2", "geoplanet:7.4.0", "geoplanet:7.4.1", "geoplanet:7.5.1", "geoplanet:7.5.2", "geoplanet:7.6.0", "geoplanet:7.8.1", "geoplanet:7.9.0", "geoplanet:7.10.0", "geoplanet:8.0.0", "woeplanet:8.0.0"], "meta:indexed": "2020-08-20T20:18:48.250874", "woe:alias_ENG_V": ["Highland Elementary"], "meta:updated": "2020-08-22T02:57:42.539124", "woe:hierarchy": {"continent": 24865672, "country": 23424977, "town": 0, "planet": 1, "county": 12589284, "suburb": 0, "state": 2347590, "region": 0, "localadmin": 0}, "woe:timezone_id": 56043665, "woe:hash": "9wnegdfm2q5s", "woe:centroid": [-103.202461, 34.42522], "geom:latitude": 34.42522, "geom:longitude": -103.202461, "geom:hash": "9wnegdfm2q5s", "woe:latitude": 34.42522, "geom:centroid": [-103.202461, 34.42522], "woe:longitude": -103.202461, "woe:repo": "woeplanet-poi-us"}, "geometry": {"coordinates": [-103.202461, 34.42522], "type": "Point"}}