{"type": "Feature", "id": 23537943, "geometry": {"type": "Point", "coordinates": [-120.040733, 35.354988]}, "properties": {"woe:id": 23537943, "woe:parent_id": 2493895, "woe:name": "Carrisa Plains Elementary School", "woe:placetype": 20, "woe:placetype_name": "POI", "woe:lang": "ENG", "iso:country": "US", "meta:provider": ["geoplanet:7.3.1", "geoplanet:7.3.2", "geoplanet:7.4.0", "geoplanet:7.4.1", "geoplanet:7.5.1", "geoplanet:7.5.2", "geoplanet:7.6.0", "geoplanet:7.8.1", "geoplanet:7.9.0", "geoplanet:7.10.0", "geoplanet:8.0.0", "woeplanet:8.0.0"], "meta:indexed": "2020-08-20T20:18:23.671586", "woe:alias_ENG_V": ["Carrisa Plains Elementary"], "meta:updated": "2020-10-14T11:20:23.794553", "woe:hierarchy": {"continent": 24865672, "country": 23424977, "town": 0, "planet": 1, "county": 12587709, "suburb": 0, "state": 2347563, "region": 0, "localadmin": 0}, "woe:timezone_id": 56043663, "woe:hash": "9q69hkjj8pmy", "woe:centroid": [-120.040733, 35.354988], "geom:latitude": 35.354988, "geom:longitude": -120.040733, "geom:hash": "9q69hkjj8pmy", "woe:latitude": 35.354988, "geom:centroid": [-120.040733, 35.354988], "woe:longitude": -120.040733, "woe:repo": "woeplanet-poi-us", "geom:area": 0.0, "woe:scale": 19}}