{"type": "Feature", "id": 23681742, "properties": {"woe:id": 23681742, "woe:parent_id": 12588123, "woe:name": "Otto Station", "woe:placetype": 20, "woe:placetype_name": "POI", "woe:lang": "ENG", "iso:country": "US", "meta:provider": ["geoplanet:7.3.1", "geoplanet:7.3.2", "geoplanet:7.4.0", "geoplanet:7.4.1", "geoplanet:7.5.1", "geoplanet:7.5.2", "geoplanet:7.6.0", "geoplanet:7.8.1", "geoplanet:7.9.0", "geoplanet:7.10.0", "geoplanet:8.0.0", "woeplanet:8.0.0"], "meta:indexed": "2020-08-20T20:19:19.300873", "meta:updated": "2020-08-22T02:58:22.140361", "woe:hierarchy": {"continent": 24865672, "country": 23424977, "town": 0, "planet": 1, "county": 12588123, "suburb": 0, "state": 2347572, "region": 0, "localadmin": 0}, "woe:timezone_id": 56043661, "woe:hash": "dp398r03j885", "woe:centroid": [-87.879059, 41.083549], "geom:latitude": 41.083549, "geom:longitude": -87.879059, "geom:hash": "dp398r03j885", "woe:latitude": 41.083549, "geom:centroid": [-87.879059, 41.083549], "woe:longitude": -87.879059, "woe:repo": "woeplanet-poi-us"}, "geometry": {"coordinates": [-87.879059, 41.083549], "type": "Point"}}