{"type": "Feature", "id": 55862630, "properties": {"woe:id": 55862630, "woe:parent_id": 55862558, "woe:name": "PAETEC Park", "woe:placetype": 20, "woe:placetype_name": "POI", "woe:lang": "ENG", "iso:country": "US", "meta:provider": ["geoplanet:7.3.1", "geoplanet:7.3.2", "geoplanet:7.4.0", "geoplanet:7.4.1", "geoplanet:7.5.1", "geoplanet:7.5.2", "geoplanet:7.6.0", "geoplanet:7.8.1", "geoplanet:7.9.0", "geoplanet:7.10.0", "geoplanet:8.0.0", "woeplanet:8.0.0"], "meta:indexed": "2020-08-20T20:19:15.873872", "meta:updated": "2020-08-22T02:58:20.170734", "woe:hierarchy": {"continent": 24865672, "country": 23424977, "town": 0, "planet": 1, "county": 12589339, "suburb": 0, "state": 2347591, "region": 0, "localadmin": 0}, "woe:timezone_id": 56043648, "woe:hash": "dr8v992fpzfh", "woe:centroid": [-77.628029, 43.161549], "geom:latitude": 43.161549, "geom:longitude": -77.628029, "geom:hash": "dr8v992fpzfh", "woe:latitude": 43.161549, "geom:centroid": [-77.628029, 43.161549], "woe:longitude": -77.628029, "woe:repo": "woeplanet-poi-us"}, "geometry": {"coordinates": [-77.628029, 43.161549], "type": "Point"}}