{"type": "Feature", "id": 23524199, "geometry": {"type": "Point", "coordinates": [-121.479919, 38.517139]}, "properties": {"woe:id": 23524199, "woe:parent_id": 55806126, "woe:name": "Collis P. Huntington Elementary School", "woe:placetype": 20, "woe:placetype_name": "POI", "woe:lang": "ENG", "iso:country": "US", "meta:provider": ["geoplanet:7.3.1", "geoplanet:7.3.2", "geoplanet:7.4.0", "geoplanet:7.4.1", "geoplanet:7.5.1", "geoplanet:7.5.2", "geoplanet:7.6.0", "geoplanet:7.8.1", "geoplanet:7.9.0", "geoplanet:7.10.0", "geoplanet:8.0.0", "woeplanet:8.0.0"], "meta:indexed": "2020-08-20T20:18:20.269531", "woe:alias_ENG_V": ["Collis P Huntington Elementary Sch", "Collis P. Huntington Elementary"], "meta:updated": "2020-10-14T11:20:03.491593", "woe:hierarchy": {"continent": 24865672, "country": 23424977, "town": 0, "planet": 1, "county": 12587703, "suburb": 0, "state": 2347563, "region": 0, "localadmin": 0}, "woe:timezone_id": 56043663, "woe:hash": "9qce5ev48ep5", "woe:centroid": [-121.479919, 38.517139], "geom:latitude": 38.517139, "geom:longitude": -121.479919, "geom:hash": "9qce5ev48ep5", "woe:latitude": 38.517139, "geom:centroid": [-121.479919, 38.517139], "woe:longitude": -121.479919, "woe:repo": "woeplanet-poi-us", "geom:area": 0.0, "woe:scale": 19}}