{"type": "Feature", "id": 23535076, "geometry": {"type": "Point", "coordinates": [-117.469963, 33.93269]}, "properties": {"woe:id": 23535076, "woe:parent_id": 2355875, "woe:name": "Wells Intermediate School", "woe:placetype": 20, "woe:placetype_name": "POI", "woe:lang": "ENG", "iso:country": "US", "meta:provider": ["geoplanet:7.3.1", "geoplanet:7.3.2", "geoplanet:7.4.0", "geoplanet:7.4.1", "geoplanet:7.5.1", "geoplanet:7.5.2", "geoplanet:7.6.0", "geoplanet:7.8.1", "geoplanet:7.9.0", "geoplanet:7.10.0", "geoplanet:8.0.0", "woeplanet:8.0.0"], "meta:indexed": "2020-08-20T20:18:22.946837", "meta:updated": "2020-10-14T11:20:19.842487", "woe:hierarchy": {"continent": 24865672, "country": 23424977, "town": 0, "planet": 1, "county": 12587702, "suburb": 0, "state": 2347563, "region": 0, "localadmin": 0}, "woe:timezone_id": 56043663, "woe:hash": "9qh3nckbpryu", "woe:centroid": [-117.469963, 33.93269], "geom:latitude": 33.93269, "geom:longitude": -117.469963, "geom:hash": "9qh3nckbpryu", "woe:latitude": 33.93269, "geom:centroid": [-117.469963, 33.93269], "woe:longitude": -117.469963, "woe:repo": "woeplanet-poi-us", "geom:area": 0.0, "woe:scale": 19}}