{"type": "Feature", "id": 23624945, "geometry": {"type": "Point", "coordinates": [-81.386429, 35.483021]}, "properties": {"woe:id": 23624945, "woe:parent_id": 2479837, "woe:name": "West Lincoln Middle School", "woe:placetype": 20, "woe:placetype_name": "POI", "woe:lang": "ENG", "iso:country": "US", "meta:provider": ["geoplanet:7.3.1", "geoplanet:7.3.2", "geoplanet:7.4.0", "geoplanet:7.4.1", "geoplanet:7.5.1", "geoplanet:7.5.2", "geoplanet:7.6.0", "geoplanet:7.8.1", "geoplanet:7.9.0", "geoplanet:7.10.0", "geoplanet:8.0.0", "woeplanet:8.0.0"], "meta:indexed": "2020-08-20T20:18:52.805668", "woe:alias_ENG_V": ["W Lincoln Middle School"], "meta:updated": "2020-10-14T11:19:53.004930", "woe:hierarchy": {"continent": 24865672, "country": 23424977, "town": 0, "planet": 1, "county": 12589428, "suburb": 0, "state": 2347592, "region": 0, "localadmin": 0}, "woe:timezone_id": 56043648, "woe:hash": "dnq1u52pwf80", "woe:centroid": [-81.386429, 35.483021], "geom:latitude": 35.483021, "geom:longitude": -81.386429, "geom:hash": "dnq1u52pwf80", "woe:latitude": 35.483021, "geom:centroid": [-81.386429, 35.483021], "woe:longitude": -81.386429, "woe:repo": "woeplanet-poi-us", "geom:area": 0.0, "woe:scale": 19}}