{"type": "Feature", "id": 23551600, "properties": {"woe:id": 23551600, "woe:parent_id": 2356940, "woe:name": "Fowler Drive Elementary School", "woe:placetype": 20, "woe:placetype_name": "POI", "woe:lang": "ENG", "iso:country": "US", "meta:provider": ["geoplanet:7.3.1", "geoplanet:7.3.2", "geoplanet:7.4.0", "geoplanet:7.4.1", "geoplanet:7.5.1", "geoplanet:7.5.2", "geoplanet:7.6.0", "geoplanet:7.8.1", "geoplanet:7.9.0", "geoplanet:7.10.0", "geoplanet:8.0.0", "woeplanet:8.0.0"], "meta:indexed": "2020-08-20T20:18:28.946672", "woe:alias_ENG_V": ["Fowler Drive Elementary"], "meta:updated": "2020-08-22T02:57:32.832620", "woe:hierarchy": {"continent": 24865672, "country": 23424977, "town": 0, "planet": 1, "county": 12587898, "suburb": 0, "state": 2347569, "region": 0, "localadmin": 0}, "woe:timezone_id": 56043648, "woe:hash": "dnh9r53pjxn6", "woe:centroid": [-83.36264, 33.988819], "geom:latitude": 33.988819, "geom:longitude": -83.36264, "geom:hash": "dnh9r53pjxn6", "woe:latitude": 33.988819, "geom:centroid": [-83.36264, 33.988819], "woe:longitude": -83.36264, "woe:repo": "woeplanet-poi-us"}, "geometry": {"coordinates": [-83.36264, 33.988819], "type": "Point"}}