{"type": "Feature", "id": 23530451, "properties": {"woe:id": 23530451, "woe:parent_id": 55969513, "woe:name": "Valle Lindo Continuation High School", "woe:placetype": 20, "woe:placetype_name": "POI", "woe:lang": "ENG", "iso:country": "US", "meta:provider": ["geoplanet:7.3.2", "geoplanet:7.4.0", "geoplanet:7.4.1", "geoplanet:7.5.1", "geoplanet:7.5.2", "geoplanet:7.6.0", "geoplanet:7.8.1", "geoplanet:7.9.0", "geoplanet:7.10.0", "geoplanet:8.0.0", "woeplanet:8.0.0"], "meta:indexed": "2020-08-20T22:02:01.773568", "woe:alias_ENG_V": ["Valle Lindo Continuation Senior High School", "Valle Lindo Continuation High", "Valle Lindo Continuation Senior High", "Valle Lindo Continuation HS", "Valle Lindo Continuation Senior HS", "Fernando R Leadsman High", "Fernando R Leadsman High School", "Fernando R Leadsman HS", "Fernando R Leadsman Senior High", "Fernando R Leadsman Senior High School", "Fernando R Leadsman Senior HS"], "meta:updated": "2020-08-22T02:58:46.324942", "woe:hierarchy": {"continent": 24865672, "country": 23424977, "town": 0, "planet": 1, "county": 12587688, "suburb": 0, "state": 2347563, "region": 0, "localadmin": 0}, "woe:timezone_id": 56043663, "woe:hash": "9qh1fg2m8n8n", "woe:centroid": [-118.003807, 34.07645], "geom:latitude": 34.07645, "geom:longitude": -118.003807, "geom:hash": "9qh1fg2m8n8n", "woe:latitude": 34.07645, "geom:centroid": [-118.003807, 34.07645], "woe:longitude": -118.003807, "woe:repo": "woeplanet-poi-us"}, "geometry": {"coordinates": [-118.003807, 34.07645], "type": "Point"}}