{"type": "Feature", "id": 23671776, "properties": {"woe:id": 23671776, "woe:parent_id": 2407974, "woe:name": "Gilbert Elementary School", "woe:placetype": 20, "woe:placetype_name": "POI", "woe:lang": "ENG", "iso:country": "US", "meta:provider": ["geoplanet:7.3.1", "geoplanet:7.3.2", "geoplanet:7.4.0", "geoplanet:7.4.1", "geoplanet:7.5.1", "geoplanet:7.5.2", "geoplanet:7.6.0", "geoplanet:7.8.1", "geoplanet:7.9.0", "geoplanet:7.10.0", "geoplanet:8.0.0", "woeplanet:8.0.0"], "meta:indexed": "2020-08-20T20:19:09.969558", "woe:alias_ENG_V": ["Gilbert Elementary"], "meta:updated": "2020-08-22T02:58:17.377553", "woe:hierarchy": {"continent": 24865672, "country": 23424977, "town": 0, "planet": 1, "county": 12590478, "suburb": 0, "state": 2347606, "region": 0, "localadmin": 0}, "woe:timezone_id": 56043663, "woe:hash": "c2630kjxd73c", "woe:centroid": [-120.567299, 46.605309], "geom:latitude": 46.605309, "geom:longitude": -120.567299, "geom:hash": "c2630kjxd73c", "woe:latitude": 46.605309, "geom:centroid": [-120.567299, 46.605309], "woe:longitude": -120.567299, "woe:repo": "woeplanet-poi-us"}, "geometry": {"coordinates": [-120.567299, 46.605309], "type": "Point"}}