{"type": "Feature", "id": 23685162, "properties": {"woe:id": 23685162, "woe:parent_id": 55805768, "woe:name": "Avon at Ridgemar Mall", "woe:placetype": 20, "woe:placetype_name": "POI", "woe:lang": "ENG", "iso:country": "US", "meta:provider": ["geoplanet:7.3.1", "geoplanet:7.3.2", "geoplanet:7.4.0", "geoplanet:7.4.1", "geoplanet:7.5.1", "geoplanet:7.5.2", "geoplanet:7.6.0", "geoplanet:7.8.1", "geoplanet:7.9.0", "geoplanet:7.10.0", "geoplanet:8.0.0", "woeplanet:8.0.0"], "meta:indexed": "2020-08-20T20:19:13.489131", "meta:updated": "2020-08-22T02:58:19.050370", "woe:hierarchy": {"continent": 24865672, "country": 23424977, "town": 0, "planet": 1, "county": 12590226, "suburb": 0, "state": 2347602, "region": 0, "localadmin": 0}, "woe:timezone_id": 56043661, "woe:hash": "9vfdqb4g7q5y", "woe:centroid": [-97.433823, 32.739849], "geom:latitude": 32.739849, "geom:longitude": -97.433823, "geom:hash": "9vfdqb4g7q5y", "woe:latitude": 32.739849, "geom:centroid": [-97.433823, 32.739849], "woe:longitude": -97.433823, "woe:repo": "woeplanet-poi-us"}, "geometry": {"coordinates": [-97.433823, 32.739849], "type": "Point"}}