{"type": "Feature", "id": 23607785, "geometry": {"type": "Point", "coordinates": [-75.033142, 39.857761]}, "properties": {"woe:id": 23607785, "woe:parent_id": 2444160, "woe:name": "Magnolia Elementary School", "woe:placetype": 20, "woe:placetype_name": "POI", "woe:lang": "ENG", "iso:country": "US", "meta:provider": ["geoplanet:7.3.1", "geoplanet:7.3.2", "geoplanet:7.4.0", "geoplanet:7.4.1", "geoplanet:7.5.1", "geoplanet:7.5.2", "geoplanet:7.6.0", "geoplanet:7.8.1", "geoplanet:7.9.0", "geoplanet:7.10.0", "geoplanet:8.0.0", "woeplanet:8.0.0"], "meta:indexed": "2020-08-20T20:18:46.893496", "woe:alias_ENG_V": ["Magnolia Elementary"], "meta:updated": "2020-10-14T11:19:35.698941", "woe:hierarchy": {"continent": 24865672, "country": 23424977, "town": 0, "planet": 1, "county": 12589261, "suburb": 0, "state": 2347589, "region": 0, "localadmin": 0}, "woe:timezone_id": 56043648, "woe:hash": "dr4dsxfs314j", "woe:centroid": [-75.033142, 39.857761], "geom:latitude": 39.857761, "geom:longitude": -75.033142, "geom:hash": "dr4dsxfs314j", "woe:latitude": 39.857761, "geom:centroid": [-75.033142, 39.857761], "woe:longitude": -75.033142, "woe:repo": "woeplanet-poi-us", "geom:area": 0.0, "woe:scale": 19}}