{"type": "Feature", "id": 23591573, "geometry": {"type": "Point", "coordinates": [-82.903763, 42.442829]}, "properties": {"woe:id": 23591573, "woe:parent_id": 2415210, "woe:name": "Stevens T. Mason Elementary School", "woe:placetype": 20, "woe:placetype_name": "POI", "woe:lang": "ENG", "iso:country": "US", "meta:provider": ["geoplanet:7.4.0", "geoplanet:7.4.1", "geoplanet:7.5.1", "geoplanet:7.5.2", "geoplanet:7.6.0", "geoplanet:7.8.1", "geoplanet:7.9.0", "geoplanet:7.10.0", "geoplanet:8.0.0", "woeplanet:8.0.0"], "meta:indexed": "2020-08-20T23:56:00.869321", "meta:updated": "2020-10-14T11:20:24.075312", "woe:hierarchy": {"continent": 24865672, "country": 23424977, "town": 0, "planet": 1, "county": 12588795, "suburb": 0, "state": 2347581, "region": 0, "localadmin": 0}, "woe:timezone_id": 56043658, "woe:hash": "dpt13qrr6kcb", "woe:centroid": [-82.903763, 42.442829], "geom:latitude": 42.442829, "geom:longitude": -82.903763, "geom:hash": "dpt13qrr6kcb", "woe:latitude": 42.442829, "geom:centroid": [-82.903763, 42.442829], "woe:longitude": -82.903763, "woe:repo": "woeplanet-poi-us", "geom:area": 0.0, "woe:scale": 19}}