{"type": "Feature", "id": 23638257, "geometry": {"type": "Point", "coordinates": [-79.882423, 40.432201]}, "properties": {"woe:id": 23638257, "woe:parent_id": 2397275, "woe:name": "Edgewood Primary School", "woe:placetype": 20, "woe:placetype_name": "POI", "woe:lang": "ENG", "iso:country": "US", "meta:provider": ["geoplanet:7.3.1", "geoplanet:7.3.2", "geoplanet:7.4.0", "geoplanet:7.4.1", "geoplanet:7.5.1", "geoplanet:7.5.2", "geoplanet:7.6.0", "geoplanet:7.8.1", "geoplanet:7.9.0", "geoplanet:7.10.0", "geoplanet:8.0.0", "woeplanet:8.0.0"], "meta:indexed": "2020-08-20T20:18:57.702994", "meta:updated": "2020-10-14T11:19:50.732974", "woe:hierarchy": {"continent": 24865672, "country": 23424977, "town": 0, "planet": 1, "county": 12589729, "suburb": 0, "state": 2347597, "region": 0, "localadmin": 0}, "woe:timezone_id": 56043648, "woe:hash": "dppnn0rqsss1", "woe:centroid": [-79.882423, 40.432201], "geom:latitude": 40.432201, "geom:longitude": -79.882423, "geom:hash": "dppnn0rqsss1", "woe:latitude": 40.432201, "geom:centroid": [-79.882423, 40.432201], "woe:longitude": -79.882423, "woe:repo": "woeplanet-poi-us", "geom:area": 0.0, "woe:scale": 19}}