{"type": "Feature", "id": 23685875, "geometry": {"type": "Point", "coordinates": [-73.981163, 40.753311]}, "properties": {"woe:id": 23685875, "woe:parent_id": 28751381, "woe:name": "New York National Boat Show", "woe:placetype": 20, "woe:placetype_name": "POI", "woe:lang": "ENG", "iso:country": "US", "meta:provider": ["geoplanet:7.3.1", "geoplanet:7.3.2", "geoplanet:7.4.0", "geoplanet:7.4.1", "geoplanet:7.5.1", "geoplanet:7.5.2", "geoplanet:7.6.0", "geoplanet:7.8.1", "geoplanet:7.9.0", "geoplanet:7.10.0", "geoplanet:8.0.0", "woeplanet:8.0.0"], "meta:indexed": "2020-08-20T20:19:14.029611", "meta:updated": "2020-10-14T11:19:43.434003", "woe:alias_ENG_V": ["NY National Boat Show"], "woe:hierarchy": {"continent": 24865672, "country": 23424977, "town": 0, "planet": 1, "county": 12589342, "suburb": 0, "state": 2347591, "region": 0, "localadmin": 0}, "woe:timezone_id": 56043648, "woe:hash": "dr5rudbt1zy9", "woe:centroid": [-73.981163, 40.753311], "geom:latitude": 40.753311, "geom:longitude": -73.981163, "geom:hash": "dr5rudbt1zy9", "woe:latitude": 40.753311, "geom:centroid": [-73.981163, 40.753311], "woe:longitude": -73.981163, "woe:repo": "woeplanet-poi-us", "geom:area": 0.0, "woe:scale": 19}}