{"type": "Feature", "id": 23612885, "geometry": {"type": "Point", "coordinates": [-73.88166, 40.840721]}, "properties": {"woe:id": 23612885, "woe:parent_id": 55992048, "woe:name": "Ps 6 West Farms School", "woe:placetype": 20, "woe:placetype_name": "POI", "woe:lang": "ENG", "iso:country": "US", "meta:provider": ["geoplanet:7.3.1", "geoplanet:7.3.2", "geoplanet:7.4.0", "geoplanet:7.4.1", "geoplanet:7.5.1", "geoplanet:7.5.2", "geoplanet:7.6.0", "geoplanet:7.8.1", "geoplanet:7.9.0", "geoplanet:7.10.0", "geoplanet:8.0.0", "woeplanet:8.0.0"], "meta:indexed": "2020-08-20T20:18:48.597227", "meta:updated": "2020-10-14T11:19:29.773794", "woe:hierarchy": {"continent": 24865672, "country": 23424977, "town": 0, "planet": 1, "county": 12589314, "suburb": 0, "state": 2347591, "region": 0, "localadmin": 0}, "woe:timezone_id": 56043648, "woe:hash": "dr72qfc42w1q", "woe:centroid": [-73.88166, 40.840721], "geom:latitude": 40.840721, "geom:longitude": -73.88166, "geom:hash": "dr72qfc42w1q", "woe:latitude": 40.840721, "geom:centroid": [-73.88166, 40.840721], "woe:longitude": -73.88166, "woe:repo": "woeplanet-poi-us", "geom:area": 0.0, "woe:scale": 19}}