{"type": "Feature", "id": 23666854, "properties": {"woe:id": 23666854, "woe:parent_id": 55858462, "woe:name": "Covenant School The", "woe:placetype": 20, "woe:placetype_name": "POI", "woe:lang": "ENG", "iso:country": "US", "meta:provider": ["geoplanet:7.3.1", "geoplanet:7.3.2", "geoplanet:7.4.0", "geoplanet:7.4.1", "geoplanet:7.5.1", "geoplanet:7.5.2", "geoplanet:7.6.0", "geoplanet:7.8.1", "geoplanet:7.9.0", "geoplanet:7.10.0", "geoplanet:8.0.0", "woeplanet:8.0.0"], "meta:indexed": "2020-08-20T20:19:08.483536", "meta:updated": "2020-08-22T02:57:51.500232", "woe:alias_ENG_V": ["Covenant School"], "woe:hierarchy": {"continent": 24865672, "country": 23424977, "town": 0, "planet": 1, "county": 12590328, "suburb": 0, "state": 2347605, "region": 0, "localadmin": 0}, "woe:timezone_id": 56043648, "woe:hash": "dqb0qjt2tg72", "woe:centroid": [-78.478867, 38.043011], "geom:latitude": 38.043011, "geom:longitude": -78.478867, "geom:hash": "dqb0qjt2tg72", "woe:latitude": 38.043011, "geom:centroid": [-78.478867, 38.043011], "woe:longitude": -78.478867, "woe:repo": "woeplanet-poi-us"}, "geometry": {"coordinates": [-78.478867, 38.043011], "type": "Point"}}