{"type": "Feature", "id": 23638211, "geometry": {"type": "Point", "coordinates": [-79.754532, 40.429699]}, "properties": {"woe:id": 23638211, "woe:parent_id": 23511305, "woe:name": "Gateway Senior High School", "woe:placetype": 20, "woe:placetype_name": "POI", "woe:lang": "ENG", "iso:country": "US", "meta:provider": ["geoplanet:7.3.1", "geoplanet:7.3.2", "geoplanet:7.4.0", "geoplanet:7.4.1", "geoplanet:7.5.1", "geoplanet:7.5.2", "geoplanet:7.6.0", "geoplanet:7.8.1", "geoplanet:7.9.0", "geoplanet:7.10.0", "geoplanet:8.0.0", "woeplanet:8.0.0"], "meta:indexed": "2020-08-20T20:18:57.665883", "woe:alias_ENG_V": ["Gateway Senior High", "Gateway High School", "Gateway High", "Gateway Senior HS", "Gateway HS"], "meta:updated": "2020-10-14T11:19:50.714535", "woe:hierarchy": {"continent": 24865672, "country": 23424977, "town": 0, "planet": 1, "county": 12589729, "suburb": 0, "state": 2347597, "region": 0, "localadmin": 0}, "woe:timezone_id": 56043648, "woe:hash": "dppq10h80dns", "woe:centroid": [-79.754532, 40.429699], "geom:latitude": 40.429699, "geom:longitude": -79.754532, "geom:hash": "dppq10h80dns", "woe:latitude": 40.429699, "geom:centroid": [-79.754532, 40.429699], "woe:longitude": -79.754532, "woe:repo": "woeplanet-poi-us", "geom:area": 0.0, "woe:scale": 19}}