{"type": "Feature", "id": 56204036, "geometry": {"type": "Point", "coordinates": [-122.452309, 37.74567]}, "properties": {"woe:id": 56204036, "woe:parent_id": 55970955, "woe:name": "Woodside Learning Center School", "woe:placetype": 20, "woe:placetype_name": "POI", "woe:lang": "ENG", "iso:country": "US", "meta:provider": ["geoplanet:7.6.0", "geoplanet:7.8.1", "geoplanet:7.9.0", "geoplanet:7.10.0", "geoplanet:8.0.0", "woeplanet:8.0.0"], "meta:indexed": "2020-08-21T08:24:23.678289", "meta:updated": "2020-10-14T11:19:58.989159", "woe:hierarchy": {"continent": 24865672, "country": 23424977, "town": 0, "planet": 1, "county": 12587707, "suburb": 0, "state": 2347563, "region": 0, "localadmin": 0}, "woe:timezone_id": 56043663, "woe:hash": "9q8ytx2uqque", "woe:centroid": [-122.452309, 37.74567], "geom:latitude": 37.74567, "geom:longitude": -122.452309, "geom:hash": "9q8ytx2uqque", "woe:latitude": 37.74567, "geom:centroid": [-122.452309, 37.74567], "woe:longitude": -122.452309, "woe:repo": "woeplanet-poi-us", "geom:area": 0.0, "woe:scale": 19}}