{"type": "Feature", "id": 23674091, "properties": {"woe:id": 23674091, "woe:parent_id": 2421380, "woe:name": "Highland Elementary School", "woe:placetype": 20, "woe:placetype_name": "POI", "woe:lang": "ENG", "iso:country": "US", "meta:provider": ["geoplanet:7.3.1", "geoplanet:7.3.2", "geoplanet:7.4.0", "geoplanet:7.4.1", "geoplanet:7.5.1", "geoplanet:7.5.2", "geoplanet:7.6.0", "geoplanet:7.8.1", "geoplanet:7.9.0", "geoplanet:7.10.0", "geoplanet:8.0.0", "woeplanet:8.0.0"], "meta:indexed": "2020-08-20T20:19:10.843529", "woe:alias_ENG_V": ["Highland Elementary"], "meta:updated": "2020-08-22T02:58:17.831995", "woe:hierarchy": {"continent": 24865672, "country": 23424977, "town": 0, "planet": 1, "county": 12590558, "suburb": 0, "state": 2347608, "region": 0, "localadmin": 0}, "woe:timezone_id": 56043661, "woe:hash": "9zxszkh39z2w", "woe:centroid": [-90.378609, 43.044731], "geom:latitude": 43.044731, "geom:longitude": -90.378609, "geom:hash": "9zxszkh39z2w", "woe:latitude": 43.044731, "geom:centroid": [-90.378609, 43.044731], "woe:longitude": -90.378609, "woe:repo": "woeplanet-poi-us"}, "geometry": {"coordinates": [-90.378609, 43.044731], "type": "Point"}}