{"type": "Feature", "id": 23543180, "geometry": {"type": "Point", "coordinates": [-72.722878, 41.714249]}, "properties": {"woe:id": 23543180, "woe:parent_id": 2459473, "woe:name": "Elizabeth Green School", "woe:placetype": 20, "woe:placetype_name": "POI", "woe:lang": "ENG", "iso:country": "US", "meta:provider": ["geoplanet:7.3.1", "geoplanet:7.3.2", "geoplanet:7.4.0", "geoplanet:7.4.1", "geoplanet:7.5.1", "geoplanet:7.5.2", "geoplanet:7.6.0", "geoplanet:7.8.1", "geoplanet:7.9.0", "geoplanet:7.10.0", "geoplanet:8.0.0", "woeplanet:8.0.0"], "meta:indexed": "2020-08-20T20:18:25.167579", "meta:updated": "2020-10-14T11:20:04.544175", "woe:hierarchy": {"continent": 24865672, "country": 23424977, "town": 0, "planet": 1, "county": 12587792, "suburb": 0, "state": 2347565, "region": 0, "localadmin": 0}, "woe:timezone_id": 56043648, "woe:hash": "drkm31ug45eg", "woe:centroid": [-72.722878, 41.714249], "geom:latitude": 41.714249, "geom:longitude": -72.722878, "geom:hash": "drkm31ug45eg", "woe:latitude": 41.714249, "geom:centroid": [-72.722878, 41.714249], "woe:longitude": -72.722878, "woe:repo": "woeplanet-poi-us", "geom:area": 0.0, "woe:scale": 19}}