{"type": "Feature", "id": 28349248, "geometry": {"type": "Point", "coordinates": [-87.570099, 33.193001]}, "properties": {"woe:id": 28349248, "woe:parent_id": 2508913, "woe:name": "Veterans Hospital", "woe:placetype": 20, "woe:placetype_name": "POI", "woe:lang": "ENG", "iso:country": "US", "meta:provider": ["geoplanet:7.3.1", "geoplanet:7.3.2", "geoplanet:7.4.0", "geoplanet:7.4.1", "geoplanet:7.5.1", "geoplanet:7.5.2", "geoplanet:7.6.0", "geoplanet:7.8.1", "geoplanet:7.9.0", "geoplanet:7.10.0", "geoplanet:8.0.0", "woeplanet:8.0.0"], "meta:indexed": "2020-08-20T20:19:15.607353", "meta:updated": "2020-10-14T11:19:26.493753", "woe:hierarchy": {"continent": 24865672, "country": 23424977, "town": 0, "planet": 1, "county": 12587549, "suburb": 0, "state": 2347559, "region": 0, "localadmin": 0}, "woe:timezone_id": 56043661, "woe:hash": "djcsz697hzce", "woe:centroid": [-87.570099, 33.193001], "geom:latitude": 33.193001, "geom:longitude": -87.570099, "geom:hash": "djcsz697hzce", "woe:latitude": 33.193001, "geom:centroid": [-87.570099, 33.193001], "woe:longitude": -87.570099, "woe:repo": "woeplanet-poi-us", "geom:area": 0.0, "woe:scale": 19}}