{"type": "Feature", "id": 23638587, "properties": {"woe:id": 23638587, "woe:parent_id": 2520470, "woe:name": "Aquinas Academy", "woe:placetype": 20, "woe:placetype_name": "POI", "woe:lang": "ENG", "iso:country": "US", "meta:provider": ["geoplanet:7.3.1", "geoplanet:7.3.2", "geoplanet:7.4.0", "geoplanet:7.4.1", "geoplanet:7.5.1", "geoplanet:7.5.2", "geoplanet:7.6.0", "geoplanet:7.8.1", "geoplanet:7.9.0", "geoplanet:7.10.0", "geoplanet:8.0.0", "woeplanet:8.0.0"], "meta:indexed": "2020-08-20T20:18:57.914152", "meta:updated": "2020-08-22T02:57:46.435120", "woe:hierarchy": {"continent": 24865672, "country": 23424977, "town": 0, "planet": 1, "county": 12589729, "suburb": 0, "state": 2347597, "region": 0, "localadmin": 0}, "woe:timezone_id": 56043648, "woe:hash": "dppnuqb9xp7r", "woe:centroid": [-79.968491, 40.5989], "geom:latitude": 40.5989, "geom:longitude": -79.968491, "geom:hash": "dppnuqb9xp7r", "woe:latitude": 40.5989, "geom:centroid": [-79.968491, 40.5989], "woe:longitude": -79.968491, "woe:repo": "woeplanet-poi-us"}, "geometry": {"coordinates": [-79.968491, 40.5989], "type": "Point"}}