{"type": "Feature", "id": 23600217, "properties": {"woe:id": 23600217, "woe:parent_id": 2424767, "woe:name": "Houston Middle School", "woe:placetype": 20, "woe:placetype_name": "POI", "woe:lang": "ENG", "iso:country": "US", "meta:provider": ["geoplanet:7.3.1", "geoplanet:7.3.2", "geoplanet:7.4.0", "geoplanet:7.4.1", "geoplanet:7.5.1", "geoplanet:7.5.2", "geoplanet:7.6.0", "geoplanet:7.8.1", "geoplanet:7.9.0", "geoplanet:7.10.0", "geoplanet:8.0.0", "woeplanet:8.0.0"], "meta:indexed": "2020-08-20T20:18:44.945394", "meta:updated": "2020-08-22T02:57:41.105177", "woe:hierarchy": {"continent": 24865672, "country": 23424977, "town": 0, "planet": 1, "county": 12589073, "suburb": 0, "state": 2347584, "region": 0, "localadmin": 0}, "woe:timezone_id": 56043661, "woe:hash": "9yws77j5mk4u", "woe:centroid": [-91.959457, 37.32663], "geom:latitude": 37.32663, "geom:longitude": -91.959457, "geom:hash": "9yws77j5mk4u", "woe:latitude": 37.32663, "geom:centroid": [-91.959457, 37.32663], "woe:longitude": -91.959457, "woe:repo": "woeplanet-poi-us"}, "geometry": {"coordinates": [-91.959457, 37.32663], "type": "Point"}}