{"type": "Feature", "id": 23675748, "properties": {"woe:id": 23675748, "woe:parent_id": 2362312, "woe:name": "Merrill Elementary School", "woe:placetype": 20, "woe:placetype_name": "POI", "woe:lang": "ENG", "iso:country": "US", "meta:provider": ["geoplanet:7.3.1", "geoplanet:7.3.2", "geoplanet:7.4.0", "geoplanet:7.4.1", "geoplanet:7.5.1", "geoplanet:7.5.2", "geoplanet:7.6.0", "geoplanet:7.8.1", "geoplanet:7.9.0", "geoplanet:7.10.0", "geoplanet:8.0.0", "woeplanet:8.0.0"], "meta:indexed": "2020-08-20T20:19:11.656500", "woe:alias_ENG_V": ["Merrill Elementary"], "meta:updated": "2020-08-22T02:58:18.199342", "woe:hierarchy": {"continent": 24865672, "country": 23424977, "town": 0, "planet": 1, "county": 12590587, "suburb": 0, "state": 2347608, "region": 0, "localadmin": 0}, "woe:timezone_id": 56043661, "woe:hash": "dp89yk0s2cur", "woe:centroid": [-89.021492, 42.51783], "geom:latitude": 42.51783, "geom:longitude": -89.021492, "geom:hash": "dp89yk0s2cur", "woe:latitude": 42.51783, "geom:centroid": [-89.021492, 42.51783], "woe:longitude": -89.021492, "woe:repo": "woeplanet-poi-us"}, "geometry": {"coordinates": [-89.021492, 42.51783], "type": "Point"}}