{"type": "Feature", "id": 23632202, "geometry": {"type": "Point", "coordinates": [-84.157021, 40.29586]}, "properties": {"woe:id": 23632202, "woe:parent_id": 2493393, "woe:name": "Christian Academy Schools", "woe:placetype": 20, "woe:placetype_name": "POI", "woe:lang": "ENG", "iso:country": "US", "meta:provider": ["geoplanet:7.3.2", "geoplanet:7.4.0", "geoplanet:7.4.1", "geoplanet:7.5.1", "geoplanet:7.5.2", "geoplanet:7.6.0", "geoplanet:7.8.1", "geoplanet:7.9.0", "geoplanet:7.10.0", "geoplanet:8.0.0", "woeplanet:8.0.0"], "meta:indexed": "2020-08-20T22:02:43.800877", "meta:updated": "2020-10-14T11:19:39.929509", "woe:hierarchy": {"continent": 24865672, "country": 23424977, "town": 0, "planet": 1, "county": 12589601, "suburb": 0, "state": 2347594, "region": 0, "localadmin": 0}, "woe:timezone_id": 56043648, "woe:hash": "dphjhzwsrk8z", "woe:centroid": [-84.157021, 40.29586], "geom:latitude": 40.29586, "geom:longitude": -84.157021, "geom:hash": "dphjhzwsrk8z", "woe:latitude": 40.29586, "geom:centroid": [-84.157021, 40.29586], "woe:longitude": -84.157021, "woe:repo": "woeplanet-poi-us", "geom:area": 0.0, "woe:scale": 19}}