{"type": "Feature", "id": 23667339, "properties": {"woe:id": 23667339, "woe:parent_id": 2501184, "woe:name": "Suburban Park Elementary School", "woe:placetype": 20, "woe:placetype_name": "POI", "woe:lang": "ENG", "iso:country": "US", "meta:provider": ["geoplanet:7.3.1", "geoplanet:7.3.2", "geoplanet:7.4.0", "geoplanet:7.4.1", "geoplanet:7.5.1", "geoplanet:7.5.2", "geoplanet:7.6.0", "geoplanet:7.8.1", "geoplanet:7.9.0", "geoplanet:7.10.0", "geoplanet:8.0.0", "woeplanet:8.0.0"], "meta:indexed": "2020-08-20T20:19:08.716680", "woe:alias_ENG_V": ["Suburban Park Elementary"], "meta:updated": "2020-08-22T02:57:51.642285", "woe:hierarchy": {"continent": 24865672, "country": 23424977, "town": 0, "planet": 1, "county": 12590391, "suburb": 0, "state": 2347605, "region": 0, "localadmin": 0}, "woe:timezone_id": 56043648, "woe:hash": "dq9cbqqkqrth", "woe:centroid": [-76.269218, 36.90522], "geom:latitude": 36.90522, "geom:longitude": -76.269218, "geom:hash": "dq9cbqqkqrth", "woe:latitude": 36.90522, "geom:centroid": [-76.269218, 36.90522], "woe:longitude": -76.269218, "woe:repo": "woeplanet-poi-us"}, "geometry": {"coordinates": [-76.269218, 36.90522], "type": "Point"}}