{"type": "Feature", "id": 23586973, "geometry": {"type": "Point", "coordinates": [-83.731277, 42.78688]}, "properties": {"woe:id": 23586973, "woe:parent_id": 2402927, "woe:name": "Andrew G. Schmidt Middle School", "woe:placetype": 20, "woe:placetype_name": "POI", "woe:lang": "ENG", "iso:country": "US", "meta:provider": ["geoplanet:7.3.1", "geoplanet:7.3.2", "geoplanet:7.4.0", "geoplanet:7.4.1", "geoplanet:7.5.1", "geoplanet:7.5.2", "geoplanet:7.6.0", "geoplanet:7.8.1", "geoplanet:7.9.0", "geoplanet:7.10.0", "geoplanet:8.0.0", "woeplanet:8.0.0"], "meta:indexed": "2020-08-20T20:18:40.137568", "meta:updated": "2020-10-14T11:20:28.281618", "woe:hierarchy": {"continent": 24865672, "country": 23424977, "town": 0, "planet": 1, "county": 12588738, "suburb": 0, "state": 2347581, "region": 0, "localadmin": 0}, "woe:timezone_id": 56043658, "woe:hash": "dps7qthexud8", "woe:centroid": [-83.731277, 42.78688], "geom:latitude": 42.78688, "geom:longitude": -83.731277, "geom:hash": "dps7qthexud8", "woe:latitude": 42.78688, "geom:centroid": [-83.731277, 42.78688], "woe:longitude": -83.731277, "woe:repo": "woeplanet-poi-us", "geom:area": 0.0, "woe:scale": 19}}