{"type": "Feature", "id": 23526233, "properties": {"woe:id": 23526233, "woe:parent_id": 2505507, "woe:name": "C. T. English Middle School", "woe:placetype": 20, "woe:placetype_name": "POI", "woe:lang": "ENG", "iso:country": "US", "meta:provider": ["geoplanet:7.3.1", "geoplanet:7.3.2", "geoplanet:7.4.0", "geoplanet:7.4.1", "geoplanet:7.5.1", "geoplanet:7.5.2", "geoplanet:7.6.0", "geoplanet:7.8.1", "geoplanet:7.9.0", "geoplanet:7.10.0", "geoplanet:8.0.0", "woeplanet:8.0.0"], "meta:indexed": "2020-08-20T20:18:20.792053", "meta:updated": "2020-08-22T02:57:28.045985", "woe:alias_ENG_V": ["C T English Middle School"], "woe:hierarchy": {"continent": 24865672, "country": 23424977, "town": 0, "planet": 1, "county": 12587713, "suburb": 0, "state": 2347563, "region": 0, "localadmin": 0}, "woe:timezone_id": 56043663, "woe:hash": "9q971q41ry60", "woe:centroid": [-121.934174, 37.123051], "geom:latitude": 37.123051, "geom:longitude": -121.934174, "geom:hash": "9q971q41ry60", "woe:latitude": 37.123051, "geom:centroid": [-121.934174, 37.123051], "woe:longitude": -121.934174, "woe:repo": "woeplanet-poi-us"}, "geometry": {"coordinates": [-121.934174, 37.123051], "type": "Point"}}