{"type": "Feature", "id": 23596510, "properties": {"woe:id": 23596510, "woe:parent_id": 2405015, "woe:name": "Hawkins Middle School", "woe:placetype": 20, "woe:placetype_name": "POI", "woe:lang": "ENG", "iso:country": "US", "meta:provider": ["geoplanet:7.3.1", "geoplanet:7.3.2", "geoplanet:7.4.0", "geoplanet:7.4.1", "geoplanet:7.5.1", "geoplanet:7.5.2", "geoplanet:7.6.0", "geoplanet:7.8.1", "geoplanet:7.9.0", "geoplanet:7.10.0", "geoplanet:8.0.0", "woeplanet:8.0.0"], "meta:indexed": "2020-08-20T20:18:43.524682", "meta:updated": "2020-08-22T02:57:40.475802", "woe:hierarchy": {"continent": 24865672, "country": 23424977, "town": 0, "planet": 1, "county": 12588945, "suburb": 0, "state": 2347583, "region": 0, "localadmin": 0}, "woe:timezone_id": 56043661, "woe:hash": "djb2h4gz1f0f", "woe:centroid": [-89.46743, 32.360069], "geom:latitude": 32.360069, "geom:longitude": -89.46743, "geom:hash": "djb2h4gz1f0f", "woe:latitude": 32.360069, "geom:centroid": [-89.46743, 32.360069], "woe:longitude": -89.46743, "woe:repo": "woeplanet-poi-us"}, "geometry": {"coordinates": [-89.46743, 32.360069], "type": "Point"}}