{"type": "Feature", "id": 23530181, "geometry": {"type": "Point", "coordinates": [-118.142052, 34.091202]}, "properties": {"woe:id": 23530181, "woe:parent_id": 55969053, "woe:name": "Century High School", "woe:placetype": 20, "woe:placetype_name": "POI", "woe:lang": "ENG", "iso:country": "US", "meta:provider": ["geoplanet:7.3.2", "geoplanet:7.4.0", "geoplanet:7.4.1", "geoplanet:7.5.1", "geoplanet:7.5.2", "geoplanet:7.6.0", "geoplanet:7.8.1", "geoplanet:7.9.0", "geoplanet:7.10.0", "geoplanet:8.0.0", "woeplanet:8.0.0"], "meta:indexed": "2020-08-20T22:02:01.599244", "woe:alias_ENG_V": ["Century Senior High School", "Century High", "Century Senior High", "Century HS", "Century Senior HS"], "meta:updated": "2020-10-14T11:20:23.520252", "woe:hierarchy": {"continent": 24865672, "country": 23424977, "town": 0, "planet": 1, "county": 12587688, "suburb": 0, "state": 2347563, "region": 0, "localadmin": 0}, "woe:timezone_id": 56043663, "woe:hash": "9q5czw5edstj", "woe:centroid": [-118.142052, 34.091202], "geom:latitude": 34.091202, "geom:longitude": -118.142052, "geom:hash": "9q5czw5edstj", "woe:latitude": 34.091202, "geom:centroid": [-118.142052, 34.091202], "woe:longitude": -118.142052, "woe:repo": "woeplanet-poi-us", "geom:area": 0.0, "woe:scale": 19}}