{"type": "Feature", "id": 23638041, "geometry": {"type": "Point", "coordinates": [-77.377213, 39.781719]}, "properties": {"woe:id": 23638041, "woe:parent_id": 28745179, "woe:name": "Fairfield Area High School", "woe:placetype": 20, "woe:placetype_name": "POI", "woe:lang": "ENG", "iso:country": "US", "meta:provider": ["geoplanet:7.3.1", "geoplanet:7.3.2", "geoplanet:7.4.0", "geoplanet:7.4.1", "geoplanet:7.5.1", "geoplanet:7.5.2", "geoplanet:7.6.0", "geoplanet:7.8.1", "geoplanet:7.9.0", "geoplanet:7.10.0", "geoplanet:8.0.0", "woeplanet:8.0.0"], "meta:indexed": "2020-08-20T20:18:57.587648", "woe:alias_ENG_V": ["Fairfield Area Senior High School", "Fairfield Area High", "Fairfield Area Senior High", "Fairfield Area HS", "Fairfield Area Senior HS", "Fairfield Area School"], "meta:updated": "2020-10-14T11:19:29.258644", "woe:hierarchy": {"continent": 24865672, "country": 23424977, "town": 0, "planet": 1, "county": 12589728, "suburb": 0, "state": 2347597, "region": 0, "localadmin": 0}, "woe:timezone_id": 56043648, "woe:hash": "dr0fr4p9k3bj", "woe:centroid": [-77.377213, 39.781719], "geom:latitude": 39.781719, "geom:longitude": -77.377213, "geom:hash": "dr0fr4p9k3bj", "woe:latitude": 39.781719, "geom:centroid": [-77.377213, 39.781719], "woe:longitude": -77.377213, "woe:repo": "woeplanet-poi-us", "geom:area": 0.0, "woe:scale": 19}}