{"type": "Feature", "id": 56063903, "properties": {"woe:id": 56063903, "woe:parent_id": 28288777, "woe:name": "Financial Dist Station", "woe:placetype": 20, "woe:placetype_name": "POI", "woe:lang": "ENG", "iso:country": "US", "meta:provider": ["geoplanet:7.3.1", "geoplanet:7.3.2", "geoplanet:7.4.0", "geoplanet:7.4.1", "geoplanet:7.5.1", "geoplanet:7.5.2", "geoplanet:7.6.0", "geoplanet:7.8.1", "geoplanet:7.9.0", "geoplanet:7.10.0", "geoplanet:8.0.0", "woeplanet:8.0.0"], "meta:indexed": "2020-08-20T20:19:20.855060", "woe:alias_ENG_V": ["Financial Dist People Mover Station", "People Mover Financial Dist Station", "People Mover-Financial Dist Station"], "meta:updated": "2020-08-22T02:58:23.015519", "woe:hierarchy": {"continent": 24865672, "country": 23424977, "town": 0, "planet": 1, "county": 12588795, "suburb": 0, "state": 2347581, "region": 0, "localadmin": 0}, "woe:timezone_id": 56043658, "woe:hash": "dpsby1z816j3", "woe:centroid": [-83.04628, 42.32896], "geom:latitude": 42.32896, "geom:longitude": -83.04628, "geom:hash": "dpsby1z816j3", "woe:latitude": 42.32896, "geom:centroid": [-83.04628, 42.32896], "woe:longitude": -83.04628, "woe:repo": "woeplanet-poi-us"}, "geometry": {"coordinates": [-83.04628, 42.32896], "type": "Point"}}