{"type": "Feature", "id": 23668945, "geometry": {"type": "Point", "coordinates": [-122.282997, 47.334751]}, "properties": {"woe:id": 23668945, "woe:parent_id": 2430083, "woe:name": "Camelot Elementary School", "woe:placetype": 20, "woe:placetype_name": "POI", "woe:lang": "ENG", "iso:country": "US", "meta:provider": ["geoplanet:7.3.1", "geoplanet:7.3.2", "geoplanet:7.4.0", "geoplanet:7.4.1", "geoplanet:7.5.1", "geoplanet:7.5.2", "geoplanet:7.6.0", "geoplanet:7.8.1", "geoplanet:7.9.0", "geoplanet:7.10.0", "geoplanet:8.0.0", "woeplanet:8.0.0"], "meta:indexed": "2020-08-20T20:19:09.234485", "woe:alias_ENG_V": ["Camelot Elementary"], "meta:updated": "2020-10-14T11:19:32.269282", "woe:hierarchy": {"continent": 24865672, "country": 23424977, "town": 0, "planet": 1, "county": 12590456, "suburb": 0, "state": 2347606, "region": 0, "localadmin": 0}, "woe:timezone_id": 56043663, "woe:hash": "c23j33h0zths", "woe:centroid": [-122.282997, 47.334751], "geom:latitude": 47.334751, "geom:longitude": -122.282997, "geom:hash": "c23j33h0zths", "woe:latitude": 47.334751, "geom:centroid": [-122.282997, 47.334751], "woe:longitude": -122.282997, "woe:repo": "woeplanet-poi-us", "geom:area": 0.0, "woe:scale": 19}}