{"type": "Feature", "id": 23636111, "geometry": {"type": "Point", "coordinates": [-123.341179, 42.327141]}, "properties": {"woe:id": 23636111, "woe:parent_id": 2456446, "woe:name": "Hidden Valley High School", "woe:placetype": 20, "woe:placetype_name": "POI", "woe:lang": "ENG", "iso:country": "US", "meta:provider": ["geoplanet:7.3.1", "geoplanet:7.3.2", "geoplanet:7.4.0", "geoplanet:7.4.1", "geoplanet:7.5.1", "geoplanet:7.5.2", "geoplanet:7.6.0", "geoplanet:7.8.1", "geoplanet:7.9.0", "geoplanet:7.10.0", "geoplanet:8.0.0", "woeplanet:8.0.0"], "meta:indexed": "2020-08-20T20:18:56.958538", "woe:alias_ENG_V": ["Hidden Valley Senior High School", "Hidden Valley High", "Hidden Valley Senior High", "Hidden Valley HS", "Hidden Valley Senior HS", "Hidden Valley Alternative School"], "meta:updated": "2020-10-14T11:19:49.008361", "woe:hierarchy": {"continent": 24865672, "country": 23424977, "town": 0, "planet": 1, "county": 12589708, "suburb": 0, "state": 2347596, "region": 0, "localadmin": 0}, "woe:timezone_id": 56043663, "woe:hash": "9r82c33tqnzp", "woe:centroid": [-123.341179, 42.327141], "geom:latitude": 42.327141, "geom:longitude": -123.341179, "geom:hash": "9r82c33tqnzp", "woe:latitude": 42.327141, "geom:centroid": [-123.341179, 42.327141], "woe:longitude": -123.341179, "woe:repo": "woeplanet-poi-us", "geom:area": 0.0, "woe:scale": 19}}