{"type": "Feature", "id": 23655410, "properties": {"woe:id": 23655410, "woe:parent_id": 56022754, "woe:name": "Crockett Middle School", "woe:placetype": 20, "woe:placetype_name": "POI", "woe:lang": "ENG", "iso:country": "US", "meta:provider": ["geoplanet:7.3.1", "geoplanet:7.3.2", "geoplanet:7.4.0", "geoplanet:7.4.1", "geoplanet:7.5.1", "geoplanet:7.5.2", "geoplanet:7.6.0", "geoplanet:7.8.1", "geoplanet:7.9.0", "geoplanet:7.10.0", "geoplanet:8.0.0", "woeplanet:8.0.0"], "meta:indexed": "2020-08-20T20:19:03.844035", "meta:updated": "2020-08-22T02:57:49.296021", "woe:hierarchy": {"continent": 24865672, "country": 23424977, "town": 0, "planet": 1, "county": 12590146, "suburb": 0, "state": 2347602, "region": 0, "localadmin": 0}, "woe:timezone_id": 56043661, "woe:hash": "9vup6qb156u5", "woe:centroid": [-95.525978, 33.65543], "geom:latitude": 33.65543, "geom:longitude": -95.525978, "geom:hash": "9vup6qb156u5", "woe:latitude": 33.65543, "geom:centroid": [-95.525978, 33.65543], "woe:longitude": -95.525978, "woe:repo": "woeplanet-poi-us"}, "geometry": {"coordinates": [-95.525978, 33.65543], "type": "Point"}}