{"type": "Feature", "id": 23549051, "geometry": {"type": "Point", "coordinates": [-80.41375, 27.64537]}, "properties": {"woe:id": 23549051, "woe:parent_id": 55984513, "woe:name": "Indian River Academy", "woe:placetype": 20, "woe:placetype_name": "POI", "woe:lang": "ENG", "iso:country": "US", "meta:provider": ["geoplanet:7.3.1", "geoplanet:7.3.2", "geoplanet:7.4.0", "geoplanet:7.4.1", "geoplanet:7.5.1", "geoplanet:7.5.2", "geoplanet:7.6.0", "geoplanet:7.8.1", "geoplanet:7.9.0", "geoplanet:7.10.0", "geoplanet:8.0.0", "woeplanet:8.0.0"], "meta:indexed": "2020-08-20T20:18:27.660379", "meta:updated": "2020-10-14T11:20:26.664253", "woe:hierarchy": {"continent": 24865672, "country": 23424977, "town": 0, "planet": 1, "county": 12587833, "suburb": 0, "state": 2347568, "region": 0, "localadmin": 0}, "woe:timezone_id": 56043648, "woe:hash": "dhyv60smzy6p", "woe:centroid": [-80.41375, 27.64537], "geom:latitude": 27.64537, "geom:longitude": -80.41375, "geom:hash": "dhyv60smzy6p", "woe:latitude": 27.64537, "geom:centroid": [-80.41375, 27.64537], "woe:longitude": -80.41375, "woe:repo": "woeplanet-poi-us", "geom:area": 0.0, "woe:scale": 19}}