{"type": "Feature", "id": 56204600, "geometry": {"type": "Point", "coordinates": [-73.953537, 40.580238]}, "properties": {"woe:id": 56204600, "woe:parent_id": 2444776, "woe:name": "Yeshiva of Manhattan Beach", "woe:placetype": 20, "woe:placetype_name": "POI", "woe:lang": "ENG", "iso:country": "US", "meta:provider": ["geoplanet:7.6.0", "geoplanet:7.8.1", "geoplanet:7.9.0", "geoplanet:7.10.0", "geoplanet:8.0.0", "woeplanet:8.0.0"], "meta:indexed": "2020-08-21T08:24:24.130495", "meta:updated": "2020-10-14T11:20:00.082324", "woe:hierarchy": {"continent": 24865672, "country": 23424977, "town": 0, "planet": 1, "county": 12589335, "suburb": 0, "state": 2347591, "region": 0, "localadmin": 0}, "woe:timezone_id": 56043648, "woe:hash": "dr5qv5ktj8wh", "woe:centroid": [-73.953537, 40.580238], "geom:latitude": 40.580238, "geom:longitude": -73.953537, "geom:hash": "dr5qv5ktj8wh", "woe:latitude": 40.580238, "geom:centroid": [-73.953537, 40.580238], "woe:longitude": -73.953537, "woe:repo": "woeplanet-poi-us", "geom:area": 0.0, "woe:scale": 19}}