{"type": "Feature", "id": 23653789, "properties": {"woe:id": 23653789, "woe:parent_id": 55994167, "woe:name": "Mesquite High School", "woe:placetype": 20, "woe:placetype_name": "POI", "woe:lang": "ENG", "iso:country": "US", "meta:provider": ["geoplanet:7.3.1", "geoplanet:7.3.2", "geoplanet:7.4.0", "geoplanet:7.4.1", "geoplanet:7.5.1", "geoplanet:7.5.2", "geoplanet:7.6.0", "geoplanet:7.8.1", "geoplanet:7.9.0", "geoplanet:7.10.0", "geoplanet:8.0.0", "woeplanet:8.0.0"], "meta:indexed": "2020-08-20T20:19:03.090241", "woe:alias_ENG_V": ["Mesquite Senior High School", "Mesquite High", "Mesquite Senior High", "Mesquite HS", "Mesquite Senior HS"], "meta:updated": "2020-08-22T02:58:49.808182", "woe:hierarchy": {"continent": 24865672, "country": 23424977, "town": 0, "planet": 1, "county": 12590063, "suburb": 0, "state": 2347602, "region": 0, "localadmin": 0}, "woe:timezone_id": 56043661, "woe:hash": "9vg63uv4kupm", "woe:centroid": [-96.595703, 32.765759], "geom:latitude": 32.765759, "geom:longitude": -96.595703, "geom:hash": "9vg63uv4kupm", "woe:latitude": 32.765759, "geom:centroid": [-96.595703, 32.765759], "woe:longitude": -96.595703, "woe:repo": "woeplanet-poi-us"}, "geometry": {"coordinates": [-96.595703, 32.765759], "type": "Point"}}