{"type": "Feature", "id": 23612894, "geometry": {"type": "Point", "coordinates": [-73.860619, 40.88781]}, "properties": {"woe:id": 23612894, "woe:parent_id": 28751559, "woe:name": "Ps 21 Philip H. Sheridan School", "woe:placetype": 20, "woe:placetype_name": "POI", "woe:lang": "ENG", "iso:country": "US", "meta:provider": ["geoplanet:7.3.1", "geoplanet:7.3.2", "geoplanet:7.4.0", "geoplanet:7.4.1", "geoplanet:7.5.1", "geoplanet:7.5.2", "geoplanet:7.6.0", "geoplanet:7.8.1", "geoplanet:7.9.0", "geoplanet:7.10.0", "geoplanet:8.0.0", "woeplanet:8.0.0"], "meta:indexed": "2020-08-20T20:18:48.602906", "meta:updated": "2020-10-14T11:19:29.758975", "woe:hierarchy": {"continent": 24865672, "country": 23424977, "town": 0, "planet": 1, "county": 12589314, "suburb": 0, "state": 2347591, "region": 0, "localadmin": 0}, "woe:timezone_id": 56043648, "woe:hash": "dr72x72kfb4x", "woe:centroid": [-73.860619, 40.88781], "geom:latitude": 40.88781, "geom:longitude": -73.860619, "geom:hash": "dr72x72kfb4x", "woe:latitude": 40.88781, "geom:centroid": [-73.860619, 40.88781], "woe:longitude": -73.860619, "woe:repo": "woeplanet-poi-us", "geom:area": 0.0, "woe:scale": 19}}