{"type": "Feature", "id": 23561215, "geometry": {"type": "Point", "coordinates": [-88.068909, 41.916088]}, "properties": {"woe:id": 23561215, "woe:parent_id": 2411113, "woe:name": "Reskin Elementary School", "woe:placetype": 20, "woe:placetype_name": "POI", "woe:lang": "ENG", "iso:country": "US", "meta:provider": ["geoplanet:7.3.1", "geoplanet:7.3.2", "geoplanet:7.4.0", "geoplanet:7.4.1", "geoplanet:7.5.1", "geoplanet:7.5.2", "geoplanet:7.6.0", "geoplanet:7.8.1", "geoplanet:7.9.0", "geoplanet:7.10.0", "geoplanet:8.0.0", "woeplanet:8.0.0"], "meta:indexed": "2020-08-20T20:18:32.012798", "woe:alias_ENG_V": ["Reskin Elementary"], "meta:updated": "2020-10-14T11:20:17.800087", "woe:hierarchy": {"continent": 24865672, "country": 23424977, "town": 0, "planet": 1, "county": 12588099, "suburb": 0, "state": 2347572, "region": 0, "localadmin": 0}, "woe:timezone_id": 56043661, "woe:hash": "dp3q7yw4vtju", "woe:centroid": [-88.068909, 41.916088], "geom:latitude": 41.916088, "geom:longitude": -88.068909, "geom:hash": "dp3q7yw4vtju", "woe:latitude": 41.916088, "geom:centroid": [-88.068909, 41.916088], "woe:longitude": -88.068909, "woe:repo": "woeplanet-poi-us", "geom:area": 0.0, "woe:scale": 19}}