{"type": "Feature", "id": 23548018, "geometry": {"type": "Point", "coordinates": [-80.160606, 25.997311]}, "properties": {"woe:id": 23548018, "woe:parent_id": 55859685, "woe:name": "Mcnicol Middle School", "woe:placetype": 20, "woe:placetype_name": "POI", "woe:lang": "ENG", "iso:country": "US", "meta:provider": ["geoplanet:7.3.1", "geoplanet:7.3.2", "geoplanet:7.4.0", "geoplanet:7.4.1", "geoplanet:7.5.1", "geoplanet:7.5.2", "geoplanet:7.6.0", "geoplanet:7.8.1", "geoplanet:7.9.0", "geoplanet:7.10.0", "geoplanet:8.0.0", "woeplanet:8.0.0"], "meta:indexed": "2020-08-20T20:18:27.118920", "meta:updated": "2020-10-14T11:20:07.253756", "woe:hierarchy": {"continent": 24865672, "country": 23424977, "town": 0, "planet": 1, "county": 12587808, "suburb": 0, "state": 2347568, "region": 0, "localadmin": 0}, "woe:timezone_id": 56043648, "woe:hash": "dhwgzusv66pb", "woe:centroid": [-80.160606, 25.997311], "geom:latitude": 25.997311, "geom:longitude": -80.160606, "geom:hash": "dhwgzusv66pb", "woe:latitude": 25.997311, "geom:centroid": [-80.160606, 25.997311], "woe:longitude": -80.160606, "woe:repo": "woeplanet-poi-us", "geom:area": 0.0, "woe:scale": 19}}