{"type": "Feature", "id": 23558620, "geometry": {"type": "Point", "coordinates": [-87.668098, 42.00362]}, "properties": {"woe:id": 23558620, "woe:parent_id": 2483814, "woe:name": "Kilmer Elementary School", "woe:placetype": 20, "woe:placetype_name": "POI", "woe:lang": "ENG", "iso:country": "US", "meta:provider": ["geoplanet:7.3.1", "geoplanet:7.3.2", "geoplanet:7.4.0", "geoplanet:7.4.1", "geoplanet:7.5.1", "geoplanet:7.5.2", "geoplanet:7.6.0", "geoplanet:7.8.1", "geoplanet:7.9.0", "geoplanet:7.10.0", "geoplanet:8.0.0", "woeplanet:8.0.0"], "meta:indexed": "2020-08-20T20:18:30.912301", "woe:alias_ENG_V": ["Kilmer Elementary"], "meta:updated": "2020-10-14T11:20:28.977561", "woe:hierarchy": {"continent": 24865672, "country": 23424977, "town": 0, "planet": 1, "county": 12588093, "suburb": 0, "state": 2347572, "region": 0, "localadmin": 0}, "woe:timezone_id": 56043661, "woe:hash": "dp3wvnd0c621", "woe:centroid": [-87.668098, 42.00362], "geom:latitude": 42.00362, "geom:longitude": -87.668098, "geom:hash": "dp3wvnd0c621", "woe:latitude": 42.00362, "geom:centroid": [-87.668098, 42.00362], "woe:longitude": -87.668098, "woe:repo": "woeplanet-poi-us", "geom:area": 0.0, "woe:scale": 19}}