{"type": "Feature", "id": 23586709, "properties": {"woe:id": 23586709, "woe:parent_id": 28743849, "woe:name": "East Essex School", "woe:placetype": 20, "woe:placetype_name": "POI", "woe:lang": "ENG", "iso:country": "US", "meta:provider": ["geoplanet:7.3.1", "geoplanet:7.3.2", "geoplanet:7.4.0", "geoplanet:7.4.1", "geoplanet:7.5.1", "geoplanet:7.5.2", "geoplanet:7.6.0", "geoplanet:7.8.1", "geoplanet:7.9.0", "geoplanet:7.10.0", "geoplanet:8.0.0", "woeplanet:8.0.0"], "meta:indexed": "2020-08-20T20:18:40.058458", "woe:alias_ENG_V": ["E Essex School"], "meta:updated": "2020-08-22T02:57:38.826671", "woe:hierarchy": {"continent": 24865672, "country": 23424977, "town": 0, "planet": 1, "county": 12588732, "suburb": 0, "state": 2347581, "region": 0, "localadmin": 0}, "woe:timezone_id": 56043658, "woe:hash": "dpev40m2swgd", "woe:centroid": [-84.631264, 43.067902], "geom:latitude": 43.067902, "geom:longitude": -84.631264, "geom:hash": "dpev40m2swgd", "woe:latitude": 43.067902, "geom:centroid": [-84.631264, 43.067902], "woe:longitude": -84.631264, "woe:repo": "woeplanet-poi-us"}, "geometry": {"coordinates": [-84.631264, 43.067902], "type": "Point"}}