{"type": "Feature", "id": 23682152, "geometry": {"type": "Point", "coordinates": [-84.406212, 42.24995]}, "properties": {"woe:id": 23682152, "woe:parent_id": 2428185, "woe:name": "Jackson Station", "woe:placetype": 20, "woe:placetype_name": "POI", "woe:lang": "ENG", "iso:country": "US", "meta:provider": ["geoplanet:7.3.1", "geoplanet:7.3.2", "geoplanet:7.4.0", "geoplanet:7.4.1", "geoplanet:7.5.1", "geoplanet:7.5.2", "geoplanet:7.6.0", "geoplanet:7.8.1", "geoplanet:7.9.0", "geoplanet:7.10.0", "geoplanet:8.0.0", "woeplanet:8.0.0"], "meta:indexed": "2020-08-20T20:19:19.508856", "meta:updated": "2020-10-14T11:19:29.180529", "woe:hierarchy": {"continent": 24865672, "country": 23424977, "town": 0, "planet": 1, "county": 12588751, "suburb": 0, "state": 2347581, "region": 0, "localadmin": 0}, "woe:timezone_id": 56043658, "woe:hash": "dpebr737b9w8", "woe:centroid": [-84.406212, 42.24995], "geom:latitude": 42.24995, "geom:longitude": -84.406212, "geom:hash": "dpebr737b9w8", "woe:latitude": 42.24995, "geom:centroid": [-84.406212, 42.24995], "woe:longitude": -84.406212, "woe:repo": "woeplanet-poi-us", "geom:area": 0.0, "woe:scale": 19}}