{"type": "Feature", "id": 23648033, "geometry": {"type": "Point", "coordinates": [-81.930298, 34.941849]}, "properties": {"woe:id": 23648033, "woe:parent_id": 2497370, "woe:name": "Montessori Academy", "woe:placetype": 20, "woe:placetype_name": "POI", "woe:lang": "ENG", "iso:country": "US", "meta:provider": ["geoplanet:7.3.1", "geoplanet:7.3.2", "geoplanet:7.4.0", "geoplanet:7.4.1", "geoplanet:7.5.1", "geoplanet:7.5.2", "geoplanet:7.6.0", "geoplanet:7.8.1", "geoplanet:7.9.0", "geoplanet:7.10.0", "geoplanet:8.0.0", "woeplanet:8.0.0"], "meta:indexed": "2020-08-20T20:19:00.984381", "meta:updated": "2020-10-14T11:19:30.733052", "woe:hierarchy": {"continent": 24865672, "country": 23424977, "town": 0, "planet": 1, "county": 12589841, "suburb": 0, "state": 2347599, "region": 0, "localadmin": 0}, "woe:timezone_id": 56043648, "woe:hash": "dnjwz8upj8vb", "woe:centroid": [-81.930298, 34.941849], "geom:latitude": 34.941849, "geom:longitude": -81.930298, "geom:hash": "dnjwz8upj8vb", "woe:latitude": 34.941849, "geom:centroid": [-81.930298, 34.941849], "woe:longitude": -81.930298, "woe:repo": "woeplanet-poi-us", "geom:area": 0.0, "woe:scale": 19}}