{"type": "Feature", "id": 23544803, "properties": {"woe:id": 23544803, "woe:parent_id": 2494446, "woe:name": "Skyline Middle School", "woe:placetype": 20, "woe:placetype_name": "POI", "woe:lang": "ENG", "iso:country": "US", "meta:provider": ["geoplanet:7.3.1", "geoplanet:7.3.2", "geoplanet:7.4.0", "geoplanet:7.4.1", "geoplanet:7.5.1", "geoplanet:7.5.2", "geoplanet:7.6.0", "geoplanet:7.8.1", "geoplanet:7.9.0", "geoplanet:7.10.0", "geoplanet:8.0.0", "woeplanet:8.0.0"], "meta:indexed": "2020-08-20T20:18:25.714201", "meta:updated": "2020-08-22T02:57:31.405128", "woe:hierarchy": {"continent": 24865672, "country": 23424977, "town": 0, "planet": 1, "county": 12587800, "suburb": 0, "state": 2347566, "region": 0, "localadmin": 0}, "woe:timezone_id": 56043648, "woe:hash": "dr41vz8rgytk", "woe:centroid": [-75.684303, 39.725182], "geom:latitude": 39.725182, "geom:longitude": -75.684303, "geom:hash": "dr41vz8rgytk", "woe:latitude": 39.725182, "geom:centroid": [-75.684303, 39.725182], "woe:longitude": -75.684303, "woe:repo": "woeplanet-poi-us"}, "geometry": {"coordinates": [-75.684303, 39.725182], "type": "Point"}}