{"type": "Feature", "id": 23558424, "properties": {"woe:id": 23558424, "woe:parent_id": 2496092, "woe:name": "Bowen High School", "woe:placetype": 20, "woe:placetype_name": "POI", "woe:lang": "ENG", "iso:country": "US", "meta:provider": ["geoplanet:7.3.1", "geoplanet:7.3.2", "geoplanet:7.4.0", "geoplanet:7.4.1", "geoplanet:7.5.1", "geoplanet:7.5.2", "geoplanet:7.6.0", "geoplanet:7.8.1", "geoplanet:7.9.0", "geoplanet:7.10.0", "geoplanet:8.0.0", "woeplanet:8.0.0"], "meta:indexed": "2020-08-20T20:18:30.773054", "woe:alias_ENG_V": ["Bowen Senior High School", "Bowen High", "Bowen Senior High", "Bowen HS", "Bowen Senior HS"], "meta:updated": "2020-08-22T02:58:46.981731", "woe:hierarchy": {"continent": 24865672, "country": 23424977, "town": 0, "planet": 1, "county": 12588093, "suburb": 0, "state": 2347572, "region": 0, "localadmin": 0}, "woe:timezone_id": 56043661, "woe:hash": "dp3trt65vhmh", "woe:centroid": [-87.558067, 41.733608], "geom:latitude": 41.733608, "geom:longitude": -87.558067, "geom:hash": "dp3trt65vhmh", "woe:latitude": 41.733608, "geom:centroid": [-87.558067, 41.733608], "woe:longitude": -87.558067, "woe:repo": "woeplanet-poi-us"}, "geometry": {"coordinates": [-87.558067, 41.733608], "type": "Point"}}