{"type": "Feature", "id": 23551209, "properties": {"woe:id": 23551209, "woe:parent_id": 2375700, "woe:name": "Cartersville High School", "woe:placetype": 20, "woe:placetype_name": "POI", "woe:lang": "ENG", "iso:country": "US", "meta:provider": ["geoplanet:7.3.1", "geoplanet:7.3.2", "geoplanet:7.4.0", "geoplanet:7.4.1", "geoplanet:7.5.1", "geoplanet:7.5.2", "geoplanet:7.6.0", "geoplanet:7.8.1", "geoplanet:7.9.0", "geoplanet:7.10.0", "geoplanet:8.0.0", "woeplanet:8.0.0"], "meta:indexed": "2020-08-20T20:18:28.763983", "woe:alias_ENG_V": ["Cartersville Senior High School", "Cartersville High", "Cartersville Senior High", "Cartersville HS", "Cartersville Senior HS"], "meta:updated": "2020-08-22T02:58:46.814779", "woe:hierarchy": {"continent": 24865672, "country": 23424977, "town": 0, "planet": 1, "county": 12587877, "suburb": 0, "state": 2347569, "region": 0, "localadmin": 0}, "woe:timezone_id": 56043648, "woe:hash": "dn5dqs4rpm10", "woe:centroid": [-84.789078, 34.168709], "geom:latitude": 34.168709, "geom:longitude": -84.789078, "geom:hash": "dn5dqs4rpm10", "woe:latitude": 34.168709, "geom:centroid": [-84.789078, 34.168709], "woe:longitude": -84.789078, "woe:repo": "woeplanet-poi-us"}, "geometry": {"coordinates": [-84.789078, 34.168709], "type": "Point"}}