{"type": "Feature", "id": 56204179, "properties": {"woe:id": 56204179, "woe:parent_id": 55860944, "woe:name": "Icon Gallery", "woe:placetype": 20, "woe:placetype_name": "POI", "woe:lang": "ENG", "iso:country": "US", "meta:provider": ["geoplanet:7.6.0", "geoplanet:7.8.1", "geoplanet:7.9.0", "geoplanet:7.10.0", "geoplanet:8.0.0", "woeplanet:8.0.0"], "meta:indexed": "2020-08-21T08:24:23.783356", "meta:updated": "2020-08-22T02:58:24.022468", "woe:hierarchy": {"continent": 24865672, "country": 23424977, "town": 0, "planet": 1, "county": 12587712, "suburb": 0, "state": 2347563, "region": 0, "localadmin": 0}, "woe:timezone_id": 56043663, "woe:hash": "9q9jh0tpsv3g", "woe:centroid": [-122.160896, 37.445469], "geom:latitude": 37.445469, "geom:longitude": -122.160896, "geom:hash": "9q9jh0tpsv3g", "woe:latitude": 37.445469, "geom:centroid": [-122.160896, 37.445469], "woe:longitude": -122.160896, "woe:repo": "woeplanet-poi-us"}, "geometry": {"coordinates": [-122.160896, 37.445469], "type": "Point"}}