{"type": "Feature", "id": 23514490, "properties": {"woe:id": 23514490, "woe:parent_id": 2503309, "woe:name": "Indian Valley Elementary School", "woe:placetype": 20, "woe:placetype_name": "POI", "woe:lang": "ENG", "iso:country": "US", "meta:provider": ["geoplanet:7.3.1", "geoplanet:7.3.2", "geoplanet:7.4.0", "geoplanet:7.4.1", "geoplanet:7.5.1", "geoplanet:7.5.2", "geoplanet:7.6.0", "geoplanet:7.8.1", "geoplanet:7.9.0", "geoplanet:7.10.0", "geoplanet:8.0.0", "woeplanet:8.0.0"], "meta:indexed": "2020-08-20T20:18:17.759357", "woe:alias_ENG_V": ["Indian Valley Elementary"], "meta:updated": "2020-08-22T02:57:26.389004", "woe:hierarchy": {"continent": 24865672, "country": 23424977, "town": 0, "planet": 1, "county": 12587547, "suburb": 0, "state": 2347559, "region": 0, "localadmin": 0}, "woe:timezone_id": 56043661, "woe:hash": "djfsvf3v3cnv", "woe:centroid": [-86.229202, 33.191978], "geom:latitude": 33.191978, "geom:longitude": -86.229202, "geom:hash": "djfsvf3v3cnv", "woe:latitude": 33.191978, "geom:centroid": [-86.229202, 33.191978], "woe:longitude": -86.229202, "woe:repo": "woeplanet-poi-us"}, "geometry": {"coordinates": [-86.229202, 33.191978], "type": "Point"}}