{"type": "Feature", "id": 23577808, "properties": {"woe:id": 23577808, "woe:parent_id": 2427941, "woe:name": "West Baton Rouge Vocational Skills Center", "woe:placetype": 20, "woe:placetype_name": "POI", "woe:lang": "ENG", "iso:country": "US", "meta:provider": ["geoplanet:7.3.1", "geoplanet:7.3.2", "geoplanet:7.4.0", "geoplanet:7.4.1", "geoplanet:7.5.1", "geoplanet:7.5.2", "geoplanet:7.6.0", "geoplanet:7.8.1", "geoplanet:7.9.0", "geoplanet:7.10.0", "geoplanet:8.0.0", "woeplanet:8.0.0"], "meta:indexed": "2020-08-20T20:18:38.022875", "woe:alias_ENG_V": ["W Baton Rouge Vocational Skills Center"], "meta:updated": "2020-08-22T02:57:37.488570", "woe:hierarchy": {"continent": 24865672, "country": 23424977, "town": 0, "planet": 1, "county": 12588656, "suburb": 0, "state": 2347577, "region": 0, "localadmin": 0}, "woe:timezone_id": 56043661, "woe:hash": "9vrj734zq01k", "woe:centroid": [-91.259392, 30.46084], "geom:latitude": 30.46084, "geom:longitude": -91.259392, "geom:hash": "9vrj734zq01k", "woe:latitude": 30.46084, "geom:centroid": [-91.259392, 30.46084], "woe:longitude": -91.259392, "woe:repo": "woeplanet-poi-us"}, "geometry": {"coordinates": [-91.259392, 30.46084], "type": "Point"}}