{"type": "Feature", "id": 23554082, "geometry": {"type": "Point", "coordinates": [-82.02298, 33.370579]}, "properties": {"woe:id": 23554082, "woe:parent_id": 28745775, "woe:name": "Gracewood Elementary School", "woe:placetype": 20, "woe:placetype_name": "POI", "woe:lang": "ENG", "iso:country": "US", "meta:provider": ["geoplanet:7.3.1", "geoplanet:7.3.2", "geoplanet:7.4.0", "geoplanet:7.4.1", "geoplanet:7.5.1", "geoplanet:7.5.2", "geoplanet:7.6.0", "geoplanet:7.8.1", "geoplanet:7.9.0", "geoplanet:7.10.0", "geoplanet:8.0.0", "woeplanet:8.0.0"], "meta:indexed": "2020-08-20T20:18:29.800627", "woe:alias_ENG_V": ["Gracewood Elementary"], "meta:updated": "2020-10-14T11:20:13.783987", "woe:hierarchy": {"continent": 24865672, "country": 23424977, "town": 0, "planet": 1, "county": 12587990, "suburb": 0, "state": 2347569, "region": 0, "localadmin": 0}, "woe:timezone_id": 56043648, "woe:hash": "djvtvdbtwnc1", "woe:centroid": [-82.02298, 33.370579], "geom:latitude": 33.370579, "geom:longitude": -82.02298, "geom:hash": "djvtvdbtwnc1", "woe:latitude": 33.370579, "geom:centroid": [-82.02298, 33.370579], "woe:longitude": -82.02298, "woe:repo": "woeplanet-poi-us", "geom:area": 0.0, "woe:scale": 19}}