{"type": "Feature", "id": 23552821, "properties": {"woe:id": 23552821, "woe:parent_id": 2485064, "woe:name": "Roswell High School", "woe:placetype": 20, "woe:placetype_name": "POI", "woe:lang": "ENG", "iso:country": "US", "meta:provider": ["geoplanet:7.3.1", "geoplanet:7.3.2", "geoplanet:7.4.0", "geoplanet:7.4.1", "geoplanet:7.5.1", "geoplanet:7.5.2", "geoplanet:7.6.0", "geoplanet:7.8.1", "geoplanet:7.9.0", "geoplanet:7.10.0", "geoplanet:8.0.0", "woeplanet:8.0.0"], "meta:indexed": "2020-08-20T20:18:29.417384", "woe:alias_ENG_V": ["Roswell Senior High School", "Roswell High", "Roswell Senior High", "Roswell HS", "Roswell Senior HS"], "meta:updated": "2020-08-22T02:58:46.865033", "woe:hierarchy": {"continent": 24865672, "country": 23424977, "town": 0, "planet": 1, "county": 12587929, "suburb": 0, "state": 2347569, "region": 0, "localadmin": 0}, "woe:timezone_id": 56043648, "woe:hash": "dn5czbcz752v", "woe:centroid": [-84.383453, 34.063], "geom:latitude": 34.063, "geom:longitude": -84.383453, "geom:hash": "dn5czbcz752v", "woe:latitude": 34.063, "geom:centroid": [-84.383453, 34.063], "woe:longitude": -84.383453, "woe:repo": "woeplanet-poi-us"}, "geometry": {"coordinates": [-84.383453, 34.063], "type": "Point"}}