{"type": "Feature", "id": 23575489, "geometry": {"type": "Point", "coordinates": [-90.985451, 30.101891]}, "properties": {"woe:id": 23575489, "woe:parent_id": 2392832, "woe:name": "Ascension Catholic High School", "woe:placetype": 20, "woe:placetype_name": "POI", "woe:lang": "ENG", "iso:country": "US", "meta:provider": ["geoplanet:7.3.1", "geoplanet:7.3.2", "geoplanet:7.4.0", "geoplanet:7.4.1", "geoplanet:7.5.1", "geoplanet:7.5.2", "geoplanet:7.6.0", "geoplanet:7.8.1", "geoplanet:7.9.0", "geoplanet:7.10.0", "geoplanet:8.0.0", "woeplanet:8.0.0"], "meta:indexed": "2020-08-20T20:18:37.189868", "woe:alias_ENG_V": ["Ascension Catholic Senior High School", "Ascension Catholic High", "Ascension Catholic Senior High", "Ascension Catholic HS", "Ascension Catholic Senior HS"], "meta:updated": "2020-10-14T11:20:07.590956", "woe:hierarchy": {"continent": 24865672, "country": 23424977, "town": 0, "planet": 1, "county": 12588598, "suburb": 0, "state": 2347577, "region": 0, "localadmin": 0}, "woe:timezone_id": 56043661, "woe:hash": "9vr71xfkjr4q", "woe:centroid": [-90.985451, 30.101891], "geom:latitude": 30.101891, "geom:longitude": -90.985451, "geom:hash": "9vr71xfkjr4q", "woe:latitude": 30.101891, "geom:centroid": [-90.985451, 30.101891], "woe:longitude": -90.985451, "woe:repo": "woeplanet-poi-us", "geom:area": 0.0, "woe:scale": 19}}