{"type": "Feature", "id": 23576552, "geometry": {"type": "Point", "coordinates": [-92.009529, 30.286949]}, "properties": {"woe:id": 23576552, "woe:parent_id": 2434560, "woe:name": "Evangeline Elementary School", "woe:placetype": 20, "woe:placetype_name": "POI", "woe:lang": "ENG", "iso:country": "US", "meta:provider": ["geoplanet:7.3.1", "geoplanet:7.3.2", "geoplanet:7.4.0", "geoplanet:7.4.1", "geoplanet:7.5.1", "geoplanet:7.5.2", "geoplanet:7.6.0", "geoplanet:7.8.1", "geoplanet:7.9.0", "geoplanet:7.10.0", "geoplanet:8.0.0", "woeplanet:8.0.0"], "meta:indexed": "2020-08-20T20:18:37.577529", "woe:alias_ENG_V": ["Evangeline Elementary"], "meta:updated": "2020-10-14T11:20:13.056190", "woe:hierarchy": {"continent": 24865672, "country": 23424977, "town": 0, "planet": 1, "county": 12588624, "suburb": 0, "state": 2347577, "region": 0, "localadmin": 0}, "woe:timezone_id": 56043661, "woe:hash": "9vqs638dq8d8", "woe:centroid": [-92.009529, 30.286949], "geom:latitude": 30.286949, "geom:longitude": -92.009529, "geom:hash": "9vqs638dq8d8", "woe:latitude": 30.286949, "geom:centroid": [-92.009529, 30.286949], "woe:longitude": -92.009529, "woe:repo": "woeplanet-poi-us", "geom:area": 0.0, "woe:scale": 19}}