{"type": "Feature", "id": 23573561, "geometry": {"type": "Point", "coordinates": [-84.067146, 37.968971]}, "properties": {"woe:id": 23573561, "woe:parent_id": 2471845, "woe:name": "Pilot View Elementary School", "woe:placetype": 20, "woe:placetype_name": "POI", "woe:lang": "ENG", "iso:country": "US", "meta:provider": ["geoplanet:7.3.2", "geoplanet:7.4.0", "geoplanet:7.4.1", "geoplanet:7.5.1", "geoplanet:7.5.2", "geoplanet:7.6.0", "geoplanet:7.8.1", "geoplanet:7.9.0", "geoplanet:7.10.0", "geoplanet:8.0.0", "woeplanet:8.0.0"], "meta:indexed": "2020-08-20T22:02:20.142855", "woe:alias_ENG_V": ["Pilot View Elementary"], "meta:updated": "2020-10-14T11:20:10.975110", "woe:hierarchy": {"continent": 24865672, "country": 23424977, "town": 0, "planet": 1, "county": 12588500, "suburb": 0, "state": 2347576, "region": 0, "localadmin": 0}, "woe:timezone_id": 56043647, "woe:hash": "dnu0p001m90w", "woe:centroid": [-84.067146, 37.968971], "geom:latitude": 37.968971, "geom:longitude": -84.067146, "geom:hash": "dnu0p001m90w", "woe:latitude": 37.968971, "geom:centroid": [-84.067146, 37.968971], "woe:longitude": -84.067146, "woe:repo": "woeplanet-poi-us", "geom:area": 0.0, "woe:scale": 19}}