{"type": "Feature", "id": 23625589, "geometry": {"type": "Point", "coordinates": [-79.42588, 35.138039]}, "properties": {"woe:id": 23625589, "woe:parent_id": 2351554, "woe:name": "Aberdeen Elementary School", "woe:placetype": 20, "woe:placetype_name": "POI", "woe:lang": "ENG", "iso:country": "US", "meta:provider": ["geoplanet:7.3.1", "geoplanet:7.3.2", "geoplanet:7.4.0", "geoplanet:7.4.1", "geoplanet:7.5.1", "geoplanet:7.5.2", "geoplanet:7.6.0", "geoplanet:7.8.1", "geoplanet:7.9.0", "geoplanet:7.10.0", "geoplanet:8.0.0", "woeplanet:8.0.0"], "meta:indexed": "2020-08-20T20:18:52.896107", "woe:alias_ENG_V": ["Aberdeen Elementary"], "meta:updated": "2020-10-14T11:19:34.381152", "woe:hierarchy": {"continent": 24865672, "country": 23424977, "town": 0, "planet": 1, "county": 12589436, "suburb": 0, "state": 2347592, "region": 0, "localadmin": 0}, "woe:timezone_id": 56043648, "woe:hash": "dnpxbsevfv5r", "woe:centroid": [-79.42588, 35.138039], "geom:latitude": 35.138039, "geom:longitude": -79.42588, "geom:hash": "dnpxbsevfv5r", "woe:latitude": 35.138039, "geom:centroid": [-79.42588, 35.138039], "woe:longitude": -79.42588, "woe:repo": "woeplanet-poi-us", "geom:area": 0.0, "woe:scale": 19}}