{"type": "Feature", "id": 23608917, "properties": {"woe:id": 23608917, "woe:parent_id": 2407479, "woe:name": "Edith Ort Thomas Elementary School", "woe:placetype": 20, "woe:placetype_name": "POI", "woe:lang": "ENG", "iso:country": "US", "meta:provider": ["geoplanet:7.3.1", "geoplanet:7.3.2", "geoplanet:7.4.0", "geoplanet:7.4.1", "geoplanet:7.5.1", "geoplanet:7.5.2", "geoplanet:7.6.0", "geoplanet:7.8.1", "geoplanet:7.9.0", "geoplanet:7.10.0", "geoplanet:8.0.0", "woeplanet:8.0.0"], "meta:indexed": "2020-08-20T20:18:47.345469", "woe:alias_ENG_V": ["Edith Ort Thomas Elementary"], "meta:updated": "2020-08-22T02:57:42.170514", "woe:hierarchy": {"continent": 24865672, "country": 23424977, "town": 0, "planet": 1, "county": 12589267, "suburb": 0, "state": 2347589, "region": 0, "localadmin": 0}, "woe:timezone_id": 56043648, "woe:hash": "dr4wefvp898y", "woe:centroid": [-75.062691, 40.533981], "geom:latitude": 40.533981, "geom:longitude": -75.062691, "geom:hash": "dr4wefvp898y", "woe:latitude": 40.533981, "geom:centroid": [-75.062691, 40.533981], "woe:longitude": -75.062691, "woe:repo": "woeplanet-poi-us"}, "geometry": {"coordinates": [-75.062691, 40.533981], "type": "Point"}}