{"type": "Feature", "id": 23526444, "geometry": {"type": "Point", "coordinates": [-121.919319, 37.255371]}, "properties": {"woe:id": 23526444, "woe:parent_id": 55971271, "woe:name": "Oster Elementary School", "woe:placetype": 20, "woe:placetype_name": "POI", "woe:lang": "ENG", "iso:country": "US", "meta:provider": ["geoplanet:7.3.2", "geoplanet:7.4.0", "geoplanet:7.4.1", "geoplanet:7.5.1", "geoplanet:7.5.2", "geoplanet:7.6.0", "geoplanet:7.8.1", "geoplanet:7.9.0", "geoplanet:7.10.0", "geoplanet:8.0.0", "woeplanet:8.0.0"], "meta:indexed": "2020-08-20T22:02:00.397942", "woe:alias_ENG_V": ["Oster Elementary"], "meta:updated": "2020-10-14T11:20:04.192659", "woe:hierarchy": {"continent": 24865672, "country": 23424977, "town": 0, "planet": 1, "county": 12587712, "suburb": 0, "state": 2347563, "region": 0, "localadmin": 0}, "woe:timezone_id": 56043663, "woe:hash": "9q97cwjh3bw8", "woe:centroid": [-121.919319, 37.255371], "geom:latitude": 37.255371, "geom:longitude": -121.919319, "geom:hash": "9q97cwjh3bw8", "woe:latitude": 37.255371, "geom:centroid": [-121.919319, 37.255371], "woe:longitude": -121.919319, "woe:repo": "woeplanet-poi-us", "geom:area": 0.0, "woe:scale": 19}}