{"type": "Feature", "id": 56204015, "geometry": {"type": "Point", "coordinates": [-122.410507, 37.78204]}, "properties": {"woe:id": 56204015, "woe:parent_id": 23512024, "woe:name": "Luggage Store", "woe:placetype": 20, "woe:placetype_name": "POI", "woe:lang": "ENG", "iso:country": "US", "meta:provider": ["geoplanet:7.6.0", "geoplanet:7.8.1", "geoplanet:7.9.0", "geoplanet:7.10.0", "geoplanet:8.0.0", "woeplanet:8.0.0"], "meta:indexed": "2020-08-21T08:24:23.663543", "meta:updated": "2020-10-14T11:19:58.984835", "woe:hierarchy": {"continent": 24865672, "country": 23424977, "town": 0, "planet": 1, "county": 12587707, "suburb": 0, "state": 2347563, "region": 0, "localadmin": 0}, "woe:timezone_id": 56043663, "woe:hash": "9q8yyqp2k6wr", "woe:centroid": [-122.410507, 37.78204], "geom:latitude": 37.78204, "geom:longitude": -122.410507, "geom:hash": "9q8yyqp2k6wr", "woe:latitude": 37.78204, "geom:centroid": [-122.410507, 37.78204], "woe:longitude": -122.410507, "woe:repo": "woeplanet-poi-us", "geom:area": 0.0, "woe:scale": 19}}