{"type": "Feature", "id": 23625620, "properties": {"woe:id": 23625620, "woe:parent_id": 2508333, "woe:name": "Tryon Elementary School", "woe:placetype": 20, "woe:placetype_name": "POI", "woe:lang": "ENG", "iso:country": "US", "meta:provider": ["geoplanet:7.3.2", "geoplanet:7.4.0", "geoplanet:7.4.1", "geoplanet:7.5.1", "geoplanet:7.5.2", "geoplanet:7.6.0", "geoplanet:7.8.1", "geoplanet:7.9.0", "geoplanet:7.10.0", "geoplanet:8.0.0", "woeplanet:8.0.0"], "meta:indexed": "2020-08-20T22:02:40.597883", "woe:alias_ENG_V": ["Tryon Elementary"], "meta:updated": "2020-08-22T02:57:44.465505", "woe:hierarchy": {"continent": 24865672, "country": 23424977, "town": 0, "planet": 1, "county": 12589448, "suburb": 0, "state": 2347592, "region": 0, "localadmin": 0}, "woe:timezone_id": 56043648, "woe:hash": "dnm826rgf663", "woe:centroid": [-82.243896, 35.213211], "geom:latitude": 35.213211, "geom:longitude": -82.243896, "geom:hash": "dnm826rgf663", "woe:latitude": 35.213211, "geom:centroid": [-82.243896, 35.213211], "woe:longitude": -82.243896, "woe:repo": "woeplanet-poi-us"}, "geometry": {"coordinates": [-82.243896, 35.213211], "type": "Point"}}