{"type": "Feature", "id": 23650414, "geometry": {"type": "Point", "coordinates": [-88.29425, 36.300819]}, "properties": {"woe:id": 23650414, "woe:parent_id": 2468280, "woe:name": "W G Rhea Elementary School", "woe:placetype": 20, "woe:placetype_name": "POI", "woe:lang": "ENG", "iso:country": "US", "meta:provider": ["geoplanet:7.3.2", "geoplanet:7.4.0", "geoplanet:7.4.1", "geoplanet:7.5.1", "geoplanet:7.5.2", "geoplanet:7.6.0", "geoplanet:7.8.1", "geoplanet:7.9.0", "geoplanet:7.10.0", "geoplanet:8.0.0", "woeplanet:8.0.0"], "meta:indexed": "2020-08-20T22:02:51.058207", "woe:alias_ENG_V": ["W G Rhea Elementary"], "meta:updated": "2020-10-14T11:19:54.494701", "woe:hierarchy": {"continent": 24865672, "country": 23424977, "town": 0, "planet": 1, "county": 12589951, "suburb": 0, "state": 2347601, "region": 0, "localadmin": 0}, "woe:timezone_id": 56043661, "woe:hash": "dn3nwb65dg5k", "woe:centroid": [-88.29425, 36.300819], "geom:latitude": 36.300819, "geom:longitude": -88.29425, "geom:hash": "dn3nwb65dg5k", "woe:latitude": 36.300819, "geom:centroid": [-88.29425, 36.300819], "woe:longitude": -88.29425, "woe:repo": "woeplanet-poi-us", "geom:area": 0.0, "woe:scale": 19}}