{"type": "Feature", "id": 23551347, "geometry": {"type": "Point", "coordinates": [-81.992538, 33.083481]}, "properties": {"woe:id": 23551347, "woe:parent_id": 2515659, "woe:name": "Burke County Middle School", "woe:placetype": 20, "woe:placetype_name": "POI", "woe:lang": "ENG", "iso:country": "US", "meta:provider": ["geoplanet:7.3.2", "geoplanet:7.4.0", "geoplanet:7.4.1", "geoplanet:7.5.1", "geoplanet:7.5.2", "geoplanet:7.6.0", "geoplanet:7.8.1", "geoplanet:7.9.0", "geoplanet:7.10.0", "geoplanet:8.0.0", "woeplanet:8.0.0"], "meta:indexed": "2020-08-20T22:02:10.784046", "meta:updated": "2020-10-14T11:20:22.078684", "woe:hierarchy": {"continent": 24865672, "country": 23424977, "town": 0, "planet": 1, "county": 12587886, "suburb": 0, "state": 2347569, "region": 0, "localadmin": 0}, "woe:timezone_id": 56043648, "woe:hash": "djvsnnwv5ru7", "woe:centroid": [-81.992538, 33.083481], "geom:latitude": 33.083481, "geom:longitude": -81.992538, "geom:hash": "djvsnnwv5ru7", "woe:latitude": 33.083481, "geom:centroid": [-81.992538, 33.083481], "woe:longitude": -81.992538, "woe:repo": "woeplanet-poi-us", "geom:area": 0.0, "woe:scale": 19}}