{"type": "Feature", "id": 23618945, "properties": {"woe:id": 23618945, "woe:parent_id": 2469188, "woe:name": "Brewster High School", "woe:placetype": 20, "woe:placetype_name": "POI", "woe:lang": "ENG", "iso:country": "US", "meta:provider": ["geoplanet:7.3.1", "geoplanet:7.3.2", "geoplanet:7.4.0", "geoplanet:7.4.1", "geoplanet:7.5.1", "geoplanet:7.5.2", "geoplanet:7.6.0", "geoplanet:7.8.1", "geoplanet:7.9.0", "geoplanet:7.10.0", "geoplanet:8.0.0", "woeplanet:8.0.0"], "meta:indexed": "2020-08-20T20:18:51.016471", "woe:alias_ENG_V": ["Brewster Senior High School", "Brewster High", "Brewster Senior High", "Brewster HS", "Brewster Senior HS"], "meta:updated": "2020-08-22T02:58:48.804672", "woe:hierarchy": {"continent": 24865672, "country": 23424977, "town": 0, "planet": 1, "county": 12589351, "suburb": 0, "state": 2347591, "region": 0, "localadmin": 0}, "woe:timezone_id": 56043648, "woe:hash": "dr7ev0h4segy", "woe:centroid": [-73.602707, 41.44088], "geom:latitude": 41.44088, "geom:longitude": -73.602707, "geom:hash": "dr7ev0h4segy", "woe:latitude": 41.44088, "geom:centroid": [-73.602707, 41.44088], "woe:longitude": -73.602707, "woe:repo": "woeplanet-poi-us"}, "geometry": {"coordinates": [-73.602707, 41.44088], "type": "Point"}}