{"type": "Feature", "id": 23514012, "properties": {"woe:id": 23514012, "woe:parent_id": 55860229, "woe:name": "Our Lady of Lourdes School", "woe:placetype": 20, "woe:placetype_name": "POI", "woe:lang": "ENG", "iso:country": "US", "meta:provider": ["geoplanet:7.3.1", "geoplanet:7.3.2", "geoplanet:7.4.0", "geoplanet:7.4.1", "geoplanet:7.5.1", "geoplanet:7.5.2", "geoplanet:7.6.0", "geoplanet:7.8.1", "geoplanet:7.9.0", "geoplanet:7.10.0", "geoplanet:8.0.0", "woeplanet:8.0.0"], "meta:indexed": "2020-08-20T20:18:17.595063", "meta:updated": "2020-08-22T02:57:26.315642", "woe:hierarchy": {"continent": 24865672, "country": 23424977, "town": 0, "planet": 1, "county": 12587535, "suburb": 0, "state": 2347559, "region": 0, "localadmin": 0}, "woe:timezone_id": 56043661, "woe:hash": "dj3q59qnt5uy", "woe:centroid": [-88.079918, 30.593941], "geom:latitude": 30.593941, "geom:longitude": -88.079918, "geom:hash": "dj3q59qnt5uy", "woe:latitude": 30.593941, "geom:centroid": [-88.079918, 30.593941], "woe:longitude": -88.079918, "woe:repo": "woeplanet-poi-us"}, "geometry": {"coordinates": [-88.079918, 30.593941], "type": "Point"}}