{"type": "Feature", "id": 56063936, "geometry": {"type": "Point", "coordinates": [-78.877258, 42.87664]}, "properties": {"woe:id": 56063936, "woe:parent_id": 28288827, "woe:name": "Special Events Station", "woe:placetype": 20, "woe:placetype_name": "POI", "woe:lang": "ENG", "iso:country": "US", "meta:provider": ["geoplanet:7.3.1", "geoplanet:7.3.2", "geoplanet:7.4.0", "geoplanet:7.4.1", "geoplanet:7.5.1", "geoplanet:7.5.2", "geoplanet:7.6.0", "geoplanet:7.8.1", "geoplanet:7.9.0", "geoplanet:7.10.0", "geoplanet:8.0.0", "woeplanet:8.0.0"], "meta:indexed": "2020-08-20T20:19:20.876358", "woe:alias_ENG_V": ["Special Events Metro Rail Station", "Metro Rail Special Events Station", "Metro Rail-Special Events Station"], "meta:updated": "2020-10-14T11:19:56.089115", "woe:hierarchy": {"continent": 24865672, "country": 23424977, "town": 0, "planet": 1, "county": 12589326, "suburb": 0, "state": 2347591, "region": 0, "localadmin": 0}, "woe:timezone_id": 56043648, "woe:hash": "dpxgvj7qd9j8", "woe:centroid": [-78.877258, 42.87664], "geom:latitude": 42.87664, "geom:longitude": -78.877258, "geom:hash": "dpxgvj7qd9j8", "woe:latitude": 42.87664, "geom:centroid": [-78.877258, 42.87664], "woe:longitude": -78.877258, "woe:repo": "woeplanet-poi-us", "geom:area": 0.0, "woe:scale": 19}}