{"type": "Feature", "id": 23616672, "geometry": {"type": "Point", "coordinates": [-73.653458, 40.651699]}, "properties": {"woe:id": 23616672, "woe:parent_id": 2464124, "woe:name": "Riverside School", "woe:placetype": 20, "woe:placetype_name": "POI", "woe:lang": "ENG", "iso:country": "US", "meta:provider": ["geoplanet:7.3.1", "geoplanet:7.3.2", "geoplanet:7.4.0", "geoplanet:7.4.1", "geoplanet:7.5.1", "geoplanet:7.5.2", "geoplanet:7.6.0", "geoplanet:7.8.1", "geoplanet:7.9.0", "geoplanet:7.10.0", "geoplanet:8.0.0", "woeplanet:8.0.0"], "meta:indexed": "2020-08-20T20:18:50.112943", "meta:updated": "2020-10-14T11:19:40.448776", "woe:hierarchy": {"continent": 24865672, "country": 23424977, "town": 0, "planet": 1, "county": 12589341, "suburb": 0, "state": 2347591, "region": 0, "localadmin": 0}, "woe:timezone_id": 56043648, "woe:hash": "dr5x7brjq1cn", "woe:centroid": [-73.653458, 40.651699], "geom:latitude": 40.651699, "geom:longitude": -73.653458, "geom:hash": "dr5x7brjq1cn", "woe:latitude": 40.651699, "geom:centroid": [-73.653458, 40.651699], "woe:longitude": -73.653458, "woe:repo": "woeplanet-poi-us", "geom:area": 0.0, "woe:scale": 19}}