{"type": "Feature", "id": 23571246, "properties": {"woe:id": 23571246, "woe:parent_id": 2509472, "woe:name": "Udall High & Junior High School", "woe:placetype": 20, "woe:placetype_name": "POI", "woe:lang": "ENG", "iso:country": "US", "meta:provider": ["geoplanet:7.3.1", "geoplanet:7.3.2", "geoplanet:7.4.0", "geoplanet:7.4.1", "geoplanet:7.5.1", "geoplanet:7.5.2", "geoplanet:7.6.0", "geoplanet:7.8.1", "geoplanet:7.9.0", "geoplanet:7.10.0", "geoplanet:8.0.0", "woeplanet:8.0.0"], "meta:indexed": "2020-08-20T20:18:35.846846", "woe:alias_ENG_V": ["Udall High & Junior High", "Udall High and Junior High School", "Udall High and Junior High"], "meta:updated": "2020-08-22T02:57:36.440473", "woe:hierarchy": {"continent": 24865672, "country": 23424977, "town": 0, "planet": 1, "county": 12588388, "suburb": 0, "state": 2347575, "region": 0, "localadmin": 0}, "woe:timezone_id": 56043661, "woe:hash": "9ydutvwv91f6", "woe:centroid": [-97.120811, 37.384682], "geom:latitude": 37.384682, "geom:longitude": -97.120811, "geom:hash": "9ydutvwv91f6", "woe:latitude": 37.384682, "geom:centroid": [-97.120811, 37.384682], "woe:longitude": -97.120811, "woe:repo": "woeplanet-poi-us"}, "geometry": {"coordinates": [-97.120811, 37.384682], "type": "Point"}}