{"type": "Feature", "id": 23551359, "geometry": {"type": "Point", "coordinates": [-83.98732, 33.289822]}, "properties": {"woe:id": 23551359, "woe:parent_id": 2428178, "woe:name": "Jackson High School", "woe:placetype": 20, "woe:placetype_name": "POI", "woe:lang": "ENG", "iso:country": "US", "meta:provider": ["geoplanet:7.3.1", "geoplanet:7.3.2", "geoplanet:7.4.0", "geoplanet:7.4.1", "geoplanet:7.5.1", "geoplanet:7.5.2", "geoplanet:7.6.0", "geoplanet:7.8.1", "geoplanet:7.9.0", "geoplanet:7.10.0", "geoplanet:8.0.0", "woeplanet:8.0.0"], "meta:indexed": "2020-08-20T20:18:28.824194", "woe:alias_ENG_V": ["Jackson Senior High School", "Jackson High", "Jackson Senior High", "Jackson HS", "Jackson Senior HS"], "meta:updated": "2020-10-14T11:20:22.045955", "woe:hierarchy": {"continent": 24865672, "country": 23424977, "town": 0, "planet": 1, "county": 12587887, "suburb": 0, "state": 2347569, "region": 0, "localadmin": 0}, "woe:timezone_id": 56043648, "woe:hash": "djum2u4r38e5", "woe:centroid": [-83.98732, 33.289822], "geom:latitude": 33.289822, "geom:longitude": -83.98732, "geom:hash": "djum2u4r38e5", "woe:latitude": 33.289822, "geom:centroid": [-83.98732, 33.289822], "woe:longitude": -83.98732, "woe:repo": "woeplanet-poi-us", "geom:area": 0.0, "woe:scale": 19}}