{"type": "Feature", "id": 23585650, "geometry": {"type": "Point", "coordinates": [-71.931343, 42.04446]}, "properties": {"woe:id": 23585650, "woe:parent_id": 2394056, "woe:name": "Nichols College", "woe:placetype": 20, "woe:placetype_name": "POI", "woe:lang": "ENG", "iso:country": "US", "meta:provider": ["geoplanet:7.3.1", "geoplanet:7.3.2", "geoplanet:7.4.0", "geoplanet:7.4.1", "geoplanet:7.5.1", "geoplanet:7.5.2", "geoplanet:7.6.0", "geoplanet:7.8.1", "geoplanet:7.9.0", "geoplanet:7.10.0", "geoplanet:8.0.0", "woeplanet:8.0.0"], "meta:indexed": "2020-08-20T20:18:39.758426", "meta:updated": "2020-10-14T11:20:07.165258", "woe:hierarchy": {"continent": 24865672, "country": 23424977, "town": 0, "planet": 1, "county": 12588713, "suburb": 0, "state": 2347580, "region": 0, "localadmin": 0}, "woe:timezone_id": 56043648, "woe:hash": "drkz5jvnwprj", "woe:centroid": [-71.931343, 42.04446], "geom:latitude": 42.04446, "geom:longitude": -71.931343, "geom:hash": "drkz5jvnwprj", "woe:latitude": 42.04446, "geom:centroid": [-71.931343, 42.04446], "woe:longitude": -71.931343, "woe:repo": "woeplanet-poi-us", "geom:area": 0.0, "woe:scale": 19}}