{"type": "Feature", "id": 56204295, "properties": {"woe:id": 56204295, "woe:parent_id": 2468432, "woe:name": "Cathedral School", "woe:placetype": 20, "woe:placetype_name": "POI", "woe:lang": "ENG", "iso:country": "US", "meta:provider": ["geoplanet:7.6.0", "geoplanet:7.8.1", "geoplanet:7.9.0", "geoplanet:7.10.0", "geoplanet:8.0.0", "woeplanet:8.0.0"], "meta:indexed": "2020-08-21T08:24:23.875526", "meta:updated": "2020-08-22T02:58:24.070466", "woe:hierarchy": {"continent": 24865672, "country": 23424977, "town": 0, "planet": 1, "county": 12589335, "suburb": 0, "state": 2347591, "region": 0, "localadmin": 0}, "woe:timezone_id": 56043648, "woe:hash": "dr5rksr8x31k", "woe:centroid": [-73.971321, 40.672852], "geom:latitude": 40.672852, "geom:longitude": -73.971321, "geom:hash": "dr5rksr8x31k", "woe:latitude": 40.672852, "geom:centroid": [-73.971321, 40.672852], "woe:longitude": -73.971321, "woe:repo": "woeplanet-poi-us"}, "geometry": {"coordinates": [-73.971321, 40.672852], "type": "Point"}}