{"type": "Feature", "id": 23512781, "properties": {"woe:id": 23512781, "woe:parent_id": 2423632, "woe:name": "Holtville Elementary School", "woe:placetype": 20, "woe:placetype_name": "POI", "woe:lang": "ENG", "iso:country": "US", "meta:provider": ["geoplanet:7.3.1", "geoplanet:7.3.2", "geoplanet:7.4.0", "geoplanet:7.4.1", "geoplanet:7.5.1", "geoplanet:7.5.2", "geoplanet:7.6.0", "geoplanet:7.8.1", "geoplanet:7.9.0", "geoplanet:7.10.0", "geoplanet:8.0.0", "woeplanet:8.0.0"], "meta:indexed": "2020-08-20T20:18:17.169835", "woe:alias_ENG_V": ["Holtville Elementary"], "meta:updated": "2020-08-22T02:57:26.118579", "woe:hierarchy": {"continent": 24865672, "country": 23424977, "town": 0, "planet": 1, "county": 12587512, "suburb": 0, "state": 2347559, "region": 0, "localadmin": 0}, "woe:timezone_id": 56043661, "woe:hash": "djf9et6c3ktr", "woe:centroid": [-86.326729, 32.636501], "geom:latitude": 32.636501, "geom:longitude": -86.326729, "geom:hash": "djf9et6c3ktr", "woe:latitude": 32.636501, "geom:centroid": [-86.326729, 32.636501], "woe:longitude": -86.326729, "woe:repo": "woeplanet-poi-us"}, "geometry": {"coordinates": [-86.326729, 32.636501], "type": "Point"}}