{"type": "Feature", "id": 23536013, "geometry": {"type": "Point", "coordinates": [-117.617493, 34.06707]}, "properties": {"woe:id": 23536013, "woe:parent_id": 55971863, "woe:name": "Mariposa Elementary School", "woe:placetype": 20, "woe:placetype_name": "POI", "woe:lang": "ENG", "iso:country": "US", "meta:provider": ["geoplanet:7.3.2", "geoplanet:7.4.0", "geoplanet:7.4.1", "geoplanet:7.5.1", "geoplanet:7.5.2", "geoplanet:7.6.0", "geoplanet:7.8.1", "geoplanet:7.9.0", "geoplanet:7.10.0", "geoplanet:8.0.0", "woeplanet:8.0.0"], "meta:indexed": "2020-08-20T22:02:04.448134", "woe:alias_ENG_V": ["Mariposa Elementary"], "meta:updated": "2020-10-14T11:20:24.655832", "woe:hierarchy": {"continent": 24865672, "country": 23424977, "town": 0, "planet": 1, "county": 12587705, "suburb": 0, "state": 2347563, "region": 0, "localadmin": 0}, "woe:timezone_id": 56043663, "woe:hash": "9qh3g99x1f0s", "woe:centroid": [-117.617493, 34.06707], "geom:latitude": 34.06707, "geom:longitude": -117.617493, "geom:hash": "9qh3g99x1f0s", "woe:latitude": 34.06707, "geom:centroid": [-117.617493, 34.06707], "woe:longitude": -117.617493, "woe:repo": "woeplanet-poi-us", "geom:area": 0.0, "woe:scale": 19}}