{"type": "Feature", "id": 23620304, "geometry": {"type": "Point", "coordinates": [-73.952538, 42.775082]}, "properties": {"woe:id": 23620304, "woe:parent_id": 2485102, "woe:name": "Mohonasen Senior High School", "woe:placetype": 20, "woe:placetype_name": "POI", "woe:lang": "ENG", "iso:country": "US", "meta:provider": ["geoplanet:7.3.1", "geoplanet:7.3.2", "geoplanet:7.4.0", "geoplanet:7.4.1", "geoplanet:7.5.1", "geoplanet:7.5.2", "geoplanet:7.6.0", "geoplanet:7.8.1", "geoplanet:7.9.0", "geoplanet:7.10.0", "geoplanet:8.0.0", "woeplanet:8.0.0"], "meta:indexed": "2020-08-20T20:18:51.561058", "woe:alias_ENG_V": ["Mohonasen Senior High", "Mohonasen High School", "Mohonasen High", "Mohonasen Senior HS", "Mohonasen HS"], "meta:updated": "2020-10-14T11:19:45.828656", "woe:hierarchy": {"continent": 24865672, "country": 23424977, "town": 0, "planet": 1, "county": 12589357, "suburb": 0, "state": 2347591, "region": 0, "localadmin": 0}, "woe:timezone_id": 56043648, "woe:hash": "dre7m4vquvnz", "woe:centroid": [-73.952538, 42.775082], "geom:latitude": 42.775082, "geom:longitude": -73.952538, "geom:hash": "dre7m4vquvnz", "woe:latitude": 42.775082, "geom:centroid": [-73.952538, 42.775082], "woe:longitude": -73.952538, "woe:repo": "woeplanet-poi-us", "geom:area": 0.0, "woe:scale": 19}}