{"type": "Feature", "id": 23618358, "properties": {"woe:id": 23618358, "woe:parent_id": 55862040, "woe:name": "George Fowler High School", "woe:placetype": 20, "woe:placetype_name": "POI", "woe:lang": "ENG", "iso:country": "US", "meta:provider": ["geoplanet:7.3.1", "geoplanet:7.3.2", "geoplanet:7.4.0", "geoplanet:7.4.1", "geoplanet:7.5.1", "geoplanet:7.5.2", "geoplanet:7.6.0", "geoplanet:7.8.1", "geoplanet:7.9.0", "geoplanet:7.10.0", "geoplanet:8.0.0", "woeplanet:8.0.0"], "meta:indexed": "2020-08-20T20:18:50.813337", "woe:alias_ENG_V": ["George Fowler Senior High School", "George Fowler High", "George Fowler Senior High", "George Fowler HS", "George Fowler Senior HS"], "meta:updated": "2020-08-22T02:58:48.791796", "woe:hierarchy": {"continent": 24865672, "country": 23424977, "town": 0, "planet": 1, "county": 12589345, "suburb": 0, "state": 2347591, "region": 0, "localadmin": 0}, "woe:timezone_id": 56043648, "woe:hash": "dr9ufegqwuwh", "woe:centroid": [-76.174438, 43.044201], "geom:latitude": 43.044201, "geom:longitude": -76.174438, "geom:hash": "dr9ufegqwuwh", "woe:latitude": 43.044201, "geom:centroid": [-76.174438, 43.044201], "woe:longitude": -76.174438, "woe:repo": "woeplanet-poi-us"}, "geometry": {"coordinates": [-76.174438, 43.044201], "type": "Point"}}