{"type": "Feature", "id": 23672229, "properties": {"woe:id": 23672229, "woe:parent_id": 2382206, "woe:name": "Fair Haven Christian School", "woe:placetype": 20, "woe:placetype_name": "POI", "woe:lang": "ENG", "iso:country": "US", "meta:provider": ["geoplanet:7.4.0", "geoplanet:7.4.1", "geoplanet:7.5.1", "geoplanet:7.5.2", "geoplanet:7.6.0", "geoplanet:7.8.1", "geoplanet:7.9.0", "geoplanet:7.10.0", "geoplanet:8.0.0", "woeplanet:8.0.0"], "meta:indexed": "2020-08-20T23:55:47.607253", "meta:updated": "2020-08-22T02:58:17.469420", "woe:hierarchy": {"continent": 24865672, "country": 23424977, "town": 0, "planet": 1, "county": 12590498, "suburb": 0, "state": 2347607, "region": 0, "localadmin": 0}, "woe:timezone_id": 56043648, "woe:hash": "dny410xcz6r4", "woe:centroid": [-81.507591, 38.323372], "geom:latitude": 38.323372, "geom:longitude": -81.507591, "geom:hash": "dny410xcz6r4", "woe:latitude": 38.323372, "geom:centroid": [-81.507591, 38.323372], "woe:longitude": -81.507591, "woe:repo": "woeplanet-poi-us"}, "geometry": {"coordinates": [-81.507591, 38.323372], "type": "Point"}}