{"type": "Feature", "id": 23647668, "geometry": {"type": "Point", "coordinates": [-80.861008, 33.520729]}, "properties": {"woe:id": 23647668, "woe:parent_id": 2508720, "woe:name": "Marshall Elementary School", "woe:placetype": 20, "woe:placetype_name": "POI", "woe:lang": "ENG", "iso:country": "US", "meta:provider": ["geoplanet:7.3.1", "geoplanet:7.3.2", "geoplanet:7.4.0", "geoplanet:7.4.1", "geoplanet:7.5.1", "geoplanet:7.5.2", "geoplanet:7.6.0", "geoplanet:7.8.1", "geoplanet:7.9.0", "geoplanet:7.10.0", "geoplanet:8.0.0", "woeplanet:8.0.0"], "meta:indexed": "2020-08-20T20:19:00.876005", "woe:alias_ENG_V": ["Marshall Elementary"], "meta:updated": "2020-10-14T11:19:38.037755", "woe:hierarchy": {"continent": 24865672, "country": 23424977, "town": 0, "planet": 1, "county": 12589837, "suburb": 0, "state": 2347599, "region": 0, "localadmin": 0}, "woe:timezone_id": 56043648, "woe:hash": "djyqxyqb3uy3", "woe:centroid": [-80.861008, 33.520729], "geom:latitude": 33.520729, "geom:longitude": -80.861008, "geom:hash": "djyqxyqb3uy3", "woe:latitude": 33.520729, "geom:centroid": [-80.861008, 33.520729], "woe:longitude": -80.861008, "woe:repo": "woeplanet-poi-us", "geom:area": 0.0, "woe:scale": 19}}