{"type": "Feature", "id": 23598245, "geometry": {"type": "Point", "coordinates": [-94.481628, 38.973228]}, "properties": {"woe:id": 23598245, "woe:parent_id": 55805998, "woe:name": "Spring Valley Elementary School", "woe:placetype": 20, "woe:placetype_name": "POI", "woe:lang": "ENG", "iso:country": "US", "meta:provider": ["geoplanet:7.3.1", "geoplanet:7.3.2", "geoplanet:7.4.0", "geoplanet:7.4.1", "geoplanet:7.5.1", "geoplanet:7.5.2", "geoplanet:7.6.0", "geoplanet:7.8.1", "geoplanet:7.9.0", "geoplanet:7.10.0", "geoplanet:8.0.0", "woeplanet:8.0.0"], "meta:indexed": "2020-08-20T20:18:44.205722", "woe:alias_ENG_V": ["Spring Valley Elementary"], "meta:updated": "2020-10-14T11:20:16.358223", "woe:hierarchy": {"continent": 24865672, "country": 23424977, "town": 0, "planet": 1, "county": 12589013, "suburb": 0, "state": 2347584, "region": 0, "localadmin": 0}, "woe:timezone_id": 56043661, "woe:hash": "9yuvdnbed2rb", "woe:centroid": [-94.481628, 38.973228], "geom:latitude": 38.973228, "geom:longitude": -94.481628, "geom:hash": "9yuvdnbed2rb", "woe:latitude": 38.973228, "geom:centroid": [-94.481628, 38.973228], "woe:longitude": -94.481628, "woe:repo": "woeplanet-poi-us", "geom:area": 0.0, "woe:scale": 19}}