{"type": "Feature", "id": 23538566, "properties": {"woe:id": 23538566, "woe:parent_id": 2488904, "woe:name": "Renaissance High School", "woe:placetype": 20, "woe:placetype_name": "POI", "woe:lang": "ENG", "iso:country": "US", "meta:provider": ["geoplanet:7.3.2", "geoplanet:7.4.0", "geoplanet:7.4.1", "geoplanet:7.5.1", "geoplanet:7.5.2", "geoplanet:7.6.0", "geoplanet:7.8.1", "geoplanet:7.9.0", "geoplanet:7.10.0", "geoplanet:8.0.0", "woeplanet:8.0.0"], "meta:indexed": "2020-08-20T22:02:05.434377", "woe:alias_ENG_V": ["Renaissance Senior High School", "Renaissance High", "Renaissance Senior High", "Renaissance HS", "Renaissance Senior HS"], "meta:updated": "2020-08-22T02:58:46.535766", "woe:hierarchy": {"continent": 24865672, "country": 23424977, "town": 0, "planet": 1, "county": 12587725, "suburb": 0, "state": 2347563, "region": 0, "localadmin": 0}, "woe:timezone_id": 56043663, "woe:hash": "9q576w25juhp", "woe:centroid": [-119.069572, 34.356159], "geom:latitude": 34.356159, "geom:longitude": -119.069572, "geom:hash": "9q576w25juhp", "woe:latitude": 34.356159, "geom:centroid": [-119.069572, 34.356159], "woe:longitude": -119.069572, "woe:repo": "woeplanet-poi-us"}, "geometry": {"coordinates": [-119.069572, 34.356159], "type": "Point"}}