{"type": "Feature", "id": 56053979, "geometry": {"type": "Point", "coordinates": [-81.379128, 28.30781]}, "properties": {"woe:id": 56053979, "woe:parent_id": 55859884, "woe:name": "Valencia Community College-Osceola", "woe:placetype": 20, "woe:placetype_name": "POI", "woe:lang": "ENG", "iso:country": "US", "meta:provider": ["geoplanet:7.3.1", "geoplanet:7.3.2", "geoplanet:7.4.0", "geoplanet:7.4.1", "geoplanet:7.5.1", "geoplanet:7.5.2", "geoplanet:7.6.0", "geoplanet:7.8.1", "geoplanet:7.9.0", "geoplanet:7.10.0", "geoplanet:8.0.0", "woeplanet:8.0.0"], "meta:indexed": "2020-08-20T20:19:17.463461", "meta:updated": "2020-10-14T11:19:55.143182", "woe:hierarchy": {"continent": 24865672, "country": 23424977, "town": 0, "planet": 1, "county": 12587851, "suburb": 0, "state": 2347568, "region": 0, "localadmin": 0}, "woe:timezone_id": 56043648, "woe:hash": "djn1h1m8byk0", "woe:centroid": [-81.379128, 28.30781], "geom:latitude": 28.30781, "geom:longitude": -81.379128, "geom:hash": "djn1h1m8byk0", "woe:latitude": 28.30781, "geom:centroid": [-81.379128, 28.30781], "woe:longitude": -81.379128, "woe:repo": "woeplanet-poi-us", "geom:area": 0.0, "woe:scale": 19}}