{"type": "Feature", "id": 23569167, "properties": {"woe:id": 23569167, "woe:parent_id": 2391099, "woe:name": "St Rose of Lima School", "woe:placetype": 20, "woe:placetype_name": "POI", "woe:lang": "ENG", "iso:country": "US", "meta:provider": ["geoplanet:7.3.1", "geoplanet:7.3.2", "geoplanet:7.4.0", "geoplanet:7.4.1", "geoplanet:7.5.1", "geoplanet:7.5.2", "geoplanet:7.6.0", "geoplanet:7.8.1", "geoplanet:7.9.0", "geoplanet:7.10.0", "geoplanet:8.0.0", "woeplanet:8.0.0"], "meta:indexed": "2020-08-20T20:18:35.071989", "meta:updated": "2020-08-22T02:57:36.102524", "woe:alias_ENG_V": ["St Rose of Lima Catholic School"], "woe:hierarchy": {"continent": 24865672, "country": 23424977, "town": 0, "planet": 1, "county": 12588295, "suburb": 0, "state": 2347574, "region": 0, "localadmin": 0}, "woe:timezone_id": 56043661, "woe:hash": "9zkpn03pf7pd", "woe:centroid": [-95.359848, 42.014439], "geom:latitude": 42.014439, "geom:longitude": -95.359848, "geom:hash": "9zkpn03pf7pd", "woe:latitude": 42.014439, "geom:centroid": [-95.359848, 42.014439], "woe:longitude": -95.359848, "woe:repo": "woeplanet-poi-us"}, "geometry": {"coordinates": [-95.359848, 42.014439], "type": "Point"}}