{"type": "Feature", "id": 23576498, "properties": {"woe:id": 23576498, "woe:parent_id": 2516376, "woe:name": "Welsh High School", "woe:placetype": 20, "woe:placetype_name": "POI", "woe:lang": "ENG", "iso:country": "US", "meta:provider": ["geoplanet:7.3.1", "geoplanet:7.3.2", "geoplanet:7.4.0", "geoplanet:7.4.1", "geoplanet:7.5.1", "geoplanet:7.5.2", "geoplanet:7.6.0", "geoplanet:7.8.1", "geoplanet:7.9.0", "geoplanet:7.10.0", "geoplanet:8.0.0", "woeplanet:8.0.0"], "meta:indexed": "2020-08-20T20:18:37.557877", "woe:alias_ENG_V": ["Welsh Senior High School", "Welsh High", "Welsh Senior High", "Welsh HS", "Welsh Senior HS"], "meta:updated": "2020-08-22T02:58:47.620134", "woe:hierarchy": {"continent": 24865672, "country": 23424977, "town": 0, "planet": 1, "county": 12588622, "suburb": 0, "state": 2347577, "region": 0, "localadmin": 0}, "woe:timezone_id": 56043661, "woe:hash": "9vqh000fqgq1", "woe:centroid": [-92.811172, 30.234779], "geom:latitude": 30.234779, "geom:longitude": -92.811172, "geom:hash": "9vqh000fqgq1", "woe:latitude": 30.234779, "geom:centroid": [-92.811172, 30.234779], "woe:longitude": -92.811172, "woe:repo": "woeplanet-poi-us"}, "geometry": {"coordinates": [-92.811172, 30.234779], "type": "Point"}}