{"type": "Feature", "id": 23574611, "properties": {"woe:id": 23574611, "woe:parent_id": 2453727, "woe:name": "Corbin Teen Parent Program", "woe:placetype": 20, "woe:placetype_name": "POI", "woe:lang": "ENG", "iso:country": "US", "meta:provider": ["geoplanet:7.3.1", "geoplanet:7.3.2", "geoplanet:7.4.0", "geoplanet:7.4.1", "geoplanet:7.5.1", "geoplanet:7.5.2", "geoplanet:7.6.0", "geoplanet:7.8.1", "geoplanet:7.9.0", "geoplanet:7.10.0", "geoplanet:8.0.0", "woeplanet:8.0.0"], "meta:indexed": "2020-08-20T20:18:36.998667", "meta:updated": "2020-08-22T02:57:36.989579", "woe:hierarchy": {"continent": 24865672, "country": 23424977, "town": 0, "planet": 1, "county": 12588536, "suburb": 0, "state": 2347576, "region": 0, "localadmin": 0}, "woe:timezone_id": 56043647, "woe:hash": "dns4nqyvs4d8", "woe:centroid": [-84.090897, 36.952099], "geom:latitude": 36.952099, "geom:longitude": -84.090897, "geom:hash": "dns4nqyvs4d8", "woe:latitude": 36.952099, "geom:centroid": [-84.090897, 36.952099], "woe:longitude": -84.090897, "woe:repo": "woeplanet-poi-us"}, "geometry": {"coordinates": [-84.090897, 36.952099], "type": "Point"}}