{"type": "Feature", "id": 23567020, "properties": {"woe:id": 23567020, "woe:parent_id": 2353022, "woe:name": "Cunningham Elementary School", "woe:placetype": 20, "woe:placetype_name": "POI", "woe:lang": "ENG", "iso:country": "US", "meta:provider": ["geoplanet:7.3.1", "geoplanet:7.3.2", "geoplanet:7.4.0", "geoplanet:7.4.1", "geoplanet:7.5.1", "geoplanet:7.5.2", "geoplanet:7.6.0", "geoplanet:7.8.1", "geoplanet:7.9.0", "geoplanet:7.10.0", "geoplanet:8.0.0", "woeplanet:8.0.0"], "meta:indexed": "2020-08-20T20:18:34.265162", "woe:alias_ENG_V": ["Cunningham Elementary"], "meta:updated": "2020-08-22T02:57:35.748002", "woe:hierarchy": {"continent": 24865672, "country": 23424977, "town": 0, "planet": 1, "county": 12588227, "suburb": 0, "state": 2347573, "region": 0, "localadmin": 0}, "woe:timezone_id": 56043656, "woe:hash": "dp5j537vgzm4", "woe:centroid": [-85.63311, 40.261799], "geom:latitude": 40.261799, "geom:longitude": -85.63311, "geom:hash": "dp5j537vgzm4", "woe:latitude": 40.261799, "geom:centroid": [-85.63311, 40.261799], "woe:longitude": -85.63311, "woe:repo": "woeplanet-poi-us"}, "geometry": {"coordinates": [-85.63311, 40.261799], "type": "Point"}}