{"type": "Feature", "id": 23560034, "geometry": {"type": "Point", "coordinates": [-88.135147, 42.06168]}, "properties": {"woe:id": 23560034, "woe:parent_id": 2422787, "woe:name": "Small World Children's Center", "woe:placetype": 20, "woe:placetype_name": "POI", "woe:lang": "ENG", "iso:country": "US", "meta:provider": ["geoplanet:7.3.2", "geoplanet:7.4.0", "geoplanet:7.4.1", "geoplanet:7.5.1", "geoplanet:7.5.2", "geoplanet:7.6.0", "geoplanet:7.8.1", "geoplanet:7.9.0", "geoplanet:7.10.0", "geoplanet:8.0.0", "woeplanet:8.0.0"], "meta:indexed": "2020-08-20T22:02:14.348378", "meta:updated": "2020-10-14T11:20:04.749635", "woe:hierarchy": {"continent": 24865672, "country": 23424977, "town": 0, "planet": 1, "county": 12588093, "suburb": 0, "state": 2347572, "region": 0, "localadmin": 0}, "woe:timezone_id": 56043661, "woe:hash": "dp3r63jgn1rn", "woe:centroid": [-88.135147, 42.06168], "geom:latitude": 42.06168, "geom:longitude": -88.135147, "geom:hash": "dp3r63jgn1rn", "woe:latitude": 42.06168, "geom:centroid": [-88.135147, 42.06168], "woe:longitude": -88.135147, "woe:repo": "woeplanet-poi-us", "geom:area": 0.0, "woe:scale": 19}}