{"type": "Feature", "id": 23622251, "geometry": {"type": "Point", "coordinates": [-77.028709, 34.701019]}, "properties": {"woe:id": 23622251, "woe:parent_id": 2366301, "woe:name": "White Oak Church of God Academy", "woe:placetype": 20, "woe:placetype_name": "POI", "woe:lang": "ENG", "iso:country": "US", "meta:provider": ["geoplanet:7.3.1", "geoplanet:7.3.2", "geoplanet:7.4.0", "geoplanet:7.4.1", "geoplanet:7.5.1", "geoplanet:7.5.2", "geoplanet:7.6.0", "geoplanet:7.8.1", "geoplanet:7.9.0", "geoplanet:7.10.0", "geoplanet:8.0.0", "woeplanet:8.0.0"], "meta:indexed": "2020-08-20T20:18:52.294550", "meta:updated": "2020-10-14T11:19:45.227443", "woe:hierarchy": {"continent": 24865672, "country": 23424977, "town": 0, "planet": 1, "county": 12589389, "suburb": 0, "state": 2347592, "region": 0, "localadmin": 0}, "woe:timezone_id": 56043648, "woe:hash": "dq1jrjjkhfz9", "woe:centroid": [-77.028709, 34.701019], "geom:latitude": 34.701019, "geom:longitude": -77.028709, "geom:hash": "dq1jrjjkhfz9", "woe:latitude": 34.701019, "geom:centroid": [-77.028709, 34.701019], "woe:longitude": -77.028709, "woe:repo": "woeplanet-poi-us", "geom:area": 0.0, "woe:scale": 19}}