{"type": "Feature", "id": 23674517, "geometry": {"type": "Point", "coordinates": [-87.659119, 44.106831]}, "properties": {"woe:id": 23674517, "woe:parent_id": 2444827, "woe:name": "Immanuel Evang Lutheran School", "woe:placetype": 20, "woe:placetype_name": "POI", "woe:lang": "ENG", "iso:country": "US", "meta:provider": ["geoplanet:7.3.1", "geoplanet:7.3.2", "geoplanet:7.4.0", "geoplanet:7.4.1", "geoplanet:7.5.1", "geoplanet:7.5.2", "geoplanet:7.6.0", "geoplanet:7.8.1", "geoplanet:7.9.0", "geoplanet:7.10.0", "geoplanet:8.0.0", "woeplanet:8.0.0"], "meta:indexed": "2020-08-20T20:19:11.040605", "meta:updated": "2020-10-14T11:19:48.032398", "woe:hierarchy": {"continent": 24865672, "country": 23424977, "town": 0, "planet": 1, "county": 12590569, "suburb": 0, "state": 2347608, "region": 0, "localadmin": 0}, "woe:timezone_id": 56043661, "woe:hash": "dpcdvm2sfmpr", "woe:centroid": [-87.659119, 44.106831], "geom:latitude": 44.106831, "geom:longitude": -87.659119, "geom:hash": "dpcdvm2sfmpr", "woe:latitude": 44.106831, "geom:centroid": [-87.659119, 44.106831], "woe:longitude": -87.659119, "woe:repo": "woeplanet-poi-us", "geom:area": 0.0, "woe:scale": 19}}