{"type": "Feature", "id": 23656365, "geometry": {"type": "Point", "coordinates": [-97.109039, 32.765041]}, "properties": {"woe:id": 23656365, "woe:parent_id": 56022648, "woe:name": "Roquemore Elementary School", "woe:placetype": 20, "woe:placetype_name": "POI", "woe:lang": "ENG", "iso:country": "US", "meta:provider": ["geoplanet:7.3.1", "geoplanet:7.3.2", "geoplanet:7.4.0", "geoplanet:7.4.1", "geoplanet:7.5.1", "geoplanet:7.5.2", "geoplanet:7.6.0", "geoplanet:7.8.1", "geoplanet:7.9.0", "geoplanet:7.10.0", "geoplanet:8.0.0", "woeplanet:8.0.0"], "meta:indexed": "2020-08-20T20:19:04.298053", "woe:alias_ENG_V": ["Roquemore Elementary"], "meta:updated": "2020-10-14T11:19:49.614646", "woe:hierarchy": {"continent": 24865672, "country": 23424977, "town": 0, "planet": 1, "county": 12590226, "suburb": 0, "state": 2347602, "region": 0, "localadmin": 0}, "woe:timezone_id": 56043661, "woe:hash": "9vffqhxq5qk6", "woe:centroid": [-97.109039, 32.765041], "geom:latitude": 32.765041, "geom:longitude": -97.109039, "geom:hash": "9vffqhxq5qk6", "woe:latitude": 32.765041, "geom:centroid": [-97.109039, 32.765041], "woe:longitude": -97.109039, "woe:repo": "woeplanet-poi-us", "geom:area": 0.0, "woe:scale": 19}}