{"type": "Feature", "id": 23550881, "properties": {"woe:id": 23550881, "woe:parent_id": 55977950, "woe:name": "Janie Howard Wilson School", "woe:placetype": 20, "woe:placetype_name": "POI", "woe:lang": "ENG", "iso:country": "US", "meta:provider": ["geoplanet:7.3.1", "geoplanet:7.3.2", "geoplanet:7.4.0", "geoplanet:7.4.1", "geoplanet:7.5.1", "geoplanet:7.5.2", "geoplanet:7.6.0", "geoplanet:7.8.1", "geoplanet:7.9.0", "geoplanet:7.10.0", "geoplanet:8.0.0", "woeplanet:8.0.0"], "meta:indexed": "2020-08-20T20:18:28.617108", "meta:updated": "2020-08-22T02:57:32.680258", "woe:alias_ENG_V": ["Janie Howard Wilson Elem School"], "woe:hierarchy": {"continent": 24865672, "country": 23424977, "town": 0, "planet": 1, "county": 12587855, "suburb": 0, "state": 2347568, "region": 0, "localadmin": 0}, "woe:timezone_id": 56043648, "woe:hash": "dhvyz64h837q", "woe:centroid": [-81.592697, 27.91704], "geom:latitude": 27.91704, "geom:longitude": -81.592697, "geom:hash": "dhvyz64h837q", "woe:latitude": 27.91704, "geom:centroid": [-81.592697, 27.91704], "woe:longitude": -81.592697, "woe:repo": "woeplanet-poi-us"}, "geometry": {"coordinates": [-81.592697, 27.91704], "type": "Point"}}