{"type": "Feature", "id": 23635011, "geometry": {"type": "Point", "coordinates": [-123.243958, 44.618851]}, "properties": {"woe:id": 23635011, "woe:parent_id": 2438730, "woe:name": "Little Beavers Preschool Inc", "woe:placetype": 20, "woe:placetype_name": "POI", "woe:lang": "ENG", "iso:country": "US", "meta:provider": ["geoplanet:7.3.1", "geoplanet:7.3.2", "geoplanet:7.4.0", "geoplanet:7.4.1", "geoplanet:7.5.1", "geoplanet:7.5.2", "geoplanet:7.6.0", "geoplanet:7.8.1", "geoplanet:7.9.0", "geoplanet:7.10.0", "geoplanet:8.0.0", "woeplanet:8.0.0"], "meta:indexed": "2020-08-20T20:18:56.683574", "meta:updated": "2020-10-14T11:19:44.947707", "woe:hierarchy": {"continent": 24865672, "country": 23424977, "town": 0, "planet": 1, "county": 12589693, "suburb": 0, "state": 2347596, "region": 0, "localadmin": 0}, "woe:timezone_id": 56043663, "woe:hash": "9rbmgd87xssm", "woe:centroid": [-123.243958, 44.618851], "geom:latitude": 44.618851, "geom:longitude": -123.243958, "geom:hash": "9rbmgd87xssm", "woe:latitude": 44.618851, "geom:centroid": [-123.243958, 44.618851], "woe:longitude": -123.243958, "woe:repo": "woeplanet-poi-us", "geom:area": 0.0, "woe:scale": 19}}