{"type": "Feature", "id": 23514845, "geometry": {"type": "Point", "coordinates": [-134.649963, 58.388962]}, "properties": {"woe:id": 23514845, "woe:parent_id": 2430300, "woe:name": "Auke Bay Elementary School", "woe:placetype": 20, "woe:placetype_name": "POI", "woe:lang": "ENG", "iso:country": "US", "meta:provider": ["geoplanet:7.3.2", "geoplanet:7.4.0", "geoplanet:7.4.1", "geoplanet:7.5.1", "geoplanet:7.5.2", "geoplanet:7.6.0", "geoplanet:7.8.1", "geoplanet:7.9.0", "geoplanet:7.10.0", "geoplanet:8.0.0", "woeplanet:8.0.0"], "meta:indexed": "2020-08-20T22:01:55.965724", "woe:alias_ENG_V": ["Auke Bay Elementary"], "meta:updated": "2020-10-14T11:20:27.605571", "woe:hierarchy": {"continent": 24865672, "country": 23424977, "town": 0, "planet": 1, "county": 12587563, "suburb": 0, "state": 2347560, "region": 0, "localadmin": 0}, "woe:timezone_id": 56043667, "woe:hash": "c42hpvquk7qt", "woe:centroid": [-134.649963, 58.388962], "geom:latitude": 58.388962, "geom:longitude": -134.649963, "geom:hash": "c42hpvquk7qt", "woe:latitude": 58.388962, "geom:centroid": [-134.649963, 58.388962], "woe:longitude": -134.649963, "woe:repo": "woeplanet-poi-us", "geom:area": 0.0, "woe:scale": 19}}