{"type": "Feature", "id": 23532526, "geometry": {"type": "Point", "coordinates": [-118.338142, 33.772678]}, "properties": {"woe:id": 23532526, "woe:parent_id": 2452267, "woe:name": "Nishiyamato Academy of Cal", "woe:placetype": 20, "woe:placetype_name": "POI", "woe:lang": "ENG", "iso:country": "US", "meta:provider": ["geoplanet:7.3.1", "geoplanet:7.3.2", "geoplanet:7.4.0", "geoplanet:7.4.1", "geoplanet:7.5.1", "geoplanet:7.5.2", "geoplanet:7.6.0", "geoplanet:7.8.1", "geoplanet:7.9.0", "geoplanet:7.10.0", "geoplanet:8.0.0", "woeplanet:8.0.0"], "meta:indexed": "2020-08-20T20:18:22.276237", "meta:updated": "2020-10-14T11:20:10.099991", "woe:hierarchy": {"continent": 24865672, "country": 23424977, "town": 0, "planet": 1, "county": 12587688, "suburb": 0, "state": 2347563, "region": 0, "localadmin": 0}, "woe:timezone_id": 56043663, "woe:hash": "9q5b5hhu17mz", "woe:centroid": [-118.338142, 33.772678], "geom:latitude": 33.772678, "geom:longitude": -118.338142, "geom:hash": "9q5b5hhu17mz", "woe:latitude": 33.772678, "geom:centroid": [-118.338142, 33.772678], "woe:longitude": -118.338142, "woe:repo": "woeplanet-poi-us", "geom:area": 0.0, "woe:scale": 19}}