{"type": "Feature", "id": 23577033, "geometry": {"type": "Point", "coordinates": [-92.162987, 32.541149]}, "properties": {"woe:id": 23577033, "woe:parent_id": 2433142, "woe:name": "Kiroli Elementary School", "woe:placetype": 20, "woe:placetype_name": "POI", "woe:lang": "ENG", "iso:country": "US", "meta:provider": ["geoplanet:7.3.1", "geoplanet:7.3.2", "geoplanet:7.4.0", "geoplanet:7.4.1", "geoplanet:7.5.1", "geoplanet:7.5.2", "geoplanet:7.6.0", "geoplanet:7.8.1", "geoplanet:7.9.0", "geoplanet:7.10.0", "geoplanet:8.0.0", "woeplanet:8.0.0"], "meta:indexed": "2020-08-20T20:18:37.741000", "woe:alias_ENG_V": ["Kiroli Elementary"], "meta:updated": "2020-10-14T11:20:04.507479", "woe:hierarchy": {"continent": 24865672, "country": 23424977, "town": 0, "planet": 1, "county": 12588632, "suburb": 0, "state": 2347577, "region": 0, "localadmin": 0}, "woe:timezone_id": 56043661, "woe:hash": "9vy3ngbvytzf", "woe:centroid": [-92.162987, 32.541149], "geom:latitude": 32.541149, "geom:longitude": -92.162987, "geom:hash": "9vy3ngbvytzf", "woe:latitude": 32.541149, "geom:centroid": [-92.162987, 32.541149], "woe:longitude": -92.162987, "woe:repo": "woeplanet-poi-us", "geom:area": 0.0, "woe:scale": 19}}