{"type": "Feature", "id": 23551556, "geometry": {"type": "Point", "coordinates": [-84.414139, 34.240768]}, "properties": {"woe:id": 23551556, "woe:parent_id": 2417721, "woe:name": "Buffington Elementary School", "woe:placetype": 20, "woe:placetype_name": "POI", "woe:lang": "ENG", "iso:country": "US", "meta:provider": ["geoplanet:7.3.1", "geoplanet:7.3.2", "geoplanet:7.4.0", "geoplanet:7.4.1", "geoplanet:7.5.1", "geoplanet:7.5.2", "geoplanet:7.6.0", "geoplanet:7.8.1", "geoplanet:7.9.0", "geoplanet:7.10.0", "geoplanet:8.0.0", "woeplanet:8.0.0"], "meta:indexed": "2020-08-20T20:18:28.924570", "woe:alias_ENG_V": ["Buffington Elementary"], "meta:updated": "2020-10-14T11:20:16.798992", "woe:hierarchy": {"continent": 24865672, "country": 23424977, "town": 0, "planet": 1, "county": 12587897, "suburb": 0, "state": 2347569, "region": 0, "localadmin": 0}, "woe:timezone_id": 56043648, "woe:hash": "dn5fz176zvzc", "woe:centroid": [-84.414139, 34.240768], "geom:latitude": 34.240768, "geom:longitude": -84.414139, "geom:hash": "dn5fz176zvzc", "woe:latitude": 34.240768, "geom:centroid": [-84.414139, 34.240768], "woe:longitude": -84.414139, "woe:repo": "woeplanet-poi-us", "geom:area": 0.0, "woe:scale": 19}}