{"type": "Feature", "id": 23666528, "properties": {"woe:id": 23666528, "woe:parent_id": 2398042, "woe:name": "Surry County High School", "woe:placetype": 20, "woe:placetype_name": "POI", "woe:lang": "ENG", "iso:country": "US", "meta:provider": ["geoplanet:7.3.2", "geoplanet:7.4.0", "geoplanet:7.4.1", "geoplanet:7.5.1", "geoplanet:7.5.2", "geoplanet:7.6.0", "geoplanet:7.8.1", "geoplanet:7.9.0", "geoplanet:7.10.0", "geoplanet:8.0.0", "woeplanet:8.0.0"], "meta:indexed": "2020-08-20T22:02:58.658010", "woe:alias_ENG_V": ["Surry County Senior High School", "Surry County High", "Surry County Senior High", "Surry County HS", "Surry County Senior HS"], "meta:updated": "2020-08-22T02:58:50.207648", "woe:hierarchy": {"continent": 24865672, "country": 23424977, "town": 0, "planet": 1, "county": 12590427, "suburb": 0, "state": 2347605, "region": 0, "localadmin": 0}, "woe:timezone_id": 56043648, "woe:hash": "dq96fn1hu1db", "woe:centroid": [-76.902748, 37.079681], "geom:latitude": 37.079681, "geom:longitude": -76.902748, "geom:hash": "dq96fn1hu1db", "woe:latitude": 37.079681, "geom:centroid": [-76.902748, 37.079681], "woe:longitude": -76.902748, "woe:repo": "woeplanet-poi-us"}, "geometry": {"coordinates": [-76.902748, 37.079681], "type": "Point"}}