{"type": "Feature", "id": 23516472, "properties": {"woe:id": 23516472, "woe:parent_id": 29230214, "woe:name": "Camelback Christian School", "woe:placetype": 20, "woe:placetype_name": "POI", "woe:lang": "ENG", "iso:country": "US", "meta:provider": ["geoplanet:7.3.2", "geoplanet:7.4.0", "geoplanet:7.4.1", "geoplanet:7.5.1", "geoplanet:7.5.2", "geoplanet:7.6.0", "geoplanet:7.8.1", "geoplanet:7.9.0", "geoplanet:7.10.0", "geoplanet:8.0.0", "woeplanet:8.0.0"], "meta:indexed": "2020-08-20T22:01:56.690275", "meta:updated": "2020-08-22T02:57:26.684242", "woe:alias_ENG_V": ["Phoenix Country Day School"], "woe:hierarchy": {"continent": 24865672, "country": 23424977, "town": 0, "planet": 1, "county": 12587587, "suburb": 0, "state": 2347561, "region": 0, "localadmin": 0}, "woe:timezone_id": 56043666, "woe:hash": "9tbqemw7ep3h", "woe:centroid": [-111.996902, 33.517181], "geom:latitude": 33.517181, "geom:longitude": -111.996902, "geom:hash": "9tbqemw7ep3h", "woe:latitude": 33.517181, "geom:centroid": [-111.996902, 33.517181], "woe:longitude": -111.996902, "woe:repo": "woeplanet-poi-us"}, "geometry": {"coordinates": [-111.996902, 33.517181], "type": "Point"}}