{"type": "Feature", "id": 23593199, "properties": {"woe:id": 23593199, "woe:parent_id": 55806448, "woe:name": "Mariucci Hockey Arena", "woe:placetype": 20, "woe:placetype_name": "POI", "woe:lang": "ENG", "iso:country": "US", "meta:provider": ["geoplanet:7.4.0", "geoplanet:7.4.1", "geoplanet:7.5.1", "geoplanet:7.5.2", "geoplanet:7.6.0", "geoplanet:7.8.1", "geoplanet:7.9.0", "geoplanet:7.10.0", "geoplanet:8.0.0", "woeplanet:8.0.0"], "meta:indexed": "2020-08-20T23:55:12.454414", "meta:updated": "2020-08-22T02:57:39.913446", "woe:hierarchy": {"continent": 24865672, "country": 23424977, "town": 0, "planet": 1, "county": 12588823, "suburb": 0, "state": 2347582, "region": 0, "localadmin": 0}, "woe:timezone_id": 56043661, "woe:hash": "9zvxyecvxf9f", "woe:centroid": [-93.227242, 44.977612], "geom:latitude": 44.977612, "geom:longitude": -93.227242, "geom:hash": "9zvxyecvxf9f", "woe:latitude": 44.977612, "geom:centroid": [-93.227242, 44.977612], "woe:longitude": -93.227242, "woe:repo": "woeplanet-poi-us"}, "geometry": {"coordinates": [-93.227242, 44.977612], "type": "Point"}}