{"type": "Feature", "id": 23643947, "geometry": {"type": "Point", "coordinates": [-75.216476, 39.940109]}, "properties": {"woe:id": 23643947, "woe:parent_id": 2432720, "woe:name": "Comegys Benjamin B School", "woe:placetype": 20, "woe:placetype_name": "POI", "woe:lang": "ENG", "iso:country": "US", "meta:provider": ["geoplanet:7.3.1", "geoplanet:7.3.2", "geoplanet:7.4.0", "geoplanet:7.4.1", "geoplanet:7.5.1", "geoplanet:7.5.2", "geoplanet:7.6.0", "geoplanet:7.8.1", "geoplanet:7.9.0", "geoplanet:7.10.0", "geoplanet:8.0.0", "woeplanet:8.0.0"], "meta:indexed": "2020-08-20T20:18:59.747420", "meta:updated": "2020-10-14T11:19:31.541869", "woe:hierarchy": {"continent": 24865672, "country": 23424977, "town": 0, "planet": 1, "county": 12589778, "suburb": 0, "state": 2347597, "region": 0, "localadmin": 0}, "woe:timezone_id": 56043648, "woe:hash": "dr4e0qv5cpfq", "woe:centroid": [-75.216476, 39.940109], "geom:latitude": 39.940109, "geom:longitude": -75.216476, "geom:hash": "dr4e0qv5cpfq", "woe:latitude": 39.940109, "geom:centroid": [-75.216476, 39.940109], "woe:longitude": -75.216476, "woe:repo": "woeplanet-poi-us", "geom:area": 0.0, "woe:scale": 19}}