{"type": "Feature", "id": 23621322, "properties": {"woe:id": 23621322, "woe:parent_id": 2440646, "woe:name": "Highland High School", "woe:placetype": 20, "woe:placetype_name": "POI", "woe:lang": "ENG", "iso:country": "US", "meta:provider": ["geoplanet:7.3.1", "geoplanet:7.3.2", "geoplanet:7.4.0", "geoplanet:7.4.1", "geoplanet:7.5.1", "geoplanet:7.5.2", "geoplanet:7.6.0", "geoplanet:7.8.1", "geoplanet:7.9.0", "geoplanet:7.10.0", "geoplanet:8.0.0", "woeplanet:8.0.0"], "meta:indexed": "2020-08-20T20:18:51.952050", "woe:alias_ENG_V": ["Highland Senior High School", "Highland High", "Highland Senior High", "Highland HS", "Highland Senior HS"], "meta:updated": "2020-08-22T02:58:48.869630", "woe:hierarchy": {"continent": 24865672, "country": 23424977, "town": 0, "planet": 1, "county": 12589367, "suburb": 0, "state": 2347591, "region": 0, "localadmin": 0}, "woe:timezone_id": 56043648, "woe:hash": "dr7m7gekwprm", "woe:centroid": [-74.010162, 41.72414], "geom:latitude": 41.72414, "geom:longitude": -74.010162, "geom:hash": "dr7m7gekwprm", "woe:latitude": 41.72414, "geom:centroid": [-74.010162, 41.72414], "woe:longitude": -74.010162, "woe:repo": "woeplanet-poi-us"}, "geometry": {"coordinates": [-74.010162, 41.72414], "type": "Point"}}