{"type": "Feature", "id": 23674762, "geometry": {"type": "Point", "coordinates": [-88.058167, 42.952209]}, "properties": {"woe:id": 23674762, "woe:parent_id": 2416183, "woe:name": "Whitnall High School", "woe:placetype": 20, "woe:placetype_name": "POI", "woe:lang": "ENG", "iso:country": "US", "meta:provider": ["geoplanet:7.3.1", "geoplanet:7.3.2", "geoplanet:7.4.0", "geoplanet:7.4.1", "geoplanet:7.5.1", "geoplanet:7.5.2", "geoplanet:7.6.0", "geoplanet:7.8.1", "geoplanet:7.9.0", "geoplanet:7.10.0", "geoplanet:8.0.0", "woeplanet:8.0.0"], "meta:indexed": "2020-08-20T20:19:11.154515", "woe:alias_ENG_V": ["Whitnall Senior High School", "Whitnall High", "Whitnall Senior High", "Whitnall HS", "Whitnall Senior HS"], "meta:updated": "2020-10-14T11:19:46.875485", "woe:hierarchy": {"continent": 24865672, "country": 23424977, "town": 0, "planet": 1, "county": 12590574, "suburb": 0, "state": 2347608, "region": 0, "localadmin": 0}, "woe:timezone_id": 56043661, "woe:hash": "dp9kk5jyzbpd", "woe:centroid": [-88.058167, 42.952209], "geom:latitude": 42.952209, "geom:longitude": -88.058167, "geom:hash": "dp9kk5jyzbpd", "woe:latitude": 42.952209, "geom:centroid": [-88.058167, 42.952209], "woe:longitude": -88.058167, "woe:repo": "woeplanet-poi-us", "geom:area": 0.0, "woe:scale": 19}}