{"type": "Feature", "id": 23627678, "geometry": {"type": "Point", "coordinates": [-84.179398, 39.075432]}, "properties": {"woe:id": 23627678, "woe:parent_id": 2359904, "woe:name": "Batavia Elementary School", "woe:placetype": 20, "woe:placetype_name": "POI", "woe:lang": "ENG", "iso:country": "US", "meta:provider": ["geoplanet:7.3.1", "geoplanet:7.3.2", "geoplanet:7.4.0", "geoplanet:7.4.1", "geoplanet:7.5.1", "geoplanet:7.5.2", "geoplanet:7.6.0", "geoplanet:7.8.1", "geoplanet:7.9.0", "geoplanet:7.10.0", "geoplanet:8.0.0", "woeplanet:8.0.0"], "meta:indexed": "2020-08-20T20:18:53.366662", "woe:alias_ENG_V": ["Batavia Elementary"], "meta:updated": "2020-10-14T11:19:36.195020", "woe:hierarchy": {"continent": 24865672, "country": 23424977, "town": 0, "planet": 1, "county": 12589539, "suburb": 0, "state": 2347594, "region": 0, "localadmin": 0}, "woe:timezone_id": 56043648, "woe:hash": "dnunk3qqvu7r", "woe:centroid": [-84.179398, 39.075432], "geom:latitude": 39.075432, "geom:longitude": -84.179398, "geom:hash": "dnunk3qqvu7r", "woe:latitude": 39.075432, "geom:centroid": [-84.179398, 39.075432], "woe:longitude": -84.179398, "woe:repo": "woeplanet-poi-us", "geom:area": 0.0, "woe:scale": 19}}