{"type": "Feature", "id": 23598808, "geometry": {"type": "Point", "coordinates": [-91.362488, 39.710789]}, "properties": {"woe:id": 23598808, "woe:parent_id": 2417091, "woe:name": "Pettibone Elementary School", "woe:placetype": 20, "woe:placetype_name": "POI", "woe:lang": "ENG", "iso:country": "US", "meta:provider": ["geoplanet:7.3.1", "geoplanet:7.3.2", "geoplanet:7.4.0", "geoplanet:7.4.1", "geoplanet:7.5.1", "geoplanet:7.5.2", "geoplanet:7.6.0", "geoplanet:7.8.1", "geoplanet:7.9.0", "geoplanet:7.10.0", "geoplanet:8.0.0", "woeplanet:8.0.0"], "meta:indexed": "2020-08-20T20:18:44.422472", "woe:alias_ENG_V": ["Pettibone Elementary"], "meta:updated": "2020-10-14T11:20:12.696001", "woe:hierarchy": {"continent": 24865672, "country": 23424977, "town": 0, "planet": 1, "county": 12589028, "suburb": 0, "state": 2347584, "region": 0, "localadmin": 0}, "woe:timezone_id": 56043661, "woe:hash": "9zp1bvpu5ex7", "woe:centroid": [-91.362488, 39.710789], "geom:latitude": 39.710789, "geom:longitude": -91.362488, "geom:hash": "9zp1bvpu5ex7", "woe:latitude": 39.710789, "geom:centroid": [-91.362488, 39.710789], "woe:longitude": -91.362488, "woe:repo": "woeplanet-poi-us", "geom:area": 0.0, "woe:scale": 19}}