{"type": "Feature", "id": 23632551, "properties": {"woe:id": 23632551, "woe:parent_id": 2480798, "woe:name": "Revere High School", "woe:placetype": 20, "woe:placetype_name": "POI", "woe:lang": "ENG", "iso:country": "US", "meta:provider": ["geoplanet:7.3.1", "geoplanet:7.3.2", "geoplanet:7.4.0", "geoplanet:7.4.1", "geoplanet:7.5.1", "geoplanet:7.5.2", "geoplanet:7.6.0", "geoplanet:7.8.1", "geoplanet:7.9.0", "geoplanet:7.10.0", "geoplanet:8.0.0", "woeplanet:8.0.0"], "meta:indexed": "2020-08-20T20:18:55.664863", "woe:alias_ENG_V": ["Revere Senior High School", "Revere High", "Revere Senior High", "Revere HS", "Revere Senior HS"], "meta:updated": "2020-08-22T02:58:49.279084", "woe:hierarchy": {"continent": 24865672, "country": 23424977, "town": 0, "planet": 1, "county": 12589603, "suburb": 0, "state": 2347594, "region": 0, "localadmin": 0}, "woe:timezone_id": 56043648, "woe:hash": "dpmfqu9tyt4y", "woe:centroid": [-81.615089, 41.202492], "geom:latitude": 41.202492, "geom:longitude": -81.615089, "geom:hash": "dpmfqu9tyt4y", "woe:latitude": 41.202492, "geom:centroid": [-81.615089, 41.202492], "woe:longitude": -81.615089, "woe:repo": "woeplanet-poi-us"}, "geometry": {"coordinates": [-81.615089, 41.202492], "type": "Point"}}