{"type": "Feature", "id": 23628250, "properties": {"woe:id": 23628250, "woe:parent_id": 2377795, "woe:name": "Chagrin Falls Intermediate Elementary School", "woe:placetype": 20, "woe:placetype_name": "POI", "woe:lang": "ENG", "iso:country": "US", "meta:provider": ["geoplanet:7.3.1", "geoplanet:7.3.2", "geoplanet:7.4.0", "geoplanet:7.4.1", "geoplanet:7.5.1", "geoplanet:7.5.2", "geoplanet:7.6.0", "geoplanet:7.8.1", "geoplanet:7.9.0", "geoplanet:7.10.0", "geoplanet:8.0.0", "woeplanet:8.0.0"], "meta:indexed": "2020-08-20T20:18:53.689999", "woe:alias_ENG_V": ["Chagrin Falls Intermediate Elementary"], "meta:updated": "2020-08-22T02:57:44.824133", "woe:hierarchy": {"continent": 24865672, "country": 23424977, "town": 0, "planet": 1, "county": 12589544, "suburb": 0, "state": 2347594, "region": 0, "localadmin": 0}, "woe:timezone_id": 56043648, "woe:hash": "dpq5eyn6urbm", "woe:centroid": [-81.388939, 41.429958], "geom:latitude": 41.429958, "geom:longitude": -81.388939, "geom:hash": "dpq5eyn6urbm", "woe:latitude": 41.429958, "geom:centroid": [-81.388939, 41.429958], "woe:longitude": -81.388939, "woe:repo": "woeplanet-poi-us"}, "geometry": {"coordinates": [-81.388939, 41.429958], "type": "Point"}}