{"type": "Feature", "id": 23554285, "geometry": {"type": "Point", "coordinates": [-83.519989, 31.44347]}, "properties": {"woe:id": 23554285, "woe:parent_id": 2471317, "woe:name": "Matt Wilson Elementary School", "woe:placetype": 20, "woe:placetype_name": "POI", "woe:lang": "ENG", "iso:country": "US", "meta:provider": ["geoplanet:7.3.1", "geoplanet:7.3.2", "geoplanet:7.4.0", "geoplanet:7.4.1", "geoplanet:7.5.1", "geoplanet:7.5.2", "geoplanet:7.6.0", "geoplanet:7.8.1", "geoplanet:7.9.0", "geoplanet:7.10.0", "geoplanet:8.0.0", "woeplanet:8.0.0"], "meta:indexed": "2020-08-20T20:18:29.869778", "woe:alias_ENG_V": ["Matt Wilson Elementary"], "meta:updated": "2020-10-14T11:20:21.561578", "woe:hierarchy": {"continent": 24865672, "country": 23424977, "town": 0, "planet": 1, "county": 12588006, "suburb": 0, "state": 2347569, "region": 0, "localadmin": 0}, "woe:timezone_id": 56043648, "woe:hash": "djsdgkne7pwk", "woe:centroid": [-83.519989, 31.44347], "geom:latitude": 31.44347, "geom:longitude": -83.519989, "geom:hash": "djsdgkne7pwk", "woe:latitude": 31.44347, "geom:centroid": [-83.519989, 31.44347], "woe:longitude": -83.519989, "woe:repo": "woeplanet-poi-us", "geom:area": 0.0, "woe:scale": 19}}