{"type": "Feature", "id": 23600266, "geometry": {"type": "Point", "coordinates": [-91.03627, 38.835609]}, "properties": {"woe:id": 23600266, "woe:parent_id": 2524118, "woe:name": "Wright City High School", "woe:placetype": 20, "woe:placetype_name": "POI", "woe:lang": "ENG", "iso:country": "US", "meta:provider": ["geoplanet:7.4.0", "geoplanet:7.4.1", "geoplanet:7.5.1", "geoplanet:7.5.2", "geoplanet:7.6.0", "geoplanet:7.8.1", "geoplanet:7.9.0", "geoplanet:7.10.0", "geoplanet:8.0.0", "woeplanet:8.0.0"], "meta:indexed": "2020-08-20T23:55:15.773339", "woe:alias_ENG_V": ["Wright City Senior High School", "Wright City High", "Wright City Senior High", "Wright City HS", "Wright City Senior HS"], "meta:updated": "2020-10-14T11:19:36.325017", "woe:hierarchy": {"continent": 24865672, "country": 23424977, "town": 0, "planet": 1, "county": 12589075, "suburb": 0, "state": 2347584, "region": 0, "localadmin": 0}, "woe:timezone_id": 56043661, "woe:hash": "9yzkbmv3v4jp", "woe:centroid": [-91.03627, 38.835609], "geom:latitude": 38.835609, "geom:longitude": -91.03627, "geom:hash": "9yzkbmv3v4jp", "woe:latitude": 38.835609, "geom:centroid": [-91.03627, 38.835609], "woe:longitude": -91.03627, "woe:repo": "woeplanet-poi-us", "geom:area": 0.0, "woe:scale": 19}}