{"type": "Feature", "id": 23594447, "geometry": {"type": "Point", "coordinates": [-93.118538, 44.958439]}, "properties": {"woe:id": 23594447, "woe:parent_id": 55806862, "woe:name": "Jackson Magnet Elementary School", "woe:placetype": 20, "woe:placetype_name": "POI", "woe:lang": "ENG", "iso:country": "US", "meta:provider": ["geoplanet:7.3.1", "geoplanet:7.3.2", "geoplanet:7.4.0", "geoplanet:7.4.1", "geoplanet:7.5.1", "geoplanet:7.5.2", "geoplanet:7.6.0", "geoplanet:7.8.1", "geoplanet:7.9.0", "geoplanet:7.10.0", "geoplanet:8.0.0", "woeplanet:8.0.0"], "meta:indexed": "2020-08-20T20:18:42.857421", "woe:alias_ENG_V": ["Jackson Preparatory Magnet School", "Jackson Magnet Elementary"], "meta:updated": "2020-10-14T11:20:11.918048", "woe:hierarchy": {"continent": 24865672, "country": 23424977, "town": 0, "planet": 1, "county": 12588858, "suburb": 0, "state": 2347582, "region": 0, "localadmin": 0}, "woe:timezone_id": 56043661, "woe:hash": "9zvzc03juu3w", "woe:centroid": [-93.118538, 44.958439], "geom:latitude": 44.958439, "geom:longitude": -93.118538, "geom:hash": "9zvzc03juu3w", "woe:latitude": 44.958439, "geom:centroid": [-93.118538, 44.958439], "woe:longitude": -93.118538, "woe:repo": "woeplanet-poi-us", "geom:area": 0.0, "woe:scale": 19}}