{"type": "Feature", "id": 56053851, "geometry": {"type": "Point", "coordinates": [-85.00209, 34.773151]}, "properties": {"woe:id": 56053851, "woe:parent_id": 2389073, "woe:name": "Dalton State College", "woe:placetype": 20, "woe:placetype_name": "POI", "woe:lang": "ENG", "iso:country": "US", "meta:provider": ["geoplanet:7.3.2", "geoplanet:7.4.0", "geoplanet:7.4.1", "geoplanet:7.5.1", "geoplanet:7.5.2", "geoplanet:7.6.0", "geoplanet:7.8.1", "geoplanet:7.9.0", "geoplanet:7.10.0", "geoplanet:8.0.0", "woeplanet:8.0.0"], "meta:indexed": "2020-08-20T22:03:08.883613", "meta:updated": "2020-10-14T11:19:55.231928", "woe:hierarchy": {"continent": 24865672, "country": 23424977, "town": 0, "planet": 1, "county": 12588024, "suburb": 0, "state": 2347569, "region": 0, "localadmin": 0}, "woe:timezone_id": 56043648, "woe:hash": "dn5tcdr279pv", "woe:centroid": [-85.00209, 34.773151], "geom:latitude": 34.773151, "geom:longitude": -85.00209, "geom:hash": "dn5tcdr279pv", "woe:latitude": 34.773151, "geom:centroid": [-85.00209, 34.773151], "woe:longitude": -85.00209, "woe:repo": "woeplanet-poi-us", "geom:area": 0.0, "woe:scale": 19}}