{"type": "Feature", "id": 23631432, "geometry": {"type": "Point", "coordinates": [-84.220863, 39.769241]}, "properties": {"woe:id": 23631432, "woe:parent_id": 55858700, "woe:name": "Jefferson Primary Ii Elementary School", "woe:placetype": 20, "woe:placetype_name": "POI", "woe:lang": "ENG", "iso:country": "US", "meta:provider": ["geoplanet:7.3.1", "geoplanet:7.3.2", "geoplanet:7.4.0", "geoplanet:7.4.1", "geoplanet:7.5.1", "geoplanet:7.5.2", "geoplanet:7.6.0", "geoplanet:7.8.1", "geoplanet:7.9.0", "geoplanet:7.10.0", "geoplanet:8.0.0", "woeplanet:8.0.0"], "meta:indexed": "2020-08-20T20:18:55.096998", "woe:alias_ENG_V": ["Jefferson Primary Ii Elementary"], "meta:updated": "2020-10-14T11:19:52.870816", "woe:hierarchy": {"continent": 24865672, "country": 23424977, "town": 0, "planet": 1, "county": 12589583, "suburb": 0, "state": 2347594, "region": 0, "localadmin": 0}, "woe:timezone_id": 56043648, "woe:hash": "dph45xb0xeug", "woe:centroid": [-84.220863, 39.769241], "geom:latitude": 39.769241, "geom:longitude": -84.220863, "geom:hash": "dph45xb0xeug", "woe:latitude": 39.769241, "geom:centroid": [-84.220863, 39.769241], "woe:longitude": -84.220863, "woe:repo": "woeplanet-poi-us", "geom:area": 0.0, "woe:scale": 19}}