{"type": "Feature", "id": 23556350, "properties": {"woe:id": 23556350, "woe:parent_id": 2386592, "woe:name": "Highland Junior Senior High School", "woe:placetype": 20, "woe:placetype_name": "POI", "woe:lang": "ENG", "iso:country": "US", "meta:provider": ["geoplanet:7.3.1", "geoplanet:7.3.2", "geoplanet:7.4.0", "geoplanet:7.4.1", "geoplanet:7.5.1", "geoplanet:7.5.2", "geoplanet:7.6.0", "geoplanet:7.8.1", "geoplanet:7.9.0", "geoplanet:7.10.0", "geoplanet:8.0.0", "woeplanet:8.0.0"], "meta:indexed": "2020-08-20T20:18:30.367073", "woe:alias_ENG_V": ["Highland Junior Senior High", "Highland Junior High School", "Highland Junior High", "Highland Junior Senior HS", "Highland Junior HS"], "meta:updated": "2020-08-22T02:58:46.948303", "woe:hierarchy": {"continent": 24865672, "country": 23424977, "town": 0, "planet": 1, "county": 12588064, "suburb": 0, "state": 2347571, "region": 0, "localadmin": 0}, "woe:timezone_id": 56043663, "woe:hash": "c2jpjd6g32t8", "woe:centroid": [-116.473213, 46.243389], "geom:latitude": 46.243389, "geom:longitude": -116.473213, "geom:hash": "c2jpjd6g32t8", "woe:latitude": 46.243389, "geom:centroid": [-116.473213, 46.243389], "woe:longitude": -116.473213, "woe:repo": "woeplanet-poi-us"}, "geometry": {"coordinates": [-116.473213, 46.243389], "type": "Point"}}