{"type": "Feature", "id": 23573596, "geometry": {"type": "Point", "coordinates": [-88.088562, 37.329109]}, "properties": {"woe:id": 23573596, "woe:parent_id": 2445768, "woe:name": "Crittenden Co Middle School", "woe:placetype": 20, "woe:placetype_name": "POI", "woe:lang": "ENG", "iso:country": "US", "meta:provider": ["geoplanet:7.3.1", "geoplanet:7.3.2", "geoplanet:7.4.0", "geoplanet:7.4.1", "geoplanet:7.5.1", "geoplanet:7.5.2", "geoplanet:7.6.0", "geoplanet:7.8.1", "geoplanet:7.9.0", "geoplanet:7.10.0", "geoplanet:8.0.0", "woeplanet:8.0.0"], "meta:indexed": "2020-08-20T20:18:36.670690", "meta:updated": "2020-10-14T11:20:10.991345", "woe:hierarchy": {"continent": 24865672, "country": 23424977, "town": 0, "planet": 1, "county": 12588503, "suburb": 0, "state": 2347576, "region": 0, "localadmin": 0}, "woe:timezone_id": 56043647, "woe:hash": "dn9k77xcgdr2", "woe:centroid": [-88.088562, 37.329109], "geom:latitude": 37.329109, "geom:longitude": -88.088562, "geom:hash": "dn9k77xcgdr2", "woe:latitude": 37.329109, "geom:centroid": [-88.088562, 37.329109], "woe:longitude": -88.088562, "woe:repo": "woeplanet-poi-us", "geom:area": 0.0, "woe:scale": 19}}