{"type": "Feature", "id": 23599211, "properties": {"woe:id": 23599211, "woe:parent_id": 2503009, "woe:name": "Swedeborg Elementary School", "woe:placetype": 20, "woe:placetype_name": "POI", "woe:lang": "ENG", "iso:country": "US", "meta:provider": ["geoplanet:7.3.1", "geoplanet:7.3.2", "geoplanet:7.4.0", "geoplanet:7.4.1", "geoplanet:7.5.1", "geoplanet:7.5.2", "geoplanet:7.6.0", "geoplanet:7.8.1", "geoplanet:7.9.0", "geoplanet:7.10.0", "geoplanet:8.0.0", "woeplanet:8.0.0"], "meta:indexed": "2020-08-20T20:18:44.542959", "woe:alias_ENG_V": ["Swedeborg Elementary"], "meta:updated": "2020-08-22T02:57:40.912522", "woe:hierarchy": {"continent": 24865672, "country": 23424977, "town": 0, "planet": 1, "county": 12589050, "suburb": 0, "state": 2347584, "region": 0, "localadmin": 0}, "woe:timezone_id": 56043661, "woe:hash": "9ywrdvnn6wjh", "woe:centroid": [-92.331734, 37.909431], "geom:latitude": 37.909431, "geom:longitude": -92.331734, "geom:hash": "9ywrdvnn6wjh", "woe:latitude": 37.909431, "geom:centroid": [-92.331734, 37.909431], "woe:longitude": -92.331734, "woe:repo": "woeplanet-poi-us"}, "geometry": {"coordinates": [-92.331734, 37.909431], "type": "Point"}}