{"type": "Feature", "id": 23581876, "properties": {"woe:id": 23581876, "woe:parent_id": 29229483, "woe:name": "Mildred D. Monroe Elementary School", "woe:placetype": 20, "woe:placetype_name": "POI", "woe:lang": "ENG", "iso:country": "US", "meta:provider": ["geoplanet:7.3.1", "geoplanet:7.3.2", "geoplanet:7.4.0", "geoplanet:7.4.1", "geoplanet:7.5.1", "geoplanet:7.5.2", "geoplanet:7.6.0", "geoplanet:7.8.1", "geoplanet:7.9.0", "geoplanet:7.10.0", "geoplanet:8.0.0", "woeplanet:8.0.0"], "meta:indexed": "2020-08-20T20:18:38.902788", "woe:alias_ENG_V": ["Mildred D. Monroe Elementary"], "meta:updated": "2020-08-22T02:57:38.148583", "woe:hierarchy": {"continent": 24865672, "country": 23424977, "town": 0, "planet": 1, "county": 12588679, "suburb": 0, "state": 2347579, "region": 0, "localadmin": 0}, "woe:timezone_id": 56043648, "woe:hash": "dqcx8eudmsy7", "woe:centroid": [-76.612228, 39.308121], "geom:latitude": 39.308121, "geom:longitude": -76.612228, "geom:hash": "dqcx8eudmsy7", "woe:latitude": 39.308121, "geom:centroid": [-76.612228, 39.308121], "woe:longitude": -76.612228, "woe:repo": "woeplanet-poi-us"}, "geometry": {"coordinates": [-76.612228, 39.308121], "type": "Point"}}