{"type": "Feature", "id": 23634981, "properties": {"woe:id": 23634981, "woe:parent_id": 2385382, "woe:name": "Hoover Elementary School", "woe:placetype": 20, "woe:placetype_name": "POI", "woe:lang": "ENG", "iso:country": "US", "meta:provider": ["geoplanet:7.3.1", "geoplanet:7.3.2", "geoplanet:7.4.0", "geoplanet:7.4.1", "geoplanet:7.5.1", "geoplanet:7.5.2", "geoplanet:7.6.0", "geoplanet:7.8.1", "geoplanet:7.9.0", "geoplanet:7.10.0", "geoplanet:8.0.0", "woeplanet:8.0.0"], "meta:indexed": "2020-08-20T20:18:56.666846", "woe:alias_ENG_V": ["Hoover Elementary"], "meta:updated": "2020-08-22T02:57:45.969841", "woe:hierarchy": {"continent": 24865672, "country": 23424977, "town": 0, "planet": 1, "county": 12589693, "suburb": 0, "state": 2347596, "region": 0, "localadmin": 0}, "woe:timezone_id": 56043663, "woe:hash": "9rbmdmctsssn", "woe:centroid": [-123.297302, 44.593102], "geom:latitude": 44.593102, "geom:longitude": -123.297302, "geom:hash": "9rbmdmctsssn", "woe:latitude": 44.593102, "geom:centroid": [-123.297302, 44.593102], "woe:longitude": -123.297302, "woe:repo": "woeplanet-poi-us"}, "geometry": {"coordinates": [-123.297302, 44.593102], "type": "Point"}}