{"type": "Feature", "id": 23576605, "properties": {"woe:id": 23576605, "woe:parent_id": 2440845, "woe:name": "Lockport Junior High School", "woe:placetype": 20, "woe:placetype_name": "POI", "woe:lang": "ENG", "iso:country": "US", "meta:provider": ["geoplanet:7.3.1", "geoplanet:7.3.2", "geoplanet:7.4.0", "geoplanet:7.4.1", "geoplanet:7.5.1", "geoplanet:7.5.2", "geoplanet:7.6.0", "geoplanet:7.8.1", "geoplanet:7.9.0", "geoplanet:7.10.0", "geoplanet:8.0.0", "woeplanet:8.0.0"], "meta:indexed": "2020-08-20T20:18:37.600461", "woe:alias_ENG_V": ["Lockport Middle School", "Lockport Junior High"], "meta:updated": "2020-08-22T02:57:37.287992", "woe:hierarchy": {"continent": 24865672, "country": 23424977, "town": 0, "planet": 1, "county": 12588625, "suburb": 0, "state": 2347577, "region": 0, "localadmin": 0}, "woe:timezone_id": 56043661, "woe:hash": "9vr8eusgcybx", "woe:centroid": [-90.531731, 29.644541], "geom:latitude": 29.644541, "geom:longitude": -90.531731, "geom:hash": "9vr8eusgcybx", "woe:latitude": 29.644541, "geom:centroid": [-90.531731, 29.644541], "woe:longitude": -90.531731, "woe:repo": "woeplanet-poi-us"}, "geometry": {"coordinates": [-90.531731, 29.644541], "type": "Point"}}