{"type": "Feature", "id": 23602710, "properties": {"woe:id": 23602710, "woe:parent_id": 2481688, "woe:name": "Rising City High School", "woe:placetype": 20, "woe:placetype_name": "POI", "woe:lang": "ENG", "iso:country": "US", "meta:provider": ["geoplanet:7.3.1", "geoplanet:7.3.2", "geoplanet:7.4.0", "geoplanet:7.4.1", "geoplanet:7.5.1", "geoplanet:7.5.2", "geoplanet:7.6.0", "geoplanet:7.8.1", "geoplanet:7.9.0", "geoplanet:7.10.0", "geoplanet:8.0.0", "woeplanet:8.0.0"], "meta:indexed": "2020-08-20T20:18:45.432120", "woe:alias_ENG_V": ["Rising City Senior High School", "Rising City High", "Rising City Senior High", "Rising City HS", "Rising City Senior HS", "Rising City Public School"], "meta:updated": "2020-08-22T02:58:48.378737", "woe:hierarchy": {"continent": 24865672, "country": 23424977, "town": 0, "planet": 1, "county": 12589149, "suburb": 0, "state": 2347586, "region": 0, "localadmin": 0}, "woe:timezone_id": 56043661, "woe:hash": "9z6f65c8hk22", "woe:centroid": [-97.292679, 41.19738], "geom:latitude": 41.19738, "geom:longitude": -97.292679, "geom:hash": "9z6f65c8hk22", "woe:latitude": 41.19738, "geom:centroid": [-97.292679, 41.19738], "woe:longitude": -97.292679, "woe:repo": "woeplanet-poi-us"}, "geometry": {"coordinates": [-97.292679, 41.19738], "type": "Point"}}