{"type": "Feature", "id": 23656359, "properties": {"woe:id": 23656359, "woe:parent_id": 56022661, "woe:name": "Lamar High School", "woe:placetype": 20, "woe:placetype_name": "POI", "woe:lang": "ENG", "iso:country": "US", "meta:provider": ["geoplanet:7.3.1", "geoplanet:7.3.2", "geoplanet:7.4.0", "geoplanet:7.4.1", "geoplanet:7.5.1", "geoplanet:7.5.2", "geoplanet:7.6.0", "geoplanet:7.8.1", "geoplanet:7.9.0", "geoplanet:7.10.0", "geoplanet:8.0.0", "woeplanet:8.0.0"], "meta:indexed": "2020-08-20T20:19:04.294361", "woe:alias_ENG_V": ["Lamar Senior High School", "Lamar High", "Lamar Senior High", "Lamar HS", "Lamar Senior HS"], "meta:updated": "2020-08-22T02:58:49.910443", "woe:hierarchy": {"continent": 24865672, "country": 23424977, "town": 0, "planet": 1, "county": 12590226, "suburb": 0, "state": 2347602, "region": 0, "localadmin": 0}, "woe:timezone_id": 56043661, "woe:hash": "9vffmudu0hvs", "woe:centroid": [-97.126343, 32.76469], "geom:latitude": 32.76469, "geom:longitude": -97.126343, "geom:hash": "9vffmudu0hvs", "woe:latitude": 32.76469, "geom:centroid": [-97.126343, 32.76469], "woe:longitude": -97.126343, "woe:repo": "woeplanet-poi-us"}, "geometry": {"coordinates": [-97.126343, 32.76469], "type": "Point"}}