{"type": "Feature", "id": 23530791, "geometry": {"type": "Point", "coordinates": [-118.216721, 34.052429]}, "properties": {"woe:id": 23530791, "woe:parent_id": 2367702, "woe:name": "Bridge Street Elementary School", "woe:placetype": 20, "woe:placetype_name": "POI", "woe:lang": "ENG", "iso:country": "US", "meta:provider": ["geoplanet:7.3.2", "geoplanet:7.4.0", "geoplanet:7.4.1", "geoplanet:7.5.1", "geoplanet:7.5.2", "geoplanet:7.6.0", "geoplanet:7.8.1", "geoplanet:7.9.0", "geoplanet:7.10.0", "geoplanet:8.0.0", "woeplanet:8.0.0"], "meta:indexed": "2020-08-20T22:02:02.017852", "woe:alias_ENG_V": ["Bridge Street Elementary"], "meta:updated": "2020-10-14T11:20:08.099171", "woe:hierarchy": {"continent": 24865672, "country": 23424977, "town": 0, "planet": 1, "county": 12587688, "suburb": 0, "state": 2347563, "region": 0, "localadmin": 0}, "woe:timezone_id": 56043663, "woe:hash": "9q5ctzj1y8zg", "woe:centroid": [-118.216721, 34.052429], "geom:latitude": 34.052429, "geom:longitude": -118.216721, "geom:hash": "9q5ctzj1y8zg", "woe:latitude": 34.052429, "geom:centroid": [-118.216721, 34.052429], "woe:longitude": -118.216721, "woe:repo": "woeplanet-poi-us", "geom:area": 0.0, "woe:scale": 19}}