{"type": "Feature", "id": 23559337, "geometry": {"type": "Point", "coordinates": [-87.771912, 41.752258]}, "properties": {"woe:id": 23559337, "woe:parent_id": 2371862, "woe:name": "Reavis High School", "woe:placetype": 20, "woe:placetype_name": "POI", "woe:lang": "ENG", "iso:country": "US", "meta:provider": ["geoplanet:7.3.1", "geoplanet:7.3.2", "geoplanet:7.4.0", "geoplanet:7.4.1", "geoplanet:7.5.1", "geoplanet:7.5.2", "geoplanet:7.6.0", "geoplanet:7.8.1", "geoplanet:7.9.0", "geoplanet:7.10.0", "geoplanet:8.0.0", "woeplanet:8.0.0"], "meta:indexed": "2020-08-20T20:18:31.425646", "woe:alias_ENG_V": ["Reavis Senior High School", "Reavis High", "Reavis Senior High", "Reavis HS", "Reavis Senior HS"], "meta:updated": "2020-10-14T11:20:14.617009", "woe:hierarchy": {"continent": 24865672, "country": 23424977, "town": 0, "planet": 1, "county": 12588093, "suburb": 0, "state": 2347572, "region": 0, "localadmin": 0}, "woe:timezone_id": 56043661, "woe:hash": "dp3td8y2w1nb", "woe:centroid": [-87.771912, 41.752258], "geom:latitude": 41.752258, "geom:longitude": -87.771912, "geom:hash": "dp3td8y2w1nb", "woe:latitude": 41.752258, "geom:centroid": [-87.771912, 41.752258], "woe:longitude": -87.771912, "woe:repo": "woeplanet-poi-us", "geom:area": 0.0, "woe:scale": 19}}