{"type": "Feature", "id": 23573111, "properties": {"woe:id": 23573111, "woe:parent_id": 55859858, "woe:name": "Hazel Grove Elementary School", "woe:placetype": 20, "woe:placetype_name": "POI", "woe:lang": "ENG", "iso:country": "US", "meta:provider": ["geoplanet:7.3.1", "geoplanet:7.3.2", "geoplanet:7.4.0", "geoplanet:7.4.1", "geoplanet:7.5.1", "geoplanet:7.5.2", "geoplanet:7.6.0", "geoplanet:7.8.1", "geoplanet:7.9.0", "geoplanet:7.10.0", "geoplanet:8.0.0", "woeplanet:8.0.0"], "meta:indexed": "2020-08-20T20:18:36.542927", "woe:alias_ENG_V": ["Hazel Grove Elemntary School", "Hazel Grove Elementary"], "meta:updated": "2020-08-22T02:57:36.754233", "woe:hierarchy": {"continent": 24865672, "country": 23424977, "town": 0, "planet": 1, "county": 12588475, "suburb": 0, "state": 2347575, "region": 0, "localadmin": 0}, "woe:timezone_id": 56043661, "woe:hash": "9yuws7bcgukz", "woe:centroid": [-94.73391, 39.132252], "geom:latitude": 39.132252, "geom:longitude": -94.73391, "geom:hash": "9yuws7bcgukz", "woe:latitude": 39.132252, "geom:centroid": [-94.73391, 39.132252], "woe:longitude": -94.73391, "woe:repo": "woeplanet-poi-us"}, "geometry": {"coordinates": [-94.73391, 39.132252], "type": "Point"}}