{"type": "Feature", "id": 23574748, "geometry": {"type": "Point", "coordinates": [-88.0784, 37.096581]}, "properties": {"woe:id": 23574748, "woe:parent_id": 2396947, "woe:name": "Lyon Co Elementary School", "woe:placetype": 20, "woe:placetype_name": "POI", "woe:lang": "ENG", "iso:country": "US", "meta:provider": ["geoplanet:7.3.1", "geoplanet:7.3.2", "geoplanet:7.4.0", "geoplanet:7.4.1", "geoplanet:7.5.1", "geoplanet:7.5.2", "geoplanet:7.6.0", "geoplanet:7.8.1", "geoplanet:7.9.0", "geoplanet:7.10.0", "geoplanet:8.0.0", "woeplanet:8.0.0"], "meta:indexed": "2020-08-20T20:18:37.019361", "woe:alias_ENG_V": ["Lyon Co Elementary"], "meta:updated": "2020-10-14T11:20:21.878561", "woe:hierarchy": {"continent": 24865672, "country": 23424977, "town": 0, "planet": 1, "county": 12588547, "suburb": 0, "state": 2347576, "region": 0, "localadmin": 0}, "woe:timezone_id": 56043647, "woe:hash": "dn9759pr0xbv", "woe:centroid": [-88.0784, 37.096581], "geom:latitude": 37.096581, "geom:longitude": -88.0784, "geom:hash": "dn9759pr0xbv", "woe:latitude": 37.096581, "geom:centroid": [-88.0784, 37.096581], "woe:longitude": -88.0784, "woe:repo": "woeplanet-poi-us", "geom:area": 0.0, "woe:scale": 19}}