{"type": "Feature", "id": 23593803, "geometry": {"type": "Point", "coordinates": [-93.522247, 47.240269]}, "properties": {"woe:id": 23593803, "woe:parent_id": 2412844, "woe:name": "Murphy Elementary School", "woe:placetype": 20, "woe:placetype_name": "POI", "woe:lang": "ENG", "iso:country": "US", "meta:provider": ["geoplanet:7.3.1", "geoplanet:7.3.2", "geoplanet:7.4.0", "geoplanet:7.4.1", "geoplanet:7.5.1", "geoplanet:7.5.2", "geoplanet:7.6.0", "geoplanet:7.8.1", "geoplanet:7.9.0", "geoplanet:7.10.0", "geoplanet:8.0.0", "woeplanet:8.0.0"], "meta:indexed": "2020-08-20T20:18:42.593617", "woe:alias_ENG_V": ["Edna I Murphy Elementary School", "Murphy Elementary"], "meta:updated": "2020-10-14T11:20:16.039614", "woe:hierarchy": {"continent": 24865672, "country": 23424977, "town": 0, "planet": 1, "county": 12588827, "suburb": 0, "state": 2347582, "region": 0, "localadmin": 0}, "woe:timezone_id": 56043661, "woe:hash": "cbmkxzg4t8qm", "woe:centroid": [-93.522247, 47.240269], "geom:latitude": 47.240269, "geom:longitude": -93.522247, "geom:hash": "cbmkxzg4t8qm", "woe:latitude": 47.240269, "geom:centroid": [-93.522247, 47.240269], "woe:longitude": -93.522247, "woe:repo": "woeplanet-poi-us", "geom:area": 0.0, "woe:scale": 19}}