{"type": "Feature", "id": 56053278, "properties": {"woe:id": 56053278, "woe:parent_id": 55986628, "woe:name": "Indiana University-Purdue Univ", "woe:placetype": 20, "woe:placetype_name": "POI", "woe:lang": "ENG", "iso:country": "US", "meta:provider": ["geoplanet:7.3.1", "geoplanet:7.3.2", "geoplanet:7.4.0", "geoplanet:7.4.1", "geoplanet:7.5.1", "geoplanet:7.5.2", "geoplanet:7.6.0", "geoplanet:7.8.1", "geoplanet:7.9.0", "geoplanet:7.10.0", "geoplanet:8.0.0", "woeplanet:8.0.0"], "meta:indexed": "2020-08-20T20:19:16.913622", "woe:alias_ENG_V": ["Iupui"], "meta:updated": "2020-08-22T02:58:20.779878", "woe:hierarchy": {"continent": 24865672, "country": 23424977, "town": 0, "planet": 1, "county": 12588228, "suburb": 0, "state": 2347573, "region": 0, "localadmin": 0}, "woe:timezone_id": 56043656, "woe:hash": "dp4dr08cfst8", "woe:centroid": [-86.175613, 39.773579], "geom:latitude": 39.773579, "geom:longitude": -86.175613, "geom:hash": "dp4dr08cfst8", "woe:latitude": 39.773579, "geom:centroid": [-86.175613, 39.773579], "woe:longitude": -86.175613, "woe:repo": "woeplanet-poi-us"}, "geometry": {"coordinates": [-86.175613, 39.773579], "type": "Point"}}