{"type": "Feature", "id": 23551566, "properties": {"woe:id": 23551566, "woe:parent_id": 2497050, "woe:name": "Boston Elementary School", "woe:placetype": 20, "woe:placetype_name": "POI", "woe:lang": "ENG", "iso:country": "US", "meta:provider": ["geoplanet:7.3.2", "geoplanet:7.4.0", "geoplanet:7.4.1", "geoplanet:7.5.1", "geoplanet:7.5.2", "geoplanet:7.6.0", "geoplanet:7.8.1", "geoplanet:7.9.0", "geoplanet:7.10.0", "geoplanet:8.0.0", "woeplanet:8.0.0"], "meta:indexed": "2020-08-20T22:02:10.899734", "woe:alias_ENG_V": ["Kleven Boston Elementary School", "Boston Elementary"], "meta:updated": "2020-08-22T02:57:32.823498", "woe:hierarchy": {"continent": 24865672, "country": 23424977, "town": 0, "planet": 1, "county": 12587897, "suburb": 0, "state": 2347569, "region": 0, "localadmin": 0}, "woe:timezone_id": 56043648, "woe:hash": "dn5f5j5c2gk5", "woe:centroid": [-84.589539, 34.129261], "geom:latitude": 34.129261, "geom:longitude": -84.589539, "geom:hash": "dn5f5j5c2gk5", "woe:latitude": 34.129261, "geom:centroid": [-84.589539, 34.129261], "woe:longitude": -84.589539, "woe:repo": "woeplanet-poi-us"}, "geometry": {"coordinates": [-84.589539, 34.129261], "type": "Point"}}