{"type": "Feature", "id": 23542909, "properties": {"woe:id": 23542909, "woe:parent_id": 2364896, "woe:name": "Barnum Station", "woe:placetype": 20, "woe:placetype_name": "POI", "woe:lang": "ENG", "iso:country": "US", "meta:provider": ["geoplanet:7.3.1", "geoplanet:7.3.2", "geoplanet:7.4.0", "geoplanet:7.4.1", "geoplanet:7.5.1", "geoplanet:7.5.2", "geoplanet:7.6.0", "geoplanet:7.8.1", "geoplanet:7.9.0", "geoplanet:7.10.0", "geoplanet:8.0.0", "woeplanet:8.0.0"], "meta:indexed": "2020-08-20T20:18:25.065519", "meta:updated": "2020-08-22T02:57:31.014598", "woe:hierarchy": {"continent": 24865672, "country": 23424977, "town": 0, "planet": 1, "county": 12587791, "suburb": 0, "state": 2347565, "region": 0, "localadmin": 0}, "woe:timezone_id": 56043648, "woe:hash": "dr7fjvdst5v7", "woe:centroid": [-73.220222, 41.163818], "geom:latitude": 41.163818, "geom:longitude": -73.220222, "geom:hash": "dr7fjvdst5v7", "woe:latitude": 41.163818, "geom:centroid": [-73.220222, 41.163818], "woe:longitude": -73.220222, "woe:repo": "woeplanet-poi-us"}, "geometry": {"coordinates": [-73.220222, 41.163818], "type": "Point"}}