{"type": "Feature", "id": 23557004, "geometry": {"type": "Point", "coordinates": [-88.181328, 40.105751]}, "properties": {"woe:id": 23557004, "woe:parent_id": 2510436, "woe:name": "Prairie Elementary School", "woe:placetype": 20, "woe:placetype_name": "POI", "woe:lang": "ENG", "iso:country": "US", "meta:provider": ["geoplanet:7.3.1", "geoplanet:7.3.2", "geoplanet:7.4.0", "geoplanet:7.4.1", "geoplanet:7.5.1", "geoplanet:7.5.2", "geoplanet:7.6.0", "geoplanet:7.8.1", "geoplanet:7.9.0", "geoplanet:7.10.0", "geoplanet:8.0.0", "woeplanet:8.0.0"], "meta:indexed": "2020-08-20T20:18:30.538595", "woe:alias_ENG_V": ["Prairie Elementary"], "meta:updated": "2020-10-14T11:20:25.691078", "woe:hierarchy": {"continent": 24865672, "country": 23424977, "town": 0, "planet": 1, "county": 12588087, "suburb": 0, "state": 2347572, "region": 0, "localadmin": 0}, "woe:timezone_id": 56043661, "woe:hash": "dp1k1mh2fju5", "woe:centroid": [-88.181328, 40.105751], "geom:latitude": 40.105751, "geom:longitude": -88.181328, "geom:hash": "dp1k1mh2fju5", "woe:latitude": 40.105751, "geom:centroid": [-88.181328, 40.105751], "woe:longitude": -88.181328, "woe:repo": "woeplanet-poi-us", "geom:area": 0.0, "woe:scale": 19}}