{"type": "Feature", "id": 23568526, "geometry": {"type": "Point", "coordinates": [-85.829239, 40.781029]}, "properties": {"woe:id": 23568526, "woe:parent_id": 2512895, "woe:name": "W C Mills Elementary School", "woe:placetype": 20, "woe:placetype_name": "POI", "woe:lang": "ENG", "iso:country": "US", "meta:provider": ["geoplanet:7.3.1", "geoplanet:7.3.2", "geoplanet:7.4.0", "geoplanet:7.4.1", "geoplanet:7.5.1", "geoplanet:7.5.2", "geoplanet:7.6.0", "geoplanet:7.8.1", "geoplanet:7.9.0", "geoplanet:7.10.0", "geoplanet:8.0.0", "woeplanet:8.0.0"], "meta:indexed": "2020-08-20T20:18:34.836002", "woe:alias_ENG_V": ["W C Mills Elementary"], "meta:updated": "2020-10-14T11:20:13.249763", "woe:hierarchy": {"continent": 24865672, "country": 23424977, "town": 0, "planet": 1, "county": 12588264, "suburb": 0, "state": 2347573, "region": 0, "localadmin": 0}, "woe:timezone_id": 56043656, "woe:hash": "dp4zyzvn9ybc", "woe:centroid": [-85.829239, 40.781029], "geom:latitude": 40.781029, "geom:longitude": -85.829239, "geom:hash": "dp4zyzvn9ybc", "woe:latitude": 40.781029, "geom:centroid": [-85.829239, 40.781029], "woe:longitude": -85.829239, "woe:repo": "woeplanet-poi-us", "geom:area": 0.0, "woe:scale": 19}}