{"type": "Feature", "id": 23521731, "geometry": {"type": "Point", "coordinates": [-122.1922, 39.741009]}, "properties": {"woe:id": 23521731, "woe:parent_id": 2466246, "woe:name": "Price Intermediate School", "woe:placetype": 20, "woe:placetype_name": "POI", "woe:lang": "ENG", "iso:country": "US", "meta:provider": ["geoplanet:7.3.1", "geoplanet:7.3.2", "geoplanet:7.4.0", "geoplanet:7.4.1", "geoplanet:7.5.1", "geoplanet:7.5.2", "geoplanet:7.6.0", "geoplanet:7.8.1", "geoplanet:7.9.0", "geoplanet:7.10.0", "geoplanet:8.0.0", "woeplanet:8.0.0"], "meta:indexed": "2020-08-20T20:18:19.883601", "meta:updated": "2020-10-14T11:20:10.316982", "woe:hierarchy": {"continent": 24865672, "country": 23424977, "town": 0, "planet": 1, "county": 12587680, "suburb": 0, "state": 2347563, "region": 0, "localadmin": 0}, "woe:timezone_id": 56043663, "woe:hash": "9r1456wk5m5b", "woe:centroid": [-122.1922, 39.741009], "geom:latitude": 39.741009, "geom:longitude": -122.1922, "geom:hash": "9r1456wk5m5b", "woe:latitude": 39.741009, "geom:centroid": [-122.1922, 39.741009], "woe:longitude": -122.1922, "woe:repo": "woeplanet-poi-us", "geom:area": 0.0, "woe:scale": 19}}