{"type": "Feature", "id": 23564545, "properties": {"woe:id": 23564545, "woe:parent_id": 2424100, "woe:name": "John Greer Elementary School", "woe:placetype": 20, "woe:placetype_name": "POI", "woe:lang": "ENG", "iso:country": "US", "meta:provider": ["geoplanet:7.3.1", "geoplanet:7.3.2", "geoplanet:7.4.0", "geoplanet:7.4.1", "geoplanet:7.5.1", "geoplanet:7.5.2", "geoplanet:7.6.0", "geoplanet:7.8.1", "geoplanet:7.9.0", "geoplanet:7.10.0", "geoplanet:8.0.0", "woeplanet:8.0.0"], "meta:indexed": "2020-08-20T20:18:33.266699", "woe:alias_ENG_V": ["John Greer Elementary"], "meta:updated": "2020-08-22T02:57:35.237480", "woe:hierarchy": {"continent": 24865672, "country": 23424977, "town": 0, "planet": 1, "county": 12588169, "suburb": 0, "state": 2347572, "region": 0, "localadmin": 0}, "woe:timezone_id": 56043661, "woe:hash": "dp1wjnvm89yb", "woe:centroid": [-87.663658, 40.46772], "geom:latitude": 40.46772, "geom:longitude": -87.663658, "geom:hash": "dp1wjnvm89yb", "woe:latitude": 40.46772, "geom:centroid": [-87.663658, 40.46772], "woe:longitude": -87.663658, "woe:repo": "woeplanet-poi-us"}, "geometry": {"coordinates": [-87.663658, 40.46772], "type": "Point"}}