{"type": "Feature", "id": 23614301, "properties": {"woe:id": 23614301, "woe:parent_id": 2354311, "woe:name": "Heim Middle School", "woe:placetype": 20, "woe:placetype_name": "POI", "woe:lang": "ENG", "iso:country": "US", "meta:provider": ["geoplanet:7.3.1", "geoplanet:7.3.2", "geoplanet:7.4.0", "geoplanet:7.4.1", "geoplanet:7.5.1", "geoplanet:7.5.2", "geoplanet:7.6.0", "geoplanet:7.8.1", "geoplanet:7.9.0", "geoplanet:7.10.0", "geoplanet:8.0.0", "woeplanet:8.0.0"], "meta:indexed": "2020-08-20T20:18:49.148750", "meta:updated": "2020-08-22T02:57:42.880113", "woe:hierarchy": {"continent": 24865672, "country": 23424977, "town": 0, "planet": 1, "county": 12589326, "suburb": 0, "state": 2347591, "region": 0, "localadmin": 0}, "woe:timezone_id": 56043648, "woe:hash": "dpxuxvbq47rz", "woe:centroid": [-78.760536, 43.01115], "geom:latitude": 43.01115, "geom:longitude": -78.760536, "geom:hash": "dpxuxvbq47rz", "woe:latitude": 43.01115, "geom:centroid": [-78.760536, 43.01115], "woe:longitude": -78.760536, "woe:repo": "woeplanet-poi-us"}, "geometry": {"coordinates": [-78.760536, 43.01115], "type": "Point"}}