{"type": "Feature", "id": 23628460, "geometry": {"type": "Point", "coordinates": [-81.79998, 41.37138]}, "properties": {"woe:id": 23628460, "woe:parent_id": 56022296, "woe:name": "Scribes and Scribblers Development Center", "woe:placetype": 20, "woe:placetype_name": "POI", "woe:lang": "ENG", "iso:country": "US", "meta:provider": ["geoplanet:7.3.1", "geoplanet:7.3.2", "geoplanet:7.4.0", "geoplanet:7.4.1", "geoplanet:7.5.1", "geoplanet:7.5.2", "geoplanet:7.6.0", "geoplanet:7.8.1", "geoplanet:7.9.0", "geoplanet:7.10.0", "geoplanet:8.0.0", "woeplanet:8.0.0"], "meta:indexed": "2020-08-20T20:18:53.771855", "woe:alias_ENG_V": ["Scribes & Scribblers Development Center"], "meta:updated": "2020-10-14T11:19:41.151326", "woe:hierarchy": {"continent": 24865672, "country": 23424977, "town": 0, "planet": 1, "county": 12589544, "suburb": 0, "state": 2347594, "region": 0, "localadmin": 0}, "woe:timezone_id": 56043648, "woe:hash": "dpmg6e7jf24n", "woe:centroid": [-81.79998, 41.37138], "geom:latitude": 41.37138, "geom:longitude": -81.79998, "geom:hash": "dpmg6e7jf24n", "woe:latitude": 41.37138, "geom:centroid": [-81.79998, 41.37138], "woe:longitude": -81.79998, "woe:repo": "woeplanet-poi-us", "geom:area": 0.0, "woe:scale": 19}}