{"type": "Feature", "id": 23654137, "properties": {"woe:id": 23654137, "woe:parent_id": 29229749, "woe:name": "Airlawn Station", "woe:placetype": 20, "woe:placetype_name": "POI", "woe:lang": "ENG", "iso:country": "US", "meta:provider": ["geoplanet:7.3.1", "geoplanet:7.3.2", "geoplanet:7.4.0", "geoplanet:7.4.1", "geoplanet:7.5.1", "geoplanet:7.5.2", "geoplanet:7.6.0", "geoplanet:7.8.1", "geoplanet:7.9.0", "geoplanet:7.10.0", "geoplanet:8.0.0", "woeplanet:8.0.0"], "meta:indexed": "2020-08-20T20:19:03.226379", "meta:updated": "2020-08-22T02:57:48.992408", "woe:hierarchy": {"continent": 24865672, "country": 23424977, "town": 0, "planet": 1, "county": 12590063, "suburb": 0, "state": 2347602, "region": 0, "localadmin": 0}, "woe:timezone_id": 56043661, "woe:hash": "9vg4sqgjc4pz", "woe:centroid": [-96.840309, 32.821281], "geom:latitude": 32.821281, "geom:longitude": -96.840309, "geom:hash": "9vg4sqgjc4pz", "woe:latitude": 32.821281, "geom:centroid": [-96.840309, 32.821281], "woe:longitude": -96.840309, "woe:repo": "woeplanet-poi-us"}, "geometry": {"coordinates": [-96.840309, 32.821281], "type": "Point"}}