{"type": "Feature", "id": 23614383, "properties": {"woe:id": 23614383, "woe:parent_id": 2495437, "woe:name": "Christ the King Elementary School", "woe:placetype": 20, "woe:placetype_name": "POI", "woe:lang": "ENG", "iso:country": "US", "meta:provider": ["geoplanet:7.3.1", "geoplanet:7.3.2", "geoplanet:7.4.0", "geoplanet:7.4.1", "geoplanet:7.5.1", "geoplanet:7.5.2", "geoplanet:7.6.0", "geoplanet:7.8.1", "geoplanet:7.9.0", "geoplanet:7.10.0", "geoplanet:8.0.0", "woeplanet:8.0.0"], "meta:indexed": "2020-08-20T20:18:49.183061", "woe:alias_ENG_V": ["Christ the King Elementary"], "meta:updated": "2020-08-22T02:57:42.896245", "woe:hierarchy": {"continent": 24865672, "country": 23424977, "town": 0, "planet": 1, "county": 12589326, "suburb": 0, "state": 2347591, "region": 0, "localadmin": 0}, "woe:timezone_id": 56043648, "woe:hash": "dpxurkwmb0vf", "woe:centroid": [-78.774368, 42.960281], "geom:latitude": 42.960281, "geom:longitude": -78.774368, "geom:hash": "dpxurkwmb0vf", "woe:latitude": 42.960281, "geom:centroid": [-78.774368, 42.960281], "woe:longitude": -78.774368, "woe:repo": "woeplanet-poi-us"}, "geometry": {"coordinates": [-78.774368, 42.960281], "type": "Point"}}