{"type": "Feature", "id": 56204436, "geometry": {"type": "Point", "coordinates": [-73.974373, 40.68549]}, "properties": {"woe:id": 56204436, "woe:parent_id": 28751452, "woe:name": "Mocada", "woe:placetype": 20, "woe:placetype_name": "POI", "woe:lang": "ENG", "iso:country": "US", "meta:provider": ["geoplanet:7.6.0", "geoplanet:7.8.1", "geoplanet:7.9.0", "geoplanet:7.10.0", "geoplanet:8.0.0", "woeplanet:8.0.0"], "meta:indexed": "2020-08-21T08:24:23.991676", "meta:updated": "2020-10-14T11:20:01.299932", "woe:hierarchy": {"continent": 24865672, "country": 23424977, "town": 0, "planet": 1, "county": 12589335, "suburb": 0, "state": 2347591, "region": 0, "localadmin": 0}, "woe:timezone_id": 56043648, "woe:hash": "dr5rkwtd0jj9", "woe:centroid": [-73.974373, 40.68549], "geom:latitude": 40.68549, "geom:longitude": -73.974373, "geom:hash": "dr5rkwtd0jj9", "woe:latitude": 40.68549, "geom:centroid": [-73.974373, 40.68549], "woe:longitude": -73.974373, "woe:repo": "woeplanet-poi-us", "geom:area": 0.0, "woe:scale": 19}}