{"type": "Feature", "id": 23598387, "properties": {"woe:id": 23598387, "woe:parent_id": 2374984, "woe:name": "Carl Junction Junior High School", "woe:placetype": 20, "woe:placetype_name": "POI", "woe:lang": "ENG", "iso:country": "US", "meta:provider": ["geoplanet:7.3.1", "geoplanet:7.3.2", "geoplanet:7.4.0", "geoplanet:7.4.1", "geoplanet:7.5.1", "geoplanet:7.5.2", "geoplanet:7.6.0", "geoplanet:7.8.1", "geoplanet:7.9.0", "geoplanet:7.10.0", "geoplanet:8.0.0", "woeplanet:8.0.0"], "meta:indexed": "2020-08-20T20:18:44.250775", "woe:alias_ENG_V": ["Carl Junction Jr High School", "Carl Junction Junior High"], "meta:updated": "2020-08-22T02:57:40.787654", "woe:hierarchy": {"continent": 24865672, "country": 23424977, "town": 0, "planet": 1, "county": 12589014, "suburb": 0, "state": 2347584, "region": 0, "localadmin": 0}, "woe:timezone_id": 56043661, "woe:hash": "9ysg2p2zz710", "woe:centroid": [-94.56897, 37.174961], "geom:latitude": 37.174961, "geom:longitude": -94.56897, "geom:hash": "9ysg2p2zz710", "woe:latitude": 37.174961, "geom:centroid": [-94.56897, 37.174961], "woe:longitude": -94.56897, "woe:repo": "woeplanet-poi-us"}, "geometry": {"coordinates": [-94.56897, 37.174961], "type": "Point"}}