{"type": "Feature", "id": 23680777, "geometry": {"type": "Point", "coordinates": [-82.824608, 30.39123]}, "properties": {"woe:id": 23680777, "woe:parent_id": 2409540, "woe:name": "Occidental Station", "woe:placetype": 20, "woe:placetype_name": "POI", "woe:lang": "ENG", "iso:country": "US", "meta:provider": ["geoplanet:7.3.1", "geoplanet:7.3.2", "geoplanet:7.4.0", "geoplanet:7.4.1", "geoplanet:7.5.1", "geoplanet:7.5.2", "geoplanet:7.6.0", "geoplanet:7.8.1", "geoplanet:7.9.0", "geoplanet:7.10.0", "geoplanet:8.0.0", "woeplanet:8.0.0"], "meta:indexed": "2020-08-20T20:19:18.649481", "meta:updated": "2020-10-14T11:19:36.718614", "woe:hierarchy": {"continent": 24865672, "country": 23424977, "town": 0, "planet": 1, "county": 12587826, "suburb": 0, "state": 2347568, "region": 0, "localadmin": 0}, "woe:timezone_id": 56043648, "woe:hash": "djmhgk8cwzbh", "woe:centroid": [-82.824608, 30.39123], "geom:latitude": 30.39123, "geom:longitude": -82.824608, "geom:hash": "djmhgk8cwzbh", "woe:latitude": 30.39123, "geom:centroid": [-82.824608, 30.39123], "woe:longitude": -82.824608, "woe:repo": "woeplanet-poi-us", "geom:area": 0.0, "woe:scale": 19}}