{"type": "Feature", "id": 23628717, "geometry": {"type": "Point", "coordinates": [-82.714371, 41.442478]}, "properties": {"woe:id": 23628717, "woe:parent_id": 56022501, "woe:name": "Osborne Elementary School", "woe:placetype": 20, "woe:placetype_name": "POI", "woe:lang": "ENG", "iso:country": "US", "meta:provider": ["geoplanet:7.3.1", "geoplanet:7.3.2", "geoplanet:7.4.0", "geoplanet:7.4.1", "geoplanet:7.5.1", "geoplanet:7.5.2", "geoplanet:7.6.0", "geoplanet:7.8.1", "geoplanet:7.9.0", "geoplanet:7.10.0", "geoplanet:8.0.0", "woeplanet:8.0.0"], "meta:indexed": "2020-08-20T20:18:53.850358", "woe:alias_ENG_V": ["Osborne Elementary"], "meta:updated": "2020-10-14T11:19:27.470674", "woe:hierarchy": {"continent": 24865672, "country": 23424977, "town": 0, "planet": 1, "county": 12589548, "suburb": 0, "state": 2347594, "region": 0, "localadmin": 0}, "woe:timezone_id": 56043648, "woe:hash": "dpm5vb35zmyd", "woe:centroid": [-82.714371, 41.442478], "geom:latitude": 41.442478, "geom:longitude": -82.714371, "geom:hash": "dpm5vb35zmyd", "woe:latitude": 41.442478, "geom:centroid": [-82.714371, 41.442478], "woe:longitude": -82.714371, "woe:repo": "woeplanet-poi-us", "geom:area": 0.0, "woe:scale": 19}}