{"type": "Feature", "id": 23658928, "geometry": {"type": "Point", "coordinates": [-95.36747, 29.82147]}, "properties": {"woe:id": 23658928, "woe:parent_id": 28751418, "woe:name": "Herrera Elementary School", "woe:placetype": 20, "woe:placetype_name": "POI", "woe:lang": "ENG", "iso:country": "US", "meta:provider": ["geoplanet:7.3.1", "geoplanet:7.3.2", "geoplanet:7.4.0", "geoplanet:7.4.1", "geoplanet:7.5.1", "geoplanet:7.5.2", "geoplanet:7.6.0", "geoplanet:7.8.1", "geoplanet:7.9.0", "geoplanet:7.10.0", "geoplanet:8.0.0", "woeplanet:8.0.0"], "meta:indexed": "2020-08-20T20:19:05.692300", "woe:alias_ENG_V": ["Herrera Elementary"], "meta:updated": "2020-10-14T11:19:39.554646", "woe:hierarchy": {"continent": 24865672, "country": 23424977, "town": 0, "planet": 1, "county": 12590107, "suburb": 0, "state": 2347602, "region": 0, "localadmin": 0}, "woe:timezone_id": 56043661, "woe:hash": "9vk1tugd8uum", "woe:centroid": [-95.36747, 29.82147], "geom:latitude": 29.82147, "geom:longitude": -95.36747, "geom:hash": "9vk1tugd8uum", "woe:latitude": 29.82147, "geom:centroid": [-95.36747, 29.82147], "woe:longitude": -95.36747, "woe:repo": "woeplanet-poi-us", "geom:area": 0.0, "woe:scale": 19}}