{"type": "Feature", "id": 23569897, "properties": {"woe:id": 23569897, "woe:parent_id": 2395196, "woe:name": "Earlham Elementary School", "woe:placetype": 20, "woe:placetype_name": "POI", "woe:lang": "ENG", "iso:country": "US", "meta:provider": ["geoplanet:7.3.1", "geoplanet:7.3.2", "geoplanet:7.4.0", "geoplanet:7.4.1", "geoplanet:7.5.1", "geoplanet:7.5.2", "geoplanet:7.6.0", "geoplanet:7.8.1", "geoplanet:7.9.0", "geoplanet:7.10.0", "geoplanet:8.0.0", "woeplanet:8.0.0"], "meta:indexed": "2020-08-20T20:18:35.288531", "woe:alias_ENG_V": ["Earlham Elementary"], "meta:updated": "2020-08-22T02:57:36.214129", "woe:hierarchy": {"continent": 24865672, "country": 23424977, "town": 0, "planet": 1, "county": 12588332, "suburb": 0, "state": 2347574, "region": 0, "localadmin": 0}, "woe:timezone_id": 56043661, "woe:hash": "9zmh44j8gx38", "woe:centroid": [-94.123154, 41.495529], "geom:latitude": 41.495529, "geom:longitude": -94.123154, "geom:hash": "9zmh44j8gx38", "woe:latitude": 41.495529, "geom:centroid": [-94.123154, 41.495529], "woe:longitude": -94.123154, "woe:repo": "woeplanet-poi-us"}, "geometry": {"coordinates": [-94.123154, 41.495529], "type": "Point"}}