{"type": "Feature", "id": 23608251, "properties": {"woe:id": 23608251, "woe:parent_id": 55806613, "woe:name": "Mt. Vernon Elementary School", "woe:placetype": 20, "woe:placetype_name": "POI", "woe:lang": "ENG", "iso:country": "US", "meta:provider": ["geoplanet:7.3.1", "geoplanet:7.3.2", "geoplanet:7.4.0", "geoplanet:7.4.1", "geoplanet:7.5.1", "geoplanet:7.5.2", "geoplanet:7.6.0", "geoplanet:7.8.1", "geoplanet:7.9.0", "geoplanet:7.10.0", "geoplanet:8.0.0", "woeplanet:8.0.0"], "meta:indexed": "2020-08-20T20:18:47.082157", "woe:alias_ENG_V": ["Mt. Vernon Elementary"], "meta:updated": "2020-08-22T02:57:42.059882", "woe:hierarchy": {"continent": 24865672, "country": 23424977, "town": 0, "planet": 1, "county": 12589264, "suburb": 0, "state": 2347589, "region": 0, "localadmin": 0}, "woe:timezone_id": 56043648, "woe:hash": "dr5py811kjd9", "woe:centroid": [-74.244057, 40.737549], "geom:latitude": 40.737549, "geom:longitude": -74.244057, "geom:hash": "dr5py811kjd9", "woe:latitude": 40.737549, "geom:centroid": [-74.244057, 40.737549], "woe:longitude": -74.244057, "woe:repo": "woeplanet-poi-us"}, "geometry": {"coordinates": [-74.244057, 40.737549], "type": "Point"}}