{"type": "Feature", "id": 23681739, "properties": {"woe:id": 23681739, "woe:parent_id": 2413140, "woe:name": "Grant Park Station", "woe:placetype": 20, "woe:placetype_name": "POI", "woe:lang": "ENG", "iso:country": "US", "meta:provider": ["geoplanet:7.3.1", "geoplanet:7.3.2", "geoplanet:7.4.0", "geoplanet:7.4.1", "geoplanet:7.5.1", "geoplanet:7.5.2", "geoplanet:7.6.0", "geoplanet:7.8.1", "geoplanet:7.9.0", "geoplanet:7.10.0", "geoplanet:8.0.0", "woeplanet:8.0.0"], "meta:indexed": "2020-08-20T20:19:19.298094", "meta:updated": "2020-08-22T02:58:22.138969", "woe:hierarchy": {"continent": 24865672, "country": 23424977, "town": 0, "planet": 1, "county": 12588123, "suburb": 0, "state": 2347572, "region": 0, "localadmin": 0}, "woe:timezone_id": 56043661, "woe:hash": "dp3dts5w2t3q", "woe:centroid": [-87.644096, 41.243778], "geom:latitude": 41.243778, "geom:longitude": -87.644096, "geom:hash": "dp3dts5w2t3q", "woe:latitude": 41.243778, "geom:centroid": [-87.644096, 41.243778], "woe:longitude": -87.644096, "woe:repo": "woeplanet-poi-us"}, "geometry": {"coordinates": [-87.644096, 41.243778], "type": "Point"}}