{"type": "Feature", "id": 23544147, "properties": {"woe:id": 23544147, "woe:parent_id": 2443929, "woe:name": "Shoreline Christian School", "woe:placetype": 20, "woe:placetype_name": "POI", "woe:lang": "ENG", "iso:country": "US", "meta:provider": ["geoplanet:7.4.0", "geoplanet:7.4.1", "geoplanet:7.5.1", "geoplanet:7.5.2", "geoplanet:7.6.0", "geoplanet:7.8.1", "geoplanet:7.9.0", "geoplanet:7.10.0", "geoplanet:8.0.0", "woeplanet:8.0.0"], "meta:indexed": "2020-08-20T23:54:50.542651", "meta:updated": "2020-08-22T02:57:31.272768", "woe:hierarchy": {"continent": 24865672, "country": 23424977, "town": 0, "planet": 1, "county": 12587795, "suburb": 0, "state": 2347565, "region": 0, "localadmin": 0}, "woe:timezone_id": 56043648, "woe:hash": "drk770j4ezmm", "woe:centroid": [-72.634567, 41.353008], "geom:latitude": 41.353008, "geom:longitude": -72.634567, "geom:hash": "drk770j4ezmm", "woe:latitude": 41.353008, "geom:centroid": [-72.634567, 41.353008], "woe:longitude": -72.634567, "woe:repo": "woeplanet-poi-us"}, "geometry": {"coordinates": [-72.634567, 41.353008], "type": "Point"}}