{"type": "Feature", "id": 23652239, "geometry": {"type": "Point", "coordinates": [-89.648201, 35.542801]}, "properties": {"woe:id": 23652239, "woe:parent_id": 2386266, "woe:name": "Crestview Middle School", "woe:placetype": 20, "woe:placetype_name": "POI", "woe:lang": "ENG", "iso:country": "US", "meta:provider": ["geoplanet:7.3.2", "geoplanet:7.4.0", "geoplanet:7.4.1", "geoplanet:7.5.1", "geoplanet:7.5.2", "geoplanet:7.6.0", "geoplanet:7.8.1", "geoplanet:7.9.0", "geoplanet:7.10.0", "geoplanet:8.0.0", "woeplanet:8.0.0"], "meta:indexed": "2020-08-20T22:02:51.658287", "meta:updated": "2020-10-14T11:19:33.892190", "woe:hierarchy": {"continent": 24865672, "country": 23424977, "town": 0, "planet": 1, "county": 12589995, "suburb": 0, "state": 2347601, "region": 0, "localadmin": 0}, "woe:timezone_id": 56043661, "woe:hash": "dn260n25vd26", "woe:centroid": [-89.648201, 35.542801], "geom:latitude": 35.542801, "geom:longitude": -89.648201, "geom:hash": "dn260n25vd26", "woe:latitude": 35.542801, "geom:centroid": [-89.648201, 35.542801], "woe:longitude": -89.648201, "woe:repo": "woeplanet-poi-us", "geom:area": 0.0, "woe:scale": 19}}