{"type": "Feature", "id": 23590703, "properties": {"woe:id": 23590703, "woe:parent_id": 2446882, "woe:name": "Mattawan Later Elementary School", "woe:placetype": 20, "woe:placetype_name": "POI", "woe:lang": "ENG", "iso:country": "US", "meta:provider": ["geoplanet:7.3.1", "geoplanet:7.3.2", "geoplanet:7.4.0", "geoplanet:7.4.1", "geoplanet:7.5.1", "geoplanet:7.5.2", "geoplanet:7.6.0", "geoplanet:7.8.1", "geoplanet:7.9.0", "geoplanet:7.10.0", "geoplanet:8.0.0", "woeplanet:8.0.0"], "meta:indexed": "2020-08-20T20:18:41.439492", "woe:alias_ENG_V": ["Mattawan Later Elementary"], "meta:updated": "2020-08-22T02:57:39.515745", "woe:hierarchy": {"continent": 24865672, "country": 23424977, "town": 0, "planet": 1, "county": 12588793, "suburb": 0, "state": 2347581, "region": 0, "localadmin": 0}, "woe:timezone_id": 56043658, "woe:hash": "dpdbpucs7ckc", "woe:centroid": [-85.790009, 42.214329], "geom:latitude": 42.214329, "geom:longitude": -85.790009, "geom:hash": "dpdbpucs7ckc", "woe:latitude": 42.214329, "geom:centroid": [-85.790009, 42.214329], "woe:longitude": -85.790009, "woe:repo": "woeplanet-poi-us"}, "geometry": {"coordinates": [-85.790009, 42.214329], "type": "Point"}}