{"type": "Feature", "id": 23652796, "properties": {"woe:id": 23652796, "woe:parent_id": 2353734, "woe:name": "Alpine Middle School", "woe:placetype": 20, "woe:placetype_name": "POI", "woe:lang": "ENG", "iso:country": "US", "meta:provider": ["geoplanet:7.3.1", "geoplanet:7.3.2", "geoplanet:7.4.0", "geoplanet:7.4.1", "geoplanet:7.5.1", "geoplanet:7.5.2", "geoplanet:7.6.0", "geoplanet:7.8.1", "geoplanet:7.9.0", "geoplanet:7.10.0", "geoplanet:8.0.0", "woeplanet:8.0.0"], "meta:indexed": "2020-08-20T20:19:02.571661", "meta:updated": "2020-08-22T02:57:48.667619", "woe:hierarchy": {"continent": 24865672, "country": 23424977, "town": 0, "planet": 1, "county": 12590028, "suburb": 0, "state": 2347602, "region": 0, "localadmin": 0}, "woe:timezone_id": 56043661, "woe:hash": "9tqk8y9f2yk8", "woe:centroid": [-103.675537, 30.358391], "geom:latitude": 30.358391, "geom:longitude": -103.675537, "geom:hash": "9tqk8y9f2yk8", "woe:latitude": 30.358391, "geom:centroid": [-103.675537, 30.358391], "woe:longitude": -103.675537, "woe:repo": "woeplanet-poi-us"}, "geometry": {"coordinates": [-103.675537, 30.358391], "type": "Point"}}