{"type": "Feature", "id": 23571211, "geometry": {"type": "Point", "coordinates": [-97.835983, 39.361832]}, "properties": {"woe:id": 23571211, "woe:parent_id": 2410605, "woe:name": "Glasco Elementary School", "woe:placetype": 20, "woe:placetype_name": "POI", "woe:lang": "ENG", "iso:country": "US", "meta:provider": ["geoplanet:7.3.1", "geoplanet:7.3.2", "geoplanet:7.4.0", "geoplanet:7.4.1", "geoplanet:7.5.1", "geoplanet:7.5.2", "geoplanet:7.6.0", "geoplanet:7.8.1", "geoplanet:7.9.0", "geoplanet:7.10.0", "geoplanet:8.0.0", "woeplanet:8.0.0"], "meta:indexed": "2020-08-20T20:18:35.837766", "woe:alias_ENG_V": ["Glasco Elementary"], "meta:updated": "2020-10-14T11:20:07.875372", "woe:hierarchy": {"continent": 24865672, "country": 23424977, "town": 0, "planet": 1, "county": 12588385, "suburb": 0, "state": 2347575, "region": 0, "localadmin": 0}, "woe:timezone_id": 56043661, "woe:hash": "9yfrvtw52379", "woe:centroid": [-97.835983, 39.361832], "geom:latitude": 39.361832, "geom:longitude": -97.835983, "geom:hash": "9yfrvtw52379", "woe:latitude": 39.361832, "geom:centroid": [-97.835983, 39.361832], "woe:longitude": -97.835983, "woe:repo": "woeplanet-poi-us", "geom:area": 0.0, "woe:scale": 19}}