{"type": "Feature", "id": 23584577, "properties": {"woe:id": 23584577, "woe:parent_id": 2491726, "woe:name": "Kendall Whaling Museum", "woe:placetype": 20, "woe:placetype_name": "POI", "woe:lang": "ENG", "iso:country": "US", "meta:provider": ["geoplanet:7.3.1", "geoplanet:7.3.2", "geoplanet:7.4.0", "geoplanet:7.4.1", "geoplanet:7.5.1", "geoplanet:7.5.2", "geoplanet:7.6.0", "geoplanet:7.8.1", "geoplanet:7.9.0", "geoplanet:7.10.0", "geoplanet:8.0.0", "woeplanet:8.0.0"], "meta:indexed": "2020-08-20T20:18:39.521528", "meta:updated": "2020-08-22T02:57:38.456400", "woe:hierarchy": {"continent": 24865672, "country": 23424977, "town": 0, "planet": 1, "county": 12588710, "suburb": 0, "state": 2347580, "region": 0, "localadmin": 0}, "woe:timezone_id": 56043648, "woe:hash": "drmrevqvq9fj", "woe:centroid": [-71.192841, 42.12936], "geom:latitude": 42.12936, "geom:longitude": -71.192841, "geom:hash": "drmrevqvq9fj", "woe:latitude": 42.12936, "geom:centroid": [-71.192841, 42.12936], "woe:longitude": -71.192841, "woe:repo": "woeplanet-poi-us"}, "geometry": {"coordinates": [-71.192841, 42.12936], "type": "Point"}}