{"type": "Feature", "id": 23548164, "properties": {"woe:id": 23548164, "woe:parent_id": 55859068, "woe:name": "Charter School of Excellence", "woe:placetype": 20, "woe:placetype_name": "POI", "woe:lang": "ENG", "iso:country": "US", "meta:provider": ["geoplanet:7.3.1", "geoplanet:7.3.2", "geoplanet:7.4.0", "geoplanet:7.4.1", "geoplanet:7.5.1", "geoplanet:7.5.2", "geoplanet:7.6.0", "geoplanet:7.8.1", "geoplanet:7.9.0", "geoplanet:7.10.0", "geoplanet:8.0.0", "woeplanet:8.0.0"], "meta:indexed": "2020-08-20T20:18:27.247411", "meta:updated": "2020-08-22T02:57:32.109504", "woe:hierarchy": {"continent": 24865672, "country": 23424977, "town": 0, "planet": 1, "county": 12587808, "suburb": 0, "state": 2347568, "region": 0, "localadmin": 0}, "woe:timezone_id": 56043648, "woe:hash": "dhxh82eu1gyw", "woe:centroid": [-80.14003, 26.10697], "geom:latitude": 26.10697, "geom:longitude": -80.14003, "geom:hash": "dhxh82eu1gyw", "woe:latitude": 26.10697, "geom:centroid": [-80.14003, 26.10697], "woe:longitude": -80.14003, "woe:repo": "woeplanet-poi-us"}, "geometry": {"coordinates": [-80.14003, 26.10697], "type": "Point"}}