{"type": "Feature", "id": 24610136, "properties": {"woe:id": 24610136, "woe:parent_id": 55858663, "woe:name": "Jay's Seafood Restaurant", "woe:placetype": 20, "woe:placetype_name": "POI", "woe:lang": "ENG", "iso:country": "US", "meta:provider": ["geoplanet:7.3.1", "geoplanet:7.3.2", "geoplanet:7.4.0", "geoplanet:7.4.1", "geoplanet:7.5.1", "geoplanet:7.5.2", "geoplanet:7.6.0", "geoplanet:7.8.1", "geoplanet:7.9.0", "geoplanet:7.10.0", "geoplanet:8.0.0", "woeplanet:8.0.0"], "meta:indexed": "2020-08-20T20:19:14.424542", "meta:updated": "2020-08-22T02:58:19.472211", "woe:hierarchy": {"continent": 24865672, "country": 23424977, "town": 0, "planet": 1, "county": 12589583, "suburb": 0, "state": 2347594, "region": 0, "localadmin": 0}, "woe:timezone_id": 56043648, "woe:hash": "dph4hnsbmqfk", "woe:centroid": [-84.192467, 39.762348], "geom:latitude": 39.762348, "geom:longitude": -84.192467, "geom:hash": "dph4hnsbmqfk", "woe:latitude": 39.762348, "geom:centroid": [-84.192467, 39.762348], "woe:longitude": -84.192467, "woe:repo": "woeplanet-poi-us"}, "geometry": {"coordinates": [-84.192467, 39.762348], "type": "Point"}}