{"type": "Feature", "id": 23598410, "geometry": {"type": "Point", "coordinates": [-94.51664, 37.067039]}, "properties": {"woe:id": 23598410, "woe:parent_id": 2429939, "woe:name": "South Middle School", "woe:placetype": 20, "woe:placetype_name": "POI", "woe:lang": "ENG", "iso:country": "US", "meta:provider": ["geoplanet:7.3.1", "geoplanet:7.3.2", "geoplanet:7.4.0", "geoplanet:7.4.1", "geoplanet:7.5.1", "geoplanet:7.5.2", "geoplanet:7.6.0", "geoplanet:7.8.1", "geoplanet:7.9.0", "geoplanet:7.10.0", "geoplanet:8.0.0", "woeplanet:8.0.0"], "meta:indexed": "2020-08-20T20:18:44.269242", "woe:alias_ENG_V": ["Joplin East Middle School", "S Middle School"], "meta:updated": "2020-10-14T11:20:14.985116", "woe:hierarchy": {"continent": 24865672, "country": 23424977, "town": 0, "planet": 1, "county": 12589014, "suburb": 0, "state": 2347584, "region": 0, "localadmin": 0}, "woe:timezone_id": 56043661, "woe:hash": "9ysfc5z54svh", "woe:centroid": [-94.51664, 37.067039], "geom:latitude": 37.067039, "geom:longitude": -94.51664, "geom:hash": "9ysfc5z54svh", "woe:latitude": 37.067039, "geom:centroid": [-94.51664, 37.067039], "woe:longitude": -94.51664, "woe:repo": "woeplanet-poi-us", "geom:area": 0.0, "woe:scale": 19}}