{"type": "Feature", "id": 23542658, "geometry": {"type": "Point", "coordinates": [-73.499733, 41.460289]}, "properties": {"woe:id": 23542658, "woe:parent_id": 2458283, "woe:name": "Meeting House Hill School", "woe:placetype": 20, "woe:placetype_name": "POI", "woe:lang": "ENG", "iso:country": "US", "meta:provider": ["geoplanet:7.3.1", "geoplanet:7.3.2", "geoplanet:7.4.0", "geoplanet:7.4.1", "geoplanet:7.5.1", "geoplanet:7.5.2", "geoplanet:7.6.0", "geoplanet:7.8.1", "geoplanet:7.9.0", "geoplanet:7.10.0", "geoplanet:8.0.0", "woeplanet:8.0.0"], "meta:indexed": "2020-08-20T20:18:24.977211", "meta:updated": "2020-10-14T11:20:23.614706", "woe:hierarchy": {"continent": 24865672, "country": 23424977, "town": 0, "planet": 1, "county": 12587791, "suburb": 0, "state": 2347565, "region": 0, "localadmin": 0}, "woe:timezone_id": 56043648, "woe:hash": "dr7ez7x5sn4c", "woe:centroid": [-73.499733, 41.460289], "geom:latitude": 41.460289, "geom:longitude": -73.499733, "geom:hash": "dr7ez7x5sn4c", "woe:latitude": 41.460289, "geom:centroid": [-73.499733, 41.460289], "woe:longitude": -73.499733, "woe:repo": "woeplanet-poi-us", "geom:area": 0.0, "woe:scale": 19}}