{"type": "Feature", "id": 23561538, "properties": {"woe:id": 23561538, "woe:parent_id": 2486743, "woe:name": "St Elmo Junior High School", "woe:placetype": 20, "woe:placetype_name": "POI", "woe:lang": "ENG", "iso:country": "US", "meta:provider": ["geoplanet:7.3.1", "geoplanet:7.3.2", "geoplanet:7.4.0", "geoplanet:7.4.1", "geoplanet:7.5.1", "geoplanet:7.5.2", "geoplanet:7.6.0", "geoplanet:7.8.1", "geoplanet:7.9.0", "geoplanet:7.10.0", "geoplanet:8.0.0", "woeplanet:8.0.0"], "meta:indexed": "2020-08-20T20:18:32.164309", "woe:alias_ENG_V": ["St Elmo Junior High"], "meta:updated": "2020-08-22T02:57:34.618497", "woe:hierarchy": {"continent": 24865672, "country": 23424977, "town": 0, "planet": 1, "county": 12588103, "suburb": 0, "state": 2347572, "region": 0, "localadmin": 0}, "woe:timezone_id": 56043661, "woe:hash": "dnby44h4wy8n", "woe:centroid": [-88.851639, 39.034889], "geom:latitude": 39.034889, "geom:longitude": -88.851639, "geom:hash": "dnby44h4wy8n", "woe:latitude": 39.034889, "geom:centroid": [-88.851639, 39.034889], "woe:longitude": -88.851639, "woe:repo": "woeplanet-poi-us"}, "geometry": {"coordinates": [-88.851639, 39.034889], "type": "Point"}}