{"type": "Feature", "id": 23673760, "properties": {"woe:id": 23673760, "woe:parent_id": 2464910, "woe:name": "Lebanon Lutheran School", "woe:placetype": 20, "woe:placetype_name": "POI", "woe:lang": "ENG", "iso:country": "US", "meta:provider": ["geoplanet:7.3.1", "geoplanet:7.3.2", "geoplanet:7.4.0", "geoplanet:7.4.1", "geoplanet:7.5.1", "geoplanet:7.5.2", "geoplanet:7.6.0", "geoplanet:7.8.1", "geoplanet:7.9.0", "geoplanet:7.10.0", "geoplanet:8.0.0", "woeplanet:8.0.0"], "meta:indexed": "2020-08-20T20:19:10.679876", "meta:updated": "2020-08-22T02:58:17.748085", "woe:hierarchy": {"continent": 24865672, "country": 23424977, "town": 0, "planet": 1, "county": 12590547, "suburb": 0, "state": 2347608, "region": 0, "localadmin": 0}, "woe:timezone_id": 56043661, "woe:hash": "dp8vz4khvxyp", "woe:centroid": [-88.631958, 43.21146], "geom:latitude": 43.21146, "geom:longitude": -88.631958, "geom:hash": "dp8vz4khvxyp", "woe:latitude": 43.21146, "geom:centroid": [-88.631958, 43.21146], "woe:longitude": -88.631958, "woe:repo": "woeplanet-poi-us"}, "geometry": {"coordinates": [-88.631958, 43.21146], "type": "Point"}}