{"type": "Feature", "id": 23546254, "geometry": {"type": "Point", "coordinates": [-81.604851, 30.177111]}, "properties": {"woe:id": 23546254, "woe:parent_id": 2444713, "woe:name": "Jacksonville Junior Academy", "woe:placetype": 20, "woe:placetype_name": "POI", "woe:lang": "ENG", "iso:country": "US", "meta:provider": ["geoplanet:7.3.1", "geoplanet:7.3.2", "geoplanet:7.4.0", "geoplanet:7.4.1", "geoplanet:7.5.1", "geoplanet:7.5.2", "geoplanet:7.6.0", "geoplanet:7.8.1", "geoplanet:7.9.0", "geoplanet:7.10.0", "geoplanet:8.0.0", "woeplanet:8.0.0"], "meta:indexed": "2020-08-20T20:18:26.370474", "meta:updated": "2020-10-14T11:20:05.005353", "woe:hierarchy": {"continent": 24865672, "country": 23424977, "town": 0, "planet": 1, "county": 12587818, "suburb": 0, "state": 2347568, "region": 0, "localadmin": 0}, "woe:timezone_id": 56043648, "woe:hash": "djmgxj94mjhy", "woe:centroid": [-81.604851, 30.177111], "geom:latitude": 30.177111, "geom:longitude": -81.604851, "geom:hash": "djmgxj94mjhy", "woe:latitude": 30.177111, "geom:centroid": [-81.604851, 30.177111], "woe:longitude": -81.604851, "woe:repo": "woeplanet-poi-us", "geom:area": 0.0, "woe:scale": 19}}