{"type": "Feature", "id": 23593626, "properties": {"woe:id": 23593626, "woe:parent_id": 55806407, "woe:name": "Pease Academy", "woe:placetype": 20, "woe:placetype_name": "POI", "woe:lang": "ENG", "iso:country": "US", "meta:provider": ["geoplanet:7.3.1", "geoplanet:7.3.2", "geoplanet:7.4.0", "geoplanet:7.4.1", "geoplanet:7.5.1", "geoplanet:7.5.2", "geoplanet:7.6.0", "geoplanet:7.8.1", "geoplanet:7.9.0", "geoplanet:7.10.0", "geoplanet:8.0.0", "woeplanet:8.0.0"], "meta:indexed": "2020-08-20T20:18:42.552974", "meta:updated": "2020-08-22T02:57:40.014127", "woe:hierarchy": {"continent": 24865672, "country": 23424977, "town": 0, "planet": 1, "county": 12588823, "suburb": 0, "state": 2347582, "region": 0, "localadmin": 0}, "woe:timezone_id": 56043661, "woe:hash": "9zvxykgusz98", "woe:centroid": [-93.235611, 44.98296], "geom:latitude": 44.98296, "geom:longitude": -93.235611, "geom:hash": "9zvxykgusz98", "woe:latitude": 44.98296, "geom:centroid": [-93.235611, 44.98296], "woe:longitude": -93.235611, "woe:repo": "woeplanet-poi-us"}, "geometry": {"coordinates": [-93.235611, 44.98296], "type": "Point"}}