{"type": "Feature", "id": 23673277, "properties": {"woe:id": 23673277, "woe:parent_id": 2418087, "woe:name": "Horizons Elementary School", "woe:placetype": 20, "woe:placetype_name": "POI", "woe:lang": "ENG", "iso:country": "US", "meta:provider": ["geoplanet:7.3.1", "geoplanet:7.3.2", "geoplanet:7.4.0", "geoplanet:7.4.1", "geoplanet:7.5.1", "geoplanet:7.5.2", "geoplanet:7.6.0", "geoplanet:7.8.1", "geoplanet:7.9.0", "geoplanet:7.10.0", "geoplanet:8.0.0", "woeplanet:8.0.0"], "meta:indexed": "2020-08-20T20:19:10.432755", "woe:alias_ENG_V": ["Horizons Elementary"], "meta:updated": "2020-08-22T02:58:17.628300", "woe:hierarchy": {"continent": 24865672, "country": 23424977, "town": 0, "planet": 1, "county": 12590541, "suburb": 0, "state": 2347608, "region": 0, "localadmin": 0}, "woe:timezone_id": 56043661, "woe:hash": "dpc5tj1r3w5q", "woe:centroid": [-88.372238, 44.237728], "geom:latitude": 44.237728, "geom:longitude": -88.372238, "geom:hash": "dpc5tj1r3w5q", "woe:latitude": 44.237728, "geom:centroid": [-88.372238, 44.237728], "woe:longitude": -88.372238, "woe:repo": "woeplanet-poi-us"}, "geometry": {"coordinates": [-88.372238, 44.237728], "type": "Point"}}