{"type": "Feature", "id": 23586471, "geometry": {"type": "Point", "coordinates": [-85.143806, 42.06041]}, "properties": {"woe:id": 23586471, "woe:parent_id": 2509764, "woe:name": "Union City Middle School", "woe:placetype": 20, "woe:placetype_name": "POI", "woe:lang": "ENG", "iso:country": "US", "meta:provider": ["geoplanet:7.3.1", "geoplanet:7.3.2", "geoplanet:7.4.0", "geoplanet:7.4.1", "geoplanet:7.5.1", "geoplanet:7.5.2", "geoplanet:7.6.0", "geoplanet:7.8.1", "geoplanet:7.9.0", "geoplanet:7.10.0", "geoplanet:8.0.0", "woeplanet:8.0.0"], "meta:indexed": "2020-08-20T20:18:39.990578", "meta:updated": "2020-10-14T11:20:23.911697", "woe:hierarchy": {"continent": 24865672, "country": 23424977, "town": 0, "planet": 1, "county": 12588725, "suburb": 0, "state": 2347581, "region": 0, "localadmin": 0}, "woe:timezone_id": 56043658, "woe:hash": "dp7rq8b5ts8w", "woe:centroid": [-85.143806, 42.06041], "geom:latitude": 42.06041, "geom:longitude": -85.143806, "geom:hash": "dp7rq8b5ts8w", "woe:latitude": 42.06041, "geom:centroid": [-85.143806, 42.06041], "woe:longitude": -85.143806, "woe:repo": "woeplanet-poi-us", "geom:area": 0.0, "woe:scale": 19}}