{"type": "Feature", "id": 23638861, "properties": {"woe:id": 23638861, "woe:parent_id": 28744490, "woe:name": "Our Lady of Fatima Elementary School", "woe:placetype": 20, "woe:placetype_name": "POI", "woe:lang": "ENG", "iso:country": "US", "meta:provider": ["geoplanet:7.3.1", "geoplanet:7.3.2", "geoplanet:7.4.0", "geoplanet:7.4.1", "geoplanet:7.5.1", "geoplanet:7.5.2", "geoplanet:7.6.0", "geoplanet:7.8.1", "geoplanet:7.9.0", "geoplanet:7.10.0", "geoplanet:8.0.0", "woeplanet:8.0.0"], "meta:indexed": "2020-08-20T20:18:57.995412", "woe:alias_ENG_V": ["Our Lady of Fatima Elementary"], "meta:updated": "2020-08-22T02:57:46.463829", "woe:hierarchy": {"continent": 24865672, "country": 23424977, "town": 0, "planet": 1, "county": 12589731, "suburb": 0, "state": 2347597, "region": 0, "localadmin": 0}, "woe:timezone_id": 56043648, "woe:hash": "dpnyvsm4gexh", "woe:centroid": [-80.259087, 40.585361], "geom:latitude": 40.585361, "geom:longitude": -80.259087, "geom:hash": "dpnyvsm4gexh", "woe:latitude": 40.585361, "geom:centroid": [-80.259087, 40.585361], "woe:longitude": -80.259087, "woe:repo": "woeplanet-poi-us"}, "geometry": {"coordinates": [-80.259087, 40.585361], "type": "Point"}}