{"type": "Feature", "id": 23553353, "properties": {"woe:id": 23553353, "woe:parent_id": 2418389, "woe:name": "Hartwell Elementary School", "woe:placetype": 20, "woe:placetype_name": "POI", "woe:lang": "ENG", "iso:country": "US", "meta:provider": ["geoplanet:7.3.1", "geoplanet:7.3.2", "geoplanet:7.4.0", "geoplanet:7.4.1", "geoplanet:7.5.1", "geoplanet:7.5.2", "geoplanet:7.6.0", "geoplanet:7.8.1", "geoplanet:7.9.0", "geoplanet:7.10.0", "geoplanet:8.0.0", "woeplanet:8.0.0"], "meta:indexed": "2020-08-20T20:18:29.595691", "woe:alias_ENG_V": ["Hartwell Elementary"], "meta:updated": "2020-08-22T02:57:33.232055", "woe:hierarchy": {"continent": 24865672, "country": 23424977, "town": 0, "planet": 1, "county": 12587942, "suburb": 0, "state": 2347569, "region": 0, "localadmin": 0}, "woe:timezone_id": 56043648, "woe:hash": "dnj52vv2rknv", "woe:centroid": [-82.928261, 34.35294], "geom:latitude": 34.35294, "geom:longitude": -82.928261, "geom:hash": "dnj52vv2rknv", "woe:latitude": 34.35294, "geom:centroid": [-82.928261, 34.35294], "woe:longitude": -82.928261, "woe:repo": "woeplanet-poi-us"}, "geometry": {"coordinates": [-82.928261, 34.35294], "type": "Point"}}