{"type": "Feature", "id": 23681606, "properties": {"woe:id": 23681606, "woe:parent_id": 2426311, "woe:name": "59th Street/University of Chicago Station", "woe:placetype": 20, "woe:placetype_name": "POI", "woe:lang": "ENG", "iso:country": "US", "meta:provider": ["geoplanet:7.3.1", "geoplanet:7.3.2", "geoplanet:7.4.0", "geoplanet:7.4.1", "geoplanet:7.5.1", "geoplanet:7.5.2", "geoplanet:7.6.0", "geoplanet:7.8.1", "geoplanet:7.9.0", "geoplanet:7.10.0", "geoplanet:8.0.0", "woeplanet:8.0.0"], "meta:indexed": "2020-08-20T20:19:19.244150", "woe:alias_ENG_V": ["59th Street/University of Chicago Metra Station", "Metra 59th Street/University of Chicago Station", "Metra-59th St Station"], "meta:updated": "2020-08-22T02:58:22.104415", "woe:hierarchy": {"continent": 24865672, "country": 23424977, "town": 0, "planet": 1, "county": 12588093, "suburb": 0, "state": 2347572, "region": 0, "localadmin": 0}, "woe:timezone_id": 56043661, "woe:hash": "dp3twz7b113v", "woe:centroid": [-87.588799, 41.78788], "geom:latitude": 41.78788, "geom:longitude": -87.588799, "geom:hash": "dp3twz7b113v", "woe:latitude": 41.78788, "geom:centroid": [-87.588799, 41.78788], "woe:longitude": -87.588799, "woe:repo": "woeplanet-poi-us"}, "geometry": {"coordinates": [-87.588799, 41.78788], "type": "Point"}}