{"type": "Feature", "id": 23617310, "properties": {"woe:id": 23617310, "woe:parent_id": 2514888, "woe:name": "Is 90 Mirabel Sisters School", "woe:placetype": 20, "woe:placetype_name": "POI", "woe:lang": "ENG", "iso:country": "US", "meta:provider": ["geoplanet:7.3.1", "geoplanet:7.3.2", "geoplanet:7.4.0", "geoplanet:7.4.1", "geoplanet:7.5.1", "geoplanet:7.5.2", "geoplanet:7.6.0", "geoplanet:7.8.1", "geoplanet:7.9.0", "geoplanet:7.10.0", "geoplanet:8.0.0", "woeplanet:8.0.0"], "meta:indexed": "2020-08-20T20:18:50.303182", "meta:updated": "2020-08-22T02:57:43.287517", "woe:hierarchy": {"continent": 24865672, "country": 23424977, "town": 0, "planet": 1, "county": 12589342, "suburb": 0, "state": 2347591, "region": 0, "localadmin": 0}, "woe:timezone_id": 56043648, "woe:hash": "dr72md97hkyp", "woe:centroid": [-73.936081, 40.83947], "geom:latitude": 40.83947, "geom:longitude": -73.936081, "geom:hash": "dr72md97hkyp", "woe:latitude": 40.83947, "geom:centroid": [-73.936081, 40.83947], "woe:longitude": -73.936081, "woe:repo": "woeplanet-poi-us"}, "geometry": {"coordinates": [-73.936081, 40.83947], "type": "Point"}}