{"type": "Feature", "id": 23683695, "geometry": {"type": "Point", "coordinates": [-87.627991, 41.885971]}, "properties": {"woe:id": 23683695, "woe:parent_id": 55986200, "woe:name": "State-lake Station", "woe:placetype": 20, "woe:placetype_name": "POI", "woe:lang": "ENG", "iso:country": "US", "meta:provider": ["geoplanet:7.3.1", "geoplanet:7.3.2", "geoplanet:7.4.0", "geoplanet:7.4.1", "geoplanet:7.5.1", "geoplanet:7.5.2", "geoplanet:7.6.0", "geoplanet:7.8.1", "geoplanet:7.9.0", "geoplanet:7.10.0", "geoplanet:8.0.0", "woeplanet:8.0.0"], "meta:indexed": "2020-08-20T20:19:20.460426", "woe:alias_ENG_V": ["State-lake CTA Station", "CTA State-lake Station", "Cta-Green Line-State & Lake"], "meta:updated": "2020-10-14T11:19:53.254570", "woe:hierarchy": {"continent": 24865672, "country": 23424977, "town": 0, "planet": 1, "county": 12588093, "suburb": 0, "state": 2347572, "region": 0, "localadmin": 0}, "woe:timezone_id": 56043661, "woe:hash": "dp3wmcp5ryfj", "woe:centroid": [-87.627991, 41.885971], "geom:latitude": 41.885971, "geom:longitude": -87.627991, "geom:hash": "dp3wmcp5ryfj", "woe:latitude": 41.885971, "geom:centroid": [-87.627991, 41.885971], "woe:longitude": -87.627991, "woe:repo": "woeplanet-poi-us", "geom:area": 0.0, "woe:scale": 19}}