{"type": "Feature", "id": 23606433, "properties": {"woe:id": 23606433, "woe:parent_id": 2424061, "woe:name": "Hooksett Village School", "woe:placetype": 20, "woe:placetype_name": "POI", "woe:lang": "ENG", "iso:country": "US", "meta:provider": ["geoplanet:7.3.1", "geoplanet:7.3.2", "geoplanet:7.4.0", "geoplanet:7.4.1", "geoplanet:7.5.1", "geoplanet:7.5.2", "geoplanet:7.6.0", "geoplanet:7.8.1", "geoplanet:7.9.0", "geoplanet:7.10.0", "geoplanet:8.0.0", "woeplanet:8.0.0"], "meta:indexed": "2020-08-20T20:18:46.438291", "meta:updated": "2020-08-22T02:57:41.782963", "woe:hierarchy": {"continent": 24865672, "country": 23424977, "town": 0, "planet": 1, "county": 12589254, "suburb": 0, "state": 2347588, "region": 0, "localadmin": 0}, "woe:timezone_id": 56043648, "woe:hash": "drtjjudspmnb", "woe:centroid": [-71.462311, 43.091839], "geom:latitude": 43.091839, "geom:longitude": -71.462311, "geom:hash": "drtjjudspmnb", "woe:latitude": 43.091839, "geom:centroid": [-71.462311, 43.091839], "woe:longitude": -71.462311, "woe:repo": "woeplanet-poi-us"}, "geometry": {"coordinates": [-71.462311, 43.091839], "type": "Point"}}