{"type": "Feature", "id": 23569694, "properties": {"woe:id": 23569694, "woe:parent_id": 56021438, "woe:name": "Regina Junior and Senior High School", "woe:placetype": 20, "woe:placetype_name": "POI", "woe:lang": "ENG", "iso:country": "US", "meta:provider": ["geoplanet:7.3.1", "geoplanet:7.3.2", "geoplanet:7.4.0", "geoplanet:7.4.1", "geoplanet:7.5.1", "geoplanet:7.5.2", "geoplanet:7.6.0", "geoplanet:7.8.1", "geoplanet:7.9.0", "geoplanet:7.10.0", "geoplanet:8.0.0", "woeplanet:8.0.0"], "meta:indexed": "2020-08-20T20:18:35.220298", "woe:alias_ENG_V": ["Regina Junior and Senior High", "Regina Junior and High School", "Regina Junior and High", "Regina Junior and Senior HS", "Regina Junior and HS", "Regina Junior & Senior High", "Regina Junior & Senior Senior High", "Regina Junior & Senior Senior HS", "Regina Junior & Senior HS", "Regina Junior & Senior Senior High School", "Regina Junior & Senior High School"], "meta:updated": "2020-08-22T02:58:47.348413", "woe:hierarchy": {"continent": 24865672, "country": 23424977, "town": 0, "planet": 1, "county": 12588323, "suburb": 0, "state": 2347574, "region": 0, "localadmin": 0}, "woe:timezone_id": 56043661, "woe:hash": "9zqvjbb5ttbx", "woe:centroid": [-91.50489, 41.664909], "geom:latitude": 41.664909, "geom:longitude": -91.50489, "geom:hash": "9zqvjbb5ttbx", "woe:latitude": 41.664909, "geom:centroid": [-91.50489, 41.664909], "woe:longitude": -91.50489, "woe:repo": "woeplanet-poi-us"}, "geometry": {"coordinates": [-91.50489, 41.664909], "type": "Point"}}