{"type": "Feature", "id": 23539032, "geometry": {"type": "Point", "coordinates": [-104.986389, 39.64957]}, "properties": {"woe:id": 23539032, "woe:parent_id": 12587730, "woe:name": "Mary L Flood Middle School", "woe:placetype": 20, "woe:placetype_name": "POI", "woe:lang": "ENG", "iso:country": "US", "meta:provider": ["geoplanet:7.3.2", "geoplanet:7.4.0", "geoplanet:7.4.1", "geoplanet:7.5.1", "geoplanet:7.5.2", "geoplanet:7.6.0", "geoplanet:7.8.1", "geoplanet:7.9.0", "geoplanet:7.10.0", "geoplanet:8.0.0", "woeplanet:8.0.0"], "meta:indexed": "2020-08-20T22:02:05.688278", "meta:updated": "2020-10-14T11:20:23.700544", "woe:hierarchy": {"continent": 24865672, "country": 23424977, "town": 0, "planet": 1, "county": 12587730, "suburb": 0, "state": 2347564, "region": 0, "localadmin": 0}, "woe:timezone_id": 56043665, "woe:hash": "9xj3dczprzd3", "woe:centroid": [-104.986389, 39.64957], "geom:latitude": 39.64957, "geom:longitude": -104.986389, "geom:hash": "9xj3dczprzd3", "woe:latitude": 39.64957, "geom:centroid": [-104.986389, 39.64957], "woe:longitude": -104.986389, "woe:repo": "woeplanet-poi-us", "geom:area": 0.0, "woe:scale": 19}}