{"type": "Feature", "id": 23559226, "properties": {"woe:id": 23559226, "woe:parent_id": 2455401, "woe:name": "Lions Park Elementary School", "woe:placetype": 20, "woe:placetype_name": "POI", "woe:lang": "ENG", "iso:country": "US", "meta:provider": ["geoplanet:7.3.1", "geoplanet:7.3.2", "geoplanet:7.4.0", "geoplanet:7.4.1", "geoplanet:7.5.1", "geoplanet:7.5.2", "geoplanet:7.6.0", "geoplanet:7.8.1", "geoplanet:7.9.0", "geoplanet:7.10.0", "geoplanet:8.0.0", "woeplanet:8.0.0"], "meta:indexed": "2020-08-20T20:18:31.338939", "woe:alias_ENG_V": ["Lions Park Elementary"], "meta:updated": "2020-08-22T02:57:34.170757", "woe:hierarchy": {"continent": 24865672, "country": 23424977, "town": 0, "planet": 1, "county": 12588093, "suburb": 0, "state": 2347572, "region": 0, "localadmin": 0}, "woe:timezone_id": 56043661, "woe:hash": "dp3rppcwbjv7", "woe:centroid": [-87.932503, 42.055481], "geom:latitude": 42.055481, "geom:longitude": -87.932503, "geom:hash": "dp3rppcwbjv7", "woe:latitude": 42.055481, "geom:centroid": [-87.932503, 42.055481], "woe:longitude": -87.932503, "woe:repo": "woeplanet-poi-us"}, "geometry": {"coordinates": [-87.932503, 42.055481], "type": "Point"}}