{"type": "Feature", "id": 23564269, "properties": {"woe:id": 23564269, "woe:parent_id": 2498306, "woe:name": "Iles Elementary School", "woe:placetype": 20, "woe:placetype_name": "POI", "woe:lang": "ENG", "iso:country": "US", "meta:provider": ["geoplanet:7.3.1", "geoplanet:7.3.2", "geoplanet:7.4.0", "geoplanet:7.4.1", "geoplanet:7.5.1", "geoplanet:7.5.2", "geoplanet:7.6.0", "geoplanet:7.8.1", "geoplanet:7.9.0", "geoplanet:7.10.0", "geoplanet:8.0.0", "woeplanet:8.0.0"], "meta:indexed": "2020-08-20T20:18:33.149582", "woe:alias_ENG_V": ["Iles Elementary"], "meta:updated": "2020-08-22T02:57:35.173880", "woe:hierarchy": {"continent": 24865672, "country": 23424977, "town": 0, "planet": 1, "county": 12588160, "suburb": 0, "state": 2347572, "region": 0, "localadmin": 0}, "woe:timezone_id": 56043661, "woe:hash": "dp06263wy43k", "woe:centroid": [-89.635132, 39.784039], "geom:latitude": 39.784039, "geom:longitude": -89.635132, "geom:hash": "dp06263wy43k", "woe:latitude": 39.784039, "geom:centroid": [-89.635132, 39.784039], "woe:longitude": -89.635132, "woe:repo": "woeplanet-poi-us"}, "geometry": {"coordinates": [-89.635132, 39.784039], "type": "Point"}}