{"type": "Feature", "id": 23580428, "geometry": {"type": "Point", "coordinates": [-76.43911, 39.529091]}, "properties": {"woe:id": 23580428, "woe:parent_id": 2378282, "woe:name": "Youths Benefit Elementary School", "woe:placetype": 20, "woe:placetype_name": "POI", "woe:lang": "ENG", "iso:country": "US", "meta:provider": ["geoplanet:7.3.2", "geoplanet:7.4.0", "geoplanet:7.4.1", "geoplanet:7.5.1", "geoplanet:7.5.2", "geoplanet:7.6.0", "geoplanet:7.8.1", "geoplanet:7.9.0", "geoplanet:7.10.0", "geoplanet:8.0.0", "woeplanet:8.0.0"], "meta:indexed": "2020-08-20T22:02:22.913680", "woe:alias_ENG_V": ["Youths Benefit Elementary"], "meta:updated": "2020-10-14T11:20:05.261393", "woe:hierarchy": {"continent": 24865672, "country": 23424977, "town": 0, "planet": 1, "county": 12588688, "suburb": 0, "state": 2347579, "region": 0, "localadmin": 0}, "woe:timezone_id": 56043648, "woe:hash": "dr18us49xssk", "woe:centroid": [-76.43911, 39.529091], "geom:latitude": 39.529091, "geom:longitude": -76.43911, "geom:hash": "dr18us49xssk", "woe:latitude": 39.529091, "geom:centroid": [-76.43911, 39.529091], "woe:longitude": -76.43911, "woe:repo": "woeplanet-poi-us", "geom:area": 0.0, "woe:scale": 19}}