{"type": "Feature", "id": 23656890, "properties": {"woe:id": 23656890, "woe:parent_id": 2508932, "woe:name": "Jim Ned Middle School", "woe:placetype": 20, "woe:placetype_name": "POI", "woe:lang": "ENG", "iso:country": "US", "meta:provider": ["geoplanet:7.3.1", "geoplanet:7.3.2", "geoplanet:7.4.0", "geoplanet:7.4.1", "geoplanet:7.5.1", "geoplanet:7.5.2", "geoplanet:7.6.0", "geoplanet:7.8.1", "geoplanet:7.9.0", "geoplanet:7.10.0", "geoplanet:8.0.0", "woeplanet:8.0.0"], "meta:indexed": "2020-08-20T20:19:04.598525", "meta:updated": "2020-08-22T02:57:49.685666", "woe:hierarchy": {"continent": 24865672, "country": 23424977, "town": 0, "planet": 1, "county": 12590227, "suburb": 0, "state": 2347602, "region": 0, "localadmin": 0}, "woe:timezone_id": 56043661, "woe:hash": "9v9p301t577z", "woe:centroid": [-99.7976, 32.212791], "geom:latitude": 32.212791, "geom:longitude": -99.7976, "geom:hash": "9v9p301t577z", "woe:latitude": 32.212791, "geom:centroid": [-99.7976, 32.212791], "woe:longitude": -99.7976, "woe:repo": "woeplanet-poi-us"}, "geometry": {"coordinates": [-99.7976, 32.212791], "type": "Point"}}