{"type": "Feature", "id": 23629405, "properties": {"woe:id": 23629405, "woe:parent_id": 2435008, "woe:name": "Kenston High School", "woe:placetype": 20, "woe:placetype_name": "POI", "woe:lang": "ENG", "iso:country": "US", "meta:provider": ["geoplanet:7.3.1", "geoplanet:7.3.2", "geoplanet:7.4.0", "geoplanet:7.4.1", "geoplanet:7.5.1", "geoplanet:7.5.2", "geoplanet:7.6.0", "geoplanet:7.8.1", "geoplanet:7.9.0", "geoplanet:7.10.0", "geoplanet:8.0.0", "woeplanet:8.0.0"], "meta:indexed": "2020-08-20T20:18:54.222085", "woe:alias_ENG_V": ["Kenston Senior High School", "Kenston High", "Kenston Senior High", "Kenston HS", "Kenston Senior HS"], "meta:updated": "2020-08-22T02:58:49.145454", "woe:hierarchy": {"continent": 24865672, "country": 23424977, "town": 0, "planet": 1, "county": 12589554, "suburb": 0, "state": 2347594, "region": 0, "localadmin": 0}, "woe:timezone_id": 56043648, "woe:hash": "dpq5mzc26wvs", "woe:centroid": [-81.307983, 41.395191], "geom:latitude": 41.395191, "geom:longitude": -81.307983, "geom:hash": "dpq5mzc26wvs", "woe:latitude": 41.395191, "geom:centroid": [-81.307983, 41.395191], "woe:longitude": -81.307983, "woe:repo": "woeplanet-poi-us"}, "geometry": {"coordinates": [-81.307983, 41.395191], "type": "Point"}}