{"type": "Feature", "id": 23677428, "properties": {"woe:id": 23677428, "woe:parent_id": 2518882, "woe:name": "Wheatland Junior High School", "woe:placetype": 20, "woe:placetype_name": "POI", "woe:lang": "ENG", "iso:country": "US", "meta:provider": ["geoplanet:7.3.1", "geoplanet:7.3.2", "geoplanet:7.4.0", "geoplanet:7.4.1", "geoplanet:7.5.1", "geoplanet:7.5.2", "geoplanet:7.6.0", "geoplanet:7.8.1", "geoplanet:7.9.0", "geoplanet:7.10.0", "geoplanet:8.0.0", "woeplanet:8.0.0"], "meta:indexed": "2020-08-20T20:19:12.226658", "woe:alias_ENG_V": ["Wheatland Junior High"], "meta:updated": "2020-08-22T02:58:18.487116", "woe:hierarchy": {"continent": 24865672, "country": 23424977, "town": 0, "planet": 1, "county": 12590621, "suburb": 0, "state": 2347609, "region": 0, "localadmin": 0}, "woe:timezone_id": 56043665, "woe:hash": "9xmr78k83rtd", "woe:centroid": [-104.957138, 42.057121], "geom:latitude": 42.057121, "geom:longitude": -104.957138, "geom:hash": "9xmr78k83rtd", "woe:latitude": 42.057121, "geom:centroid": [-104.957138, 42.057121], "woe:longitude": -104.957138, "woe:repo": "woeplanet-poi-us"}, "geometry": {"coordinates": [-104.957138, 42.057121], "type": "Point"}}