{"type": "Feature", "id": 23661217, "properties": {"woe:id": 23661217, "woe:parent_id": 2390706, "woe:name": "East Side Elementary School", "woe:placetype": 20, "woe:placetype_name": "POI", "woe:lang": "ENG", "iso:country": "US", "meta:provider": ["geoplanet:7.3.1", "geoplanet:7.3.2", "geoplanet:7.4.0", "geoplanet:7.4.1", "geoplanet:7.5.1", "geoplanet:7.5.2", "geoplanet:7.6.0", "geoplanet:7.8.1", "geoplanet:7.9.0", "geoplanet:7.10.0", "geoplanet:8.0.0", "woeplanet:8.0.0"], "meta:indexed": "2020-08-20T20:19:06.848106", "woe:alias_ENG_V": ["E Side Elementary School", "E Side Elementary", "East Side Elementary"], "meta:updated": "2020-08-22T02:57:50.682711", "woe:hierarchy": {"continent": 24865672, "country": 23424977, "town": 0, "planet": 1, "county": 12590239, "suburb": 0, "state": 2347602, "region": 0, "localadmin": 0}, "woe:timezone_id": 56043661, "woe:hash": "9v0r052zwgvv", "woe:centroid": [-100.89711, 29.37463], "geom:latitude": 29.37463, "geom:longitude": -100.89711, "geom:hash": "9v0r052zwgvv", "woe:latitude": 29.37463, "geom:centroid": [-100.89711, 29.37463], "woe:longitude": -100.89711, "woe:repo": "woeplanet-poi-us"}, "geometry": {"coordinates": [-100.89711, 29.37463], "type": "Point"}}