{"type": "Feature", "id": 23668398, "geometry": {"type": "Point", "coordinates": [-117.97673, 46.317421]}, "properties": {"woe:id": 23668398, "woe:parent_id": 2389879, "woe:name": "Dayton Elementary School", "woe:placetype": 20, "woe:placetype_name": "POI", "woe:lang": "ENG", "iso:country": "US", "meta:provider": ["geoplanet:7.3.1", "geoplanet:7.3.2", "geoplanet:7.4.0", "geoplanet:7.4.1", "geoplanet:7.5.1", "geoplanet:7.5.2", "geoplanet:7.6.0", "geoplanet:7.8.1", "geoplanet:7.9.0", "geoplanet:7.10.0", "geoplanet:8.0.0", "woeplanet:8.0.0"], "meta:indexed": "2020-08-20T20:19:09.112484", "woe:alias_ENG_V": ["Dayton Elementary"], "meta:updated": "2020-10-14T11:19:33.269240", "woe:hierarchy": {"continent": 24865672, "country": 23424977, "town": 0, "planet": 1, "county": 12590446, "suburb": 0, "state": 2347606, "region": 0, "localadmin": 0}, "woe:timezone_id": 56043663, "woe:hash": "c2hp7rgfwcn4", "woe:centroid": [-117.97673, 46.317421], "geom:latitude": 46.317421, "geom:longitude": -117.97673, "geom:hash": "c2hp7rgfwcn4", "woe:latitude": 46.317421, "geom:centroid": [-117.97673, 46.317421], "woe:longitude": -117.97673, "woe:repo": "woeplanet-poi-us", "geom:area": 0.0, "woe:scale": 19}}