{"type": "Feature", "id": 23584240, "geometry": {"type": "Point", "coordinates": [-71.174568, 42.363461]}, "properties": {"woe:id": 23584240, "woe:parent_id": 2396313, "woe:name": "Perkins School For the Blind", "woe:placetype": 20, "woe:placetype_name": "POI", "woe:lang": "ENG", "iso:country": "US", "meta:provider": ["geoplanet:7.3.1", "geoplanet:7.3.2", "geoplanet:7.4.0", "geoplanet:7.4.1", "geoplanet:7.5.1", "geoplanet:7.5.2", "geoplanet:7.6.0", "geoplanet:7.8.1", "geoplanet:7.9.0", "geoplanet:7.10.0", "geoplanet:8.0.0", "woeplanet:8.0.0"], "meta:indexed": "2020-08-20T20:18:39.454544", "meta:updated": "2020-10-14T11:20:17.903444", "woe:hierarchy": {"continent": 24865672, "country": 23424977, "town": 0, "planet": 1, "county": 12588708, "suburb": 0, "state": 2347580, "region": 0, "localadmin": 0}, "woe:timezone_id": 56043648, "woe:hash": "drt3h2h303e8", "woe:centroid": [-71.174568, 42.363461], "geom:latitude": 42.363461, "geom:longitude": -71.174568, "geom:hash": "drt3h2h303e8", "woe:latitude": 42.363461, "geom:centroid": [-71.174568, 42.363461], "woe:longitude": -71.174568, "woe:repo": "woeplanet-poi-us", "geom:area": 0.0, "woe:scale": 19}}