{"type": "Feature", "id": 23520347, "geometry": {"type": "Point", "coordinates": [-121.811012, 39.750671]}, "properties": {"woe:id": 23520347, "woe:parent_id": 26344213, "woe:name": "Sierra View Elementary School", "woe:placetype": 20, "woe:placetype_name": "POI", "woe:lang": "ENG", "iso:country": "US", "meta:provider": ["geoplanet:7.3.2", "geoplanet:7.4.0", "geoplanet:7.4.1", "geoplanet:7.5.1", "geoplanet:7.5.2", "geoplanet:7.6.0", "geoplanet:7.8.1", "geoplanet:7.9.0", "geoplanet:7.10.0", "geoplanet:8.0.0", "woeplanet:8.0.0"], "meta:indexed": "2020-08-20T22:01:58.188548", "woe:alias_ENG_V": ["Sierra View Elementary"], "meta:updated": "2020-10-14T11:20:20.778630", "woe:hierarchy": {"continent": 24865672, "country": 23424977, "town": 0, "planet": 1, "county": 12587673, "suburb": 0, "state": 2347563, "region": 0, "localadmin": 0}, "woe:timezone_id": 56043663, "woe:hash": "9r16hh7umwnh", "woe:centroid": [-121.811012, 39.750671], "geom:latitude": 39.750671, "geom:longitude": -121.811012, "geom:hash": "9r16hh7umwnh", "woe:latitude": 39.750671, "geom:centroid": [-121.811012, 39.750671], "woe:longitude": -121.811012, "woe:repo": "woeplanet-poi-us", "geom:area": 0.0, "woe:scale": 19}}