{"type": "Feature", "id": 23580791, "properties": {"woe:id": 23580791, "woe:parent_id": 2411210, "woe:name": "Wheaton High School", "woe:placetype": 20, "woe:placetype_name": "POI", "woe:lang": "ENG", "iso:country": "US", "meta:provider": ["geoplanet:7.3.2", "geoplanet:7.4.0", "geoplanet:7.4.1", "geoplanet:7.5.1", "geoplanet:7.5.2", "geoplanet:7.6.0", "geoplanet:7.8.1", "geoplanet:7.9.0", "geoplanet:7.10.0", "geoplanet:8.0.0", "woeplanet:8.0.0"], "meta:indexed": "2020-08-20T22:02:23.087584", "woe:alias_ENG_V": ["Wheaton Senior High School", "Wheaton High", "Wheaton Senior High", "Wheaton HS", "Wheaton Senior HS"], "meta:updated": "2020-08-22T02:58:47.746496", "woe:hierarchy": {"continent": 24865672, "country": 23424977, "town": 0, "planet": 1, "county": 12588691, "suburb": 0, "state": 2347579, "region": 0, "localadmin": 0}, "woe:timezone_id": 56043648, "woe:hash": "dqcnnr19v9tv", "woe:centroid": [-77.066788, 39.062199], "geom:latitude": 39.062199, "geom:longitude": -77.066788, "geom:hash": "dqcnnr19v9tv", "woe:latitude": 39.062199, "geom:centroid": [-77.066788, 39.062199], "woe:longitude": -77.066788, "woe:repo": "woeplanet-poi-us"}, "geometry": {"coordinates": [-77.066788, 39.062199], "type": "Point"}}