{"type": "Feature", "id": 23646204, "geometry": {"type": "Point", "coordinates": [-71.398956, 41.858089]}, "properties": {"woe:id": 23646204, "woe:parent_id": 2424182, "woe:name": "Main Street Bridge", "woe:placetype": 20, "woe:placetype_name": "POI", "woe:lang": "ENG", "iso:country": "US", "meta:provider": ["geoplanet:7.3.1", "geoplanet:7.3.2", "geoplanet:7.4.0", "geoplanet:7.4.1", "geoplanet:7.5.1", "geoplanet:7.5.2", "geoplanet:7.6.0", "geoplanet:7.8.1", "geoplanet:7.9.0", "geoplanet:7.10.0", "geoplanet:8.0.0", "woeplanet:8.0.0"], "meta:indexed": "2020-08-20T20:19:00.435673", "meta:updated": "2020-10-14T11:19:28.667341", "woe:hierarchy": {"continent": 24865672, "country": 23424977, "town": 0, "planet": 1, "county": 12589798, "suburb": 0, "state": 2347598, "region": 0, "localadmin": 0}, "woe:timezone_id": 56043648, "woe:hash": "drmnpk0c59rd", "woe:centroid": [-71.398956, 41.858089], "geom:latitude": 41.858089, "geom:longitude": -71.398956, "geom:hash": "drmnpk0c59rd", "woe:latitude": 41.858089, "geom:centroid": [-71.398956, 41.858089], "woe:longitude": -71.398956, "woe:repo": "woeplanet-poi-us", "geom:area": 0.0, "woe:scale": 19}}