{"type": "Feature", "id": 24609928, "properties": {"woe:id": 24609928, "woe:parent_id": 28745672, "woe:name": "Little Palm Island & Spa", "woe:placetype": 20, "woe:placetype_name": "POI", "woe:lang": "ENG", "iso:country": "US", "meta:provider": ["geoplanet:7.3.1", "geoplanet:7.3.2", "geoplanet:7.4.0", "geoplanet:7.4.1", "geoplanet:7.5.1", "geoplanet:7.5.2", "geoplanet:7.6.0", "geoplanet:7.8.1", "geoplanet:7.9.0", "geoplanet:7.10.0", "geoplanet:8.0.0", "woeplanet:8.0.0"], "meta:indexed": "2020-08-20T20:19:14.264510", "woe:alias_ENG_V": ["Little Palm Island and Spa"], "meta:updated": "2020-08-22T02:58:19.388968", "woe:hierarchy": {"continent": 24865672, "country": 23424977, "town": 0, "planet": 1, "county": 12587846, "suburb": 0, "state": 2347568, "region": 0, "localadmin": 0}, "woe:timezone_id": 56043648, "woe:hash": "dhqh7fuf9w7k", "woe:centroid": [-81.391113, 24.66889], "geom:latitude": 24.66889, "geom:longitude": -81.391113, "geom:hash": "dhqh7fuf9w7k", "woe:latitude": 24.66889, "geom:centroid": [-81.391113, 24.66889], "woe:longitude": -81.391113, "woe:repo": "woeplanet-poi-us"}, "geometry": {"coordinates": [-81.391113, 24.66889], "type": "Point"}}