{"type": "Feature", "id": 23671101, "properties": {"woe:id": 23671101, "woe:parent_id": 2378872, "woe:name": "Cheney Middle School", "woe:placetype": 20, "woe:placetype_name": "POI", "woe:lang": "ENG", "iso:country": "US", "meta:provider": ["geoplanet:7.3.1", "geoplanet:7.3.2", "geoplanet:7.4.0", "geoplanet:7.4.1", "geoplanet:7.5.1", "geoplanet:7.5.2", "geoplanet:7.6.0", "geoplanet:7.8.1", "geoplanet:7.9.0", "geoplanet:7.10.0", "geoplanet:8.0.0", "woeplanet:8.0.0"], "meta:indexed": "2020-08-20T20:19:09.808205", "meta:updated": "2020-08-22T02:57:52.232595", "woe:hierarchy": {"continent": 24865672, "country": 23424977, "town": 0, "planet": 1, "county": 12590471, "suburb": 0, "state": 2347606, "region": 0, "localadmin": 0}, "woe:timezone_id": 56043663, "woe:hash": "c2kqk821dejr", "woe:centroid": [-117.575569, 47.506531], "geom:latitude": 47.506531, "geom:longitude": -117.575569, "geom:hash": "c2kqk821dejr", "woe:latitude": 47.506531, "geom:centroid": [-117.575569, 47.506531], "woe:longitude": -117.575569, "woe:repo": "woeplanet-poi-us"}, "geometry": {"coordinates": [-117.575569, 47.506531], "type": "Point"}}