{"type": "Feature", "id": 23668221, "geometry": {"type": "Point", "coordinates": [-123.440048, 48.108471]}, "properties": {"woe:id": 23668221, "woe:parent_id": 55996299, "woe:name": "Jefferson Elementary School", "woe:placetype": 20, "woe:placetype_name": "POI", "woe:lang": "ENG", "iso:country": "US", "meta:provider": ["geoplanet:7.3.1", "geoplanet:7.3.2", "geoplanet:7.4.0", "geoplanet:7.4.1", "geoplanet:7.5.1", "geoplanet:7.5.2", "geoplanet:7.6.0", "geoplanet:7.8.1", "geoplanet:7.9.0", "geoplanet:7.10.0", "geoplanet:8.0.0", "woeplanet:8.0.0"], "meta:indexed": "2020-08-20T20:19:09.039795", "woe:alias_ENG_V": ["Jefferson Elementary"], "meta:updated": "2020-10-14T11:19:35.079537", "woe:hierarchy": {"continent": 24865672, "country": 23424977, "town": 0, "planet": 1, "county": 12590444, "suburb": 0, "state": 2347606, "region": 0, "localadmin": 0}, "woe:timezone_id": 56043663, "woe:hash": "c281xjcsnkuz", "woe:centroid": [-123.440048, 48.108471], "geom:latitude": 48.108471, "geom:longitude": -123.440048, "geom:hash": "c281xjcsnkuz", "woe:latitude": 48.108471, "geom:centroid": [-123.440048, 48.108471], "woe:longitude": -123.440048, "woe:repo": "woeplanet-poi-us", "geom:area": 0.0, "woe:scale": 19}}