{"type": "Feature", "id": 23567216, "geometry": {"type": "Point", "coordinates": [-85.996323, 39.872829]}, "properties": {"woe:id": 23567216, "woe:parent_id": 2437251, "woe:name": "Fall Creek Valley Middle School", "woe:placetype": 20, "woe:placetype_name": "POI", "woe:lang": "ENG", "iso:country": "US", "meta:provider": ["geoplanet:7.3.1", "geoplanet:7.3.2", "geoplanet:7.4.0", "geoplanet:7.4.1", "geoplanet:7.5.1", "geoplanet:7.5.2", "geoplanet:7.6.0", "geoplanet:7.8.1", "geoplanet:7.9.0", "geoplanet:7.10.0", "geoplanet:8.0.0", "woeplanet:8.0.0"], "meta:indexed": "2020-08-20T20:18:34.326132", "meta:updated": "2020-10-14T11:20:05.510648", "woe:hierarchy": {"continent": 24865672, "country": 23424977, "town": 0, "planet": 1, "county": 12588228, "suburb": 0, "state": 2347573, "region": 0, "localadmin": 0}, "woe:timezone_id": 56043656, "woe:hash": "dp4fg4ekh6jc", "woe:centroid": [-85.996323, 39.872829], "geom:latitude": 39.872829, "geom:longitude": -85.996323, "geom:hash": "dp4fg4ekh6jc", "woe:latitude": 39.872829, "geom:centroid": [-85.996323, 39.872829], "woe:longitude": -85.996323, "woe:repo": "woeplanet-poi-us", "geom:area": 0.0, "woe:scale": 19}}