{"type": "Feature", "id": 23592904, "properties": {"woe:id": 23592904, "woe:parent_id": 2355289, "woe:name": "Echo Park Elementary School", "woe:placetype": 20, "woe:placetype_name": "POI", "woe:lang": "ENG", "iso:country": "US", "meta:provider": ["geoplanet:7.3.1", "geoplanet:7.3.2", "geoplanet:7.4.0", "geoplanet:7.4.1", "geoplanet:7.5.1", "geoplanet:7.5.2", "geoplanet:7.6.0", "geoplanet:7.8.1", "geoplanet:7.9.0", "geoplanet:7.10.0", "geoplanet:8.0.0", "woeplanet:8.0.0"], "meta:indexed": "2020-08-20T20:18:42.239574", "woe:alias_ENG_V": ["Echo Park Elementary"], "meta:updated": "2020-08-22T02:57:39.880408", "woe:hierarchy": {"continent": 24865672, "country": 23424977, "town": 0, "planet": 1, "county": 12588815, "suburb": 0, "state": 2347582, "region": 0, "localadmin": 0}, "woe:timezone_id": 56043661, "woe:hash": "9zvwtf5w0dzh", "woe:centroid": [-93.258102, 44.74836], "geom:latitude": 44.74836, "geom:longitude": -93.258102, "geom:hash": "9zvwtf5w0dzh", "woe:latitude": 44.74836, "geom:centroid": [-93.258102, 44.74836], "woe:longitude": -93.258102, "woe:repo": "woeplanet-poi-us"}, "geometry": {"coordinates": [-93.258102, 44.74836], "type": "Point"}}