{"type": "Feature", "id": 23627671, "properties": {"woe:id": 23627671, "woe:parent_id": 2455410, "woe:name": "Boyd E Smith Elementary School", "woe:placetype": 20, "woe:placetype_name": "POI", "woe:lang": "ENG", "iso:country": "US", "meta:provider": ["geoplanet:7.3.1", "geoplanet:7.3.2", "geoplanet:7.4.0", "geoplanet:7.4.1", "geoplanet:7.5.1", "geoplanet:7.5.2", "geoplanet:7.6.0", "geoplanet:7.8.1", "geoplanet:7.9.0", "geoplanet:7.10.0", "geoplanet:8.0.0", "woeplanet:8.0.0"], "meta:indexed": "2020-08-20T20:18:53.361022", "woe:alias_ENG_V": ["Boyd E Smith Elementary"], "meta:updated": "2020-08-22T02:57:44.709700", "woe:hierarchy": {"continent": 24865672, "country": 23424977, "town": 0, "planet": 1, "county": 12589539, "suburb": 0, "state": 2347594, "region": 0, "localadmin": 0}, "woe:timezone_id": 56043648, "woe:hash": "dnup545y2njm", "woe:centroid": [-84.238007, 39.211311], "geom:latitude": 39.211311, "geom:longitude": -84.238007, "geom:hash": "dnup545y2njm", "woe:latitude": 39.211311, "geom:centroid": [-84.238007, 39.211311], "woe:longitude": -84.238007, "woe:repo": "woeplanet-poi-us"}, "geometry": {"coordinates": [-84.238007, 39.211311], "type": "Point"}}