{"type": "Feature", "id": 23623614, "geometry": {"type": "Point", "coordinates": [-79.98951, 34.965389]}, "properties": {"woe:id": 23623614, "woe:parent_id": 2439246, "woe:name": "Lilesville Elementary School", "woe:placetype": 20, "woe:placetype_name": "POI", "woe:lang": "ENG", "iso:country": "US", "meta:provider": ["geoplanet:7.3.2", "geoplanet:7.4.0", "geoplanet:7.4.1", "geoplanet:7.5.1", "geoplanet:7.5.2", "geoplanet:7.6.0", "geoplanet:7.8.1", "geoplanet:7.9.0", "geoplanet:7.10.0", "geoplanet:8.0.0", "woeplanet:8.0.0"], "meta:indexed": "2020-08-20T22:02:39.939190", "woe:alias_ENG_V": ["Lilesville Elementary"], "meta:updated": "2020-10-14T11:19:35.240918", "woe:hierarchy": {"continent": 24865672, "country": 23424977, "town": 0, "planet": 1, "county": 12589377, "suburb": 0, "state": 2347592, "region": 0, "localadmin": 0}, "woe:timezone_id": 56043648, "woe:hash": "dnpngv32jkfm", "woe:centroid": [-79.98951, 34.965389], "geom:latitude": 34.965389, "geom:longitude": -79.98951, "geom:hash": "dnpngv32jkfm", "woe:latitude": 34.965389, "geom:centroid": [-79.98951, 34.965389], "woe:longitude": -79.98951, "woe:repo": "woeplanet-poi-us", "geom:area": 0.0, "woe:scale": 19}}