{"type": "Feature", "id": 23586849, "properties": {"woe:id": 23586849, "woe:parent_id": 26342914, "woe:name": "Central Elementary School", "woe:placetype": 20, "woe:placetype_name": "POI", "woe:lang": "ENG", "iso:country": "US", "meta:provider": ["geoplanet:7.3.1", "geoplanet:7.3.2", "geoplanet:7.4.0", "geoplanet:7.4.1", "geoplanet:7.5.1", "geoplanet:7.5.2", "geoplanet:7.6.0", "geoplanet:7.8.1", "geoplanet:7.9.0", "geoplanet:7.10.0", "geoplanet:8.0.0", "woeplanet:8.0.0"], "meta:indexed": "2020-08-20T20:18:40.111888", "woe:alias_ENG_V": ["Central Elementary"], "meta:updated": "2020-08-22T02:57:38.853378", "woe:hierarchy": {"continent": 24865672, "country": 23424977, "town": 0, "planet": 1, "county": 12588737, "suburb": 0, "state": 2347581, "region": 0, "localadmin": 0}, "woe:timezone_id": 56043658, "woe:hash": "f05d4g9qppgm", "woe:centroid": [-84.955254, 45.371861], "geom:latitude": 45.371861, "geom:longitude": -84.955254, "geom:hash": "f05d4g9qppgm", "woe:latitude": 45.371861, "geom:centroid": [-84.955254, 45.371861], "woe:longitude": -84.955254, "woe:repo": "woeplanet-poi-us"}, "geometry": {"coordinates": [-84.955254, 45.371861], "type": "Point"}}