{"type": "Feature", "id": 23674366, "geometry": {"type": "Point", "coordinates": [-91.241158, 43.846619]}, "properties": {"woe:id": 23674366, "woe:parent_id": 2434169, "woe:name": "Franklin Elementary School", "woe:placetype": 20, "woe:placetype_name": "POI", "woe:lang": "ENG", "iso:country": "US", "meta:provider": ["geoplanet:7.3.1", "geoplanet:7.3.2", "geoplanet:7.4.0", "geoplanet:7.4.1", "geoplanet:7.5.1", "geoplanet:7.5.2", "geoplanet:7.6.0", "geoplanet:7.8.1", "geoplanet:7.9.0", "geoplanet:7.10.0", "geoplanet:8.0.0", "woeplanet:8.0.0"], "meta:indexed": "2020-08-20T20:19:10.956305", "woe:alias_ENG_V": ["Franklin Elementary"], "meta:updated": "2020-10-14T11:19:51.750717", "woe:hierarchy": {"continent": 24865672, "country": 23424977, "town": 0, "planet": 1, "county": 12590565, "suburb": 0, "state": 2347608, "region": 0, "localadmin": 0}, "woe:timezone_id": 56043661, "woe:hash": "9zz17y01nfjw", "woe:centroid": [-91.241158, 43.846619], "geom:latitude": 43.846619, "geom:longitude": -91.241158, "geom:hash": "9zz17y01nfjw", "woe:latitude": 43.846619, "geom:centroid": [-91.241158, 43.846619], "woe:longitude": -91.241158, "woe:repo": "woeplanet-poi-us", "geom:area": 0.0, "woe:scale": 19}}