{"type": "Feature", "id": 23591292, "properties": {"woe:id": 23591292, "woe:parent_id": 29229832, "woe:name": "Chandler Elementary School", "woe:placetype": 20, "woe:placetype_name": "POI", "woe:lang": "ENG", "iso:country": "US", "meta:provider": ["geoplanet:7.3.1", "geoplanet:7.3.2", "geoplanet:7.4.0", "geoplanet:7.4.1", "geoplanet:7.5.1", "geoplanet:7.5.2", "geoplanet:7.6.0", "geoplanet:7.8.1", "geoplanet:7.9.0", "geoplanet:7.10.0", "geoplanet:8.0.0", "woeplanet:8.0.0"], "meta:indexed": "2020-08-20T20:18:41.638147", "woe:alias_ENG_V": ["Chandler Elementary"], "meta:updated": "2020-08-22T02:57:39.614015", "woe:hierarchy": {"continent": 24865672, "country": 23424977, "town": 0, "planet": 1, "county": 12588795, "suburb": 0, "state": 2347581, "region": 0, "localadmin": 0}, "woe:timezone_id": 56043658, "woe:hash": "dpscphjbz3x3", "woe:centroid": [-83.004478, 42.385391], "geom:latitude": 42.385391, "geom:longitude": -83.004478, "geom:hash": "dpscphjbz3x3", "woe:latitude": 42.385391, "geom:centroid": [-83.004478, 42.385391], "woe:longitude": -83.004478, "woe:repo": "woeplanet-poi-us"}, "geometry": {"coordinates": [-83.004478, 42.385391], "type": "Point"}}