{"type": "Feature", "id": 24866450, "properties": {"woe:id": 24866450, "woe:parent_id": 2487170, "woe:name": "Gustavus Adolphus College", "woe:placetype": 20, "woe:placetype_name": "POI", "woe:lang": "ENG", "iso:country": "US", "meta:provider": ["geoplanet:7.3.1", "geoplanet:7.3.2", "geoplanet:7.4.0", "geoplanet:7.4.1", "geoplanet:7.5.1", "geoplanet:7.5.2", "geoplanet:7.6.0", "geoplanet:7.8.1", "geoplanet:7.9.0", "geoplanet:7.10.0", "geoplanet:8.0.0", "woeplanet:8.0.0"], "meta:indexed": "2020-08-20T20:19:15.110796", "meta:updated": "2020-08-22T02:58:19.783653", "woe:hierarchy": {"continent": 24865672, "country": 23424977, "town": 0, "planet": 1, "county": 12588848, "suburb": 0, "state": 2347582, "region": 0, "localadmin": 0}, "woe:timezone_id": 56043661, "woe:hash": "9zvhju2c4et7", "woe:centroid": [-93.96492, 44.320412], "geom:latitude": 44.320412, "geom:longitude": -93.96492, "geom:hash": "9zvhju2c4et7", "woe:latitude": 44.320412, "geom:centroid": [-93.96492, 44.320412], "woe:longitude": -93.96492, "woe:repo": "woeplanet-poi-us"}, "geometry": {"coordinates": [-93.96492, 44.320412], "type": "Point"}}