{"type": "Feature", "id": 23621497, "geometry": {"type": "Point", "coordinates": [-73.325127, 43.172749]}, "properties": {"woe:id": 23621497, "woe:parent_id": 2487380, "woe:name": "Salem Elementary School", "woe:placetype": 20, "woe:placetype_name": "POI", "woe:lang": "ENG", "iso:country": "US", "meta:provider": ["geoplanet:7.3.1", "geoplanet:7.3.2", "geoplanet:7.4.0", "geoplanet:7.4.1", "geoplanet:7.5.1", "geoplanet:7.5.2", "geoplanet:7.6.0", "geoplanet:7.8.1", "geoplanet:7.9.0", "geoplanet:7.10.0", "geoplanet:8.0.0", "woeplanet:8.0.0"], "meta:indexed": "2020-08-20T20:18:52.006304", "woe:alias_ENG_V": ["Salem Elementary"], "meta:updated": "2020-10-14T11:19:44.990502", "woe:hierarchy": {"continent": 24865672, "country": 23424977, "town": 0, "planet": 1, "county": 12589369, "suburb": 0, "state": 2347591, "region": 0, "localadmin": 0}, "woe:timezone_id": 56043648, "woe:hash": "dreve7q72xwr", "woe:centroid": [-73.325127, 43.172749], "geom:latitude": 43.172749, "geom:longitude": -73.325127, "geom:hash": "dreve7q72xwr", "woe:latitude": 43.172749, "geom:centroid": [-73.325127, 43.172749], "woe:longitude": -73.325127, "woe:repo": "woeplanet-poi-us", "geom:area": 0.0, "woe:scale": 19}}