{"type": "Feature", "id": 23667445, "geometry": {"type": "Point", "coordinates": [-76.381783, 36.85878]}, "properties": {"woe:id": 23667445, "woe:parent_id": 2475747, "woe:name": "Churchland Elementary School", "woe:placetype": 20, "woe:placetype_name": "POI", "woe:lang": "ENG", "iso:country": "US", "meta:provider": ["geoplanet:7.3.1", "geoplanet:7.3.2", "geoplanet:7.4.0", "geoplanet:7.4.1", "geoplanet:7.5.1", "geoplanet:7.5.2", "geoplanet:7.6.0", "geoplanet:7.8.1", "geoplanet:7.9.0", "geoplanet:7.10.0", "geoplanet:8.0.0", "woeplanet:8.0.0"], "meta:indexed": "2020-08-20T20:19:08.761282", "woe:alias_ENG_V": ["Churchland Elementary"], "meta:updated": "2020-10-14T11:19:38.538406", "woe:hierarchy": {"continent": 24865672, "country": 23424977, "town": 0, "planet": 1, "county": 12590402, "suburb": 0, "state": 2347605, "region": 0, "localadmin": 0}, "woe:timezone_id": 56043648, "woe:hash": "dq99tvumzqwe", "woe:centroid": [-76.381783, 36.85878], "geom:latitude": 36.85878, "geom:longitude": -76.381783, "geom:hash": "dq99tvumzqwe", "woe:latitude": 36.85878, "geom:centroid": [-76.381783, 36.85878], "woe:longitude": -76.381783, "woe:repo": "woeplanet-poi-us", "geom:area": 0.0, "woe:scale": 19}}