{"type": "Feature", "id": 56052710, "geometry": {"type": "Point", "coordinates": [-78.873154, 42.882099]}, "properties": {"woe:id": 56052710, "woe:parent_id": 28288827, "woe:name": "Erie Community College-City Campus", "woe:placetype": 20, "woe:placetype_name": "POI", "woe:lang": "ENG", "iso:country": "US", "meta:provider": ["geoplanet:7.3.1", "geoplanet:7.3.2", "geoplanet:7.4.0", "geoplanet:7.4.1", "geoplanet:7.5.1", "geoplanet:7.5.2", "geoplanet:7.6.0", "geoplanet:7.8.1", "geoplanet:7.9.0", "geoplanet:7.10.0", "geoplanet:8.0.0", "woeplanet:8.0.0"], "meta:indexed": "2020-08-20T20:19:16.504533", "meta:updated": "2020-10-14T11:19:56.385605", "woe:hierarchy": {"continent": 24865672, "country": 23424977, "town": 0, "planet": 1, "county": 12589326, "suburb": 0, "state": 2347591, "region": 0, "localadmin": 0}, "woe:timezone_id": 56043648, "woe:hash": "dpxgvnqq669s", "woe:centroid": [-78.873154, 42.882099], "geom:latitude": 42.882099, "geom:longitude": -78.873154, "geom:hash": "dpxgvnqq669s", "woe:latitude": 42.882099, "geom:centroid": [-78.873154, 42.882099], "woe:longitude": -78.873154, "woe:repo": "woeplanet-poi-us", "geom:area": 0.0, "woe:scale": 19}}