{"type": "Feature", "id": 23515996, "properties": {"woe:id": 23515996, "woe:parent_id": 2411335, "woe:name": "Kyrene De La Mirada School", "woe:placetype": 20, "woe:placetype_name": "POI", "woe:lang": "ENG", "iso:country": "US", "meta:provider": ["geoplanet:7.3.1", "geoplanet:7.3.2", "geoplanet:7.4.0", "geoplanet:7.4.1", "geoplanet:7.5.1", "geoplanet:7.5.2", "geoplanet:7.6.0", "geoplanet:7.8.1", "geoplanet:7.9.0", "geoplanet:7.10.0", "geoplanet:8.0.0", "woeplanet:8.0.0"], "meta:indexed": "2020-08-20T20:18:18.165554", "meta:updated": "2020-08-22T02:57:26.568841", "woe:alias_ENG_V": ["Kyrene de la Mirada Elementary Sch"], "woe:hierarchy": {"continent": 24865672, "country": 23424977, "town": 0, "planet": 1, "county": 12587587, "suburb": 0, "state": 2347561, "region": 0, "localadmin": 0}, "woe:timezone_id": 56043666, "woe:hash": "9tbmsb4xpm9m", "woe:centroid": [-111.935951, 33.311779], "geom:latitude": 33.311779, "geom:longitude": -111.935951, "geom:hash": "9tbmsb4xpm9m", "woe:latitude": 33.311779, "geom:centroid": [-111.935951, 33.311779], "woe:longitude": -111.935951, "woe:repo": "woeplanet-poi-us"}, "geometry": {"coordinates": [-111.935951, 33.311779], "type": "Point"}}