{"type": "Feature", "id": 23524872, "geometry": {"type": "Point", "coordinates": [-122.499893, 37.75066]}, "properties": {"woe:id": 23524872, "woe:parent_id": 23512061, "woe:name": "John A. O'connell High School", "woe:placetype": 20, "woe:placetype_name": "POI", "woe:lang": "ENG", "iso:country": "US", "meta:provider": ["geoplanet:7.3.1", "geoplanet:7.3.2", "geoplanet:7.4.0", "geoplanet:7.4.1", "geoplanet:7.5.1", "geoplanet:7.5.2", "geoplanet:7.6.0", "geoplanet:7.8.1", "geoplanet:7.9.0", "geoplanet:7.10.0", "geoplanet:8.0.0", "woeplanet:8.0.0"], "meta:indexed": "2020-08-20T20:18:20.468537", "woe:alias_ENG_V": ["John A. O'connell Senior High School", "John A. O'connell High", "John A. O'connell Senior High", "John A. O'connell HS", "John A. O'connell Senior HS", "John O'connell High", "John O'connell High School", "John O'connell HS", "John O'connell Senior High", "John O'connell Senior High School", "John O'connell Senior HS"], "meta:updated": "2020-10-14T11:20:08.567376", "woe:hierarchy": {"continent": 24865672, "country": 23424977, "town": 0, "planet": 1, "county": 12587707, "suburb": 0, "state": 2347563, "region": 0, "localadmin": 0}, "woe:timezone_id": 56043663, "woe:hash": "9q8yu2q39956", "woe:centroid": [-122.499893, 37.75066], "geom:latitude": 37.75066, "geom:longitude": -122.499893, "geom:hash": "9q8yu2q39956", "woe:latitude": 37.75066, "geom:centroid": [-122.499893, 37.75066], "woe:longitude": -122.499893, "woe:repo": "woeplanet-poi-us", "geom:area": 0.0, "woe:scale": 19}}