{"type": "Feature", "id": 23677249, "geometry": {"type": "Point", "coordinates": [-106.302498, 42.850491]}, "properties": {"woe:id": 23677249, "woe:parent_id": 2375993, "woe:name": "Willard Elementary School", "woe:placetype": 20, "woe:placetype_name": "POI", "woe:lang": "ENG", "iso:country": "US", "meta:provider": ["geoplanet:7.3.2", "geoplanet:7.4.0", "geoplanet:7.4.1", "geoplanet:7.5.1", "geoplanet:7.5.2", "geoplanet:7.6.0", "geoplanet:7.8.1", "geoplanet:7.9.0", "geoplanet:7.10.0", "geoplanet:8.0.0", "woeplanet:8.0.0"], "meta:indexed": "2020-08-20T22:03:03.347598", "woe:alias_ENG_V": ["Willard Elementary"], "meta:updated": "2020-10-14T11:19:27.425594", "woe:hierarchy": {"continent": 24865672, "country": 23424977, "town": 0, "planet": 1, "county": 12590618, "suburb": 0, "state": 2347609, "region": 0, "localadmin": 0}, "woe:timezone_id": 56043665, "woe:hash": "9xs7v08yhq2r", "woe:centroid": [-106.302498, 42.850491], "geom:latitude": 42.850491, "geom:longitude": -106.302498, "geom:hash": "9xs7v08yhq2r", "woe:latitude": 42.850491, "geom:centroid": [-106.302498, 42.850491], "woe:longitude": -106.302498, "woe:repo": "woeplanet-poi-us", "geom:area": 0.0, "woe:scale": 19}}