{"type": "Feature", "id": 23600763, "properties": {"woe:id": 23600763, "woe:parent_id": 2362331, "woe:name": "Belt High School", "woe:placetype": 20, "woe:placetype_name": "POI", "woe:lang": "ENG", "iso:country": "US", "meta:provider": ["geoplanet:7.3.2", "geoplanet:7.4.0", "geoplanet:7.4.1", "geoplanet:7.5.1", "geoplanet:7.5.2", "geoplanet:7.6.0", "geoplanet:7.8.1", "geoplanet:7.9.0", "geoplanet:7.10.0", "geoplanet:8.0.0", "woeplanet:8.0.0"], "meta:indexed": "2020-08-20T22:02:31.331332", "woe:alias_ENG_V": ["Belt Senior High School", "Belt High", "Belt Senior High", "Belt HS", "Belt Senior HS"], "meta:updated": "2020-08-22T02:58:48.334228", "woe:hierarchy": {"continent": 24865672, "country": 23424977, "town": 0, "planet": 1, "county": 12589087, "suburb": 0, "state": 2347585, "region": 0, "localadmin": 0}, "woe:timezone_id": 56043665, "woe:hash": "c83jefcmz05v", "woe:centroid": [-110.926933, 47.389141], "geom:latitude": 47.389141, "geom:longitude": -110.926933, "geom:hash": "c83jefcmz05v", "woe:latitude": 47.389141, "geom:centroid": [-110.926933, 47.389141], "woe:longitude": -110.926933, "woe:repo": "woeplanet-poi-us"}, "geometry": {"coordinates": [-110.926933, 47.389141], "type": "Point"}}