{"type": "Feature", "id": 23618317, "properties": {"woe:id": 23618317, "woe:parent_id": 2444851, "woe:name": "Enders Road Elementary School", "woe:placetype": 20, "woe:placetype_name": "POI", "woe:lang": "ENG", "iso:country": "US", "meta:provider": ["geoplanet:7.3.1", "geoplanet:7.3.2", "geoplanet:7.4.0", "geoplanet:7.4.1", "geoplanet:7.5.1", "geoplanet:7.5.2", "geoplanet:7.6.0", "geoplanet:7.8.1", "geoplanet:7.9.0", "geoplanet:7.10.0", "geoplanet:8.0.0", "woeplanet:8.0.0"], "meta:indexed": "2020-08-20T20:18:50.774582", "woe:alias_ENG_V": ["Enders Road Elementary"], "meta:updated": "2020-08-22T02:57:43.438631", "woe:hierarchy": {"continent": 24865672, "country": 23424977, "town": 0, "planet": 1, "county": 12589345, "suburb": 0, "state": 2347591, "region": 0, "localadmin": 0}, "woe:timezone_id": 56043648, "woe:hash": "dr9uxeftz6bz", "woe:centroid": [-75.955727, 43.000118], "geom:latitude": 43.000118, "geom:longitude": -75.955727, "geom:hash": "dr9uxeftz6bz", "woe:latitude": 43.000118, "geom:centroid": [-75.955727, 43.000118], "woe:longitude": -75.955727, "woe:repo": "woeplanet-poi-us"}, "geometry": {"coordinates": [-75.955727, 43.000118], "type": "Point"}}