{"type": "Feature", "id": 23570001, "properties": {"woe:id": 23570001, "woe:parent_id": 2465613, "woe:name": "Lark Elementary School", "woe:placetype": 20, "woe:placetype_name": "POI", "woe:lang": "ENG", "iso:country": "US", "meta:provider": ["geoplanet:7.3.2", "geoplanet:7.4.0", "geoplanet:7.4.1", "geoplanet:7.5.1", "geoplanet:7.5.2", "geoplanet:7.6.0", "geoplanet:7.8.1", "geoplanet:7.9.0", "geoplanet:7.10.0", "geoplanet:8.0.0", "woeplanet:8.0.0"], "meta:indexed": "2020-08-20T22:02:18.504897", "woe:alias_ENG_V": ["Lark Elementary"], "meta:updated": "2020-08-22T02:57:36.234012", "woe:hierarchy": {"continent": 24865672, "country": 23424977, "town": 0, "planet": 1, "county": 12588338, "suburb": 0, "state": 2347574, "region": 0, "localadmin": 0}, "woe:timezone_id": 56043661, "woe:hash": "9z7xj7wjv7g0", "woe:centroid": [-96.088943, 42.031952], "geom:latitude": 42.031952, "geom:longitude": -96.088943, "geom:hash": "9z7xj7wjv7g0", "woe:latitude": 42.031952, "geom:centroid": [-96.088943, 42.031952], "woe:longitude": -96.088943, "woe:repo": "woeplanet-poi-us"}, "geometry": {"coordinates": [-96.088943, 42.031952], "type": "Point"}}