{"type": "Feature", "id": 56063729, "geometry": {"type": "Point", "coordinates": [-121.718399, 37.695]}, "properties": {"woe:id": 56063729, "woe:parent_id": 2440549, "woe:name": "Vasco Station", "woe:placetype": 20, "woe:placetype_name": "POI", "woe:lang": "ENG", "iso:country": "US", "meta:provider": ["geoplanet:7.3.1", "geoplanet:7.3.2", "geoplanet:7.4.0", "geoplanet:7.4.1", "geoplanet:7.5.1", "geoplanet:7.5.2", "geoplanet:7.6.0", "geoplanet:7.8.1", "geoplanet:7.9.0", "geoplanet:7.10.0", "geoplanet:8.0.0", "woeplanet:8.0.0"], "meta:indexed": "2020-08-20T20:19:20.733505", "woe:alias_ENG_V": ["Ace-Vasco Road Station", "Vasco ACE Station", "ACE Vasco Station", "Ace-Vasco Station"], "meta:updated": "2020-10-14T11:19:56.467987", "woe:hierarchy": {"continent": 24865672, "country": 23424977, "town": 0, "planet": 1, "county": 12587670, "suburb": 0, "state": 2347563, "region": 0, "localadmin": 0}, "woe:timezone_id": 56043663, "woe:hash": "9q9qqnpm79r9", "woe:centroid": [-121.718399, 37.695], "geom:latitude": 37.695, "geom:longitude": -121.718399, "geom:hash": "9q9qqnpm79r9", "woe:latitude": 37.695, "geom:centroid": [-121.718399, 37.695], "woe:longitude": -121.718399, "woe:repo": "woeplanet-poi-us", "geom:area": 0.0, "woe:scale": 19}}