{"type": "Feature", "id": 23622432, "geometry": {"type": "Point", "coordinates": [-78.868896, 35.050529]}, "properties": {"woe:id": 23622432, "woe:parent_id": 55858960, "woe:name": "Fayette Centerl Christian Academy", "woe:placetype": 20, "woe:placetype_name": "POI", "woe:lang": "ENG", "iso:country": "US", "meta:provider": ["geoplanet:7.3.1", "geoplanet:7.3.2", "geoplanet:7.4.0", "geoplanet:7.4.1", "geoplanet:7.5.1", "geoplanet:7.5.2", "geoplanet:7.6.0", "geoplanet:7.8.1", "geoplanet:7.9.0", "geoplanet:7.10.0", "geoplanet:8.0.0", "woeplanet:8.0.0"], "meta:indexed": "2020-08-20T20:18:52.341544", "meta:updated": "2020-10-14T11:19:43.750892", "woe:hierarchy": {"continent": 24865672, "country": 23424977, "town": 0, "planet": 1, "county": 12589399, "suburb": 0, "state": 2347592, "region": 0, "localadmin": 0}, "woe:timezone_id": 56043648, "woe:hash": "dnpzmkc2js0t", "woe:centroid": [-78.868896, 35.050529], "geom:latitude": 35.050529, "geom:longitude": -78.868896, "geom:hash": "dnpzmkc2js0t", "woe:latitude": 35.050529, "geom:centroid": [-78.868896, 35.050529], "woe:longitude": -78.868896, "woe:repo": "woeplanet-poi-us", "geom:area": 0.0, "woe:scale": 19}}