{"type": "Feature", "id": 23526032, "properties": {"woe:id": 23526032, "woe:parent_id": 55971302, "woe:name": "Happy Hollow Park and Zoo", "woe:placetype": 20, "woe:placetype_name": "POI", "woe:lang": "ENG", "iso:country": "US", "meta:provider": ["geoplanet:7.3.1", "geoplanet:7.3.2", "geoplanet:7.4.0", "geoplanet:7.4.1", "geoplanet:7.5.1", "geoplanet:7.5.2", "geoplanet:7.6.0", "geoplanet:7.8.1", "geoplanet:7.9.0", "geoplanet:7.10.0", "geoplanet:8.0.0", "woeplanet:8.0.0"], "meta:indexed": "2020-08-20T20:18:20.735213", "woe:alias_ENG_V": ["Happy Hollow Park & Zoo"], "meta:updated": "2020-08-22T02:57:28.003429", "woe:hierarchy": {"continent": 24865672, "country": 23424977, "town": 0, "planet": 1, "county": 12587712, "suburb": 0, "state": 2347563, "region": 0, "localadmin": 0}, "woe:timezone_id": 56043663, "woe:hash": "9q9k6fzp64h3", "woe:centroid": [-121.861633, 37.325932], "geom:latitude": 37.325932, "geom:longitude": -121.861633, "geom:hash": "9q9k6fzp64h3", "woe:latitude": 37.325932, "geom:centroid": [-121.861633, 37.325932], "woe:longitude": -121.861633, "woe:repo": "woeplanet-poi-us"}, "geometry": {"coordinates": [-121.861633, 37.325932], "type": "Point"}}