{"type": "Feature", "id": 23612759, "geometry": {"type": "Point", "coordinates": [-73.886337, 40.862228]}, "properties": {"woe:id": 23612759, "woe:parent_id": 23511805, "woe:name": "Fordham University", "woe:placetype": 20, "woe:placetype_name": "POI", "woe:lang": "ENG", "iso:country": "US", "meta:provider": ["geoplanet:7.3.1", "geoplanet:7.3.2", "geoplanet:7.4.0", "geoplanet:7.4.1", "geoplanet:7.5.1", "geoplanet:7.5.2", "geoplanet:7.6.0", "geoplanet:7.8.1", "geoplanet:7.9.0", "geoplanet:7.10.0", "geoplanet:8.0.0", "woeplanet:8.0.0"], "meta:indexed": "2020-08-20T20:18:48.562724", "meta:updated": "2020-10-14T11:19:41.512334", "woe:hierarchy": {"continent": 24865672, "country": 23424977, "town": 0, "planet": 1, "county": 12589314, "suburb": 0, "state": 2347591, "region": 0, "localadmin": 0}, "woe:timezone_id": 56043648, "woe:hash": "dr72qwtxex3u", "woe:centroid": [-73.886337, 40.862228], "geom:latitude": 40.862228, "geom:longitude": -73.886337, "geom:hash": "dr72qwtxex3u", "woe:latitude": 40.862228, "geom:centroid": [-73.886337, 40.862228], "woe:longitude": -73.886337, "woe:repo": "woeplanet-poi-us", "geom:area": 0.0, "woe:scale": 19}}