{"type": "Feature", "id": 23593846, "properties": {"woe:id": 23593846, "woe:parent_id": 2521015, "woe:name": "Roosevelt Elementary School", "woe:placetype": 20, "woe:placetype_name": "POI", "woe:lang": "ENG", "iso:country": "US", "meta:provider": ["geoplanet:7.3.1", "geoplanet:7.3.2", "geoplanet:7.4.0", "geoplanet:7.4.1", "geoplanet:7.5.1", "geoplanet:7.5.2", "geoplanet:7.6.0", "geoplanet:7.8.1", "geoplanet:7.9.0", "geoplanet:7.10.0", "geoplanet:8.0.0", "woeplanet:8.0.0"], "meta:indexed": "2020-08-20T20:18:42.611344", "woe:alias_ENG_V": ["Roosevelt Elementary"], "meta:updated": "2020-08-22T02:57:40.038193", "woe:hierarchy": {"continent": 24865672, "country": 23424977, "town": 0, "planet": 1, "county": 12588830, "suburb": 0, "state": 2347582, "region": 0, "localadmin": 0}, "woe:timezone_id": 56043661, "woe:hash": "cbh2sdy1zurt", "woe:centroid": [-95.067101, 45.103321], "geom:latitude": 45.103321, "geom:longitude": -95.067101, "geom:hash": "cbh2sdy1zurt", "woe:latitude": 45.103321, "geom:centroid": [-95.067101, 45.103321], "woe:longitude": -95.067101, "woe:repo": "woeplanet-poi-us"}, "geometry": {"coordinates": [-95.067101, 45.103321], "type": "Point"}}