{"type": "Feature", "id": 23615018, "properties": {"woe:id": 23615018, "woe:parent_id": 55992170, "woe:name": "Franklin K. Lane High School", "woe:placetype": 20, "woe:placetype_name": "POI", "woe:lang": "ENG", "iso:country": "US", "meta:provider": ["geoplanet:7.3.1", "geoplanet:7.3.2", "geoplanet:7.4.0", "geoplanet:7.4.1", "geoplanet:7.5.1", "geoplanet:7.5.2", "geoplanet:7.6.0", "geoplanet:7.8.1", "geoplanet:7.9.0", "geoplanet:7.10.0", "geoplanet:8.0.0", "woeplanet:8.0.0"], "meta:indexed": "2020-08-20T20:18:49.316707", "woe:alias_ENG_V": ["Franklin K. Lane Senior High School", "Franklin K. Lane High", "Franklin K. Lane Senior High", "Franklin K. Lane HS", "Franklin K. Lane Senior HS", "Franklin Lane High", "Franklin Lane High School", "Franklin Lane HS", "Franklin Lane Senior High", "Franklin Lane Senior High School", "Franklin Lane Senior HS"], "meta:updated": "2020-08-22T02:58:48.710566", "woe:hierarchy": {"continent": 24865672, "country": 23424977, "town": 0, "planet": 1, "county": 12589335, "suburb": 0, "state": 2347591, "region": 0, "localadmin": 0}, "woe:timezone_id": 56043648, "woe:hash": "dr5rrpd6ewxx", "woe:centroid": [-73.86882, 40.691078], "geom:latitude": 40.691078, "geom:longitude": -73.86882, "geom:hash": "dr5rrpd6ewxx", "woe:latitude": 40.691078, "geom:centroid": [-73.86882, 40.691078], "woe:longitude": -73.86882, "woe:repo": "woeplanet-poi-us"}, "geometry": {"coordinates": [-73.86882, 40.691078], "type": "Point"}}