{"type": "Feature", "id": 23632013, "geometry": {"type": "Point", "coordinates": [-82.67012, 40.886478]}, "properties": {"woe:id": 23632013, "woe:parent_id": 2492126, "woe:name": "Shelby High School", "woe:placetype": 20, "woe:placetype_name": "POI", "woe:lang": "ENG", "iso:country": "US", "meta:provider": ["geoplanet:7.3.1", "geoplanet:7.3.2", "geoplanet:7.4.0", "geoplanet:7.4.1", "geoplanet:7.5.1", "geoplanet:7.5.2", "geoplanet:7.6.0", "geoplanet:7.8.1", "geoplanet:7.9.0", "geoplanet:7.10.0", "geoplanet:8.0.0", "woeplanet:8.0.0"], "meta:indexed": "2020-08-20T20:18:55.400932", "woe:alias_ENG_V": ["Shelby Senior High School", "Shelby High", "Shelby Senior High", "Shelby HS", "Shelby Senior HS"], "meta:updated": "2020-10-14T11:19:43.566888", "woe:hierarchy": {"continent": 24865672, "country": 23424977, "town": 0, "planet": 1, "county": 12589596, "suburb": 0, "state": 2347594, "region": 0, "localadmin": 0}, "woe:timezone_id": 56043648, "woe:hash": "dpm0wg1kyxft", "woe:centroid": [-82.67012, 40.886478], "geom:latitude": 40.886478, "geom:longitude": -82.67012, "geom:hash": "dpm0wg1kyxft", "woe:latitude": 40.886478, "geom:centroid": [-82.67012, 40.886478], "woe:longitude": -82.67012, "woe:repo": "woeplanet-poi-us", "geom:area": 0.0, "woe:scale": 19}}