{"type": "Feature", "id": 23661718, "properties": {"woe:id": 23661718, "woe:parent_id": 2517597, "woe:name": "West Point Elementary School", "woe:placetype": 20, "woe:placetype_name": "POI", "woe:lang": "ENG", "iso:country": "US", "meta:provider": ["geoplanet:7.3.1", "geoplanet:7.3.2", "geoplanet:7.4.0", "geoplanet:7.4.1", "geoplanet:7.5.1", "geoplanet:7.5.2", "geoplanet:7.6.0", "geoplanet:7.8.1", "geoplanet:7.9.0", "geoplanet:7.10.0", "geoplanet:8.0.0", "woeplanet:8.0.0"], "meta:indexed": "2020-08-20T20:19:07.065706", "woe:alias_ENG_V": ["W Point Elementary School", "W Point Elementary", "West Point Elementary"], "meta:updated": "2020-08-22T02:57:50.781194", "woe:hierarchy": {"continent": 24865672, "country": 23424977, "town": 0, "planet": 1, "county": 12590266, "suburb": 0, "state": 2347603, "region": 0, "localadmin": 0}, "woe:timezone_id": 56043665, "woe:hash": "9x23cj7fsc1c", "woe:centroid": [-112.099136, 41.118141], "geom:latitude": 41.118141, "geom:longitude": -112.099136, "geom:hash": "9x23cj7fsc1c", "woe:latitude": 41.118141, "geom:centroid": [-112.099136, 41.118141], "woe:longitude": -112.099136, "woe:repo": "woeplanet-poi-us"}, "geometry": {"coordinates": [-112.099136, 41.118141], "type": "Point"}}