{"type": "Feature", "id": 56054650, "properties": {"woe:id": 56054650, "woe:parent_id": 2362865, "woe:name": "Greenville Technical College-Nw", "woe:placetype": 20, "woe:placetype_name": "POI", "woe:lang": "ENG", "iso:country": "US", "meta:provider": ["geoplanet:7.3.1", "geoplanet:7.3.2", "geoplanet:7.4.0", "geoplanet:7.4.1", "geoplanet:7.5.1", "geoplanet:7.5.2", "geoplanet:7.6.0", "geoplanet:7.8.1", "geoplanet:7.9.0", "geoplanet:7.10.0", "geoplanet:8.0.0", "woeplanet:8.0.0"], "meta:indexed": "2020-08-20T20:19:18.007061", "meta:updated": "2020-08-22T02:58:21.409673", "woe:alias_ENG_V": ["Greenville Technical College-Northwest"], "woe:hierarchy": {"continent": 24865672, "country": 23424977, "town": 0, "planet": 1, "county": 12589822, "suburb": 0, "state": 2347599, "region": 0, "localadmin": 0}, "woe:timezone_id": 56043648, "woe:hash": "dnjqe2mnjz5w", "woe:centroid": [-82.467247, 34.89502], "geom:latitude": 34.89502, "geom:longitude": -82.467247, "geom:hash": "dnjqe2mnjz5w", "woe:latitude": 34.89502, "geom:centroid": [-82.467247, 34.89502], "woe:longitude": -82.467247, "woe:repo": "woeplanet-poi-us"}, "geometry": {"coordinates": [-82.467247, 34.89502], "type": "Point"}}