{"type": "Feature", "id": 23519990, "properties": {"woe:id": 23519990, "woe:parent_id": 55969040, "woe:name": "St Philip Neri School", "woe:placetype": 20, "woe:placetype_name": "POI", "woe:lang": "ENG", "iso:country": "US", "meta:provider": ["geoplanet:7.3.1", "geoplanet:7.3.2", "geoplanet:7.4.0", "geoplanet:7.4.1", "geoplanet:7.5.1", "geoplanet:7.5.2", "geoplanet:7.6.0", "geoplanet:7.8.1", "geoplanet:7.9.0", "geoplanet:7.10.0", "geoplanet:8.0.0", "woeplanet:8.0.0"], "meta:indexed": "2020-08-20T20:18:19.599073", "meta:updated": "2020-08-22T02:57:27.206414", "woe:hierarchy": {"continent": 24865672, "country": 23424977, "town": 0, "planet": 1, "county": 12587670, "suburb": 0, "state": 2347563, "region": 0, "localadmin": 0}, "woe:timezone_id": 56043663, "woe:hash": "9q9nf92x0p0j", "woe:centroid": [-122.2332, 37.75713], "geom:latitude": 37.75713, "geom:longitude": -122.2332, "geom:hash": "9q9nf92x0p0j", "woe:latitude": 37.75713, "geom:centroid": [-122.2332, 37.75713], "woe:longitude": -122.2332, "woe:repo": "woeplanet-poi-us"}, "geometry": {"coordinates": [-122.2332, 37.75713], "type": "Point"}}