{"type": "Feature", "id": 23655949, "properties": {"woe:id": 23655949, "woe:parent_id": 2391156, "woe:name": "Curtis Elementary School", "woe:placetype": 20, "woe:placetype_name": "POI", "woe:lang": "ENG", "iso:country": "US", "meta:provider": ["geoplanet:7.3.1", "geoplanet:7.3.2", "geoplanet:7.4.0", "geoplanet:7.4.1", "geoplanet:7.5.1", "geoplanet:7.5.2", "geoplanet:7.6.0", "geoplanet:7.8.1", "geoplanet:7.9.0", "geoplanet:7.10.0", "geoplanet:8.0.0", "woeplanet:8.0.0"], "meta:indexed": "2020-08-20T20:19:04.104871", "woe:alias_ENG_V": ["Curtis Elementary"], "meta:updated": "2020-08-22T02:57:49.427384", "woe:hierarchy": {"continent": 24865672, "country": 23424977, "town": 0, "planet": 1, "county": 12590190, "suburb": 0, "state": 2347602, "region": 0, "localadmin": 0}, "woe:timezone_id": 56043661, "woe:hash": "9vf3ejxm0ckk", "woe:centroid": [-97.944107, 32.6385], "geom:latitude": 32.6385, "geom:longitude": -97.944107, "geom:hash": "9vf3ejxm0ckk", "woe:latitude": 32.6385, "geom:centroid": [-97.944107, 32.6385], "woe:longitude": -97.944107, "woe:repo": "woeplanet-poi-us"}, "geometry": {"coordinates": [-97.944107, 32.6385], "type": "Point"}}