{"type": "Feature", "id": 23529579, "geometry": {"type": "Point", "coordinates": [-118.037453, 34.02]}, "properties": {"woe:id": 23529579, "woe:parent_id": 55971916, "woe:name": "Rio Hondo College", "woe:placetype": 20, "woe:placetype_name": "POI", "woe:lang": "ENG", "iso:country": "US", "meta:provider": ["geoplanet:7.3.1", "geoplanet:7.3.2", "geoplanet:7.4.0", "geoplanet:7.4.1", "geoplanet:7.5.1", "geoplanet:7.5.2", "geoplanet:7.6.0", "geoplanet:7.8.1", "geoplanet:7.9.0", "geoplanet:7.10.0", "geoplanet:8.0.0", "woeplanet:8.0.0"], "meta:indexed": "2020-08-20T20:18:21.459030", "meta:updated": "2020-10-14T11:20:16.408020", "woe:alias_ENG_V": ["Rio Hondo Community College"], "woe:hierarchy": {"continent": 24865672, "country": 23424977, "town": 0, "planet": 1, "county": 12587688, "suburb": 0, "state": 2347563, "region": 0, "localadmin": 0}, "woe:timezone_id": 56043663, "woe:hash": "9qh19cpszgxu", "woe:centroid": [-118.037453, 34.02], "geom:latitude": 34.02, "geom:longitude": -118.037453, "geom:hash": "9qh19cpszgxu", "woe:latitude": 34.02, "geom:centroid": [-118.037453, 34.02], "woe:longitude": -118.037453, "woe:repo": "woeplanet-poi-us", "geom:area": 0.0, "woe:scale": 19}}