{"type": "Feature", "id": 23643940, "properties": {"woe:id": 23643940, "woe:parent_id": 2480508, "woe:name": "Rhawnhurst School", "woe:placetype": 20, "woe:placetype_name": "POI", "woe:lang": "ENG", "iso:country": "US", "meta:provider": ["geoplanet:7.3.1", "geoplanet:7.3.2", "geoplanet:7.4.0", "geoplanet:7.4.1", "geoplanet:7.5.1", "geoplanet:7.5.2", "geoplanet:7.6.0", "geoplanet:7.8.1", "geoplanet:7.9.0", "geoplanet:7.10.0", "geoplanet:8.0.0", "woeplanet:8.0.0"], "meta:indexed": "2020-08-20T20:18:59.743098", "meta:updated": "2020-08-22T02:57:47.254484", "woe:alias_ENG_V": ["Rhawnhurst Elementary School"], "woe:hierarchy": {"continent": 24865672, "country": 23424977, "town": 0, "planet": 1, "county": 12589778, "suburb": 0, "state": 2347597, "region": 0, "localadmin": 0}, "woe:timezone_id": 56043648, "woe:hash": "dr4egur7u78j", "woe:centroid": [-75.059441, 40.058189], "geom:latitude": 40.058189, "geom:longitude": -75.059441, "geom:hash": "dr4egur7u78j", "woe:latitude": 40.058189, "geom:centroid": [-75.059441, 40.058189], "woe:longitude": -75.059441, "woe:repo": "woeplanet-poi-us"}, "geometry": {"coordinates": [-75.059441, 40.058189], "type": "Point"}}