{"type": "Feature", "id": 23614632, "geometry": {"type": "Point", "coordinates": [-74.511276, 44.973881]}, "properties": {"woe:id": 23614632, "woe:parent_id": 2405645, "woe:name": "Salmon River Elementary School", "woe:placetype": 20, "woe:placetype_name": "POI", "woe:lang": "ENG", "iso:country": "US", "meta:provider": ["geoplanet:7.3.1", "geoplanet:7.3.2", "geoplanet:7.4.0", "geoplanet:7.4.1", "geoplanet:7.5.1", "geoplanet:7.5.2", "geoplanet:7.6.0", "geoplanet:7.8.1", "geoplanet:7.9.0", "geoplanet:7.10.0", "geoplanet:8.0.0", "woeplanet:8.0.0"], "meta:indexed": "2020-08-20T20:18:49.213038", "woe:alias_ENG_V": ["Salmon River Elementary"], "meta:updated": "2020-10-14T11:19:41.249020", "woe:hierarchy": {"continent": 24865672, "country": 23424977, "town": 0, "planet": 1, "county": 12589328, "suburb": 0, "state": 2347591, "region": 0, "localadmin": 0}, "woe:timezone_id": 56043648, "woe:hash": "drgpb7nxc7jd", "woe:centroid": [-74.511276, 44.973881], "geom:latitude": 44.973881, "geom:longitude": -74.511276, "geom:hash": "drgpb7nxc7jd", "woe:latitude": 44.973881, "geom:centroid": [-74.511276, 44.973881], "woe:longitude": -74.511276, "woe:repo": "woeplanet-poi-us", "geom:area": 0.0, "woe:scale": 19}}