{"type": "Feature", "id": 23542636, "properties": {"woe:id": 23542636, "woe:parent_id": 2361828, "woe:name": "Hamilton Avenue School", "woe:placetype": 20, "woe:placetype_name": "POI", "woe:lang": "ENG", "iso:country": "US", "meta:provider": ["geoplanet:7.3.1", "geoplanet:7.3.2", "geoplanet:7.4.0", "geoplanet:7.4.1", "geoplanet:7.5.1", "geoplanet:7.5.2", "geoplanet:7.6.0", "geoplanet:7.8.1", "geoplanet:7.9.0", "geoplanet:7.10.0", "geoplanet:8.0.0", "woeplanet:8.0.0"], "meta:indexed": "2020-08-20T20:18:24.960121", "meta:updated": "2020-08-22T02:57:30.959611", "woe:hierarchy": {"continent": 24865672, "country": 23424977, "town": 0, "planet": 1, "county": 12587791, "suburb": 0, "state": 2347565, "region": 0, "localadmin": 0}, "woe:timezone_id": 56043648, "woe:hash": "dr79k7129qtr", "woe:centroid": [-73.63958, 41.017578], "geom:latitude": 41.017578, "geom:longitude": -73.63958, "geom:hash": "dr79k7129qtr", "woe:latitude": 41.017578, "geom:centroid": [-73.63958, 41.017578], "woe:longitude": -73.63958, "woe:repo": "woeplanet-poi-us"}, "geometry": {"coordinates": [-73.63958, 41.017578], "type": "Point"}}