{"type": "Feature", "id": 56054277, "geometry": {"type": "Point", "coordinates": [-112.016739, 46.59589]}, "properties": {"woe:id": 56054277, "woe:parent_id": 2419761, "woe:name": "University of Montana-Helena", "woe:placetype": 20, "woe:placetype_name": "POI", "woe:lang": "ENG", "iso:country": "US", "meta:provider": ["geoplanet:7.3.1", "geoplanet:7.3.2", "geoplanet:7.4.0", "geoplanet:7.4.1", "geoplanet:7.5.1", "geoplanet:7.5.2", "geoplanet:7.6.0", "geoplanet:7.8.1", "geoplanet:7.9.0", "geoplanet:7.10.0", "geoplanet:8.0.0", "woeplanet:8.0.0"], "meta:indexed": "2020-08-20T20:19:17.708927", "woe:alias_ENG_V": ["Um-Helena"], "meta:updated": "2020-10-14T11:19:56.549254", "woe:hierarchy": {"continent": 24865672, "country": 23424977, "town": 0, "planet": 1, "county": 12589105, "suburb": 0, "state": 2347585, "region": 0, "localadmin": 0}, "woe:timezone_id": 56043665, "woe:hash": "c8234fxbsz3w", "woe:centroid": [-112.016739, 46.59589], "geom:latitude": 46.59589, "geom:longitude": -112.016739, "geom:hash": "c8234fxbsz3w", "woe:latitude": 46.59589, "geom:centroid": [-112.016739, 46.59589], "woe:longitude": -112.016739, "woe:repo": "woeplanet-poi-us", "geom:area": 0.0, "woe:scale": 19}}