{"type": "Feature", "id": 23621535, "properties": {"woe:id": 23621535, "woe:parent_id": 2459267, "woe:name": "Newark Senior High School", "woe:placetype": 20, "woe:placetype_name": "POI", "woe:lang": "ENG", "iso:country": "US", "meta:provider": ["geoplanet:7.3.1", "geoplanet:7.3.2", "geoplanet:7.4.0", "geoplanet:7.4.1", "geoplanet:7.5.1", "geoplanet:7.5.2", "geoplanet:7.6.0", "geoplanet:7.8.1", "geoplanet:7.9.0", "geoplanet:7.10.0", "geoplanet:8.0.0", "woeplanet:8.0.0"], "meta:indexed": "2020-08-20T20:18:52.021208", "woe:alias_ENG_V": ["Newark Senior High", "Newark High School", "Newark High", "Newark Senior HS", "Newark HS"], "meta:updated": "2020-08-22T02:58:48.876397", "woe:hierarchy": {"continent": 24865672, "country": 23424977, "town": 0, "planet": 1, "county": 12589370, "suburb": 0, "state": 2347591, "region": 0, "localadmin": 0}, "woe:timezone_id": 56043648, "woe:hash": "dr9hv6u9zskg", "woe:centroid": [-77.106529, 43.037891], "geom:latitude": 43.037891, "geom:longitude": -77.106529, "geom:hash": "dr9hv6u9zskg", "woe:latitude": 43.037891, "geom:centroid": [-77.106529, 43.037891], "woe:longitude": -77.106529, "woe:repo": "woeplanet-poi-us"}, "geometry": {"coordinates": [-77.106529, 43.037891], "type": "Point"}}