{"type": "Feature", "id": 56054756, "properties": {"woe:id": 56054756, "woe:parent_id": 2391639, "woe:name": "Minnesota State Community Tech College", "woe:placetype": 20, "woe:placetype_name": "POI", "woe:lang": "ENG", "iso:country": "US", "meta:provider": ["geoplanet:7.3.1", "geoplanet:7.3.2", "geoplanet:7.4.0", "geoplanet:7.4.1", "geoplanet:7.5.1", "geoplanet:7.5.2", "geoplanet:7.6.0", "geoplanet:7.8.1", "geoplanet:7.9.0", "geoplanet:7.10.0", "geoplanet:8.0.0", "woeplanet:8.0.0"], "meta:indexed": "2020-08-20T20:19:18.095340", "meta:updated": "2020-08-22T02:58:21.458177", "woe:alias_ENG_V": ["Minnesota State Community Tech Col"], "woe:hierarchy": {"continent": 24865672, "country": 23424977, "town": 0, "planet": 1, "county": 12588799, "suburb": 0, "state": 2347582, "region": 0, "localadmin": 0}, "woe:timezone_id": 56043661, "woe:hash": "cb7f7k2szjgv", "woe:centroid": [-95.832748, 46.825951], "geom:latitude": 46.825951, "geom:longitude": -95.832748, "geom:hash": "cb7f7k2szjgv", "woe:latitude": 46.825951, "geom:centroid": [-95.832748, 46.825951], "woe:longitude": -95.832748, "woe:repo": "woeplanet-poi-us"}, "geometry": {"coordinates": [-95.832748, 46.825951], "type": "Point"}}