{"type": "Feature", "id": 23632519, "geometry": {"type": "Point", "coordinates": [-81.560188, 41.240269]}, "properties": {"woe:id": 23632519, "woe:parent_id": 2470209, "woe:name": "Woodridge Intermediate Elementary School", "woe:placetype": 20, "woe:placetype_name": "POI", "woe:lang": "ENG", "iso:country": "US", "meta:provider": ["geoplanet:7.3.1", "geoplanet:7.3.2", "geoplanet:7.4.0", "geoplanet:7.4.1", "geoplanet:7.5.1", "geoplanet:7.5.2", "geoplanet:7.6.0", "geoplanet:7.8.1", "geoplanet:7.9.0", "geoplanet:7.10.0", "geoplanet:8.0.0", "woeplanet:8.0.0"], "meta:indexed": "2020-08-20T20:18:55.647167", "woe:alias_ENG_V": ["Woodridge Intermediate Elementary"], "meta:updated": "2020-10-14T11:19:33.908052", "woe:hierarchy": {"continent": 24865672, "country": 23424977, "town": 0, "planet": 1, "county": 12589603, "suburb": 0, "state": 2347594, "region": 0, "localadmin": 0}, "woe:timezone_id": 56043648, "woe:hash": "dpq48599vz7f", "woe:centroid": [-81.560188, 41.240269], "geom:latitude": 41.240269, "geom:longitude": -81.560188, "geom:hash": "dpq48599vz7f", "woe:latitude": 41.240269, "geom:centroid": [-81.560188, 41.240269], "woe:longitude": -81.560188, "woe:repo": "woeplanet-poi-us", "geom:area": 0.0, "woe:scale": 19}}