{"type": "Feature", "id": 23614941, "geometry": {"type": "Point", "coordinates": [-73.985672, 40.69429]}, "properties": {"woe:id": 23614941, "woe:parent_id": 28751214, "woe:name": "Polytechnic University", "woe:placetype": 20, "woe:placetype_name": "POI", "woe:lang": "ENG", "iso:country": "US", "meta:provider": ["geoplanet:7.3.1", "geoplanet:7.3.2", "geoplanet:7.4.0", "geoplanet:7.4.1", "geoplanet:7.5.1", "geoplanet:7.5.2", "geoplanet:7.6.0", "geoplanet:7.8.1", "geoplanet:7.9.0", "geoplanet:7.10.0", "geoplanet:8.0.0", "woeplanet:8.0.0"], "meta:indexed": "2020-08-20T20:18:49.297341", "meta:updated": "2020-10-14T11:19:35.333290", "woe:hierarchy": {"continent": 24865672, "country": 23424977, "town": 0, "planet": 1, "county": 12589335, "suburb": 0, "state": 2347591, "region": 0, "localadmin": 0}, "woe:timezone_id": 56043648, "woe:hash": "dr5rs2jm2vkr", "woe:centroid": [-73.985672, 40.69429], "geom:latitude": 40.69429, "geom:longitude": -73.985672, "geom:hash": "dr5rs2jm2vkr", "woe:latitude": 40.69429, "geom:centroid": [-73.985672, 40.69429], "woe:longitude": -73.985672, "woe:repo": "woeplanet-poi-us", "geom:area": 0.0, "woe:scale": 19}}