{"type": "Feature", "id": 23661170, "geometry": {"type": "Point", "coordinates": [-97.696198, 30.41609]}, "properties": {"woe:id": 23661170, "woe:parent_id": 55993054, "woe:name": "North Park Station", "woe:placetype": 20, "woe:placetype_name": "POI", "woe:lang": "ENG", "iso:country": "US", "meta:provider": ["geoplanet:7.3.1", "geoplanet:7.3.2", "geoplanet:7.4.0", "geoplanet:7.4.1", "geoplanet:7.5.1", "geoplanet:7.5.2", "geoplanet:7.6.0", "geoplanet:7.8.1", "geoplanet:7.9.0", "geoplanet:7.10.0", "geoplanet:8.0.0", "woeplanet:8.0.0"], "meta:indexed": "2020-08-20T20:19:06.825456", "woe:alias_ENG_V": ["N Park Station"], "meta:updated": "2020-10-14T11:19:46.116538", "woe:hierarchy": {"continent": 24865672, "country": 23424977, "town": 0, "planet": 1, "county": 12590233, "suburb": 0, "state": 2347602, "region": 0, "localadmin": 0}, "woe:timezone_id": 56043661, "woe:hash": "9v6t0c5f9d4u", "woe:centroid": [-97.696198, 30.41609], "geom:latitude": 30.41609, "geom:longitude": -97.696198, "geom:hash": "9v6t0c5f9d4u", "woe:latitude": 30.41609, "geom:centroid": [-97.696198, 30.41609], "woe:longitude": -97.696198, "woe:repo": "woeplanet-poi-us", "geom:area": 0.0, "woe:scale": 19}}