{"type": "Feature", "id": 23530198, "properties": {"woe:id": 23530198, "woe:parent_id": 55969072, "woe:name": "Foothills Middle School", "woe:placetype": 20, "woe:placetype_name": "POI", "woe:lang": "ENG", "iso:country": "US", "meta:provider": ["geoplanet:7.3.1", "geoplanet:7.3.2", "geoplanet:7.4.0", "geoplanet:7.4.1", "geoplanet:7.5.1", "geoplanet:7.5.2", "geoplanet:7.6.0", "geoplanet:7.8.1", "geoplanet:7.9.0", "geoplanet:7.10.0", "geoplanet:8.0.0", "woeplanet:8.0.0"], "meta:indexed": "2020-08-20T20:18:21.542704", "meta:updated": "2020-08-22T02:57:28.556381", "woe:hierarchy": {"continent": 24865672, "country": 23424977, "town": 0, "planet": 1, "county": 12587688, "suburb": 0, "state": 2347563, "region": 0, "localadmin": 0}, "woe:timezone_id": 56043663, "woe:hash": "9qh46326qcbn", "woe:centroid": [-118.02549, 34.152771], "geom:latitude": 34.152771, "geom:longitude": -118.02549, "geom:hash": "9qh46326qcbn", "woe:latitude": 34.152771, "geom:centroid": [-118.02549, 34.152771], "woe:longitude": -118.02549, "woe:repo": "woeplanet-poi-us"}, "geometry": {"coordinates": [-118.02549, 34.152771], "type": "Point"}}