{"type": "Feature", "id": 56054147, "geometry": {"type": "Point", "coordinates": [-79.945068, 40.462269]}, "properties": {"woe:id": 56054147, "woe:parent_id": 23511273, "woe:name": "Clarion University-Pittsburgh", "woe:placetype": 20, "woe:placetype_name": "POI", "woe:lang": "ENG", "iso:country": "US", "meta:provider": ["geoplanet:7.3.1", "geoplanet:7.3.2", "geoplanet:7.4.0", "geoplanet:7.4.1", "geoplanet:7.5.1", "geoplanet:7.5.2", "geoplanet:7.6.0", "geoplanet:7.8.1", "geoplanet:7.9.0", "geoplanet:7.10.0", "geoplanet:8.0.0", "woeplanet:8.0.0"], "meta:indexed": "2020-08-20T20:19:17.601407", "meta:updated": "2020-10-14T11:19:56.643513", "woe:hierarchy": {"continent": 24865672, "country": 23424977, "town": 0, "planet": 1, "county": 12589729, "suburb": 0, "state": 2347597, "region": 0, "localadmin": 0}, "woe:timezone_id": 56043648, "woe:hash": "dppnhvcvbcss", "woe:centroid": [-79.945068, 40.462269], "geom:latitude": 40.462269, "geom:longitude": -79.945068, "geom:hash": "dppnhvcvbcss", "woe:latitude": 40.462269, "geom:centroid": [-79.945068, 40.462269], "woe:longitude": -79.945068, "woe:repo": "woeplanet-poi-us", "geom:area": 0.0, "woe:scale": 19}}