{"type": "Feature", "id": 23635957, "properties": {"woe:id": 23635957, "woe:parent_id": 2411703, "woe:name": "Patrick Elementary School", "woe:placetype": 20, "woe:placetype_name": "POI", "woe:lang": "ENG", "iso:country": "US", "meta:provider": ["geoplanet:7.3.1", "geoplanet:7.3.2", "geoplanet:7.4.0", "geoplanet:7.4.1", "geoplanet:7.5.1", "geoplanet:7.5.2", "geoplanet:7.6.0", "geoplanet:7.8.1", "geoplanet:7.9.0", "geoplanet:7.10.0", "geoplanet:8.0.0", "woeplanet:8.0.0"], "meta:indexed": "2020-08-20T20:18:56.901747", "woe:alias_ENG_V": ["Patrick Elementary"], "meta:updated": "2020-08-22T02:57:46.069268", "woe:hierarchy": {"continent": 24865672, "country": 23424977, "town": 0, "planet": 1, "county": 12589706, "suburb": 0, "state": 2347596, "region": 0, "localadmin": 0}, "woe:timezone_id": 56043663, "woe:hash": "9r83rsszc4ru", "woe:centroid": [-123.062271, 42.433289], "geom:latitude": 42.433289, "geom:longitude": -123.062271, "geom:hash": "9r83rsszc4ru", "woe:latitude": 42.433289, "geom:centroid": [-123.062271, 42.433289], "woe:longitude": -123.062271, "woe:repo": "woeplanet-poi-us"}, "geometry": {"coordinates": [-123.062271, 42.433289], "type": "Point"}}