{"type": "Feature", "id": 23595971, "properties": {"woe:id": 23595971, "woe:parent_id": 2419671, "woe:name": "Heidelberg High School", "woe:placetype": 20, "woe:placetype_name": "POI", "woe:lang": "ENG", "iso:country": "US", "meta:provider": ["geoplanet:7.3.1", "geoplanet:7.3.2", "geoplanet:7.4.0", "geoplanet:7.4.1", "geoplanet:7.5.1", "geoplanet:7.5.2", "geoplanet:7.6.0", "geoplanet:7.8.1", "geoplanet:7.9.0", "geoplanet:7.10.0", "geoplanet:8.0.0", "woeplanet:8.0.0"], "meta:indexed": "2020-08-20T20:18:43.371202", "woe:alias_ENG_V": ["Heidelberg Senior High School", "Heidelberg High", "Heidelberg Senior High", "Heidelberg HS", "Heidelberg Senior HS"], "meta:updated": "2020-08-22T02:58:48.132813", "woe:hierarchy": {"continent": 24865672, "country": 23424977, "town": 0, "planet": 1, "county": 12588914, "suburb": 0, "state": 2347583, "region": 0, "localadmin": 0}, "woe:timezone_id": 56043661, "woe:hash": "dj8tqyntnv85", "woe:centroid": [-88.991028, 31.894199], "geom:latitude": 31.894199, "geom:longitude": -88.991028, "geom:hash": "dj8tqyntnv85", "woe:latitude": 31.894199, "geom:centroid": [-88.991028, 31.894199], "woe:longitude": -88.991028, "woe:repo": "woeplanet-poi-us"}, "geometry": {"coordinates": [-88.991028, 31.894199], "type": "Point"}}