{"type": "Feature", "id": 23654289, "geometry": {"type": "Point", "coordinates": [-97.05072, 33.062462]}, "properties": {"woe:id": 23654289, "woe:parent_id": 55993777, "woe:name": "Prairie Trail Elementary School", "woe:placetype": 20, "woe:placetype_name": "POI", "woe:lang": "ENG", "iso:country": "US", "meta:provider": ["geoplanet:7.3.1", "geoplanet:7.3.2", "geoplanet:7.4.0", "geoplanet:7.4.1", "geoplanet:7.5.1", "geoplanet:7.5.2", "geoplanet:7.6.0", "geoplanet:7.8.1", "geoplanet:7.9.0", "geoplanet:7.10.0", "geoplanet:8.0.0", "woeplanet:8.0.0"], "meta:indexed": "2020-08-20T20:19:03.306727", "woe:alias_ENG_V": ["Prairie Trail Elementary"], "meta:updated": "2020-10-14T11:19:46.527378", "woe:hierarchy": {"continent": 24865672, "country": 23424977, "town": 0, "planet": 1, "county": 12590067, "suburb": 0, "state": 2347602, "region": 0, "localadmin": 0}, "woe:timezone_id": 56043661, "woe:hash": "9vfupdcff3dh", "woe:centroid": [-97.05072, 33.062462], "geom:latitude": 33.062462, "geom:longitude": -97.05072, "geom:hash": "9vfupdcff3dh", "woe:latitude": 33.062462, "geom:centroid": [-97.05072, 33.062462], "woe:longitude": -97.05072, "woe:repo": "woeplanet-poi-us", "geom:area": 0.0, "woe:scale": 19}}