{"type": "Feature", "id": 56053104, "properties": {"woe:id": 56053104, "woe:parent_id": 56019378, "woe:name": "Mti Business College of Stockton", "woe:placetype": 20, "woe:placetype_name": "POI", "woe:lang": "ENG", "iso:country": "US", "meta:provider": ["geoplanet:7.3.1", "geoplanet:7.3.2", "geoplanet:7.4.0", "geoplanet:7.4.1", "geoplanet:7.5.1", "geoplanet:7.5.2", "geoplanet:7.6.0", "geoplanet:7.8.1", "geoplanet:7.9.0", "geoplanet:7.10.0", "geoplanet:8.0.0", "woeplanet:8.0.0"], "meta:indexed": "2020-08-20T20:19:16.780987", "meta:updated": "2020-08-22T02:58:20.704136", "woe:hierarchy": {"continent": 24865672, "country": 23424977, "town": 0, "planet": 1, "county": 12587708, "suburb": 0, "state": 2347563, "region": 0, "localadmin": 0}, "woe:timezone_id": 56043663, "woe:hash": "9qc8px1dwrkk", "woe:centroid": [-121.308701, 38.007671], "geom:latitude": 38.007671, "geom:longitude": -121.308701, "geom:hash": "9qc8px1dwrkk", "woe:latitude": 38.007671, "geom:centroid": [-121.308701, 38.007671], "woe:longitude": -121.308701, "woe:repo": "woeplanet-poi-us"}, "geometry": {"coordinates": [-121.308701, 38.007671], "type": "Point"}}