{"type": "Feature", "id": 23649595, "properties": {"woe:id": 23649595, "woe:parent_id": 2464871, "woe:name": "Andrew Jackson Elementary School", "woe:placetype": 20, "woe:placetype_name": "POI", "woe:lang": "ENG", "iso:country": "US", "meta:provider": ["geoplanet:7.3.1", "geoplanet:7.3.2", "geoplanet:7.4.0", "geoplanet:7.4.1", "geoplanet:7.5.1", "geoplanet:7.5.2", "geoplanet:7.6.0", "geoplanet:7.8.1", "geoplanet:7.9.0", "geoplanet:7.10.0", "geoplanet:8.0.0", "woeplanet:8.0.0"], "meta:indexed": "2020-08-20T20:19:01.553409", "woe:alias_ENG_V": ["Andrew Jackson Elementary"], "meta:updated": "2020-08-22T02:57:48.112300", "woe:hierarchy": {"continent": 24865672, "country": 23424977, "town": 0, "planet": 1, "county": 12589930, "suburb": 0, "state": 2347601, "region": 0, "localadmin": 0}, "woe:timezone_id": 56043661, "woe:hash": "dn6qhgfh669w", "woe:centroid": [-86.624352, 36.232281], "geom:latitude": 36.232281, "geom:longitude": -86.624352, "geom:hash": "dn6qhgfh669w", "woe:latitude": 36.232281, "geom:centroid": [-86.624352, 36.232281], "woe:longitude": -86.624352, "woe:repo": "woeplanet-poi-us"}, "geometry": {"coordinates": [-86.624352, 36.232281], "type": "Point"}}