{"type": "Feature", "id": 23545909, "geometry": {"type": "Point", "coordinates": [-80.627968, 28.07877]}, "properties": {"woe:id": 23545909, "woe:parent_id": 2449097, "woe:name": "Florida Air Academy", "woe:placetype": 20, "woe:placetype_name": "POI", "woe:lang": "ENG", "iso:country": "US", "meta:provider": ["geoplanet:7.3.2", "geoplanet:7.4.0", "geoplanet:7.4.1", "geoplanet:7.5.1", "geoplanet:7.5.2", "geoplanet:7.6.0", "geoplanet:7.8.1", "geoplanet:7.9.0", "geoplanet:7.10.0", "geoplanet:8.0.0", "woeplanet:8.0.0"], "meta:indexed": "2020-08-20T22:02:08.024255", "meta:updated": "2020-10-14T11:20:24.707463", "woe:hierarchy": {"continent": 24865672, "country": 23424977, "town": 0, "planet": 1, "county": 12587807, "suburb": 0, "state": 2347568, "region": 0, "localadmin": 0}, "woe:timezone_id": 56043648, "woe:hash": "dhyxtr8d8nje", "woe:centroid": [-80.627968, 28.07877], "geom:latitude": 28.07877, "geom:longitude": -80.627968, "geom:hash": "dhyxtr8d8nje", "woe:latitude": 28.07877, "geom:centroid": [-80.627968, 28.07877], "woe:longitude": -80.627968, "woe:repo": "woeplanet-poi-us", "geom:area": 0.0, "woe:scale": 19}}