{"type": "Feature", "id": 23603247, "geometry": {"type": "Point", "coordinates": [-96.027153, 41.26984]}, "properties": {"woe:id": 23603247, "woe:parent_id": 55806353, "woe:name": "Creighton Preparatory School", "woe:placetype": 20, "woe:placetype_name": "POI", "woe:lang": "ENG", "iso:country": "US", "meta:provider": ["geoplanet:7.3.1", "geoplanet:7.3.2", "geoplanet:7.4.0", "geoplanet:7.4.1", "geoplanet:7.5.1", "geoplanet:7.5.2", "geoplanet:7.6.0", "geoplanet:7.8.1", "geoplanet:7.9.0", "geoplanet:7.10.0", "geoplanet:8.0.0", "woeplanet:8.0.0"], "meta:indexed": "2020-08-20T20:18:45.683611", "meta:updated": "2020-10-14T11:19:50.639471", "woe:hierarchy": {"continent": 24865672, "country": 23424977, "town": 0, "planet": 1, "county": 12589165, "suburb": 0, "state": 2347586, "region": 0, "localadmin": 0}, "woe:timezone_id": 56043661, "woe:hash": "9z7dybgnjpub", "woe:centroid": [-96.027153, 41.26984], "geom:latitude": 41.26984, "geom:longitude": -96.027153, "geom:hash": "9z7dybgnjpub", "woe:latitude": 41.26984, "geom:centroid": [-96.027153, 41.26984], "woe:longitude": -96.027153, "woe:repo": "woeplanet-poi-us", "geom:area": 0.0, "woe:scale": 19}}