{"type": "Feature", "id": 23551784, "geometry": {"type": "Point", "coordinates": [-84.635101, 33.901981]}, "properties": {"woe:id": 23551784, "woe:parent_id": 2443809, "woe:name": "Dowell Elementary School", "woe:placetype": 20, "woe:placetype_name": "POI", "woe:lang": "ENG", "iso:country": "US", "meta:provider": ["geoplanet:7.3.1", "geoplanet:7.3.2", "geoplanet:7.4.0", "geoplanet:7.4.1", "geoplanet:7.5.1", "geoplanet:7.5.2", "geoplanet:7.6.0", "geoplanet:7.8.1", "geoplanet:7.9.0", "geoplanet:7.10.0", "geoplanet:8.0.0", "woeplanet:8.0.0"], "meta:indexed": "2020-08-20T20:18:29.029879", "woe:alias_ENG_V": ["Dowell Elementary"], "meta:updated": "2020-10-14T11:20:25.343852", "woe:hierarchy": {"continent": 24865672, "country": 23424977, "town": 0, "planet": 1, "county": 12587902, "suburb": 0, "state": 2347569, "region": 0, "localadmin": 0}, "woe:timezone_id": 56043648, "woe:hash": "dn5bf5dt75q9", "woe:centroid": [-84.635101, 33.901981], "geom:latitude": 33.901981, "geom:longitude": -84.635101, "geom:hash": "dn5bf5dt75q9", "woe:latitude": 33.901981, "geom:centroid": [-84.635101, 33.901981], "woe:longitude": -84.635101, "woe:repo": "woeplanet-poi-us", "geom:area": 0.0, "woe:scale": 19}}