{"type": "Feature", "id": 23654670, "properties": {"woe:id": 23654670, "woe:parent_id": 2380332, "woe:name": "Scotsdale Elementary School", "woe:placetype": 20, "woe:placetype_name": "POI", "woe:lang": "ENG", "iso:country": "US", "meta:provider": ["geoplanet:7.3.1", "geoplanet:7.3.2", "geoplanet:7.4.0", "geoplanet:7.4.1", "geoplanet:7.5.1", "geoplanet:7.5.2", "geoplanet:7.6.0", "geoplanet:7.8.1", "geoplanet:7.9.0", "geoplanet:7.10.0", "geoplanet:8.0.0", "woeplanet:8.0.0"], "meta:indexed": "2020-08-20T20:19:03.513854", "woe:alias_ENG_V": ["Scottsdale Elementary School", "Scotsdale Elementary"], "meta:updated": "2020-08-22T02:57:49.131029", "woe:hierarchy": {"continent": 24865672, "country": 23424977, "town": 0, "planet": 1, "county": 12590076, "suburb": 0, "state": 2347602, "region": 0, "localadmin": 0}, "woe:timezone_id": 56043665, "woe:hash": "9tskgc9vbtc6", "woe:centroid": [-106.356216, 31.781719], "geom:latitude": 31.781719, "geom:longitude": -106.356216, "geom:hash": "9tskgc9vbtc6", "woe:latitude": 31.781719, "geom:centroid": [-106.356216, 31.781719], "woe:longitude": -106.356216, "woe:repo": "woeplanet-poi-us"}, "geometry": {"coordinates": [-106.356216, 31.781719], "type": "Point"}}