{"type": "Feature", "id": 23674341, "properties": {"woe:id": 23674341, "woe:parent_id": 2394869, "woe:name": "Saint Louis Catholic School", "woe:placetype": 20, "woe:placetype_name": "POI", "woe:lang": "ENG", "iso:country": "US", "meta:provider": ["geoplanet:7.4.0", "geoplanet:7.4.1", "geoplanet:7.5.1", "geoplanet:7.5.2", "geoplanet:7.6.0", "geoplanet:7.8.1", "geoplanet:7.9.0", "geoplanet:7.10.0", "geoplanet:8.0.0", "woeplanet:8.0.0"], "meta:indexed": "2020-08-20T23:55:48.623482", "meta:updated": "2020-08-22T02:58:17.882425", "woe:hierarchy": {"continent": 24865672, "country": 23424977, "town": 0, "planet": 1, "county": 12590564, "suburb": 0, "state": 2347608, "region": 0, "localadmin": 0}, "woe:timezone_id": 56043661, "woe:hash": "dpctfymwbq7r", "woe:centroid": [-87.762207, 44.640018], "geom:latitude": 44.640018, "geom:longitude": -87.762207, "geom:hash": "dpctfymwbq7r", "woe:latitude": 44.640018, "geom:centroid": [-87.762207, 44.640018], "woe:longitude": -87.762207, "woe:repo": "woeplanet-poi-us"}, "geometry": {"coordinates": [-87.762207, 44.640018], "type": "Point"}}