{"type": "Feature", "id": 23644088, "geometry": {"type": "Point", "coordinates": [-75.130379, 40.003399]}, "properties": {"woe:id": 23644088, "woe:parent_id": 29389131, "woe:name": "St Hugh School", "woe:placetype": 20, "woe:placetype_name": "POI", "woe:lang": "ENG", "iso:country": "US", "meta:provider": ["geoplanet:7.4.0", "geoplanet:7.4.1", "geoplanet:7.5.1", "geoplanet:7.5.2", "geoplanet:7.6.0", "geoplanet:7.8.1", "geoplanet:7.9.0", "geoplanet:7.10.0", "geoplanet:8.0.0", "woeplanet:8.0.0"], "meta:indexed": "2020-08-20T23:55:34.374794", "meta:updated": "2020-10-14T11:19:38.133688", "woe:hierarchy": {"continent": 24865672, "country": 23424977, "town": 0, "planet": 1, "county": 12589778, "suburb": 0, "state": 2347597, "region": 0, "localadmin": 0}, "woe:timezone_id": 56043648, "woe:hash": "dr4ed67sxq14", "woe:centroid": [-75.130379, 40.003399], "geom:latitude": 40.003399, "geom:longitude": -75.130379, "geom:hash": "dr4ed67sxq14", "woe:latitude": 40.003399, "geom:centroid": [-75.130379, 40.003399], "woe:longitude": -75.130379, "woe:repo": "woeplanet-poi-us", "geom:area": 0.0, "woe:scale": 19}}