{"type": "Feature", "id": 23512652, "properties": {"woe:id": 23512652, "woe:parent_id": 2388901, "woe:name": "Daleville High School", "woe:placetype": 20, "woe:placetype_name": "POI", "woe:lang": "ENG", "iso:country": "US", "meta:provider": ["geoplanet:7.3.1", "geoplanet:7.3.2", "geoplanet:7.4.0", "geoplanet:7.4.1", "geoplanet:7.5.1", "geoplanet:7.5.2", "geoplanet:7.6.0", "geoplanet:7.8.1", "geoplanet:7.9.0", "geoplanet:7.10.0", "geoplanet:8.0.0", "woeplanet:8.0.0"], "meta:indexed": "2020-08-20T20:18:17.135235", "woe:alias_ENG_V": ["Daleville Senior High School", "Daleville High", "Daleville Senior High", "Daleville HS", "Daleville Senior HS"], "meta:updated": "2020-08-22T02:58:45.843517", "woe:hierarchy": {"continent": 24865672, "country": 23424977, "town": 0, "planet": 1, "county": 12587509, "suburb": 0, "state": 2347559, "region": 0, "localadmin": 0}, "woe:timezone_id": 56043661, "woe:hash": "dje41tg2g0w4", "woe:centroid": [-85.710732, 31.32078], "geom:latitude": 31.32078, "geom:longitude": -85.710732, "geom:hash": "dje41tg2g0w4", "woe:latitude": 31.32078, "geom:centroid": [-85.710732, 31.32078], "woe:longitude": -85.710732, "woe:repo": "woeplanet-poi-us"}, "geometry": {"coordinates": [-85.710732, 31.32078], "type": "Point"}}