{"type": "Feature", "id": 23566821, "properties": {"woe:id": 23566821, "woe:parent_id": 2422616, "woe:name": "John Wood Elementary School", "woe:placetype": 20, "woe:placetype_name": "POI", "woe:lang": "ENG", "iso:country": "US", "meta:provider": ["geoplanet:7.3.1", "geoplanet:7.3.2", "geoplanet:7.4.0", "geoplanet:7.4.1", "geoplanet:7.5.1", "geoplanet:7.5.2", "geoplanet:7.6.0", "geoplanet:7.8.1", "geoplanet:7.9.0", "geoplanet:7.10.0", "geoplanet:8.0.0", "woeplanet:8.0.0"], "meta:indexed": "2020-08-20T20:18:34.191330", "woe:alias_ENG_V": ["John Wood Elementary"], "meta:updated": "2020-08-22T02:57:35.711505", "woe:hierarchy": {"continent": 24865672, "country": 23424977, "town": 0, "planet": 1, "county": 12588225, "suburb": 0, "state": 2347573, "region": 0, "localadmin": 0}, "woe:timezone_id": 56043656, "woe:hash": "dp3gyrbfk2tf", "woe:centroid": [-87.263184, 41.483391], "geom:latitude": 41.483391, "geom:longitude": -87.263184, "geom:hash": "dp3gyrbfk2tf", "woe:latitude": 41.483391, "geom:centroid": [-87.263184, 41.483391], "woe:longitude": -87.263184, "woe:repo": "woeplanet-poi-us"}, "geometry": {"coordinates": [-87.263184, 41.483391], "type": "Point"}}