{"type": "Feature", "id": 23650770, "properties": {"woe:id": 23650770, "woe:parent_id": 2416378, "woe:name": "Halls Elementary School", "woe:placetype": 20, "woe:placetype_name": "POI", "woe:lang": "ENG", "iso:country": "US", "meta:provider": ["geoplanet:7.3.1", "geoplanet:7.3.2", "geoplanet:7.4.0", "geoplanet:7.4.1", "geoplanet:7.5.1", "geoplanet:7.5.2", "geoplanet:7.6.0", "geoplanet:7.8.1", "geoplanet:7.9.0", "geoplanet:7.10.0", "geoplanet:8.0.0", "woeplanet:8.0.0"], "meta:indexed": "2020-08-20T20:19:01.913794", "woe:alias_ENG_V": ["Halls Elementary"], "meta:updated": "2020-08-22T02:57:48.320764", "woe:hierarchy": {"continent": 24865672, "country": 23424977, "town": 0, "planet": 1, "county": 12589960, "suburb": 0, "state": 2347601, "region": 0, "localadmin": 0}, "woe:timezone_id": 56043661, "woe:hash": "dn2kjs4tuq86", "woe:centroid": [-89.403122, 35.88237], "geom:latitude": 35.88237, "geom:longitude": -89.403122, "geom:hash": "dn2kjs4tuq86", "woe:latitude": 35.88237, "geom:centroid": [-89.403122, 35.88237], "woe:longitude": -89.403122, "woe:repo": "woeplanet-poi-us"}, "geometry": {"coordinates": [-89.403122, 35.88237], "type": "Point"}}