{"type": "Feature", "id": 23630759, "properties": {"woe:id": 23630759, "woe:parent_id": 55806759, "woe:name": "Longfellow Elementary School", "woe:placetype": 20, "woe:placetype_name": "POI", "woe:lang": "ENG", "iso:country": "US", "meta:provider": ["geoplanet:7.3.1", "geoplanet:7.3.2", "geoplanet:7.4.0", "geoplanet:7.4.1", "geoplanet:7.5.1", "geoplanet:7.5.2", "geoplanet:7.6.0", "geoplanet:7.8.1", "geoplanet:7.9.0", "geoplanet:7.10.0", "geoplanet:8.0.0", "woeplanet:8.0.0"], "meta:indexed": "2020-08-20T20:18:54.822086", "woe:alias_ENG_V": ["Longfellow Elementary"], "meta:updated": "2020-08-22T02:57:45.255322", "woe:hierarchy": {"continent": 24865672, "country": 23424977, "town": 0, "planet": 1, "county": 12589574, "suburb": 0, "state": 2347594, "region": 0, "localadmin": 0}, "woe:timezone_id": 56043648, "woe:hash": "dpkt1yprku1u", "woe:centroid": [-83.584808, 41.694382], "geom:latitude": 41.694382, "geom:longitude": -83.584808, "geom:hash": "dpkt1yprku1u", "woe:latitude": 41.694382, "geom:centroid": [-83.584808, 41.694382], "woe:longitude": -83.584808, "woe:repo": "woeplanet-poi-us"}, "geometry": {"coordinates": [-83.584808, 41.694382], "type": "Point"}}