{"type": "Feature", "id": 23542778, "geometry": {"type": "Point", "coordinates": [-73.225357, 41.238731]}, "properties": {"woe:id": 23542778, "woe:parent_id": 2441550, "woe:name": "Saint Theresas School", "woe:placetype": 20, "woe:placetype_name": "POI", "woe:lang": "ENG", "iso:country": "US", "meta:provider": ["geoplanet:7.4.0", "geoplanet:7.4.1", "geoplanet:7.5.1", "geoplanet:7.5.2", "geoplanet:7.6.0", "geoplanet:7.8.1", "geoplanet:7.9.0", "geoplanet:7.10.0", "geoplanet:8.0.0", "woeplanet:8.0.0"], "meta:indexed": "2020-08-20T23:54:49.911397", "meta:updated": "2020-10-14T11:20:24.259919", "woe:alias_ENG_V": ["St Theresa School"], "woe:hierarchy": {"continent": 24865672, "country": 23424977, "town": 0, "planet": 1, "county": 12587791, "suburb": 0, "state": 2347565, "region": 0, "localadmin": 0}, "woe:timezone_id": 56043648, "woe:hash": "dr7fteqcj88k", "woe:centroid": [-73.225357, 41.238731], "geom:latitude": 41.238731, "geom:longitude": -73.225357, "geom:hash": "dr7fteqcj88k", "woe:latitude": 41.238731, "geom:centroid": [-73.225357, 41.238731], "woe:longitude": -73.225357, "woe:repo": "woeplanet-poi-us", "geom:area": 0.0, "woe:scale": 19}}