{"type": "Feature", "id": 23596571, "properties": {"woe:id": 23596571, "woe:parent_id": 2378315, "woe:name": "Charleston High School", "woe:placetype": 20, "woe:placetype_name": "POI", "woe:lang": "ENG", "iso:country": "US", "meta:provider": ["geoplanet:7.3.1", "geoplanet:7.3.2", "geoplanet:7.4.0", "geoplanet:7.4.1", "geoplanet:7.5.1", "geoplanet:7.5.2", "geoplanet:7.6.0", "geoplanet:7.8.1", "geoplanet:7.9.0", "geoplanet:7.10.0", "geoplanet:8.0.0", "woeplanet:8.0.0"], "meta:indexed": "2020-08-20T20:18:43.545785", "woe:alias_ENG_V": ["Charleston Senior High School", "Charleston High", "Charleston Senior High", "Charleston HS", "Charleston Senior HS"], "meta:updated": "2020-08-22T02:58:48.159353", "woe:hierarchy": {"continent": 24865672, "country": 23424977, "town": 0, "planet": 1, "county": 12588951, "suburb": 0, "state": 2347583, "region": 0, "localadmin": 0}, "woe:timezone_id": 56043661, "woe:hash": "9ypcqz5kuqw0", "woe:centroid": [-90.050278, 34.009029], "geom:latitude": 34.009029, "geom:longitude": -90.050278, "geom:hash": "9ypcqz5kuqw0", "woe:latitude": 34.009029, "geom:centroid": [-90.050278, 34.009029], "woe:longitude": -90.050278, "woe:repo": "woeplanet-poi-us"}, "geometry": {"coordinates": [-90.050278, 34.009029], "type": "Point"}}