{"type": "Feature", "id": 23632824, "properties": {"woe:id": 23632824, "woe:parent_id": 56022333, "woe:name": "St Joseph Elementary School", "woe:placetype": 20, "woe:placetype_name": "POI", "woe:lang": "ENG", "iso:country": "US", "meta:provider": ["geoplanet:7.3.1", "geoplanet:7.3.2", "geoplanet:7.4.0", "geoplanet:7.4.1", "geoplanet:7.5.1", "geoplanet:7.5.2", "geoplanet:7.6.0", "geoplanet:7.8.1", "geoplanet:7.9.0", "geoplanet:7.10.0", "geoplanet:8.0.0", "woeplanet:8.0.0"], "meta:indexed": "2020-08-20T20:18:55.783352", "woe:alias_ENG_V": ["St Joseph Elementary"], "meta:updated": "2020-08-22T02:57:45.598582", "woe:hierarchy": {"continent": 24865672, "country": 23424977, "town": 0, "planet": 1, "county": 12589605, "suburb": 0, "state": 2347594, "region": 0, "localadmin": 0}, "woe:timezone_id": 56043648, "woe:hash": "dpnn9c1b17mz", "woe:centroid": [-81.483131, 40.52309], "geom:latitude": 40.52309, "geom:longitude": -81.483131, "geom:hash": "dpnn9c1b17mz", "woe:latitude": 40.52309, "geom:centroid": [-81.483131, 40.52309], "woe:longitude": -81.483131, "woe:repo": "woeplanet-poi-us"}, "geometry": {"coordinates": [-81.483131, 40.52309], "type": "Point"}}