{"type": "Feature", "id": 56064014, "properties": {"woe:id": 56064014, "woe:parent_id": 2521596, "woe:name": "Kent Road Station", "woe:placetype": 20, "woe:placetype_name": "POI", "woe:lang": "ENG", "iso:country": "US", "meta:provider": ["geoplanet:7.3.1", "geoplanet:7.3.2", "geoplanet:7.4.0", "geoplanet:7.4.1", "geoplanet:7.5.1", "geoplanet:7.5.2", "geoplanet:7.6.0", "geoplanet:7.8.1", "geoplanet:7.9.0", "geoplanet:7.10.0", "geoplanet:8.0.0", "woeplanet:8.0.0"], "meta:indexed": "2020-08-20T20:19:20.937133", "woe:alias_ENG_V": ["Kent Road Metro Station", "Metro Kent Road Station", "Metro-North-Kent Road"], "meta:updated": "2020-08-22T02:58:23.058061", "woe:hierarchy": {"continent": 24865672, "country": 23424977, "town": 0, "planet": 1, "county": 12587791, "suburb": 0, "state": 2347565, "region": 0, "localadmin": 0}, "woe:timezone_id": 56043648, "woe:hash": "dr7f1m9hn59s", "woe:centroid": [-73.419998, 41.163731], "geom:latitude": 41.163731, "geom:longitude": -73.419998, "geom:hash": "dr7f1m9hn59s", "woe:latitude": 41.163731, "geom:centroid": [-73.419998, 41.163731], "woe:longitude": -73.419998, "woe:repo": "woeplanet-poi-us"}, "geometry": {"coordinates": [-73.419998, 41.163731], "type": "Point"}}