{"type": "Feature", "id": 23654328, "geometry": {"type": "Point", "coordinates": [-97.024757, 33.04755]}, "properties": {"woe:id": 23654328, "woe:parent_id": 55993991, "woe:name": "Blossom Valley Academy", "woe:placetype": 20, "woe:placetype_name": "POI", "woe:lang": "ENG", "iso:country": "US", "meta:provider": ["geoplanet:7.3.2", "geoplanet:7.4.0", "geoplanet:7.4.1", "geoplanet:7.5.1", "geoplanet:7.5.2", "geoplanet:7.6.0", "geoplanet:7.8.1", "geoplanet:7.9.0", "geoplanet:7.10.0", "geoplanet:8.0.0", "woeplanet:8.0.0"], "meta:indexed": "2020-08-20T22:02:52.841248", "meta:updated": "2020-10-14T11:19:40.176770", "woe:hierarchy": {"continent": 24865672, "country": 23424977, "town": 0, "planet": 1, "county": 12590067, "suburb": 0, "state": 2347602, "region": 0, "localadmin": 0}, "woe:timezone_id": 56043661, "woe:hash": "9vgh00hezmcd", "woe:centroid": [-97.024757, 33.04755], "geom:latitude": 33.04755, "geom:longitude": -97.024757, "geom:hash": "9vgh00hezmcd", "woe:latitude": 33.04755, "geom:centroid": [-97.024757, 33.04755], "woe:longitude": -97.024757, "woe:repo": "woeplanet-poi-us", "geom:area": 0.0, "woe:scale": 19}}