{"type": "Feature", "id": 23661467, "geometry": {"type": "Point", "coordinates": [-97.413811, 30.59411]}, "properties": {"woe:id": 23661467, "woe:parent_id": 2504318, "woe:name": "Taylor High School", "woe:placetype": 20, "woe:placetype_name": "POI", "woe:lang": "ENG", "iso:country": "US", "meta:provider": ["geoplanet:7.3.1", "geoplanet:7.3.2", "geoplanet:7.4.0", "geoplanet:7.4.1", "geoplanet:7.5.1", "geoplanet:7.5.2", "geoplanet:7.6.0", "geoplanet:7.8.1", "geoplanet:7.9.0", "geoplanet:7.10.0", "geoplanet:8.0.0", "woeplanet:8.0.0"], "meta:indexed": "2020-08-20T20:19:06.979646", "woe:alias_ENG_V": ["Taylor Senior High School", "Taylor High", "Taylor Senior High", "Taylor HS", "Taylor Senior HS"], "meta:updated": "2020-10-14T11:19:44.833774", "woe:hierarchy": {"continent": 24865672, "country": 23424977, "town": 0, "planet": 1, "county": 12590252, "suburb": 0, "state": 2347602, "region": 0, "localadmin": 0}, "woe:timezone_id": 56043661, "woe:hash": "9v6wp33rtemy", "woe:centroid": [-97.413811, 30.59411], "geom:latitude": 30.59411, "geom:longitude": -97.413811, "geom:hash": "9v6wp33rtemy", "woe:latitude": 30.59411, "geom:centroid": [-97.413811, 30.59411], "woe:longitude": -97.413811, "woe:repo": "woeplanet-poi-us", "geom:area": 0.0, "woe:scale": 19}}