{"type": "Feature", "id": 23593512, "geometry": {"type": "Point", "coordinates": [-93.25296, 44.870571]}, "properties": {"woe:id": 23593512, "woe:parent_id": 2480793, "woe:name": "Centennial Elementary School", "woe:placetype": 20, "woe:placetype_name": "POI", "woe:lang": "ENG", "iso:country": "US", "meta:provider": ["geoplanet:7.3.1", "geoplanet:7.3.2", "geoplanet:7.4.0", "geoplanet:7.4.1", "geoplanet:7.5.1", "geoplanet:7.5.2", "geoplanet:7.6.0", "geoplanet:7.8.1", "geoplanet:7.9.0", "geoplanet:7.10.0", "geoplanet:8.0.0", "woeplanet:8.0.0"], "meta:indexed": "2020-08-20T20:18:42.488908", "woe:alias_ENG_V": ["Centennial Elementary"], "meta:updated": "2020-10-14T11:20:23.581578", "woe:hierarchy": {"continent": 24865672, "country": 23424977, "town": 0, "planet": 1, "county": 12588823, "suburb": 0, "state": 2347582, "region": 0, "localadmin": 0}, "woe:timezone_id": 56043661, "woe:hash": "9zvxmbrq089j", "woe:centroid": [-93.25296, 44.870571], "geom:latitude": 44.870571, "geom:longitude": -93.25296, "geom:hash": "9zvxmbrq089j", "woe:latitude": 44.870571, "geom:centroid": [-93.25296, 44.870571], "woe:longitude": -93.25296, "woe:repo": "woeplanet-poi-us", "geom:area": 0.0, "woe:scale": 19}}