{"type": "Feature", "id": 23579073, "geometry": {"type": "Point", "coordinates": [-67.887398, 44.53904]}, "properties": {"woe:id": 23579073, "woe:parent_id": 2450874, "woe:name": "Milbridge Elementary School", "woe:placetype": 20, "woe:placetype_name": "POI", "woe:lang": "ENG", "iso:country": "US", "meta:provider": ["geoplanet:7.3.1", "geoplanet:7.3.2", "geoplanet:7.4.0", "geoplanet:7.4.1", "geoplanet:7.5.1", "geoplanet:7.5.2", "geoplanet:7.6.0", "geoplanet:7.8.1", "geoplanet:7.9.0", "geoplanet:7.10.0", "geoplanet:8.0.0", "woeplanet:8.0.0"], "meta:indexed": "2020-08-20T20:18:38.291721", "woe:alias_ENG_V": ["Milbridge Elementary"], "meta:updated": "2020-10-14T11:20:28.391613", "woe:hierarchy": {"continent": 24865672, "country": 23424977, "town": 0, "planet": 1, "county": 12588674, "suburb": 0, "state": 2347578, "region": 0, "localadmin": 0}, "woe:timezone_id": 56043648, "woe:hash": "drztrhjfsyz4", "woe:centroid": [-67.887398, 44.53904], "geom:latitude": 44.53904, "geom:longitude": -67.887398, "geom:hash": "drztrhjfsyz4", "woe:latitude": 44.53904, "geom:centroid": [-67.887398, 44.53904], "woe:longitude": -67.887398, "woe:repo": "woeplanet-poi-us", "geom:area": 0.0, "woe:scale": 19}}