{"type": "Feature", "id": 56053515, "properties": {"woe:id": 56053515, "woe:parent_id": 2441464, "woe:name": "Univ of Southern Miss Gulf Coast", "woe:placetype": 20, "woe:placetype_name": "POI", "woe:lang": "ENG", "iso:country": "US", "meta:provider": ["geoplanet:7.3.1", "geoplanet:7.3.2", "geoplanet:7.4.0", "geoplanet:7.4.1", "geoplanet:7.5.1", "geoplanet:7.5.2", "geoplanet:7.6.0", "geoplanet:7.8.1", "geoplanet:7.9.0", "geoplanet:7.10.0", "geoplanet:8.0.0", "woeplanet:8.0.0"], "meta:indexed": "2020-08-20T20:19:17.112376", "meta:updated": "2020-08-22T02:58:20.887841", "woe:hierarchy": {"continent": 24865672, "country": 23424977, "town": 0, "planet": 1, "county": 12588907, "suburb": 0, "state": 2347583, "region": 0, "localadmin": 0}, "woe:timezone_id": 56043661, "woe:hash": "dj2sethgcf8f", "woe:centroid": [-89.136467, 30.350389], "geom:latitude": 30.350389, "geom:longitude": -89.136467, "geom:hash": "dj2sethgcf8f", "woe:latitude": 30.350389, "geom:centroid": [-89.136467, 30.350389], "woe:longitude": -89.136467, "woe:repo": "woeplanet-poi-us"}, "geometry": {"coordinates": [-89.136467, 30.350389], "type": "Point"}}