{"type": "Feature", "id": 23531457, "geometry": {"type": "Point", "coordinates": [-118.004181, 33.908401]}, "properties": {"woe:id": 23531457, "woe:parent_id": 55969693, "woe:name": "La Mirada High School", "woe:placetype": 20, "woe:placetype_name": "POI", "woe:lang": "ENG", "iso:country": "US", "meta:provider": ["geoplanet:7.3.2", "geoplanet:7.4.0", "geoplanet:7.4.1", "geoplanet:7.5.1", "geoplanet:7.5.2", "geoplanet:7.6.0", "geoplanet:7.8.1", "geoplanet:7.9.0", "geoplanet:7.10.0", "geoplanet:8.0.0", "woeplanet:8.0.0"], "meta:indexed": "2020-08-20T22:02:02.483313", "woe:alias_ENG_V": ["La Mirada Senior High School", "La Mirada High", "La Mirada Senior High", "La Mirada HS", "La Mirada Senior HS"], "meta:updated": "2020-10-14T11:20:27.701270", "woe:hierarchy": {"continent": 24865672, "country": 23424977, "town": 0, "planet": 1, "county": 12587688, "suburb": 0, "state": 2347563, "region": 0, "localadmin": 0}, "woe:timezone_id": 56043663, "woe:hash": "9qh0fszfz214", "woe:centroid": [-118.004181, 33.908401], "geom:latitude": 33.908401, "geom:longitude": -118.004181, "geom:hash": "9qh0fszfz214", "woe:latitude": 33.908401, "geom:centroid": [-118.004181, 33.908401], "woe:longitude": -118.004181, "woe:repo": "woeplanet-poi-us", "geom:area": 0.0, "woe:scale": 19}}