{"type": "Feature", "id": 24701306, "properties": {"woe:id": 24701306, "woe:parent_id": 2351905, "woe:name": "The Hoosac Tunnel", "woe:placetype": 20, "woe:placetype_name": "POI", "woe:lang": "ENG", "iso:country": "US", "meta:provider": ["geoplanet:7.3.1", "geoplanet:7.3.2", "geoplanet:7.4.0", "geoplanet:7.4.1", "geoplanet:7.5.1", "geoplanet:7.5.2", "geoplanet:7.6.0", "geoplanet:7.8.1", "geoplanet:7.9.0", "geoplanet:7.10.0", "geoplanet:8.0.0", "woeplanet:8.0.0"], "meta:indexed": "2020-08-20T20:19:14.550400", "meta:updated": "2020-08-22T02:58:19.531257", "woe:hierarchy": {"continent": 24865672, "country": 23424977, "town": 0, "planet": 1, "county": 12588701, "suburb": 0, "state": 2347580, "region": 0, "localadmin": 0}, "woe:timezone_id": 56043648, "woe:hash": "drs48m5vwe4h", "woe:centroid": [-73.108582, 42.65538], "geom:latitude": 42.65538, "geom:longitude": -73.108582, "geom:hash": "drs48m5vwe4h", "woe:latitude": 42.65538, "geom:centroid": [-73.108582, 42.65538], "woe:longitude": -73.108582, "woe:repo": "woeplanet-poi-us"}, "geometry": {"coordinates": [-73.108582, 42.65538], "type": "Point"}}