{"type": "Feature", "id": 23575435, "geometry": {"type": "Point", "coordinates": [-92.585518, 30.191891]}, "properties": {"woe:id": 23575435, "woe:parent_id": 2449638, "woe:name": "Mermentau Elementary School", "woe:placetype": 20, "woe:placetype_name": "POI", "woe:lang": "ENG", "iso:country": "US", "meta:provider": ["geoplanet:7.3.1", "geoplanet:7.3.2", "geoplanet:7.4.0", "geoplanet:7.4.1", "geoplanet:7.5.1", "geoplanet:7.5.2", "geoplanet:7.6.0", "geoplanet:7.8.1", "geoplanet:7.9.0", "geoplanet:7.10.0", "geoplanet:8.0.0", "woeplanet:8.0.0"], "meta:indexed": "2020-08-20T20:18:37.163600", "woe:alias_ENG_V": ["Mermentau Elementary"], "meta:updated": "2020-10-14T11:20:07.601399", "woe:hierarchy": {"continent": 24865672, "country": 23424977, "town": 0, "planet": 1, "county": 12588596, "suburb": 0, "state": 2347577, "region": 0, "localadmin": 0}, "woe:timezone_id": 56043661, "woe:hash": "9vq5v0m2906j", "woe:centroid": [-92.585518, 30.191891], "geom:latitude": 30.191891, "geom:longitude": -92.585518, "geom:hash": "9vq5v0m2906j", "woe:latitude": 30.191891, "geom:centroid": [-92.585518, 30.191891], "woe:longitude": -92.585518, "woe:repo": "woeplanet-poi-us", "geom:area": 0.0, "woe:scale": 19}}