{"type": "Feature", "id": 23607816, "properties": {"woe:id": 23607816, "woe:parent_id": 2415946, "woe:name": "Paul Vi High School", "woe:placetype": 20, "woe:placetype_name": "POI", "woe:lang": "ENG", "iso:country": "US", "meta:provider": ["geoplanet:7.3.1", "geoplanet:7.3.2", "geoplanet:7.4.0", "geoplanet:7.4.1", "geoplanet:7.5.1", "geoplanet:7.5.2", "geoplanet:7.6.0", "geoplanet:7.8.1", "geoplanet:7.9.0", "geoplanet:7.10.0", "geoplanet:8.0.0", "woeplanet:8.0.0"], "meta:indexed": "2020-08-20T20:18:46.915010", "woe:alias_ENG_V": ["Paul Vi Senior High School", "Paul Vi High", "Paul Vi Senior High", "Paul Vi HS", "Paul Vi Senior HS"], "meta:updated": "2020-08-22T02:58:48.516194", "woe:hierarchy": {"continent": 24865672, "country": 23424977, "town": 0, "planet": 1, "county": 12589261, "suburb": 0, "state": 2347589, "region": 0, "localadmin": 0}, "woe:timezone_id": 56043648, "woe:hash": "dr4dgzj394rt", "woe:centroid": [-75.062317, 39.897121], "geom:latitude": 39.897121, "geom:longitude": -75.062317, "geom:hash": "dr4dgzj394rt", "woe:latitude": 39.897121, "geom:centroid": [-75.062317, 39.897121], "woe:longitude": -75.062317, "woe:repo": "woeplanet-poi-us"}, "geometry": {"coordinates": [-75.062317, 39.897121], "type": "Point"}}