{"type": "Feature", "id": 23675571, "geometry": {"type": "Point", "coordinates": [-89.582771, 44.541149]}, "properties": {"woe:id": 23675571, "woe:parent_id": 2499752, "woe:name": "Stevens Point Area High School", "woe:placetype": 20, "woe:placetype_name": "POI", "woe:lang": "ENG", "iso:country": "US", "meta:provider": ["geoplanet:7.3.1", "geoplanet:7.3.2", "geoplanet:7.4.0", "geoplanet:7.4.1", "geoplanet:7.5.1", "geoplanet:7.5.2", "geoplanet:7.6.0", "geoplanet:7.8.1", "geoplanet:7.9.0", "geoplanet:7.10.0", "geoplanet:8.0.0", "woeplanet:8.0.0"], "meta:indexed": "2020-08-20T20:19:11.571353", "woe:alias_ENG_V": ["Stevens Point Area Senior High School", "Stevens Point Area High", "Stevens Point Area Senior High", "Stevens Point Area HS", "Stevens Point Area Senior HS", "Stevens Point Sr High", "Stevens Point Sr High School", "Stevens Point Sr HS", "Stevens Point Sr Senior High", "Stevens Point Sr Senior High School", "Stevens Point Sr Senior HS"], "meta:updated": "2020-10-14T11:19:37.140087", "woe:hierarchy": {"continent": 24865672, "country": 23424977, "town": 0, "planet": 1, "county": 12590583, "suburb": 0, "state": 2347608, "region": 0, "localadmin": 0}, "woe:timezone_id": 56043661, "woe:hash": "dpbm3kryfpur", "woe:centroid": [-89.582771, 44.541149], "geom:latitude": 44.541149, "geom:longitude": -89.582771, "geom:hash": "dpbm3kryfpur", "woe:latitude": 44.541149, "geom:centroid": [-89.582771, 44.541149], "woe:longitude": -89.582771, "woe:repo": "woeplanet-poi-us", "geom:area": 0.0, "woe:scale": 19}}