{"type": "Feature", "id": 23524034, "geometry": {"type": "Point", "coordinates": [-121.392601, 38.726429]}, "properties": {"woe:id": 23524034, "woe:parent_id": 2355002, "woe:name": "Mcclellan High School", "woe:placetype": 20, "woe:placetype_name": "POI", "woe:lang": "ENG", "iso:country": "US", "meta:provider": ["geoplanet:7.3.2", "geoplanet:7.4.0", "geoplanet:7.4.1", "geoplanet:7.5.1", "geoplanet:7.5.2", "geoplanet:7.6.0", "geoplanet:7.8.1", "geoplanet:7.9.0", "geoplanet:7.10.0", "geoplanet:8.0.0", "woeplanet:8.0.0"], "meta:indexed": "2020-08-20T22:01:59.346001", "woe:alias_ENG_V": ["Mcclellan Senior High School", "Mcclellan High", "Mcclellan Senior High", "Mcclellan HS", "Mcclellan Senior HS"], "meta:updated": "2020-10-14T11:20:08.970894", "woe:hierarchy": {"continent": 24865672, "country": 23424977, "town": 0, "planet": 1, "county": 12587703, "suburb": 0, "state": 2347563, "region": 0, "localadmin": 0}, "woe:timezone_id": 56043663, "woe:hash": "9qcsm9utg3s5", "woe:centroid": [-121.392601, 38.726429], "geom:latitude": 38.726429, "geom:longitude": -121.392601, "geom:hash": "9qcsm9utg3s5", "woe:latitude": 38.726429, "geom:centroid": [-121.392601, 38.726429], "woe:longitude": -121.392601, "woe:repo": "woeplanet-poi-us", "geom:area": 0.0, "woe:scale": 19}}