{"type": "Feature", "id": 28349390, "geometry": {"type": "Point", "coordinates": [-80.410004, 25.7013]}, "properties": {"woe:id": 28349390, "woe:parent_id": 2431425, "woe:name": "Morales Discount Pharmacy", "woe:placetype": 20, "woe:placetype_name": "POI", "woe:lang": "ENG", "iso:country": "US", "meta:provider": ["geoplanet:7.3.1", "geoplanet:7.3.2", "geoplanet:7.4.0", "geoplanet:7.4.1", "geoplanet:7.5.1", "geoplanet:7.5.2", "geoplanet:7.6.0", "geoplanet:7.8.1", "geoplanet:7.9.0", "geoplanet:7.10.0", "geoplanet:8.0.0", "woeplanet:8.0.0"], "meta:indexed": "2020-08-20T20:19:15.631590", "meta:updated": "2020-10-14T11:19:26.530671", "woe:hierarchy": {"continent": 24865672, "country": 23424977, "town": 0, "planet": 1, "county": 12587815, "suburb": 0, "state": 2347568, "region": 0, "localadmin": 0}, "woe:timezone_id": 56043648, "woe:hash": "dhwf4nz0zje6", "woe:centroid": [-80.410004, 25.7013], "geom:latitude": 25.7013, "geom:longitude": -80.410004, "geom:hash": "dhwf4nz0zje6", "woe:latitude": 25.7013, "geom:centroid": [-80.410004, 25.7013], "woe:longitude": -80.410004, "woe:repo": "woeplanet-poi-us", "geom:area": 0.0, "woe:scale": 19}}