{"type": "Feature", "id": 23613062, "geometry": {"type": "Point", "coordinates": [-73.850601, 40.83947]}, "properties": {"woe:id": 23613062, "woe:parent_id": 2518043, "woe:name": "Sacred Heart Private School", "woe:placetype": 20, "woe:placetype_name": "POI", "woe:lang": "ENG", "iso:country": "US", "meta:provider": ["geoplanet:7.3.1", "geoplanet:7.3.2", "geoplanet:7.4.0", "geoplanet:7.4.1", "geoplanet:7.5.1", "geoplanet:7.5.2", "geoplanet:7.6.0", "geoplanet:7.8.1", "geoplanet:7.9.0", "geoplanet:7.10.0", "geoplanet:8.0.0", "woeplanet:8.0.0"], "meta:indexed": "2020-08-20T20:18:48.670544", "meta:updated": "2020-10-14T11:19:40.134681", "woe:hierarchy": {"continent": 24865672, "country": 23424977, "town": 0, "planet": 1, "county": 12589314, "suburb": 0, "state": 2347591, "region": 0, "localadmin": 0}, "woe:timezone_id": 56043648, "woe:hash": "dr72r6xehkbx", "woe:centroid": [-73.850601, 40.83947], "geom:latitude": 40.83947, "geom:longitude": -73.850601, "geom:hash": "dr72r6xehkbx", "woe:latitude": 40.83947, "geom:centroid": [-73.850601, 40.83947], "woe:longitude": -73.850601, "woe:repo": "woeplanet-poi-us", "geom:area": 0.0, "woe:scale": 19}}