{"type": "Feature", "id": 23577668, "properties": {"woe:id": 23577668, "woe:parent_id": 2402410, "woe:name": "Farmerville High School", "woe:placetype": 20, "woe:placetype_name": "POI", "woe:lang": "ENG", "iso:country": "US", "meta:provider": ["geoplanet:7.3.1", "geoplanet:7.3.2", "geoplanet:7.4.0", "geoplanet:7.4.1", "geoplanet:7.5.1", "geoplanet:7.5.2", "geoplanet:7.6.0", "geoplanet:7.8.1", "geoplanet:7.9.0", "geoplanet:7.10.0", "geoplanet:8.0.0", "woeplanet:8.0.0"], "meta:indexed": "2020-08-20T20:18:37.967778", "woe:alias_ENG_V": ["Farmerville Senior High School", "Farmerville High", "Farmerville Senior High", "Farmerville HS", "Farmerville Senior HS"], "meta:updated": "2020-08-22T02:58:47.661542", "woe:hierarchy": {"continent": 24865672, "country": 23424977, "town": 0, "planet": 1, "county": 12588651, "suburb": 0, "state": 2347577, "region": 0, "localadmin": 0}, "woe:timezone_id": 56043661, "woe:hash": "9vy63pp2d63w", "woe:centroid": [-92.406937, 32.777809], "geom:latitude": 32.777809, "geom:longitude": -92.406937, "geom:hash": "9vy63pp2d63w", "woe:latitude": 32.777809, "geom:centroid": [-92.406937, 32.777809], "woe:longitude": -92.406937, "woe:repo": "woeplanet-poi-us"}, "geometry": {"coordinates": [-92.406937, 32.777809], "type": "Point"}}