{"type": "Feature", "id": 23514213, "properties": {"woe:id": 23514213, "woe:parent_id": 55860384, "woe:name": "Lagoon Park Station", "woe:placetype": 20, "woe:placetype_name": "POI", "woe:lang": "ENG", "iso:country": "US", "meta:provider": ["geoplanet:7.3.1", "geoplanet:7.3.2", "geoplanet:7.4.0", "geoplanet:7.4.1", "geoplanet:7.5.1", "geoplanet:7.5.2", "geoplanet:7.6.0", "geoplanet:7.8.1", "geoplanet:7.9.0", "geoplanet:7.10.0", "geoplanet:8.0.0", "woeplanet:8.0.0"], "meta:indexed": "2020-08-20T20:18:17.674731", "meta:updated": "2020-08-22T02:57:26.354435", "woe:hierarchy": {"continent": 24865672, "country": 23424977, "town": 0, "planet": 1, "county": 12587537, "suburb": 0, "state": 2347559, "region": 0, "localadmin": 0}, "woe:timezone_id": 56043661, "woe:hash": "djf8q4pc8pqj", "woe:centroid": [-86.210052, 32.398979], "geom:latitude": 32.398979, "geom:longitude": -86.210052, "geom:hash": "djf8q4pc8pqj", "woe:latitude": 32.398979, "geom:centroid": [-86.210052, 32.398979], "woe:longitude": -86.210052, "woe:repo": "woeplanet-poi-us"}, "geometry": {"coordinates": [-86.210052, 32.398979], "type": "Point"}}