{"type": "Feature", "id": 23667532, "geometry": {"type": "Point", "coordinates": [-77.411057, 37.53516]}, "properties": {"woe:id": 23667532, "woe:parent_id": 55861418, "woe:name": "George Mason Elementary School", "woe:placetype": 20, "woe:placetype_name": "POI", "woe:lang": "ENG", "iso:country": "US", "meta:provider": ["geoplanet:7.3.1", "geoplanet:7.3.2", "geoplanet:7.4.0", "geoplanet:7.4.1", "geoplanet:7.5.1", "geoplanet:7.5.2", "geoplanet:7.6.0", "geoplanet:7.8.1", "geoplanet:7.9.0", "geoplanet:7.10.0", "geoplanet:8.0.0", "woeplanet:8.0.0"], "meta:indexed": "2020-08-20T20:19:08.804344", "woe:alias_ENG_V": ["George Mason Elementary"], "meta:updated": "2020-10-14T11:19:51.176064", "woe:hierarchy": {"continent": 24865672, "country": 23424977, "town": 0, "planet": 1, "county": 12590410, "suburb": 0, "state": 2347605, "region": 0, "localadmin": 0}, "woe:timezone_id": 56043648, "woe:hash": "dq8vw3nfpsuq", "woe:centroid": [-77.411057, 37.53516], "geom:latitude": 37.53516, "geom:longitude": -77.411057, "geom:hash": "dq8vw3nfpsuq", "woe:latitude": 37.53516, "geom:centroid": [-77.411057, 37.53516], "woe:longitude": -77.411057, "woe:repo": "woeplanet-poi-us", "geom:area": 0.0, "woe:scale": 19}}