{"type": "Feature", "id": 23588834, "properties": {"woe:id": 23588834, "woe:parent_id": 56022140, "woe:name": "Warren Woods Middle School", "woe:placetype": 20, "woe:placetype_name": "POI", "woe:lang": "ENG", "iso:country": "US", "meta:provider": ["geoplanet:7.3.1", "geoplanet:7.3.2", "geoplanet:7.4.0", "geoplanet:7.4.1", "geoplanet:7.5.1", "geoplanet:7.5.2", "geoplanet:7.6.0", "geoplanet:7.8.1", "geoplanet:7.9.0", "geoplanet:7.10.0", "geoplanet:8.0.0", "woeplanet:8.0.0"], "meta:indexed": "2020-08-20T20:18:40.774470", "meta:updated": "2020-08-22T02:57:39.189350", "woe:hierarchy": {"continent": 24865672, "country": 23424977, "town": 0, "planet": 1, "county": 12588763, "suburb": 0, "state": 2347581, "region": 0, "localadmin": 0}, "woe:timezone_id": 56043658, "woe:hash": "dpsczd32cgnd", "woe:centroid": [-82.988922, 42.507622], "geom:latitude": 42.507622, "geom:longitude": -82.988922, "geom:hash": "dpsczd32cgnd", "woe:latitude": 42.507622, "geom:centroid": [-82.988922, 42.507622], "woe:longitude": -82.988922, "woe:repo": "woeplanet-poi-us"}, "geometry": {"coordinates": [-82.988922, 42.507622], "type": "Point"}}