{"type": "Feature", "id": 23558127, "geometry": {"type": "Point", "coordinates": [-87.624634, 41.871361]}, "properties": {"woe:id": 23558127, "woe:parent_id": 2441891, "woe:name": "East-west University", "woe:placetype": 20, "woe:placetype_name": "POI", "woe:lang": "ENG", "iso:country": "US", "meta:provider": ["geoplanet:7.3.1", "geoplanet:7.3.2", "geoplanet:7.4.0", "geoplanet:7.4.1", "geoplanet:7.5.1", "geoplanet:7.5.2", "geoplanet:7.6.0", "geoplanet:7.8.1", "geoplanet:7.9.0", "geoplanet:7.10.0", "geoplanet:8.0.0", "woeplanet:8.0.0"], "meta:indexed": "2020-08-20T20:18:30.645416", "woe:alias_ENG_V": ["E-west University"], "meta:updated": "2020-10-14T11:20:07.530484", "woe:hierarchy": {"continent": 24865672, "country": 23424977, "town": 0, "planet": 1, "county": 12588093, "suburb": 0, "state": 2347572, "region": 0, "localadmin": 0}, "woe:timezone_id": 56043661, "woe:hash": "dp3wnn3wq53m", "woe:centroid": [-87.624634, 41.871361], "geom:latitude": 41.871361, "geom:longitude": -87.624634, "geom:hash": "dp3wnn3wq53m", "woe:latitude": 41.871361, "geom:centroid": [-87.624634, 41.871361], "woe:longitude": -87.624634, "woe:repo": "woeplanet-poi-us", "geom:area": 0.0, "woe:scale": 19}}