{"type": "Feature", "id": 23638492, "geometry": {"type": "Point", "coordinates": [-79.963303, 40.560749]}, "properties": {"woe:id": 23638492, "woe:parent_id": 2353504, "woe:name": "St Ursula Elementary School", "woe:placetype": 20, "woe:placetype_name": "POI", "woe:lang": "ENG", "iso:country": "US", "meta:provider": ["geoplanet:7.3.1", "geoplanet:7.3.2", "geoplanet:7.4.0", "geoplanet:7.4.1", "geoplanet:7.5.1", "geoplanet:7.5.2", "geoplanet:7.6.0", "geoplanet:7.8.1", "geoplanet:7.9.0", "geoplanet:7.10.0", "geoplanet:8.0.0", "woeplanet:8.0.0"], "meta:indexed": "2020-08-20T20:18:57.873138", "woe:alias_ENG_V": ["St Ursula Elementary"], "meta:updated": "2020-10-14T11:19:26.552227", "woe:hierarchy": {"continent": 24865672, "country": 23424977, "town": 0, "planet": 1, "county": 12589729, "suburb": 0, "state": 2347597, "region": 0, "localadmin": 0}, "woe:timezone_id": 56043648, "woe:hash": "dppnsru7rzxs", "woe:centroid": [-79.963303, 40.560749], "geom:latitude": 40.560749, "geom:longitude": -79.963303, "geom:hash": "dppnsru7rzxs", "woe:latitude": 40.560749, "geom:centroid": [-79.963303, 40.560749], "woe:longitude": -79.963303, "woe:repo": "woeplanet-poi-us", "geom:area": 0.0, "woe:scale": 19}}