{"type": "Feature", "id": 23647680, "geometry": {"type": "Point", "coordinates": [-80.866074, 33.5159]}, "properties": {"woe:id": 23647680, "woe:parent_id": 2520611, "woe:name": "St Andrews Methodist Kindergarten", "woe:placetype": 20, "woe:placetype_name": "POI", "woe:lang": "ENG", "iso:country": "US", "meta:provider": ["geoplanet:7.3.1", "geoplanet:7.3.2", "geoplanet:7.4.0", "geoplanet:7.4.1", "geoplanet:7.5.1", "geoplanet:7.5.2", "geoplanet:7.6.0", "geoplanet:7.8.1", "geoplanet:7.9.0", "geoplanet:7.10.0", "geoplanet:8.0.0", "woeplanet:8.0.0"], "meta:indexed": "2020-08-20T20:19:00.882228", "meta:updated": "2020-10-14T11:19:38.031647", "woe:hierarchy": {"continent": 24865672, "country": 23424977, "town": 0, "planet": 1, "county": 12589837, "suburb": 0, "state": 2347599, "region": 0, "localadmin": 0}, "woe:timezone_id": 56043648, "woe:hash": "djyqxv7h7bsg", "woe:centroid": [-80.866074, 33.5159], "geom:latitude": 33.5159, "geom:longitude": -80.866074, "geom:hash": "djyqxv7h7bsg", "woe:latitude": 33.5159, "geom:centroid": [-80.866074, 33.5159], "woe:longitude": -80.866074, "woe:repo": "woeplanet-poi-us", "geom:area": 0.0, "woe:scale": 19}}