{"type": "Feature", "id": 23517210, "properties": {"woe:id": 23517210, "woe:parent_id": 55805880, "woe:name": "Jefferson Park Elementary School", "woe:placetype": 20, "woe:placetype_name": "POI", "woe:lang": "ENG", "iso:country": "US", "meta:provider": ["geoplanet:7.3.1", "geoplanet:7.3.2", "geoplanet:7.4.0", "geoplanet:7.4.1", "geoplanet:7.5.1", "geoplanet:7.5.2", "geoplanet:7.6.0", "geoplanet:7.8.1", "geoplanet:7.9.0", "geoplanet:7.10.0", "geoplanet:8.0.0", "woeplanet:8.0.0"], "meta:indexed": "2020-08-20T20:18:18.694142", "woe:alias_ENG_V": ["Jefferson Park Elementary"], "meta:updated": "2020-08-22T02:57:26.797780", "woe:hierarchy": {"continent": 24865672, "country": 23424977, "town": 0, "planet": 1, "county": 12587590, "suburb": 0, "state": 2347561, "region": 0, "localadmin": 0}, "woe:timezone_id": 56043666, "woe:hash": "9t9p7q6gr9k8", "woe:centroid": [-110.946823, 32.246811], "geom:latitude": 32.246811, "geom:longitude": -110.946823, "geom:hash": "9t9p7q6gr9k8", "woe:latitude": 32.246811, "geom:centroid": [-110.946823, 32.246811], "woe:longitude": -110.946823, "woe:repo": "woeplanet-poi-us"}, "geometry": {"coordinates": [-110.946823, 32.246811], "type": "Point"}}