{"type": "Feature", "id": 23577254, "properties": {"woe:id": 23577254, "woe:parent_id": 2388643, "woe:name": "N. P. Trist Middle School", "woe:placetype": 20, "woe:placetype_name": "POI", "woe:lang": "ENG", "iso:country": "US", "meta:provider": ["geoplanet:7.4.0", "geoplanet:7.4.1", "geoplanet:7.5.1", "geoplanet:7.5.2", "geoplanet:7.6.0", "geoplanet:7.8.1", "geoplanet:7.9.0", "geoplanet:7.10.0", "geoplanet:8.0.0", "woeplanet:8.0.0"], "meta:indexed": "2020-08-20T23:55:05.657172", "meta:updated": "2020-08-22T02:57:37.391158", "woe:alias_ENG_V": ["Np Trist Middle"], "woe:hierarchy": {"continent": 24865672, "country": 23424977, "town": 0, "planet": 1, "county": 12588639, "suburb": 0, "state": 2347577, "region": 0, "localadmin": 0}, "woe:timezone_id": 56043661, "woe:hash": "dj2438q1eezx", "woe:centroid": [-89.925682, 29.92841], "geom:latitude": 29.92841, "geom:longitude": -89.925682, "geom:hash": "dj2438q1eezx", "woe:latitude": 29.92841, "geom:centroid": [-89.925682, 29.92841], "woe:longitude": -89.925682, "woe:repo": "woeplanet-poi-us"}, "geometry": {"coordinates": [-89.925682, 29.92841], "type": "Point"}}