{"type": "Feature", "id": 23652913, "properties": {"woe:id": 23652913, "woe:parent_id": 2382871, "woe:name": "Coleman High School", "woe:placetype": 20, "woe:placetype_name": "POI", "woe:lang": "ENG", "iso:country": "US", "meta:provider": ["geoplanet:7.3.1", "geoplanet:7.3.2", "geoplanet:7.4.0", "geoplanet:7.4.1", "geoplanet:7.5.1", "geoplanet:7.5.2", "geoplanet:7.6.0", "geoplanet:7.8.1", "geoplanet:7.9.0", "geoplanet:7.10.0", "geoplanet:8.0.0", "woeplanet:8.0.0"], "meta:indexed": "2020-08-20T20:19:02.615932", "woe:alias_ENG_V": ["Coleman Senior High School", "Coleman High", "Coleman Senior High", "Coleman HS", "Coleman Senior HS"], "meta:updated": "2020-08-22T02:58:49.777903", "woe:hierarchy": {"continent": 24865672, "country": 23424977, "town": 0, "planet": 1, "county": 12590048, "suburb": 0, "state": 2347602, "region": 0, "localadmin": 0}, "woe:timezone_id": 56043661, "woe:hash": "9v9kcx1w60uq", "woe:centroid": [-99.424118, 31.811991], "geom:latitude": 31.811991, "geom:longitude": -99.424118, "geom:hash": "9v9kcx1w60uq", "woe:latitude": 31.811991, "geom:centroid": [-99.424118, 31.811991], "woe:longitude": -99.424118, "woe:repo": "woeplanet-poi-us"}, "geometry": {"coordinates": [-99.424118, 31.811991], "type": "Point"}}