{"type": "Feature", "id": 23526390, "properties": {"woe:id": 23526390, "woe:parent_id": 2521129, "woe:name": "Willow Glen Elementary School", "woe:placetype": 20, "woe:placetype_name": "POI", "woe:lang": "ENG", "iso:country": "US", "meta:provider": ["geoplanet:7.3.2", "geoplanet:7.4.0", "geoplanet:7.4.1", "geoplanet:7.5.1", "geoplanet:7.5.2", "geoplanet:7.6.0", "geoplanet:7.8.1", "geoplanet:7.9.0", "geoplanet:7.10.0", "geoplanet:8.0.0", "woeplanet:8.0.0"], "meta:indexed": "2020-08-20T22:02:00.355917", "woe:alias_ENG_V": ["Willow Glen Elementary"], "meta:updated": "2020-08-22T02:57:28.090407", "woe:hierarchy": {"continent": 24865672, "country": 23424977, "town": 0, "planet": 1, "county": 12587712, "suburb": 0, "state": 2347563, "region": 0, "localadmin": 0}, "woe:timezone_id": 56043663, "woe:hash": "9q9k4nv6z472", "woe:centroid": [-121.896782, 37.303188], "geom:latitude": 37.303188, "geom:longitude": -121.896782, "geom:hash": "9q9k4nv6z472", "woe:latitude": 37.303188, "geom:centroid": [-121.896782, 37.303188], "woe:longitude": -121.896782, "woe:repo": "woeplanet-poi-us"}, "geometry": {"coordinates": [-121.896782, 37.303188], "type": "Point"}}