{"type": "Feature", "id": 23599746, "geometry": {"type": "Point", "coordinates": [-90.592712, 38.59547]}, "properties": {"woe:id": 23599746, "woe:parent_id": 2398817, "woe:name": "Ellisville Elementary School", "woe:placetype": 20, "woe:placetype_name": "POI", "woe:lang": "ENG", "iso:country": "US", "meta:provider": ["geoplanet:7.3.1", "geoplanet:7.3.2", "geoplanet:7.4.0", "geoplanet:7.4.1", "geoplanet:7.5.1", "geoplanet:7.5.2", "geoplanet:7.6.0", "geoplanet:7.8.1", "geoplanet:7.9.0", "geoplanet:7.10.0", "geoplanet:8.0.0", "woeplanet:8.0.0"], "meta:indexed": "2020-08-20T20:18:44.789551", "woe:alias_ENG_V": ["Ellisville Elementary"], "meta:updated": "2020-10-14T11:20:28.158250", "woe:hierarchy": {"continent": 24865672, "country": 23424977, "town": 0, "planet": 1, "county": 12589066, "suburb": 0, "state": 2347584, "region": 0, "localadmin": 0}, "woe:timezone_id": 56043661, "woe:hash": "9yzedd06uv1f", "woe:centroid": [-90.592712, 38.59547], "geom:latitude": 38.59547, "geom:longitude": -90.592712, "geom:hash": "9yzedd06uv1f", "woe:latitude": 38.59547, "geom:centroid": [-90.592712, 38.59547], "woe:longitude": -90.592712, "woe:repo": "woeplanet-poi-us", "geom:area": 0.0, "woe:scale": 19}}