{"type": "Feature", "id": 23632740, "properties": {"woe:id": 23632740, "woe:parent_id": 2417475, "woe:name": "Bascom Elementary School", "woe:placetype": 20, "woe:placetype_name": "POI", "woe:lang": "ENG", "iso:country": "US", "meta:provider": ["geoplanet:7.3.1", "geoplanet:7.3.2", "geoplanet:7.4.0", "geoplanet:7.4.1", "geoplanet:7.5.1", "geoplanet:7.5.2", "geoplanet:7.6.0", "geoplanet:7.8.1", "geoplanet:7.9.0", "geoplanet:7.10.0", "geoplanet:8.0.0", "woeplanet:8.0.0"], "meta:indexed": "2020-08-20T20:18:55.751811", "woe:alias_ENG_V": ["Bascom Elementary"], "meta:updated": "2020-08-22T02:57:45.587420", "woe:hierarchy": {"continent": 24865672, "country": 23424977, "town": 0, "planet": 1, "county": 12589604, "suburb": 0, "state": 2347594, "region": 0, "localadmin": 0}, "woe:timezone_id": 56043648, "woe:hash": "dpq6xwp5w7hv", "woe:centroid": [-80.87146, 41.25428], "geom:latitude": 41.25428, "geom:longitude": -80.87146, "geom:hash": "dpq6xwp5w7hv", "woe:latitude": 41.25428, "geom:centroid": [-80.87146, 41.25428], "woe:longitude": -80.87146, "woe:repo": "woeplanet-poi-us"}, "geometry": {"coordinates": [-80.87146, 41.25428], "type": "Point"}}