{"type": "Feature", "id": 23671850, "geometry": {"type": "Point", "coordinates": [-77.95182, 39.473591]}, "properties": {"woe:id": 23671850, "woe:parent_id": 2446393, "woe:name": "Martinsburg North Middle School", "woe:placetype": 20, "woe:placetype_name": "POI", "woe:lang": "ENG", "iso:country": "US", "meta:provider": ["geoplanet:7.3.1", "geoplanet:7.3.2", "geoplanet:7.4.0", "geoplanet:7.4.1", "geoplanet:7.5.1", "geoplanet:7.5.2", "geoplanet:7.6.0", "geoplanet:7.8.1", "geoplanet:7.9.0", "geoplanet:7.10.0", "geoplanet:8.0.0", "woeplanet:8.0.0"], "meta:indexed": "2020-08-20T20:19:09.988947", "meta:updated": "2020-10-14T11:19:53.368085", "woe:hierarchy": {"continent": 24865672, "country": 23424977, "town": 0, "planet": 1, "county": 12590480, "suburb": 0, "state": 2347607, "region": 0, "localadmin": 0}, "woe:timezone_id": 56043648, "woe:hash": "dr08d1vnqfwn", "woe:centroid": [-77.95182, 39.473591], "geom:latitude": 39.473591, "geom:longitude": -77.95182, "geom:hash": "dr08d1vnqfwn", "woe:latitude": 39.473591, "geom:centroid": [-77.95182, 39.473591], "woe:longitude": -77.95182, "woe:repo": "woeplanet-poi-us", "geom:area": 0.0, "woe:scale": 19}}