{"type": "Feature", "id": 23683657, "properties": {"woe:id": 23683657, "woe:parent_id": 55861014, "woe:name": "Allen Metro Station", "woe:placetype": 20, "woe:placetype_name": "POI", "woe:lang": "ENG", "iso:country": "US", "meta:provider": ["geoplanet:7.3.1", "geoplanet:7.3.2", "geoplanet:7.4.0", "geoplanet:7.4.1", "geoplanet:7.5.1", "geoplanet:7.5.2", "geoplanet:7.6.0", "geoplanet:7.8.1", "geoplanet:7.9.0", "geoplanet:7.10.0", "geoplanet:8.0.0", "woeplanet:8.0.0"], "meta:indexed": "2020-08-20T20:19:20.429885", "meta:updated": "2020-08-22T02:58:22.787803", "woe:hierarchy": {"continent": 24865672, "country": 23424977, "town": 0, "planet": 1, "county": 12587688, "suburb": 0, "state": 2347563, "region": 0, "localadmin": 0}, "woe:timezone_id": 56043663, "woe:hash": "9qh42326x9hc", "woe:centroid": [-118.113342, 34.152809], "geom:latitude": 34.152809, "geom:longitude": -118.113342, "geom:hash": "9qh42326x9hc", "woe:latitude": 34.152809, "geom:centroid": [-118.113342, 34.152809], "woe:longitude": -118.113342, "woe:repo": "woeplanet-poi-us"}, "geometry": {"coordinates": [-118.113342, 34.152809], "type": "Point"}}