{"type": "Feature", "id": 23516460, "geometry": {"type": "Point", "coordinates": [-112.740211, 33.96653]}, "properties": {"woe:id": 23516460, "woe:parent_id": 2520114, "woe:name": "Gospel Outreach Christian School", "woe:placetype": 20, "woe:placetype_name": "POI", "woe:lang": "ENG", "iso:country": "US", "meta:provider": ["geoplanet:7.3.1", "geoplanet:7.3.2", "geoplanet:7.4.0", "geoplanet:7.4.1", "geoplanet:7.5.1", "geoplanet:7.5.2", "geoplanet:7.6.0", "geoplanet:7.8.1", "geoplanet:7.9.0", "geoplanet:7.10.0", "geoplanet:8.0.0", "woeplanet:8.0.0"], "meta:indexed": "2020-08-20T20:18:18.449687", "meta:updated": "2020-10-14T11:20:29.372909", "woe:hierarchy": {"continent": 24865672, "country": 23424977, "town": 0, "planet": 1, "county": 12587587, "suburb": 0, "state": 2347561, "region": 0, "localadmin": 0}, "woe:timezone_id": 56043666, "woe:hash": "9qpc4x3j6sje", "woe:centroid": [-112.740211, 33.96653], "geom:latitude": 33.96653, "geom:longitude": -112.740211, "geom:hash": "9qpc4x3j6sje", "woe:latitude": 33.96653, "geom:centroid": [-112.740211, 33.96653], "woe:longitude": -112.740211, "woe:repo": "woeplanet-poi-us", "geom:area": 0.0, "woe:scale": 19}}