{"type": "Feature", "id": 23661240, "geometry": {"type": "Point", "coordinates": [-96.980049, 28.841459]}, "properties": {"woe:id": 23661240, "woe:parent_id": 2512082, "woe:name": "Rowland Elementary School", "woe:placetype": 20, "woe:placetype_name": "POI", "woe:lang": "ENG", "iso:country": "US", "meta:provider": ["geoplanet:7.3.1", "geoplanet:7.3.2", "geoplanet:7.4.0", "geoplanet:7.4.1", "geoplanet:7.5.1", "geoplanet:7.5.2", "geoplanet:7.6.0", "geoplanet:7.8.1", "geoplanet:7.9.0", "geoplanet:7.10.0", "geoplanet:8.0.0", "woeplanet:8.0.0"], "meta:indexed": "2020-08-20T20:19:06.856887", "woe:alias_ENG_V": ["Rowland Elementary"], "meta:updated": "2020-10-14T11:19:42.616562", "woe:hierarchy": {"continent": 24865672, "country": 23424977, "town": 0, "planet": 1, "county": 12590241, "suburb": 0, "state": 2347602, "region": 0, "localadmin": 0}, "woe:timezone_id": 56043661, "woe:hash": "9v5h14mm9jdh", "woe:centroid": [-96.980049, 28.841459], "geom:latitude": 28.841459, "geom:longitude": -96.980049, "geom:hash": "9v5h14mm9jdh", "woe:latitude": 28.841459, "geom:centroid": [-96.980049, 28.841459], "woe:longitude": -96.980049, "woe:repo": "woeplanet-poi-us", "geom:area": 0.0, "woe:scale": 19}}