{"type": "Feature", "id": 23677466, "properties": {"woe:id": 23677466, "woe:parent_id": 2492421, "woe:name": "Holy Name School", "woe:placetype": 20, "woe:placetype_name": "POI", "woe:lang": "ENG", "iso:country": "US", "meta:provider": ["geoplanet:7.3.1", "geoplanet:7.3.2", "geoplanet:7.4.0", "geoplanet:7.4.1", "geoplanet:7.5.1", "geoplanet:7.5.2", "geoplanet:7.6.0", "geoplanet:7.8.1", "geoplanet:7.9.0", "geoplanet:7.10.0", "geoplanet:8.0.0", "woeplanet:8.0.0"], "meta:indexed": "2020-08-20T20:19:12.233285", "meta:updated": "2020-08-22T02:58:18.492603", "woe:hierarchy": {"continent": 24865672, "country": 23424977, "town": 0, "planet": 1, "county": 12590622, "suburb": 0, "state": 2347609, "region": 0, "localadmin": 0}, "woe:timezone_id": 56043665, "woe:hash": "9xgyy6bh1y2z", "woe:centroid": [-106.951828, 44.796101], "geom:latitude": 44.796101, "geom:longitude": -106.951828, "geom:hash": "9xgyy6bh1y2z", "woe:latitude": 44.796101, "geom:centroid": [-106.951828, 44.796101], "woe:longitude": -106.951828, "woe:repo": "woeplanet-poi-us"}, "geometry": {"coordinates": [-106.951828, 44.796101], "type": "Point"}}