{"type": "Feature", "id": 23652481, "properties": {"woe:id": 23652481, "woe:parent_id": 2406968, "woe:name": "New Hope Academy", "woe:placetype": 20, "woe:placetype_name": "POI", "woe:lang": "ENG", "iso:country": "US", "meta:provider": ["geoplanet:7.3.2", "geoplanet:7.4.0", "geoplanet:7.4.1", "geoplanet:7.5.1", "geoplanet:7.5.2", "geoplanet:7.6.0", "geoplanet:7.8.1", "geoplanet:7.9.0", "geoplanet:7.10.0", "geoplanet:8.0.0", "woeplanet:8.0.0"], "meta:indexed": "2020-08-20T22:02:51.803132", "meta:updated": "2020-08-22T02:57:48.606009", "woe:hierarchy": {"continent": 24865672, "country": 23424977, "town": 0, "planet": 1, "county": 12590005, "suburb": 0, "state": 2347601, "region": 0, "localadmin": 0}, "woe:timezone_id": 56043661, "woe:hash": "dn6hqfhf71q4", "woe:centroid": [-86.884209, 35.9147], "geom:latitude": 35.9147, "geom:longitude": -86.884209, "geom:hash": "dn6hqfhf71q4", "woe:latitude": 35.9147, "geom:centroid": [-86.884209, 35.9147], "woe:longitude": -86.884209, "woe:repo": "woeplanet-poi-us"}, "geometry": {"coordinates": [-86.884209, 35.9147], "type": "Point"}}