{"type": "Feature", "id": 23588326, "geometry": {"type": "Point", "coordinates": [-85.62558, 43.013321]}, "properties": {"woe:id": 23588326, "woe:parent_id": 55859456, "woe:name": "Northeast Station", "woe:placetype": 20, "woe:placetype_name": "POI", "woe:lang": "ENG", "iso:country": "US", "meta:provider": ["geoplanet:7.3.1", "geoplanet:7.3.2", "geoplanet:7.4.0", "geoplanet:7.4.1", "geoplanet:7.5.1", "geoplanet:7.5.2", "geoplanet:7.6.0", "geoplanet:7.8.1", "geoplanet:7.9.0", "geoplanet:7.10.0", "geoplanet:8.0.0", "woeplanet:8.0.0"], "meta:indexed": "2020-08-20T20:18:40.580753", "woe:alias_ENG_V": ["NE Station"], "meta:updated": "2020-10-14T11:20:14.261722", "woe:hierarchy": {"continent": 24865672, "country": 23424977, "town": 0, "planet": 1, "county": 12588754, "suburb": 0, "state": 2347581, "region": 0, "localadmin": 0}, "woe:timezone_id": 56043658, "woe:hash": "dpehew36g25y", "woe:centroid": [-85.62558, 43.013321], "geom:latitude": 43.013321, "geom:longitude": -85.62558, "geom:hash": "dpehew36g25y", "woe:latitude": 43.013321, "geom:centroid": [-85.62558, 43.013321], "woe:longitude": -85.62558, "woe:repo": "woeplanet-poi-us", "geom:area": 0.0, "woe:scale": 19}}