{"type": "Feature", "id": 56054816, "geometry": {"type": "Point", "coordinates": [-119.821609, 36.292419]}, "properties": {"woe:id": 56054816, "woe:parent_id": 2438231, "woe:name": "West Hills College", "woe:placetype": 20, "woe:placetype_name": "POI", "woe:lang": "ENG", "iso:country": "US", "meta:provider": ["geoplanet:7.3.1", "geoplanet:7.3.2", "geoplanet:7.4.0", "geoplanet:7.4.1", "geoplanet:7.5.1", "geoplanet:7.5.2", "geoplanet:7.6.0", "geoplanet:7.8.1", "geoplanet:7.9.0", "geoplanet:7.10.0", "geoplanet:8.0.0", "woeplanet:8.0.0"], "meta:indexed": "2020-08-20T20:19:18.142987", "meta:updated": "2020-10-14T11:19:56.009563", "woe:hierarchy": {"continent": 24865672, "country": 23424977, "town": 0, "planet": 1, "county": 12587685, "suburb": 0, "state": 2347563, "region": 0, "localadmin": 0}, "woe:timezone_id": 56043663, "woe:hash": "9q6y3quddjk8", "woe:centroid": [-119.821609, 36.292419], "geom:latitude": 36.292419, "geom:longitude": -119.821609, "geom:hash": "9q6y3quddjk8", "woe:latitude": 36.292419, "geom:centroid": [-119.821609, 36.292419], "woe:longitude": -119.821609, "woe:repo": "woeplanet-poi-us", "geom:area": 0.0, "woe:scale": 19}}