{"type": "Feature", "id": 23570365, "geometry": {"type": "Point", "coordinates": [-93.694672, 41.611259]}, "properties": {"woe:id": 23570365, "woe:parent_id": 55858745, "woe:name": "Mount Olive Lutheran School", "woe:placetype": 20, "woe:placetype_name": "POI", "woe:lang": "ENG", "iso:country": "US", "meta:provider": ["geoplanet:7.3.1", "geoplanet:7.3.2", "geoplanet:7.4.0", "geoplanet:7.4.1", "geoplanet:7.5.1", "geoplanet:7.5.2", "geoplanet:7.6.0", "geoplanet:7.8.1", "geoplanet:7.9.0", "geoplanet:7.10.0", "geoplanet:8.0.0", "woeplanet:8.0.0"], "meta:indexed": "2020-08-20T20:18:35.470901", "woe:alias_ENG_V": ["Mt Olive Lutheran School"], "meta:updated": "2020-10-14T11:20:18.201130", "woe:hierarchy": {"continent": 24865672, "country": 23424977, "town": 0, "planet": 1, "county": 12588348, "suburb": 0, "state": 2347574, "region": 0, "localadmin": 0}, "woe:timezone_id": 56043661, "woe:hash": "9zmkezje5uuu", "woe:centroid": [-93.694672, 41.611259], "geom:latitude": 41.611259, "geom:longitude": -93.694672, "geom:hash": "9zmkezje5uuu", "woe:latitude": 41.611259, "geom:centroid": [-93.694672, 41.611259], "woe:longitude": -93.694672, "woe:repo": "woeplanet-poi-us", "geom:area": 0.0, "woe:scale": 19}}