{"type": "Feature", "id": 23581125, "properties": {"woe:id": 23581125, "woe:parent_id": 2428995, "woe:name": "Francis T. Evans Elementary School", "woe:placetype": 20, "woe:placetype_name": "POI", "woe:lang": "ENG", "iso:country": "US", "meta:provider": ["geoplanet:7.3.2", "geoplanet:7.4.0", "geoplanet:7.4.1", "geoplanet:7.5.1", "geoplanet:7.5.2", "geoplanet:7.6.0", "geoplanet:7.8.1", "geoplanet:7.9.0", "geoplanet:7.10.0", "geoplanet:8.0.0", "woeplanet:8.0.0"], "meta:indexed": "2020-08-20T22:02:23.235916", "woe:alias_ENG_V": ["Francis T. Evans Elementary"], "meta:updated": "2020-08-22T02:57:38.009198", "woe:hierarchy": {"continent": 24865672, "country": 23424977, "town": 0, "planet": 1, "county": 12588692, "suburb": 0, "state": 2347579, "region": 0, "localadmin": 0}, "woe:timezone_id": 56043648, "woe:hash": "dqckdk37ppgm", "woe:centroid": [-76.891289, 38.783669], "geom:latitude": 38.783669, "geom:longitude": -76.891289, "geom:hash": "dqckdk37ppgm", "woe:latitude": 38.783669, "geom:centroid": [-76.891289, 38.783669], "woe:longitude": -76.891289, "woe:repo": "woeplanet-poi-us"}, "geometry": {"coordinates": [-76.891289, 38.783669], "type": "Point"}}