{"type": "Feature", "id": 23531064, "geometry": {"type": "Point", "coordinates": [-118.29525, 33.824509]}, "properties": {"woe:id": 23531064, "woe:parent_id": 2516788, "woe:name": "Meyler Street Elementary School", "woe:placetype": 20, "woe:placetype_name": "POI", "woe:lang": "ENG", "iso:country": "US", "meta:provider": ["geoplanet:7.3.2", "geoplanet:7.4.0", "geoplanet:7.4.1", "geoplanet:7.5.1", "geoplanet:7.5.2", "geoplanet:7.6.0", "geoplanet:7.8.1", "geoplanet:7.9.0", "geoplanet:7.10.0", "geoplanet:8.0.0", "woeplanet:8.0.0"], "meta:indexed": "2020-08-20T22:02:02.209822", "woe:alias_ENG_V": ["Meyler Street Elementary"], "meta:updated": "2020-10-14T11:20:26.990713", "woe:hierarchy": {"continent": 24865672, "country": 23424977, "town": 0, "planet": 1, "county": 12587688, "suburb": 0, "state": 2347563, "region": 0, "localadmin": 0}, "woe:timezone_id": 56043663, "woe:hash": "9q5bkjs40ckr", "woe:centroid": [-118.29525, 33.824509], "geom:latitude": 33.824509, "geom:longitude": -118.29525, "geom:hash": "9q5bkjs40ckr", "woe:latitude": 33.824509, "geom:centroid": [-118.29525, 33.824509], "woe:longitude": -118.29525, "woe:repo": "woeplanet-poi-us", "geom:area": 0.0, "woe:scale": 19}}