{"type": "Feature", "id": 23665549, "properties": {"woe:id": 23665549, "woe:parent_id": 2499669, "woe:name": "Faith Christian School", "woe:placetype": 20, "woe:placetype_name": "POI", "woe:lang": "ENG", "iso:country": "US", "meta:provider": ["geoplanet:7.4.0", "geoplanet:7.4.1", "geoplanet:7.5.1", "geoplanet:7.5.2", "geoplanet:7.6.0", "geoplanet:7.8.1", "geoplanet:7.9.0", "geoplanet:7.10.0", "geoplanet:8.0.0", "woeplanet:8.0.0"], "meta:indexed": "2020-08-20T23:55:44.633143", "meta:updated": "2020-08-22T02:57:51.310237", "woe:hierarchy": {"continent": 24865672, "country": 23424977, "town": 0, "planet": 1, "county": 12590376, "suburb": 0, "state": 2347605, "region": 0, "localadmin": 0}, "woe:timezone_id": 56043648, "woe:hash": "dqbynbh394rt", "woe:centroid": [-77.392792, 39.023708], "geom:latitude": 39.023708, "geom:longitude": -77.392792, "geom:hash": "dqbynbh394rt", "woe:latitude": 39.023708, "geom:centroid": [-77.392792, 39.023708], "woe:longitude": -77.392792, "woe:repo": "woeplanet-poi-us"}, "geometry": {"coordinates": [-77.392792, 39.023708], "type": "Point"}}