{"type": "Feature", "id": 23617559, "properties": {"woe:id": 23617559, "woe:parent_id": 23511893, "woe:name": "Spence School", "woe:placetype": 20, "woe:placetype_name": "POI", "woe:lang": "ENG", "iso:country": "US", "meta:provider": ["geoplanet:7.4.0", "geoplanet:7.4.1", "geoplanet:7.5.1", "geoplanet:7.5.2", "geoplanet:7.6.0", "geoplanet:7.8.1", "geoplanet:7.9.0", "geoplanet:7.10.0", "geoplanet:8.0.0", "woeplanet:8.0.0"], "meta:indexed": "2020-08-20T23:55:22.591575", "meta:updated": "2020-08-22T02:57:43.343410", "woe:hierarchy": {"continent": 24865672, "country": 23424977, "town": 0, "planet": 1, "county": 12589342, "suburb": 0, "state": 2347591, "region": 0, "localadmin": 0}, "woe:timezone_id": 56043648, "woe:hash": "dr72j0d1bd1r", "woe:centroid": [-73.957191, 40.784309], "geom:latitude": 40.784309, "geom:longitude": -73.957191, "geom:hash": "dr72j0d1bd1r", "woe:latitude": 40.784309, "geom:centroid": [-73.957191, 40.784309], "woe:longitude": -73.957191, "woe:repo": "woeplanet-poi-us"}, "geometry": {"coordinates": [-73.957191, 40.784309], "type": "Point"}}