{"type": "Feature", "id": 23673294, "geometry": {"type": "Point", "coordinates": [-88.165619, 44.029968]}, "properties": {"woe:id": 23673294, "woe:parent_id": 2379795, "woe:name": "Chilton Catholic Elementary School", "woe:placetype": 20, "woe:placetype_name": "POI", "woe:lang": "ENG", "iso:country": "US", "meta:provider": ["geoplanet:7.3.1", "geoplanet:7.3.2", "geoplanet:7.4.0", "geoplanet:7.4.1", "geoplanet:7.5.1", "geoplanet:7.5.2", "geoplanet:7.6.0", "geoplanet:7.8.1", "geoplanet:7.9.0", "geoplanet:7.10.0", "geoplanet:8.0.0", "woeplanet:8.0.0"], "meta:indexed": "2020-08-20T20:19:10.445937", "woe:alias_ENG_V": ["Chilton Catholic Elementary"], "meta:updated": "2020-10-14T11:19:29.031579", "woe:hierarchy": {"continent": 24865672, "country": 23424977, "town": 0, "planet": 1, "county": 12590541, "suburb": 0, "state": 2347608, "region": 0, "localadmin": 0}, "woe:timezone_id": 56043661, "woe:hash": "dpc63xrv0hvt", "woe:centroid": [-88.165619, 44.029968], "geom:latitude": 44.029968, "geom:longitude": -88.165619, "geom:hash": "dpc63xrv0hvt", "woe:latitude": 44.029968, "geom:centroid": [-88.165619, 44.029968], "woe:longitude": -88.165619, "woe:repo": "woeplanet-poi-us", "geom:area": 0.0, "woe:scale": 19}}