{"type": "Feature", "id": 23656062, "geometry": {"type": "Point", "coordinates": [-101.857353, 35.158661]}, "properties": {"woe:id": 23656062, "woe:parent_id": 2354141, "woe:name": "South Lawn Elementary School", "woe:placetype": 20, "woe:placetype_name": "POI", "woe:lang": "ENG", "iso:country": "US", "meta:provider": ["geoplanet:7.3.1", "geoplanet:7.3.2", "geoplanet:7.4.0", "geoplanet:7.4.1", "geoplanet:7.5.1", "geoplanet:7.5.2", "geoplanet:7.6.0", "geoplanet:7.8.1", "geoplanet:7.9.0", "geoplanet:7.10.0", "geoplanet:8.0.0", "woeplanet:8.0.0"], "meta:indexed": "2020-08-20T20:19:04.157307", "woe:alias_ENG_V": ["S Lawn Elementary School", "S Lawn Elementary", "South Lawn Elementary"], "meta:updated": "2020-10-14T11:19:44.006646", "woe:hierarchy": {"continent": 24865672, "country": 23424977, "town": 0, "planet": 1, "county": 12590197, "suburb": 0, "state": 2347602, "region": 0, "localadmin": 0}, "woe:timezone_id": 56043661, "woe:hash": "9wr840mwp9ky", "woe:centroid": [-101.857353, 35.158661], "geom:latitude": 35.158661, "geom:longitude": -101.857353, "geom:hash": "9wr840mwp9ky", "woe:latitude": 35.158661, "geom:centroid": [-101.857353, 35.158661], "woe:longitude": -101.857353, "woe:repo": "woeplanet-poi-us", "geom:area": 0.0, "woe:scale": 19}}