{"type": "Feature", "id": 23618947, "properties": {"woe:id": 23618947, "woe:parent_id": 28745020, "woe:name": "Henry H. Wells Middle School", "woe:placetype": 20, "woe:placetype_name": "POI", "woe:lang": "ENG", "iso:country": "US", "meta:provider": ["geoplanet:7.3.1", "geoplanet:7.3.2", "geoplanet:7.4.0", "geoplanet:7.4.1", "geoplanet:7.5.1", "geoplanet:7.5.2", "geoplanet:7.6.0", "geoplanet:7.8.1", "geoplanet:7.9.0", "geoplanet:7.10.0", "geoplanet:8.0.0", "woeplanet:8.0.0"], "meta:indexed": "2020-08-20T20:18:51.018156", "meta:updated": "2020-08-22T02:57:43.522769", "woe:hierarchy": {"continent": 24865672, "country": 23424977, "town": 0, "planet": 1, "county": 12589351, "suburb": 0, "state": 2347591, "region": 0, "localadmin": 0}, "woe:timezone_id": 56043648, "woe:hash": "dr7etng6y5p7", "woe:centroid": [-73.603668, 41.434052], "geom:latitude": 41.434052, "geom:longitude": -73.603668, "geom:hash": "dr7etng6y5p7", "woe:latitude": 41.434052, "geom:centroid": [-73.603668, 41.434052], "woe:longitude": -73.603668, "woe:repo": "woeplanet-poi-us"}, "geometry": {"coordinates": [-73.603668, 41.434052], "type": "Point"}}