{"type": "Feature", "id": 23579762, "geometry": {"type": "Point", "coordinates": [-76.82196, 39.471088]}, "properties": {"woe:id": 23579762, "woe:parent_id": 2411567, "woe:name": "Sacred Heart Elementary School", "woe:placetype": 20, "woe:placetype_name": "POI", "woe:lang": "ENG", "iso:country": "US", "meta:provider": ["geoplanet:7.3.1", "geoplanet:7.3.2", "geoplanet:7.4.0", "geoplanet:7.4.1", "geoplanet:7.5.1", "geoplanet:7.5.2", "geoplanet:7.6.0", "geoplanet:7.8.1", "geoplanet:7.9.0", "geoplanet:7.10.0", "geoplanet:8.0.0", "woeplanet:8.0.0"], "meta:indexed": "2020-08-20T20:18:38.429295", "woe:alias_ENG_V": ["Sacred Heart Elementary"], "meta:updated": "2020-10-14T11:20:28.330012", "woe:hierarchy": {"continent": 24865672, "country": 23424977, "town": 0, "planet": 1, "county": 12588678, "suburb": 0, "state": 2347579, "region": 0, "localadmin": 0}, "woe:timezone_id": 56043648, "woe:hash": "dr12ec7zy84g", "woe:centroid": [-76.82196, 39.471088], "geom:latitude": 39.471088, "geom:longitude": -76.82196, "geom:hash": "dr12ec7zy84g", "woe:latitude": 39.471088, "geom:centroid": [-76.82196, 39.471088], "woe:longitude": -76.82196, "woe:repo": "woeplanet-poi-us", "geom:area": 0.0, "woe:scale": 19}}