{"type": "Feature", "id": 23604366, "geometry": {"type": "Point", "coordinates": [-115.053238, 36.078091]}, "properties": {"woe:id": 23604366, "woe:parent_id": 23417687, "woe:name": "Thorpe Elementary School", "woe:placetype": 20, "woe:placetype_name": "POI", "woe:lang": "ENG", "iso:country": "US", "meta:provider": ["geoplanet:7.4.0", "geoplanet:7.4.1", "geoplanet:7.5.1", "geoplanet:7.5.2", "geoplanet:7.6.0", "geoplanet:7.8.1", "geoplanet:7.9.0", "geoplanet:7.10.0", "geoplanet:8.0.0", "woeplanet:8.0.0"], "meta:indexed": "2020-08-20T23:56:00.909307", "meta:updated": "2020-10-14T11:19:33.038191", "woe:alias_ENG_V": ["Jim Thorpe Elementary School"], "woe:hierarchy": {"continent": 24865672, "country": 23424977, "town": 0, "planet": 1, "county": 12589233, "suburb": 0, "state": 2347587, "region": 0, "localadmin": 0}, "woe:timezone_id": 56043663, "woe:hash": "9qqjjzuf15xg", "woe:centroid": [-115.053238, 36.078091], "geom:latitude": 36.078091, "geom:longitude": -115.053238, "geom:hash": "9qqjjzuf15xg", "woe:latitude": 36.078091, "geom:centroid": [-115.053238, 36.078091], "woe:longitude": -115.053238, "woe:repo": "woeplanet-poi-us", "geom:area": 0.0, "woe:scale": 19}}