{"type": "Feature", "id": 23603472, "properties": {"woe:id": 23603472, "woe:parent_id": 2515461, "woe:name": "Wausa High School", "woe:placetype": 20, "woe:placetype_name": "POI", "woe:lang": "ENG", "iso:country": "US", "meta:provider": ["geoplanet:7.3.1", "geoplanet:7.3.2", "geoplanet:7.4.0", "geoplanet:7.4.1", "geoplanet:7.5.1", "geoplanet:7.5.2", "geoplanet:7.6.0", "geoplanet:7.8.1", "geoplanet:7.9.0", "geoplanet:7.10.0", "geoplanet:8.0.0", "woeplanet:8.0.0"], "meta:indexed": "2020-08-20T20:18:45.777549", "woe:alias_ENG_V": ["Wausa Senior High School", "Wausa High", "Wausa Senior High", "Wausa HS", "Wausa Senior HS"], "meta:updated": "2020-08-22T02:58:48.407934", "woe:hierarchy": {"continent": 24865672, "country": 23424977, "town": 0, "planet": 1, "county": 12589191, "suburb": 0, "state": 2347586, "region": 0, "localadmin": 0}, "woe:timezone_id": 56043661, "woe:hash": "9zd9u2khecjk", "woe:centroid": [-97.541946, 42.497269], "geom:latitude": 42.497269, "geom:longitude": -97.541946, "geom:hash": "9zd9u2khecjk", "woe:latitude": 42.497269, "geom:centroid": [-97.541946, 42.497269], "woe:longitude": -97.541946, "woe:repo": "woeplanet-poi-us"}, "geometry": {"coordinates": [-97.541946, 42.497269], "type": "Point"}}