{"type": "Feature", "id": 23574055, "geometry": {"type": "Point", "coordinates": [-85.794601, 37.171848]}, "properties": {"woe:id": 23574055, "woe:parent_id": 2438018, "woe:name": "Legrande Elementary School", "woe:placetype": 20, "woe:placetype_name": "POI", "woe:lang": "ENG", "iso:country": "US", "meta:provider": ["geoplanet:7.3.2", "geoplanet:7.4.0", "geoplanet:7.4.1", "geoplanet:7.5.1", "geoplanet:7.5.2", "geoplanet:7.6.0", "geoplanet:7.8.1", "geoplanet:7.9.0", "geoplanet:7.10.0", "geoplanet:8.0.0", "woeplanet:8.0.0"], "meta:indexed": "2020-08-20T22:02:20.325074", "woe:alias_ENG_V": ["Legrande Elementary"], "meta:updated": "2020-10-14T11:20:10.602163", "woe:hierarchy": {"continent": 24865672, "country": 23424977, "town": 0, "planet": 1, "county": 12588525, "suburb": 0, "state": 2347576, "region": 0, "localadmin": 0}, "woe:timezone_id": 56043647, "woe:hash": "dndgrwym8ysy", "woe:centroid": [-85.794601, 37.171848], "geom:latitude": 37.171848, "geom:longitude": -85.794601, "geom:hash": "dndgrwym8ysy", "woe:latitude": 37.171848, "geom:centroid": [-85.794601, 37.171848], "woe:longitude": -85.794601, "woe:repo": "woeplanet-poi-us", "geom:area": 0.0, "woe:scale": 19}}