{"type": "Feature", "id": 23650322, "geometry": {"type": "Point", "coordinates": [-88.243881, 35.227051]}, "properties": {"woe:id": 23650322, "woe:parent_id": 2489313, "woe:name": "North Savannah Elementary School", "woe:placetype": 20, "woe:placetype_name": "POI", "woe:lang": "ENG", "iso:country": "US", "meta:provider": ["geoplanet:7.3.2", "geoplanet:7.4.0", "geoplanet:7.4.1", "geoplanet:7.5.1", "geoplanet:7.5.2", "geoplanet:7.6.0", "geoplanet:7.8.1", "geoplanet:7.9.0", "geoplanet:7.10.0", "geoplanet:8.0.0", "woeplanet:8.0.0"], "meta:indexed": "2020-08-20T22:02:51.030395", "woe:alias_ENG_V": ["N Savannah Elementary School", "N Savannah Elementary", "North Savannah Elementary"], "meta:updated": "2020-10-14T11:19:39.896628", "woe:hierarchy": {"continent": 24865672, "country": 23424977, "town": 0, "planet": 1, "county": 12589947, "suburb": 0, "state": 2347601, "region": 0, "localadmin": 0}, "woe:timezone_id": 56043661, "woe:hash": "dn30ruyu2w30", "woe:centroid": [-88.243881, 35.227051], "geom:latitude": 35.227051, "geom:longitude": -88.243881, "geom:hash": "dn30ruyu2w30", "woe:latitude": 35.227051, "geom:centroid": [-88.243881, 35.227051], "woe:longitude": -88.243881, "woe:repo": "woeplanet-poi-us", "geom:area": 0.0, "woe:scale": 19}}