{"type": "Feature", "id": 23543493, "geometry": {"type": "Point", "coordinates": [-73.000366, 41.90855]}, "properties": {"woe:id": 23543493, "woe:parent_id": 2474039, "woe:name": "Barkhamsted Elementary School", "woe:placetype": 20, "woe:placetype_name": "POI", "woe:lang": "ENG", "iso:country": "US", "meta:provider": ["geoplanet:7.4.0", "geoplanet:7.4.1", "geoplanet:7.5.1", "geoplanet:7.5.2", "geoplanet:7.6.0", "geoplanet:7.8.1", "geoplanet:7.9.0", "geoplanet:7.10.0", "geoplanet:8.0.0", "woeplanet:8.0.0"], "meta:indexed": "2020-08-20T23:56:00.739024", "meta:updated": "2020-10-14T11:20:14.940831", "woe:hierarchy": {"continent": 24865672, "country": 23424977, "town": 0, "planet": 1, "county": 12587793, "suburb": 0, "state": 2347565, "region": 0, "localadmin": 0}, "woe:timezone_id": 56043648, "woe:hash": "drkn6v4ybpvy", "woe:centroid": [-73.000366, 41.90855], "geom:latitude": 41.90855, "geom:longitude": -73.000366, "geom:hash": "drkn6v4ybpvy", "woe:latitude": 41.90855, "geom:centroid": [-73.000366, 41.90855], "woe:longitude": -73.000366, "woe:repo": "woeplanet-poi-us", "geom:area": 0.0, "woe:scale": 19}}