{"type": "Feature", "id": 23544341, "geometry": {"type": "Point", "coordinates": [-72.105614, 41.357658]}, "properties": {"woe:id": 23544341, "woe:parent_id": 28338013, "woe:name": "Title I Preschool Program", "woe:placetype": 20, "woe:placetype_name": "POI", "woe:lang": "ENG", "iso:country": "US", "meta:provider": ["geoplanet:7.3.1", "geoplanet:7.3.2", "geoplanet:7.4.0", "geoplanet:7.4.1", "geoplanet:7.5.1", "geoplanet:7.5.2", "geoplanet:7.6.0", "geoplanet:7.8.1", "geoplanet:7.9.0", "geoplanet:7.10.0", "geoplanet:8.0.0", "woeplanet:8.0.0"], "meta:indexed": "2020-08-20T20:18:25.557143", "meta:updated": "2020-10-14T11:20:12.114858", "woe:hierarchy": {"continent": 24865672, "country": 23424977, "town": 0, "planet": 1, "county": 12587796, "suburb": 0, "state": 2347565, "region": 0, "localadmin": 0}, "woe:timezone_id": 56043648, "woe:hash": "drker0ymc6jr", "woe:centroid": [-72.105614, 41.357658], "geom:latitude": 41.357658, "geom:longitude": -72.105614, "geom:hash": "drker0ymc6jr", "woe:latitude": 41.357658, "geom:centroid": [-72.105614, 41.357658], "woe:longitude": -72.105614, "woe:repo": "woeplanet-poi-us", "geom:area": 0.0, "woe:scale": 19}}