{"type": "Feature", "id": 23644378, "geometry": {"type": "Point", "coordinates": [-75.217422, 40.035019]}, "properties": {"woe:id": 23644378, "woe:parent_id": 2485356, "woe:name": "Roxborough Finance Station", "woe:placetype": 20, "woe:placetype_name": "POI", "woe:lang": "ENG", "iso:country": "US", "meta:provider": ["geoplanet:7.3.1", "geoplanet:7.3.2", "geoplanet:7.4.0", "geoplanet:7.4.1", "geoplanet:7.5.1", "geoplanet:7.5.2", "geoplanet:7.6.0", "geoplanet:7.8.1", "geoplanet:7.9.0", "geoplanet:7.10.0", "geoplanet:8.0.0", "woeplanet:8.0.0"], "meta:indexed": "2020-08-20T20:18:59.939863", "meta:updated": "2020-10-14T11:19:36.389192", "woe:hierarchy": {"continent": 24865672, "country": 23424977, "town": 0, "planet": 1, "county": 12589778, "suburb": 0, "state": 2347597, "region": 0, "localadmin": 0}, "woe:timezone_id": 56043648, "woe:hash": "dr4eb2hkgh3n", "woe:centroid": [-75.217422, 40.035019], "geom:latitude": 40.035019, "geom:longitude": -75.217422, "geom:hash": "dr4eb2hkgh3n", "woe:latitude": 40.035019, "geom:centroid": [-75.217422, 40.035019], "woe:longitude": -75.217422, "woe:repo": "woeplanet-poi-us", "geom:area": 0.0, "woe:scale": 19}}