{"type": "Feature", "id": 23627431, "geometry": {"type": "Point", "coordinates": [-84.544899, 39.390099]}, "properties": {"woe:id": 23627431, "woe:parent_id": 2416591, "woe:name": "Buchanan Elementary School", "woe:placetype": 20, "woe:placetype_name": "POI", "woe:lang": "ENG", "iso:country": "US", "meta:provider": ["geoplanet:7.3.1", "geoplanet:7.3.2", "geoplanet:7.4.0", "geoplanet:7.4.1", "geoplanet:7.5.1", "geoplanet:7.5.2", "geoplanet:7.6.0", "geoplanet:7.8.1", "geoplanet:7.9.0", "geoplanet:7.10.0", "geoplanet:8.0.0", "woeplanet:8.0.0"], "meta:indexed": "2020-08-20T20:18:53.236385", "woe:alias_ENG_V": ["Buchanan Elementary"], "meta:updated": "2020-10-14T11:19:30.739810", "woe:hierarchy": {"continent": 24865672, "country": 23424977, "town": 0, "planet": 1, "county": 12589535, "suburb": 0, "state": 2347594, "region": 0, "localadmin": 0}, "woe:timezone_id": 56043648, "woe:hash": "dp5bh4srcndj", "woe:centroid": [-84.544899, 39.390099], "geom:latitude": 39.390099, "geom:longitude": -84.544899, "geom:hash": "dp5bh4srcndj", "woe:latitude": 39.390099, "geom:centroid": [-84.544899, 39.390099], "woe:longitude": -84.544899, "woe:repo": "woeplanet-poi-us", "geom:area": 0.0, "woe:scale": 19}}