{"type": "Feature", "id": 23586599, "properties": {"woe:id": 23586599, "woe:parent_id": 2509681, "woe:name": "Baldwin Elementary School", "woe:placetype": 20, "woe:placetype_name": "POI", "woe:lang": "ENG", "iso:country": "US", "meta:provider": ["geoplanet:7.3.1", "geoplanet:7.3.2", "geoplanet:7.4.0", "geoplanet:7.4.1", "geoplanet:7.5.1", "geoplanet:7.5.2", "geoplanet:7.6.0", "geoplanet:7.8.1", "geoplanet:7.9.0", "geoplanet:7.10.0", "geoplanet:8.0.0", "woeplanet:8.0.0"], "meta:indexed": "2020-08-20T20:18:40.037276", "woe:alias_ENG_V": ["Baldwin Elementary"], "meta:updated": "2020-08-22T02:57:38.813181", "woe:hierarchy": {"continent": 24865672, "country": 23424977, "town": 0, "planet": 1, "county": 12588727, "suburb": 0, "state": 2347581, "region": 0, "localadmin": 0}, "woe:timezone_id": 56043658, "woe:hash": "dp6vwrhv97js", "woe:centroid": [-85.85157, 41.78746], "geom:latitude": 41.78746, "geom:longitude": -85.85157, "geom:hash": "dp6vwrhv97js", "woe:latitude": 41.78746, "geom:centroid": [-85.85157, 41.78746], "woe:longitude": -85.85157, "woe:repo": "woeplanet-poi-us"}, "geometry": {"coordinates": [-85.85157, 41.78746], "type": "Point"}}