{"type": "Feature", "id": 23599671, "geometry": {"type": "Point", "coordinates": [-90.475761, 38.57943]}, "properties": {"woe:id": 23599671, "woe:parent_id": 2467263, "woe:name": "Barretts Elementary School", "woe:placetype": 20, "woe:placetype_name": "POI", "woe:lang": "ENG", "iso:country": "US", "meta:provider": ["geoplanet:7.3.1", "geoplanet:7.3.2", "geoplanet:7.4.0", "geoplanet:7.4.1", "geoplanet:7.5.1", "geoplanet:7.5.2", "geoplanet:7.6.0", "geoplanet:7.8.1", "geoplanet:7.9.0", "geoplanet:7.10.0", "geoplanet:8.0.0", "woeplanet:8.0.0"], "meta:indexed": "2020-08-20T20:18:44.737224", "woe:alias_ENG_V": ["Barretts Elementary"], "meta:updated": "2020-10-14T11:20:16.315693", "woe:hierarchy": {"continent": 24865672, "country": 23424977, "town": 0, "planet": 1, "county": 12589066, "suburb": 0, "state": 2347584, "region": 0, "localadmin": 0}, "woe:timezone_id": 56043661, "woe:hash": "9yzempjt3znb", "woe:centroid": [-90.475761, 38.57943], "geom:latitude": 38.57943, "geom:longitude": -90.475761, "geom:hash": "9yzempjt3znb", "woe:latitude": 38.57943, "geom:centroid": [-90.475761, 38.57943], "woe:longitude": -90.475761, "woe:repo": "woeplanet-poi-us", "geom:area": 0.0, "woe:scale": 19}}