{"type": "Feature", "id": 23683503, "geometry": {"type": "Point", "coordinates": [-88.602539, 43.14563]}, "properties": {"woe:id": 23683503, "woe:parent_id": 2428082, "woe:name": "Ixonia Station", "woe:placetype": 20, "woe:placetype_name": "POI", "woe:lang": "ENG", "iso:country": "US", "meta:provider": ["geoplanet:7.3.1", "geoplanet:7.3.2", "geoplanet:7.4.0", "geoplanet:7.4.1", "geoplanet:7.5.1", "geoplanet:7.5.2", "geoplanet:7.6.0", "geoplanet:7.8.1", "geoplanet:7.9.0", "geoplanet:7.10.0", "geoplanet:8.0.0", "woeplanet:8.0.0"], "meta:indexed": "2020-08-20T20:19:20.319455", "meta:updated": "2020-10-14T11:19:54.243303", "woe:hierarchy": {"continent": 24865672, "country": 23424977, "town": 0, "planet": 1, "county": 12590561, "suburb": 0, "state": 2347608, "region": 0, "localadmin": 0}, "woe:timezone_id": 56043661, "woe:hash": "dp8vry3te0qk", "woe:centroid": [-88.602539, 43.14563], "geom:latitude": 43.14563, "geom:longitude": -88.602539, "geom:hash": "dp8vry3te0qk", "woe:latitude": 43.14563, "geom:centroid": [-88.602539, 43.14563], "woe:longitude": -88.602539, "woe:repo": "woeplanet-poi-us", "geom:area": 0.0, "woe:scale": 19}}