{"type": "Feature", "id": 23681938, "properties": {"woe:id": 23681938, "woe:parent_id": 2471820, "woe:name": "West Pilot Station", "woe:placetype": 20, "woe:placetype_name": "POI", "woe:lang": "ENG", "iso:country": "US", "meta:provider": ["geoplanet:7.3.1", "geoplanet:7.3.2", "geoplanet:7.4.0", "geoplanet:7.4.1", "geoplanet:7.5.1", "geoplanet:7.5.2", "geoplanet:7.6.0", "geoplanet:7.8.1", "geoplanet:7.9.0", "geoplanet:7.10.0", "geoplanet:8.0.0", "woeplanet:8.0.0"], "meta:indexed": "2020-08-20T20:19:19.421940", "woe:alias_ENG_V": ["W Pilot Station"], "meta:updated": "2020-08-22T02:58:22.218772", "woe:hierarchy": {"continent": 24865672, "country": 23424977, "town": 0, "planet": 1, "county": 12588683, "suburb": 0, "state": 2347579, "region": 0, "localadmin": 0}, "woe:timezone_id": 56043648, "woe:hash": "dr1ccerxftvs", "woe:centroid": [-76.21273, 39.701832], "geom:latitude": 39.701832, "geom:longitude": -76.21273, "geom:hash": "dr1ccerxftvs", "woe:latitude": 39.701832, "geom:centroid": [-76.21273, 39.701832], "woe:longitude": -76.21273, "woe:repo": "woeplanet-poi-us"}, "geometry": {"coordinates": [-76.21273, 39.701832], "type": "Point"}}