{"type": "Feature", "id": 23550670, "properties": {"woe:id": 23550670, "woe:parent_id": 2387517, "woe:name": "Osceola High School", "woe:placetype": 20, "woe:placetype_name": "POI", "woe:lang": "ENG", "iso:country": "US", "meta:provider": ["geoplanet:7.3.1", "geoplanet:7.3.2", "geoplanet:7.4.0", "geoplanet:7.4.1", "geoplanet:7.5.1", "geoplanet:7.5.2", "geoplanet:7.6.0", "geoplanet:7.8.1", "geoplanet:7.9.0", "geoplanet:7.10.0", "geoplanet:8.0.0", "woeplanet:8.0.0"], "meta:indexed": "2020-08-20T20:18:28.497446", "woe:alias_ENG_V": ["Osceola Senior High School", "Osceola High", "Osceola Senior High", "Osceola HS", "Osceola Senior HS"], "meta:updated": "2020-08-22T02:58:46.804873", "woe:hierarchy": {"continent": 24865672, "country": 23424977, "town": 0, "planet": 1, "county": 12587854, "suburb": 0, "state": 2347568, "region": 0, "localadmin": 0}, "woe:timezone_id": 56043648, "woe:hash": "dhvnkrtrv1tq", "woe:centroid": [-82.774551, 27.859921], "geom:latitude": 27.859921, "geom:longitude": -82.774551, "geom:hash": "dhvnkrtrv1tq", "woe:latitude": 27.859921, "geom:centroid": [-82.774551, 27.859921], "woe:longitude": -82.774551, "woe:repo": "woeplanet-poi-us"}, "geometry": {"coordinates": [-82.774551, 27.859921], "type": "Point"}}