{"type": "Feature", "id": 23668325, "geometry": {"type": "Point", "coordinates": [-122.637489, 45.626049]}, "properties": {"woe:id": 23668325, "woe:parent_id": 55996974, "woe:name": "Harney Elementary School", "woe:placetype": 20, "woe:placetype_name": "POI", "woe:lang": "ENG", "iso:country": "US", "meta:provider": ["geoplanet:7.3.1", "geoplanet:7.3.2", "geoplanet:7.4.0", "geoplanet:7.4.1", "geoplanet:7.5.1", "geoplanet:7.5.2", "geoplanet:7.6.0", "geoplanet:7.8.1", "geoplanet:7.9.0", "geoplanet:7.10.0", "geoplanet:8.0.0", "woeplanet:8.0.0"], "meta:indexed": "2020-08-20T20:19:09.089871", "woe:alias_ENG_V": ["Harney Elementary"], "meta:updated": "2020-10-14T11:19:33.261735", "woe:hierarchy": {"continent": 24865672, "country": 23424977, "town": 0, "planet": 1, "county": 12590445, "suburb": 0, "state": 2347606, "region": 0, "localadmin": 0}, "woe:timezone_id": 56043663, "woe:hash": "c20g93fngrur", "woe:centroid": [-122.637489, 45.626049], "geom:latitude": 45.626049, "geom:longitude": -122.637489, "geom:hash": "c20g93fngrur", "woe:latitude": 45.626049, "geom:centroid": [-122.637489, 45.626049], "woe:longitude": -122.637489, "woe:repo": "woeplanet-poi-us", "geom:area": 0.0, "woe:scale": 19}}