{"type": "Feature", "id": 23575840, "geometry": {"type": "Point", "coordinates": [-93.189034, 30.203199]}, "properties": {"woe:id": 23575840, "woe:parent_id": 2434769, "woe:name": "Oak Park Middle School", "woe:placetype": 20, "woe:placetype_name": "POI", "woe:lang": "ENG", "iso:country": "US", "meta:provider": ["geoplanet:7.3.1", "geoplanet:7.3.2", "geoplanet:7.4.0", "geoplanet:7.4.1", "geoplanet:7.5.1", "geoplanet:7.5.2", "geoplanet:7.6.0", "geoplanet:7.8.1", "geoplanet:7.9.0", "geoplanet:7.10.0", "geoplanet:8.0.0", "woeplanet:8.0.0"], "meta:indexed": "2020-08-20T20:18:37.326115", "meta:updated": "2020-10-14T11:20:20.244014", "woe:hierarchy": {"continent": 24865672, "country": 23424977, "town": 0, "planet": 1, "county": 12588605, "suburb": 0, "state": 2347577, "region": 0, "localadmin": 0}, "woe:timezone_id": 56043661, "woe:hash": "9vmez6mf6h7g", "woe:centroid": [-93.189034, 30.203199], "geom:latitude": 30.203199, "geom:longitude": -93.189034, "geom:hash": "9vmez6mf6h7g", "woe:latitude": 30.203199, "geom:centroid": [-93.189034, 30.203199], "woe:longitude": -93.189034, "woe:repo": "woeplanet-poi-us", "geom:area": 0.0, "woe:scale": 19}}