{"type": "Feature", "id": 23558979, "properties": {"woe:id": 23558979, "woe:parent_id": 2404937, "woe:name": "Tidye A Phillips Elementary School", "woe:placetype": 20, "woe:placetype_name": "POI", "woe:lang": "ENG", "iso:country": "US", "meta:provider": ["geoplanet:7.3.1", "geoplanet:7.3.2", "geoplanet:7.4.0", "geoplanet:7.4.1", "geoplanet:7.5.1", "geoplanet:7.5.2", "geoplanet:7.6.0", "geoplanet:7.8.1", "geoplanet:7.9.0", "geoplanet:7.10.0", "geoplanet:8.0.0", "woeplanet:8.0.0"], "meta:indexed": "2020-08-20T20:18:31.163444", "woe:alias_ENG_V": ["Tidye A Phillips Elementary"], "meta:updated": "2020-08-22T02:57:34.072262", "woe:hierarchy": {"continent": 24865672, "country": 23424977, "town": 0, "planet": 1, "county": 12588093, "suburb": 0, "state": 2347572, "region": 0, "localadmin": 0}, "woe:timezone_id": 56043661, "woe:hash": "dp3snujj0nme", "woe:centroid": [-87.58712, 41.50724], "geom:latitude": 41.50724, "geom:longitude": -87.58712, "geom:hash": "dp3snujj0nme", "woe:latitude": 41.50724, "geom:centroid": [-87.58712, 41.50724], "woe:longitude": -87.58712, "woe:repo": "woeplanet-poi-us"}, "geometry": {"coordinates": [-87.58712, 41.50724], "type": "Point"}}