{"type": "Feature", "id": 23597123, "properties": {"woe:id": 23597123, "woe:parent_id": 2428176, "woe:name": "Jackson Middle School", "woe:placetype": 20, "woe:placetype_name": "POI", "woe:lang": "ENG", "iso:country": "US", "meta:provider": ["geoplanet:7.3.1", "geoplanet:7.3.2", "geoplanet:7.4.0", "geoplanet:7.4.1", "geoplanet:7.5.1", "geoplanet:7.5.2", "geoplanet:7.6.0", "geoplanet:7.8.1", "geoplanet:7.9.0", "geoplanet:7.10.0", "geoplanet:8.0.0", "woeplanet:8.0.0"], "meta:indexed": "2020-08-20T20:18:43.753983", "meta:updated": "2020-08-22T02:57:40.570009", "woe:hierarchy": {"continent": 24865672, "country": 23424977, "town": 0, "planet": 1, "county": 12588981, "suburb": 0, "state": 2347584, "region": 0, "localadmin": 0}, "woe:timezone_id": 56043661, "woe:hash": "dn8hxpkwpz4d", "woe:centroid": [-89.685867, 37.394409], "geom:latitude": 37.394409, "geom:longitude": -89.685867, "geom:hash": "dn8hxpkwpz4d", "woe:latitude": 37.394409, "geom:centroid": [-89.685867, 37.394409], "woe:longitude": -89.685867, "woe:repo": "woeplanet-poi-us"}, "geometry": {"coordinates": [-89.685867, 37.394409], "type": "Point"}}