{"type": "Feature", "id": 56054132, "properties": {"woe:id": 56054132, "woe:parent_id": 2465243, "woe:name": "Empire State College-Olean", "woe:placetype": 20, "woe:placetype_name": "POI", "woe:lang": "ENG", "iso:country": "US", "meta:provider": ["geoplanet:7.3.1", "geoplanet:7.3.2", "geoplanet:7.4.0", "geoplanet:7.4.1", "geoplanet:7.5.1", "geoplanet:7.5.2", "geoplanet:7.6.0", "geoplanet:7.8.1", "geoplanet:7.9.0", "geoplanet:7.10.0", "geoplanet:8.0.0", "woeplanet:8.0.0"], "meta:indexed": "2020-08-20T20:19:17.588519", "meta:updated": "2020-08-22T02:58:21.172174", "woe:hierarchy": {"continent": 24865672, "country": 23424977, "town": 0, "planet": 1, "county": 12589316, "suburb": 0, "state": 2347591, "region": 0, "localadmin": 0}, "woe:timezone_id": 56043648, "woe:hash": "dr2prk95ew9q", "woe:centroid": [-78.429871, 42.08102], "geom:latitude": 42.08102, "geom:longitude": -78.429871, "geom:hash": "dr2prk95ew9q", "woe:latitude": 42.08102, "geom:centroid": [-78.429871, 42.08102], "woe:longitude": -78.429871, "woe:repo": "woeplanet-poi-us"}, "geometry": {"coordinates": [-78.429871, 42.08102], "type": "Point"}}