{"type": "Feature", "id": 23660886, "geometry": {"type": "Point", "coordinates": [-97.516563, 28.02832]}, "properties": {"woe:id": 23660886, "woe:parent_id": 2494102, "woe:name": "E Merle Smith Junior High School", "woe:placetype": 20, "woe:placetype_name": "POI", "woe:lang": "ENG", "iso:country": "US", "meta:provider": ["geoplanet:7.3.1", "geoplanet:7.3.2", "geoplanet:7.4.0", "geoplanet:7.4.1", "geoplanet:7.5.1", "geoplanet:7.5.2", "geoplanet:7.6.0", "geoplanet:7.8.1", "geoplanet:7.9.0", "geoplanet:7.10.0", "geoplanet:8.0.0", "woeplanet:8.0.0"], "meta:indexed": "2020-08-20T20:19:06.675499", "woe:alias_ENG_V": ["E Merle Smith Junior High"], "meta:updated": "2020-10-14T11:19:30.152119", "woe:hierarchy": {"continent": 24865672, "country": 23424977, "town": 0, "planet": 1, "county": 12590211, "suburb": 0, "state": 2347602, "region": 0, "localadmin": 0}, "woe:timezone_id": 56043661, "woe:hash": "9ufxkyqsg3s3", "woe:centroid": [-97.516563, 28.02832], "geom:latitude": 28.02832, "geom:longitude": -97.516563, "geom:hash": "9ufxkyqsg3s3", "woe:latitude": 28.02832, "geom:centroid": [-97.516563, 28.02832], "woe:longitude": -97.516563, "woe:repo": "woeplanet-poi-us", "geom:area": 0.0, "woe:scale": 19}}