{"type": "Feature", "id": 23521115, "properties": {"woe:id": 23521115, "woe:parent_id": 55971642, "woe:name": "Pioneer Elementary School", "woe:placetype": 20, "woe:placetype_name": "POI", "woe:lang": "ENG", "iso:country": "US", "meta:provider": ["geoplanet:7.4.0", "geoplanet:7.4.1", "geoplanet:7.5.1", "geoplanet:7.5.2", "geoplanet:7.6.0", "geoplanet:7.8.1", "geoplanet:7.9.0", "geoplanet:7.10.0", "geoplanet:8.0.0", "woeplanet:8.0.0"], "meta:indexed": "2020-08-20T23:54:26.982620", "woe:alias_ENG_V": ["Pioneer Elementary"], "meta:updated": "2020-08-22T02:57:27.367365", "woe:hierarchy": {"continent": 24865672, "country": 23424977, "town": 0, "planet": 1, "county": 12587678, "suburb": 0, "state": 2347563, "region": 0, "localadmin": 0}, "woe:timezone_id": 56043663, "woe:hash": "9qf5thq3ypr6", "woe:centroid": [-120.708923, 38.60767], "geom:latitude": 38.60767, "geom:longitude": -120.708923, "geom:hash": "9qf5thq3ypr6", "woe:latitude": 38.60767, "geom:centroid": [-120.708923, 38.60767], "woe:longitude": -120.708923, "woe:repo": "woeplanet-poi-us"}, "geometry": {"coordinates": [-120.708923, 38.60767], "type": "Point"}}