{"type": "Feature", "id": 23564137, "geometry": {"type": "Point", "coordinates": [-90.093773, 38.462219]}, "properties": {"woe:id": 23564137, "woe:parent_id": 2451584, "woe:name": "Millstadt Elementary School", "woe:placetype": 20, "woe:placetype_name": "POI", "woe:lang": "ENG", "iso:country": "US", "meta:provider": ["geoplanet:7.3.1", "geoplanet:7.3.2", "geoplanet:7.4.0", "geoplanet:7.4.1", "geoplanet:7.5.1", "geoplanet:7.5.2", "geoplanet:7.6.0", "geoplanet:7.8.1", "geoplanet:7.9.0", "geoplanet:7.10.0", "geoplanet:8.0.0", "woeplanet:8.0.0"], "meta:indexed": "2020-08-20T20:18:33.108403", "woe:alias_ENG_V": ["Millstadt Cons Elementary School", "Millstadt Elementary"], "meta:updated": "2020-10-14T11:20:06.052423", "woe:hierarchy": {"continent": 24865672, "country": 23424977, "town": 0, "planet": 1, "county": 12588164, "suburb": 0, "state": 2347572, "region": 0, "localadmin": 0}, "woe:timezone_id": 56043661, "woe:hash": "9yzfvcgdwvmc", "woe:centroid": [-90.093773, 38.462219], "geom:latitude": 38.462219, "geom:longitude": -90.093773, "geom:hash": "9yzfvcgdwvmc", "woe:latitude": 38.462219, "geom:centroid": [-90.093773, 38.462219], "woe:longitude": -90.093773, "woe:repo": "woeplanet-poi-us", "geom:area": 0.0, "woe:scale": 19}}