{"type": "Feature", "id": 23550427, "geometry": {"type": "Point", "coordinates": [-80.24823, 26.677971]}, "properties": {"woe:id": 23550427, "woe:parent_id": 2442753, "woe:name": "Wellington Station", "woe:placetype": 20, "woe:placetype_name": "POI", "woe:lang": "ENG", "iso:country": "US", "meta:provider": ["geoplanet:7.3.1", "geoplanet:7.3.2", "geoplanet:7.4.0", "geoplanet:7.4.1", "geoplanet:7.5.1", "geoplanet:7.5.2", "geoplanet:7.6.0", "geoplanet:7.8.1", "geoplanet:7.9.0", "geoplanet:7.10.0", "geoplanet:8.0.0", "woeplanet:8.0.0"], "meta:indexed": "2020-08-20T20:18:28.360092", "meta:updated": "2020-10-14T11:20:29.285415", "woe:hierarchy": {"continent": 24865672, "country": 23424977, "town": 0, "planet": 1, "county": 12587852, "suburb": 0, "state": 2347568, "region": 0, "localadmin": 0}, "woe:timezone_id": 56043648, "woe:hash": "dhwzvbt42wnx", "woe:centroid": [-80.24823, 26.677971], "geom:latitude": 26.677971, "geom:longitude": -80.24823, "geom:hash": "dhwzvbt42wnx", "woe:latitude": 26.677971, "geom:centroid": [-80.24823, 26.677971], "woe:longitude": -80.24823, "woe:repo": "woeplanet-poi-us", "geom:area": 0.0, "woe:scale": 19}}