{"type": "Feature", "id": 23676235, "geometry": {"type": "Point", "coordinates": [-91.92907, 45.73402]}, "properties": {"woe:id": 23676235, "woe:parent_id": 2492199, "woe:name": "Shell Lake Junior & Senior High School", "woe:placetype": 20, "woe:placetype_name": "POI", "woe:lang": "ENG", "iso:country": "US", "meta:provider": ["geoplanet:7.3.1", "geoplanet:7.3.2", "geoplanet:7.4.0", "geoplanet:7.4.1", "geoplanet:7.5.1", "geoplanet:7.5.2", "geoplanet:7.6.0", "geoplanet:7.8.1", "geoplanet:7.9.0", "geoplanet:7.10.0", "geoplanet:8.0.0", "woeplanet:8.0.0"], "meta:indexed": "2020-08-20T20:19:11.899629", "woe:alias_ENG_V": ["Shell Lake Junior & Senior High", "Shell Lake Junior High School", "Shell Lake Junior & High", "Shell Lake Junior & Senior HS", "Shell Lake Junior HS", "Shell Lake Junior and Senior High", "Shell Lake Junior and Senior Senior High", "Shell Lake Junior and Senior Senior HS", "Shell Lake Junior and Senior HS", "Shell Lake Junior and Senior Senior High School", "Shell Lake Junior and Senior High School"], "meta:updated": "2020-10-14T11:19:47.312244", "woe:hierarchy": {"continent": 24865672, "country": 23424977, "town": 0, "planet": 1, "county": 12590599, "suburb": 0, "state": 2347608, "region": 0, "localadmin": 0}, "woe:timezone_id": 56043661, "woe:hash": "cbnshje7crjp", "woe:centroid": [-91.92907, 45.73402], "geom:latitude": 45.73402, "geom:longitude": -91.92907, "geom:hash": "cbnshje7crjp", "woe:latitude": 45.73402, "geom:centroid": [-91.92907, 45.73402], "woe:longitude": -91.92907, "woe:repo": "woeplanet-poi-us", "geom:area": 0.0, "woe:scale": 19}}