{"type": "Feature", "id": 23531867, "properties": {"woe:id": 23531867, "woe:parent_id": 2492476, "woe:name": "St Francis De Sales School", "woe:placetype": 20, "woe:placetype_name": "POI", "woe:lang": "ENG", "iso:country": "US", "meta:provider": ["geoplanet:7.3.1", "geoplanet:7.3.2", "geoplanet:7.4.0", "geoplanet:7.4.1", "geoplanet:7.5.1", "geoplanet:7.5.2", "geoplanet:7.6.0", "geoplanet:7.8.1", "geoplanet:7.9.0", "geoplanet:7.10.0", "geoplanet:8.0.0", "woeplanet:8.0.0"], "meta:indexed": "2020-08-20T20:18:21.985719", "meta:updated": "2020-08-22T02:57:29.032940", "woe:alias_ENG_V": ["St Francis de Sales Elementary Sch"], "woe:hierarchy": {"continent": 24865672, "country": 23424977, "town": 0, "planet": 1, "county": 12587688, "suburb": 0, "state": 2347563, "region": 0, "localadmin": 0}, "woe:timezone_id": 56043663, "woe:hash": "9q5f31jgxxkr", "woe:centroid": [-118.424393, 34.151642], "geom:latitude": 34.151642, "geom:longitude": -118.424393, "geom:hash": "9q5f31jgxxkr", "woe:latitude": 34.151642, "geom:centroid": [-118.424393, 34.151642], "woe:longitude": -118.424393, "woe:repo": "woeplanet-poi-us"}, "geometry": {"coordinates": [-118.424393, 34.151642], "type": "Point"}}