{"type": "Feature", "id": 23590639, "geometry": {"type": "Point", "coordinates": [-83.407303, 43.491718]}, "properties": {"woe:id": 23590639, "woe:parent_id": 2375251, "woe:name": "Caro High School", "woe:placetype": 20, "woe:placetype_name": "POI", "woe:lang": "ENG", "iso:country": "US", "meta:provider": ["geoplanet:7.3.2", "geoplanet:7.4.0", "geoplanet:7.4.1", "geoplanet:7.5.1", "geoplanet:7.5.2", "geoplanet:7.6.0", "geoplanet:7.8.1", "geoplanet:7.9.0", "geoplanet:7.10.0", "geoplanet:8.0.0", "woeplanet:8.0.0"], "meta:indexed": "2020-08-20T22:02:27.043788", "woe:alias_ENG_V": ["Caro Senior High School", "Caro High", "Caro Senior High", "Caro HS", "Caro Senior HS"], "meta:updated": "2020-10-14T11:20:04.815097", "woe:hierarchy": {"continent": 24865672, "country": 23424977, "town": 0, "planet": 1, "county": 12588792, "suburb": 0, "state": 2347581, "region": 0, "localadmin": 0}, "woe:timezone_id": 56043658, "woe:hash": "dpsxqj2tsgz5", "woe:centroid": [-83.407303, 43.491718], "geom:latitude": 43.491718, "geom:longitude": -83.407303, "geom:hash": "dpsxqj2tsgz5", "woe:latitude": 43.491718, "geom:centroid": [-83.407303, 43.491718], "woe:longitude": -83.407303, "woe:repo": "woeplanet-poi-us", "geom:area": 0.0, "woe:scale": 19}}