{"type": "Feature", "id": 23647807, "geometry": {"type": "Point", "coordinates": [-81.207748, 34.107811]}, "properties": {"woe:id": 23647807, "woe:parent_id": 12589839, "woe:name": "H. E. Corley Elementary School", "woe:placetype": 20, "woe:placetype_name": "POI", "woe:lang": "ENG", "iso:country": "US", "meta:provider": ["geoplanet:7.4.0", "geoplanet:7.4.1", "geoplanet:7.5.1", "geoplanet:7.5.2", "geoplanet:7.6.0", "geoplanet:7.8.1", "geoplanet:7.9.0", "geoplanet:7.10.0", "geoplanet:8.0.0", "woeplanet:8.0.0"], "meta:indexed": "2020-08-20T23:56:01.228581", "meta:updated": "2020-10-14T11:19:47.451537", "woe:alias_ENG_V": ["He Corley Elementary School"], "woe:hierarchy": {"continent": 24865672, "country": 23424977, "town": 0, "planet": 1, "county": 12589839, "suburb": 0, "state": 2347599, "region": 0, "localadmin": 0}, "woe:timezone_id": 56043648, "woe:hash": "dnn6014k6kf3", "woe:centroid": [-81.207748, 34.107811], "geom:latitude": 34.107811, "geom:longitude": -81.207748, "geom:hash": "dnn6014k6kf3", "woe:latitude": 34.107811, "geom:centroid": [-81.207748, 34.107811], "woe:longitude": -81.207748, "woe:repo": "woeplanet-poi-us", "geom:area": 0.0, "woe:scale": 19}}