{"type": "Feature", "id": 23610197, "properties": {"woe:id": 23610197, "woe:parent_id": 55861022, "woe:name": "Manchester Regional High School", "woe:placetype": 20, "woe:placetype_name": "POI", "woe:lang": "ENG", "iso:country": "US", "meta:provider": ["geoplanet:7.3.1", "geoplanet:7.3.2", "geoplanet:7.4.0", "geoplanet:7.4.1", "geoplanet:7.5.1", "geoplanet:7.5.2", "geoplanet:7.6.0", "geoplanet:7.8.1", "geoplanet:7.9.0", "geoplanet:7.10.0", "geoplanet:8.0.0", "woeplanet:8.0.0"], "meta:indexed": "2020-08-20T20:18:47.859746", "woe:alias_ENG_V": ["Manchester Regional Senior High School", "Manchester Regional High", "Manchester Regional Senior High", "Manchester Regional HS", "Manchester Regional Senior HS"], "meta:updated": "2020-08-22T02:58:48.581980", "woe:hierarchy": {"continent": 24865672, "country": 23424977, "town": 0, "planet": 1, "county": 12589273, "suburb": 0, "state": 2347589, "region": 0, "localadmin": 0}, "woe:timezone_id": 56043648, "woe:hash": "dr70zvjyr9hv", "woe:centroid": [-74.182449, 40.941631], "geom:latitude": 40.941631, "geom:longitude": -74.182449, "geom:hash": "dr70zvjyr9hv", "woe:latitude": 40.941631, "geom:centroid": [-74.182449, 40.941631], "woe:longitude": -74.182449, "woe:repo": "woeplanet-poi-us"}, "geometry": {"coordinates": [-74.182449, 40.941631], "type": "Point"}}