{"type": "Feature", "id": 23598384, "properties": {"woe:id": 23598384, "woe:parent_id": 2357779, "woe:name": "Avilla Elementary School", "woe:placetype": 20, "woe:placetype_name": "POI", "woe:lang": "ENG", "iso:country": "US", "meta:provider": ["geoplanet:7.3.1", "geoplanet:7.3.2", "geoplanet:7.4.0", "geoplanet:7.4.1", "geoplanet:7.5.1", "geoplanet:7.5.2", "geoplanet:7.6.0", "geoplanet:7.8.1", "geoplanet:7.9.0", "geoplanet:7.10.0", "geoplanet:8.0.0", "woeplanet:8.0.0"], "meta:indexed": "2020-08-20T20:18:44.248974", "woe:alias_ENG_V": ["Avilla Elementary"], "meta:updated": "2020-08-22T02:57:40.786713", "woe:hierarchy": {"continent": 24865672, "country": 23424977, "town": 0, "planet": 1, "county": 12589014, "suburb": 0, "state": 2347584, "region": 0, "localadmin": 0}, "woe:timezone_id": 56043661, "woe:hash": "9yt5d4bdxb6m", "woe:centroid": [-94.129837, 37.193272], "geom:latitude": 37.193272, "geom:longitude": -94.129837, "geom:hash": "9yt5d4bdxb6m", "woe:latitude": 37.193272, "geom:centroid": [-94.129837, 37.193272], "woe:longitude": -94.129837, "woe:repo": "woeplanet-poi-us"}, "geometry": {"coordinates": [-94.129837, 37.193272], "type": "Point"}}