{"type": "Feature", "id": 23576789, "properties": {"woe:id": 23576789, "woe:parent_id": 23512127, "woe:name": "G. W. Carver High School", "woe:placetype": 20, "woe:placetype_name": "POI", "woe:lang": "ENG", "iso:country": "US", "meta:provider": ["geoplanet:7.3.2", "geoplanet:7.4.0", "geoplanet:7.4.1", "geoplanet:7.5.1", "geoplanet:7.5.2", "geoplanet:7.6.0", "geoplanet:7.8.1", "geoplanet:7.9.0", "geoplanet:7.10.0", "geoplanet:8.0.0", "woeplanet:8.0.0"], "meta:indexed": "2020-08-20T22:02:21.511399", "woe:alias_ENG_V": ["G. W. Carver Senior High School", "G. W. Carver High", "G. W. Carver Senior High", "G. W. Carver HS", "G. W. Carver Senior HS"], "meta:updated": "2020-08-22T02:58:47.628291", "woe:hierarchy": {"continent": 24865672, "country": 23424977, "town": 0, "planet": 1, "county": 12588631, "suburb": 0, "state": 2347577, "region": 0, "localadmin": 0}, "woe:timezone_id": 56043661, "woe:hash": "9vrfxhh7z3zn", "woe:centroid": [-90.037788, 29.99333], "geom:latitude": 29.99333, "geom:longitude": -90.037788, "geom:hash": "9vrfxhh7z3zn", "woe:latitude": 29.99333, "geom:centroid": [-90.037788, 29.99333], "woe:longitude": -90.037788, "woe:repo": "woeplanet-poi-us"}, "geometry": {"coordinates": [-90.037788, 29.99333], "type": "Point"}}