{"type": "Feature", "id": 23620112, "properties": {"woe:id": 23620112, "woe:parent_id": 2485936, "woe:name": "Edwards-knox Junior High School", "woe:placetype": 20, "woe:placetype_name": "POI", "woe:lang": "ENG", "iso:country": "US", "meta:provider": ["geoplanet:7.3.1", "geoplanet:7.3.2", "geoplanet:7.4.0", "geoplanet:7.4.1", "geoplanet:7.5.1", "geoplanet:7.5.2", "geoplanet:7.6.0", "geoplanet:7.8.1", "geoplanet:7.9.0", "geoplanet:7.10.0", "geoplanet:8.0.0", "woeplanet:8.0.0"], "meta:indexed": "2020-08-20T20:18:51.490483", "woe:alias_ENG_V": ["Edwards-knox Junior High"], "meta:updated": "2020-08-22T02:57:43.699074", "woe:hierarchy": {"continent": 24865672, "country": 23424977, "town": 0, "planet": 1, "county": 12589361, "suburb": 0, "state": 2347591, "region": 0, "localadmin": 0}, "woe:timezone_id": 56043648, "woe:hash": "drfs2sqc7x9v", "woe:centroid": [-75.20298, 44.364422], "geom:latitude": 44.364422, "geom:longitude": -75.20298, "geom:hash": "drfs2sqc7x9v", "woe:latitude": 44.364422, "geom:centroid": [-75.20298, 44.364422], "woe:longitude": -75.20298, "woe:repo": "woeplanet-poi-us"}, "geometry": {"coordinates": [-75.20298, 44.364422], "type": "Point"}}