{"type": "Feature", "id": 23667411, "geometry": {"type": "Point", "coordinates": [-77.415451, 37.206329]}, "properties": {"woe:id": 23667411, "woe:parent_id": 2470959, "woe:name": "A. P. Hill Elementary School", "woe:placetype": 20, "woe:placetype_name": "POI", "woe:lang": "ENG", "iso:country": "US", "meta:provider": ["geoplanet:7.3.1", "geoplanet:7.3.2", "geoplanet:7.4.0", "geoplanet:7.4.1", "geoplanet:7.5.1", "geoplanet:7.5.2", "geoplanet:7.6.0", "geoplanet:7.8.1", "geoplanet:7.9.0", "geoplanet:7.10.0", "geoplanet:8.0.0", "woeplanet:8.0.0"], "meta:indexed": "2020-08-20T20:19:08.748470", "woe:alias_ENG_V": ["Ap Hill Elementary School", "A. P. Hill Elementary"], "meta:updated": "2020-10-14T11:19:38.546213", "woe:hierarchy": {"continent": 24865672, "country": 23424977, "town": 0, "planet": 1, "county": 12590399, "suburb": 0, "state": 2347605, "region": 0, "localadmin": 0}, "woe:timezone_id": 56043648, "woe:hash": "dq8gwm5y94rv", "woe:centroid": [-77.415451, 37.206329], "geom:latitude": 37.206329, "geom:longitude": -77.415451, "geom:hash": "dq8gwm5y94rv", "woe:latitude": 37.206329, "geom:centroid": [-77.415451, 37.206329], "woe:longitude": -77.415451, "woe:repo": "woeplanet-poi-us", "geom:area": 0.0, "woe:scale": 19}}