{"type": "Feature", "id": 23565111, "geometry": {"type": "Point", "coordinates": [-89.07679, 42.286839]}, "properties": {"woe:id": 23565111, "woe:parent_id": 55861490, "woe:name": "Walker Elementary School", "woe:placetype": 20, "woe:placetype_name": "POI", "woe:lang": "ENG", "iso:country": "US", "meta:provider": ["geoplanet:7.3.1", "geoplanet:7.3.2", "geoplanet:7.4.0", "geoplanet:7.4.1", "geoplanet:7.5.1", "geoplanet:7.5.2", "geoplanet:7.6.0", "geoplanet:7.8.1", "geoplanet:7.9.0", "geoplanet:7.10.0", "geoplanet:8.0.0", "woeplanet:8.0.0"], "meta:indexed": "2020-08-20T20:18:33.498735", "woe:alias_ENG_V": ["Walker Elementary"], "meta:updated": "2020-10-14T11:20:11.129414", "woe:hierarchy": {"continent": 24865672, "country": 23424977, "town": 0, "planet": 1, "county": 12588178, "suburb": 0, "state": 2347572, "region": 0, "localadmin": 0}, "woe:timezone_id": 56043661, "woe:hash": "dp88t4068q5k", "woe:centroid": [-89.07679, 42.286839], "geom:latitude": 42.286839, "geom:longitude": -89.07679, "geom:hash": "dp88t4068q5k", "woe:latitude": 42.286839, "geom:centroid": [-89.07679, 42.286839], "woe:longitude": -89.07679, "woe:repo": "woeplanet-poi-us", "geom:area": 0.0, "woe:scale": 19}}