{"type": "Feature", "id": 23664767, "properties": {"woe:id": 23664767, "woe:parent_id": 2403815, "woe:name": "Cherry Run Elementary School", "woe:placetype": 20, "woe:placetype_name": "POI", "woe:lang": "ENG", "iso:country": "US", "meta:provider": ["geoplanet:7.3.1", "geoplanet:7.3.2", "geoplanet:7.4.0", "geoplanet:7.4.1", "geoplanet:7.5.1", "geoplanet:7.5.2", "geoplanet:7.6.0", "geoplanet:7.8.1", "geoplanet:7.9.0", "geoplanet:7.10.0", "geoplanet:8.0.0", "woeplanet:8.0.0"], "meta:indexed": "2020-08-20T20:19:07.891014", "woe:alias_ENG_V": ["Cherry Run Elementary"], "meta:updated": "2020-08-22T02:57:51.160468", "woe:hierarchy": {"continent": 24865672, "country": 23424977, "town": 0, "planet": 1, "county": 12590343, "suburb": 0, "state": 2347605, "region": 0, "localadmin": 0}, "woe:timezone_id": 56043648, "woe:hash": "dqch93kvu62s", "woe:centroid": [-77.282112, 38.767632], "geom:latitude": 38.767632, "geom:longitude": -77.282112, "geom:hash": "dqch93kvu62s", "woe:latitude": 38.767632, "geom:centroid": [-77.282112, 38.767632], "woe:longitude": -77.282112, "woe:repo": "woeplanet-poi-us"}, "geometry": {"coordinates": [-77.282112, 38.767632], "type": "Point"}}