{"type": "Feature", "id": 23654543, "properties": {"woe:id": 23654543, "woe:parent_id": 55993605, "woe:name": "Charles Middle School", "woe:placetype": 20, "woe:placetype_name": "POI", "woe:lang": "ENG", "iso:country": "US", "meta:provider": ["geoplanet:7.3.1", "geoplanet:7.3.2", "geoplanet:7.4.0", "geoplanet:7.4.1", "geoplanet:7.5.1", "geoplanet:7.5.2", "geoplanet:7.6.0", "geoplanet:7.8.1", "geoplanet:7.9.0", "geoplanet:7.10.0", "geoplanet:8.0.0", "woeplanet:8.0.0"], "meta:indexed": "2020-08-20T20:19:03.417154", "meta:updated": "2020-08-22T02:57:49.083678", "woe:alias_ENG_V": ["He Charles Middle School"], "woe:hierarchy": {"continent": 24865672, "country": 23424977, "town": 0, "planet": 1, "county": 12590076, "suburb": 0, "state": 2347602, "region": 0, "localadmin": 0}, "woe:timezone_id": 56043665, "woe:hash": "9tsmd47nrcfx", "woe:centroid": [-106.431091, 31.91774], "geom:latitude": 31.91774, "geom:longitude": -106.431091, "geom:hash": "9tsmd47nrcfx", "woe:latitude": 31.91774, "geom:centroid": [-106.431091, 31.91774], "woe:longitude": -106.431091, "woe:repo": "woeplanet-poi-us"}, "geometry": {"coordinates": [-106.431091, 31.91774], "type": "Point"}}