{"type": "Feature", "id": 23593391, "properties": {"woe:id": 23593391, "woe:parent_id": 55806454, "woe:name": "South Senior School", "woe:placetype": 20, "woe:placetype_name": "POI", "woe:lang": "ENG", "iso:country": "US", "meta:provider": ["geoplanet:7.3.1", "geoplanet:7.3.2", "geoplanet:7.4.0", "geoplanet:7.4.1", "geoplanet:7.5.1", "geoplanet:7.5.2", "geoplanet:7.6.0", "geoplanet:7.8.1", "geoplanet:7.9.0", "geoplanet:7.10.0", "geoplanet:8.0.0", "woeplanet:8.0.0"], "meta:indexed": "2020-08-20T20:18:42.416254", "woe:alias_ENG_V": ["South High School", "S Senior School"], "meta:updated": "2020-08-22T02:57:39.955911", "woe:hierarchy": {"continent": 24865672, "country": 23424977, "town": 0, "planet": 1, "county": 12588823, "suburb": 0, "state": 2347582, "region": 0, "localadmin": 0}, "woe:timezone_id": 56043661, "woe:hash": "9zvxwnjh7pwt", "woe:centroid": [-93.244949, 44.945839], "geom:latitude": 44.945839, "geom:longitude": -93.244949, "geom:hash": "9zvxwnjh7pwt", "woe:latitude": 44.945839, "geom:centroid": [-93.244949, 44.945839], "woe:longitude": -93.244949, "woe:repo": "woeplanet-poi-us"}, "geometry": {"coordinates": [-93.244949, 44.945839], "type": "Point"}}