{"type": "Feature", "id": 23561479, "geometry": {"type": "Point", "coordinates": [-87.688492, 39.604469]}, "properties": {"woe:id": 23561479, "woe:parent_id": 2468283, "woe:name": "Memorial Elementary School", "woe:placetype": 20, "woe:placetype_name": "POI", "woe:lang": "ENG", "iso:country": "US", "meta:provider": ["geoplanet:7.3.1", "geoplanet:7.3.2", "geoplanet:7.4.0", "geoplanet:7.4.1", "geoplanet:7.5.1", "geoplanet:7.5.2", "geoplanet:7.6.0", "geoplanet:7.8.1", "geoplanet:7.9.0", "geoplanet:7.10.0", "geoplanet:8.0.0", "woeplanet:8.0.0"], "meta:indexed": "2020-08-20T20:18:32.142481", "woe:alias_ENG_V": ["Memorial Elementary"], "meta:updated": "2020-10-14T11:20:19.657230", "woe:hierarchy": {"continent": 24865672, "country": 23424977, "town": 0, "planet": 1, "county": 12588100, "suburb": 0, "state": 2347572, "region": 0, "localadmin": 0}, "woe:timezone_id": 56043661, "woe:hash": "dp19k9g0y017", "woe:centroid": [-87.688492, 39.604469], "geom:latitude": 39.604469, "geom:longitude": -87.688492, "geom:hash": "dp19k9g0y017", "woe:latitude": 39.604469, "geom:centroid": [-87.688492, 39.604469], "woe:longitude": -87.688492, "woe:repo": "woeplanet-poi-us", "geom:area": 0.0, "woe:scale": 19}}