{"type": "Feature", "id": 23531795, "properties": {"woe:id": 23531795, "woe:parent_id": 55969929, "woe:name": "L.a. County High School For the Arts", "woe:placetype": 20, "woe:placetype_name": "POI", "woe:lang": "ENG", "iso:country": "US", "meta:provider": ["geoplanet:7.3.2", "geoplanet:7.4.0", "geoplanet:7.4.1", "geoplanet:7.5.1", "geoplanet:7.5.2", "geoplanet:7.6.0", "geoplanet:7.8.1", "geoplanet:7.9.0", "geoplanet:7.10.0", "geoplanet:8.0.0", "woeplanet:8.0.0"], "meta:indexed": "2020-08-20T22:02:02.731417", "meta:updated": "2020-08-22T02:58:46.381272", "woe:alias_ENG_V": ["L.a. County Senior High For the Arts", "L.a. County High School For the Arts", "L.a. County High For the Arts", "L.a. County Senior HS For the Arts", "L.a. County HS For the Arts", "La County High for The Arts", "La County High School for The Arts", "La County HS for The Arts", "La County Senior High for The Arts", "La County Senior High School for The Arts", "La County Senior HS for The Arts"], "woe:hierarchy": {"continent": 24865672, "country": 23424977, "town": 0, "planet": 1, "county": 12587688, "suburb": 0, "state": 2347563, "region": 0, "localadmin": 0}, "woe:timezone_id": 56043663, "woe:hash": "9q5cz0b6hx5w", "woe:centroid": [-118.168404, 34.062119], "geom:latitude": 34.062119, "geom:longitude": -118.168404, "geom:hash": "9q5cz0b6hx5w", "woe:latitude": 34.062119, "geom:centroid": [-118.168404, 34.062119], "woe:longitude": -118.168404, "woe:repo": "woeplanet-poi-us"}, "geometry": {"coordinates": [-118.168404, 34.062119], "type": "Point"}}