{"type": "Feature", "id": 23629712, "geometry": {"type": "Point", "coordinates": [-84.35997, 39.284672]}, "properties": {"woe:id": 23629712, "woe:parent_id": 2368404, "woe:name": "Stewart Elementary School", "woe:placetype": 20, "woe:placetype_name": "POI", "woe:lang": "ENG", "iso:country": "US", "meta:provider": ["geoplanet:7.3.1", "geoplanet:7.3.2", "geoplanet:7.4.0", "geoplanet:7.4.1", "geoplanet:7.5.1", "geoplanet:7.5.2", "geoplanet:7.6.0", "geoplanet:7.8.1", "geoplanet:7.9.0", "geoplanet:7.10.0", "geoplanet:8.0.0", "woeplanet:8.0.0"], "meta:indexed": "2020-08-20T20:18:54.358846", "woe:alias_ENG_V": ["Stewart Elementary"], "meta:updated": "2020-10-14T11:19:52.350903", "woe:hierarchy": {"continent": 24865672, "country": 23424977, "town": 0, "planet": 1, "county": 12589557, "suburb": 0, "state": 2347594, "region": 0, "localadmin": 0}, "woe:timezone_id": 56043648, "woe:hash": "dnup2rdcy1xh", "woe:centroid": [-84.35997, 39.284672], "geom:latitude": 39.284672, "geom:longitude": -84.35997, "geom:hash": "dnup2rdcy1xh", "woe:latitude": 39.284672, "geom:centroid": [-84.35997, 39.284672], "woe:longitude": -84.35997, "woe:repo": "woeplanet-poi-us", "geom:area": 0.0, "woe:scale": 19}}