{"type": "Feature", "id": 23576037, "properties": {"woe:id": 23576037, "woe:parent_id": 2444146, "woe:name": "Central High School", "woe:placetype": 20, "woe:placetype_name": "POI", "woe:lang": "ENG", "iso:country": "US", "meta:provider": ["geoplanet:7.3.1", "geoplanet:7.3.2", "geoplanet:7.4.0", "geoplanet:7.4.1", "geoplanet:7.5.1", "geoplanet:7.5.2", "geoplanet:7.6.0", "geoplanet:7.8.1", "geoplanet:7.9.0", "geoplanet:7.10.0", "geoplanet:8.0.0", "woeplanet:8.0.0"], "meta:indexed": "2020-08-20T20:18:37.376386", "woe:alias_ENG_V": ["Central Senior High School", "Central High", "Central Senior High", "Central HS", "Central Senior HS"], "meta:updated": "2020-08-22T02:58:47.601807", "woe:hierarchy": {"continent": 24865672, "country": 23424977, "town": 0, "planet": 1, "county": 12588612, "suburb": 0, "state": 2347577, "region": 0, "localadmin": 0}, "woe:timezone_id": 56043661, "woe:hash": "9vrm8zdqv8b7", "woe:centroid": [-91.018402, 30.540409], "geom:latitude": 30.540409, "geom:longitude": -91.018402, "geom:hash": "9vrm8zdqv8b7", "woe:latitude": 30.540409, "geom:centroid": [-91.018402, 30.540409], "woe:longitude": -91.018402, "woe:repo": "woeplanet-poi-us"}, "geometry": {"coordinates": [-91.018402, 30.540409], "type": "Point"}}