{"type": "Feature", "id": 23667195, "properties": {"woe:id": 23667195, "woe:parent_id": 2444628, "woe:name": "Manassas Park High School", "woe:placetype": 20, "woe:placetype_name": "POI", "woe:lang": "ENG", "iso:country": "US", "meta:provider": ["geoplanet:7.3.2", "geoplanet:7.4.0", "geoplanet:7.4.1", "geoplanet:7.5.1", "geoplanet:7.5.2", "geoplanet:7.6.0", "geoplanet:7.8.1", "geoplanet:7.9.0", "geoplanet:7.10.0", "geoplanet:8.0.0", "woeplanet:8.0.0"], "meta:indexed": "2020-08-20T22:02:58.976106", "woe:alias_ENG_V": ["Manassas Park Senior High School", "Manassas Park High", "Manassas Park Senior High", "Manassas Park HS", "Manassas Park Senior HS"], "meta:updated": "2020-08-22T02:58:50.226572", "woe:hierarchy": {"continent": 24865672, "country": 23424977, "town": 0, "planet": 1, "county": 12590382, "suburb": 0, "state": 2347605, "region": 0, "localadmin": 0}, "woe:timezone_id": 56043648, "woe:hash": "dqbutgdz8xqt", "woe:centroid": [-77.43882, 38.780319], "geom:latitude": 38.780319, "geom:longitude": -77.43882, "geom:hash": "dqbutgdz8xqt", "woe:latitude": 38.780319, "geom:centroid": [-77.43882, 38.780319], "woe:longitude": -77.43882, "woe:repo": "woeplanet-poi-us"}, "geometry": {"coordinates": [-77.43882, 38.780319], "type": "Point"}}