{"type": "Feature", "id": 23628599, "properties": {"woe:id": 23628599, "woe:parent_id": 2511899, "woe:name": "Versailles High School", "woe:placetype": 20, "woe:placetype_name": "POI", "woe:lang": "ENG", "iso:country": "US", "meta:provider": ["geoplanet:7.3.1", "geoplanet:7.3.2", "geoplanet:7.4.0", "geoplanet:7.4.1", "geoplanet:7.5.1", "geoplanet:7.5.2", "geoplanet:7.6.0", "geoplanet:7.8.1", "geoplanet:7.9.0", "geoplanet:7.10.0", "geoplanet:8.0.0", "woeplanet:8.0.0"], "meta:indexed": "2020-08-20T20:18:53.796741", "woe:alias_ENG_V": ["Versailles Senior High School", "Versailles High", "Versailles Senior High", "Versailles HS", "Versailles Senior HS"], "meta:updated": "2020-08-22T02:58:49.110834", "woe:hierarchy": {"continent": 24865672, "country": 23424977, "town": 0, "planet": 1, "county": 12589545, "suburb": 0, "state": 2347594, "region": 0, "localadmin": 0}, "woe:timezone_id": 56043648, "woe:hash": "dp5uv983wzqj", "woe:centroid": [-84.484222, 40.218498], "geom:latitude": 40.218498, "geom:longitude": -84.484222, "geom:hash": "dp5uv983wzqj", "woe:latitude": 40.218498, "geom:centroid": [-84.484222, 40.218498], "woe:longitude": -84.484222, "woe:repo": "woeplanet-poi-us"}, "geometry": {"coordinates": [-84.484222, 40.218498], "type": "Point"}}