{"type": "Feature", "id": 23514010, "geometry": {"type": "Point", "coordinates": [-88.136307, 30.7054]}, "properties": {"woe:id": 23514010, "woe:parent_id": 56017655, "woe:name": "St Ignatius Catholic School", "woe:placetype": 20, "woe:placetype_name": "POI", "woe:lang": "ENG", "iso:country": "US", "meta:provider": ["geoplanet:7.3.2", "geoplanet:7.4.0", "geoplanet:7.4.1", "geoplanet:7.5.1", "geoplanet:7.5.2", "geoplanet:7.6.0", "geoplanet:7.8.1", "geoplanet:7.9.0", "geoplanet:7.10.0", "geoplanet:8.0.0", "woeplanet:8.0.0"], "meta:indexed": "2020-08-20T22:01:55.593765", "meta:updated": "2020-10-14T11:20:04.223078", "woe:alias_ENG_V": ["St Ignatius School"], "woe:hierarchy": {"continent": 24865672, "country": 23424977, "town": 0, "planet": 1, "county": 12587535, "suburb": 0, "state": 2347559, "region": 0, "localadmin": 0}, "woe:timezone_id": 56043661, "woe:hash": "dj3qdmtpgjqj", "woe:centroid": [-88.136307, 30.7054], "geom:latitude": 30.7054, "geom:longitude": -88.136307, "geom:hash": "dj3qdmtpgjqj", "woe:latitude": 30.7054, "geom:centroid": [-88.136307, 30.7054], "woe:longitude": -88.136307, "woe:repo": "woeplanet-poi-us", "geom:area": 0.0, "woe:scale": 19}}