{"type": "Feature", "id": 23639223, "geometry": {"type": "Point", "coordinates": [-78.395851, 40.50946]}, "properties": {"woe:id": 23639223, "woe:parent_id": 2353991, "woe:name": "Altoona Catholic/st Marys School", "woe:placetype": 20, "woe:placetype_name": "POI", "woe:lang": "ENG", "iso:country": "US", "meta:provider": ["geoplanet:7.3.1", "geoplanet:7.3.2", "geoplanet:7.4.0", "geoplanet:7.4.1", "geoplanet:7.5.1", "geoplanet:7.5.2", "geoplanet:7.6.0", "geoplanet:7.8.1", "geoplanet:7.9.0", "geoplanet:7.10.0", "geoplanet:8.0.0", "woeplanet:8.0.0"], "meta:indexed": "2020-08-20T20:18:58.110322", "meta:updated": "2020-10-14T11:19:45.812099", "woe:hierarchy": {"continent": 24865672, "country": 23424977, "town": 0, "planet": 1, "county": 12589734, "suburb": 0, "state": 2347597, "region": 0, "localadmin": 0}, "woe:timezone_id": 56043648, "woe:hash": "dr0q2n9bsq8t", "woe:centroid": [-78.395851, 40.50946], "geom:latitude": 40.50946, "geom:longitude": -78.395851, "geom:hash": "dr0q2n9bsq8t", "woe:latitude": 40.50946, "geom:centroid": [-78.395851, 40.50946], "woe:longitude": -78.395851, "woe:repo": "woeplanet-poi-us", "geom:area": 0.0, "woe:scale": 19}}