{"type": "Feature", "id": 23684020, "properties": {"woe:id": 23684020, "woe:parent_id": 55981421, "woe:name": "Tropicana Field", "woe:placetype": 20, "woe:placetype_name": "POI", "woe:lang": "ENG", "iso:country": "US", "meta:provider": ["geoplanet:7.3.1", "geoplanet:7.3.2", "geoplanet:7.4.0", "geoplanet:7.4.1", "geoplanet:7.5.1", "geoplanet:7.5.2", "geoplanet:7.6.0", "geoplanet:7.8.1", "geoplanet:7.9.0", "geoplanet:7.10.0", "geoplanet:8.0.0", "woeplanet:8.0.0"], "meta:indexed": "2020-08-20T20:19:12.676566", "meta:updated": "2020-08-22T02:58:18.655757", "woe:hierarchy": {"continent": 24865672, "country": 23424977, "town": 0, "planet": 1, "county": 12587854, "suburb": 0, "state": 2347568, "region": 0, "localadmin": 0}, "woe:timezone_id": 56043648, "woe:hash": "dhvjznvwhmqh", "woe:centroid": [-82.653389, 27.76763], "geom:latitude": 27.76763, "geom:longitude": -82.653389, "geom:hash": "dhvjznvwhmqh", "woe:latitude": 27.76763, "geom:centroid": [-82.653389, 27.76763], "woe:longitude": -82.653389, "woe:repo": "woeplanet-poi-us"}, "geometry": {"coordinates": [-82.653389, 27.76763], "type": "Point"}}