{"type": "Feature", "id": 23517665, "geometry": {"type": "Point", "coordinates": [-112.02739, 34.737068]}, "properties": {"woe:id": 23517665, "woe:parent_id": 2385640, "woe:name": "Verde Valley Christian School", "woe:placetype": 20, "woe:placetype_name": "POI", "woe:lang": "ENG", "iso:country": "US", "meta:provider": ["geoplanet:7.3.2", "geoplanet:7.4.0", "geoplanet:7.4.1", "geoplanet:7.5.1", "geoplanet:7.5.2", "geoplanet:7.6.0", "geoplanet:7.8.1", "geoplanet:7.9.0", "geoplanet:7.10.0", "geoplanet:8.0.0", "woeplanet:8.0.0"], "meta:indexed": "2020-08-20T22:01:57.134195", "meta:updated": "2020-10-14T11:20:22.408936", "woe:alias_ENG_V": ["Sedona Christian School"], "woe:hierarchy": {"continent": 24865672, "country": 23424977, "town": 0, "planet": 1, "county": 12587593, "suburb": 0, "state": 2347561, "region": 0, "localadmin": 0}, "woe:timezone_id": 56043666, "woe:hash": "9w0mdg8nhdg9", "woe:centroid": [-112.02739, 34.737068], "geom:latitude": 34.737068, "geom:longitude": -112.02739, "geom:hash": "9w0mdg8nhdg9", "woe:latitude": 34.737068, "geom:centroid": [-112.02739, 34.737068], "woe:longitude": -112.02739, "woe:repo": "woeplanet-poi-us", "geom:area": 0.0, "woe:scale": 19}}