{"type": "Feature", "id": 23681910, "properties": {"woe:id": 23681910, "woe:parent_id": 2491192, "woe:name": "Shadeland Station", "woe:placetype": 20, "woe:placetype_name": "POI", "woe:lang": "ENG", "iso:country": "US", "meta:provider": ["geoplanet:7.3.1", "geoplanet:7.3.2", "geoplanet:7.4.0", "geoplanet:7.4.1", "geoplanet:7.5.1", "geoplanet:7.5.2", "geoplanet:7.6.0", "geoplanet:7.8.1", "geoplanet:7.9.0", "geoplanet:7.10.0", "geoplanet:8.0.0", "woeplanet:8.0.0"], "meta:indexed": "2020-08-20T20:19:19.399647", "meta:updated": "2020-08-22T02:58:22.206144", "woe:hierarchy": {"continent": 24865672, "country": 23424977, "town": 0, "planet": 1, "county": 12588258, "suburb": 0, "state": 2347573, "region": 0, "localadmin": 0}, "woe:timezone_id": 56043656, "woe:hash": "dp4jtme0uu3z", "woe:centroid": [-86.952461, 40.372162], "geom:latitude": 40.372162, "geom:longitude": -86.952461, "geom:hash": "dp4jtme0uu3z", "woe:latitude": 40.372162, "geom:centroid": [-86.952461, 40.372162], "woe:longitude": -86.952461, "woe:repo": "woeplanet-poi-us"}, "geometry": {"coordinates": [-86.952461, 40.372162], "type": "Point"}}