{"type": "Feature", "id": 23642059, "geometry": {"type": "Point", "coordinates": [-75.954819, 40.058491]}, "properties": {"woe:id": 23642059, "woe:parent_id": 2496332, "woe:name": "Stoney Lane School", "woe:placetype": 20, "woe:placetype_name": "POI", "woe:lang": "ENG", "iso:country": "US", "meta:provider": ["geoplanet:7.3.2", "geoplanet:7.4.0", "geoplanet:7.4.1", "geoplanet:7.5.1", "geoplanet:7.5.2", "geoplanet:7.6.0", "geoplanet:7.8.1", "geoplanet:7.9.0", "geoplanet:7.10.0", "geoplanet:8.0.0", "woeplanet:8.0.0"], "meta:indexed": "2020-08-20T22:02:47.926649", "meta:updated": "2020-10-14T11:19:47.606163", "woe:hierarchy": {"continent": 24865672, "country": 23424977, "town": 0, "planet": 1, "county": 12589763, "suburb": 0, "state": 2347597, "region": 0, "localadmin": 0}, "woe:timezone_id": 56043648, "woe:hash": "dr1gzs7ms7yn", "woe:centroid": [-75.954819, 40.058491], "geom:latitude": 40.058491, "geom:longitude": -75.954819, "geom:hash": "dr1gzs7ms7yn", "woe:latitude": 40.058491, "geom:centroid": [-75.954819, 40.058491], "woe:longitude": -75.954819, "woe:repo": "woeplanet-poi-us", "geom:area": 0.0, "woe:scale": 19}}