{"type": "Feature", "id": 23648499, "geometry": {"type": "Point", "coordinates": [-100.35334, 44.379822]}, "properties": {"woe:id": 23648499, "woe:parent_id": 2471666, "woe:name": "Jefferson Elementary School", "woe:placetype": 20, "woe:placetype_name": "POI", "woe:lang": "ENG", "iso:country": "US", "meta:provider": ["geoplanet:7.3.1", "geoplanet:7.3.2", "geoplanet:7.4.0", "geoplanet:7.4.1", "geoplanet:7.5.1", "geoplanet:7.5.2", "geoplanet:7.6.0", "geoplanet:7.8.1", "geoplanet:7.9.0", "geoplanet:7.10.0", "geoplanet:8.0.0", "woeplanet:8.0.0"], "meta:indexed": "2020-08-20T20:19:01.192383", "woe:alias_ENG_V": ["Jefferson Elementary"], "meta:updated": "2020-10-14T11:19:40.714757", "woe:hierarchy": {"continent": 24865672, "country": 23424977, "town": 0, "planet": 1, "county": 12589877, "suburb": 0, "state": 2347600, "region": 0, "localadmin": 0}, "woe:timezone_id": 56043661, "woe:hash": "9zbskrhgjwqn", "woe:centroid": [-100.35334, 44.379822], "geom:latitude": 44.379822, "geom:longitude": -100.35334, "geom:hash": "9zbskrhgjwqn", "woe:latitude": 44.379822, "geom:centroid": [-100.35334, 44.379822], "woe:longitude": -100.35334, "woe:repo": "woeplanet-poi-us", "geom:area": 0.0, "woe:scale": 19}}