{"type": "Feature", "id": 23668299, "geometry": {"type": "Point", "coordinates": [-122.52243, 45.65728]}, "properties": {"woe:id": 23668299, "woe:parent_id": 55862330, "woe:name": "Burnt Bridge Creek Elementary School", "woe:placetype": 20, "woe:placetype_name": "POI", "woe:lang": "ENG", "iso:country": "US", "meta:provider": ["geoplanet:7.3.1", "geoplanet:7.3.2", "geoplanet:7.4.0", "geoplanet:7.4.1", "geoplanet:7.5.1", "geoplanet:7.5.2", "geoplanet:7.6.0", "geoplanet:7.8.1", "geoplanet:7.9.0", "geoplanet:7.10.0", "geoplanet:8.0.0", "woeplanet:8.0.0"], "meta:indexed": "2020-08-20T20:19:09.077363", "woe:alias_ENG_V": ["Burnt Brg Creek Elementary School", "Burnt Bridge Creek Elementary"], "meta:updated": "2020-10-14T11:19:35.087700", "woe:hierarchy": {"continent": 24865672, "country": 23424977, "town": 0, "planet": 1, "county": 12590445, "suburb": 0, "state": 2347606, "region": 0, "localadmin": 0}, "woe:timezone_id": 56043663, "woe:hash": "c20geztuumye", "woe:centroid": [-122.52243, 45.65728], "geom:latitude": 45.65728, "geom:longitude": -122.52243, "geom:hash": "c20geztuumye", "woe:latitude": 45.65728, "geom:centroid": [-122.52243, 45.65728], "woe:longitude": -122.52243, "woe:repo": "woeplanet-poi-us", "geom:area": 0.0, "woe:scale": 19}}