{"type": "Feature", "id": 23658252, "geometry": {"type": "Point", "coordinates": [-96.870972, 29.908449]}, "properties": {"woe:id": 23658252, "woe:parent_id": 2434209, "woe:name": "La Grange Middle School", "woe:placetype": 20, "woe:placetype_name": "POI", "woe:lang": "ENG", "iso:country": "US", "meta:provider": ["geoplanet:7.3.1", "geoplanet:7.3.2", "geoplanet:7.4.0", "geoplanet:7.4.1", "geoplanet:7.5.1", "geoplanet:7.5.2", "geoplanet:7.6.0", "geoplanet:7.8.1", "geoplanet:7.9.0", "geoplanet:7.10.0", "geoplanet:8.0.0", "woeplanet:8.0.0"], "meta:indexed": "2020-08-20T20:19:05.336381", "meta:updated": "2020-10-14T11:19:43.604125", "woe:hierarchy": {"continent": 24865672, "country": 23424977, "town": 0, "planet": 1, "county": 12590081, "suburb": 0, "state": 2347602, "region": 0, "localadmin": 0}, "woe:timezone_id": 56043661, "woe:hash": "9v745sstqdzz", "woe:centroid": [-96.870972, 29.908449], "geom:latitude": 29.908449, "geom:longitude": -96.870972, "geom:hash": "9v745sstqdzz", "woe:latitude": 29.908449, "geom:centroid": [-96.870972, 29.908449], "woe:longitude": -96.870972, "woe:repo": "woeplanet-poi-us", "geom:area": 0.0, "woe:scale": 19}}