{"type": "Feature", "id": 23639050, "properties": {"woe:id": 23639050, "woe:parent_id": 55992591, "woe:name": "Southern Middle School", "woe:placetype": 20, "woe:placetype_name": "POI", "woe:lang": "ENG", "iso:country": "US", "meta:provider": ["geoplanet:7.3.1", "geoplanet:7.3.2", "geoplanet:7.4.0", "geoplanet:7.4.1", "geoplanet:7.5.1", "geoplanet:7.5.2", "geoplanet:7.6.0", "geoplanet:7.8.1", "geoplanet:7.9.0", "geoplanet:7.10.0", "geoplanet:8.0.0", "woeplanet:8.0.0"], "meta:indexed": "2020-08-20T20:18:58.053508", "meta:updated": "2020-08-22T02:57:46.483727", "woe:hierarchy": {"continent": 24865672, "country": 23424977, "town": 0, "planet": 1, "county": 12589733, "suburb": 0, "state": 2347597, "region": 0, "localadmin": 0}, "woe:timezone_id": 56043648, "woe:hash": "dr4j2qjr71q1", "woe:centroid": [-75.919167, 40.332062], "geom:latitude": 40.332062, "geom:longitude": -75.919167, "geom:hash": "dr4j2qjr71q1", "woe:latitude": 40.332062, "geom:centroid": [-75.919167, 40.332062], "woe:longitude": -75.919167, "woe:repo": "woeplanet-poi-us"}, "geometry": {"coordinates": [-75.919167, 40.332062], "type": "Point"}}