{"type": "Feature", "id": 23679527, "properties": {"woe:id": 23679527, "woe:parent_id": 2500361, "woe:name": "Verducci Hall", "woe:placetype": 20, "woe:placetype_name": "POI", "woe:lang": "ENG", "iso:country": "US", "meta:provider": ["geoplanet:7.3.1", "geoplanet:7.3.2", "geoplanet:7.4.0", "geoplanet:7.4.1", "geoplanet:7.5.1", "geoplanet:7.5.2", "geoplanet:7.6.0", "geoplanet:7.8.1", "geoplanet:7.9.0", "geoplanet:7.10.0", "geoplanet:8.0.0", "woeplanet:8.0.0"], "meta:indexed": "2020-08-20T20:19:12.479456", "meta:updated": "2020-08-22T02:58:18.606784", "woe:hierarchy": {"continent": 24865672, "country": 23424977, "town": 0, "planet": 1, "county": 12587707, "suburb": 0, "state": 2347563, "region": 0, "localadmin": 0}, "woe:timezone_id": 56043663, "woe:hash": "9q8ysgds1c2d", "woe:centroid": [-122.483063, 37.724998], "geom:latitude": 37.724998, "geom:longitude": -122.483063, "geom:hash": "9q8ysgds1c2d", "woe:latitude": 37.724998, "geom:centroid": [-122.483063, 37.724998], "woe:longitude": -122.483063, "woe:repo": "woeplanet-poi-us"}, "geometry": {"coordinates": [-122.483063, 37.724998], "type": "Point"}}