{"type": "Feature", "id": 23564439, "geometry": {"type": "Point", "coordinates": [-89.525429, 40.69894]}, "properties": {"woe:id": 23564439, "woe:parent_id": 2396019, "woe:name": "Armstrong-oakview Elementary School", "woe:placetype": 20, "woe:placetype_name": "POI", "woe:lang": "ENG", "iso:country": "US", "meta:provider": ["geoplanet:7.3.1", "geoplanet:7.3.2", "geoplanet:7.4.0", "geoplanet:7.4.1", "geoplanet:7.5.1", "geoplanet:7.5.2", "geoplanet:7.6.0", "geoplanet:7.8.1", "geoplanet:7.9.0", "geoplanet:7.10.0", "geoplanet:8.0.0", "woeplanet:8.0.0"], "meta:indexed": "2020-08-20T20:18:33.208880", "woe:alias_ENG_V": ["Armstrong-oakview Elementary"], "meta:updated": "2020-10-14T11:20:17.363250", "woe:hierarchy": {"continent": 24865672, "country": 23424977, "town": 0, "planet": 1, "county": 12588167, "suburb": 0, "state": 2347572, "region": 0, "localadmin": 0}, "woe:timezone_id": 56043661, "woe:hash": "dp0rdc18d23c", "woe:centroid": [-89.525429, 40.69894], "geom:latitude": 40.69894, "geom:longitude": -89.525429, "geom:hash": "dp0rdc18d23c", "woe:latitude": 40.69894, "geom:centroid": [-89.525429, 40.69894], "woe:longitude": -89.525429, "woe:repo": "woeplanet-poi-us", "geom:area": 0.0, "woe:scale": 19}}