{"type": "Feature", "id": 23626687, "properties": {"woe:id": 23626687, "woe:parent_id": 2525224, "woe:name": "Zeeland High School", "woe:placetype": 20, "woe:placetype_name": "POI", "woe:lang": "ENG", "iso:country": "US", "meta:provider": ["geoplanet:7.3.2", "geoplanet:7.4.0", "geoplanet:7.4.1", "geoplanet:7.5.1", "geoplanet:7.5.2", "geoplanet:7.6.0", "geoplanet:7.8.1", "geoplanet:7.9.0", "geoplanet:7.10.0", "geoplanet:8.0.0", "woeplanet:8.0.0"], "meta:indexed": "2020-08-20T22:02:40.956266", "woe:alias_ENG_V": ["Zeeland Senior High School", "Zeeland High", "Zeeland Senior High", "Zeeland HS", "Zeeland Senior HS"], "meta:updated": "2020-08-22T02:58:49.032404", "woe:hierarchy": {"continent": 24865672, "country": 23424977, "town": 0, "planet": 1, "county": 12589499, "suburb": 0, "state": 2347593, "region": 0, "localadmin": 0}, "woe:timezone_id": 56043661, "woe:hash": "cb1j823tymuv", "woe:centroid": [-99.830429, 45.969189], "geom:latitude": 45.969189, "geom:longitude": -99.830429, "geom:hash": "cb1j823tymuv", "woe:latitude": 45.969189, "geom:centroid": [-99.830429, 45.969189], "woe:longitude": -99.830429, "woe:repo": "woeplanet-poi-us"}, "geometry": {"coordinates": [-99.830429, 45.969189], "type": "Point"}}