{"type": "Feature", "id": 23649864, "geometry": {"type": "Point", "coordinates": [-89.384361, 36.035019]}, "properties": {"woe:id": 23649864, "woe:parent_id": 2394932, "woe:name": "Dyersburg Middle School", "woe:placetype": 20, "woe:placetype_name": "POI", "woe:lang": "ENG", "iso:country": "US", "meta:provider": ["geoplanet:7.3.1", "geoplanet:7.3.2", "geoplanet:7.4.0", "geoplanet:7.4.1", "geoplanet:7.5.1", "geoplanet:7.5.2", "geoplanet:7.6.0", "geoplanet:7.8.1", "geoplanet:7.9.0", "geoplanet:7.10.0", "geoplanet:8.0.0", "woeplanet:8.0.0"], "meta:indexed": "2020-08-20T20:19:01.680599", "meta:updated": "2020-10-14T11:19:53.849438", "woe:hierarchy": {"continent": 24865672, "country": 23424977, "town": 0, "planet": 1, "county": 12589934, "suburb": 0, "state": 2347601, "region": 0, "localadmin": 0}, "woe:timezone_id": 56043661, "woe:hash": "dn2kypbr1qmt", "woe:centroid": [-89.384361, 36.035019], "geom:latitude": 36.035019, "geom:longitude": -89.384361, "geom:hash": "dn2kypbr1qmt", "woe:latitude": 36.035019, "geom:centroid": [-89.384361, 36.035019], "woe:longitude": -89.384361, "woe:repo": "woeplanet-poi-us", "geom:area": 0.0, "woe:scale": 19}}