{"type": "Feature", "id": 23577345, "geometry": {"type": "Point", "coordinates": [-92.44014, 30.492701]}, "properties": {"woe:id": 23577345, "woe:parent_id": 2400561, "woe:name": "Eunice High School", "woe:placetype": 20, "woe:placetype_name": "POI", "woe:lang": "ENG", "iso:country": "US", "meta:provider": ["geoplanet:7.3.1", "geoplanet:7.3.2", "geoplanet:7.4.0", "geoplanet:7.4.1", "geoplanet:7.5.1", "geoplanet:7.5.2", "geoplanet:7.6.0", "geoplanet:7.8.1", "geoplanet:7.9.0", "geoplanet:7.10.0", "geoplanet:8.0.0", "woeplanet:8.0.0"], "meta:indexed": "2020-08-20T20:18:37.842208", "woe:alias_ENG_V": ["Eunice Senior High School", "Eunice High", "Eunice Senior High", "Eunice HS", "Eunice Senior HS"], "meta:updated": "2020-10-14T11:20:27.108469", "woe:hierarchy": {"continent": 24865672, "country": 23424977, "town": 0, "planet": 1, "county": 12588644, "suburb": 0, "state": 2347577, "region": 0, "localadmin": 0}, "woe:timezone_id": 56043661, "woe:hash": "9vqm2rp0ue7w", "woe:centroid": [-92.44014, 30.492701], "geom:latitude": 30.492701, "geom:longitude": -92.44014, "geom:hash": "9vqm2rp0ue7w", "woe:latitude": 30.492701, "geom:centroid": [-92.44014, 30.492701], "woe:longitude": -92.44014, "woe:repo": "woeplanet-poi-us", "geom:area": 0.0, "woe:scale": 19}}