{"type": "Feature", "id": 23583412, "geometry": {"type": "Point", "coordinates": [-72.983879, 42.28698]}, "properties": {"woe:id": 23583412, "woe:parent_id": 2379268, "woe:name": "Blandford Elementary School", "woe:placetype": 20, "woe:placetype_name": "POI", "woe:lang": "ENG", "iso:country": "US", "meta:provider": ["geoplanet:7.3.1", "geoplanet:7.3.2", "geoplanet:7.4.0", "geoplanet:7.4.1", "geoplanet:7.5.1", "geoplanet:7.5.2", "geoplanet:7.6.0", "geoplanet:7.8.1", "geoplanet:7.9.0", "geoplanet:7.10.0", "geoplanet:8.0.0", "woeplanet:8.0.0"], "meta:indexed": "2020-08-20T20:18:39.236279", "woe:alias_ENG_V": ["Blandford Elementary"], "meta:updated": "2020-10-14T11:20:09.173499", "woe:hierarchy": {"continent": 24865672, "country": 23424977, "town": 0, "planet": 1, "county": 12588706, "suburb": 0, "state": 2347580, "region": 0, "localadmin": 0}, "woe:timezone_id": 56043648, "woe:hash": "drs0e4ng827m", "woe:centroid": [-72.983879, 42.28698], "geom:latitude": 42.28698, "geom:longitude": -72.983879, "geom:hash": "drs0e4ng827m", "woe:latitude": 42.28698, "geom:centroid": [-72.983879, 42.28698], "woe:longitude": -72.983879, "woe:repo": "woeplanet-poi-us", "geom:area": 0.0, "woe:scale": 19}}