{"type": "Feature", "id": 23526445, "properties": {"woe:id": 23526445, "woe:parent_id": 55969939, "woe:name": "Union Middle School", "woe:placetype": 20, "woe:placetype_name": "POI", "woe:lang": "ENG", "iso:country": "US", "meta:provider": ["geoplanet:7.3.1", "geoplanet:7.3.2", "geoplanet:7.4.0", "geoplanet:7.4.1", "geoplanet:7.5.1", "geoplanet:7.5.2", "geoplanet:7.6.0", "geoplanet:7.8.1", "geoplanet:7.9.0", "geoplanet:7.10.0", "geoplanet:8.0.0", "woeplanet:8.0.0"], "meta:indexed": "2020-08-20T20:18:20.865094", "meta:updated": "2020-08-22T02:57:28.106271", "woe:hierarchy": {"continent": 24865672, "country": 23424977, "town": 0, "planet": 1, "county": 12587712, "suburb": 0, "state": 2347563, "region": 0, "localadmin": 0}, "woe:timezone_id": 56043663, "woe:hash": "9q97c7cjvrfr", "woe:centroid": [-121.935654, 37.243309], "geom:latitude": 37.243309, "geom:longitude": -121.935654, "geom:hash": "9q97c7cjvrfr", "woe:latitude": 37.243309, "geom:centroid": [-121.935654, 37.243309], "woe:longitude": -121.935654, "woe:repo": "woeplanet-poi-us"}, "geometry": {"coordinates": [-121.935654, 37.243309], "type": "Point"}}