{"type": "Feature", "id": 23543075, "geometry": {"type": "Point", "coordinates": [-72.634193, 41.761169]}, "properties": {"woe:id": 23543075, "woe:parent_id": 2395673, "woe:name": "Silver Lane School", "woe:placetype": 20, "woe:placetype_name": "POI", "woe:lang": "ENG", "iso:country": "US", "meta:provider": ["geoplanet:7.3.1", "geoplanet:7.3.2", "geoplanet:7.4.0", "geoplanet:7.4.1", "geoplanet:7.5.1", "geoplanet:7.5.2", "geoplanet:7.6.0", "geoplanet:7.8.1", "geoplanet:7.9.0", "geoplanet:7.10.0", "geoplanet:8.0.0", "woeplanet:8.0.0"], "meta:indexed": "2020-08-20T20:18:25.113932", "meta:updated": "2020-10-14T11:20:13.495615", "woe:alias_ENG_V": ["Silver Lane Elementary School"], "woe:hierarchy": {"continent": 24865672, "country": 23424977, "town": 0, "planet": 1, "county": 12587792, "suburb": 0, "state": 2347565, "region": 0, "localadmin": 0}, "woe:timezone_id": 56043648, "woe:hash": "drkme4mkkwhh", "woe:centroid": [-72.634193, 41.761169], "geom:latitude": 41.761169, "geom:longitude": -72.634193, "geom:hash": "drkme4mkkwhh", "woe:latitude": 41.761169, "geom:centroid": [-72.634193, 41.761169], "woe:longitude": -72.634193, "woe:repo": "woeplanet-poi-us", "geom:area": 0.0, "woe:scale": 19}}