{"type": "Feature", "id": 23662511, "geometry": {"type": "Point", "coordinates": [-111.81884, 39.14024]}, "properties": {"woe:id": 23662511, "woe:parent_id": 2415682, "woe:name": "Gunnison Valley Elementary School", "woe:placetype": 20, "woe:placetype_name": "POI", "woe:lang": "ENG", "iso:country": "US", "meta:provider": ["geoplanet:7.3.1", "geoplanet:7.3.2", "geoplanet:7.4.0", "geoplanet:7.4.1", "geoplanet:7.5.1", "geoplanet:7.5.2", "geoplanet:7.6.0", "geoplanet:7.8.1", "geoplanet:7.9.0", "geoplanet:7.10.0", "geoplanet:8.0.0", "woeplanet:8.0.0"], "meta:indexed": "2020-08-20T20:19:07.292411", "woe:alias_ENG_V": ["Gunnison Valley Elementary"], "meta:updated": "2020-10-14T11:19:36.095074", "woe:hierarchy": {"continent": 24865672, "country": 23424977, "town": 0, "planet": 1, "county": 12590280, "suburb": 0, "state": 2347603, "region": 0, "localadmin": 0}, "woe:timezone_id": 56043665, "woe:hash": "9wbqxt202jtd", "woe:centroid": [-111.81884, 39.14024], "geom:latitude": 39.14024, "geom:longitude": -111.81884, "geom:hash": "9wbqxt202jtd", "woe:latitude": 39.14024, "geom:centroid": [-111.81884, 39.14024], "woe:longitude": -111.81884, "woe:repo": "woeplanet-poi-us", "geom:area": 0.0, "woe:scale": 19}}