{"type": "Feature", "id": 23648606, "properties": {"woe:id": 23648606, "woe:parent_id": 2462273, "woe:name": "Aspire High School", "woe:placetype": 20, "woe:placetype_name": "POI", "woe:lang": "ENG", "iso:country": "US", "meta:provider": ["geoplanet:7.4.0", "geoplanet:7.4.1", "geoplanet:7.5.1", "geoplanet:7.5.2", "geoplanet:7.6.0", "geoplanet:7.8.1", "geoplanet:7.9.0", "geoplanet:7.10.0", "geoplanet:8.0.0", "woeplanet:8.0.0"], "meta:indexed": "2020-08-20T23:56:01.283430", "meta:updated": "2020-08-22T02:58:49.643939", "woe:alias_ENG_V": ["Aspire Senior High School", "Aspire High", "Aspire Senior High", "Aspire HS", "Aspire Senior HS"], "woe:hierarchy": {"continent": 24865672, "country": 23424977, "town": 0, "planet": 1, "county": 12589886, "suburb": 0, "state": 2347600, "region": 0, "localadmin": 0}, "woe:timezone_id": 56043661, "woe:hash": "9zejje1kucwu", "woe:centroid": [-96.787621, 43.08371], "geom:latitude": 43.08371, "geom:longitude": -96.787621, "geom:hash": "9zejje1kucwu", "woe:latitude": 43.08371, "geom:centroid": [-96.787621, 43.08371], "woe:longitude": -96.787621, "woe:repo": "woeplanet-poi-us"}, "geometry": {"coordinates": [-96.787621, 43.08371], "type": "Point"}}