{"type": "Feature", "id": 23518397, "properties": {"woe:id": 23518397, "woe:parent_id": 2457166, "woe:name": "Nashville High School", "woe:placetype": 20, "woe:placetype_name": "POI", "woe:lang": "ENG", "iso:country": "US", "meta:provider": ["geoplanet:7.3.1", "geoplanet:7.3.2", "geoplanet:7.4.0", "geoplanet:7.4.1", "geoplanet:7.5.1", "geoplanet:7.5.2", "geoplanet:7.6.0", "geoplanet:7.8.1", "geoplanet:7.9.0", "geoplanet:7.10.0", "geoplanet:8.0.0", "woeplanet:8.0.0"], "meta:indexed": "2020-08-20T20:18:19.047110", "woe:alias_ENG_V": ["Nashville Senior High School", "Nashville High", "Nashville Senior High", "Nashville HS", "Nashville Senior HS"], "meta:updated": "2020-08-22T02:58:45.977786", "woe:hierarchy": {"continent": 24865672, "country": 23424977, "town": 0, "planet": 1, "county": 12587625, "suburb": 0, "state": 2347562, "region": 0, "localadmin": 0}, "woe:timezone_id": 56043661, "woe:hash": "9yj30mgg6feh", "woe:centroid": [-93.850929, 33.957939], "geom:latitude": 33.957939, "geom:longitude": -93.850929, "geom:hash": "9yj30mgg6feh", "woe:latitude": 33.957939, "geom:centroid": [-93.850929, 33.957939], "woe:longitude": -93.850929, "woe:repo": "woeplanet-poi-us"}, "geometry": {"coordinates": [-93.850929, 33.957939], "type": "Point"}}