{"type": "Feature", "id": 23635677, "properties": {"woe:id": 23635677, "woe:parent_id": 2484630, "woe:name": "Roseburg Junior Academy", "woe:placetype": 20, "woe:placetype_name": "POI", "woe:lang": "ENG", "iso:country": "US", "meta:provider": ["geoplanet:7.3.1", "geoplanet:7.3.2", "geoplanet:7.4.0", "geoplanet:7.4.1", "geoplanet:7.5.1", "geoplanet:7.5.2", "geoplanet:7.6.0", "geoplanet:7.8.1", "geoplanet:7.9.0", "geoplanet:7.10.0", "geoplanet:8.0.0", "woeplanet:8.0.0"], "meta:indexed": "2020-08-20T20:18:56.877653", "meta:updated": "2020-08-22T02:57:46.060848", "woe:alias_ENG_V": ["Roseburg Jr Academy"], "woe:hierarchy": {"continent": 24865672, "country": 23424977, "town": 0, "planet": 1, "county": 12589701, "suburb": 0, "state": 2347596, "region": 0, "localadmin": 0}, "woe:timezone_id": 56043663, "woe:hash": "9r8mbm2tzpgy", "woe:centroid": [-123.386459, 43.228111], "geom:latitude": 43.228111, "geom:longitude": -123.386459, "geom:hash": "9r8mbm2tzpgy", "woe:latitude": 43.228111, "geom:centroid": [-123.386459, 43.228111], "woe:longitude": -123.386459, "woe:repo": "woeplanet-poi-us"}, "geometry": {"coordinates": [-123.386459, 43.228111], "type": "Point"}}