{"type": "Feature", "id": 23667691, "properties": {"woe:id": 23667691, "woe:parent_id": 2499333, "woe:name": "Robert E. Lee High School", "woe:placetype": 20, "woe:placetype_name": "POI", "woe:lang": "ENG", "iso:country": "US", "meta:provider": ["geoplanet:7.3.2", "geoplanet:7.4.0", "geoplanet:7.4.1", "geoplanet:7.5.1", "geoplanet:7.5.2", "geoplanet:7.6.0", "geoplanet:7.8.1", "geoplanet:7.9.0", "geoplanet:7.10.0", "geoplanet:8.0.0", "woeplanet:8.0.0"], "meta:indexed": "2020-08-20T22:02:59.263743", "woe:alias_ENG_V": ["Robert E. Lee Senior High School", "Robert E. Lee High", "Robert E. Lee Senior High", "Robert E. Lee HS", "Robert E. Lee Senior HS"], "meta:updated": "2020-08-22T02:58:50.239730", "woe:hierarchy": {"continent": 24865672, "country": 23424977, "town": 0, "planet": 1, "county": 12590425, "suburb": 0, "state": 2347605, "region": 0, "localadmin": 0}, "woe:timezone_id": 56043648, "woe:hash": "dnzc159pq5rh", "woe:centroid": [-79.055977, 38.16502], "geom:latitude": 38.16502, "geom:longitude": -79.055977, "geom:hash": "dnzc159pq5rh", "woe:latitude": 38.16502, "geom:centroid": [-79.055977, 38.16502], "woe:longitude": -79.055977, "woe:repo": "woeplanet-poi-us"}, "geometry": {"coordinates": [-79.055977, 38.16502], "type": "Point"}}