{"type": "Feature", "id": 23579739, "geometry": {"type": "Point", "coordinates": [-76.508743, 39.244621]}, "properties": {"woe:id": 23579739, "woe:parent_id": 12588678, "woe:name": "Sollers Point/southeastern Technical High School", "woe:placetype": 20, "woe:placetype_name": "POI", "woe:lang": "ENG", "iso:country": "US", "meta:provider": ["geoplanet:7.3.2", "geoplanet:7.4.0", "geoplanet:7.4.1", "geoplanet:7.5.1", "geoplanet:7.5.2", "geoplanet:7.6.0", "geoplanet:7.8.1", "geoplanet:7.9.0", "geoplanet:7.10.0", "geoplanet:8.0.0", "woeplanet:8.0.0"], "meta:indexed": "2020-08-20T22:02:22.623630", "woe:alias_ENG_V": ["Sollers Point/southeastern Technical Senior High School", "Sollers Point/southeastern Technical High", "Sollers Point/southeastern Technical Senior High", "Sollers Point/southeastern Technical HS", "Sollers Point/southeastern Technical Senior HS"], "meta:updated": "2020-10-14T11:20:28.334723", "woe:hierarchy": {"continent": 24865672, "country": 23424977, "town": 0, "planet": 1, "county": 12588678, "suburb": 0, "state": 2347579, "region": 0, "localadmin": 0}, "woe:timezone_id": 56043648, "woe:hash": "dqcx70203pd6", "woe:centroid": [-76.508743, 39.244621], "geom:latitude": 39.244621, "geom:longitude": -76.508743, "geom:hash": "dqcx70203pd6", "woe:latitude": 39.244621, "geom:centroid": [-76.508743, 39.244621], "woe:longitude": -76.508743, "woe:repo": "woeplanet-poi-us", "geom:area": 0.0, "woe:scale": 19}}