{"type": "Feature", "id": 23553277, "geometry": {"type": "Point", "coordinates": [-83.908257, 34.219791]}, "properties": {"woe:id": 23553277, "woe:parent_id": 2463914, "woe:name": "West Hall Middle School", "woe:placetype": 20, "woe:placetype_name": "POI", "woe:lang": "ENG", "iso:country": "US", "meta:provider": ["geoplanet:7.3.1", "geoplanet:7.3.2", "geoplanet:7.4.0", "geoplanet:7.4.1", "geoplanet:7.5.1", "geoplanet:7.5.2", "geoplanet:7.6.0", "geoplanet:7.8.1", "geoplanet:7.9.0", "geoplanet:7.10.0", "geoplanet:8.0.0", "woeplanet:8.0.0"], "meta:indexed": "2020-08-20T20:18:29.564379", "woe:alias_ENG_V": ["W Hall Middle School"], "meta:updated": "2020-10-14T11:20:24.977463", "woe:hierarchy": {"continent": 24865672, "country": 23424977, "town": 0, "planet": 1, "county": 12587938, "suburb": 0, "state": 2347569, "region": 0, "localadmin": 0}, "woe:timezone_id": 56043648, "woe:hash": "dnh6dtebezku", "woe:centroid": [-83.908257, 34.219791], "geom:latitude": 34.219791, "geom:longitude": -83.908257, "geom:hash": "dnh6dtebezku", "woe:latitude": 34.219791, "geom:centroid": [-83.908257, 34.219791], "woe:longitude": -83.908257, "woe:repo": "woeplanet-poi-us", "geom:area": 0.0, "woe:scale": 19}}