{"type": "Feature", "id": 23573997, "geometry": {"type": "Point", "coordinates": [-85.975739, 37.889172]}, "properties": {"woe:id": 23573997, "woe:parent_id": 2484579, "woe:name": "Newgarden Station", "woe:placetype": 20, "woe:placetype_name": "POI", "woe:lang": "ENG", "iso:country": "US", "meta:provider": ["geoplanet:7.3.1", "geoplanet:7.3.2", "geoplanet:7.4.0", "geoplanet:7.4.1", "geoplanet:7.5.1", "geoplanet:7.5.2", "geoplanet:7.6.0", "geoplanet:7.8.1", "geoplanet:7.9.0", "geoplanet:7.10.0", "geoplanet:8.0.0", "woeplanet:8.0.0"], "meta:indexed": "2020-08-20T20:18:36.784461", "meta:updated": "2020-10-14T11:20:15.311247", "woe:hierarchy": {"continent": 24865672, "country": 23424977, "town": 0, "planet": 1, "county": 12588522, "suburb": 0, "state": 2347576, "region": 0, "localadmin": 0}, "woe:timezone_id": 56043647, "woe:hash": "dndze9d2kjd6", "woe:centroid": [-85.975739, 37.889172], "geom:latitude": 37.889172, "geom:longitude": -85.975739, "geom:hash": "dndze9d2kjd6", "woe:latitude": 37.889172, "geom:centroid": [-85.975739, 37.889172], "woe:longitude": -85.975739, "woe:repo": "woeplanet-poi-us", "geom:area": 0.0, "woe:scale": 19}}