{"type": "Feature", "id": 23620930, "geometry": {"type": "Point", "coordinates": [-72.431671, 41.061329]}, "properties": {"woe:id": 23620930, "woe:parent_id": 2497109, "woe:name": "Southold Junior High School", "woe:placetype": 20, "woe:placetype_name": "POI", "woe:lang": "ENG", "iso:country": "US", "meta:provider": ["geoplanet:7.3.1", "geoplanet:7.3.2", "geoplanet:7.4.0", "geoplanet:7.4.1", "geoplanet:7.5.1", "geoplanet:7.5.2", "geoplanet:7.6.0", "geoplanet:7.8.1", "geoplanet:7.9.0", "geoplanet:7.10.0", "geoplanet:8.0.0", "woeplanet:8.0.0"], "meta:indexed": "2020-08-20T20:18:51.849764", "woe:alias_ENG_V": ["Southold Junior High"], "meta:updated": "2020-10-14T11:19:33.874269", "woe:hierarchy": {"continent": 24865672, "country": 23424977, "town": 0, "planet": 1, "county": 12589363, "suburb": 0, "state": 2347591, "region": 0, "localadmin": 0}, "woe:timezone_id": 56043648, "woe:hash": "drk3xfbzedx8", "woe:centroid": [-72.431671, 41.061329], "geom:latitude": 41.061329, "geom:longitude": -72.431671, "geom:hash": "drk3xfbzedx8", "woe:latitude": 41.061329, "geom:centroid": [-72.431671, 41.061329], "woe:longitude": -72.431671, "woe:repo": "woeplanet-poi-us", "geom:area": 0.0, "woe:scale": 19}}