{"type": "Feature", "id": 23514467, "properties": {"woe:id": 23514467, "woe:parent_id": 2422580, "woe:name": "Sumter Academy", "woe:placetype": 20, "woe:placetype_name": "POI", "woe:lang": "ENG", "iso:country": "US", "meta:provider": ["geoplanet:7.3.1", "geoplanet:7.3.2", "geoplanet:7.4.0", "geoplanet:7.4.1", "geoplanet:7.5.1", "geoplanet:7.5.2", "geoplanet:7.6.0", "geoplanet:7.8.1", "geoplanet:7.9.0", "geoplanet:7.10.0", "geoplanet:8.0.0", "woeplanet:8.0.0"], "meta:indexed": "2020-08-20T20:18:17.758069", "meta:updated": "2020-08-22T02:57:26.388144", "woe:hierarchy": {"continent": 24865672, "country": 23424977, "town": 0, "planet": 1, "county": 12587546, "suburb": 0, "state": 2347559, "region": 0, "localadmin": 0}, "woe:timezone_id": 56043661, "woe:hash": "djc1pf3k8ch3", "woe:centroid": [-88.251419, 32.532669], "geom:latitude": 32.532669, "geom:longitude": -88.251419, "geom:hash": "djc1pf3k8ch3", "woe:latitude": 32.532669, "geom:centroid": [-88.251419, 32.532669], "woe:longitude": -88.251419, "woe:repo": "woeplanet-poi-us"}, "geometry": {"coordinates": [-88.251419, 32.532669], "type": "Point"}}