{"type": "Feature", "id": 56053665, "geometry": {"type": "Point", "coordinates": [-77.114197, 38.8372]}, "properties": {"woe:id": 56053665, "woe:parent_id": 55857726, "woe:name": "Northern Va Community College-Alexandria", "woe:placetype": 20, "woe:placetype_name": "POI", "woe:lang": "ENG", "iso:country": "US", "meta:provider": ["geoplanet:7.3.1", "geoplanet:7.3.2", "geoplanet:7.4.0", "geoplanet:7.4.1", "geoplanet:7.5.1", "geoplanet:7.5.2", "geoplanet:7.6.0", "geoplanet:7.8.1", "geoplanet:7.9.0", "geoplanet:7.10.0", "geoplanet:8.0.0", "woeplanet:8.0.0"], "meta:indexed": "2020-08-20T20:19:17.225120", "meta:updated": "2020-10-14T11:19:55.842406", "woe:alias_ENG_V": ["Northern Va Cmty College-Alexandria"], "woe:hierarchy": {"continent": 24865672, "country": 23424977, "town": 0, "planet": 1, "county": 12590306, "suburb": 0, "state": 2347605, "region": 0, "localadmin": 0}, "woe:timezone_id": 56043648, "woe:hash": "dqchvnp5hfz4", "woe:centroid": [-77.114197, 38.8372], "geom:latitude": 38.8372, "geom:longitude": -77.114197, "geom:hash": "dqchvnp5hfz4", "woe:latitude": 38.8372, "geom:centroid": [-77.114197, 38.8372], "woe:longitude": -77.114197, "woe:repo": "woeplanet-poi-us", "geom:area": 0.0, "woe:scale": 19}}