{"type": "Feature", "id": 24930838, "properties": {"woe:id": 24930838, "woe:parent_id": 2477224, "woe:name": "Martin Stadium", "woe:placetype": 20, "woe:placetype_name": "POI", "woe:lang": "ENG", "iso:country": "US", "meta:provider": ["geoplanet:7.3.1", "geoplanet:7.3.2", "geoplanet:7.4.0", "geoplanet:7.4.1", "geoplanet:7.5.1", "geoplanet:7.5.2", "geoplanet:7.6.0", "geoplanet:7.8.1", "geoplanet:7.9.0", "geoplanet:7.10.0", "geoplanet:8.0.0", "woeplanet:8.0.0"], "meta:indexed": "2020-08-20T20:19:15.473829", "meta:updated": "2020-08-22T02:58:19.975676", "woe:hierarchy": {"continent": 24865672, "country": 23424977, "town": 0, "planet": 1, "county": 12590477, "suburb": 0, "state": 2347606, "region": 0, "localadmin": 0}, "woe:timezone_id": 56043663, "woe:hash": "c2k9vgnq1fyg", "woe:centroid": [-117.160522, 46.731392], "geom:latitude": 46.731392, "geom:longitude": -117.160522, "geom:hash": "c2k9vgnq1fyg", "woe:latitude": 46.731392, "geom:centroid": [-117.160522, 46.731392], "woe:longitude": -117.160522, "woe:repo": "woeplanet-poi-us"}, "geometry": {"coordinates": [-117.160522, 46.731392], "type": "Point"}}