{"type": "Feature", "id": 24866621, "properties": {"woe:id": 24866621, "woe:parent_id": 2486929, "woe:name": "College of Saint Benedict", "woe:placetype": 20, "woe:placetype_name": "POI", "woe:lang": "ENG", "iso:country": "US", "meta:provider": ["geoplanet:7.3.1", "geoplanet:7.3.2", "geoplanet:7.4.0", "geoplanet:7.4.1", "geoplanet:7.5.1", "geoplanet:7.5.2", "geoplanet:7.6.0", "geoplanet:7.8.1", "geoplanet:7.9.0", "geoplanet:7.10.0", "geoplanet:8.0.0", "woeplanet:8.0.0"], "meta:indexed": "2020-08-20T20:19:15.221514", "meta:updated": "2020-08-22T02:58:19.839893", "woe:alias_ENG_V": ["College of St Benedict"], "woe:hierarchy": {"continent": 24865672, "country": 23424977, "town": 0, "planet": 1, "county": 12588869, "suburb": 0, "state": 2347582, "region": 0, "localadmin": 0}, "woe:timezone_id": 56043661, "woe:hash": "cbhgjwttdyg4", "woe:centroid": [-94.320938, 45.56403], "geom:latitude": 45.56403, "geom:longitude": -94.320938, "geom:hash": "cbhgjwttdyg4", "woe:latitude": 45.56403, "geom:centroid": [-94.320938, 45.56403], "woe:longitude": -94.320938, "woe:repo": "woeplanet-poi-us"}, "geometry": {"coordinates": [-94.320938, 45.56403], "type": "Point"}}