{"type": "Feature", "id": 23527642, "properties": {"woe:id": 23527642, "woe:parent_id": 55861811, "woe:name": "Yulupa Elementary School", "woe:placetype": 20, "woe:placetype_name": "POI", "woe:lang": "ENG", "iso:country": "US", "meta:provider": ["geoplanet:7.3.2", "geoplanet:7.4.0", "geoplanet:7.4.1", "geoplanet:7.5.1", "geoplanet:7.5.2", "geoplanet:7.6.0", "geoplanet:7.8.1", "geoplanet:7.9.0", "geoplanet:7.10.0", "geoplanet:8.0.0", "woeplanet:8.0.0"], "meta:indexed": "2020-08-20T22:02:00.771762", "woe:alias_ENG_V": ["Yulupa Elementary"], "meta:updated": "2020-08-22T02:57:28.243669", "woe:hierarchy": {"continent": 24865672, "country": 23424977, "town": 0, "planet": 1, "county": 12587718, "suburb": 0, "state": 2347563, "region": 0, "localadmin": 0}, "woe:timezone_id": 56043663, "woe:hash": "9qbf8e8m8kee", "woe:centroid": [-122.672981, 38.428398], "geom:latitude": 38.428398, "geom:longitude": -122.672981, "geom:hash": "9qbf8e8m8kee", "woe:latitude": 38.428398, "geom:centroid": [-122.672981, 38.428398], "woe:longitude": -122.672981, "woe:repo": "woeplanet-poi-us"}, "geometry": {"coordinates": [-122.672981, 38.428398], "type": "Point"}}