{"type": "Feature", "id": 23591150, "geometry": {"type": "Point", "coordinates": [-83.227341, 42.328609]}, "properties": {"woe:id": 23591150, "woe:parent_id": 56021821, "woe:name": "Dearborn Academy", "woe:placetype": 20, "woe:placetype_name": "POI", "woe:lang": "ENG", "iso:country": "US", "meta:provider": ["geoplanet:7.3.1", "geoplanet:7.3.2", "geoplanet:7.4.0", "geoplanet:7.4.1", "geoplanet:7.5.1", "geoplanet:7.5.2", "geoplanet:7.6.0", "geoplanet:7.8.1", "geoplanet:7.9.0", "geoplanet:7.10.0", "geoplanet:8.0.0", "woeplanet:8.0.0"], "meta:indexed": "2020-08-20T20:18:41.563042", "meta:updated": "2020-10-14T11:20:12.811803", "woe:hierarchy": {"continent": 24865672, "country": 23424977, "town": 0, "planet": 1, "county": 12588795, "suburb": 0, "state": 2347581, "region": 0, "localadmin": 0}, "woe:timezone_id": 56043658, "woe:hash": "dpsbf1ewn2se", "woe:centroid": [-83.227341, 42.328609], "geom:latitude": 42.328609, "geom:longitude": -83.227341, "geom:hash": "dpsbf1ewn2se", "woe:latitude": 42.328609, "geom:centroid": [-83.227341, 42.328609], "woe:longitude": -83.227341, "woe:repo": "woeplanet-poi-us", "geom:area": 0.0, "woe:scale": 19}}