{"type": "Feature", "id": 23555547, "properties": {"woe:id": 23555547, "woe:parent_id": 2382479, "woe:name": "Southside Elementary School", "woe:placetype": 20, "woe:placetype_name": "POI", "woe:lang": "ENG", "iso:country": "US", "meta:provider": ["geoplanet:7.3.1", "geoplanet:7.3.2", "geoplanet:7.4.0", "geoplanet:7.4.1", "geoplanet:7.5.1", "geoplanet:7.5.2", "geoplanet:7.6.0", "geoplanet:7.8.1", "geoplanet:7.9.0", "geoplanet:7.10.0", "geoplanet:8.0.0", "woeplanet:8.0.0"], "meta:indexed": "2020-08-20T20:18:30.209426", "woe:alias_ENG_V": ["Southside Elementary"], "meta:updated": "2020-08-22T02:57:33.614605", "woe:hierarchy": {"continent": 24865672, "country": 23424977, "town": 0, "planet": 1, "county": 12588042, "suburb": 0, "state": 2347571, "region": 0, "localadmin": 0}, "woe:timezone_id": 56043663, "woe:hash": "c2t1dkq79gbx", "woe:centroid": [-116.611214, 48.10014], "geom:latitude": 48.10014, "geom:longitude": -116.611214, "geom:hash": "c2t1dkq79gbx", "woe:latitude": 48.10014, "geom:centroid": [-116.611214, 48.10014], "woe:longitude": -116.611214, "woe:repo": "woeplanet-poi-us"}, "geometry": {"coordinates": [-116.611214, 48.10014], "type": "Point"}}