{"type": "Feature", "id": 23625695, "properties": {"woe:id": 23625695, "woe:parent_id": 2443954, "woe:name": "New Vision Intermediate School", "woe:placetype": 20, "woe:placetype_name": "POI", "woe:lang": "ENG", "iso:country": "US", "meta:provider": ["geoplanet:7.3.1", "geoplanet:7.3.2", "geoplanet:7.4.0", "geoplanet:7.4.1", "geoplanet:7.5.1", "geoplanet:7.5.2", "geoplanet:7.6.0", "geoplanet:7.8.1", "geoplanet:7.9.0", "geoplanet:7.10.0", "geoplanet:8.0.0", "woeplanet:8.0.0"], "meta:indexed": "2020-08-20T20:18:52.920257", "meta:updated": "2020-08-22T02:57:44.482400", "woe:hierarchy": {"continent": 24865672, "country": 23424977, "town": 0, "planet": 1, "county": 12589452, "suburb": 0, "state": 2347592, "region": 0, "localadmin": 0}, "woe:timezone_id": 56043648, "woe:hash": "dnrph4sbgzku", "woe:centroid": [-79.973778, 36.40062], "geom:latitude": 36.40062, "geom:longitude": -79.973778, "geom:hash": "dnrph4sbgzku", "woe:latitude": 36.40062, "geom:centroid": [-79.973778, 36.40062], "woe:longitude": -79.973778, "woe:repo": "woeplanet-poi-us"}, "geometry": {"coordinates": [-79.973778, 36.40062], "type": "Point"}}