{"type": "Feature", "id": 23580613, "properties": {"woe:id": 23580613, "woe:parent_id": 2398663, "woe:name": "Ellicott Mills Station", "woe:placetype": 20, "woe:placetype_name": "POI", "woe:lang": "ENG", "iso:country": "US", "meta:provider": ["geoplanet:7.3.1", "geoplanet:7.3.2", "geoplanet:7.4.0", "geoplanet:7.4.1", "geoplanet:7.5.1", "geoplanet:7.5.2", "geoplanet:7.6.0", "geoplanet:7.8.1", "geoplanet:7.9.0", "geoplanet:7.10.0", "geoplanet:8.0.0", "woeplanet:8.0.0"], "meta:indexed": "2020-08-20T20:18:38.613388", "meta:updated": "2020-08-22T02:57:37.890912", "woe:hierarchy": {"continent": 24865672, "country": 23424977, "town": 0, "planet": 1, "county": 12588689, "suburb": 0, "state": 2347579, "region": 0, "localadmin": 0}, "woe:timezone_id": 56043648, "woe:hash": "dqcrkkky9w52", "woe:centroid": [-76.798828, 39.267658], "geom:latitude": 39.267658, "geom:longitude": -76.798828, "geom:hash": "dqcrkkky9w52", "woe:latitude": 39.267658, "geom:centroid": [-76.798828, 39.267658], "woe:longitude": -76.798828, "woe:repo": "woeplanet-poi-us"}, "geometry": {"coordinates": [-76.798828, 39.267658], "type": "Point"}}