{"type": "Feature", "id": 23600824, "geometry": {"type": "Point", "coordinates": [-105.833107, 46.409359]}, "properties": {"woe:id": 23600824, "woe:parent_id": 2450922, "woe:name": "Jefferson School", "woe:placetype": 20, "woe:placetype_name": "POI", "woe:lang": "ENG", "iso:country": "US", "meta:provider": ["geoplanet:7.3.1", "geoplanet:7.3.2", "geoplanet:7.4.0", "geoplanet:7.4.1", "geoplanet:7.5.1", "geoplanet:7.5.2", "geoplanet:7.6.0", "geoplanet:7.8.1", "geoplanet:7.9.0", "geoplanet:7.10.0", "geoplanet:8.0.0", "woeplanet:8.0.0"], "meta:indexed": "2020-08-20T20:18:45.164106", "meta:updated": "2020-10-14T11:19:39.978507", "woe:hierarchy": {"continent": 24865672, "country": 23424977, "town": 0, "planet": 1, "county": 12589089, "suburb": 0, "state": 2347585, "region": 0, "localadmin": 0}, "woe:timezone_id": 56043665, "woe:hash": "c8k8p8wdjge9", "woe:centroid": [-105.833107, 46.409359], "geom:latitude": 46.409359, "geom:longitude": -105.833107, "geom:hash": "c8k8p8wdjge9", "woe:latitude": 46.409359, "geom:centroid": [-105.833107, 46.409359], "woe:longitude": -105.833107, "woe:repo": "woeplanet-poi-us", "geom:area": 0.0, "woe:scale": 19}}