{"type": "Feature", "id": 23603147, "geometry": {"type": "Point", "coordinates": [-96.067017, 41.308331]}, "properties": {"woe:id": 23603147, "woe:parent_id": 55806352, "woe:name": "Masters Elementary School", "woe:placetype": 20, "woe:placetype_name": "POI", "woe:lang": "ENG", "iso:country": "US", "meta:provider": ["geoplanet:7.3.1", "geoplanet:7.3.2", "geoplanet:7.4.0", "geoplanet:7.4.1", "geoplanet:7.5.1", "geoplanet:7.5.2", "geoplanet:7.6.0", "geoplanet:7.8.1", "geoplanet:7.9.0", "geoplanet:7.10.0", "geoplanet:8.0.0", "woeplanet:8.0.0"], "meta:indexed": "2020-08-20T20:18:45.615465", "woe:alias_ENG_V": ["Jc Masters Elementary School", "Masters Elementary"], "meta:updated": "2020-10-14T11:19:51.495476", "woe:hierarchy": {"continent": 24865672, "country": 23424977, "town": 0, "planet": 1, "county": 12589165, "suburb": 0, "state": 2347586, "region": 0, "localadmin": 0}, "woe:timezone_id": 56043661, "woe:hash": "9z7dvzynkr00", "woe:centroid": [-96.067017, 41.308331], "geom:latitude": 41.308331, "geom:longitude": -96.067017, "geom:hash": "9z7dvzynkr00", "woe:latitude": 41.308331, "geom:centroid": [-96.067017, 41.308331], "woe:longitude": -96.067017, "woe:repo": "woeplanet-poi-us", "geom:area": 0.0, "woe:scale": 19}}