{"type": "Feature", "id": 23614274, "geometry": {"type": "Point", "coordinates": [-78.799408, 43.028648]}, "properties": {"woe:id": 23614274, "woe:parent_id": 28339720, "woe:name": "Heritage Hts Elementary School", "woe:placetype": 20, "woe:placetype_name": "POI", "woe:lang": "ENG", "iso:country": "US", "meta:provider": ["geoplanet:7.3.1", "geoplanet:7.3.2", "geoplanet:7.4.0", "geoplanet:7.4.1", "geoplanet:7.5.1", "geoplanet:7.5.2", "geoplanet:7.6.0", "geoplanet:7.8.1", "geoplanet:7.9.0", "geoplanet:7.10.0", "geoplanet:8.0.0", "woeplanet:8.0.0"], "meta:indexed": "2020-08-20T20:18:49.127640", "woe:alias_ENG_V": ["Heritage Hts Elementary"], "meta:updated": "2020-10-14T11:19:53.821596", "woe:hierarchy": {"continent": 24865672, "country": 23424977, "town": 0, "planet": 1, "county": 12589326, "suburb": 0, "state": 2347591, "region": 0, "localadmin": 0}, "woe:timezone_id": 56043648, "woe:hash": "dpxuychh09qe", "woe:centroid": [-78.799408, 43.028648], "geom:latitude": 43.028648, "geom:longitude": -78.799408, "geom:hash": "dpxuychh09qe", "woe:latitude": 43.028648, "geom:centroid": [-78.799408, 43.028648], "woe:longitude": -78.799408, "woe:repo": "woeplanet-poi-us", "geom:area": 0.0, "woe:scale": 19}}