{"type": "Feature", "id": 23618483, "geometry": {"type": "Point", "coordinates": [-76.111931, 43.068619]}, "properties": {"woe:id": 23618483, "woe:parent_id": 2396623, "woe:name": "Eastwood Station", "woe:placetype": 20, "woe:placetype_name": "POI", "woe:lang": "ENG", "iso:country": "US", "meta:provider": ["geoplanet:7.3.1", "geoplanet:7.3.2", "geoplanet:7.4.0", "geoplanet:7.4.1", "geoplanet:7.5.1", "geoplanet:7.5.2", "geoplanet:7.6.0", "geoplanet:7.8.1", "geoplanet:7.9.0", "geoplanet:7.10.0", "geoplanet:8.0.0", "woeplanet:8.0.0"], "meta:indexed": "2020-08-20T20:18:50.857406", "meta:updated": "2020-10-14T11:19:44.797109", "woe:hierarchy": {"continent": 24865672, "country": 23424977, "town": 0, "planet": 1, "county": 12589345, "suburb": 0, "state": 2347591, "region": 0, "localadmin": 0}, "woe:timezone_id": 56043648, "woe:hash": "dr9vh02uzkqz", "woe:centroid": [-76.111931, 43.068619], "geom:latitude": 43.068619, "geom:longitude": -76.111931, "geom:hash": "dr9vh02uzkqz", "woe:latitude": 43.068619, "geom:centroid": [-76.111931, 43.068619], "woe:longitude": -76.111931, "woe:repo": "woeplanet-poi-us", "geom:area": 0.0, "woe:scale": 19}}