{"type": "Feature", "id": 23586980, "geometry": {"type": "Point", "coordinates": [-83.7444, 43.034389]}, "properties": {"woe:id": 23586980, "woe:parent_id": 55858977, "woe:name": "Anderson School", "woe:placetype": 20, "woe:placetype_name": "POI", "woe:lang": "ENG", "iso:country": "US", "meta:provider": ["geoplanet:7.3.1", "geoplanet:7.3.2", "geoplanet:7.4.0", "geoplanet:7.4.1", "geoplanet:7.5.1", "geoplanet:7.5.2", "geoplanet:7.6.0", "geoplanet:7.8.1", "geoplanet:7.9.0", "geoplanet:7.10.0", "geoplanet:8.0.0", "woeplanet:8.0.0"], "meta:indexed": "2020-08-20T20:18:40.141630", "meta:updated": "2020-10-14T11:20:28.269699", "woe:hierarchy": {"continent": 24865672, "country": 23424977, "town": 0, "planet": 1, "county": 12588738, "suburb": 0, "state": 2347581, "region": 0, "localadmin": 0}, "woe:timezone_id": 56043658, "woe:hash": "dpsky65jqp93", "woe:centroid": [-83.7444, 43.034389], "geom:latitude": 43.034389, "geom:longitude": -83.7444, "geom:hash": "dpsky65jqp93", "woe:latitude": 43.034389, "geom:centroid": [-83.7444, 43.034389], "woe:longitude": -83.7444, "woe:repo": "woeplanet-poi-us", "geom:area": 0.0, "woe:scale": 19}}