{"type": "Feature", "id": 23585695, "geometry": {"type": "Point", "coordinates": [-71.9907, 42.24527]}, "properties": {"woe:id": 23585695, "woe:parent_id": 2497502, "woe:name": "David Prouty Intermediate School", "woe:placetype": 20, "woe:placetype_name": "POI", "woe:lang": "ENG", "iso:country": "US", "meta:provider": ["geoplanet:7.3.1", "geoplanet:7.3.2", "geoplanet:7.4.0", "geoplanet:7.4.1", "geoplanet:7.5.1", "geoplanet:7.5.2", "geoplanet:7.6.0", "geoplanet:7.8.1", "geoplanet:7.9.0", "geoplanet:7.10.0", "geoplanet:8.0.0", "woeplanet:8.0.0"], "meta:indexed": "2020-08-20T20:18:39.762284", "meta:updated": "2020-10-14T11:20:07.166779", "woe:hierarchy": {"continent": 24865672, "country": 23424977, "town": 0, "planet": 1, "county": 12588713, "suburb": 0, "state": 2347580, "region": 0, "localadmin": 0}, "woe:timezone_id": 56043648, "woe:hash": "drsb3f9bx157", "woe:centroid": [-71.9907, 42.24527], "geom:latitude": 42.24527, "geom:longitude": -71.9907, "geom:hash": "drsb3f9bx157", "woe:latitude": 42.24527, "geom:centroid": [-71.9907, 42.24527], "woe:longitude": -71.9907, "woe:repo": "woeplanet-poi-us", "geom:area": 0.0, "woe:scale": 19}}