{"type": "Feature", "id": 23638956, "properties": {"woe:id": 23638956, "woe:parent_id": 28744892, "woe:name": "Everett Area Elementary School", "woe:placetype": 20, "woe:placetype_name": "POI", "woe:lang": "ENG", "iso:country": "US", "meta:provider": ["geoplanet:7.3.1", "geoplanet:7.3.2", "geoplanet:7.4.0", "geoplanet:7.4.1", "geoplanet:7.5.1", "geoplanet:7.5.2", "geoplanet:7.6.0", "geoplanet:7.8.1", "geoplanet:7.9.0", "geoplanet:7.10.0", "geoplanet:8.0.0", "woeplanet:8.0.0"], "meta:indexed": "2020-08-20T20:18:58.007495", "woe:alias_ENG_V": ["Everett Area Elementary"], "meta:updated": "2020-08-22T02:57:46.468860", "woe:hierarchy": {"continent": 24865672, "country": 23424977, "town": 0, "planet": 1, "county": 12589732, "suburb": 0, "state": 2347597, "region": 0, "localadmin": 0}, "woe:timezone_id": 56043648, "woe:hash": "dr078fuc7qk3", "woe:centroid": [-78.35881, 40.005589], "geom:latitude": 40.005589, "geom:longitude": -78.35881, "geom:hash": "dr078fuc7qk3", "woe:latitude": 40.005589, "geom:centroid": [-78.35881, 40.005589], "woe:longitude": -78.35881, "woe:repo": "woeplanet-poi-us"}, "geometry": {"coordinates": [-78.35881, 40.005589], "type": "Point"}}