{"type": "Feature", "id": 23616576, "geometry": {"type": "Point", "coordinates": [-73.657722, 40.6007]}, "properties": {"woe:id": 23616576, "woe:parent_id": 2427843, "woe:name": "Francis X. Hegarty Elementary School", "woe:placetype": 20, "woe:placetype_name": "POI", "woe:lang": "ENG", "iso:country": "US", "meta:provider": ["geoplanet:7.3.1", "geoplanet:7.3.2", "geoplanet:7.4.0", "geoplanet:7.4.1", "geoplanet:7.5.1", "geoplanet:7.5.2", "geoplanet:7.6.0", "geoplanet:7.8.1", "geoplanet:7.9.0", "geoplanet:7.10.0", "geoplanet:8.0.0", "woeplanet:8.0.0"], "meta:indexed": "2020-08-20T20:18:50.036034", "woe:alias_ENG_V": ["Francis X. Hegarty Elementary"], "meta:updated": "2020-10-14T11:19:44.664304", "woe:hierarchy": {"continent": 24865672, "country": 23424977, "town": 0, "planet": 1, "county": 12589341, "suburb": 0, "state": 2347591, "region": 0, "localadmin": 0}, "woe:timezone_id": 56043648, "woe:hash": "dr5wgzhh4xj9", "woe:centroid": [-73.657722, 40.6007], "geom:latitude": 40.6007, "geom:longitude": -73.657722, "geom:hash": "dr5wgzhh4xj9", "woe:latitude": 40.6007, "geom:centroid": [-73.657722, 40.6007], "woe:longitude": -73.657722, "woe:repo": "woeplanet-poi-us", "geom:area": 0.0, "woe:scale": 19}}