{"type": "Feature", "id": 23670313, "geometry": {"type": "Point", "coordinates": [-122.444328, 47.137421]}, "properties": {"woe:id": 23670313, "woe:parent_id": 55996395, "woe:name": "Gates Secondary School", "woe:placetype": 20, "woe:placetype_name": "POI", "woe:lang": "ENG", "iso:country": "US", "meta:provider": ["geoplanet:7.3.1", "geoplanet:7.3.2", "geoplanet:7.4.0", "geoplanet:7.4.1", "geoplanet:7.5.1", "geoplanet:7.5.2", "geoplanet:7.6.0", "geoplanet:7.8.1", "geoplanet:7.9.0", "geoplanet:7.10.0", "geoplanet:8.0.0", "woeplanet:8.0.0"], "meta:indexed": "2020-08-20T20:19:09.614963", "meta:updated": "2020-10-14T11:19:42.928820", "woe:hierarchy": {"continent": 24865672, "country": 23424977, "town": 0, "planet": 1, "county": 12590466, "suburb": 0, "state": 2347606, "region": 0, "localadmin": 0}, "woe:timezone_id": 56043663, "woe:hash": "c22ujtng2k5s", "woe:centroid": [-122.444328, 47.137421], "geom:latitude": 47.137421, "geom:longitude": -122.444328, "geom:hash": "c22ujtng2k5s", "woe:latitude": 47.137421, "geom:centroid": [-122.444328, 47.137421], "woe:longitude": -122.444328, "woe:repo": "woeplanet-poi-us", "geom:area": 0.0, "woe:scale": 19}}