{"type": "Feature", "id": 23554634, "properties": {"woe:id": 23554634, "woe:parent_id": 2429266, "woe:name": "Martha Puckett Middle School", "woe:placetype": 20, "woe:placetype_name": "POI", "woe:lang": "ENG", "iso:country": "US", "meta:provider": ["geoplanet:7.3.1", "geoplanet:7.3.2", "geoplanet:7.4.0", "geoplanet:7.4.1", "geoplanet:7.5.1", "geoplanet:7.5.2", "geoplanet:7.6.0", "geoplanet:7.8.1", "geoplanet:7.9.0", "geoplanet:7.10.0", "geoplanet:8.0.0", "woeplanet:8.0.0"], "meta:indexed": "2020-08-20T20:18:29.909172", "meta:updated": "2020-08-22T02:57:33.439806", "woe:hierarchy": {"continent": 24865672, "country": 23424977, "town": 0, "planet": 1, "county": 12588020, "suburb": 0, "state": 2347569, "region": 0, "localadmin": 0}, "woe:timezone_id": 56043648, "woe:hash": "djtgbh0tb815", "woe:centroid": [-81.913353, 31.61964], "geom:latitude": 31.61964, "geom:longitude": -81.913353, "geom:hash": "djtgbh0tb815", "woe:latitude": 31.61964, "geom:centroid": [-81.913353, 31.61964], "woe:longitude": -81.913353, "woe:repo": "woeplanet-poi-us"}, "geometry": {"coordinates": [-81.913353, 31.61964], "type": "Point"}}