{"type": "Feature", "id": 23578700, "properties": {"woe:id": 23578700, "woe:parent_id": 2408004, "woe:name": "Molly Ockett Middle School", "woe:placetype": 20, "woe:placetype_name": "POI", "woe:lang": "ENG", "iso:country": "US", "meta:provider": ["geoplanet:7.3.1", "geoplanet:7.3.2", "geoplanet:7.4.0", "geoplanet:7.4.1", "geoplanet:7.5.1", "geoplanet:7.5.2", "geoplanet:7.6.0", "geoplanet:7.8.1", "geoplanet:7.9.0", "geoplanet:7.10.0", "geoplanet:8.0.0", "woeplanet:8.0.0"], "meta:indexed": "2020-08-20T20:18:38.211176", "meta:updated": "2020-08-22T02:57:37.581182", "woe:hierarchy": {"continent": 24865672, "country": 23424977, "town": 0, "planet": 1, "county": 12588668, "suburb": 0, "state": 2347578, "region": 0, "localadmin": 0}, "woe:timezone_id": 56043648, "woe:hash": "drvd3jtdxgf5", "woe:centroid": [-70.963791, 44.01992], "geom:latitude": 44.01992, "geom:longitude": -70.963791, "geom:hash": "drvd3jtdxgf5", "woe:latitude": 44.01992, "geom:centroid": [-70.963791, 44.01992], "woe:longitude": -70.963791, "woe:repo": "woeplanet-poi-us"}, "geometry": {"coordinates": [-70.963791, 44.01992], "type": "Point"}}