{"type": "Feature", "id": 23623957, "geometry": {"type": "Point", "coordinates": [-81.269127, 35.642208]}, "properties": {"woe:id": 23623957, "woe:parent_id": 2499239, "woe:name": "Startown Elementary School", "woe:placetype": 20, "woe:placetype_name": "POI", "woe:lang": "ENG", "iso:country": "US", "meta:provider": ["geoplanet:7.3.2", "geoplanet:7.4.0", "geoplanet:7.4.1", "geoplanet:7.5.1", "geoplanet:7.5.2", "geoplanet:7.6.0", "geoplanet:7.8.1", "geoplanet:7.9.0", "geoplanet:7.10.0", "geoplanet:8.0.0", "woeplanet:8.0.0"], "meta:indexed": "2020-08-20T22:02:40.066878", "woe:alias_ENG_V": ["Startown Elementary"], "meta:updated": "2020-10-14T11:19:45.132855", "woe:hierarchy": {"continent": 24865672, "country": 23424977, "town": 0, "planet": 1, "county": 12589391, "suburb": 0, "state": 2347592, "region": 0, "localadmin": 0}, "woe:timezone_id": 56043648, "woe:hash": "dnq4y8mwuj4u", "woe:centroid": [-81.269127, 35.642208], "geom:latitude": 35.642208, "geom:longitude": -81.269127, "geom:hash": "dnq4y8mwuj4u", "woe:latitude": 35.642208, "geom:centroid": [-81.269127, 35.642208], "woe:longitude": -81.269127, "woe:repo": "woeplanet-poi-us", "geom:area": 0.0, "woe:scale": 19}}