{"type": "Feature", "id": 23541146, "properties": {"woe:id": 23541146, "woe:parent_id": 55973247, "woe:name": "Escalante Middle School", "woe:placetype": 20, "woe:placetype_name": "POI", "woe:lang": "ENG", "iso:country": "US", "meta:provider": ["geoplanet:7.3.1", "geoplanet:7.3.2", "geoplanet:7.4.0", "geoplanet:7.4.1", "geoplanet:7.5.1", "geoplanet:7.5.2", "geoplanet:7.6.0", "geoplanet:7.8.1", "geoplanet:7.9.0", "geoplanet:7.10.0", "geoplanet:8.0.0", "woeplanet:8.0.0"], "meta:indexed": "2020-08-20T20:18:24.669744", "meta:updated": "2020-08-22T02:57:30.828030", "woe:hierarchy": {"continent": 24865672, "country": 23424977, "town": 0, "planet": 1, "county": 12587760, "suburb": 0, "state": 2347564, "region": 0, "localadmin": 0}, "woe:timezone_id": 56043665, "woe:hash": "9we7c9069wdy", "woe:centroid": [-107.863358, 37.227638], "geom:latitude": 37.227638, "geom:longitude": -107.863358, "geom:hash": "9we7c9069wdy", "woe:latitude": 37.227638, "geom:centroid": [-107.863358, 37.227638], "woe:longitude": -107.863358, "woe:repo": "woeplanet-poi-us"}, "geometry": {"coordinates": [-107.863358, 37.227638], "type": "Point"}}