{"type": "Feature", "id": 23543551, "geometry": {"type": "Point", "coordinates": [-73.075867, 41.90921]}, "properties": {"woe:id": 23543551, "woe:parent_id": 2521705, "woe:name": "Batcheller Elementary School", "woe:placetype": 20, "woe:placetype_name": "POI", "woe:lang": "ENG", "iso:country": "US", "meta:provider": ["geoplanet:7.3.2", "geoplanet:7.4.0", "geoplanet:7.4.1", "geoplanet:7.5.1", "geoplanet:7.5.2", "geoplanet:7.6.0", "geoplanet:7.8.1", "geoplanet:7.9.0", "geoplanet:7.10.0", "geoplanet:8.0.0", "woeplanet:8.0.0"], "meta:indexed": "2020-08-20T22:02:07.141194", "woe:alias_ENG_V": ["Batcheller Primary School", "Batcheller Elementary"], "meta:updated": "2020-10-14T11:20:23.368876", "woe:hierarchy": {"continent": 24865672, "country": 23424977, "town": 0, "planet": 1, "county": 12587793, "suburb": 0, "state": 2347565, "region": 0, "localadmin": 0}, "woe:timezone_id": 56043648, "woe:hash": "drkn3j7fbfup", "woe:centroid": [-73.075867, 41.90921], "geom:latitude": 41.90921, "geom:longitude": -73.075867, "geom:hash": "drkn3j7fbfup", "woe:latitude": 41.90921, "geom:centroid": [-73.075867, 41.90921], "woe:longitude": -73.075867, "woe:repo": "woeplanet-poi-us", "geom:area": 0.0, "woe:scale": 19}}