{"type": "Feature", "id": 24866235, "geometry": {"type": "Point", "coordinates": [-121.782478, 42.254139]}, "properties": {"woe:id": 24866235, "woe:parent_id": 2433280, "woe:name": "Oregon Institute of Technology", "woe:placetype": 20, "woe:placetype_name": "POI", "woe:lang": "ENG", "iso:country": "US", "meta:provider": ["geoplanet:7.3.1", "geoplanet:7.3.2", "geoplanet:7.4.0", "geoplanet:7.4.1", "geoplanet:7.5.1", "geoplanet:7.5.2", "geoplanet:7.6.0", "geoplanet:7.8.1", "geoplanet:7.9.0", "geoplanet:7.10.0", "geoplanet:8.0.0", "woeplanet:8.0.0"], "meta:indexed": "2020-08-20T20:19:14.970214", "meta:updated": "2020-10-14T11:19:25.852243", "woe:hierarchy": {"continent": 24865672, "country": 23424977, "town": 0, "planet": 1, "county": 12589709, "suburb": 0, "state": 2347596, "region": 0, "localadmin": 0}, "woe:timezone_id": 56043663, "woe:hash": "9r92ku0snw6t", "woe:centroid": [-121.782478, 42.254139], "geom:latitude": 42.254139, "geom:longitude": -121.782478, "geom:hash": "9r92ku0snw6t", "woe:latitude": 42.254139, "geom:centroid": [-121.782478, 42.254139], "woe:longitude": -121.782478, "woe:repo": "woeplanet-poi-us", "geom:area": 0.0, "woe:scale": 19}}