{"type": "Feature", "id": 23619082, "properties": {"woe:id": 23619082, "woe:parent_id": 2444424, "woe:name": "Flushing High School", "woe:placetype": 20, "woe:placetype_name": "POI", "woe:lang": "ENG", "iso:country": "US", "meta:provider": ["geoplanet:7.3.1", "geoplanet:7.3.2", "geoplanet:7.4.0", "geoplanet:7.4.1", "geoplanet:7.5.1", "geoplanet:7.5.2", "geoplanet:7.6.0", "geoplanet:7.8.1", "geoplanet:7.9.0", "geoplanet:7.10.0", "geoplanet:8.0.0", "woeplanet:8.0.0"], "meta:indexed": "2020-08-20T20:18:51.051670", "woe:alias_ENG_V": ["Flushing Senior High School", "Flushing High", "Flushing Senior High", "Flushing HS", "Flushing Senior HS"], "meta:updated": "2020-08-22T02:58:48.809977", "woe:hierarchy": {"continent": 24865672, "country": 23424977, "town": 0, "planet": 1, "county": 12589352, "suburb": 0, "state": 2347591, "region": 0, "localadmin": 0}, "woe:timezone_id": 56043648, "woe:hash": "dr5xbj0556uh", "woe:centroid": [-73.82798, 40.765301], "geom:latitude": 40.765301, "geom:longitude": -73.82798, "geom:hash": "dr5xbj0556uh", "woe:latitude": 40.765301, "geom:centroid": [-73.82798, 40.765301], "woe:longitude": -73.82798, "woe:repo": "woeplanet-poi-us"}, "geometry": {"coordinates": [-73.82798, 40.765301], "type": "Point"}}