{"type": "Feature", "id": 23551662, "properties": {"woe:id": 23551662, "woe:parent_id": 2434779, "woe:name": "Babb Middle School", "woe:placetype": 20, "woe:placetype_name": "POI", "woe:lang": "ENG", "iso:country": "US", "meta:provider": ["geoplanet:7.3.2", "geoplanet:7.4.0", "geoplanet:7.4.1", "geoplanet:7.5.1", "geoplanet:7.5.2", "geoplanet:7.6.0", "geoplanet:7.8.1", "geoplanet:7.9.0", "geoplanet:7.10.0", "geoplanet:8.0.0", "woeplanet:8.0.0"], "meta:indexed": "2020-08-20T22:02:10.958070", "meta:updated": "2020-08-22T02:57:32.846478", "woe:alias_ENG_V": ["Gp Babb Middle School"], "woe:hierarchy": {"continent": 24865672, "country": 23424977, "town": 0, "planet": 1, "county": 12587900, "suburb": 0, "state": 2347569, "region": 0, "localadmin": 0}, "woe:timezone_id": 56043648, "woe:hash": "djup0t39hfph", "woe:centroid": [-84.350754, 33.603241], "geom:latitude": 33.603241, "geom:longitude": -84.350754, "geom:hash": "djup0t39hfph", "woe:latitude": 33.603241, "geom:centroid": [-84.350754, 33.603241], "woe:longitude": -84.350754, "woe:repo": "woeplanet-poi-us"}, "geometry": {"coordinates": [-84.350754, 33.603241], "type": "Point"}}