{"type": "Feature", "id": 23665226, "properties": {"woe:id": 23665226, "woe:parent_id": 2357135, "woe:name": "Cool Spring Elementary School", "woe:placetype": 20, "woe:placetype_name": "POI", "woe:lang": "ENG", "iso:country": "US", "meta:provider": ["geoplanet:7.3.1", "geoplanet:7.3.2", "geoplanet:7.4.0", "geoplanet:7.4.1", "geoplanet:7.5.1", "geoplanet:7.5.2", "geoplanet:7.6.0", "geoplanet:7.8.1", "geoplanet:7.9.0", "geoplanet:7.10.0", "geoplanet:8.0.0", "woeplanet:8.0.0"], "meta:indexed": "2020-08-20T20:19:08.039021", "woe:alias_ENG_V": ["Cool Spring Elementary"], "meta:updated": "2020-08-22T02:57:51.242710", "woe:hierarchy": {"continent": 24865672, "country": 23424977, "town": 0, "planet": 1, "county": 12590362, "suburb": 0, "state": 2347605, "region": 0, "localadmin": 0}, "woe:timezone_id": 56043648, "woe:hash": "dq8yq6psp0gc", "woe:centroid": [-77.410049, 37.67281], "geom:latitude": 37.67281, "geom:longitude": -77.410049, "geom:hash": "dq8yq6psp0gc", "woe:latitude": 37.67281, "geom:centroid": [-77.410049, 37.67281], "woe:longitude": -77.410049, "woe:repo": "woeplanet-poi-us"}, "geometry": {"coordinates": [-77.410049, 37.67281], "type": "Point"}}