{"type": "Feature", "id": 23607238, "geometry": {"type": "Point", "coordinates": [-74.107719, 40.855438]}, "properties": {"woe:id": 23607238, "woe:parent_id": 2513680, "woe:name": "Wallington High School", "woe:placetype": 20, "woe:placetype_name": "POI", "woe:lang": "ENG", "iso:country": "US", "meta:provider": ["geoplanet:7.4.0", "geoplanet:7.4.1", "geoplanet:7.5.1", "geoplanet:7.5.2", "geoplanet:7.6.0", "geoplanet:7.8.1", "geoplanet:7.9.0", "geoplanet:7.10.0", "geoplanet:8.0.0", "woeplanet:8.0.0"], "meta:indexed": "2020-08-20T23:56:00.962040", "meta:updated": "2020-10-14T11:19:30.395255", "woe:alias_ENG_V": ["Wallington Senior High School", "Wallington High", "Wallington Senior High", "Wallington HS", "Wallington Senior HS"], "woe:hierarchy": {"continent": 24865672, "country": 23424977, "town": 0, "planet": 1, "county": 12589259, "suburb": 0, "state": 2347589, "region": 0, "localadmin": 0}, "woe:timezone_id": 56043648, "woe:hash": "dr723ts2hvxs", "woe:centroid": [-74.107719, 40.855438], "geom:latitude": 40.855438, "geom:longitude": -74.107719, "geom:hash": "dr723ts2hvxs", "woe:latitude": 40.855438, "geom:centroid": [-74.107719, 40.855438], "woe:longitude": -74.107719, "woe:repo": "woeplanet-poi-us", "geom:area": 0.0, "woe:scale": 19}}