{"type": "Feature", "id": 24867019, "properties": {"woe:id": 24867019, "woe:parent_id": 28744419, "woe:name": "St. Norbert College", "woe:placetype": 20, "woe:placetype_name": "POI", "woe:lang": "ENG", "iso:country": "US", "meta:provider": ["geoplanet:7.3.1", "geoplanet:7.3.2", "geoplanet:7.4.0", "geoplanet:7.4.1", "geoplanet:7.5.1", "geoplanet:7.5.2", "geoplanet:7.6.0", "geoplanet:7.8.1", "geoplanet:7.9.0", "geoplanet:7.10.0", "geoplanet:8.0.0", "woeplanet:8.0.0"], "meta:indexed": "2020-08-20T20:19:15.450977", "meta:updated": "2020-08-22T02:58:19.964749", "woe:hierarchy": {"continent": 24865672, "country": 23424977, "town": 0, "planet": 1, "county": 12590538, "suburb": 0, "state": 2347608, "region": 0, "localadmin": 0}, "woe:timezone_id": 56043661, "woe:hash": "dpckkpkx71bx", "woe:centroid": [-88.060097, 44.381901], "geom:latitude": 44.381901, "geom:longitude": -88.060097, "geom:hash": "dpckkpkx71bx", "woe:latitude": 44.381901, "geom:centroid": [-88.060097, 44.381901], "woe:longitude": -88.060097, "woe:repo": "woeplanet-poi-us"}, "geometry": {"coordinates": [-88.060097, 44.381901], "type": "Point"}}