{"type": "Feature", "id": 23621196, "geometry": {"type": "Point", "coordinates": [-76.353607, 42.06004]}, "properties": {"woe:id": 23621196, "woe:parent_id": 2506631, "woe:name": "Tioga Elementary School", "woe:placetype": 20, "woe:placetype_name": "POI", "woe:lang": "ENG", "iso:country": "US", "meta:provider": ["geoplanet:7.3.1", "geoplanet:7.3.2", "geoplanet:7.4.0", "geoplanet:7.4.1", "geoplanet:7.5.1", "geoplanet:7.5.2", "geoplanet:7.6.0", "geoplanet:7.8.1", "geoplanet:7.9.0", "geoplanet:7.10.0", "geoplanet:8.0.0", "woeplanet:8.0.0"], "meta:indexed": "2020-08-20T20:18:51.923230", "woe:alias_ENG_V": ["Tioga Elementary"], "meta:updated": "2020-10-14T11:19:34.047455", "woe:hierarchy": {"continent": 24865672, "country": 23424977, "town": 0, "planet": 1, "county": 12589365, "suburb": 0, "state": 2347591, "region": 0, "localadmin": 0}, "woe:timezone_id": 56043648, "woe:hash": "dr3xq8c12p8p", "woe:centroid": [-76.353607, 42.06004], "geom:latitude": 42.06004, "geom:longitude": -76.353607, "geom:hash": "dr3xq8c12p8p", "woe:latitude": 42.06004, "geom:centroid": [-76.353607, 42.06004], "woe:longitude": -76.353607, "woe:repo": "woeplanet-poi-us", "geom:area": 0.0, "woe:scale": 19}}