{"type": "Feature", "id": 23578774, "geometry": {"type": "Point", "coordinates": [-68.793854, 44.80381]}, "properties": {"woe:id": 23578774, "woe:parent_id": 2358941, "woe:name": "Fourteenth Street School", "woe:placetype": 20, "woe:placetype_name": "POI", "woe:lang": "ENG", "iso:country": "US", "meta:provider": ["geoplanet:7.3.1", "geoplanet:7.3.2", "geoplanet:7.4.0", "geoplanet:7.4.1", "geoplanet:7.5.1", "geoplanet:7.5.2", "geoplanet:7.6.0", "geoplanet:7.8.1", "geoplanet:7.9.0", "geoplanet:7.10.0", "geoplanet:8.0.0", "woeplanet:8.0.0"], "meta:indexed": "2020-08-20T20:18:38.220557", "meta:updated": "2020-10-14T11:20:22.781651", "woe:hierarchy": {"continent": 24865672, "country": 23424977, "town": 0, "planet": 1, "county": 12588669, "suburb": 0, "state": 2347578, "region": 0, "localadmin": 0}, "woe:timezone_id": 56043648, "woe:hash": "drznfs3c5589", "woe:centroid": [-68.793854, 44.80381], "geom:latitude": 44.80381, "geom:longitude": -68.793854, "geom:hash": "drznfs3c5589", "woe:latitude": 44.80381, "geom:centroid": [-68.793854, 44.80381], "woe:longitude": -68.793854, "woe:repo": "woeplanet-poi-us", "geom:area": 0.0, "woe:scale": 19}}