{"type": "Feature", "id": 23595316, "geometry": {"type": "Point", "coordinates": [-93.552292, 45.261379]}, "properties": {"woe:id": 23595316, "woe:parent_id": 2466753, "woe:name": "Otsego Elementary School", "woe:placetype": 20, "woe:placetype_name": "POI", "woe:lang": "ENG", "iso:country": "US", "meta:provider": ["geoplanet:7.3.1", "geoplanet:7.3.2", "geoplanet:7.4.0", "geoplanet:7.4.1", "geoplanet:7.5.1", "geoplanet:7.5.2", "geoplanet:7.6.0", "geoplanet:7.8.1", "geoplanet:7.9.0", "geoplanet:7.10.0", "geoplanet:8.0.0", "woeplanet:8.0.0"], "meta:indexed": "2020-08-20T20:18:43.172723", "woe:alias_ENG_V": ["Otsego Elementary"], "meta:updated": "2020-10-14T11:20:19.550580", "woe:hierarchy": {"continent": 24865672, "country": 23424977, "town": 0, "planet": 1, "county": 12588882, "suburb": 0, "state": 2347582, "region": 0, "localadmin": 0}, "woe:timezone_id": 56043661, "woe:hash": "cbj3rpt69se4", "woe:centroid": [-93.552292, 45.261379], "geom:latitude": 45.261379, "geom:longitude": -93.552292, "geom:hash": "cbj3rpt69se4", "woe:latitude": 45.261379, "geom:centroid": [-93.552292, 45.261379], "woe:longitude": -93.552292, "woe:repo": "woeplanet-poi-us", "geom:area": 0.0, "woe:scale": 19}}