{"type": "Feature", "id": 23620029, "geometry": {"type": "Point", "coordinates": [-74.060997, 41.082199]}, "properties": {"woe:id": 23620029, "woe:parent_id": 2379468, "woe:name": "Green Meadow Waldorf School", "woe:placetype": 20, "woe:placetype_name": "POI", "woe:lang": "ENG", "iso:country": "US", "meta:provider": ["geoplanet:7.3.1", "geoplanet:7.3.2", "geoplanet:7.4.0", "geoplanet:7.4.1", "geoplanet:7.5.1", "geoplanet:7.5.2", "geoplanet:7.6.0", "geoplanet:7.8.1", "geoplanet:7.9.0", "geoplanet:7.10.0", "geoplanet:8.0.0", "woeplanet:8.0.0"], "meta:indexed": "2020-08-20T20:18:51.484571", "meta:updated": "2020-10-14T11:19:46.991004", "woe:hierarchy": {"continent": 24865672, "country": 23424977, "town": 0, "planet": 1, "county": 12589355, "suburb": 0, "state": 2347591, "region": 0, "localadmin": 0}, "woe:timezone_id": 56043648, "woe:hash": "dr73dwy3jsyn", "woe:centroid": [-74.060997, 41.082199], "geom:latitude": 41.082199, "geom:longitude": -74.060997, "geom:hash": "dr73dwy3jsyn", "woe:latitude": 41.082199, "geom:centroid": [-74.060997, 41.082199], "woe:longitude": -74.060997, "woe:repo": "woeplanet-poi-us", "geom:area": 0.0, "woe:scale": 19}}