{"type": "Feature", "id": 23581403, "properties": {"woe:id": 23581403, "woe:parent_id": 2377666, "woe:name": "Kennard Elementary School", "woe:placetype": 20, "woe:placetype_name": "POI", "woe:lang": "ENG", "iso:country": "US", "meta:provider": ["geoplanet:7.3.1", "geoplanet:7.3.2", "geoplanet:7.4.0", "geoplanet:7.4.1", "geoplanet:7.5.1", "geoplanet:7.5.2", "geoplanet:7.6.0", "geoplanet:7.8.1", "geoplanet:7.9.0", "geoplanet:7.10.0", "geoplanet:8.0.0", "woeplanet:8.0.0"], "meta:indexed": "2020-08-20T20:18:38.809060", "woe:alias_ENG_V": ["Kennard Elementary"], "meta:updated": "2020-08-22T02:57:38.076772", "woe:hierarchy": {"continent": 24865672, "country": 23424977, "town": 0, "planet": 1, "county": 12588693, "suburb": 0, "state": 2347579, "region": 0, "localadmin": 0}, "woe:timezone_id": 56043648, "woe:hash": "dqcyj4u16bdb", "woe:centroid": [-76.063721, 39.038761], "geom:latitude": 39.038761, "geom:longitude": -76.063721, "geom:hash": "dqcyj4u16bdb", "woe:latitude": 39.038761, "geom:centroid": [-76.063721, 39.038761], "woe:longitude": -76.063721, "woe:repo": "woeplanet-poi-us"}, "geometry": {"coordinates": [-76.063721, 39.038761], "type": "Point"}}