{"type": "Feature", "id": 23632860, "geometry": {"type": "Point", "coordinates": [-83.364929, 40.230621]}, "properties": {"woe:id": 23632860, "woe:parent_id": 2446574, "woe:name": "Trinity Lutheran School", "woe:placetype": 20, "woe:placetype_name": "POI", "woe:lang": "ENG", "iso:country": "US", "meta:provider": ["geoplanet:7.3.2", "geoplanet:7.4.0", "geoplanet:7.4.1", "geoplanet:7.5.1", "geoplanet:7.5.2", "geoplanet:7.6.0", "geoplanet:7.8.1", "geoplanet:7.9.0", "geoplanet:7.10.0", "geoplanet:8.0.0", "woeplanet:8.0.0"], "meta:indexed": "2020-08-20T22:02:44.180019", "meta:updated": "2020-10-14T11:19:39.008332", "woe:hierarchy": {"continent": 24865672, "country": 23424977, "town": 0, "planet": 1, "county": 12589606, "suburb": 0, "state": 2347594, "region": 0, "localadmin": 0}, "woe:timezone_id": 56043648, "woe:hash": "dphsygz8277d", "woe:centroid": [-83.364929, 40.230621], "geom:latitude": 40.230621, "geom:longitude": -83.364929, "geom:hash": "dphsygz8277d", "woe:latitude": 40.230621, "geom:centroid": [-83.364929, 40.230621], "woe:longitude": -83.364929, "woe:repo": "woeplanet-poi-us", "geom:area": 0.0, "woe:scale": 19}}