{"type": "Feature", "id": 23512965, "geometry": {"type": "Point", "coordinates": [-85.380753, 31.26572]}, "properties": {"woe:id": 23512965, "woe:parent_id": 2393127, "woe:name": "Dothan Technology Center", "woe:placetype": 20, "woe:placetype_name": "POI", "woe:lang": "ENG", "iso:country": "US", "meta:provider": ["geoplanet:7.3.2", "geoplanet:7.4.0", "geoplanet:7.4.1", "geoplanet:7.5.1", "geoplanet:7.5.2", "geoplanet:7.6.0", "geoplanet:7.8.1", "geoplanet:7.9.0", "geoplanet:7.10.0", "geoplanet:8.0.0", "woeplanet:8.0.0"], "meta:indexed": "2020-08-20T22:01:55.162027", "meta:updated": "2020-10-14T11:20:14.407177", "woe:hierarchy": {"continent": 24865672, "country": 23424977, "town": 0, "planet": 1, "county": 12587521, "suburb": 0, "state": 2347559, "region": 0, "localadmin": 0}, "woe:timezone_id": 56043661, "woe:hash": "dje3c5g8h28h", "woe:centroid": [-85.380753, 31.26572], "geom:latitude": 31.26572, "geom:longitude": -85.380753, "geom:hash": "dje3c5g8h28h", "woe:latitude": 31.26572, "geom:centroid": [-85.380753, 31.26572], "woe:longitude": -85.380753, "woe:repo": "woeplanet-poi-us", "geom:area": 0.0, "woe:scale": 19}}