{"type": "Feature", "id": 23668562, "properties": {"woe:id": 23668562, "woe:parent_id": 2521520, "woe:name": "Coulee City Middle School", "woe:placetype": 20, "woe:placetype_name": "POI", "woe:lang": "ENG", "iso:country": "US", "meta:provider": ["geoplanet:7.3.1", "geoplanet:7.3.2", "geoplanet:7.4.0", "geoplanet:7.4.1", "geoplanet:7.5.1", "geoplanet:7.5.2", "geoplanet:7.6.0", "geoplanet:7.8.1", "geoplanet:7.9.0", "geoplanet:7.10.0", "geoplanet:8.0.0", "woeplanet:8.0.0"], "meta:indexed": "2020-08-20T20:19:09.145517", "meta:updated": "2020-08-22T02:57:51.875409", "woe:hierarchy": {"continent": 24865672, "country": 23424977, "town": 0, "planet": 1, "county": 12590452, "suburb": 0, "state": 2347606, "region": 0, "localadmin": 0}, "woe:timezone_id": 56043663, "woe:hash": "c27mc3171z0b", "woe:centroid": [-119.122963, 47.423038], "geom:latitude": 47.423038, "geom:longitude": -119.122963, "geom:hash": "c27mc3171z0b", "woe:latitude": 47.423038, "geom:centroid": [-119.122963, 47.423038], "woe:longitude": -119.122963, "woe:repo": "woeplanet-poi-us"}, "geometry": {"coordinates": [-119.122963, 47.423038], "type": "Point"}}