{"type": "Feature", "id": 23625372, "properties": {"woe:id": 23625372, "woe:parent_id": 55988271, "woe:name": "Pinewood Elementary School", "woe:placetype": 20, "woe:placetype_name": "POI", "woe:lang": "ENG", "iso:country": "US", "meta:provider": ["geoplanet:7.3.2", "geoplanet:7.4.0", "geoplanet:7.4.1", "geoplanet:7.5.1", "geoplanet:7.5.2", "geoplanet:7.6.0", "geoplanet:7.8.1", "geoplanet:7.9.0", "geoplanet:7.10.0", "geoplanet:8.0.0", "woeplanet:8.0.0"], "meta:indexed": "2020-08-20T22:02:40.479787", "woe:alias_ENG_V": ["Pinewood Elementary"], "meta:updated": "2020-08-22T02:57:44.422995", "woe:hierarchy": {"continent": 24865672, "country": 23424977, "town": 0, "planet": 1, "county": 12589433, "suburb": 0, "state": 2347592, "region": 0, "localadmin": 0}, "woe:timezone_id": 56043648, "woe:hash": "dnq2pct47w1u", "woe:centroid": [-80.863342, 35.164909], "geom:latitude": 35.164909, "geom:longitude": -80.863342, "geom:hash": "dnq2pct47w1u", "woe:latitude": 35.164909, "geom:centroid": [-80.863342, 35.164909], "woe:longitude": -80.863342, "woe:repo": "woeplanet-poi-us"}, "geometry": {"coordinates": [-80.863342, 35.164909], "type": "Point"}}