{"type": "Feature", "id": 23608012, "properties": {"woe:id": 23608012, "woe:parent_id": 55991659, "woe:name": "R.d. Wood Elementary School", "woe:placetype": 20, "woe:placetype_name": "POI", "woe:lang": "ENG", "iso:country": "US", "meta:provider": ["geoplanet:7.3.1", "geoplanet:7.3.2", "geoplanet:7.4.0", "geoplanet:7.4.1", "geoplanet:7.5.1", "geoplanet:7.5.2", "geoplanet:7.6.0", "geoplanet:7.8.1", "geoplanet:7.9.0", "geoplanet:7.10.0", "geoplanet:8.0.0", "woeplanet:8.0.0"], "meta:indexed": "2020-08-20T20:18:46.969070", "woe:alias_ENG_V": ["Rd Wood Elementary School", "R.d. Wood Elementary"], "meta:updated": "2020-08-22T02:57:42.011385", "woe:hierarchy": {"continent": 24865672, "country": 23424977, "town": 0, "planet": 1, "county": 12589263, "suburb": 0, "state": 2347589, "region": 0, "localadmin": 0}, "woe:timezone_id": 56043648, "woe:hash": "dr48hmhjuqtc", "woe:centroid": [-75.041924, 39.403488], "geom:latitude": 39.403488, "geom:longitude": -75.041924, "geom:hash": "dr48hmhjuqtc", "woe:latitude": 39.403488, "geom:centroid": [-75.041924, 39.403488], "woe:longitude": -75.041924, "woe:repo": "woeplanet-poi-us"}, "geometry": {"coordinates": [-75.041924, 39.403488], "type": "Point"}}