{"type": "Feature", "id": 23589539, "geometry": {"type": "Point", "coordinates": [-83.246399, 42.516491]}, "properties": {"woe:id": 23589539, "woe:parent_id": 56021916, "woe:name": "Wylie E. Groves High School", "woe:placetype": 20, "woe:placetype_name": "POI", "woe:lang": "ENG", "iso:country": "US", "meta:provider": ["geoplanet:7.3.2", "geoplanet:7.4.0", "geoplanet:7.4.1", "geoplanet:7.5.1", "geoplanet:7.5.2", "geoplanet:7.6.0", "geoplanet:7.8.1", "geoplanet:7.9.0", "geoplanet:7.10.0", "geoplanet:8.0.0", "woeplanet:8.0.0"], "meta:indexed": "2020-08-20T22:02:26.439178", "woe:alias_ENG_V": ["Wylie E. Groves Senior High School", "Wylie E. Groves High", "Wylie E. Groves Senior High", "Wylie E. Groves HS", "Wylie E. Groves Senior HS"], "meta:updated": "2020-10-14T11:20:26.853722", "woe:hierarchy": {"continent": 24865672, "country": 23424977, "town": 0, "planet": 1, "county": 12588776, "suburb": 0, "state": 2347581, "region": 0, "localadmin": 0}, "woe:timezone_id": 56043658, "woe:hash": "dpsccevud23g", "woe:centroid": [-83.246399, 42.516491], "geom:latitude": 42.516491, "geom:longitude": -83.246399, "geom:hash": "dpsccevud23g", "woe:latitude": 42.516491, "geom:centroid": [-83.246399, 42.516491], "woe:longitude": -83.246399, "woe:repo": "woeplanet-poi-us", "geom:area": 0.0, "woe:scale": 19}}