{"type": "Feature", "id": 23648670, "properties": {"woe:id": 23648670, "woe:parent_id": 2396178, "woe:name": "School For the Deaf Middle School", "woe:placetype": 20, "woe:placetype_name": "POI", "woe:lang": "ENG", "iso:country": "US", "meta:provider": ["geoplanet:7.3.1", "geoplanet:7.3.2", "geoplanet:7.4.0", "geoplanet:7.4.1", "geoplanet:7.5.1", "geoplanet:7.5.2", "geoplanet:7.6.0", "geoplanet:7.8.1", "geoplanet:7.9.0", "geoplanet:7.10.0", "geoplanet:8.0.0", "woeplanet:8.0.0"], "meta:indexed": "2020-08-20T20:19:01.275654", "meta:updated": "2020-08-22T02:57:47.971752", "woe:hierarchy": {"continent": 24865672, "country": 23424977, "town": 0, "planet": 1, "county": 12589894, "suburb": 0, "state": 2347600, "region": 0, "localadmin": 0}, "woe:timezone_id": 56043661, "woe:hash": "9zepxxb356gc", "woe:centroid": [-96.701172, 43.548618], "geom:latitude": 43.548618, "geom:longitude": -96.701172, "geom:hash": "9zepxxb356gc", "woe:latitude": 43.548618, "geom:centroid": [-96.701172, 43.548618], "woe:longitude": -96.701172, "woe:repo": "woeplanet-poi-us"}, "geometry": {"coordinates": [-96.701172, 43.548618], "type": "Point"}}