{"type": "Feature", "id": 23658581, "geometry": {"type": "Point", "coordinates": [-97.971786, 29.575371]}, "properties": {"woe:id": 23658581, "woe:parent_id": 2490592, "woe:name": "Ball Elementary School", "woe:placetype": 20, "woe:placetype_name": "POI", "woe:lang": "ENG", "iso:country": "US", "meta:provider": ["geoplanet:7.3.2", "geoplanet:7.4.0", "geoplanet:7.4.1", "geoplanet:7.5.1", "geoplanet:7.5.2", "geoplanet:7.6.0", "geoplanet:7.8.1", "geoplanet:7.9.0", "geoplanet:7.10.0", "geoplanet:8.0.0", "woeplanet:8.0.0"], "meta:indexed": "2020-08-20T22:02:55.137797", "woe:alias_ENG_V": ["Ball Elementary"], "meta:updated": "2020-10-14T11:19:45.936530", "woe:hierarchy": {"continent": 24865672, "country": 23424977, "town": 0, "planet": 1, "county": 12590100, "suburb": 0, "state": 2347602, "region": 0, "localadmin": 0}, "woe:timezone_id": 56043661, "woe:hash": "9v6268515bv8", "woe:centroid": [-97.971786, 29.575371], "geom:latitude": 29.575371, "geom:longitude": -97.971786, "geom:hash": "9v6268515bv8", "woe:latitude": 29.575371, "geom:centroid": [-97.971786, 29.575371], "woe:longitude": -97.971786, "woe:repo": "woeplanet-poi-us", "geom:area": 0.0, "woe:scale": 19}}