{"type": "Feature", "id": 23517810, "geometry": {"type": "Point", "coordinates": [-91.850677, 33.354]}, "properties": {"woe:id": 23517810, "woe:parent_id": 2406277, "woe:name": "Fountain Hill High School", "woe:placetype": 20, "woe:placetype_name": "POI", "woe:lang": "ENG", "iso:country": "US", "meta:provider": ["geoplanet:7.3.1", "geoplanet:7.3.2", "geoplanet:7.4.0", "geoplanet:7.4.1", "geoplanet:7.5.1", "geoplanet:7.5.2", "geoplanet:7.6.0", "geoplanet:7.8.1", "geoplanet:7.9.0", "geoplanet:7.10.0", "geoplanet:8.0.0", "woeplanet:8.0.0"], "meta:indexed": "2020-08-20T20:18:18.852731", "woe:alias_ENG_V": ["Fountain Hill Senior High School", "Fountain Hill High", "Fountain Hill Senior High", "Fountain Hill HS", "Fountain Hill Senior HS"], "meta:updated": "2020-10-14T11:20:08.423769", "woe:hierarchy": {"continent": 24865672, "country": 23424977, "town": 0, "planet": 1, "county": 12587596, "suburb": 0, "state": 2347562, "region": 0, "localadmin": 0}, "woe:timezone_id": 56043661, "woe:hash": "9vyttzumhh5p", "woe:centroid": [-91.850677, 33.354], "geom:latitude": 33.354, "geom:longitude": -91.850677, "geom:hash": "9vyttzumhh5p", "woe:latitude": 33.354, "geom:centroid": [-91.850677, 33.354], "woe:longitude": -91.850677, "woe:repo": "woeplanet-poi-us", "geom:area": 0.0, "woe:scale": 19}}