{"type": "Feature", "id": 23656189, "properties": {"woe:id": 23656189, "woe:parent_id": 2377220, "woe:name": "C H Daniels Intermediate School", "woe:placetype": 20, "woe:placetype_name": "POI", "woe:lang": "ENG", "iso:country": "US", "meta:provider": ["geoplanet:7.3.1", "geoplanet:7.3.2", "geoplanet:7.4.0", "geoplanet:7.4.1", "geoplanet:7.5.1", "geoplanet:7.5.2", "geoplanet:7.6.0", "geoplanet:7.8.1", "geoplanet:7.9.0", "geoplanet:7.10.0", "geoplanet:8.0.0", "woeplanet:8.0.0"], "meta:indexed": "2020-08-20T20:19:04.214676", "meta:updated": "2020-08-22T02:57:49.480520", "woe:hierarchy": {"continent": 24865672, "country": 23424977, "town": 0, "planet": 1, "county": 12590216, "suburb": 0, "state": 2347602, "region": 0, "localadmin": 0}, "woe:timezone_id": 56043661, "woe:hash": "9vthc4702754", "woe:centroid": [-94.17067, 31.78488], "geom:latitude": 31.78488, "geom:longitude": -94.17067, "geom:hash": "9vthc4702754", "woe:latitude": 31.78488, "geom:centroid": [-94.17067, 31.78488], "woe:longitude": -94.17067, "woe:repo": "woeplanet-poi-us"}, "geometry": {"coordinates": [-94.17067, 31.78488], "type": "Point"}}