{"type": "Feature", "id": 23586593, "geometry": {"type": "Point", "coordinates": [-86.088127, 41.789791]}, "properties": {"woe:id": 23586593, "woe:parent_id": 2397540, "woe:name": "Eagle Lake Elementary School", "woe:placetype": 20, "woe:placetype_name": "POI", "woe:lang": "ENG", "iso:country": "US", "meta:provider": ["geoplanet:7.3.1", "geoplanet:7.3.2", "geoplanet:7.4.0", "geoplanet:7.4.1", "geoplanet:7.5.1", "geoplanet:7.5.2", "geoplanet:7.6.0", "geoplanet:7.8.1", "geoplanet:7.9.0", "geoplanet:7.10.0", "geoplanet:8.0.0", "woeplanet:8.0.0"], "meta:indexed": "2020-08-20T20:18:40.034660", "woe:alias_ENG_V": ["Eagle Lake Elementary"], "meta:updated": "2020-10-14T11:20:19.596320", "woe:hierarchy": {"continent": 24865672, "country": 23424977, "town": 0, "planet": 1, "county": 12588727, "suburb": 0, "state": 2347581, "region": 0, "localadmin": 0}, "woe:timezone_id": 56043658, "woe:hash": "dp6v9p8e1jxv", "woe:centroid": [-86.088127, 41.789791], "geom:latitude": 41.789791, "geom:longitude": -86.088127, "geom:hash": "dp6v9p8e1jxv", "woe:latitude": 41.789791, "geom:centroid": [-86.088127, 41.789791], "woe:longitude": -86.088127, "woe:repo": "woeplanet-poi-us", "geom:area": 0.0, "woe:scale": 19}}