{"type": "Feature", "id": 23643912, "properties": {"woe:id": 23643912, "woe:parent_id": 2425783, "woe:name": "Barton Clara School", "woe:placetype": 20, "woe:placetype_name": "POI", "woe:lang": "ENG", "iso:country": "US", "meta:provider": ["geoplanet:7.3.1", "geoplanet:7.3.2", "geoplanet:7.4.0", "geoplanet:7.4.1", "geoplanet:7.5.1", "geoplanet:7.5.2", "geoplanet:7.6.0", "geoplanet:7.8.1", "geoplanet:7.9.0", "geoplanet:7.10.0", "geoplanet:8.0.0", "woeplanet:8.0.0"], "meta:indexed": "2020-08-20T20:18:59.721304", "meta:updated": "2020-08-22T02:57:47.242995", "woe:alias_ENG_V": ["Clara Barton Elementary School"], "woe:hierarchy": {"continent": 24865672, "country": 23424977, "town": 0, "planet": 1, "county": 12589778, "suburb": 0, "state": 2347597, "region": 0, "localadmin": 0}, "woe:timezone_id": 56043648, "woe:hash": "dr4edt79p29w", "woe:centroid": [-75.119392, 40.019249], "geom:latitude": 40.019249, "geom:longitude": -75.119392, "geom:hash": "dr4edt79p29w", "woe:latitude": 40.019249, "geom:centroid": [-75.119392, 40.019249], "woe:longitude": -75.119392, "woe:repo": "woeplanet-poi-us"}, "geometry": {"coordinates": [-75.119392, 40.019249], "type": "Point"}}