{"type": "Feature", "id": 23627141, "geometry": {"type": "Point", "coordinates": [-84.146881, 40.745739]}, "properties": {"woe:id": 23627141, "woe:parent_id": 2439322, "woe:name": "Westwood Elementary School", "woe:placetype": 20, "woe:placetype_name": "POI", "woe:lang": "ENG", "iso:country": "US", "meta:provider": ["geoplanet:7.3.1", "geoplanet:7.3.2", "geoplanet:7.4.0", "geoplanet:7.4.1", "geoplanet:7.5.1", "geoplanet:7.5.2", "geoplanet:7.6.0", "geoplanet:7.8.1", "geoplanet:7.9.0", "geoplanet:7.10.0", "geoplanet:8.0.0", "woeplanet:8.0.0"], "meta:indexed": "2020-08-20T20:18:53.125257", "woe:alias_ENG_V": ["Westwood Elementary"], "meta:updated": "2020-10-14T11:19:40.850830", "woe:hierarchy": {"continent": 24865672, "country": 23424977, "town": 0, "planet": 1, "county": 12589528, "suburb": 0, "state": 2347594, "region": 0, "localadmin": 0}, "woe:timezone_id": 56043648, "woe:hash": "dphpv1w15s3b", "woe:centroid": [-84.146881, 40.745739], "geom:latitude": 40.745739, "geom:longitude": -84.146881, "geom:hash": "dphpv1w15s3b", "woe:latitude": 40.745739, "geom:centroid": [-84.146881, 40.745739], "woe:longitude": -84.146881, "woe:repo": "woeplanet-poi-us", "geom:area": 0.0, "woe:scale": 19}}