{"type": "Feature", "id": 23522832, "properties": {"woe:id": 23522832, "woe:parent_id": 2475962, "woe:name": "Potter Valley High School", "woe:placetype": 20, "woe:placetype_name": "POI", "woe:lang": "ENG", "iso:country": "US", "meta:provider": ["geoplanet:7.3.2", "geoplanet:7.4.0", "geoplanet:7.4.1", "geoplanet:7.5.1", "geoplanet:7.5.2", "geoplanet:7.6.0", "geoplanet:7.8.1", "geoplanet:7.9.0", "geoplanet:7.10.0", "geoplanet:8.0.0", "woeplanet:8.0.0"], "meta:indexed": "2020-08-20T22:01:59.003503", "woe:alias_ENG_V": ["Potter Valley Senior High School", "Potter Valley High", "Potter Valley Senior High", "Potter Valley HS", "Potter Valley Senior HS", "Potter Valley Jr & Sr High", "Potter Valley Jr & Sr High School", "Potter Valley Jr & Sr HS", "Potter Valley Jr & Sr Senior High", "Potter Valley Jr & Sr Senior High School", "Potter Valley Jr & Sr Senior HS"], "meta:updated": "2020-08-22T02:58:46.114465", "woe:hierarchy": {"continent": 24865672, "country": 23424977, "town": 0, "planet": 1, "county": 12587692, "suburb": 0, "state": 2347563, "region": 0, "localadmin": 0}, "woe:timezone_id": 56043663, "woe:hash": "9qbrwwmd85vy", "woe:centroid": [-123.105232, 39.321892], "geom:latitude": 39.321892, "geom:longitude": -123.105232, "geom:hash": "9qbrwwmd85vy", "woe:latitude": 39.321892, "geom:centroid": [-123.105232, 39.321892], "woe:longitude": -123.105232, "woe:repo": "woeplanet-poi-us"}, "geometry": {"coordinates": [-123.105232, 39.321892], "type": "Point"}}