{"type": "Feature", "id": 23623966, "properties": {"woe:id": 23623966, "woe:parent_id": 28339391, "woe:name": "W M Jenkins Elementary School", "woe:placetype": 20, "woe:placetype_name": "POI", "woe:lang": "ENG", "iso:country": "US", "meta:provider": ["geoplanet:7.3.2", "geoplanet:7.4.0", "geoplanet:7.4.1", "geoplanet:7.5.1", "geoplanet:7.5.2", "geoplanet:7.6.0", "geoplanet:7.8.1", "geoplanet:7.9.0", "geoplanet:7.10.0", "geoplanet:8.0.0", "woeplanet:8.0.0"], "meta:indexed": "2020-08-20T22:02:40.072260", "woe:alias_ENG_V": ["Wm Jenkins Elementary School", "W M Jenkins Elementary"], "meta:updated": "2020-08-22T02:57:44.281290", "woe:hierarchy": {"continent": 24865672, "country": 23424977, "town": 0, "planet": 1, "county": 12589391, "suburb": 0, "state": 2347592, "region": 0, "localadmin": 0}, "woe:timezone_id": 56043648, "woe:hash": "dnq5t3wnv750", "woe:centroid": [-81.323318, 35.780899], "geom:latitude": 35.780899, "geom:longitude": -81.323318, "geom:hash": "dnq5t3wnv750", "woe:latitude": 35.780899, "geom:centroid": [-81.323318, 35.780899], "woe:longitude": -81.323318, "woe:repo": "woeplanet-poi-us"}, "geometry": {"coordinates": [-81.323318, 35.780899], "type": "Point"}}