{"type": "Feature", "id": 23592861, "geometry": {"type": "Point", "coordinates": [-92.848663, 44.734241]}, "properties": {"woe:id": 23592861, "woe:parent_id": 2418575, "woe:name": "Kennedy Elementary School", "woe:placetype": 20, "woe:placetype_name": "POI", "woe:lang": "ENG", "iso:country": "US", "meta:provider": ["geoplanet:7.3.1", "geoplanet:7.3.2", "geoplanet:7.4.0", "geoplanet:7.4.1", "geoplanet:7.5.1", "geoplanet:7.5.2", "geoplanet:7.6.0", "geoplanet:7.8.1", "geoplanet:7.9.0", "geoplanet:7.10.0", "geoplanet:8.0.0", "woeplanet:8.0.0"], "meta:indexed": "2020-08-20T20:18:42.205455", "woe:alias_ENG_V": ["Kennedy Elementary"], "meta:updated": "2020-10-14T11:20:06.641647", "woe:hierarchy": {"continent": 24865672, "country": 23424977, "town": 0, "planet": 1, "county": 12588815, "suburb": 0, "state": 2347582, "region": 0, "localadmin": 0}, "woe:timezone_id": 56043661, "woe:hash": "9zvyrptev6fv", "woe:centroid": [-92.848663, 44.734241], "geom:latitude": 44.734241, "geom:longitude": -92.848663, "geom:hash": "9zvyrptev6fv", "woe:latitude": 44.734241, "geom:centroid": [-92.848663, 44.734241], "woe:longitude": -92.848663, "woe:repo": "woeplanet-poi-us", "geom:area": 0.0, "woe:scale": 19}}