{"type": "Feature", "id": 23656762, "properties": {"woe:id": 23656762, "woe:parent_id": 56022745, "woe:name": "Fort Worth Country Day School", "woe:placetype": 20, "woe:placetype_name": "POI", "woe:lang": "ENG", "iso:country": "US", "meta:provider": ["geoplanet:7.4.0", "geoplanet:7.4.1", "geoplanet:7.5.1", "geoplanet:7.5.2", "geoplanet:7.6.0", "geoplanet:7.8.1", "geoplanet:7.9.0", "geoplanet:7.10.0", "geoplanet:8.0.0", "woeplanet:8.0.0"], "meta:indexed": "2020-08-20T23:55:40.131498", "meta:updated": "2020-08-22T02:57:49.662066", "woe:hierarchy": {"continent": 24865672, "country": 23424977, "town": 0, "planet": 1, "county": 12590226, "suburb": 0, "state": 2347602, "region": 0, "localadmin": 0}, "woe:timezone_id": 56043661, "woe:hash": "9vf9zrr5vf77", "woe:centroid": [-97.405907, 32.691849], "geom:latitude": 32.691849, "geom:longitude": -97.405907, "geom:hash": "9vf9zrr5vf77", "woe:latitude": 32.691849, "geom:centroid": [-97.405907, 32.691849], "woe:longitude": -97.405907, "woe:repo": "woeplanet-poi-us"}, "geometry": {"coordinates": [-97.405907, 32.691849], "type": "Point"}}