{"type": "Feature", "id": 23544669, "geometry": {"type": "Point", "coordinates": [-75.432281, 38.91954]}, "properties": {"woe:id": 23544669, "woe:parent_id": 2443336, "woe:name": "Benjamin Banneker Elementary School", "woe:placetype": 20, "woe:placetype_name": "POI", "woe:lang": "ENG", "iso:country": "US", "meta:provider": ["geoplanet:7.3.1", "geoplanet:7.3.2", "geoplanet:7.4.0", "geoplanet:7.4.1", "geoplanet:7.5.1", "geoplanet:7.5.2", "geoplanet:7.6.0", "geoplanet:7.8.1", "geoplanet:7.9.0", "geoplanet:7.10.0", "geoplanet:8.0.0", "woeplanet:8.0.0"], "meta:indexed": "2020-08-20T20:18:25.665585", "woe:alias_ENG_V": ["Benjamin Banneker Elementary"], "meta:updated": "2020-10-14T11:20:24.241937", "woe:hierarchy": {"continent": 24865672, "country": 23424977, "town": 0, "planet": 1, "county": 12587799, "suburb": 0, "state": 2347566, "region": 0, "localadmin": 0}, "woe:timezone_id": 56043648, "woe:hash": "dqfm7mpfu2ne", "woe:centroid": [-75.432281, 38.91954], "geom:latitude": 38.91954, "geom:longitude": -75.432281, "geom:hash": "dqfm7mpfu2ne", "woe:latitude": 38.91954, "geom:centroid": [-75.432281, 38.91954], "woe:longitude": -75.432281, "woe:repo": "woeplanet-poi-us", "geom:area": 0.0, "woe:scale": 19}}