{"type": "Feature", "id": 23602422, "properties": {"woe:id": 23602422, "woe:parent_id": 2351651, "woe:name": "Absarokee High School", "woe:placetype": 20, "woe:placetype_name": "POI", "woe:lang": "ENG", "iso:country": "US", "meta:provider": ["geoplanet:7.3.2", "geoplanet:7.4.0", "geoplanet:7.4.1", "geoplanet:7.5.1", "geoplanet:7.5.2", "geoplanet:7.6.0", "geoplanet:7.8.1", "geoplanet:7.9.0", "geoplanet:7.10.0", "geoplanet:8.0.0", "woeplanet:8.0.0"], "meta:indexed": "2020-08-20T22:02:31.575513", "woe:alias_ENG_V": ["Absarokee Senior High School", "Absarokee High", "Absarokee Senior High", "Absarokee HS", "Absarokee Senior HS"], "meta:updated": "2020-08-22T02:58:48.365590", "woe:hierarchy": {"continent": 24865672, "country": 23424977, "town": 0, "planet": 1, "county": 12589128, "suburb": 0, "state": 2347585, "region": 0, "localadmin": 0}, "woe:timezone_id": 56043665, "woe:hash": "c844vmqnbpvq", "woe:centroid": [-109.44854, 45.513439], "geom:latitude": 45.513439, "geom:longitude": -109.44854, "geom:hash": "c844vmqnbpvq", "woe:latitude": 45.513439, "geom:centroid": [-109.44854, 45.513439], "woe:longitude": -109.44854, "woe:repo": "woeplanet-poi-us"}, "geometry": {"coordinates": [-109.44854, 45.513439], "type": "Point"}}