{"type": "Feature", "id": 23568294, "properties": {"woe:id": 23568294, "woe:parent_id": 2434562, "woe:name": "Miami Elementary School", "woe:placetype": 20, "woe:placetype_name": "POI", "woe:lang": "ENG", "iso:country": "US", "meta:provider": ["geoplanet:7.3.2", "geoplanet:7.4.0", "geoplanet:7.4.1", "geoplanet:7.5.1", "geoplanet:7.5.2", "geoplanet:7.6.0", "geoplanet:7.8.1", "geoplanet:7.9.0", "geoplanet:7.10.0", "geoplanet:8.0.0", "woeplanet:8.0.0"], "meta:indexed": "2020-08-20T22:02:17.745045", "woe:alias_ENG_V": ["Miami Elementary"], "meta:updated": "2020-08-22T02:57:35.960188", "woe:hierarchy": {"continent": 24865672, "country": 23424977, "town": 0, "planet": 1, "county": 12588258, "suburb": 0, "state": 2347573, "region": 0, "localadmin": 0}, "woe:timezone_id": 56043656, "woe:hash": "dp4jy34f4xvh", "woe:centroid": [-86.908951, 40.391621], "geom:latitude": 40.391621, "geom:longitude": -86.908951, "geom:hash": "dp4jy34f4xvh", "woe:latitude": 40.391621, "geom:centroid": [-86.908951, 40.391621], "woe:longitude": -86.908951, "woe:repo": "woeplanet-poi-us"}, "geometry": {"coordinates": [-86.908951, 40.391621], "type": "Point"}}