{"type": "Feature", "id": 23532344, "properties": {"woe:id": 23532344, "woe:parent_id": 55971910, "woe:name": "West Covina Hills Adventist School", "woe:placetype": 20, "woe:placetype_name": "POI", "woe:lang": "ENG", "iso:country": "US", "meta:provider": ["geoplanet:7.3.1", "geoplanet:7.3.2", "geoplanet:7.4.0", "geoplanet:7.4.1", "geoplanet:7.5.1", "geoplanet:7.5.2", "geoplanet:7.6.0", "geoplanet:7.8.1", "geoplanet:7.9.0", "geoplanet:7.10.0", "geoplanet:8.0.0", "woeplanet:8.0.0"], "meta:indexed": "2020-08-20T20:18:22.212624", "woe:alias_ENG_V": ["W Covina Hills Adventist School"], "meta:updated": "2020-08-22T02:57:29.144491", "woe:hierarchy": {"continent": 24865672, "country": 23424977, "town": 0, "planet": 1, "county": 12587688, "suburb": 0, "state": 2347563, "region": 0, "localadmin": 0}, "woe:timezone_id": 56043663, "woe:hash": "9qh1vf6pbbhh", "woe:centroid": [-117.86953, 34.071308], "geom:latitude": 34.071308, "geom:longitude": -117.86953, "geom:hash": "9qh1vf6pbbhh", "woe:latitude": 34.071308, "geom:centroid": [-117.86953, 34.071308], "woe:longitude": -117.86953, "woe:repo": "woeplanet-poi-us"}, "geometry": {"coordinates": [-117.86953, 34.071308], "type": "Point"}}