{"type": "Feature", "id": 23638479, "properties": {"woe:id": 23638479, "woe:parent_id": 2451634, "woe:name": "Holy Spirit Cath School", "woe:placetype": 20, "woe:placetype_name": "POI", "woe:lang": "ENG", "iso:country": "US", "meta:provider": ["geoplanet:7.3.1", "geoplanet:7.3.2", "geoplanet:7.4.0", "geoplanet:7.4.1", "geoplanet:7.5.1", "geoplanet:7.5.2", "geoplanet:7.6.0", "geoplanet:7.8.1", "geoplanet:7.9.0", "geoplanet:7.10.0", "geoplanet:8.0.0", "woeplanet:8.0.0"], "meta:indexed": "2020-08-20T20:18:57.867482", "meta:updated": "2020-08-22T02:57:46.414988", "woe:hierarchy": {"continent": 24865672, "country": 23424977, "town": 0, "planet": 1, "county": 12589729, "suburb": 0, "state": 2347597, "region": 0, "localadmin": 0}, "woe:timezone_id": 56043648, "woe:hash": "dppnk14rxng6", "woe:centroid": [-79.977074, 40.48045], "geom:latitude": 40.48045, "geom:longitude": -79.977074, "geom:hash": "dppnk14rxng6", "woe:latitude": 40.48045, "geom:centroid": [-79.977074, 40.48045], "woe:longitude": -79.977074, "woe:repo": "woeplanet-poi-us"}, "geometry": {"coordinates": [-79.977074, 40.48045], "type": "Point"}}