{"type": "Feature", "id": 23668910, "properties": {"woe:id": 23668910, "woe:parent_id": 23418260, "woe:name": "Hazelwood Elementary School", "woe:placetype": 20, "woe:placetype_name": "POI", "woe:lang": "ENG", "iso:country": "US", "meta:provider": ["geoplanet:7.3.1", "geoplanet:7.3.2", "geoplanet:7.4.0", "geoplanet:7.4.1", "geoplanet:7.5.1", "geoplanet:7.5.2", "geoplanet:7.6.0", "geoplanet:7.8.1", "geoplanet:7.9.0", "geoplanet:7.10.0", "geoplanet:8.0.0", "woeplanet:8.0.0"], "meta:indexed": "2020-08-20T20:19:09.217768", "woe:alias_ENG_V": ["Hazelwood Elementary"], "meta:updated": "2020-08-22T02:57:51.912789", "woe:hierarchy": {"continent": 24865672, "country": 23424977, "town": 0, "planet": 1, "county": 12590456, "suburb": 0, "state": 2347606, "region": 0, "localadmin": 0}, "woe:timezone_id": 56043663, "woe:hash": "c23j78hk7wf5", "woe:centroid": [-122.183952, 47.329868], "geom:latitude": 47.329868, "geom:longitude": -122.183952, "geom:hash": "c23j78hk7wf5", "woe:latitude": 47.329868, "geom:centroid": [-122.183952, 47.329868], "woe:longitude": -122.183952, "woe:repo": "woeplanet-poi-us"}, "geometry": {"coordinates": [-122.183952, 47.329868], "type": "Point"}}