{"type": "Feature", "id": 23563715, "properties": {"woe:id": 23563715, "woe:parent_id": 2482924, "woe:name": "Rochelle Junior High School", "woe:placetype": 20, "woe:placetype_name": "POI", "woe:lang": "ENG", "iso:country": "US", "meta:provider": ["geoplanet:7.3.1", "geoplanet:7.3.2", "geoplanet:7.4.0", "geoplanet:7.4.1", "geoplanet:7.5.1", "geoplanet:7.5.2", "geoplanet:7.6.0", "geoplanet:7.8.1", "geoplanet:7.9.0", "geoplanet:7.10.0", "geoplanet:8.0.0", "woeplanet:8.0.0"], "meta:indexed": "2020-08-20T20:18:32.934443", "woe:alias_ENG_V": ["Rochelle Junior High"], "meta:updated": "2020-08-22T02:57:35.046171", "woe:hierarchy": {"continent": 24865672, "country": 23424977, "town": 0, "planet": 1, "county": 12588148, "suburb": 0, "state": 2347572, "region": 0, "localadmin": 0}, "woe:timezone_id": 56043661, "woe:hash": "dp2wt3q2fm1v", "woe:centroid": [-89.05748, 41.930851], "geom:latitude": 41.930851, "geom:longitude": -89.05748, "geom:hash": "dp2wt3q2fm1v", "woe:latitude": 41.930851, "geom:centroid": [-89.05748, 41.930851], "woe:longitude": -89.05748, "woe:repo": "woeplanet-poi-us"}, "geometry": {"coordinates": [-89.05748, 41.930851], "type": "Point"}}