{"type": "Feature", "id": 23632669, "geometry": {"type": "Point", "coordinates": [-80.694199, 41.154301]}, "properties": {"woe:id": 23632669, "woe:parent_id": 2410446, "woe:name": "Girard High School", "woe:placetype": 20, "woe:placetype_name": "POI", "woe:lang": "ENG", "iso:country": "US", "meta:provider": ["geoplanet:7.3.1", "geoplanet:7.3.2", "geoplanet:7.4.0", "geoplanet:7.4.1", "geoplanet:7.5.1", "geoplanet:7.5.2", "geoplanet:7.6.0", "geoplanet:7.8.1", "geoplanet:7.9.0", "geoplanet:7.10.0", "geoplanet:8.0.0", "woeplanet:8.0.0"], "meta:indexed": "2020-08-20T20:18:55.700573", "woe:alias_ENG_V": ["Girard Senior High School", "Girard High", "Girard Senior High", "Girard HS", "Girard Senior HS"], "meta:updated": "2020-10-14T11:19:34.828478", "woe:hierarchy": {"continent": 24865672, "country": 23424977, "town": 0, "planet": 1, "county": 12589604, "suburb": 0, "state": 2347594, "region": 0, "localadmin": 0}, "woe:timezone_id": 56043648, "woe:hash": "dpqd5gbm0vsp", "woe:centroid": [-80.694199, 41.154301], "geom:latitude": 41.154301, "geom:longitude": -80.694199, "geom:hash": "dpqd5gbm0vsp", "woe:latitude": 41.154301, "geom:centroid": [-80.694199, 41.154301], "woe:longitude": -80.694199, "woe:repo": "woeplanet-poi-us", "geom:area": 0.0, "woe:scale": 19}}