{"type": "Feature", "id": 23530432, "geometry": {"type": "Point", "coordinates": [-118.043991, 34.09145]}, "properties": {"woe:id": 23530432, "woe:parent_id": 55969509, "woe:name": "Gidley Elementary School", "woe:placetype": 20, "woe:placetype_name": "POI", "woe:lang": "ENG", "iso:country": "US", "meta:provider": ["geoplanet:7.3.2", "geoplanet:7.4.0", "geoplanet:7.4.1", "geoplanet:7.5.1", "geoplanet:7.5.2", "geoplanet:7.6.0", "geoplanet:7.8.1", "geoplanet:7.9.0", "geoplanet:7.10.0", "geoplanet:8.0.0", "woeplanet:8.0.0"], "meta:indexed": "2020-08-20T22:02:01.758086", "woe:alias_ENG_V": ["Gidley Elementary"], "meta:updated": "2020-10-14T11:20:13.854487", "woe:hierarchy": {"continent": 24865672, "country": 23424977, "town": 0, "planet": 1, "county": 12587688, "suburb": 0, "state": 2347563, "region": 0, "localadmin": 0}, "woe:timezone_id": 56043663, "woe:hash": "9qh1cy4vpdus", "woe:centroid": [-118.043991, 34.09145], "geom:latitude": 34.09145, "geom:longitude": -118.043991, "geom:hash": "9qh1cy4vpdus", "woe:latitude": 34.09145, "geom:centroid": [-118.043991, 34.09145], "woe:longitude": -118.043991, "woe:repo": "woeplanet-poi-us", "geom:area": 0.0, "woe:scale": 19}}