{"type": "Feature", "id": 24865800, "geometry": {"type": "Point", "coordinates": [-92.341881, 34.72694]}, "properties": {"woe:id": 24865800, "woe:parent_id": 2440351, "woe:name": "University of Arkansas Little Rock", "woe:placetype": 20, "woe:placetype_name": "POI", "woe:lang": "ENG", "iso:country": "US", "meta:provider": ["geoplanet:7.3.1", "geoplanet:7.3.2", "geoplanet:7.4.0", "geoplanet:7.4.1", "geoplanet:7.5.1", "geoplanet:7.5.2", "geoplanet:7.6.0", "geoplanet:7.8.1", "geoplanet:7.9.0", "geoplanet:7.10.0", "geoplanet:8.0.0", "woeplanet:8.0.0"], "meta:indexed": "2020-08-20T20:19:16.110372", "woe:alias_ENG_V": ["University of Arkansas-Little Rock", "Ualr", "University of Arkansas, Little Rock"], "meta:updated": "2020-10-14T11:19:26.360578", "woe:hierarchy": {"continent": 24865672, "country": 23424977, "town": 0, "planet": 1, "county": 12587654, "suburb": 0, "state": 2347562, "region": 0, "localadmin": 0}, "woe:timezone_id": 56043661, "woe:hash": "9ynmd9yen4yf", "woe:centroid": [-92.341881, 34.72694], "geom:latitude": 34.72694, "geom:longitude": -92.341881, "geom:hash": "9ynmd9yen4yf", "woe:latitude": 34.72694, "geom:centroid": [-92.341881, 34.72694], "woe:longitude": -92.341881, "woe:repo": "woeplanet-poi-us", "geom:area": 0.0, "woe:scale": 19}}