{"type": "Feature", "id": 23596842, "geometry": {"type": "Point", "coordinates": [-94.335831, 38.253391]}, "properties": {"woe:id": 23596842, "woe:parent_id": 2372593, "woe:name": "Butler High School", "woe:placetype": 20, "woe:placetype_name": "POI", "woe:lang": "ENG", "iso:country": "US", "meta:provider": ["geoplanet:7.3.2", "geoplanet:7.4.0", "geoplanet:7.4.1", "geoplanet:7.5.1", "geoplanet:7.5.2", "geoplanet:7.6.0", "geoplanet:7.8.1", "geoplanet:7.9.0", "geoplanet:7.10.0", "geoplanet:8.0.0", "woeplanet:8.0.0"], "meta:indexed": "2020-08-20T22:02:29.671451", "woe:alias_ENG_V": ["Butler Senior High School", "Butler High", "Butler Senior High", "Butler HS", "Butler Senior HS", "Butler R-V High", "Butler R-V High School", "Butler R-V HS", "Butler R-V Senior High", "Butler R-V Senior High School", "Butler R-V Senior HS"], "meta:updated": "2020-10-14T11:20:10.648571", "woe:hierarchy": {"continent": 24865672, "country": 23424977, "town": 0, "planet": 1, "county": 12588972, "suburb": 0, "state": 2347584, "region": 0, "localadmin": 0}, "woe:timezone_id": 56043661, "woe:hash": "9yuct7fdpufj", "woe:centroid": [-94.335831, 38.253391], "geom:latitude": 38.253391, "geom:longitude": -94.335831, "geom:hash": "9yuct7fdpufj", "woe:latitude": 38.253391, "geom:centroid": [-94.335831, 38.253391], "woe:longitude": -94.335831, "woe:repo": "woeplanet-poi-us", "geom:area": 0.0, "woe:scale": 19}}