{"type": "Feature", "id": 23564438, "properties": {"woe:id": 23564438, "woe:parent_id": 2396019, "woe:name": "East Peoria High School", "woe:placetype": 20, "woe:placetype_name": "POI", "woe:lang": "ENG", "iso:country": "US", "meta:provider": ["geoplanet:7.3.1", "geoplanet:7.3.2", "geoplanet:7.4.0", "geoplanet:7.4.1", "geoplanet:7.5.1", "geoplanet:7.5.2", "geoplanet:7.6.0", "geoplanet:7.8.1", "geoplanet:7.9.0", "geoplanet:7.10.0", "geoplanet:8.0.0", "woeplanet:8.0.0"], "meta:indexed": "2020-08-20T20:18:33.208246", "woe:alias_ENG_V": ["East Peoria Senior High School", "East Peoria High", "East Peoria Senior High", "East Peoria HS", "East Peoria Senior HS", "E Peoria High", "E Peoria High School", "E Peoria HS", "E Peoria Senior High", "E Peoria Senior High School", "E Peoria Senior HS"], "meta:updated": "2020-08-22T02:58:47.155038", "woe:hierarchy": {"continent": 24865672, "country": 23424977, "town": 0, "planet": 1, "county": 12588167, "suburb": 0, "state": 2347572, "region": 0, "localadmin": 0}, "woe:timezone_id": 56043661, "woe:hash": "dp0r65979jrt", "woe:centroid": [-89.558777, 40.66927], "geom:latitude": 40.66927, "geom:longitude": -89.558777, "geom:hash": "dp0r65979jrt", "woe:latitude": 40.66927, "geom:centroid": [-89.558777, 40.66927], "woe:longitude": -89.558777, "woe:repo": "woeplanet-poi-us"}, "geometry": {"coordinates": [-89.558777, 40.66927], "type": "Point"}}