{"type": "Feature", "id": 23681359, "geometry": {"type": "Point", "coordinates": [-83.734062, 33.518139]}, "properties": {"woe:id": 23681359, "woe:parent_id": 2444974, "woe:name": "Mansfield Station", "woe:placetype": 20, "woe:placetype_name": "POI", "woe:lang": "ENG", "iso:country": "US", "meta:provider": ["geoplanet:7.3.1", "geoplanet:7.3.2", "geoplanet:7.4.0", "geoplanet:7.4.1", "geoplanet:7.5.1", "geoplanet:7.5.2", "geoplanet:7.6.0", "geoplanet:7.8.1", "geoplanet:7.9.0", "geoplanet:7.10.0", "geoplanet:8.0.0", "woeplanet:8.0.0"], "meta:indexed": "2020-08-20T20:19:19.092453", "meta:updated": "2020-10-14T11:19:47.213923", "woe:hierarchy": {"continent": 24865672, "country": 23424977, "town": 0, "planet": 1, "county": 12587976, "suburb": 0, "state": 2347569, "region": 0, "localadmin": 0}, "woe:timezone_id": 56043648, "woe:hash": "djuqwtf9qcyp", "woe:centroid": [-83.734062, 33.518139], "geom:latitude": 33.518139, "geom:longitude": -83.734062, "geom:hash": "djuqwtf9qcyp", "woe:latitude": 33.518139, "geom:centroid": [-83.734062, 33.518139], "woe:longitude": -83.734062, "woe:repo": "woeplanet-poi-us", "geom:area": 0.0, "woe:scale": 19}}