{"type": "Feature", "id": 23654970, "properties": {"woe:id": 23654970, "woe:parent_id": 2441761, "woe:name": "Spring Hill Intermediate School", "woe:placetype": 20, "woe:placetype_name": "POI", "woe:lang": "ENG", "iso:country": "US", "meta:provider": ["geoplanet:7.3.1", "geoplanet:7.3.2", "geoplanet:7.4.0", "geoplanet:7.4.1", "geoplanet:7.5.1", "geoplanet:7.5.2", "geoplanet:7.6.0", "geoplanet:7.8.1", "geoplanet:7.9.0", "geoplanet:7.10.0", "geoplanet:8.0.0", "woeplanet:8.0.0"], "meta:indexed": "2020-08-20T20:19:03.646351", "meta:updated": "2020-08-22T02:57:49.201092", "woe:hierarchy": {"continent": 24865672, "country": 23424977, "town": 0, "planet": 1, "county": 12590098, "suburb": 0, "state": 2347602, "region": 0, "localadmin": 0}, "woe:timezone_id": 56043661, "woe:hash": "9vu94zd30x0u", "woe:centroid": [-94.797913, 32.56094], "geom:latitude": 32.56094, "geom:longitude": -94.797913, "geom:hash": "9vu94zd30x0u", "woe:latitude": 32.56094, "geom:centroid": [-94.797913, 32.56094], "woe:longitude": -94.797913, "woe:repo": "woeplanet-poi-us"}, "geometry": {"coordinates": [-94.797913, 32.56094], "type": "Point"}}