{"type": "Feature", "id": 23588412, "properties": {"woe:id": 23588412, "woe:parent_id": 2436505, "woe:name": "Lapeer East Senior High School", "woe:placetype": 20, "woe:placetype_name": "POI", "woe:lang": "ENG", "iso:country": "US", "meta:provider": ["geoplanet:7.3.1", "geoplanet:7.3.2", "geoplanet:7.4.0", "geoplanet:7.4.1", "geoplanet:7.5.1", "geoplanet:7.5.2", "geoplanet:7.6.0", "geoplanet:7.8.1", "geoplanet:7.9.0", "geoplanet:7.10.0", "geoplanet:8.0.0", "woeplanet:8.0.0"], "meta:indexed": "2020-08-20T20:18:40.597206", "woe:alias_ENG_V": ["Lapeer East Senior High", "Lapeer East High School", "Lapeer East High", "Lapeer East Senior HS", "Lapeer East HS"], "meta:updated": "2020-08-22T02:58:47.967395", "woe:hierarchy": {"continent": 24865672, "country": 23424977, "town": 0, "planet": 1, "county": 12588757, "suburb": 0, "state": 2347581, "region": 0, "localadmin": 0}, "woe:timezone_id": 56043658, "woe:hash": "dpsub6u173hj", "woe:centroid": [-83.303688, 43.037788], "geom:latitude": 43.037788, "geom:longitude": -83.303688, "geom:hash": "dpsub6u173hj", "woe:latitude": 43.037788, "geom:centroid": [-83.303688, 43.037788], "woe:longitude": -83.303688, "woe:repo": "woeplanet-poi-us"}, "geometry": {"coordinates": [-83.303688, 43.037788], "type": "Point"}}