{"type": "Feature", "id": 23644904, "geometry": {"type": "Point", "coordinates": [-75.866348, 41.83733]}, "properties": {"woe:id": 23644904, "woe:parent_id": 28745553, "woe:name": "Lathrop Street Elementary School", "woe:placetype": 20, "woe:placetype_name": "POI", "woe:lang": "ENG", "iso:country": "US", "meta:provider": ["geoplanet:7.3.1", "geoplanet:7.3.2", "geoplanet:7.4.0", "geoplanet:7.4.1", "geoplanet:7.5.1", "geoplanet:7.5.2", "geoplanet:7.6.0", "geoplanet:7.8.1", "geoplanet:7.9.0", "geoplanet:7.10.0", "geoplanet:8.0.0", "woeplanet:8.0.0"], "meta:indexed": "2020-08-20T20:19:00.024654", "woe:alias_ENG_V": ["Lathrop Street Elementary"], "meta:updated": "2020-10-14T11:19:41.296204", "woe:hierarchy": {"continent": 24865672, "country": 23424977, "town": 0, "planet": 1, "county": 12589785, "suburb": 0, "state": 2347597, "region": 0, "localadmin": 0}, "woe:timezone_id": 56043648, "woe:hash": "dr6n187b1gwf", "woe:centroid": [-75.866348, 41.83733], "geom:latitude": 41.83733, "geom:longitude": -75.866348, "geom:hash": "dr6n187b1gwf", "woe:latitude": 41.83733, "geom:centroid": [-75.866348, 41.83733], "woe:longitude": -75.866348, "woe:repo": "woeplanet-poi-us", "geom:area": 0.0, "woe:scale": 19}}