{"type": "Feature", "id": 23577631, "geometry": {"type": "Point", "coordinates": [-90.689339, 29.574181]}, "properties": {"woe:id": 23577631, "woe:parent_id": 28338864, "woe:name": "Oaklawn Junior High School", "woe:placetype": 20, "woe:placetype_name": "POI", "woe:lang": "ENG", "iso:country": "US", "meta:provider": ["geoplanet:7.3.1", "geoplanet:7.3.2", "geoplanet:7.4.0", "geoplanet:7.4.1", "geoplanet:7.5.1", "geoplanet:7.5.2", "geoplanet:7.6.0", "geoplanet:7.8.1", "geoplanet:7.9.0", "geoplanet:7.10.0", "geoplanet:8.0.0", "woeplanet:8.0.0"], "meta:indexed": "2020-08-20T20:18:37.956492", "woe:alias_ENG_V": ["Oaklawn Jr High School", "Oaklawn Junior High"], "meta:updated": "2020-10-14T11:20:21.960081", "woe:hierarchy": {"continent": 24865672, "country": 23424977, "town": 0, "planet": 1, "county": 12588650, "suburb": 0, "state": 2347577, "region": 0, "localadmin": 0}, "woe:timezone_id": 56043661, "woe:hash": "9vr80rf414zt", "woe:centroid": [-90.689339, 29.574181], "geom:latitude": 29.574181, "geom:longitude": -90.689339, "geom:hash": "9vr80rf414zt", "woe:latitude": 29.574181, "geom:centroid": [-90.689339, 29.574181], "woe:longitude": -90.689339, "woe:repo": "woeplanet-poi-us", "geom:area": 0.0, "woe:scale": 19}}