{"type": "Feature", "id": 56052573, "geometry": {"type": "Point", "coordinates": [-77.438026, 39.048481]}, "properties": {"woe:id": 56052573, "woe:parent_id": 23511479, "woe:name": "Strayer University-Loudon", "woe:placetype": 20, "woe:placetype_name": "POI", "woe:lang": "ENG", "iso:country": "US", "meta:provider": ["geoplanet:7.3.1", "geoplanet:7.3.2", "geoplanet:7.4.0", "geoplanet:7.4.1", "geoplanet:7.5.1", "geoplanet:7.5.2", "geoplanet:7.6.0", "geoplanet:7.8.1", "geoplanet:7.9.0", "geoplanet:7.10.0", "geoplanet:8.0.0", "woeplanet:8.0.0"], "meta:indexed": "2020-08-20T20:19:16.409432", "meta:updated": "2020-10-14T11:19:56.303747", "woe:hierarchy": {"continent": 24865672, "country": 23424977, "town": 0, "planet": 1, "county": 12590376, "suburb": 0, "state": 2347605, "region": 0, "localadmin": 0}, "woe:timezone_id": 56043648, "woe:hash": "dqbyjue3ghqw", "woe:centroid": [-77.438026, 39.048481], "geom:latitude": 39.048481, "geom:longitude": -77.438026, "geom:hash": "dqbyjue3ghqw", "woe:latitude": 39.048481, "geom:centroid": [-77.438026, 39.048481], "woe:longitude": -77.438026, "woe:repo": "woeplanet-poi-us", "geom:area": 0.0, "woe:scale": 19}}