{"type": "Feature", "id": 23668948, "properties": {"woe:id": 23668948, "woe:parent_id": 55996233, "woe:name": "Illahee Junior High School", "woe:placetype": 20, "woe:placetype_name": "POI", "woe:lang": "ENG", "iso:country": "US", "meta:provider": ["geoplanet:7.3.1", "geoplanet:7.3.2", "geoplanet:7.4.0", "geoplanet:7.4.1", "geoplanet:7.5.1", "geoplanet:7.5.2", "geoplanet:7.6.0", "geoplanet:7.8.1", "geoplanet:7.9.0", "geoplanet:7.10.0", "geoplanet:8.0.0", "woeplanet:8.0.0"], "meta:indexed": "2020-08-20T20:19:09.236875", "woe:alias_ENG_V": ["Illahee Middle School", "Illahee Junior High"], "meta:updated": "2020-08-22T02:57:51.922339", "woe:hierarchy": {"continent": 24865672, "country": 23424977, "town": 0, "planet": 1, "county": 12590456, "suburb": 0, "state": 2347606, "region": 0, "localadmin": 0}, "woe:timezone_id": 56043663, "woe:hash": "c23hbnw7gzjp", "woe:centroid": [-122.334999, 47.277599], "geom:latitude": 47.277599, "geom:longitude": -122.334999, "geom:hash": "c23hbnw7gzjp", "woe:latitude": 47.277599, "geom:centroid": [-122.334999, 47.277599], "woe:longitude": -122.334999, "woe:repo": "woeplanet-poi-us"}, "geometry": {"coordinates": [-122.334999, 47.277599], "type": "Point"}}