{"type": "Feature", "id": 23603327, "properties": {"woe:id": 23603327, "woe:parent_id": 2360839, "woe:name": "Beatrice High School", "woe:placetype": 20, "woe:placetype_name": "POI", "woe:lang": "ENG", "iso:country": "US", "meta:provider": ["geoplanet:7.3.1", "geoplanet:7.3.2", "geoplanet:7.4.0", "geoplanet:7.4.1", "geoplanet:7.5.1", "geoplanet:7.5.2", "geoplanet:7.6.0", "geoplanet:7.8.1", "geoplanet:7.9.0", "geoplanet:7.10.0", "geoplanet:8.0.0", "woeplanet:8.0.0"], "meta:indexed": "2020-08-20T20:18:45.710410", "woe:alias_ENG_V": ["Beatrice Senior High School", "Beatrice High", "Beatrice Senior High", "Beatrice HS", "Beatrice Senior HS"], "meta:updated": "2020-08-22T02:58:48.399420", "woe:hierarchy": {"continent": 24865672, "country": 23424977, "town": 0, "planet": 1, "county": 12589171, "suburb": 0, "state": 2347586, "region": 0, "localadmin": 0}, "woe:timezone_id": 56043661, "woe:hash": "9z5jp38fykkw", "woe:centroid": [-96.711342, 40.262642], "geom:latitude": 40.262642, "geom:longitude": -96.711342, "geom:hash": "9z5jp38fykkw", "woe:latitude": 40.262642, "geom:centroid": [-96.711342, 40.262642], "woe:longitude": -96.711342, "woe:repo": "woeplanet-poi-us"}, "geometry": {"coordinates": [-96.711342, 40.262642], "type": "Point"}}