{"type": "Feature", "id": 23569188, "geometry": {"type": "Point", "coordinates": [-93.882568, 41.61034]}, "properties": {"woe:id": 23569188, "woe:parent_id": 2515432, "woe:name": "Waukee Elementary School", "woe:placetype": 20, "woe:placetype_name": "POI", "woe:lang": "ENG", "iso:country": "US", "meta:provider": ["geoplanet:7.3.1", "geoplanet:7.3.2", "geoplanet:7.4.0", "geoplanet:7.4.1", "geoplanet:7.5.1", "geoplanet:7.5.2", "geoplanet:7.6.0", "geoplanet:7.8.1", "geoplanet:7.9.0", "geoplanet:7.10.0", "geoplanet:8.0.0", "woeplanet:8.0.0"], "meta:indexed": "2020-08-20T20:18:35.076846", "woe:alias_ENG_V": ["Waukee Elementary"], "meta:updated": "2020-10-14T11:20:26.564653", "woe:hierarchy": {"continent": 24865672, "country": 23424977, "town": 0, "planet": 1, "county": 12588296, "suburb": 0, "state": 2347574, "region": 0, "localadmin": 0}, "woe:timezone_id": 56043661, "woe:hash": "9zmhxwuvc9e6", "woe:centroid": [-93.882568, 41.61034], "geom:latitude": 41.61034, "geom:longitude": -93.882568, "geom:hash": "9zmhxwuvc9e6", "woe:latitude": 41.61034, "geom:centroid": [-93.882568, 41.61034], "woe:longitude": -93.882568, "woe:repo": "woeplanet-poi-us", "geom:area": 0.0, "woe:scale": 19}}