{"type": "Feature", "id": 23660410, "geometry": {"type": "Point", "coordinates": [-99.240707, 28.43388]}, "properties": {"woe:id": 23660410, "woe:parent_id": 2385690, "woe:name": "Ramirez Elementary School", "woe:placetype": 20, "woe:placetype_name": "POI", "woe:lang": "ENG", "iso:country": "US", "meta:provider": ["geoplanet:7.3.1", "geoplanet:7.3.2", "geoplanet:7.4.0", "geoplanet:7.4.1", "geoplanet:7.5.1", "geoplanet:7.5.2", "geoplanet:7.6.0", "geoplanet:7.8.1", "geoplanet:7.9.0", "geoplanet:7.10.0", "geoplanet:8.0.0", "woeplanet:8.0.0"], "meta:indexed": "2020-08-20T20:19:06.427468", "woe:alias_ENG_V": ["Ramirez Elementary"], "meta:updated": "2020-10-14T11:19:53.391816", "woe:hierarchy": {"continent": 24865672, "country": 23424977, "town": 0, "planet": 1, "county": 12590145, "suburb": 0, "state": 2347602, "region": 0, "localadmin": 0}, "woe:timezone_id": 56043661, "woe:hash": "9v13v8pp7gmk", "woe:centroid": [-99.240707, 28.43388], "geom:latitude": 28.43388, "geom:longitude": -99.240707, "geom:hash": "9v13v8pp7gmk", "woe:latitude": 28.43388, "geom:centroid": [-99.240707, 28.43388], "woe:longitude": -99.240707, "woe:repo": "woeplanet-poi-us", "geom:area": 0.0, "woe:scale": 19}}