{"type": "Feature", "id": 23518861, "geometry": {"type": "Point", "coordinates": [-94.2127, 34.644859]}, "properties": {"woe:id": 23518861, "woe:parent_id": 2351782, "woe:name": "Acorn High School", "woe:placetype": 20, "woe:placetype_name": "POI", "woe:lang": "ENG", "iso:country": "US", "meta:provider": ["geoplanet:7.3.1", "geoplanet:7.3.2", "geoplanet:7.4.0", "geoplanet:7.4.1", "geoplanet:7.5.1", "geoplanet:7.5.2", "geoplanet:7.6.0", "geoplanet:7.8.1", "geoplanet:7.9.0", "geoplanet:7.10.0", "geoplanet:8.0.0", "woeplanet:8.0.0"], "meta:indexed": "2020-08-20T20:18:19.196317", "woe:alias_ENG_V": ["Acorn Senior High School", "Acorn High", "Acorn Senior High", "Acorn HS", "Acorn Senior HS"], "meta:updated": "2020-10-14T11:20:10.499511", "woe:hierarchy": {"continent": 24865672, "country": 23424977, "town": 0, "planet": 1, "county": 12587651, "suburb": 0, "state": 2347562, "region": 0, "localadmin": 0}, "woe:timezone_id": 56043661, "woe:hash": "9yjj04ukuvz1", "woe:centroid": [-94.2127, 34.644859], "geom:latitude": 34.644859, "geom:longitude": -94.2127, "geom:hash": "9yjj04ukuvz1", "woe:latitude": 34.644859, "geom:centroid": [-94.2127, 34.644859], "woe:longitude": -94.2127, "woe:repo": "woeplanet-poi-us", "geom:area": 0.0, "woe:scale": 19}}