{"type": "Feature", "id": 23628208, "geometry": {"type": "Point", "coordinates": [-81.845718, 41.483601]}, "properties": {"woe:id": 23628208, "woe:parent_id": 56022498, "woe:name": "Kensington Intermediate Elementary School", "woe:placetype": 20, "woe:placetype_name": "POI", "woe:lang": "ENG", "iso:country": "US", "meta:provider": ["geoplanet:7.3.1", "geoplanet:7.3.2", "geoplanet:7.4.0", "geoplanet:7.4.1", "geoplanet:7.5.1", "geoplanet:7.5.2", "geoplanet:7.6.0", "geoplanet:7.8.1", "geoplanet:7.9.0", "geoplanet:7.10.0", "geoplanet:8.0.0", "woeplanet:8.0.0"], "meta:indexed": "2020-08-20T20:18:53.661736", "woe:alias_ENG_V": ["Kensington Intermediate Elementary"], "meta:updated": "2020-10-14T11:19:38.777517", "woe:hierarchy": {"continent": 24865672, "country": 23424977, "town": 0, "planet": 1, "county": 12589544, "suburb": 0, "state": 2347594, "region": 0, "localadmin": 0}, "woe:timezone_id": 56043648, "woe:hash": "dpmgcxcg2x9q", "woe:centroid": [-81.845718, 41.483601], "geom:latitude": 41.483601, "geom:longitude": -81.845718, "geom:hash": "dpmgcxcg2x9q", "woe:latitude": 41.483601, "geom:centroid": [-81.845718, 41.483601], "woe:longitude": -81.845718, "woe:repo": "woeplanet-poi-us", "geom:area": 0.0, "woe:scale": 19}}