{"type": "Feature", "id": 23658706, "properties": {"woe:id": 23658706, "woe:parent_id": 28751418, "woe:name": "Anderson Academy", "woe:placetype": 20, "woe:placetype_name": "POI", "woe:lang": "ENG", "iso:country": "US", "meta:provider": ["geoplanet:7.3.1", "geoplanet:7.3.2", "geoplanet:7.4.0", "geoplanet:7.4.1", "geoplanet:7.5.1", "geoplanet:7.5.2", "geoplanet:7.6.0", "geoplanet:7.8.1", "geoplanet:7.9.0", "geoplanet:7.10.0", "geoplanet:8.0.0", "woeplanet:8.0.0"], "meta:indexed": "2020-08-20T20:19:05.541343", "meta:updated": "2020-08-22T02:57:50.113887", "woe:hierarchy": {"continent": 24865672, "country": 23424977, "town": 0, "planet": 1, "county": 12590107, "suburb": 0, "state": 2347602, "region": 0, "localadmin": 0}, "woe:timezone_id": 56043661, "woe:hash": "9vk1umnkb4m7", "woe:centroid": [-95.429642, 29.867161], "geom:latitude": 29.867161, "geom:longitude": -95.429642, "geom:hash": "9vk1umnkb4m7", "woe:latitude": 29.867161, "geom:centroid": [-95.429642, 29.867161], "woe:longitude": -95.429642, "woe:repo": "woeplanet-poi-us"}, "geometry": {"coordinates": [-95.429642, 29.867161], "type": "Point"}}