{"type": "Feature", "id": 23644093, "geometry": {"type": "Point", "coordinates": [-75.22068, 40.024899]}, "properties": {"woe:id": 23644093, "woe:parent_id": 2444635, "woe:name": "St John the Baptist School", "woe:placetype": 20, "woe:placetype_name": "POI", "woe:lang": "ENG", "iso:country": "US", "meta:provider": ["geoplanet:7.4.0", "geoplanet:7.4.1", "geoplanet:7.5.1", "geoplanet:7.5.2", "geoplanet:7.6.0", "geoplanet:7.8.1", "geoplanet:7.9.0", "geoplanet:7.10.0", "geoplanet:8.0.0", "woeplanet:8.0.0"], "meta:indexed": "2020-08-20T23:55:34.377459", "meta:updated": "2020-10-14T11:19:38.168588", "woe:hierarchy": {"continent": 24865672, "country": 23424977, "town": 0, "planet": 1, "county": 12589778, "suburb": 0, "state": 2347597, "region": 0, "localadmin": 0}, "woe:timezone_id": 56043648, "woe:hash": "dr4e8q3czjgw", "woe:centroid": [-75.22068, 40.024899], "geom:latitude": 40.024899, "geom:longitude": -75.22068, "geom:hash": "dr4e8q3czjgw", "woe:latitude": 40.024899, "geom:centroid": [-75.22068, 40.024899], "woe:longitude": -75.22068, "woe:repo": "woeplanet-poi-us", "geom:area": 0.0, "woe:scale": 19}}