{"type": "Feature", "id": 23590710, "properties": {"woe:id": 23590710, "woe:parent_id": 2496321, "woe:name": "Maple Grove Elementary School", "woe:placetype": 20, "woe:placetype_name": "POI", "woe:lang": "ENG", "iso:country": "US", "meta:provider": ["geoplanet:7.3.1", "geoplanet:7.3.2", "geoplanet:7.4.0", "geoplanet:7.4.1", "geoplanet:7.5.1", "geoplanet:7.5.2", "geoplanet:7.6.0", "geoplanet:7.8.1", "geoplanet:7.9.0", "geoplanet:7.10.0", "geoplanet:8.0.0", "woeplanet:8.0.0"], "meta:indexed": "2020-08-20T20:18:41.443573", "woe:alias_ENG_V": ["Maple Grove Elementary"], "meta:updated": "2020-08-22T02:57:39.518026", "woe:hierarchy": {"continent": 24865672, "country": 23424977, "town": 0, "planet": 1, "county": 12588793, "suburb": 0, "state": 2347581, "region": 0, "localadmin": 0}, "woe:timezone_id": 56043658, "woe:hash": "dpd9j6n7mkfb", "woe:centroid": [-86.24485, 42.374851], "geom:latitude": 42.374851, "geom:longitude": -86.24485, "geom:hash": "dpd9j6n7mkfb", "woe:latitude": 42.374851, "geom:centroid": [-86.24485, 42.374851], "woe:longitude": -86.24485, "woe:repo": "woeplanet-poi-us"}, "geometry": {"coordinates": [-86.24485, 42.374851], "type": "Point"}}