{"type": "Feature", "id": 23568325, "properties": {"woe:id": 23568325, "woe:parent_id": 2434562, "woe:name": "Apostolic Christian Acadmemy", "woe:placetype": 20, "woe:placetype_name": "POI", "woe:lang": "ENG", "iso:country": "US", "meta:provider": ["geoplanet:7.4.0", "geoplanet:7.4.1", "geoplanet:7.5.1", "geoplanet:7.5.2", "geoplanet:7.6.0", "geoplanet:7.8.1", "geoplanet:7.9.0", "geoplanet:7.10.0", "geoplanet:8.0.0", "woeplanet:8.0.0"], "meta:indexed": "2020-08-20T23:55:01.466972", "meta:updated": "2020-08-22T02:57:35.967977", "woe:hierarchy": {"continent": 24865672, "country": 23424977, "town": 0, "planet": 1, "county": 12588258, "suburb": 0, "state": 2347573, "region": 0, "localadmin": 0}, "woe:timezone_id": 56043656, "woe:hash": "dp4jyehp30x8", "woe:centroid": [-86.896309, 40.403469], "geom:latitude": 40.403469, "geom:longitude": -86.896309, "geom:hash": "dp4jyehp30x8", "woe:latitude": 40.403469, "geom:centroid": [-86.896309, 40.403469], "woe:longitude": -86.896309, "woe:repo": "woeplanet-poi-us"}, "geometry": {"coordinates": [-86.896309, 40.403469], "type": "Point"}}