{"type": "Feature", "id": 23567133, "geometry": {"type": "Point", "coordinates": [-86.282219, 39.652748]}, "properties": {"woe:id": 23567133, "woe:parent_id": 55986610, "woe:name": "West Newton Elementary School", "woe:placetype": 20, "woe:placetype_name": "POI", "woe:lang": "ENG", "iso:country": "US", "meta:provider": ["geoplanet:7.3.1", "geoplanet:7.3.2", "geoplanet:7.4.0", "geoplanet:7.4.1", "geoplanet:7.5.1", "geoplanet:7.5.2", "geoplanet:7.6.0", "geoplanet:7.8.1", "geoplanet:7.9.0", "geoplanet:7.10.0", "geoplanet:8.0.0", "woeplanet:8.0.0"], "meta:indexed": "2020-08-20T20:18:34.303050", "woe:alias_ENG_V": ["W Newton Elementary School", "W Newton Elementary", "West Newton Elementary"], "meta:updated": "2020-10-14T11:20:13.928590", "woe:hierarchy": {"continent": 24865672, "country": 23424977, "town": 0, "planet": 1, "county": 12588228, "suburb": 0, "state": 2347573, "region": 0, "localadmin": 0}, "woe:timezone_id": 56043656, "woe:hash": "dp49sde1yxfr", "woe:centroid": [-86.282219, 39.652748], "geom:latitude": 39.652748, "geom:longitude": -86.282219, "geom:hash": "dp49sde1yxfr", "woe:latitude": 39.652748, "geom:centroid": [-86.282219, 39.652748], "woe:longitude": -86.282219, "woe:repo": "woeplanet-poi-us", "geom:area": 0.0, "woe:scale": 19}}