{"type": "Feature", "id": 23614741, "geometry": {"type": "Point", "coordinates": [-73.817108, 42.262859]}, "properties": {"woe:id": 23614741, "woe:parent_id": 2356939, "woe:name": "Edward J. Arthur Elementary School", "woe:placetype": 20, "woe:placetype_name": "POI", "woe:lang": "ENG", "iso:country": "US", "meta:provider": ["geoplanet:7.3.1", "geoplanet:7.3.2", "geoplanet:7.4.0", "geoplanet:7.4.1", "geoplanet:7.5.1", "geoplanet:7.5.2", "geoplanet:7.6.0", "geoplanet:7.8.1", "geoplanet:7.9.0", "geoplanet:7.10.0", "geoplanet:8.0.0", "woeplanet:8.0.0"], "meta:indexed": "2020-08-20T20:18:49.251052", "woe:alias_ENG_V": ["Edward J. Arthur Elementary"], "meta:updated": "2020-10-14T11:19:29.278874", "woe:hierarchy": {"continent": 24865672, "country": 23424977, "town": 0, "planet": 1, "county": 12589331, "suburb": 0, "state": 2347591, "region": 0, "localadmin": 0}, "woe:timezone_id": 56043648, "woe:hash": "dre82m8nbxyv", "woe:centroid": [-73.817108, 42.262859], "geom:latitude": 42.262859, "geom:longitude": -73.817108, "geom:hash": "dre82m8nbxyv", "woe:latitude": 42.262859, "geom:centroid": [-73.817108, 42.262859], "woe:longitude": -73.817108, "woe:repo": "woeplanet-poi-us", "geom:area": 0.0, "woe:scale": 19}}