{"type": "Feature", "id": 23516435, "geometry": {"type": "Point", "coordinates": [-111.943153, 33.524719]}, "properties": {"woe:id": 23516435, "woe:parent_id": 29230214, "woe:name": "Camelback Desert School", "woe:placetype": 20, "woe:placetype_name": "POI", "woe:lang": "ENG", "iso:country": "US", "meta:provider": ["geoplanet:7.3.1", "geoplanet:7.3.2", "geoplanet:7.4.0", "geoplanet:7.4.1", "geoplanet:7.5.1", "geoplanet:7.5.2", "geoplanet:7.6.0", "geoplanet:7.8.1", "geoplanet:7.9.0", "geoplanet:7.10.0", "geoplanet:8.0.0", "woeplanet:8.0.0"], "meta:indexed": "2020-08-20T20:18:18.440864", "meta:updated": "2020-10-14T11:20:29.358485", "woe:hierarchy": {"continent": 24865672, "country": 23424977, "town": 0, "planet": 1, "county": 12587587, "suburb": 0, "state": 2347561, "region": 0, "localadmin": 0}, "woe:timezone_id": 56043666, "woe:hash": "9tbqswvrxkx4", "woe:centroid": [-111.943153, 33.524719], "geom:latitude": 33.524719, "geom:longitude": -111.943153, "geom:hash": "9tbqswvrxkx4", "woe:latitude": 33.524719, "geom:centroid": [-111.943153, 33.524719], "woe:longitude": -111.943153, "woe:repo": "woeplanet-poi-us", "geom:area": 0.0, "woe:scale": 19}}