{"type": "Feature", "id": 23550179, "geometry": {"type": "Point", "coordinates": [-80.061363, 26.67668]}, "properties": {"woe:id": 23550179, "woe:parent_id": 55862442, "woe:name": "Conniston Middle School", "woe:placetype": 20, "woe:placetype_name": "POI", "woe:lang": "ENG", "iso:country": "US", "meta:provider": ["geoplanet:7.3.1", "geoplanet:7.3.2", "geoplanet:7.4.0", "geoplanet:7.4.1", "geoplanet:7.5.1", "geoplanet:7.5.2", "geoplanet:7.6.0", "geoplanet:7.8.1", "geoplanet:7.9.0", "geoplanet:7.10.0", "geoplanet:8.0.0", "woeplanet:8.0.0"], "meta:indexed": "2020-08-20T20:18:28.232925", "meta:updated": "2020-10-14T11:20:15.585174", "woe:hierarchy": {"continent": 24865672, "country": 23424977, "town": 0, "planet": 1, "county": 12587852, "suburb": 0, "state": 2347568, "region": 0, "localadmin": 0}, "woe:timezone_id": 56043648, "woe:hash": "dhxpf0m4gj8f", "woe:centroid": [-80.061363, 26.67668], "geom:latitude": 26.67668, "geom:longitude": -80.061363, "geom:hash": "dhxpf0m4gj8f", "woe:latitude": 26.67668, "geom:centroid": [-80.061363, 26.67668], "woe:longitude": -80.061363, "woe:repo": "woeplanet-poi-us", "geom:area": 0.0, "woe:scale": 19}}