{"type": "Feature", "id": 23619970, "properties": {"woe:id": 23619970, "woe:parent_id": 26342953, "woe:name": "New City Elementary School", "woe:placetype": 20, "woe:placetype_name": "POI", "woe:lang": "ENG", "iso:country": "US", "meta:provider": ["geoplanet:7.3.1", "geoplanet:7.3.2", "geoplanet:7.4.0", "geoplanet:7.4.1", "geoplanet:7.5.1", "geoplanet:7.5.2", "geoplanet:7.6.0", "geoplanet:7.8.1", "geoplanet:7.9.0", "geoplanet:7.10.0", "geoplanet:8.0.0", "woeplanet:8.0.0"], "meta:indexed": "2020-08-20T20:18:51.442868", "woe:alias_ENG_V": ["New City Elementary"], "meta:updated": "2020-08-22T02:57:43.681674", "woe:hierarchy": {"continent": 24865672, "country": 23424977, "town": 0, "planet": 1, "county": 12589355, "suburb": 0, "state": 2347591, "region": 0, "localadmin": 0}, "woe:timezone_id": 56043648, "woe:hash": "dr76h7nws62y", "woe:centroid": [-73.98381, 41.150421], "geom:latitude": 41.150421, "geom:longitude": -73.98381, "geom:hash": "dr76h7nws62y", "woe:latitude": 41.150421, "geom:centroid": [-73.98381, 41.150421], "woe:longitude": -73.98381, "woe:repo": "woeplanet-poi-us"}, "geometry": {"coordinates": [-73.98381, 41.150421], "type": "Point"}}