{"type": "Feature", "id": 23655822, "geometry": {"type": "Point", "coordinates": [-94.714546, 33.035172]}, "properties": {"woe:id": 23655822, "woe:parent_id": 2388784, "woe:name": "Daingerfield Junior High School", "woe:placetype": 20, "woe:placetype_name": "POI", "woe:lang": "ENG", "iso:country": "US", "meta:provider": ["geoplanet:7.3.1", "geoplanet:7.3.2", "geoplanet:7.4.0", "geoplanet:7.4.1", "geoplanet:7.5.1", "geoplanet:7.5.2", "geoplanet:7.6.0", "geoplanet:7.8.1", "geoplanet:7.9.0", "geoplanet:7.10.0", "geoplanet:8.0.0", "woeplanet:8.0.0"], "meta:indexed": "2020-08-20T20:19:04.052484", "woe:alias_ENG_V": ["Daingerfield Junior High"], "meta:updated": "2020-10-14T11:19:27.819611", "woe:hierarchy": {"continent": 24865672, "country": 23424977, "town": 0, "planet": 1, "county": 12590178, "suburb": 0, "state": 2347602, "region": 0, "localadmin": 0}, "woe:timezone_id": 56043661, "woe:hash": "9vueutygz47s", "woe:centroid": [-94.714546, 33.035172], "geom:latitude": 33.035172, "geom:longitude": -94.714546, "geom:hash": "9vueutygz47s", "woe:latitude": 33.035172, "geom:centroid": [-94.714546, 33.035172], "woe:longitude": -94.714546, "woe:repo": "woeplanet-poi-us", "geom:area": 0.0, "woe:scale": 19}}