{"type": "Feature", "id": 23619607, "geometry": {"type": "Point", "coordinates": [-73.888031, 40.749371]}, "properties": {"woe:id": 23619607, "woe:parent_id": 2428245, "woe:name": "Jackson Heights Station", "woe:placetype": 20, "woe:placetype_name": "POI", "woe:lang": "ENG", "iso:country": "US", "meta:provider": ["geoplanet:7.3.1", "geoplanet:7.3.2", "geoplanet:7.4.0", "geoplanet:7.4.1", "geoplanet:7.5.1", "geoplanet:7.5.2", "geoplanet:7.6.0", "geoplanet:7.8.1", "geoplanet:7.9.0", "geoplanet:7.10.0", "geoplanet:8.0.0", "woeplanet:8.0.0"], "meta:indexed": "2020-08-20T20:18:51.289511", "meta:updated": "2020-10-14T11:19:39.479812", "woe:hierarchy": {"continent": 24865672, "country": 23424977, "town": 0, "planet": 1, "county": 12589352, "suburb": 0, "state": 2347591, "region": 0, "localadmin": 0}, "woe:timezone_id": 56043648, "woe:hash": "dr5rydhqk16f", "woe:centroid": [-73.888031, 40.749371], "geom:latitude": 40.749371, "geom:longitude": -73.888031, "geom:hash": "dr5rydhqk16f", "woe:latitude": 40.749371, "geom:centroid": [-73.888031, 40.749371], "woe:longitude": -73.888031, "woe:repo": "woeplanet-poi-us", "geom:area": 0.0, "woe:scale": 19}}