{"type": "Feature", "id": 56053173, "geometry": {"type": "Point", "coordinates": [-70.974426, 43.290241]}, "properties": {"woe:id": 56053173, "woe:parent_id": 55991564, "woe:name": "Granite State College-Rochester", "woe:placetype": 20, "woe:placetype_name": "POI", "woe:lang": "ENG", "iso:country": "US", "meta:provider": ["geoplanet:7.3.1", "geoplanet:7.3.2", "geoplanet:7.4.0", "geoplanet:7.4.1", "geoplanet:7.5.1", "geoplanet:7.5.2", "geoplanet:7.6.0", "geoplanet:7.8.1", "geoplanet:7.9.0", "geoplanet:7.10.0", "geoplanet:8.0.0", "woeplanet:8.0.0"], "meta:indexed": "2020-08-20T20:19:16.830471", "meta:updated": "2020-10-14T11:19:56.157495", "woe:hierarchy": {"continent": 24865672, "country": 23424977, "town": 0, "planet": 1, "county": 12589256, "suburb": 0, "state": 2347588, "region": 0, "localadmin": 0}, "woe:timezone_id": 56043648, "woe:hash": "drtw2bwpbjb4", "woe:centroid": [-70.974426, 43.290241], "geom:latitude": 43.290241, "geom:longitude": -70.974426, "geom:hash": "drtw2bwpbjb4", "woe:latitude": 43.290241, "geom:centroid": [-70.974426, 43.290241], "woe:longitude": -70.974426, "woe:repo": "woeplanet-poi-us", "geom:area": 0.0, "woe:scale": 19}}