{"type": "Feature", "id": 23568288, "geometry": {"type": "Point", "coordinates": [-86.885567, 40.378201]}, "properties": {"woe:id": 23568288, "woe:parent_id": 2434562, "woe:name": "Amelia Earhart Elementary School", "woe:placetype": 20, "woe:placetype_name": "POI", "woe:lang": "ENG", "iso:country": "US", "meta:provider": ["geoplanet:7.3.1", "geoplanet:7.3.2", "geoplanet:7.4.0", "geoplanet:7.4.1", "geoplanet:7.5.1", "geoplanet:7.5.2", "geoplanet:7.6.0", "geoplanet:7.8.1", "geoplanet:7.9.0", "geoplanet:7.10.0", "geoplanet:8.0.0", "woeplanet:8.0.0"], "meta:indexed": "2020-08-20T20:18:34.732807", "woe:alias_ENG_V": ["Amelia Earhart Elementary"], "meta:updated": "2020-10-14T11:20:10.867209", "woe:hierarchy": {"continent": 24865672, "country": 23424977, "town": 0, "planet": 1, "county": 12588258, "suburb": 0, "state": 2347573, "region": 0, "localadmin": 0}, "woe:timezone_id": 56043656, "woe:hash": "dp4jwyeu5d1x", "woe:centroid": [-86.885567, 40.378201], "geom:latitude": 40.378201, "geom:longitude": -86.885567, "geom:hash": "dp4jwyeu5d1x", "woe:latitude": 40.378201, "geom:centroid": [-86.885567, 40.378201], "woe:longitude": -86.885567, "woe:repo": "woeplanet-poi-us", "geom:area": 0.0, "woe:scale": 19}}