{"type": "Feature", "id": 23572867, "geometry": {"type": "Point", "coordinates": [-95.747902, 39.037369]}, "properties": {"woe:id": 23572867, "woe:parent_id": 55862284, "woe:name": "Mccarter Elementary School", "woe:placetype": 20, "woe:placetype_name": "POI", "woe:lang": "ENG", "iso:country": "US", "meta:provider": ["geoplanet:7.3.1", "geoplanet:7.3.2", "geoplanet:7.4.0", "geoplanet:7.4.1", "geoplanet:7.5.1", "geoplanet:7.5.2", "geoplanet:7.6.0", "geoplanet:7.8.1", "geoplanet:7.9.0", "geoplanet:7.10.0", "geoplanet:8.0.0", "woeplanet:8.0.0"], "meta:indexed": "2020-08-20T20:18:36.457835", "woe:alias_ENG_V": ["Mccarter Elementary"], "meta:updated": "2020-10-14T11:20:29.122084", "woe:hierarchy": {"continent": 24865672, "country": 23424977, "town": 0, "planet": 1, "county": 12588459, "suburb": 0, "state": 2347575, "region": 0, "localadmin": 0}, "woe:timezone_id": 56043661, "woe:hash": "9ygyj4w90jj8", "woe:centroid": [-95.747902, 39.037369], "geom:latitude": 39.037369, "geom:longitude": -95.747902, "geom:hash": "9ygyj4w90jj8", "woe:latitude": 39.037369, "geom:centroid": [-95.747902, 39.037369], "woe:longitude": -95.747902, "woe:repo": "woeplanet-poi-us", "geom:area": 0.0, "woe:scale": 19}}