{"type": "Feature", "id": 23570727, "geometry": {"type": "Point", "coordinates": [-94.368217, 41.070999]}, "properties": {"woe:id": 23570727, "woe:parent_id": 2387127, "woe:name": "Creston High School", "woe:placetype": 20, "woe:placetype_name": "POI", "woe:lang": "ENG", "iso:country": "US", "meta:provider": ["geoplanet:7.3.1", "geoplanet:7.3.2", "geoplanet:7.4.0", "geoplanet:7.4.1", "geoplanet:7.5.1", "geoplanet:7.5.2", "geoplanet:7.6.0", "geoplanet:7.8.1", "geoplanet:7.9.0", "geoplanet:7.10.0", "geoplanet:8.0.0", "woeplanet:8.0.0"], "meta:indexed": "2020-08-20T20:18:35.657802", "woe:alias_ENG_V": ["Creston Senior High School", "Creston High", "Creston Senior High", "Creston HS", "Creston Senior HS"], "meta:updated": "2020-10-14T11:20:21.469040", "woe:hierarchy": {"continent": 24865672, "country": 23424977, "town": 0, "planet": 1, "county": 12588359, "suburb": 0, "state": 2347574, "region": 0, "localadmin": 0}, "woe:timezone_id": 56043661, "woe:hash": "9zkcssepvjjk", "woe:centroid": [-94.368217, 41.070999], "geom:latitude": 41.070999, "geom:longitude": -94.368217, "geom:hash": "9zkcssepvjjk", "woe:latitude": 41.070999, "geom:centroid": [-94.368217, 41.070999], "woe:longitude": -94.368217, "woe:repo": "woeplanet-poi-us", "geom:area": 0.0, "woe:scale": 19}}