{"type": "Feature", "id": 23638851, "properties": {"woe:id": 23638851, "woe:parent_id": 2482953, "woe:name": "Rochester Area High School", "woe:placetype": 20, "woe:placetype_name": "POI", "woe:lang": "ENG", "iso:country": "US", "meta:provider": ["geoplanet:7.3.1", "geoplanet:7.3.2", "geoplanet:7.4.0", "geoplanet:7.4.1", "geoplanet:7.5.1", "geoplanet:7.5.2", "geoplanet:7.6.0", "geoplanet:7.8.1", "geoplanet:7.9.0", "geoplanet:7.10.0", "geoplanet:8.0.0", "woeplanet:8.0.0"], "meta:indexed": "2020-08-20T20:18:57.986757", "woe:alias_ENG_V": ["Rochester Area Senior High School", "Rochester Area High", "Rochester Area Senior High", "Rochester Area HS", "Rochester Area Senior HS"], "meta:updated": "2020-08-22T02:58:49.437090", "woe:hierarchy": {"continent": 24865672, "country": 23424977, "town": 0, "planet": 1, "county": 12589731, "suburb": 0, "state": 2347597, "region": 0, "localadmin": 0}, "woe:timezone_id": 56043648, "woe:hash": "dpnzt4x284ms", "woe:centroid": [-80.278122, 40.707191], "geom:latitude": 40.707191, "geom:longitude": -80.278122, "geom:hash": "dpnzt4x284ms", "woe:latitude": 40.707191, "geom:centroid": [-80.278122, 40.707191], "woe:longitude": -80.278122, "woe:repo": "woeplanet-poi-us"}, "geometry": {"coordinates": [-80.278122, 40.707191], "type": "Point"}}