{"type": "Feature", "id": 23534003, "properties": {"woe:id": 23534003, "woe:parent_id": 55969301, "woe:name": "A. E. Arnold Elementary School", "woe:placetype": 20, "woe:placetype_name": "POI", "woe:lang": "ENG", "iso:country": "US", "meta:provider": ["geoplanet:7.3.1", "geoplanet:7.3.2", "geoplanet:7.4.0", "geoplanet:7.4.1", "geoplanet:7.5.1", "geoplanet:7.5.2", "geoplanet:7.6.0", "geoplanet:7.8.1", "geoplanet:7.9.0", "geoplanet:7.10.0", "geoplanet:8.0.0", "woeplanet:8.0.0"], "meta:indexed": "2020-08-20T20:18:22.581575", "woe:alias_ENG_V": ["Arnold Elementary School", "A. E. Arnold Elementary"], "meta:updated": "2020-08-22T02:57:29.345081", "woe:hierarchy": {"continent": 24865672, "country": 23424977, "town": 0, "planet": 1, "county": 12587699, "suburb": 0, "state": 2347563, "region": 0, "localadmin": 0}, "woe:timezone_id": 56043663, "woe:hash": "9qh03tgkbzun", "woe:centroid": [-118.054581, 33.826389], "geom:latitude": 33.826389, "geom:longitude": -118.054581, "geom:hash": "9qh03tgkbzun", "woe:latitude": 33.826389, "geom:centroid": [-118.054581, 33.826389], "woe:longitude": -118.054581, "woe:repo": "woeplanet-poi-us"}, "geometry": {"coordinates": [-118.054581, 33.826389], "type": "Point"}}