{"type": "Feature", "id": 23519963, "properties": {"woe:id": 23519963, "woe:parent_id": 55859604, "woe:name": "Our Lady of the Rosary School", "woe:placetype": 20, "woe:placetype_name": "POI", "woe:lang": "ENG", "iso:country": "US", "meta:provider": ["geoplanet:7.3.1", "geoplanet:7.3.2", "geoplanet:7.4.0", "geoplanet:7.4.1", "geoplanet:7.5.1", "geoplanet:7.5.2", "geoplanet:7.6.0", "geoplanet:7.8.1", "geoplanet:7.9.0", "geoplanet:7.10.0", "geoplanet:8.0.0", "woeplanet:8.0.0"], "meta:indexed": "2020-08-20T20:18:19.590373", "meta:updated": "2020-08-22T02:57:27.201750", "woe:hierarchy": {"continent": 24865672, "country": 23424977, "town": 0, "planet": 1, "county": 12587670, "suburb": 0, "state": 2347563, "region": 0, "localadmin": 0}, "woe:timezone_id": 56043663, "woe:hash": "9q9jzjxyuq8k", "woe:centroid": [-122.025307, 37.604649], "geom:latitude": 37.604649, "geom:longitude": -122.025307, "geom:hash": "9q9jzjxyuq8k", "woe:latitude": 37.604649, "geom:centroid": [-122.025307, 37.604649], "woe:longitude": -122.025307, "woe:repo": "woeplanet-poi-us"}, "geometry": {"coordinates": [-122.025307, 37.604649], "type": "Point"}}