{"type": "Feature", "id": 23663585, "geometry": {"type": "Point", "coordinates": [-73.22612, 43.518372]}, "properties": {"woe:id": 23663585, "woe:parent_id": 2476019, "woe:name": "Poultney High School", "woe:placetype": 20, "woe:placetype_name": "POI", "woe:lang": "ENG", "iso:country": "US", "meta:provider": ["geoplanet:7.3.1", "geoplanet:7.3.2", "geoplanet:7.4.0", "geoplanet:7.4.1", "geoplanet:7.5.1", "geoplanet:7.5.2", "geoplanet:7.6.0", "geoplanet:7.8.1", "geoplanet:7.9.0", "geoplanet:7.10.0", "geoplanet:8.0.0", "woeplanet:8.0.0"], "meta:indexed": "2020-08-20T20:19:07.555502", "woe:alias_ENG_V": ["Poultney Senior High School", "Poultney High", "Poultney Senior High", "Poultney HS", "Poultney Senior HS"], "meta:updated": "2020-10-14T11:19:26.796987", "woe:hierarchy": {"continent": 24865672, "country": 23424977, "town": 0, "planet": 1, "county": 12590300, "suburb": 0, "state": 2347604, "region": 0, "localadmin": 0}, "woe:timezone_id": 56043648, "woe:hash": "dreztdq2gsx2", "woe:centroid": [-73.22612, 43.518372], "geom:latitude": 43.518372, "geom:longitude": -73.22612, "geom:hash": "dreztdq2gsx2", "woe:latitude": 43.518372, "geom:centroid": [-73.22612, 43.518372], "woe:longitude": -73.22612, "woe:repo": "woeplanet-poi-us", "geom:area": 0.0, "woe:scale": 19}}