{"type": "Feature", "id": 23555136, "geometry": {"type": "Point", "coordinates": [-156.313034, 20.857571]}, "properties": {"woe:id": 23555136, "woe:parent_id": 55985944, "woe:name": "Makawao Elementary School", "woe:placetype": 20, "woe:placetype_name": "POI", "woe:lang": "ENG", "iso:country": "US", "meta:provider": ["geoplanet:7.3.1", "geoplanet:7.3.2", "geoplanet:7.4.0", "geoplanet:7.4.1", "geoplanet:7.5.1", "geoplanet:7.5.2", "geoplanet:7.6.0", "geoplanet:7.8.1", "geoplanet:7.9.0", "geoplanet:7.10.0", "geoplanet:8.0.0", "woeplanet:8.0.0"], "meta:indexed": "2020-08-20T20:18:30.080077", "woe:alias_ENG_V": ["Makawao Elementary"], "meta:updated": "2020-10-14T11:20:25.924376", "woe:hierarchy": {"continent": 24865672, "country": 23424977, "town": 0, "planet": 1, "county": 12588033, "suburb": 0, "state": 2347570, "region": 0, "localadmin": 0}, "woe:timezone_id": 28350949, "woe:hash": "8e8yej024m1c", "woe:centroid": [-156.313034, 20.857571], "geom:latitude": 20.857571, "geom:longitude": -156.313034, "geom:hash": "8e8yej024m1c", "woe:latitude": 20.857571, "geom:centroid": [-156.313034, 20.857571], "woe:longitude": -156.313034, "woe:repo": "woeplanet-poi-us", "geom:area": 0.0, "woe:scale": 19}}