{"type": "Feature", "id": 23516247, "properties": {"woe:id": 23516247, "woe:parent_id": 2477737, "woe:name": "Queen Creek High School", "woe:placetype": 20, "woe:placetype_name": "POI", "woe:lang": "ENG", "iso:country": "US", "meta:provider": ["geoplanet:7.4.0", "geoplanet:7.4.1", "geoplanet:7.5.1", "geoplanet:7.5.2", "geoplanet:7.6.0", "geoplanet:7.8.1", "geoplanet:7.9.0", "geoplanet:7.10.0", "geoplanet:8.0.0", "woeplanet:8.0.0"], "meta:indexed": "2020-08-20T23:54:24.843500", "woe:alias_ENG_V": ["Queen Creek Senior High School", "Queen Creek High", "Queen Creek Senior High", "Queen Creek HS", "Queen Creek Senior HS"], "meta:updated": "2020-08-22T02:58:45.930414", "woe:hierarchy": {"continent": 24865672, "country": 23424977, "town": 0, "planet": 1, "county": 12587587, "suburb": 0, "state": 2347561, "region": 0, "localadmin": 0}, "woe:timezone_id": 56043666, "woe:hash": "9tbt5xq56sjm", "woe:centroid": [-111.634712, 33.263062], "geom:latitude": 33.263062, "geom:longitude": -111.634712, "geom:hash": "9tbt5xq56sjm", "woe:latitude": 33.263062, "geom:centroid": [-111.634712, 33.263062], "woe:longitude": -111.634712, "woe:repo": "woeplanet-poi-us"}, "geometry": {"coordinates": [-111.634712, 33.263062], "type": "Point"}}