{"type": "Feature", "id": 23667970, "geometry": {"type": "Point", "coordinates": [-117.057838, 46.410851]}, "properties": {"woe:id": 23667970, "woe:parent_id": 2380860, "woe:name": "Educational Opportunity Center", "woe:placetype": 20, "woe:placetype_name": "POI", "woe:lang": "ENG", "iso:country": "US", "meta:provider": ["geoplanet:7.3.1", "geoplanet:7.3.2", "geoplanet:7.4.0", "geoplanet:7.4.1", "geoplanet:7.5.1", "geoplanet:7.5.2", "geoplanet:7.6.0", "geoplanet:7.8.1", "geoplanet:7.9.0", "geoplanet:7.10.0", "geoplanet:8.0.0", "woeplanet:8.0.0"], "meta:indexed": "2020-08-20T20:19:08.998260", "meta:updated": "2020-10-14T11:19:40.632222", "woe:hierarchy": {"continent": 24865672, "country": 23424977, "town": 0, "planet": 1, "county": 12590441, "suburb": 0, "state": 2347606, "region": 0, "localadmin": 0}, "woe:timezone_id": 56043663, "woe:hash": "c2kb02c4f9tw", "woe:centroid": [-117.057838, 46.410851], "geom:latitude": 46.410851, "geom:longitude": -117.057838, "geom:hash": "c2kb02c4f9tw", "woe:latitude": 46.410851, "geom:centroid": [-117.057838, 46.410851], "woe:longitude": -117.057838, "woe:repo": "woeplanet-poi-us", "geom:area": 0.0, "woe:scale": 19}}