{"type": "Feature", "id": 56054790, "geometry": {"type": "Point", "coordinates": [-86.245132, 42.408932]}, "properties": {"woe:id": 56054790, "woe:parent_id": 2496321, "woe:name": "Lake Michigan College-South Haven", "woe:placetype": 20, "woe:placetype_name": "POI", "woe:lang": "ENG", "iso:country": "US", "meta:provider": ["geoplanet:7.3.1", "geoplanet:7.3.2", "geoplanet:7.4.0", "geoplanet:7.4.1", "geoplanet:7.5.1", "geoplanet:7.5.2", "geoplanet:7.6.0", "geoplanet:7.8.1", "geoplanet:7.9.0", "geoplanet:7.10.0", "geoplanet:8.0.0", "woeplanet:8.0.0"], "meta:indexed": "2020-08-20T20:19:18.121261", "meta:updated": "2020-10-14T11:19:55.377742", "woe:hierarchy": {"continent": 24865672, "country": 23424977, "town": 0, "planet": 1, "county": 12588793, "suburb": 0, "state": 2347581, "region": 0, "localadmin": 0}, "woe:timezone_id": 56043658, "woe:hash": "dpd9m2q1yvbt", "woe:centroid": [-86.245132, 42.408932], "geom:latitude": 42.408932, "geom:longitude": -86.245132, "geom:hash": "dpd9m2q1yvbt", "woe:latitude": 42.408932, "geom:centroid": [-86.245132, 42.408932], "woe:longitude": -86.245132, "woe:repo": "woeplanet-poi-us", "geom:area": 0.0, "woe:scale": 19}}