{"type": "Feature", "id": 23572581, "properties": {"woe:id": 23572581, "woe:parent_id": 2419148, "woe:name": "Haysville Alternative High School", "woe:placetype": 20, "woe:placetype_name": "POI", "woe:lang": "ENG", "iso:country": "US", "meta:provider": ["geoplanet:7.4.0", "geoplanet:7.4.1", "geoplanet:7.5.1", "geoplanet:7.5.2", "geoplanet:7.6.0", "geoplanet:7.8.1", "geoplanet:7.9.0", "geoplanet:7.10.0", "geoplanet:8.0.0", "woeplanet:8.0.0"], "meta:indexed": "2020-08-20T23:56:00.799454", "meta:updated": "2020-08-22T02:58:47.491071", "woe:alias_ENG_V": ["Haysville Alternative Senior High School", "Haysville Alternative High", "Haysville Alternative Senior High", "Haysville Alternative HS", "Haysville Alternative Senior HS"], "woe:hierarchy": {"continent": 24865672, "country": 23424977, "town": 0, "planet": 1, "county": 12588457, "suburb": 0, "state": 2347575, "region": 0, "localadmin": 0}, "woe:timezone_id": 56043661, "woe:hash": "9ydv8wqshqqh", "woe:centroid": [-97.351723, 37.56435], "geom:latitude": 37.56435, "geom:longitude": -97.351723, "geom:hash": "9ydv8wqshqqh", "woe:latitude": 37.56435, "geom:centroid": [-97.351723, 37.56435], "woe:longitude": -97.351723, "woe:repo": "woeplanet-poi-us"}, "geometry": {"coordinates": [-97.351723, 37.56435], "type": "Point"}}