{"type": "Feature", "id": 23617304, "properties": {"woe:id": 23617304, "woe:parent_id": 2501158, "woe:name": "Health Professions & Human Svcs High School", "woe:placetype": 20, "woe:placetype_name": "POI", "woe:lang": "ENG", "iso:country": "US", "meta:provider": ["geoplanet:7.3.1", "geoplanet:7.3.2", "geoplanet:7.4.0", "geoplanet:7.4.1", "geoplanet:7.5.1", "geoplanet:7.5.2", "geoplanet:7.6.0", "geoplanet:7.8.1", "geoplanet:7.9.0", "geoplanet:7.10.0", "geoplanet:8.0.0", "woeplanet:8.0.0"], "meta:indexed": "2020-08-20T20:18:50.300303", "woe:alias_ENG_V": ["Health Professions & Human Svcs Senior High School", "Health Professions & Human Svcs High", "Health Professions & Human Svcs Senior High", "Health Professions & Human Svcs HS", "Health Professions & Human Svcs Senior HS", "Health Professions and Human Svcs High", "Health Professions and Human Svcs High School", "Health Professions and Human Svcs HS", "Health Professions and Human Svcs Senior High", "Health Professions and Human Svcs Senior High School", "Health Professions and Human Svcs Senior HS"], "meta:updated": "2020-08-22T02:58:48.766687", "woe:hierarchy": {"continent": 24865672, "country": 23424977, "town": 0, "planet": 1, "county": 12589342, "suburb": 0, "state": 2347591, "region": 0, "localadmin": 0}, "woe:timezone_id": 56043648, "woe:hash": "dr5rsrp5sqb6", "woe:centroid": [-73.983124, 40.732449], "geom:latitude": 40.732449, "geom:longitude": -73.983124, "geom:hash": "dr5rsrp5sqb6", "woe:latitude": 40.732449, "geom:centroid": [-73.983124, 40.732449], "woe:longitude": -73.983124, "woe:repo": "woeplanet-poi-us"}, "geometry": {"coordinates": [-73.983124, 40.732449], "type": "Point"}}