{"type": "Feature", "id": 23599921, "properties": {"woe:id": 23599921, "woe:parent_id": 2512520, "woe:name": "Agape Academy & Child Development", "woe:placetype": 20, "woe:placetype_name": "POI", "woe:lang": "ENG", "iso:country": "US", "meta:provider": ["geoplanet:7.3.1", "geoplanet:7.3.2", "geoplanet:7.4.0", "geoplanet:7.4.1", "geoplanet:7.5.1", "geoplanet:7.5.2", "geoplanet:7.6.0", "geoplanet:7.8.1", "geoplanet:7.9.0", "geoplanet:7.10.0", "geoplanet:8.0.0", "woeplanet:8.0.0"], "meta:indexed": "2020-08-20T20:18:44.864634", "woe:alias_ENG_V": ["Agape Academy & Child Develop Ctr", "Agape Academy and Child Development"], "meta:updated": "2020-08-22T02:57:41.068789", "woe:hierarchy": {"continent": 24865672, "country": 23424977, "town": 0, "planet": 1, "county": 12589066, "suburb": 0, "state": 2347584, "region": 0, "localadmin": 0}, "woe:timezone_id": 56043661, "woe:hash": "9yzgbxbhw11f", "woe:centroid": [-90.32933, 38.67128], "geom:latitude": 38.67128, "geom:longitude": -90.32933, "geom:hash": "9yzgbxbhw11f", "woe:latitude": 38.67128, "geom:centroid": [-90.32933, 38.67128], "woe:longitude": -90.32933, "woe:repo": "woeplanet-poi-us"}, "geometry": {"coordinates": [-90.32933, 38.67128], "type": "Point"}}