{"type": "Feature", "id": 23592283, "properties": {"woe:id": 23592283, "woe:parent_id": 2376559, "woe:name": "Cedar Elementary School", "woe:placetype": 20, "woe:placetype_name": "POI", "woe:lang": "ENG", "iso:country": "US", "meta:provider": ["geoplanet:7.3.1", "geoplanet:7.3.2", "geoplanet:7.4.0", "geoplanet:7.4.1", "geoplanet:7.5.1", "geoplanet:7.5.2", "geoplanet:7.6.0", "geoplanet:7.8.1", "geoplanet:7.9.0", "geoplanet:7.10.0", "geoplanet:8.0.0", "woeplanet:8.0.0"], "meta:indexed": "2020-08-20T20:18:42.058023", "woe:alias_ENG_V": ["Cedar Headstart", "Cedar Elementary"], "meta:updated": "2020-08-22T02:57:39.802299", "woe:hierarchy": {"continent": 24865672, "country": 23424977, "town": 0, "planet": 1, "county": 12588798, "suburb": 0, "state": 2347582, "region": 0, "localadmin": 0}, "woe:timezone_id": 56043661, "woe:hash": "cbj9v0z78tyr", "woe:centroid": [-93.285912, 45.31237], "geom:latitude": 45.31237, "geom:longitude": -93.285912, "geom:hash": "cbj9v0z78tyr", "woe:latitude": 45.31237, "geom:centroid": [-93.285912, 45.31237], "woe:longitude": -93.285912, "woe:repo": "woeplanet-poi-us"}, "geometry": {"coordinates": [-93.285912, 45.31237], "type": "Point"}}