{"type": "Feature", "id": 23676535, "geometry": {"type": "Point", "coordinates": [-89.0644, 44.345032]}, "properties": {"woe:id": 23676535, "woe:parent_id": 2515454, "woe:name": "Waupaca Middle School", "woe:placetype": 20, "woe:placetype_name": "POI", "woe:lang": "ENG", "iso:country": "US", "meta:provider": ["geoplanet:7.3.1", "geoplanet:7.3.2", "geoplanet:7.4.0", "geoplanet:7.4.1", "geoplanet:7.5.1", "geoplanet:7.5.2", "geoplanet:7.6.0", "geoplanet:7.8.1", "geoplanet:7.9.0", "geoplanet:7.10.0", "geoplanet:8.0.0", "woeplanet:8.0.0"], "meta:indexed": "2020-08-20T20:19:12.051151", "meta:updated": "2020-10-14T11:19:37.319132", "woe:hierarchy": {"continent": 24865672, "country": 23424977, "town": 0, "planet": 1, "county": 12590602, "suburb": 0, "state": 2347608, "region": 0, "localadmin": 0}, "woe:timezone_id": 56043661, "woe:hash": "dpbsm2c2911g", "woe:centroid": [-89.0644, 44.345032], "geom:latitude": 44.345032, "geom:longitude": -89.0644, "geom:hash": "dpbsm2c2911g", "woe:latitude": 44.345032, "geom:centroid": [-89.0644, 44.345032], "woe:longitude": -89.0644, "woe:repo": "woeplanet-poi-us", "geom:area": 0.0, "woe:scale": 19}}