{"type": "Feature", "id": 23531694, "geometry": {"type": "Point", "coordinates": [-118.320992, 33.8801]}, "properties": {"woe:id": 23531694, "woe:parent_id": 55862288, "woe:name": "Lincoln Elementary School", "woe:placetype": 20, "woe:placetype_name": "POI", "woe:lang": "ENG", "iso:country": "US", "meta:provider": ["geoplanet:7.3.2", "geoplanet:7.4.0", "geoplanet:7.4.1", "geoplanet:7.5.1", "geoplanet:7.5.2", "geoplanet:7.6.0", "geoplanet:7.8.1", "geoplanet:7.9.0", "geoplanet:7.10.0", "geoplanet:8.0.0", "woeplanet:8.0.0"], "meta:indexed": "2020-08-20T22:02:02.654781", "woe:alias_ENG_V": ["Lincoln Elementary"], "meta:updated": "2020-10-14T11:20:17.003007", "woe:hierarchy": {"continent": 24865672, "country": 23424977, "town": 0, "planet": 1, "county": 12587688, "suburb": 0, "state": 2347563, "region": 0, "localadmin": 0}, "woe:timezone_id": 56043663, "woe:hash": "9q5bex9mch3u", "woe:centroid": [-118.320992, 33.8801], "geom:latitude": 33.8801, "geom:longitude": -118.320992, "geom:hash": "9q5bex9mch3u", "woe:latitude": 33.8801, "geom:centroid": [-118.320992, 33.8801], "woe:longitude": -118.320992, "woe:repo": "woeplanet-poi-us", "geom:area": 0.0, "woe:scale": 19}}