{"type": "Feature", "id": 23668573, "geometry": {"type": "Point", "coordinates": [-119.289177, 47.12429]}, "properties": {"woe:id": 23668573, "woe:parent_id": 28340643, "woe:name": "Columbia Basin Alternative High School", "woe:placetype": 20, "woe:placetype_name": "POI", "woe:lang": "ENG", "iso:country": "US", "meta:provider": ["geoplanet:7.3.1", "geoplanet:7.3.2", "geoplanet:7.4.0", "geoplanet:7.4.1", "geoplanet:7.5.1", "geoplanet:7.5.2", "geoplanet:7.6.0", "geoplanet:7.8.1", "geoplanet:7.9.0", "geoplanet:7.10.0", "geoplanet:8.0.0", "woeplanet:8.0.0"], "meta:indexed": "2020-08-20T20:19:09.147074", "woe:alias_ENG_V": ["Columbia Basin Alternative Senior High School", "Columbia Basin Alternative High", "Columbia Basin Alternative Senior High", "Columbia Basin Alternative HS", "Columbia Basin Alternative Senior HS"], "meta:updated": "2020-10-14T11:19:37.499419", "woe:hierarchy": {"continent": 24865672, "country": 23424977, "town": 0, "planet": 1, "county": 12590452, "suburb": 0, "state": 2347606, "region": 0, "localadmin": 0}, "woe:timezone_id": 56043663, "woe:hash": "c27hjd8qbsqe", "woe:centroid": [-119.289177, 47.12429], "geom:latitude": 47.12429, "geom:longitude": -119.289177, "geom:hash": "c27hjd8qbsqe", "woe:latitude": 47.12429, "geom:centroid": [-119.289177, 47.12429], "woe:longitude": -119.289177, "woe:repo": "woeplanet-poi-us", "geom:area": 0.0, "woe:scale": 19}}