{"type": "Feature", "id": 23596118, "geometry": {"type": "Point", "coordinates": [-88.726143, 34.272709]}, "properties": {"woe:id": 23596118, "woe:parent_id": 2508655, "woe:name": "Joyner Elementary School", "woe:placetype": 20, "woe:placetype_name": "POI", "woe:lang": "ENG", "iso:country": "US", "meta:provider": ["geoplanet:7.3.2", "geoplanet:7.4.0", "geoplanet:7.4.1", "geoplanet:7.5.1", "geoplanet:7.5.2", "geoplanet:7.6.0", "geoplanet:7.8.1", "geoplanet:7.9.0", "geoplanet:7.10.0", "geoplanet:8.0.0", "woeplanet:8.0.0"], "meta:indexed": "2020-08-20T22:02:29.393891", "woe:alias_ENG_V": ["Joyner Avenue Elementary School", "Joyner Elementary"], "meta:updated": "2020-10-14T11:20:26.235297", "woe:hierarchy": {"continent": 24865672, "country": 23424977, "town": 0, "planet": 1, "county": 12588924, "suburb": 0, "state": 2347583, "region": 0, "localadmin": 0}, "woe:timezone_id": 56043661, "woe:hash": "dn0fuzpt5008", "woe:centroid": [-88.726143, 34.272709], "geom:latitude": 34.272709, "geom:longitude": -88.726143, "geom:hash": "dn0fuzpt5008", "woe:latitude": 34.272709, "geom:centroid": [-88.726143, 34.272709], "woe:longitude": -88.726143, "woe:repo": "woeplanet-poi-us", "geom:area": 0.0, "woe:scale": 19}}