{"type": "Feature", "id": 23637550, "properties": {"woe:id": 23637550, "woe:parent_id": 2434203, "woe:name": "Grande Ronde Child Center", "woe:placetype": 20, "woe:placetype_name": "POI", "woe:lang": "ENG", "iso:country": "US", "meta:provider": ["geoplanet:7.3.1", "geoplanet:7.3.2", "geoplanet:7.4.0", "geoplanet:7.4.1", "geoplanet:7.5.1", "geoplanet:7.5.2", "geoplanet:7.6.0", "geoplanet:7.8.1", "geoplanet:7.9.0", "geoplanet:7.10.0", "geoplanet:8.0.0", "woeplanet:8.0.0"], "meta:indexed": "2020-08-20T20:18:57.452109", "meta:updated": "2020-08-22T02:57:46.270100", "woe:hierarchy": {"continent": 24865672, "country": 23424977, "town": 0, "planet": 1, "county": 12589722, "suburb": 0, "state": 2347596, "region": 0, "localadmin": 0}, "woe:timezone_id": 56043663, "woe:hash": "c2h1b97e8htf", "woe:centroid": [-118.098213, 45.315109], "geom:latitude": 45.315109, "geom:longitude": -118.098213, "geom:hash": "c2h1b97e8htf", "woe:latitude": 45.315109, "geom:centroid": [-118.098213, 45.315109], "woe:longitude": -118.098213, "woe:repo": "woeplanet-poi-us"}, "geometry": {"coordinates": [-118.098213, 45.315109], "type": "Point"}}