{"type": "Feature", "id": 23636871, "geometry": {"type": "Point", "coordinates": [-123.008308, 44.99604]}, "properties": {"woe:id": 23636871, "woe:parent_id": 55861611, "woe:name": "Kennedy Elementary School", "woe:placetype": 20, "woe:placetype_name": "POI", "woe:lang": "ENG", "iso:country": "US", "meta:provider": ["geoplanet:7.3.1", "geoplanet:7.3.2", "geoplanet:7.4.0", "geoplanet:7.4.1", "geoplanet:7.5.1", "geoplanet:7.5.2", "geoplanet:7.6.0", "geoplanet:7.8.1", "geoplanet:7.9.0", "geoplanet:7.10.0", "geoplanet:8.0.0", "woeplanet:8.0.0"], "meta:indexed": "2020-08-20T20:18:57.185506", "woe:alias_ENG_V": ["Salem Keizer School", "Kennedy Elementary"], "meta:updated": "2020-10-14T11:19:31.695990", "woe:hierarchy": {"continent": 24865672, "country": 23424977, "town": 0, "planet": 1, "county": 12589715, "suburb": 0, "state": 2347596, "region": 0, "localadmin": 0}, "woe:timezone_id": 56043663, "woe:hash": "9rbxbzk0ftv9", "woe:centroid": [-123.008308, 44.99604], "geom:latitude": 44.99604, "geom:longitude": -123.008308, "geom:hash": "9rbxbzk0ftv9", "woe:latitude": 44.99604, "geom:centroid": [-123.008308, 44.99604], "woe:longitude": -123.008308, "woe:repo": "woeplanet-poi-us", "geom:area": 0.0, "woe:scale": 19}}