{"type": "Feature", "id": 23624930, "geometry": {"type": "Point", "coordinates": [-83.161369, 35.405392]}, "properties": {"woe:id": 23624930, "woe:parent_id": 12589423, "woe:name": "Scotts Creek Elementary School", "woe:placetype": 20, "woe:placetype_name": "POI", "woe:lang": "ENG", "iso:country": "US", "meta:provider": ["geoplanet:7.3.2", "geoplanet:7.4.0", "geoplanet:7.4.1", "geoplanet:7.5.1", "geoplanet:7.5.2", "geoplanet:7.6.0", "geoplanet:7.8.1", "geoplanet:7.9.0", "geoplanet:7.10.0", "geoplanet:8.0.0", "woeplanet:8.0.0"], "meta:indexed": "2020-08-20T22:02:40.392570", "woe:alias_ENG_V": ["Scotts Creek Elementary"], "meta:updated": "2020-10-14T11:19:53.016710", "woe:hierarchy": {"continent": 24865672, "country": 23424977, "town": 0, "planet": 1, "county": 12589423, "suburb": 0, "state": 2347592, "region": 0, "localadmin": 0}, "woe:timezone_id": 56043648, "woe:hash": "dnkc7t7erekv", "woe:centroid": [-83.161369, 35.405392], "geom:latitude": 35.405392, "geom:longitude": -83.161369, "geom:hash": "dnkc7t7erekv", "woe:latitude": 35.405392, "geom:centroid": [-83.161369, 35.405392], "woe:longitude": -83.161369, "woe:repo": "woeplanet-poi-us", "geom:area": 0.0, "woe:scale": 19}}