{"type": "Feature", "id": 23524177, "properties": {"woe:id": 23524177, "woe:parent_id": 2482885, "woe:name": "Main Avenue Elementary School", "woe:placetype": 20, "woe:placetype_name": "POI", "woe:lang": "ENG", "iso:country": "US", "meta:provider": ["geoplanet:7.3.2", "geoplanet:7.4.0", "geoplanet:7.4.1", "geoplanet:7.5.1", "geoplanet:7.5.2", "geoplanet:7.6.0", "geoplanet:7.8.1", "geoplanet:7.9.0", "geoplanet:7.10.0", "geoplanet:8.0.0", "woeplanet:8.0.0"], "meta:indexed": "2020-08-20T22:01:59.441222", "woe:alias_ENG_V": ["Main Avenue Elementary"], "meta:updated": "2020-08-22T02:57:27.725277", "woe:hierarchy": {"continent": 24865672, "country": 23424977, "town": 0, "planet": 1, "county": 12587703, "suburb": 0, "state": 2347563, "region": 0, "localadmin": 0}, "woe:timezone_id": 56043663, "woe:hash": "9qceusye7vt4", "woe:centroid": [-121.433777, 38.65461], "geom:latitude": 38.65461, "geom:longitude": -121.433777, "geom:hash": "9qceusye7vt4", "woe:latitude": 38.65461, "geom:centroid": [-121.433777, 38.65461], "woe:longitude": -121.433777, "woe:repo": "woeplanet-poi-us"}, "geometry": {"coordinates": [-121.433777, 38.65461], "type": "Point"}}