{"type": "Feature", "id": 23516892, "geometry": {"type": "Point", "coordinates": [-110.945709, 32.230511]}, "properties": {"woe:id": 23516892, "woe:parent_id": 55805871, "woe:name": "Mckale Center", "woe:placetype": 20, "woe:placetype_name": "POI", "woe:lang": "ENG", "iso:country": "US", "meta:provider": ["geoplanet:7.3.1", "geoplanet:7.3.2", "geoplanet:7.4.0", "geoplanet:7.4.1", "geoplanet:7.5.1", "geoplanet:7.5.2", "geoplanet:7.6.0", "geoplanet:7.8.1", "geoplanet:7.9.0", "geoplanet:7.10.0", "geoplanet:8.0.0", "woeplanet:8.0.0"], "meta:indexed": "2020-08-20T20:18:18.565904", "woe:alias_ENG_V": ["McKale Memorial Center"], "meta:updated": "2020-10-14T11:20:29.392160", "woe:hierarchy": {"continent": 24865672, "country": 23424977, "town": 0, "planet": 1, "county": 12587590, "suburb": 0, "state": 2347561, "region": 0, "localadmin": 0}, "woe:timezone_id": 56043666, "woe:hash": "9t9p777u3der", "woe:centroid": [-110.945709, 32.230511], "geom:latitude": 32.230511, "geom:longitude": -110.945709, "geom:hash": "9t9p777u3der", "woe:latitude": 32.230511, "geom:centroid": [-110.945709, 32.230511], "woe:longitude": -110.945709, "woe:repo": "woeplanet-poi-us", "geom:area": 0.0, "woe:scale": 19}}