{"type": "Feature", "id": 23553708, "properties": {"woe:id": 23553708, "woe:parent_id": 2414549, "woe:name": "Greenville Elementary School", "woe:placetype": 20, "woe:placetype_name": "POI", "woe:lang": "ENG", "iso:country": "US", "meta:provider": ["geoplanet:7.3.1", "geoplanet:7.3.2", "geoplanet:7.4.0", "geoplanet:7.4.1", "geoplanet:7.5.1", "geoplanet:7.5.2", "geoplanet:7.6.0", "geoplanet:7.8.1", "geoplanet:7.9.0", "geoplanet:7.10.0", "geoplanet:8.0.0", "woeplanet:8.0.0"], "meta:indexed": "2020-08-20T20:18:29.704879", "woe:alias_ENG_V": ["Greenville Elementary"], "meta:updated": "2020-08-22T02:57:33.299947", "woe:hierarchy": {"continent": 24865672, "country": 23424977, "town": 0, "planet": 1, "county": 12587968, "suburb": 0, "state": 2347569, "region": 0, "localadmin": 0}, "woe:timezone_id": 56043648, "woe:hash": "djggb4yv9mmk", "woe:centroid": [-84.717232, 33.019009], "geom:latitude": 33.019009, "geom:longitude": -84.717232, "geom:hash": "djggb4yv9mmk", "woe:latitude": 33.019009, "geom:centroid": [-84.717232, 33.019009], "woe:longitude": -84.717232, "woe:repo": "woeplanet-poi-us"}, "geometry": {"coordinates": [-84.717232, 33.019009], "type": "Point"}}