{"type": "Feature", "id": 23641720, "geometry": {"type": "Point", "coordinates": [-77.23674, 40.565571]}, "properties": {"woe:id": 23641720, "woe:parent_id": 2505831, "woe:name": "Thompsontown-delaware Elementary School", "woe:placetype": 20, "woe:placetype_name": "POI", "woe:lang": "ENG", "iso:country": "US", "meta:provider": ["geoplanet:7.3.1", "geoplanet:7.3.2", "geoplanet:7.4.0", "geoplanet:7.4.1", "geoplanet:7.5.1", "geoplanet:7.5.2", "geoplanet:7.6.0", "geoplanet:7.8.1", "geoplanet:7.9.0", "geoplanet:7.10.0", "geoplanet:8.0.0", "woeplanet:8.0.0"], "meta:indexed": "2020-08-20T20:18:58.977954", "woe:alias_ENG_V": ["Thompsontown-Delaware Elem Sch", "Thompsontown-delaware Elementary"], "meta:updated": "2020-10-14T11:19:29.515072", "woe:hierarchy": {"continent": 24865672, "country": 23424977, "town": 0, "planet": 1, "county": 12589761, "suburb": 0, "state": 2347597, "region": 0, "localadmin": 0}, "woe:timezone_id": 56043648, "woe:hash": "dr1nf2tztd82", "woe:centroid": [-77.23674, 40.565571], "geom:latitude": 40.565571, "geom:longitude": -77.23674, "geom:hash": "dr1nf2tztd82", "woe:latitude": 40.565571, "geom:centroid": [-77.23674, 40.565571], "woe:longitude": -77.23674, "woe:repo": "woeplanet-poi-us", "geom:area": 0.0, "woe:scale": 19}}