{"type": "Feature", "id": 23563295, "geometry": {"type": "Point", "coordinates": [-89.82547, 39.126251]}, "properties": {"woe:id": 23563295, "woe:parent_id": 2410252, "woe:name": "Gillespie Middle School", "woe:placetype": 20, "woe:placetype_name": "POI", "woe:lang": "ENG", "iso:country": "US", "meta:provider": ["geoplanet:7.3.1", "geoplanet:7.3.2", "geoplanet:7.4.0", "geoplanet:7.4.1", "geoplanet:7.5.1", "geoplanet:7.5.2", "geoplanet:7.6.0", "geoplanet:7.8.1", "geoplanet:7.9.0", "geoplanet:7.10.0", "geoplanet:8.0.0", "woeplanet:8.0.0"], "meta:indexed": "2020-08-20T20:18:32.787716", "meta:updated": "2020-10-14T11:20:10.140118", "woe:hierarchy": {"continent": 24865672, "country": 23424977, "town": 0, "planet": 1, "county": 12588133, "suburb": 0, "state": 2347572, "region": 0, "localadmin": 0}, "woe:timezone_id": 56043661, "woe:hash": "dnbnefxnfvg4", "woe:centroid": [-89.82547, 39.126251], "geom:latitude": 39.126251, "geom:longitude": -89.82547, "geom:hash": "dnbnefxnfvg4", "woe:latitude": 39.126251, "geom:centroid": [-89.82547, 39.126251], "woe:longitude": -89.82547, "woe:repo": "woeplanet-poi-us", "geom:area": 0.0, "woe:scale": 19}}