{"type": "Feature", "id": 23613952, "geometry": {"type": "Point", "coordinates": [-73.910271, 41.744431]}, "properties": {"woe:id": 23613952, "woe:parent_id": 23417772, "woe:name": "St Peter School", "woe:placetype": 20, "woe:placetype_name": "POI", "woe:lang": "ENG", "iso:country": "US", "meta:provider": ["geoplanet:7.3.1", "geoplanet:7.3.2", "geoplanet:7.4.0", "geoplanet:7.4.1", "geoplanet:7.5.1", "geoplanet:7.5.2", "geoplanet:7.6.0", "geoplanet:7.8.1", "geoplanet:7.9.0", "geoplanet:7.10.0", "geoplanet:8.0.0", "woeplanet:8.0.0"], "meta:indexed": "2020-08-20T20:18:48.994892", "meta:updated": "2020-10-14T11:19:52.564255", "woe:hierarchy": {"continent": 24865672, "country": 23424977, "town": 0, "planet": 1, "county": 12589325, "suburb": 0, "state": 2347591, "region": 0, "localadmin": 0}, "woe:timezone_id": 56043648, "woe:hash": "dr7mqpk4vvgw", "woe:centroid": [-73.910271, 41.744431], "geom:latitude": 41.744431, "geom:longitude": -73.910271, "geom:hash": "dr7mqpk4vvgw", "woe:latitude": 41.744431, "geom:centroid": [-73.910271, 41.744431], "woe:longitude": -73.910271, "woe:repo": "woeplanet-poi-us", "geom:area": 0.0, "woe:scale": 19}}