{"type": "Feature", "id": 23606934, "properties": {"woe:id": 23606934, "woe:parent_id": 2459591, "woe:name": "Richards Elementary School", "woe:placetype": 20, "woe:placetype_name": "POI", "woe:lang": "ENG", "iso:country": "US", "meta:provider": ["geoplanet:7.3.2", "geoplanet:7.4.0", "geoplanet:7.4.1", "geoplanet:7.5.1", "geoplanet:7.5.2", "geoplanet:7.6.0", "geoplanet:7.8.1", "geoplanet:7.9.0", "geoplanet:7.10.0", "geoplanet:8.0.0", "woeplanet:8.0.0"], "meta:indexed": "2020-08-20T22:02:33.050463", "woe:alias_ENG_V": ["Richards School", "Richards Elementary"], "meta:updated": "2020-08-22T02:57:41.855755", "woe:hierarchy": {"continent": 24865672, "country": 23424977, "town": 0, "planet": 1, "county": 12589257, "suburb": 0, "state": 2347588, "region": 0, "localadmin": 0}, "woe:timezone_id": 56043648, "woe:hash": "drswtwwtsmvz", "woe:centroid": [-72.171059, 43.36676], "geom:latitude": 43.36676, "geom:longitude": -72.171059, "geom:hash": "drswtwwtsmvz", "woe:latitude": 43.36676, "geom:centroid": [-72.171059, 43.36676], "woe:longitude": -72.171059, "woe:repo": "woeplanet-poi-us"}, "geometry": {"coordinates": [-72.171059, 43.36676], "type": "Point"}}