{"type": "Feature", "id": 23610990, "properties": {"woe:id": 23610990, "woe:parent_id": 55991828, "woe:name": "Cibola High School", "woe:placetype": 20, "woe:placetype_name": "POI", "woe:lang": "ENG", "iso:country": "US", "meta:provider": ["geoplanet:7.3.2", "geoplanet:7.4.0", "geoplanet:7.4.1", "geoplanet:7.5.1", "geoplanet:7.5.2", "geoplanet:7.6.0", "geoplanet:7.8.1", "geoplanet:7.9.0", "geoplanet:7.10.0", "geoplanet:8.0.0", "woeplanet:8.0.0"], "meta:indexed": "2020-08-20T22:02:34.908510", "woe:alias_ENG_V": ["Cibola Senior High School", "Cibola High", "Cibola Senior High", "Cibola HS", "Cibola Senior HS"], "meta:updated": "2020-08-22T02:58:48.604116", "woe:hierarchy": {"continent": 24865672, "country": 23424977, "town": 0, "planet": 1, "county": 12589279, "suburb": 0, "state": 2347590, "region": 0, "localadmin": 0}, "woe:timezone_id": 56043665, "woe:hash": "9wk0kc5b6rp8", "woe:centroid": [-106.661003, 35.205769], "geom:latitude": 35.205769, "geom:longitude": -106.661003, "geom:hash": "9wk0kc5b6rp8", "woe:latitude": 35.205769, "geom:centroid": [-106.661003, 35.205769], "woe:longitude": -106.661003, "woe:repo": "woeplanet-poi-us"}, "geometry": {"coordinates": [-106.661003, 35.205769], "type": "Point"}}