{"type": "Feature", "id": 23658981, "geometry": {"type": "Point", "coordinates": [-95.356522, 29.738159]}, "properties": {"woe:id": 23658981, "woe:parent_id": 55993951, "woe:name": "Douglass Elementary School", "woe:placetype": 20, "woe:placetype_name": "POI", "woe:lang": "ENG", "iso:country": "US", "meta:provider": ["geoplanet:7.3.1", "geoplanet:7.3.2", "geoplanet:7.4.0", "geoplanet:7.4.1", "geoplanet:7.5.1", "geoplanet:7.5.2", "geoplanet:7.6.0", "geoplanet:7.8.1", "geoplanet:7.9.0", "geoplanet:7.10.0", "geoplanet:8.0.0", "woeplanet:8.0.0"], "meta:indexed": "2020-08-20T20:19:05.732023", "woe:alias_ENG_V": ["Douglass Elementary"], "meta:updated": "2020-10-14T11:19:39.548489", "woe:hierarchy": {"continent": 24865672, "country": 23424977, "town": 0, "planet": 1, "county": 12590107, "suburb": 0, "state": 2347602, "region": 0, "localadmin": 0}, "woe:timezone_id": 56043661, "woe:hash": "9vk1njemrfxs", "woe:centroid": [-95.356522, 29.738159], "geom:latitude": 29.738159, "geom:longitude": -95.356522, "geom:hash": "9vk1njemrfxs", "woe:latitude": 29.738159, "geom:centroid": [-95.356522, 29.738159], "woe:longitude": -95.356522, "woe:repo": "woeplanet-poi-us", "geom:area": 0.0, "woe:scale": 19}}