{"type": "Feature", "id": 23571856, "properties": {"woe:id": 23571856, "woe:parent_id": 12588416, "woe:name": "Rockhurst High School", "woe:placetype": 20, "woe:placetype_name": "POI", "woe:lang": "ENG", "iso:country": "US", "meta:provider": ["geoplanet:7.3.1", "geoplanet:7.3.2", "geoplanet:7.4.0", "geoplanet:7.4.1", "geoplanet:7.5.1", "geoplanet:7.5.2", "geoplanet:7.6.0", "geoplanet:7.8.1", "geoplanet:7.9.0", "geoplanet:7.10.0", "geoplanet:8.0.0", "woeplanet:8.0.0"], "meta:indexed": "2020-08-20T20:18:36.113681", "woe:alias_ENG_V": ["Rockhurst Senior High School", "Rockhurst High", "Rockhurst Senior High", "Rockhurst HS", "Rockhurst Senior HS"], "meta:updated": "2020-08-22T02:58:47.452588", "woe:hierarchy": {"continent": 24865672, "country": 23424977, "town": 0, "planet": 1, "county": 12588416, "suburb": 0, "state": 2347575, "region": 0, "localadmin": 0}, "woe:timezone_id": 56043661, "woe:hash": "9yutxhk6ywd9", "woe:centroid": [-94.608139, 38.9594], "geom:latitude": 38.9594, "geom:longitude": -94.608139, "geom:hash": "9yutxhk6ywd9", "woe:latitude": 38.9594, "geom:centroid": [-94.608139, 38.9594], "woe:longitude": -94.608139, "woe:repo": "woeplanet-poi-us"}, "geometry": {"coordinates": [-94.608139, 38.9594], "type": "Point"}}