{"type": "Feature", "id": 23681918, "geometry": {"type": "Point", "coordinates": [-85.091782, 40.776428]}, "properties": {"woe:id": 23681918, "woe:parent_id": 2386611, "woe:name": "Craigville Station", "woe:placetype": 20, "woe:placetype_name": "POI", "woe:lang": "ENG", "iso:country": "US", "meta:provider": ["geoplanet:7.3.1", "geoplanet:7.3.2", "geoplanet:7.4.0", "geoplanet:7.4.1", "geoplanet:7.5.1", "geoplanet:7.5.2", "geoplanet:7.6.0", "geoplanet:7.8.1", "geoplanet:7.9.0", "geoplanet:7.10.0", "geoplanet:8.0.0", "woeplanet:8.0.0"], "meta:indexed": "2020-08-20T20:19:19.404909", "meta:updated": "2020-10-14T11:19:32.709072", "woe:hierarchy": {"continent": 24865672, "country": 23424977, "town": 0, "planet": 1, "county": 12588269, "suburb": 0, "state": 2347573, "region": 0, "localadmin": 0}, "woe:timezone_id": 56043656, "woe:hash": "dp5rzxn5cv0e", "woe:centroid": [-85.091782, 40.776428], "geom:latitude": 40.776428, "geom:longitude": -85.091782, "geom:hash": "dp5rzxn5cv0e", "woe:latitude": 40.776428, "geom:centroid": [-85.091782, 40.776428], "woe:longitude": -85.091782, "woe:repo": "woeplanet-poi-us", "geom:area": 0.0, "woe:scale": 19}}