{"type": "Feature", "id": 56063509, "properties": {"woe:id": 56063509, "woe:parent_id": 2514971, "woe:name": "Wasilla Station", "woe:placetype": 20, "woe:placetype_name": "POI", "woe:lang": "ENG", "iso:country": "US", "meta:provider": ["geoplanet:7.3.1", "geoplanet:7.3.2", "geoplanet:7.4.0", "geoplanet:7.4.1", "geoplanet:7.5.1", "geoplanet:7.5.2", "geoplanet:7.6.0", "geoplanet:7.8.1", "geoplanet:7.9.0", "geoplanet:7.10.0", "geoplanet:8.0.0", "woeplanet:8.0.0"], "meta:indexed": "2020-08-20T20:19:20.574451", "woe:alias_ENG_V": ["Wasilla Alaska Railroad Station", "Alaska Railroad Wasilla Station", "Alaska Railroad-Wasilla"], "meta:updated": "2020-08-22T02:58:22.857740", "woe:hierarchy": {"continent": 24865672, "country": 23424977, "town": 0, "planet": 1, "county": 12587568, "suburb": 0, "state": 2347560, "region": 0, "localadmin": 0}, "woe:timezone_id": 56043669, "woe:hash": "bdvwr6key6ku", "woe:centroid": [-149.440567, 61.580399], "geom:latitude": 61.580399, "geom:longitude": -149.440567, "geom:hash": "bdvwr6key6ku", "woe:latitude": 61.580399, "geom:centroid": [-149.440567, 61.580399], "woe:longitude": -149.440567, "woe:repo": "woeplanet-poi-us"}, "geometry": {"coordinates": [-149.440567, 61.580399], "type": "Point"}}