{"type": "Feature", "id": 23565763, "properties": {"woe:id": 23565763, "woe:parent_id": 2456291, "woe:name": "Northside Middle School", "woe:placetype": 20, "woe:placetype_name": "POI", "woe:lang": "ENG", "iso:country": "US", "meta:provider": ["geoplanet:7.3.1", "geoplanet:7.3.2", "geoplanet:7.4.0", "geoplanet:7.4.1", "geoplanet:7.5.1", "geoplanet:7.5.2", "geoplanet:7.6.0", "geoplanet:7.8.1", "geoplanet:7.9.0", "geoplanet:7.10.0", "geoplanet:8.0.0", "woeplanet:8.0.0"], "meta:indexed": "2020-08-20T20:18:33.757080", "meta:updated": "2020-08-22T02:57:35.494119", "woe:hierarchy": {"continent": 24865672, "country": 23424977, "town": 0, "planet": 1, "county": 12588197, "suburb": 0, "state": 2347573, "region": 0, "localadmin": 0}, "woe:timezone_id": 56043656, "woe:hash": "dp5kb27t9n44", "woe:centroid": [-85.413849, 40.212311], "geom:latitude": 40.212311, "geom:longitude": -85.413849, "geom:hash": "dp5kb27t9n44", "woe:latitude": 40.212311, "geom:centroid": [-85.413849, 40.212311], "woe:longitude": -85.413849, "woe:repo": "woeplanet-poi-us"}, "geometry": {"coordinates": [-85.413849, 40.212311], "type": "Point"}}