{"type": "Feature", "id": 23574538, "properties": {"woe:id": 23574538, "woe:parent_id": 2426704, "woe:name": "Summit View Elementary School", "woe:placetype": 20, "woe:placetype_name": "POI", "woe:lang": "ENG", "iso:country": "US", "meta:provider": ["geoplanet:7.3.1", "geoplanet:7.3.2", "geoplanet:7.4.0", "geoplanet:7.4.1", "geoplanet:7.5.1", "geoplanet:7.5.2", "geoplanet:7.6.0", "geoplanet:7.8.1", "geoplanet:7.9.0", "geoplanet:7.10.0", "geoplanet:8.0.0", "woeplanet:8.0.0"], "meta:indexed": "2020-08-20T20:18:36.986090", "woe:alias_ENG_V": ["Summit View Elementary"], "meta:updated": "2020-08-22T02:57:36.980041", "woe:hierarchy": {"continent": 24865672, "country": 23424977, "town": 0, "planet": 1, "county": 12588534, "suburb": 0, "state": 2347576, "region": 0, "localadmin": 0}, "woe:timezone_id": 56043647, "woe:hash": "dngvshnr433y", "woe:centroid": [-84.542099, 38.958729], "geom:latitude": 38.958729, "geom:longitude": -84.542099, "geom:hash": "dngvshnr433y", "woe:latitude": 38.958729, "geom:centroid": [-84.542099, 38.958729], "woe:longitude": -84.542099, "woe:repo": "woeplanet-poi-us"}, "geometry": {"coordinates": [-84.542099, 38.958729], "type": "Point"}}