{"type": "Feature", "id": 23664022, "properties": {"woe:id": 23664022, "woe:parent_id": 55857881, "woe:name": "Glebe Elementary School", "woe:placetype": 20, "woe:placetype_name": "POI", "woe:lang": "ENG", "iso:country": "US", "meta:provider": ["geoplanet:7.3.1", "geoplanet:7.3.2", "geoplanet:7.4.0", "geoplanet:7.4.1", "geoplanet:7.5.1", "geoplanet:7.5.2", "geoplanet:7.6.0", "geoplanet:7.8.1", "geoplanet:7.9.0", "geoplanet:7.10.0", "geoplanet:8.0.0", "woeplanet:8.0.0"], "meta:indexed": "2020-08-20T20:19:07.642199", "woe:alias_ENG_V": ["Glebe Elementary"], "meta:updated": "2020-08-22T02:57:51.050809", "woe:hierarchy": {"continent": 24865672, "country": 23424977, "town": 0, "planet": 1, "county": 12590311, "suburb": 0, "state": 2347605, "region": 0, "localadmin": 0}, "woe:timezone_id": 56043648, "woe:hash": "dqcjm05k0twx", "woe:centroid": [-77.11953, 38.892319], "geom:latitude": 38.892319, "geom:longitude": -77.11953, "geom:hash": "dqcjm05k0twx", "woe:latitude": 38.892319, "geom:centroid": [-77.11953, 38.892319], "woe:longitude": -77.11953, "woe:repo": "woeplanet-poi-us"}, "geometry": {"coordinates": [-77.11953, 38.892319], "type": "Point"}}