{"type": "Feature", "id": 23550219, "properties": {"woe:id": 23550219, "woe:parent_id": 23417432, "woe:name": "Clifford O. Taylor/kirkland Elementary School", "woe:placetype": 20, "woe:placetype_name": "POI", "woe:lang": "ENG", "iso:country": "US", "meta:provider": ["geoplanet:7.3.1", "geoplanet:7.3.2", "geoplanet:7.4.0", "geoplanet:7.4.1", "geoplanet:7.5.1", "geoplanet:7.5.2", "geoplanet:7.6.0", "geoplanet:7.8.1", "geoplanet:7.9.0", "geoplanet:7.10.0", "geoplanet:8.0.0", "woeplanet:8.0.0"], "meta:indexed": "2020-08-20T20:18:28.269173", "woe:alias_ENG_V": ["Clifford o Taylor Kirklane Elem Sch", "Clifford O. Taylor/kirkland Elementary"], "meta:updated": "2020-08-22T02:57:32.531661", "woe:hierarchy": {"continent": 24865672, "country": 23424977, "town": 0, "planet": 1, "county": 12587852, "suburb": 0, "state": 2347568, "region": 0, "localadmin": 0}, "woe:timezone_id": 56043648, "woe:hash": "dhxp947mxthb", "woe:centroid": [-80.107513, 26.64419], "geom:latitude": 26.64419, "geom:longitude": -80.107513, "geom:hash": "dhxp947mxthb", "woe:latitude": 26.64419, "geom:centroid": [-80.107513, 26.64419], "woe:longitude": -80.107513, "woe:repo": "woeplanet-poi-us"}, "geometry": {"coordinates": [-80.107513, 26.64419], "type": "Point"}}