{"type": "Feature", "id": 23568480, "geometry": {"type": "Point", "coordinates": [-87.40448, 39.445]}, "properties": {"woe:id": 23568480, "woe:parent_id": 2504883, "woe:name": "Sarah Scott Middle School", "woe:placetype": 20, "woe:placetype_name": "POI", "woe:lang": "ENG", "iso:country": "US", "meta:provider": ["geoplanet:7.3.1", "geoplanet:7.3.2", "geoplanet:7.4.0", "geoplanet:7.4.1", "geoplanet:7.5.1", "geoplanet:7.5.2", "geoplanet:7.6.0", "geoplanet:7.8.1", "geoplanet:7.9.0", "geoplanet:7.10.0", "geoplanet:8.0.0", "woeplanet:8.0.0"], "meta:indexed": "2020-08-20T20:18:34.819494", "meta:updated": "2020-10-14T11:20:12.242780", "woe:hierarchy": {"continent": 24865672, "country": 23424977, "town": 0, "planet": 1, "county": 12588263, "suburb": 0, "state": 2347573, "region": 0, "localadmin": 0}, "woe:timezone_id": 56043656, "woe:hash": "dp1b7h9zzbzy", "woe:centroid": [-87.40448, 39.445], "geom:latitude": 39.445, "geom:longitude": -87.40448, "geom:hash": "dp1b7h9zzbzy", "woe:latitude": 39.445, "geom:centroid": [-87.40448, 39.445], "woe:longitude": -87.40448, "woe:repo": "woeplanet-poi-us", "geom:area": 0.0, "woe:scale": 19}}