{"type": "Feature", "id": 23570127, "geometry": {"type": "Point", "coordinates": [-96.16671, 42.777302]}, "properties": {"woe:id": 23570127, "woe:parent_id": 2437475, "woe:name": "Kluckhohn Elementary School", "woe:placetype": 20, "woe:placetype_name": "POI", "woe:lang": "ENG", "iso:country": "US", "meta:provider": ["geoplanet:7.3.1", "geoplanet:7.3.2", "geoplanet:7.4.0", "geoplanet:7.4.1", "geoplanet:7.5.1", "geoplanet:7.5.2", "geoplanet:7.6.0", "geoplanet:7.8.1", "geoplanet:7.9.0", "geoplanet:7.10.0", "geoplanet:8.0.0", "woeplanet:8.0.0"], "meta:indexed": "2020-08-20T20:18:35.385462", "woe:alias_ENG_V": ["Kluckhohn Elementary"], "meta:updated": "2020-10-14T11:20:22.091399", "woe:hierarchy": {"continent": 24865672, "country": 23424977, "town": 0, "planet": 1, "county": 12588346, "suburb": 0, "state": 2347574, "region": 0, "localadmin": 0}, "woe:timezone_id": 56043661, "woe:hash": "9zee7emec5p9", "woe:centroid": [-96.16671, 42.777302], "geom:latitude": 42.777302, "geom:longitude": -96.16671, "geom:hash": "9zee7emec5p9", "woe:latitude": 42.777302, "geom:centroid": [-96.16671, 42.777302], "woe:longitude": -96.16671, "woe:repo": "woeplanet-poi-us", "geom:area": 0.0, "woe:scale": 19}}