{"type": "Feature", "id": 23636921, "geometry": {"type": "Point", "coordinates": [-122.987198, 45.004509]}, "properties": {"woe:id": 23636921, "woe:parent_id": 55861611, "woe:name": "Chemawa Indian School", "woe:placetype": 20, "woe:placetype_name": "POI", "woe:lang": "ENG", "iso:country": "US", "meta:provider": ["geoplanet:7.3.1", "geoplanet:7.3.2", "geoplanet:7.4.0", "geoplanet:7.4.1", "geoplanet:7.5.1", "geoplanet:7.5.2", "geoplanet:7.6.0", "geoplanet:7.8.1", "geoplanet:7.9.0", "geoplanet:7.10.0", "geoplanet:8.0.0", "woeplanet:8.0.0"], "meta:indexed": "2020-08-20T20:18:57.221477", "meta:updated": "2020-10-14T11:19:40.339287", "woe:hierarchy": {"continent": 24865672, "country": 23424977, "town": 0, "planet": 1, "county": 12589715, "suburb": 0, "state": 2347596, "region": 0, "localadmin": 0}, "woe:timezone_id": 56043663, "woe:hash": "c20812g6q8d3", "woe:centroid": [-122.987198, 45.004509], "geom:latitude": 45.004509, "geom:longitude": -122.987198, "geom:hash": "c20812g6q8d3", "woe:latitude": 45.004509, "geom:centroid": [-122.987198, 45.004509], "woe:longitude": -122.987198, "woe:repo": "woeplanet-poi-us", "geom:area": 0.0, "woe:scale": 19}}