{"type": "Feature", "id": 23557011, "geometry": {"type": "Point", "coordinates": [-88.248528, 40.114319]}, "properties": {"woe:id": 23557011, "woe:parent_id": 2377942, "woe:name": "Holy Cross Elementary School", "woe:placetype": 20, "woe:placetype_name": "POI", "woe:lang": "ENG", "iso:country": "US", "meta:provider": ["geoplanet:7.3.2", "geoplanet:7.4.0", "geoplanet:7.4.1", "geoplanet:7.5.1", "geoplanet:7.5.2", "geoplanet:7.6.0", "geoplanet:7.8.1", "geoplanet:7.9.0", "geoplanet:7.10.0", "geoplanet:8.0.0", "woeplanet:8.0.0"], "meta:indexed": "2020-08-20T22:02:12.962717", "woe:alias_ENG_V": ["Holy Cross Elementary"], "meta:updated": "2020-10-14T11:20:25.699461", "woe:hierarchy": {"continent": 24865672, "country": 23424977, "town": 0, "planet": 1, "county": 12588087, "suburb": 0, "state": 2347572, "region": 0, "localadmin": 0}, "woe:timezone_id": 56043661, "woe:hash": "dp1hpye6u701", "woe:centroid": [-88.248528, 40.114319], "geom:latitude": 40.114319, "geom:longitude": -88.248528, "geom:hash": "dp1hpye6u701", "woe:latitude": 40.114319, "geom:centroid": [-88.248528, 40.114319], "woe:longitude": -88.248528, "woe:repo": "woeplanet-poi-us", "geom:area": 0.0, "woe:scale": 19}}