{"type": "Feature", "id": 23667359, "geometry": {"type": "Point", "coordinates": [-76.241028, 36.91069]}, "properties": {"woe:id": 23667359, "woe:parent_id": 55860612, "woe:name": "Alpha Beta Cappa Academy", "woe:placetype": 20, "woe:placetype_name": "POI", "woe:lang": "ENG", "iso:country": "US", "meta:provider": ["geoplanet:7.3.1", "geoplanet:7.3.2", "geoplanet:7.4.0", "geoplanet:7.4.1", "geoplanet:7.5.1", "geoplanet:7.5.2", "geoplanet:7.6.0", "geoplanet:7.8.1", "geoplanet:7.9.0", "geoplanet:7.10.0", "geoplanet:8.0.0", "woeplanet:8.0.0"], "meta:indexed": "2020-08-20T20:19:08.730883", "meta:updated": "2020-10-14T11:19:32.382308", "woe:hierarchy": {"continent": 24865672, "country": 23424977, "town": 0, "planet": 1, "county": 12590391, "suburb": 0, "state": 2347605, "region": 0, "localadmin": 0}, "woe:timezone_id": 56043648, "woe:hash": "dq9ccp6ur734", "woe:centroid": [-76.241028, 36.91069], "geom:latitude": 36.91069, "geom:longitude": -76.241028, "geom:hash": "dq9ccp6ur734", "woe:latitude": 36.91069, "geom:centroid": [-76.241028, 36.91069], "woe:longitude": -76.241028, "woe:repo": "woeplanet-poi-us", "geom:area": 0.0, "woe:scale": 19}}