{"type": "Feature", "id": 23665834, "geometry": {"type": "Point", "coordinates": [-80.265778, 36.774792]}, "properties": {"woe:id": 23665834, "woe:parent_id": 2523918, "woe:name": "Woolwine Elementary School", "woe:placetype": 20, "woe:placetype_name": "POI", "woe:lang": "ENG", "iso:country": "US", "meta:provider": ["geoplanet:7.3.1", "geoplanet:7.3.2", "geoplanet:7.4.0", "geoplanet:7.4.1", "geoplanet:7.5.1", "geoplanet:7.5.2", "geoplanet:7.6.0", "geoplanet:7.8.1", "geoplanet:7.9.0", "geoplanet:7.10.0", "geoplanet:8.0.0", "woeplanet:8.0.0"], "meta:indexed": "2020-08-20T20:19:08.211676", "woe:alias_ENG_V": ["Woolwine Elementary"], "meta:updated": "2020-10-14T11:19:51.904936", "woe:hierarchy": {"continent": 24865672, "country": 23424977, "town": 0, "planet": 1, "county": 12590398, "suburb": 0, "state": 2347605, "region": 0, "localadmin": 0}, "woe:timezone_id": 56043648, "woe:hash": "dnwcjw8hxy45", "woe:centroid": [-80.265778, 36.774792], "geom:latitude": 36.774792, "geom:longitude": -80.265778, "geom:hash": "dnwcjw8hxy45", "woe:latitude": 36.774792, "geom:centroid": [-80.265778, 36.774792], "woe:longitude": -80.265778, "woe:repo": "woeplanet-poi-us", "geom:area": 0.0, "woe:scale": 19}}