{"type": "Feature", "id": 56063620, "properties": {"woe:id": 56063620, "woe:parent_id": 2496456, "woe:name": "Lockport Station", "woe:placetype": 20, "woe:placetype_name": "POI", "woe:lang": "ENG", "iso:country": "US", "meta:provider": ["geoplanet:7.3.1", "geoplanet:7.3.2", "geoplanet:7.4.0", "geoplanet:7.4.1", "geoplanet:7.5.1", "geoplanet:7.5.2", "geoplanet:7.6.0", "geoplanet:7.8.1", "geoplanet:7.9.0", "geoplanet:7.10.0", "geoplanet:8.0.0", "woeplanet:8.0.0"], "meta:indexed": "2020-08-20T20:19:20.658758", "woe:alias_ENG_V": ["Lockport Metra Station", "Metra Lockport Station", "Metra-Lockport Station"], "meta:updated": "2020-08-22T02:58:22.904999", "woe:hierarchy": {"continent": 24865672, "country": 23424977, "town": 0, "planet": 1, "county": 12588176, "suburb": 0, "state": 2347572, "region": 0, "localadmin": 0}, "woe:timezone_id": 56043661, "woe:hash": "dp3ks4kgfjgc", "woe:centroid": [-88.059792, 41.5853], "geom:latitude": 41.5853, "geom:longitude": -88.059792, "geom:hash": "dp3ks4kgfjgc", "woe:latitude": 41.5853, "geom:centroid": [-88.059792, 41.5853], "woe:longitude": -88.059792, "woe:repo": "woeplanet-poi-us"}, "geometry": {"coordinates": [-88.059792, 41.5853], "type": "Point"}}