{"type": "Feature", "id": 23650888, "properties": {"woe:id": 23650888, "woe:parent_id": 2434557, "woe:name": "Central Elementary School", "woe:placetype": 20, "woe:placetype_name": "POI", "woe:lang": "ENG", "iso:country": "US", "meta:provider": ["geoplanet:7.3.1", "geoplanet:7.3.2", "geoplanet:7.4.0", "geoplanet:7.4.1", "geoplanet:7.5.1", "geoplanet:7.5.2", "geoplanet:7.6.0", "geoplanet:7.8.1", "geoplanet:7.9.0", "geoplanet:7.10.0", "geoplanet:8.0.0", "woeplanet:8.0.0"], "meta:indexed": "2020-08-20T20:19:01.950675", "woe:alias_ENG_V": ["Central Elementary"], "meta:updated": "2020-08-22T02:57:48.339066", "woe:hierarchy": {"continent": 24865672, "country": 23424977, "town": 0, "planet": 1, "county": 12589965, "suburb": 0, "state": 2347601, "region": 0, "localadmin": 0}, "woe:timezone_id": 56043661, "woe:hash": "dn6zf61ht1hb", "woe:centroid": [-86.032341, 36.530319], "geom:latitude": 36.530319, "geom:longitude": -86.032341, "geom:hash": "dn6zf61ht1hb", "woe:latitude": 36.530319, "geom:centroid": [-86.032341, 36.530319], "woe:longitude": -86.032341, "woe:repo": "woeplanet-poi-us"}, "geometry": {"coordinates": [-86.032341, 36.530319], "type": "Point"}}