{"type": "Feature", "id": 23671106, "properties": {"woe:id": 23671106, "woe:parent_id": 2390431, "woe:name": "Arcadia Elementary School", "woe:placetype": 20, "woe:placetype_name": "POI", "woe:lang": "ENG", "iso:country": "US", "meta:provider": ["geoplanet:7.3.2", "geoplanet:7.4.0", "geoplanet:7.4.1", "geoplanet:7.5.1", "geoplanet:7.5.2", "geoplanet:7.6.0", "geoplanet:7.8.1", "geoplanet:7.9.0", "geoplanet:7.10.0", "geoplanet:8.0.0", "woeplanet:8.0.0"], "meta:indexed": "2020-08-20T22:03:00.551477", "woe:alias_ENG_V": ["Arcadia Elementary"], "meta:updated": "2020-08-22T02:57:52.234203", "woe:hierarchy": {"continent": 24865672, "country": 23424977, "town": 0, "planet": 1, "county": 12590471, "suburb": 0, "state": 2347606, "region": 0, "localadmin": 0}, "woe:timezone_id": 56043663, "woe:hash": "c2s2z1jj7ms1", "woe:centroid": [-117.458809, 47.95076], "geom:latitude": 47.95076, "geom:longitude": -117.458809, "geom:hash": "c2s2z1jj7ms1", "woe:latitude": 47.95076, "geom:centroid": [-117.458809, 47.95076], "woe:longitude": -117.458809, "woe:repo": "woeplanet-poi-us"}, "geometry": {"coordinates": [-117.458809, 47.95076], "type": "Point"}}