{"type": "Feature", "id": 23603179, "properties": {"woe:id": 23603179, "woe:parent_id": 55806362, "woe:name": "Jackson Elementary School", "woe:placetype": 20, "woe:placetype_name": "POI", "woe:lang": "ENG", "iso:country": "US", "meta:provider": ["geoplanet:7.3.1", "geoplanet:7.3.2", "geoplanet:7.4.0", "geoplanet:7.4.1", "geoplanet:7.5.1", "geoplanet:7.5.2", "geoplanet:7.6.0", "geoplanet:7.8.1", "geoplanet:7.9.0", "geoplanet:7.10.0", "geoplanet:8.0.0", "woeplanet:8.0.0"], "meta:indexed": "2020-08-20T20:18:45.641725", "woe:alias_ENG_V": ["Jackson School", "Jackson Elementary"], "meta:updated": "2020-08-22T02:57:41.415444", "woe:hierarchy": {"continent": 24865672, "country": 23424977, "town": 0, "planet": 1, "county": 12589165, "suburb": 0, "state": 2347586, "region": 0, "localadmin": 0}, "woe:timezone_id": 56043661, "woe:hash": "9z7f8qj9e1bb", "woe:centroid": [-95.957893, 41.253929], "geom:latitude": 41.253929, "geom:longitude": -95.957893, "geom:hash": "9z7f8qj9e1bb", "woe:latitude": 41.253929, "geom:centroid": [-95.957893, 41.253929], "woe:longitude": -95.957893, "woe:repo": "woeplanet-poi-us"}, "geometry": {"coordinates": [-95.957893, 41.253929], "type": "Point"}}