{"type": "Feature", "id": 23556612, "geometry": {"type": "Point", "coordinates": [-114.465187, 42.541618]}, "properties": {"woe:id": 23556612, "woe:parent_id": 2509104, "woe:name": "Oregon Trail Elementary School", "woe:placetype": 20, "woe:placetype_name": "POI", "woe:lang": "ENG", "iso:country": "US", "meta:provider": ["geoplanet:7.3.2", "geoplanet:7.4.0", "geoplanet:7.4.1", "geoplanet:7.5.1", "geoplanet:7.5.2", "geoplanet:7.6.0", "geoplanet:7.8.1", "geoplanet:7.9.0", "geoplanet:7.10.0", "geoplanet:8.0.0", "woeplanet:8.0.0"], "meta:indexed": "2020-08-20T22:02:12.842594", "woe:alias_ENG_V": ["Oregon Trail Elementary"], "meta:updated": "2020-10-14T11:20:18.834392", "woe:hierarchy": {"continent": 24865672, "country": 23424977, "town": 0, "planet": 1, "county": 12588075, "suburb": 0, "state": 2347571, "region": 0, "localadmin": 0}, "woe:timezone_id": 56043662, "woe:hash": "9rwd522yzu6k", "woe:centroid": [-114.465187, 42.541618], "geom:latitude": 42.541618, "geom:longitude": -114.465187, "geom:hash": "9rwd522yzu6k", "woe:latitude": 42.541618, "geom:centroid": [-114.465187, 42.541618], "woe:longitude": -114.465187, "woe:repo": "woeplanet-poi-us", "geom:area": 0.0, "woe:scale": 19}}