{"type": "Feature", "id": 23672135, "properties": {"woe:id": 23672135, "woe:parent_id": 2478880, "woe:name": "Ravenswood Middle School", "woe:placetype": 20, "woe:placetype_name": "POI", "woe:lang": "ENG", "iso:country": "US", "meta:provider": ["geoplanet:7.3.1", "geoplanet:7.3.2", "geoplanet:7.4.0", "geoplanet:7.4.1", "geoplanet:7.5.1", "geoplanet:7.5.2", "geoplanet:7.6.0", "geoplanet:7.8.1", "geoplanet:7.9.0", "geoplanet:7.10.0", "geoplanet:8.0.0", "woeplanet:8.0.0"], "meta:indexed": "2020-08-20T20:19:10.073665", "meta:updated": "2020-08-22T02:58:17.437477", "woe:hierarchy": {"continent": 24865672, "country": 23424977, "town": 0, "planet": 1, "county": 12590496, "suburb": 0, "state": 2347607, "region": 0, "localadmin": 0}, "woe:timezone_id": 56043648, "woe:hash": "dnvved8t37me", "woe:centroid": [-81.759506, 38.950199], "geom:latitude": 38.950199, "geom:longitude": -81.759506, "geom:hash": "dnvved8t37me", "woe:latitude": 38.950199, "geom:centroid": [-81.759506, 38.950199], "woe:longitude": -81.759506, "woe:repo": "woeplanet-poi-us"}, "geometry": {"coordinates": [-81.759506, 38.950199], "type": "Point"}}